Workbook
Name A: #REF!
Name Actividad: [1]Formulas!$H$2:$H$5000
Name arearesponsable: '[2]Listas desplegables'!$BB$2:$BB$100
Name Clientes: [1]Clientes!$A$2:$A$100
Name COORDINADOR: [3]Hoja2!$D$2:$D$30
Name Coordinadores: [1]Coordinadores!$A$2:$A$1000
Name DOCUMENTADOR: [3]Hoja2!$A$2:$A$30
Name ES: [3]Hoja2!$K$2:$K$30
Name ESS: [3]Hoja2!$K$2:$K$30
Name Estado: [1]Formulas!$K$2:$K$5000
Name ESTADOACTIVIDAD: [3]Hoja2!$M$2:$M$30
Name ESTADOS: '[4]Listas desplegables'!$B$1:$D$1
Name ESTADOSCIERRES: '[5]lista desplegable'!$CX$1:$DA$1
Name Facturacion: '[6]Listas desplegables'!$AO$1:$AR$1
Name FACTURACIÓN: '[4]Listas desplegables'!$Y$1:$AB$1
Name falla: #REF!
Name Fallas: '[7]Listas desplegables'!$F$2:$L$2
Name Grupo_Falla: '[8]Listas Desplegables'!$CH$2:$CH$5
Name inconservmanager: '[9]Listas desplegables'!$BC$2:$BC$100
Name INCUMPLIMIENTO: '[2]Listas desplegables'!$AK$1:$AN$1
Name LISTA: [10]Dptos!$A$1139:$A$1171
Name LISTA2: #REF!
Name LOLO: [11]Coordinadores!$A$2:$A$1000
Name solicitudes: '[12]Listas desplegables'!$AF$1:$AQ$1
Name Tecnicos: [1]Tecnicos!$A$2:$A$1000
Name Version: [1]Formulas!$I$2:$I$3

Sheet BASE LIQUIDACION
A1: TARIFAS 2025 | E1: Incremento 2025
A2: Tipificación | B2: Descripción | C2: Dia actividad Exitosa | D2: Dia actividad Fallida | E2: 0.052
A3: Tipo I | B3: Metropolitano | C3: =62700.07*(1+$E$2) -> 65960.474 | D3: =42357.4*(1+$E$2) -> 44559.985
A4: Tipo II | B4: Hasta 3 horas | C4: =155716.31*(1+$E$2) -> 163813.56 | D4: =127766.53*(1+$E$2) -> 134410.39
A5: Tipo III | B5: De 3 a 5 horas | C5: =262099.22*(1+$E$2) -> 275728.38 | D5: =211886.19*(1+$E$2) -> 222904.27
A6: Tipo IV | B6: Más de 5 horas | C6: =455883.78*(1+$E$2) -> 479589.74 | D6: =441833.68*(1+$E$2) -> 464809.03
A7: Destino aereo | B7: No incluye valor del Tiquete | C7: =455883.78*(1+$E$2) -> 479589.74 | D7: =441833.68*(1+$E$2) -> 464809.03
A8: *Donde se requiera transporte aéreo o fluvial se factura adicional a tarifa TIPO IV el valor del tiquete + el 12% de admon.
A10: Gestión Telefónica | B10: =36031.04*(1+$E$2) -> 37904.654
A11: Mts Acometida electrica | B11: =30182.1*(1+$E$2) -> 31751.569
A12: Mts Acometida datos | B12: =15432.22*(1+$E$2) -> 16234.695
A13: switche | B13: =244669.03*(1+$E$2) -> 257391.82
A14: Router | B14: =291399.51*(1+$E$2) -> 306552.28
A15: Envio operador Logistico | B15: =53547.34*(1+$E$2) -> 56331.802

Sheet RESUMEN LIQUIDACIONES
A1: LÍNEA COMUNICACIONES S.A.S | F1: FACTURACIÓN CORRESPONSALES BANCARIOS TIQUIETES AEREOS
A2: FACTURACIÓN PROYECTO CB BANCOLOMBIA | F2: =A3 -> 45960
A3: 45960
F4: CONCEPTOS | G4: TRAYECTOS | H4: TOTAL | I4: % Administración | J4: TOTAL
A5: CONCEPTOS | B5: CANTIDAD | C5: VALOR UNITARIO | D5: VALOR TOTAL | F5: INCIDENTE 2890962 | G5: ARAUCA-SARAVENA-ARAUCA | H5: =416200+565450 -> 981650 | I5: =H5*0.12 -> 117798 | J5: =H5+I5 -> 1099448
A6: Adecuaciones CB | B6: =COUNTA(ADECUCACIONES!A:A)-1 -> 20 | C6: 0 | D6: =ADECUCACIONES!AE22 -> 2624774 | I6: =H6*0.12 -> 0 | J6: =H6+I6 -> 0
A7: Incidentes | B7: =COUNTA(INCIDENTES!A:A)-1 -> 114 | C7: 0 | D7: =INCIDENTES!AH116 -> 13289236 | I7: =H7*0.12 -> 0 | J7: =H7+I7 -> 0
A8: Ordenes de Cambio | B8: =COUNTA(OC!A:A)-1 -> 10 | C8: 0 | D8: =OC!AG12 -> 561069 | I8: =H8*0.12 -> 0 | J8: =H8+I8 -> 0
A9: Tiquetes | B9: 0 | C9: 0 | D9: =J12 -> 1099448 | I9: =H9*0.12 -> 0 | J9: =H9+I9 -> 0
A10: SUBTOTAL | D10: =SUM(D6:D9) -> 17574527 | I10: =H10*0.12 -> 0 | J10: =H10+I10 -> 0
A11: Iva | D11: =D10*0.19 -> 3339160.1 | I11: =H11*0.12 -> 0 | J11: =H11+I11 -> 0
A12: TOTAL | D12: =D10+D11 -> 20913687 | F12: TOTAL | H12: =SUM(H5:H11) -> 981650 | I12: =SUM(I5:I11) -> 117798 | J12: =SUM(J5:J11) -> 1099448

Sheet ADECUCACIONES
A1: CIUDAD SEDE | B1: ZONA | C1: CENTRO DE COSTOS LINEACOM | D1: CODIGO DANE | E1: TA/CODIGO ACTIVIDAD | F1: CODIGO CB | G1: ACTIVIDAD | H1: TIPO DE APERTURA | I1: DEPARTAMENTO | J1: CIUDAD | K1: NOMBRE DEL CB | L1: RED | M1: FO | N1: FECHA LISTA | O1: FECHA ULTIMA ACTUALIZACION | P1: FORMATO | Q1: CADENA | R1: ESTADO | S1: OBSERVACIONES CLIENTE | T1: FORMA DE ATENCION | U1: TERMINAL(ES) | V1: TIPIFICACION | W1: TIPO DE TRAYECTO | X1: NOMBRE DEL TECNICO | Y1: ACOMETIDA DATOS | Z1: ACOMETIDA ELECTRICA | AA1: SWITCH | AB1: ROUTER | AC1: VALOR DIAS ACTIVIDAD FACTURABLES | AD1: DIAS ACTIVIDAD FACTURABLES | AE1: VALOR TOTAL INSTALACION DE PUBLICIDAD
A2: PASTO | B2: SUROCCIDENTE Y EJE CAFETERO | C2: 0004-0003 | D2: 86568 | E2: TA-25-1145877 | F2: 3007081676 | G2: APERTURA | H2: CB CRECIMIENTO ALIANZA - NUEVO | I2: PUTUMAYO | J2: PUERTO ASIS | K2: DISTRICOL FERRETERIA PRADO HC | L2: REDEBAN | M2: FO-25-1577758 | N2: 45924.619 | O2: 45932.457 | P2: AGREGADOR | Q2: DISTRICOL | R2: EJECUTADO/CANCELADO | S2: 24/09/2025 24-09 PROGRAMACIÓN REALIZADA POR LA ALIANZA | 30/09/2025 NO SE OGRA LLEGAR EL DIA DE HOY A SITIO POR PROBLEMAS EN LAS VIAS , SE LLEGARA EL DIA DE MAÑANA PARA ATENCION DE ACTIVIDADES | 02/10/2025 SE VISITA EL COMERCIO PARA REVISAR APERTURA DEL CORRESPONSAL PERO NO ES POSIBLE POR DIRECCIÓN ERRADA, EN CÁMARA DE COMERCIO APARECE DIRECCIÓN CR 27 CL 22 BRR EL PRADO Y EL COMERCIO ESTÁ UBICADO EN DIRECCIÓN CRA 22 # 27 POR LO TANTO SE CANCELA LA INSTALACIÓN | T2: VISITA TECNICA | V2: TIPO IV | W2: TERRESTRE | X2: GUERRERO RAMIREZ OSCAR DARIO | Y2: 0 | Z2: 0 | AA2: 0 | AB2: 0 | AC2: 1 | AD2: 464809 | AE2: 464809
A3: CALI | B3: SUROCCIDENTE Y EJE CAFETERO | C3: 0004-0003 | D3: 76001 | E3: TA-25-1157236 | F3: 3007081704 | G3: APERTURA | H3: CB CRECIMIENTO ALIANZA - NUEVO | I3: VALLE DEL CAUCA | J3: CALI | K3: DISTRICOL DISTRIB EL GRANJERO | L3: REDEBAN | M3: FO-25-1598686 | N3: 45929.697 | O3: 45952.646 | P3: AGREGADOR | Q3: DISTRICOL | R3: EJECUTADO/CANCELADO | S3: 29/09/2025 29-09 PROGRAMACIÓN REALIZADA POR LA ALIANZA | 22/10/2025 SE LLAMA AL CLIENTE SE VÁLIDA LA INFORMACIÓN, DISPONIBILIDAD Y LUGAR DE LA DIRECCIÓN DE LA INSTALACIÓN, SE LLEGA AL COMERCIO SE EVIDENCIA PROXIMIDAD 30 MTS CON OTRO CORRESPONSAL 1 A 1 AL FRENTE CB 40569 BARRIO LA BUITRERA EL PORTENTO CALI, EL CASO SE ESCALA PARA CONSULTAR LA INSTALACIÓN DE AUTORIZACIÓN | T3: VISITA TECNICA | V3: TIPO I | W3: TERRESTRE | X3: HERRERA MONAR GEOVANNY | Y3: 0 | Z3: 0 | AA3: 0 | AB3: 0 | AC3: 1 | AD3: 44560 | AE3: 44560
A4: MEDELLIN | B4: NOROCCIDENTE | C4: 0004-0005 | D4: 5360 | E4: TA-25-1165179 | F4: 3007081728 | G4: APERTURA | H4: CB CRECIMIENTO ALIANZA - NUEVO | I4: ANTIOQUIA | J4: ITAGUI | K4: DISTRICOL RG | L4: REDEBAN | M4: FO-25-1624400 | FO-25-1611140 | N4: 45931.707 | O4: 45936.61 | P4: AGREGADOR | Q4: DISTRICOL | R4: EJECUTADO | EJECUTADO/CANCELADO | S4: 06/10/2025 SE INSTALA CORRESPONSAL OK | T4: VISITA TECNICA | U4: SUZZZ674 | V4: TIPO I | W4: TERRESTRE | X4: RUA ALVAREZ RICHARD ANDRES | Y4: 0 | Z4: 0 | AA4: 0 | AB4: 0 | AC4: 1 | AD4: 44560 | AE4: 44560
A5: CALI | B5: SUROCCIDENTE Y EJE CAFETERO | C5: 0004-0003 | D5: 19698 | E5: TA-25-1165186 | F5: 3007081737 | G5: APERTURA | H5: CB CRECIMIENTO ALIANZA - NUEVO | I5: CAUCA | J5: SANTANDER DE QUILICHAO | K5: DISTRICOL DANICELL PLUS | L5: REDEBAN | M5: FO-25-1611165 | N5: 45931.741 | O5: 45932.625 | P5: AGREGADOR | Q5: DISTRICOL | R5: EJECUTADO/CANCELADO | S5: 01/10/2025 01-10 PROGRAMACIÓN REALIZADA POR LA ALIANZA | 02/10/2025 SE REALIZA VISITA TÉCNICA PERO AL MOMENTO DE INICIALIZAR EL EQUIPO ARROJA ERROR EN CONEXIÓN SE COMPRUEBAN CONEXIONES Y TODO OK, EL COMERCIO NO CUENTA CON INTERNET EN EL MOMENTO SE ESPERAN AL REDEDOR DE 30-40MIN PERO EL PROBLEMA NO ES SOLUCIONADO, EL CLIENTE VALIDA CON EL PROVEEDOR DE INTERNET PERO INDICA QUE NO TIENE FECHA DE SOLUCION. | T5: VISITA TECNICA | V5: TIPO II | W5: TERRESTRE | X5: MONTERO MUESES GIAN CARLO | Y5: 0 | Z5: 0 | AA5: 0 | AB5: 0 | AC5: 1 | AD5: 134410 | AE5: 134410
A6: PASTO | B6: SUROCCIDENTE Y EJE CAFETERO | C6: 0004-0003 | D6: 52687 | E6: TA-25-1165197 | F6: 3007081735 | G6: APERTURA | H6: CB CRECIMIENTO ALIANZA - NUEVO | I6: NARIÑO | J6: SAN LORENZO | K6: DISTRICOL PIPE CELL | L6: REDEBAN | M6: FO-25-1611190 | N6: 45931.698 | O6: 45937.377 | P6: AGREGADOR | Q6: DISTRICOL | R6: EJECUTADO/CANCELADO | S6: 01/10/2025 01-10 PROGRAMACIÓN REALIZADA POR LA ALIANZA | 02/10/2025 NO SE PUEDE REALIZAR DESPLAZAMIENTO A SITIO POR FALTA DE TRANSPORTE Y CUPO, EL CUAL INFORMAN QUE SOLO SALE EN UNA JORNADA DEL MEDIO DÍA Y NO SE ENCUENTRA DISPONIBILIDAD EN HORARIO DE LA MAÑANA, SE LLAMÓ AL CLIENTE INFORMANDO QUE APENAS HAYA TRANSPORTE O CUPO A SITIO SE PROGRAMARÁ LA VISITA | 07/10/2025 SE VISITO E COMERCIO PARA INSTALAR CB NO ES POSIBIE POR DIRECCION ERRADA YA QUE EN SYTEX APARECE CR 3 MZ 10 LADO D CA 22 BRR CENTRO Y EN FACTURA DE SERVICIOS PUBLICOS APARECE CRA 3 M2 10 LADO D CASA 23 POR LO QUE SE CANCELA LA INSTALACION. TAMPOCO ES POSIBLE VALIDAR CON CAMARA DE COMERCIO PORQUE CUENTA CON UNA DIRECCIÓN DIFERENTE | T6: VISITA TECNICA | V6: TIPO II | W6: TERRESTRE | X6: GUERRERO RAMIREZ OSCAR DARIO | Y6: 0 | Z6: 0 | AA6: 0 | AB6: 0 | AC6: 1 | AD6: 134410 | AE6: 134410
A7: BOGOTA | B7: CUNDINAMARCA | C7: 0004-0004 | D7: 11001 | E7: TA-25-1165210 | F7: 3007081717 | G7: APERTURA | H7: CB CRECIMIENTO ALIANZA - NUEVO | I7: CUNDINAMARCA | J7: BOGOTA | K7: DISTRICOL TODO A LA MANO | L7: REDEBAN | M7: FO-25-1611242 | N7: 45931.333 | O7: 45932.518 | P7: AGREGADOR | Q7: DISTRICOL | R7: EJECUTADO/CANCELADO | S7: 01/10/2025 01-10 PROGRAMACIÓN REALIZADA POR LA ALIANZA | 02/10/2025 DURANTE LA IMPLEMENTACIÓN DE CORRESPONSAL BANCARIO AL LLEGAR SE EVIDENCIA QUE COMERCIO SU ACTIVIDAD ECONÓMICA ES DE JUEGOS DE AZAR Y APUESTAS LO CUAL, IMPIDE REALIZAR LA IMPLEMENTACIÓN DE CORRESPONSAL, SE REALIZA ESCALAMIENTO A LA ENTIDAD NOS ENCONTRAMOS A LA ESPERA DE RESPUESTA DE LA MISMA PARA REALIZAR CANCELACIÓN DE LA IMPLEMENTACIÓN O CONTINUAR CON LA MISMA SE BRINDA INFORMACIÓN A COMERCIO | T7: VISITA TECNICA | V7: TIPO I | W7: TERRESTRE | X7: GALEANO SORIANO JUAN DAVID | Y7: 0 | Z7: 0 | AA7: 0 | AB7: 0 | AC7: 1 | AD7: 44560 | AE7: 44560
A8: BOGOTA | B8: CUNDINAMARCA | C8: 0004-0004 | D8: 11001 | E8: TA-25-1165214 | F8: 3007081718 | G8: APERTURA | H8: CB CRECIMIENTO ALIANZA - NUEVO | I8: CUNDINAMARCA | J8: BOGOTA | K8: DISTRICOL TODO EN UNO SUBA | L8: REDEBAN | M8: FO-25-1611245 | N8: 45931.5 | O8: 45932.592 | P8: AGREGADOR | Q8: DISTRICOL | R8: EJECUTADO/CANCELADO | S8: 01/10/2025 01-10 PROGRAMACIÓN REALIZADA POR LA ALIANZA | 02/10/2025 SE VISITA COMERCIO PARA REALIZAR LA INSTALACIÓN DEL CB BANCOLOMBIA RBM, SE EVIDENCIA QUE LA DIRECCIÓN DADA EN LA ORDEN ES (CR 103B #152-32) PERO ESTÁ DIRECCIÓN NO ES LA REAL YA QUE LA CORRECTA DONDE ESTÁ EL ESTABLECIMIENTO ES (CR 103B #152-35) EN LA ACERA DE EN FRENTE, LA CÁMARA Y COMERCIO SI TIENE LA DIRECCIÓN DE LA ORDEN PERO LA DIRECCIÓN DADA SE SITÚA EN EL PATIO DE DESCANSO DE UN COLEGIO, TAMBIÉN SE VÁLIDA Y EL ESTABLECIMIENTO CUENTA COMO ACTIVIDAD REALIZAR APUESTAS (LOTERÍA Y CHANCE) ALGO POR LO QUE NO ESTÁ PERMITIDO REALIZAR INSTALACIÓN EN DICHOS COMERCIOS, SE ESCALA AL COORDINADOR Y A RBM Y LUEGO DAN RESPUESTA DE NO INSTALAR, SE LE EXPLICA LA SITUACION AL CLIENTE Y ENTIENDE. | T8: VISITA TECNICA | V8: TIPO I | W8: TERRESTRE | X8: VEGA MANRIQUE JONATAN MAURICIO | Y8: 0 | Z8: 0 | AA8: 0 | AB8: 0 | AC8: 1 | AD8: 44560 | AE8: 44560
A9: NEIVA | B9: REMOTAS | C9: 0004-0007 | D9: 41319 | E9: TA-25-1194778 | F9: 3007081860 | G9: APERTURA | H9: CB CRECIMIENTO ALIANZA - NUEVO | I9: HUILA | J9: GUADALUPE | K9: PTM GUADALUPE VARIEDADES ANDRE | L9: REDEBAN | M9: FO-25-1666972 | N9: 45940.315 | O9: 45945.482 | P9: AGREGADOR | Q9: COMCARD - PTM | R9: EJECUTADO/CANCELADO | S9: 10/10/2025 9/10/2025 PROGRAMACIÓN REALIZADA POR LA ALIANZA| INSTALACIÓN PROGRAMADA PARA EL 2025-10-15 | 15/10/2025 SE REALIZA VISITA PARA IMPLEMENTAR CB PTM 81860, PERO SE EVIDENCIA QUE APROXIMADAMENTE 40 MTS HAY UN CB UNO A UNO INSTALADO (35020), SE ESCALA CASO A ENTIDAD DONDE FUE CANCELADA POR LA MISMA | T9: VISITA TECNICA | V9: TIPO III | W9: TERRESTRE | X9: ANDRADE HERNANDEZ JUAN CARLOS | Y9: 0 | Z9: 0 | AA9: 0 | AB9: 0 | AC9: 1 | AD9: 222904 | AE9: 222904
A10: PASTO | B10: SUROCCIDENTE Y EJE CAFETERO | C10: 0004-0003 | D10: 52001 | E10: TA-25-1194785 | F10: 3007081861 | G10: APERTURA | H10: CB CRECIMIENTO ALIANZA - NUEVO | I10: NARIÑO | J10: PASTO | K10: PTM PASTO R&R STORE | L10: REDEBAN | M10: FO-25-1687223 | FO-25-1666979 | N10: 45940.734 | O10: 45946.548 | P10: AGREGADOR | Q10: COMCARD - PTM | R10: EJECUTADO | EJECUTADO/CANCELADO | S10: 16/10/2025 SE REALIZÓ LA INSTALACIÓN DE EQUIPOS PUBLICIDAD Y ACCESORIOS PARA APERTURA CB BANCOLOMBIA SE DIO CAPACITACIÓN MANEJO DE DATÁFONO CB Y SOMOS BANCOLOMBIA SE EJECUTAN PRUEBAS TX EXITOSAS QUEDA OPERATIVO | T10: VISITA TECNICA | U10: VWZZZ800 // VYZZZ068 | V10: TIPO I | W10: TERRESTRE | X10: REMICIO AMADO JOHN HEBER | Y10: 0 | Z10: 0 | AA10: 0 | AB10: 0 | AC10: 1 | AD10: 44560 | AE10: 44560
A11: BUCARAMANGA | B11: SANTANDERES | C11: 0004-0008 | D11: 68276 | E11: TA-25-1194794 | F11: 3007081858 | G11: APERTURA | H11: CB CRECIMIENTO ALIANZA - NUEVO | I11: SANTANDER | J11: FLORIDABLANCA | K11: PTM FLORIDABLANCA TIENDA LA AN | L11: REDEBAN | M11: FO-25-1683636 | FO-25-1666991 | N11: 45940.442 | O11: 45946.618 | P11: AGREGADOR | Q11: COMCARD - PTM | R11: EJECUTADO | EJECUTADO/CANCELADO | S11: 15/10/2025 LUEGO DE CONTESTACION EMITIDA POR LA RED NOS INDICAN QUE SE PROCEDERA CON UN CAMBIO DE TERMINALES SE PROCEDERA CON LA CULMINACIÓN DE LA ACTIVIDAD UNA VEZ INFORME LA RED SE ESTABLECE CONTACTO CON LA USUARIA QUE A LA VEZ NOS INDICA QUE NOS PODRÁ ATENDER EL DÍA MAÑANA SIN NINGÚN PROBLEMA | 16/10/2025 SE REALIZA INSTALACIÓN DE AVISO EXTERIOR FLANGER DISPLAY LEGAL IDENTIFICADOR DE PUNTO BASE DATÁFONO LECTORA CAMBIO DE SISTEMA OPERATIVO INVERSION 9.90 CREACIÓN DE USUARIOS CAPACITACIÓN ADMINISTRATIVA OPERATIVA PRUEBAS OK SERVICIO OPERATIVO | T11: VISITA TECNICA | U11: VYZZZ063 / VWZZZ803 | V11: TIPO I | W11: TERRESTRE | X11: ECHEVERRI ECHEVERRI EVELIN DANIELA | Y11: 0 | Z11: 0 | AA11: 0 | AB11: 0 | AC11: 1 | AD11: 44560 | AE11: 44560
A12: CALI | B12: SUROCCIDENTE Y EJE CAFETERO | C12: 0004-0003 | D12: 76001 | E12: TA-25-1194800 | F12: 3007081855 | G12: APERTURA | H12: CB CRECIMIENTO ALIANZA - NUEVO | I12: VALLE DEL CAUCA | J12: CALI | K12: PTM CALI PAPELERIA Y VARIEDADE | L12: REDEBAN | M12: FO-25-1686966 | FO-25-1667001 | N12: 45940.713 | O12: 45946.249 | P12: AGREGADOR | Q12: COMCARD - PTM | R12: EJECUTADO | EJECUTADO/CANCELADO | S12: 15/10/2025 SE INSTALA DATÁFONO SE CAPACITA AL CLIENTE SE ENTREGAN ROLLOS SE HACEN PRUEBAS CB QUEDA FUNCIONANDO CORRECTAMENTE NO SE HACEN MÁS PRUEBAS YA QUE CLIENTE NO TENÍA TARJETA BANCOLOMBIA Y LA DEL TECNICO ESTABA BLOQUEADA | T12: VISITA TECNICA | U12: VWZZZ805 - VYZZZ065 | V12: TIPO I | W12: TERRESTRE | X12: CUERO RUIZ JHONNY | Y12: 0 | Z12: 0 | AA12: 0 | AB12: 0 | AC12: 1 | AD12: 44560 | AE12: 44560
A13: SANTA MARTA | B13: COSTA | C13: 0004-0001 | D13: 44090 | E13: TA-25-1220622 | F13: 3007081877 | G13: APERTURA | H13: CB CRECIMIENTO ALIANZA - NUEVO | I13: LA GUAJIRA | J13: DIBULLA | K13: PTM DIBULLA PAPELERIA Y VARIED | L13: REDEBAN | M13: FO-25-1706158 | N13: 45950.333 | O13: 45952.556 | P13: AGREGADOR | Q13: COMCARD - PTM | R13: EJECUTADO/CANCELADO | S13: 20/10/2025 20-10 PROGRAMACIÓN REALIZADA POR LA ALIANZA| INSTALACIÓN PROGRAMADA PARA EL 2025-10-21 | 21/10/2025 SE REALIZA GESTIÓN TELEFÓNICA, EL USUARIO INFORMA QUE EN EL DÍA DE HOY EL MUNICIPIO NO CONTARÁ CON SERVICIO ELÉCTRICO YA QUE LA VAN A QUITAR DURANTE TODO EL DÍA, QUE SE REPROGRAME LA INSTALACIÓN PARA EL MIÉRCOLES 22 | 22/10/2025 NO SE PUEDE REALIZAR LA APERTURA POR DIRECCIÓN ERRADA YA QUE LA DIRECCIÓN EN EL SISTEMA APARECE DIFERENTE AL DEL PUNTO, SE ESCALA EL CASO CON EL COORDINADOR Y SE CANCELA LA INSTALACIÓN | T13: VISITA TECNICA | V13: TIPO III | W13: TERRESTRE | X13: THOMAS CAMPO SIGIFREDO SEGUNDO | Y13: 0 | Z13: 0 | AA13: 0 | AB13: 0 | AC13: 1 | AD13: 222904 | AE13: 222904
A14: BOGOTA | B14: CUNDINAMARCA | C14: 0004-0004 | D14: 11001 | E14: TA-25-1220633 | F14: 3007081873 | G14: APERTURA | H14: CB CRECIMIENTO ALIANZA - NUEVO | I14: CUNDINAMARCA | J14: BOGOTA | K14: PTM BOGOTA FLAG MART | L14: REDEBAN | M14: FO-25-1716863 | FO-25-1706191 | N14: 45950.333 | O14: 45953.287 | P14: AGREGADOR | Q14: COMCARD - PTM | R14: EJECUTADO | EJECUTADO/CANCELADO | S14: 22/10/2025 SE REALIZA LA INSTALACIÓN DEL CB PTM BOGOTA FLAG MARY, EL CLIENTE Y TÉCNICO NO MANEJAN TARJETA BANCOLOMBIA SE REALIZAN PRUEBAS ENVIANDO Y RETIRANDO POR NEQUI | T14: VISITA TECNICA | U14: AE001940 | V14: TIPO I | W14: TERRESTRE | X14: ALARCON AREVALO JOHAN STIVEN | Y14: 0 | Z14: 0 | AA14: 0 | AB14: 0 | AC14: 1 | AD14: 44560 | AE14: 44560
A15: CALI | B15: SUROCCIDENTE Y EJE CAFETERO | C15: 0004-0003 | D15: 76001 | E15: TA-25-1229179 | F15: 3007081937 | G15: APERTURA | H15: CB CRECIMIENTO ALIANZA - NUEVO | I15: VALLE DEL CAUCA | J15: CALI | K15: PTM CALI SKYNET 2.2 | L15: REDEBAN | M15: FO-25-1718419 | N15: 45952.715 | O15: 45954.647 | P15: AGREGADOR | Q15: COMCARD - PTM | R15: EJECUTADO/CANCELADO | S15: 22/10/2025 22-10 PROGRAMACIÓN REALIZADA POR LA ALIANZA| INSTALACIÓN PROGRAMADA PARA EL 2025-10-24 | 24/10/2025 SE CANCELA LA APERTURA POR DIRECCIÓN ERRADA, LA DIRECCIÓN CORRECTA ES CALLE 39A # 43 - 03 QUE ES OA DIRECCIÓN DE LA CAMARA Y COMERCIO Y LA DIRECCIÓN DE LA ORDEN ES KRA 39A # 43 - 03 | T15: VISITA TECNICA | V15: TIPO I | W15: TERRESTRE | X15: PAREDES CASTILLO DIEGO | Y15: 0 | Z15: 0 | AA15: 0 | AB15: 0 | AC15: 1 | AD15: 44560 | AE15: 44560
A16: MEDELLIN | B16: NOROCCIDENTE | C16: 0004-0005 | D16: 5001 | E16: TA-25-1247954 | F16: 3007082076 | G16: APERTURA | H16: CB CRECIMIENTO ALIANZA - NUEVO | I16: ANTIOQUIA | J16: MEDELLIN | K16: DISTRICOL CANO TIENDA | L16: REDEBAN | M16: FO-25-1751685 | N16: 45959.881 | O16: 45961.287 | P16: AGREGADOR | Q16: DISTRICOL | R16: EJECUTADO/CANCELADO | S16: 29/10/2025 29-10 PROGRAMACIÓN REALIZADA POR LA ALIANZA| INSTALACIÓN PROGRAMADA PARA EL 2025-10-30 | 30/10/2025 VISITA FALLIDA SE LLEGA A LA DIRECCIÓN DADA Y NO SE ENCUENTRA EL COMERCIO INDICADO PARA LA INSTALACIÓN TAMPOCO CONOCEN LA PERSONA Y NO CONTESTAN LLAMADAS NI WPP EN EL NÚMERO DE CONTACTO SE ESTÁ EN LA DIRECCIÓN Y LOCAL CORRECTO PERO NO SABEN NADA SOBRE LA INSTALACIÓN | T16: VISITA TECNICA | V16: TIPO I | W16: TERRESTRE | X16: PAREJA ECHAVARRIA JHON DAVID | Y16: 0 | Z16: 0 | AA16: 0 | AB16: 0 | AC16: 1 | AD16: 44560 | AE16: 44560
A17: MEDELLIN | B17: NOROCCIDENTE | C17: 0004-0005 | D17: 5736 | E17: TA-25-1247964 | F17: 3007082061 | G17: APERTURA | H17: CB CRECIMIENTO ALIANZA - NUEVO | I17: ANTIOQUIA | J17: SEGOVIA | K17: DISTRICOL PLANETARIO 2000 | L17: REDEBAN | M17: FO-25-1751719 | N17: 45959.882 | O17: 45961.484 | P17: AGREGADOR | Q17: DISTRICOL | R17: EJECUTADO/CANCELADO | S17: 29/10/2025 29-10 PROGRAMACIÓN REALIZADA POR LA ALIANZA| INSTALACIÓN PROGRAMADA PARA EL 2025-10-31 | 31/10/2025 SE LLEGA A PUNTO Y EN DIRECCIÓN NO SE ENCUENTRA LOCAL, SE COMUNICA CON CLIENTE Y NO BRINDA UBICACIÓN DEL PUNTO, SE CANCELA | T17: VISITA TECNICA | V17: TIPO IV | W17: TERRESTRE | X17: QUINTERO SANCHEZ JUAN SEBASTIAN | Y17: 0 | Z17: 0 | AA17: 0 | AB17: 0 | AC17: 1 | AD17: 464809 | AE17: 464809
A18: PASTO | B18: SUROCCIDENTE Y EJE CAFETERO | C18: 0004-0003 | D18: 52001 | E18: TA-25-1247984 | F18: 3007082052 | G18: APERTURA | H18: CB CRECIMIENTO ALIANZA - NUEVO | I18: NARIÑO | J18: PASTO | K18: DISTRICOL AS SER TRANS ON LINE | L18: REDEBAN | M18: FO-25-1751773 | N18: 45959.681 | O18: 45961.555 | P18: AGREGADOR | Q18: DISTRICOL | R18: EJECUTADO/CANCELADO | S18: 29/10/2025 29-10 PROGRAMACIÓN REALIZADA POR LA ALIANZA| INSTALACIÓN PROGRAMADA PARA EL 2025-10-31 | 31/10/2025 SE LLEGÓ AL PUNTO PARA EJECUTAR LA IMPLEMENTACIÓN DE CB BANCOLOMBIA POR PARTE DE LA ALIANZA DISTRICOL PERO SE ENCONTRÓ OTRO CORRESPONSAL A MENOS DE 50 M POR LO QUE SE ESCALÓ LA NOVEDAD A RBM Y BANCOLOMBIA NOTIFICANDO A LA HORA QUE LA IMPLEMENTACIÓN DEBE SER CANCELADA SE NOTIFICA AL CLIENTE EL MOTIVO POR EL CUAL NO SE HACE LA IMPLEMENTACIÓN, NO SE ENTREGA NINGÚN ELEMENTO POR ACTIVIDAD CANCELADA. | T18: VISITA TECNICA | V18: TIPO I | W18: TERRESTRE | X18: REMICIO AMADO JOHN HEBER | Y18: 0 | Z18: 0 | AA18: 0 | AB18: 0 | AC18: 1 | AD18: 44560 | AE18: 44560
A19: PASTO | B19: SUROCCIDENTE Y EJE CAFETERO | C19: 0004-0003 | D19: 52378 | E19: TA-25-1247988 | F19: 3007082041 | G19: APERTURA | H19: CB CRECIMIENTO ALIANZA - NUEVO | I19: NARIÑO | J19: LA CRUZ | K19: DISTRICOL MASCOTIENDA LA CRUZ | L19: REDEBAN | M19: FO-25-1751783 | N19: 45959.684 | O19: 45961.715 | P19: AGREGADOR | Q19: DISTRICOL | R19: EJECUTADO/CANCELADO | S19: 29/10/2025 29-10 PROGRAMACIÓN REALIZADA POR LA ALIANZA| INSTALACIÓN PROGRAMADA PARA EL 2025-10-31 | 31/10/2025 SE VISITA CLIENTE EN UBICACIÓN INDICADA POR ELLA YA QUE EN ZONA NO HAY NOMENCLATURA. AL LLEGAR AL COMERCIO SE EVIDENCIA QUE EL NOMBRE DEL COMERCIO ES FARMACENTER LA HUMANIDAD 2 Y NO MASCOTIENDA LA CRUZ. SE SOLICITA CÁMARA DE COMERCIO Y EN ELLA EL NOMBRE ES MASCOTIENDA LA CRUZ Y LA DIRECCIÓN ES LA MISMA DEL CORREO ELECTRÓNICO. SE ESCALA A REDEBAN Y LA RESPUESTA ES QUE NO SE PROCEDA A INSTALAR YA QUE LA CÁMARA DE COMERCIO NO COINCIDE CON EL COMERCIO QUE SE VISITA. SE CANCELA INSTALACION PORQUE NOMBRE DE COMERCIO NO COINCIDE CON CAMARA DE COMERCIO | T19: VISITA TECNICA | V19: TIPO III | W19: TERRESTRE | X19: CASTILLO HERRERA ALEX RICARDO | Y19: 0 | Z19: 0 | AA19: 0 | AB19: 0 | AC19: 1 | AD19: 222904 | AE19: 222904
A20: PEREIRA | B20: SUROCCIDENTE Y EJE CAFETERO | C20: 0004-0002 | D20: 66001 | E20: TA-25-1247994 | F20: 3007082056 | G20: APERTURA | H20: CB CRECIMIENTO ALIANZA - NUEVO | I20: RISARALDA | J20: PEREIRA | K20: DISTRICOL PAPELERIA ALAN JU | L20: REDEBAN | M20: FO-25-1751801 | N20: 45959.641 | O20: 45960.581 | P20: AGREGADOR | Q20: DISTRICOL | R20: EJECUTADO/CANCELADO | S20: 29/10/2025 29-10 PROGRAMACIÓN REALIZADA POR LA ALIANZA| INSTALACIÓN PROGRAMADA PARA EL 2025-10-30 | 30/10/2025 SE LLEGA AL PUNTO, SE EVIDENCIA QUE HAY OTRO CB UNO A UNO CERCA, SE ESCALA CON RBM EL CASO Y SE QUEDA A LA ESPERA DE UNA RESPUESTA. | T20: VISITA TECNICA | V20: TIPO I | W20: TERRESTRE | X20: FRANCO CAÑAVERAL YAMID RAUL | Y20: 0 | Z20: 0 | AA20: 0 | AB20: 0 | AC20: 1 | AD20: 44560 | AE20: 44560
A21: SINCELEJO | B21: COSTA | C21: 0004-0001 | D21: 70708 | E21: TA-25-1247995 | F21: 3007082064 | G21: APERTURA | H21: CB CRECIMIENTO ALIANZA - NUEVO | I21: SUCRE | J21: SAN MARCOS | K21: DISTRICOL DROGUERÍA FARMASUCRE | L21: REDEBAN | M21: FO-25-1751804 | N21: 45959.485 | O21: 45961.57 | P21: AGREGADOR | Q21: DISTRICOL | R21: EJECUTADO/CANCELADO | S21: 29/10/2025 29-10 PROGRAMACIÓN REALIZADA POR LA ALIANZA| INSTALACIÓN PROGRAMADA PARA EL 2025-10-31 | 31/10/2025 SE VISITA COMERCIO PARA INSTALACIÓN DEL CB, PERO NO ES POSIBLE REALIZAR LA APERTURA YA QUE SE ESCALÓ EL CASO CON RBM, PUESTO QUE EL BARRIO NO CONCUERDA CON EL DE LA ORDEN DE SERVICIO, LA RESPUESTA DADA POR LA ENTIDAD ES CANCELAR LA IMPLEMENTACIÓN. | T21: VISITA TECNICA | V21: TIPO III | W21: TERRESTRE | X21: CACERES HERNANDEZ ANDRES | Y21: 0 | Z21: 0 | AA21: 0 | AB21: 0 | AC21: 1 | AD21: 222904 | AE21: 222904
AE22: =SUM(AE2:AE21) -> 2624774

Sheet INCIDENTES
A1: CIUDAD SEDE | B1: ZONA | C1: CENTRO DE COSTOS LINEACOM | D1: CODIGO DANE | E1: TA/CODIGO ACTIVIDAD | F1: CODIGO CB | G1: ACTIVIDAD | H1: DEPARTAMENTO | I1: CIUDAD | J1: NOMBRE DEL CB | K1: RED | L1: FO | M1: FECHA ASIGNACION A LINEA COMUNICACIONES | N1: FECHA CIERRE DEL TICKET (DD/MM/AAAA HH:MM) | O1: ACOMETIDA | P1: GRUPO_FALLA | Q1: CATEGORIA | R1: FALLA | S1: FORMATO | T1: CADENA | U1: ESTADO | V1: OBSERVACION | W1: FORMA DE ATENCION | X1: TERMINAL(ES) | Y1: TIPIFICACION | Z1: TIPO DE TRAYECTO | AA1: NOMBRE DEL TECNICO | AB1: DIAS DE VISITA | AC1: ACOMETIDA DATOS | AD1: ACOMETIDA ELÉCTRICA | AE1: SWITCH | AF1: ROUTER | AG1: VALOR DIAS ACTIVIDAD FACTURABLES | AH1: VALOR DIAS ACOMPAÑAMIENTO FACTURABLES
A2: NEIVA | B2: REMOTAS | C2: 0004-0007 | D2: 41349 | E2: 2807230 | F2: 3007031383 | G2: INCIDENTE | H2: HUILA | I2: HOBO | J2: BARRIO LOS PINOS | K2: REDEBAN | L2: FO-25-1607884 | FO-25-1598160 | M2: 45929.441 | N2: 45931.434 | O2: NO | P2: ENTIDAD | Q2: ERROR DE TRANSACCIONES | R2: TRANSACCION NO PERMITIDA | S2: CB UNO A UNO | T2: CB UNO A UNO | U2: EJECUTADO | EJECUTADO / CANCELADO | V2: 01/10/2025 SE REALIZA VISITA AL PUNTO NUEVAMENTE YA QUE ESTE HABIA QUEDADO EN RECHAZO GENERAL DESPUÉS DEL CAMBIO QUE SE REALIZO POR DAÑO, RG QUE NO SE PUDO GESTIONAR POR FALTA DE SOPORTE POR HORA . SE REALIZA GESTIÓN CON RBM SE INICIALIZA EQUIPO SE REALIZAN PRUEBAS EXITOSAS. SE DEJA EQUIPO CON VR 10.3 PRUEBAS CB OK . ***SE REALIZA LLAMADA A LA LÍNEA DEL BANCO 018000953344, LOS CUALES INDICAN QUE EL PUNTO SE ENCONTRABA BLOQUEADO POR RAZONES SE ASUNTOS INTERNOS, SE DESBLOQUEA PUNTO SE REALIZAN PRUEBAS PERO EN LA LÍNEA INDICAN QUE POSIBLEMENTE LO VOVERAN A BLOQUEAR. SE LE INDICA AL CLIENTE QUE SI ESTO OCURRE DEBE COMUNICACARSE DIRECTAMENTE A LA LÍNEA Y VALIDAR EL MOTIVO DEL BLOQEO . | W2: VISITA TECNICA | X2: BL01Y558 | Y2: TIPO II | Z2: TERRESTRE | AA2: DEVIA REINOSO JUAN CARLOS | AB2: 1 | AC2: 0 | AD2: 0 | AE2: 0 | AF2: 0 | AG2: 163814 | AH2: 163814
A3: CUCUTA | B3: SANTANDERES | C3: 0004-0008 | D3: 54874 | E3: 2813895 | F3: 3007071930 | G3: INCIDENTE | H3: NORTE DE SANTANDER | I3: VILLA DEL ROSARIO | J3: PTM LA PALMITA VILLA DEL ROSAR | K3: REDEBAN | L3: FO-25-1603466 | M3: 45930.414 | N3: 45931.413 | O3: NO | P3: ENTIDAD | Q3: ERROR DE TRANSACCIONES | R3: TRANSACCION NO PERMITIDA | S3: AGREGADOR | T3: COMCARD - PTM | U3: CANCELADO | V3: 30/09/2025 SE ESCALA PARA VISITA. LLAMAR ANTES DE VISITAR, CONFIRMAR FALLA Y DATOS | 01/10/2025 SE REALIZA VISITA, COMERCIO NO EXISTEN EN LA DIRECCIÓN, SE INTENTA CONTACTAR TELEFÓNICAMENTE AL CLIENTE PERO NO RESPONDE, SE VALIDA CON RBM Y LA DIRECCIÓN DE ENCUENTRA CORRECTA Y NO EXISTE INFORMACIÓN DE SOLICITUD DE TRASLADO. | W3: VISITA TECNICA | X3: NONE - NONE | Y3: TIPO I | Z3: TERRESTRE | AA3: PACHECO BUITRAGO JAVIER ALONSO | AB3: 1 | AC3: 0 | AD3: 0 | AE3: 0 | AF3: 0 | AG3: 65960 | AH3: 65960
A4: SINCELEJO | B4: COSTA | C4: 0004-0001 | D4: 70742 | E4: 2818336 | F4: 3007046075 | G4: INCIDENTE | H4: SUCRE | I4: SAN LUIS DE SINCE | J4: PTM SAN LUIS DE SINCE PUNTO SE | K4: REDEBAN | L4: FO-25-1607028 | M4: 45930.709 | N4: 45931.585 | O4: NO | P4: USUARIO | Q4: CIERRE | R4: COMERCIO NO REALIZA CIERRE | S4: AGREGADOR | T4: COMCARD - PTM | U4: EJECUTADO | V4: 30/09/2025 SE ESCALA PARA VISITA. LLAMAR ANTES DE VISITAR, CONFIRMAR FALLA Y DATOS | 01/10/2025 SE VISITA SITIO SE VERIFICA INFORMACIÓN, SE REALIZA PRIMEROS AUXILIOS, CB CON CIERRE ACUMULADO NO IMPRIME, SE REALIZA CIERRE DE TRANS, SE RETROALIMENTA EN EL PROCESO CIERRE, LA FALLA REPORTADA CORRESPONDE A QUE EL OPERARIO REALIZA LA OPERACIÓN DE RECAUDO POR DEPOSITO CTA CTE. SE REALIZA PRUEBA PRUEBAS TRX EXITOSAS. | W4: VISITA TECNICA | X4: XP004617 | Y4: TIPO II | Z4: TERRESTRE | AA4: SANTOS GUZMAN CHRISTIAN FELIPE | AB4: 1 | AC4: 0 | AD4: 0 | AE4: 0 | AF4: 0 | AG4: 163814 | AH4: 163814
A5: BOGOTA | B5: CUNDINAMARCA | C5: 0004-0004 | D5: 25754 | E5: 2818811 | F5: 3007068813 | G5: INCIDENTE | H5: CUNDINAMARCA | I5: SOACHA | J5: BARRIO HOGAR DEL SOL SOACHA SO | K5: REDEBAN | L5: FO-25-1608422 | M5: 45931.333 | N5: 45931.485 | O5: NO | P5: USUARIO | Q5: MANTENIMIENTO | R5: MANTENIMIENTO GENERAL | S5: CB UNO A UNO | T5: CB UNO A UNO | V5: 01/10/2025 SE PROCEDE A CERRAR ESTE CASO YAQUE QUEDO MAL CREADO YA QUE EL CB ES WOMPI Y QUEDO COMO REDEBAN, SE LE INFORMA AL USUARIO QUE SE DEBE COMUNICAR DE NUEVO PARA GENERAR OTRO RADICADO | 01/10/2025 SE PROCEDE A CERRAR ESTE CASO YAQUE QUEDO MAL CREADO YA QUE EL CB ES WOMPI Y QUEDO COMO REDEBAN, SE LE INFORMA AL USUARIO QUE SE DEBE COMUNICAR DE NUEVO PARA GENERAR OTRO RADICADO | 01/10/2025 SE PROCEDE A CERRAR ESTE CASO YAQUE QUEDO MAL CREADO YA QUE EL CB ES WOMPI Y QUEDO COMO REDEBAN, SE LE INFORMA AL USUARIO QUE SE DEBE COMUNICAR DE NUEVO PARA GENERAR OTRO RADICADO | 01/10/2025 SE PROCEDE A CERRAR ESTE CASO YAQUE QUEDO MAL CREADO YA QUE EL CB ES WOMPI Y QUEDO COMO REDEBAN, SE LE INFORMA AL USUARIO QUE SE DEBE COMUNICAR DE NUEVO PARA GENERAR OTRO RADICADO | W5: SOPORTE TELEFONICO | Y5: TIPO I | Z5: TERRESTRE | AA5: ORTIZ MARTINEZ STIVEN | AB5: 0 | AC5: 0 | AD5: 0 | AE5: 0 | AF5: 0 | AG5: 37905 | AH5: 37905
A6: YOPAL | B6: REMOTAS | C6: 0004-0007 | D6: 85001 | E6: 2821677 | F6: 3007036905 | G6: INCIDENTE | H6: CASANARE | I6: YOPAL | J6: BARRIO YOPAL CASANARE | K6: REDEBAN | L6: FO-25-1609710 | M6: 45931.448 | N6: 45931.959 | O6: NO | P6: USUARIO | Q6: CIERRE | R6: COMERCIO NO REALIZA CIERRE | S6: CB UNO A UNO | T6: CB UNO A UNO | V6: 01/10/2025 SE ESCALA PARA VISITA. LLAMAR ANTES DE VISITAR, CONFIRMAR FALLA Y DATOS | 01/10/2025 EN COMUNICACIÓN CON LA SEÑORA LAURA SIERRA AL NUMERO 3145591437, SE ORIENTA PARA REALIZAR EL BORRADO TRANS. SE LE INDICA EL PROCESO PARA REALIZAR LOS CIERRES TODOS LOS DIAS. | W6: SOPORTE TELEFONICO | Y6: TIPO I | Z6: TERRESTRE | AA6: BERNAL ELAICA EDGAR ALEXIS | AB6: 0 | AC6: 0 | AD6: 0 | AE6: 0 | AF6: 0 | AG6: 37905 | AH6: 37905
A7: CUCUTA | B7: SANTANDERES | C7: 0004-0008 | D7: 54874 | E7: 2822103 | F7: 3007080549 | G7: INCIDENTE | H7: NORTE DE SANTANDER | I7: VILLA DEL ROSARIO | J7: BARRIO TRAPICHES VILLA DEL ROSARIO | K7: REDEBAN | L7: FO-25-1610689 | M7: 45931.462 | N7: 45931.963 | O7: NO | P7: USUARIO | Q7: MANTENIMIENTO | R7: MANTENIMIENTO GENERAL | S7: UNO A UNO | T7: UNO A UNO | U7: EJECUTADO | V7: 01/10/2025 SE ESCALA PARA VISITA. LLAMAR ANTES DE VISITAR, CONFIRMAR FALLA Y DATOS | 01/10/2025 SE REALIZA VISITA, SE REALIZA MANTENIMIENTO, SE REALIZAN PRUEBAS Y CIERRES OK | W7: VISITA TECNICA | X7: SEZZZ162 | Y7: TIPO I | Z7: TERRESTRE | AA7: PACHECO BUITRAGO JAVIER ALONSO | AB7: 1 | AC7: 0 | AD7: 0 | AE7: 0 | AF7: 0 | AG7: 65960 | AH7: 65960
A8: MEDELLIN | B8: NOROCCIDENTE | C8: 0004-0005 | D8: 5615 | E8: 2823798 | F8: 3007074672 | G8: INCIDENTE | H8: ANTIOQUIA | I8: RIONEGRO | J8: PTM LLANOGRANDE MEDELLIN PAPEL | K8: REDEBAN | L8: FO-25-1611652 | M8: 45931.612 | N8: 45933.495 | O8: NO | P8: USUARIO | Q8: COMUNICACION | R8: CANAL DEL COMERCIO | S8: AGREGADOR | T8: COMCARD - PTM | U8: EJECUTADO | V8: 01/10/2025 SE ESCALA PARA VISITA. LLAMAR ANTES DE VISITAR, CONFIRMAR FALLA Y DATOS | 03/10/2025 SE REALIZA VALIDACIÓN DEL CB SE HACEN PRUEBAS OK , SE LLEGA Y USUARIO E UD OCA QUE HABÍA SOLICITADO CAMBIO PERO DEL DATAFONO DEL COMERCIO | W8: VISITA TECNICA | X8: LNQZZ022 | Y8: TIPO II | Z8: TERRESTRE | AA8: MONTOYA VELEZ ANDRES FELIPE | AB8: 1 | AC8: 0 | AD8: 0 | AE8: 0 | AF8: 0 | AG8: 163814 | AH8: 163814
A9: CALI | B9: SUROCCIDENTE Y EJE CAFETERO | C9: 0004-0003 | D9: 76126 | E9: 2823985 | F9: 3007079619 | G9: INCIDENTE | H9: VALLE DEL CAUCA | I9: CALIMA | J9: BARRIO OBRERO CALIMA | K9: REDEBAN | L9: FO-25-1611647 | M9: 45931.617 | N9: 45932.646 | O9: NO | P9: USUARIO | Q9: MANTENIMIENTO | R9: MANTENIMIENTO GENERAL | S9: CB UNO A UNO | T9: CB UNO A UNO | U9: EJECUTADO | V9: 01/10/2025 SE ESCALA PARA VISITA. LLAMAR ANTES DE VISITAR, CONFIRMAR FALLA Y DATOS | 02/10/2025 SE VISITA CORRESPONSAL Y SE RECONFIGURA DATÁFONO. TRANSACCIONES DE PRUEBA EXITOSAS. | W9: VISITA TECNICA | X9: SXUZZ145 | Y9: TIPO II | Z9: TERRESTRE | AA9: BOLAÑOS TABORDA JORGE ENRIQUE | AB9: 1 | AC9: 0 | AD9: 0 | AE9: 0 | AF9: 0 | AG9: 163814 | AH9: 163814
A10: CALI | B10: SUROCCIDENTE Y EJE CAFETERO | C10: 0004-0003 | D10: 76001 | E10: 2826164 | F10: 3007059017 | G10: INCIDENTE | H10: VALLE DEL CAUCA | I10: CALI | J10: REDY GUADALUPE | K10: REDEBAN | L10: FO-25-1613641 | M10: 45932.333 | N10: 45932.64 | O10: NO | P10: USUARIO | Q10: MANTENIMIENTO | R10: MANTENIMIENTO GENERAL | S10: ROBUSTO | T10: REDY | U10: EJECUTADO / CANCELADO | V10: 02/10/2025 SE ESCALA PARA VISITA. LLAMAR ANTES DE VISITAR | 02/10/2025 SE REALIZA VISITA TÉCNICA EN DONDE SE ENTREGA EL CARNET Y SE ESPERA 45 MINUTOS EN DONDE NO LE DAN RESPUESTA DE INGRESO Y SE PROCEDE A CERRAR, SE LE INDICA AL CLIENTE QUE POR FAVOR VUELVA A REPORTAR PARA QUE LE GENEREN OTRA VISITA | W10: VISITA TECNICA | X10: NO | Y10: TIPO I | Z10: TERRESTRE | AA10: ESCOBAR LENIS JUAN SEBASTIAN | AB10: 1 | AC10: 0 | AD10: 0 | AE10: 0 | AF10: 0 | AG10: 65960 | AH10: 65960
A11: CALI | B11: SUROCCIDENTE Y EJE CAFETERO | C11: 0004-0003 | D11: 19256 | E11: 2827571 | F11: 3007066562 | G11: INCIDENTE | H11: CAUCA | I11: EL TAMBO | J11: BARRIO LA CAPILLA EL TAMBO | K11: REDEBAN | L11: FO-25-1614205 | M11: 45932.373 | N11: 45934.44 | O11: NO | P11: USUARIO | Q11: COMUNICACION | R11: CANAL DEL COMERCIO | S11: CB UNO A UNO | T11: CB UNO A UNO | V11: 02/10/2025 SE REALIZAN 3 INTENTOS DE LLAMADA AL NUMERO DE CONTACTO 3226466689 PERO NO FUE POSIBLE LA COMUNICACION | 04/10/2025 SE VALIDA CON EL CLIENTE POR PROBLEMAS DE CONEXION , SE LE INDICA QUE POR FAVOR REALIZR REINICIO DEL ROUTER DE INTENET, EL CLIENTE REALIZA LO PERTIENENTE Y CONFIRMA SERVICIO Y OPERATIVIDAD DEL DATAFONO, SE CIERRA CASO | W11: SOPORTE TELEFONICO | Y11: TIPO III | Z11: TERRESTRE | AA11: HENAO CARDONA DIEGO FERNANDO | AB11: 0 | AC11: 0 | AD11: 0 | AE11: 0 | AF11: 0 | AG11: 37905 | AH11: 37905
A12: CUCUTA | B12: SANTANDERES | C12: 0004-0008 | D12: 54874 | E12: 2829063 | F12: 3007077939 | G12: INCIDENTE | H12: NORTE DE SANTANDER | I12: VILLA DEL ROSARIO | J12: BARRIO 20 JULIO VILLA DEL ROSA | K12: REDEBAN | L12: FO-25-1615600 | M12: 45932.446 | N12: 45933.384 | O12: NO | P12: USUARIO | Q12: COMUNICACION | R12: CONEXIONES DE COMERCIO | S12: CB UNO A UNO | T12: CB UNO A UNO | U12: EJECUTADO | V12: 02/10/2025 SE ESCALA PARA VISITA. LLAMAR ANTES DE VISITAR | 03/10/2025 SE VISITA COMERCIO Y SE EVIDENCIA SWITCH DEL CLIENTE DAÑADO, SE ALIMENTAN DATOS DE DATÁFONO DIRECTAMENTE, SE LE INDICA AL CLIENTE EL EQUIPO QUE TIENEN DAÑADO, SE REALIZAN CIERRES Y PRUEBAS OK. | W12: VISITA TECNICA | X12: A1NZZ992 | Y12: TIPO I | Z12: TERRESTRE | AA12: TORRES MANTILLA JOSE DANIEL | AB12: 1 | AC12: 0 | AD12: 0 | AE12: 0 | AF12: 0 | AG12: 65960 | AH12: 65960
A13: PASTO | B13: SUROCCIDENTE Y EJE CAFETERO | C13: 0004-0003 | D13: 86568 | E13: 2829426 | F13: 3007067186 | G13: INCIDENTE | H13: PUTUMAYO | I13: PUERTO ASIS | J13: DISTRICOL LUXURY GM | K13: REDEBAN | L13: FO-25-1615579 | M13: 45932.457 | N13: 45932.749 | O13: NO | P13: USUARIO | Q13: MANTENIMIENTO | R13: MANTENIMIENTO GENERAL | S13: AGREGADOR | T13: DISTRICOL | U13: EJECUTADO | V13: 02/10/2025 SE REALIZÓ VISITAR CORRESPONSAL PARA REVISAR FALLAS DE LECTORA Y DE IMPRESIÓN, SE REALIZÓ CONFIGURACIÓN DE LECTORA, Y LIMPIEZA DE DATÁFONO, SE REALIZÓ PRUEBAS EXITOSAS, EL CORRESPONSAL ESTÁ OPERATIVO | W13: VISITA TECNICA | X13: AAL06527 | Y13: TIPO IV | Z13: TERRESTRE | AA13: GUERRERO RAMIREZ OSCAR DARIO | AB13: 1 | AC13: 0 | AD13: 0 | AE13: 0 | AF13: 0 | AG13: 479590 | AH13: 479590
A14: CALI | B14: SUROCCIDENTE Y EJE CAFETERO | C14: 0004-0003 | D14: 76001 | E14: 2830256 | F14: 3007034770 | G14: INCIDENTE | H14: VALLE DEL CAUCA | I14: CALI | J14: BARRIO MONTEBELLO 1 CALI | K14: REDEBAN | L14: FO-25-1616165 | M14: 45932.513 | N14: 45933.381 | O14: NO | P14: USUARIO | Q14: USUARIOS | R14: USUARIOS BLOQUEADOS | S14: UNO A UNO | T14: CB UNO A UNO | V14: 02/10/2025 SE ESCALA PARA VISITA. LLAMAR ANTES DE VISITAR | 03/10/2025 SE REALIZA VALIDACION CON EL CLIENTE INDICA QUE EL USUARIO SE LE HABIA BLOQUEADO Y NO LE DEJABA INGRESAR PERO , QUE PUDO ORGANIZARLO COMO LO NECESITABA | W14: SOPORTE TELEFONICO | Y14: TIPO I | Z14: TERRESTRE | AA14: HENAO CARDONA DIEGO FERNANDO | AB14: 0 | AC14: 0 | AD14: 0 | AE14: 0 | AF14: 0 | AG14: 37905 | AH14: 37905
A15: PASTO | B15: SUROCCIDENTE Y EJE CAFETERO | C15: 0004-0003 | D15: 52051 | E15: 2832368 | F15: 3007047683 | G15: INCIDENTE | H15: NARIÑO | I15: ARBOLEDA | J15: DISTRICOL DROGUERIA JUAN JOSE | K15: REDEBAN | L15: FO-25-1617910 | M15: 45932.684 | N15: 45934.443 | O15: NO | P15: USUARIO | Q15: COMUNICACION | R15: CANAL DEL COMERCIO | S15: AGREGADOR | T15: DISTRICOL | V15: 02/10/2025 SE COMUNICA CON EL SR RICARDO PARA REPORTAR QUE EL DATÁFONO SE VIENE REINICIANDO A DIARIO 1 VEZ POR DÍA, PER HOY SE HA REINICIADO DE MANERA AUTOMÁTICA MÁS DE 3 VECES, | 04/10/2025 SE VALIDA CON EL CLIENTE POR PROBLEMAS DE CONEXION , SE LE INDICA QUE POR FAVOR REALIZR REINICIO DEL ROUTER DE INTENET, EL CLIENTE REALIZA LO PERTIENENTE Y CONFIRMA SERVICIO Y OPERATIVIDAD DEL DATAFONO, SE CIERRA CASO | W15: SOPORTE TELEFONICO | Y15: TIPO II | Z15: TERRESTRE | AA15: HENAO CARDONA DIEGO FERNANDO | AB15: 0 | AC15: 0 | AD15: 0 | AE15: 0 | AF15: 0 | AG15: 37905 | AH15: 37905
A16: MONTERIA | B16: COSTA | C16: 0004-0001 | D16: 5154 | E16: 2832487 | F16: 3007075821 | G16: INCIDENTE | H16: ANTIOQUIA | I16: CAUCASIA | J16: PTM CAUCASIA PAPELERIA G J | K16: REDEBAN | L16: FO-25-1626785 | M16: 45932.696 | N16: 45937.706 | O16: NO | P16: USUARIO | Q16: MANTENIMIENTO | R16: MANTENIMIENTO GENERAL | S16: AGREGADOR | T16: COMCARD - PTM | U16: EJECUTADO | V16: 03/10/2025 SE ESCALA PARA VISITA. LLAMAR ANTES DE VISITAR | 07/10/2025 SE VISITA SITIO, SE INSTALA DATAFONO DEK3500 POR REPOSICIÓN OK. SE INICIALIZA TERMINALES DE CB Y ADQUIRENCIA PERO DATAFONO NO MUESTRA MÓDULO DE CB, SE REALIZA REFRESH DE TERMINALES PERO SIGUE CON NOVEDAD, CB INDICA QUE NO UTILIZA MÓDULO DE ADQUIRENCIA, POR LO CUAL AUTORIZA QUE SE DEJE EQUIPO COMO PURO, SE CAMBIA DATAFONO INSTALADO POR DAÑO RG, NO SE REALIZAN PRUEBAS CB BLOQUEADO POR ENTIDAD | W16: VISITA TECNICA | X16: VRZZZ270 | Y16: TIPO II | Z16: TERRESTRE | AA16: COGOLLO VERTEL EDER LUIS | AB16: 1 | AC16: 0 | AD16: 0 | AE16: 0 | AF16: 0 | AG16: 163814 | AH16: 163814
A17: MEDELLIN | B17: NOROCCIDENTE | C17: 0004-0005 | D17: 5001 | E17: 2832687 | F17: 3007068764 | G17: INCIDENTE | H17: ANTIOQUIA | I17: MEDELLIN | J17: PTM MEDELLIN DISTRIBUIDORA MOR | K17: REDEBAN | L17: FO-25-1618123 | M17: 45932.721 | N17: 45933.481 | O17: NO | P17: USUARIO | Q17: MANTENIMIENTO | R17: MANTENIMIENTO GENERAL | S17: AGREGADOR | T17: COMCARD - PTM | U17: EJECUTADO | V17: 02/10/2025 SE ESCALA PARA VISITA. LLAMAR ANTES DE VISITAR | 03/10/2025 SE VERIFICAN PARÁMETROS SE VERIFICA CABLEADO Y TAMBIÉN SE REALIZA MANTENIMIENTO DE LECTOR DE TARJETAS HACIENDO LIMPIEZA CON ALCOHOL. TODO ESTÁ FUNCIONANDO CORRECTAMENTE. | W17: VISITA TECNICA | X17: AALUZ190 - AALUZ336 | Y17: TIPO I | Z17: TERRESTRE | AA17: RAMIREZ TABARES JUAN DIEGO | AB17: 1 | AC17: 0 | AD17: 0 | AE17: 0 | AF17: 0 | AG17: 65960 | AH17: 65960
A18: PASTO | B18: SUROCCIDENTE Y EJE CAFETERO | C18: 0004-0003 | D18: 52835 | E18: 2837077 | F18: 3007046106 | G18: INCIDENTE | H18: NARIÑO | I18: SAN ANDRES DE TUMACO | J18: BARRIO PUENTE ORTIZ SAN ANDRES | K18: REDEBAN | L18: FO-25-1625936 | M18: 45933.607 | N18: 45937.387 | O18: NO | P18: USUARIO | Q18: MANTENIMIENTO | R18: MANTENIMIENTO GENERAL | S18: CB UNO A UNO | T18: CB UNO A UNO | U18: EJECUTADO | V18: 03/10/2025 SE COMUNICA CON EL SR LUIS ANGULO PARA REPORTAR QUE LA IMPRESORA ESTA DAÑADA YA QUE, IMPRIME BORROSO, YA CAMBIO EL ROLLO PERO PERSISTE E INDICA QUE HA TENIDO PROBLEMA CON VARIOS CLIENTES 3003709163 2: 47 PM | 07/10/2025 SE ENCUENTRA DATAFONO CON IMPRESIÓN BORROSA SE REALIZA MANTENIMIENTO GENERAL AL DATAFONO Y SE OBTIENE FUNCIONAMIENTO EXITOSO CONFIGURACIÓN OK PARÁMETROS OK Y SE REALIZAN PRUEBAS EXITOSAS DE TRANSACCIONES | W18: VISITA TECNICA | X18: TR003801 | Y18: TIPO IV | Z18: TERRESTRE | AA18: PAZ MARTINEZ RICHARD HUMBERTO | AB18: 1 | AC18: 0 | AD18: 0 | AE18: 0 | AF18: 0 | AG18: 479590 | AH18: 479590
A19: VILLAVICENCIO | B19: REMOTAS | C19: 0004-0007 | D19: 50686 | E19: 2837222 | F19: 3007021483 | G19: INCIDENTE | H19: META | I19: SAN JUANITO | J19: SAN JUANITO META | K19: REDEBAN | L19: FO-25-1625929 | M19: 45933.612 | N19: 45936.409 | O19: NO | P19: USUARIO | Q19: COMUNICACION | R19: CONEXIONES DE COMERCIO | S19: CB UNO A UNO | T19: CB UNO A UNO | V19: 03/10/2025 LUIS ANGULO PARA REPORTAR QUE LA IMPRESORA ESTA DAÑADA YA QUE, IMPRIME BORROSO, YA CAMBIO EL ROLLO PERO PERSISTE E INDICA QUE HA TENIDO PROBLEMA CON VARIOS CLIENTES | 06/10/2025 SE CONTACTA AL CLIENTE VIKI ORTIS E INFORMA QUE EL SERVICIO YA SE ENCUENTRA OPERATIVO Y QUE HABÍA LLAMADO A DESISTIR DE LA VISITA TÉCNICO ERA LAS CONEXIONES FÍSICAS | W19: SOPORTE TELEFONICO | Y19: TIPO IV | Z19: TERRESTRE | AA19: ROZO JIMENEZ EDGAR ARMANDO | AB19: 0 | AC19: 0 | AD19: 0 | AE19: 0 | AF19: 0 | AG19: 37905 | AH19: 37905
A20: SANTA MARTA | B20: COSTA | C20: 0004-0001 | D20: 44430 | E20: 2837542 | F20: 3007078712 | G20: INCIDENTE | H20: LA GUAJIRA | I20: MAICAO | J20: PTM MAICAO TIENDA Y VARIEDADES | K20: REDEBAN | L20: FO-25-1626342 | M20: 45933.641 | N20: 45936.583 | O20: NO | P20: ENTIDAD | Q20: ERROR DE TRANSACCIONES | R20: TRANSACCION NO PERMITIDA | S20: AGREGADOR | T20: COMCARD - PTM | U20: EJECUTADO | V20: 03/10/2025 SE COMUNICA CON EL SR HOLMER, DATAFONO ARROJA MUY BORROSO LOS VOUCHER, INTERNET PROPIO Y FUNCIONA BIEN 3115485300 3:25 PM | 06/10/2025 SE REALIZA LA VISITA, EL USUARIO INFORMA QUE YA EL DATÁFONO ESTÁ TRABAJANDO BIEN DE HECHO AL DÍA SIGUIENTE QUE SE PRESENTÓ EL DAÑO, SE REALIZA PRUEBAS DE TRANSACCIÓN Y TODO OK | W20: VISITA TECNICA | X20: A1RZZ262 - A1RZZ369 | Y20: TIPO IV | Z20: TERRESTRE | AA20: THOMAS CAMPO SIGIFREDO SEGUNDO | AB20: 1 | AC20: 0 | AD20: 0 | AE20: 0 | AF20: 0 | AG20: 479590 | AH20: 479590
A21: CALI | B21: SUROCCIDENTE Y EJE CAFETERO | C21: 0004-0003 | D21: 76892 | E21: 2838376 | F21: 3007079709 | G21: INCIDENTE | H21: VALLE DEL CAUCA | I21: YUMBO | J21: PTM YUMBO PAPELERIA MILU YUMBO | K21: REDEBAN | L21: FO-25-1626991 | M21: 45933.728 | N21: 45934.51 | O21: NO | P21: USUARIO | Q21: USUARIOS | R21: MALA MANIPULACION POS | S21: AGREGADOR | T21: COMCARD - PTM | U21: EJECUTADO | V21: 03/10/2025 SE ESCALA PARA VISITA. LLAMAR ANTES DE VISITAR | 04/10/2025 SE VISITA CORRESPONSAL E INFORMA QUE EL DATÁFONO FUNCIONA CORRECTAMENTE . PIDE CERRAR CASO. NO SE MANIPULAN EQUIPOS NI SE INGRESA AL CB. | W21: VISITA TECNICA | X21: V1YZZ451 | Y21: TIPO I | Z21: TERRESTRE | AA21: BOLAÑOS TABORDA JORGE ENRIQUE | AB21: 1 | AC21: 0 | AD21: 0 | AE21: 0 | AF21: 0 | AG21: 65960 | AH21: 65960
A22: BARRANQUILLA | B22: COSTA | C22: 0004-0001 | D22: 47675 | E22: 2838839 | F22: 3007035493 | G22: INCIDENTE | H22: MAGDALENA | I22: SALAMINA | J22: DISTRICOL LA PERSEVERANCIA | K22: REDEBAN | L22: FO-25-1628331 | M22: 45934.333 | N22: 45936.456 | O22: NO | P22: USUARIO | Q22: COMUNICACION | R22: CONEXIONES DE COMERCIO | S22: AGREGADOR | T22: DISTRICOL | V22: 04/10/2025 SE ESCALA PARA VISITA. LLAMAR ANTES DE VISITAR | 06/10/2025 EN COMUNICACIÓN CON EL SEÑOR LUIS PERTUZ AL NÚMERO 3004626987, ME INFORMA QUE YA NO ES NECESARIA LA VISITA , QUE TENÍAN PROBLEMAS CON UNA CONEXIÓN INTERNA, PERO QUE YA LO SOLUCIONARON | W22: SOPORTE TELEFONICO | Y22: TIPO II | Z22: TERRESTRE | AA22: DE AVILA SIADES ALBERTO ENRIQUE | AB22: 0 | AC22: 0 | AD22: 0 | AE22: 0 | AF22: 0 | AG22: 37905 | AH22: 37905
A23: MEDELLIN | B23: NOROCCIDENTE | C23: 0004-0005 | D23: 5756 | E23: 2840606 | F23: 3007076637 | G23: INCIDENTE | H23: ANTIOQUIA | I23: SONSON | J23: BARRIO SONSON SONSON 6 | K23: REDEBAN | L23: FO-25-1631222 | M23: 45935.448 | N23: 45936.627 | O23: NO | P23: USUARIO | Q23: COMUNICACION | R23: CANAL DEL COMERCIO | S23: CB UNO A UNO | T23: CB UNO A UNO | V23: 05/10/2025 SE ESCALA PARA VISITA. LLAMAR ANTES DE VISITAR, CONFIRMAR FALLA Y DATOS | 06/10/2025 SE LLAMA AL 3205395286 Y SE HA LA CON ANGIE LA CUAL INFORMA QUE YA FUNCIONA BIEN Y NO NECESITA VISITA | W23: SOPORTE TELEFONICO | Y23: TIPO III | Z23: TERRESTRE | AA23: ALVAREZ ARENAS VICTOR HUGO | AB23: 0 | AC23: 0 | AD23: 0 | AE23: 0 | AF23: 0 | AG23: 37905 | AH23: 37905
A24: MONTERIA | B24: COSTA | C24: 0004-0001 | D24: 5154 | E24: 2843176 | F24: 3007080876 | G24: INCIDENTE | H24: ANTIOQUIA | I24: CAUCASIA | J24: BARRIO ASOVIVIENDA CAUCASIA 2 | K24: REDEBAN | L24: FO-25-1634137 | M24: 45936.43 | N24: 45937.503 | O24: NO | P24: USUARIO | Q24: USUARIOS | R24: USUARIOS BLOQUEADOS | S24: UNO A UNO | T24: UNO A UNO | U24: EJECUTADO | V24: 06/10/2025 SE ESCALA PARA VISITA. LLAMAR ANTES DE VISITAR, CONFIRMAR FALLA Y DATOS | 07/10/2025 SE VISITA SITIO, SE REALIZA DESBLOQUEO DE TECLADO CON CLAVE SUPERVISOR OK PRUEBAS EXITOSAS | W24: VISITA TECNICA | X24: FGZZZ910 | Y24: TIPO II | Z24: TERRESTRE | AA24: COGOLLO VERTEL EDER LUIS | AB24: 1 | AC24: 0 | AD24: 0 | AE24: 0 | AF24: 0 | AG24: 163814 | AH24: 163814
A25: YOPAL | B25: REMOTAS | C25: 0004-0007 | D25: 85001 | E25: 2845916 | F25: 3007080510 | G25: INCIDENTE | H25: CASANARE | I25: YOPAL | J25: DISTRICOL DROGUE FARMA ORIENTE | K25: REDEBAN | L25: FO-25-1635899 | M25: 45936.606 | N25: 45936.738 | O25: NO | P25: USUARIO | Q25: COMUNICACION | R25: CONEXIONES DE COMERCIO | S25: AGREGADOR | T25: DISTRICOL | V25: 06/10/2025 SE ESCALA PARA VISITA. LLAMAR ANTES DE VISITAR, CONFIRMAR FALLA Y DATOS | 06/10/2025 EN COMUNICACIÓN CON LA SEÑORA NICOL ZAPATA 3106889846, INDICA QUE NO REQUIERE LA VISITA, LA FALLA FUE RESUELTA POR PERSONAL DE INTERNET PROPIO. INDICA OPERATIVO EL SERVICIO. | W25: SOPORTE TELEFONICO | Y25: TIPO I | Z25: TERRESTRE | AA25: BERNAL ELAICA EDGAR ALEXIS | AB25: 0 | AC25: 0 | AD25: 0 | AE25: 0 | AF25: 0 | AG25: 37905 | AH25: 37905
A26: BOGOTA | B26: CUNDINAMARCA | C26: 0004-0004 | D26: 11001 | E26: 2847580 | F26: 3007061294 | G26: INCIDENTE | H26: CUNDINAMARCA | I26: BOGOTA | J26: BARRIO BOSA LIBERTAD BOGOTA 4 | K26: REDEBAN | L26: FO-25-1637291 | M26: 45936.708 | N26: 45937.703 | O26: NO | P26: USUARIO | Q26: MANTENIMIENTO | R26: MANTENIMIENTO GENERAL | S26: CB UNO A UNO | T26: CB UNO A UNO | U26: EJECUTADO / CANCELADO | V26: 06/10/2025 SE ESCALA PARA VISITA. LLAMAR ANTES DE VISITAR, CONFIRMAR FALLA Y DATOS | 07/10/2025 SE REALIZA VISITA AL LLEGAR A CB SE ENCUENTRA CERRADO SE LLAMA A ENCARGADA ALEJANDRA MUÑOZ AL NUMERO 3133404113 EL CUAL NO SE TIENE COMUNICACIÓN SE DEJA REGISTRO FOTOGRÁFICO | W26: VISITA TECNICA | X26: FUAOH983 | Y26: TIPO I | Z26: TERRESTRE | AA26: JAIMES VALERO NELSON RICARDO | AB26: 1 | AC26: 0 | AD26: 0 | AE26: 0 | AF26: 0 | AG26: 65960 | AH26: 65960
A27: NEIVA | B27: REMOTAS | C27: 0004-0007 | D27: 18001 | E27: 2847972 | F27: 3007076544 | G27: INCIDENTE | H27: CAQUETA | I27: FLORENCIA | J27: OPRAP EXITO GRAN PLAZA FLORENC | K27: REDEBAN | L27: FO-25-1638491 | M27: 45937.333 | N27: 45938.626 | O27: NO | P27: USUARIO | Q27: COMUNICACION | R27: CONEXIONES DE COMERCIO | S27: ROBUSTO | T27: OPRAP | U27: EJECUTADO | V27: 07/10/2025 SE ESCALA PARA VISITA. LLAMAR ANTES DE VISITAR, CONFIRMAR FALLA Y DATOS | 07/10/2025 SE REALIZO CONTACTÓ TELEFÓNICO Y VÍA WHATSAPP CON LA SEÑORA MARCELA AL NÚMERO 320 9153649 PARA REALIZAR LA VISITA AL OPPRAP, PERO SE DEBE GENERAR UN PERMISO DE INGRESO POR PARTE DE OPPRAP PARA QUE PUEDA ENTRAR AL ESTACIONAMIENTO, SE ENVÍA CERTIFICADO DE SEGURIDAD SOCIAL PARA EL INGRESO, ESTOY ATENTO A QUE LA SEÑORA MARCELA ME CONFIRME SI PUEDE INGRESAR AL ESTABLECIMIENTO. | 08/10/2025 SE REALIZA BORRADO DE MEMORIA POR LENTITUD EN LAS TRANSACCIONES Y SE ORGANIZAN LOS CABLES YA QUE ESTABAN GENERANDO DESCONEXIÓN EN EL EQUIPO, PRUEBAS CB OK SE DEJA OPERATIVO. | W27: VISITA TECNICA | X27: 103ZZ224 | Y27: TIPO IV | Z27: TERRESTRE | AA27: BERMUDEZ SANCHEZ JOSE NEYBER | AB27: 1 | AC27: 0 | AD27: 0 | AE27: 0 | AF27: 0 | AG27: 479590 | AH27: 479590
A28: PASTO | B28: SUROCCIDENTE Y EJE CAFETERO | C28: 0004-0003 | D28: 52001 | E28: 2850211 | F28: 3007029176 | G28: INCIDENTE | H28: NARIÑO | I28: PASTO | J28: BARRIO CENTENARIO 3 PASTO | K28: REDEBAN | L28: FO-25-1639582 | M28: 45937.425 | N28: 45937.653 | O28: NO | P28: USUARIO | Q28: COMUNICACION | R28: CANAL DEL COMERCIO | S28: CB UNO A UNO | T28: CB UNO A UNO | U28: EJECUTADO | V28: 07/10/2025 SE ESCALA PARA VISITA. LLAMAR ANTES DE VISITAR, CONFIRMAR FALLA Y DATOS | 07/10/2025 SE VERIFICÓ FALLA DE ERROR DE CONEXIÓN, SE VERIFICA CABLEADO, SE REVISO CONEXIÓN CON CADA ROUTER DEL CLIENTE PERO FALLA PERSISTE, SE INTENTÓ CONECTAR OTROS DATÁFONOS HACIENDO PRUEBAS DE CONEXIÓN PERO FALLA PERSISTE, SE ESTABLECIÓ IP ESTÁTICA Y LIBRE PERO AÚN SIGUE LA FALLA, POR LO CUAL LA FALLA ES DEL MODEN DEL OPERADOR DE INTERNET PERO ESTE NO SE PUEDE REINICIAR YA QUE ES LA CONEXIÓN PRINCIPAL DEL CLIENTE PORQUE MANEJA CONEXIONES DE SERVIDOR INTERNAS, POR LO CUAL NO SE PUDE RESTABLECER LA CONEXIÓN AL DATÁFONO ASÍ QUE SE LE INDICO AL CLIENTE QUE APENAS EN LA NOCHE CUANDO YA NO REALICEN MÁS ACTIVIDADES DE COMERCIO REINICIEN EL MÓDEM Y REALICEN PRUEBAS DE COMUNICACIÓN EL DÍA SIGUIENTE SI LA FALLA PERSISTE QUE POR FAVOR VERIFIQUEN CON EL OPERADOR DE INTERNET O EN SU CASO REPORTAR NUEVAMENTE A LA ENTIDAD BANCARIA. | W28: VISITA TECNICA | X28: BBBBI984 | Y28: TIPO I | Z28: TERRESTRE | AA28: REMICIO AMADO JOHN HEBER | AB28: 1 | AC28: 0 | AD28: 0 | AE28: 0 | AF28: 0 | AG28: 65960 | AH28: 65960
A29: MEDELLIN | B29: NOROCCIDENTE | C29: 0004-0005 | D29: 5353 | E29: 2850255 | F29: 3007038046 | G29: INCIDENTE | H29: ANTIOQUIA | I29: HISPANIA | J29: BARRIO CALLE SALIDA HISPANIA H | K29: REDEBAN | L29: FO-25-1640061 | M29: 45937.432 | N29: 45939.605 | O29: NO | P29: USUARIO | Q29: COMUNICACION | R29: CONEXIONES DE COMERCIO | S29: CB UNO A UNO | T29: CB UNO A UNO | U29: EJECUTADO | V29: 07/10/2025 SE COMUNICA CON LA SRE ELSA PARA REPORTAR QUE EL CABLE QUE VA CONECTADO AL DATAFONO SE DAÑO, Y EL DATAFONO YA NO CONECTA CON LA CAJA, POR QUE E CABLE NO FUNCIONA 3117333003 10:44 | 09/10/2025 SE CAMBIA LECTOR DE BARRAS CON CABLE DAÑADO | W29: VISITA TECNICA | X29: AA00T745 | Y29: TIPO III | Z29: TERRESTRE | AA29: CASTAÑEDA PALACIO CARLOS FELIPE | AB29: 1 | AC29: 0 | AD29: 0 | AE29: 0 | AF29: 0 | AG29: 275728 | AH29: 275728
A30: MONTERIA | B30: COSTA | C30: 0004-0001 | D30: 23001 | E30: 2850429 | F30: 3007075532 | G30: INCIDENTE | H30: CORDOBA | I30: MONTERIA | J30: PTM MONTERIA PAPELERIA +X- | K30: REDEBAN | L30: FO-25-1640048 | M30: 45937.435 | N30: 45937.656 | O30: NO | P30: USUARIO | Q30: COMUNICACION | R30: CANAL DEL COMERCIO | S30: AGREGADOR | T30: COMCARD - PTM | U30: EJECUTADO | V30: 07/10/2025 SE ESCALA PARA VISITA. LLAMAR ANTES DE VISITAR, CONFIRMAR FALLA Y DATOS | 07/10/2025 SE REALIZA VISITA TÉCNICA Y SE ENCONTRÓ FALLAS CON PTO LAN DEL COMERCIO, SE HACE NECESARIO CAMBIAR DE PTO LA CONEXIÓN LAN DEL DATÁFONO PARA VOLVER RESTABLECER EL SERVICIO Y DEJAR OK. SE REALIZAN PRUEBAS OK. | W30: VISITA TECNICA | X30: SX00J089 - SX00J151 | Y30: TIPO I | Z30: TERRESTRE | AA30: CASSIANI PEREZ RAUL RAMIRO | AB30: 1 | AC30: 0 | AD30: 0 | AE30: 0 | AF30: 0 | AG30: 65960 | AH30: 65960
A31: BUCARAMANGA | B31: SANTANDERES | C31: 0004-0008 | D31: 20770 | E31: 2851577 | F31: 3007081736 | G31: INCIDENTE | H31: CESAR | I31: SAN MARTIN | J31: DISTRICOL MISCELANIA ISAVIC | K31: REDEBAN | L31: FO-25-1641179 | M31: 45937.513 | N31: 45939.618 | O31: NO | P31: USUARIO | Q31: COMUNICACION | R31: CONEXIONES DE COMERCIO | S31: AGREGADOR | T31: DISTRICOL | V31: 07/10/2025 SE REALIZAN 3 INTENTOS DE LLAMADAS AL NUMERO DE CONTACTO 3165079528 PERO NO FUE POSIBLE LA COMUNICACION | 09/10/2025 EN COMUNICACIÓN CON LA SEÑORA LEIDY GELVEZ , MANIFIESTA Q ERA UNA FALLLA DEL INTERNET QUE EL DATAFONO YA SE ENCUENTRA FUNCIONANDO CORRECTAMENTE ,Y ESTA OPERATIVO, SE LE INDICA AL CLIENTE Q SE PROCEDE A CERRAR ORDEN. | W31: SOPORTE TELEFONICO | Y31: TIPO III | Z31: TERRESTRE | AA31: GELVEZ MOGOLLON JOSE ELISEO | AB31: 0 | AC31: 0 | AD31: 0 | AE31: 0 | AF31: 0 | AG31: 37905 | AH31: 37905
A32: NEIVA | B32: REMOTAS | C32: 0004-0007 | D32: 41001 | E32: 2851722 | F32: 3007040764 | G32: INCIDENTE | H32: HUILA | I32: NEIVA | J32: DISTRICOL FRUVER DON EDER | K32: REDEBAN | L32: FO-25-1641165 | M32: 45937.519 | N32: 45938.456 | O32: NO | P32: USUARIO | Q32: MANTENIMIENTO | R32: MANTENIMIENTO GENERAL | S32: AGREGADOR | T32: DISTRICOL | V32: 07/10/2025 SE ESCALA PARA VISITA. LLAMAR ANTES DE VISITAR, CONFIRMAR FALLA Y DATOS | 08/10/2025 SE LLAMA AL CLIENTE EDER PASCUAS AL CELULAR 3152980015 , SE COMENTA QUE DE NUESTRA PARTE NO PODEMOS REALIZAR EL CAMBIO DE NOMBRE DE CB EN EL BAUCHER HASTA QUE DISTRICOL REALICE Y AUTORICE EL CAMBIO DE RAZÓN SOCIAL Y SALGA LA ORDEN COMO INSTALACIÓN NUEVA PARA NOSOTROS PROCEDER CON EL CAMBIO DE EQUIPOS Y ACTUALIZACIÓN DE LA INFORMACIÓN EN EL BAUCHER . | W32: SOPORTE TELEFONICO | Y32: TIPO I | Z32: TERRESTRE | AA32: ANDRADE HERNANDEZ JUAN CARLOS | AB32: 0 | AC32: 0 | AD32: 0 | AE32: 0 | AF32: 0 | AG32: 37905 | AH32: 37905
A33: MEDELLIN | B33: NOROCCIDENTE | C33: 0004-0005 | D33: 5001 | E33: 2851978 | F33: 3007069146 | G33: INCIDENTE | H33: ANTIOQUIA | I33: MEDELLIN | J33: DISTRICOL DIGITAL SAS | K33: REDEBAN | L33: FO-25-1641699 | M33: 45937.573 | N33: 45938.618 | O33: NO | P33: USUARIO | Q33: COMUNICACION | R33: CONEXIONES DE COMERCIO | S33: AGREGADOR | T33: DISTRICOL | U33: EJECUTADO | V33: 07/10/2025 SE ESCALA PARA VISITA. LLAMAR ANTES DE VISITAR, CONFIRMAR FALLA Y DATOS | 08/10/2025 SE REALIZA LA PONCHADA DEL CONECTOR RJ45 SE HACEN PRUEBAS QUEDA OK | W33: VISITA TECNICA | X33: A103Z552 | Y33: TIPO I | Z33: TERRESTRE | AA33: MONTOYA VELEZ ANDRES FELIPE | AB33: 1 | AC33: 0 | AD33: 0 | AE33: 0 | AF33: 0 | AG33: 65960 | AH33: 65960
A34: BOGOTA | B34: CUNDINAMARCA | C34: 0004-0004 | D34: 11001 | E34: 2854023 | F34: 3007055845 | G34: INCIDENTE | H34: CUNDINAMARCA | I34: BOGOTA | J34: PTM BOGOTA DROGUERIA EL GUARDI | K34: REDEBAN | L34: FO-25-1643246 | M34: 45937.702 | N34: 45938.628 | O34: NO | P34: USUARIO | Q34: COMUNICACION | R34: CONEXIONES DE COMERCIO | S34: AGREGADOR | T34: COMCARD - PTM | U34: EJECUTADO | V34: 07/10/2025 SE ESCALA PARA VISITA. LLAMAR ANTES DE VISITAR, CONFIRMAR FALLA Y DATOS | 08/10/2025 SE REVISA CONEXIONES, EQUIPO SE REALIZAN PRUEBAS DEL EQUIPO NO SE ENCUENTRA FALLO AL MOMENTO, INDICA QUE EL FALLO SE PRESENTÓ EL DÍA 07-10-2025 CON BLOQUEO DEL DATÁFONO PERO NO SÉ OBSERVAN ANORMALIDADES EN EL EQUIPO NI EN LAS CONEXIONES | W34: VISITA TECNICA | X34: XPJZZ846 - XPJZZ710 | Y34: TIPO I | Z34: TERRESTRE | AA34: ALARCON AREVALO JOHAN STIVEN | AB34: 1 | AC34: 0 | AD34: 0 | AE34: 0 | AF34: 0 | AG34: 65960 | AH34: 65960
A35: CALI | B35: SUROCCIDENTE Y EJE CAFETERO | C35: 0004-0003 | D35: 76275 | E35: 2855347 | F35: 3007080944 | G35: INCIDENTE | H35: VALLE DEL CAUCA | I35: FLORIDA | J35: BARRIO LA ESPERANZA FLORIDA 1 | K35: REDEBAN | L35: FO-25-1644159 | M35: 45938.343 | N35: 45938.588 | O35: NO | P35: USUARIO | Q35: COMUNICACION | R35: CANAL DEL COMERCIO | S35: UNO A UNO | T35: UNO A UNO | V35: 08/10/2025 SE ESCALA ACTIVIDAD PARA GESTION WOMPI | 08/10/2025 SE LLAMA AL CLIENTE E INDICA QUE ERA PROBLEMA DE ENERGÍA Y QUE EL DATAFONO YA ESTA FUNCIONANDO CORRECTAMENTE | W35: SOPORTE TELEFONICO | Y35: TIPO II | Z35: TERRESTRE | AA35: CUERO RUIZ JHONNY | AB35: 0 | AC35: 0 | AD35: 0 | AE35: 0 | AF35: 0 | AG35: 37905 | AH35: 37905
A36: NEIVA | B36: REMOTAS | C36: 0004-0007 | D36: 41551 | E36: 2855467 | F36: 3007053192 | G36: INCIDENTE | H36: HUILA | I36: PITALITO | J36: BARRIO LOS NOGALES PITALITO 2 | K36: REDEBAN | L36: FO-25-1644778 | M36: 45938.362 | N36: 45939.753 | O36: NO | P36: USUARIO | Q36: MANTENIMIENTO | R36: MANTENIMIENTO GENERAL | S36: CB UNO A UNO | T36: CB UNO A UNO | U36: EJECUTADO | V36: 08/10/2025 SE REALIZAN 3 INTENTOS DE LLAMADA AL NUMERO DE CONTACTO 3227711342 PERO NO FUE POSIBLE LA COMUNICACION | 09/10/2025 SE REALIZA FORMATEO, CONFIGURACIÓN E INICIALIZA DATAFONO, SE CREA USUARIO Y CLAVE CON EL CLIENTE, SE REALIZA PRUEBAS OK | W36: VISITA TECNICA | X36: XP0OZ148 | Y36: TIPO III | Z36: TERRESTRE | AA36: ANDRADE HERNANDEZ JUAN CARLOS | AB36: 1 | AC36: 0 | AD36: 0 | AE36: 0 | AF36: 0 | AG36: 275728 | AH36: 275728
A37: CALI | B37: SUROCCIDENTE Y EJE CAFETERO | C37: 0004-0003 | D37: 76001 | E37: 2857908 | F37: 3007076411 | G37: INCIDENTE | H37: VALLE DEL CAUCA | I37: CALI | J37: PTM CALI PAPELERIA Y VARIEDADE | K37: REDEBAN | L37: FO-25-1647109 | M37: 45938.529 | N37: 45939.438 | O37: NO | P37: USUARIO | Q37: MANTENIMIENTO | R37: MANTENIMIENTO GENERAL | S37: AGREGADOR | T37: COMCARD - PTM | U37: EJECUTADO | V37: 08/10/2025 SE ESCALA PARA VISITA. LLAMAR ANTES DE VISITAR, CONFIRMAR FALLA Y DATOS | 09/10/2025 SE VISITA CORRESPONSAL Y CLIENTE INFORMÓ QUE EL DATÁFONO ESTABA IMPRIMIENDO MAL PERO QUE REALIZÓ LIMPIEZA DE IMPRESORA Y QUEDÓ BIEN. PIDE CERRAR CASO Y NO SE INGRESA A CB. | W37: VISITA TECNICA | X37: A40UZ499 | Y37: TIPO I | Z37: TERRESTRE | AA37: BOLAÑOS TABORDA JORGE ENRIQUE | AB37: 1 | AC37: 0 | AD37: 0 | AE37: 0 | AF37: 0 | AG37: 65960 | AH37: 65960
A38: PASTO | B38: SUROCCIDENTE Y EJE CAFETERO | C38: 0004-0003 | D38: 52001 | E38: 2859764 | F38: 3007029176 | G38: INCIDENTE | H38: NARIÑO | I38: PASTO | J38: BARRIO CENTENARIO 3 PASTO | K38: REDEBAN | L38: FO-25-1648704 | M38: 45938.687 | N38: 45939.525 | O38: NO | P38: USUARIO | Q38: COMUNICACION | R38: CANAL DEL COMERCIO | S38: CB UNO A UNO | T38: CB UNO A UNO | U38: EJECUTADO | V38: 08/10/2025 SE ESCALA PARA VISITA. LLAMAR ANTES DE VISITAR, CONFIRMAR FALLA Y DATOS | 09/10/2025 SE LLEGO A SITIO PARA VERIFICAR FALLA DE COMUNICACIÓN ERROR DE CONEXIÓN PERO EL CLIENTE NO FORMA QUE EL SISTEMA SE REESTABLECIÓ SOLO EL DÍA DE AYER EN HORAS DE LA TARDE, SE REALIZO PRUEBAS DE CONEXIÓN Y TX EXITOSAS QUEDA OPERATIVO | W38: VISITA TECNICA | X38: BBBBI984 | Y38: TIPO I | Z38: TERRESTRE | AA38: REMICIO AMADO JOHN HEBER | AB38: 1 | AC38: 0 | AD38: 0 | AE38: 0 | AF38: 0 | AG38: 65960 | AH38: 65960
A39: TUNJA | B39: SANTANDERES | C39: 0004-0008 | D39: 15759 | E39: 2861978 | F39: 3007080408 | G39: INCIDENTE | H39: BOYACA | I39: SOGAMOSO | J39: BARRIO LA FLORESTA SOGAMOSO 4 | K39: REDEBAN | L39: FO-25-1652261 | M39: 45939.411 | N39: 45940.505 | O39: NO | P39: USUARIO | Q39: USUARIOS | R39: CREACION DE USUARIOS | S39: UNO A UNO | T39: UNO A UNO | U39: EJECUTADO | V39: 09/10/2025 SE ESCALA PARA VISITA. LLAMAR ANTES DE VISITAR, CONFIRMAR FALLA Y DATOS | 10/10/2025 SE VISITA PUNTO SE REALIZAR CREACIÓN DE USUARIOS SOLUCIONANDO LA FALLA REPORTADA SE LE INDICA NUEVAMENTE COMO CREAR MODIFICAR O ELIMINAR UN USUARIO PRUEBAS OK CLIENTE CONFORME | W39: VISITA TECNICA | X39: LBZZZ666 | Y39: TIPO II | Z39: TERRESTRE | AA39: RODRIGUEZ MURCIA YERSON IVAN | AB39: 1 | AC39: 0 | AD39: 0 | AE39: 0 | AF39: 0 | AG39: 163814 | AH39: 163814
A40: APARTADO | B40: NOROCCIDENTE | C40: 0004-0005 | D40: 5045 | E40: 2862896 | F40: 3007034146 | G40: INCIDENTE | H40: ANTIOQUIA | I40: APARTADO | J40: DISTRICOL RECARGAS MOVILES | K40: REDEBAN | L40: FO-25-1654928 | M40: 45939.468 | N40: 45940.371 | O40: NO | P40: USUARIO | Q40: MANTENIMIENTO | R40: MANTENIMIENTO GENERAL | S40: AGREGADOR | T40: DISTRICOL | U40: EJECUTADO | V40: 09/10/2025 SE ESCALA ACTIVIDAD PARA GESTION WOMPI | 09/10/2025 CLIENTE INDICA QUE DATAFONO FUNCIONA BIEN SOLO SE REINICIA CUANDO INTRODUCE TARJETAS VIEJAS. | W40: VISITA TECNICA | X40: 1QZZZ786 | Y40: TIPO I | Z40: TERRESTRE | AA40: CASTRO HENAO DANIEL ESTEBAN | AB40: 1 | AC40: 0 | AD40: 0 | AE40: 0 | AF40: 0 | AG40: 65960 | AH40: 65960
A41: PASTO | B41: SUROCCIDENTE Y EJE CAFETERO | C41: 0004-0003 | D41: 86865 | E41: 2865925 | F41: 3007081358 | G41: INCIDENTE | H41: PUTUMAYO | I41: VALLE DEL GUAMUEZ | J41: DISTRICOL LA ECONOMIA AYS | K41: REDEBAN | L41: FO-25-1663800 | M41: 45939.74 | N41: 45945.362 | O41: NO | P41: USUARIO | Q41: MANTENIMIENTO | R41: MANTENIMIENTO GENERAL | S41: AGREGADOR | T41: DISTRICOL | V41: 09/10/2025 SE ESCALA PARA VISITA. LLAMAR ANTES DE VISITAR, CONFIRMAR FALLA Y DATOS | 12/10/2025 SE DEBE REALIZAR DESPLAZAMIENTO LA PROXIMA SEMANA POR TEMAS DE LA VIA HACIA PUTUMAYO | 15/10/2025 SE REALIZA COMUNICACIÓN TELEFÓNICA CON LA CLIENTE PARA CONFIRMAR VISITA TÉCNICA PERO LA CLIENTE INFORMA QUE EL DETARONO YA SE ENCUENTRA FUNCIONANDO CORRECTAMENTE, PRESENTO FALLA AL HACER CAMBIO DE ROLLO PERO YA SE SOLUCIONÓ. CLIENTE AUTORIZA CERRAR LA ACTIVIDAD. | W41: SOPORTE TELEFONICO | Y41: TIPO IV | Z41: TERRESTRE | AA41: CASTILLO HERRERA ALEX RICARDO | AB41: 0 | AC41: 0 | AD41: 0 | AE41: 0 | AF41: 0 | AG41: 37905 | AH41: 37905
A42: BOGOTA | B42: CUNDINAMARCA | C42: 0004-0004 | D42: 25175 | E42: 2865951 | F42: 3007078315 | G42: INCIDENTE | H42: CUNDINAMARCA | I42: CHIA | J42: BARRIO PARQUE PRINCIPAL DE CHI | K42: REDEBAN | L42: FO-25-1664690 | M42: 45940.333 | N42: 45940.465 | O42: NO | P42: USUARIO | Q42: MANTENIMIENTO | R42: MANTENIMIENTO GENERAL | S42: CB UNO A UNO | T42: CB UNO A UNO | U42: EJECUTADO / CANCELADO | V42: 10/10/2025 SE ESCALA PARA VISITA. LLAMAR ANTES DE VISITAR, CONFIRMAR FALLA Y DATOS | 10/10/2025 SE LLEGA A COMERCIO SE VÁLIDA QUE CLIENTE TUVO MIGRACIÓN A WOMPI SE LE INFORMA QUE TIENE QUE COMUNICARSE CON LA ENTIDAD YA QUE TIENE INCONFORMIDAD POR QUÉ SALE EL NOMBRE DE TITULAR EN EL BAUCHER | W42: VISITA TECNICA | X42: NA | Y42: TIPO II | Z42: TERRESTRE | AA42: INFANTE SIERRA MANUEL FERNANDO | AB42: 1 | AC42: 0 | AD42: 0 | AE42: 0 | AF42: 0 | AG42: 163814 | AH42: 163814
A43: PEREIRA | B43: SUROCCIDENTE Y EJE CAFETERO | C43: 0004-0002 | D43: 63001 | E43: 2866147 | F43: 3007045416 | G43: INCIDENTE | H43: QUINDIO | I43: ARMENIA | J43: PTM ARMENIA PAPELERIA Y VARIE | K43: REDEBAN | L43: FO-25-1664616 | M43: 45940.333 | N43: 45941.638 | O43: NO | P43: USUARIO | Q43: MANTENIMIENTO | R43: MANTENIMIENTO GENERAL | S43: AGREGADOR | T43: COMCARD - PTM | U43: EJECUTADO / CANCELADO | V43: 10/10/2025 SE ESCALA PARA VISITA. LLAMAR ANTES DE VISITAR, CONFIRMAR FALLA Y DATOS | 11/10/2025 SE VISITA COMERCIO SE ENCUENTRA CERRADO SE LLAMA A CONTACTO VARIAS VECES Y MANDA A BUZÓN DE VOZ SE HACE ESPERA DE 20 MINUTOS AFUERA DE COMERCIO PERO NADIE LLEGA. | W43: VISITA TECNICA | X43: ACONZ767 | Y43: TIPO II | Z43: TERRESTRE | AA43: SANCHEZ SOLORZANO JUAN SEBASTIAN | AB43: 1 | AC43: 0 | AD43: 0 | AE43: 0 | AF43: 0 | AG43: 163814 | AH43: 163814
A44: PEREIRA | B44: SUROCCIDENTE Y EJE CAFETERO | C44: 0004-0002 | D44: 66170 | E44: 2867905 | F44: 3007079380 | G44: INCIDENTE | H44: RISARALDA | I44: DOSQUEBRADAS | J44: BARRIO ZONA INDUSTRIALES LA MA | K44: REDEBAN | L44: FO-25-1665912 | M44: 45940.409 | N44: 45940.717 | O44: NO | P44: USUARIO | Q44: CIERRE | R44: COMERCIO NO REALIZA CIERRE | S44: CB UNO A UNO | T44: CB UNO A UNO | U44: EJECUTADO | V44: 10/10/2025 SE ESCALA PARA VISITA. LLAMAR ANTES DE VISITAR, CONFIRMAR FALLA Y DATOS | 10/10/2025 SE VISITA COMERCIO SE IDENTIFICA DATÁFONO CON LENTITUD AL IMPRIMIR CIERRE SE REALIZA BORRADO E INSTALACIÓN DE APLICATIVO SE REALIZA PRUEBAS OK | W44: VISITA TECNICA | X44: 10XZZ918 | Y44: TIPO I | Z44: TERRESTRE | AA44: LOAIZA LOPEZ JHON FREDDY | AB44: 1 | AC44: 0 | AD44: 0 | AE44: 0 | AF44: 0 | AG44: 65960 | AH44: 65960
A45: MANIZALES | B45: SUROCCIDENTE Y EJE CAFETERO | C45: 0004-0002 | D45: 17001 | E45: 2868203 | F45: 3007059083 | G45: INCIDENTE | H45: CALDAS | I45: MANIZALES | J45: DISTRICOL DROGERIA FARMI VIDA | K45: REDEBAN | L45: FO-25-1666651 | M45: 45940.428 | N45: 45941.377 | O45: NO | P45: USUARIO | Q45: USUARIOS | R45: USUARIOS BLOQUEADOS | S45: AGREGADOR | T45: DISTRICOL | V45: 10/10/2025 SE ESCALA PARA VISITA. LLAMAR ANTES DE VISITAR, CONFIRMAR FALLA Y DATOS | 11/10/2025 SE REALIZA VALIDACION CON EL CLIENTE , PERO INDICA QUE YA ANOCHE FUE A REALIZAR EL CIERRE Y YA PUDO REALIZARLO CON NORMALIDAD, LE FUNCIONO LA CLAVE , ENTONCES SE CIERRA CASO. | W45: SOPORTE TELEFONICO | Y45: TIPO I | Z45: TERRESTRE | AA45: HENAO CARDONA DIEGO FERNANDO | AB45: 0 | AC45: 0 | AD45: 0 | AE45: 0 | AF45: 0 | AG45: 37905 | AH45: 37905
A46: VALLEDUPAR | B46: COSTA | C46: 0004-0001 | D46: 44650 | E46: 2868650 | F46: 3007031484 | G46: INCIDENTE | H46: LA GUAJIRA | I46: SAN JUAN DEL CESAR | J46: ARRIO CENTRO 6 | K46: REDEBAN | L46: FO-25-1674359 | M46: 45940.465 | N46: 45941.674 | O46: NO | P46: USUARIO | Q46: MANTENIMIENTO | R46: MANTENIMIENTO GENERAL | S46: CB UNO A UNO | T46: CB UNO A UNO | U46: CANCELADO | V46: 11/10/2025 SE INTENTA COMUNICACION EN VARIAS OCASIONES CON EL SEÑOR CRISTIAN PEÑA AL NUMERO 3180749290 PARA CONFIRMAR FALLA Y RED PERO NO HA SIDO POSIBLE, SE PROCEDE A CERRAR ESTE CASO YA QUE USUARIO NO FUE CONTACTADO | 11/10/2025 SE INTENTA COMUNICACION EN VARIAS OCASIONES CON EL SEÑOR CRISTIAN PEÑA AL NUMERO 3180749290 PARA CONFIRMAR FALLA Y RED PERO NO HA SIDO POSIBLE, SE PROCEDE A CERRAR ESTE CASO YA QUE USUARIO NO FUE CONTACTADO | 11/10/2025 SE INTENTA COMUNICACION EN VARIAS OCASIONES CON EL SEÑOR CRISTIAN PEÑA AL NUMERO 3180749290 PARA CONFIRMAR FALLA Y RED PERO NO HA SIDO POSIBLE, SE PROCEDE A CERRAR ESTE CASO YA QUE USUARIO NO FUE CONTACTADO | W46: SOPORTE TELEFONICO | Y46: TIPO II | Z46: TERRESTRE | AA46: DIAZ ACOSTA MARIA ISABEL | AB46: 0 | AC46: 0 | AD46: 0 | AE46: 0 | AF46: 0 | AG46: 37905 | AH46: 37905
A47: MEDELLIN | B47: NOROCCIDENTE | C47: 0004-0005 | D47: 5088 | E47: 2871335 | F47: 3007035559 | G47: INCIDENTE | H47: ANTIOQUIA | I47: BELLO | J47: COMCARD BELLO REJA BLANCA | K47: REDEBAN | L47: FO-25-1668594 | M47: 45940.7 | N47: 45941.682 | O47: NO | P47: USUARIO | Q47: USUARIOS | R47: MALA MANIPULACION POS | S47: AGREGADOR | T47: COMCARD - PTM | U47: EJECUTADO | V47: 11/10/2025 SE REALIZA VISITA TÉCNICA EN RESPUESTA AL INCIDENTE REPORTADO CON EL DATÁFONO DEL CORRESPONSAL BANCOLOMBIA. EL USUARIO CONFIRMA SU IDENTIDAD Y PROCEDE A INFORMAR QUE EL EQUIPO PRESENTÓ UNA FALLA VISUAL: UNA SOMBRA OSCURA EN LA PANTALLA QUE IMPEDÍA SU CORRECTA OPERACIÓN. DURANTE LA REVISIÓN, SE REALIZA MANTENIMIENTO PREVENTIVO Y SE VERIFICA EL ESTADO DE LOS CABLES Y CONEXIONES, SIN ENCONTRAR ANOMALÍAS FÍSICAS. SE CONCLUYE QUE EL EQUIPO ESTÁ EN CONDICIONES ÓPTIMAS. FINALMENTE, SE INSTRUYE AL USUARIO SOBRE EL PROCEDIMIENTO ADECUADO PARA REINICIAR EL DATÁFONO EN CASO DE QUE LA FALLA VUELVA A PRESENTARSE, ASEGURANDO ASÍ UNA CORRECTA GESTIÓN ANTE FUTURAS INCIDENCIAS. | W47: VISITA TECNICA | X47: AA004690 - II00T240 | Y47: TIPO I | Z47: TERRESTRE | AA47: MARTINEZ TOVAR OSCAR DAVID | AB47: 1 | AC47: 0 | AD47: 0 | AE47: 0 | AF47: 0 | AG47: 65960 | AH47: 65960
A48: YOPAL | B48: REMOTAS | C48: 0004-0007 | D48: 85001 | E48: 2872794 | F48: 3007081518 | G48: INCIDENTE | H48: CASANARE | I48: YOPAL | J48: DISTRICOL DROGUERIA FENIX | K48: REDEBAN | L48: FO-25-1674815 | M48: 45942.333 | N48: 45943.399 | O48: NO | P48: USUARIO | Q48: NO ENCIENDE | R48: CONEXIONES DE COMERCIO | S48: AGREGADOR | T48: DISTRICOL | V48: 12/10/2025 SE ESCALA PARA VISITA. LLAMAR ANTES DE VISITAR, CONFIRMAR FALLA Y DATOS | 13/10/2025 EN COMUNICACIÓN CON LA SEÑORA LAURA URBINA AL NUMERO 3133841617. INDICA QUE SE ENCUENTRA OPERATIVO EL SERVICIO. | W48: SOPORTE TELEFONICO | Y48: TIPO I | Z48: TERRESTRE | AA48: BERNAL ELAICA EDGAR ALEXIS | AB48: 0 | AC48: 0 | AD48: 0 | AE48: 0 | AF48: 0 | AG48: 37905 | AH48: 37905
A49: NEIVA | B49: REMOTAS | C49: 0004-0007 | D49: 41791 | E49: 2874161 | F49: 3007056851 | G49: INCIDENTE | H49: HUILA | I49: TARQUI | J49: BARRIO QUITURO TARQUI | K49: REDEBAN | L49: FO-25-1677091 | M49: 45943.468 | N49: 45945.732 | O49: NO | P49: USUARIO | Q49: MANTENIMIENTO | R49: MANTENIMIENTO GENERAL | S49: CB UNO A UNO | T49: CB UNO A UNO | U49: EJECUTADO | V49: 13/10/2025 SE ESCALA PARA VISITA. LLAMAR ANTES DE VISITAR, CONFIRMAR FALLA Y DATOS | 15/10/2025 SE REALIZA CAMBIO CABLE UTP (INTERNET) TENÍA LOS PINES DAÑADOS , SE REALIZA EL CAMBIO , SE REALIZA PRUEBAS OK | W49: VISITA TECNICA | X49: IIOZZ199 | Y49: TIPO III | Z49: TERRESTRE | AA49: ANDRADE HERNANDEZ JUAN CARLOS | AB49: 1 | AC49: 0 | AD49: 0 | AE49: 0 | AF49: 0 | AG49: 275728 | AH49: 275728
A50: NEIVA | B50: REMOTAS | C50: 0004-0007 | D50: 41026 | E50: 2874180 | F50: 3007036483 | G50: INCIDENTE | H50: HUILA | I50: ALTAMIRA | J50: BARRIO CENTRO ALTAMIRA | K50: REDEBAN | L50: FO-25-1677076 | M50: 45943.489 | N50: 45944.658 | O50: NO | P50: USUARIO | Q50: MANTENIMIENTO | R50: MANTENIMIENTO GENERAL | S50: CB UNO A UNO | T50: CB UNO A UNO | U50: EJECUTADO | V50: 13/10/2025 SE ESCALA PARA VISITA. LLAMAR ANTES DE VISITAR, CONFIRMAR FALLA Y DATOS | 14/10/2025 SE REALIZA CAMBIO CABLE MAGIC BOX,SE PIDE REALIZAR CIERRES , SE FORMATEA , CONFIGURA E INICIALIZA DATAFONO, SE CREA USUARIO Y CLAVE CON EL CLIENTE, SE REALIZA PRUEBAS OK | W50: VISITA TECNICA | X50: AA00D472 | Y50: TIPO III | Z50: TERRESTRE | AA50: ANDRADE HERNANDEZ JUAN CARLOS | AB50: 1 | AC50: 0 | AD50: 0 | AE50: 0 | AF50: 0 | AG50: 275728 | AH50: 275728
A51: PEREIRA | B51: SUROCCIDENTE Y EJE CAFETERO | C51: 0004-0002 | D51: 66001 | E51: 2874926 | F51: 3007023457 | G51: INCIDENTE | H51: RISARALDA | I51: PEREIRA | J51: BR PLAZOLETA TRIBUNAS PERE | K51: REDEBAN | L51: FO-25-1678577 | M51: 45944.333 | N51: 45944.485 | O51: NO | P51: USUARIO | Q51: COMUNICACION | R51: CANAL DEL COMERCIO | S51: CB UNO A UNO | T51: CB UNO A UNO | U51: EJECUTADO | V51: 14/10/2025 SE ESCALA PARA VISITA. LLAMAR ANTES DE VISITAR, CONFIRMAR FALLA Y DATOS | 14/10/2025 VISITAMOS COMERCIO CLIENTE INDICA QUE EL DATAFO APARECE ERROR EN CONEXIÓN, REVISAMOS EL DATAFONO Y EL CABLEADO PERO TODO ESTÁ BIEN ENCONTRAMOS QUE LOS PUERTOS DEL MÓDEM ESTAN MALOS LE INDICAMOS AL CLIENTE QUE SE DEBE COMUNICAR CON EL PROVEEDOR DE SERVICIO PARA QUE LE SOLUCIONEN LA FALLA CON EL MÓDEM, NO SE HACEN PRUEBAS EXITOSAS YA QUE EL MODEM NO ESTÁ FUNCIONAN. | W51: VISITA TECNICA | X51: ABC05358 | Y51: TIPO I | Z51: TERRESTRE | AA51: ARROYAVE CANO MANUEL GUILLERMO | AB51: 1 | AC51: 0 | AD51: 0 | AE51: 0 | AF51: 0 | AG51: 65960 | AH51: 65960
A52: NEIVA | B52: REMOTAS | C52: 0004-0007 | D52: 41551 | E52: 2876291 | F52: 3007062753 | G52: INCIDENTE | H52: HUILA | I52: PITALITO | J52: BARRIO CONJUNTO SANTA CLARA PI | K52: REDEBAN | L52: FO-25-1679667 | M52: 45944.401 | N52: 45946.394 | O52: NO | P52: USUARIO | Q52: COMUNICACION | R52: CANAL DEL COMERCIO | S52: CB UNO A UNO | T52: CB UNO A UNO | U52: EJECUTADO / CANCELADO | V52: 14/10/2025 SE ESCALA PARA VISITA. LLAMAR ANTES DE VISITAR, CONFIRMAR FALLA Y DATOS | 16/10/2025 SE VISITA PUNTO , CLIENTE INDICA DATAFONO OPERANDO NORMAL , ERA PROBLEMAS DEL PROVEEDOR DE COMUNICACIONES . | W52: VISITA TECNICA | X52: KA00R028 | Y52: TIPO III | Z52: TERRESTRE | AA52: ANDRADE HERNANDEZ JUAN CARLOS | AB52: 1 | AC52: 0 | AD52: 0 | AE52: 0 | AF52: 0 | AG52: 275728 | AH52: 275728
A53: MONTERIA | B53: COSTA | C53: 0004-0001 | D53: 23001 | E53: 2876478 | F53: 3007021725 | G53: INCIDENTE | H53: CORDOBA | I53: MONTERIA | J53: AKT MONTERIA 1 | K53: REDEBAN | L53: FO-25-1679621 | M53: 45944.409 | N53: 45944.666 | O53: NO | P53: USUARIO | Q53: COMUNICACION | R53: CONEXIONES DE COMERCIO | S53: AGREGADOR | T53: CONTIGO | U53: EJECUTADO | V53: 14/10/2025 SE ESCALA PARA VISITA. LLAMAR ANTES DE VISITAR, CONFIRMAR FALLA Y DATOS | 14/10/2025 SE LLEGA AL SITIO Y SE REALIZA REVISIÓN AL SISTEMA DE COMUNICACIÓN DE DATÁFONO, SE ENCUENTRA QUE PUNTO DE ETHERNET DE LA TOMA DEL COMERCIO SE ENCUENTRA DAÑADO YA QUE SE PRUEBA COMUNICACIÓN EN OTRO PUERTO Y EL DATAFONOS REACCIONÓ Y FUNCIONÓ CORRECTAMENTE, SE REALIZAN PRUEBAS OK. SE RECOMIENDA AL CLIENTE REALIZAR MANTENIMIENTO AL TOMA DEL PUERTO DE ETHERNET, YA QUE EL DATAFONO SE ENCUENTRA EN PERFECTO ESTADO. | W53: VISITA TECNICA | X53: AAVZZ244 | Y53: TIPO I | Z53: TERRESTRE | AA53: CASSIANI PEREZ RAUL RAMIRO | AB53: 1 | AC53: 0 | AD53: 0 | AE53: 0 | AF53: 0 | AG53: 65960 | AH53: 65960
A54: YOPAL | B54: REMOTAS | C54: 0004-0007 | D54: 85010 | E54: 2878706 | F54: 3007039888 | G54: INCIDENTE | H54: CASANARE | I54: AGUAZUL | J54: DISTRICOL DROGUERIA COLFAN | K54: REDEBAN | L54: FO-25-1681349 | M54: 45944.538 | N54: 45945.669 | O54: NO | P54: USUARIO | Q54: MANTENIMIENTO | R54: MANTENIMIENTO GENERAL | S54: AGREGADOR | T54: DISTRICOL | V54: 14/10/2025 SE ESCALA PARA VISITA. LLAMAR ANTES DE VISITAR, CONFIRMAR FALLA Y DATOS | 15/10/2025 EN COMUNICACIÓN CON LA SEÑORA ANGELA RIAÑO AL NUMERO 3132719453 INDICA NO REQUIERE LA VISITA. YA AJUSTO LA TAPA DE IMPRESION. INDICA SE ENCUENTRA OPERATIVO EL | W54: SOPORTE TELEFONICO | Y54: TIPO II | Z54: TERRESTRE | AA54: BERNAL ELAICA EDGAR ALEXIS | AB54: 0 | AC54: 0 | AD54: 0 | AE54: 0 | AF54: 0 | AG54: 37905 | AH54: 37905
A55: MANIZALES | B55: SUROCCIDENTE Y EJE CAFETERO | C55: 0004-0002 | D55: 17001 | E55: 2879163 | F55: 3007059083 | G55: INCIDENTE | H55: CALDAS | I55: MANIZALES | J55: DISTRICOL DROGERIA FARMI VIDA | K55: REDEBAN | L55: FO-25-1681768 | M55: 45944.592 | N55: 45944.675 | O55: NO | P55: USUARIO | Q55: COMUNICACION | R55: CONEXIONES DE COMERCIO | S55: AGREGADOR | T55: DISTRICOL | V55: 14/10/2025 SE ESCALA PARA VISITA. LLAMAR ANTES DE VISITAR, CONFIRMAR FALLA Y DATOS | 14/10/2025 SE REALIZA LLAMADA CON USUARIO PARA VALIDAR FALLAS INDICA QUE SE LE PRESENTO EN UN MOMENTO PERO YA SE ENCUENTRA EN BUEN ESTADO Y TRABAJANDO CON NORMALIDAD | W55: SOPORTE TELEFONICO | Y55: TIPO I | Z55: TERRESTRE | AA55: AGUIRRE HENAO RAUL EDUARDO | AB55: 0 | AC55: 0 | AD55: 0 | AE55: 0 | AF55: 0 | AG55: 37905 | AH55: 37905
A56: BUCARAMANGA | B56: SANTANDERES | C56: 0004-0008 | D56: 68425 | E56: 2882996 | F56: 3007027180 | G56: INCIDENTE | H56: SANTANDER | I56: MACARAVITA | J56: BARRIO CENTRO MACARAVITA | K56: REDEBAN | L56: FO-25-1684794 | M56: 45945.387 | N56: 45945.519 | O56: NO | P56: USUARIO | Q56: COMUNICACION | R56: CANAL DEL COMERCIO | S56: CB UNO A UNO | T56: CB UNO A UNO | V56: 15/10/2025 SE ESCALA PARA VISITA. LLAMAR ANTES DE VISITAR, CONFIRMAR FALLA Y DATOS | 15/10/2025 SE REALIZA LLAMADA TELEFÓNICA PARA ATENDER VISITA POR ERROR EN LA CONEXIÓN, SE HABLA CON SEÑOR ÓSCAR ESTUPIÑÁN QUIEN INDICA QUE SIEMPRE HA TENIDO OPERATIVO UNA ANTENA SATELITAL Y EL INTERNET ES PROPORCIONADO POR BANCOLOMBIA POR LO TANTO SE VERIFICA QUE EL DATÁFONO ESTÁ OPERANDO EN OTRO MÓDEM. POR LO ANTERIOR SEÑOR ÓSCAR SOLICITO REVISIÓN DEL INTERNET PROPIEDAD DE BANCOLOMBIA YA QUE INDICA NO TENER MÁS OPERADORES PARA MANEJAR EL CORRESPONSAL YA QUE PARA PROBAR LE PRESTARON UN MÓDEM Y ASÍ CONFIRMA QUE EL DATÁFONO ESTÁ OPERANDO CORRECTAMENTE | W56: SOPORTE TELEFONICO | Y56: TIPO IV | Z56: TERRESTRE | AA56: PEÑA DIAZ IVAN YESID | AB56: 0 | AC56: 0 | AD56: 0 | AE56: 0 | AF56: 0 | AG56: 37905 | AH56: 37905
A57: MEDELLIN | B57: NOROCCIDENTE | C57: 0004-0005 | D57: 5001 | E57: 2883163 | F57: 3007034992 | G57: INCIDENTE | H57: ANTIOQUIA | I57: MEDELLIN | J57: COMCARD PAPELERIA Y MISCELANEA | K57: REDEBAN | L57: FO-25-1684796 | M57: 45945.386 | N57: 45945.515 | O57: NO | P57: USUARIO | Q57: NO ENCIENDE | R57: CONEXIONES DE COMERCIO | S57: AGREGADOR | T57: COMCARD - PTM | U57: EJECUTADO | V57: 15/10/2025 SE ESCALA PARA VISITA. LLAMAR ANTES DE VISITAR, CONFIRMAR FALLA Y DATOS | 15/10/2025 SE REALIZÓ RECONEXIÓN AL DATÁFONO SE REALIZÓ PRUEBA POS OK | W57: VISITA TECNICA | X57: BL02Z746 | Y57: TIPO I | Z57: TERRESTRE | AA57: CASTAÑEDA PALACIO CARLOS FELIPE | AB57: 1 | AC57: 0 | AD57: 0 | AE57: 0 | AF57: 0 | AG57: 65960 | AH57: 65960
A58: PASTO | B58: SUROCCIDENTE Y EJE CAFETERO | C58: 0004-0003 | D58: 52323 | E58: 2885371 | F58: 3007010155 | G58: INCIDENTE | H58: NARIÑO | I58: GUALMATAN | J58: GUA MA A A INO | K58: REDEBAN | L58: FO-25-1686478 | M58: 45945.516 | N58: 45946.585 | O58: NO | P58: USUARIO | Q58: COMUNICACION | R58: CANAL DEL COMERCIO | S58: CB UNO A UNO | T58: CB UNO A UNO | U58: EJECUTADO | V58: 15/10/2025 SE ESCALA PARA VISITA. LLAMAR ANTES DE VISITAR, CONFIRMAR FALLA Y DATOS | 16/10/2025 SE ENCUENTRA DATAFONO SIN CONEXIÓN SE LE INFORMA AL CLIENTE QUE ES FALLA DEL CANAL DE INTERNET, SE REALIZA MANTENIMIENTO Y SE OBTIENE CONEXIÓN EXITOSA, CONFIGURACIÓN OK PARÁMETROS OK Y SE REALIZAN PRUEBAS ÉXITOSAS DE TRANSACCIONES | W58: VISITA TECNICA | X58: IZ7ZZ871 | Y58: TIPO II | Z58: TERRESTRE | AA58: PAZ MARTINEZ RICHARD HUMBERTO | AB58: 1 | AC58: 0 | AD58: 0 | AE58: 0 | AF58: 0 | AG58: 163814 | AH58: 163814
A59: VILLAVICENCIO | B59: REMOTAS | C59: 0004-0007 | D59: 50689 | E59: 2885380 | F59: 3007052948 | G59: INCIDENTE | H59: META | I59: SAN MARTIN | J59: PTM SAN MARTIN DROGERIA V&E | K59: REDEBAN | L59: FO-25-1686475 | M59: 45945.517 | N59: 45946.569 | O59: NO | P59: USUARIO | Q59: COMUNICACION | R59: CONEXIONES DE COMERCIO | S59: AGREGADOR | T59: COMCARD - PTM | U59: EJECUTADO | V59: 15/10/2025 SE ESCALA PARA VISITA. LLAMAR ANTES DE VISITAR, CONFIRMAR FALLA Y DATOS | 16/10/2025 SE REALIZA VISITA AL CB POR SOLICITUD DE RED, SE VERIFICA LOS CABLES DE ETHERNET SE SUELTA Y SE VUELVE A CONECTAR BIEN Y FUNCIONANDO SIN NINGÚN PROBLEMA QUEDA TODO OK SIN NOVEDAD SE REALIZAN PRUEBAS OK | W59: VISITA TECNICA | X59: AB11O704 | Y59: TIPO II | Z59: TERRESTRE | AA59: MOLINA CASTRO JAVIER ALBERTO | AB59: 1 | AC59: 0 | AD59: 0 | AE59: 0 | AF59: 0 | AG59: 163814 | AH59: 163814
A60: MONTERIA | B60: COSTA | C60: 0004-0001 | D60: 23670 | E60: 2885593 | F60: 3007035167 | G60: INCIDENTE | H60: CORDOBA | I60: SAN ANDRES SOTAVENTO | J60: COMCARD SOTAVENTO TUCHIN | K60: REDEBAN | L60: FO-25-1686891 | M60: 45945.549 | N60: 45946.723 | O60: NO | P60: USUARIO | Q60: COMUNICACION | R60: CANAL DEL COMERCIO | S60: AGREGADOR | T60: COMCARD - PTM | U60: EJECUTADO | V60: 16/10/2025 SE ESCALA PARA VISITA. LLAMAR ANTES DE VISITAR, CONFIRMAR FALLA Y DATOS | 16/10/2025 SE VISITA COMERCIO, SE VERIFICA EL EQUIPO PERO ESTÁ FUNCIONANDO CORRECTAMENTE, TENIA UN PROBLEMA DE CONEXIÓN CON EL CANAL DEL COMERCIO PERO YA SE SOLUCIONÓ YA SE ENCUENTRA FUNCIONANDO CORRECTAMENTE, SE REALIZAN PRUEBAS OK. | W60: VISITA TECNICA | X60: BL0DZ129 | Y60: TIPO II | Z60: TERRESTRE | AA60: CACERES HERNANDEZ ANDRES | AB60: 1 | AC60: 0 | AD60: 0 | AE60: 0 | AF60: 0 | AG60: 163814 | AH60: 163814
A61: CALI | B61: SUROCCIDENTE Y EJE CAFETERO | C61: 0004-0003 | D61: 76001 | E61: 2886628 | F61: 3007035510 | G61: INCIDENTE | H61: VALLE DEL CAUCA | I61: CALI | J61: REDY LA PRIMERA | K61: REDEBAN | L61: FO-25-1688290 | M61: 45945.626 | N61: 45946.599 | O61: NO | P61: USUARIO | Q61: COMUNICACION | R61: CANAL DEL COMERCIO | S61: ROBUSTO | T61: REDY | U61: EJECUTADO | V61: 15/10/2025 SE ESCALA PARA VISITA. LLAMAR ANTES DE VISITAR, CONFIRMAR FALLA Y DATOS | 16/10/2025 SE CONFIGURA EQUIPO POR DHCP PORQUE ESTABA PRESENTAMDO CONFLICTO CON LAS IP DE LAS CAMARAS, CB BANCOLOMBIA PURO, PRUEBAS OK | W61: VISITA TECNICA | X61: GZ001385 | Y61: TIPO I | Z61: TERRESTRE | AA61: PAREDES CASTILLO DIEGO | AB61: 1 | AC61: 0 | AD61: 0 | AE61: 0 | AF61: 0 | AG61: 65960 | AH61: 65960
A62: MEDELLIN | B62: NOROCCIDENTE | C62: 0004-0005 | D62: 5001 | E62: 2888908 | F62: 3007033080 | G62: INCIDENTE | H62: ANTIOQUIA | I62: MEDELLIN | J62: BARRIO PEDREGAL MEDELLIN | K62: REDEBAN | L62: FO-25-1690464 | M62: 45946.333 | N62: 45946.41 | O62: NO | P62: USUARIO | Q62: MANTENIMIENTO | R62: MANTENIMIENTO GENERAL | S62: CB UNO A UNO | T62: CB UNO A UNO | V62: 16/10/2025 SE ESCALA PARA VISITA. LLAMAR ANTES DE VISITAR, CONFIRMAR FALLA Y DATOS | 16/10/2025 SE LLAMA AL CLIENTE Y SE LE INDICA COMO REINICIAR EL DATÁFONO, SE REINICIA DATÁFONO Y QUEDA FUNCIONAL | W62: SOPORTE TELEFONICO | Y62: TIPO I | Z62: TERRESTRE | AA62: CARDONA MOLINA BROLIN STIVEN | AB62: 0 | AC62: 0 | AD62: 0 | AE62: 0 | AF62: 0 | AG62: 37905 | AH62: 37905
A63: BUCARAMANGA | B63: SANTANDERES | C63: 0004-0008 | D63: 68001 | E63: 2890461 | F63: 3007044230 | G63: INCIDENTE | H63: SANTANDER | I63: BUCARAMANGA | J63: PAGAFACIL ABASTOS BUCARAMANGA | K63: REDEBAN | L63: FO-25-1692016 | M63: 45946.445 | N63: 45947.42 | O63: NO | P63: ENTIDAD | Q63: ERROR DE TRANSACCIONES | R63: SIN CUPO HABILITADO | S63: ROBUSTO | T63: PAGAFACIL | V63: 17/10/2025 SE ESCALA PARA VISITA. LLAMAR ANTES DE VISITAR, CONFIRMAR FALLA Y DATOS | 17/10/2025 ORDEN SE ESCALA CON PAOLA DE REDEBAN QUIEN INFORMA QUE SE ESCALA CASO DIRECTO CON PAGAFACIL Y AUTORIZA CERRAR ORDEN DE TRABAJO | W63: SOPORTE TELEFONICO | Y63: TIPO I | Z63: TERRESTRE | AA63: BARRERA ORTEGA MARLON STWAR | AB63: 0 | AC63: 0 | AD63: 0 | AE63: 0 | AF63: 0 | AG63: 37905 | AH63: 37905
A64: IBAGUE | B64: REMOTAS | C64: 0004-0007 | D64: 73411 | E64: 2890573 | F64: 3007079896 | G64: INCIDENTE | H64: TOLIMA | I64: LIBANO | J64: DISTRICOL MAXIFARMA | K64: REDEBAN | L64: FO-25-1692003 | M64: 45946.455 | N64: 45947.695 | O64: NO | P64: USUARIO | Q64: USUARIOS | R64: MALA MANIPULACION POS | S64: AGREGADOR | T64: DISTRICOL | U64: EJECUTADO | V64: 16/10/2025 SE ESCALA PARA VISITA. LLAMAR ANTES DE VISITAR, CONFIRMAR FALLA Y DATOS | 17/10/2025 SE LLEGA AL CORRESPONSAL Y SE HABLA CON LA SEÑORA ALBA POVEDA, ME INDICA SOBRE EL PROBLEMA DE LA IMPRESORA, HAGO PRUEBAS Y EL DATÁFONO IMPRIME BIEN Y HACE LAS TRANSACCIONES CORRECTAMENTE. SE LE EXPLICA NUEVAMENTE EL APAGADO Y ENCENDIDO CORRECTAMENTE DEL DATÁFONO. SE HACEN LAS PRUEBAS DE TRANSACCIONES TODO OK | W64: VISITA TECNICA | X64: SAUZZ974 | Y64: TIPO III | Z64: TERRESTRE | AA64: VARGAS HERRERA JHON JAIRO | AB64: 1 | AC64: 0 | AD64: 0 | AE64: 0 | AF64: 0 | AG64: 275728 | AH64: 275728
A65: BUCARAMANGA | B65: SANTANDERES | C65: 0004-0008 | D65: 81736 | E65: 2890962 | F65: 3007071366 | G65: INCIDENTE | H65: ARAUCA | I65: SARAVENA | J65: DISTRICOL MULTISERVICIOS ANDRE | K65: REDEBAN | L65: FO-25-1692799 | M65: 45946.481 | N65: 45946.651 | O65: NO | P65: USUARIO | Q65: COMUNICACION | R65: CONEXIONES DE COMERCIO | S65: AGREGADOR | T65: DISTRICOL | U65: EJECUTADO | V65: 16/10/2025 SE ESCALA PARA VISITA. LLAMAR ANTES DE VISITAR, CONFIRMAR FALLA Y DATOS | 16/10/2025 SE SOLICITA A COORDINADOR DE ZONA CREACIÓN DE ORDEN DE INCIDENTE SOLICITADO POR EL ADMINISTRADOR CON RADICADO RADICADO 14257529. PARA ATENCIÓN DE VISITA. | 16/10/2025 SE REALIZA AJUSTE DE CONEXIÓNES, SE CONECTA DIRECTAMENTE AL MÓDEM Y SE REALIZAN PRUEBAS EXITOSA, SE HACE ACOMPAÑAMIENTO VARIAS TRANSACCIONES EXITOSA. | W65: VISITA TECNICA | X65: SV00C189 | Y65: TIPO V | Z65: AEREO | AA65: MARTINEZ FLOREZ DONIS ALBERTO | AB65: 1 | AC65: 0 | AD65: 0 | AE65: 0 | AF65: 0 | AG65: 988463 | AH65: 988463
A66: MEDELLIN | B66: NOROCCIDENTE | C66: 0004-0005 | D66: 5088 | E66: 2894012 | F66: 3007040226 | G66: INCIDENTE | H66: ANTIOQUIA | I66: BELLO | J66: PTM BELLO LA CHINCA | K66: REDEBAN | L66: FO-25-1695498 | M66: 45947.333 | N66: 45947.563 | O66: NO | P66: USUARIO | Q66: COMUNICACION | R66: CANAL DEL COMERCIO | S66: AGREGADOR | T66: COMCARD - PTM | U66: EJECUTADO | V66: 17/10/2025 SE ESCALA PARA VISITA. LLAMAR ANTES DE VISITAR, CONFIRMAR FALLA Y DATOS | 17/10/2025 SE LLEGA A PUNTO Y CLIENTE INDICA QUE TIENE PROBLEMAS CON EL INTERNET Y YA ESTA EL PROVEEDOR DE SERVICIO VERIFICANDO | W66: VISITA TECNICA | X66: AA0JZ957 | Y66: TIPO I | Z66: TERRESTRE | AA66: BADEL ACUÑA LUIS ALBERTO | AB66: 1 | AC66: 0 | AD66: 0 | AE66: 0 | AF66: 0 | AG66: 65960 | AH66: 65960
A67: MEDELLIN | B67: NOROCCIDENTE | C67: 0004-0005 | D67: 5001 | E67: 2894773 | F67: 3007075978 | G67: INCIDENTE | H67: ANTIOQUIA | I67: MEDELLIN | J67: PTM MEDELLIN DROGUERIA PLENITU | K67: REDEBAN | L67: FO-25-1696517 | M67: 45947.354 | N67: 45947.467 | O67: NO | P67: USUARIO | Q67: CIERRE | R67: COMERCIO NO REALIZA CIERRE | S67: AGREGADOR | T67: COMCARD - PTM | U67: EJECUTADO | V67: 17/10/2025 SE VALIDA NUEVAMENTE CLAVE DE SUPERVISOR Y SE DEJAN LAS INDICACIONES. | W67: VISITA TECNICA | X67: FA09Z507 - UVRZZ574 | Y67: TIPO I | Z67: TERRESTRE | AA67: MARIN PIEDRAHITA JIMMY ALEXIS | AB67: 1 | AC67: 0 | AD67: 0 | AE67: 0 | AF67: 0 | AG67: 65960 | AH67: 65960
A68: CALI | B68: SUROCCIDENTE Y EJE CAFETERO | C68: 0004-0003 | D68: 76001 | E68: 2895978 | F68: 3007028195 | G68: INCIDENTE | H68: VALLE DEL CAUCA | I68: CALI | J68: PAGAFACIL PLAZA CAICEDO II | K68: REDEBAN | L68: FO-25-1697390 | M68: 45947.432 | N68: 45947.677 | O68: NO | P68: USUARIO | Q68: COMUNICACION | R68: CONEXIONES DE COMERCIO | S68: ROBUSTO | T68: PAGAFACIL | U68: EJECUTADO | V68: 17/08/2025 SE ESCALA PARA VISITA. LLAMAR ANTES DE VISITAR, CONFIRMAR FALLA Y DATOS | 17/10/2025 CLIENTE TIENE IP DUPLICADA SE CONFIGURA Y PERSISTE LA FALLA SE LLAMA AL TECNICO DEL INTERNET DEL CLIENTE Y QUEDA FUNCIONANDO CORRECTAMENTE | W68: VISITA TECNICA | X68: 9LZZZ753 | Y68: TIPO I | Z68: TERRESTRE | AA68: CUERO RUIZ JHONNY | AB68: 1 | AC68: 0 | AD68: 0 | AE68: 0 | AF68: 0 | AG68: 65960 | AH68: 65960
A69: MEDELLIN | B69: NOROCCIDENTE | C69: 0004-0005 | D69: 5129 | E69: 2897272 | F69: 3007024577 | G69: INCIDENTE | H69: ANTIOQUIA | I69: CALDAS | J69: COMCARD CALDAS SIMOLIS | K69: REDEBAN | L69: FO-25-1698792 | M69: 45947.568 | N69: 45948.422 | O69: NO | P69: USUARIO | Q69: COMUNICACION | R69: CANAL DEL COMERCIO | S69: AGREGADOR | T69: COMCARD - PTM | U69: EJECUTADO | V69: 17/10/2025 SE ESCALA PARA VISITA. LLAMAR ANTES DE VISITAR, CONFIRMAR FALLA Y DATOS | 18/10/2025 SE LLEGA AL CB SE HABIA CONFIRMADO LA VISITA , PERO CB CERRADO SE LLAMA AL USUARIO NUEVAMENTE E INDICA QUE AYER MOVISTAR LE DIO SOLUCIÓN YA QUE ERA PROBLEMA EN EL MODEM DEL OPERADOR DE SERVICIO DE INTERNET E INDICA QUE TODO QUEDO OK CORRESPONSAL OK | W69: VISITA TECNICA | X69: ABC0Z263 | Y69: TIPO I | Z69: TERRESTRE | AA69: MONTOYA VELEZ ANDRES FELIPE | AB69: 1 | AC69: 0 | AD69: 0 | AE69: 0 | AF69: 0 | AG69: 65960 | AH69: 65960
A70: MEDELLIN | B70: NOROCCIDENTE | C70: 0004-0005 | D70: 5615 | E70: 2898043 | F70: 3007035666 | G70: INCIDENTE | H70: ANTIOQUIA | I70: RIONEGRO | J70: COMCARD KIME COMERCIALIZADORA | K70: REDEBAN | L70: FO-25-1701583 | M70: 45947.632 | N70: 45954.635 | O70: NO | P70: USUARIO | Q70: COMUNICACION | R70: CANAL DEL COMERCIO | S70: AGREGADOR | T70: COMCARD - PTM | U70: EJECUTADO | V70: 18/10/2025 SE ESCALA PARA VISITA. LLAMAR ANTES DE VISITAR, CONFIRMAR FALLA Y DATOS | 19/10/2025 VISITA SE REALIZARÁ EN DÍA HÁBIL DEBIDO A QUE NOVEDAD DE CONEXIÓN EN SITIO SE DA POR PROBLEMA DE EQUIPO. FIN DE SEMANA NO SE TIENE SOPORTE PARA CAMBIOS. VISITA E REALZARÁ EN DÍA HÁBIL DE LA PRÓXIMA SEMANA. | 24/10/2025 SE LLEGA A PUNTO Y SE VERIFICA FLUCTUACION DE CANAL, EQUIPOS YA FUNCIONAN | W70: VISITA TECNICA | X70: 9A005433 | Y70: TIPO II | Z70: TERRESTRE | AA70: BADEL ACUÑA LUIS ALBERTO | AB70: 1 | AC70: 0 | AD70: 0 | AE70: 0 | AF70: 0 | AG70: 163814 | AH70: 163814
A71: MEDELLIN | B71: NOROCCIDENTE | C71: 0004-0005 | D71: 5059 | E71: 2898626 | F71: 3007081524 | G71: INCIDENTE | H71: ANTIOQUIA | I71: ARMENIA | J71: PTM ARMENIA DACAFE HOGAR Y FER | K71: REDEBAN | L71: FO-25-1699999 | M71: 45947.677 | N71: 45948.397 | O71: NO | P71: USUARIO | Q71: MANTENIMIENTO | R71: MANTENIMIENTO GENERAL | S71: AGREGADOR | T71: COMCARD - PTM | U71: EJECUTADO | V71: 18/10/2025 SE REALIZÓ RECONEXIÓN DE DATÁFONO PRUEBA EXITOSA | W71: VISITA TECNICA | X71: SPZZZ3301 - FTZZZ821 | Y71: TIPO II | Z71: TERRESTRE | AA71: CASTAÑEDA PALACIO CARLOS FELIPE | AB71: 1 | AC71: 0 | AD71: 0 | AE71: 0 | AF71: 0 | AG71: 163814 | AH71: 163814
A72: VILLAVICENCIO | B72: REMOTAS | C72: 0004-0007 | D72: 50001 | E72: 2899343 | F72: 3007047991 | G72: INCIDENTE | H72: META | I72: VILLAVICENCIO | J72: DISTRICOL MASIVOS MINI EXPRESS | K72: REDEBAN | L72: FO-25-1701000 | M72: 45948.333 | N72: 45949.353 | O72: NO | P72: USUARIO | Q72: USUARIOS | R72: USUARIOS BLOQUEADOS | S72: AGREGADOR | T72: DISTRICOL | V72: 18/10/2025 SE REALIZA CONTACTO TELEFONICO CON EL SEÑOR JORGE Y SE LE RELAIZA SOPORTE Y SE LE REALIZA CAMBIO DE CONTRASEÑA DE SUPERVISOR | W72: SOPORTE TELEFONICO | Y72: TIPO I | Z72: TERRESTRE | AA72: PEDREROS CONTRERAS MICHAEL STEVENS | AB72: 0 | AC72: 0 | AD72: 0 | AE72: 0 | AF72: 0 | AG72: 37905 | AH72: 37905
A73: MEDELLIN | B73: NOROCCIDENTE | C73: 0004-0005 | D73: 5001 | E73: 2900795 | F73: 3007022852 | G73: INCIDENTE | H73: ANTIOQUIA | I73: MEDELLIN | J73: COMCARD MEDELLIN ROBLEDO DIMAS | K73: REDEBAN | L73: FO-25-1704285 | M73: 45949.47 | N73: 45950.464 | O73: NO | P73: USUARIO | Q73: MANTENIMIENTO | R73: MANTENIMIENTO GENERAL | S73: AGREGADOR | T73: COMCARD - PTM | U73: EJECUTADO / CANCELADO | V73: 19/10/2025 SE ESCALA PARA VISITA. LLAMAR ANTES DE VISITAR, CONFIRMAR FALLA Y DATOS | 20/10/2025 VISITA FALLIDA, SE VISITA PUNTO USUARIA NO PERMITE INGRESO YA QUE EN LA LINEA DE BANCOLOMBIA NO CONTESTAN NI POR LLAMADA NI POR WHATSAPP, USUARIA INDICA QUE LLAMARA DE NUEVO A SOLICITAR RADICADO SE CIERRA CASO | W73: VISITA TECNICA | X73: NONE | Y73: TIPO I | Z73: TERRESTRE | AA73: CARDONA MOLINA BROLIN STIVEN | AB73: 1 | AC73: 0 | AD73: 0 | AE73: 0 | AF73: 0 | AG73: 65960 | AH73: 65960
A74: VILLAVICENCIO | B74: REMOTAS | C74: 0004-0007 | D74: 50689 | E74: 2900911 | F74: 3007080461 | G74: INCIDENTE | H74: META | I74: SAN MARTIN | J74: BARRIO FUNDADORES SAN MARTIN 9 | K74: REDEBAN | L74: FO-25-1704144 | M74: 45949.439 | N74: 45950.633 | O74: NO | P74: USUARIO | Q74: COMUNICACION | R74: CONEXIONES DE COMERCIO | S74: UNO A UNO | T74: UNO A UNO | U74: EJECUTADO | V74: 19/10/2025 SE ESCALA PARA VISITA. LLAMAR ANTES DE VISITAR, CONFIRMAR FALLA Y DATOS | 20/10/2025 SE REALIZA CAMBIO DE PUERTO LAN EN EL ROUTER SE REALIZA PRUEBAS OK | W74: VISITA TECNICA | X74: SAZZZ771 | Y74: TIPO II | Z74: TERRESTRE | AA74: ROZO JIMENEZ EDGAR ARMANDO | AB74: 1 | AC74: 0 | AD74: 0 | AE74: 0 | AF74: 0 | AG74: 163814 | AH74: 163814
A75: BOGOTA | B75: CUNDINAMARCA | C75: 0004-0004 | D75: 25473 | E75: 2902251 | F75: 3007052225 | G75: INCIDENTE | H75: CUNDINAMARCA | I75: MOSQUERA | J75: BARRIO PORVENIR RIO MOSQUERA | K75: REDEBAN | L75: FO-25-1705348 | M75: 45950.355 | N75: 45950.79 | O75: NO | P75: ENTIDAD | Q75: ERROR DE TRANSACCIONES | R75: TRANSACCION NO PERMITIDA | S75: CB UNO A UNO | T75: CB UNO A UNO | U75: EJECUTADO | V75: 20/10/2025 SE ESCALA PARA VISITA. LLAMAR ANTES DE VISITAR, CONFIRMAR FALLA Y DATOS | 20/10/2025 SE VISITA COMERCIO CB BANCOLOMBIA, PERO ESTE YA ESTÁ MIGRADO A WOMPI, EL CLIENTE INDICA QUE LA FALLA LA PRESENTO EN LA MAÑANA Y ERA POR QUÉ LE DECLINABA LAS TRANSACCIONES Y ESTO ES POR QUÉ HAY UNA FALLA A NIVEL GENERAL EN LOS CORRESPONSALES, YA EL SERVICIO ESTÁ RESTABLECIDO Y NO PRESENTA NINGÚN PROBLEMA, SE TOMA EVIDENCIA DE LA VISITA Y NOS RETIRAMOS, NO SE MANIPULAN EQUIPOS. | W75: VISITA TECNICA | X75: NONE | Y75: TIPO I | Z75: TERRESTRE | AA75: VEGA MANRIQUE JONATAN MAURICIO | AB75: 1 | AC75: 0 | AD75: 0 | AE75: 0 | AF75: 0 | AG75: 65960 | AH75: 65960
A76: PEREIRA | B76: SUROCCIDENTE Y EJE CAFETERO | C76: 0004-0002 | D76: 66001 | E76: 2909827 | F76: 3007057069 | G76: INCIDENTE | H76: RISARALDA | I76: PEREIRA | J76: PTM PEREIRA DROGUERIA MEDICA N | K76: REDEBAN | L76: FO-25-1709231 | M76: 45951.333 | N76: 45951.743 | O76: NO | P76: USUARIO | Q76: USUARIOS | R76: USUARIOS BLOQUEADOS | S76: AGREGADOR | T76: COMCARD - PTM | V76: 21/10/2025 SE ESCALA PARA VISITA. LLAMAR ANTES DE VISITAR, CONFIRMAR FALLA Y DATOS | 21/10/2025 SE REALIZA LLAMADA AL CLIENTE PARA VALIDAR INCONVENIENTE PERO INDICA QUE PARECE QUE ERA UN BLOQUEO POR QUE YA ESTA MAÑANA INTENTO REALIZAR EL CIERRE Y LO PUDO REALIZAR SIN PROBLEMA, | W76: SOPORTE TELEFONICO | Y76: TIPO I | Z76: TERRESTRE | AA76: HENAO CARDONA DIEGO FERNANDO | AB76: 0 | AC76: 0 | AD76: 0 | AE76: 0 | AF76: 0 | AG76: 37905 | AH76: 37905
A77: MANIZALES | B77: SUROCCIDENTE Y EJE CAFETERO | C77: 0004-0002 | D77: 17001 | E77: 2910457 | F77: 3007020866 | G77: INCIDENTE | H77: CALDAS | I77: MANIZALES | J77: BARRIO GALERIA V MANIZALES | K77: REDEBAN | L77: FO-25-1709221 | M77: 45951.333 | N77: 45951.517 | O77: NO | P77: USUARIO | Q77: COMUNICACION | R77: CONEXIONES DE COMERCIO | S77: CB UNO A UNO | T77: CB UNO A UNO | U77: EJECUTADO | V77: 21/10/2025 SE ESCALA PARA VISITA. LLAMAR ANTES DE VISITAR, CONFIRMAR FALLA Y DATOS | 21/10/2025 SE REALIZA VISITA SE VALIDA CABLEADO SE EVIDENCIA QUE CONTABA CON EXTENSOR DE RJ45 EN MAL ESTADO, SE CONECTORIZA RJ45 Y DA CONEXIÓN SE HACEN PRUEBAS SERVICIO OK | W77: VISITA TECNICA | X77: AAAGZ523 | Y77: TIPO I | Z77: TERRESTRE | AA77: AGUIRRE HENAO RAUL EDUARDO | AB77: 1 | AC77: 0 | AD77: 0 | AE77: 0 | AF77: 0 | AG77: 65960 | AH77: 65960
A78: TUNJA | B78: SANTANDERES | C78: 0004-0008 | D78: 15455 | E78: 2915001 | F78: 3007040145 | G78: INCIDENTE | H78: BOYACA | I78: MIRAFLORES | J78: BARRIO CENTRO MIRAFLORES 1 | K78: REDEBAN | L78: FO-25-1713575 | M78: 45951.622 | N78: 45951.656 | O78: NO | P78: USUARIO | Q78: COMUNICACION | R78: CANAL DEL COMERCIO | S78: CB UNO A UNO | T78: CB UNO A UNO | V78: 21/10/2025 EN COMUNICACIÓN CON LA SR NANCY RAMIREZ AL NUMERO 3128564722 INDICA QUE LA FALLA ES CON EL PROVEEDOR DE INTERNET Y QUE NO REQUIERE VISITA TECNICA. SE PROCEDE A CERRAR RADICADO | W78: SOPORTE TELEFONICO | Y78: TIPO IV | Z78: TERRESTRE | AA78: HERNANDEZ GUARIN MIGUEL JULIAN | AB78: 0 | AC78: 0 | AD78: 0 | AE78: 0 | AF78: 0 | AG78: 37905 | AH78: 37905
A79: MEDELLIN | B79: NOROCCIDENTE | C79: 0004-0005 | D79: 5001 | E79: 2919221 | F79: 3007074073 | G79: INCIDENTE | H79: ANTIOQUIA | I79: MEDELLIN | J79: PTM MEDELLIN AUTOSERVICIO NARI | K79: REDEBAN | L79: FO-25-1717796 | M79: 45952.451 | N79: 45952.572 | O79: NO | P79: USUARIO | Q79: COMUNICACION | R79: CANAL DEL COMERCIO | S79: AGREGADOR | T79: COMCARD - PTM | U79: EJECUTADO | V79: 22/10/2025 SE ESCALA PARA VISITA. LLAMAR ANTES DE VISITAR, CONFIRMAR FALLA Y DATOS | 22/10/2025 SE LLEGA A PUNTO SE VERIFICA CONEXIÓN DEL COMERCIO, SE ORGANIZA QUEDA OPERATIVO | W79: VISITA TECNICA | X79: UV0PZ153 - NN00E890 | Y79: TIPO I | Z79: TERRESTRE | AA79: BADEL ACUÑA LUIS ALBERTO | AB79: 1 | AC79: 0 | AD79: 0 | AE79: 0 | AF79: 0 | AG79: 65960 | AH79: 65960
A80: BUCARAMANGA | B80: SANTANDERES | C80: 0004-0008 | D80: 68276 | E80: 2920304 | F80: 3007052197 | G80: INCIDENTE | H80: SANTANDER | I80: FLORIDABLANCA | J80: DISTRICOL DIAMAR SPORT CONF | K80: REDEBAN | L80: FO-25-1718539 | M80: 45952.548 | N80: 45953.536 | O80: NO | P80: USUARIO | Q80: NO ENCIENDE | R80: CONEXIONES DE COMERCIO | S80: AGREGADOR | T80: DISTRICOL | U80: EJECUTADO | V80: 22/10/2025 SE ESCALA PARA VISITA. LLAMAR ANTES DE VISITAR, CONFIRMAR FALLA Y DATOS | 23/10/2025 EN VISITA A COMERCIAL POR QUÉ NO RESPONDE LLAMADA , AL MOMENTO DE LLEGAR EL SEÑOR INFORMO QUE EL EQUIPO YA ESTÁ OPERANDO CORRECTAMENTE SE HABÍA DESCONECTADO POR LO TANTO NO NECESITA QUE EL TÉCNICO INGRESE Y CANCELA LA VISITA | W80: VISITA TECNICA | X80: GB0DZ023 | Y80: TIPO I | Z80: TERRESTRE | AA80: PEÑA DIAZ IVAN YESID | AB80: 1 | AC80: 0 | AD80: 0 | AE80: 0 | AF80: 0 | AG80: 65960 | AH80: 65960
A81: VILLAVICENCIO | B81: REMOTAS | C81: 0004-0007 | D81: 50577 | E81: 2920804 | F81: 3007081173 | G81: INCIDENTE | H81: META | I81: PUERTO LLERAS | J81: BARRIO CENTRO PUERTO 7 LLERAS | K81: REDEBAN | L81: FO-25-1719919 | M81: 45952.61 | N81: 45953.511 | O81: NO | P81: USUARIO | Q81: COMUNICACION | R81: CONEXIONES DE COMERCIO | S81: UNO A UNO | T81: UNO A UNO | V81: 22/10/2025 SE INTENTA COMUNICACION CON EL USUARIO AL NUMERO 3227618406 , SE ESCALA PARA VISITA. LLAMAR ANTES DE VISITAR, CONFIRMAR FALLA Y DATOS | 23/10/2025 CLIENTE REGRESA LA LLAMADA E INFORMA QUÉ EL DÍA DE HOY ESTÁ FUNCIONANDO SIN NOVEDAD Y NO REQUIERE SERVICIO TÉCNICO Y QUE HASTA EL MOMENTO ESTA FUNCIONANDO SIN NOVEDAD | W81: SOPORTE TELEFONICO | Y81: TIPO III | Z81: TERRESTRE | AA81: ROZO JIMENEZ EDGAR ARMANDO | AB81: 0 | AC81: 0 | AD81: 0 | AE81: 0 | AF81: 0 | AG81: 37905 | AH81: 37905
A82: BUCARAMANGA | B82: SANTANDERES | C82: 0004-0008 | D82: 68001 | E82: 2921504 | F82: 3007071679 | G82: INCIDENTE | H82: SANTANDER | I82: BUCARAMANGA | J82: PTM BUCARAMANGA PAPELERIA ABA | K82: REDEBAN | L82: FO-25-1719940 | M82: 45952.657 | N82: 45953.551 | O82: NO | P82: USUARIO | Q82: COMUNICACION | R82: CONEXIONES DE COMERCIO | S82: AGREGADOR | T82: COMCARD - PTM | U82: EJECUTADO | V82: 22/10/2025 SE ESCALA PARA VISITA. LLAMAR ANTES DE VISITAR, CONFIRMAR FALLA Y DATOS | 23/10/2025 SE REALIZA VISITA AL COMERCIO CB, SE VALIDA Y SE ENCUENTRA QUE EL PROBLEMA RADICO EN LA CONEXIÓN INTERNA, NO ESTABA TOMANDO INTERNET O ERROR EN CONEXIÓN SE ARREGLA Y SE DEJA FUNCIONADO OK, PRUEBAS OK | W82: VISITA TECNICA | X82: MN00G322 - MN00G394 | Y82: TIPO I | Z82: TERRESTRE | AA82: GONZALEZ ESTUPIÑAN YEISON WALTER ANTONIO | AB82: 1 | AC82: 0 | AD82: 0 | AE82: 0 | AF82: 0 | AG82: 65960 | AH82: 65960
A83: MEDELLIN | B83: NOROCCIDENTE | C83: 0004-0005 | D83: 5376 | E83: 2922606 | F83: 3007038372 | G83: INCIDENTE | H83: ANTIOQUIA | I83: LA CEJA | J83: DISTRICOL SUPERMERCADO COLOMBI | K83: REDEBAN | L83: FO-25-1720880 | M83: 45953.333 | N83: 45954.615 | O83: NO | P83: USUARIO | Q83: MANTENIMIENTO | R83: MANTENIMIENTO GENERAL | S83: AGREGADOR | T83: DISTRICOL | V83: 23/10/2025 SE ESCALA PARA VISITA. LLAMAR ANTES DE VISITAR, CONFIRMAR FALLA Y DATOS | 24/10/2025 USUARIO NOS INDICA QUE NO HABÍAN PUESTO EL ROLLO, REINICIÓ EL DATÁFONO Y PUSO UN ROLLO NUEVO, QUEDA OPERATIVO | W83: SOPORTE TELEFONICO | Y83: TIPO II | Z83: TERRESTRE | AA83: CARDONA MOLINA BROLIN STIVEN | AB83: 0 | AC83: 0 | AD83: 0 | AE83: 0 | AF83: 0 | AG83: 37905 | AH83: 37905
A84: APARTADO | B84: NOROCCIDENTE | C84: 0004-0005 | D84: 5045 | E84: 2923249 | F84: 3007035610 | G84: INCIDENTE | H84: ANTIOQUIA | I84: APARTADO | J84: DISTRICOL COMUNICACIONES KATEB | K84: REDEBAN | L84: FO-25-1721724 | M84: 45953.333 | N84: 45953.499 | O84: NO | P84: USUARIO | Q84: COMUNICACION | R84: CANAL DEL COMERCIO | S84: AGREGADOR | T84: DISTRICOL | U84: EJECUTADO | V84: 23/10/2025 SE ESCALA PARA VISITA. LLAMAR ANTES DE VISITAR, CONFIRMAR FALLA Y DATOS | 23/10/2025 SE LE INDICA AL CLIENTE QUE EL PIN PAD 1500 NO ES COMPATIBLE CON EL DATAFONO 2600 POR LO TANTO SE LE RECOMIENDA SOLICITAR UN PIN PAD ADICIONAL LA LINEA BANCOLOMBIA. | W84: VISITA TECNICA | X84: AA004403 | Y84: TIPO I | Z84: TERRESTRE | AA84: CASTRO HENAO DANIEL ESTEBAN | AB84: 1 | AC84: 0 | AD84: 0 | AE84: 0 | AF84: 0 | AG84: 65960 | AH84: 65960
A85: CALI | B85: SUROCCIDENTE Y EJE CAFETERO | C85: 0004-0003 | D85: 76001 | E85: 2925033 | F85: 3007052580 | G85: INCIDENTE | H85: VALLE DEL CAUCA | I85: CALI | J85: BARRIO EL JARDIN CALI 1 | K85: REDEBAN | L85: FO-25-1723048 | M85: 45953.445 | N85: 45953.767 | O85: NO | P85: USUARIO | Q85: CIERRE | R85: COMERCIO NO REALIZA CIERRE | S85: CB UNO A UNO | T85: CB UNO A UNO | U85: EJECUTADO | V85: 23/10/2025 SE ESCALA PARA VISITA. LLAMAR ANTES DE VISITAR, CONFIRMAR FALLA Y DATOS | 23/10/2025 CLIENTE HABRE A LAS 2 PM | 23/10/2025 CLIENTE NO CUENTA CON CLAVE DE SUPERVISOR SE LE CREA UNA NUEVA Y QUEDA FUNCIONANDO CORRECTAMENTE | W85: VISITA TECNICA | X85: 1A00N237 | Y85: TIPO I | Z85: TERRESTRE | AA85: CUERO RUIZ JHONNY | AB85: 1 | AC85: 0 | AD85: 0 | AE85: 0 | AF85: 0 | AG85: 65960 | AH85: 65960
A86: VILLAVICENCIO | B86: REMOTAS | C86: 0004-0007 | D86: 50450 | E86: 2926323 | F86: 3007078907 | G86: INCIDENTE | H86: META | I86: PUERTO CONCORDIA | J86: BARRIO VRD SAN FERNANDO PUERTO CONCORDIA | K86: REDEBAN | L86: FO-25-1727698 | M86: 45953.556 | N86: 45954.576 | O86: NO | P86: USUARIO | Q86: COMUNICACION | R86: CONEXIONES DE COMERCIO | S86: UNO A UNO | T86: UNO A UNO | V86: 23/10/2025 EN COMUNICACION CON EL SR CLAUDIA GAVIRIA AL NUMERO 3124735857 SE CONFIRMAR FALLA Y DATOS . SE ESCALA PARA VISITA. | 24/10/2025 SE REALIZA LLAMADA TELEFÓNICA ALA USUARIA, NOS INFORMA QUE EL PROBLEMA SE SOLUCIONÓ QUE EL DATÁFONO ESTÁ FUNCIONANDO NORMALMENTE, QUE HABÍA SIDO POR FALLAS DEL INTERNET QUE ESTABA ALGO INTERMITENTE PERO QUE YA SE HABÍA ARREGLADO | W86: SOPORTE TELEFONICO | Y86: TIPO IV | Z86: TERRESTRE | AA86: MOLINA CASTRO JAVIER ALBERTO | AB86: 0 | AC86: 0 | AD86: 0 | AE86: 0 | AF86: 0 | AG86: 37905 | AH86: 37905
A87: BOGOTA | B87: CUNDINAMARCA | C87: 0004-0004 | D87: 25843 | E87: 2928425 | F87: 3007049326 | G87: INCIDENTE | H87: CUNDINAMARCA | I87: VILLA DE SAN DIEGO DE UBATE | J87: BARRIO UBATE VILLA DE SAN DIEG | K87: REDEBAN | L87: FO-25-1726698 | M87: 45953.713 | N87: 45954.597 | O87: NO | P87: ENTIDAD | Q87: ERROR DE TRANSACCIONES | R87: TRANSACCION NO PERMITIDA | S87: UNO A UNO | T87: CB UNO A UNO | U87: EJECUTADO | V87: 23/10/2025 SE ESCALA PARA VISITA. LLAMAR ANTES DE VISITAR, CONFIRMAR FALLA Y DATOS | 24/10/2025 DURANTE LA VISITA TECNICA PARA ATENDER INCIDENTE REPORTADO POR CORRESPONSAL BANCARIO, CORRESPONSAL NOS INDICA QUE EL DAÑO YA FUE SOLUCIONADO, SE HACEN PRUEBAS CONFIRMANDO QUE SERVICIO SE ENCUENTRA FUNCIONAL Y OPERATIVO A CONFORMIDAD DEL CB SIN NOVEDAD EN EL INCIDENTE SALDO OK | W87: VISITA TECNICA | X87: 9C00Q176 | Y87: TIPO II | Z87: TERRESTRE | AA87: GALEANO SORIANO JUAN DAVID | AB87: 1 | AC87: 0 | AD87: 0 | AE87: 0 | AF87: 0 | AG87: 163814 | AH87: 163814
A88: PASTO | B88: SUROCCIDENTE Y EJE CAFETERO | C88: 0004-0003 | D88: 52490 | E88: 2928658 | F88: 3007069331 | G88: INCIDENTE | H88: NARIÑO | I88: OLAYA HERRERA | J88: BARRIO LA ISLA OLAYA HERRERA | K88: REDEBAN | L88: FO-25-1726970 | M88: 45954.333 | N88: 45957.686 | O88: NO | P88: USUARIO | Q88: NO ENCIENDE | R88: CONEXIONES DE COMERCIO | S88: CB UNO A UNO | T88: CB UNO A UNO | V88: 23/10/2025 SE ESCALA PARA VISITA. LLAMAR ANTES DE VISITAR, CONFIRMAR FALLA Y DATOS | 27/10/2025 SE REALIZA LLAMADA TELEFÓNICA PARA CONFIRMAR VISITA, SE CONTACTA CON EL SEÑOR DUVAN SÁNCHEZ EL CUAL INFORMA QUE SE LE ESTABA REINICIANDO Y APAGANDO EL DÍA QUE HIZO EL REPORTE PERO QUE REVISO CONEXIÓNES Y QUE YA EL DATAFONO SE ENCUENTRA FUNCIONANDO CORRECTAMENTE POR LO CUAL YA NO DESEA VISITA | W88: SOPORTE TELEFONICO | Y88: TIPO V | Z88: FLUVIAL | AA88: PAZ MARTINEZ RICHARD HUMBERTO | AB88: 0 | AC88: 0 | AD88: 0 | AE88: 0 | AF88: 0 | AG88: 37905 | AH88: 37905
A89: BOGOTA | B89: CUNDINAMARCA | C89: 0004-0004 | D89: 25875 | E89: 2928819 | F89: 3007073822 | G89: INCIDENTE | H89: CUNDINAMARCA | I89: VILLETA | J89: BARRIO CENTRO VILLETA 9 | K89: REDEBAN | L89: FO-25-1727374 | M89: 45954.333 | N89: 45954.567 | O89: NO | P89: USUARIO | Q89: MANTENIMIENTO | R89: MANTENIMIENTO GENERAL | S89: CB UNO A UNO | T89: CB UNO A UNO | U89: EJECUTADO / CANCELADO | V89: 23/10/2025 SE ESCALA PARA VISITA. LLAMAR ANTES DE VISITAR, CONFIRMAR FALLA Y DATOS | 24/10/2025 CB YA SE ENCUENTRA MIGRADO A LA OTRA RED, SE CANCELA SOLICITUD Y SE LE INDICA AL USUARIO QUE DEBE COMUNICARSE DE NUEVO CON LA LINEA PARA GENERAR UN CORRECTO RADICADO. | W89: VISITA TECNICA | X89: 0 | Y89: TIPO II | Z89: TERRESTRE | AA89: ARIAS QUILINDO JULIAN | AB89: 1 | AC89: 0 | AD89: 0 | AE89: 0 | AF89: 0 | AG89: 163814 | AH89: 163814
A90: BOGOTA | B90: CUNDINAMARCA | C90: 0004-0004 | D90: 25843 | E90: 2931614 | F90: 3007019537 | G90: INCIDENTE | H90: CUNDINAMARCA | I90: VILLA DE SAN DIEGO DE UBATE | J90: REVAL UBATE | K90: REDEBAN | L90: FO-25-1730192 | M90: 45954.526 | N90: 45954.723 | O90: NO | P90: USUARIO | Q90: COMUNICACION | R90: CANAL DEL COMERCIO | S90: ROBUSTO | T90: REVAL | U90: EJECUTADO | V90: 24/10/2025 SE ESCALA PARA VISITA. LLAMAR ANTES DE VISITAR, CONFIRMAR FALLA Y DATOS | 24/10/2025 DURANTE LA VISITA TECNICA PARA ATENDER INCIDENTE REPORTADO POR CORRESPONSAL BANCARIO, CORRESPONSAL NOS INDICA QUE EL DAÑO YA FUE SOLUCIONADO, SE HACEN PRUEBAS CONFIRMANDO QUE SERVICIO SE ENCUENTRA FUNCIONAL Y OPERATIVO A CONFORMIDAD DEL CB SIN NOVEDAD EN EL INCIDENTE SALDO OK NOTA NO SE INGRESA AL CORRESPONSAL REVAL | W90: VISITA TECNICA | X90: MNZZZ464-AD00B080 | Y90: TIPO II | Z90: TERRESTRE | AA90: GALEANO SORIANO JUAN DAVID | AB90: 1 | AC90: 0 | AD90: 0 | AE90: 0 | AF90: 0 | AG90: 163814 | AH90: 163814
A91: MEDELLIN | B91: NOROCCIDENTE | C91: 0004-0005 | D91: 5390 | E91: 2931701 | F91: 3007010288 | G91: INCIDENTE | H91: ANTIOQUIA | I91: LA PINTADA | J91: LA PINTADA-ANTIOQUIA | K91: REDEBAN | L91: FO-25-1730186 | M91: 45954.53 | N91: 45955.431 | O91: NO | P91: USUARIO | Q91: MANTENIMIENTO | R91: MANTENIMIENTO GENERAL | S91: CB UNO A UNO | T91: CB UNO A UNO | U91: EJECUTADO | V91: 24/10/2025 SE ESCALA PARA VISITA. LLAMAR ANTES DE VISITAR, CONFIRMAR FALLA Y DATOS | 25/10/2025 SE REALIZÓ MANTENIMIENTO GENERAL Y AJUSTE Y LIMPIEZA DE IMPRESORA | W91: VISITA TECNICA | X91: IZ7ZZ886 - 9B08Z097 | Y91: TIPO II | Z91: TERRESTRE | AA91: CASTAÑEDA PALACIO CARLOS FELIPE | AB91: 1 | AC91: 0 | AD91: 0 | AE91: 0 | AF91: 0 | AG91: 163814 | AH91: 163814
A92: MEDELLIN | B92: NOROCCIDENTE | C92: 0004-0005 | D92: 5001 | E92: 2931954 | F92: 3007080857 | G92: INCIDENTE | H92: ANTIOQUIA | I92: MEDELLIN | J92: PTM MEDELLIN VARIEDADES LA CHI | K92: REDEBAN | L92: FO-25-1730562 | M92: 45954.591 | N92: 45955.488 | O92: NO | P92: USUARIO | Q92: COMUNICACION | R92: CANAL DEL COMERCIO | S92: AGREGADOR | T92: COMCARD - PTM | V92: 24/10/2025 SE ESCALA PARA VISITA. LLAMAR ANTES DE VISITAR, CONFIRMAR FALLA Y DATOS | 25/10/2025 SE HACE SOPORTE TELEFÓNICO Y CLIENTE NOS MANIFIESTA QUE YA ESTA OPERANDO CON NORMALIDAD | W92: SOPORTE TELEFONICO | Y92: TIPO I | Z92: TERRESTRE | AA92: DIAZ ZABALA FRANCIS DUBAN | AB92: 0 | AC92: 0 | AD92: 0 | AE92: 0 | AF92: 0 | AG92: 37905 | AH92: 37905
A93: MEDELLIN | B93: NOROCCIDENTE | C93: 0004-0005 | D93: 5607 | E93: 2935004 | F93: 3007014258 | G93: INCIDENTE | H93: ANTIOQUIA | I93: RETIRO | J93: MULTIPAGAS EL RETIRO | K93: REDEBAN | L93: FO-25-1734206 | M93: 45955.542 | N93: 45957.528 | O93: NO | P93: USUARIO | Q93: COMUNICACION | R93: CONEXIONES DE COMERCIO | S93: ROBUSTO | T93: MULTIPAGAS | U93: EJECUTADO | V93: 25/10/2025 SE ESCALA PARA VISITA. LLAMAR ANTES DE VISITAR, CONFIRMAR FALLA Y DATOS | 27/10/2025 COMERCIO NO ABRE DÍAS DOMINGOS, VISITA SE REALIZARÁ EN DÍA HABIL DE LA PROXIMA SEMANA. | 27/10/2025 SE LLEGA AL PUNTO Y CLIENTE NOS COMENTA QUE ERA ALGO EXTERNO Y SE PUDO SOLUCIONAR (CABLE PINPAD DESCONECTADO) PAGAFACIL | W93: VISITA TECNICA | X93: JADZZ364 | Y93: TIPO II | Z93: TERRESTRE | AA93: CARDONA MOLINA BROLIN STIVEN | AB93: 1 | AC93: 0 | AD93: 0 | AE93: 0 | AF93: 0 | AG93: 163814 | AH93: 163814
A94: MONTERIA | B94: COSTA | C94: 0004-0001 | D94: 23001 | E94: 2937239 | F94: 3007014750 | G94: INCIDENTE | H94: CORDOBA | I94: MONTERIA | J94: BARRIO SANTA FE DE MONTERIA MO | K94: REDEBAN | L94: FO-25-1737574 | M94: 45957.374 | N94: 45957.699 | O94: NO | P94: USUARIO | Q94: COMUNICACION | R94: CANAL DEL COMERCIO | S94: CB UNO A UNO | T94: CB UNO A UNO | U94: EJECUTADO | V94: 27/10/2025 SE ESCALA PARA VISITA. LLAMAR ANTES DE VISITAR, CONFIRMAR FALLA Y DATOS | 27/10/2025 SE VISITA SITIO, SE VERIFICA DATAFONO, FUNCIONA CORRECTAMENTE, CB INDICA POSIBLE PROBLEMAS CON CANAL DE COMUNICACIÓN 9A0F EN HORAS DE LA MAÑANA . PRUEBAS EXITOSAS | W94: VISITA TECNICA | X94: 9A0FZ496 | Y94: TIPO I | Z94: TERRESTRE | AA94: COGOLLO VERTEL EDER LUIS | AB94: 1 | AC94: 0 | AD94: 0 | AE94: 0 | AF94: 0 | AG94: 65960 | AH94: 65960
A95: MEDELLIN | B95: NOROCCIDENTE | C95: 0004-0005 | D95: 5656 | E95: 2939239 | F95: 3007034032 | G95: INCIDENTE | H95: ANTIOQUIA | I95: SAN JERONIMO | J95: DISTRICOL AUTOSERVICIO SUPER D | K95: REDEBAN | L95: FO-25-1738903 | M95: 45957.461 | N95: 45958.677 | O95: NO | P95: USUARIO | Q95: CIERRE | R95: COMERCIO NO REALIZA CIERRE | S95: AGREGADOR | T95: DISTRICOL | V95: 27/10/2025 SE ESCALA PARA VISITA. LLAMAR ANTES DE VISITAR, CONFIRMAR FALLA Y DATOS | 28/10/2025 SE HABLA CON SEÑOR MIGUEL, SE REALIZA PROCESO PARA VERIFICAR CIERRES Y DUPLICADOS Y FUNCIONAN SIN NOVEDAD, SE CIERRA INCIDENTE, CB OPERATIVO. | W95: SOPORTE TELEFONICO | Y95: TIPO II | Z95: TERRESTRE | AA95: CASTAÑEDA PALACIO CARLOS FELIPE | AB95: 0 | AC95: 0 | AD95: 0 | AE95: 0 | AF95: 0 | AG95: 37905 | AH95: 37905
A96: MEDELLIN | B96: NOROCCIDENTE | C96: 0004-0005 | D96: 5001 | E96: 2940343 | F96: 3007056953 | G96: INCIDENTE | H96: ANTIOQUIA | I96: MEDELLIN | J96: PTM MEDELLIN MERCADOS FH AL CO | K96: REDEBAN | L96: FO-25-1739894 | M96: 45957.551 | N96: 45958.494 | O96: NO | P96: USUARIO | Q96: MANTENIMIENTO | R96: MANTENIMIENTO GENERAL | S96: AGREGADOR | T96: COMCARD - PTM | U96: EJECUTADO | V96: 27/10/2025 SE ESCALA PARA VISITA. LLAMAR ANTES DE VISITAR, CONFIRMAR FALLA Y DATOS | 28/10/2025 SE LLAMA AL CLIENTE Y DICE QUE ABRE A LAS 9AM, SE LLEGA AL PUNTO Y SE ESPERA 15M, SE REALIZA MANTENIMIENTO Y CAMBIO DE CABLE DE RED POR DAÑO | W96: VISITA TECNICA | X96: TRQZZ971 - AB11N977 | Y96: TIPO I | Z96: TERRESTRE | AA96: CARDONA MOLINA BROLIN STIVEN | AB96: 1 | AC96: 0 | AD96: 0 | AE96: 0 | AF96: 0 | AG96: 65960 | AH96: 65960
A97: MEDELLIN | B97: NOROCCIDENTE | C97: 0004-0005 | D97: 5001 | E97: 2940619 | F97: 3007045297 | G97: INCIDENTE | H97: ANTIOQUIA | I97: MEDELLIN | J97: PTM MEDELLIN VARIEDADES LA 56 | K97: REDEBAN | L97: FO-25-1740159 | M97: 45957.575 | N97: 45958.479 | O97: NO | P97: USUARIO | Q97: MANTENIMIENTO | R97: MANTENIMIENTO GENERAL | S97: AGREGADOR | T97: COMCARD - PTM | U97: EJECUTADO | V97: 27/10/2025 SE ESCALA PARA VISITA. LLAMAR ANTES DE VISITAR, CONFIRMAR FALLA Y DATOS | 28/10/2025 SE REALIZA MANTENIMIENTO Y CAMBIO DE FUENTE DE PODER YA QUE EL DATÁFONO IMPRIMÍA LENTO, LUEGO DEL CAMBIO QUEDA OPERATIVO | W97: VISITA TECNICA | X97: 9B0NZ740 - TRKZZZ963 | Y97: TIPO I | Z97: TERRESTRE | AA97: CARDONA MOLINA BROLIN STIVEN | AB97: 1 | AC97: 0 | AD97: 0 | AE97: 0 | AF97: 0 | AG97: 65960 | AH97: 65960
A98: TUNJA | B98: SANTANDERES | C98: 0004-0008 | D98: 15001 | E98: 2941411 | F98: 3007069305 | G98: INCIDENTE | H98: BOYACA | I98: TUNJA | J98: BARRIO LAS AMERICAS TUNJA | K98: REDEBAN | L98: FO-25-1740878 | M98: 45957.625 | N98: 45958.519 | O98: NO | P98: USUARIO | Q98: COMUNICACION | R98: CONEXIONES DE COMERCIO | S98: UNO A UNO | T98: CB UNO A UNO | U98: EJECUTADO | V98: 27/10/2025 SE ESCALA PARA VISITA. LLAMAR ANTES DE VISITAR, CONFIRMAR FALLA Y DATOS | 28/10/2025 SE REALIZA CONFIGURACIÓN DE ROUTER REPETIDOR ENLAZADO AL ROUTER PRINCIPAL DEL COMERCIO , DEJANDO PRUEBAS OK | W98: VISITA TECNICA | X98: 9L6ZZ639 | Y98: TIPO I | Z98: TERRESTRE | AA98: ALVARADO MORENO CRISTHIAN | AB98: 1 | AC98: 0 | AD98: 0 | AE98: 0 | AF98: 0 | AG98: 65960 | AH98: 65960
A99: MANIZALES | B99: SUROCCIDENTE Y EJE CAFETERO | C99: 0004-0002 | D99: 17001 | E99: 2941568 | F99: 3007049692 | G99: INCIDENTE | H99: CALDAS | I99: MANIZALES | J99: PTM MANIZALES VARIEDADES JUAND | K99: REDEBAN | L99: FO-25-1741050 | M99: 45957.634 | N99: 45957.697 | O99: NO | P99: USUARIO | Q99: COMUNICACION | R99: CONEXIONES DE COMERCIO | S99: AGREGADOR | T99: COMCARD - PTM | V99: 27/10/2025 SE ESCALA PARA VISITA. LLAMAR ANTES DE VISITAR, CONFIRMAR FALLA Y DATOS | 27/10/2025 SE REALIZA LLAMADA CON USUARIO EL CUAL INDICA QUE CAMBIO DE PROVEEDOR DE INTERNET Y NO LE DABA EL SERVICIO PERO REINICIO EL MODEM DEL NUEVO PROVEEDOR Y QUEDA CON SERVICIO OPERATIVO Y EN BUEN ESTADO, SERVICIO OK | W99: SOPORTE TELEFONICO | Y99: TIPO I | Z99: TERRESTRE | AA99: AGUIRRE HENAO RAUL EDUARDO | AB99: 0 | AC99: 0 | AD99: 0 | AE99: 0 | AF99: 0 | AG99: 37905 | AH99: 37905
A100: BARRANQUILLA | B100: COSTA | C100: 0004-0001 | D100: 8001 | E100: 2942598 | F100: 3007080994 | G100: INCIDENTE | H100: ATLANTICO | I100: BARRANQUILLA | J100: DISTRICOL Q´CHICHA S.A.S. | K100: REDEBAN | L100: FO-25-1741960 | M100: 45957.706 | N100: 45958.631 | O100: NO | P100: USUARIO | Q100: COMUNICACION | R100: CONEXIONES DE COMERCIO | S100: AGREGADOR | T100: DISTRICOL | U100: EJECUTADO | V100: 27/10/2025 SE ESCALA PARA VISITA. LLAMAR ANTES DE VISITAR, CONFIRMAR FALLA Y DATOS | 28/10/2025 SE REALIZA VISITA SE VALIDA DATAFONO Y TODO OK ,NO TENÍA INTERNET SE PROCEDE A CONFIGURAR NUEVAMENTE Y TODO OK ,PRUEBAS OK, CB OPERATIVO | W100: VISITA TECNICA | X100: FJZZZ899 | Y100: TIPO I | Z100: TERRESTRE | AA100: PORRAS CASTRO DARLON NASCK | AB100: 1 | AC100: 0 | AD100: 0 | AE100: 0 | AF100: 0 | AG100: 65960 | AH100: 65960
...

Sheet OC
A1: CIUDAD SEDE | B1: ZONA | C1: CENTRO DE COSTOS LINEACOM | D1: CODIGO DANE | E1: TA/CODIGO ACTIVIDAD | F1: CODIGO CB | G1: ACTIVIDAD | H1: DEPARTAMENTO | I1: CIUDAD | J1: NOMBRE DEL CB | K1: RED | L1: FO | M1: FECHA ASIGNACION A LINEA COMUNICACIONES | N1: FECHA CIERRE DEL TICKET (DD/MM/AAAA HH:MM) | O1: ACOMETIDA | P1: SOLICITUD | Q1: DESCRIPCION | R1: FORMATO | S1: CADENA | T1: ESTADO | U1: CAUSAL ESTADO | V1: OBSERVACION | W1: FORMA DE ATENCION | X1: TERMINAL(ES) | Y1: TIPIFICACION | Z1: TIPO DE TRAYECTO | AA1: NOMBRE DEL TECNICO | AB1: DIAS DE VISITA | AC1: SWITCH | AD1: ACOMETIDA DATOS | AE1: ACOMETIDA ELÉCTRICA | AF1: VALOR ACTIVIDAD | AG1: VALOR TOTAL
A2: BUCARAMANGA | B2: SANTANDERES | C2: 0004-0008 | D2: 20770 | E2: 14207887 | F2: 3007046145 | G2: OC TRASLADO | H2: CESAR | I2: SAN MARTIN | J2: PTM SAN MARTIN TIENDA Y MULTIS | K2: REDEBAN | L2: FO-25-1685818 | M2: 45945.333 | N2: 45945.494 | O2: NO | P2: TRASLADO | Q2: TRASLADO EXTERNO | R2: AGREGADOR | S2: COMCARD - PTM | U2: CANCELADO POR EL USUARIO | V2: 15/10/2025 EN COMUNICACIÓN CON LA SEÑORA YURLEY NARANJO AL NUMERO 3188651011 INDICA QUE YA LE REALIZARON EL TRASLADO EXTERNO, QUE ESTA OPERANDO BIEN, DIRECCION EN VAUCHER CORRECTA Y QUE NO REQUIERE VISITA | 15/10/2025 EN COMUNICACIÓN CON LA SEÑORA YURLEY NARANJO AL NUMERO 3188651011 INDICA QUE YA LE REALIZARON EL TRASLADO EXTERNO, QUE ESTA OPERANDO BIEN, DIRECCION EN VAUCHER CORRECTA Y QUE NO REQUIERE VISITA | 15/10/2025 EN COMUNICACIÓN CON LA SEÑORA YURLEY NARANJO AL NUMERO 3188651011 INDICA QUE YA LE REALIZARON EL TRASLADO EXTERNO, QUE ESTA OPERANDO BIEN, DIRECCION EN VAUCHER CORRECTA Y QUE NO REQUIERE VISITA | W2: SOPORTE TELEFONICO | Y2: TIPO III | Z2: TERRESTRE | AA2: GARCIA CHAVARRIA TATIANA EDELMIRA | AB2: 0 | AC2: 0 | AD2: 0 | AE2: 0 | AF2: 37905 | AG2: 37905
A3: CALI | B3: SUROCCIDENTE Y EJE CAFETERO | C3: 0004-0003 | D3: 76001 | E3: 14207963 | F3: 3007070125 | G3: OC TRASLADO | H3: VALLE DEL CAUCA | I3: CALI | J3: PTM CALI AUTOSERVICIO EL CRUC | K3: REDEBAN | L3: FO-25-1685815 | M3: 45945.333 | N3: 45945.489 | O3: NO | P3: TRASLADO | Q3: TRASLADO EXTERNO | R3: AGREGADOR | S3: COMCARD - PTM | U3: CANCELADO POR EL USUARIO | V3: 15/10/2025 EN COMUNICACIÓN CON LA SEÑORA ADRIANA MARIA CHAPARRO PARRA AL NUMERO 3156756178 INDICA QUE YA LE REALIZARON EL TRASLADO EXTERNO, QUE ESTA OPERANDO BIEN, DIRECCION EN VAUCHER CORRECTA Y QUE NO REQUIERE VISITA | 15/10/2025 EN COMUNICACIÓN CON LA SEÑORA ADRIANA MARIA CHAPARRO PARRA AL NUMERO 3156756178 INDICA QUE YA LE REALIZARON EL TRASLADO EXTERNO, QUE ESTA OPERANDO BIEN, DIRECCION EN VAUCHER CORRECTA Y QUE NO REQUIERE VISITA | 15/10/2025 EN COMUNICACIÓN CON LA SEÑORA ADRIANA MARIA CHAPARRO PARRA AL NUMERO 3156756178 INDICA QUE YA LE REALIZARON EL TRASLADO EXTERNO, QUE ESTA OPERANDO BIEN, DIRECCION EN VAUCHER CORRECTA Y QUE NO REQUIERE VISITA | W3: SOPORTE TELEFONICO | Y3: TIPO I | Z3: TERRESTRE | AA3: GARCIA CHAVARRIA TATIANA EDELMIRA | AB3: 0 | AC3: 0 | AD3: 0 | AE3: 0 | AF3: 37905 | AG3: 37905
A4: CUCUTA | B4: SANTANDERES | C4: 0004-0008 | D4: 54874 | E4: 14208390 | F4: 3007078662 | G4: OC TRASLADO | H4: NORTE DE SANTANDER | I4: VILLA DEL ROSARIO | J4: DISTRICOL HERMANOS PERLIZ | K4: REDEBAN | L4: FO-25-1705983 | M4: 45947.556 | N4: 45951.686 | O4: NO | P4: TRASLADO | Q4: TRASLADO EXTERNO | R4: AGREGADOR | S4: DISTRICOL | U4: CANCELADO POR EL USUARIO | V4: 20/10/2025 SE INTENTA COMUNICACIÓN AL NÚMERO 3001108807 PERO NO HAY CONTACTO, SE ESCALA PARA VISITA | W4: SOPORTE TELEFONICO | Y4: TIPO I | Z4: TERRESTRE | AA4: PACHECO BUITRAGO JAVIER ALONSO | AB4: 0 | AC4: 0 | AD4: 0 | AE4: 0 | AF4: 37905 | AG4: 37905
A5: NEIVA | B5: REMOTAS | C5: 0004-0007 | D5: 18001 | E5: 14215933 | F5: 3007076503 | G5: OC TRASLADO | H5: CAQUETA | I5: FLORENCIA | J5: BARRIO EL PORVENIR FLORENCIA 2 | K5: REDEBAN | L5: FO-25-1726264 | M5: 45953.516 | N5: 45954.492 | O5: NO | P5: TRASLADO | Q5: TRASLADO EXTERNO | R5: CB UNO A UNO | S5: CB UNO A UNO | U5: CANCELADO POR EL USUARIO | V5: 23/10/2025 SE CONFIRMAN DATOS Y SOLICITUD CON EL USUARIO, SE ESCALA PARA VIISTA-POR FAVOR LLAMAR ANTES DE DESPLAZARSE | W5: SOPORTE TELEFONICO | Y5: TIPO IV | Z5: TERRESTRE | AA5: BERMUDEZ SANCHEZ JOSE NEYBER | AB5: 0 | AC5: 0 | AD5: 0 | AE5: 0 | AF5: 37905 | AG5: 37905
A6: MEDELLIN | B6: NOROCCIDENTE | C6: 0004-0005 | D6: 5364 | E6: 14216119 | F6: 3007030864 | G6: OC TRASLADO | H6: ANTIOQUIA | I6: JARDIN | J6: COMCARD JARDIN CITARA | K6: REDEBAN | L6: FO-25-1707954 | M6: 45947.556 | N6: 45950.699 | O6: NO | P6: TRASLADO | Q6: TRASLADO EXTERNO | R6: AGREGADOR | S6: COMCARD - PTM | U6: CANCELADO POR LA RED-SOPORTE TELEFONICO | V6: 20/10/2025 , EN COMUNICACIÓN CON EL SEÑOR DIEGO SALGADO AL NÚMERO 3128705069 NOS INDICA QUE LA DIRECCIÓN CORRECTA CALLE 9 # 5 - 50 LA CUAL NO COINCIDE CON LA DE LA LISTA DE CHEQUEO, SE ESCALA | 20/10/2025 , EN COMUNICACIÓN CON EL SEÑOR DIEGO SALGADO AL NÚMERO 3128705069 NOS INDICA QUE LA DIRECCIÓN CORRECTA CALLE 9 # 5 - 50 LA CUAL NO COINCIDE CON LA DE LA LISTA DE CHEQUEO | 20/10/2025 , EN COMUNICACIÓN CON EL SEÑOR DIEGO SALGADO AL NÚMERO 3128705069 NOS INDICA QUE LA DIRECCIÓN CORRECTA CALLE 9 # 5 - 50 LA CUAL NO COINCIDE CON LA DE LA LISTA DE CHEQUEO | W6: SOPORTE TELEFONICO | Y6: TIPO III | Z6: TERRESTRE | AA6: GARCIA CHAVARRIA TATIANA EDELMIRA | AB6: 0 | AC6: 0 | AD6: 0 | AE6: 0 | AF6: 37905 | AG6: 37905
A7: CALI | B7: SUROCCIDENTE Y EJE CAFETERO | C7: 0004-0003 | D7: 76001 | E7: 14223011 | F7: 3007034770 | G7: OC TRASLADO | H7: VALLE DEL CAUCA | I7: CALI | J7: BARRIO MONTEBELLO 1 CALI | K7: REDEBAN | L7: FO-25-1710859 | M7: 45950.721 | N7: 45951.449 | O7: NO | P7: TRASLADO | Q7: TRASLADO EXTERNO | R7: UNO A UNO | S7: CB UNO A UNO | V7: 21/10/2025 EN COMUNICACIÓN CON LA SRA LUZ PESCADOR AL NÚMERO 3154164882, NOS INFORMA QUE AÚN NO CUENTA CON INTERNET EN LA NUEVA DIRECCIÓN, SE LE INDICA QUE CUANDO TENGA TODAS LAS ADECUACIONES LITSAS SE COMUNIQUE NUEVAMENTE A LA LINEA PARA SOLICITAR EL TRASLADO | W7: SOPORTE TELEFONICO | Y7: TIPO I | Z7: TERRESTRE | AA7: CONTRERAS ROSSI LITZY YULIETH | AB7: 0 | AC7: 0 | AD7: 0 | AE7: 0 | AF7: 37905 | AG7: 37905
A8: CUCUTA | B8: SANTANDERES | C8: 0004-0008 | D8: 54001 | E8: 14227681 | F8: 3007071024 | G8: OC TRASLADO | H8: NORTE DE SANTANDER | I8: CUCUTA | J8: DISTRICOL MAKARENA CEN BELLEZA | K8: REDEBAN | L8: FO-25-1731950 | FO-25-1710747 | M8: 45950.712 | N8: 45957.416 | O8: NO | P8: TRASLADO | Q8: TRASLADO EXTERNO | R8: AGREGADOR | S8: DISTRICOL | T8: EJECUTADO | EJECUTADO / CANCELADO | U8: EJECUTADO EXITOSO | V8: 27/10/2025 SE REALIZÓ VISITA A LA DIRECCIÓN ASIGNADA PARA EL TRASLADO Y SE REALIZA TRASLADO DE DATAFONO, LECTORA SE REALIZA INCIALIZACION DE EQUIPO, DIRECCIÓN OK, PRUEBAS EXITOSAS | W8: VISITA TECNICA | X8: MN00C098 | Y8: TIPO I | Z8: TERRESTRE | AA8: MORA VEGA JEAMPIER | AB8: 1 | AC8: 0 | AD8: 0 | AE8: 0 | AF8: 65960 | AG8: 65960
A9: CALI | B9: SUROCCIDENTE Y EJE CAFETERO | C9: 0004-0003 | D9: 19001 | E9: 14256898 | F9: 3007028623 | G9: OC TRASLADO | H9: CAUCA | I9: POPAYAN | J9: BARRIO MODELO 6 POPAYAN | K9: REDEBAN | L9: FO-25-1747899 | M9: 45958.636 | N9: 45958.734 | O9: NO | P9: TRASLADO | R9: CB UNO A UNO | S9: CB UNO A UNO | V9: 28/10/2025 NOS LLEGA TRASLADO CON RADICADO 14256898 PARA EL PUNTO 28623 PERO REALIZANDO VALIDACIONES Y LA USUARIA TAMBIÉN NOS INFORMO QUE PERTENECEN A WOMPI, SE PROCEDE A CERRAR EL CASO. | 28/10/2025 NOS LLEGA TRASLADO CON RADICADO 14256898 PARA EL PUNTO 28623 PERO REALIZANDO VALIDACIONES Y LA USUARIA TAMBIÉN NOS INFORMO QUE PERTENECEN A WOMPI, SE PROCEDE A CERRAR EL CASO. | W9: SOPORTE TELEFONICO | Y9: TIPO III | Z9: TERRESTRE | AA9: TORO CARDONA ELIZABETH | AB9: 0 | AC9: 0 | AD9: 0 | AE9: 0 | AF9: 37905 | AG9: 37905
A10: BOGOTA | B10: CUNDINAMARCA | C10: 0004-0004 | D10: 25754 | E10: 14288732 | F10: 3007069977 | G10: OC TRASLADO | H10: CUNDINAMARCA | I10: SOACHA | J10: PTM SOACHA PAPELERIA Y VARIED | K10: REDEBAN | L10: FO-25-1760907 | M10: 45960.456 | N10: 45961.71 | O10: NO | P10: TRASLADO | Q10: TRASLADO EXTERNO | R10: AGREGADOR | S10: COMCARD - PTM | T10: EJECUTADO / CANCELADO | U10: PETICIÓN USUARIO | V10: 30/10/2025 SE LLAMA A LOS 2 NUMERO NO HAY COMUNICACION | 31/10/2025 SE LLEGA A DIRECCIÓN PARA REALIZAR TRASLADO, EN SITIO EN SERIE CARLOS INDICA QUE NO HAN SOLICITADO TRASLADO DE VALIDA UN VOUCHER EN EL MOMENTO Y EFECTIVAMENTE LA DIRECCIÓN ESTÁ OK, SE ESCALA A COORDINADOR VALIDANDO QUE LOS DATOS ESTÁN OK NO SE MANIPULA TERMINAL CLIENTE REQUIERE DESBLOQUEO PARA PODER REALIZAR TRANSACCIONES EL CUAL SE ATRIBUYE A PTM TÉCNICO NO MANIPULA TERMINAL NO FIRMAN EL CONTROL | W10: VISITA TECNICA | Y10: TIPO I | Z10: TERRESTRE | AA10: BUSTOS MORA DIEGO MANUEL | AB10: 1 | AC10: 0 | AD10: 0 | AE10: 0 | AF10: 65960 | AG10: 65960
A11: BOGOTA | B11: CUNDINAMARCA | C11: 0004-0004 | D11: 25843 | E11: 14290565 | F11: 3007076569 | G11: OC TRASLADO | H11: CUNDINAMARCA | I11: VILLA DE SAN DIEGO DE UBATE | J11: BARRIO SAN JOSE VILLA DE SAN DIEGO DE UBATE | K11: REDEBAN | L11: FO-25-1760674 | FO-25-1747837 | M11: 45958.636 | N11: 45960.678 | O11: NO | P11: TRASLADO | Q11: TRASLADO EXTERNO | R11: UNO A UNO | S11: UNO A UNO | T11: EJECUTADO | EJECUTADO / CANCELADO | U11: EJECUTADO EXITOSO | V11: 30/10/2025 SE REALIZA VISITA A COMERCIO, SE PROCEDE A REALIZAR EL TRASLADO DE DATAFONO - LECTOR SE CREAN USUARIOS, PRUEBAS OKAY. | W11: VISITA TECNICA | X11: 103ZZ249 | Y11: TIPO II | Z11: TERRESTRE | AA11: ARIAS QUILINDO JULIAN | AB11: 1 | AC11: 0 | AD11: 0 | AE11: 0 | AF11: 163814 | AG11: 163814
AG12: =SUM(AG2:AG11) -> 561069
