Workbook
Name A: #REF!
Name Actividad: #REF!
Name Analistas: #REF!
Name arearesponsable: #REF!
Name CCO: #REF!
Name Clientes: #REF!
Name COORDINADOR: #REF!
Name Coordinadores: #REF!
Name DOCUMENTADOR: #REF!
Name ES: #REF!
Name ESS: #REF!
Name Estado: #REF!
Name ESTADOACTIVIDAD: #REF!
Name ESTADOS: #REF!
Name ESTADOSCIERRES: #REF!
Name Facturacion: #REF!
Name FACTURACIÓN: #REF!
Name falla: #REF!
Name Fallas: #REF!
Name Grupo_Falla: #REF!
Name inconservmanager: #REF!
Name INCUMPLIMIENTO: #REF!
Name LISTA: #REF!
Name LISTA2: #REF!
Name LOLO: #REF!
Name solicitudes: #REF!
Name Tecnicos: #REF!
Name Version: #REF!

Sheet BASE LIQUIDACION REDEBAN 2025
A1: Tipificación | B1: Implementaciones | C1: Incidentes – Ordenes de Cambio | D1: Fallida | G1: Tipificación | H1: Actividad sin cambio de datafono | J1: Actividad + adicional cambio de datafono | L1: Visita Fallida | N1: Incremento 2025
A2: TIPO I | B2: =71384.4052*(1+$N$2) -> 75096.394 | C2: =62699.6885*(1+$N$2) -> 65960.072 | D2: =35693.4343*(1+$N$2) -> 37549.493 | H2: Instalación Pinpad + HUB | I2: Segunda actividad en mismo comercio, misma visita | J2: Instalación Pinpad + HUB | K2: Segunda actividad en mismo comercio, misma visita | N2: 0.052
A3: TIPO II | B3: =155716.4408*(1+$N$2) -> 163813.7 | C3: =137802.16*(1+$N$2) -> 144967.87 | D3: =117879.8485*(1+$N$2) -> 124009.6 | G3: Tipo I | H3: =31819.23994686*(1+$N$2) -> 33473.84 | I3: =26222.67548178*(1+$N$2) -> 27586.255 | J3: =51196.46628516*(1+$N$2) -> 53858.683 | K3: =42157.66342524*(1+$N$2) -> 44349.862 | L3: =28948.10610808*(1+$N$2) -> 30453.408
A4: TIPO III | B4: =262099.6015*(1+$N$2) -> 275728.78 | C4: =262099.6015*(1+$N$2) -> 275728.78 | D4: =262099.6015*(1+$N$2) -> 275728.78 | G4: Tipo II | H4: =98014.03066668*(1+$N$2) -> 103110.76 | I4: =26222.67548178*(1+$N$2) -> 27586.255 | J4: =119562.49505524*(1+$N$2) -> 125779.74 | K4: =42157.66342524*(1+$N$2) -> 44349.862 | L4: =94765.6295813*(1+$N$2) -> 99693.442
A5: TIPO IV | B5: =479878.9419*(1+$N$2) -> 504832.65 | C5: =455882.9625*(1+$N$2) -> 479588.88 | D5: =370911.6746*(1+$N$2) -> 390199.08 | G5: Tipo III | H5: =189140.9827006*(1+$N$2) -> 198976.31 | I5: =26222.67548178*(1+$N$2) -> 27586.255 | J5: =200461.60194168*(1+$N$2) -> 210885.61 | K5: =42157.66342524*(1+$N$2) -> 44349.862 | L5: =171492.68108896*(1+$N$2) -> 180410.3
A6: Destino Aéreo | B6: =939603.5767*(1+$N$2) -> 988462.96 | C6: a partir del 5to servicio | G6: Tipo IV | H6: =461621.60109668*(1+$N$2) -> 485625.92 | I6: =26222.67548178*(1+$N$2) -> 27586.255 | J6: =461621.60109668*(1+$N$2) -> 485625.92 | K6: =42157.66342524*(1+$N$2) -> 44349.862 | L6: =461621.60109668*(1+$N$2) -> 485625.92
G7: * Tipo IV Especial Donde se requiera desplazamiento aéreo o fluvial será facturado el valor de la actividad y adicional el valor de $988.463 por cada 5 actividades de esta tipología
A8: Tarifas para día adicional de actividades:
A9: Tipificación | B9: Día adicional- menos de dos horas | C9: Medio día adicional | D9: Día adicional- más de 4 horas
A10: Tipo I | B10: =71384.4052*(1+$N$2) -> 75096.394 | C10: =133455.9267*(1+$N$2) -> 140395.63 | D10: =191225.1201*(1+$N$2) -> 201168.83 | G10: Actividad | H10: Unidad | I10: Valor Unitario
A11: Tipo II | B11: =133455.9267*(1+$N$2) -> 140395.63 | C11: =191225.1201*(1+$N$2) -> 201168.83 | D11: =257740.6152*(1+$N$2) -> 271143.13 | G11: Gestión telefónica y cierre de incidente de bloqueo | H11: Unidad | I11: =17639.19516086*(1+$N$2) -> 18556.433
A12: Tipo III | B12: =186821.7926*(1+$N$2) -> 196536.53 | C12: =248892.0824*(1+$N$2) -> 261834.47 | D12: =306662.5075*(1+$N$2) -> 322608.96 | G12: Servicio de cierre de incidente de bloqueo | H12: Unidad | I12: =4810.80785492*(1+$N$2) -> 5060.9699
A13: Tipo IV | B13: =186821.7926*(1+$N$2) -> 196536.53 | C13: =248892.0824*(1+$N$2) -> 261834.47 | D13: =306662.5075*(1+$N$2) -> 322608.96
A16: Servicio | B16: Tarifa actividad | D16: VALOR DE LA TERMINAL ADICIONAL | E16: VALOR DE INSTALACIÓN DE BASE EN "Y"
A17: Papelería – Tarifa única | B17: =34010.9321*(1+$N$2) -> 35779.501 | D17: =20537.3658*(1+$N$2) -> 21605.309 | E17: =10737.9606*(1+$N$2) -> 11296.335
A18: Papelería Tipo II - Visita técnica | B18: =64310*(1+$N$2) -> 67654.12
A19: Solución telefónica | B19: =39202.5476*(1+$N$2) -> 41241.08
A22: Traifas 2024
A23: Tipificación | B23: Implementaciones | C23: Incidentes – Ordenes de Cambio | D23: Fallida | G23: Tipificación | H23: Actividad sin cambio de datafono | J23: Actividad + adicional cambio de datafono | L23: Visita Fallida
A24: TIPO I | B24: 71384.405 | C24: 62699.688 | D24: 35693.434 | H24: Instalación Pinpad + HUB | I24: Segunda actividad en mismo comercio, misma visita | J24: Instalación Pinpad + HUB | K24: Segunda actividad en mismo comercio, misma visita
A25: TIPO II | B25: 155716.44 | C25: 137802.16 | D25: 117879.85 | G25: Tipo I | H25: 31819.24 | I25: 26222.675 | J25: 51196.466 | K25: 42157.663 | L25: 28948.106
A26: TIPO III | B26: 262099.6 | C26: 262099.6 | D26: 262099.6 | G26: Tipo II | H26: 98014.031 | I26: 26222.675 | J26: 119562.5 | K26: 42157.663 | L26: 94765.63
A27: TIPO IV | B27: 479878.94 | C27: 455882.96 | D27: 370911.67 | G27: Tipo III | H27: 189140.98 | I27: 26222.675 | J27: 200461.6 | K27: 42157.663 | L27: 171492.68
A28: Destino Aéreo | B28: 939603.58 | C28: a partir del 5to servicio | G28: Tipo IV | H28: 461621.6 | I28: 26222.675 | J28: 461621.6 | K28: 42157.663 | L28: 461621.6
G29: * Tipo IV Especial Donde se requiera desplazamiento aéreo o fluvial será facturado el valor de la actividad y adicional el valor de $939,604 por cada 5 actividades de esta tipología
A30: Tarifas para día adicional de actividades:
A31: Tipificación | B31: Día adicional- menos de dos horas | C31: Medio día adicional | D31: Día adicional- más de 4 horas
A32: Tipo I | B32: 71384.405 | C32: 133455.93 | D32: 191225.12 | G32: Actividad | H32: Unidad | I32: Valor Unitario
A33: Tipo II | B33: 133455.93 | C33: 191225.12 | D33: 257740.62 | G33: Gestión telefónica y cierre de incidente de bloqueo | H33: Unidad | I33: 17639.195
A34: Tipo III | B34: 186821.79 | C34: 248892.08 | D34: 306662.51 | G34: Servicio de cierre de incidente de bloqueo | H34: Unidad | I34: 4810.8079
A35: Tipo IV | B35: 186821.79 | C35: 248892.08 | D35: 306662.51
A38: Servicio | B38: Tarifa actividad | D38: VALOR DE LA TERMINAL ADICIONAL | E38: VALOR DE INSTALACIÓN DE BASE EN "Y"
A39: Papelería – Tarifa única | B39: 34010.932 | D39: 20537.366 | E39: 10737.961
A40: Papelería Tipo II - Visita técnica | B40: 64310
A41: Solución telefónica | B41: 39202.548

Sheet RESUMEN LIQUIDACION
A1: FACTURACIÓN ACTIVIDADES REDEBAN CB BANCOLOMBIA Y AVAL
A2: 1 AL 30 DE OCTUBRE 2025
A4: CONCEPTOS | B4: CANTIDAD | C4: TOTAL
A5: Aperturas Bancolombia | B5: =COUNTA(APERTURAS_BANCOLOMBIA!A:A)-1 -> 180 | C5: =APERTURAS_BANCOLOMBIA!AB182 -> 28693432
A6: Incidentes Bancolombia | B6: =COUNTA(INCIDENTES_BANCOLOMBIA!A:A)-1 -> 975 | C6: =INCIDENTES_BANCOLOMBIA!AE977 -> 162740088
A7: Gestión de Campo Bancolombia | B7: =COUNTA(OC_BANCOLOMBIA!A:A)-1 -> 353 | C7: =OC_BANCOLOMBIA!AE355 -> 57676313
A8: Soporte Papelería Bancolombia | B8: =COUNTA(PAPELERIA!A:A)-1 -> 2311 | C8: =PAPELERIA!AD2313 -> 103538227
A9: Aperturas Aval | B9: =COUNTA(APERTURAS_AVAL!A:A)-1 -> 223 | C9: =APERTURAS_AVAL!AB225 -> 37006327
A10: Incidentes Aval | B10: =COUNTA(INCIDENTES_AVAL!A:A)-1 -> 342 | C10: =INCIDENTES_AVAL!AC344 -> 38230031
A11: Gestión de Campo Aval | B11: =COUNTA(OC_AVAL!A:A)-1 -> 102 | C11: =OC_AVAL!AE104 -> 13704688
A12: Aperturas BBVA | B12: =COUNTA(APERTURAS_BBVA!A:A)-1 -> 1 | C12: =APERTURAS_BBVA!AB3 -> 75096
A13: Gestión de Campo BBVA | B13: =COUNTA(OC_BBVA!A:A)-1 -> 2 | C13: =OC_BBVA!AE4 -> 289935.74
A14: Incidentes BBVA | B14: =COUNTA(INCIDENTES_BBVA!A:A)-1 -> 2 | C14: =INCIDENTES_BBVA!AB4 -> 289936
A15: SUBTOTAL | C15: =SUM(C5:C14) -> 4.4224407e+08
A16: Iva | C16: =C15*0.19 -> 84026374
A17: TOTAL | C17: =SUM(C15:C16) -> 5.2627045e+08

Sheet APERTURAS_BANCOLOMBIA
A1: CIUDAD SEDE | B1: ZONA | C1: CENTRO DE COSTOS LINEACOM | D1: CODIGO DANE | E1: TA/CODIGO ACTIVIDAD | F1: CODIGO CB | G1: ACTIVIDAD | H1: TIPO DE APERTURA | I1: DEPARTAMENTO | J1: CIUDAD | K1: NOMBRE DEL CB | L1: RED | M1: FO | N1: FECHA LISTA | O1: FECHA ULTIMA ACTUALIZACION | P1: FORMATO | Q1: CADENA | R1: ESTADO | S1: OBSERVACIONES CLIENTE | T1: FORMA DE ATENCION | U1: TERMINAL(ES) | V1: TIPIFICACION | W1: TIPO DE TRAYECTO | X1: NOMBRE DEL TECNICO | Y1: DIAS DE VISITA | Z1: DIA ADICIONAL | AA1: VALOR DIAS ACTIVIDAD FACTURABLES | AB1: VALOR TOTAL
A2: PASTO | B2: SUROCCIDENTE Y EJE CAFETERO | C2: 0004-0003 | D2: 86320 | E2: TA-25-1145855 | F2: 3007081670 | G2: APERTURA | H2: CB CRECIMIENTO ALIANZA - NUEVO | I2: PUTUMAYO | J2: ORITO | K2: DISTRICOL BOUTIQUEMISANGELITOS | L2: REDEBAN | M2: FO-25-1577742 | N2: 45924.523 | O2: 45931.706 | P2: AGREGADOR | Q2: DISTRICOL | R2: EJECUTADO | S2: 24/09/2025 24-09 PROGRAMACIÓN REALIZADA POR LA ALIANZA | 29/09/2025 SE ESPERA REALIZAR INSTALACIÓN EL MIÉRCOLES EN LA JORNADA DE LA TARDE YA QUE HAY VARIAS ACTIVIDADES EN LA ZONA | 01/10/2025 SE REALIZA INSTALACIÓN DE CB. SE CAPACITA SOBRE SOMOS BANCOLOMBIA, MANEJO DE DATAFONO Y PARTE ADMINISTRATIVA. SE INSTALA AVISO EXTERIOR, FLANGER Y DISPLAY LEGAL CON INSERTO HORARIO, TARIFAS Y NÚMERO DE CB. SE ENTREGAN 40 ROLLOS. SE REALIZA PRUEBAS TX EXITOSAS. QUEDA OPERATIVO | T2: VISITA TECNICA | U2: FWZZZ496 | V2: TIPO IV | W2: TERRESTRE | X2: CASTILLO HERRERA ALEX RICARDO | Y2: 1 | Z2: 0 | AA2: 504833 | AB2: 504833
A3: PASTO | B3: SUROCCIDENTE Y EJE CAFETERO | C3: 0004-0003 | D3: 86568 | E3: TA-25-1145861 | F3: 3007081675 | G3: APERTURA | H3: CB CRECIMIENTO ALIANZA - NUEVO | I3: PUTUMAYO | J3: PUERTO ASIS | K3: DISTRICOL SOCCER LAGUNA | L3: REDEBAN | M3: FO-25-1577748 | N3: 45924.619 | O3: 45931.733 | P3: AGREGADOR | Q3: DISTRICOL | R3: EJECUTADO | S3: 24/09/2025 24-09 PROGRAMACIÓN REALIZADA POR LA ALIANZA | 30/09/2025 NO SE LOGRA LLEGAR AL DESTINO EL DIA DE HOY POR PROBLEMAS EN LAS VIAS, SE LLEGARA EL DIA DE MAÑANA PARA ATENCION DE ACTIVIDADES | 01/10/2025 SE VISITO EL COMERCIO PARA DAR APERTURA AL CB, SE INSTALA DATAFONO CON LECTORA BASE Y MAGIC BOX, SE INSTALA PUBLICIDAD Y SE ENTREGA ROLLOS, SE CAPACITA OK, PRUEBAS OK EXCEPTO RECAUDO POR NO TENER ELEMENTOS PARA HACERLA, SOMOS BANCOLOMBIA OK, CB OPERATIVO | T3: VISITA TECNICA | U3: FWZZZ497 | V3: TIPO IV | W3: TERRESTRE | X3: GUERRERO RAMIREZ OSCAR DARIO | Y3: 1 | Z3: 0 | AA3: 504833 | AB3: 504833
A4: PASTO | B4: SUROCCIDENTE Y EJE CAFETERO | C4: 0004-0003 | D4: 86568 | E4: TA-25-1145865 | F4: 3007081677 | G4: APERTURA | H4: CB CRECIMIENTO ALIANZA - NUEVO | I4: PUTUMAYO | J4: PUERTO ASIS | K4: DISTRICOL DROGUERIA SANTANA | L4: REDEBAN | M4: FO-25-1577752 | N4: 45924.619 | O4: 45932.633 | P4: AGREGADOR | Q4: DISTRICOL | R4: EJECUTADO | S4: 24/09/2025 24-09 PROGRAMACIÓN REALIZADA POR LA ALIANZA | 30/09/2025 NO SE LOGRA LLEGAR EL DIA DE HOY AL DESTINO POR PROBLEMAS EN LA VIA, SE LLEGARA AL SITIO EL DIA DE MAÑANA PARA ATENCION DE ACTIVIDADES . | 02/10/2025 SE VISITO EL COMERCIO PARA DAR APERTURA AL CB, SE INSTALA DATAFONO CON LECTORA BASE Y MAGIC BOX, SE INSTALA PUBLICIDAD Y SE ENTREGA ROLLOS, SE CAPACITA OK, PRUEBAS OK EXCEPTO RECAUDO POR NO TENER ELEMENTOS PARA HACERLA, SOMOS BANCOLOMBIA OK, CB OPERATIVO | T4: VISITA TECNICA | U4: FWZZZ498 | V4: TIPO IV | W4: TERRESTRE | X4: GUERRERO RAMIREZ OSCAR DARIO | Y4: 1 | Z4: 0 | AA4: 504833 | AB4: 504833
A5: PASTO | B5: SUROCCIDENTE Y EJE CAFETERO | C5: 0004-0003 | D5: 86757 | E5: TA-25-1145899 | F5: 3007081680 | G5: APERTURA | H5: CB CRECIMIENTO ALIANZA - NUEVO | I5: PUTUMAYO | J5: SAN MIGUEL | K5: DISTRICOL MI PAPALERIA MP | L5: REDEBAN | M5: FO-25-1577762 | N5: 45924.523 | O5: 45931.459 | P5: AGREGADOR | Q5: DISTRICOL | R5: EJECUTADO | S5: 24/09/2025 24-09 PROGRAMACIÓN REALIZADA POR LA ALIANZA | 29/09/2025 ACTIVIDAD SE REALIZARÁ EL DÍA MIÉRCOLES DEBIDO YA QUE EL TRAYECTO ES DE MÁS DE 9 HORAS DESDE LA CIUDAD DE PASTO | 01/10/2025 SE REALIZA INSTALACIÓN DE CB. SE CAPACITA SOBRE SOMOS BANCOLOMBIA, MANEJO DE DATAFONO Y PARTE ADMINISTRATIVA. SE INSTALA AVISO EXTERIOR, FLANGER Y DISPLAY LEGAL CON INSERTO HORARIO, TARIFAS Y NÚMERO DE CB. SE ENTREGAN 40 ROLLOS. SE REALIZA PRUEBAS TX EXITOSAS. QUEDA OPERATIVO | T5: VISITA TECNICA | U5: FWZZZ500 | V5: TIPO IV | W5: TERRESTRE | X5: CASTILLO HERRERA ALEX RICARDO | Y5: 1 | Z5: 0 | AA5: 504833 | AB5: 504833
A6: NEIVA | B6: REMOTAS | C6: 0004-0007 | D6: 18001 | E6: TA-25-1157218 | F6: 3007081709 | G6: APERTURA | H6: CB CRECIMIENTO ALIANZA - NUEVO | I6: CAQUETA | J6: FLORENCIA | K6: DISTRICOL CILEA A&V | L6: REDEBAN | M6: FO-25-1598630 | N6: 45929.795 | O6: 45931.478 | P6: AGREGADOR | Q6: DISTRICOL | R6: EJECUTADO | S6: 29/09/2025 29-09 PROGRAMACIÓN REALIZADA POR LA ALIANZA | 01/10/2025 SE REALIZA INSTALACIÓN DE DATAFONO LECTORA BASE FUENTE DE PODER CABLE DE RED SE ENTREGAN 40 ROLLOS RBM SE INSTALA AVISO EXTERIOR Y PUBLICIDAD SE CAPACITA EN CB Y SOMOS BANCOLOMBIA TIENE CREADO EL USUARIO SOMOS BANCOLOMBIA PRUEBAS CB OK SE DEJA OPERATIVO | T6: VISITA TECNICA | U6: FYZZZ187 | V6: TIPO IV | W6: TERRESTRE | X6: BERMUDEZ SANCHEZ JOSE NEYBER | Y6: 1 | Z6: 0 | AA6: 504833 | AB6: 504833
A7: NEIVA | B7: REMOTAS | C7: 0004-0007 | D7: 18150 | E7: TA-25-1157223 | F7: 3007081706 | G7: APERTURA | H7: CB CRECIMIENTO ALIANZA - NUEVO | I7: CAQUETA | J7: CARTAGENA DEL CHAIRA | K7: DISTRICOL ANGELA’S BOUTIQUE | L7: REDEBAN | M7: FO-25-1598635 | N7: 45929.795 | O7: 45933.487 | P7: AGREGADOR | Q7: DISTRICOL | R7: EJECUTADO | S7: 29/09/2025 29-09 PROGRAMACIÓN REALIZADA POR LA ALIANZA | 03/10/2025 SE REALIZA INSTALACIÓN DE DATÁFONO LECTORA BASE FUENTE DE PODER CABLE DE RED SE ENTREGAN 40 ROLLOS RBM SE INSTALA AVISO EXTERIOR Y PUBLICIDAD SE CAPACITA EN CB Y SOMOS BANCOLOMBIA TIENE CREADO EL USUARIO SOMOS BANCOLOMBIA PRUEBAS CB OK SE DEJA OPERATIVO | T7: VISITA TECNICA | U7: FYZZZ188 | V7: TIPO V | W7: TERRESTRE | X7: BERMUDEZ SANCHEZ JOSE NEYBER | Y7: 1 | Z7: 0 | AA7: 504833 | AB7: 504833
A8: PASTO | B8: SUROCCIDENTE Y EJE CAFETERO | C8: 0004-0003 | D8: 52227 | E8: TA-25-1157227 | F8: 3007081708 | G8: APERTURA | H8: CB CRECIMIENTO ALIANZA - NUEVO | I8: NARIÑO | J8: CUMBAL | K8: DISTRICOL MEGANET PANAN | L8: REDEBAN | M8: FO-25-1598652 | N8: 45929.694 | O8: 45931.655 | P8: AGREGADOR | Q8: DISTRICOL | R8: EJECUTADO | S8: 29/09/2025 29-09 PROGRAMACIÓN REALIZADA POR LA ALIANZA | 01/10/2025 SE REALIZÓ LA INSTALACIÓN DE EQUIPOS PUBLICIDAD Y ACCESORIOS PARA APERTURA CB BANCOLOMBIA SE DIO CAPACITACIÓN MANEJO DE DATÁFONO CB Y SOMOS BANCOLOMBIA SE EJECUTAN PRUEBAS TX EXITOSAS QUEDA OPERATIVO | T8: VISITA TECNICA | U8: FYZZZ191 | V8: TIPO III | W8: TERRESTRE | X8: REMICIO AMADO JOHN HEBER | Y8: 1 | Z8: 0 | AA8: 275729 | AB8: 275729
A9: CUCUTA | B9: SANTANDERES | C9: 0004-0008 | D9: 54498 | E9: TA-25-1157229 | F9: 3007081710 | G9: APERTURA | H9: CB CRECIMIENTO ALIANZA - NUEVO | I9: NORTE DE SANTANDER | J9: OCAÑA | K9: DISTRICOL MAXILIAM | L9: REDEBAN | M9: FO-25-1598662 | N9: 45929.29 | O9: 45932.68 | P9: AGREGADOR | Q9: DISTRICOL | R9: EJECUTADO | S9: 29/09/2025 29-09 PROGRAMACIÓN REALIZADA POR LA ALIANZA | 01/10/2025 SE COMUNICA CON LA CLIENTE SE PROGRAMA VISITA PARA MAÑANA POR DISPONIBILIDAD DEL CLIENTE, ZONA CATATUMBO. | 02/10/2025 SE VISITA COMERCIO, SE INSTALA DATAFONO, BASE, SCANNER, AVISO EXTERIOR, PUBLICIDAD DEL BANCO, SE CAPACITA PERSONAL, PRUEBAS Y CIERRES EXITOSO, CB OPERATIVO. | T9: VISITA TECNICA | U9: FYZZZ193 | V9: TIPO IV | W9: TERRESTRE | X9: NARANJO AFANADOR RUBEN JESUS | Y9: 1 | Z9: 0 | AA9: 504833 | AB9: 504833
A10: CUCUTA | B10: SANTANDERES | C10: 0004-0008 | D10: 54800 | E10: TA-25-1157231 | F10: 3007081714 | G10: APERTURA | H10: CB CRECIMIENTO ALIANZA - NUEVO | I10: NORTE DE SANTANDER | J10: TEORAMA | K10: DISTRICOL FABRICAMUEBLESVALENT | L10: REDEBAN | M10: FO-25-1598665 | N10: 45929.29 | O10: 45933.478 | P10: AGREGADOR | Q10: DISTRICOL | R10: EJECUTADO | S10: 29/09/2025 29-09 PROGRAMACIÓN REALIZADA POR LA ALIANZA | 06/10/2025 SE REALIZA APERTURA EN SITIO ACORDADA CON EL CLIENTE EN OCAÑA, SE INSTALA BATAFONO, VERSION, SE REALIZAN PRUEBAS EXITOSA, SE CAPACITA CLIENTE, PUBLICIDAD, CB OPERATIVO. | T10: VISITA TECNICA | U10: FYZZZ194 | V10: TIPO IV | W10: TERRESTRE | X10: NARANJO AFANADOR RUBEN JESUS | Y10: 1 | Z10: 0 | AA10: 504833 | AB10: 504833
A11: PASTO | B11: SUROCCIDENTE Y EJE CAFETERO | C11: 0004-0003 | D11: 86568 | E11: TA-25-1157240 | F11: 3007081713 | G11: APERTURA | H11: CB CRECIMIENTO ALIANZA - NUEVO | I11: PUTUMAYO | J11: PUERTO ASIS | K11: DISTRICOL FERRETERIA A/S S.A.S | L11: REDEBAN | M11: FO-25-1598692 | N11: 45929.618 | O11: 45932.38 | P11: AGREGADOR | Q11: DISTRICOL | R11: EJECUTADO | S11: 29/09/2025 29-09 PROGRAMACIÓN REALIZADA POR LA ALIANZA | 01/10/2025 NO SE HA PODIDO REALIZAR INSTALACIÓN DE PUBLICIDAD POR PROBLEMAS CLIMATICOS EN LA ZONA, LO CUAL RETRASO LA LABOR, Y EL COMERCIO CIERRA A LAS 17:30 HORAS, POR LO QUE NO SE PUEDE REALIZAR LA INSTALACIÓN EL DIA DE HOY | 02/10/2025 SE VISITO EL COMERCIO PARA DAR APERTURA AL CB, SE INSTALA DATAFONO CON LECTORA BASE Y MAGIC BOX, SE INSTALA PUBLICIDAD Y SE ENTREGA ROLLOS, SE CAPACITA OK, PRUEBAS OK EXCEPTO RECAUDO POR NO TENER ELEMENTOS PARA HACERLA, SOMOS BANCOLOMBIA OK, CB OPERATIVO | T11: VISITA TECNICA | U11: FYZZZ198 | V11: TIPO IV | W11: TERRESTRE | X11: GUERRERO RAMIREZ OSCAR DARIO | Y11: 1 | Z11: 0 | AA11: 504833 | AB11: 504833
A12: PASTO | B12: SUROCCIDENTE Y EJE CAFETERO | C12: 0004-0003 | D12: 52838 | E12: TA-25-1157243 | F12: 3007079019 | G12: APERTURA | H12: DATAFONO ADICIONAL - ALIANZA | I12: NARIÑO | J12: TUQUERRES | K12: PTM NARINO PORTIPLASTICO | L12: REDEBAN | M12: FO-25-1598697 | N12: 45929.622 | O12: 45931.662 | P12: AGREGADOR | Q12: COMCARD - PTM | R12: EJECUTADO | S12: 29/09/2025 29-09 PROGRAMACIÓN REALIZADA POR LA ALIANZA | 22/10/2025 SE REALIZA INSTALACIÓN DE DATAFONO ADICIONAL SE REALIZA PRUEBAS DE RETIRO, DEPOSITO, CONSULTA DE SALDO, NO SE PUEDE REALIZAR PRUEBAS DE OTRAS TRANSACCIONES YA QUE NO SE CUENTA CON RECURSOS PARA REALIZAR DEMÁS TRANSACCIONES CB QUEDA OPERATIVO COMERCIO INFORMA TENER TODA LA PUBLICIDAD DE CB | T12: VISITA TECNICA | U12: FYZZZ199 | V12: TIPO II | W12: TERRESTRE | X12: BRAVO MADROÑERO OSCAR ESTEBAN | Y12: 1 | Z12: 0 | AA12: 163814 | AB12: 163814
A13: MEDELLIN | B13: NOROCCIDENTE | C13: 0004-0005 | D13: 5001 | E13: TA-25-1165173 | F13: 3007081741 | G13: APERTURA | H13: CB CRECIMIENTO ALIANZA - NUEVO | I13: ANTIOQUIA | J13: MEDELLIN | K13: DISTRICOL DROGUERIA EL VERGEL | L13: REDEBAN | M13: FO-25-1611123 | N13: 45931.706 | O13: 45933.517 | P13: AGREGADOR | Q13: DISTRICOL | R13: EJECUTADO | S13: 01/10/2025 01-10 PROGRAMACIÓN REALIZADA POR LA ALIANZA | 03/10/2025 SE INSTALAN EQUIPOS OK | T13: VISITA TECNICA | U13: SUZZZ670 | V13: TIPO I | W13: TERRESTRE | X13: QUINTERO SANCHEZ JUAN SEBASTIAN | Y13: 1 | Z13: 0 | AA13: 75096 | AB13: 75096
... A181: BOGOTA | B181: CUNDINAMARCA | C181: 0004-0004 | D181: 11001 | E181: TA-25-1248010 | F181: 3007082028 | G181: APERTURA | H181: CB CRECIMIENTO ALIANZA - NUEVO | I181: CUNDINAMARCA | J181: BOGOTA | K181: DISTRICOL LUXUR | L181: REDEBAN | M181: FO-25-1751850 | N181: 45959.542 | O181: 45960.586 | P181: AGREGADOR | Q181: DISTRICOL | R181: EJECUTADO | S181: 29/10/2025 29-10 PROGRAMACIÓN REALIZADA POR LA ALIANZA| INSTALACIÓN PROGRAMADA PARA EL 2025-10-30 | 30/10/2025 INSTALACIÓN DE CORRESPONSAL OK PRUEBA OK CAPACITACIÓN SOMOS BANCOLOMBIA OK CAPACITACIÓN IVA OK CAPACITACIÓN DATAFONO OK NO SE REALIZAN PRUEBAS CON TARJETA YA QUE CLIENTE NO CUENTA CON TARJETA DE PRUEBA | T181: VISITA TECNICA | U181: CA002319 | V181: TIPO I | W181: TERRESTRE | X181: GOMEZ VEGA DAVID SNEYDER | Y181: 1 | Z181: 0 | AA181: 75096 | AB181: 75096
AB182: =SUM(AB2:AB181) -> 28693432

Sheet APERTURAS_BBVA
A1: CIUDAD SEDE | B1: ZONA | C1: CENTRO DE COSTOS LINEACOM | D1: CODIGO DANE | E1: TA/CODIGO ACTIVIDAD | F1: CODIGO CB | G1: ACTIVIDAD | H1: TIPO DE APERTURA | I1: DEPARTAMENTO | J1: CIUDAD | K1: NOMBRE DEL CB | L1: RED | M1: FO | N1: FECHA LISTA | O1: FECHA ULTIMA ACTUALIZACION | P1: CODIGO CIIU | Q1: BANCO | R1: ESTADO | S1: OBSERVACIONES CLIENTE | T1: FORMA DE ATENCION | U1: TERMINAL(ES) | V1: TIPIFICACION | W1: TIPO DE TRAYECTO | X1: NOMBRE DEL TECNICO | Y1: DIAS DE VISITA | Z1: DIA ADICIONAL | AA1: VALOR DIAS ACTIVIDAD FACTURABLES | AB1: VALOR TOTAL
A2: MEDELLIN | B2: NOROCCIDENTE | C2: 0004-0005 | D2: 5001 | E2: TA-25-1237761 | F2: 3013001502 | G2: APERTURA | I2: ANTIOQUIA | J2: MEDELLIN | K2: EXPOSICIONES | L2: BBVA | M2: FO-25-1730672 | N2: 45954.701 | O2: 45958.485 | R2: EJECUTADO | S2: 24/10/2025 24/10/2025 23-10 SE REALIZA LLAMADA AL CLIENTE, SE HABLA CON EL SR JUAN CASTAÑEDA SE VALIDA DIRECCIÓN OK, CANAL OK, DISPONIBILIDAD TOTA, LLAMAR EL DÍA LA INSTALACIÓN PARA CONFIRMAR VISITA | 28/10/2025 INSTALACIÓN EXITOSA SE ENTREGARON 20 ROLLOS | T2: VISITA TECNICA | U2: AE004031 | V2: TIPO I | W2: TERRESTRE | X2: CASTAÑEDA PALACIO CARLOS FELIPE | Y2: 1 | Z2: 0 | AA2: 75096 | AB2: =AA2*Y2 -> 75096
AB3: =SUM(AB2) -> 75096

Sheet INCIDENTES_BANCOLOMBIA
A1: CIUDAD SEDE | B1: ZONA | C1: CENTRO DE COSTOS LINEACOM | D1: CODIGO DANE | E1: TA/CODIGO ACTIVIDAD | F1: CODIGO CB | G1: ACTIVIDAD | H1: DEPARTAMENTO | I1: CIUDAD | J1: NOMBRE DEL CB | K1: RED | L1: FO | M1: FECHA ASIGNACION A LINEA COMUNICACIONES | N1: FECHA CIERRE DEL TICKET (DD/MM/AAAA HH:MM) | O1: ACOMETIDA | P1: GRUPO_FALLA | Q1: CATEGORIA | R1: FALLA | S1: FORMATO | T1: CADENA | U1: ESTADO | V1: OBSERVACION | W1: FORMA DE ATENCION | X1: TERMINAL(ES) | Y1: TIPIFICACION | Z1: TIPO DE TRAYECTO | AA1: NOMBRE DEL TECNICO | AB1: DIAS DE VISITA | AC1: DIA ADICIONAL | AD1: VALOR DIAS ACTIVIDAD FACTURABLES | AE1: VALOR TOTAL
A2: MEDELLIN | B2: NOROCCIDENTE | C2: 0004-0005 | D2: 27075 | E2: 2769787 | F2: 3007050373 | G2: INCIDENTE | H2: CHOCO | I2: BAHIA SOLANO | J2: BARRIO FILLO CASTRO BAHIA SOLA | K2: REDEBAN | L2: FO-25-1560569 | M2: 45920.643 | N2: 45932.56 | O2: NO | P2: HARDWARE | Q2: LECTOR DE TARJETAS | R2: DAÑO POS | S2: UNO A UNO | T2: CB UNO A UNO | U2: EJECUTADO | V2: 21/09/2025 SE ESCALA PARA VISITA. LLAMAR ANTES DE VISITAR, CONFIRMAR FALLA Y DATOS | 24/09/2025 NO SE HA LOGRADO CONSEGUIR VUELO IDONEO DEBIDO A TEMPORADA ALTA EN LA ZONA POR AVISTAMIENTO DE BALLENAS. CONTINUAMOS EN CONSULTA CON AEROLINEAS PARA CONSEGUIR VUELO. | 02/10/2025 SE CAMBIA EQUIPO POR DAÑO EN LECTOR CHIP | W2: VISITA TECNICA | X2: TR00D584 | Y2: TIPO V | Z2: AEREO | AA2: BADEL ACUÑA LUIS ALBERTO | AB2: 1 | AC2: 0 | AD2: 988463 | AE2: 988463
A3: PASTO | B3: SUROCCIDENTE Y EJE CAFETERO | C3: 0004-0003 | D3: 86320 | E3: 2790533 | F3: 3007060644 | G3: INCIDENTE | H3: PUTUMAYO | I3: ORITO | J3: DISTRICOL JPULIDO | K3: REDEBAN | L3: FO-25-1580246 | M3: 45924.74 | N3: 45932.567 | O3: NO | P3: HARDWARE | Q3: TECLADO | R3: DAÑO POS | S3: AGREGADOR | T3: DISTRICOL | U3: EJECUTADO | V3: 24/09/2025 SE ESCALA PARA VISITA. LLAMAR ANTES DE VISITAR, CONFIRMAR FALLA Y DATOS | 27/09/2025 NO SE PUEDE REALIZAR DESPLAZAMIENTO A LA ZONA POR PROBLEMAS EN LA VIA, DADO SE REQUIERE CAMBIO DE EQUIPO, SE REALIZARA VALIDACION PARA DESPLAZARNOS LA PROXIMA SEMANA. | 02/10/2025 SE VISITA CB. SE EVIDENCIA DATAFONO CON DETERIORO EN EL TECLADO, SE REALIZA CAMBIO DE EQUIPO. SE REALIZAN PRUEBAS TX EXITOSAS. QUEDA OPERATIVO | W3: VISITA TECNICA | X3: MA00C933 | Y3: TIPO IV | Z3: TERRESTRE | AA3: CASTILLO HERRERA ALEX RICARDO | AB3: 1 | AC3: 0 | AD3: 479589 | AE3: 479589
A4: VILLAVICENCIO | B4: REMOTAS | C4: 0004-0007 | D4: 95001 | E4: 2791700 | F4: 3007080059 | G4: INCIDENTE | H4: GUAVIARE | I4: SAN JOSE DEL GUAVIARE | J4: BARRIO EL PORVENIR SAN JOSE DEL GUAVIARE 4 | K4: REDEBAN | L4: FO-25-1581442 | M4: 45925.357 | N4: 45931.732 | O4: NO | P4: HARDWARE | Q4: IMPRESION | R4: NO AVANZA PAPEL | S4: UNO A UNO | T4: UNO A UNO | U4: EJECUTADO | V4: 25/09/2025 EN COMUNICACIÓN CON LA SRA MARY RESTREPO AL NÚMERO 3134977520 NOS INFORMA QUE LA FALLA ES CON LA IMPRESION, CONFIRMA DATOS E INDICA QUE LA RED ES REDEBAN, SE ESCALA PARA VISITA | 01/10/2025 SE REALIZA CAMBIO DE EQUIPO POR DAÑO EN ENGRANAJE DE ENTREGA OPERATIVO SIN NOVEDAD | W4: VISITA TECNICA | X4: SAXZZ468 | Y4: TIPO IV | Z4: TERRESTRE | AA4: ROZO JIMENEZ EDGAR ARMANDO | AB4: 1 | AC4: 0 | AD4: 479589 | AE4: 479589
A5: MEDELLIN | B5: NOROCCIDENTE | C5: 0004-0005 | D5: 5040 | E5: 2802931 | F5: 3007031338 | G5: INCIDENTE | H5: ANTIOQUIA | I5: ANORI | J5: BARRIO PARQUE 2 | K5: REDEBAN | L5: FO-25-1592836 | M5: 45927.453 | N5: 45931.343 | O5: NO | P5: HARDWARE | Q5: IMPRESION | R5: NO IMPRIME UNO O VARIOS CARACTERES | S5: CB UNO A UNO | T5: CB UNO A UNO | U5: EJECUTADO | V5: 27/09/2025 EN COMUNICACIÓN CON LA SRA MARIA DURLEY MEJIA TELÉFONO AL NÚMERO 3105209400 NOS INFORMA QUE LA FALLA ES CON LA IMPRESION, CONFIRMA DATOS E INDICA QUE LA RED ES REDEBAN, SE ESCALA PARA VISTA | 30/09/2025 SE REALIZA VISITA TÉCNICA EN RESPUESTA AL INCIDENTE REPORTADO CON EL DATÁFONO DEL CORRESPONSAL BANCOLOMBIA. EL USUARIO CONFIRMA SU IDENTIFICACIÓN Y PROCEDE A INFORMAR QUE EL EQUIPO ESTÁ GENERANDO VOUCHERS CON IMPRESIÓN BORROSA, OMITIENDO ALGUNOS CARACTERES. TRAS LA VALIDACIÓN DEL FUNCIONAMIENTO, SE IDENTIFICA DESGASTE EN EL RODILLO DE IMPRESIÓN. SE PROCEDE AL REEMPLAZO DEL COMPONENTE, DEJANDO EL DATÁFONO OPERATIVO Y CON IMPRESIÓN LEGIBLE. EL USUARIO VERIFICA Y CONFIRMA LA CORRECTA RESOLUCIÓN DEL INCONVENIENTE. | W5: VISITA TECNICA | X5: 11116372 | Y5: TIPO IV | Z5: TERRESTRE | AA5: MARTINEZ TOVAR OSCAR DAVID | AB5: 1 | AC5: 0 | AD5: 479589 | AE5: 479589
A6: APARTADO | B6: NOROCCIDENTE | C6: 0004-0005 | D6: 27615 | E6: 2802933 | F6: 3007076760 | G6: INCIDENTE | H6: CHOCO | I6: RIOSUCIO | J6: BARRIO ESCOBAR AL LADO DEL COL | K6: REDEBAN | L6: FO-25-1592828 | M6: 45927.454 | N6: 45931.416 | O6: NO | P6: SOFTWARE | Q6: LECTOR DE TARJETAS | R6: CTL CONFIGURACION LECTOR INTERNAL | S6: CB UNO A UNO | T6: CB UNO A UNO | U6: EJECUTADO | V6: 27/09/2025 EN COMUNICACIÓN CON EL SR LUIS FERNANDO ORTIZ TELÉFONO AL NÚMERO 3105142732 NOS INDICA QUE LA FALLA ES CON EL LECTOR DE TARJETAS, CONFIRMA DATOS E INDICA QUE LA RED ES REDEBAN, SE ESCALA PARA VISITA | 01/10/2025 SE REALIZA LIMPIEZA Y MANTENIMIENTO DEL EQUIPO Y LEE LAS TARJETAS PERFECTAMENTE, PRUEBAS EXITOSAS SERVICIO OPERATIVO OK | W6: VISITA TECNICA | X6: A48ZZ319 | Y6: TIPO V | Z6: TERRESTRE/FLUVIAL | AA6: ZAPATA LOPEZ EDWARD ASDRUBAL | AB6: 1 | AC6: 0 | AD6: 479589 | AE6: 479589
A7: CARTAGENA | B7: COSTA | C7: 0004-0001 | D7: 13430 | E7: 2803330 | F7: 3007016325 | G7: INCIDENTE | H7: BOLIVAR | I7: MAGANGUE | J7: ARRIO CENTRO MAGANGUE | K7: REDEBAN | L7: FO-25-1594667 | M7: 45927.644 | N7: 45931.598 | O7: NO | P7: HARDWARE | Q7: FLAS FULL | R7: MEMORIA DEL DISPOSITIVO INSUFICIENTE | S7: CB UNO A UNO | T7: CB UNO A UNO | U7: EJECUTADO | V7: 28/09/2025 SE ESCALA PARA VISITA. LLAMAR ANTES DE VISITAR, CONFIRMAR FALLA Y DATOS | 01/10/2025 SE VISITA COMERCIO POR FALLA, SE HACE BORRADO S.O Y SE CARGA NUEVAMENTE, SE DEJA CON LA VERSIÓN 9.90, SE INICIALIZA DATÁFONO, SE REALIZA PRUEBA OK. | W7: VISITA TECNICA | X7: ON004007 | Y7: TIPO IV | Z7: TERRESTRE | AA7: CACERES HERNANDEZ ANDRES | AB7: 1 | AC7: 0 | AD7: 479589 | AE7: 479589
A8: MEDELLIN | B8: NOROCCIDENTE | C8: 0004-0005 | D8: 5086 | E8: 2805048 | F8: 3007081138 | G8: INCIDENTE | H8: ANTIOQUIA | I8: BELMIRA | J8: BARRIO BELMIRA BELMIRA | K8: REDEBAN | L8: FO-25-1596229 | M8: 45929.351 | N8: 45931.328 | O8: NO | P8: SOFTWARE | Q8: LECTOR DE TARJETAS | R8: CTL CONFIGURACION LECTOR INTERNAL | S8: UNO A UNO | T8: UNO A UNO | U8: EJECUTADO | V8: 29/09/2025 SE ESCALA PARA VISITA. LLAMAR ANTES DE VISITAR, CONFIRMAR FALLA Y DATOS | 04/10/2025 SE RECONGIFURA EL EQUIPO NUEVAMENTE Y SE INICIALIZA NUEVAMENTE | W8: VISITA TECNICA | X8: SIZZZ882 | Y8: TIPO II | Z8: TERRESTRE | AA8: CARDONA MOLINA BROLIN STIVEN | AB8: 1 | AC8: 0 | AD8: 144968 | AE8: 144968
A9: NEIVA | B9: REMOTAS | C9: 0004-0007 | D9: 41349 | E9: 2807230 | F9: 3007031383 | G9: INCIDENTE | H9: HUILA | I9: HOBO | J9: BARRIO LOS PINOS | K9: REDEBAN | L9: FO-25-1607884 | FO-25-1598160 | M9: 45929.441 | N9: 45931.434 | O9: NO | P9: ENTIDAD | Q9: ERROR DE TRANSACCIONES | R9: TRANSACCION NO PERMITIDA | S9: CB UNO A UNO | T9: CB UNO A UNO | U9: EJECUTADO | EJECUTADO / CANCELADO | V9: 01/10/2025 SE REALIZA VISITA AL PUNTO NUEVAMENTE YA QUE ESTE HABIA QUEDADO EN RECHAZO GENERAL DESPUÉS DEL CAMBIO QUE SE REALIZO POR DAÑO, RG QUE NO SE PUDO GESTIONAR POR FALTA DE SOPORTE POR HORA . SE REALIZA GESTIÓN CON RBM SE INICIALIZA EQUIPO SE REALIZAN PRUEBAS EXITOSAS. SE DEJA EQUIPO CON VR 10.3 PRUEBAS CB OK . ***SE REALIZA LLAMADA A LA LÍNEA DEL BANCO 018000953344, LOS CUALES INDICAN QUE EL PUNTO SE ENCONTRABA BLOQUEADO POR RAZONES SE ASUNTOS INTERNOS, SE DESBLOQUEA PUNTO SE REALIZAN PRUEBAS PERO EN LA LÍNEA INDICAN QUE POSIBLEMENTE LO VOVERAN A BLOQUEAR. SE LE INDICA AL CLIENTE QUE SI ESTO OCURRE DEBE COMUNICACARSE DIRECTAMENTE A LA LÍNEA Y VALIDAR EL MOTIVO DEL BLOQEO . | W9: VISITA TECNICA | X9: BL01Y558 | Y9: TIPO II | Z9: TERRESTRE | AA9: DEVIA REINOSO JUAN CARLOS | AB9: 1 | AC9: 0 | AD9: 144968 | AE9: 144968
A10: YOPAL | B10: REMOTAS | C10: 0004-0007 | D10: 85230 | E10: 2807561 | F10: 3007073242 | G10: INCIDENTE | H10: CASANARE | I10: OROCUE | J10: DISTRICOL DROGAS OROCUE | K10: REDEBAN | L10: FO-25-1598133 | M10: 45929.461 | N10: 45931.728 | O10: NO | P10: SOFTWARE | Q10: LECTOR DE BARRAS | R10: LECTOR DESCONFIGURADO | S10: AGREGADOR | T10: DISTRICOL | U10: EJECUTADO | V10: 29/09/2025 SE ESCALA PARA VISITA. LLAMAR ANTES DE VISITAR, CONFIRMAR FALLA Y DATOS SE COMUNICA AL 3124832415 SE LE MARCA EN REPETIDAS OCACIONES PERO NO FUE POSIBLE LA COMUNICACION | 02/10/2025 SE VISITA COMERCIO, SE REALIZA CAMBIA DE LECTOR DE BARRAS. PRUEBAS OK. OPERATIVO EL SERVICIO | W10: VISITA TECNICA | X10: SV00T122 | Y10: TIPO V | Z10: TERRESTRE/FLUVIAL | AA10: BERNAL ELAICA EDGAR ALEXIS | AB10: 1 | AC10: 0 | AD10: 479589 | AE10: 479589
A11: MEDELLIN | B11: NOROCCIDENTE | C11: 0004-0005 | D11: 27245 | E11: 2807610 | F11: 3007060835 | G11: INCIDENTE | H11: CHOCO | I11: EL CARMEN DE ATRATO | J11: BARRIO EL SIETE EL CARMEN DE A | K11: REDEBAN | L11: FO-25-1598127 | M11: 45929.462 | N11: 45932.569 | O11: NO | P11: HARDWARE | Q11: ALERT IRRUPTION | R11: ALERT IRRUPTION | S11: CB UNO A UNO | T11: CB UNO A UNO | U11: EJECUTADO | V11: 29/09/2025 SE ESCALA PARA VISITA. SE COMUNICA JUAN ALEJO PARA REPORTAR QUE SU DATÁFONO SE LE QUEDÓ BLOQUEADO, SE LE QUEDÓ EN PANTALLA AZUL CON EL ERROR "ALERT INTERRUPTION LLAMAR ANTES DE VISITAR, CONFIRMAR FALLA Y DATOS | 02/10/2025 SE CAMBIA EQUIPO POR ALERTA INTERRUPTION TODO OK | W11: VISITA TECNICA | X11: FUA0G719 | Y11: TIPO IV | Z11: TERRESTRE | AA11: ALVAREZ ARENAS VICTOR HUGO | AB11: 1 | AC11: 0 | AD11: 479589 | AE11: 479589
A12: VALLEDUPAR | B12: COSTA | C12: 0004-0001 | D12: 20383 | E12: 2808585 | F12: 3007032450 | G12: INCIDENTE | H12: CESAR | I12: LA GLORIA | J12: BARRIO LA MATA LA GLORIA CESAR | K12: REDEBAN | L12: FO-25-1598871 | M12: 45929.527 | N12: 45931.419 | O12: NO | P12: HARDWARE | Q12: LECTOR DE TARJETAS | R12: DAÑO POS | S12: CB UNO A UNO | T12: CB UNO A UNO | U12: EJECUTADO | V12: 29/09/2025 SE ESCALA PARA VISITA. LLAMAR ANTES DE VISITAR, CONFIRMAR FALLA Y DATOS | 01/10/2025 BUENOS DÍAS SE VISITA CB Y SE VALIDA QUE EL DATAFONO NO LEE TARJETAS, SE PROCEDE A HACER EL CAMBIO Y TODO QUEDA OK SE HACEN PRUEBAS DE TRANSACCIONES | W12: VISITA TECNICA | X12: 11GZZ509 | Y12: TIPO IV | Z12: TERRESTRE | AA12: BENITEZ CARVAJAL ALVARO JAVIER | AB12: 1 | AC12: 0 | AD12: 479589 | AE12: 479589
A13: VALLEDUPAR | B13: COSTA | C13: 0004-0001 | D13: 13473 | E13: 2809305 | F13: 3007061347 | G13: INCIDENTE | H13: BOLIVAR | I13: MORALES | J13: BARRIO MINA GALLO MORALES | K13: REDEBAN | L13: FO-25-1599476 | M13: 45929.591 | N13: 45931.385 | O13: NO | P13: HARDWARE | Q13: COMUNICACION | R13: MENSAJE CABLE DE RED DESCONECTADO | S13: CB UNO A UNO | T13: CB UNO A UNO | U13: EJECUTADO | V13: 29/09/2025 SE ESCALA PARA VISITA. LLAMAR ANTES DE VISITAR, CONFIRMAR FALLA Y DATOS SE MARCA EN DIFERENTES OCACIONES A LOS N- DE CONTACTO PERO NO FUE POSIBLE LA COMUNICACION 3128020947 - 3148118261 | 01/10/2025 SE REALIZAN VARIOS INTENTOS DE PODER TENER COMUNICACIÓN CON LA SRA ANGELICA ARRIETA Y/O LEDYS RINCON A LOS NUMEROS DE CONTACTO 3128020947- 3148118261 PROPORCIONADOS EN LA ORDEN Y NO HA SIDO POSIBLE COMUNICARME CON ELLAS POR MEDIO DE WHATSAPP TAMBIEN SE HA TRATADO DE ESTABLECER COMUNICACIÓN Y TAMPOCO SE HA LOGRADO, PARA PODER SABER LAS INDICACIONES DE LA CLIENTE Y PODER LLEGAR AL SITIO YA QUE ES ZONA ROJA Y QUEDA DICHO SITIO BASTANTE RETIRADO | 01/10/2025 SE REALIZA VISITA AL CB, SE VALIDA Y EL CLIENTE COMENTA QUE EL DATÁFONO PIERDE CONSTANTEMENTE LA CONEXIÓN A INTERNET, SE HACEN PRUEBAS SONDE SE EVIDENCIO EL DAÑO, SE PROCEDE A HACER CAMBIO DEL EQUIPO, SE CONFIGURA Y SE HACEN PRUEBAS DEJANDO TODO OK | W13: VISITA TECNICA | X13: HA00J530 | Y13: TIPO IV | Z13: TERRESTRE | AA13: GONZALEZ ESTUPIÑAN YEISON WALTER ANTONIO | AB13: 1 | AC13: 0 | AD13: 479589 | AE13: 479589
A14: VILLAVICENCIO | B14: REMOTAS | C14: 0004-0007 | D14: 50318 | E14: 2810965 | F14: 3007053978 | G14: INCIDENTE | H14: META | I14: GUAMAL | J14: BARRIO FUNDADORES GUAMAL 2 | K14: REDEBAN | L14: FO-25-1600762 | M14: 45929.688 | N14: 45931.545 | O14: NO | P14: SOFTWARE | Q14: COMUNICACION | R14: VERIFIQUE PARAMETROS | S14: CB UNO A UNO | T14: CB UNO A UNO | U14: EJECUTADO | V14: 29/09/2025 SE ESCALA ACTIVIDAD PARA GESTION WOMPI | 01/10/2025 SE REALIZA AJUSTES SE VERIFICA PARÁMETROS SE ENTREGA OPERATIVO YA QUE PRECENTABA BLOQUEO | W14: VISITA TECNICA | X14: XP1ZZ999 | Y14: TIPO II | Z14: TERRESTRE | AA14: ROZO JIMENEZ EDGAR ARMANDO | AB14: 1 | AC14: 0 | AD14: 144968 | AE14: 144968
A15: CARTAGENA | B15: COSTA | C15: 0004-0001 | D15: 13657 | E15: 2812340 | F15: 3007038271 | G15: INCIDENTE | H15: BOLIVAR | I15: SAN JUAN NEPOMUCENO | J15: BARRIO LA TRONCAL SAN JUAN DE | K15: REDEBAN | L15: FO-25-1601504 | M15: 45930.333 | N15: 45931.62 | O15: NO | P15: HARDWARE | Q15: LECTOR DE TARJETAS | R15: MENSAJE RETIRE TARJETA | S15: CB UNO A UNO | T15: CB UNO A UNO | U15: EJECUTADO | V15: 30/09/2025 SE ESCALA PARA VISITA. LLAMAR ANTES DE VISITAR, CONFIRMAR FALLA Y DATOS | 01/10/2025 SE REALIZA VISITA TÉCNICA, SE CAMBIA EL DATAFONO, SE REALIZAN PRUEBAS EXITOSAS, EQUIPO FUNCIONA CORRECTAMENTE, CB QUEDA OPERATIVO. | W15: VISITA TECNICA | X15: AB00U639 | Y15: TIPO II | Z15: TERRESTRE | AA15: DE AGUAS MUÑOZ DAVID JOSE | AB15: 1 | AC15: 0 | AD15: 144968 | AE15: 144968
A16: BOGOTA | B16: CUNDINAMARCA | C16: 0004-0004 | D16: 25483 | E16: 2812525 | F16: 3007068889 | G16: INCIDENTE | H16: CUNDINAMARCA | I16: NARIÑO | J16: INMACULADA NARINO | K16: REDEBAN | L16: FO-25-1601513 | M16: 45930.333 | N16: 45931.438 | O16: NO | P16: HARDWARE | Q16: LECTOR DE BARRAS | R16: CABLE LECTORA AVERIADO | S16: CB UNO A UNO | T16: CB UNO A UNO | U16: EJECUTADO | V16: 30/09/2025 SE INTENTA COMUNICACIÓN CON LA SRA ADRIANA LUCÍA BERMUDEZ RAMÍREZ AL NÚMERO 3204940662 PARA CONFIRMAR DATOS Y FALLA PERO NO HAY CONTACTO, SE ESCALA AL COORDINADOR DE ZONA PARA VALIDAR EN SITIO | 01/10/2025 SE REALIZA VISITA DE CAMPO ENCONTRADO QUE LECTORA NO PRENDE, POR LO ANTERIOR SE REALIZA CAMBIO DE LECTORA PRUEBAS CUPO Y USUARIO OK. | W16: VISITA TECNICA | X16: AAJYZ123 | Y16: TIPO III | Z16: TERRESTRE | AA16: LOZADA ROJAS CHRISTIAN ANDRES | AB16: 1 | AC16: 0 | AD16: 275729 | AE16: 275729
A17: BUCARAMANGA | B17: SANTANDERES | C17: 0004-0008 | D17: 68235 | E17: 2812626 | F17: 3007066522 | G17: INCIDENTE | H17: SANTANDER | I17: EL CARMEN DE CHUCURI | J17: BARRIO EL CARMEN DE CHUCURI EL | K17: REDEBAN | L17: FO-25-1601956 | M17: 45930.347 | N17: 45931.622 | O17: NO | P17: HARDWARE | Q17: SE REINICIA | R17: DAÑO POS | S17: CB UNO A UNO | T17: CB UNO A UNO | U17: EJECUTADO | V17: 30/09/2025 SE ESCALA PARA VISITA. LLAMAR ANTES DE VISITAR, CONFIRMAR FALLA Y DATOS, SE CONTACTA CON LA SRA JENNY MAGALLY MIELES REPORTAR QUE EL DATAFONO NO ESTA FUNCIONANDO, REGISTRA ERROR DE CONEXION, CABLE TST DESCONECTADO 3102645047 8 : 40 | 01/10/2025 CB CON EQUIPO EN DAÑO, CAMBIO DE DATAFONO Y FUENTE, BORRADO E INYECCION DE SO +VER 9.90, CONFIGURACION CB OK, CUBRE CLAVE OK, PRUEBAS OK. | W17: VISITA TECNICA | X17: 4A00W942 | Y17: TIPO IV | Z17: TERRESTRE | AA17: SANTOS GONZALEZ JOHAN FABIAN | AB17: 1 | AC17: 0 | AD17: 479589 | AE17: 479589
A18: PASTO | B18: SUROCCIDENTE Y EJE CAFETERO | C18: 0004-0003 | D18: 52788 | E18: 2812696 | F18: 3007030800 | G18: INCIDENTE | H18: NARIÑO | I18: TANGUA | J18: BARRIO SAN RAFAEL | K18: REDEBAN | L18: FO-25-1602098 | M18: 45930.361 | N18: 45931.628 | O18: NO | P18: HARDWARE | Q18: COMUNICACION | R18: DAÑO POS | S18: CB UNO A UNO | T18: CB UNO A UNO | U18: EJECUTADO | V18: 30/09/2025 SE ESCALA PARA VISITA. LLAMAR ANTES DE VISITAR, CONFIRMAR FALLA Y DATOS | 01/10/2025 SE REALIZA CAMBIO DE DATAFONO POR DAÑO EN PUERTO DE INTERNET, SE RECONFIGURA OK PARÁMETROS OK Y SE REALIZAN PRUEBAS ÉXITOSAS DE TRANSACCIONES | W18: VISITA TECNICA | X18: BRZZZ268 | Y18: TIPO II | Z18: TERRESTRE | AA18: PAZ MARTINEZ RICHARD HUMBERTO | AB18: 1 | AC18: 0 | AD18: 144968 | AE18: 144968
A19: MEDELLIN | B19: NOROCCIDENTE | C19: 0004-0005 | D19: 5030 | E19: 2812900 | F19: 3007041623 | G19: INCIDENTE | H19: ANTIOQUIA | I19: AMAGA | J19: BARRIO MINAS AMAGA | K19: REDEBAN | L19: FO-25-1602091 | M19: 45930.363 | N19: 45931.625 | O19: NO | P19: HARDWARE | Q19: LECTOR DE TARJETAS | R19: DAÑO POS | S19: CB UNO A UNO | T19: CB UNO A UNO | U19: EJECUTADO | V19: 30/09/2025 SE ESCALA PARA VISITA. LLAMAR ANTES DE VISITAR, CONFIRMAR FALLA Y DATOS | 01/10/2025 SE REALIZA CAMBIO DE DATAFONO POR LECTOR DE TARJETAS MALO , RAYA LAS TARJETAS SE HACEN PRUEBAS OK | W19: VISITA TECNICA | X19: FUA0U710 | Y19: TIPO II | Z19: TERRESTRE | AA19: MONTOYA VELEZ ANDRES FELIPE | AB19: 1 | AC19: 0 | AD19: 144968 | AE19: 144968
A20: MEDELLIN | B20: NOROCCIDENTE | C20: 0004-0005 | D20: 5400 | E20: 2813256 | F20: 3007079629 | G20: INCIDENTE | H20: ANTIOQUIA | I20: LA UNION | J20: BARRIO EL EDEN LA UNION | K20: REDEBAN | L20: FO-25-1602346 | M20: 45930.387 | N20: 45931.501 | O20: NO | P20: HARDWARE | Q20: IMPRESION | R20: NO AVANZA PAPEL | S20: CB UNO A UNO | T20: CB UNO A UNO | U20: EJECUTADO | V20: 01/10/2025 CAMBIO EQUIPO POR DAÑO NO AVANZA PAPEL PRUEBAS OK NO TELECARGA | W20: VISITA TECNICA | X20: SXUZZ155 | Y20: TIPO II | Z20: TERRESTRE | AA20: PAREJA ECHAVARRIA JHON DAVID | AB20: 1 | AC20: 0 | AD20: 144968 | AE20: 144968
A21: CALI | B21: SUROCCIDENTE Y EJE CAFETERO | C21: 0004-0003 | D21: 76306 | E21: 2813273 | F21: 3007029986 | G21: INCIDENTE | H21: VALLE DEL CAUCA | I21: GINEBRA | J21: BARRIO GINEBRA GINEBRA | K21: REDEBAN | L21: FO-25-1602545 | M21: 45930.388 | N21: 45931.444 | O21: NO | P21: HARDWARE | Q21: CABLEADO | R21: CABLE MAGICBOX AVERIADO | S21: CB UNO A UNO | T21: CB UNO A UNO | U21: EJECUTADO | V21: 30/09/2025 SE ESCALA PARA VISITA. LLAMAR ANTES DE VISITAR, CONFIRMAR FALLA Y DATOS | 01/10/2025 EN LA VISITA TÉCNICA VISITA TÉCNICA SE REALIZÓ EL CAMBIO DE LA FUENTE DE PODER Y CABLE MAGIC BOX TETRA DESK 3500,YA QUE DICHO CABLE SE ENCONTRÓ AVERIADO,SE REALIZÓ LIMPIEZA A LA IMPRESORA Y SE AJUSTÓ EL RODILLO CORRECTAMENTE,EL SERVICIO QUEDÓ OPERATIVO SIN FALLAS Y SIN NOVEDAD. | W21: VISITA TECNICA | X21: BBJZZ206 | Y21: TIPO II | Z21: TERRESTRE | AA21: SANCHEZ URREGO ROBINSON DAVID | AB21: 1 | AC21: 0 | AD21: 144968 | AE21: 144968
... A38: BOGOTA | B38: CUNDINAMARCA | C38: 0004-0004 | D38: 25126 | E38: 2816002 | F38: 3007024381 | G38: INCIDENTE | H38: CUNDINAMARCA | I38: CAJICA | J38: MULTIPAGAS CAJICA | K38: REDEBAN | L38: FO-25-1605147 | M38: 45930.546 | N38: 45931.571 | O38: NO | P38: HARDWARE | Q38: HUB | R38: SE REINICIA | S38: ROBUSTO | T38: MULTIPAGAS | U38: EJECUTADO | V38: 30/09/2025 SE ESCALA PARA VISITA. LLAMAR ANTES DE VISITAR, CONFIRMAR FALLA Y DATOS | 01/10/2025 ME ENCUENTRO EN SITIO EN ESPERA DE INGRESO, SE ENCUENTRAN VALIDANDO IDENTIDAD DEL TÉCNICO | 01/10/2025 SE REALIZA VISITA DE CAMPO ENCONTRANDO QUE HUB REINICIA EL DATAFONO AL MOMENTO DE REALIZAR UNA TX SE CAMBIA HUB REALIZANDO PRUEBAS OK PARÁMETROS OKAY A CONFORMIDAD DE CORRESPONSAL SIN NOVEDAD EN INCIDENTE | W38: VISITA TECNICA | X38: ABCFZ919 | Y38: TIPO II | Z38: TERRESTRE | AA38: GALEANO SORIANO JUAN DAVID | AB38: 1 | AC38: 0 | AD38: 144968 | AE38: 144968
A39: VILLAVICENCIO | B39: REMOTAS | C39: 0004-0007 | D39: 50370 | E39: 2816008 | F39: 3007067482 | G39: INCIDENTE | H39: META | I39: URIBE | J39: BARRIO DIVISO ZONA RURAL URIBE | K39: REDEBAN | L39: FO-25-1605144 | M39: 45930.547 | N39: 45939.39 | P39: HARDWARE | Q39: CABLEADO | R39: CABLE MAGICBOX AVERIADO | S39: UNO A UNO | T39: CB UNO A UNO | V39: 30/09/2025 SE ESCALA PARA VISITA. LLAMAR ANTES DE VISITAR, CONFIRMAR FALLA Y DATOS | 06/10/2025 POR TEMAS DE ORDEN PÚBLICO EN LA ZONA, SE REALIZARA ENVÍO DE CABLES POR CARROS DE LA ZONA. AUTORIZADO POR YENNY GARZÓN | 07/10/2025 SE REALIZA CONTACTO TELEFÓNICO CON LA SEÑORA LILIANA Y SE LE INFORMA QUE LOS CABLES FUERON ENVIADOS POR EL MEDIO DE TRANSPORTE QUE NOS INFORMO. SE REALIZO CONTACTO CON LA SEÑORA LILIANA LA CUAL INFORMA QUE REALIZO EL CAMBIO DE CABLEADO Y QUEDO FUNCIONANDO OK | W39: SOPORTE TELEFONICO | Y39: TIPO V | Z39: AEREO | AA39: PEDREROS CONTRERAS MICHAEL STEVENS | AB39: 0 | AC39: 0 | AD39: 41241 | AE39: 41241
A40: BOGOTA | B40: CUNDINAMARCA | C40: 0004-0004 | D40: 11001 | E40: 2816020 | F40: 3007053507 | G40: INCIDENTE | H40: CUNDINAMARCA | I40: BOGOTA | J40: BARRIO CHUSACA BOGOTA | K40: REDEBAN | L40: FO-25-1605135 | M40: 45930.553 | N40: 45931.615 | O40: NO | P40: HARDWARE | Q40: LECTOR DE TARJETAS | R40: MENSAJE RETIRE TARJETA | S40: CB UNO A UNO | T40: CB UNO A UNO | U40: EJECUTADO | V40: 30/09/2025 SE ESCALA PARA VISITA. LLAMAR ANTES DE VISITAR, CONFIRMAR FALLA Y DATOS | 01/10/2025 11:45 DURANTE LA VISITA ES NECESARIO CAMBIAR EL EQUIPO YA QUE ES RECURRENTE LA FALLA, TÉCNICO CUENTA CON DOS EQUIPOS DE BACKUP DESK 2600 PERO NINGUNO CARGA INTERNET SE REALIZAN VARIAS PRENDAS DESCARTANDO MAGIC BOX, CABLES ETC PERO LA FALLA PERSISTE, INTERNET DEL CLIENTE OK SE PRUEBA CON OTROS DISPOSITIVOS TÉCNICO RECOGERÁ UN DATAFONO DESK 3500 PARA REALIZAR LAS PRUEBAS | 01/10/2025 SE REALIZA CAMBIO DE EQUIPO POR DAÑO RETIRE TARJETA CONSTANTE SERVICIO OPERATIVO PRUEBAS OK TRNA RBM CB CUENTA CON IP FIJA 10.35.201.60 PUERTA DE ENLACE TERMINADA EN 1, ANTES DE CULMINAR EL EQUIPO DE SISTEMAS REALIZARÁ CAMBIO DE ESTÁ IP PARA QUE QUEDE EN DHCP PIDEN ESPERAR MIENTRAS CONFIGURAN EL SWITCH 14:00 TÉCNICO INDICA QUE MÁXIMO PUEDE ESPERAR 20 MINUTOS | W40: VISITA TECNICA | X40: TR0VZ584 | Y40: TIPO I | Z40: TERRESTRE | AA40: BUSTOS MORA DIEGO MANUEL | AB40: 1 | AC40: 0 | AD40: 65960 | AE40: 65960
A41: MEDELLIN | B41: NOROCCIDENTE | C41: 0004-0005 | D41: 5001 | E41: 2816392 | F41: 3007017886 | G41: INCIDENTE | H41: ANTIOQUIA | I41: MEDELLIN | J41: ALKOMPRAR SAN DIEGO | K41: REDEBAN | L41: FO-25-1605638 | M41: 45930.601 | N41: 45931.464 | O41: NO | P41: HARDWARE | Q41: CABLEADO | R41: DAÑO POS | S41: RETAIL | T41: ALKOMPRAR | U41: EJECUTADO | V41: 30/09/2025 SE ESCALA PARA VISITA. LLAMAR ANTES DE VISITAR, CONFIRMAR FALLA Y DATOS | 01/10/2025 SE CAMBIA CABLE ENSORTIJADO YA QUE ESTA PARTIDO Y ESTABA CAUSANDO REINICIOS | W41: VISITA TECNICA | X41: JRZZZ853 | Y41: TIPO I | Z41: TERRESTRE | AA41: BADEL ACUÑA LUIS ALBERTO | AB41: 1 | AC41: 0 | AD41: 65960 | AE41: 65960
A42: CARTAGENA | B42: COSTA | C42: 0004-0001 | D42: 13838 | E42: 2816831 | F42: 3007035963 | G42: INCIDENTE | H42: BOLIVAR | I42: TURBANA | J42: BARRIO LOS NISPEROS TURBANA | K42: REDEBAN | L42: FO-25-1606014 | M42: 45930.62 | N42: 45932.609 | O42: NO | P42: HARDWARE | Q42: HUB | R42: SE REINICIA | S42: CB UNO A UNO | T42: CB UNO A UNO | U42: EJECUTADO | V42: 30/09/2025 SE ESCALA PARA VISITA. LLAMAR ANTES DE VISITAR, CONFIRMAR FALLA Y DATOS | 02/10/2025 EN SITIO ESPERANDO AUTORIZACIÓN DE INGRESO INFORMAN QUE LA PERSONA ENCARGADA NO SE ENCUENTRA PERO QUE LO VAN A LLAMAR PARA VALIDAR LA NOVEDAD | 02/10/2025 SE CAMBIA HUB POR REINICIOS Y SE CAMBIA FUENTE DE PODER POR CABLE DEGOLLADO SE PRUEBA Y TODO QUEDA OK | W42: VISITA TECNICA | X42: GZ006904 | Y42: TIPO II | Z42: TERRESTRE | AA42: MARTINEZ SALGUEDO ANDRES AUGUSTO | AB42: 1 | AC42: 0 | AD42: 144968 | AE42: 144968
A43: APARTADO | B43: NOROCCIDENTE | C43: 0004-0005 | D43: 5045 | E43: 2817082 | F43: 3007081497 | G43: INCIDENTE | H43: ANTIOQUIA | I43: APARTADO | J43: DISTRICOL FERROUNO | K43: REDEBAN | L43: FO-25-1606216 | M43: 45930.633 | N43: 45931.617 | O43: NO | P43: SOFTWARE | Q43: ERROR DE TRANSACCIONES | R43: RECHAZO GENERAL | S43: AGREGADOR | T43: DISTRICOL | U43: EJECUTADO | V43: 30/09/2025 SE ESCALA ACTIVIDAD PARA GESTION WOMPI | 01/10/2025 DATAFONO PIERDE COMUNICACIÓN SE VERIFICA PARÁMETROS Y CONFIGURACIÓN DESAPARECIÓ, SE PREINSTALA Y SE REINICIALIZA. DATAFONO QUEDA OPERATIVO | W43: VISITA TECNICA | X43: FSZZZ896 | Y43: TIPO I | Z43: TERRESTRE | AA43: CASTRO HENAO DANIEL ESTEBAN | AB43: 1 | AC43: 0 | AD43: 65960 | AE43: 65960
A44: VALLEDUPAR | B44: COSTA | C44: 0004-0001 | D44: 44378 | E44: 2817274 | F44: 3007034454 | G44: INCIDENTE | H44: LA GUAJIRA | I44: HATONUEVO | J44: BARRIO CENTRO HATONUEVO 1 | K44: REDEBAN | L44: FO-25-1606537 | M44: 45930.652 | N44: 45932.572 | O44: NO | P44: HARDWARE | Q44: LECTOR DE BARRAS | R44: CABLE LECTORA AVERIADO | S44: CB UNO A UNO | T44: CB UNO A UNO | U44: EJECUTADO | V44: 30/09/2025 SE ESCALA PARA VISITA. LLAMAR ANTES DE VISITAR, CONFIRMAR FALLA Y DATOS, SE REALIZAN 3 INTENTOS DE LLAMADA AL NUMERO DE CONTACTO 3157435907 PERO NO FUE POSIBLE LA COMUNICACION | 02/10/2025 SE REALIZA CAMBIO DE LECTOR, YA QUE EL LECTOR DEL CLIENTE TENIA EL CABLE AVERIADO, SE REALIZAN PRUEBAS DEJANDO SERVICIO FUNCIONAL AL 100 % | W44: VISITA TECNICA | X44: NN001067 - A1KZZ149 | Y44: TIPO III | Z44: TERRESTRE | AA44: MONTES DIAZ JOHN FRED | AB44: 1 | AC44: 0 | AD44: 275729 | AE44: 275729
A45: MONTERIA | B45: COSTA | C45: 0004-0001 | D45: 23807 | E45: 2817279 | F45: 3007080411 | G45: INCIDENTE | H45: CORDOBA | I45: TIERRALTA | J45: BARRIO EL PRADO TIERRALTA 3 | K45: REDEBAN | L45: FO-25-1606531 | M45: 45930.654 | N45: 45931.643 | O45: NO | P45: HARDWARE | Q45: IMPRESION | R45: DAÑO POS | S45: UNO A UNO | T45: UNO A UNO | U45: EJECUTADO | V45: 30/09/2025 SE ESCALA PARA VISITA. LLAMAR ANTES DE VISITAR, CONFIRMAR FALLA Y DATOS, SE REALIZAN 3 INTENTOS DE LLAMADA AL NUMERO DE CONTACTO 3222779180 PERO NO FUE POSIBLE LA COMUNICACION | 01/10/2025 SE VISITA SITIO, SE CAMBIA DATAFONO POR DAÑO EN IMPRESORA, NO AVANZA PAPEL, SE REALIZAN PRUEBAS EXITOSAS OK | W45: VISITA TECNICA | X45: LBZZZ669 | Y45: TIPO III | Z45: TERRESTRE | AA45: COGOLLO VERTEL EDER LUIS | AB45: 1 | AC45: 0 | AD45: 275729 | AE45: 275729
A46: BUCARAMANGA | B46: SANTANDERES | C46: 0004-0008 | D46: 68655 | E46: 2817585 | F46: 3007064502 | G46: INCIDENTE | H46: SANTANDER | I46: SABANA DE TORRES | J46: PMT SABANA DE TORRES FERRETAL | K46: REDEBAN | L46: FO-25-1606772 | M46: 45930.672 | N46: 45931.495 | O46: NO | P46: HARDWARE | Q46: LECTOR DE BARRAS | R46: CABLE LECTORA AVERIADO | S46: AGREGADOR | T46: COMCARD - PTM | U46: EJECUTADO | V46: 30/09/2025 SE ESCALA PARA VISITA. LLAMAR ANTES DE VISITAR, CONFIRMAR FALLA Y DATOS, SE REALIZA 3 INTENTOS DE LLAMADAS AL CONTACTO 3164418359 PERO NOFUE POSIBLE LA COMUNICACION | 01/10/2025 SE REALIZA CAMBIO DE LECTOR DE BARRAS POR CABLE AVERIADO. PRUEBAS Y LIMPIEZA DE EQUIPOS OK | W46: VISITA TECNICA | X46: 1A003458 | Y46: TIPO III | Z46: TERRESTRE | AA46: MARTINEZ FLOREZ DONIS ALBERTO | AB46: 1 | AC46: 0 | AD46: 275729 | AE46: 275729
A47: BOGOTA | B47: CUNDINAMARCA | C47: 0004-0004 | D47: 25290 | E47: 2817738 | F47: 3007063003 | G47: INCIDENTE | H47: CUNDINAMARCA | I47: FUSAGASUGA | J47: BARRIO SAN FERNANDO FUSAGASUGA | K47: REDEBAN | L47: FO-25-1606765 | M47: 45930.673 | N47: 45931.608 | O47: NO | P47: HARDWARE | Q47: SE REINICIA | R47: DAÑO POS | S47: CB UNO A UNO | T47: CB UNO A UNO | U47: EJECUTADO | V47: 30/09/2025 SE ESCALA PARA VISITA. LLAMAR ANTES DE VISITAR, CONFIRMAR FALLA Y DATOS | 01/10/2025 CAMBIO DE MAGIC BOX SE REALIZA ACTUALIZACIÓN SE ENTREGA SERVICIO OPERATIVO | W47: VISITA TECNICA | X47: SXOZZ718 | Y47: TIPO II | Z47: TERRESTRE | AA47: HERNANDEZ NARANJO OSCAR EDUARDO | AB47: 1 | AC47: 0 | AD47: 144968 | AE47: 144968
A48: BOGOTA | B48: CUNDINAMARCA | C48: 0004-0004 | D48: 25286 | E48: 2817773 | F48: 3007081076 | G48: INCIDENTE | H48: CUNDINAMARCA | I48: FUNZA | J48: BARRIO PADRE FUNZA FUNZA | K48: REDEBAN | L48: FO-25-1606753 | M48: 45930.678 | N48: 45932.574 | O48: NO | P48: HARDWARE | Q48: IMPRESION | R48: NO AVANZA PAPEL | S48: UNO A UNO | T48: UNO A UNO | U48: EJECUTADO | V48: 30/09/2025 SE ESCALA PARA VISITA. LLAMAR ANTES DE VISITAR, CONFIRMAR FALLA Y DATOS | 02/10/2025 SE REALIZA LLEGA A COMERCIO EN EL CUAL INFORMAN QUE EN EL MOMENTO NO TIENEN SERVICIO DE INTERNET PERO QUE EL DATAFONO YA SE ENCUENTRA FUNCIONANDO EN PERFECTAS CONDICIONES SE REALIZAR IMPRESIONES DE VERSIÓN. OK | W48: VISITA TECNICA | X48: SHZZZ002 | Y48: TIPO II | Z48: TERRESTRE | AA48: ORTIZ MARTINEZ STIVEN | AB48: 1 | AC48: 0 | AD48: 144968 | AE48: 144968
A49: BOGOTA | B49: CUNDINAMARCA | C49: 0004-0004 | D49: 11001 | E49: 2817810 | F49: 3007055704 | G49: INCIDENTE | H49: CUNDINAMARCA | I49: BOGOTA | J49: PTM BOGOTA TIENDA Y MISCELANEA | K49: REDEBAN | L49: FO-25-1606756 | M49: 45930.676 | N49: 45931.592 | O49: NO | P49: HARDWARE | Q49: DETERIORO | R49: DATAFONO | S49: AGREGADOR | T49: COMCARD - PTM | U49: EJECUTADO | V49: 30/09/2025 SE ESCALA PARA VISITA. LLAMAR ANTES DE VISITAR, CONFIRMAR FALLA Y DATOS | 01/10/2025 SE LLEGA A LA DIRECCIÓN INDICADA Y SE REALIZA CAMBIO DE DATAFONO POR DETERIORO Y FALLO EN IMPRESORA, VERSIONAMIENTO Y CONFIGURACIÓN OK, USUARIO OK , CUPO OK, SE REALIZAN PRUEBAS EXITOSAS | W49: VISITA TECNICA | X49: IIGZZ984 - TRDZZ663 | Y49: TIPO I | Z49: TERRESTRE | AA49: GARCIA PASTRANA KEVIN FERNANDO | AB49: 1 | AC49: 0 | AD49: 65960 | AE49: 65960
A50: CALI | B50: SUROCCIDENTE Y EJE CAFETERO | C50: 0004-0003 | D50: 76001 | E50: 2817919 | F50: 3007076951 | G50: INCIDENTE | H50: VALLE DEL CAUCA | I50: CALI | J50: BARRIO CENTRAL CALI | K50: REDEBAN | L50: FO-25-1610814 | FO-25-1606780 | M50: 45930.682 | N50: 45933.439 | O50: NO | P50: HARDWARE | Q50: COMUNICACION | R50: MENSAJE CABLE DE RED DESCONECTADO | S50: CB UNO A UNO | T50: CB UNO A UNO | U50: EJECUTADO | EJECUTADO / CANCELADO | V50: 03/10/2025 SE REALIZA CAMBIO DE EQUIPO E6 PUERTO IP MALO, CB BANCOLOMBIA PURO, PRUEBAS OK | W50: VISITA TECNICA | X50: A18ZZ388 | Y50: TIPO I | Z50: TERRESTRE | AA50: PAREDES CASTILLO DIEGO | AB50: 2 | AC50: 0 | AD50: 131920 | AE50: 131920
A51: IBAGUE | B51: REMOTAS | C51: 0004-0007 | D51: 73001 | E51: 2818398 | F51: 3007065322 | G51: INCIDENTE | H51: TOLIMA | I51: IBAGUE | J51: BARRIO GALAN IBAGUE 1 | K51: REDEBAN | L51: FO-25-1607152 | M51: 45930.733 | N51: 45931.449 | O51: NO | P51: HARDWARE | Q51: ALERT IRRUPTION | R51: ALERT IRRUPTION | S51: CB UNO A UNO | T51: CB UNO A UNO | U51: EJECUTADO | V51: 30/09/2025 SE ESCALA PARA VISITA. LLAMAR ANTES DE VISITAR, CONFIRMAR FALLA Y DATOS | 01/10/2025 SE REALIZA CAMBIO DE EQUIPO POR DAÑO, SE REALIZA PRUEBAS DE FUNCIONAMIENTO OK; CUBRE CLAVE INSTALADO. | W51: VISITA TECNICA | X51: 4A005663 | Y51: TIPO I | Z51: TERRESTRE | AA51: BARRAGAN TAFUR EDWIN ESTEBAN | AB51: 1 | AC51: 0 | AD51: 65960 | AE51: 65960
... A54: CALI | B54: SUROCCIDENTE Y EJE CAFETERO | C54: 0004-0003 | D54: 19075 | E54: 2818692 | F54: 3007062988 | G54: INCIDENTE | H54: CAUCA | I54: BALBOA | J54: BARRIO LA LOMITA BALBOA | K54: REDEBAN | L54: FO-25-1608429 | M54: 45931.333 | N54: 45933.65 | O54: NO | P54: HARDWARE | Q54: ALERT IRRUPTION | R54: ALERT IRRUPTION | S54: CB UNO A UNO | T54: CB UNO A UNO | U54: EJECUTADO | V54: 01/10/2025 SE REALIZA 3 INTENTOS DE LLAMADA AL NUMERO DE CONTACTO 3103215073 PERO NO FUE POSIBLE LA COMUNICACION | 03/10/2025 SE INGRESA EQUIPO CON ALERTINTERRUPTION SE PROCEDE A CAMBIAR EQUIPO SE HACEN PRUEBAS OK TELECARGA DRNA | W54: VISITA TECNICA | X54: CZZZZ704 | Y54: TIPO IV | Z54: TERRESTRE | AA54: GIMBUEL LASSO LUIS GERMAN | AB54: 1 | AC54: 0 | AD54: 479589 | AE54: 479589
A55: MONTERIA | B55: COSTA | C55: 0004-0001 | D55: 23162 | E55: 2818693 | F55: 3007058775 | G55: INCIDENTE | H55: CORDOBA | I55: CERETE | J55: ARA0873 CERETE VENUS | K55: REDEBAN | L55: FO-25-1608794 | M55: 45931.333 | N55: 45931.992 | P55: HARDWARE | Q55: SE REINICIA | R55: DAÑO POS | S55: RETAIL | T55: TIENDAS ARA | V55: 01/10/2025 SE ESCALA CASO ARA A LA RED** TU SOLICITUD REFERENTE A GENERACIÓN DE CASOS CB ARA BANCOLOMBIA QUEDÓ RADICADA BAJO EL TICKET NÚMERO 5821571 AL ÁREA ENCARGADA. | 01/10/2025 SE ESCALA CASO ARA A LA RED** TU SOLICITUD REFERENTE A GENERACIÓN DE CASOS CB ARA BANCOLOMBIA QUEDÓ RADICADA BAJO EL TICKET NÚMERO 5821571 AL ÁREA ENCARGADA. | 01/10/2025 SE ESCALA CASO ARA A LA RED** TU SOLICITUD REFERENTE A GENERACIÓN DE CASOS CB ARA BANCOLOMBIA QUEDÓ RADICADA BAJO EL TICKET NÚMERO 5821571 AL ÁREA ENCARGADA. | 01/10/2025 SE ESCALA CASO ARA A LA RED** TU SOLICITUD REFERENTE A GENERACIÓN DE CASOS CB ARA BANCOLOMBIA QUEDÓ RADICADA BAJO EL TICKET NÚMERO 5821571 AL ÁREA ENCARGADA. | W55: SOPORTE TELEFONICO | Y55: TIPO I | Z55: TERRESTRE | AA55: DIAZ ACOSTA MARIA ISABEL | AB55: 0 | AC55: 0 | AD55: 41241 | AE55: 41241
A56: CALI | B56: SUROCCIDENTE Y EJE CAFETERO | C56: 0004-0003 | D56: 19022 | E56: 2818857 | F56: 3007037307 | G56: INCIDENTE | H56: CAUCA | I56: ALMAGUER | J56: BARRIO SAN FRANCISCO ALMAGUER | K56: REDEBAN | L56: FO-25-1608408 | M56: 45931.333 | N56: 45932.576 | P56: HARDWARE | Q56: COMUNICACION | R56: MENSAJE CABLE DE RED DESCONECTADO | S56: UNO A UNO | T56: CB UNO A UNO | V56: 01/10/2025 SE ESCALA PARA VISITA. LLAMAR ANTES DE VISITAR, CONFIRMAR FALLA Y DATOS, SE REALIZA 3 INTENTOS DE LLAMADA AL NUMERO DE CONTACTO 3147008853 PERO NO FUE POSIBLE LA COMUNICACION | 02/10/2025 SE REALIZA LLAMADA CELULAR CON LA SEÑORA ALBA INFORMA YA TIENE CONEXION A INTERNET OK EL DATOFONO | W56: SOPORTE TELEFONICO | Y56: TIPO IV | Z56: TERRESTRE | AA56: GIMBUEL LASSO LUIS GERMAN | AB56: 0 | AC56: 0 | AD56: 41241 | AE56: 41241
A57: CALI | B57: SUROCCIDENTE Y EJE CAFETERO | C57: 0004-0003 | D57: 19001 | E57: 2819731 | F57: 3007030339 | G57: INCIDENTE | H57: CAUCA | I57: POPAYAN | J57: BARRIO SAN EDUARDO POPAYAN | K57: REDEBAN | L57: FO-25-1608474 | M57: 45931.35 | N57: 45932.744 | O57: NO | P57: HARDWARE | Q57: PINPAD | R57: DAÑO POS | S57: CB UNO A UNO | T57: CB UNO A UNO | U57: EJECUTADO | V57: 01/10/2025 SE REALIZA 3 INTENTOS DE LLAMADA AL NUMERO DE CONTACTO 3105396586 PERO NO FUE POSIBLE LA COMUNICACION 3105396586 | 02/10/2025 SE INGRESA EQUIPO PIN PAD CON LECTOR CHIP TARJETAS NO LEE TARJETAS SE PROCEDE HACER LIMPIEZA A LECTOR CHIP SE HACEN PRUEBAS OK TELECARGA DRNA | W57: VISITA TECNICA | X57: AB000272 | Y57: TIPO III | Z57: TERRESTRE | AA57: GIMBUEL LASSO LUIS GERMAN | AB57: 1 | AC57: 0 | AD57: 275729 | AE57: 275729
A58: IBAGUE | B58: REMOTAS | C58: 0004-0007 | D58: 73168 | E58: 2820041 | F58: 3007032030 | G58: INCIDENTE | H58: TOLIMA | I58: CHAPARRAL | J58: BARRIO PRIMERO DE MAYO CHAPARR | K58: REDEBAN | L58: FO-25-1609233 | M58: 45931.365 | N58: 45932.603 | O58: NO | P58: SOFTWARE | Q58: COMUNICACION | R58: VERIFIQUE PARAMETROS | S58: CB UNO A UNO | T58: CB UNO A UNO | U58: EJECUTADO | V58: 01/10/2025 SE ESCALA PARA VISITA. LLAMAR ANTES DE VISITAR, CONFIRMAR FALLA Y DATOS,SE MARACA EN REPETIDAS OCACIONES AL NUMERO DEL CONTACTO 3134243169 PERO NO FUE POSIBLE LA COMUNICACION | 02/10/2025 SE CAMBIA DATÁFONO POR FALLA DE COMUNICACIÓN CONSTANTE. SE HACEN PRUEBAS DE TRANSACCIONES TODO OK | W58: VISITA TECNICA | X58: A16ZZ720 | Y58: TIPO III | Z58: TERRESTRE | AA58: VARGAS HERRERA JHON JAIRO | AB58: 1 | AC58: 0 | AD58: 275729 | AE58: 275729
A59: MEDELLIN | B59: NOROCCIDENTE | C59: 0004-0005 | D59: 5607 | E59: 2820848 | F59: 3007057197 | G59: INCIDENTE | H59: ANTIOQUIA | I59: RETIRO | J59: BARRIO VEREDA DON DIEGO RETIRO | K59: REDEBAN | L59: FO-25-1609199 | M59: 45931.405 | N59: 45933.467 | O59: NO | P59: SOFTWARE | Q59: LECTOR DE TARJETAS | R59: CTL CONFIGURACION LECTOR INTERNAL | S59: CB UNO A UNO | T59: CB UNO A UNO | U59: EJECUTADO | V59: 01/10/2025 SE ESCALA PARA VISITA. LLAMAR ANTES DE VISITAR, CONFIRMAR FALLA Y DATOS | 03/10/2025 NO SE LOGRA LLEGAR A TIEMPO YA QUE SE TIENE REUNIÓN DE GH EN HORAS DE LA MAÑANA. INCIDENTE VENCE 9.43AM. | 03/10/2025 SE REALIZA LA CONFIGURACIÓN DE LECTOR DE BARRAS DE HACEN PRUEBAS OK | W59: VISITA TECNICA | X59: TRSZZ764 | Y59: TIPO II | Z59: TERRESTRE | AA59: MONTOYA VELEZ ANDRES FELIPE | AB59: 1 | AC59: 0 | AD59: 144968 | AE59: 144968
A60: MEDELLIN | B60: NOROCCIDENTE | C60: 0004-0005 | D60: 5001 | E60: 2821453 | F60: 3007032505 | G60: INCIDENTE | H60: ANTIOQUIA | I60: MEDELLIN | J60: COMCARD MED RED LUZ EDY | K60: REDEBAN | L60: FO-25-1609458 | M60: 45931.431 | N60: 45931.953 | O60: NO | P60: SOFTWARE | Q60: COMUNICACION | R60: PARAMETROS DE CONFIGURACION EN POS | S60: AGREGADOR | T60: COMCARD - PTM | U60: EJECUTADO | V60: 01/10/2025 SE ESCALA PARA VISITA. LLAMAR ANTES DE VISITAR, CONFIRMAR FALLA Y DATOS | 01/10/2025 SE REMARCAN PARÁMETROS Y SE BORRA REV. | W60: VISITA TECNICA | X60: 11KZZ075 | Y60: TIPO I | Z60: TERRESTRE | AA60: MARIN PIEDRAHITA JIMMY ALEXIS | AB60: 1 | AC60: 0 | AD60: 65960 | AE60: 65960
A61: CUCUTA | B61: SANTANDERES | C61: 0004-0008 | D61: 54003 | E61: 2821546 | F61: 3007066094 | G61: INCIDENTE | H61: NORTE DE SANTANDER | I61: ABREGO | J61: BARRIO VEREDA LA LABRANZA ABRE | K61: REDEBAN | L61: FO-25-1609451 | M61: 45931.437 | N61: 45933.497 | O61: NO | P61: HARDWARE | Q61: COMUNICACION | R61: DAÑO POS | S61: UNO A UNO | T61: CB UNO A UNO | U61: EJECUTADO | V61: 01/10/2025 SE ESCALA PARA VISITA. LLAMAR ANTES DE VISITAR, CONFIRMAR FALLA Y DATOS ,SE COMUNICA CON LA SRA NEREYDA ORTIZ GARCIA 3107925159 REPORTAR QUE EL DATAFONO NO LE ESTA RECIBIENDO EL INTERNET, REGISTRA ERROR DE CONEXION, LA RED DE INTERNET 10: 41 AM | 03/10/2025 SE VISITA COMERCIO, SE REALIZA CAMBIO DE DATAFONO POR DAÑO DE PUERTO ETHERNET , SE HACEN PRUEBAS OK, CB OPERATIVO. | W61: VISITA TECNICA | X61: 7A00K556 | Y61: TIPO III | Z61: TERRESTRE | AA61: NARANJO AFANADOR RUBEN JESUS | AB61: 1 | AC61: 0 | AD61: 275729 | AE61: 275729
A62: BARRANQUILLA | B62: COSTA | C62: 0004-0001 | D62: 8296 | E62: 2821759 | F62: 3007047534 | G62: INCIDENTE | H62: ATLANTICO | I62: GALAPA | J62: BARRIO GALAPA GALAPA 1 | K62: REDEBAN | L62: FO-25-1609701 | M62: 45931.448 | N62: 45932.42 | O62: NO | P62: HARDWARE | Q62: PINPAD | R62: ALERTADO | S62: CB UNO A UNO | T62: CB UNO A UNO | U62: EJECUTADO | V62: 01/10/2025 SE ESCALA PARA VISITA. LLAMAR ANTES DE VISITAR, CONFIRMAR FALLA Y DATOS | 02/10/2025 SE REMPLAZA PIN PAN, ESTABA ALERT INTERRUPCIÓN | W62: VISITA TECNICA | X62: GB00H063 | Y62: TIPO I | Z62: TERRESTRE | AA62: DE AVILA SIADES ALBERTO ENRIQUE | AB62: 1 | AC62: 0 | AD62: 65960 | AE62: 65960
A63: MEDELLIN | B63: NOROCCIDENTE | C63: 0004-0005 | D63: 5308 | E63: 2821793 | F63: 3007034272 | G63: INCIDENTE | H63: ANTIOQUIA | I63: GIRARDOTA | J63: BARRIO AUTOPISTA NORTE GIRARDO | K63: REDEBAN | L63: FO-25-1609697 | M63: 45931.456 | N63: 45931.958 | O63: NO | P63: SOFTWARE | Q63: COMUNICACION | R63: PARAMETROS DE CONFIGURACION EN POS | S63: UNO A UNO | T63: CB UNO A UNO | U63: EJECUTADO | V63: 01/10/2025 SE ESCALA PARA VISITA. LLAMAR ANTES DE VISITAR, CONFIRMAR FALLA Y DATOS | 01/10/2025 SE BORRA APLICATIVO Y SE RECONFIGURA NUEVAMENTE, ADICIONAL SE INICIALIZA NUEVAMENTE. | W63: VISITA TECNICA | X63: 1ZZZZ812 | Y63: TIPO I | Z63: TERRESTRE | AA63: RAMIREZ TABARES JUAN DIEGO | AB63: 1 | AC63: 0 | AD63: 65960 | AE63: 65960
A64: MONTERIA | B64: COSTA | C64: 0004-0001 | D64: 5250 | E64: 2821822 | F64: 3007070808 | G64: INCIDENTE | H64: ANTIOQUIA | I64: EL BAGRE | J64: BARRIO LA VICTORIA EL BAGRE 1 | K64: REDEBAN | L64: FO-25-1609716 | M64: 45931.447 | N64: 45933.47 | O64: NO | P64: HARDWARE | Q64: LECTOR DE BARRAS | R64: DAÑO POS | S64: CB UNO A UNO | T64: CB UNO A UNO | U64: EJECUTADO | V64: 01/10/2025 SE ESCALA PARA VISITA. LLAMAR ANTES DE VISITAR, CONFIRMAR FALLA Y DATOS, SE COMUNICA CON LA SRA DERLYS 3135565423 CR 48 58A 55 LC 1 REPORTAR QUE E LECTOR DE BARRAS NO ESTA LEYENDO NINGUNA FACTURA, SALE TRANSACCIÓN INVALIDA | 03/10/2025 SE REALIZÓ CAMBIO DE LECTOR DE CÓDIGO DE BARRAS OK, PRUEBAS OK, TELECARGA DRNA. | W64: VISITA TECNICA | X64: EF00B338 | Y64: TIPO IV | Z64: TERRESTRE | AA64: CALDERA SALCEDO CARLOS JULIO | AB64: 1 | AC64: 0 | AD64: 479589 | AE64: 479589
A65: BOGOTA | B65: CUNDINAMARCA | C65: 0004-0004 | D65: 25175 | E65: 2821896 | F65: 3007070277 | G65: INCIDENTE | H65: CUNDINAMARCA | I65: CHIA | J65: BARRIO MARGARITAS CHIA | K65: REDEBAN | L65: FO-25-1610696 | M65: 45931.46 | N65: 45932.628 | O65: NO | P65: HARDWARE | Q65: LECTOR DE BARRAS | R65: DAÑO POS | S65: CB UNO A UNO | T65: CB UNO A UNO | U65: EJECUTADO | V65: 01/10/2025 SE ESCALA PARA VISITA. LLAMAR ANTES DE VISITAR, CONFIRMAR FALLA Y DATOS | 02/10/2025 SE REALIZA VISITA TECNICA, SE VALIDA LECTOR CODIGO DE BARRAS, NO FUNCIONA PARA LEER LOS CODIGOS DE BARRAS, SE PROCEDE A REALIZAR EL CAMBIO, SE REALIZA PRUEBAS OK SIN NOVEDAD. | W65: VISITA TECNICA | X65: MN007341 | Y65: TIPO II | Z65: TERRESTRE | AA65: ARIAS QUILINDO JULIAN | AB65: 1 | AC65: 0 | AD65: 144968 | AE65: 144968
A66: BUCARAMANGA | B66: SANTANDERES | C66: 0004-0008 | D66: 68001 | E66: 2821965 | F66: 3007081046 | G66: INCIDENTE | H66: SANTANDER | I66: BUCARAMANGA | J66: PTM BUCARAMANGA FERREMUEBLES S | K66: REDEBAN | L66: FO-25-1610709 | M66: 45931.458 | N66: 45931.965 | O66: NO | P66: HARDWARE | Q66: LECTOR DE BARRAS | R66: FORMATO INVALIDO LECTOR DAÑADO | S66: AGREGADOR | T66: COMCARD - PTM | U66: EJECUTADO | V66: 01/10/2025 SE REALIZA VISITA AL COMERCIO SE HACE CAMBIO DE LECTORA SE REALIZAN PRUEBAS OK | W66: VISITA TECNICA | X66: SGZZZ961 - SGZZZ607 | Y66: TIPO I | Z66: TERRESTRE | AA66: MARIÑO PABON JORGE ENRIQUE | AB66: 1 | AC66: 0 | AD66: 65960 | AE66: 65960
A67: MEDELLIN | B67: NOROCCIDENTE | C67: 0004-0005 | D67: 27361 | E67: 2822083 | F67: 3007077243 | G67: INCIDENTE | H67: CHOCO | I67: ISTMINA | J67: BARRIO BRR DIEGO LUIS ISTMINA | K67: REDEBAN | L67: FO-25-1629502 | FO-25-1610665 | M67: 45931.471 | N67: 45940.433 | O67: NO | P67: HARDWARE | Q67: ALERT IRRUPTION | R67: ALERT IRRUPTION | S67: UNO A UNO | T67: UNO A UNO | U67: EJECUTADO / CANCELADO | V67: 07/10/2025 REPORTO PARO MINERO EN EL DEPARTAMENTO DEL CHOCÓ AL MOMENTO SE PRESENTAN BLOQUEOS EN LA VÍA HACIA EL SAN JUAN (CERTEGUI, ISTMINA, CONDOTO, TADÓ ) Y SUS ALREDEDORES, DICHO BLOQUEO SE PRESENTA A LA ALTURA DE TANANDO MUNICIPIO DE ATRATO | 10/10/2025 EL DÍA JUEVES 09 SE INTENTA REALIZAR VISITA TECNICA PERO SE PRESENTA BLOQUEO EN LA VÍA, ESPERAMOS HASTA MEDIO DÍA PERO NO HABILITAN PASO POR PARO MINERO. VISITA PENDIENTE | 10/10/2025 SE REALIZA VISITA, SE ENCUENTRA COMERCIO CERRADO, SE INTENTA COMUNICACIÓN ESTANDO EN SITIO Y NO ES EXITOSO, PREVIAMENTE SE LE HABÍA CONFIRMADO AL CLIENTE QUE ÍBAMOS EN CAMINO | W67: VISITA TECNICA | X67: LMHZZ293 | Y67: TIPO V | Z67: AEREO | AA67: ROBLEDO DIAZ ANDRES FELIPE | AB67: 2 | AC67: 0 | AD67: 1976926 | AE67: 1976926
A68: MEDELLIN | B68: NOROCCIDENTE | C68: 0004-0005 | D68: 5001 | E68: 2822238 | F68: 3007042713 | G68: INCIDENTE | H68: ANTIOQUIA | I68: MEDELLIN | J68: PTM MED TIA LAURA CARNICOS Y P | K68: REDEBAN | L68: FO-25-1610681 | M68: 45931.468 | N68: 45931.962 | O68: NO | P68: HARDWARE | Q68: NO ENCIENDE SE REINICIA | R68: FUENTE PODER AVERIADA | S68: AGREGADOR | T68: COMCARD - PTM | U68: EJECUTADO | V68: 01/10/2025 SE ESCALA PARA VISITA. LLAMAR ANTES DE VISITAR, CONFIRMAR FALLA Y DATOS | 01/10/2025 SE CAMBIA FUENTE DE PODER | W68: VISITA TECNICA | X68: GZ7ZZ141 - TRZZZ932 | Y68: TIPO I | Z68: TERRESTRE | AA68: CASTAÑEDA PALACIO CARLOS FELIPE | AB68: 1 | AC68: 0 | AD68: 65960 | AE68: 65960
... A85: BOGOTA | B85: CUNDINAMARCA | C85: 0004-0004 | D85: 25754 | E85: 2826135 | F85: 3007066235 | G85: INCIDENTE | H85: CUNDINAMARCA | I85: SOACHA | J85: BARRIO NEMESIS SOACHA | K85: REDEBAN | L85: FO-25-1613649 | M85: 45932.333 | N85: 45932.644 | O85: NO | P85: HARDWARE | Q85: LECTOR DE BARRAS | R85: CABLE LECTORA AVERIADO | S85: CB UNO A UNO | T85: CB UNO A UNO | U85: EJECUTADO | V85: 02/10/2025 SE ESCALA PARA VISITA. LLAMAR ANTES DE VISITAR | 02/10/2025 CAMBIO DE LECTORA POR DAÑO SE REALIZA PRUEBAS OK SE ENTREGA SERVICIO OPERATIVO LECTORA SIN PLACA RBM CONFIRMA INVENTARIO | W85: VISITA TECNICA | X85: 2A00L313 | Y85: TIPO I | Z85: TERRESTRE | AA85: HERNANDEZ NARANJO OSCAR EDUARDO | AB85: 1 | AC85: 0 | AD85: 65960 | AE85: 65960
A86: MEDELLIN | B86: NOROCCIDENTE | C86: 0004-0005 | D86: 5088 | E86: 2826167 | F86: 3007081532 | G86: INCIDENTE | H86: ANTIOQUIA | I86: BELLO | J86: PTM BELLO ANGELA MARIA RESTREP | K86: REDEBAN | L86: FO-25-1613636 | M86: 45932.333 | N86: 45932.638 | P86: SOFTWARE | Q86: LECTOR DE BARRAS | R86: LECTOR DESCONFIGURADO | S86: AGREGADOR | T86: COMCARD - PTM | V86: 02/10/2025 SE ESCALA PARA VISITA. LLAMAR ANTES DE VISITAR | 02/10/2025 SE REALIZÓ GESTIÓN TELEFÓNICA SE HACE RECONFIGURACIÓN DE LECTOR SE REALIZÓ PRUEBA EXITOSA SE PROCEDE A CERRAR CASO | W86: SOPORTE TELEFONICO | Y86: TIPO I | Z86: TERRESTRE | AA86: CASTAÑEDA PALACIO CARLOS FELIPE | AB86: 0 | AC86: 0 | AD86: 41241 | AE86: 41241
A87: MEDELLIN | B87: NOROCCIDENTE | C87: 0004-0005 | D87: 5088 | E87: 2827098 | F87: 3007033971 | G87: INCIDENTE | H87: ANTIOQUIA | I87: BELLO | J87: PAGAFACIL PLAZA DE BELLO | K87: REDEBAN | L87: FO-25-1613822 | M87: 45932.351 | N87: 45932.653 | O87: NO | P87: HARDWARE | Q87: LECTOR DE BARRAS | R87: CABLE LECTORA AVERIADO | S87: ROBUSTO | T87: PAGAFACIL | U87: EJECUTADO | V87: 02/10/2025 SE ESCALA PARA VISITA. LLAMAR ANTES DE VISITAR | 02/10/2025 SE CAMBIA LECTOR DE BARRAS CON CABLE DALDO | W87: VISITA TECNICA | X87: 1LZZZ894 | Y87: TIPO I | Z87: TERRESTRE | AA87: CASTAÑEDA PALACIO CARLOS FELIPE | AB87: 1 | AC87: 0 | AD87: 65960 | AE87: 65960
A88: VALLEDUPAR | B88: COSTA | C88: 0004-0001 | D88: 20001 | E88: 2827103 | F88: 3007075059 | G88: INCIDENTE | H88: CESAR | I88: VALLEDUPAR | J88: BARRIO FRANCISCO DE PAULA SANT | K88: REDEBAN | L88: FO-25-1613834 | M88: 45932.346 | N88: 45933.451 | O88: NO | P88: HARDWARE | Q88: SE REINICIA | R88: DAÑO POS | S88: CB UNO A UNO | T88: CB UNO A UNO | U88: EJECUTADO | V88: 02/10/2025 SE ESCALA PARA VISITA. LLAMAR ANTES DE VISITAR | 03/10/2025 SE REALIZA VISITA TECNICA YA QIE CLIENTE MANIFIESTA QUE EL EQUIPO SE LE REINICIA, SE LLEGA A SITIO Y SE EVIDENCIA QUE EL CLIENTE REALIZO UNA ADAPTACIÓN DE UN CABLE USB PARA DARLE MAS LARGO AL CABLE DE PIN PAD, SE REALIZAN VALIDACIONES SE CONECTA CABLE PUN PAD DIRECTAMENTE AL HUB Y QUEDA EQUIPO OPERATIVO SIN REINICIOS, SE LE DAN INDICACONES AL CLIENTE QUE ESA ADAPTACIÓN QUE REALIZARON LES ESTA CAUSANDO REINICIO DEL PIN PAD,SE LES DA RECOMENDACION DE UTILIZAR EL EQUIPO CON SUS ACCESORIOS ORIGINALES PARA PODER GARANTIZAR UN BUEN FUNCIONAMIENTO,SE REALIZAN PRUEBAS QUEDANDO EQUIPO OPERATIVO | W88: VISITA TECNICA | X88: NRZZZ543 - SV04Z151 | Y88: TIPO I | Z88: TERRESTRE | AA88: MAESTRE MENGUAL EDGAR ENRIQUE | AB88: 1 | AC88: 0 | AD88: 65960 | AE88: 65960
A89: CALI | B89: SUROCCIDENTE Y EJE CAFETERO | C89: 0004-0003 | D89: 19075 | E89: 2827117 | F89: 3007077642 | G89: INCIDENTE | H89: CAUCA | I89: BALBOA | J89: BARRIO BELEN BALBOA | K89: REDEBAN | L89: FO-25-1613827 | M89: 45932.348 | N89: 45933.708 | P89: HARDWARE | Q89: COMUNICACION | R89: MENSAJE CABLE DE RED DESCONECTADO | S89: UNO A UNO | T89: UNO A UNO | V89: 02/10/2025 SE COMUNICA CON EL SR MIGUEL HOYOS PARA REPORTAR QUE EL DATAFONO LE ARROJA MENSAJE DE ERROR IN CONEXION, EL CB REALIZO LOS PRIMEROS AUXILIOS Y NO LE FUNCIONO, REALIZO TEST DE COMUNICACION Y LE REGISTRA QUE NO TIENE CONEXION, EL INTERNET ES PROPIO Y SI TIENE INTERNE, REINICIO EL MODEM PERO NO CONECTA EN EL DATAFONO 8:34 AM 3112768515 | 03/10/2025 SE REALIZA LLAMADA CELULAR CON EL SEÑOR MIGUEL INFORMA YA EL DATAFONO TIENE CONEXION OK | W89: SOPORTE TELEFONICO | Y89: TIPO IV | Z89: TERRESTRE | AA89: GIMBUEL LASSO LUIS GERMAN | AB89: 0 | AC89: 0 | AD89: 41241 | AE89: 41241
A90: BOGOTA | B90: CUNDINAMARCA | C90: 0004-0004 | D90: 11001 | E90: 2827148 | F90: 3007020851 | G90: INCIDENTE | H90: CUNDINAMARCA | I90: BOGOTA | J90: BARRIO TOBERIN VIII BOGOTA | K90: REDEBAN | L90: FO-25-1613817 | M90: 45932.354 | N90: 45932.651 | O90: NO | P90: HARDWARE | Q90: IMPRESION | R90: NO IMPRIME UNO O VARIOS CARACTERES | S90: CB UNO A UNO | T90: CB UNO A UNO | U90: EJECUTADO | V90: 02/10/2025 SE ESCALA PARA VISITA. LLAMAR ANTES DE VISITAR | 02/10/2025 SE REALIZA VISITA SE REALIZA LIMPIEZA DE IMPRESORA TÉRMICA SE REALIZAN PRUEBAS QUEDANDO FUNCIONAL | W90: VISITA TECNICA | X90: 6A0NZ515 | Y90: TIPO I | Z90: TERRESTRE | AA90: JAIMES VALERO NELSON RICARDO | AB90: 1 | AC90: 0 | AD90: 65960 | AE90: 65960
A91: MEDELLIN | B91: NOROCCIDENTE | C91: 0004-0005 | D91: 5664 | E91: 2827224 | F91: 3007048480 | G91: INCIDENTE | H91: ANTIOQUIA | I91: SAN PEDRO DE LOS MILAGROS | J91: BARRIO PARQUE SAN PEDRO DE LOS | K91: REDEBAN | L91: FO-25-1614219 | M91: 45932.356 | N91: 45933.549 | O91: NO | P91: HARDWARE | Q91: ALERT IRRUPTION | R91: ALERT IRRUPTION | S91: CB UNO A UNO | T91: CB UNO A UNO | U91: EJECUTADO | V91: 02/10/2025 SE ESCALA PARA VISITA. LLAMAR ANTES DE VISITAR | 03/10/2025 SE REALIZA CAMBIO DE EQUIPO POR ALERT IRRUPTION, PRUEBAS OK | W91: VISITA TECNICA | X91: II00J427 | Y91: TIPO II | Z91: TERRESTRE | AA91: CARDONA MOLINA BROLIN STIVEN | AB91: 1 | AC91: 0 | AD91: 144968 | AE91: 144968
A92: IBAGUE | B92: REMOTAS | C92: 0004-0007 | D92: 73520 | E92: 2827507 | F92: 3007073348 | G92: INCIDENTE | H92: TOLIMA | I92: PALOCABILDO | J92: BARRIO CENTRO INTERIOR 1 PALOC | K92: REDEBAN | L92: FO-25-1614214 | M92: 45932.366 | N92: 45933.574 | O92: NO | P92: HARDWARE | Q92: ALERT IRRUPTION | R92: ALERT IRRUPTION | S92: CB UNO A UNO | T92: CB UNO A UNO | U92: EJECUTADO | V92: 02/10/2025 SE COMUNICA CON LA SR NANCY PARA REPORTAR QUE EL DATAFONO ESTA ARROJANDO ALERT INTERRUPTION 3102437234 9: 09 AM | 03/10/2025 SE CAMBIA DATÁFONO POR ALERT IRRUPTION. SE HACEN PRUEBAS DE TRANSACCIONES TODO OK | W92: VISITA TECNICA | X92: EF00Y721 | Y92: TIPO III | Z92: TERRESTRE | AA92: VARGAS HERRERA JHON JAIRO | AB92: 1 | AC92: 0 | AD92: 275729 | AE92: 275729
A93: CARTAGENA | B93: COSTA | C93: 0004-0001 | D93: 13001 | E93: 2827515 | F93: 3007030600 | G93: INCIDENTE | H93: BOLIVAR | I93: CARTAGENA | J93: BARRIO VILLAS DE LA CANDELARIA | K93: REDEBAN | L93: FO-25-1614210 | M93: 45932.368 | N93: 45932.55 | O93: NO | P93: HARDWARE | Q93: COMUNICACION | R93: MENSAJE CABLE DE RED DESCONECTADO | S93: CB UNO A UNO | T93: CB UNO A UNO | U93: EJECUTADO | V93: 02/10/2025 SE ESCALA PARA VISITA. LLAMAR ANTES DE VISITAR | 02/10/2025 SE CAMBIA EQUIPO PUERTO DE RED DAÑADO Y SE CAMBIA LECTORA CABLE DEGOLLADO QUEDA TODO OK SE HACEN PRUEBAS | W93: VISITA TECNICA | X93: BOZZZ261 | Y93: TIPO I | Z93: TERRESTRE | AA93: CANEDO HERRERA ALEXANDER | AB93: 1 | AC93: 0 | AD93: 65960 | AE93: 65960
A94: BOGOTA | B94: CUNDINAMARCA | C94: 0004-0004 | D94: 25799 | E94: 2827595 | F94: 3007023836 | G94: INCIDENTE | H94: CUNDINAMARCA | I94: TENJO | J94: BARRIO LA PUNTA II TENJO | K94: REDEBAN | L94: FO-25-1614198 | M94: 45932.375 | N94: 45932.657 | O94: NO | P94: HARDWARE | Q94: PINPAD | R94: DAÑO POS | S94: CB UNO A UNO | T94: CB UNO A UNO | U94: EJECUTADO | V94: 02/10/2025 SE ESCALA PARA VISITA. LLAMAR ANTES DE VISITAR | 02/10/2025 SE REALIZA VISITA DE CAMPO SE VERIFICA PINPAD Y APARECE EN DAÑO, SE PROCEDE A INSTALAR PINPAD, PARÁMETROS OKAY USUARIOS OKAY A CONFORMIDAD DEL CLIENTE | W94: VISITA TECNICA | X94: ABC0L717 | Y94: TIPO II | Z94: TERRESTRE | AA94: ARIAS QUILINDO JULIAN | AB94: 1 | AC94: 0 | AD94: 144968 | AE94: 144968
A95: APARTADO | B95: NOROCCIDENTE | C95: 0004-0005 | D95: 5045 | E95: 2827749 | F95: 3007044406 | G95: INCIDENTE | H95: ANTIOQUIA | I95: APARTADO | J95: DISTRICOL SERRANIA FRUTAS Y LE | K95: REDEBAN | L95: FO-25-1614940 | M95: 45932.383 | N95: 45932.542 | O95: NO | P95: HARDWARE | Q95: COMUNICACION | R95: MENSAJE CABLE DE RED DESCONECTADO | S95: AGREGADOR | T95: DISTRICOL | U95: EJECUTADO | V95: 02/10/2025 SE ESCALA PARA VISITA. LLAMAR ANTES DE VISITAR | 02/10/2025 DATÁFONO NO TIENE INTERNET, SE VALIDAN CONEXIONES, LOS CABLES Y SE PRUEBAN CON OTRO DATÁFONO DE BACKUP Y PERSISTE EL PROBLEMA. USUARIO NO CUENTA CON VECINOS QUE NOS DEJEN PROBAR CON EL INTERNET DE ELLOS. SE PROCEDE A DECIRLE AL USUARIO QUE SE COMUNIQUE CON PROVEEDOR DE SU INTERNET Y QUE CUANDO LE GARANTICEN SALIDA DE INTERNET POR LOS PUERTOS ETHERNET VUELVA A LLAMAR A PEDIR ATENCIÓN TÉCNICA. | W95: VISITA TECNICA | X95: AB19Z212 | Y95: TIPO I | Z95: TERRESTRE | AA95: SALDARRIAGA MIRANDA SANTIAGO | AB95: 1 | AC95: 0 | AD95: 65960 | AE95: 65960
A96: VALLEDUPAR | B96: COSTA | C96: 0004-0001 | D96: 13042 | E96: 2827802 | F96: 3007048692 | G96: INCIDENTE | H96: BOLIVAR | I96: ARENAL | J96: DISTRICOL PERFUMERIA VICTORIAS | K96: REDEBAN | L96: FO-25-1614945 | M96: 45932.376 | N96: 45936.572 | O96: NO | P96: HARDWARE | Q96: IMPRESION | R96: NO IMPRIME UNO O VARIOS CARACTERES | S96: AGREGADOR | T96: DISTRICOL | U96: EJECUTADO | V96: 02/10/2025 SE REALIZAN 3 INTENTOS DE LLAMADA AL NUMERO DE CONTACTO 3154219989 PERO NO FUE POSIBLE LA COMUNICACION | 06/10/2025 POR BAJA FRECUENCIA TRANSPORTE FLUVIAL, A LA ESPERA QUE PASE LANCHA PARA LLEGAR AL MUNICIPIO. | 06/10/2025 SE REALIZA CAMBIO DE DATAFONO, YA QUE NO IMPRIMIA TODOS LOS CARACTERES EN LA TIRILLAS, ESTA ES LA TERCERA VEZ QUE SE LE CAMBIA EL EQUIPO POR EL MISMO CAUSAL, SE LE RECOMIENDA QUE COLOQUE UN ESTABILIZADOR DE ENERGIA YA QUE EN LA ZONA HAY MUCHO BAJONES DE SERVICIO ELÉCTRICO, SE REALIZAN PRUEBAS DEJANDO SERVICIO FUNCIONAL AL 100 % | W96: VISITA TECNICA | X96: BA00L826 | Y96: TIPO IV | Z96: TERRESTRE | AA96: MONTES DIAZ JOHN FRED | AB96: 1 | AC96: 0 | AD96: 479589 | AE96: 479589
A97: BUCARAMANGA | B97: SANTANDERES | C97: 0004-0008 | D97: 13688 | E97: 2828310 | F97: 3007058306 | G97: INCIDENTE | H97: BOLIVAR | I97: SANTA ROSA DEL SUR | J97: BARRIO SAN ISIDRO SANTA ROSA D | K97: REDEBAN | L97: FO-25-1615611 | M97: 45932.402 | N97: 45933.431 | O97: NO | P97: HARDWARE | Q97: NO ENCIENDE | R97: DAÑO POS | S97: CB UNO A UNO | T97: CB UNO A UNO | U97: EJECUTADO | V97: 02/10/2025 SE COMUNICA CON LA SRA LEIDY PARA REPORTAR QUE SE LE QUEMO EL DATAFONO POR UNA DESCARGA ELECTRÓNICA 3172258449 10:03 AM | 03/10/2025 SE REALIZA VISITA AL COMERCIO, SE VALIDA Y SE HACE CAMBUO DE DATÁFONO, LECTOR DE BARRAS, ESTABAN QUEMADOS, SE CAMBIO POR DESK 2600 SE INSTALO MÁGIC BOX, SE CONFIGURA Y SE HACEN PRUEBAS DEJANDO TODO OK | W97: VISITA TECNICA | X97: IMZZZ428 | Y97: TIPO V | Z97: TERRESTRE/FLUVIAL | AA97: GONZALEZ ESTUPIÑAN YEISON WALTER ANTONIO | AB97: 1 | AC97: 0 | AD97: 479589 | AE97: 479589
A98: APARTADO | B98: NOROCCIDENTE | C98: 0004-0005 | D98: 5172 | E98: 2828349 | F98: 3007050648 | G98: INCIDENTE | H98: ANTIOQUIA | I98: CHIGORODO | J98: PTM CHIGORODO TECNICELL MYS | K98: REDEBAN | L98: FO-25-1614924 | M98: 45932.404 | N98: 45933.349 | O98: NO | P98: HARDWARE | Q98: COMUNICACION | R98: MENSAJE CABLE DE RED DESCONECTADO | S98: AGREGADOR | T98: COMCARD - PTM | U98: EJECUTADO | V98: 02/10/2025 SE ESCALA PARA VISITA. LLAMAR ANTES DE VISITAR | 02/10/2025 SE REALIZA PONCHADO DEL CABLE DE RED SE REALIZAN PRUEBAS EXITOSAS SERVICIO OPERATIVO | W98: VISITA TECNICA | X98: BA00Y348 | Y98: TIPO II | Z98: TERRESTRE | AA98: ZAPATA LOPEZ EDWARD ASDRUBAL | AB98: 1 | AC98: 0 | AD98: 144968 | AE98: 144968
A99: MEDELLIN | B99: NOROCCIDENTE | C99: 0004-0005 | D99: 5001 | E99: 2828622 | F99: 3007033409 | G99: INCIDENTE | H99: ANTIOQUIA | I99: MEDELLIN | J99: COMCARD MED PELUQUERO PICACHO | K99: REDEBAN | L99: FO-25-1614918 | M99: 45932.414 | N99: 45932.553 | O99: NO | P99: HARDWARE | Q99: CIERRE | R99: MEMORIA DEL DISPOSITIVO INSUFICIENTE | S99: AGREGADOR | T99: COMCARD - PTM | U99: EJECUTADO | V99: 02/10/2025 SE ESCALA PARA VISITA. LLAMAR ANTES DE VISITAR | 02/10/2025 SE HACE MANTENIMIENTO OK SE BORRA TRANSACCIONES Y SE VUELVE A MONTA SO | W99: VISITA TECNICA | X99: 17ZZZ957 - NA001728 | Y99: TIPO I | Z99: TERRESTRE | AA99: DIAZ ZABALA FRANCIS DUBAN | AB99: 1 | AC99: 0 | AD99: 65960 | AE99: 65960
A100: BOGOTA | B100: CUNDINAMARCA | C100: 0004-0004 | D100: 11001 | E100: 2828636 | F100: 3007046598 | G100: INCIDENTE | H100: CUNDINAMARCA | I100: BOGOTA | J100: BARRIO CANADA GUIRA BOGOTA | K100: REDEBAN | L100: FO-25-1614912 | M100: 45932.416 | N100: 45932.746 | O100: NO | P100: HARDWARE | Q100: DETERIORO | R100: DATAFONO | S100: CB UNO A UNO | T100: CB UNO A UNO | U100: EJECUTADO / CANCELADO | V100: 02/10/2025 SE ESCALA PARA VISITA. LLAMAR ANTES DE VISITAR | 02/10/2025 SE CIERRA SIN REALIZAR NINGUNA ACTIVIDAD, YA QUE SE LE INDICA AL CLIENTE QUE EL PROCESO DE CAMBIO DE DATAFONO TARDA COMO MÍNIMO 30 MINUTOS APROXIMADAMENTE SIN QUE SE PRESENTEN INCONVENIENTES.. A LO QUE MENCIONA QUE ES BASTANTE TIEMPO E INDICA QUEDARCE CON EL DATÁFONO COMO ESTÁ, EL DISPOSITIVO SE ENCUENTRA FUNCIONANDO DE MANERA CORRECTA SIN PRESENTAR FALLAS DE COMUNICACIÓN | W100: VISITA TECNICA | X100: AD009386 | Y100: TIPO I | Z100: TERRESTRE | AA100: ORTIZ YARA FRANKLYN ISRAEL | AB100: 1 | AC100: 0 | AD100: 65960 | AE100: 65960
A101: TUNJA | B101: SANTANDERES | C101: 0004-0008 | D101: 15176 | E101: 2829046 | F101: 3007065866 | G101: INCIDENTE | H101: BOYACA | I101: CHIQUINQUIRA | J101: BARRIO BELENCITO CHIQUINQUIRA | K101: REDEBAN | L101: FO-25-1615606 | M101: 45932.442 | N101: 45933.551 | O101: NO | P101: HARDWARE | Q101: LECTOR DE BARRAS | R101: FORMATO INVALIDO LECTOR DAÑADO | S101: CB UNO A UNO | T101: CB UNO A UNO | U101: EJECUTADO | V101: 02/10/2025 SE ESCALA PARA VISITA. LLAMAR ANTES DE VISITAR | 03/10/2025 SE REALIZA VISITA AL COMERCIO, SE BORRA Y ACTUALIZA EQUIPO A VERSION 9.9, SE PONCHA CABLE UTP EN UN EXTREMO, SE CAMBIA LECTORA POR DAÑO. | W101: VISITA TECNICA | X101: 3A00G779 | Y101: TIPO III | Z101: TERRESTRE | AA101: SOLER HOYOS CRISTIAN LEONARDO | AB101: 1 | AC101: 0 | AD101: 275729 | AE101: 275729
... A111: CALI | B111: SUROCCIDENTE Y EJE CAFETERO | C111: 0004-0003 | D111: 76113 | E111: 2830197 | F111: 3007038315 | G111: INCIDENTE | H111: VALLE DEL CAUCA | I111: BUGALAGRANDE | J111: BARRIO CENTRO BUGALAGRANDE 2 | K111: REDEBAN | L111: FO-25-1616157 | M111: 45932.521 | N111: 45933.655 | O111: NO | P111: HARDWARE | Q111: DETERIORO | R111: DATAFONO | S111: CB UNO A UNO | T111: CB UNO A UNO | U111: EJECUTADO | V111: 02/10/2025 SE ESCALA PARA VISITA. LLAMAR ANTES DE VISITAR | 03/10/2025 SE REALIZA CAMBIO DE DATÁFONO POR DETERIOR EN EL TECLADO E IMPRESIONES MUY CLARAS. SE REALIZAN PRUEBAS OPERATIVAS SIN NOVEDAD. CB QUEDA OKEY. | W111: VISITA TECNICA | X111: AB00U572 | Y111: TIPO II | Z111: TERRESTRE | AA111: TORRES GARCIA JENDRY JOSE | AB111: 1 | AC111: 0 | AD111: 144968 | AE111: 144968
A112: VALLEDUPAR | B112: COSTA | C112: 0004-0001 | D112: 20011 | E112: 2830376 | F112: 3007078811 | G112: INCIDENTE | H112: CESAR | I112: AGUACHICA | J112: DISTRICOL PAPELERIA GRAFITOS | K112: REDEBAN | L112: FO-25-1616142 | M112: 45932.527 | N112: 45933.658 | P112: HARDWARE | Q112: IMPRESION | R112: NO AVANZA PAPEL | S112: AGREGADOR | T112: DISTRICOL | V112: 02/10/2025 SE COMUNICA CON LA SRA JANETH REPORTANDO FALLAS CON EL DATÁFONO, INDICA QUE LOS VOUCHER ESTAN IMPRIMIENDO BORROSOS 1:03 PM 3015275585 | 03/10/2025 EN COMUNICACIÓN CON LA SEÑORA JANETH AL NUMERO 3015275585 PARA Q NOS INFORME COMO LLEGAR, BOS MANIFIESTA Q CANCELA LA VISITA , INFORMA Q YA EL DATAFONO SE ENCUENTRA OPERATIVO Y NO NECESITA LA VISITA TECNICA, SE PROCEDE A CERRAR ORDEN | W112: SOPORTE TELEFONICO | Y112: TIPO IV | Z112: TERRESTRE | AA112: GELVEZ MOGOLLON JOSE ELISEO | AB112: 0 | AC112: 0 | AD112: 41241 | AE112: 41241
A113: VALLEDUPAR | B113: COSTA | C113: 0004-0001 | D113: 20001 | E113: 2830403 | F113: 3007049438 | G113: INCIDENTE | H113: CESAR | I113: VALLEDUPAR | J113: BARRIO GARUPAL VALLEDUPAR 2 | K113: REDEBAN | L113: FO-25-1616151 | M113: 45932.521 | N113: 45933.517 | O113: NO | P113: HARDWARE | Q113: LECTOR DE BARRAS | R113: CABLE LECTORA AVERIADO | S113: CB UNO A UNO | T113: CB UNO A UNO | U113: EJECUTADO | V113: 02/10/2025 SE ESCALA PARA VISITA. LLAMAR ANTES DE VISITAR | 03/10/2025 SE REALIZA VISITA POR SOLCITUD DE CLIENTE ,SE REALIZAN CAMBIO DE LECTORA LA CUAL SE ENCUENTRA CON CABLE ABERIADO CAUSANDO REINICIO DEL EQUIPO,SE REALIZAN CAMBIO DE FUENTE DE PODER QUEDANDO SERVICIO OPERÁTIVO AL 100% | W113: VISITA TECNICA | X113: AD00P288 | Y113: TIPO I | Z113: TERRESTRE | AA113: MAESTRE MENGUAL EDGAR ENRIQUE | AB113: 1 | AC113: 0 | AD113: 65960 | AE113: 65960
A114: BOGOTA | B114: CUNDINAMARCA | C114: 0004-0004 | D114: 11001 | E114: 2830418 | F114: 3007022815 | G114: INCIDENTE | H114: CUNDINAMARCA | I114: BOGOTA | J114: MULTIPAGAS MONTEVIDEO | K114: REDEBAN | L114: FO-25-1616146 | M114: 45932.525 | N114: 45932.692 | O114: NO | P114: HARDWARE | Q114: LECTOR DE BARRAS | R114: CABLE LECTORA AVERIADO | S114: ROBUSTO | T114: MULTIPAGAS | U114: EJECUTADO | V114: 02/10/2025 SE ESCALA PARA VISITA. LLAMAR ANTES DE VISITAR | 02/10/2025 SE REALIZA VISITA A CB PARA ATENDER INCIDENTE SE REALIZA CAMBIO DE LECTORA POR FALLA CABLE ROTO,SE REALIZAN PRUEBAS OK | W114: VISITA TECNICA | X114: AB0PZ881 | Y114: TIPO I | Z114: TERRESTRE | AA114: GALINDO ROJAS LUIS FELIPE | AB114: 1 | AC114: 0 | AD114: 65960 | AE114: 65960
A115: BOGOTA | B115: CUNDINAMARCA | C115: 0004-0004 | D115: 11001 | E115: 2830604 | F115: 3007034830 | G115: INCIDENTE | H115: CUNDINAMARCA | I115: BOGOTA | J115: BARRIO PATIO BONITO 1 SECTOR | K115: REDEBAN | L115: FO-25-1616137 | M115: 45932.537 | N115: 45932.674 | O115: NO | P115: SOFTWARE | Q115: COMUNICACION | R115: PARAMETROS DE CONFIGURACION EN POS | S115: CB UNO A UNO | T115: CB UNO A UNO | U115: EJECUTADO | V115: 02/10/2025 SE ESCALA PARA VISITA. LLAMAR ANTES DE VISITAR | 02/10/2025 SE REALIZA RECONSTRUCCIÓN PARÁMETROS DE COMUNICACIÓN PRUEBA OK | W115: VISITA TECNICA | X115: 9A003366 | Y115: TIPO I | Z115: TERRESTRE | AA115: ORTIZ MARTINEZ STIVEN | AB115: 1 | AC115: 0 | AD115: 65960 | AE115: 65960
A116: CUCUTA | B116: SANTANDERES | C116: 0004-0008 | D116: 54001 | E116: 2830954 | F116: 3007017882 | G116: INCIDENTE | H116: NORTE DE SANTANDER | I116: CUCUTA | J116: PAGAFACIL AVENIDA CERO | K116: REDEBAN | L116: FO-25-1616605 | M116: 45932.594 | N116: 45933.59 | O116: NO | P116: HARDWARE | Q116: TECLADO | R116: DAÑO POS | S116: ROBUSTO | T116: PAGAFACIL | U116: EJECUTADO | V116: 02/10/2025 SE ESCALA PARA VISITA. LLAMAR ANTES DE VISITAR | 03/10/2025 SE REALIZA VISITA, SE REALIZA CAMBIO DE DATAFONO POR DAÑO, SE INSTALA ÚLTIMA VERSIÓN, SE CREAN USUARIOS OK, SE REALIZAN PRUEBAS Y CIERRES OK. | W116: VISITA TECNICA | X116: JRZZZ888 - JRZZZ887 | Y116: TIPO I | Z116: TERRESTRE | AA116: PACHECO BUITRAGO JAVIER ALONSO | AB116: 1 | AC116: 0 | AD116: 65960 | AE116: 65960
A117: MEDELLIN | B117: NOROCCIDENTE | C117: 0004-0005 | D117: 5001 | E117: 2831096 | F117: 3007056906 | G117: INCIDENTE | H117: ANTIOQUIA | I117: MEDELLIN | J117: BARRIO MANRIQUE MEDELLIN 22 | K117: REDEBAN | L117: FO-25-1616830 | M117: 45932.606 | N117: 45933.503 | O117: NO | P117: HARDWARE | Q117: DETERIORO | R117: DATAFONO | S117: CB UNO A UNO | T117: CB UNO A UNO | U117: EJECUTADO | V117: 02/10/2025 SE ESCALA PARA VISITA. LLAMAR ANTES DE VISITAR | 03/10/2025 SE REALIZA CAMBIO DE DATÁFONO YA QUE ESTE TIENE TECLADO BORROSO Y ADICIONAL TAPA DE IMPRESIÓN MALA, SE CONFIGURA NUEVAMENTE SE REALIZAN PRUEBAS Y FUNCIONA CORRECTAMENTE. | W117: VISITA TECNICA | X117: 9CQZZ664 | Y117: TIPO I | Z117: TERRESTRE | AA117: RAMIREZ TABARES JUAN DIEGO | AB117: 1 | AC117: 0 | AD117: 65960 | AE117: 65960
A118: BARRANQUILLA | B118: COSTA | C118: 0004-0001 | D118: 8372 | E118: 2831136 | F118: 3007012025 | G118: INCIDENTE | H118: ATLANTICO | I118: JUAN DE ACOSTA | J118: JUAN DE ACOSTA - ATLANTICO | K118: REDEBAN | L118: FO-25-1616823 | M118: 45932.608 | N118: 45933.473 | O118: NO | P118: HARDWARE | Q118: LECTOR DE TARJETAS | R118: MENSAJE RETIRE TARJETA | S118: CB UNO A UNO | T118: CB UNO A UNO | U118: EJECUTADO | V118: 02/10/2025 SE ESCALA PARA VISITA. LLAMAR ANTES DE VISITAR | 03/10/2025 SE REALIZA CAMBIO DE CABLE PINPAD SE REALIZAN PRUEBAS DE CORRECTO FUNCIONAMIENTO | W118: VISITA TECNICA | X118: JAAAC753 | Y118: TIPO II | Z118: TERRESTRE | AA118: VILLACOB VILLACOB ELKIN EDUARDO | AB118: 1 | AC118: 0 | AD118: 144968 | AE118: 144968
A119: BOGOTA | B119: CUNDINAMARCA | C119: 0004-0004 | D119: 11001 | E119: 2831334 | F119: 3007031751 | G119: INCIDENTE | H119: CUNDINAMARCA | I119: BOGOTA | J119: OPRAP CARULLA 170 | K119: REDEBAN | L119: FO-25-1616816 | M119: 45932.609 | N119: 45933.506 | O119: NO | P119: HARDWARE | Q119: IMPRESION | R119: NO IMPRIME UNO O VARIOS CARACTERES | S119: ROBUSTO | T119: OPRAP | U119: EJECUTADO | V119: 02/10/2025 SE ESCALA PARA VISITA. LLAMAR ANTES DE VISITAR | 03/10/2025 SE REALIZA VISITA A COMERCIO, VERIFICANDO QUE TAPA DE IMPRESORA ESTA EN DAÑO, SE PROCEDE A REALIZAR EL CAMBIO DEL EQUIPO, SE CREA USUARIO PRUEBAS OK SIN NOVEDAD | W119: VISITA TECNICA | X119: 1111H942 | Y119: TIPO I | Z119: TERRESTRE | AA119: ARIAS QUILINDO JULIAN | AB119: 1 | AC119: 0 | AD119: 65960 | AE119: 65960
A120: MEDELLIN | B120: NOROCCIDENTE | C120: 0004-0005 | D120: 5360 | E120: 2831413 | F120: 3007076636 | G120: INCIDENTE | H120: ANTIOQUIA | I120: ITAGUI | J120: PTM ITAGUI MERCALAN EXPRESS PI | K120: REDEBAN | L120: FO-25-1616984 | M120: 45932.619 | N120: 45933.494 | O120: NO | P120: HARDWARE | Q120: LECTOR DE BARRAS | R120: CABLE LECTORA AVERIADO | S120: AGREGADOR | T120: COMCARD - PTM | U120: EJECUTADO | V120: 02/10/2025 SE ESCALA PARA VISITA. LLAMAR ANTES DE VISITAR | 03/10/2025 SE REALIZA CAMBIO DE LECTORA POR DAÑO DAÑO EL CABLE | W120: VISITA TECNICA | X120: LA2ZZ419 - LA2ZZ501 | Y120: TIPO I | Z120: TERRESTRE | AA120: HERNANDEZ CHAVARRIA JUAN CAMILO | AB120: 1 | AC120: 0 | AD120: 65960 | AE120: 65960
A121: MONTERIA | B121: COSTA | C121: 0004-0001 | D121: 23001 | E121: 2831576 | F121: 3007020874 | G121: INCIDENTE | H121: CORDOBA | I121: MONTERIA | J121: MULTIPAGAS MONTERIA | K121: REDEBAN | L121: FO-25-1617154 | M121: 45932.637 | N121: 45933.5 | O121: NO | P121: HARDWARE | Q121: LECTOR DE BARRAS | R121: CABLE LECTORA AVERIADO | S121: ROBUSTO | T121: MULTIPAGAS | U121: EJECUTADO | V121: 02/10/2025 SE ESCALA PARA VISITA. LLAMAR ANTES DE VISITAR | 03/10/2025 SE VISITA SITIO, SE CAMBIA LECTOR DE BARRAS POR DAÑO OK. SE REALIZAN PRUEBAS EXITOSAS | W121: VISITA TECNICA | X121: AAAGZ636 | Y121: TIPO I | Z121: TERRESTRE | AA121: COGOLLO VERTEL EDER LUIS | AB121: 1 | AC121: 0 | AD121: 65960 | AE121: 65960
A122: BOGOTA | B122: CUNDINAMARCA | C122: 0004-0004 | D122: 11001 | E122: 2831661 | F122: 3007017996 | G122: INCIDENTE | H122: CUNDINAMARCA | I122: BOGOTA | J122: BARRIO VALLA MARIA DE SUBA BOG | K122: REDEBAN | L122: FO-25-1617038 | M122: 45932.63 | N122: 45933.49 | O122: NO | P122: SOFTWARE | Q122: COMUNICACION | R122: VERIFIQUE PARAMETROS | S122: CB UNO A UNO | T122: CB UNO A UNO | U122: EJECUTADO | V122: 02/10/2025 SE ESCALA PARA VISITA. LLAMAR ANTES DE VISITAR | 03/10/2025 SE REALIZA BORRADO DE DATAFONO POR FALLAS EN VERIFIQUE COMPONENTES PRUEBA OK SE CREAN USUARIOS OK | W122: VISITA TECNICA | X122: A03ZZ932 | Y122: TIPO I | Z122: TERRESTRE | AA122: ORTIZ MARTINEZ STIVEN | AB122: 1 | AC122: 0 | AD122: 65960 | AE122: 65960
A123: MEDELLIN | B123: NOROCCIDENTE | C123: 0004-0005 | D123: 5088 | E123: 2831684 | F123: 3007045785 | G123: INCIDENTE | H123: ANTIOQUIA | I123: BELLO | J123: PTM BELLO PAPELERIA Y VARIEDA | K123: REDEBAN | L123: FO-25-1617160 | M123: 45932.635 | N123: 45933.487 | O123: NO | P123: HARDWARE | Q123: TECLADO | R123: DAÑO POS | S123: AGREGADOR | T123: COMCARD - PTM | U123: EJECUTADO | V123: 02/10/2025 SE ESCALA PARA VISITA. LLAMAR ANTES DE VISITAR | 03/10/2025 SE CAMBIA DATÁFONO POR EN TECLADO | W123: VISITA TECNICA | X123: BA000935 - TRZZZ977 | Y123: TIPO I | Z123: TERRESTRE | AA123: DIAZ ZABALA FRANCIS DUBAN | AB123: 1 | AC123: 0 | AD123: 65960 | AE123: 65960
A124: MONTERIA | B124: COSTA | C124: 0004-0001 | D124: 23807 | E124: 2831826 | F124: 3007010947 | G124: INCIDENTE | H124: CORDOBA | I124: TIERRALTA | J124: TIERRALTA - CORDOBA | K124: REDEBAN | L124: FO-25-1617266 | M124: 45932.644 | N124: 45934.529 | O124: NO | P124: HARDWARE | Q124: TECLADO | R124: DAÑO POS | S124: CB UNO A UNO | T124: CB UNO A UNO | U124: EJECUTADO | V124: 02/10/2025 SE REALIZA 3 INTENTOS DE LLAMADA AL NUMERO DE CONTACTO 3137453519 PERO NO FUE POSIBLE LA COMUNICACION | 04/10/2025 SE REALIZÓ CAMBIO DE EQUIPO OK, USUARIOS OK, PRUEBAS OK, TELECARGA DRNA. | W124: VISITA TECNICA | X124: IZ7ZZ601 | Y124: TIPO III | Z124: TERRESTRE | AA124: CALDERA SALCEDO CARLOS JULIO | AB124: 1 | AC124: 0 | AD124: 275729 | AE124: 275729
... A134: APARTADO | B134: NOROCCIDENTE | C134: 0004-0005 | D134: 5837 | E134: 2833034 | F134: 3007033972 | G134: INCIDENTE | H134: ANTIOQUIA | I134: TURBO | J134: PAGAFACIL CURRULAO | K134: REDEBAN | L134: FO-25-1619287 | M134: 45933.333 | N134: 45933.728 | O134: NO | P134: HARDWARE | Q134: LECTOR DE TARJETAS | R134: DAÑO POS | S134: ROBUSTO | T134: PAGAFACIL | U134: EJECUTADO | V134: 03/10/2025 SE ESCALA PARA VISITA. LLAMAR ANTES DE VISITAR | 03/10/2025 PIN PAD NO RECONOCE VARIAS TARJETAS. SE DEBE HACER EL CAMBIO. SE PROCEDE A INSTALAR UN NUEVO PIN PAD 1600 JUNTO CON DATÁFONO DESK 2600. SE HACEN PRUEBAS DE RETIRO, CONSULTA, CONSIGNACIÓN Y PRUEBA DE LECTORA DEJANDO TODO FUNCIONANDO CORRECTAMENTE. SE CAMBIA LECTORA YA QUE LA ACTUAL TIENE EL CABLE MUY CORTO Y DEFECTUOSOS | W134: VISITA TECNICA | X134: 1LZZZ907 | Y134: TIPO II | Z134: TERRESTRE | AA134: SALDARRIAGA MIRANDA SANTIAGO | AB134: 1 | AC134: 0 | AD134: 144968 | AE134: 144968
A135: CALI | B135: SUROCCIDENTE Y EJE CAFETERO | C135: 0004-0003 | D135: 76520 | E135: 2833301 | F135: 3007064884 | G135: INCIDENTE | H135: VALLE DEL CAUCA | I135: PALMIRA | J135: DISTRICOL ARTHEMIS | K135: REDEBAN | L135: FO-25-1619265 | M135: 45933.333 | N135: 45934.367 | P135: SOFTWARE | Q135: LECTOR DE BARRAS | R135: FORMATO INVALIDO | S135: AGREGADOR | T135: DISTRICOL | V135: 03/10/2025 SE ESCALA PARA VISITA. LLAMAR ANTES DE VISITAR | 03/10/2025 SE HABLA CON LA ZHARICK PARA VALIDAR DAÑO Y DISPONIBILIDAD PARA LA VISITA PERO LA SEÑORA INFORMA QUE EN ESTE MOMENTO SE ENCUENTRA SIN SERVICIO DE INTERNET EN EL LOCAL POR LO QUE NO PODRIAMOS VALIDAR LA SOLUCION AL DAÑO, SOLICITA SEA VISITADA MAÑANA EN LA MAÑANA YA QUE ESTA A LA ESPERA DE RESTABLECER EL INTERNET. | 04/10/2025 SE COMUNICA NUEVAMENTE CON EL CB VÍA TELÉFONICA E INDICA QUE YA CUENTA CON INTERNET Y YA ESTÁ REALIZANDO TRX CON NORMALIDAD. | W135: SOPORTE TELEFONICO | Y135: TIPO I | Z135: TERRESTRE | AA135: MONTERO MUESES GIAN CARLO | AB135: 0 | AC135: 0 | AD135: 41241 | AE135: 41241
A136: PASTO | B136: SUROCCIDENTE Y EJE CAFETERO | C136: 0004-0003 | D136: 86757 | E136: 2833849 | F136: 3007041966 | G136: INCIDENTE | H136: PUTUMAYO | I136: SAN MIGUEL | J136: PTM 24 HRS DROGUERIA | K136: REDEBAN | L136: FO-25-1619261 | M136: 45933.339 | N136: 45939.456 | O136: NO | P136: HARDWARE | Q136: LECTOR DE TARJETAS | R136: DAÑO POS | S136: AGREGADOR | T136: COMCARD - PTM | U136: EJECUTADO | V136: 03/10/2025 SE REALIZA 3 INTENTOS DE LLAMADA AL NUMERO DE CONTACTO 3136142778 PERO NO FUE POSIBLE LA COMUNICACION 8: 39 AM | 06/10/2025 DADO PROBLEMAS PARA EL DESPLAZAMIENTO AL DEPARTAMENTO DE PUTUMAYO DEBIDO A LAS VIAS, SE ESTARA REALIZANDO EL DIA DE MAÑANA HACIA EL SECTOR. | 08/10/2025 SE ESTABLECE COMUNICACIÓN CON CLIENTE SE LE INFORMA QUE POR TRABAJOS EN LA VÍA EL DÍA DE MAÑANA SE ESTARA REALIZANDO VISITA PARA ATENDER INCIDENTE REPORTADO | 09/10/2025 SE REALIZA CAMBIO DE EQUIPO POR FALLA EN LECTOR DE TARJETA Y TECLADO BORROSO SE INSTALA VERSIÓN EN NUEVO EQUIPO SE CONFIGURA PARÁMETROS SE INICIALIZA SE REALIZA PRUEBAS DE FUNCIONAMIENTO EXITOSAS CB QUEDA OPERATIVO | W136: VISITA TECNICA | X136: GZ0WZ982 | Y136: TIPO IV | Z136: TERRESTRE | AA136: BRAVO MADROÑERO OSCAR ESTEBAN | AB136: 1 | AC136: 0 | AD136: 479589 | AE136: 479589
A137: BUCARAMANGA | B137: SANTANDERES | C137: 0004-0008 | D137: 68547 | E137: 2833863 | F137: 3007038837 | G137: INCIDENTE | H137: SANTANDER | I137: PIEDECUESTA | J137: PTM PIEDECUESTA MARNIETO | K137: REDEBAN | L137: FO-25-1619255 | M137: 45933.343 | N137: 45933.715 | O137: NO | P137: HARDWARE | Q137: LECTOR DE BARRAS | R137: FORMATO INVALIDO LECTOR DAÑADO | S137: AGREGADOR | T137: COMCARD - PTM | U137: EJECUTADO | V137: 03/10/2025 SE ESCALA PARA VISITA. LLAMAR ANTES DE VISITAR | 03/10/2025 SE VISITA COMERCIO SE REALIZA EL CAMBIO DE EQUIPO LECTOR DE BARRAS OK, VERSION 9.90 OK, PRUEBAS OK, LECTOR DE BARRAS OK, CB OPERATIVO SE REALIZA PRUEBAS CONSULTA DE SALDO Y LECTOR DE BARRAS OK | W137: VISITA TECNICA | X137: 9A03Z943 - TSZZZ296 | Y137: TIPO II | Z137: TERRESTRE | AA137: BARAJAS BERMUDEZ YAHIR MAURICIO | AB137: 1 | AC137: 0 | AD137: 144968 | AE137: 144968
A138: IBAGUE | B138: REMOTAS | C138: 0004-0007 | D138: 73268 | E138: 2834020 | F138: 3007051317 | G138: INCIDENTE | H138: TOLIMA | I138: ESPINAL | J138: BARRIO CORREGIMENTO CHICORAL E | K138: REDEBAN | L138: FO-25-1619241 | M138: 45933.357 | N138: 45934.551 | O138: NO | P138: HARDWARE | Q138: COMUNICACION | R138: DAÑO POS | S138: CB UNO A UNO | T138: CB UNO A UNO | U138: EJECUTADO | V138: 03/10/2025 SE ESCALA PARA VISITA. LLAMAR ANTES DE VISITAR | 04/10/2025 SE REALIZA CAMBIO DE EQUIPO PUERTO DE IP MALO TRANSACCIONES DE PRUEBA EN O.K | W138: VISITA TECNICA | X138: BA05Z143 - XP3ZZ526 | Y138: TIPO II | Z138: TERRESTRE | AA138: GUTIERREZ CAMILO ANDRES | AB138: 1 | AC138: 0 | AD138: 144968 | AE138: 144968
A139: CALI | B139: SUROCCIDENTE Y EJE CAFETERO | C139: 0004-0003 | D139: 76130 | E139: 2834116 | F139: 3007045534 | G139: INCIDENTE | H139: VALLE DEL CAUCA | I139: CANDELARIA | J139: PTM CANDELARIA SERVICENTRO TE | K139: REDEBAN | L139: FO-25-1619246 | M139: 45933.357 | N139: 45934.547 | O139: NO | P139: HARDWARE | Q139: PANTALLA | R139: DAÑO POS | S139: AGREGADOR | T139: COMCARD - PTM | U139: EJECUTADO | V139: 03/10/2025 SE ESCALA PARA VISITA. LLAMAR ANTES DE VISITAR | 04/10/2025 SE REALIZA CAMBIO DE DATÁFONO DEBIDO A QUE NO PASA DEL LETRERO DE "WELCOME" Y NO MUESTRA EL INICIO CON EL LOGO DE REDEBAN, SE REALIZAN PRUEBAS OK. | W139: VISITA TECNICA | X139: GB002370 | Y139: TIPO II | Z139: TERRESTRE | AA139: MONTERO MUESES GIAN CARLO | AB139: 1 | AC139: 0 | AD139: 144968 | AE139: 144968
A140: BUCARAMANGA | B140: SANTANDERES | C140: 0004-0008 | D140: 5893 | E140: 2834253 | F140: 3007010306 | G140: INCIDENTE | H140: ANTIOQUIA | I140: YONDO | J140: YONDO - ANTIOQUIA | K140: REDEBAN | L140: FO-25-1620013 | M140: 45933.372 | N140: 45937.435 | O140: NO | P140: HARDWARE | Q140: NO ENCIENDE SE REINICIA | R140: FUENTE PODER AVERIADA | S140: CB UNO A UNO | T140: CB UNO A UNO | U140: EJECUTADO | V140: 03/10/2025 SE REALIZAN 3 INTENTOS DE LLAMADA AL NUMERO DE CONTAACTO 3124785310 PERO NO FUE POSIBLE LA COMUNICACION | 06/10/2025 SE ESTABLECE CONTACTO TELEFÓNICO CON LA USUARIA QUIEN NOS INDICA POR TEMAS DE DESPLAZAMIENTO HACIA LA ZONA Y POR DISPONIBILIDAD DEL USUARIO ERIKA LERMA 301714049 , NOS ENCONTRAMOS EN TRASLADO HACIA EL SECTOR QUIEN NOS CONFIRMA QUE NOS PODRÁ ATENDER EL DIA DE MAÑANA SOBRE LAS 10 AM YA QUE TIENE UNA DILIGENCIA EN BARRANCABERMEJA SOBRE LAS 8 AM Y POR ESTE MOTIVO NOS INDICA QUE NOS ES POSIBLE ATENDERNOS ANTES | 07/10/2025 SE ESTABLECE CONTACTO TELEFÓNICO CON LA USUARIA QUIEN NOS INDICA POR TEMAS DE DESPLAZAMIENTO HACIA LA ZONA Y POR DISPONIBILIDAD DEL USUARIO ERIKA LERMA 301714049 , NOS ENCONTRAMOS EN TRASLADO HACIA EL SECTOR.QUIEN NOS CONFIRMA QUE NOS PODRÁ ATENDER EL DIA DE HOY SOBRE LAS 10 AM YA QUE TIENE UNA DILIGENCIA EN BARRANCABERMEJA SOBRE LAS 8 AM Y POR ESTE MOTIVO NOS INDICA QUE NOS ES POSIBLE ATENDERNOS ANTES | 07/10/2025 SE REALIZA VERIFICACIÓN DEL EQUIPO EL CUAL NO ENCIENDE SE PROCEDE VERIFICANDO FUENTE DE PODER LA CUAL SE ENCUENTRA FUNCIONAL SE PROCEDE A REALIZAR EL CAMBIO DE BATERÍA DE EQUIPO DESK 2600 CORRIGIENDO LA FALLA SE REALIZAN PRUEBAS SE ENTREGA SERVICIO OPERATIVO | W140: VISITA TECNICA | X140: A00IZ801 | Y140: TIPO IV | Z140: TERRESTRE | AA140: REYES RAMIREZ DIEGO ALEXANDER | AB140: 1 | AC140: 0 | AD140: 479589 | AE140: 479589
A141: MEDELLIN | B141: NOROCCIDENTE | C141: 0004-0005 | D141: 5266 | E141: 2834371 | F141: 3007027564 | G141: INCIDENTE | H141: ANTIOQUIA | I141: ENVIGADO | J141: BARRIO SAN MARCOS ENVIGADO | K141: REDEBAN | L141: FO-25-1619983 | M141: 45933.385 | N141: 45933.477 | O141: NO | P141: HARDWARE | Q141: COMUNICACION | R141: MENSAJE CABLE DE RED DESCONECTADO | S141: CB UNO A UNO | T141: CB UNO A UNO | U141: EJECUTADO | V141: 03/10/2025 SE ESCALA PARA VISITA. LLAMAR ANTES DE VISITAR | 03/10/2025 SE REALIZA CONFIGURACIÓN DE PARAMETROS QUEDA CB OPERATIVO | W141: VISITA TECNICA | X141: 99HZZ284 | Y141: TIPO I | Z141: TERRESTRE | AA141: HERNANDEZ CHAVARRIA JUAN CAMILO | AB141: 1 | AC141: 0 | AD141: 65960 | AE141: 65960
A142: MEDELLIN | B142: NOROCCIDENTE | C142: 0004-0005 | D142: 5001 | E142: 2834472 | F142: 3007043848 | G142: INCIDENTE | H142: ANTIOQUIA | I142: MEDELLIN | J142: PTM MED VARIEDADES HM1 | K142: REDEBAN | L142: FO-25-1619973 | M142: 45933.391 | N142: 45933.476 | O142: NO | P142: HARDWARE | Q142: IMPRESION | R142: NO IMPRIME UNO O VARIOS CARACTERES | S142: AGREGADOR | T142: COMCARD - PTM | U142: EJECUTADO | V142: 03/10/2025 SE ESCALA PARA VISITA. LLAMAR ANTES DE VISITAR | 03/10/2025 SE LE LIMPIA CONTACTO DE IMPRESIÓN Y SE ORGANIZA TAPA QUEDA IMPRIMIENDO BIEN | W142: VISITA TECNICA | X142: GZIZZ409 | Y142: TIPO I | Z142: TERRESTRE | AA142: ALVAREZ ARENAS VICTOR HUGO | AB142: 1 | AC142: 0 | AD142: 65960 | AE142: 65960
A143: IBAGUE | B143: REMOTAS | C143: 0004-0007 | D143: 73319 | E143: 2834487 | F143: 3007059251 | G143: INCIDENTE | H143: TOLIMA | I143: GUAMO | J143: BARRIO EL CARMEN GUAMO | K143: REDEBAN | L143: FO-25-1619966 | M143: 45933.396 | N143: 45933.578 | O143: NO | P143: HARDWARE | Q143: IMPRESION | R143: TAPA IMPRESORA | S143: CB UNO A UNO | T143: CB UNO A UNO | U143: EJECUTADO | V143: 03/10/2025 SE ESCALA PARA VISITA. LLAMAR ANTES DE VISITAR | 03/10/2025 SE REALIZA CAMBIO TAPA IMPRESORA , SE REALIZA PRUEBAS OK | W143: VISITA TECNICA | X143: JA002627 | Y143: TIPO II | Z143: TERRESTRE | AA143: ANDRADE HERNANDEZ JUAN CARLOS | AB143: 1 | AC143: 0 | AD143: 144968 | AE143: 144968
A144: IBAGUE | B144: REMOTAS | C144: 0004-0007 | D144: 73001 | E144: 2834653 | F144: 3007071556 | G144: INCIDENTE | H144: TOLIMA | I144: IBAGUE | J144: PTM IBAGUE DROGUERIA PROSALUD | K144: REDEBAN | L144: FO-25-1619955 | M144: 45933.4 | N144: 45933.756 | O144: NO | P144: HARDWARE | Q144: IMPRESION | R144: NO IMPRIME UNO O VARIOS CARACTERES | S144: AGREGADOR | T144: COMCARD - PTM | U144: EJECUTADO | V144: 03/10/2025 SE ESCALA PARA VISITA. LLAMAR ANTES DE VISITAR | 03/10/2025 SE REALIZA CAMBIO DE EQUIPO " NO IMPRIME ALGUNOS CARACTERES"TRANSACCIONES DE PRUEBA O.K INSTALA EQUIPO DSSK 2600, MAGIC BOX, FUENTE DE PODER | W144: VISITA TECNICA | X144: A30KZ123 - A30KZ279 | Y144: TIPO I | Z144: TERRESTRE | AA144: GUTIERREZ CAMILO ANDRES | AB144: 1 | AC144: 0 | AD144: 65960 | AE144: 65960
A145: MONTERIA | B145: COSTA | C145: 0004-0001 | D145: 5154 | E145: 2834792 | F145: 3007078928 | G145: INCIDENTE | H145: ANTIOQUIA | I145: CAUCASIA | J145: DISTRICOL PAPELERIA MIL VARIE | K145: REDEBAN | L145: FO-25-1619948 | M145: 45933.409 | N145: 45934.475 | O145: NO | P145: HARDWARE | Q145: NO ENCIENDE SE REINICIA | R145: FUENTE PODER AVERIADA | S145: AGREGADOR | T145: DISTRICOL | U145: EJECUTADO | V145: 03/10/2025 SE ESCALA PARA VISITA. LLAMAR ANTES DE VISITAR | 04/10/2025 SE REALIZA VISITA TÉCNICA PARA, REVISIÓN Y SE ENCONTRÓ FUENTE DE PODER QUEMADA, SE PROCEDE A REALIZAR EL CAMBIO Y SE DEJA NUEVAMENTE EL SERVICIO FUNCIONANDO CORRECTAMENTE. | W145: VISITA TECNICA | X145: F1SZZ801 | Y145: TIPO II | Z145: TERRESTRE | AA145: CASSIANI PEREZ RAUL RAMIRO | AB145: 1 | AC145: 0 | AD145: 144968 | AE145: 144968
A146: PASTO | B146: SUROCCIDENTE Y EJE CAFETERO | C146: 0004-0003 | D146: 86885 | E146: 2835080 | F146: 3007042142 | G146: INCIDENTE | H146: PUTUMAYO | I146: VILLAGARZON | J146: BARRIO CENTRO VILLAGARZON | K146: REDEBAN | L146: FO-25-1620569 | M146: 45933.423 | N146: 45938.608 | O146: NO | P146: HARDWARE | Q146: PINPAD | R146: SE REINICIA | S146: CB UNO A UNO | T146: CB UNO A UNO | U146: EJECUTADO | V146: 03/10/2025 SE COMUNICA CON LA SRA MARYURY PARA REPORTAR DATAFONO SE REINICIA CONSTANTEMENTE 3133224941 10: 43 AM | 06/10/2025 DADO COMPLICACION EN LAS VIAS PARA ACCCEER AL PUTUMAYO , SE ESTARA REALILZANDO DESPLAZAMIENTO EL DIA DE MAÑANA. | 08/10/2025 SE REALIZA CAMBIO DE EQUIPO Y PINPAD POR FALLA DE REINICIO CONSTANTEMENTE SE INSTALA VERSION EN NUEVO EQUIPO SE CONFIGURA PARÁMETROS SE INICIALIZA SE PRESENTA NOVEDAD CON INTERNET NO COMUNICA SE REALIZA REINICIO DE MÓDEM SE VERIFICA PUERTOS SE REALIZA PRUEBAS DE FUNCIONAMIENTO EXITOSAS CB QUEDA OPERATIVO | W146: VISITA TECNICA | X146: 9A1ZZ165 | Y146: TIPO IV | Z146: TERRESTRE | AA146: BRAVO MADROÑERO OSCAR ESTEBAN | AB146: 1 | AC146: 0 | AD146: 479589 | AE146: 479589
A147: IBAGUE | B147: REMOTAS | C147: 0004-0007 | D147: 73001 | E147: 2835114 | F147: 3007049348 | G147: INCIDENTE | H147: TOLIMA | I147: IBAGUE | J147: BARRIO EL SALADO IBAGUE 3 | K147: REDEBAN | L147: FO-25-1620581 | M147: 45933.422 | N147: 45934.408 | O147: NO | P147: HARDWARE | Q147: IMPRESION | R147: NO IMPRIME UNO O VARIOS CARACTERES | S147: CB UNO A UNO | T147: CB UNO A UNO | U147: EJECUTADO | V147: 03/10/2025 SE ESCALA PARA VISITA. LLAMAR ANTES DE VISITAR | 03/10/2025 SE COMUNICA AL NÚMERO 3118135846, LA SEÑORA YENI PATRICIA MURCIA SOLICITA REALIZAR ACTIVIDAD EL DÍA 04-10-2025 ALAS 8 AM POR DISPONIBILIDAD DE TIEMPO. | 04/10/2025 SE REALIZA CAMBIO DE DATÁFONO POR DAÑO EN IMPRESIÓN, SE REALIZA PRUEBAS DE FUNCIONAMIENTO OK; CUBRE CLAVE INSTALADO. | W147: VISITA TECNICA | X147: 9C00Q198 | Y147: TIPO I | Z147: TERRESTRE | AA147: BARRAGAN TAFUR EDWIN ESTEBAN | AB147: 1 | AC147: 0 | AD147: 65960 | AE147: 65960
... A163: BOGOTA | B163: CUNDINAMARCA | C163: 0004-0004 | D163: 25386 | E163: 2836738 | F163: 3007064636 | G163: INCIDENTE | H163: CUNDINAMARCA | I163: LA MESA | J163: PAGAFACIL PARQUE COMERCIAL TEQ | K163: REDEBAN | L163: FO-25-1624721 | M163: 45933.576 | N163: 45934.508 | O163: NO | P163: HARDWARE | Q163: PINPAD | R163: DAÑO POS | S163: ROBUSTO | T163: PAGAFACIL | U163: EJECUTADO | V163: 04/10/2025 SE REALIZA VISITA DE CAMPO, SE VERIFICA PINPAD Y SE ENCUENTRA EN DAÑO, SE PROCEDE A PARA REALIZAR CAMBIO DE PINPAD, PARÁMETROS OKAY USUARIOS OKAY A CONFORMIDAD DEL CLIENTE. | W163: VISITA TECNICA | X163: 2A000219 | Y163: TIPO II | Z163: TERRESTRE | AA163: ARIAS QUILINDO JULIAN | AB163: 1 | AC163: 0 | AD163: 144968 | AE163: 144968
A164: BOGOTA | B164: CUNDINAMARCA | C164: 0004-0004 | D164: 25245 | E164: 2836741 | F164: 3007034785 | G164: INCIDENTE | H164: CUNDINAMARCA | I164: EL COLEGIO | J164: ARA0550 - CENTRO EL COLEGIO | K164: REDEBAN | L164: FO-25-1626885 | M164: 45933.578 | N164: 45934.386 | P164: HARDWARE | Q164: FLAS FULL | R164: DAÑO POS | S164: RETAIL | T164: TIENDAS ARA | V164: 04/10/2025 SE ESCALA CASO ARA A LA RED**TU SOLICITUD REFERENTE A GENERACIÓN DE CASOS CB ARA BANCOLOMBIA QUEDÓ RADICADA BAJO EL TICKET NÚMERO ** AL ÁREA ENCARGADA. | 04/10/2025 SE ESCALA CASO ARA A LA RED**TU SOLICITUD REFERENTE A GENERACIÓN DE CASOS CB ARA BANCOLOMBIA QUEDÓ RADICADA BAJO EL TICKET NÚMERO ** AL ÁREA ENCARGADA. | 04/10/2025 SE ESCALA CASO ARA A LA RED**TU SOLICITUD REFERENTE A GENERACIÓN DE CASOS CB ARA BANCOLOMBIA QUEDÓ RADICADA BAJO EL TICKET NÚMERO ** AL ÁREA ENCARGADA. | 04/10/2025 SE ESCALA CASO ARA A LA RED**TU SOLICITUD REFERENTE A GENERACIÓN DE CASOS CB ARA BANCOLOMBIA QUEDÓ RADICADA BAJO EL TICKET NÚMERO ** AL ÁREA ENCARGADA. | W164: SOPORTE TELEFONICO | Y164: TIPO II | Z164: TERRESTRE | AA164: DIAZ ACOSTA MARIA ISABEL | AB164: 0 | AC164: 0 | AD164: 41241 | AE164: 41241
A165: BUCARAMANGA | B165: SANTANDERES | C165: 0004-0008 | D165: 68001 | E165: 2836745 | F165: 3007069120 | G165: INCIDENTE | H165: SANTANDER | I165: BUCARAMANGA | J165: PTM BUCARAMANGA FRUTOS SECOS L | K165: REDEBAN | L165: FO-25-1624705 | M165: 45933.578 | N165: 45934.412 | O165: NO | P165: HARDWARE | Q165: TECLADO | R165: DAÑO POS | S165: AGREGADOR | T165: COMCARD - PTM | U165: EJECUTADO | V165: 03/10/2025 SE ESCALA PARA VISITA. LLAMAR ANTES DE VISITAR | 04/10/2025 SE REALIZA VISITA AL COMERCIO SE HACE CAMBIO DE DATAFONO SE REALIZAN PRUEBAS OK | W165: VISITA TECNICA | X165: A103Z526 - A100G799 | Y165: TIPO I | Z165: TERRESTRE | AA165: MARIÑO PABON JORGE ENRIQUE | AB165: 1 | AC165: 0 | AD165: 65960 | AE165: 65960
A166: MEDELLIN | B166: NOROCCIDENTE | C166: 0004-0005 | D166: 5790 | E166: 2837044 | F166: 3007054067 | G166: INCIDENTE | H166: ANTIOQUIA | I166: TARAZA | J166: DISTRICOLPAPELERIAUNIVERSAL | K166: REDEBAN | L166: FO-25-1625732 | M166: 45933.6 | N166: 45933.722 | O166: NO | P166: HARDWARE | Q166: LECTOR DE BARRAS | R166: CABLE LECTORA AVERIADO | S166: AGREGADOR | T166: DISTRICOL | U166: EJECUTADO | V166: 03/10/2025 SE COMUNICA CON LA SRA BIBIANA, PARA REPORTAR FALLA CON EL LECTOR DE CODIGO DE BARRAS, NO LE LEE NINGUNA FACTURA SE TOMARON PRIMEROS AUXILIOS Y CONTINUA IGUAL 3146356767 2:30 PM | 03/10/2025 SE REALIZA CAMBIO DE LECTOR DE BARRAS, LECTOR ENCONTRADO CON CABLE DE DATOS AVERIADO, SE INSTALA NUEVO LECTOR OPERATIVO OK, PRUEBAS EXITOSAS OK, CLIENTE CB VALIDA SALDO ANTES Y DESPUÉS DEL MANTENIMIENTO OK, | W166: VISITA TECNICA | X166: 9B2ZZ628 | Y166: TIPO IV | Z166: TERRESTRE | AA166: GONZALEZ FERRER JESUS ALEXANDER | AB166: 1 | AC166: 0 | AD166: 479589 | AE166: 479589
A167: MEDELLIN | B167: NOROCCIDENTE | C167: 0004-0005 | D167: 5360 | E167: 2837402 | F167: 3007053500 | G167: INCIDENTE | H167: ANTIOQUIA | I167: ITAGUI | J167: BARRIO CALLE PRINCIPAL ITAGUI | K167: REDEBAN | L167: FO-25-1625959 | M167: 45933.62 | N167: 45934.438 | O167: NO | P167: HARDWARE | Q167: COMUNICACION | R167: MENSAJE CABLE DE RED DESCONECTADO | S167: CB UNO A UNO | T167: CB UNO A UNO | U167: EJECUTADO | V167: 03/10/2025 SE ESCALA PARA VISITA. LLAMAR ANTES DE VISITAR | 04/10/2025 SE REALIZA CONFIGURACIÓN DE PARAMETROS EQUIPO QUEDA OK | W167: VISITA TECNICA | X167: TR0VZ577 | Y167: TIPO I | Z167: TERRESTRE | AA167: HERNANDEZ CHAVARRIA JUAN CAMILO | AB167: 1 | AC167: 0 | AD167: 65960 | AE167: 65960
...

Sheet OC_BANCOLOMBIA
A1: CIUDAD SEDE | B1: ZONA | C1: CENTRO DE COSTOS LINEACOM | D1: CODIGO DANE | E1: TA/CODIGO ACTIVIDAD | F1: CODIGO CB | G1: ACTIVIDAD | H1: DEPARTAMENTO | I1: CIUDAD | J1: NOMBRE DEL CB | K1: RED | L1: FO | M1: FECHA ASIGNACION A LINEA COMUNICACIONES | N1: FECHA CIERRE DEL TICKET (DD/MM/AAAA HH:MM) | O1: ACOMETIDA | P1: SOLICITUD | Q1: DESCRIPCION | R1: FORMATO | S1: CADENA | T1: ESTADO | U1: CAUSAL ESTADO | V1: OBSERVACION | W1: FORMA DE ATENCION | X1: TERMINAL(ES) | Y1: TIPIFICACION | Z1: TIPO DE TRAYECTO | AA1: NOMBRE DEL TECNICO | AB1: DIAS DE VISITA | AC1: DIA ADICIONAL | AD1: VALOR DIAS ACTIVIDAD FACTURABLES | AE1: VALOR TOTAL
A2: CARTAGENA | B2: COSTA | C2: 0004-0001 | D2: 13673 | E2: 14105000 | F2: 3007078615 | G2: OC TRASLADO | H2: BOLIVAR | I2: SANTA CATALINA | J2: BARRIO EL MERCADO SANTA CATALI | K2: REDEBAN | L2: FO-25-1615743 | M2: 45931.333 | N2: 45933.536 | O2: NO | P2: TRASLADO | Q2: TRASLADO EXTERNO | R2: CB UNO A UNO | S2: CB UNO A UNO | T2: EJECUTADO | U2: EJECUTADO EXITOSO | V2: 02/10/2025 SE INTENTA COMUNICACIÓN A LOS NÚMEROS 3006988881 - 3160679119 Y SE ENCUENTRAN APAGADOS Y NO HAY RESPUESTA POR WHATSAPP. POR FAVOR, COMUNICARSE CON USUARIO PARA CONFIRMAR UBICACION, SOLICITUD Y PROGRAMAR VISITA TECNICA | 03/10/2025 SE REALIZA TRASLADO EXITOSO | W2: VISITA TECNICA | X2: F1MZZ644 | Y2: TIPO II | Z2: TERRESTRE | AA2: MARTINEZ SALGUEDO ANDRES AUGUSTO | AB2: 1 | AC2: 0 | AD2: 144968 | AE2: 144968
A3: MONTERIA | B3: COSTA | C3: 0004-0001 | D3: 23001 | E3: 14122320 | F3: 3007040354 | G3: OC TRASLADO | H3: CORDOBA | I3: MONTERIA | J3: BARRIO KM 12 MONTERIA | K3: REDEBAN | L3: FO-25-1615739 | M3: 45931.333 | N3: 45933.442 | O3: NO | P3: TRASLADO | Q3: TRASLADO EXTERNO | R3: UNO A UNO | S3: CB UNO A UNO | T3: EJECUTADO | U3: EJECUTADO EXITOSO | V3: 02/10/2025 EN COMUNICACIÓN CON LA SEÑORA DANNA PAOLA CASARRUBIA ORTEGA AL NÚMERO 3147811755 CONFIRMA SOLICITUD, DATOS CORRECTOS. SE ESCALA PARA VISITA | 03/10/2025 SE REALIZA TRASLADO DE CB DE DIRECCIÓN KM 12 VÍA PLANERA RICA A CLL 1 CRA 2 VDA JARAQUIEL OK SE INICIALIZA TERMINAL Y SE CONFIRMA CAMBIO DE DIRECCIÓN. CB BLOQUEADO POR ENTIDAD, NO SE REALIZAN PRUEBAS | W3: VISITA TECNICA | X3: 9A0KZ257 | Y3: TIPO I | Z3: TERRESTRE | AA3: COGOLLO VERTEL EDER LUIS | AB3: 1 | AC3: 0 | AD3: 65960 | AE3: 65960
A4: MONTERIA | B4: COSTA | C4: 0004-0001 | D4: 23001 | E4: 14123100 | F4: 3007057438 | G4: OC TRASLADO | H4: CORDOBA | I4: MONTERIA | J4: BARRIO CENTRO MONTERIA 38 | K4: REDEBAN | L4: FO-25-1615735 | M4: 45931.333 | N4: 45933.694 | O4: NO | P4: TRASLADO | Q4: TRASLADO EXTERNO | R4: CB UNO A UNO | S4: CB UNO A UNO | T4: EJECUTADO | U4: EJECUTADO EXITOSO | V4: 02/10/2025 EN COMUNICACIÓN CON LA SEÑORA ELIZABETH CARTAGENA MONTOYA AL NÚMERO 3156727761 CONFIRMA SOLICITUD, DATOS CORRECTOS. SE ESCALA PARA VISITA | 03/10/2025 SE VISITA SITIO, SE REALIZA TRASLADO DE CB A DIRECCIÓN CLL 1 B # 28 SE INICIALIZA TERMINAL Y SE VERIFICA CAMBIO DE DIRECCIÓN OK CB BLOQUEADO POR ENTIDAD, NO SE REALIZAN PRUEBAS. EQUIPOS EN SITIO. | W4: VISITA TECNICA | X4: 9CUZZ957 | Y4: TIPO I | Z4: TERRESTRE | AA4: COGOLLO VERTEL EDER LUIS | AB4: 1 | AC4: 0 | AD4: 65960 | AE4: 65960
A5: CALI | B5: SUROCCIDENTE Y EJE CAFETERO | C5: 0004-0003 | D5: 76001 | E5: 14125738 | F5: 3007064801 | G5: OC TRASLADO | H5: VALLE DEL CAUCA | I5: CALI | J5: BARRIO CRISTOBAL COLON CALI 3 | K5: REDEBAN | L5: FO-25-1636246 | M5: 45933.333 | N5: 45937.51 | O5: NO | P5: TRASLADO | Q5: TRASLADO EXTERNO | R5: CB UNO A UNO | S5: CB UNO A UNO | T5: EJECUTADO | U5: EJECUTADO EXITOSO | V5: 06/10/2025 EN COMUNICACIÓN CON EL SEÑOR CARLOS PAREDES AL NUMERO 3103793424 CONFIRMA SOLICITUD DE TRASLADO EXTERNO, INFORMA QUE LOS EQUIPOS SE ENCUENTRAN EN LA NUEVA DIRECCION, CONFIRMA DATOS, SE ESCALA PARA VISITA | 06/10/2025 EN COMUNICACIÓN CON EL SEÑOR CARLOS PAREDES AL NUMERO 3103793424 CONFIRMA SOLICITUD DE TRASLADO EXTERNO, INFORMA QUE LOS EQUIPOS SE ENCUENTRAN EN LA NUEVA DIRECCION, CONFIRMA DATOS, SE ESCALA PARA VISITA | 06/10/2025 EN COMUNICACIÓN CON EL SEÑOR CARLOS PAREDES AL NUMERO 3103793424 CONFIRMA SOLICITUD DE TRASLADO EXTERNO, INFORMA QUE LOS EQUIPOS SE ENCUENTRAN EN LA NUEVA DIRECCION, CONFIRMA DATOS, SE ESCALA PARA VISITA | 07/10/2025 SE REALIZA VISITA TÉCNICA EN LA NUEVA DIRECCIÓN, DONDE SE ENCUENTRA EL COMERCIO CARRERA 16 32B-23 SE PROCEDE A INICIALIZAR EL EQUIPO Y SE REALIZAN PRUEBAS OK | W5: VISITA TECNICA | X5: 3A003178 | Y5: TIPO I | Z5: TERRESTRE | AA5: ESCOBAR LENIS JUAN SEBASTIAN | AB5: 1 | AC5: 0 | AD5: 65960 | AE5: 65960
A6: APARTADO | B6: NOROCCIDENTE | C6: 0004-0005 | D6: 5045 | E6: 14128019 | F6: 3007052863 | G6: OC PINPAD | H6: ANTIOQUIA | I6: APARTADO | J6: DISTRICOL ANGELES DEC Y REG JB | K6: REDEBAN | L6: FO-25-1583013 | M6: 45924.333 | N6: 45931.705 | O6: NO | P6: PINPAD | Q6: PINPAD | R6: AGREGADOR | S6: DISTRICOL | T6: EJECUTADO / CANCELADO | U6: DIRECCION ERRADA | V6: 25/09/2025 POR FAVOR, COMUNICARSE CON USUARIO PARA CONFIRMAR UBICACION, SOLICITUD Y PROGRAMAR VISITA TECNICA | 01/10/2025 SE LLEGA SITIO, SE ENCUENTRA DIRECCION ERRADA Y CORRESPONSAL CERRADO. | W6: VISITA TECNICA | Y6: TIPO I | Z6: TERRESTRE | AA6: CASTRO HENAO DANIEL ESTEBAN | AB6: 1 | AC6: 0 | AD6: 65960 | AE6: 65960
A7: PASTO | B7: SUROCCIDENTE Y EJE CAFETERO | C7: 0004-0003 | D7: 86865 | E7: 14131120 | F7: 3007072653 | G7: OC TRASLADO | H7: PUTUMAYO | I7: VALLE DEL GUAMUEZ | J7: BARRIO EL EDEN VALLE DEL GUAMU | K7: REDEBAN | L7: FO-25-1637491 | M7: 45936.698 | N7: 45939.647 | O7: NO | P7: TRASLADO | Q7: TRASLADO EXTERNO | R7: CB UNO A UNO | S7: CB UNO A UNO | T7: EJECUTADO | U7: EJECUTADO EXITOSO | V7: 09/10/2025 SE REALIZA TRASLADO EXTERNO SE INICIALIZA EQUIPO SE ACTUALIZA NUEVA DIRECCIÓN COMERCIO CUENTA CON TODA LA PUBLICIDAD PRUEBAS DE FUNCIONAMIENTO EXITOSAS CB QUEDA OPERATIVO Y LEGALIZADO TRASLADO | W7: VISITA TECNICA | X7: LM0TZ838 | Y7: TIPO IV | Z7: TERRESTRE | AA7: BRAVO MADROÑERO OSCAR ESTEBAN | AB7: 1 | AC7: 0 | AD7: 479589 | AE7: 479589
A8: VALLEDUPAR | B8: COSTA | C8: 0004-0001 | D8: 20228 | E8: 14131175 | F8: 3007053172 | G8: OC TRASLADO | H8: CESAR | I8: CURUMANI | J8: BARRIO EL CENTRO CURUMANI | K8: REDEBAN | L8: FO-25-1637482 | M8: 45936.698 | N8: 45939.857 | O8: NO | P8: TRASLADO | Q8: TRASLADO EXTERNO | R8: CB UNO A UNO | S8: CB UNO A UNO | T8: EJECUTADO | U8: EJECUTADO EXITOSO | V8: 06/10/2025 EN COMUNICACIÓN CON EL SEÑOR JOHAN GALVAN VILLA AL NUMERO 3187032445 CONFIRMA SOLICITUD DE TRASLADO EXTERNO, CONFIRMA DATOS, SE ESCALA PARA VISITA | 06/10/2025 EN COMUNICACIÓN CON EL SEÑOR JOHAN GALVAN VILLA AL NUMERO 3187032445 CONFIRMA SOLICITUD DE TRASLADO EXTERNO, CONFIRMA DATOS, SE ESCALA PARA VISITA | 06/10/2025 EN COMUNICACIÓN CON EL SEÑOR JOHAN GALVAN VILLA AL NUMERO 3187032445 CONFIRMA SOLICITUD DE TRASLADO EXTERNO, CONFIRMA DATOS, SE ESCALA PARA VISITA | 09/10/2025 BUENAS TARDES SE VISITA CB Y SE LE HACE TRASLADO DE DATAFONO Y LECTOR. EL DATAFONO SE LE BORRÓ LA PLACA POR LO CUAL SE LE ESCRIBE MANUAL Y SE LE PEGA EN LA PARTE DE AL LADO. SE DEJA EQUIPO INICIALIZADO OK PERO NO HACE NINGÚNA TRANSACCIÓN YA QUE TIENE UN BLOQUEO POR PARTE DE BANCOLOMBIA, SE ANEXAN LAS FOTOS DE LA TRANSACCIÓN DE RECHAZO GENERAL | W8: VISITA TECNICA | X8: XP0OZ128 | Y8: TIPO III | Z8: TERRESTRE | AA8: BENITEZ CARVAJAL ALVARO JAVIER | AB8: 1 | AC8: 0 | AD8: 275729 | AE8: 275729
A9: MONTERIA | B9: COSTA | C9: 0004-0001 | D9: 23001 | E9: 14139886 | F9: 3007061363 | G9: OC TRASLADO | H9: CORDOBA | I9: MONTERIA | J9: BARRIO JUAN XXIII MONTERIA 5 | K9: REDEBAN | L9: FO-25-1637479 | M9: 45936.698 | N9: 45939.476 | O9: NO | P9: TRASLADO | Q9: TRASLADO EXTERNO | R9: CB UNO A UNO | S9: CB UNO A UNO | T9: EJECUTADO | U9: EJECUTADO EXITOSO | V9: 09/10/2025 SE REALIZÓ TRASLADO DE CB BANCOLOMBIA SIN NOVEDAD, PRUEBAS OK, TELECARGA DRNA. | W9: VISITA TECNICA | X9: HA00J546 | Y9: TIPO I | Z9: TERRESTRE | AA9: CALDERA SALCEDO CARLOS JULIO | AB9: 1 | AC9: 0 | AD9: 65960 | AE9: 65960
A10: PASTO | B10: SUROCCIDENTE Y EJE CAFETERO | C10: 0004-0003 | D10: 52687 | E10: 14146443 | F10: 3007068165 | G10: OC PINPAD | H10: NARIÑO | I10: SAN LORENZO | J10: BARRIO CORREGIMIENTO DEL CARME | K10: REDEBAN | L10: FO-25-1615725 | M10: 45931.333 | N10: 45937.255 | O10: NO | P10: PINPAD | Q10: PINPAD | R10: CB UNO A UNO | S10: CB UNO A UNO | T10: CANCELADO | U10: CANCELADO POR EL USUARIO | V10: 02/10/2025 POR FAVOR, COMUNICARSE CON USUARIO PARA CONFIRMAR UBICACION, SOLICITUD Y PROGRAMAR VISITA TECNICA | 07/10/2025 SE REALIZÓ COMUNICACIÓN TELEFÓNICA CON USUARIA QUIEN MANIFIESTA QUE EL CORRESPONSAL YA FUE MIGRADO A WOMPI POR LO QUE NO SE REALIZA DESPLAZAMIENTO HASTA EL CB YA QUE NO ES NECESARIO INSTALACIÓN DEL PIN PAD | W10: SOPORTE TELEFONICO | Y10: TIPO II | Z10: TERRESTRE | AA10: GUERRERO RAMIREZ OSCAR DARIO | AB10: 0 | AC10: 0 | AD10: 41241 | AE10: 41241
A11: VILLAVICENCIO | B11: REMOTAS | C11: 0004-0007 | D11: 50313 | E11: 14146818 | F11: 3007070757 | G11: OC TRASLADO | H11: META | I11: GRANADA | J11: BARRIO LA SABANA GRANADA | K11: REDEBAN | L11: FO-25-1637489 | M11: 45936.698 | N11: 45937.521 | O11: NO | P11: TRASLADO | Q11: TRASLADO EXTERNO | R11: CB UNO A UNO | S11: CB UNO A UNO | T11: EJECUTADO | U11: EJECUTADO EXITOSO | V11: 06/10/2025 EN COMUNICACIÓN CON LA SEÑORA ADRIANA OSORIO AL NUMERO 3118211343 CONFIRMA SOLICITUD DE TRASLADO EXTERNO, INFORMA QUE LOS EQUIPOS SE ENCUENTRAN EN LA NUEVA DIRECCION, CONFIRMA DATOS, SE ESCALA PARA VISITA | 06/10/2025 EN COMUNICACIÓN CON LA SEÑORA ADRIANA OSORIO AL NUMERO 3118211343 CONFIRMA SOLICITUD DE TRASLADO EXTERNO, INFORMA QUE LOS EQUIPOS SE ENCUENTRAN EN LA NUEVA DIRECCION, CONFIRMA DATOS, SE ESCALA PARA VISITA | 06/10/2025 EN COMUNICACIÓN CON LA SEÑORA ADRIANA OSORIO AL NUMERO 3118211343 CONFIRMA SOLICITUD DE TRASLADO EXTERNO, INFORMA QUE LOS EQUIPOS SE ENCUENTRAN EN LA NUEVA DIRECCION, CONFIRMA DATOS, SE ESCALA PARA VISITA | 07/10/2025 SE REALIZA TRASLADO A SOLICITUD DE CLIENTE | W11: VISITA TECNICA | X11: A30IZ492 | Y11: TIPO II | Z11: TERRESTRE | AA11: PEDREROS CONTRERAS MICHAEL STEVENS | AB11: 1 | AC11: 0 | AD11: 144968 | AE11: 144968
A12: CALI | B12: SUROCCIDENTE Y EJE CAFETERO | C12: 0004-0003 | D12: 76001 | E12: 14150250 | F12: 3007071074 | G12: OC TRASLADO | H12: VALLE DEL CAUCA | I12: CALI | J12: PTM CALI MAKAMA G´I | K12: REDEBAN | L12: FO-25-1618753 | M12: 45931.333 | N12: 45936.647 | O12: NO | P12: TRASLADO | Q12: TRASLADO EXTERNO | R12: AGREGADOR | S12: COMCARD - PTM | T12: EJECUTADO | U12: EJECUTADO EXITOSO | V12: 02/10/2025 POR FAVOR, COMUNICARSE CON USUARIO PARA CONFIRMAR UBICACION, SOLICITUD Y PROGRAMAR VISITA TECNICA | 06/10/2025 SE REALIZA VISITA TÉCNICA EN LA NUEVA DIRECCIÓN DONDE ESTÁ ESTABLECIDO EL COMERCIO CALLE 27 29- 25 SE REALIZA INICIALIZACION DEL DISPOSITIVO Y SE REALIZAN PRUEBAS EN EL DISPOSITIVO | W12: VISITA TECNICA | X12: MN00C148 | Y12: TIPO I | Z12: TERRESTRE | AA12: ESCOBAR LENIS JUAN SEBASTIAN | AB12: 1 | AC12: 0 | AD12: 65960 | AE12: 65960
A13: VALLEDUPAR | B13: COSTA | C13: 0004-0001 | D13: 20011 | E13: 14150300 | F13: 3007071108 | G13: OC PINPAD | H13: CESAR | I13: AGUACHICA | J13: AGUACHICA VILLAMARE | K13: REDEBAN | L13: FO-25-1615731 | M13: 45931.333 | N13: 45933.615 | O13: NO | P13: PINPAD | Q13: PINPAD | R13: CB UNO A UNO | S13: CB UNO A UNO | T13: EJECUTADO / CANCELADO | U13: PETICIÓN RED | V13: 02/10/2025 POR FAVOR, COMUNICARSE CON USUARIO PARA CONFIRMAR UBICACION, SOLICITUD Y PROGRAMAR VISITA TECNICA | 03/10/2025 SE LLEGA A SITIO , Y CLIENTE YA TIENE INSTALADO EL DATAFONO DE WOMPI, SE ESCALA AL COORDINADOR , DONDE MANIFIESTA Q DESISTIMOS DE LA INSTALACIÓN DEL PINPAD, VISITA FALLIDA, CLIENTE WOMPI | W13: VISITA TECNICA | Y13: TIPO IV | Z13: TERRESTRE | AA13: GELVEZ MOGOLLON JOSE ELISEO | AB13: 1 | AC13: 0 | AD13: 479589 | AE13: 479589
A14: BUCARAMANGA | B14: SANTANDERES | C14: 0004-0008 | D14: 20770 | E14: 14150333 | F14: 3007046145 | G14: OC TRASLADO | H14: CESAR | I14: SAN MARTIN | J14: PTM SAN MARTIN TIENDA Y MULTIS | K14: REDEBAN | L14: FO-25-1618772 | M14: 45931.333 | N14: 45933.418 | O14: NO | P14: TRASLADO | Q14: TRASLADO EXTERNO | R14: AGREGADOR | S14: COMCARD - PTM | T14: EJECUTADO | U14: EJECUTADO EXITOSO | V14: 02/10/2025 POR FAVOR, COMUNICARSE CON USUARIO PARA CONFIRMAR UBICACION, SOLICITUD Y PROGRAMAR VISITA TECNICA | 03/10/2025 SE TRASLADA DATAFONO ,LECTOR , CABLES Y FUENTE DE PODER, SE FORMATEA DATAFONO Y SE INCIALIZA , Y SE ACTUALIZA DIRECCIÓN OK, PRUEBAS RECHAZADAS DEBIDO A Q SE ENCUENTRA BLOQUEADO ,POR EL BANCO , SE LE INDICA AL CLIENTE Q DEBE DE LLAMAR A LA LINEA BANCOLOMBIA OARA Q LE GENEREN LA ACTIVACIÓN DEL CORRESPONSAL , TEASLADO EXITOSO | W14: VISITA TECNICA | X14: II003142 | Y14: TIPO III | Z14: TERRESTRE | AA14: GELVEZ MOGOLLON JOSE ELISEO | AB14: 1 | AC14: 0 | AD14: 275729 | AE14: 275729
A15: CALI | B15: SUROCCIDENTE Y EJE CAFETERO | C15: 0004-0003 | D15: 76001 | E15: 14154068 | F15: 3007070125 | G15: OC TRASLADO | H15: VALLE DEL CAUCA | I15: CALI | J15: PTM CALI AUTOSERVICIO EL CRUC | K15: REDEBAN | L15: FO-25-1618749 | M15: 45931.333 | N15: 45937.553 | O15: NO | P15: TRASLADO | Q15: TRASLADO EXTERNO | R15: AGREGADOR | S15: COMCARD - PTM | T15: EJECUTADO | U15: EJECUTADO EXITOSO | V15: 02/10/2025 POR FAVOR, COMUNICARSE CON USUARIO PARA CONFIRMAR UBICACION, SOLICITUD Y PROGRAMAR VISITA TECNICA | 07/10/2025 SE VISITA CORRESPONSAL SE INICIALIZAR Y SE ACTUALIZA DIRECCIÓN. TRANSACCIONES DE PRUEBA EN COMERCIO OK PERO EN CB BANCOLOMBIA ESTÁ BLOQUEADO. | W15: VISITA TECNICA | X15: A30EZ521 | Y15: TIPO I | Z15: TERRESTRE | AA15: BOLAÑOS TABORDA JORGE ENRIQUE | AB15: 1 | AC15: 0 | AD15: 65960 | AE15: 65960
A16: BUCARAMANGA | B16: SANTANDERES | C16: 0004-0008 | D16: 81065 | E16: 14158505 | F16: 3007079034 | G16: OC TRASLADO | H16: ARAUCA | I16: ARAUQUITA | J16: BARRIO OBRERO ARAUQUITA 2 | K16: REDEBAN | L16: FO-25-1637484 | M16: 45936.698 | N16: 45946.689 | O16: NO | P16: TRASLADO | Q16: TRASLADO EXTERNO | R16: CB UNO A UNO | S16: CB UNO A UNO | T16: EJECUTADO | U16: EJECUTADO EXITOSO | V16: 14/10/2025 POR FAVOR, COMUNICARSE CON USUARIO PARA CONFIRMAR UBICACION, SOLICITUD Y PROGRAMAR VISITA TECNICA | 14/10/2025 ORDEN CREADA SIN NÚMERO DE CONTACTO, SE ESCALA A COORDINADOR DE ZONA, ACTIVIDAD DE ESTARÁ EJECUTANDO EN TRANSCURSO DE LA SEMANA POR TEMAS DE ORDEN PÚBLICO Y DISPONIBILIDAD DE VUELO. | 16/10/2025 SE REALIZA TRASLADO EXTERNO A LA SIGUIENTE DIRECCIÓN CRA 6 # 6-83, LIMPIEZA DE EQUIPOS OK, CORRESPONSAL SE ENCUENTRA BLOQUEADO POR EL BANCO, SE HACE SOLICITUD 2 VECES DE DESBLOQUEO AL BANCO Y NO FUE EXITOSA | W16: VISITA TECNICA | X16: SASZZ609 | Y16: TIPO V | Z16: AEREO | AA16: MARTINEZ FLOREZ DONIS ALBERTO | AB16: 1 | AC16: 0 | AD16: 988463 | AE16: 988463
A17: MONTERIA | B17: COSTA | C17: 0004-0001 | D17: 23675 | E17: 14158694 | F17: 3007080398 | G17: OC TRASLADO | H17: CORDOBA | I17: SAN BERNARDO DEL VIENTO | J17: BARRIO 10 DE AGOSTO SAN BERNARDO DEL VIENTO | K17: REDEBAN | L17: FO-25-1637475 | M17: 45936.698 | N17: 45939.526 | O17: NO | P17: TRASLADO | Q17: TRASLADO EXTERNO | R17: UNO A UNO | S17: UNO A UNO | T17: EJECUTADO | U17: EJECUTADO EXITOSO | V17: 06/10/2025 POR FAVOR, COMUNICARSE CON USUARIO PARA CONFIRMAR UBICACION, SOLICITUD Y PROGRAMAR VISITA TECNICA | 09/10/2025 SE REALIZA TRASLADO DE CB, SE INSTALA DATÁFONO, ACCESORIOS Y PUBLICIDAD EN LA NUEVA DIRECCIÓN, SE INICIALIZA TERMINAL PARA DEJAR NUEVA DIRECCIÓN Y SE DEJA CB LISTO PARA OPERACIONES. | W17: VISITA TECNICA | X17: LBZZZ656 | Y17: TIPO II | Z17: TERRESTRE | AA17: CASSIANI PEREZ RAUL RAMIRO | AB17: 1 | AC17: 0 | AD17: 144968 | AE17: 144968
A18: CUCUTA | B18: SANTANDERES | C18: 0004-0008 | D18: 54001 | E18: 14163632 | F18: 3007079234 | G18: OC TRASLADO | H18: NORTE DE SANTANDER | I18: CUCUTA | J18: DISTRICOL LUCHI 2 MULTISERVI | K18: REDEBAN | L18: FO-25-1618757 | M18: 45931.333 | N18: 45936.652 | O18: NO | P18: TRASLADO | Q18: TRASLADO EXTERNO | R18: AGREGADOR | S18: DISTRICOL | T18: EJECUTADO | U18: EJECUTADO EXITOSO | V18: 02/10/2025 POR FAVOR, COMUNICARSE CON USUARIO PARA CONFIRMAR UBICACION, SOLICITUD Y PROGRAMAR VISITA TECNICA | 06/10/2025 SE VISITA COMERCIO, SE REALIZA TRASLADO EXITOSO, SE HACEN PRUEBAS EXITOSA, CB OPERATIVO. | W18: VISITA TECNICA | X18: A4WZZ111 | Y18: TIPO I | Z18: TERRESTRE | AA18: NARANJO AFANADOR RUBEN JESUS | AB18: 1 | AC18: 0 | AD18: 65960 | AE18: 65960
A19: CALI | B19: SUROCCIDENTE Y EJE CAFETERO | C19: 0004-0003 | D19: 76520 | E19: 14163755 | F19: 3007049028 | G19: OC TRASLADO | H19: VALLE DEL CAUCA | I19: PALMIRA | J19: DISTRICOL EDDYJAID | K19: REDEBAN | L19: FO-25-1618743 | M19: 45931.333 | N19: 45937.605 | O19: NO | P19: TRASLADO | Q19: TRASLADO EXTERNO | R19: AGREGADOR | S19: DISTRICOL | T19: EJECUTADO | U19: EJECUTADO EXITOSO | V19: 02/10/2025 POR FAVOR, COMUNICARSE CON USUARIO PARA CONFIRMAR UBICACION, SOLICITUD Y PROGRAMAR VISITA TECNICA | 07/10/2025 EN LA VISITA TÉCNICA SE ENCONTRÓ QUE YA EL CLIENTE HABÍA REALIZADO EL TRASLADO DE LOS EQUIPOS Y PUBLICIDAD PARA LA NUEVA DIRECCIÓN,SE FORMATEO EL DATÁFONO POR MEMORIA LLENA, SE INSTALA EL SISTEMA OPERATIVO Y VERSIÓN 9.90,SE REALIZÓ LA CONFIGURACIÓN E INICIALIZACIÓN OK,SE CREARON LOS USUARIOS Y SE REALIZARON LAS PRUEBAS DEJANDO EL SERVICIO OPERANDO SIN FALLAS Y SIN NOVEDAD. | W19: VISITA TECNICA | X19: AD00O665 | Y19: TIPO I | Z19: TERRESTRE | AA19: SANCHEZ URREGO ROBINSON DAVID | AB19: 1 | AC19: 0 | AD19: 65960 | AE19: 65960
A20: IBAGUE | B20: REMOTAS | C20: 0004-0007 | D20: 73001 | E20: 14163823 | F20: 3007079892 | G20: OC TRASLADO | H20: TOLIMA | I20: IBAGUE | J20: DISTRICOL MISCELANEA ANGELLY | K20: REDEBAN | L20: FO-25-1618761 | M20: 45931.333 | N20: 45938.463 | O20: NO | P20: TRASLADO | Q20: TRASLADO EXTERNO | R20: AGREGADOR | S20: DISTRICOL | T20: EJECUTADO | U20: EJECUTADO EXITOSO | V20: 02/10/2025 POR FAVOR, COMUNICARSE CON USUARIO PARA CONFIRMAR UBICACION, SOLICITUD Y PROGRAMAR VISITA TECNICA | 08/10/2025 SE REALIZA TRASLADO EXTERNO DE DIRECCIÓN ANTIGUA MZ 70 CA 11 ETAPA 3 A DIRECCIÓN NUEVA MZ M CASA 1, SE REALIZA PRUEBAS DE FUNCIONAMIENTO OK; CUBRE CLAVE INSTALADO. | W20: VISITA TECNICA | X20: SAUZZ972 | Y20: TIPO I | Z20: TERRESTRE | AA20: BARRAGAN TAFUR EDWIN ESTEBAN | AB20: 1 | AC20: 0 | AD20: 65960 | AE20: 65960
A21: IBAGUE | B21: REMOTAS | C21: 0004-0007 | D21: 17380 | E21: 14163923 | F21: 3007059786 | G21: OC TRASLADO | H21: CALDAS | I21: LA DORADA | J21: DISTRICOL BELLEZA Y COSMETICOS | K21: REDEBAN | L21: FO-25-1618746 | M21: 45931.333 | N21: 45933.711 | O21: NO | P21: TRASLADO | Q21: TRASLADO EXTERNO | R21: AGREGADOR | S21: DISTRICOL | T21: EJECUTADO | U21: EJECUTADO EXITOSO | V21: 02/10/2025 EN COMUNICACIÓN CON EL SEÑOR CRISTIAN CAMILO LOZANO ÁVILA AL NÚMERO 3506772016 CONFIRMA SOLICITUD, DATOS CORRECTOS. SE ESCALA PARA VISITA | 03/10/2025 SE ACTUALIZA DATÁFONO Y SE INSTALA LO QUE EL CLIENTE TIENE EN EL NUEVO COMERCIO. SE HACEN LAS PRUEBAS DE TRANSACCIONES TODO OK | W21: VISITA TECNICA | X21: FUA0B326 | Y21: TIPO III | Z21: TERRESTRE | AA21: VARGAS HERRERA JHON JAIRO | AB21: 1 | AC21: 0 | AD21: 275729 | AE21: 275729
A22: NEIVA | B22: REMOTAS | C22: 0004-0007 | D22: 41548 | E22: 14164373 | F22: 3007034738 | G22: OC TRASLADO | H22: HUILA | I22: PITAL | J22: BARRIO CENTRO PITAL | K22: REDEBAN | L22: FO-25-1637472 | M22: 45936.698 | N22: 45937.507 | O22: NO | P22: TRASLADO | Q22: TRASLADO EXTERNO | R22: CB UNO A UNO | S22: CB UNO A UNO | T22: EJECUTADO | U22: EJECUTADO EXITOSO | V22: 06/10/2025 EN COMUNICACIÓN CON LA SEÑORA CAROLINA CAICEDO AL NUMERO 3235232897 CONFIRMA SOLICITUD DE TRASLADO EXTERNO, INFORMA QUE LOS EQUIPOS SE ENCUENTRAN EN LA NUEVA DIRECCION, CONFIRMA DATOS, SE ESCALA PARA VISITA | 06/10/2025 EN COMUNICACIÓN CON LA SEÑORA CAROLINA CAICEDO AL NUMERO 3235232897 CONFIRMA SOLICITUD DE TRASLADO EXTERNO, INFORMA QUE LOS EQUIPOS SE ENCUENTRAN EN LA NUEVA DIRECCION, CONFIRMA DATOS, SE ESCALA PARA VISITA | 06/10/2025 EN COMUNICACIÓN CON LA SEÑORA CAROLINA CAICEDO AL NUMERO 3235232897 CONFIRMA SOLICITUD DE TRASLADO EXTERNO, INFORMA QUE LOS EQUIPOS SE ENCUENTRAN EN LA NUEVA DIRECCION, CONFIRMA DATOS, SE ESCALA PARA VISITA | 07/10/2025 SE REALIZA VISITA AL PUNTO, SE TRASLADA CON EXITO BASE DATAFONO, LECTOR DE BARRAS , AVISO EXTERIOR, SE INICIALIZA EQUIPO SE ACTUALIZA DIRECCIÓN. CB OPERATIVO. | W22: VISITA TECNICA | X22: BL01F937 | Y22: TIPO III | Z22: TERRESTRE | AA22: DEVIA REINOSO JUAN CARLOS | AB22: 1 | AC22: 0 | AD22: 275729 | AE22: 275729
A23: MEDELLIN | B23: NOROCCIDENTE | C23: 0004-0005 | D23: 5266 | E23: 14166279 | F23: 3007049253 | G23: OC PINPAD | H23: ANTIOQUIA | I23: ENVIGADO | J23: DISTRICOL BURBUJA LA TECNO EQ | K23: REDEBAN | L23: FO-25-1618769 | M23: 45931.333 | N23: 45936.421 | O23: NO | P23: PINPAD | Q23: PINPAD | R23: AGREGADOR | S23: DISTRICOL | T23: EJECUTADO | U23: EJECUTADO EXITOSO | V23: 02/10/2025 POR FAVOR, COMUNICARSE CON USUARIO PARA CONFIRMAR UBICACION, SOLICITUD Y PROGRAMAR VISITA TECNICA | 06/10/2025 SE REALIZA INSTALACIÓN DE PINPAD | W23: VISITA TECNICA | X23: 9C00Q103 | Y23: TIPO I | Z23: TERRESTRE | AA23: HERNANDEZ CHAVARRIA JUAN CAMILO | AB23: 1 | AC23: 0 | AD23: 65960 | AE23: 65960
A24: MONTERIA | B24: COSTA | C24: 0004-0001 | D24: 23162 | E24: 14167240 | F24: 3007039909 | G24: OC TRASLADO | H24: CORDOBA | I24: CERETE | J24: ARRIO RETIRO DE LOS INDIOS CE | K24: REDEBAN | L24: FO-25-1637487 | M24: 45936.698 | N24: 45939.618 | O24: NO | P24: TRASLADO | Q24: TRASLADO EXTERNO | R24: CB UNO A UNO | S24: CB UNO A UNO | T24: EJECUTADO | U24: EJECUTADO EXITOSO | V24: 06/10/2025 POR FAVOR, COMUNICARSE CON USUARIO PARA CONFIRMAR UBICACION, SOLICITUD Y PROGRAMAR VISITA TECNICA | 09/10/2025 SE REALIZÓ TRASLADO DE CB BANCOLOMBIA SIN NOVEDAD, PRUEBAS OK, TELECARGA DRNA. SÓLO SE ENCONTRÓ AVISO EXTERIOR. EL CB SE ENCUENTRA BLOQUEADO POR EL BANCO. | W24: VISITA TECNICA | X24: AB0DZ747 | Y24: TIPO I | Z24: TERRESTRE | AA24: CALDERA SALCEDO CARLOS JULIO | AB24: 1 | AC24: 0 | AD24: 65960 | AE24: 65960
A25: VALLEDUPAR | B25: COSTA | C25: 0004-0001 | D25: 20570 | E25: 14167886 | F25: 3007075415 | G25: OC TRASLADO | H25: CESAR | I25: PUEBLO BELLO | J25: BARRIO LOMITA BLANCA PUEBLO BE | K25: REDEBAN | L25: FO-25-1637477 | M25: 45936.698 | N25: 45938.76 | O25: NO | P25: TRASLADO | Q25: TRASLADO EXTERNO | R25: CB UNO A UNO | S25: CB UNO A UNO | T25: EJECUTADO | U25: EJECUTADO EXITOSO | V25: 06/10/2025 EN COMUNICACIÓN CON LA SEÑORA YESICA PATRICIA AL NUMERO 3113216037 CONFIRMA SOLICITUD DE TRASLADO EXTERNO , CONFIRMA DATOS E INFORMA QUE LOS EQUIPOS SEENCUENTRAN EN LA NUEVA DIRECCION, SE ESCALA PARA VISITA | 06/10/2025 EN COMUNICACIÓN CON LA SEÑORA YESICA PATRICIA AL NUMERO 3113216037 CONFIRMA SOLICITUD DE TRASLADO EXTERNO , CONFIRMA DATOS E INFORMA QUE LOS EQUIPOS SEENCUENTRAN EN LA NUEVA DIRECCION, SE ESCALA PARA VISITA | 06/10/2025 EN COMUNICACIÓN CON LA SEÑORA YESICA PATRICIA AL NUMERO 3113216037 CONFIRMA SOLICITUD DE TRASLADO EXTERNO , CONFIRMA DATOS E INFORMA QUE LOS EQUIPOS SEENCUENTRAN EN LA NUEVA DIRECCION, SE ESCALA PARA VISITA | 08/10/2025 BUENAS TARDES SE VISITA CB Y SE LE REALIZA EL TRASLADO DE EQUIPO CON SU DATAFONO Y LA PUBLICIDAD | W25: VISITA TECNICA | X25: V1009471 | Y25: TIPO III | Z25: TERRESTRE | AA25: BENITEZ CARVAJAL ALVARO JAVIER | AB25: 1 | AC25: 0 | AD25: 275729 | AE25: 275729
... A54: VILLAVICENCIO | B54: REMOTAS | C54: 0004-0007 | D54: 50001 | E54: 14214141 | F54: 3007047291 | G54: OC TRASLADO | H54: META | I54: VILLAVICENCIO | J54: BARRIO CANTARRANA VILLAVICENCI | K54: REDEBAN | L54: FO-25-1726249 | M54: 45953.516 | N54: 45954.463 | O54: NO | P54: TRASLADO | Q54: TRASLADO EXTERNO | R54: UNO A UNO | S54: CB UNO A UNO | T54: EJECUTADO | U54: EJECUTADO EXITOSO | V54: 23/10/2025 SE CONFIRMAN DATOS Y SOLICITUD CON EL USUARIO, SE ESCALA PARA VIISTA-POR FAVOR LLAMAR ANTES DE DESPLAZARSE | 24/10/2025 SE REALIZA INICIALIZACION DE TERMINAL CB, NO SE ENCUENTRA FLANGED, NO HAY DISPLAY LEGAL, AVISO EXTERIOR AMARILLO EN MAL ESTADO, PRUEBAS DE TX FALLIDAS POR SOLICITUD DE TRASLADO. | W54: VISITA TECNICA | X54: TR00D599 | Y54: TIPO I | Z54: TERRESTRE | AA54: MURCIA HERNANDEZ HARVEY IGNACIO | AB54: 1 | AC54: 0 | AD54: 65960 | AE54: 65960
A55: SANTA MARTA | B55: COSTA | C55: 0004-0001 | D55: 47245 | E55: 14215355 | F55: 3007081073 | G55: OC TRASLADO | H55: MAGDALENA | I55: EL BANCO | J55: BARRIO MANZANARES EL BANCO | K55: REDEBAN | L55: FO-25-1726268 | M55: 45953.516 | N55: 45960.65 | O55: NO | R55: UNO A UNO | S55: UNO A UNO | T55: EJECUTADO | U55: EJECUTADO EXITOSO | V55: 23/10/2025 SE CONFIRMAN DATOS Y SOLICITUD CON EL USUARIO, SE ESCALA PARA VIISTA-POR FAVOR LLAMAR ANTES DE DESPLAZARSE | 30/10/2025 BUENAS TARDES SE VISITA CB Y SE LE HACE EL TRASLADO OK , SE ACTUALIZA DIRECCIÓN Y CAMARA DE COMERCIO. SE INCIALIZA EL EQUIPO OK PERO PERO AL REALIZAR LAS TRANSACCIÓNES DE PRUEBAS SALE RECHAZO GENERAL DEBIDO AL BLOQUEO QUE TIENE | W55: VISITA TECNICA | X55: SGZZZ968 | Y55: TIPO IV | Z55: TERRESTRE | AA55: BENITEZ CARVAJAL ALVARO JAVIER | AB55: 1 | AC55: 0 | AD55: 479589 | AE55: 479589
A56: CALI | B56: SUROCCIDENTE Y EJE CAFETERO | C56: 0004-0003 | D56: 76364 | E56: 14215940 | F56: 3007071851 | G56: OC TRASLADO | H56: VALLE DEL CAUCA | I56: JAMUNDI | J56: JAMUNDI VILLA PYME | K56: REDEBAN | L56: FO-25-1710734 | M56: 45950.721 | N56: 45952.732 | O56: NO | P56: TRASLADO | Q56: TRASLADO EXTERNO | R56: CB UNO A UNO | S56: CB UNO A UNO | T56: EJECUTADO | U56: EJECUTADO EXITOSO | V56: 21/10/2025 EN COMUNICACIÓN CON LA SRA LORENA FRANCO SEPULVEDA AL NÚMERO 3212277007 NOS CONFIRMA LA SOLICITUD, DATOS CORRECTOS, SE ESCALA PARA VISITA | 27/10/2025 SE VISITA CORRESPONSAL Y SE PROCEDE A EJECUTAR TRASLADO, SE INICIALIZA Y QUEDA DIRECCIÓN ACTUALIZADA. TRANSACCIONES DE PRUEBA EXITOSAS. | W56: VISITA TECNICA | X56: A30TZ909 | Y56: TIPO II | Z56: TERRESTRE | AA56: BOLAÑOS TABORDA JORGE ENRIQUE | AB56: 1 | AC56: 0 | AD56: 144968 | AE56: 144968
A57: CALI | B57: SUROCCIDENTE Y EJE CAFETERO | C57: 0004-0003 | D57: 76109 | E57: 14217616 | F57: 3007072976 | G57: OC TRASLADO | H57: VALLE DEL CAUCA | I57: BUENAVENTURA | J57: EL CARMEN BUENAVENTURA | K57: REDEBAN | L57: FO-25-1710724 | M57: 45950.721 | N57: 45954.585 | O57: NO | P57: TRASLADO | Q57: TRASLADO EXTERNO | R57: CB UNO A UNO | S57: CB UNO A UNO | T57: EJECUTADO | U57: EJECUTADO EXITOSO | V57: 21/10/2025 EN COMUNICACIÓN CON LA SRA MARGY MORALES AL NÚMERO 3184378463 NOS CONFIRMA LA SOLICITUD, DATOS CORRECTOS. SE ESCALA PARA VISITA, POR FAVOR LLAMAR ANTES DE DESPLAZARSE | 24/10/2025 SE REALIZA TRASLADO EXTERNO DE CB BANCOLOMBIA PURO, SE TRASLADAN EQUIPOS, ACCESORIOS Y PUBLICIDAD, SE INICIALIZA TERMINAL Y CARGA INFORMACIÓN CON LA DIRECCIÓN ACTUALIZADA. SE REALIZAN PRUEBAS OK. | W57: VISITA TECNICA | X57: LN00R314 | Y57: TIPO III | Z57: TERRESTRE | AA57: MONTERO MUESES GIAN CARLO | AB57: 1 | AC57: 0 | AD57: 275729 | AE57: 275729
A58: VILLAVICENCIO | B58: REMOTAS | C58: 0004-0007 | D58: 50568 | E58: 14218395 | F58: 3007064588 | G58: OC TRASLADO | H58: META | I58: PUERTO GAITAN | J58: BARRIO VILLA ORTIZ PUERTO GAIT | K58: REDEBAN | L58: FO-25-1726259 | M58: 45953.516 | N58: 45957.589 | O58: NO | P58: TRASLADO | Q58: TRASLADO EXTERNO | R58: CB UNO A UNO | S58: CB UNO A UNO | T58: EJECUTADO | U58: EJECUTADO EXITOSO | V58: 23/10/2025 SE INTENTA COMUNICACIÓN AL NÚMERO 3177632125 PERO NO HAY CONTACTO | 23/10/2025 SE CONFIRMAN SOLICITUD CON EL USUARIO, DATOS OK, SE ESCALA PARA VISITA | 27/10/2025 SE REALIZA INICIALIZACION DE PLACA, SE ACTUALIZA DIRECCIÓN OK, CB CON BLOQUEO POR SOLICITUD DE TRASLADO EXTERNO, NO SE REALIZAN PRUEBAS POR RECHAZO GENERAL POR BLOQUEO. | W58: VISITA TECNICA | X58: 1A003544 | Y58: TIPO III | Z58: TERRESTRE | AA58: MURCIA HERNANDEZ HARVEY IGNACIO | AB58: 1 | AC58: 0 | AD58: 275729 | AE58: 275729
A59: MEDELLIN | B59: NOROCCIDENTE | C59: 0004-0005 | D59: 5736 | E59: 14220543 | F59: 3007080620 | G59: OC TRASLADO | H59: ANTIOQUIA | I59: SEGOVIA | J59: BARRIO LA MADRE SEGOVIA | K59: REDEBAN | L59: FO-25-1710735 | M59: 45950.721 | N59: 45957.698 | O59: NO | P59: TRASLADO | Q59: TRASLADO EXTERNO | R59: UNO A UNO | S59: UNO A UNO | T59: EJECUTADO | U59: EJECUTADO EXITOSO | V59: 21/10/2025 EN COMUNICACIÓN CON LA SRA NORAIMA ANDREA ROJAS TAPIAS AL NÚMERO 3123826065 NOS CONFIRMA LA SOLICITUD, DATOS CORRECTOS. SE ESCALA PARA VISITA, POR FAVOR LLAMAR ANTES DE DESPLAZARSE | 27/10/2025 SE HACE TRASLADO EXITOSAMENTE | W59: VISITA TECNICA | X59: V6ZZZ807 | Y59: TIPO IV | Z59: TERRESTRE | AA59: RUA ALVAREZ RICHARD ANDRES | AB59: 1 | AC59: 0 | AD59: 479589 | AE59: 479589
A60: CUCUTA | B60: SANTANDERES | C60: 0004-0008 | D60: 54874 | E60: 14221982 | F60: 3007077332 | G60: OC TRASLADO | H60: NORTE DE SANTANDER | I60: VILLA DEL ROSARIO | J60: BARRIO BELLAVISTA VILLA DEL RO | K60: REDEBAN | L60: FO-25-1726247 | M60: 45953.516 | N60: 45954.718 | O60: NO | P60: TRASLADO | Q60: TRASLADO EXTERNO | R60: CB UNO A UNO | S60: CB UNO A UNO | T60: EJECUTADO | U60: EJECUTADO EXITOSO | V60: 23/10/2025 EN COMUNICACÓN CON LA SRA LIZMAR LOPEZ AL NÚMERO 3215906394, NOS CONFIRMA LA SOLICITUD, DATOS CORRECTOS, SE ESCALA PARA VISITA POR FAVOR LLAMAR ANTES DE DESPLAZARSE | 24/10/2025 SE REALIZA VISITA, SE REALIZA TRASLADO EXTERNO, NO SE REALIZAN PRUEBAS YA QUE EL PUNTO SE ENCUENTRA BLOQUEADO. | W60: VISITA TECNICA | X60: FACZZ909 | Y60: TIPO I | Z60: TERRESTRE | AA60: PACHECO BUITRAGO JAVIER ALONSO | AB60: 1 | AC60: 0 | AD60: 65960 | AE60: 65960
A61: BUCARAMANGA | B61: SANTANDERES | C61: 0004-0008 | D61: 68167 | E61: 14224711 | F61: 3007074789 | G61: OC TRASLADO | H61: SANTANDER | I61: CHARALA | J61: BARRIO CENTRO CHARALA 2 | K61: REDEBAN | L61: FO-25-1726262 | M61: 45953.516 | N61: 45959.447 | O61: SI | P61: TRASLADO | Q61: TRASLADO EXTERNO | R61: CB UNO A UNO | S61: CB UNO A UNO | T61: EJECUTADO | U61: EJECUTADO EXITOSO | V61: 23/10/2025 EN COMUNICACIÓN CON EL ESPOSO DE LA SRA BEATRIZ DURAN AL NÚMERO 3204967424 NOS CONFIRMA LA OLICITUD, DATOS CORRECTOS. SE ESCALA PARA VISITA | 29/10/2025 SE REALIZA VISITA AL COMERCIO DIRECCIÓN DADA POR LA RED SE VALIDA Y SE REALIZA TRASLADO DEL CORRESPONSAL BANCOLOMBIA PURO SE INSTALA AVISO FLANGER DISPLAY QUE YA TENÍA EL USUARIO EN EL ANTERIOR COMERCIO O DIRECCIÓN SE REALIZA LA DEBIDA APERTURA DE LA TERMINAL SE INICIALIZA Y SE HACEN PRUEBAS DEJANDO CORRESPONSAL FUNCIONANDO CON LA DIRECCIÓN ACTUALIZADA. SE REALIZÓ EXTENSIÓN DE 6 M DE CABLE UTP YA QUE EL MÓDEM ESTABA RETIRADO DE DONDE IBA A QUEDAR EL DATÁFONO. | W61: VISITA TECNICA | X61: MNPZZ739 | Y61: TIPO IV | Z61: TERRESTRE | AA61: GONZALEZ ESTUPIÑAN YEISON WALTER ANTONIO | AB61: 1 | AC61: 0 | AD61: 479589 | AE61: 479589
A62: BOGOTA | B62: CUNDINAMARCA | C62: 0004-0004 | D62: 11001 | E62: 14225971 | F62: 3007031754 | G62: OC TRASLADO | H62: CUNDINAMARCA | I62: BOGOTA | J62: BARRIO BOSA 11 BOGOTA | K62: REDEBAN | L62: FO-25-1710726 | M62: 45950.721 | N62: 45951.722 | O62: NO | P62: TRASLADO | Q62: TRASLADO EXTERNO | R62: CB UNO A UNO | S62: CB UNO A UNO | T62: EJECUTADO | U62: EJECUTADO EXITOSO | V62: 21/10/2025 EN COMUNICACIÓN CON ALEXANDRA SANTIESTEBAN JIMENEZ AL NÚMERO 3102694293 NOS CONFIRMA LA SOLICITUD, DATOS CORRECTOS, SE ESCALA PARA VISITA | 21/10/2025 SE LLEGA A COMERCIO SE REALIZA TRASLADO DE EQUIPO ÉXITOSO SE REALIZAN PRUEBAS OK | W62: VISITA TECNICA | X62: 1111I264 | Y62: TIPO I | Z62: TERRESTRE | AA62: INFANTE SIERRA MANUEL FERNANDO | AB62: 1 | AC62: 0 | AD62: 65960 | AE62: 65960
A63: BOGOTA | B63: CUNDINAMARCA | C63: 0004-0004 | D63: 11001 | E63: 14226409 | F63: 3007051641 | G63: OC PINPAD | H63: CUNDINAMARCA | I63: BOGOTA | J63: BARRIO ONCE DE NOVIEMBRE BOGOT | K63: REDEBAN | L63: FO-25-1697842 | M63: 45945.704 | N63: 45947.493 | O63: NO | P63: PINPAD | Q63: PINPAD | R63: CB UNO A UNO | S63: CB UNO A UNO | V63: 17/10/2025 EN COMUNICACIÓN CON LA SEÑORA AIDE AL NÚMERO 3203946679 INFORMA QUE YA CUENTA CON EL DATAFONO WOMPI, HA ESTADO TRABAJANDO CON LAS DOS REDES, SE LE INDICA QUE NO ES POSIBLE REALIZAR LA INSTALACIÓN DEL PIN PAD YA QUE EL CB FUE MIGRADO, SE PROCEDE A CERRAR ESTE CASO CON LA INFORMACIÓN BRINDADA | 17/10/2025 EN COMUNICACIÓN CON LA SEÑORA AIDE AL NÚMERO 3203946679 INFORMA QUE YA CUENTA CON EL DATAFONO WOMPI, HA ESTADO TRABAJANDO CON LAS DOS REDES, SE LE INDICA QUE NO ES POSIBLE REALIZAR LA INSTALACIÓN DEL PIN PAD YA QUE EL CB FUE MIGRADO, SE PROCEDE A CERRAR ESTE CASO CON LA INFORMACIÓN BRINDADA | 17/10/2025 EN COMUNICACIÓN CON LA SEÑORA AIDE AL NÚMERO 3203946679 INFORMA QUE YA CUENTA CON EL DATAFONO WOMPI, HA ESTADO TRABAJANDO CON LAS DOS REDES, SE LE INDICA QUE NO ES POSIBLE REALIZAR LA INSTALACIÓN DEL PIN PAD YA QUE EL CB FUE MIGRADO, SE PROCEDE A CERRAR ESTE CASO CON LA INFORMACIÓN BRINDADA | W63: SOPORTE TELEFONICO | Y63: TIPO I | Z63: TERRESTRE | AA63: GARCIA CHAVARRIA TATIANA EDELMIRA | AB63: 0 | AC63: 0 | AD63: 41241 | AE63: 41241
A64: PASTO | B64: SUROCCIDENTE Y EJE CAFETERO | C64: 0004-0003 | D64: 86568 | E64: 14227652 | F64: 3007032486 | G64: OC TRASLADO | H64: PUTUMAYO | I64: PUERTO ASIS | J64: DISTRICOL SERVIPLOTTER PUERTO | K64: REDEBAN | L64: FO-25-1710744 | M64: 45950.712 | N64: 45952.541 | O64: NO | P64: TRASLADO | Q64: TRASLADO EXTERNO | R64: AGREGADOR | S64: DISTRICOL | T64: EJECUTADO | U64: EJECUTADO EXITOSO | V64: 21/10/2025 EN COMUNICACIÓN CON EL SR JAIR YOVANY RUIZ HERNANDEZ AL NÚMERO 3102442197 NOS CONFIRMA LA SOLICITUD, DATOS CORRECTOS, SE ESCALA PARA VISITA | 22/10/2025 SE VISITA EL CB EN NUEVA DIRECCIÓN PARA HACER EFECTIVO EL TRASLADO, SE INICIALIZA OK, CAMBIO DE DIRECCIÓN OK, PRUEBAS OK, CB OPERATIVO | W64: VISITA TECNICA | X64: 11GZZ455 | Y64: TIPO IV | Z64: TERRESTRE | AA64: GUERRERO RAMIREZ OSCAR DARIO | AB64: 1 | AC64: 0 | AD64: 479589 | AE64: 479589
A65: CUCUTA | B65: SANTANDERES | C65: 0004-0008 | D65: 54001 | E65: 14227681 | F65: 3007071024 | G65: OC TRASLADO | H65: NORTE DE SANTANDER | I65: CUCUTA | J65: DISTRICOL MAKARENA CEN BELLEZA | K65: REDEBAN | L65: FO-25-1731950 | FO-25-1710747 | M65: 45950.712 | N65: 45957.416 | O65: NO | P65: TRASLADO | Q65: TRASLADO EXTERNO | R65: AGREGADOR | S65: DISTRICOL | T65: EJECUTADO | EJECUTADO / CANCELADO | U65: EJECUTADO EXITOSO | V65: 27/10/2025 SE REALIZÓ VISITA A LA DIRECCIÓN ASIGNADA PARA EL TRASLADO Y SE REALIZA TRASLADO DE DATAFONO, LECTORA SE REALIZA INCIALIZACION DE EQUIPO, DIRECCIÓN OK, PRUEBAS EXITOSAS | W65: VISITA TECNICA | X65: MN00C098 | Y65: TIPO I | Z65: TERRESTRE | AA65: MORA VEGA JEAMPIER | AB65: 1 | AC65: 0 | AD65: 65960 | AE65: 65960
A66: MEDELLIN | B66: NOROCCIDENTE | C66: 0004-0005 | D66: 5615 | E66: 14230893 | F66: 3007080328 | G66: OC TRASLADO | H66: ANTIOQUIA | I66: RIONEGRO | J66: PTM RIONEGRO DROGUERIA FARMASA | K66: REDEBAN | L66: FO-25-1710742 | M66: 45950.712 | N66: 45952.459 | O66: NO | P66: TRASLADO | Q66: TRASLADO EXTERNO | R66: AGREGADOR | S66: COMCARD - PTM | T66: EJECUTADO | U66: EJECUTADO EXITOSO | V66: 21/10/2025 EN COMUNICACIÓN CON EL SR GONZALO DE JESUS PEREZ VILLA A NÚMERO 3227313531 NOS CONFIRMA LA SOLICITUD, DATOS CORRECTOS. SE ESCALA PARA VISITA, POR FAVOR LLAMAR ANTES DE DESPLAZARSE | 22/10/2025 SE REALIZA TRASLADO DE CORRESPONSAL EL CLIENTE YA SE ENCUENTRA UBICADO EN LA NUEVA DIRECCIÓN DE REALIZAR CONFIGURACIÓN DEL EQUIPO Y SE ACTUALIZA INFORMACIÓN SE REALIZAN PRUEBAS EXITOSAS SERVICIO OPERATIVO | W66: VISITA TECNICA | X66: FFZZZ035 - FCZZZ081 | Y66: TIPO II | Z66: TERRESTRE | AA66: ZAPATA LOPEZ EDWARD ASDRUBAL | AB66: 1 | AC66: 0 | AD66: 144968 | AE66: 144968
A67: BOGOTA | B67: CUNDINAMARCA | C67: 0004-0004 | D67: 11001 | E67: 14230955 | F67: 3007080470 | G67: OC PINPAD | H67: CUNDINAMARCA | I67: BOGOTA | J67: DISTRICOL NIZA COMUNICACIONES | K67: REDEBAN | L67: FO-25-1705993 | M67: 45947.556 | N67: 45951.446 | O67: NO | P67: PINPAD | Q67: PINPAD | R67: AGREGADOR | S67: DISTRICOL | T67: EJECUTADO | U67: EJECUTADO EXITOSO | V67: 20/10/2025 SE INTENTA COMUNICACIÓN AL NÚMERO 3108062793 PERO NO HAY CONTACTO,SE ESCALA AL COORDINADOR DE ZONA PARA VISITA | 21/10/2025 ME RECIBEN SIN NOVEDAD | 21/10/2025 SE REALIZA VISITA DE CAMPO PARA REALIZAR INSTALACIÓN DE PIN PAD, PARÁMETROS OKAY USUARIOS OKAY A CONFORMIDAD DEL CLIENTE | W67: VISITA TECNICA | X67: SDZZZ943 | Y67: TIPO I | Z67: TERRESTRE | AA67: ARIAS QUILINDO JULIAN | AB67: 1 | AC67: 0 | AD67: 65960 | AE67: 65960
A68: TUNJA | B68: SANTANDERES | C68: 0004-0008 | D68: 15759 | E68: 14234802 | F68: 3007013276 | G68: OC TRASLADO | H68: BOYACA | I68: SOGAMOSO | J68: BARRIO CENTRO III SOGAMOSO | K68: REDEBAN | L68: FO-25-1726240 | M68: 45953.516 | N68: 45957.64 | O68: NO | P68: TRASLADO | Q68: TRASLADO EXTERNO | R68: CB UNO A UNO | S68: CB UNO A UNO | T68: EJECUTADO | U68: EJECUTADO EXITOSO | V68: 23/10/2025 SE CONFIRMAN DATOS Y SOLICITUD CON EL USUARIO, SE ESCALA PARA VIISTA-POR FAVOR LLAMAR ANTES DE DESPLAZARSE | 24/10/2025 SE INTENTA COMUNICACION TELEFÓNICAMENTE CON LA SEÑORA LEIDY ARIZA PARA CONFIRMACION DE LA VISITA SOLICITADA AL NÚMERO DE CONTACTO 3114960922 NO SE LOGRA CONTACTAR AL CLIENTE SE DEJA MENSAJE POR WHATSAPP INDICANDOLE SOBRE LA VISITA NO SE OPTIENE UNA RESPUESTA A ESPERA QUE EL CLIENTE CONTESTE. | 28/10/2025 TRASLADO EXTERNO EXITOSO, PUBLICIDAD AVISO EXTERIOR, DATAFONO, LECTOR DE CÓDIGO DE BARRAS, IMPOSIBLE HACER PRUEBAS CB BLOQUEADO POR INOPERATIVIDAD, SE LE INFORMA AL CLIENTE QUE DEBE COMUNICARSE CON LA LÍNEA PARA GENERAR EL DESBLOQUEO INFORMANDO QUE EL TRASLADO FUE EXITOSO. SE VALIDA DIRECCIÓN DE ADQUIRENCIA CON RBM QUIEN INDICA QUE ES LA INFORMACIÓN CORRECTA, BAUCHER DE CORRESPONSALÍA SE CONFIRMA Y TAMBIÉN ESTÁ CORRECTO SEGÚN INFORMACIÓN DE RBM. SE LE RECOMIENDA AL CLIENTE LA ACTUALIZACIÓN DEL AVISO EXTERIOR AL MODELO NEGRO A TRAVEZ DE LA LÍNEA NACIONAL. TRASLADO EXITOSO | W68: VISITA TECNICA | X68: AB11T178;AB11U519 | Y68: TIPO II | Z68: TERRESTRE | AA68: HERRERA GARZON JEYSON STEVENT | AB68: 1 | AC68: 0 | AD68: 144968 | AE68: 144968
A69: MONTERIA | B69: COSTA | C69: 0004-0001 | D69: 23189 | E69: 14240965 | F69: 3007042599 | G69: OC TRASLADO | H69: CORDOBA | I69: CIENAGA DE ORO | J69: BARRIO SEIS DE ENERO CIENAGA D | K69: REDEBAN | L69: FO-25-1726270 | M69: 45953.516 | N69: 45955.558 | O69: NO | P69: TRASLADO | Q69: TRASLADO EXTERNO | R69: CB UNO A UNO | S69: CB UNO A UNO | T69: EJECUTADO | U69: EJECUTADO EXITOSO | V69: 23/10/2025 EN COMUNICACÓN CON EL SR FREDY JOSE GÓMEZ CORREA AL NÚMERO 3186657181, NOS CONFIRMA LA SOLICITUD, DATOS CORRECTOS, SE ESCALA PARA VISITA POR FAVOR LLAMAR ANTES DE DESPLAZARSE | 25/10/2025 SE REALIZA TRASLADO DE CORRESPONSAL EXITOSO, EQUIPOS TRASLADADOS DESK 3500 PLACA 942494 Y LECTOR DE BARRAS FM100 PLACA 534401 EN BUEN ESTADO OK, NUEVA DIRECCIÓN CONFIGURADA OK, PRUEBAS DE TRANSACCIÓNES EXITOSAS OK, CLIENTE CB VALIDA SALDO EN CERO ANTES Y DESPUÉS DEL TRASLADO OK, SE DEJA CB OPERATIVO EN NUEVA DIRECCIÓN OK | W69: VISITA TECNICA | X69: 9A5ZZ150 | Y69: TIPO II | Z69: TERRESTRE | AA69: GONZALEZ FERRER JESUS ALEXANDER | AB69: 1 | AC69: 0 | AD69: 144968 | AE69: 144968
A70: BOGOTA | B70: CUNDINAMARCA | C70: 0004-0004 | D70: 25430 | E70: 14244918 | F70: 3007046065 | G70: OC TRASLADO | H70: CUNDINAMARCA | I70: MADRID | J70: REVAL MADRID CODENSA | K70: REDEBAN | L70: FO-25-1705977 | M70: 45947.556 | N70: 45951.724 | O70: NO | P70: TRASLADO | Q70: TRASLADO EXTERNO | R70: ROBUSTO | S70: REVAL | T70: EJECUTADO | U70: EJECUTADO EXITOSO | V70: 20/10/2025 SE INTENTA COMUNICACIÓN AL NÚMERO 3165500718 PERO NO HAY CONTACTO, SE ESCALA PARA VISITA | 21/10/2025 SE REALIZA VISITA DE CAMPO CON EL FIN DE REALIZAR TRASLADO DE CB, SE PORCEDE A REALIZAR INICIALIZACION DE EQUIPOS EVIDENCIADO QUE EQUIPOS NO TOMAN LA DIRECCIÓN NUEVA, POR LO ANTERIOR SE ESCALA CASO CON SEBASTIAN GONZALES DE REDEBAN EN DONDE SE HACE PROCESO DE INICIALIZAON EN VARIAS OCASIONES VALIDANDO QUE EQUIPOS SIGUEN CON INFORMACIÓN ERRADA, LUEGO DE UN TIEMPO SOLO LA TERMINAL XP004571 QUEDA CON LA DIRECCIÓN CORRECTA, LAS DEMÁS NO, DE ACUERDO A INDICACIONES POR PARTE DE SEBASTIAN GONZALES DE REDEBAN INFORMA QUE SE HARÁ LA ACTUALIZACIÓN DE MANERA REMOTA Y UNA VEZ QUEDE SE LE INFORMARA AL CB, DE IGUAL MANERA MANIFESTA QUE SE ESCALO CASO CON EL ÁREA DE IT DE REDEBAN Y AUTORIZAN CIERRE DE SOLICITUD, NO SE HACEN PRUEBAS YA QUE CB SE ENCYRA BLOQUEADO DE ACUERDO A INFORMACIÓN DE LA LÍNEA DE ATENCIÓN AL CLIENTE. | W70: VISITA TECNICA | X70: XP004574-XP004571-XP004573 | Y70: TIPO II | Z70: TERRESTRE | AA70: LOZADA ROJAS CHRISTIAN ANDRES | AB70: 1 | AC70: 0 | AD70: 144968 | AE70: 144968
A71: PASTO | B71: SUROCCIDENTE Y EJE CAFETERO | C71: 0004-0003 | D71: 86001 | E71: 14251164 | F71: 3007044313 | G71: OC PINPAD | H71: PUTUMAYO | I71: MOCOA | J71: DSTRICOL CLL IS IAPELER IA | K71: REDEBAN | L71: FO-25-1710749 | M71: 45950.712 | N71: 45953.411 | O71: NO | P71: PINPAD | Q71: PINPAD | R71: AGREGADOR | S71: DISTRICOL | T71: EJECUTADO | U71: EJECUTADO EXITOSO | V71: 21/10/2025 SE INTENTA COMUNICACIÓN A LOS NÚMEROS 3172112098-3144261974 PERO NO HAY CONTACTO, SE INTENTARÁ NUEVAMENTE | 21/10/2025 SE INTENTA COMUNICACIÓN A LOS NÚMEROS 3172112098-3144261974 PERO NO HAY CONTACTO, SE INTENTARÁ NUEVAMENTE | 21/10/2025 POR FAVOR COMUNICARSE CON USUARIO PARA CONFIRMAR UBICACION, SE ESCALA PARA VISITA TECNICA | 23/10/2025 SE VISITA EL CB PARA INSTALAR PINPAD, CLIENTE CUENTA CON CABINA Y VIDRIO DE SEGURIDAD, INSTALACION PIN PAD OK, SE HACE CAMBIO DE DATÁFONO POR TECNOLOGÍA, SE HACEN PRUEBAS OK CB OPERATIVO | W71: VISITA TECNICA | X71: 9B05Z215 | Y71: TIPO IV | Z71: TERRESTRE | AA71: GUERRERO RAMIREZ OSCAR DARIO | AB71: 1 | AC71: 0 | AD71: 479589 | AE71: 479589
A72: BOGOTA | B72: CUNDINAMARCA | C72: 0004-0004 | D72: 25754 | E72: 14258735 | F72: 3007060569 | G72: OC TRASLADO | H72: CUNDINAMARCA | I72: SOACHA | J72: BARRIO SOACHA CIUDAD DE QUITO | K72: REDEBAN | L72: FO-25-1747838 | M72: 45958.636 | N72: 45961.65 | O72: NO | P72: TRASLADO | Q72: TRASLADO EXTERNO | R72: UNO A UNO | S72: CB UNO A UNO | T72: EJECUTADO | U72: EJECUTADO EXITOSO | V72: 28/10/2025 SE INTENTA COMUNICACIÓN AL NÚMERO 3158130148 PERO NO HAY RESPUESTA. SE ESCALA PARA VISITA POR FAVOR LLAMAR ANTES DE DESPLAZARSE | 31/10/2025 SE REALIZA TRASLADO EXITOSO A SOLICITUD DEL USUARIO SERVICIO OPERATIVO PRUEBAS OK CON UNA CONSULTA DE SALDO DIRECCIÓN NUEVA OK | W72: VISITA TECNICA | X72: JA00E965 | Y72: TIPO I | Z72: TERRESTRE | AA72: BUSTOS MORA DIEGO MANUEL | AB72: 1 | AC72: 0 | AD72: 65960 | AE72: 65960
A73: CARTAGENA | B73: COSTA | C73: 0004-0001 | D73: 13001 | E73: 14259723 | F73: 3007078171 | G73: OC TRASLADO | H73: BOLIVAR | I73: CARTAGENA | J73: PTM CARTAGENA TALLER OPTICO BU | K73: REDEBAN | L73: FO-25-1728790 | M73: 45954.356 | N73: 45955.562 | O73: NO | P73: TRASLADO | Q73: TRASLADO EXTERNO | R73: AGREGADOR | S73: COMCARD - PTM | T73: EJECUTADO | U73: EJECUTADO EXITOSO | V73: 24/10/2025 SE CONFIRMA SOLICITUD CON EL USUARIO, DATOS CORRECTOS, SE ESCALA PARA VISITA | 26/10/2025 SE REALIZA TRASLADO DEL EQUIPO LECTORA BASE PINPAD PUBLICIDAD SE HACEN PRUEBAS | W73: VISITA TECNICA | X73: SXLZZ553-F1KZZ768 | Y73: TIPO I | Z73: TERRESTRE | AA73: CANEDO HERRERA ALEXANDER | AB73: 1 | AC73: 0 | AD73: 65960 | AE73: 65960
A74: SANTA MARTA | B74: COSTA | C74: 0004-0001 | D74: 47707 | E74: 14281175 | F74: 3007073277 | G74: OC PINPAD | H74: MAGDALENA | I74: SANTA ANA | J74: BARRIO PRIMERO MAYO SANTA ANA | K74: REDEBAN | L74: FO-25-1747844 | M74: 45958.636 | N74: 45960.458 | O74: NO | R74: CB UNO A UNO | S74: CB UNO A UNO | T74: EJECUTADO | U74: EJECUTADO EXITOSO | V74: 28/10/2025 SE INTENTA COMUNICACIÓN A LOS NÚMEROS 3013043483 FUERA DE SERVICIO Y AL 3205338681 NO HAY RESPUESTA, TIMBRA Y SE VA A BUZÓN. SE ESCALA PARA VISITA POR FAVOR LLAMAR ANTES DE DESPLAZARSE | 30/10/2025 SE REALIZA INSTALACIÓN DE PINPAD, SE INSTALA HUB, SE REALIZAN PRUEBAS DEJANDO SERVICIO FUNCIONAL AL 100 % | W74: VISITA TECNICA | X74: A30ZZ413 | Y74: TIPO IV | Z74: TERRESTRE | AA74: MONTES DIAZ JOHN FRED | AB74: 1 | AC74: 0 | AD74: 479589 | AE74: 479589
A75: BOGOTA | B75: CUNDINAMARCA | C75: 0004-0004 | D75: 25843 | E75: 14290565 | F75: 3007076569 | G75: OC TRASLADO | H75: CUNDINAMARCA | I75: VILLA DE SAN DIEGO DE UBATE | J75: BARRIO SAN JOSE VILLA DE SAN DIEGO DE UBATE | K75: REDEBAN | L75: FO-25-1760674 | FO-25-1747837 | M75: 45958.636 | N75: 45960.678 | O75: NO | P75: TRASLADO | Q75: TRASLADO EXTERNO | R75: UNO A UNO | S75: UNO A UNO | T75: EJECUTADO | EJECUTADO / CANCELADO | U75: EJECUTADO EXITOSO | V75: 30/10/2025 SE REALIZA VISITA A COMERCIO, SE PROCEDE A REALIZAR EL TRASLADO DE DATAFONO - LECTOR SE CREAN USUARIOS, PRUEBAS OKAY. | W75: VISITA TECNICA | X75: 103ZZ249 | Y75: TIPO II | Z75: TERRESTRE | AA75: ARIAS QUILINDO JULIAN | AB75: 1 | AC75: 0 | AD75: 144968 | AE75: 144968
A76: CALI | B76: SUROCCIDENTE Y EJE CAFETERO | C76: 0004-0003 | D76: 76001 | E76: 14297224 | F76: 3007032416 | G76: OC TRASLADO | H76: VALLE DEL CAUCA | I76: CALI | J76: OPRAP CENTRO COMERCIAL ELITE | K76: REDEBAN | L76: FO-25-1755274 | M76: 45959.701 | N76: 45960.581 | O76: NO | P76: TRASLADO | Q76: TRASLADO EXTERNO | R76: ROBUSTO | S76: OPRAP | T76: EJECUTADO | U76: EJECUTADO EXITOSO | V76: 30/10/2025 POR FAVOR, COMUNICARSE CON USUARIO PARA CONFIRMAR UBICACION, SOLICITUD Y PROGRAMAR VISITA TECNICA | 30/10/2025 SE HACE TRASLADO DE EQUIPOS PINPAD LECTOR SE HACEN PRUEBAS SE VERIFICA DIRECCIÓN Y QUEDA FUNCIONANDO CORRECTAMENTE | W76: VISITA TECNICA | X76: 119ZZ442-LMKZZ167-119ZZ443-9C00E732-LMKZZ168-9C00E733 | Y76: TIPO I | Z76: TERRESTRE | AA76: CUERO RUIZ JHONNY | AB76: 1 | AC76: 0 | AD76: 65960 | AE76: 65960
A77: CALI | B77: SUROCCIDENTE Y EJE CAFETERO | C77: 0004-0003 | D77: 76001 | E77: 14307988 | F77: 3007074231 | G77: OC TRASLADO | H77: VALLE DEL CAUCA | I77: CALI | J77: PTM CALI LR EL LIDO | K77: REDEBAN | L77: FO-25-1760904 | M77: 45960.456 | N77: 45961.492 | O77: NO | P77: TRASLADO | Q77: TRASLADO EXTERNO | R77: AGREGADOR | S77: COMCARD - PTM | T77: EJECUTADO | U77: EJECUTADO EXITOSO | V77: 30/10/2025 SE LLAMA AL USUARIO NO HAY COMUNICACION | 31/10/2025 SE REALIZA VISITA TÉCNICA EN DONDE SE INICIALIZA EL EQUIPO CORRECTAMENTE, EL DISPOSITIVO QUEDA BOLUDEADO HASTA NO SE ENVÍE CORREO DE REDEBAN | W77: VISITA TECNICA | X77: EG3ZZ029 | Y77: TIPO I | Z77: TERRESTRE | AA77: ESCOBAR LENIS JUAN SEBASTIAN | AB77: 1 | AC77: 0 | AD77: 65960 | AE77: 65960
A78: BOGOTA | B78: CUNDINAMARCA | C78: 0004-0004 | D78: 25035 | E78: 2655401 | F78: 3007011702 | G78: OC BASE DATAFONO | H78: CUNDINAMARCA | I78: ANAPOIMA | J78: ANAPOIMA | K78: REDEBAN | L78: FO-25-1436372 | M78: 45897.333 | N78: 45936.512 | O78: NO | P78: BASEDATAFONO | Q78: BASE DATAFONO | R78: CB UNO A UNO | S78: CB UNO A UNO | T78: EJECUTADO | V78: 27/08/2025 POR FAVOR, COMUNICARSE CON USUARIO PARA CONFIRMAR UBICACION, SOLICITUD Y PROGRAMAR VISITA TECNICA | 06/10/2025 INSTALACIÓN DE BASE PARA DATAFONO SOLICITADAS POR CLIENTE YA QUE NO TENÍAN PARA 1 DE LOS DATAFONOS DEL PUNTO | W78: VISITA TECNICA | X78: 1111V000 | Y78: TIPO II | Z78: TERRESTRE | AA78: GOMEZ VEGA DAVID SNEYDER | AB78: 1 | AC78: 0 | AD78: 144968 | AE78: 144968
A79: APARTADO | B79: NOROCCIDENTE | C79: 0004-0005 | D79: 5045 | E79: 2789402 | F79: 3007032309 | G79: OC BASE DATAFONO | H79: ANTIOQUIA | I79: APARTADO | J79: CHINITA APARTADO ANTIOQUIA | K79: REDEBAN | L79: FO-25-1579119 | M79: 45924.642 | N79: 45931.628 | O79: NO | P79: BASEDATAFONO | Q79: BASE DATAFONO | R79: CB UNO A UNO | S79: CB UNO A UNO | T79: EJECUTADO | U79: EJECUTADO EXITOSO | V79: 24/09/2025 POR FAVOR, COMUNICARSE CON USUARIO PARA CONFIRMAR UBICACION, SOLICITUD Y PROGRAMAR VISITA TECNICA | 01/10/2025 SE REALIZA INSTALACIÓN BASE DATAFONO | W79: VISITA TECNICA | X79: NN00M741 | Y79: TIPO I | Z79: TERRESTRE | AA79: CASTRO HENAO DANIEL ESTEBAN | AB79: 1 | AC79: 0 | AD79: 65960 | AE79: 65960
A80: BUCARAMANGA | B80: SANTANDERES | C80: 0004-0008 | D80: 68276 | E80: 2795176 | F80: 3007058155 | G80: OC BASE DATAFONO | H80: SANTANDER | I80: FLORIDABLANCA | J80: PTM FLORIDABLNACA PAPELERIA MI | K80: REDEBAN | L80: FO-25-1584942 | M80: 45925.645 | N80: 45932.623 | O80: NO | P80: BASEDATAFONO | Q80: BASE DATAFONO | R80: AGREGADOR | S80: COMCARD - PTM | T80: EJECUTADO | U80: EJECUTADO EXITOSO | V80: 25/09/2025 POR FAVOR, COMUNICARSE CON USUARIO PARA CONFIRMAR UBICACION, SOLICITUD Y PROGRAMAR VISITA TECNICA | 02/10/2025 SE REALIZA VISITA PARA AJUSTAR Y PEGAR BASE PARA DATAFONO TUZZZ346 | W80: VISITA TECNICA | X80: TUZZZ346 | Y80: TIPO I | Z80: TERRESTRE | AA80: PEÑA DIAZ IVAN YESID | AB80: 1 | AC80: 0 | AD80: 65960 | AE80: 65960
A81: MEDELLIN | B81: NOROCCIDENTE | C81: 0004-0005 | D81: 5736 | E81: 2814264 | F81: 3007052839 | G81: OC BASE DATAFONO | H81: ANTIOQUIA | I81: SEGOVIA | J81: DISTRICOL OFICINA GENERAL | K81: REDEBAN | L81: FO-25-1604014 | M81: 45930.428 | N81: 45937.526 | O81: NO | P81: BASEDATAFONO | Q81: BASE DATAFONO | R81: AGREGADOR | S81: DISTRICOL | T81: EJECUTADO | U81: EJECUTADO EXITOSO | V81: 30/09/2025 EN COMUNICACIÓN CON LA SEÑORA YULIANA RAMIREZ AL NÚMERO 3145353286 CONFIRMA SOLICITUD, DATOS CORRECTOS. SE ESCALA PARA VISITA | 07/10/2025 EN COMUNICACIÓN CON CLIENTE TE INFORMA QUE OFICINA ABRE DESPUÉS DE 10:30 | 07/10/2025 SE INSTALA BASE NUEVO DEBIDO A DAÑO EN PARTE BAJA | W81: VISITA TECNICA | X81: BA0IZ142 | Y81: TIPO IV | Z81: TERRESTRE | AA81: QUINTERO SANCHEZ JUAN SEBASTIAN | AB81: 1 | AC81: 0 | AD81: 479589 | AE81: 479589
A82: CALI | B82: SUROCCIDENTE Y EJE CAFETERO | C82: 0004-0003 | D82: 76109 | E82: 2820527 | F82: 3007024448 | G82: OC BASE DATAFONO | H82: VALLE DEL CAUCA | I82: BUENAVENTURA | J82: PAGAFACIL VIVA BUENAVENTURA | K82: REDEBAN | L82: FO-25-1609048 | M82: 45931.389 | N82: 45936.742 | O82: NO | P82: BASEDATAFONO | Q82: BASE DATAFONO | R82: ROBUSTO | S82: PAGAFACIL | T82: EJECUTADO | U82: EJECUTADO EXITOSO | V82: 01/10/2025 POR FAVOR, COMUNICARSE CON USUARIO PARA CONFIRMAR UBICACION, SOLICITUD Y PROGRAMAR VISITA TECNICA, YA QUE SE INTENTÓ COMUNICACIÓN PERO NO HUBO RESPUESTA | 06/10/2025 SE VISITA EL COMERCIO, SE REALIZA CAMBIAN DE DOS BASES DE DATAFONO EN MAL ESTADO | W82: VISITA TECNICA | X82: ABCGZ829 - ABCGZ830 | Y82: TIPO III | Z82: TERRESTRE | AA82: HERRERA MONAR GEOVANNY | AB82: 1 | AC82: 0 | AD82: 275729 | AE82: 275729
A83: MEDELLIN | B83: NOROCCIDENTE | C83: 0004-0005 | D83: 5129 | E83: 2831441 | F83: 3007045422 | G83: OC BASE DATAFONO | H83: ANTIOQUIA | I83: CALDAS | J83: DISTRICOL FERRIPINTURAS | K83: REDEBAN | L83: FO-25-1617108 | M83: 45932.624 | N83: 45933.619 | O83: NO | P83: BASEDATAFONO | Q83: BASE DATAFONO | R83: AGREGADOR | S83: DISTRICOL | T83: EJECUTADO | U83: EJECUTADO EXITOSO | V83: 02/10/2025 POR FAVOR, COMUNICARSE CON USUARIO PARA CONFIRMAR UBICACION, SOLICITUD Y PROGRAMAR VISITA TECNICA | 03/10/2025 SE REALIZÓ FIJADO DE BASE | W83: VISITA TECNICA | X83: AC0MZ773 | Y83: TIPO I | Z83: TERRESTRE | AA83: CASTAÑEDA PALACIO CARLOS FELIPE | AB83: 1 | AC83: 0 | AD83: 65960 | AE83: 65960
A84: CALI | B84: SUROCCIDENTE Y EJE CAFETERO | C84: 0004-0003 | D84: 76001 | E84: 2835494 | F84: 3007028195 | G84: OC BASE DATAFONO | H84: VALLE DEL CAUCA | I84: CALI | J84: PAGAFACIL PLAZA CAICEDO II | K84: REDEBAN | L84: FO-25-1621704 | M84: 45933.46 | N84: 45934.536 | O84: NO | P84: BASEDATAFONO | Q84: BASE DATAFONO | R84: ROBUSTO | S84: PAGAFACIL | T84: EJECUTADO | U84: EJECUTADO EXITOSO | V84: 03/10/2025 POR FAVOR, COMUNICARSE CON USUARIO PARA CONFIRMAR UBICACION, SOLICITUD Y PROGRAMAR VISITA TECNICA | 04/10/2025 SE VISITA EL COMERCIO, SE ENCUENTRA BASE DE DATAFONO DAÑADA POR LO QUE SE INSTALA UNA NUEVA, NO SE INTERVIENE EQUIPOS | W84: VISITA TECNICA | X84: 9LZZZ752 | Y84: TIPO I | Z84: TERRESTRE | AA84: HERRERA MONAR GEOVANNY | AB84: 1 | AC84: 0 | AD84: 65960 | AE84: 65960
A85: VALLEDUPAR | B85: COSTA | C85: 0004-0001 | D85: 20013 | E85: 2836257 | F85: 3007077212 | G85: OC BASE DATAFONO | H85: CESAR | I85: AGUSTIN CODAZZI | J85: BARRIO LOS LAURELES AGUSTIN CO | K85: REDEBAN | L85: FO-25-1626024 | M85: 45933.512 | N85: 45933.701 | O85: NO | P85: BASEDATAFONO | Q85: BASE DATAFONO | R85: CB UNO A UNO | S85: CB UNO A UNO | T85: EJECUTADO | U85: EJECUTADO EXITOSO | V85: 03/10/2025 SE INSTALA BASE NUEVA YA QUÉ LA ANTERIOR SE DAÑÓ. | W85: VISITA TECNICA | X85: SX9ZZ500 | Y85: TIPO II | Z85: TERRESTRE | AA85: BENITEZ CARVAJAL ALVARO JAVIER | AB85: 1 | AC85: 0 | AD85: 144968 | AE85: 144968
A86: IBAGUE | B86: REMOTAS | C86: 0004-0007 | D86: 73001 | E86: 2839412 | F86: 3007071556 | G86: OC BASE DATAFONO | H86: TOLIMA | I86: IBAGUE | J86: PTM IBAGUE DROGUERIA PROSALUD | K86: REDEBAN | L86: FO-25-1628837 | M86: 45934.375 | N86: 45939.641 | O86: NO | P86: BASEDATAFONO | Q86: BASE DATAFONO | R86: AGREGADOR | S86: COMCARD - PTM | T86: EJECUTADO | U86: EJECUTADO EXITOSO | V86: 04/10/2025 POR FAVOR, COMUNICARSE CON USUARIO PARA CONFIRMAR UBICACION, SOLICITUD Y PROGRAMAR VISITA TECNICA | 09/10/2025 SE REALIZA INSTALACIÓN DE BASE PARA DATÁFONO POR DAÑO, SE INSTALA SEGÚN DONDE INDICA EL CLIENTE. | W86: VISITA TECNICA | X86: A30KZ123 | Y86: TIPO I | Z86: TERRESTRE | AA86: BARRAGAN TAFUR EDWIN ESTEBAN | AB86: 1 | AC86: 0 | AD86: 65960 | AE86: 65960
A87: MEDELLIN | B87: NOROCCIDENTE | C87: 0004-0005 | D87: 5579 | E87: 2839532 | F87: 3007060457 | G87: OC BASE DATAFONO | H87: ANTIOQUIA | I87: PUERTO BERRIO | J87: BARRIO CENTRO PUERTO BERRIO 4 | K87: REDEBAN | L87: FO-25-1629571 | M87: 45934.471 | N87: 45936.691 | O87: NO | P87: BASEDATAFONO | Q87: BASE DATAFONO | R87: UNO A UNO | S87: CB UNO A UNO | T87: EJECUTADO | U87: EJECUTADO EXITOSO | V87: 04/10/2025 POR FAVOR, COMUNICARSE CON USUARIO PARA CONFIRMAR UBICACION, SOLICITUD Y PROGRAMAR VISITA TECNICA | 06/10/2025 INSTALACIÓN DE BASE DATAFONO OK, ANTERIOR SE HABÍA QUEBRADO. | W87: VISITA TECNICA | X87: KA00C838 | Y87: TIPO III | Z87: TERRESTRE | AA87: PAREJA ECHAVARRIA JHON DAVID | AB87: 1 | AC87: 0 | AD87: 275729 | AE87: 275729
A88: BUCARAMANGA | B88: SANTANDERES | C88: 0004-0008 | D88: 68307 | E88: 2842617 | F88: 3007064672 | G88: OC BASE DATAFONO | H88: SANTANDER | I88: GIRON | J88: PTM GIRON MISCELANEA LA ECONOM | K88: REDEBAN | L88: FO-25-1633584 | M88: 45936.394 | N88: 45936.706 | O88: NO | P88: BASEDATAFONO | Q88: BASE DATAFONO | R88: AGREGADOR | S88: COMCARD - PTM | T88: EJECUTADO | U88: EJECUTADO EXITOSO | V88: 06/10/2025 POR FAVOR, COMUNICARSE CON USUARIO PARA CONFIRMAR UBICACION, SOLICITUD Y PROGRAMAR VISITA TECNICA | 06/10/2025 SE REALIZA VISITA AL COMERCIO CB, SE VALIDA Y SE HACE INSTALACIÓN DE BASE PARA EL DATÁFONO(SE DESPEGO), SE DEJA AL GUSTO DEL CLIENTE | W88: VISITA TECNICA | X88: 3A003049 | Y88: TIPO I | Z88: TERRESTRE | AA88: GONZALEZ ESTUPIÑAN YEISON WALTER ANTONIO | AB88: 1 | AC88: 0 | AD88: 65960 | AE88: 65960
A89: CALI | B89: SUROCCIDENTE Y EJE CAFETERO | C89: 0004-0003 | D89: 76001 | E89: 2844959 | F89: 3007022967 | G89: OC BASE DATAFONO | H89: VALLE DEL CAUCA | I89: CALI | J89: BARRIO PONDAGE CALI | K89: REDEBAN | L89: FO-25-1636194 | M89: 45936.524 | N89: 45937.56 | O89: NO | P89: BASEDATAFONO | Q89: BASE DATAFONO | R89: CB UNO A UNO | S89: CB UNO A UNO | T89: EJECUTADO / CANCELADO | U89: PETICIÓN USUARIO | V89: 06/10/2025 POR FAVOR, COMUNICARSE CON USUARIO PARA CONFIRMAR UBICACION, SOLICITUD Y PROGRAMAR VISITA TECNICA | 07/10/2025 SE REALIZA VISITA TÉCNICA AL COMERCIO EN DONDE EL COMERCIO ME INDICA QUE ELLOS NO HAN SOLICITADO BASE PARA EL DATÁFONO Y NO ME PERMITEN EL INGRESO AL COMERCIO, ENTONCES SE PROCEDE A CERRAR | W89: VISITA TECNICA | X89: 000 | Y89: TIPO I | Z89: TERRESTRE | AA89: ESCOBAR LENIS JUAN SEBASTIAN | AB89: 1 | AC89: 0 | AD89: 65960 | AE89: 65960
A90: PEREIRA | B90: SUROCCIDENTE Y EJE CAFETERO | C90: 0004-0002 | D90: 66594 | E90: 2846531 | F90: 3007013036 | G90: OC BASE DATAFONO | H90: RISARALDA | I90: QUINCHIA | J90: QUINCHIA III RISARALDA | K90: REDEBAN | L90: FO-25-1637414 | M90: 45936.638 | N90: 45944.594 | O90: NO | P90: BASEDATAFONO | Q90: BASE DATAFONO | R90: CB UNO A UNO | S90: CB UNO A UNO | T90: CANCELADO | U90: CANCELADO POR EL USUARIO | V90: 06/10/2025 POR FAVOR, COMUNICARSE CON USUARIO PARA CONFIRMAR UBICACION, SOLICITUD Y PROGRAMAR VISITA TECNICA | 14/10/2025 SE HABLA CON EL SEÑOR MAURICIO PARA VALIDAR VISITA PARA INSTALACION DE BASE PERO INDICA QUE ELLOS HABIA LLAMADO PERO QUE LA BASE ESTA BIEN , QUE AL PARECER SE HABIA AFLOJADO Y PARECIA DAÑADA PERO QUE AL REVISAR BIEN ESTA FUNCIONANDO NORMAL, SE PROCEDE A CERRAR EL CASO | W90: SOPORTE TELEFONICO | X90: 000000000 | Y90: TIPO II | Z90: TERRESTRE | AA90: HENAO CARDONA DIEGO FERNANDO | AB90: 0 | AC90: 0 | AD90: 41241 | AE90: 41241
... A111: BOGOTA | B111: CUNDINAMARCA | C111: 0004-0004 | D111: 25307 | E111: 2893264 | F111: 3007064766 | G111: OC BASE DATAFONO | H111: CUNDINAMARCA | I111: GIRARDOT | J111: BARRIO SAN MIGUEL GIRARDOT 2 | K111: REDEBAN | L111: FO-25-1695104 | M111: 45946.688 | N111: 45946.918 | O111: NO | P111: BASEDATAFONO | Q111: BASE DATAFONO | R111: CB UNO A UNO | S111: CB UNO A UNO | T111: EJECUTADO | U111: EJECUTADO EXITOSO | V111: 16/10/2025 POR FAVOR, COMUNICARSE CON USUARIO PARA CONFIRMAR UBICACION, SOLICITUD Y PROGRAMAR VISITA TECNICA | 16/10/2025 DURANTE LA VISITA TECNICA REALIZAMOS LA INSTALACIÓN DE LA BASE PARA EL DATAFONO POR DAÑO SE PARTIÓ, EN LUGARES INDICADOS POR COMERCIO SIN NOVEDAD EN LA INSTALACIÓN PRUEBAS OK SALDO OK A CONFORMIDAD DE CORRESPONSAL | W111: VISITA TECNICA | X111: 6Z005946 | Y111: TIPO III | Z111: TERRESTRE | AA111: GALEANO SORIANO JUAN DAVID | AB111: 1 | AC111: 0 | AD111: 275729 | AE111: 275729
A112: APARTADO | B112: NOROCCIDENTE | C112: 0004-0005 | D112: 5837 | E112: 2900017 | F112: 3007062542 | G112: OC BASE DATAFONO | H112: ANTIOQUIA | I112: TURBO | J112: PTM TURBO AGROINSUMOS NUEVO AN | K112: REDEBAN | L112: FO-25-1704094 | M112: 45948.485 | N112: 45951.592 | O112: NO | P112: BASEDATAFONO | Q112: BASE DATAFONO | R112: AGREGADOR | S112: COMCARD - PTM | T112: EJECUTADO | V112: 19/10/2025 POR FAVOR, COMUNICARSE CON USUARIO PARA CONFIRMAR UBICACION, SOLICITUD Y PROGRAMAR VISITA TECNICA | 21/10/2025 SE INSTALA BASE DE DATAFONO NUEVA YA QUE LA ANTERIOR SE PARTIO | W112: VISITA TECNICA | X112: LA00O170 | Y112: TIPO II | Z112: TERRESTRE | AA112: SALDARRIAGA MIRANDA SANTIAGO | AB112: 1 | AC112: 0 | AD112: 144968 | AE112: 144968
A113: MEDELLIN | B113: NOROCCIDENTE | C113: 0004-0005 | D113: 5001 | E113: 2900108 | F113: 3007074659 | G113: OC BASE DATAFONO | H113: ANTIOQUIA | I113: MEDELLIN | J113: PTM VEREDA BARRO BLANCO MEDELL | K113: REDEBAN | L113: FO-25-1704097 | M113: 45948.484 | N113: 45951.51 | O113: NO | P113: BASEDATAFONO | Q113: BASE DATAFONO | R113: AGREGADOR | S113: COMCARD - PTM | T113: EJECUTADO | U113: EJECUTADO EXITOSO | V113: 19/10/2025 POR FAVOR, COMUNICARSE CON USUARIO PARA CONFIRMAR UBICACION, SOLICITUD Y PROGRAMAR VISITA TECNICA | 21/10/2025 INSTALACIÓN DE BASE DATAFONO POR DAÑO CAÍDA EN LA ANTERIOR OK | W113: VISITA TECNICA | X113: NN00E975 | Y113: TIPO I | Z113: TERRESTRE | AA113: PAREJA ECHAVARRIA JHON DAVID | AB113: 1 | AC113: 0 | AD113: 65960 | AE113: 65960
A114: IBAGUE | B114: REMOTAS | C114: 0004-0007 | D114: 73268 | E114: 2900264 | F114: 3007047055 | G114: OC BASE DATAFONO | H114: TOLIMA | I114: ESPINAL | J114: BARRIO VILLA MARINA ESPINAL | K114: REDEBAN | L114: FO-25-1704091 | M114: 45950.333 | N114: 45950.685 | O114: NO | P114: BASEDATAFONO | Q114: BASE DATAFONO | R114: UNO A UNO | S114: CB UNO A UNO | T114: EJECUTADO | U114: EJECUTADO EXITOSO | V114: 19/10/2025 POR FAVOR, COMUNICARSE CON USUARIO PARA CONFIRMAR UBICACION, SOLICITUD Y PROGRAMAR VISITA TECNICA | 20/10/2025 SE INSTALA BASE PARA DATÁFONO POR DAÑO DEL ANTERIOR. | W114: VISITA TECNICA | X114: TR00B992 | Y114: TIPO II | Z114: TERRESTRE | AA114: VARGAS HERRERA JHON JAIRO | AB114: 1 | AC114: 0 | AD114: 144968 | AE114: 144968
A115: MEDELLIN | B115: NOROCCIDENTE | C115: 0004-0005 | D115: 5001 | E115: 2910501 | F115: 3007022852 | G115: OC BASE DATAFONO | H115: ANTIOQUIA | I115: MEDELLIN | J115: COMCARD MEDELLIN ROBLEDO DIMAS | K115: REDEBAN | L115: FO-25-1710717 | M115: 45951.333 | N115: 45952.614 | O115: NO | P115: BASEDATAFONO | Q115: BASE DATAFONO | R115: AGREGADOR | S115: COMCARD - PTM | T115: EJECUTADO | U115: EJECUTADO EXITOSO | V115: 21/10/2025 EN COMUNICACIÓN CON LA SRA MARTHA SILVA AL NÚMERO 3216378761 NOS CONFIRMA LA SOLICITUD, DATOS CORRECTOS, SE ESCALA PARA VISITA | 22/10/2025 ENTREGA E INSTALACIÓN DE BASE DE DATÁFONO OK | W115: VISITA TECNICA | X115: CZZZZ185 | Y115: TIPO I | Z115: TERRESTRE | AA115: CARDONA MOLINA BROLIN STIVEN | AB115: 1 | AC115: 0 | AD115: 65960 | AE115: 65960
A116: PEREIRA | B116: SUROCCIDENTE Y EJE CAFETERO | C116: 0004-0002 | D116: 66170 | E116: 2914725 | F116: 3007055907 | G116: OC BASE DATAFONO | H116: RISARALDA | I116: DOSQUEBRADAS | J116: PTM DOSQUEBRADAS AUTOSERVICIO | K116: REDEBAN | L116: FO-25-1713223 | M116: 45951.61 | N116: 45952.61 | O116: NO | P116: BASEDATAFONO | Q116: BASE DATAFONO | R116: AGREGADOR | S116: COMCARD - PTM | T116: EJECUTADO | U116: EJECUTADO EXITOSO | V116: 21/10/2025 EN COMUNICACIÓN CON LA SRA MARIA HERNANDEZ AL NÚMERO 3164756914 NOS CONFIRMA LA SOLICITUD, DATOS CORRECTOS, SE ESCALA PARA VISITA | 22/10/2025 SE INSTALA BASE DE DATÁFONO, YA QUE LA ANTERIOR SE PARTIÓ. | W116: VISITA TECNICA | X116: 9BKZZ314 | Y116: TIPO I | Z116: TERRESTRE | AA116: FRANCO CAÑAVERAL YAMID RAUL | AB116: 1 | AC116: 0 | AD116: 65960 | AE116: 65960
A117: CALI | B117: SUROCCIDENTE Y EJE CAFETERO | C117: 0004-0003 | D117: 76520 | E117: 2916212 | F117: 3007061326 | G117: OC BASE DATAFONO | H117: VALLE DEL CAUCA | I117: PALMIRA | J117: DISTRICOL DROGAS BULEVAR LA IT | K117: REDEBAN | L117: FO-25-1715642 | M117: 45951.7 | N117: 45952.627 | O117: NO | P117: BASEDATAFONO | Q117: BASE DATAFONO | R117: AGREGADOR | S117: DISTRICOL | T117: EJECUTADO | U117: EJECUTADO EXITOSO | V117: 22/10/2025 POR FAVOR COMUNICARSE CON USUARIO PARA CONFIRMAR UBICACION, SE ESCALA PARA VISITA | 22/10/2025 SE REALIZA INSTALACIÓN DE NUEVA BASE PARA DATAFONO DEBIDO A QUE LA ANTERIOR SE DAÑÓ. | W117: VISITA TECNICA | X117: HA00J509 | Y117: TIPO I | Z117: TERRESTRE | AA117: MONTERO MUESES GIAN CARLO | AB117: 1 | AC117: 0 | AD117: 65960 | AE117: 65960
A118: CALI | B118: SUROCCIDENTE Y EJE CAFETERO | C118: 0004-0003 | D118: 76520 | E118: 2919013 | F118: 3007049028 | G118: OC BASE DATAFONO | H118: VALLE DEL CAUCA | I118: PALMIRA | J118: DISTRICOL EDDYJAID | K118: REDEBAN | L118: FO-25-1717981 | M118: 45952.445 | N118: 45953.492 | O118: NO | P118: BASEDATAFONO | Q118: BASE DATAFONO | R118: AGREGADOR | S118: DISTRICOL | T118: EJECUTADO | U118: EJECUTADO EXITOSO | V118: 22/10/2025 POR FAVOR COMUNICARSE CON USUARIO PARA CONFIRMAR UBICACION, SE ESCALA PARA VISITA | 23/10/2025 EN LA VISITA TÉCNICA SE REALIZÓ LA INSTALACIÓN DE LA BASE SOPORTE DE EL DATÁFONO YA QUE LA ANTERIOR SE ENCONTRÓ PARTIDA. | W118: VISITA TECNICA | X118: AD00O665 | Y118: TIPO I | Z118: TERRESTRE | AA118: SANCHEZ URREGO ROBINSON DAVID | AB118: 1 | AC118: 0 | AD118: 65960 | AE118: 65960
A119: BOGOTA | B119: CUNDINAMARCA | C119: 0004-0004 | D119: 25386 | E119: 2921142 | F119: 3007049511 | G119: OC BASE DATAFONO | H119: CUNDINAMARCA | I119: LA MESA | J119: DISTRICOL LOXIAN TECHNOLOGY | K119: REDEBAN | L119: FO-25-1720044 | M119: 45952.637 | N119: 45953.494 | O119: NO | P119: BASEDATAFONO | Q119: BASE DATAFONO | R119: AGREGADOR | S119: DISTRICOL | T119: EJECUTADO | U119: EJECUTADO EXITOSO | V119: 22/10/2025 POR FAVOR, COMUNICARSE CON USUARIO PARA CONFIRMAR UBICACION, SOLICITUD Y PROGRAMAR VISITA TECNICA | 23/10/2025 INSTALACIÓN DE BASE PARA DATAFONO ROTA | W119: VISITA TECNICA | X119: AD00Q089 | Y119: TIPO II | Z119: TERRESTRE | AA119: GOMEZ VEGA DAVID SNEYDER | AB119: 1 | AC119: 0 | AD119: 144968 | AE119: 144968
A120: VALLEDUPAR | B120: COSTA | C120: 0004-0001 | D120: 20001 | E120: 2924864 | F120: 3007078444 | G120: OC BASE DATAFONO | H120: CESAR | I120: VALLEDUPAR | J120: BARRIO ENRIQUE PUPO VALLEDUPAR | K120: REDEBAN | L120: FO-25-1723370 | M120: 45953.438 | N120: 45955.426 | O120: NO | P120: BASEDATAFONO | Q120: BASE DATAFONO | R120: CB UNO A UNO | S120: CB UNO A UNO | T120: EJECUTADO | U120: EJECUTADO EXITOSO | V120: 23/10/2025 POR FAVOR, COMUNICARSE CON USUARIO PARA CONFIRMAR UBICACION, SOLICITUD Y PROGRAMAR VISITA TECNICA | 24/10/2025 SE REALIZA INSTALACIÓN DE BASE PARA DATÁFONO YA QUE LA QUE SE ENCONTRABA EN SITIO SE PARTIO Y NO LE PERMITIA EN BUEN USO | W120: VISITA TECNICA | X120: V1OZZ364 | Y120: TIPO I | Z120: TERRESTRE | AA120: MAESTRE MENGUAL EDGAR ENRIQUE | AB120: 1 | AC120: 0 | AD120: 65960 | AE120: 65960
A121: APARTADO | B121: NOROCCIDENTE | C121: 0004-0005 | D121: 5045 | E121: 2926122 | F121: 3007076953 | G121: OC BASE DATAFONO | H121: ANTIOQUIA | I121: APARTADO | J121: DISTRICOL PUNTO ANDROID URABA | K121: REDEBAN | L121: FO-25-1724789 | M121: 45953.518 | N121: 45957.706 | O121: NO | P121: BASEDATAFONO | Q121: BASE DATAFONO | R121: AGREGADOR | S121: DISTRICOL | T121: EJECUTADO | U121: EJECUTADO EXITOSO | V121: 23/10/2025 POR FAVOR, COMUNICARSE CON USUARIO PARA CONFIRMAR UBICACION, SOLICITUD Y PROGRAMAR VISITA TECNICA | 27/10/2025 INSTALACIÓN BASE DATAFONO | W121: VISITA TECNICA | X121: A18ZZ390 | Y121: TIPO I | Z121: TERRESTRE | AA121: CASTRO HENAO DANIEL ESTEBAN | AB121: 1 | AC121: 0 | AD121: 65960 | AE121: 65960
A122: BOGOTA | B122: CUNDINAMARCA | C122: 0004-0004 | D122: 11001 | E122: 2927441 | F122: 3007051013 | G122: OC BASE DATAFONO | H122: CUNDINAMARCA | I122: BOGOTA | J122: BARRIO BOSA BOGOTA 10 | K122: REDEBAN | L122: FO-25-1726232 | M122: 45953.642 | N122: 45955.52 | O122: NO | P122: BASEDATAFONO | Q122: BASE DATAFONO | R122: CB UNO A UNO | S122: CB UNO A UNO | T122: EJECUTADO / CANCELADO | U122: PETICIÓN USUARIO | V122: 23/10/2025 POR FAVOR, COMUNICARSE CON USUARIO PARA CONFIRMAR UBICACION, SOLICITUD Y PROGRAMAR VISITA TECNICA | 25/10/2025 SE LLEGA A COMERCIO A REALIZAR ENTREGA DE BASE CLIENTE INDICA QUE EL SOLICITO EL LO QUE SOLICITO FUE EL CAMBIO DE DATAFONO A TECNOLOGÍA WOMPI QUE LA BASE NO LE SIRVE SE LE INFORMA QUE ESA MIGRACIÓN LA ESTÁ REALIZANDO DIRECTAMENTE EL BANCO | W122: VISITA TECNICA | X122: TVIZZ645 | Y122: TIPO I | Z122: TERRESTRE | AA122: ORTIZ MARTINEZ STIVEN | AB122: 1 | AC122: 0 | AD122: 65960 | AE122: 65960
A123: PASTO | B123: SUROCCIDENTE Y EJE CAFETERO | C123: 0004-0003 | D123: 52001 | E123: 2931964 | F123: 3007065589 | G123: OC BASE DATAFONO | H123: NARIÑO | I123: PASTO | J123: DISTRICOL FABRIHOGAR JL | K123: REDEBAN | L123: FO-25-1730689 | M123: 45954.595 | N123: 45955.528 | O123: NO | P123: BASEDATAFONO | Q123: BASE DATAFONO | R123: AGREGADOR | S123: DISTRICOL | T123: EJECUTADO | U123: EJECUTADO EXITOSO | V123: 24/10/2025 SE ESCALA PARA VISITA, POR FAVOR COMUNICARSE CON EL USUARIO PARA CONFIRMAR UBICACIÓN | 25/10/2025 SE VISITA CB. SE REALIZA INSTALACIÓN DE BASE DE DATAFONO. CLIENTE INFORMA QUE EL DATAFONO FUNCIONA CORRECTAMENTE. NO SÉ MANIPULA DATAFONO | W123: VISITA TECNICA | X123: 4A008180 | Y123: TIPO I | Z123: TERRESTRE | AA123: CASTILLO HERRERA ALEX RICARDO | AB123: 1 | AC123: 0 | AD123: 65960 | AE123: 65960
A124: MEDELLIN | B124: NOROCCIDENTE | C124: 0004-0005 | D124: 5001 | E124: 2934927 | F124: 3007034522 | G124: OC BASE DATAFONO | H124: ANTIOQUIA | I124: MEDELLIN | J124: OPRAP AVENTURA PLAZA | K124: REDEBAN | L124: FO-25-1734865 | M124: 45957.333 | N124: 45959.617 | O124: NO | P124: BASEDATAFONO | Q124: BASE DATAFONO | R124: ROBUSTO | S124: OPRAP | T124: EJECUTADO | U124: EJECUTADO EXITOSO | V124: 25/10/2025 POR FAVOR, COMUNICARSE CON USUARIO PARA CONFIRMAR UBICACION, SOLICITUD Y PROGRAMAR VISITA TECNICA | 29/10/2025 SE INSTALA BASE DE DATAFONO EXITOSAMENTE | W124: VISITA TECNICA | X124: BL019985 | Y124: TIPO I | Z124: TERRESTRE | AA124: RUA ALVAREZ RICHARD ANDRES | AB124: 1 | AC124: 0 | AD124: 65960 | AE124: 65960
... A131: BUCARAMANGA | B131: SANTANDERES | C131: 0004-0008 | D131: 68051 | E131: LC-CS-25-000613 | F131: 3007075404 | G131: OC CIERRE | H131: SANTANDER | I131: ARATOCA | J131: BARRIO EL RAMAL ARATOCA | K131: REDEBAN | L131: FO-25-1592235 | M131: 45927.375 | N131: 45931.59 | O131: NO | P131: CIERRE | Q131: CIERRE | R131: UNO A UNO | S131: UNO A UNO | T131: EJECUTADO | U131: CIERRE EXITOSO | V131: 27/09/2025 EN COMUNICACIÓN CON EL SR LAURA ESTEFANIA DULCEY MUÑOZ AL NÚMERO 3182519900 NOS CONFIRMA LA SOLICITUD, DATOS CORRECTOS. SE ESCALA PARA VISITA | 27/09/2025 SE ESTABLECE CONTACTO TELEFÓNICO AL NÚMERO 3182519900 CON LAURA ESTEFANIA DULCEY QUIEN NOS INDICA QUE PODRA REALIZAR LA ENTREGA DE QLOS EQUIPOS EL DIA LUNES APARTIR DE LAS 8 AM CONFIRMA DIRECCIÓN OK | 29/09/2025 SE ESTABLECE CONTACTO TELEFÓNICO CON LA SEÑORA LAURA ESTEFANIA DULCEY MUÑOZ AL CELULAR: 3182519900 QUIEN NOS INDICA QUE LA MUCHACHA QUE VA REALIZAR LA ENTREGA NO ESTA DISPONIBLE SOLICITA REAGENDAR PARA EL DIA DE MAÑANA Y LLAMAR A VERIFICAR ANTES DE IR PARA NO PERDER LA IDA | 01/10/2025 SE REALIZA RECOLECCIÓN DE DATAFONO Y LECTORA NO AE ENCUENTRA PUBLICIDAD EN SITIO | W131: VISITA TECNICA | X131: V1009460 | Y131: TIPO II | Z131: TERRESTRE | AA131: REYES RAMIREZ DIEGO ALEXANDER | AB131: 1 | AC131: 0 | AD131: 144968 | AE131: 144968
A132: BOGOTA | B132: CUNDINAMARCA | C132: 0004-0004 | D132: 25320 | E132: LC-CS-25-000622 | F132: 3007076091 | G132: OC CIERRE | H132: CUNDINAMARCA | I132: GUADUAS | J132: BARRIO CENTRO GUADUAS 3 | K132: REDEBAN | L132: FO-25-1600112 | M132: 45929.64 | N132: 45933.381 | O132: NO | P132: CIERRE | Q132: RECUPERACION DE EQUIPOS | T132: EJECUTADO | U132: CIERRE EXITOSO | V132: 02/10/2025 SE INTENTA COMUNICACIÓN A EL NUMERO 3222235837 SUENA PERO NO HAY CONTACTO, SE INTENTARÁ NUEVAMENTE | 02/10/2025 SE INTENTA COMUNICACIÓN A EL NUMERO 3222235837 SUENA PERO NO HAY CONTACTO, SE INTENTARÁ NUEVAMENTE | 02/10/2025 SE LLEGA A LA DIRECCIÓN INDICADA, DIRECCIÓN DIFERENTE DONDE SE ENCONTRABA EL CB , SE RETIRA DATAFONO Y LECTOR , LA SRA ADRIANA INDICA QUE RETIRO PUBLICIDAD Y REALIZÓ DISPOSICIÓN FINAL. | W132: VISITA TECNICA | X132: LA0EZ266 | Y132: TIPO III | Z132: TERRESTRE | AA132: GARCIA PASTRANA KEVIN FERNANDO | AB132: 2 | AC132: 0 | AD132: 551458 | AE132: 551458
A133: MONTERIA | B133: COSTA | C133: 0004-0001 | D133: 23162 | E133: LC-CS-25-000624 | F133: 3007077163 | G133: OC CIERRE | H133: CORDOBA | I133: CERETE | J133: BARRIO SANTA CLARA CERETE | K133: REDEBAN | L133: FO-25-1600133 | M133: 45929.64 | N133: 45933.517 | O133: NO | P133: CIERRE | Q133: RECUPERACION DE EQUIPOS | R133: UNO A UNO | S133: UNO A UNO | T133: EJECUTADO | U133: CIERRE EXITOSO | V133: 01/10/2025 SE REALIZA CIERRE DE CORRESPONSAL OK, SE RETIRAN EQUIPOS, DATAFONO, LECTOR DE BARRAS, Y ACCESORIOS EN BUEN ESTADO, NO SE RETIRA PUBLICIDAD CB DETERIORO POR USO DESTRUIDA POR CB, CIERRE CB EXITOSO OK | W133: VISITA TECNICA | X133: SX6ZZ422 | Y133: TIPO I | Z133: TERRESTRE | AA133: GONZALEZ FERRER JESUS ALEXANDER | AB133: 1 | AC133: 0 | AD133: 65960 | AE133: 65960
A134: MONTERIA | B134: COSTA | C134: 0004-0001 | D134: 5250 | E134: LC-CS-25-000625 | F134: 3007081260 | G134: OC CIERRE | H134: ANTIOQUIA | I134: EL BAGRE | J134: DISTRICOL DROGUERIA G&P | K134: REDEBAN | L134: FO-25-1600148 | M134: 45929.64 | N134: 45933.385 | O134: NO | P134: CIERRE | Q134: CIERRE | R134: AGREGADOR | S134: DISTRICOL | T134: EJECUTADO | U134: CIERRE EXITOSO | V134: 02/10/2025 SE REALIZÓ RETIRO DE EQUIPOS POR CIERRE DE CB BANCOLOMBIA, EQUIPOS EN BUEN ESTADO. EN EL SITIO NO SE ENCONTRÓ PUBLICIDAD INSTALADA. | W134: VISITA TECNICA | X134: SKZZZ566 | Y134: TIPO IV | Z134: TERRESTRE | AA134: CALDERA SALCEDO CARLOS JULIO | AB134: 1 | AC134: 0 | AD134: 479589 | AE134: 479589
A135: SANTA MARTA | B135: COSTA | C135: 0004-0001 | D135: 44001 | E135: LC-CS-25-000626 | F135: 3007037644 | G135: OC CIERRE | H135: LA GUAJIRA | I135: RIOHACHA | J135: DISTRICOL YARONEMA | K135: REDEBAN | L135: FO-25-1600156 | M135: 45929.64 | N135: 45932.44 | O135: NO | P135: CIERRE | Q135: CIERRE | R135: AGREGADOR | S135: DISTRICOL | T135: EJECUTADO | U135: CIERRE EXITOSO | V135: 02/10/2025 SE REALIZA CIERRE DE CB, SE RECOGE DATAFONO, LECTOR, PINPAD Y HUB, NO SE RETIRA PUBLICIDAD YA QUE EL CLIENTE HIZO DISPOSICIÓN FINAL DE ELLA | W135: VISITA TECNICA | X135: 9A00Q706 | Y135: TIPO III | Z135: TERRESTRE | AA135: MONTES DIAZ JOHN FRED | AB135: 1 | AC135: 0 | AD135: 275729 | AE135: 275729
A136: MEDELLIN | B136: NOROCCIDENTE | C136: 0004-0005 | D136: 5001 | E136: LC-CS-25-000637 | F136: 3007072667 | G136: OC CIERRE | H136: ANTIOQUIA | I136: MEDELLIN | J136: BARRIO EL DIAMANTE MEDELLIN | K136: REDEBAN | L136: FO-25-1607638 | M136: 45931.333 | N136: 45937.52 | O136: NO | P136: CIERRE | Q136: CIERRE | R136: UNO A UNO | S136: UNO A UNO | T136: EJECUTADO | U136: CIERRE EXITOSO | V136: 02/10/2025 EN COMUNICACIÓN CON EL SR JUAN PABLO MOLINA ROJAS AL NÚMERO 3005243177 NOS CONFIRMA LA SOLICITUD, DATOS CORRECTOS. DA NUEVA DIRRECION EN DONDE RECOGER LOS EQUIPOS CARRERA 79 73 59 SE ESCALA PARA VISITA | 04/10/2025 LLAMO A USUARIO Y NO ES POSIBLE CONTACTO, LE ESCRIBO POR WHATSAPP E INDICA QUE PUEDE A LAS 2 PM, POR TAL MOTIVO TOCA REAGENDAR PARA EL DÍA LUNES YA QUE TRABAJAMOS HASTA LA 1 PM USUARIO INDICA QUE PUEDE ATENDER A CUALQUIER HORA EL LUNES. | 07/10/2025 CIERRE EXITOSO SIN PUBLICIDAD CB INFORMA QUE LE DIÓ DISPOSICIÓN FINAL | W136: VISITA TECNICA | X136: EF00R044 | Y136: TIPO I | Z136: TERRESTRE | AA136: CASTAÑEDA PALACIO CARLOS FELIPE | AB136: 1 | AC136: 0 | AD136: 65960 | AE136: 65960
A137: VALLEDUPAR | B137: COSTA | C137: 0004-0001 | D137: 20001 | E137: LC-CS-25-000638 | F137: 3007075459 | G137: OC CIERRE | H137: CESAR | I137: VALLEDUPAR | J137: BARRIO LA GRANJA VALLEDUPAR 10 | K137: REDEBAN | L137: FO-25-1607614 | M137: 45931.333 | N137: 45932.495 | O137: NO | P137: CIERRE | Q137: CIERRE | R137: CB UNO A UNO | S137: CB UNO A UNO | T137: EJECUTADO | U137: CIERRE EXITOSO | V137: 02/10/2025 SE REALIZA DESMONTÉ DE CB ,SE RETIRA EQUIPO Y LECTORA DE BARRAS | W137: VISITA TECNICA | X137: V100C082 | Y137: TIPO I | Z137: TERRESTRE | AA137: MAESTRE MENGUAL EDGAR ENRIQUE | AB137: 1 | AC137: 0 | AD137: 65960 | AE137: 65960
A138: MEDELLIN | B138: NOROCCIDENTE | C138: 0004-0005 | D138: 5088 | E138: LC-CS-25-000639 | F138: 3007075313 | G138: OC CIERRE | H138: ANTIOQUIA | I138: BELLO | J138: BARRIO BELLO BELLO 20 | K138: REDEBAN | L138: FO-25-1607624 | M138: 45931.333 | N138: 45931.581 | O138: NO | P138: CIERRE | Q138: CIERRE | R138: CB UNO A UNO | S138: CB UNO A UNO | T138: EJECUTADO | U138: CIERRE EXITOSO | V138: 01/10/2025 SE REALIZA RECOGIDA DE QUIPOS POR CIERRE CB,USUARIO REALIZA DISPOSICIÓN FINAL DE LA PUBLICIDAD | W138: VISITA TECNICA | X138: LM003500 | Y138: TIPO I | Z138: TERRESTRE | AA138: CASTAÑEDA PALACIO CARLOS FELIPE | AB138: 1 | AC138: 0 | AD138: 65960 | AE138: 65960
A139: MEDELLIN | B139: NOROCCIDENTE | C139: 0004-0005 | D139: 5541 | E139: LC-CS-25-000640 | F139: 3007066127 | G139: OC CIERRE | H139: ANTIOQUIA | I139: PEÑOL | J139: BARRIO CONQUISTADORES PENOL | K139: REDEBAN | L139: FO-25-1607627 | M139: 45931.333 | N139: 45932.685 | O139: NO | P139: CIERRE | Q139: CIERRE | R139: CB UNO A UNO | S139: CB UNO A UNO | T139: EJECUTADO | U139: CIERRE EXITOSO | V139: 02/10/2025 SE REALIZA RECOGIDA DE QUIPOS POR CIERRE CB,SE REALIZA DESTRUCCIÓN DE LA PUBLICIDAD. | W139: VISITA TECNICA | X139: 1A00N039 | Y139: TIPO II | Z139: TERRESTRE | AA139: RAMIREZ TABARES JUAN DIEGO | AB139: 1 | AC139: 0 | AD139: 144968 | AE139: 144968
A140: TUNJA | B140: SANTANDERES | C140: 0004-0008 | D140: 15861 | E140: LC-CS-25-000641 | F140: 3007017020 | G140: OC CIERRE | H140: BOYACA | I140: VENTAQUEMADA | J140: BARRIO VENTAQUEMADA II | K140: REDEBAN | L140: FO-25-1607610 | M140: 45931.333 | N140: 45931.578 | O140: NO | P140: CIERRE | Q140: CIERRE | R140: UNO A UNO | S140: CB UNO A UNO | T140: EJECUTADO | U140: CIERRE EXITOSO | V140: 01/10/2025 SE VISITA CB CIERRE...RETIRO DE EQUIPOS CB SIN PUBLICIDAD | W140: VISITA TECNICA | X140: BL07Z506 | Y140: TIPO II | Z140: TERRESTRE | AA140: GONZALEZ GONZALEZ MARIO ALBERTO | AB140: 1 | AC140: 0 | AD140: 144968 | AE140: 144968
A141: PASTO | B141: SUROCCIDENTE Y EJE CAFETERO | C141: 0004-0003 | D141: 52683 | E141: LC-CS-25-000642 | F141: 3007064347 | G141: OC CIERRE | H141: NARIÑO | I141: SANDONA | J141: BARRIO HERNANDO GOMEZ SANDONA | K141: REDEBAN | L141: FO-25-1607641 | M141: 45931.333 | N141: 45936.515 | O141: NO | P141: CIERRE | Q141: CIERRE | R141: UNO A UNO | S141: CB UNO A UNO | T141: EJECUTADO | U141: CIERRE EXITOSO | V141: 02/10/2025 SE INTENTA COMUNICACIÓN A EL NUMERO 3176500350 SUENA PERO NO HAY CONTACTO, SE INTENTARÁ NUEVAMENTE | 06/10/2025 SE REALIZA CIERRE DE CORRESPONSAL BANCARIO SE RETIRA DATAFONO LECTOR BASE FUENTE AVISO EXTERIOR DISPLAY HORARIO FLANGER CANTIDAD DE ROLLOS RETIRADOS CERO PUBLICIDAD DESTRUIDA EN SITIO CIERRE EXITOSO | W141: VISITA TECNICA | X141: 6A001366 | Y141: TIPO II | Z141: TERRESTRE | AA141: BRAVO MADROÑERO OSCAR ESTEBAN | AB141: 1 | AC141: 0 | AD141: 144968 | AE141: 144968
A142: YOPAL | B142: REMOTAS | C142: 0004-0007 | D142: 85162 | E142: LC-CS-25-000643 | F142: 3007064315 | G142: OC CIERRE | H142: CASANARE | I142: MONTERREY | J142: BARRIO LA FLORESTA MONTERREY | K142: REDEBAN | L142: FO-25-1607620 | M142: 45931.333 | N142: 45936.646 | O142: NO | P142: CIERRE | Q142: CIERRE | R142: UNO A UNO | S142: CB UNO A UNO | T142: EJECUTADO | U142: CIERRE EXITOSO | V142: 02/10/2025 SE INTENTA COMUNICACIÓN A EL NUMERO 3176500350 SUENA PERO NO HAY CONTACTO, SE INTENTARÁ NUEVAMENTE | 06/10/2025 SE REALIZA CIERRE CB SE RETIRA DATÁFONO Y LECTOR OK SIN NOVEDAD | W142: VISITA TECNICA | X142: AA000952 | Y142: TIPO II | Z142: TERRESTRE | AA142: CASTRILLON URREA LONDIER LEANDRO | AB142: 1 | AC142: 0 | AD142: 144968 | AE142: 144968
A143: TUNJA | B143: SANTANDERES | C143: 0004-0008 | D143: 15516 | E143: LC-CS-25-000644 | F143: 3007030094 | G143: OC CIERRE | H143: BOYACA | I143: PAIPA | J143: BARRIO CENTRO PAIPA | K143: REDEBAN | L143: FO-25-1607617 | M143: 45931.333 | N143: 45931.644 | O143: NO | P143: CIERRE | Q143: RECUPERACION DE EQUIPOS | R143: CB UNO A UNO | S143: CB UNO A UNO | T143: EJECUTADO | U143: CIERRE EXITOSO | V143: 01/10/2025 SE EJECUTA CIERRE CORRESPONSAL BANCARIO BANCOLOMBIA RETIRANDO LOS EQUIPOS EXISTENTES EN EL PUNTO COMERCIO SIN PUBLICIDAD | W143: VISITA TECNICA | X143: BBTZZ395 | Y143: TIPO II | Z143: TERRESTRE | AA143: RODRIGUEZ MURCIA YERSON IVAN | AB143: 1 | AC143: 0 | AD143: 144968 | AE143: 144968
A144: CUCUTA | B144: SANTANDERES | C144: 0004-0008 | D144: 54001 | E144: LC-CS-25-000645 | F144: 3007079630 | G144: OC CIERRE | H144: NORTE DE SANTANDER | I144: CUCUTA | J144: BARRIO LATINO CUCUTA 20 | K144: REDEBAN | L144: FO-25-1607630 | M144: 45931.333 | N144: 45931.658 | O144: NO | P144: CIERRE | Q144: RECUPERACION DE EQUIPOS | R144: UNO A UNO | S144: UNO A UNO | T144: EJECUTADO | U144: CIERRE EXITOSO | V144: 01/10/2025 SE RETIRÓ DATAFONO LECTOR BASE Y ACCESORIOS PUBLICIDAD FUE DESTRUIDA POR EL COMERCIO POR MAL ESTADO ROLLOS FUERON USADOS EN EL CB | W144: VISITA TECNICA | X144: SXUZZ156 | Y144: TIPO I | Z144: TERRESTRE | AA144: DURAN ACOSTA FRANK YONNY | AB144: 1 | AC144: 0 | AD144: 65960 | AE144: 65960
... A204: MEDELLIN | B204: NOROCCIDENTE | C204: 0004-0005 | D204: 5631 | E204: LC-CS-25-003866 | F204: 3007074673 | G204: OC CIERRE | H204: ANTIOQUIA | I204: SABANETA | J204: DISTRICOL MERKA TODO SABANETA | K204: REDEBAN | L204: FO-25-1663836 | M204: 45940.333 | N204: 45944.309 | O204: NO | P204: CIERRE | Q204: CIERRE | R204: AGREGADOR | S204: DISTRICOL | T204: EJECUTADO | U204: CIERRE EXITOSO | V204: 11/10/2025 SE CONFIRMA VISITA | 11/10/2025 SE REALIZA CIERRE DE CB, NO SE RETIRA ROLLOS YA QUE TIENEN OTRO PUNTO ACTIVO | W204: VISITA TECNICA | X204: EGQZZ165 | Y204: TIPO I | Z204: TERRESTRE | AA204: HERNANDEZ CHAVARRIA JUAN CAMILO | AB204: 1 | AC204: 0 | AD204: 65960 | AE204: 65960
A205: MONTERIA | B205: COSTA | C205: 0004-0001 | D205: 23555 | E205: LC-CS-25-003867 | F205: 3007053315 | G205: OC CIERRE | H205: CORDOBA | I205: PLANETA RICA | J205: DISTRICOL GRANERO EL BARATON | K205: REDEBAN | L205: FO-25-1663765 | M205: 45940.333 | N205: 45947.569 | O205: NO | P205: CIERRE | Q205: CIERRE | R205: AGREGADOR | S205: DISTRICOL | T205: EJECUTADO | U205: CIERRE EXITOSO | V205: 17/10/2025 SE REALIZÓ LLAMADA PARA VALIDAR LA DIRECCIÓN YA QUÉ NO ERA POSIBLE LLEGAR SIN INDICACIONES. | 17/10/2025 SE REALIZÓ RETIRO DE EQUIPOS POR CIERRE DE CB BANCOLOMBIA. NO SÉ ENCONTRÓ PUBLICIDAD INSTALADA EN EL SITIO. | W205: VISITA TECNICA | X205: II0NZ140 | Y205: TIPO II | Z205: TERRESTRE | AA205: CALDERA SALCEDO CARLOS JULIO | AB205: 1 | AC205: 0 | AD205: 144968 | AE205: 144968
A206: BOGOTA | B206: CUNDINAMARCA | C206: 0004-0004 | D206: 25290 | E206: LC-CS-25-003868 | F206: 3007054783 | G206: OC CIERRE | H206: CUNDINAMARCA | I206: FUSAGASUGA | J206: DISTRICOL DANET COMUNICA | K206: REDEBAN | L206: FO-25-1663750 | M206: 45940.333 | N206: 45946.622 | O206: NO | P206: CIERRE | Q206: CIERRE | R206: AGREGADOR | S206: DISTRICOL | T206: EJECUTADO | U206: CIERRE EXITOSO | V206: 16/10/2025 SE ESCALA PARA VISITA. CONFIRMAR DATOS PARA LA RECOLECCION DE EQUIPOS | 15/10/2025 COMERCIO PIDE SEA VISITADO EL DÍA DE MAÑANA 16-10-2025 | 16/10/2025 DURANTE LA VISITA TECNICA SE REALIZA RETIRO DE DATAFONO, A SOLICITUD DE CLIENTE, COMERCIO INDICA QUE NO DESEA QUEDAR COMO ADQUIRENTE INDICA QUE RETIREMOS EL DATAFONO SE RETIRA LECTOR DE CODIGO DE BARRAS POR CIERRE DE PUNTO PUBLICIDAD FUE RETIRADA Y DESTRUIDA POR COMERCIO INDICAN | W206: VISITA TECNICA | X206: TR8ZZ939 | Y206: TIPO II | Z206: TERRESTRE | AA206: GALEANO SORIANO JUAN DAVID | AB206: 1 | AC206: 0 | AD206: 144968 | AE206: 144968
A207: BARRANQUILLA | B207: COSTA | C207: 0004-0001 | D207: 8141 | E207: LC-CS-25-003873 | F207: 3007080938 | G207: OC CIERRE | H207: ATLANTICO | I207: CANDELARIA | J207: BARRIO CANDELARIA CANDELARIA | K207: REDEBAN | L207: FO-25-1663731 | M207: 45940.333 | N207: 45945.403 | O207: NO | P207: CIERRE | Q207: CIERRE | R207: UNO A UNO | S207: UNO A UNO | T207: EJECUTADO | U207: CIERRE EXITOSO | V207: 11/10/2025 SE REALIZA LLAMADA AL CLIENTE SEÑOR ABID MUÑOZ 300 6639418,EL CUAL DICE QUE NOS PUEDE ATENDER EL DÍA LUNES 14 DE OCTUBRE DEL 2025 ,TIPO MEDIA DIA | 14/10/2025 SE REALIZA VISITA SE PROCEDE A RECIBIR EQUIPOS ,DATAFONO ,LECTOR ,BASE DEL DATAFONOS, CABLE DE RED ,FUENTE DE PODER ,MAGIC BOX ,NO TIENE ROLLOS CONSUMIÓ, AVISO EXTERIOR SE LO ROBARON ,SOLO TIENE FLANGED Y DISPLAY LEGAL ,SE DESTRUYE EN SITIO, RECUPERACIÓN DE EQUIPOS OK ,CIERRE EXITOSO | W207: VISITA TECNICA | X207: FIZZZ278 | Y207: TIPO II | Z207: TERRESTRE | AA207: PORRAS CASTRO DARLON NASCK | AB207: 1 | AC207: 0 | AD207: 144968 | AE207: 144968
A208: PEREIRA | B208: SUROCCIDENTE Y EJE CAFETERO | C208: 0004-0002 | D208: 66001 | E208: LC-CS-25-003874 | F208: 3007069337 | G208: OC CIERRE | H208: RISARALDA | I208: PEREIRA | J208: CENTRO PEREIRA RISARALDA 3 | K208: REDEBAN | L208: FO-25-1663734 | M208: 45940.333 | N208: 45951.328 | O208: NO | P208: CIERRE | Q208: CIERRE | R208: UNO A UNO | S208: CB UNO A UNO | T208: EJECUTADO | U208: CIERRE EXITOSO | V208: 20/10/2025 VISITAMOS | 20/10/2025 VISITAMOS COMERCIO REALIZAMOS RETIRO DE DATÁFONO CON LECTOR DE BARRAS CON CABLE PATCH CORD 3MT, FUENTE DE PODER, MAGIC BOX TETRA Y 100 ROLLOS DESMONTAMOS TODA LA PUBLICIDAD Y LA DESTRUIMOS EN EL PUNTO. BASE SOLO TIENE LA MITAD. | W208: VISITA TECNICA | X208: 9L6ZZ671 | Y208: TIPO I | Z208: TERRESTRE | AA208: ARROYAVE CANO MANUEL GUILLERMO | AB208: 1 | AC208: 0 | AD208: 65960 | AE208: 65960
A209: VALLEDUPAR | B209: COSTA | C209: 0004-0001 | D209: 20001 | E209: LC-CS-25-003875 | F209: 3007077497 | G209: OC CIERRE | H209: CESAR | I209: VALLEDUPAR | J209: BARRIO BELLO HORIZONTE VALLLED | K209: REDEBAN | L209: FO-25-1663813 | M209: 45940.333 | N209: 45944.307 | O209: NO | P209: CIERRE | Q209: CIERRE | R209: CB UNO A UNO | S209: CB UNO A UNO | T209: EJECUTADO | U209: CIERRE EXITOSO | V209: 11/10/2025 SE AGENDA VISITA PARA HOY SÁBADO 11/20/2025 | 11/10/2025 SE REALIZA DESMONTÉ DE CB, SE RETIRA EQUIPO Y SUS RESPECTIVOS ACCESORIOS | W209: VISITA TECNICA | X209: A4IZZ040 | Y209: TIPO I | Z209: TERRESTRE | AA209: MAESTRE MENGUAL EDGAR ENRIQUE | AB209: 1 | AC209: 0 | AD209: 65960 | AE209: 65960
A210: BOGOTA | B210: CUNDINAMARCA | C210: 0004-0004 | D210: 11001 | E210: LC-CS-25-003877 | F210: 3007043355 | G210: OC CIERRE | H210: CUNDINAMARCA | I210: BOGOTA | J210: BARRIO FONTIBON BOGOTA 9 | K210: REDEBAN | L210: FO-25-1663779 | M210: 45940.333 | N210: 45945.421 | O210: NO | P210: CIERRE | Q210: RECUPERACION DE EQUIPOS | R210: CB UNO A UNO | S210: CB UNO A UNO | T210: EJECUTADO | U210: CIERRE EXITOSO | V210: 14/10/2025 CB PERMITE RETIRÓ DE EQUIPO Y ACCESORIOS Y PUBLICIDAD | 14/10/2025 SE REALIZA VISITA A CB SE RETIRA EQUIPO Y ACCESORIOS EXITOSO, SE DESTRUYE PUBLICIDAD. SE DEJA REGISTRO FOTOGRÁFICO | W210: VISITA TECNICA | X210: GA00M866 | Y210: TIPO I | Z210: TERRESTRE | AA210: JAIMES VALERO NELSON RICARDO | AB210: 1 | AC210: 0 | AD210: 65960 | AE210: 65960
A211: MEDELLIN | B211: NOROCCIDENTE | C211: 0004-0005 | D211: 5001 | E211: LC-CS-25-003878 | F211: 3007079673 | G211: OC CIERRE | H211: ANTIOQUIA | I211: MEDELLIN | J211: BARRIO LAURELES MEDELLIN 20 | K211: REDEBAN | L211: FO-25-1663771 | M211: 45940.333 | N211: 45944.488 | O211: NO | P211: CIERRE | Q211: CIERRE | R211: CB UNO A UNO | S211: CB UNO A UNO | T211: EJECUTADO | U211: CIERRE EXITOSO | V211: 10/10/2025 SE COMUNICA CON EL USUARIO PARA CONFIRMAR LA VISITA HE INDICA QUE NO ESTÁ DISPONIBLE HASTA EL MARTES. | 10/10/2025 SE COMUNICA CON EL USUARIO PARA CONFIRMAR LA VISITA HE INDICA QUE NO ESTÁ DISPONIBLE HASTA EL MARTES. | 11/10/2025 SE INTENTA COMUNICA CON EL USUARIO EN REITERADAS PARA CONFIRMAR LA VISITA, CUANDO CONTESTA INDICA NUEVAMENTE QUE NO ESTÁRA DISPONIBLE HASTA EL MARTES | 14/10/2025 SE REALIZA CIERRE EXITOSO TODO OK | W211: VISITA TECNICA | X211: SXUZZ199 | Y211: TIPO I | Z211: TERRESTRE | AA211: ALVAREZ ARENAS VICTOR HUGO | AB211: 1 | AC211: 0 | AD211: 65960 | AE211: 65960
A212: MEDELLIN | B212: NOROCCIDENTE | C212: 0004-0005 | D212: 5679 | E212: LC-CS-25-003879 | F212: 3007049049 | G212: OC CIERRE | H212: ANTIOQUIA | I212: SANTA BARBARA | J212: BARRIO HOSPITAL SANTA BARBARA | K212: REDEBAN | L212: FO-25-1663741 | M212: 45940.333 | N212: 45945.491 | O212: NO | P212: CIERRE | Q212: CIERRE | R212: CB UNO A UNO | S212: CB UNO A UNO | T212: EJECUTADO | U212: CIERRE EXITOSO | V212: 15/10/2025 SE PROGRAMA CIERRE | 15/10/2025 SE REALIZA CIERRE DE CB | W212: VISITA TECNICA | X212: AD00O686 | Y212: TIPO II | Z212: TERRESTRE | AA212: HERNANDEZ CHAVARRIA JUAN CAMILO | AB212: 1 | AC212: 0 | AD212: 144968 | AE212: 144968
A213: BARRANQUILLA | B213: COSTA | C213: 0004-0001 | D213: 8001 | E213: LC-CS-25-003880 | F213: 3007070607 | G213: OC CIERRE | H213: ATLANTICO | I213: BARRANQUILLA | J213: ME QUEJO BARRANQUILLA 2 | K213: REDEBAN | L213: FO-25-1663821 | M213: 45940.333 | N213: 45941.312 | O213: NO | P213: CIERRE | Q213: CIERRE | R213: CB UNO A UNO | S213: CB UNO A UNO | T213: EJECUTADO | U213: CIERRE EXITOSO | V213: 10/10/2025 SE RETIRAN EQUIPOS Y ACCESORIOS EN BUEN ESTADO X CIERRE DEL CB LA ENTREGA LA HACE EL SEÑOR YILDER SIERRA | W213: VISITA TECNICA | X213: UV008349 | Y213: TIPO I | Z213: TERRESTRE | AA213: DE AVILA SIADES ALBERTO ENRIQUE | AB213: 1 | AC213: 0 | AD213: 65960 | AE213: 65960
...

Sheet PAPELERIA
A1: CIUDAD SEDE | B1: ZONA | C1: CENTRO DE COSTOS LINEACOM | D1: CODIGO DANE | E1: TA/CODIGO ACTIVIDAD | F1: CODIGO CB | G1: ACTIVIDAD | H1: DEPARTAMENTO | I1: CIUDAD | J1: NOMBRE DEL CB | K1: RED | L1: FO | M1: FECHA ASIGNACION A LINEA COMUNICACIONES | N1: FECHA CIERRE DEL TICKET (DD/MM/AAAA HH:MM) | O1: ACOMETIDA | P1: SOLICITUD | Q1: DESCRIPCION | R1: FORMATO | S1: CADENA | T1: ESTADO | U1: CAUSAL ESTADO | V1: OBSERVACION | W1: FORMA DE ATENCION | X1: TERMINAL(ES) | Y1: TIPIFICACION | Z1: TIPO DE TRAYECTO | AA1: NOMBRE DEL TECNICO | AB1: DIAS DE VISITA | AC1: VALOR DIAS ACTIVIDAD FACTURABLES | AD1: VALOR TOTAL
A2: APARTADO | B2: NOROCCIDENTE | C2: 0004-0005 | D2: 27430 | E2: 2675497 | F2: 3007079151 | G2: OC VISITA ROLLOS | H2: CHOCO | I2: MEDIO BAUDO | J2: BARRIO CL COMERCIO PUERTO MELU | K2: REDEBAN | L2: FO-25-1582532 | FO-25-1465077 | M2: 45901.638 | N2: 45934.456 | P2: VISITA | Q2: ROLLOS | R2: CB UNO A UNO | S2: CB UNO A UNO | T2: EJECUTADO | U2: EJECUTADO EXITOSO | V2: 30/09/2025 SE LE INFORMA A LA USUARIA QUE LOS ROLLOS YA APARECEN LISTOS PARA RECLAMAR EN OFICINA | 02/10/2025 SE VALIDA LA GUIA Y ESTA EN ESTADO: YA PUEDES RECOGER TU ENVÍO SE VALIDA CON EL USUARIO DONDE INDICA QUE A LA OFICINA NO HA LLEGADO NADA | 26/09/2025 SE ENVIARON 20 ROLLOS POR INTERRAPIDISIMO SE EVIDENCIO QUE EN PUERTO MELUK NO HAY OFICINA DE INTERRAPIDISIMO SE HABLÓ CON LA SEÑORA CLAUDIA Y PIDE ENVIAR LOS ROLLOS A LA OFICINA DE QUIBDO ELLA TIENE UN CONTACTO EN LA OFICINA DE INTERRAPIDISIMO Y SE LOS HACE LLEGAR HASTA PUERTO MELUK | W2: ENVIO FLOTA - OPERADOR LOGISTICO | Y2: TIPO IV | Z2: TERRESTRE | AA2: CASTAÑEDA PALACIO CARLOS FELIPE | AB2: 0 | AC2: 35780 | AD2: =AC2 -> 35780
A3: MEDELLIN | B3: NOROCCIDENTE | C3: 0004-0005 | D3: 5858 | E3: 2714924 | F3: 3007012304 | G3: OC ENVIO ROLLOS | H3: ANTIOQUIA | I3: VEGACHI | J3: VEGACHI III - ANTIOQUIA | K3: REDEBAN | L3: FO-25-1503664 | M3: 45909.456 | N3: 45933.39 | P3: ENVIO | R3: CB UNO A UNO | S3: CB UNO A UNO | U3: EJECUTADO EXITOSO | V3: 09/09/2025 SE LLAMA AL 3118923794; SE CONTACTA A MARGARITA MUÑETON SE CONFIRMA SOLICITUD, DATOS DE ENVIO Y DIRECCION | 16/09/2025 SE REALIZA COMUNICACION CON EL USUARIO DONDE INDICA QUE AUN NO LE ENTREGAN LOS ROLLOS | 23/09/2025 SE REALIZA COMUNICACION CON EL USUARIO DONDE INDICA QUE AUN NO LE ENTREGAN LOS ROLLOS | 23/09/2025 SE ESCALA A SERVIENTREGA EL 16-09. RESPUESTA DE SERVIENTREGA 284607409: EN EL MOMENTO ESTÁ SIN MOVIMIENTOS. DESDE SU INGRESO AL CENTRO LOGÍSTICO EL 10 DE SEPTIEMBRE POR LO TANTO, PARA REALIZAR LA GESTIÓN PERTINENTE SOLICITAMOS QUE POR FAVOR NOS PUEDAS REMITIR POR ESTE MISMO MAYORES CARACTERÍSTICAS DETALLADAS DEL CONTENIDO (MARCA, COLOR, CANTIDAD, TALLA, MATERIAL), TAMBIÉN DEL EMPAQUE (CAJA, CARTÓN, BOLSA, VINIPEL) PARA UNA PRONTA GESTIÓN. SI ES POSIBLE, ADJUNTAR REGISTRO FOTOGRÁFICO. | 23/09/2025 SE CREA NUEVO MO PARA REALIZAR NUEVAMENTE EL ENVIO YA QUE SERVIENTREGA AL PARECER LO PERDIO, USUARIA AL TANTO Y DE ACUERDO | 03/10/2025 SE REALIZA ENVIO DE 70 ROLLOS, CON LA GUIA 284607430 SERVIENTREGA. SE CONFIRMA ENTREGA EXITOSA POR PARTE DE LA TRANSPORTADORA | W3: ENVIO | Y3: TIPO III | Z3: TERRESTRE | AB3: 0 | AC3: 35780 | AD3: =AC3 -> 35780
A4: CARTAGENA | B4: COSTA | C4: No encontrado | D4: 13810 | E4: 2748150 | F4: 3007047737 | G4: OC ENVIO ROLLOS | H4: BOLIVAR | I4: TIQUISIO | J4: BARRIO EL CRISTO CRR TIQUISIO | K4: REDEBAN | L4: FO-25-1541472 | M4: 45916.495 | N4: 45932.498 | P4: ENVIO | R4: UNO A UNO | S4: CB UNO A UNO | U4: EJECUTADO EXITOSO | V4: 17/09/2025 SE REALIZA ENVIO DE ROLLOS CON GUIA | 20/09/2025 EN COMUNICACIÓN CON EL USUARIO AL NÚMERO 3135890777 INDICA QUE AUN NO HA RECIBIDO LOS ROLLOS | 22/09/2025 EN COMUNICACIÓN CON EL USUARIO AL NÚMERO 3135890777 INDICA QUE AUN NO HA RECIBIDO LOS ROLLOS | 23/09/2025 EN COMUNICACIÓN CON EL USUARIO AL NÚMERO 3135890777 INDICA QUE AUN NO HA RECIBIDO LOS ROLLOS | 24/09/2025 EN COMUNICACIÓN CON EL USUARIO AL NÚMERO 3135890777 INDICA QUE AUN NO HA RECIBIDO LOS ROLLOS | 24/09/2025 SE ESCALA A SERVIENTREGA PARA VALIDAR EL ESTADO DEL ENVIO YA QUE LLEVA 6 DIAS SIN MOVIMIENTO | 02/10/2025 SE REALIZA ENVIO DE 10 ROLLOS, CON LA GUIA 2205447180 SERVIENTREGA. SE CONFIRMA ENTREGA EXITOSA POR PARTE DE LA TRANSPORTADORA | W4: ENVIO | Y4: TIPO IV | Z4: TERRESTRE | AB4: 0 | AC4: 35780 | AD4: =AC4 -> 35780
A5: APARTADO | B5: NOROCCIDENTE | C5: 0004-0005 | D5: 27006 | E5: 2755941 | F5: 3007057048 | G5: OC ENVIO ROLLOS | H5: CHOCO | I5: ACANDI | J5: BARRIO ACANDI ACANDI 1 | K5: REDEBAN | L5: FO-25-1544613 | M5: 45917.628 | N5: 45937.608 | P5: ENVIO | R5: CB UNO A UNO | S5: CB UNO A UNO | U5: EJECUTADO EXITOSO | V5: 17/09/2025 SE REALIZA ENVIO DE ROLLOS CON GUIA | 22/09/2025 SE VALIDA A DON ERGAR LA GUIA DONDE INDICA QUE LA GUIA ES 284607426 SERVIENTREGA | 24/09/2025 SE COMUNICA CON EL USUARIO DONDE INFORMA QUE AUN NO RECIBE LOS ROLLOS | 07/10/2025 SE REALIZA ENVIO DE 50 ROLLOS, CON LA GUIA SERVIENTREGA SERVIENTREGA. SE CONFIRMA ENTREGA EXITOSA POR PARTE DE LA TRANSPORTADORA | W5: ENVIO | Y5: TIPO V | Z5: AEREO | AB5: 0 | AC5: 35780 | AD5: =AC5 -> 35780
A6: MONTERIA | B6: COSTA | C6: 0004-0001 | D6: 23682 | E6: 2758645 | F6: 3007079908 | G6: OC ENVIO ROLLOS | H6: CORDOBA | I6: SAN JOSE DE URE | J6: DISTRICOL FRUTA FRESCA MERCADO | K6: REDEBAN | L6: FO-25-1549152 | M6: 45918.354 | N6: 45934.403 | P6: ENVIO | R6: AGREGADOR | S6: DISTRICOL | U6: EJECUTADO EXITOSO | V6: 18/09/2025 SE REALIZA ENVIO DE ROLLOS CON GUIA | 25/09/2025 SE VALIDA Y LA GUIA FUE GENERADA EL DIA 22-09, SE VALIDA ANTES DEL VENCIMIENTO EL ESTADO 25/09/2025 SALIO A CIUDAD DESTINO - BARRANQUILLA (ATLANTICO) | 04/10/2025 ADICIONAL DE LA DEMORA EN LA GENERACION DE LA GUIA OR PARTE DE BODEGA, OPERADOR LOGISTICO TARDA CASI DOS SEMANA EN ENTREGARLO, SE CORRIGE INCUMPLIMIENTO | 04/10/2025 SE REALIZA ENVIO DE 10 ROLLOS, CON LA GUIA 2265100378 SERVIENTREGA. SE CONFIRMA ENTREGA EXITOSA POR PARTE DE LA TRANSPORTADORA | W6: ENVIO | Y6: TIPO III | Z6: TERRESTRE | AB6: 0 | AC6: 35780 | AD6: =AC6 -> 35780
A7: MEDELLIN | B7: NOROCCIDENTE | C7: 0004-0005 | D7: 27075 | E7: 2771594 | F7: 3007073899 | G7: OC VISITA ROLLOS | H7: CHOCO | I7: BAHIA SOLANO | J7: BARRIO FLLO CASTRO BAHIA SOLAN | K7: REDEBAN | L7: FO-25-1563578 | M7: 45922.349 | N7: 45932.475 | P7: VISITA | Q7: ROLLOS | R7: CB UNO A UNO | S7: CB UNO A UNO | T7: EJECUTADO | U7: EJECUTADO EXITOSO | V7: 22/09/2025 SE REALIZA ENVIO DE ROLLOS CON GUIA | 02/10/2025 SE ENTREGAN 40 ROLLOS | W7: VISITA TECNICA | Y7: TIPO V | Z7: AEREO | AA7: BADEL ACUÑA LUIS ALBERTO | AB7: 1 | AC7: 35780 | AD7: =AC7 -> 35780
A8: APARTADO | B8: NOROCCIDENTE | C8: 0004-0005 | D8: 27615 | E8: 2776315 | F8: 3007077157 | G8: OC ENVIO ROLLOS | H8: CHOCO | I8: RIOSUCIO | J8: DISTRICOL GANGAZO PAISA DEL 10 | K8: REDEBAN | L8: FO-25-1566408 | M8: 45922.632 | N8: 45937.617 | P8: ENVIO | R8: AGREGADOR | S8: DISTRICOL | U8: EJECUTADO EXITOSO | V8: 22/09/2025 SE REALIZA ENVIO DE ROLLOS CON GUIA | 29/09/2025 SE COMUNICA CON EL USUARIO DONDE INFORMA QUE AUN NO RECIBE LOS ROLLOS | 03/10/2025 OPERADOR REPORTA QUE LA VIA PRINCIPAL SE ENCUENTRA CERRADA, POR LO CUAL ENVIO SE RETRASA | 07/10/2025 SE REALIZA ENVIO DE 20 ROLLOS, CON LA GUIA 284607428 SERVIENTREGA. SE CONFIRMA ENTREGA EXITOSA POR PARTE DE LA TRANSPORTADORA | W8: ENVIO | Y8: TIPO V | Z8: TERRESTRE/FLUVIAL | AB8: 0 | AC8: 35780 | AD8: =AC8 -> 35780
