Workbook
Name A: #REF!
Name Actividad: [1]Formulas!$H$2:$H$5000
Name arearesponsable: '[2]Listas desplegables'!$BB$2:$BB$100
Name Clientes: [1]Clientes!$A$2:$A$100
Name COORDINADOR: [3]Hoja2!$D$2:$D$30
Name Coordinadores: [1]Coordinadores!$A$2:$A$1000
Name DOCUMENTADOR: [3]Hoja2!$A$2:$A$30
Name ES: [3]Hoja2!$K$2:$K$30
Name ESS: [3]Hoja2!$K$2:$K$30
Name Estado: [1]Formulas!$K$2:$K$5000
Name ESTADOACTIVIDAD: [3]Hoja2!$M$2:$M$30
Name ESTADOS: '[4]Listas desplegables'!$B$1:$D$1
Name ESTADOSCIERRES: '[5]lista desplegable'!$CX$1:$DA$1
Name Facturacion: '[6]Listas desplegables'!$AO$1:$AR$1
Name FACTURACIÓN: '[4]Listas desplegables'!$Y$1:$AB$1
Name falla: #REF!
Name Fallas: '[7]Listas desplegables'!$F$2:$L$2
Name Grupo_Falla: '[8]Listas Desplegables'!$CH$2:$CH$5
Name inconservmanager: '[9]Listas desplegables'!$BC$2:$BC$100
Name INCUMPLIMIENTO: '[2]Listas desplegables'!$AK$1:$AN$1
Name LISTA: [10]Dptos!$A$1139:$A$1171
Name LISTA2: #REF!
Name LOLO: [11]Coordinadores!$A$2:$A$1000
Name solicitudes: '[12]Listas desplegables'!$AF$1:$AQ$1
Name Tecnicos: [1]Tecnicos!$A$2:$A$1000
Name Version: [1]Formulas!$I$2:$I$3

Sheet RESUMEN LIQUIDACIONES
A1: LÍNEA COMUNICACIONES S.A.S | F1: FACTURACIÓN CORRESPONSALES BANCARIOS TIQUIETES AEREOS
A2: FACTURACIÓN PROYECTO CB BANCOLOMBIA | F2: =A3 -> 45992
A3: 45992
F4: CONCEPTOS | G4: TRAYECTOS | H4: TOTAL | I4: % Administración | J4: TOTAL
A5: CONCEPTOS | B5: CANTIDAD | C5: VALOR UNITARIO | D5: VALOR TOTAL | F5: INCIDENTE 3003898 | G5: BUCARAMANGA - ARAUCA - BUCARAMANGA | H5: =440000+285800 -> 725800 | I5: =H5*0.12 -> 87096 | J5: =H5+I5 -> 812896
A6: Adecuaciones CB | B6: =COUNTA(ADECUCACIONES!A:A)-1 -> 5 | C6: 0 | D6: =SUM(ADECUCACIONES!AE2:AE10000) -> 821393 | F6: INCIDENTE 63236 -3156570 | G6: MEDELLIN - RIOSUCIO- MEDELLIN | H6: 451500 | I6: =H6*0.12 -> 54180 | J6: =H6+I6 -> 505680
A7: Incidentes | B7: =COUNTA(INCIDENTES!A:A)-1 -> 92 | C7: 0 | D7: =SUM(INCIDENTES!AH2:AH9913) -> 13108018 | F7: INCIDENTE 76854-3183532 | G7: MEDELLIN - QUIBDÓ- MEDELLIN | H7: 507600 | I7: =H7*0.12 -> 60912 | J7: =H7+I7 -> 568512
A8: Ordenes de Cambio | B8: =COUNTA(OC!A:A)-1 -> 7 | C8: 0 | D8: =SUM(OC!AG2:AG10000) -> 1154917 | I8: =H8*0.12 -> 0 | J8: =H8+I8 -> 0
A9: Tiquetes | B9: 3 | C9: 0 | D9: =J12 -> 1887088 | I9: =H9*0.12 -> 0 | J9: =H9+I9 -> 0
A10: SUBTOTAL | D10: =SUM(D6:D9) -> 16971416 | I10: =H10*0.12 -> 0 | J10: =H10+I10 -> 0
A11: Iva | D11: =D10*0.19 -> 3224569 | I11: =H11*0.12 -> 0 | J11: =H11+I11 -> 0
A12: TOTAL | D12: =D10+D11 -> 20195985 | F12: TOTAL | H12: =SUM(H5:H11) -> 1684900 | I12: =SUM(I5:I11) -> 202188 | J12: =SUM(J5:J11) -> 1887088

Sheet BASE LIQUIDACION
A1: TARIFAS 2025 | E1: Incremento 2025
A2: Tipificación | B2: Descripción | C2: Dia actividad Exitosa | D2: Dia actividad Fallida | E2: 0.052
A3: Tipo I | B3: Metropolitano | C3: =62700.07*(1+$E$2) -> 65960.474 | D3: =42357.4*(1+$E$2) -> 44559.985
A4: Tipo II | B4: Hasta 3 horas | C4: =155716.31*(1+$E$2) -> 163813.56 | D4: =127766.53*(1+$E$2) -> 134410.39
A5: Tipo III | B5: De 3 a 5 horas | C5: =262099.22*(1+$E$2) -> 275728.38 | D5: =211886.19*(1+$E$2) -> 222904.27
A6: Tipo IV | B6: Más de 5 horas | C6: =455883.78*(1+$E$2) -> 479589.74 | D6: =441833.68*(1+$E$2) -> 464809.03
A7: Destino aereo | B7: No incluye valor del Tiquete | C7: =455883.78*(1+$E$2) -> 479589.74 | D7: =441833.68*(1+$E$2) -> 464809.03
A8: *Donde se requiera transporte aéreo o fluvial se factura adicional a tarifa TIPO IV el valor del tiquete + el 12% de admon.
A10: Gestión Telefónica | B10: =36031.04*(1+$E$2) -> 37904.654
A11: Mts Acometida electrica | B11: =30182.1*(1+$E$2) -> 31751.569
A12: Mts Acometida datos | B12: =15432.22*(1+$E$2) -> 16234.695
A13: switche | B13: =244669.03*(1+$E$2) -> 257391.82
A14: Router | B14: =291399.51*(1+$E$2) -> 306552.28
A15: Envio operador Logistico | B15: =53547.34*(1+$E$2) -> 56331.802

Sheet Hoja1
A2: ADEC
A3: Etiquetas de fila | B3: Suma de VALOR TOTAL INSTALACION DE PUBLICIDAD | C3: CC | D3: VALOR
A4: 0004-0001 | B4: 222904 | C4: =A4 -> 0004-0001 | D4: =B4 -> 222904 | H4: Etiquetas de fila | I4: Suma de VALOR
A5: COSTA | B5: 222904 | G5: COS | H5: 0004-0001 | I5: 1229698
A6: 0004-0003 | B6: 44560 | C6: =A6 -> 0004-0003 | D6: =B6 -> 44560 | G6: EJE | H6: 0004-0002 | I6: 737077
A7: SUROCCIDENTE Y EJE CAFETERO | B7: 44560 | G7: SUR | H7: 0004-0003 | I7: 1132105
A8: 0004-0005 | B8: 509369 | C8: =A8 -> 0004-0005 | D8: =B8 -> 509369 | G8: CEN | H8: 0004-0004 | I8: 973204
A9: NOROCCIDENTE | B9: 509369 | G9: NOR | H9: 0004-0005 | I9: 5885241
A10: 0004-0007 | B10: 44560 | C10: =A10 -> 0004-0007 | D10: =B10 -> 44560 | G10: REM | H10: 0004-0007 | I10: 2839242
A11: REMOTAS | B11: 44560 | G11: SAN | H11: 0004-0008 | I11: 2287761
A12: Total general | B12: 821393 | H12: Total general | I12: 15084328
A18: INC
A19: Etiquetas de fila | B19: Suma de VALOR DIAS ACOMPAÑAMIENTO FACTURABLE
A20: 0004-0001 | B20: 1006794 | C20: =A20 -> 0004-0001 | D20: =B20 -> 1006794
A21: COSTA | B21: 1006794
A22: 0004-0003 | B22: 1087545 | C22: =A22 -> 0004-0003 | D22: =B22 -> 1087545
A23: SUROCCIDENTE Y EJE CAFETERO | B23: 1087545
A24: 0004-0005 | B24: 5034184 | C24: =A24 -> 0004-0005 | D24: =B24 -> 5034184
A25: NOROCCIDENTE | B25: 5034184
A26: 0004-0007 | B26: 2756777 | C26: =A26 -> 0004-0007 | D26: =B26 -> 2756777
A27: REMOTAS | B27: 2756777
A28: 0004-0008 | B28: 2123947 | C28: =A28 -> 0004-0008 | D28: =B28 -> 2123947
A29: SANTANDERES | B29: 2123947
A30: 0004-0004 | B30: 361694 | C30: =A30 -> 0004-0004 | D30: =B30 -> 361694
A31: CUNDINAMARCA | B31: 361694
A32: 0004-0002 | B32: 737077 | C32: =A32 -> 0004-0002 | D32: =B32 -> 737077
A33: SUROCCIDENTE Y EJE CAFETERO | B33: 737077
A34: Total general | B34: 13108018
A41: OC
A42: Etiquetas de fila | B42: Suma de VALOR TOTAL
A43: 0004-0005 | B43: 341688 | C43: =A43 -> 0004-0005 | D43: =B43 -> 341688
A44: NOROCCIDENTE | B44: 341688
A45: 0004-0007 | B45: 37905 | C45: =A45 -> 0004-0007 | D45: =B45 -> 37905
A46: REMOTAS | B46: 37905
A47: 0004-0008 | B47: 163814 | C47: =A47 -> 0004-0008 | D47: =B47 -> 163814
A48: SANTANDERES | B48: 163814
A49: 0004-0004 | B49: 611510 | C49: =A49 -> 0004-0004 | D49: =B49 -> 611510
A50: CUNDINAMARCA | B50: 611510
A51: Total general | B51: 1154917

Sheet ADECUCACIONES
A1: CIUDAD SEDE | B1: ZONA | C1: CENTRO DE COSTOS LINEACOM | D1: CODIGO DANE | E1: TA/CODIGO ACTIVIDAD | F1: CODIGO CB | G1: ACTIVIDAD | H1: TIPO DE APERTURA | I1: DEPARTAMENTO | J1: CIUDAD | K1: NOMBRE DEL CB | L1: RED | M1: FO | N1: FECHA LISTA | O1: FECHA ULTIMA ACTUALIZACION | P1: FORMATO | Q1: CADENA | R1: ESTADO | S1: OBSERVACIONES CLIENTE | T1: FORMA DE ATENCION | U1: TERMINAL(ES) | V1: TIPIFICACION | W1: TIPO DE TRAYECTO | X1: NOMBRE DEL TECNICO | Y1: ACOMETIDA DATOS | Z1: ACOMETIDA ELECTRICA | AA1: SWITCH | AB1: ROUTER | AC1: VALOR DIAS ACTIVIDAD FACTURABLES | AD1: DIAS ACTIVIDAD FACTURABLES | AE1: VALOR TOTAL INSTALACION DE PUBLICIDAD
A2: CALI | B2: SUROCCIDENTE Y EJE CAFETERO | C2: 0004-0003 | D2: 76001 | E2: TA-25-1330514 | F2: 3007082238 | G2: APERTURA | H2: CB CRECIMIENTO ALIANZA - OTRAS LISTAS | I2: VALLE DEL CAUCA | J2: CALI | K2: PTM CALI DISTRIBUIDORA LA 23 S | L2: REDEBAN | M2: FO-25-1905019 | FO-25-1884065 | N2: 45988.333 | O2: 46009.462 | R2: CANCELADO | EJECUTADO/CANCELADO | S2: [FO-25-1905019] 02/12/2025 ‎POR MOTIVO QUE EL CLIENTE TUVO DILIGENCIAS MÉDICAS, "DIÓ A LUZ" NO SE PODRÁ ATENDER LA INSTALACIÓN EL DÍA DE HOY, QUEDAMOS EN REPROGRAMAR DICHO SERVICIO. | 18/12/2025 ‎SE REALIZA COMUNICACIÓN CON LA SEÑORA ISABEL CRISTINA E INDICA QUE EL DÍA DE AYER 17 DE DICIEMBRE REALIZÓ EL PROCESO DE CANCELACIÓN PORQUE SE ENCUENTRA INDISPUESTA DE SALUD QUE PARA ENERO RETOMA LA SOLICITUD DE INSTALACIÓN CON PTM. || [FO-25-1884065] 26/11/2025 26-11 PROGRAMACION REALIZADA POR LA ALIANZA| INSTALACIÓN PROGRAMADA PARA EL 2025-11-28 | 28/11/2025 SE LLEGO A EL CB DESDE TEMPRANO, POR INCONVENIENTE CON LAS TERMINALES REDEBAN REALIZO CAMBIO DE LA MISMA A UNAS NUEVAS. ‎SE CONFIGURA LA NUEVA TERMINAL COMO PURA POR SOLICITUD DE REDEBAN Y SIENDO LAS 17:00 LA TERMINAL AUN PRESENTA INCONVENIENTES, LAS CUALES AL REALIZAR PRUEBAS DA RECHAZOS GENERAL. ‎SE INDAGO CON PTM Y BANCOLOMBIA POSIBLES BLOQUEO Y ANTES LAS ENTIDADES ESTA BIEN. ‎CLIENTE INDICA QUE NO PUEDE SEGUIR CON EL PROCESO DESPUES DE LAS 5 POR MOTIVO DE SEGURIDAD DE LA ZONA Y SOLICITA LA REPROGRAMACIÓN PARA EL DIA MARTES. ‎PD. POR SOLICITUD DE REDEBAN EQUIPO QUEDARIA CON TERMINAL PURA | T2: SOPORTE TELEFONICO | V2: TIPO I | W2: TERRESTRE | X2: TORRES GARCIA JENDRY JOSE | Y2: 0 | Z2: 0 | AA2: 0 | AB2: 0 | AC2: 1 | AD2: 44560 | AE2: 44560
A3: IBAGUE | B3: REMOTAS | C3: 0004-0007 | D3: 73001 | E3: TA-25-1330683 | F3: 3007082329 | G3: APERTURA | H3: CB CRECIMIENTO ALIANZA - NUEVO | I3: TOLIMA | J3: IBAGUE | K3: PTM IBAGUE EL MANA DE LOS PLA | L3: REDEBAN | M3: FO-25-1898216 | FO-25-1884319 | N3: 45988.333 | O3: 45993.419 | R3: CANCELADO | EJECUTADO/CANCELADO | S3: [FO-25-1898216] 02/12/2025 CONFIRMO LA CANCELACIÓN DE LA IMPLEMENTACIÓN DEL CB 82329 POR PARTE DEL USUARIO DEBIDO A QUE EN LA PLATAFORMA DE SOMOD BANCOLOMBIA NO LE FUNCIONA EL USUARIO Y CONTRASEÑA || [FO-25-1884319] 26/11/2025 26-11 PROGRAMACION REALIZADA POR LA ALIANZA| INSTALACIÓN PROGRAMADA PARA EL 2025-11-27 | 27/11/2025 SE VISITA DIRECCIÓN INDICADA DE INSTALACIÓN DE CB, SE VALIDA CORREO DE USUARIO PARA LA PLATAFORMA SOMOS BANCOLOMBIA . EVIDENCIA QUE PRESENTA INCONSISTENCIA . POR TAL MOTIVO NO ES POSIBLE EL INGRESO A SOMOS BANCOLOMBIA EL CLIENTE MANIFIESTA NO RECIBIR LA INSTALACIÓN DEL CB YA QUE NO PUEDE VISUALIZAR LOS MOVIMIENTOS DE LA PLATAFORMA ESTAR SEGURA DE LA OPERATIVIDAD DEL CB INFORMA QUE SE COMUNICARA CON EL PTM PARA CORRECCIÓN DE CORREO | T3: SOPORTE TELEFONICO | V3: TIPO I | W3: TERRESTRE | X3: GUTIERREZ CAMILO ANDRES | Y3: 0 | Z3: 0 | AA3: 0 | AB3: 0 | AC3: 1 | AD3: 44560 | AE3: 44560
A4: VALLEDUPAR | B4: COSTA | C4: 0004-0001 | D4: 44378 | E4: TA-25-1341466 | F4: 3007057635 | G4: APERTURA | H4: DATAFONO ADICIONAL - ALIANZA | I4: LA GUAJIRA | J4: HATONUEVO | K4: MULTIPAGAS HATONUEVO | L4: REDEBAN | M4: FO-25-1921921 | FO-25-1911535 | N4: 45993.333 | O4: 45997.455 | P4: ROBUSTO | Q4: MULTIPAGAS | R4: EJECUTADO | EJECUTADO/CANCELADO | S4: [FO-25-1921921] 09/12/2025 SE REALIZA INSTALACIÓN DE DATAFONO ADICIONAL, SE INSTALA DATAFONO, LECTOR, PINPAD Y MAGICBOX 2600, SE ENTREGAN 40 ROLLOS, SE BRINDA CAPACITACIÓN, SE REALIZAN PRUEBAS DE TRANSACCIONES, DEJANDO SERVICIO FUNCIONAL AL 100 % || [FO-25-1911535] 01/12/2025 01-12 SE REALIZA LLAMADA AL CLIENTE, SE HABLA CON LA SRA TATIANA TOLOZA SE VALIDA DIRECCIÓN OK, CANAL OK, DISPONIBILIDAD TOTAL, LLAMAR EL DÍA LA INSTALACIÓN PARA CONFIRMAR VISITA | 03/12/2025 SE LLEGA A SITIO, COMERCIO INDICA QUE PARA PODER INGRESAR SE NECESITA LA AUTORIZACIÓN Y VALIDACION DE BANCOLOMBIA, PROCEDEN A LLAMAR A LA LINEA PERO ESTA NO RESPONDEN, SE INTENTA POR OTROS MEDIOS COMO WPP Y TAMPOCO CONTESTAN, SE LE INDICA AL JEFE DEL MULTIPAGAS QUE VAMOS A REALIZAR UNA INSTALACIÓN DE UN DATAFONO ADICIONAL Y ESTE INDICA QUE SIN LA AUTORIZACIÓN DEL BANCO, NO ME PERMITEN EL INGRESO, SE INTENTA COMUNICAR CON LA LINEA DE BANCOLOMBIA EN UN LAPSO DE TIEMPO DE UNA HORA Y MEDIA, Y NUNCA CONTESTARON, ME COMUNICO CON EL COORDINADOR JOSE HERNÁNDEZ Y ESTE MANIFIESTA QUE SE TIENE QUE REAGENDAR LA VISITA Y QUE ME RETIRE DEL SITIO | T4: VISITA TECNICA | U4: AE007354 | V4: TIPO III | W4: TERRESTRE | X4: MONTES DIAZ JOHN FRED | Y4: 0 | Z4: 0 | AA4: 0 | AB4: 0 | AC4: 1 | AD4: 222904 | AE4: 222904
A5: MEDELLIN | B5: NOROCCIDENTE | C5: 0004-0005 | D5: 5001 | E5: TA-25-1393500 | F5: 3007082482 | G5: APERTURA | H5: CB CRECIMIENTO ALIANZA - NUEVO | I5: ANTIOQUIA | J5: MEDELLIN | K5: DISTRICOL JUGOS Y DOGS | L5: REDEBAN | M5: FO-25-1959693 | N5: 46003.333 | O5: 46003.701 | P5: AGREGADOR | Q5: DISTRICOL | R5: EJECUTADO/CANCELADO | S5: 11/12/2025 11-12 PROGRAMACION REALIZADA POR LA ALIANZA| INSTALACIÓN PROGRAMADA PARA EL 2025-12-12 | 12/12/2025 LA DIRECCIÓN A LA QUE DEBO INSTALAR EL CB BANCARIO ESTÁ ERRADA, LA USUARIA INDICA QUE SE PASARON DE LOCAL HACE POCO | T5: VISITA TECNICA | V5: TIPO I | W5: TERRESTRE | X5: RUA ALVAREZ RICHARD ANDRES | Y5: 0 | Z5: 0 | AA5: 0 | AB5: 0 | AC5: 1 | AD5: 44560 | AE5: 44560
A6: MEDELLIN | B6: NOROCCIDENTE | C6: 0004-0005 | D6: 5736 | E6: TA-25-1446323 | F6: 3007082552 | G6: APERTURA | H6: CB CRECIMIENTO ALIANZA - NUEVO | I6: ANTIOQUIA | J6: SEGOVIA | K6: DISTRICOL MAYRA SEGOVIA | L6: REDEBAN | M6: FO-25-2050073 | FO-25-2024451 | N6: 46015.333 | O6: 46021.473 | P6: AGREGADOR | Q6: DISTRICOL | R6: EJECUTADO | EJECUTADO/CANCELADO | S6: [FO-25-2050073] 30/12/2025 SE TERMINA DE HACER IMPLEMENTACION OK SE INSTALAS PUBLICIDAD OK PRUEBAS EXITOSAS || [FO-25-2024451] 23/12/2025 23-12 PROGRAMACION REALIZADA POR LA ALIANZA| INSTALACIÓN PROGRAMADA PARA EL 2025-12-26 | 26/12/2025 NO SE ENCUENTRA TIQUETE EN TÉRMINAL POR ALTO FLUJO DE PASAJERO. EN TAQUILLA INFORMAN QUE YA ESTÁN SOBRE VENDIDOS SE LE INFORMA AL USUARIO | 29/12/2025 SE ATIENDE IMPLEMENTACION OK, SE CAPACITA EN MENÚ OPERATIVO, SOMOS BANCOLOMBIA OK, SE INICIALIZA EQUIPOS OK. NO SE INSTALA PUBLICIDAD YA QUE SE ENVIÓ DESDE EL DÍA VIERNES Y HOY LUNES LA OFICINA ESTÁ CERRADA. NOS INDICAN QUE PARA EL DÍA DE MAÑANA ABREN NUEVAMENTE. SE DEJA VISITA PARA MAÑANA INSTALAR PUBLICIDAD | T6: VISITA TECNICA | U6: OB007843 | V6: TIPO IV | W6: TERRESTRE | X6: DIAZ ZABALA FRANCIS DUBAN | Y6: 0 | Z6: 0 | AA6: 0 | AB6: 0 | AC6: 1 | AD6: 464809 | AE6: 464809

Sheet INCIDENTES
A1: CIUDAD SEDE | B1: ZONA | C1: CENTRO DE COSTOS LINEACOM | D1: CODIGO DANE | E1: TA/CODIGO ACTIVIDAD | F1: CODIGO CB | G1: ACTIVIDAD | H1: DEPARTAMENTO | I1: CIUDAD | J1: NOMBRE DEL CB | K1: RED | L1: FO | M1: FECHA ASIGNACION A LINEA COMUNICACIONES | N1: FECHA CIERRE DEL TICKET (DD/MM/AAAA HH:MM) | O1: ACOMETIDA | P1: GRUPO_FALLA | Q1: CATEGORIA | R1: FALLA | S1: FORMATO | T1: CADENA | U1: ESTADO | V1: OBSERVACION | W1: FORMA DE ATENCION | X1: TERMINAL(ES) | Y1: TIPIFICACION | Z1: TIPO DE TRAYECTO | AA1: NOMBRE DEL TECNICO | AB1: DIAS DE VISITA | AC1: ACOMETIDA DATOS | AD1: ACOMETIDA ELÉCTRICA | AE1: SWITCH | AF1: ROUTER | AG1: VALOR DIAS ACTIVIDAD FACTURABLES | AH1: VALOR DIAS ACOMPAÑAMIENTO FACTURABLE
A2: VILLAVICENCIO | B2: REMOTAS | C2: 0004-0007 | D2: 50313 | E2: 3069845 | F2: 3007050504 | G2: INCIDENTE | H2: META | I2: GRANADA | J2: BARRIO ZONA RURAL GRANADA META | K2: REDEBAN | L2: FO-25-1895555 | M2: 45988.363 | N2: 45992.437 | O2: NO | P2: USUARIO | Q2: MANTENIMIENTO | R2: MANTENIMIENTO GENERAL | S2: CB UNO A UNO | T2: CB UNO A UNO | V2: 27/11/2025 SE ESCALA PARA VISITA. LLAMAR ANTES DE VISITAR, CONFIRMAR FALLA Y DATOS | 30/11/2025 CLIENTE INFORMA QUE NOS RECIBE EL LUNES YA QUE NO SE ENCUENTRA DISPONIBLE | 01/12/2025 SE REALIZA CONTACTO TELEFONICO CON EL CLIENTE Y SE LE INFORMA EL CAMBIO DE CONTRASEÑA Y QUEDAN OPERANDO OK | W2: SOPORTE TELEFONICO | Y2: TIPO II | Z2: TERRESTRE | AA2: PEDREROS CONTRERAS MICHAEL STEVENS | AB2: 0 | AC2: 0 | AD2: 0 | AE2: 0 | AF2: 0 | AG2: 37905 | AH2: 37905
A3: IBAGUE | B3: REMOTAS | C3: 0004-0007 | D3: 17495 | E3: 3073674 | F3: 3007067178 | G3: INCIDENTE | H3: CALDAS | I3: NORCASIA | J3: DISTRICOL PAPE & DET MIL IDEAS | K3: REDEBAN | L3: FO-25-1899864 | M3: 45988.738 | N3: 45995.526 | O3: NO | P3: USUARIO | Q3: COMUNICACION | R3: CONEXIONES DE COMERCIO | S3: AGREGADOR | T3: DISTRICOL | V3: 27/11/2025 SE ESCALA PARA VISITA. LLAMAR ANTES DE VISITAR, CONFIRMAR FALLA Y DATOS | 04/12/2025 SE LLAMA AL SEÑOR JOHAN CORTES, AL NÚMERO DE TELÉFONO 3128503919 Y ME INDICA QUE EL DATAFONO ESTÁ FUNCIONANDO CORRECTAMENTE. QUE PARECE QUE SOLO ERA BAJONES DE ENERGÍA. | W3: SOPORTE TELEFONICO | Y3: TIPO IV | Z3: TERRESTRE | AA3: VARGAS HERRERA JHON JAIRO | AB3: 0 | AC3: 0 | AD3: 0 | AE3: 0 | AF3: 0 | AG3: 37905 | AH3: 37905
A4: CALI | B4: SUROCCIDENTE Y EJE CAFETERO | C4: 0004-0003 | D4: 76834 | E4: 3079308 | F4: 3007068412 | G4: INCIDENTE | H4: VALLE DEL CAUCA | I4: TULUA | J4: BARRIO MARACAIBO TULUA 4 | K4: REDEBAN | L4: FO-25-1908630 | M4: 45990.663 | N4: 45992.375 | O4: NO | P4: USUARIO | Q4: COMUNICACION | R4: CONEXIONES DE COMERCIO | S4: CB UNO A UNO | T4: CB UNO A UNO | V4: 30/11/2025 SE ESCALA PARA VISITA. LLAMAR ANTES DE VISITAR, CONFIRMAR FALLA Y DATOS | 01/12/2025 SE HABLA CON LA SRA FANNY CASTRO E INDICA QUE YA EL EQUIPO ESTA OPERATIVO, QUE CONECTO EL DATAFONO A OTRO PUERTO Y REINICIO EL MODEM Y TODO QUEDO OK, CB OPERATIVO Y OK, LA CLIENTA AUTORIZA CERRAR LA ORDEN | W4: SOPORTE TELEFONICO | Y4: TIPO II | Z4: TERRESTRE | AA4: PAREDES CASTILLO DIEGO | AB4: 0 | AC4: 0 | AD4: 0 | AE4: 0 | AF4: 0 | AG4: 37905 | AH4: 37905
A5: MEDELLIN | B5: NOROCCIDENTE | C5: 0004-0005 | D5: 5579 | E5: 3082818 | F5: 3007081068 | G5: INCIDENTE | H5: ANTIOQUIA | I5: PUERTO BERRIO | J5: BARRIO CENTRO PUERTO BERRIO 9 | K5: REDEBAN | L5: FO-25-1912127 | M5: 45992.443 | N5: 45994.57 | O5: NO | P5: USUARIO | Q5: COMUNICACION | R5: CONEXIONES DE COMERCIO | S5: UNO A UNO | T5: UNO A UNO | U5: EJECUTADO | V5: 01/12/2025 SE ESCALA PARA VISITA. LLAMAR ANTES DE VISITAR, CONFIRMAR FALLA Y DATOS | 03/12/2025 SE HACE MANTENIMIENTO OK SE VALIDA CABLEADO DEL CLIENTE SE EVIDENCIA QUE TIENE DOS MULTIPUNTOS DE INTERNET MAL CONECTADOS, OCASIONADO LA INTERMITENCIA EN EL DATAFONO. SE ORGANIZA CABLE Y SE ENTREGA NUEVAMENTE DATAFONO FUNCIONANDO CORRECTAMENTE. | W5: VISITA TECNICA | X5: SHZZZ029 | Y5: TIPO III | Z5: TERRESTRE | AA5: DIAZ ZABALA FRANCIS DUBAN | AB5: 1 | AC5: 0 | AD5: 0 | AE5: 0 | AF5: 0 | AG5: 275728 | AH5: 275728
A6: MEDELLIN | B6: NOROCCIDENTE | C6: 0004-0005 | D6: 5101 | E6: 3083235 | F6: 3007066781 | G6: INCIDENTE | H6: ANTIOQUIA | I6: CIUDAD BOLIVAR | J6: BARRIO CIUDAD BOLIVAR CIUDAD B | K6: REDEBAN | L6: FO-25-1912725 | M6: 45992.462 | N6: 45993.51 | O6: NO | P6: USUARIO | Q6: NO ENCIENDE | R6: CONEXIONES DE COMERCIO | S6: UNO A UNO | T6: CB UNO A UNO | U6: EJECUTADO | V6: 01/12/2025 SE ESCALA PARA VISITA. LLAMAR ANTES DE VISITAR, CONFIRMAR FALLA Y DATOS | 02/12/2025 SE VERIFICACION DE LA CONEXIÓN DEL CB SE CAMBIA DE TOMA DE ALIMENTACIÓN | W6: VISITA TECNICA | X6: 3A0CZ741 | Y6: TIPO II | Z6: TERRESTRE | AA6: CASTAÑEDA PALACIO CARLOS FELIPE | AB6: 1 | AC6: 0 | AD6: 0 | AE6: 0 | AF6: 0 | AG6: 163814 | AH6: 163814
A7: MEDELLIN | B7: NOROCCIDENTE | C7: 0004-0005 | D7: 5308 | E7: 3085365 | F7: 3007082034 | G7: INCIDENTE | H7: ANTIOQUIA | I7: GIRARDOTA | J7: DISTRICOL PELUQUERÍA CANINA | K7: REDEBAN | L7: FO-25-1914679 | M7: 45992.612 | N7: 45993.431 | O7: NO | P7: USUARIO | Q7: COMUNICACION | R7: CONEXIONES DE COMERCIO | S7: AGREGADOR | T7: DISTRICOL | V7: 01/12/2025 SE ESCALA PARA VISITA. LLAMAR ANTES DE VISITAR, CONFIRMAR FALLA Y DATOS | 02/12/2025 SE REALIZÓ LLAMADA TELEFÓNICA AL CORRESPONSAL BANCOLOMBIA PARA VERIFICAR EL ESTADO DEL INCIDENTE REPORTADO CON EL DATÁFONO. EL USUARIO INFORMÓ QUE EL DISPOSITIVO YA SE ENCUENTRA EN FUNCIONAMIENTO Y QUE NO ES NECESARIA LA VISITA TÉCNICA, DADO QUE LA FALLA ESTABA ASOCIADA A LA CONEXIÓN DE INTERNET DEL COMERCIO Y FUE SOLUCIONADA. | W7: SOPORTE TELEFONICO | Y7: TIPO I | Z7: TERRESTRE | AA7: MARTINEZ TOVAR OSCAR DAVID | AB7: 0 | AC7: 0 | AD7: 0 | AE7: 0 | AF7: 0 | AG7: 37905 | AH7: 37905
A8: MONTERIA | B8: COSTA | C8: 0004-0001 | D8: 23675 | E8: 3087575 | F8: 3007079907 | G8: INCIDENTE | H8: CORDOBA | I8: SAN BERNARDO DEL VIENTO | J8: DISTRICOL EL CAMPESINO GRANERO | K8: REDEBAN | L8: FO-25-1916922 | M8: 45993.333 | N8: 45993.506 | O8: NO | P8: USUARIO | Q8: COMUNICACION | R8: CONEXIONES DE COMERCIO | S8: AGREGADOR | T8: DISTRICOL | U8: EJECUTADO | V8: 02/12/2025 SE ESCALA ACTIVIDAD PARA GESTION WOMPI | 02/12/2025 SE REALIZA VISITA TÉCNICA Y SE CORRIGE COMUNICACIÓN ETHERNET CON EL DATAFONO, IDENTIFICADO EL INCONVENIENTE EN EL PUERTO ETHERNET DEL MODEM DEL CLIENTE REALIZANDO CAMBIO DE PUERTO PARA ASÍ RESTABLECER NUEVAMENTE LA COMUNICACIÓN Y DEJAR EL SERVICIO OPERATIVO DANDO SOLUCIÓN AL PROBLEMA. | W8: VISITA TECNICA | X8: SAUZZ956 | Y8: TIPO II | Z8: TERRESTRE | AA8: CASSIANI PEREZ RAUL RAMIRO | AB8: 1 | AC8: 0 | AD8: 0 | AE8: 0 | AF8: 0 | AG8: 163814 | AH8: 163814
A9: CUCUTA | B9: SANTANDERES | C9: 0004-0008 | D9: 54001 | E9: 3097841 | F9: 3007061712 | G9: INCIDENTE | H9: NORTE DE SANTANDER | I9: CUCUTA | J9: PTM CUCUTA VARIEDADES REYMAR 3 | K9: REDEBAN | L9: FO-25-1926607 | M9: 45994.592 | N9: 45995.457 | O9: NO | P9: USUARIO | Q9: MANTENIMIENTO | R9: MANTENIMIENTO GENERAL | S9: AGREGADOR | T9: COMCARD - PTM | U9: EJECUTADO | V9: 03/12/2025 SE ESCALA PARA VISITA. LLAMAR ANTES DE VISITAR, CONFIRMAR FALLA Y DATOS | 04/12/2025 SE ENCONTRÓ TAPA MAL CERRADA,SE REALIZA MANTENIMIENTO CIERRES Y PRUEBAS OK | W9: VISITA TECNICA | X9: FUA0L506 FUA0L603 | Y9: TIPO I | Z9: TERRESTRE | AA9: DURAN ACOSTA FRANK YONNY | AB9: 1 | AC9: 0 | AD9: 0 | AE9: 0 | AF9: 0 | AG9: 65960 | AH9: 65960
A10: CALI | B10: SUROCCIDENTE Y EJE CAFETERO | C10: 0004-0003 | D10: 76001 | E10: 3098032 | F10: 3007040255 | G10: INCIDENTE | H10: VALLE DEL CAUCA | I10: CALI | J10: PTM CALI MUNDO MOVIL | K10: REDEBAN | L10: FO-25-1926596 | M10: 45994.605 | N10: 45994.681 | O10: NO | P10: USUARIO | Q10: COMUNICACION | R10: CONEXIONES DE COMERCIO | S10: AGREGADOR | T10: COMCARD - PTM | U10: EJECUTADO | V10: 03/12/2025 SE ESCALA PARA VISITA. LLAMAR ANTES DE VISITAR, CONFIRMAR FALLA Y DATOS | 03/12/2025 SE LLEGA AL COMERCIO SE ENCUENTRA QUE ESTÁ DESCONECTADO EL INTERNET DEL ROUTER SE CONECTA SE HACEN PRUEBAS EXITOSAS | W10: VISITA TECNICA | X10: AB0HZ961 UV001663 | Y10: TIPO I | Z10: TERRESTRE | AA10: PALACIOS GOMEZ BRAHIAN ANDRES | AB10: 1 | AC10: 0 | AD10: 0 | AE10: 0 | AF10: 0 | AG10: 65960 | AH10: 65960
A11: IBAGUE | B11: REMOTAS | C11: 0004-0007 | D11: 73585 | E11: 3099382 | F11: 3007032656 | G11: INCIDENTE | H11: TOLIMA | I11: PURIFICACION | J11: BARRIO LOS CAMBULOS PURIFICACI | K11: REDEBAN | L11: FO-25-1927810 | M11: 45995.333 | N11: 45995.833 | O11: NO | P11: USUARIO | Q11: NO ENCIENDE | R11: CONEXIONES DE COMERCIO | S11: CB UNO A UNO | T11: CB UNO A UNO | U11: EJECUTADO | V11: 03/12/2025 SE ESCALA PARA VISITA. LLAMAR ANTES DE VISITAR, CONFIRMAR FALLA Y DATOS | 04/12/2025 SE REALIZA VISITA AL PUNTO, SE CONECTA DE FORMA CORRECTA EL PINPAD ,EQUIPO FUNCIONA DE FORMA EXITOSA, CB OPERATIVO | W11: VISITA TECNICA | X11: BL01X782 | Y11: TIPO II | Z11: TERRESTRE | AA11: DEVIA REINOSO JUAN CARLOS | AB11: 1 | AC11: 0 | AD11: 0 | AE11: 0 | AF11: 0 | AG11: 163814 | AH11: 163814
A12: BOGOTA | B12: CUNDINAMARCA | C12: 0004-0004 | D12: 11001 | E12: 3101986 | F12: 3007076110 | G12: INCIDENTE | H12: CUNDINAMARCA | I12: BOGOTA | J12: PTM BOGOTA HERRAJES E INSUMOS | K12: REDEBAN | L12: FO-25-1929961 | M12: 45995.433 | N12: 45996.426 | O12: NO | P12: USUARIO | Q12: COMUNICACION | R12: CONEXIONES DE COMERCIO | S12: AGREGADOR | T12: COMCARD - PTM | U12: EJECUTADO | V12: 04/12/2025 SE ESCALA PARA VISITA. LLAMAR ANTES DE VISITAR, CONFIRMAR FALLA Y DATOS | 05/12/2025 EN CAMINO CLIENTE SOLICITA SER ATENDIDO DESPUÉS DE LAS 11 AM YA QUE SE ENCUENTRA EN DILIGENCIAS PERSONALES | 05/12/2025 FALLA EN EL CABLE DE RED DEL CLIENTE SE REALIZA REPARACIÓN CON PONCHADORA DEL TÉCNICO PRUEBAS OK NO TIENEN TARJETA PARA REALIZAR PRUEBAS DE ADQUIRENCIA | W12: VISITA TECNICA | X12: SX0GZ261 SX0HZ210 | Y12: TIPO I | Z12: TERRESTRE | AA12: GOMEZ VEGA DAVID SNEYDER | AB12: 1 | AC12: 0 | AD12: 0 | AE12: 0 | AF12: 0 | AG12: 65960 | AH12: 65960
A13: BARRANQUILLA | B13: COSTA | C13: 0004-0001 | D13: 8638 | E13: 3101991 | F13: 3007048428 | G13: INCIDENTE | H13: ATLANTICO | I13: SABANALARGA | J13: PTM SABANALARGA MULTISERVICI | K13: REDEBAN | L13: FO-25-1929960 | M13: 45995.434 | N13: 45996.693 | O13: NO | P13: ENTIDAD | Q13: ERROR DE TRANSACCIONES | R13: TRANSACCION NO PERMITIDA | S13: AGREGADOR | T13: COMCARD - PTM | U13: EJECUTADO | V13: 04/12/2025 SE ESCALA PARA VISITA. LLAMAR ANTES DE VISITAR, CONFIRMAR FALLA Y DATOS | 05/12/2025 DESPUÉS ESTAR HACIENDO PRUEBAS TODO EL DÍA,EL SEÑOR EDINSON SAMBONI DE SOPORTE RBM, ME INFORMA LO SIGUIENTE EL ERROR PROVIENE DE UN PROCESAMIENTO ERRADO EN EL TRASLADO DESDE LA ENTIDAD QUE GENERÓ ERROR EN LA PLATAFORMA DE BASE24 Y EL CASO ESTÁ EN PROCESO DE SOLUCIÓN EN NIVEL 3 CON TI, OPERACIONES Y BACKOFFICE. LA ENTIDAD PROCEDO MAL LOS PUNTOS POR ORDEN DE SOPORTE RBM, NOS RETIRAMOS DEL SITIO UNO DE LOS DATADONOS ERA MIXTO, Y SE DEJA PURO, CLIENTE TE DICE QUE NO USA LA FRANQUICIA, LA TERMINAL MA00B931 CON LA PLACA 771708, SE ANULA POR ORDEN DE SOPORTE RBM QUEDA A LA ESPERA DE LA SOLUCIÓN | W13: VISITA TECNICA | X13: IIRZZ937 -NA00K179 | Y13: TIPO II | Z13: TERRESTRE | AA13: DE AVILA SIADES ALBERTO ENRIQUE | AB13: 1 | AC13: 0 | AD13: 0 | AE13: 0 | AF13: 0 | AG13: 163814 | AH13: 163814
A14: APARTADO | B14: NOROCCIDENTE | C14: 0004-0005 | D14: 5837 | E14: 3106177 | F14: 3007038814 | G14: INCIDENTE | H14: ANTIOQUIA | I14: TURBO | J14: PTM VARILOCHE ALL FASHION | K14: REDEBAN | L14: FO-25-1934649 | M14: 45996.366 | N14: 45996.46 | O14: NO | P14: USUARIO | Q14: MANTENIMIENTO | R14: MANTENIMIENTO GENERAL | S14: AGREGADOR | T14: COMCARD - PTM | U14: EJECUTADO | V14: 05/12/2025 SE ESCALA PARA VISITA. LLAMAR ANTES DE VISITAR, CONFIRMAR FALLA Y DATOS | 05/12/2025 SE LE INDICA AL CLIENTE QUE LOS DATAFONOS DESK 2600 VIENEN CON FALLAS DE FABRICA, COMO EN ESTE CASO NOS TOCA CONVIVIR CON ELLA, SE LE EXPLICA AL CLIENTE COMO OPERAR LA IMPRESORA PARA QUE EL VOUCHER IMPRIMA BIEN HACIENDO PRESIÓN SOBRE LA TAPA. | W14: VISITA TECNICA | X14: MAA00L465 | Y14: TIPO II | Z14: TERRESTRE | AA14: CASTRO HENAO DANIEL ESTEBAN | AB14: 1 | AC14: 0 | AD14: 0 | AE14: 0 | AF14: 0 | AG14: 163814 | AH14: 163814
A15: VILLAVICENCIO | B15: REMOTAS | C15: 0004-0007 | D15: 50568 | E15: 3106528 | F15: 3007050427 | G15: INCIDENTE | H15: META | I15: PUERTO GAITAN | J15: PTM PUERTO GAITAN SERVI LA 18 | K15: REDEBAN | L15: FO-25-1935156 | M15: 45996.391 | N15: 46000.699 | O15: NO | P15: USUARIO | Q15: LECTOR DE BARRAS | R15: CAPACITACION MANIPULACION DE COMERCIO | S15: AGREGADOR | T15: COMCARD - PTM | U15: EJECUTADO | V15: 05/12/2025 SE ESCALA PARA VISITA. LLAMAR ANTES DE VISITAR, CONFIRMAR FALLA Y DATOS | 09/12/2025 SE VISITA EL CB POR SOLICITUD LECTORA DE BARRAS, SE LLEGA Y SE VERIFICA Y ESTABA MA CONECTADA SE CONECTA BIEN Y FUNCIONA CON NORMALIDAD SE REALIZAN PRUEBAS Y TODO OK | W15: VISITA TECNICA | X15: TR00W392 | Y15: TIPO III | Z15: TERRESTRE | AA15: MOLINA CASTRO JAVIER ALBERTO | AB15: 1 | AC15: 0 | AD15: 0 | AE15: 0 | AF15: 0 | AG15: 275728 | AH15: 275728
A16: CALI | B16: SUROCCIDENTE Y EJE CAFETERO | C16: 0004-0003 | D16: 76109 | E16: 3107267 | F16: 3007010970 | G16: INCIDENTE | H16: VALLE DEL CAUCA | I16: BUENAVENTURA | J16: BARRIO EL DORADO - BUENAVENTUR | K16: REDEBAN | L16: FO-25-1935702 | M16: 45996.455 | N16: 45997.515 | O16: NO | P16: USUARIO | Q16: COMUNICACION | R16: CANAL DEL COMERCIO | S16: CB UNO A UNO | T16: CB UNO A UNO | V16: 05/12/2025 SE ESCALA PARA VISITA. LLAMAR ANTES DE VISITAR, CONFIRMAR FALLA Y DATOS | 06/12/2025 SE VALIDA CON EL CLIENTE PERO SE ENCUENTRA PROBLEMAS CON EL CANAL DE INTERNET EL CUAL ESTA PRESENTANDO CAIDA Y ESO OCACIONA QUE EL DATAFONO TENGA CAIDAS, EL CANAL ES UN CANAL QUE EL CLIENTE TIENE HACE MUCHO INSTALADO POR BANCOLOMBIA, PERO SE LE INDICA QUE SOBRE ESTOS CANALES DEBE SOLICITAR SOPORTE A LA ENTIDAD. SE LE INFORMA QUE EN LO POSIBLE HAGA LA CONEXION CON UN CANAL PROPIO. | W16: SOPORTE TELEFONICO | Y16: TIPO III | Z16: TERRESTRE | AA16: HENAO CARDONA DIEGO FERNANDO | AB16: 0 | AC16: 0 | AD16: 0 | AE16: 0 | AF16: 0 | AG16: 37905 | AH16: 37905
A17: MEDELLIN | B17: NOROCCIDENTE | C17: 0004-0005 | D17: 5237 | E17: 3109370 | F17: 3007034409 | G17: INCIDENTE | H17: ANTIOQUIA | I17: DON MATIAS | J17: COMCARD DON MATIAS INT ZONE | K17: REDEBAN | L17: FO-25-1938040 | M17: 45996.654 | N17: 45997.381 | O17: NO | P17: USUARIO | Q17: COMUNICACION | R17: CANAL DEL COMERCIO | S17: AGREGADOR | T17: COMCARD - PTM | V17: 05/12/2025 SE ESCALA PARA VISITA. LLAMAR ANTES DE VISITAR, CONFIRMAR FALLA Y DATOS | 06/12/2025 SE LLAMA AL 3135404048 CLIENTE E INFORMA QUE LOS DATAFONO YA ESTÁN FUNCIONANDO BIEN Y NO NECESITA VISITA POR LO QUE SE CIERRA ACTIVIDAD | W17: SOPORTE TELEFONICO | Y17: TIPO II | Z17: TERRESTRE | AA17: ALVAREZ ARENAS VICTOR HUGO | AB17: 0 | AC17: 0 | AD17: 0 | AE17: 0 | AF17: 0 | AG17: 37905 | AH17: 37905
A18: MEDELLIN | B18: NOROCCIDENTE | C18: 0004-0005 | D18: 5237 | E18: 3109371 | F18: 3007055435 | G18: INCIDENTE | H18: ANTIOQUIA | I18: DON MATIAS | J18: BARRIO DON MATIAS DONMATIAS 2 | K18: REDEBAN | L18: FO-25-1938036 | M18: 45996.655 | N18: 45997.377 | O18: NO | P18: USUARIO | Q18: COMUNICACION | R18: CANAL DEL COMERCIO | S18: CB UNO A UNO | T18: CB UNO A UNO | U18: EJECUTADO | V18: 05/12/2025 SE ESCALA PARA VISITA. LLAMAR ANTES DE VISITAR, CONFIRMAR FALLA Y DATOS | 06/12/2025 SE LLEGA AL PUNTO PERO CB YA ESTABA OPERATIVO PARECE SER QUE ERA EL CANAL DEL CLIENTE | W18: VISITA TECNICA | X18: 9BGZZ206 | Y18: TIPO II | Z18: TERRESTRE | AA18: ALVAREZ ARENAS VICTOR HUGO | AB18: 1 | AC18: 0 | AD18: 0 | AE18: 0 | AF18: 0 | AG18: 163814 | AH18: 163814
A19: MEDELLIN | B19: NOROCCIDENTE | C19: 0004-0005 | D19: 5237 | E19: 3109620 | F19: 3007029892 | G19: INCIDENTE | H19: ANTIOQUIA | I19: DON MATIAS | J19: BARRIO PARQUE 3 DONMATIAS | K19: REDEBAN | L19: FO-25-1938032 | M19: 45996.66 | N19: 45997.393 | O19: NO | P19: USUARIO | Q19: COMUNICACION | R19: CANAL DEL COMERCIO | S19: CB UNO A UNO | T19: CB UNO A UNO | V19: 05/12/2025 SE ESCALA PARA VISITA. LLAMAR ANTES DE VISITAR, CONFIRMAR FALLA Y DATOS | 06/12/2025 SE LLAMA AL 3193812221 SE HABLA CON RAÚL GONZÁLES EL CUAL INFORMA QUE HOY AMANECIÓ BIEN EL CB AL PARECER HUBO UNA FALLA DE CANAL EN EL PUEBLO Y QUE YA NO NECESITA VISITA POR LO QUE SE CIERRA LA TA | W19: SOPORTE TELEFONICO | Y19: TIPO II | Z19: TERRESTRE | AA19: ALVAREZ ARENAS VICTOR HUGO | AB19: 0 | AC19: 0 | AD19: 0 | AE19: 0 | AF19: 0 | AG19: 37905 | AH19: 37905
A20: MEDELLIN | B20: NOROCCIDENTE | C20: 0004-0005 | D20: 5890 | E20: 3111188 | F20: 3007047258 | G20: INCIDENTE | H20: ANTIOQUIA | I20: YOLOMBO | J20: BARRIO EL HORMIGUERO YOLOMBO | K20: REDEBAN | L20: FO-25-1942691 | M20: 45998.531 | N20: 46000.387 | O20: NO | P20: USUARIO | Q20: COMUNICACION | R20: CONEXIONES DE COMERCIO | S20: CB UNO A UNO | T20: CB UNO A UNO | V20: 07/12/2025 SE ESCALA PARA VISITA. LLAMAR ANTES DE VISITAR, CONFIRMAR FALLA Y DATOS | 09/12/2025 EN COMUNICACIÓN CON LA SEÑORA BEATRIZ MANIFIESTA QUE YA EL EQUIPO ESTÁ OPERANDO CON NORMALIDAD. LA FALLA ERA UNA CAÍDA DEL INTERNET DEL COMERCIO EQUIPO OPERANDO CON NORMALIDAD | W20: SOPORTE TELEFONICO | Y20: TIPO II | Z20: TERRESTRE | AA20: DIAZ ZABALA FRANCIS DUBAN | AB20: 0 | AC20: 0 | AD20: 0 | AE20: 0 | AF20: 0 | AG20: 37905 | AH20: 37905
A21: MEDELLIN | B21: NOROCCIDENTE | C21: 0004-0005 | D21: 5088 | E21: 3111252 | F21: 3007059337 | G21: INCIDENTE | H21: ANTIOQUIA | I21: BELLO | J21: DISTRICOL TIENDA FERSAN | K21: REDEBAN | L21: FO-25-1942127 | M21: 45997.735 | N21: 45998.418 | O21: NO | P21: USUARIO | Q21: LECTOR DE BARRAS | R21: ERROR PAGOS PARCIALES DE FACTURAS | S21: AGREGADOR | T21: DISTRICOL | V21: 07/12/2025 SE ESCALA PARA VISITA. LLAMAR ANTES DE VISITAR, CONFIRMAR FALLA Y DATOS | 07/12/2025 SE REALIZÓ LLAMADA TELEFÓNICA AL CORRESPONSAL BANCOLOMBIA PARA CONFIRMAR EL INCIDENTE REPORTADO CON EL LECTOR DE CÓDIGOS DE BARRAS. EL USUARIO INFORMÓ QUE EL DÍA ANTERIOR EL DISPOSITIVO PRESENTÓ FALLAS AL MOMENTO DE LEER ALGUNAS FACTURAS; SIN EMBARGO, INDICÓ QUE EN LA FECHA ACTUAL EL LECTOR FUNCIONA DE MANERA NORMAL. POR TAL MOTIVO, EL USUARIO MANIFESTÓ QUE NO ES NECESARIA UNA VISITA TÉCNICA. | W21: SOPORTE TELEFONICO | Y21: TIPO I | Z21: TERRESTRE | AA21: MARTINEZ TOVAR OSCAR DAVID | AB21: 0 | AC21: 0 | AD21: 0 | AE21: 0 | AF21: 0 | AG21: 37905 | AH21: 37905
A22: IBAGUE | B22: REMOTAS | C22: 0004-0007 | D22: 73001 | E22: 3113118 | F22: 3007030812 | G22: INCIDENTE | H22: TOLIMA | I22: IBAGUE | J22: BARRIO CADIZ 4 | K22: REDEBAN | L22: FO-25-1945924 | M22: 46000.35 | N22: 46001.362 | O22: NO | P22: ENTIDAD | Q22: ERROR DE TRANSACCIONES | R22: TRANSACCION NO PERMITIDA | S22: CB UNO A UNO | T22: CB UNO A UNO | V22: 09/12/2025 SE ESCALA PARA VISITA. LLAMAR ANTES DE VISITAR, CONFIRMAR FALLA Y DATOS | 10/12/2025 SE COMUNICA AL NÚMERO 3015973051, EL SEÑOR WILFRIDO MORALES INDICA QUE ESTÁ PRESENTANDO ERROR EN TRANSACCIONES MARCA NO HABILITADA, DEBIDO A QUE NO FUE POSIBLE REALIZAR LA MIGRACIÓN A WOMPI POR TEMAS DE RAZÓN SOCIAL. SE LE RECOMIENDA AL CLIENTE QUE SE COMUNIQUE DIRECTAMENTE CON EL BANCO PARA QUE LE HABILITEN EL CB NUEVAMENTE. GESTIÓN TELEFÓNICA | W22: SOPORTE TELEFONICO | Y22: TIPO I | Z22: TERRESTRE | AA22: BARRAGAN TAFUR EDWIN ESTEBAN | AB22: 0 | AC22: 0 | AD22: 0 | AE22: 0 | AF22: 0 | AG22: 37905 | AH22: 37905
A23: IBAGUE | B23: REMOTAS | C23: 0004-0007 | D23: 73555 | E23: 3114244 | F23: 3007079015 | G23: INCIDENTE | H23: TOLIMA | I23: PLANADAS | J23: PTM PLANADAS HUEVOS DEL SUR DI | K23: REDEBAN | L23: FO-25-1946837 | M23: 46000.412 | N23: 46003.39 | O23: NO | P23: USUARIO | Q23: COMUNICACION | R23: CONEXIONES DE COMERCIO | S23: AGREGADOR | T23: COMCARD - PTM | U23: EJECUTADO | V23: 09/12/2025 SE ESCALA PARA VISITA. LLAMAR ANTES DE VISITAR, CONFIRMAR FALLA Y DATOS | 12/12/2025 SE REALIZA VISITA AL PUNTO, SE EVIDENCIA COMERCIO PRESENTA INTERMITENCIA EN EL INTERNET INSTALADO EN EL PUNTO, SE REVISAN CONEXIONES Y CABLES DEL EQUIPO Y ESTÁN EN BUEN ESTADO.EQUIPO OPERATIVO. PRUEBAS OK | W23: VISITA TECNICA | X23: SASZZ590 SASZZ754 | Y23: TIPO IV | Z23: TERRESTRE | AA23: DEVIA REINOSO JUAN CARLOS | AB23: 1 | AC23: 0 | AD23: 0 | AE23: 0 | AF23: 0 | AG23: 479590 | AH23: 479590
A24: CALI | B24: SUROCCIDENTE Y EJE CAFETERO | C24: 0004-0003 | D24: 76001 | E24: 3114593 | F24: 3007082168 | G24: INCIDENTE | H24: VALLE DEL CAUCA | I24: CALI | J24: PTM CALI VARIEDADES BLU | K24: REDEBAN | L24: FO-25-1947294 | M24: 46000.433 | N24: 46000.715 | O24: NO | P24: HARDWARE | Q24: COMUNICACION | R24: MENSAJE CABLE DE RED DESCONECTADO | U24: EJECUTADO | V24: 09/12/2025 SE ESCALA PARA VISITA. LLAMAR ANTES DE VISITAR, CONFIRMAR FALLA Y DATOS | 09/12/2025 SE VISITA CORRESPONSAL Y SE REPARA CABLE DE RED DE ACOMETIDA DAÑADO.( PONCHADO) TRANSACCIÓNES DE PRUEBA EXITOSAS. | W24: VISITA TECNICA | X24: FB001822 FB001570 | Y24: TIPO I | Z24: TERRESTRE | AA24: BOLAÑOS TABORDA JORGE ENRIQUE | AB24: 0 | AC24: 0 | AD24: 0 | AE24: 0 | AF24: 0 | AG24: 306552 | AH24: 306552
A25: CUCUTA | B25: SANTANDERES | C25: 0004-0008 | D25: 54498 | E25: 3120323 | F25: 3007029042 | G25: INCIDENTE | H25: NORTE DE SANTANDER | I25: OCAÑA | J25: BARRIO CENTRO OCANA | K25: REDEBAN | L25: FO-25-1952613 | M25: 46001.392 | N25: 46002.447 | O25: NO | P25: USUARIO | Q25: COMUNICACION | R25: CONEXIONES DE COMERCIO | S25: CB UNO A UNO | T25: COOGUASIMALES | U25: EJECUTADO | V25: 10/12/2025 SE ESCALA PARA VISITA. LLAMAR ANTES DE VISITAR, CONFIRMAR FALLA Y DATOS | 11/12/2025 SE REALIZA VISITA AL COMERCIO Y SE REVISAN CONEXIONES DEL CONEXIONES DEL DATAFONO Y PARÁMETROS TODO OK, SE EVIDENCIA QUE LA FALLA SON LAS CONEXIONES PARTE INTERNA DEL COMERCIO, SE HABLÓ CON LA SRA JEFE DEL ÁREA DEL PAGO FACIL, SRA BRENDA SUJEY MANIFIESTA QUE LE DEJEMOS EL DATAFONO SIN CONEXIÓN A LA CAJA. | W25: VISITA TECNICA | X25: BBBBF023 | Y25: TIPO IV | Z25: TERRESTRE | AA25: MORA VEGA JEAMPIER | AB25: 1 | AC25: 0 | AD25: 0 | AE25: 0 | AF25: 0 | AG25: 479590 | AH25: 479590
A26: CALI | B26: SUROCCIDENTE Y EJE CAFETERO | C26: 0004-0003 | D26: 76892 | E26: 3120999 | F26: 3007021211 | G26: INCIDENTE | H26: VALLE DEL CAUCA | I26: YUMBO | J26: BARRIO CENTRO VIII YUMBO | K26: REDEBAN | L26: FO-25-1953530 | M26: 46001.454 | N26: 46002.423 | O26: NO | P26: USUARIO | Q26: USUARIOS | R26: TAPA MAL ASEGURADA | S26: CB UNO A UNO | T26: CB UNO A UNO | U26: EJECUTADO | V26: 10/12/2025 SE ESCALA PARA VISITA. LLAMAR ANTES DE VISITAR, CONFIRMAR FALLA Y DATOS | 11/12/2025 SE VISITA CORRESPONSAL Y SE ENCONTRÓ DATÁFONO EN BUEN ESTADO. IMPRIME CORRECTAMENTE. TRANSACCIONES DE PRUEBA EXITOSAS. | W26: VISITA TECNICA | X26: 9B2ZZ833 | Y26: TIPO I | Z26: TERRESTRE | AA26: BOLAÑOS TABORDA JORGE ENRIQUE | AB26: 1 | AC26: 0 | AD26: 0 | AE26: 0 | AF26: 0 | AG26: 65960 | AH26: 65960
A27: APARTADO | B27: NOROCCIDENTE | C27: 0004-0005 | D27: 5045 | E27: 3125304 | F27: 3007032310 | G27: INCIDENTE | H27: ANTIOQUIA | I27: APARTADO | J27: PAGAFACIL APARTADO CENTRO II | K27: REDEBAN | L27: FO-25-1957611 | M27: 46002.339 | N27: 46002.647 | O27: NO | P27: USUARIO | Q27: CIERRE | R27: COMERCIO NO REALIZA CIERRE | S27: ROBUSTO | T27: PAGAFACIL | U27: EJECUTADO | V27: 11/12/2025 SE ESCALA PARA VISITA. LLAMAR ANTES DE VISITAR, CONFIRMAR FALLA Y DATOS | 11/12/2025 SE REALIZA REPISADO DE PARAMETRO Y INICIALIZACION. DATAFONO QUEDA OPERATIVO. | W27: VISITA TECNICA | X27: 111JZ555 | Y27: TIPO I | Z27: TERRESTRE | AA27: CASTRO HENAO DANIEL ESTEBAN | AB27: 1 | AC27: 0 | AD27: 0 | AE27: 0 | AF27: 0 | AG27: 65960 | AH27: 65960
A28: VILLAVICENCIO | B28: REMOTAS | C28: 0004-0007 | D28: 50287 | E28: 3126154 | F28: 3007080450 | G28: INCIDENTE | H28: META | I28: FUENTE DE ORO | J28: BARRIO CENTRO FUENTE DE ORO 5 | K28: REDEBAN | L28: FO-25-1958710 | M28: 46002.412 | N28: 46003.524 | O28: NO | P28: USUARIO | Q28: NO ENCIENDE | R28: CONEXIONES DE COMERCIO | S28: UNO A UNO | T28: UNO A UNO | U28: EJECUTADO | V28: 11/12/2025 SE ESCALA PARA VISITA. LLAMAR ANTES DE VISITAR, CONFIRMAR FALLA Y DATOS | 12/12/2025 SE REALIZA VISITA AL CB POR SOLICITUD DATÁFONO NO PRENDE LA USUARIA TATIANA GONZALES NOS RECIBE LA VISITA,SE VERIFICA LAS CONEXIONES DEL COMERCIO Y DEL EQUIPO Y SE EVIDENCIA QUE NO SE ENCUENTRA BIEN CONECTADO EL CABLE FUENTE DE PODER, SE CONECTA BIEN Y EL EQUIPO ENCIENDE CON NORMALIDAD, PROCEDO A REALIZAR PRUEBAS Y TODO SALE CORRECTO SE DEJA FUNCIONAL DÁNDOLE SOLUCIÓN AL PROBLEMA QUE PRESENTABA EL USUARIO | W28: VISITA TECNICA | X28: SAZZZ799 | Y28: TIPO III | Z28: TERRESTRE | AA28: MOLINA CASTRO JAVIER ALBERTO | AB28: 1 | AC28: 0 | AD28: 0 | AE28: 0 | AF28: 0 | AG28: 275728 | AH28: 275728
A29: TUNJA | B29: SANTANDERES | C29: 0004-0008 | D29: 15646 | E29: 3127796 | F29: 3007080299 | G29: INCIDENTE | H29: BOYACA | I29: SAMACA | J29: BARRIO VEREDA CHURUVITA SAMACA | K29: REDEBAN | L29: FO-25-1960579 | M29: 46002.583 | N29: 46005.479 | O29: NO | P29: USUARIO | Q29: COMUNICACION | R29: CONEXIONES DE COMERCIO | S29: UNO A UNO | T29: UNO A UNO | U29: EJECUTADO | V29: 11/12/2025 SE ESCALA PARA VISITA. LLAMAR ANTES DE VISITAR, CONFIRMAR FALLA Y DATOS | 13/12/2025 SE VISITA PUNTO EVIDENCIANDO QUE EL EQUIPO NO TIENE COMUNICACIÓN ROUTER REPETIDOR DESCONFIGURADO DEBIDO AL CAMBIO DE CLAVE DEL ROUTER PRINCIPAL SE PROCEDE A REALIZAR LAS CORRECCIONES CORRESPONDIENTES PRUEBAS EXITOSAS CLIENTE CONFORME. | W29: VISITA TECNICA | X29: FAZZZ477 | Y29: TIPO II | Z29: TERRESTRE | AA29: RODRIGUEZ MURCIA YERSON IVAN | AB29: 1 | AC29: 0 | AD29: 0 | AE29: 0 | AF29: 0 | AG29: 163814 | AH29: 163814
A30: CUCUTA | B30: SANTANDERES | C30: 0004-0008 | D30: 54498 | E30: 3128766 | F30: 3007029042 | G30: INCIDENTE | H30: NORTE DE SANTANDER | I30: OCAÑA | J30: BARRIO CENTRO OCANA | K30: REDEBAN | L30: FO-25-1961434 | M30: 46002.655 | N30: 46003.376 | O30: NO | P30: USUARIO | Q30: COMUNICACION | R30: CONEXIONES DE COMERCIO | S30: CB UNO A UNO | T30: COOGUASIMALES | U30: EJECUTADO | V30: 11/12/2025 SE ESCALA PARA VISITA. LLAMAR ANTES DE VISITAR, CONFIRMAR FALLA Y DATOS | 12/12/2025 SE REALIZA VISITA AL COMERCIO Y SE REALIZA INTEGRACIÓN A CAJA, SE REALIZAN PRUEBAS EXITOSAS | W30: VISITA TECNICA | X30: BBBBF023 | Y30: TIPO IV | Z30: TERRESTRE | AA30: MORA VEGA JEAMPIER | AB30: 1 | AC30: 0 | AD30: 0 | AE30: 0 | AF30: 0 | AG30: 479590 | AH30: 479590
A31: BOGOTA | B31: CUNDINAMARCA | C31: 0004-0004 | D31: 25754 | E31: 3130682 | F31: 3007072701 | G31: INCIDENTE | H31: CUNDINAMARCA | I31: SOACHA | J31: PRADO VEGAS SOACHA 2 | K31: REDEBAN | L31: FO-25-1964892 | M31: 46003.38 | N31: 46005.499 | O31: NO | P31: USUARIO | Q31: COMUNICACION | R31: CANAL DEL COMERCIO | S31: CB UNO A UNO | T31: CB UNO A UNO | U31: EJECUTADO | V31: 12/12/2025 SE ESCALA PARA VISITA. LLAMAR ANTES DE VISITAR, CONFIRMAR FALLA Y DATOS | 13/12/2025 SE REALIZA LLAMADA A NÚMEROS REGISTRADOS 3183835633-3138784133 NO HAY CONTACTO, TÉCNICO REALIZARÁ DESPLAZAMIENTO A SITIO DEMORAS EN TRAFICO POR SALIDA DE CARROS DE BOGOTÁ POR SOACHA Y OBRAS DE TRANSMILENIO DEL MUNICIPIO | 13/12/2025 SE REALIZA VISITA TÉCNICA EN SITIO YA QUE NO HUBO CONTACTO PREVIO, ATIENDE DANNA NO INDICA APELLIDO DICE QUE NO TIENE CONOCIMIENTO DE LA VISITA Y QUE EL DATAFONO ESTÁ OPERANDO SIN PROBLEMAS NO ENTREGA SOPORTES Y NO FIRMA CONTROL SERVICIO ESTÁ OPERATIVO TÉCNICO NO MANIPULA TERMINAL | W31: VISITA TECNICA | X31: 0 | Y31: TIPO I | Z31: TERRESTRE | AA31: BUSTOS MORA DIEGO MANUEL | AB31: 1 | AC31: 0 | AD31: 0 | AE31: 0 | AF31: 0 | AG31: 65960 | AH31: 65960
A32: MEDELLIN | B32: NOROCCIDENTE | C32: 0004-0005 | D32: 5001 | E32: 3132042 | F32: 3007015529 | G32: INCIDENTE | H32: ANTIOQUIA | I32: MEDELLIN | J32: MULTIPAGAS LA MOTA | K32: REDEBAN | L32: FO-25-1965873 | M32: 46003.477 | N32: 46003.547 | O32: NO | P32: USUARIO | Q32: COMUNICACION | R32: CANAL DEL COMERCIO | S32: ROBUSTO | T32: MULTIPAGAS | V32: 12/12/2025 SE ESCALA PARA VISITA. LLAMAR ANTES DE VISITAR, CONFIRMAR FALLA Y DATOS | 12/12/2025 SE CONTACTA CON USUARIO ANDERSON DEL RIO - 3215189192 SE EVIDENCIA FALLA DEL INTERNET DEL COMERCIO, SE VERIFICA AJUSTES Y TODO OK, PRUEBAS DE CONEXIÓN OK, USUARIO INFORMA TRABAJAR SIN NOVEDAD, CB OPERATIVO | W32: SOPORTE TELEFONICO | Y32: TIPO I | Z32: TERRESTRE | AA32: HERNANDEZ CHAVARRIA JUAN CAMILO | AB32: 0 | AC32: 0 | AD32: 0 | AE32: 0 | AF32: 0 | AG32: 37905 | AH32: 37905
A33: NEIVA | B33: REMOTAS | C33: 0004-0007 | D33: 41551 | E33: 3132225 | F33: 3007017502 | G33: INCIDENTE | H33: HUILA | I33: PITALITO | J33: CENTRO PITALITO HUILA | K33: REDEBAN | L33: FO-25-1966140 | M33: 46003.5 | N33: 46005.51 | O33: NO | P33: USUARIO | Q33: COMUNICACION | R33: CONEXIONES DE COMERCIO | S33: CB UNO A UNO | T33: CB UNO A UNO | U33: EJECUTADO / CANCELADO | V33: 12/12/2025 SE ESCALA PARA VISITA. LLAMAR ANTES DE VISITAR, CONFIRMAR FALLA Y DATOS | 13/12/2025 SE LLEGA AL PUNTO, LA SEÑORITA CAROLINA MURCIA COMENTA QUE EL DATAFONO ESTÁ TRABAJANDO OK , ELLA MOVIÓ CABLES Y TRABAJO EL EQUIPO, NO HUBO NECESIDAD DE INGRESO A MANIPULAR EQUIPOS. | W33: VISITA TECNICA | X33: 00000 | Y33: TIPO III | Z33: TERRESTRE | AA33: ANDRADE HERNANDEZ JUAN CARLOS | AB33: 1 | AC33: 0 | AD33: 0 | AE33: 0 | AF33: 0 | AG33: 275728 | AH33: 275728
A34: MEDELLIN | B34: NOROCCIDENTE | C34: 0004-0005 | D34: 5631 | E34: 3133920 | F34: 3007069707 | G34: INCIDENTE | H34: ANTIOQUIA | I34: SABANETA | J34: DISTRICOL RESPLANDOR TODO PAR | K34: REDEBAN | L34: FO-25-1968243 | M34: 46003.717 | N34: 46005.444 | O34: NO | P34: ENTIDAD | Q34: ERROR DE TRANSACCIONES | R34: TRANSACCION NO PERMITIDA | S34: AGREGADOR | T34: DISTRICOL | U34: EJECUTADO | V34: 12/12/2025 SE ESCALA PARA VISITA. LLAMAR ANTES DE VISITAR, CONFIRMAR FALLA Y DATOS | 13/12/2025 EQUIPO DESCONFIGURADO, SE VUELVE A CONFIGURAR PARAMETROS, PRUEBAS Y TODO OK | W34: VISITA TECNICA | X34: MN002473 | Y34: TIPO I | Z34: TERRESTRE | AA34: HERNANDEZ CHAVARRIA JUAN CAMILO | AB34: 1 | AC34: 0 | AD34: 0 | AE34: 0 | AF34: 0 | AG34: 65960 | AH34: 65960
A35: APARTADO | B35: NOROCCIDENTE | C35: 0004-0005 | D35: 5045 | E35: 3134639 | F35: 3007070262 | G35: INCIDENTE | H35: ANTIOQUIA | I35: APARTADO | J35: DISTRICOL AL NATURAL JUGS | K35: REDEBAN | L35: FO-25-1970121 | M35: 46004.471 | N35: 46006.582 | O35: NO | P35: USUARIO | Q35: COMUNICACION | R35: CANAL DEL COMERCIO | S35: AGREGADOR | T35: DISTRICOL | V35: 13/12/2025 SE ESCALA PARA VISITA. LLAMAR ANTES DE VISITAR, CONFIRMAR FALLA Y DATOS | 13/12/2025 SE RELAIZO CONTACTO TELEFONICO SE HABLO LA SEÑORA BEATRIZ EUGENIA VELAZQUEZ EN EL TELEFONO 3016249493 SE HACEN LA VALIDACIONES DE CONEXION DEL DATAFANO SE ENCUENTRA NORMAL, APARENTE PUERTO LAN DEL DATAFONO AVERIADO NNO SE ALCANZA A VISITAR, REDEBAN SOLO FUNCIONA PARA CAMBIOS HASTA LA 1PM | 15/12/2025 CLIENTE INDICA QUE NO TENÍA INTERNET EN SU COMERCIO, AL VERIFICAR EL SWICTH Y REINICIALO RETOMO EL INTERNET EN EL DATAFONO. | W35: SOPORTE TELEFONICO | Y35: TIPO I | Z35: TERRESTRE | AA35: CASTRO HENAO DANIEL ESTEBAN | AB35: 0 | AC35: 0 | AD35: 0 | AE35: 0 | AF35: 0 | AG35: 37905 | AH35: 37905
A36: BUCARAMANGA | B36: SANTANDERES | C36: 0004-0008 | D36: 68406 | E36: 3134640 | F36: 3007067508 | G36: INCIDENTE | H36: SANTANDER | I36: LEBRIJA | J36: PTM LEBRIJA VARIEDADES LIYU | K36: REDEBAN | L36: FO-25-1970386 | M36: 46004.473 | N36: 46006.404 | O36: NO | P36: USUARIO | Q36: LECTOR DE BARRAS | R36: ERROR PAGOS PARCIALES DE FACTURAS | S36: AGREGADOR | T36: COMCARD - PTM | V36: 13/12/2025 SE ESCALA PARA VISITA. LLAMAR ANTES DE VISITAR, CONFIRMAR FALLA Y DATOS | 15/12/2025 EN COMUNICACIÓN CON LA SEÑORA YULITZA AL MOVIL 3203770878, INDICA QUE EL LECTOR DE CÓDIGO DE BARRAS ESTA OPERANDO CORRECTAMENTE, INDICA QUE NO REQUIERE DE LA VISITA TÉCNICA, SE LE INDICA QUE SE PROCEDE A CERRAR LA ORDEN QUÉ ANTE UNA NUEVA NOVEDAD DEBE SOLICITAR UNA NUEVA ORDEN. | W36: SOPORTE TELEFONICO | Y36: TIPO II | Z36: TERRESTRE | AA36: SANTOS GONZALEZ JOHAN FABIAN | AB36: 0 | AC36: 0 | AD36: 0 | AE36: 0 | AF36: 0 | AG36: 37905 | AH36: 37905
A37: IBAGUE | B37: REMOTAS | C37: 0004-0007 | D37: 73616 | E37: 3134646 | F37: 3007028327 | G37: INCIDENTE | H37: TOLIMA | I37: RIOBLANCO | J37: CENTRO HERRERA RIOBLANCO TOL | K37: REDEBAN | L37: FO-25-1970375 | M37: 46004.489 | N37: 46013.406 | O37: NO | P37: USUARIO | Q37: COMUNICACION | R37: CONEXIONES DE COMERCIO | S37: CB UNO A UNO | T37: CB UNO A UNO | V37: 13/12/2025 SE ESCALA PARA VISITA. LLAMAR ANTES DE VISITAR, CONFIRMAR FALLA Y DATOS | 22/12/2025 SE LLAMA AL SEÑOR WILINTON GONZÁLEZ, AL NÚMERO 3209271925, ME INDICA QUE EL DATAFONO ESTÁ FUNCIONANDO CORRECTAMENTE Y QUE EL PROBLEMA DE LA IMPRESORA ERA EL ROLLO QUE ESTABA MALO, LO CAMBIO Y EL DATÁFONO ESTÁ IMPRIMIENDO BIEN. | W37: SOPORTE TELEFONICO | Y37: TIPO IV | Z37: TERRESTRE | AA37: VARGAS HERRERA JHON JAIRO | AB37: 0 | AC37: 0 | AD37: 0 | AE37: 0 | AF37: 0 | AG37: 37905 | AH37: 37905
A38: VILLAVICENCIO | B38: REMOTAS | C38: 0004-0007 | D38: 95001 | E38: 3134649 | F38: 3007062794 | G38: INCIDENTE | H38: GUAVIARE | I38: SAN JOSE DEL GUAVIARE | J38: BARRIO EL PORVENIR SAN JOSE DE | K38: REDEBAN | L38: FO-25-1970167 | M38: 46004.493 | N38: 46006.634 | O38: NO | P38: USUARIO | Q38: COMUNICACION | R38: CANAL DEL COMERCIO | S38: CB UNO A UNO | T38: CB UNO A UNO | V38: 13/12/2025 SE ESCALA PARA VISITA. LLAMAR ANTES DE VISITAR, CONFIRMAR FALLA Y DATOS | 15/12/2025 SE CONTACTA A LA SEÑORA YURLEY BARRETO CRISTANCHO 3222173240 AL NUMERO SE REALIZA VALIDACION SE LE INDICA COMERCIO QUE DEBE LLAMAR A GESTION PARA RELIZAR BORRADO U OTRAS CONFUGURACIONES PARA QUE NO DESCONFIGURE O MANIPIULE CONFIGURACIONES DEL EQUIPO SEENTREGA OPERATIVO SIN NOVEDAS | W38: SOPORTE TELEFONICO | Y38: TIPO IV | Z38: TERRESTRE | AA38: ROZO JIMENEZ EDGAR ARMANDO | AB38: 0 | AC38: 0 | AD38: 0 | AE38: 0 | AF38: 0 | AG38: 37905 | AH38: 37905
A39: IBAGUE | B39: REMOTAS | C39: 0004-0007 | D39: 73585 | E39: 3134694 | F39: 3007047760 | G39: INCIDENTE | H39: TOLIMA | I39: PURIFICACION | J39: BARRIO EL TRIANGULO PURIFICACI | K39: REDEBAN | L39: FO-25-1971818 | M39: 46005.409 | N39: 46007.405 | O39: NO | P39: USUARIO | Q39: CIERRE | R39: COMERCIO NO REALIZA CIERRE | S39: CB UNO A UNO | T39: CB UNO A UNO | V39: 14/12/2025 SE ESCALA PARA VISITA. LLAMAR ANTES DE VISITAR, CONFIRMAR FALLA Y DATOS | 16/12/2025 EN COMUNICACIÓN CON EL CLIENTE EL SEÑOR CÉSAR RODRÍGUEZ,AL NÚMERO +57 311 5152036, INDICA QUE NOS PUEDE RECIBIR SOLO HASTA DESPUÉS DE LAS 2 DE LA TARDE YA QUE SE ENCUENTRA HACIENDO UNA DILIGENCIA FUERA DEL MUNICIPIO | 16/12/2025 EN COMUNICACIÓN CON EL CLIENTE VÍA TELEFÓNICA, EL SEÑOR CÉSAR RODRÍGUEZ VÍA +573115152036, SE CREA USUARIO SUPERVISOR PRUEBAS OK, CB OPERATIVO | W39: SOPORTE TELEFONICO | Y39: TIPO II | Z39: TERRESTRE | AA39: DEVIA REINOSO JUAN CARLOS | AB39: 0 | AC39: 0 | AD39: 0 | AE39: 0 | AF39: 0 | AG39: 37905 | AH39: 37905
A40: CALI | B40: SUROCCIDENTE Y EJE CAFETERO | C40: 0004-0003 | D40: 76001 | E40: 3134828 | F40: 3007075926 | G40: INCIDENTE | H40: VALLE DEL CAUCA | I40: CALI | J40: BARRIO COLSEGUROS CALI 1 | K40: REDEBAN | L40: FO-25-1970362 | M40: 46004.496 | N40: 46006.462 | O40: NO | P40: USUARIO | Q40: COMUNICACION | R40: CANAL DEL COMERCIO | S40: UNO A UNO | T40: UNO A UNO | U40: EJECUTADO / CANCELADO | V40: 13/12/2025 SE ESCALA PARA VISITA. LLAMAR ANTES DE VISITAR, CONFIRMAR FALLA Y DATOS | 14/12/2025 SE REALIZARA VISITA EL DIA LUNES YA QUE EL CLIENTE SOLO LABORA LOS SABADOS HASTA MEDIO DIA. Y NO LABORA LOS DIAS DOMINGO | 15/12/2025 SE LLEGA AL COMERCIO LA SEÑORA MARÍA PAULA INFORMA QUE EL EQUIPO YA ESTÁ BUENO NO PERMITEN INGRESO YA QUE NO HAY AUTORIZACIÓN TAMPOCO FIRMA LOS SOLAMENTE NOS COMPARTE UN RECIBO DEL DÍA DE HOY | W40: VISITA TECNICA | Y40: TIPO I | Z40: TERRESTRE | AA40: PALACIOS GOMEZ BRAHIAN ANDRES | AB40: 1 | AC40: 0 | AD40: 0 | AE40: 0 | AF40: 0 | AG40: 65960 | AH40: 65960
A41: APARTADO | B41: NOROCCIDENTE | C41: 0004-0005 | D41: 5172 | E41: 3137415 | F41: 3007038905 | G41: INCIDENTE | H41: ANTIOQUIA | I41: CHIGORODO | J41: DISTRICOL CELULARES XIMENA | K41: REDEBAN | L41: FO-25-1974545 | M41: 46006.433 | N41: 46007.515 | O41: NO | P41: USUARIO | Q41: MANTENIMIENTO | R41: MANTENIMIENTO GENERAL | S41: AGREGADOR | T41: DISTRICOL | U41: EJECUTADO | V41: 15/12/2025 SE ESCALA PARA VISITA. LLAMAR ANTES DE VISITAR, CONFIRMAR FALLA Y DATOS | 16/12/2025 SE CAPACITACIÓN AL CLIENTE EN EL USO DEL DATAFONO, COMO RETIRAR LA TIRILLA Y COMO REINICIAR DATAFONO CADA VEZ QUE SE BLOQUEE | W41: VISITA TECNICA | X41: HA007027 | Y41: TIPO II | Z41: TERRESTRE | AA41: CASTRO HENAO DANIEL ESTEBAN | AB41: 1 | AC41: 0 | AD41: 0 | AE41: 0 | AF41: 0 | AG41: 163814 | AH41: 163814
A42: IBAGUE | B42: REMOTAS | C42: 0004-0007 | D42: 17380 | E42: 3137587 | F42: 3007078708 | G42: INCIDENTE | H42: CALDAS | I42: LA DORADA | J42: PTM LA DORADA D D MULTISERVICI | K42: REDEBAN | L42: FO-25-1974851 | M42: 46006.456 | N42: 46013.737 | O42: NO | P42: USUARIO | Q42: NO ENCIENDE | R42: CONEXIONES DE COMERCIO | S42: AGREGADOR | T42: COMCARD - PTM | U42: EJECUTADO | V42: 15/12/2025 SE ESCALA PARA VISITA. LLAMAR ANTES DE VISITAR, CONFIRMAR FALLA Y DATOS | 22/12/2025 SE VISITA COMERCIO PERO INDICA QUE EL DATÁFONO YA ESTÁ EN BUEN FUNCIONAMIENTO SE VERIFICA TRANSACCIONES OK | W42: VISITA TECNICA | X42: A1RZZ258 | Y42: TIPO III | Z42: TERRESTRE | AA42: LEAL POVEDA YOHAN SEBASTIAN | AB42: 1 | AC42: 0 | AD42: 0 | AE42: 0 | AF42: 0 | AG42: 275728 | AH42: 275728
A43: APARTADO | B43: NOROCCIDENTE | C43: 0004-0005 | D43: 5045 | E43: 3139291 | F43: 3007061651 | G43: INCIDENTE | H43: ANTIOQUIA | I43: APARTADO | J43: PAGAFACIL PLAZA DEL RIO | K43: REDEBAN | L43: FO-25-1976527 | M43: 46006.61 | N43: 46007.406 | O43: NO | P43: USUARIO | Q43: CIERRE | R43: COMERCIO NO REALIZA CIERRE | S43: ROBUSTO | T43: PAGAFACIL | U43: EJECUTADO | V43: 15/12/2025 SE ESCALA PARA VISITA. LLAMAR ANTES DE VISITAR, CONFIRMAR FALLA Y DATOS | 16/12/2025 SE VERIFICA DATAFONO DESK 2600, SE LE INDICA A CLIENTE QUE DEBE REINICIAR EL DATAFONO RETIRANDO BATERÍA Y CABLE DE DATOS PARA DARLE UN REINICIO PROFUNDO, DATAFONO SE ENCUENTRA OPERATIVO. EVIDENCIAS ADJUNTAS. | W43: VISITA TECNICA | X43: FUA0K569 | Y43: TIPO I | Z43: TERRESTRE | AA43: CASTRO HENAO DANIEL ESTEBAN | AB43: 1 | AC43: 0 | AD43: 0 | AE43: 0 | AF43: 0 | AG43: 65960 | AH43: 65960
A44: CUCUTA | B44: SANTANDERES | C44: 0004-0008 | D44: 54498 | E44: 3139592 | F44: 3007043390 | G44: INCIDENTE | H44: NORTE DE SANTANDER | I44: OCAÑA | J44: PTM OCANA EL CAMPEON | K44: REDEBAN | L44: FO-25-1977118 | M44: 46006.642 | N44: 46014.486 | O44: NO | P44: USUARIO | Q44: LECTOR DE BARRAS | R44: CAPACITACION MANIPULACION DE COMERCIO | S44: AGREGADOR | T44: COMCARD - PTM | V44: 15/12/2025 SE ESCALA PARA VISITA. LLAMAR ANTES DE VISITAR, CONFIRMAR FALLA Y DATOS | 16/12/2025 SE REALIZA LLAMADA TELEFÓNICA AL NÚMERO 3132568932 SE HABLÓ CON LA SRA NATALIA, SE LE MANIFIESTA QUE POR MOTIVO DE PARO A NIVEL NACIONAL, NO SE ESTÁ VIAJANDO A LA ZONA DE OCAÑA, HASTA NUEVA ORDEN. | 23/12/2025 SE COMUNICA CON LA CLIENTE NATALIA ARIAS AL #3132568932, NOS INFORMA QUE LA FALLA DEL LECTOR DE BARRAS YA SE SOLUCIONO. CB OPERATIVO. | W44: SOPORTE TELEFONICO | Y44: TIPO IV | Z44: TERRESTRE | AA44: NARANJO AFANADOR RUBEN JESUS | AB44: 0 | AC44: 0 | AD44: 0 | AE44: 0 | AF44: 0 | AG44: 37905 | AH44: 37905
A45: SINCELEJO | B45: COSTA | C45: 0004-0001 | D45: 70708 | E45: 3140500 | F45: 3007082064 | G45: INCIDENTE | H45: SUCRE | I45: SAN MARCOS | J45: DISTRICOL DROGUERÍA FARMASUCRE | K45: REDEBAN | L45: FO-25-1978337 | M45: 46006.685 | N45: 46008.59 | O45: NO | P45: USUARIO | Q45: USUARIOS | R45: TAPA MAL ASEGURADA | S45: AGREGADOR | T45: DISTRICOL | U45: EJECUTADO | V45: 15/12/2025 SE ESCALA PARA VISITA. LLAMAR ANTES DE VISITAR, CONFIRMAR FALLA Y DATOS | 17/12/2025 SE VISITA COMERCIO POR FALLA, YA QUE NO LE ESTABA IMPRIMIENDO LOS VOUCHER, SE VERIFICA Y SE EVIDENCIA TAPA MAL ASEGURADA, SE LE EXPLICA A LA ENCARGADA DEL FUNCIONAMIENTO, SE ENCUENTRA CON LA VERSIÓN 10.3, SE REALIZAN PRUEBAS OK. | W45: VISITA TECNICA | X45: CA001882 | Y45: TIPO III | Z45: TERRESTRE | AA45: CACERES HERNANDEZ ANDRES | AB45: 1 | AC45: 0 | AD45: 0 | AE45: 0 | AF45: 0 | AG45: 275728 | AH45: 275728
A46: CALI | B46: SUROCCIDENTE Y EJE CAFETERO | C46: 0004-0003 | D46: 19001 | E46: 3141948 | F46: 3007074737 | G46: INCIDENTE | H46: CAUCA | I46: POPAYAN | J46: BARRIO SAN CAMILO POPAYAN 1 | K46: REDEBAN | L46: FO-25-1980965 | M46: 46007.374 | N46: 46007.429 | O46: NO | P46: USUARIO | Q46: MANTENIMIENTO | R46: MANTENIMIENTO GENERAL | S46: CB UNO A UNO | T46: CB UNO A UNO | V46: 16/12/2025 SE PROCEDE A CERRAR CASO POR ROBO DE DATAFONO SE INTENTA COMUNICACION CON EL USUARIO PERO NO CONTESTA | 16/12/2025 SE PROCEDE A CERRAR CASO POR ROBO DE DATAFONO SE INTENTA COMUNICACION CON EL USUARIO PERO NO CONTESTA | 16/12/2025 SE PROCEDE A CERRAR CASO POR ROBO DE DATAFONO SE INTENTA COMUNICACION CON EL USUARIO PERO NO CONTESTA | W46: SOPORTE TELEFONICO | Y46: TIPO III | Z46: TERRESTRE | AA46: HENAO CARDONA DIEGO FERNANDO | AB46: 0 | AC46: 0 | AD46: 0 | AE46: 0 | AF46: 0 | AG46: 37905 | AH46: 37905
A47: BUCARAMANGA | B47: SANTANDERES | C47: 0004-0008 | D47: 68307 | E47: 3144980 | F47: 3007040306 | G47: INCIDENTE | H47: SANTANDER | I47: GIRON | J47: BARRIO CENTRO COMERCIAL CHIMIT | K47: REDEBAN | L47: FO-25-1983310 | M47: 46007.616 | N47: 46008.423 | O47: NO | P47: USUARIO | Q47: COMUNICACION | R47: CANAL DEL COMERCIO | S47: UNO A UNO | T47: CB UNO A UNO | U47: EJECUTADO | V47: 16/12/2025 SE ESCALA PARA VISITA. LLAMAR ANTES DE VISITAR, CONFIRMAR FALLA Y DATOS | 17/12/2025 DATAFONO ARROJA CABLE DE RED DESCONECTADO, PROCEDE VALIDAR CON OTRA CONEXIÓN Y FUNCIONA CORRECTAMENTE, SE LE INDICA AL CLIENTE QUE LA FALLA EN EL OPERADOR DE INTERNET, SE HACEN PRUEBAS OK | W47: VISITA TECNICA | X47: AA0JZ985 | Y47: TIPO I | Z47: TERRESTRE | AA47: GELVEZ MOGOLLON JOSE ELISEO | AB47: 1 | AC47: 0 | AD47: 0 | AE47: 0 | AF47: 0 | AG47: 65960 | AH47: 65960
A48: BOGOTA | B48: CUNDINAMARCA | C48: 0004-0004 | D48: 11001 | E48: 3145077 | F48: 3007058748 | G48: INCIDENTE | H48: CUNDINAMARCA | I48: BOGOTA | J48: REVAL CADE LUCEROS | K48: REDEBAN | L48: FO-25-1983404 | M48: 46007.623 | N48: 46008.47 | O48: NO | P48: USUARIO | Q48: COMUNICACION | R48: CONEXIONES DE COMERCIO | S48: ROBUSTO | T48: REVAL | U48: EJECUTADO | V48: 16/12/2025 SE ESCALA PARA VISITA. LLAMAR ANTES DE VISITAR, CONFIRMAR FALLA Y DATOS | 17/12/2025 SE REALIZA VISITA A COMERCIO, SE VALIDA CONEXIONES POR PARTE DEL COMERCIO, Y NO TENIA ACCESO A INTERNET, SE PROCEDE A REALIZAR CONEXIONES, DE REALIZAN PRUEBAS EXITOSAS SIN NOVEDAD. | W48: VISITA TECNICA | X48: JA001232 | Y48: TIPO I | Z48: TERRESTRE | AA48: ARIAS QUILINDO JULIAN | AB48: 1 | AC48: 0 | AD48: 0 | AE48: 0 | AF48: 0 | AG48: 65960 | AH48: 65960
A49: MEDELLIN | B49: NOROCCIDENTE | C49: 0004-0005 | D49: 5212 | E49: 3146554 | F49: 3007030570 | G49: INCIDENTE | H49: ANTIOQUIA | I49: COPACABANA | J49: ARRIO VILLA NUEVA COPACABANA | K49: REDEBAN | L49: FO-25-1985774 | M49: 46008.333 | N49: 46008.676 | O49: NO | P49: USUARIO | Q49: COMUNICACION | R49: CONEXIONES DE COMERCIO | S49: CB UNO A UNO | T49: CB UNO A UNO | U49: EJECUTADO | V49: 17/12/2025 SE ESCALA PARA VISITA. LLAMAR ANTES DE VISITAR, CONFIRMAR FALLA Y DATOS | 17/12/2025 SE VERIFICAN CONEXIONES DEL COMERCIO Y SE IDENTIFICA EL CABLE DE RED MAL CONECTADO, SE DEJAN SERVICIOS FUNCIONANDO CORRECTAMENTE | W49: VISITA TECNICA | X49: BL01Y284 | Y49: TIPO I | Z49: TERRESTRE | AA49: BARRIENTOS HERNANDEZ CRISTIAN HORACIO | AB49: 1 | AC49: 0 | AD49: 0 | AE49: 0 | AF49: 0 | AG49: 65960 | AH49: 65960
A50: CALI | B50: SUROCCIDENTE Y EJE CAFETERO | C50: 0004-0003 | D50: 76248 | E50: 3146575 | F50: 3007016798 | G50: INCIDENTE | H50: VALLE DEL CAUCA | I50: EL CERRITO | J50: BARRIO LA ESTRELLA EL CERRITO | K50: REDEBAN | L50: FO-25-1985902 | M50: 46008.333 | N50: 46008.531 | O50: NO | P50: USUARIO | Q50: USUARIOS | R50: CREACION DE USUARIOS | S50: CB UNO A UNO | T50: CB UNO A UNO | U50: EJECUTADO | V50: 17/12/2025 SE ESCALA PARA VISITA. LLAMAR ANTES DE VISITAR, CONFIRMAR FALLA Y DATOS | 17/12/2025 SE REALIZA VISITA TÉCNICA AL COMERCIO PARA REALIZAR CAMBIO DE CLAVE DE USUARIO YA QUE AL CLIENTE SE EL OLVIDO EL USUARIO PARA ENTRAR | W50: VISITA TECNICA | X50: JFZZZ742 | Y50: TIPO II | Z50: TERRESTRE | AA50: ESCOBAR LENIS JUAN SEBASTIAN | AB50: 1 | AC50: 0 | AD50: 0 | AE50: 0 | AF50: 0 | AG50: 163814 | AH50: 163814
A51: PEREIRA | B51: SUROCCIDENTE Y EJE CAFETERO | C51: 0004-0002 | D51: 63001 | E51: 3150587 | F51: 3007018910 | G51: INCIDENTE | H51: QUINDIO | I51: ARMENIA | J51: MULTIPAGAS ARMENIA | K51: REDEBAN | L51: FO-25-1992298 | M51: 46008.656 | N51: 46009.422 | O51: NO | P51: USUARIO | Q51: MANTENIMIENTO | R51: MANTENIMIENTO GENERAL | S51: ROBUSTO | T51: MULTIPAGAS | U51: EJECUTADO | V51: 17/12/2025 SE ESCALA PARA VISITA. LLAMAR ANTES DE VISITAR, CONFIRMAR FALLA Y DATOS | 18/12/2025 SE VISITA COMERCIO SE REALIZÓ VERIFICACIÓN DE CONEXIONES, VERIFICACIÓN DE EQUIPOS, SE REALIZÓ PRUEBAS OK. | W51: VISITA TECNICA | X51: GZ0OZ597 | Y51: TIPO II | Z51: TERRESTRE | AA51: SANCHEZ SOLORZANO JUAN SEBASTIAN | AB51: 1 | AC51: 0 | AD51: 0 | AE51: 0 | AF51: 0 | AG51: 163814 | AH51: 163814
A52: APARTADO | B52: NOROCCIDENTE | C52: 0004-0005 | D52: 5480 | E52: 3150901 | F52: 3007030310 | G52: INCIDENTE | H52: ANTIOQUIA | I52: MUTATA | J52: BARRIO CALLE PRINCIPAL MUTATA | K52: REDEBAN | L52: FO-25-1992223 | M52: 46008.655 | N52: 46010.527 | O52: NO | P52: USUARIO | Q52: MANTENIMIENTO | R52: MANTENIMIENTO GENERAL | S52: CB UNO A UNO | T52: CB UNO A UNO | U52: EJECUTADO | V52: 17/12/2025 SE ESCALA PARA VISITA. LLAMAR ANTES DE VISITAR, CONFIRMAR FALLA Y DATOS | 19/12/2025 SE REALIZA REPISADO DE PARÁMETROS Y QUEDA OK | W52: VISITA TECNICA | X52: BRZZZ288 | Y52: TIPO II | Z52: TERRESTRE | AA52: CASTRO HENAO DANIEL ESTEBAN | AB52: 1 | AC52: 0 | AD52: 0 | AE52: 0 | AF52: 0 | AG52: 163814 | AH52: 163814
A53: MEDELLIN | B53: NOROCCIDENTE | C53: 0004-0005 | D53: 5604 | E53: 3153174 | F53: 3007080457 | G53: INCIDENTE | H53: ANTIOQUIA | I53: REMEDIOS | J53: BARRIO REMEDIOS REMEDIOS 1 | K53: REDEBAN | L53: FO-25-1996041 | M53: 46009.403 | N53: 46009.753 | O53: NO | P53: USUARIO | Q53: COMUNICACION | R53: CANAL DEL COMERCIO | S53: UNO A UNO | T53: UNO A UNO | U53: EJECUTADO | V53: 18/12/2025 SE ESCALA PARA VISITA. LLAMAR ANTES DE VISITAR, CONFIRMAR FALLA Y DATOS | 18/12/2025 SE VERIFICAN SERVICIOS Y CONEXIONES, SERVICIOS ESTÁN OK POSIBLE CAÍDA DEL CANAL DEL COMERCIO | W53: VISITA TECNICA | X53: SAZZZ791 | Y53: TIPO IV | Z53: TERRESTRE | AA53: BARRIENTOS HERNANDEZ CRISTIAN HORACIO | AB53: 1 | AC53: 0 | AD53: 0 | AE53: 0 | AF53: 0 | AG53: 479590 | AH53: 479590
A54: VILLAVICENCIO | B54: REMOTAS | C54: 0004-0007 | D54: 50313 | E54: 3155311 | F54: 3007076270 | G54: INCIDENTE | H54: META | I54: GRANADA | J54: BARRIO BELEN GRANDA | K54: REDEBAN | L54: FO-25-1997120 | M54: 46009.585 | N54: 46009.679 | O54: NO | P54: USUARIO | Q54: NO ENCIENDE | R54: CONEXIONES DE COMERCIO | S54: CB UNO A UNO | T54: CB UNO A UNO | U54: EJECUTADO | V54: 18/12/2025 SE ESCALA PARA VISITA. LLAMAR ANTES DE VISITAR, CONFIRMAR FALLA Y DATOS | 18/12/2025 SE AJUSTA CONEXIÓN DE CABLE DE PODER YA QUE DEBAJO DE LA VITRINA SE ENCONTRÓ DESCONECTADO SE LE INFORMA A LA PERSONA QUE ATIENDE AJUSTANDO LAS CONEXIONES Y ENTREGANDO OPERATIVO SIN NOVEDAD JANEY TRIANA | W54: VISITA TECNICA | X54: EG0OZ132 | Y54: TIPO II | Z54: TERRESTRE | AA54: ROZO JIMENEZ EDGAR ARMANDO | AB54: 1 | AC54: 0 | AD54: 0 | AE54: 0 | AF54: 0 | AG54: 163814 | AH54: 163814
A55: PEREIRA | B55: SUROCCIDENTE Y EJE CAFETERO | C55: 0004-0002 | D55: 76828 | E55: 3156309 | F55: 3007011694 | G55: INCIDENTE | H55: VALLE DEL CAUCA | I55: TRUJILLO | J55: TRUJILLO VALLE DEL CAUCA | K55: REDEBAN | L55: FO-25-1998373 | M55: 46009.671 | N55: 46010.556 | O55: NO | P55: USUARIO | Q55: MANTENIMIENTO | R55: MANTENIMIENTO GENERAL | S55: CB UNO A UNO | T55: CB UNO A UNO | U55: EJECUTADO | V55: 18/12/2025 SE ESCALA PARA VISITA. LLAMAR ANTES DE VISITAR, CONFIRMAR FALLA Y DATOS | 19/12/2025 VISITAMOS COMERCIO LA TAPA DE LA IMPRESORA ESTABA MAL PUESTA LA AJUSTAMOS BIEN REALIZAMOS PRUEBAS OK DATÁFONO QUEDA FUNCIONANDO. | W55: VISITA TECNICA | X55: JAAAD113 | Y55: TIPO II | Z55: TERRESTRE | AA55: ARROYAVE CANO MANUEL GUILLERMO | AB55: 1 | AC55: 0 | AD55: 0 | AE55: 0 | AF55: 0 | AG55: 163814 | AH55: 163814
A56: MEDELLIN | B56: NOROCCIDENTE | C56: 0004-0005 | D56: 5001 | E56: 3156454 | F56: 3007023659 | G56: INCIDENTE | H56: ANTIOQUIA | I56: MEDELLIN | J56: COMCARD MEDELLIN SALVADOR BELL | K56: REDEBAN | L56: FO-25-1998588 | M56: 46009.702 | N56: 46010.672 | O56: NO | P56: USUARIO | Q56: COMUNICACION | R56: CANAL DEL COMERCIO | S56: AGREGADOR | T56: COMCARD - PTM | U56: EJECUTADO | V56: 18/12/2025 SE ESCALA PARA VISITA. LLAMAR ANTES DE VISITAR, CONFIRMAR FALLA Y DATOS | 19/12/2025 SE VISITA Y SE ENCUENTRA OPERANDO NORMAL EL CANAL DEL COMERCIO ESTABA CAÍDO PRUEBAS OK | W56: VISITA TECNICA | X56: ABC0D992 NA001792 | Y56: TIPO I | Z56: TERRESTRE | AA56: MARIN PIEDRAHITA JIMMY ALEXIS | AB56: 1 | AC56: 0 | AD56: 0 | AE56: 0 | AF56: 0 | AG56: 65960 | AH56: 65960
A57: APARTADO | B57: NOROCCIDENTE | C57: 0004-0005 | D57: 27615 | E57: 3156570 | F57: 3007063236 | G57: INCIDENTE | H57: CHOCO | I57: RIOSUCIO | J57: DISTRICOL TECNOCHUY 2 | K57: REDEBAN | L57: FO-25-1999797 | M57: 46010.333 | N57: 46010.691 | O57: NO | P57: USUARIO | Q57: MANTENIMIENTO | R57: MANTENIMIENTO GENERAL | S57: AGREGADOR | T57: DISTRICOL | U57: EJECUTADO | V57: 19/12/2025 SE ESCALA PARA VISITA. LLAMAR ANTES DE VISITAR, CONFIRMAR FALLA Y DATOS | 19/12/2025 SE VERIFICA IMPRESORA Y SE ENCUENTRA BUENA, SE IMPRIME VARIOS VOUCHER SE EVIDENCIA TODO OK | W57: VISITA TECNICA | X57: FUA00713 | Y57: TIPO V | Z57: TERRESTRE/FLUVIAL | AA57: CASTRO HENAO DANIEL ESTEBAN | AB57: 1 | AC57: 0 | AD57: 0 | AE57: 0 | AF57: 0 | AG57: 479590 | AH57: 479590
A58: NEIVA | B58: REMOTAS | C58: 0004-0007 | D58: 41551 | E58: 3157851 | F58: 3007079826 | G58: INCIDENTE | H58: HUILA | I58: PITALITO | J58: BARRIO CALAMO PITALITO 3 | K58: REDEBAN | L58: FO-25-2000550 | M58: 46010.382 | N58: 46010.465 | O58: NO | P58: USUARIO | Q58: NO ENCIENDE | R58: CONEXIONES DE COMERCIO | S58: UNO A UNO | T58: UNO A UNO | U58: EJECUTADO | V58: 19/12/2025 SE ESCALA PARA VISITA. LLAMAR ANTES DE VISITAR, CONFIRMAR FALLA Y DATOS | 19/12/2025 SE REALIZA VISITA AL PUNTO, SE EVIDENCIA EQUIPO NO SE ENCUENTRA CONECTADO AL LA CORRIENTE CONTINUAMENTE POR ESE MOTIVO LA BATERÍA INTERNA DEL EQUIPO DSK2600 NO CARGA AL 100% ,ESTO HACE QUE AL MOMENTO QUE EL EQUIPO VA GENERAR VAUCHER SE QUEDA CORTA DE ENERGÍA . PRUEBAS OK, CB OPERATIVO. SE LE INDICA AL CLIENTE QUE DEBE VALIDAR SIEMPRE QUE LA BATERÍA ESTE CARGADA AL 100 % PARA QUE EL DATAFONO FUNCIONE DE FORMA ÓPTIMA . | W58: VISITA TECNICA | X58: F1XZZ058 | Y58: TIPO III | Z58: TERRESTRE | AA58: DEVIA REINOSO JUAN CARLOS | AB58: 1 | AC58: 0 | AD58: 0 | AE58: 0 | AF58: 0 | AG58: 275728 | AH58: 275728
A59: NEIVA | B59: REMOTAS | C59: 0004-0007 | D59: 18001 | E59: 3158278 | F59: 3007037490 | G59: INCIDENTE | H59: CAQUETA | I59: FLORENCIA | J59: BARRIO CENTRO FLORENCIA 1 | K59: REDEBAN | L59: FO-25-2001022 | M59: 46010.413 | N59: 46014.396 | O59: NO | P59: USUARIO | Q59: NO ENCIENDE | R59: CONEXIONES DE COMERCIO | S59: UNO A UNO | T59: CB UNO A UNO | V59: 19/12/2025 SE ESCALA PARA VISITA. LLAMAR ANTES DE VISITAR, CONFIRMAR FALLA Y DATOS | 23/12/2025 EN COMUNICACIÓN VÍA TELEFÓNICA CON EL SEÑOR DIEGO CARVAJAL AL NÚMERO 3208358585, INDICA QUE EL EQUIPO SE ENCUENTRA FUNCIONANDO DE MANERA NORMAL , QUE EL PROBLEMA QUE NO ENCENDÍA SE DEBIÓ A UNA MALA CONEXIÓN ,PERO QUE YA ESTÁ OPERANDO CON NORMALIDAD PIDE Y POR FAVOR SE CANCELA LA VISITA | W59: SOPORTE TELEFONICO | Y59: TIPO IV | Z59: TERRESTRE | AA59: DEVIA REINOSO JUAN CARLOS | AB59: 0 | AC59: 0 | AD59: 0 | AE59: 0 | AF59: 0 | AG59: 37905 | AH59: 37905
A60: TUNJA | B60: SANTANDERES | C60: 0004-0008 | D60: 15047 | E60: 3158628 | F60: 3007039481 | G60: INCIDENTE | H60: BOYACA | I60: AQUITANIA | J60: BARRIO PLAYA BLANCA AQUITANIA | K60: REDEBAN | L60: FO-25-2040746 | M60: 46010.512 | N60: 46018.622 | O60: NO | P60: USUARIO | Q60: COMUNICACION | R60: CANAL DEL COMERCIO | S60: UNO A UNO | T60: CB UNO A UNO | U60: EJECUTADO | V60: 27/12/2025 CENTRO DE GESTION REALIZÓ EL CARGUE DE LA ORDEN CON FECHA VENCIDA , ES UNA TA QUE TUVIERON TA QUE CREAR NUEVA ( TA-25-3158628)- YA QUE HABIAN CREADO UNA TA QUE BAJO COMO OC BASE DATAGONO Y MA ORDEN TENIA QUE SER COMO INCIDENTE .SE VISITARA PUNTO CONFIRMADA VISITA CON EL SEÑOR YESID SANTOS . | 27/12/2025 SE REALIZA BORRADO DE EQUIPO CARGANDO VERSIÓN 9_90 , SE REALIZA VALIDACIONES DE CONEXIÓN EXITOSAMENTE , SE REALIZA CAMBIO DEL LECTOR DE BARRRAS POR DAÑO CABLE MAL ESTADO , SE CABIA CABLE TEF ENTORCHADO POR MANTENIMIENTO PREVENTIVO DEJANDO PRUEBAS OK ,SIN TELECARGA NO AUTORIZADA | W60: VISITA TECNICA | X60: GZ08Z101 | Y60: TIPO III | Z60: TERRESTRE | AA60: ALVARADO MORENO CRISTHIAN | AB60: 1 | AC60: 0 | AD60: 0 | AE60: 0 | AF60: 0 | AG60: 275728 | AH60: 275728
A61: IBAGUE | B61: REMOTAS | C61: 0004-0007 | D61: 73067 | E61: 3159596 | F61: 3007057307 | G61: INCIDENTE | H61: TOLIMA | I61: ATACO | J61: BARRIO CORREGIMIENTO SANTIAGO | K61: REDEBAN | L61: FO-25-2006868 | M61: 46010.572 | N61: 46013.399 | O61: NO | P61: USUARIO | Q61: COMUNICACION | R61: CONEXIONES DE COMERCIO | S61: UNO A UNO | T61: CB UNO A UNO | V61: 19/12/2025 SE ESCALA PARA VISITA. LLAMAR ANTES DE VISITAR, CONFIRMAR FALLA Y DATOS | 22/12/2025 LLAMO A LA SEÑORA ARCILA MORENO, AL NÚMERO 3118056638 PARA EL MANTENIMIENTO DE CONEXIÓN A INTERNET Y ELLA ME INDICA QUE EL DATÁFONO ESTÁ FUNCIONANDO CORRECTAMENTE. QUE REINICIO EL MÓDEM Y QUE SE SOLUCIONO EL PROBLEMA DE INTERNET. | W61: SOPORTE TELEFONICO | Y61: TIPO III | Z61: TERRESTRE | AA61: VARGAS HERRERA JHON JAIRO | AB61: 0 | AC61: 0 | AD61: 0 | AE61: 0 | AF61: 0 | AG61: 37905 | AH61: 37905
A62: TUNJA | B62: SANTANDERES | C62: 0004-0008 | D62: 15248 | E62: 3159658 | F62: 3007011094 | G62: INCIDENTE | H62: BOYACA | I62: EL ESPINO | J62: EL ESPINO - BOYACA | K62: REDEBAN | L62: FO-25-2006308 | M62: 46010.56 | N62: 46020.733 | O62: NO | P62: USUARIO | Q62: COMUNICACION | R62: CANAL DEL COMERCIO | S62: CB UNO A UNO | T62: CB UNO A UNO | U62: CANCELADO | V62: 19/12/2025 SE ESCALA PARA VISITA. LLAMAR ANTES DE VISITAR, CONFIRMAR FALLA Y DATOS | 22/12/2025 SE REALIZA INTENTO DE COMUNICACION CON EL CLIENTE PARA VALIDAR LA FALLA YA QUE EN OCACIONES ANTERIORES LA FALLA QUE PRESENTA EL CLIENTE ES A CAUSA DE EL INTERNET DEL COMERCIO, POR LO CUAL NO SE PUEDE REALIZAR NINGUNA CORRECCION A LOS EQUIPOS, SE INTETARA COMUNICACION EN HORAS DE AM PARA VALIDAR LA FALLA Y CONFIRMAR LA VISITA YA QUE POR LEJANIA, ZONA EN ALERTA POR GRUPOS ARMADOS ILEGALES Y TRANSPORTE AL LUGAR ES COMPLICADO VISITAR. | 23/12/2025 SE REALIZA INTENTO DE COMUNICACION CON EL CLIENTE PARA VALIDAR LA FALLA YA QUE EN OCACIONES ANTERIORES LA FALLA QUE PRESENTA EL CLIENTE ES A CAUSA DE EL INTERNET DEL COMERCIO, POR LO CUAL NO SE PUEDE REALIZAR NINGUNA CORRECCION A LOS EQUIPOS, SE INTETARA COMUNICACION EN HORAS DE AM PARA VALIDAR LA FALLA Y CONFIRMAR LA VISITA YA QUE POR LEJANIA, ZONA EN ALERTA POR GRUPOS ARMADOS ILEGALES Y TRANSPORTE AL LUGAR ES COMPLICADO VISITAR. | 29/12/2025 DESPLAZAMIENTO HACIA SITIO CLIENTE CONFIRMA FUNCIONAMIENTO DE EQUIPO, FALLA QUE PRESENTA ES EN INTERNET SUMINISTRADO POR ENTIDAD PERO EQUIPO NO TIENE FALLA Y YA SE ENCUENTRA OPERANDO NORMALMENTE | W62: VISITA TECNICA | Y62: TIPO IV | Z62: TERRESTRE | AA62: GONZALEZ GONZALEZ MARIO ALBERTO | AB62: 1 | AC62: 0 | AD62: 0 | AE62: 0 | AF62: 0 | AG62: 479590 | AH62: 479590
A63: VILLAVICENCIO | B63: REMOTAS | C63: 0004-0007 | D63: 50006 | E63: 3160158 | F63: 3007080573 | G63: INCIDENTE | H63: META | I63: ACACIAS | J63: BARRIO CENTRO ACACIAS 16 | K63: REDEBAN | L63: FO-25-2007316 | M63: 46010.616 | N63: 46011.467 | O63: NO | P63: USUARIO | Q63: MANTENIMIENTO | R63: MANTENIMIENTO GENERAL | S63: UNO A UNO | T63: UNO A UNO | U63: EJECUTADO / CANCELADO | V63: 19/12/2025 SE ESCALA PARA VISITA. LLAMAR ANTES DE VISITAR, CONFIRMAR FALLA Y DATOS | 20/12/2025 SE REALIZA VISTA AL CB, POR SOLICITUD DE PANTALLA BLOQUEADA SE LLEGA AL LUGAR PERO SE OBSERVA QUE SE ENCUENTRA CERRADO, SE LLAMA AL USUARIO FELIPE DÍAZ 3219620617 PERO NO CONTESTA NO ES POSIBLE REALIZAR LA VISITA | W63: VISITA TECNICA | X63: 0 | Y63: TIPO II | Z63: TERRESTRE | AA63: MOLINA CASTRO JAVIER ALBERTO | AB63: 1 | AC63: 0 | AD63: 0 | AE63: 0 | AF63: 0 | AG63: 163814 | AH63: 163814
A64: MEDELLIN | B64: NOROCCIDENTE | C64: 0004-0005 | D64: 5034 | E64: 3162097 | F64: 3007058974 | G64: INCIDENTE | H64: ANTIOQUIA | I64: ANDES | J64: BARRIO CENTRO ANDES 1 | K64: REDEBAN | L64: FO-25-2011592 | M64: 46011.695 | N64: 46013.406 | O64: NO | P64: USUARIO | Q64: LECTOR DE TARJETAS | R64: OBSTRUCCION DEL LECTOR | S64: CB UNO A UNO | T64: CB UNO A UNO | U64: EJECUTADO | V64: 21/12/2025 SE ESCALA PARA VISITA. LLAMAR ANTES DE VISITAR, CONFIRMAR FALLA Y DATOS | 22/12/2025 SE REALIZÓ LIMPIEZA DE LECTOR CHIP, PRUEBAS OK CB OPERATIVO | W64: VISITA TECNICA | X64: LA002189 | Y64: TIPO III | Z64: TERRESTRE | AA64: CASTAÑEDA PALACIO CARLOS FELIPE | AB64: 1 | AC64: 0 | AD64: 0 | AE64: 0 | AF64: 0 | AG64: 275728 | AH64: 275728
A65: PEREIRA | B65: SUROCCIDENTE Y EJE CAFETERO | C65: 0004-0002 | D65: 17877 | E65: 3163255 | F65: 3007074680 | G65: INCIDENTE | H65: CALDAS | I65: VITERBO | J65: PTM VITERBO PUNTO SERVIS VITER | K65: REDEBAN | L65: FO-25-2013504 | M65: 46013.355 | N65: 46013.384 | O65: NO | P65: USUARIO | Q65: COMUNICACION | R65: CANAL DEL COMERCIO | S65: AGREGADOR | T65: COMCARD - PTM | V65: 22/12/2025 SE ESCALA PARA VISITA. LLAMAR ANTES DE VISITAR, CONFIRMAR FALLA Y DATOS | 22/12/2025 EN COMUNICACIÓN CON LA SR DORIS INDICA QUE EL EQUIPO YA ESTA FUNCIONANDO CORRECTAMENTE, SE PROCEDE CON EL CIERRA DE LA ACTIVIDAD | W65: SOPORTE TELEFONICO | Y65: TIPO II | Z65: TERRESTRE | AA65: HENAO CARDONA DIEGO FERNANDO | AB65: 0 | AC65: 0 | AD65: 0 | AE65: 0 | AF65: 0 | AG65: 37905 | AH65: 37905
A66: CALI | B66: SUROCCIDENTE Y EJE CAFETERO | C66: 0004-0003 | D66: 76001 | E66: 3166264 | F66: 3007078638 | G66: INCIDENTE | H66: VALLE DEL CAUCA | I66: CALI | J66: DISTRICOL VMJ BOCHALEMA | K66: REDEBAN | L66: FO-25-2015902 | M66: 46013.554 | N66: 46014.479 | O66: NO | P66: USUARIO | Q66: USUARIOS | R66: MALA MANIPULACION POS | S66: AGREGADOR | T66: DISTRICOL | V66: 22/12/2025 SE ESCALA PARA VISITA. LLAMAR ANTES DE VISITAR, CONFIRMAR FALLA Y DATOS | 23/12/2025 SE LLAMA AL CLIENTE AL NÚMERO 3225887906 HABLO CON LA SEÑORA PATRICIA INFORMA EL DÍA DE AYER NO LE FUNCIONÓ LA CLAVE 1526 PARA IMPRIMIR DUPLICADOS, SE REALIZA SOPORTE TELEFÓNICO SOLICITÁNDOLE EL PROBLEMA Y EL CLIENTE INDICA QUE YA NO REQUIERE VISITA TÉCNICA | W66: SOPORTE TELEFONICO | Y66: TIPO I | Z66: TERRESTRE | AA66: HERRERA MONAR GEOVANNY | AB66: 0 | AC66: 0 | AD66: 0 | AE66: 0 | AF66: 0 | AG66: 37905 | AH66: 37905
A67: MEDELLIN | B67: NOROCCIDENTE | C67: 0004-0005 | D67: 5001 | E67: 3171472 | F67: 3007082268 | G67: INCIDENTE | H67: ANTIOQUIA | I67: MEDELLIN | J67: DISTRICOL LLAVE MAGICA DISTRIB | K67: REDEBAN | L67: FO-25-2023553 | M67: 46014.552 | N67: 46014.622 | O67: NO | P67: USUARIO | Q67: LECTOR DE BARRAS | R67: CAPACITACION MANIPULACION DE COMERCIO | U67: EJECUTADO | V67: 23/12/2025 SE ESCALA PARA VISITA. LLAMAR ANTES DE VISITAR, CONFIRMAR FALLA Y DATOS | 23/12/2025 SE LE EXPLICA AL USUARIO EL CORRECTO FUNCIONAMIENTO DE LA LECTORA Y LA POSICIÓN CORRECTA DEL LECTOR PRUEBAS EXITOSAS SERVICIO OPERATIVO | W67: VISITA TECNICA | X67: 0B002009 | Y67: TIPO I | Z67: TERRESTRE | AA67: RIOS CASTRILLON JUAN SEBASTIAN | AB67: 1 | AC67: 0 | AD67: 0 | AE67: 0 | AF67: 0 | AG67: 65960 | AH67: 65960
A68: PEREIRA | B68: SUROCCIDENTE Y EJE CAFETERO | C68: 0004-0002 | D68: 63001 | E68: 3172074 | F68: 3007033988 | G68: INCIDENTE | H68: QUINDIO | I68: ARMENIA | J68: PAGAFACIL LA 14 ARMENIA | K68: REDEBAN | L68: FO-25-2024290 | M68: 46014.616 | N68: 46015.499 | O68: NO | P68: USUARIO | Q68: MANTENIMIENTO | R68: MANTENIMIENTO GENERAL | S68: ROBUSTO | T68: PAGAFACIL | U68: EJECUTADO | V68: 23/12/2025 SE ESCALA PARA VISITA. LLAMAR ANTES DE VISITAR, CONFIRMAR FALLA Y DATOS | 24/12/2025 SE VISITA COMERCIO SE REALIZÓ VERIFICACIÓN DE CABLEADO Y DE EQUIPOS SE REALIZÓ PRUEBAS OK. | W68: VISITA TECNICA | X68: 1KZZZ682 | Y68: TIPO II | Z68: TERRESTRE | AA68: SANCHEZ SOLORZANO JUAN SEBASTIAN | AB68: 1 | AC68: 0 | AD68: 0 | AE68: 0 | AF68: 0 | AG68: 163814 | AH68: 163814
A69: PEREIRA | B69: SUROCCIDENTE Y EJE CAFETERO | C69: 0004-0002 | D69: 76403 | E69: 3172107 | F69: 3007031089 | G69: INCIDENTE | H69: VALLE DEL CAUCA | I69: LA VICTORIA | J69: BARRIO CENTRO 5 | K69: REDEBAN | L69: FO-25-2024201 | M69: 46014.614 | N69: 46014.698 | O69: NO | P69: USUARIO | Q69: COMUNICACION | R69: CANAL DEL COMERCIO | S69: CB UNO A UNO | T69: CB UNO A UNO | V69: 23/12/2025 SE ESCALA PARA VISITA. LLAMAR ANTES DE VISITAR, CONFIRMAR FALLA Y DATOS | 23/12/2025 SE HABLA CON EL CLIENTE, EL SEÑOR ANDRES MANIFIESTA QUE EL DATAFONO LE ARROJA UN ERROR DE CONEXIÓN PERO TIENE EL ICONO DE LA RED EN VERDE, SE LE SOLITA REINICIAR EL ROUTER DE INTERNET DESDE EL RACK, EL CLIENTE REALIZA EL REINICIO DE SUS EQUIPOS Y REALIZA UNA PRUEBA EXITOSA | W69: SOPORTE TELEFONICO | Y69: TIPO II | Z69: TERRESTRE | AA69: HENAO CARDONA DIEGO FERNANDO | AB69: 0 | AC69: 0 | AD69: 0 | AE69: 0 | AF69: 0 | AG69: 37905 | AH69: 37905
A70: PEREIRA | B70: SUROCCIDENTE Y EJE CAFETERO | C70: 0004-0002 | D70: 66170 | E70: 3172424 | F70: 3007079238 | G70: INCIDENTE | H70: RISARALDA | I70: DOSQUEBRADAS | J70: DISTRICOL VARIEDADES MIFER | K70: REDEBAN | L70: FO-25-2024937 | M70: 46014.644 | N70: 46015.415 | O70: NO | P70: USUARIO | Q70: MANTENIMIENTO | R70: MANTENIMIENTO GENERAL | S70: AGREGADOR | T70: DISTRICOL | U70: EJECUTADO | V70: 23/12/2025 SE ESCALA PARA VISITA. LLAMAR ANTES DE VISITAR, CONFIRMAR FALLA Y DATOS | 24/12/2025 VISITAMOS COMERCIO EL DATÁFONO NO IMPRIME LAS TRX DESCONECTAMOS Y CONECTAMOS LA BATERÍA DEL DATAFONO REALIZAMOS MOVIMIENTO A LA IMPRESORA TÉRMICA REALIZAMOS PRUEBAS OK LE EXPLICAMOS AL CLIENTE QUE DEBE HACER CUANDO EL DATAFONO PRESENTE EL MISMO INCONVENIENTE. | W70: VISITA TECNICA | X70: A4WZZ115 | Y70: TIPO I | Z70: TERRESTRE | AA70: ARROYAVE CANO MANUEL GUILLERMO | AB70: 1 | AC70: 0 | AD70: 0 | AE70: 0 | AF70: 0 | AG70: 65960 | AH70: 65960
A71: MEDELLIN | B71: NOROCCIDENTE | C71: 0004-0005 | D71: 27361 | E71: 3173413 | F71: 3007067920 | G71: INCIDENTE | H71: CHOCO | I71: ISTMINA | J71: BARRIO INDEPENDENCIA ISTMINA | K71: REDEBAN | L71: FO-25-2025560 | M71: 46014.748 | N71: 46017.379 | O71: NO | P71: USUARIO | Q71: COMUNICACION | R71: CONEXIONES DE COMERCIO | S71: CB UNO A UNO | T71: CB UNO A UNO | V71: 23/12/2025 SE ESCALA PARA VISITA. LLAMAR ANTES DE VISITAR, CONFIRMAR FALLA Y DATOS | 26/12/2025 SE REALIZA CONTACTO TELEFÓNICO CON LA CLIENTE Y REPORTA QUE EL CB YA SE ENCUENTRA OPERATIVO YA QUE LA ZONA ESTABA PRESENTANDO PROBLEMAS DE COMUNICACIÓN PERO YA ESTA FUNCIONANDO CON NORMALIDAD | W71: SOPORTE TELEFONICO | Y71: TIPO V | Z71: AEREO | AA71: ROBLEDO DIAZ ANDRES FELIPE | AB71: 0 | AC71: 0 | AD71: 0 | AE71: 0 | AF71: 0 | AG71: 37905 | AH71: 37905
A72: MONTERIA | B72: COSTA | C72: 0004-0001 | D72: 23660 | E72: 3173658 | F72: 3007037366 | G72: INCIDENTE | H72: CORDOBA | I72: SAHAGUN | J72: ARRIO CENTRO SAHAGUN 1 | K72: REDEBAN | L72: FO-25-2026234 | M72: 46015.348 | N72: 46017.517 | O72: NO | P72: USUARIO | Q72: LECTOR DE TARJETAS | R72: OBSTRUCCION DEL LECTOR | S72: CB UNO A UNO | T72: CB UNO A UNO | U72: EJECUTADO | V72: 24/12/2025 SE ESCALA PARA VISITA. LLAMAR ANTES DE VISITAR, CONFIRMAR FALLA Y DATOS | 24/12/2025 SE REQUIERE CAMBIO DE EQUIPO Y NO HAY SOPORTE REDEBAN, SE REAGENDA PARA EL 26 DE DICIEMBRE. | 26/12/2025 SE VISITA SITIO SE VERIFICA INFORMACIÓN SE REALIZA PRIMEROS, SE REALIZA LIMPIEZA DEL LECTOR SE RETIRA LA OBSTRUCCIÓN , SE REALIZA PRUEBA TRX EXITOSA, TECLADO OK, IMPRESIÓN OK, SELLOS OK. | W72: VISITA TECNICA | X72: AB00N078 | Y72: TIPO II | Z72: TERRESTRE | AA72: SANTOS GUZMAN CHRISTIAN FELIPE | AB72: 1 | AC72: 0 | AD72: 0 | AE72: 0 | AF72: 0 | AG72: 163814 | AH72: 163814
A73: MEDELLIN | B73: NOROCCIDENTE | C73: 0004-0005 | D73: 5001 | E73: 3177110 | F73: 3007041259 | G73: INCIDENTE | H73: ANTIOQUIA | I73: MEDELLIN | J73: PTM MEDELLIN MONTESSORI | K73: REDEBAN | L73: FO-25-2029481 | M73: 46017.359 | N73: 46017.513 | O73: NO | P73: USUARIO | Q73: COMUNICACION | R73: CONEXIONES DE COMERCIO | S73: AGREGADOR | T73: COMCARD - PTM | U73: EJECUTADO | V73: 26/12/2025 SE ESCALA PARA VISITA. LLAMAR ANTES DE VISITAR, CONFIRMAR FALLA Y DATOS | 26/12/2025 SE REORGANIZA ACOMETIDA DE CABLE DE DATOS, SE ANULA UNIÓN RJ45 SE QUITA BISEL SE PASA CABLEADO Y SE VUELVE A PONER BISEL SE HACEN PRUEBAS OK | W73: VISITA TECNICA | X73: AA0QZ372 IIHZZ255 | Y73: TIPO I | Z73: TERRESTRE | AA73: MONTOYA VELEZ ANDRES FELIPE | AB73: 1 | AC73: 0 | AD73: 0 | AE73: 0 | AF73: 0 | AG73: 65960 | AH73: 65960
A74: CALI | B74: SUROCCIDENTE Y EJE CAFETERO | C74: 0004-0003 | D74: 76001 | E74: 3177549 | F74: 3007081938 | G74: INCIDENTE | H74: VALLE DEL CAUCA | I74: CALI | J74: PTM CALI INTERLADO | K74: REDEBAN | L74: FO-25-2029780 | M74: 46017.39 | N74: 46017.454 | O74: NO | P74: USUARIO | Q74: COMUNICACION | R74: CONEXIONES DE COMERCIO | S74: AGREGADOR | T74: COMCARD - PTM | U74: EJECUTADO / CANCELADO | V74: 26/12/2025 SE ESCALA PARA VISITA. LLAMAR ANTES DE VISITAR, CONFIRMAR FALLA Y DATOS | 26/12/2025 SE REALIZA LLAMADA TELEFÓNICA A LA SEÑORA ADRIANA DONDE ME INDICA QUE ESTÁ DE VIAJE Y NO PUEDE ATENDER LA APERTURA YA QUE ELLA NO ESTÁ PRESENTE, SE LE INFORMAR QUE SI TIENE ALGÚN PERSONAL ATENDIENDO EL NEGOCIO PARA HACER LA INSTALACIÓN PERO ME DICE QUE LA SEÑORA ADRIANA QUE LE GUSTARÁ PRESENCIAR LA INSTALACIÓN Y QUE EL DÍA DE HOY NO ME PUEDE ATENDER YA QUE NO SE ENCUENTRA EN LA CIUDAD Y QUIERE PRESENCIAR LA INSTALACIÓN DEL EQUIPO | W74: VISITA TECNICA | X74: DA005927 | Y74: TIPO I | Z74: TERRESTRE | AA74: ESCOBAR LENIS JUAN SEBASTIAN | AB74: 1 | AC74: 0 | AD74: 0 | AE74: 0 | AF74: 0 | AG74: 65960 | AH74: 65960
A75: SINCELEJO | B75: COSTA | C75: 0004-0001 | D75: 70713 | E75: 3180857 | F75: 3007038418 | G75: INCIDENTE | H75: SUCRE | I75: SAN ONOFRE | J75: DISTRICOL PANADERIA LA ESPIGA | K75: REDEBAN | L75: FO-25-2040452 | M75: 46018.45 | N75: 46020.543 | O75: NO | P75: USUARIO | Q75: LECTOR DE BARRAS | R75: CAPACITACION MANIPULACION DE COMERCIO | S75: AGREGADOR | T75: DISTRICOL | U75: EJECUTADO | V75: 27/12/2025 SE ESCALA PARA VISITA. LLAMAR ANTES DE VISITAR, CONFIRMAR FALLA Y DATOS | 28/12/2025 SE REQUIERE CAMBIO DE EQUIPO Y NO HAY SOPORTE REDEBAN SE REAGENDA PARA EL 29 DICIEMBRE A PARTIR DEL MEDIO DÍA. | 29/12/2025 SE VISITA SITIO, SE VERIFICA INFORMACIÓN, SE REALIZA PRIMEROS AUXILIOS, SE RECONFIGURA ESCÁNER, LECTURA OK, SE RETROALIMENTA AL ENCARGADO QUE LAS CÓDIGOS DE BARRAS IMPRESOS DEBEN ESTAR NÍTIDOS PARA UNA LECTURA RAPIDA, SE REALIZA PRUEBA TRX EXITOSA. | W75: VISITA TECNICA | X75: AA00X613 | Y75: TIPO II | Z75: TERRESTRE | AA75: SANTOS GUZMAN CHRISTIAN FELIPE | AB75: 1 | AC75: 0 | AD75: 0 | AE75: 0 | AF75: 0 | AG75: 163814 | AH75: 163814
A76: CALI | B76: SUROCCIDENTE Y EJE CAFETERO | C76: 0004-0003 | D76: 19573 | E76: 3180893 | F76: 3007051873 | G76: INCIDENTE | H76: CAUCA | I76: PUERTO TEJADA | J76: PTM PUERTO TEJADA MISCELANEA | K76: REDEBAN | L76: FO-25-2041027 | M76: 46018.519 | N76: 46020.438 | O76: NO | P76: USUARIO | Q76: COMUNICACION | R76: CANAL DEL COMERCIO | S76: AGREGADOR | T76: COMCARD - PTM | U76: EJECUTADO / CANCELADO | V76: 27/12/2025 SE ESCALA PARA VISITA. LLAMAR ANTES DE VISITAR, CONFIRMAR FALLA Y DATOS | 29/12/2025 SE LLEGA AL COMERCIO EL CUAL LA SEÑORA ALEJANDRA PASTRANA INDICA QUE EL EQUIPO ESTÁ FUNCIONANDO BIEN NO PERMITE LA MANIPULACIÓN Y REVISIÓN DEL EQUIPO YA QUE LA PERSONA ENCARGADA NO SE ENCUENTRA Y NO CONTESTA | W76: VISITA TECNICA | X76: BA0BZ027 | Y76: TIPO II | Z76: TERRESTRE | AA76: PALACIOS GOMEZ BRAHIAN ANDRES | AB76: 1 | AC76: 0 | AD76: 0 | AE76: 0 | AF76: 0 | AG76: 163814 | AH76: 163814
A77: MEDELLIN | B77: NOROCCIDENTE | C77: 0004-0005 | D77: 5360 | E77: 3181348 | F77: 3007074670 | G77: INCIDENTE | H77: ANTIOQUIA | I77: ITAGUI | J77: PTM ITAGUI RAPITIENDA LA PLACI | K77: REDEBAN | L77: FO-25-2040453 | M77: 46018.448 | N77: 46018.515 | O77: NO | P77: ENTIDAD | Q77: ERROR DE TRANSACCIONES | R77: TRANSACCION NO PERMITIDA | S77: AGREGADOR | T77: COMCARD - PTM | U77: EJECUTADO | V77: 27/12/2025 SE REALIZA VISITA TÉCNICA POR REPORTE DE POSIBLE BLOQUEO O CAÍDA DE LA ENTIDAD. AL MOMENTO DE LA ATENCIÓN, EL USUARIO NO CUENTA CON SUMINISTRO DE LUZ, POR LO CUAL NO ES POSIBLE VALIDAR EL FUNCIONAMIENTO DEL SERVICIO. SE INFORMA AL USUARIO QUE DEBE COMUNICARSE CON LA LÍNEA DE ATENCIÓN CORRESPONDIENTE PARA VALIDAR SI EXISTE BLOQUEO DE LA ENTIDAD; DE LO CONTRARIO, SI NO PRESENTA BLOQUEO, DEBERÁ VOLVER A COMUNICARSE PARA SOLICITAR UNA NUEVA VISITA UNA VEZ CUENTE CON SUMINISTRO ELÉCTRICO Y ASÍ PODER REALIZAR LAS VALIDACIONES CORRESPONDIENTES. | W77: VISITA TECNICA | X77: EGQZZ162 LNPZZ494 | Y77: TIPO I | Z77: TERRESTRE | AA77: HERNANDEZ CHAVARRIA JUAN CAMILO | AB77: 1 | AC77: 0 | AD77: 0 | AE77: 0 | AF77: 0 | AG77: 65960 | AH77: 65960
A78: MEDELLIN | B78: NOROCCIDENTE | C78: 0004-0005 | D78: 5001 | E78: 3181355 | F78: 3007079925 | G78: INCIDENTE | H78: ANTIOQUIA | I78: MEDELLIN | J78: DISTRICOL PALACIO DE LA LENCER | K78: REDEBAN | L78: FO-25-2040539 | M78: 46018.455 | N78: 46018.556 | O78: NO | P78: USUARIO | Q78: LECTOR DE TARJETAS | R78: OBSTRUCCION DEL LECTOR | S78: AGREGADOR | T78: DISTRICOL | U78: EJECUTADO | V78: 27/12/2025 SE REALIZA LIMPIEZA DE LECTOR CHIP CON OBSTRUCCIÓN OK PRUEBAS OK NO TELECARGA | W78: VISITA TECNICA | X78: SAUZZ940 | Y78: TIPO I | Z78: TERRESTRE | AA78: PAREJA ECHAVARRIA JHON DAVID | AB78: 1 | AC78: 0 | AD78: 0 | AE78: 0 | AF78: 0 | AG78: 65960 | AH78: 65960
A79: VALLEDUPAR | B79: COSTA | C79: 0004-0001 | D79: 20001 | E79: 3181616 | F79: 3007069837 | G79: INCIDENTE | H79: CESAR | I79: VALLEDUPAR | J79: PTM VALLEDUPAR DISTRIBUCIONES | K79: REDEBAN | L79: FO-25-2041643 | M79: 46018.615 | N79: 46019.491 | O79: NO | P79: ENTIDAD | Q79: ERROR DE TRANSACCIONES | R79: TRANSACCION NO PERMITIDA | S79: AGREGADOR | T79: COMCARD - PTM | V79: 27/12/2025 SE ESCALA PARA VISITA. LLAMAR ANTES DE VISITAR, CONFIRMAR FALLA Y DATOS | 28/12/2025 SE REALIZA GESTIÓN TELEFÓNICA ATIENDE LA SRA ANGIE DIAZ LA CUAL NOS INDICA QUE EL DIA DE AYER EL DATÁFONO NO LE PERMITIA REALIZAR TX PERO EL DIA DE HOY ESTA FUNCIONANDO PERFECTAMENTE | W79: SOPORTE TELEFONICO | Y79: TIPO I | Z79: TERRESTRE | AA79: MAESTRE MENGUAL EDGAR ENRIQUE | AB79: 0 | AC79: 0 | AD79: 0 | AE79: 0 | AF79: 0 | AG79: 37905 | AH79: 37905
A80: BOGOTA | B80: CUNDINAMARCA | C80: 0004-0004 | D80: 25899 | E80: 3181632 | F80: 3007017931 | G80: INCIDENTE | H80: CUNDINAMARCA | I80: ZIPAQUIRA | J80: BARRIO CENTRO VII ZIPAQUIRA | K80: REDEBAN | L80: FO-25-2042183 | M80: 46019.333 | N80: 46020.463 | O80: NO | P80: USUARIO | Q80: CIERRE | R80: COMERCIO NO REALIZA CIERRE | S80: CB UNO A UNO | T80: CB UNO A UNO | U80: EJECUTADO / CANCELADO | V80: 28/12/2025 SE ESCALA PARA VISITA. LLAMAR ANTES DE VISITAR, CONFIRMAR FALLA Y DATOS | 29/12/2025 SE REALIZA VISITA DE CAMPO ENCONTRADO QUE COMERCIO ESTA CERRADO SE INTENTA COMUNICACIÓN A LA LÍNEA 3138162283 PERO NO HAY RESPUESTA, SE INFORMA A SUPERVISOR QUIEN AUTORIZA CIERRE DE SOLICITUD. | W80: VISITA TECNICA | Y80: TIPO II | Z80: TERRESTRE | AA80: LOZADA ROJAS CHRISTIAN ANDRES | AB80: 1 | AC80: 0 | AD80: 0 | AE80: 0 | AF80: 0 | AG80: 163814 | AH80: 163814
A81: MEDELLIN | B81: NOROCCIDENTE | C81: 0004-0005 | D81: 5756 | E81: 3181662 | F81: 3007059025 | G81: INCIDENTE | H81: ANTIOQUIA | I81: SONSON | J81: BARRIO SONSON SONSON 3 | K81: REDEBAN | L81: FO-25-2043197 | M81: 46019.61 | N81: 46020.723 | O81: NO | P81: USUARIO | Q81: USUARIOS | R81: MALA MANIPULACION POS | S81: CB UNO A UNO | T81: CB UNO A UNO | U81: EJECUTADO | V81: 28/12/2025 SE ESCALA PARA VISITA. LLAMAR ANTES DE VISITAR, CONFIRMAR FALLA Y DATOS | 29/12/2025 SE REVISA EQUIPO Y SE EVIDENCIA QUE LOS PARÁMETROS ESTABAN BORRADOS, PROCEDO A FORMATEAR EL EQUIPO E INICIALIZAR, EQUIPO QUEDA OK Y FUNCIONANDO CORRECTAMENTE | W81: VISITA TECNICA | X81: MA002184 | Y81: TIPO III | Z81: TERRESTRE | AA81: RUA ALVAREZ RICHARD ANDRES | AB81: 1 | AC81: 0 | AD81: 0 | AE81: 0 | AF81: 0 | AG81: 275728 | AH81: 275728
A82: MEDELLIN | B82: NOROCCIDENTE | C82: 0004-0005 | D82: 5670 | E82: 3183256 | F82: 3007048502 | G82: INCIDENTE | H82: ANTIOQUIA | I82: SAN ROQUE | J82: BARRIO JUAN 23 SAN ROQUE | K82: REDEBAN | L82: FO-25-2045841 | M82: 46020.393 | N82: 46022.427 | O82: NO | P82: USUARIO | Q82: COMUNICACION | R82: CANAL DEL COMERCIO | S82: CB UNO A UNO | T82: CB UNO A UNO | U82: EJECUTADO | V82: 29/12/2025 EN COMUNICACION CON EL SR OSCAR JARAMILLO AL NUMERO 3164197228 SE CONFIRMAR FALLA DATAFONO NO RESIVE CONEXION A INTERNET Y DATOS CODIGO DEL PUNTO 48502 DIRECCION VRD SAN JOSE DEL BUS BARRIO JU . SE ESCALA PARA VISITA. | 31/12/2025 SE VISITA COMERCIO Y EL USUARIO NOS MANIFIESTA QUE PUSO UN INTENET NUEVO Y NO LE COGE EL INTERNET PERO CON EL ANTERIOR SI, SE HACEN VALIDACIONES DE CABLE DEL DATAFONO Y FUNCIONA CORRECTAMENTE SE REVISA EL MONDEN NUEVO DEL CLIENTE Y SE EVIDENCIA QUE LOS PUERTOS ESTÁN QUEDANDO YA QUE SE CONETA UNA CÁMARA Y UN COMPUTADOR Y QUEDAN SIN INTERNET. SE LE INDICA AL USUARIO QUE DEBE PEDIR LA REVISIÓN TÉCNICA DEL PROVEEDOR DE INTERNET. YA QUE EL EQUIPO ESTÁ OPERANDO CON NORMALIDAD CON OTRO MODEN | W82: VISITA TECNICA | X82: II00J449 | Y82: TIPO III | Z82: TERRESTRE | AA82: DIAZ ZABALA FRANCIS DUBAN | AB82: 1 | AC82: 0 | AD82: 0 | AE82: 0 | AF82: 0 | AG82: 275728 | AH82: 275728
A83: MEDELLIN | B83: NOROCCIDENTE | C83: 0004-0005 | D83: 27001 | E83: 3183532 | F83: 3007076854 | G83: INCIDENTE | H83: CHOCO | I83: QUIBDO | J83: BARR CABI VIA YUTO QUIBDO | K83: REDEBAN | L83: FO-25-2045837 | M83: 46020.405 | N83: 46021.586 | O83: NO | P83: USUARIO | Q83: MANTENIMIENTO | R83: MANTENIMIENTO GENERAL | S83: CB UNO A UNO | T83: CB UNO A UNO | U83: EJECUTADO | V83: 29/12/2025 EN COMUNICACION CON EL SR LORENA AL NUMERO 3142533824SE CONFIRMAR FALLA DATAFONO ERROR DE CONEXION Y DATOS CODIGO DEL PUNTO 76854 DIRECCION CABI VIA YUTO QUEBRADA DESECHO . SE ESCALA PARA VISITA. | 30/12/2025 SE REALIZA BORRADO DE VERSION, SE VUELVE A CARGAR, SE RELAIZAN PRUEBAS Y EL CB QUEDA OPERATIVO | W83: VISITA TECNICA | X83: 108ZZ458 | Y83: TIPO V | Z83: AEREO | AA83: ROBLEDO DIAZ ANDRES FELIPE | AB83: 1 | AC83: 0 | AD83: 0 | AE83: 0 | AF83: 0 | AG83: 988463 | AH83: 988463
A84: APARTADO | B84: NOROCCIDENTE | C84: 0004-0005 | D84: 5147 | E84: 3183904 | F84: 3007070444 | G84: INCIDENTE | H84: ANTIOQUIA | I84: CAREPA | J84: BARRIO CENTRO CAREPA | K84: REDEBAN | L84: FO-25-2045833 | M84: 46020.419 | N84: 46020.66 | O84: NO | P84: USUARIO | Q84: MANTENIMIENTO | R84: MANTENIMIENTO GENERAL | S84: CB UNO A UNO | T84: CB UNO A UNO | U84: EJECUTADO | V84: 29/12/2025 SE ESCALA PARA VISITA. LLAMAR ANTES DE VISITAR, CONFIRMAR FALLA Y DATOS | 29/12/2025 SE REALIZA FORMATEO Y REPISADO DE PARÁMETROS EQUIPOS SE ENCUENTRA OPERATIVO. | W84: VISITA TECNICA | X84: 0N008851 | Y84: TIPO I | Z84: TERRESTRE | AA84: CASTRO HENAO DANIEL ESTEBAN | AB84: 1 | AC84: 0 | AD84: 0 | AE84: 0 | AF84: 0 | AG84: 65960 | AH84: 65960
A85: MEDELLIN | B85: NOROCCIDENTE | C85: 0004-0005 | D85: 5861 | E85: 3184669 | F85: 3007045982 | G85: INCIDENTE | H85: ANTIOQUIA | I85: VENECIA | J85: BARRIO MALL POLLOS MARIO VENEC | K85: REDEBAN | L85: FO-25-2046366 | M85: 46020.481 | N85: 46021.693 | O85: NO | P85: USUARIO | Q85: USUARIOS | R85: CREACION DE USUARIOS | S85: CB UNO A UNO | T85: CB UNO A UNO | V85: 29/12/2025 SE ESCALA PARA VISITA. LLAMAR ANTES DE VISITAR, CONFIRMAR FALLA Y DATOS | 30/12/2025 SE LLAMA AL USUARIO E INDICA QUE YA SE LE HIZO EL CAMBIO DEL EQUIPO Y QUEDO OK | W85: SOPORTE TELEFONICO | Y85: TIPO II | Z85: TERRESTRE | AA85: MONTOYA VELEZ ANDRES FELIPE | AB85: 0 | AC85: 0 | AD85: 0 | AE85: 0 | AF85: 0 | AG85: 37905 | AH85: 37905
A86: IBAGUE | B86: REMOTAS | C86: 0004-0007 | D86: 73001 | E86: 3185433 | F86: 3007080605 | G86: INCIDENTE | H86: TOLIMA | I86: IBAGUE | J86: BARRIO LA GAVIOTA IBAGUE 8 | K86: REDEBAN | L86: FO-25-2046922 | M86: 46020.551 | N86: 46021.492 | O86: NO | P86: USUARIO | Q86: NO ENCIENDE | R86: CONEXIONES DE COMERCIO | S86: UNO A UNO | T86: UNO A UNO | V86: 29/12/2025 SE ESCALA PARA VISITA. LLAMAR ANTES DE VISITAR, CONFIRMAR FALLA Y DATOS | 30/12/2025 SE HABLA CON LA SEÑORA ALEJANDRA CEDIEL, POR EL NÚMERO DE TELÉFONO 3138388765, ME INDICA QUE EL DATÁFONO ESTÁ FUNCIONANDO CORRECTAMENTE E IMPRIME CORRECTAMENTE. | W86: SOPORTE TELEFONICO | Y86: TIPO I | Z86: TERRESTRE | AA86: VARGAS HERRERA JHON JAIRO | AB86: 0 | AC86: 0 | AD86: 0 | AE86: 0 | AF86: 0 | AG86: 37905 | AH86: 37905
A87: CALI | B87: SUROCCIDENTE Y EJE CAFETERO | C87: 0004-0003 | D87: 76892 | E87: 3185446 | F87: 3007021211 | G87: INCIDENTE | H87: VALLE DEL CAUCA | I87: YUMBO | J87: BARRIO CENTRO VIII YUMBO | K87: REDEBAN | L87: FO-25-2047116 | M87: 46020.573 | N87: 46021.568 | O87: NO | P87: USUARIO | Q87: USUARIOS | R87: MALA MANIPULACION POS | S87: CB UNO A UNO | T87: CB UNO A UNO | V87: 29/12/2025 SE ESCALA PARA VISITA. LLAMAR ANTES DE VISITAR, CONFIRMAR FALLA Y DATOS | 30/12/2025 SE HABLA CON EL CLIENTE QUIEN INDICA QUE NO PUEDO REALIZAR EL CIERRE EL DIA DE AYER NO LE GENERO CIERRE LE SALIA ERROR EN LA CLAVE, SE REALIZA LLAMADA AL CLIENTE Y VALIDACION DEL PROCESO ADECUADO DE CIERRE, Y SE ENCUENTRA QUE EL CLIENTE ESTABA REALIZANDO MAL LA GESTION DEL CIERRE, PUES INGRESABA A BORRAR TRANSACCIONES Y DESPUES INGRESABA POR COMERCIO A REALIZAR EL CIERRE, SE LE EXPLICA LA MANERA ADECUADA DE REALIZAR EL CIERRE Y EL NO PROCEDER A BORRAR TRANSACCIONES SIN EL ACOMPAÑAMIENTO DE LA LINEA PERO EL DATAFONO ESTA OPERANDO NORMAL CON SUS USUARIOS. | W87: SOPORTE TELEFONICO | Y87: TIPO I | Z87: TERRESTRE | AA87: HENAO CARDONA DIEGO FERNANDO | AB87: 0 | AC87: 0 | AD87: 0 | AE87: 0 | AF87: 0 | AG87: 37905 | AH87: 37905
A88: MANIZALES | B88: SUROCCIDENTE Y EJE CAFETERO | C88: 0004-0002 | D88: 17001 | E88: 3188457 | F88: 3007018888 | G88: INCIDENTE | H88: CALDAS | I88: MANIZALES | J88: MULTIPAGAS FUNDADORES | K88: REDEBAN | L88: FO-25-2051393 | M88: 46021.39 | N88: 46022.399 | O88: NO | P88: USUARIO | Q88: COMUNICACION | R88: CONEXIONES DE COMERCIO | S88: ROBUSTO | T88: MULTIPAGAS | U88: EJECUTADO | V88: 30/12/2025 SE ESCALA PARA VISITA. LLAMAR ANTES DE VISITAR, CONFIRMAR FALLA Y DATOS | 31/12/2025 SE LLEGA A LUGAR DE LA VISITA EL CUAL INDICAN PODER ATENDER SOBRE LAS 9AM MIENTRAS ABREN Y DAN AUTORIZACIÓN DE INGRESO | 31/12/2025 SE REALIZA VISITA SE EVIDENCIA QUE CAJA DE CONEXIONES PARA EL CABLE ETHERNET PRESENTA FALLAS, SE PRUEBA EN OTRA CAJA DE ETHERNET Y SI DA CONEXIÓN SE HACEN PRUEBAS SERVICIO OK, SE LE EXPLICA AL USUARIO QUE SON SUS CONEXIONES | W88: VISITA TECNICA | X88: TZZZZ177 | Y88: TIPO I | Z88: TERRESTRE | AA88: AGUIRRE HENAO RAUL EDUARDO | AB88: 1 | AC88: 0 | AD88: 0 | AE88: 0 | AF88: 0 | AG88: 65960 | AH88: 65960
A89: MANIZALES | B89: SUROCCIDENTE Y EJE CAFETERO | C89: 0004-0002 | D89: 17001 | E89: 3191142 | F89: 3007042332 | G89: INCIDENTE | H89: CALDAS | I89: MANIZALES | J89: DISTRICOL MERQUEMAS ARANJUEZ | K89: REDEBAN | L89: FO-25-2055303 | M89: 46021.713 | N89: 46022.445 | O89: NO | P89: USUARIO | Q89: USUARIOS | R89: MALA MANIPULACION POS | S89: AGREGADOR | T89: DISTRICOL | V89: 31/12/2025 SE ESCALA PARA VISITA. LLAMAR ANTES DE VISITAR, CONFIRMAR FALLA Y DATOS | 31/12/2025 SE REALIZA LLAMADA CON USUARIO PARA VALIDAR FALLA, INDICA QUE NO LE ESTABA INGRESANDO LA CLAVE 1526 PARA CIERRES PERO HOY QUE DE REALIZAN PRUEBAS EN LLAMADA INDICA QUE YA LE ESTA FUNCIONANDO BIEN Y LO DEJA INGRESAR CON NORMALIDAD, AL PARECER LA ESTABA INGRESANDO MAL, SE HACEN PRUEBAS EN LLAMADA, SERVICIO OK | W89: SOPORTE TELEFONICO | Y89: TIPO I | Z89: TERRESTRE | AA89: AGUIRRE HENAO RAUL EDUARDO | AB89: 0 | AC89: 0 | AD89: 0 | AE89: 0 | AF89: 0 | AG89: 37905 | AH89: 37905
A90: VALLEDUPAR | B90: COSTA | C90: 0004-0001 | D90: 20001 | E90: 3191492 | F90: 3007032347 | G90: INCIDENTE | H90: CESAR | I90: VALLEDUPAR | J90: MULTIPAGAS GUATAPURI | K90: REDEBAN | L90: FO-25-2056336 | M90: 46022.418 | N90: 46022.701 | O90: NO | P90: USUARIO | Q90: LECTOR DE BARRAS | R90: ERROR PAGOS PARCIALES DE FACTURAS | S90: ROBUSTO | T90: MULTIPAGAS | V90: 31/12/2025 SE ESCALA PARA VISITA. LLAMAR ANTES DE VISITAR, CONFIRMAR FALLA Y DATOS | 31/12/2025 SE REALIZA GESTIÓN TELEFÓNICA CLIENTE INDICA QUE EL LECTOR DE BARRAS YA LE ESTÁ FUNCIONANDO BIEN | W90: SOPORTE TELEFONICO | Y90: TIPO I | Z90: TERRESTRE | AA90: MAESTRE MENGUAL EDGAR ENRIQUE | AB90: 0 | AC90: 0 | AD90: 0 | AE90: 0 | AF90: 0 | AG90: 37905 | AH90: 37905
A91: YOPAL | B91: REMOTAS | C91: 0004-0007 | D91: 85001 | E91: TA-25-1364353 | F91: 3007078773 | G91: INCIDENTE | H91: CASANARE | I91: YOPAL | J91: DISTRICOL DROGUERIA DROVITAL S | K91: REDEBAN | L91: FO-25-1930783 | M91: 45995.002 | N91: 45995.564 | O91: NO | P91: ENTIDAD | Q91: ERROR DE TRANSACCIONES | R91: TRANSACCION NO PERMITIDA | S91: AGREGADOR | T91: DISTRICOL | U91: EJECUTADO | V91: 04/12/2025 SE VISITA COMERCIO, SE REALIZA INICIALIZACION A LA NUEVA TERMINAL. PRUEBAS OK. OPERATIVO EL SERVICIO. | W91: VISITA TECNICA | X91: AE005095 | Y91: TIPO I | Z91: TERRESTRE | AA91: BERNAL ELAICA EDGAR ALEXIS | AB91: 1 | AC91: 0 | AD91: 0 | AE91: 0 | AF91: 0 | AG91: 65960 | AH91: 65960
A92: MEDELLIN | B92: NOROCCIDENTE | C92: 0004-0005 | D92: 5237 | E92: TA-25-1423059 | F92: 3007016764 | G92: INCIDENTE | H92: ANTIOQUIA | I92: DON MATIAS | J92: BRR SANCHEZ DON MATIAS | K92: REDEBAN | L92: FO-25-1980415 | M92: 46007.368 | N92: 46007.649 | O92: NO | P92: USUARIO | Q92: COMUNICACION | R92: CONEXIONES DE COMERCIO | S92: CB UNO A UNO | T92: CB UNO A UNO | U92: EJECUTADO | V92: 16/12/2025 SE REALIZA VISITA TÉCNICA AL CORRESPONSAL BANCOLOMBIA POR INCIDENTE REPORTADO CON EL DATÁFONO EL USUARIO CONFIRMA SU IDENTIFICACIÓN E INFORMA QUE EL EQUIPO PRESENTÓ UN ERROR DE CONEXIÓN PERO QUE LE HABÍAN REALIZADO UNOS PRIMEROS AUXILIOS Y CON ELLO FUNCIONÓ EL USUARIO AUTORIZA LA VERIFICACIÓN PARA DETERMINAR LA CAUSA DE LA NOVEDAD SE REVISA LA CONFIGURACIÓN Y TODO SE ENCUENTRA NORMAL SE EJECUTAN PRUEBAS QUE RESULTAN EXITOSAS IDENTIFICANDO QUE LA AFECTACIÓN CORRESPONDE A PROBLEMAS DE CONEXIÓN PROPIOS DEL COMERCIO | W92: VISITA TECNICA | X92: JEZZZ364 | Y92: TIPO II | Z92: TERRESTRE | AA92: MARTINEZ TOVAR OSCAR DAVID | AB92: 1 | AC92: 0 | AD92: 0 | AE92: 0 | AF92: 0 | AG92: 163814 | AH92: 163814
A93: BUCARAMANGA | B93: SANTANDERES | C93: 0004-0008 | D93: 68276 | E93: TA-25-1445579 | F93: 3007081858 | G93: INCIDENTE | H93: SANTANDER | I93: FLORIDABLANCA | J93: PTM FLORIDABLANCA TIENDA LA AN | K93: REDEBAN | L93: FO-25-2022782 | M93: 46014.353 | N93: 46014.539 | O93: NO | P93: USUARIO | Q93: MANTENIMIENTO | R93: MANTENIMIENTO GENERAL | S93: AGREGADOR | T93: COMCARD - PTM | V93: 23/12/2025 SE ESTABLECE CONTACTO VÍA WHATSAPP AL NÚMERO 3228385680 CON MARIELA MANCILLA CASTRO PARA VALIDAR HORARIO DE ATENCIÓN PARA INICIAR EL RESPECTIVO DESPLAZAMIENTO AL PUNTO EN COMUNICACIÓN CLIENTE NOS INDICA QUE SE COMUNICA A REALIZAR CONSULTA POR QUE EL DATAFONO NO LE IMPRIMIA LO CUAL SE DEBIA AL MAL POCISIONAMIENTO DEL ROLLO DEL DATAFONO NOS INDICA QUE TODO ESTA FUNCIONANDO BIEN Y NO REQUIERE EL SERVICIO TÉCNICO AGRADECE POR LA ATENCIÓN PRESTADA | W93: SOPORTE TELEFONICO | Y93: TIPO I | Z93: TERRESTRE | AA93: REYES RAMIREZ DIEGO ALEXANDER | AB93: 0 | AC93: 0 | AD93: 0 | AE93: 0 | AF93: 0 | AG93: 37905 | AH93: 37905

Sheet OC
A1: CIUDAD SEDE | B1: ZONA | C1: CENTRO DE COSTOS LINEACOM | D1: CODIGO DANE | E1: TA/CODIGO ACTIVIDAD | F1: CODIGO CB | G1: ACTIVIDAD | H1: DEPARTAMENTO | I1: CIUDAD | J1: NOMBRE DEL CB | K1: RED | L1: FO | M1: FECHA ASIGNACION A LINEA COMUNICACIONES | N1: FECHA CIERRE DEL TICKET (DD/MM/AAAA HH:MM) | O1: ACOMETIDA | P1: SOLICITUD | Q1: DESCRIPCION | R1: FORMATO | S1: CADENA | T1: ESTADO | U1: CAUSAL ESTADO | V1: OBSERVACION | W1: FORMA DE ATENCION | X1: TERMINAL(ES) | Y1: TIPIFICACION | Z1: TIPO DE TRAYECTO | AA1: NOMBRE DEL TECNICO | AB1: DIAS DE VISITA | AC1: SWITCH | AD1: ACOMETIDA DATOS | AE1: ACOMETIDA ELÉCTRICA | AF1: VALOR ACTIVIDAD | AG1: VALOR TOTAL
A2: TUNJA | B2: SANTANDERES | C2: 0004-0008 | D2: 15693 | E2: 14463423 | F2: 3007080298 | G2: OC TRASLADO | H2: BOYACA | I2: SANTA ROSA DE VITERBO | J2: BARRIO CENTRO SANTA ROSA DE VITERBO 10 | K2: REDEBAN | L2: FO-25-1938750 | FO-25-1930207 | M2: 45994.716 | N2: 46001.687 | O2: NO | P2: TRASLADO | Q2: TRASLADO EXTERNO | R2: UNO A UNO | S2: UNO A UNO | T2: EJECUTADO | U2: EJECUTADO EXITOSO | V2: [FO-25-1938750] 10/12/2025 SE REALIZÓ LA VISITA Y SE EJECUTARON LOS PROCEDIMIENTOS INDICADOS POR REDEBAN. SE FORMATEA EL EQUIPO, SE MONTA LA VERSIÓN CORRESPONDIENTE Y SE INSTALA EL SISTEMA OPERATIVO; SIN EMBARGO, EL PROCEDIMIENTO NO RESULTA EFECTIVO. SE ESCALA NUEVAMENTE EL CASO CON REDEBAN, DONDE PAOLA GARZÓN REALIZA EL DEBIDO ESCALAMIENTO CON OPERACIONES, QUIENES AUTORIZAN EL CAMBIO DE LA TERMINAL. SE DEJA INSTALADA LA TERMINAL DA006757 Y SE REALIZAN LAS RESPECTIVAS CONFIGURACIONES, OBTENIENDO PRUEBAS EXITOSAS. PROCEDIMIENTO REALIZADO POR PAOLA GARZÓN DE REDEBAN. CLIENTE CONFORME. || [FO-25-1930207] 04/12/2025 POR FAVOR, COMUNICARSE CON USUARIO PARA CONFIRMAR UBICACION, SOLICITUD Y PROGRAMAR VISITA TECNICA | 04/12/2025 SE ESTABLECE COMUNICACIÓN CON LA SEÑORA SANDRA RINCÓN AL NÚMERO DE CONTACTO 3135875987 CLIENTE INDICA QUE AÚN NO LE HAN REALIZADO LA INSTALACIÓN DEL PUNTO DE INTERNET EN LA NUEVA DIRECCIÓN INFORMA QUE SE VA A COMUNICAR CON EL PROVEEDOR DE INTERNET PARA COORDINAR LA INSTALACIÓN TAN PRONTO TENGA UNA RESPUESTA NO LA COMUNICA PARA PROGRAMAR LA VISITA PARA EL TRASLADO. | 05/12/2025 SE EJECUTA TRASLADO EXTERNO INSTALANDO EQUIPOS Y PUBLICIDAD NO ES POSIBLE EJECUTAR LA INICIALIZACION PRESENTA ERROR AL INICIALIZAR AL EQUIPO SE ESCALA A REDEBAN EL CASO INDICAN QUE EL ERROR PROVIENE DE UN PROCEDIMIENTO ERRADO EN EL TRASLADO DESDE LA ENTIDAD QUE GENERÓ ERROR EN LA PLATAFORMA DE BESE 24 EL CASO ESTÁ EN PROCESO DE SOLUCIÓN EN NIVEL 3 CON TI OPERACIONES Y BACKOFFICE AUTORIZAN RETIRARNOS DEL PUNTO DEJANDO EL CASO ABIERTO REPROGRAMAR VISITA. | W2: VISITA TECNICA | X2: DA006757 | Y2: TIPO II | Z2: TERRESTRE | AA2: RODRIGUEZ MURCIA YERSON IVAN | AB2: 1 | AC2: 0 | AD2: 0 | AE2: 0 | AF2: 163814 | AG2: 163814
A3: MEDELLIN | B3: NOROCCIDENTE | C3: 0004-0005 | D3: 5138 | E3: 14481176 | F3: 3007070983 | G3: OC TRASLADO | H3: ANTIOQUIA | I3: CAÑASGORDAS | J3: BARRIO CANASGORDAS CANASGORDA | K3: REDEBAN | L3: FO-25-1950930 | M3: 45996.684 | N3: 46002.969 | O3: NO | P3: TRASLADO | Q3: TRASLADO EXTERNO | R3: CB UNO A UNO | S3: CB UNO A UNO | T3: CANCELADO | U3: PETICIÓN USUARIO | V3: 09/12/2025 POR FAVOR, COMUNICARSE CON USUARIO PARA CONFIRMAR UBICACION, SOLICITUD Y PROGRAMAR VISITA TECNICA | W3: VISITA TECNICA | Y3: TIPO III | Z3: TERRESTRE | AA3: BARRIENTOS HERNANDEZ CRISTIAN HORACIO | AB3: 1 | AC3: 0 | AD3: 0 | AE3: 0 | AF3: 275728 | AG3: 275728
A4: BOGOTA | B4: CUNDINAMARCA | C4: 0004-0004 | D4: 11001 | E4: 14493357 | F4: 3007043354 | G4: OC TRASLADO | H4: CUNDINAMARCA | I4: BOGOTA | J4: BARRIO BOSA BRASIL BOGOTA 2 | K4: REDEBAN | L4: FO-25-1950925 | M4: 45996.684 | N4: 46002.515 | O4: NO | P4: TRASLADO | Q4: TRASLADO EXTERNO | R4: CB UNO A UNO | S4: CB UNO A UNO | T4: EJECUTADO / CANCELADO | U4: PETICIÓN USUARIO | V4: 09/12/2025 POR FAVOR, COMUNICARSE CON USUARIO PARA CONFIRMAR UBICACION, SOLICITUD Y PROGRAMAR VISITA TECNICA | W4: VISITA TECNICA | Y4: TIPO I | Z4: TERRESTRE | AA4: HERNANDEZ NARANJO OSCAR EDUARDO | AB4: 1 | AC4: 0 | AD4: 0 | AE4: 0 | AF4: 65960 | AG4: 65960
A5: MEDELLIN | B5: NOROCCIDENTE | C5: 0004-0005 | D5: 5001 | E5: 14494063 | F5: 3007037905 | G5: OC TRASLADO | H5: ANTIOQUIA | I5: MEDELLIN | J5: BARRIO LOPEZ DE MESA MEDELLIN | K5: REDEBAN | L5: FO-25-1930242 | M5: 45994.716 | N5: 46001.404 | O5: NO | P5: TRASLADO | Q5: TRASLADO INTERNO | R5: CB UNO A UNO | S5: CB UNO A UNO | T5: EJECUTADO | U5: PETICIÓN USUARIO | V5: 04/12/2025 POR FAVOR, COMUNICARSE CON USUARIO PARA CONFIRMAR UBICACION, SOLICITUD Y PROGRAMAR VISITA TECNICA | 10/12/2025 EN LA DESCRIPCIÓN DE SOLICITUD DE TRASLADO, NO HAY NINGÚN NÚMERO ANEXADO, POR LO TANTO, SE VISITA EL SITIO YA QUE DICE QUE EL MOVIMIENTO QUE HICIERON ES EN EL MISMO PUNTO. DESPUÉS DE VISITAR EL SITIO, QUIÉN YA ES EL NUEVO ADMINISTRADOR, INFORMA QUE EL CB LO QUITARON Y QUE NO SABEN ACERCA DE LA CONTINUIDAD DEL CB EN ALGUNA OTRA DIRECCIÓN Y COMO NO HAY UN NÚMERO DE CONTACTO, NO SE PUEDE VALIDAR. | W5: VISITA TECNICA | X5: 00000 | Y5: TIPO I | Z5: TERRESTRE | AA5: MARIN PIEDRAHITA JIMMY ALEXIS | AB5: 1 | AC5: 0 | AD5: 0 | AE5: 0 | AF5: 65960 | AG5: 65960
A6: NEIVA | B6: REMOTAS | C6: 0004-0007 | D6: 41001 | E6: 14516194 | F6: 3007081806 | G6: OC TRASLADO | H6: HUILA | I6: NEIVA | J6: PTM NEIVA SERVICIOS PROFESIONA | K6: REDEBAN | L6: FO-25-1992654 | M6: 46008.619 | N6: 46011.363 | O6: NO | P6: TRASLADO | Q6: TRASLADO EXTERNO | R6: AGREGADOR | S6: COMCARD - PTM | U6: CANCELADO POR EL USUARIO | V6: 17/12/2025 SE REALIZAN VARIOS INTLA GESTIONENTOS DE COMUNICACION CON LOS USUARIOS Y NO SE LOGRA ESTABLECER CONTACTO, PORFAVOR LLAMAR ANTES DE REALIZAR | W6: SOPORTE TELEFONICO | Y6: TIPO I | Z6: TERRESTRE | AA6: DIAZ VARGAS JONATHAN MIGUEL | AB6: 0 | AC6: 0 | AD6: 0 | AE6: 0 | AF6: 37905 | AG6: 37905
A7: BOGOTA | B7: CUNDINAMARCA | C7: 0004-0004 | D7: 25885 | E7: 14536522 | F7: 3007074206 | G7: OC TRASLADO | H7: CUNDINAMARCA | I7: YACOPI | J7: BARRIO CENTRO YACOPÍ | K7: REDEBAN | L7: FO-25-2001064 | M7: 46009.726 | N7: 46015.349 | O7: NO | P7: TRASLADO | Q7: TRASLADO EXTERNO | R7: CB UNO A UNO | S7: CB UNO A UNO | T7: EJECUTADO / CANCELADO | U7: PETICIÓN RED | V7: 19/12/2025 SE REALIZARON VARIOS INTENTOS PARA REALIZAR LA VERIFICACION Y ACTUALIZACION DE DATOS AL NUMERO AL NUMERO 3025865277 PERO EN NINGUNO DE LOS INTENTOS LA COMUNICACION FUE EXITOSA.PORFAVOR LLAMAR ANTES DE REALIZAR LA GESTION | W7: VISITA TECNICA | Y7: TIPO IV | Z7: TERRESTRE | AA7: INFANTE SIERRA MANUEL FERNANDO | AB7: 1 | AC7: 0 | AD7: 0 | AE7: 0 | AF7: 479590 | AG7: 479590
A8: BOGOTA | B8: CUNDINAMARCA | C8: 0004-0004 | D8: 11001 | E8: 14576180 | F8: 3007043354 | G8: OC TRASLADO | H8: CUNDINAMARCA | I8: BOGOTA | J8: BARRIO BOSA BRASIL BOGOTA 2 | K8: REDEBAN | L8: FO-25-2027033 | M8: 46014.707 | N8: 46020.51 | O8: NO | P8: TRASLADO | Q8: TRASLADO EXTERNO | R8: CB UNO A UNO | S8: CB UNO A UNO | T8: EJECUTADO / CANCELADO | U8: DIRECCION ERRADA | V8: 24/12/2025 "SE ESTABLECE COMUNICACION CON LA SEÑORA BLANCA RAMIREZ CON NUMERO DE TELEFONO 3213815155.SE REALIZA CONFIRMACION DE DIRECCION DE LA DIRECCION EN LA CUAL QUEDARA INSTALADO EL SERVICIO CR 88 I # 51 A 10 SUR CUNDINAMARCA | W8: VISITA TECNICA | Y8: TIPO I | Z8: TERRESTRE | AA8: ALARCON AREVALO JOHAN STIVEN | AB8: 1 | AC8: 0 | AD8: 0 | AE8: 0 | AF8: 65960 | AG8: 65960
