Workbook
Name A: #REF!
Name Actividad: #REF!
Name Analistas: #REF!
Name arearesponsable: #REF!
Name CCO: #REF!
Name Clientes: #REF!
Name COORDINADOR: #REF!
Name Coordinadores: #REF!
Name DOCUMENTADOR: #REF!
Name ES: #REF!
Name ESS: #REF!
Name Estado: #REF!
Name ESTADOACTIVIDAD: #REF!
Name ESTADOS: #REF!
Name ESTADOSCIERRES: #REF!
Name Facturacion: #REF!
Name FACTURACIÓN: #REF!
Name falla: #REF!
Name Fallas: #REF!
Name Grupo_Falla: #REF!
Name inconservmanager: #REF!
Name INCUMPLIMIENTO: #REF!
Name LISTA: #REF!
Name LISTA2: #REF!
Name LOLO: #REF!
Name solicitudes: #REF!
Name Tecnicos: #REF!
Name Version: #REF!

Sheet Hoja1
A2: aperturas bancol
A3: Etiquetas de fila | B3: Suma de VALOR TOTAL
A4: COSTA | B4: 2291476 | C4: cc | D4: valor
A5: 0004-0001 | B5: 2291476 | C5: =A5 -> 0004-0001 | D5: =B5 -> 2291476 | H5: Etiquetas de fila | I5: Suma de valor
A6: NOROCCIDENTE | B6: 5027174 | G6: costa | H6: 0004-0001 | I6: 54060187
A7: 0004-0005 | B7: 5027174 | C7: =A7 -> 0004-0005 | D7: =B7 -> 5027174 | G7: eje | H7: 0004-0002 | I7: 9675354
A8: SANTANDERES | B8: 2466323 | G8: sur | H8: 0004-0003 | I8: 46546603
A9: 0004-0008 | B9: 2466323 | C9: =A9 -> 0004-0008 | D9: =B9 -> 2466323 | G9: centro | H9: 0004-0004 | I9: 37256173
A10: SUROCCIDENTE Y EJE CAFETERO | B10: 655025 | G10: noroccidente | H10: 0004-0005 | I10: 81773717
A11: 0004-0002 | B11: 75096 | C11: =A11 -> 0004-0002 | D11: =B11 -> 75096 | G11: oriente | H11: 0004-0007 | I11: 41222756
A12: 0004-0003 | B12: 579929 | C12: =A12 -> 0004-0003 | D12: =B12 -> 579929 | G12: santanderes | H12: 0004-0008 | I12: 58086348
A13: CENTRO | B13: 903741 | H13: Total general | I13: 328621138
A14: 0004-0004 | B14: 903741 | C14: =A14 -> 0004-0004 | D14: =B14 -> 903741
A15: ORIENTE | B15: 1343284
A16: 0004-0007 | B16: 1343284 | C16: =A16 -> 0004-0007 | D16: =B16 -> 1343284
A17: SUROCCIDENTE | B17: 2826954
A18: 0004-0003 | B18: 2826954 | C18: =A18 -> 0004-0003 | D18: =B18 -> 2826954
A19: EJE CAFETERO | B19: 477820
A20: 0004-0002 | B20: 477820 | C20: =A20 -> 0004-0002 | D20: =B20 -> 477820
A21: Total general | B21: 15991797
A24: incidentes bancol
A25: Etiquetas de fila | B25: Suma de VALOR TOTAL
A26: COSTA | B26: 27964716
A27: 0004-0001 | B27: 27964716 | C27: =A27 -> 0004-0001 | D27: =B27 -> 27964716
A28: CUNDINAMARCA | B28: 9650846
A29: 0004-0004 | B29: 9650846 | C29: =A29 -> 0004-0004 | D29: =B29 -> 9650846
A30: NOROCCIDENTE | B30: 38628762
A31: 0004-0005 | B31: 38628762 | C31: =A31 -> 0004-0005 | D31: =B31 -> 38628762
A32: REMOTAS | B32: 12478601
A33: 0004-0007 | B33: 12478601 | C33: =A33 -> 0004-0007 | D33: =B33 -> 12478601
A34: SANTANDERES | B34: 17736345
A35: 0004-0008 | B35: 17736345 | C35: =A35 -> 0004-0008 | D35: =B35 -> 17736345
A36: SUROCCIDENTE Y EJE CAFETERO | B36: 23915193
A37: 0004-0002 | B37: 4069894 | C37: =A37 -> 0004-0002 | D37: =B37 -> 4069894
A38: 0004-0003 | B38: 19845299 | C38: =A38 -> 0004-0003 | D38: =B38 -> 19845299
A39: SUROCCIDENTE | B39: 144968
A40: 0004-0003 | B40: 144968 | C40: =A40 -> 0004-0003 | D40: =B40 -> 144968
A41: Total general | B41: 130519431
A44: oc bancol
A45: Etiquetas de fila | B45: Suma de VALOR TOTAL
A46: COSTA | B46: 7516537
A47: 0004-0001 | B47: 7516537 | C47: =A47 -> 0004-0001 | D47: =B47 -> 7516537
A48: CUNDINAMARCA | B48: 3166017
A49: 0004-0004 | B49: 3166017 | C49: =A49 -> 0004-0004 | D49: =B49 -> 3166017
A50: NOROCCIDENTE | B50: 11634196
A51: 0004-0005 | B51: 11634196 | C51: =A51 -> 0004-0005 | D51: =B51 -> 11634196
A52: REMOTAS | B52: 7152414
A53: 0004-0007 | B53: 7152414 | C53: =A53 -> 0004-0007 | D53: =B53 -> 7152414
A54: SANTANDERES | B54: 11564692
A55: 0004-0008 | B55: 11564692 | C55: =A55 -> 0004-0008 | D55: =B55 -> 11564692
A56: SUROCCIDENTE Y EJE CAFETERO | B56: 6252240
A57: 0004-0002 | B57: 1317321 | C57: =A57 -> 0004-0002 | D57: =B57 -> 1317321
A58: 0004-0003 | B58: 4934919 | C58: =A58 -> 0004-0003 | D58: =B58 -> 4934919
A59: Total general | B59: 47286096
A63: papeleria
A64: Etiquetas de fila | B64: Suma de VALOR TOTAL
A65: COSTA | B65: 8567520
A66: 0004-0001 | B66: 8567520 | C66: =A66 -> 0004-0001 | D66: =B66 -> 8567520
A67: CUNDINAMARCA | B67: 5632611
A68: 0004-0004 | B68: 5632611 | C68: =A68 -> 0004-0004 | D68: =B68 -> 5632611
A69: NOROCCIDENTE | B69: 15247877
A70: 0004-0005 | B70: 15247877 | C70: =A70 -> 0004-0005 | D70: =B70 -> 15247877
A71: REMOTAS | B71: 4523431
A72: 0004-0007 | B72: 4523431 | C72: =A72 -> 0004-0007 | D72: =B72 -> 4523431
A73: SANTANDERES | B73: 7303179
A74: 0004-0008 | B74: 7303179 | C74: =A74 -> 0004-0008 | D74: =B74 -> 7303179
A75: SUROCCIDENTE Y EJE CAFETERO | B75: 10029002
A76: 0004-0002 | B76: 1734316 | C76: =A76 -> 0004-0002 | D76: =B76 -> 1734316
A77: 0004-0003 | B77: 8294686 | C77: =A77 -> 0004-0003 | D77: =B77 -> 8294686
A78: Total general | B78: 51303620
A81: apertura aval
A82: Etiquetas de fila | B82: Suma de VALOR FACTURABLE A LA RED
A83: 0004-0001 | B83: 1494934 | C83: =A83 -> 0004-0001 | D83: =B83 -> 1494934
A84: COSTA | B84: 1494934
A85: 0004-0002 | B85: 819070 | C85: =A85 -> 0004-0002 | D85: =B85 -> 819070
A86: SUROCCIDENTE Y EJE CAFETERO | B86: 327628
A87: EJE CAFETERO | B87: 491442
A88: 0004-0003 | B88: 2122946 | C88: =A88 -> 0004-0003 | D88: =B88 -> 2122946
A89: SUROCCIDENTE Y EJE CAFETERO | B89: 1522178
A90: SUROCCIDENTE | B90: 600768
A91: 0004-0004 | B91: 7733912 | C91: =A91 -> 0004-0004 | D91: =B91 -> 7733912
A92: CUNDINAMARCA | B92: 3228778
A93: CENTRO | B93: 4505134
A94: 0004-0005 | B94: 2722076 | C94: =A94 -> 0004-0005 | D94: =B94 -> 2722076
A95: NOROCCIDENTE | B95: 2722076
A96: 0004-0007 | B96: 6427073 | C96: =A96 -> 0004-0007 | D96: =B96 -> 6427073
A97: REMOTAS | B97: 4892962
A98: ORIENTE | B98: 1534111
A99: 0004-0008 | B99: 5516622 | C99: =A99 -> 0004-0008 | D99: =B99 -> 5516622
A100: SANTANDERES | B100: 5516622
A101: Total general | B101: 26836633
A104: incidente aval
A105: Etiquetas de fila | B105: Suma de VALOR FACTURABLE A LA RED
A106: 0004-0001 | B106: 4712121 | C106: =A106 -> 0004-0001 | D106: =B106 -> 4712121
A107: COSTA | B107: 4712121
A108: 0004-0002 | B108: 891901 | C108: =A108 -> 0004-0002 | D108: =B108 -> 891901
A109: SUROCCIDENTE Y EJE CAFETERO | B109: 718740
A110: EJE CAFETERO | B110: 173161
A111: 0004-0003 | B111: 5174989 | C111: =A111 -> 0004-0003 | D111: =B111 -> 5174989
A112: SUROCCIDENTE Y EJE CAFETERO | B112: 5174989
...

Sheet BASE LIQUIDACION REDEBAN 2025
A1: Tipificación | B1: Implementaciones | C1: Incidentes – Ordenes de Cambio | D1: Fallida | G1: Tipificación | H1: Actividad sin cambio de datafono | J1: Actividad + adicional cambio de datafono | L1: Visita Fallida | N1: Incremento 2025
A2: TIPO I | B2: =71384.4052*(1+$N$2) -> 75096.394 | C2: =62699.6885*(1+$N$2) -> 65960.072 | D2: =35693.4343*(1+$N$2) -> 37549.493 | H2: Instalación Pinpad + HUB | I2: Segunda actividad en mismo comercio, misma visita | J2: Instalación Pinpad + HUB | K2: Segunda actividad en mismo comercio, misma visita | N2: 0.052
A3: TIPO II | B3: =155716.4408*(1+$N$2) -> 163813.7 | C3: =137802.16*(1+$N$2) -> 144967.87 | D3: =117879.8485*(1+$N$2) -> 124009.6 | G3: Tipo I | H3: =31819.23994686*(1+$N$2) -> 33473.84 | I3: =26222.67548178*(1+$N$2) -> 27586.255 | J3: =51196.46628516*(1+$N$2) -> 53858.683 | K3: =42157.66342524*(1+$N$2) -> 44349.862 | L3: =28948.10610808*(1+$N$2) -> 30453.408
A4: TIPO III | B4: =262099.6015*(1+$N$2) -> 275728.78 | C4: =262099.6015*(1+$N$2) -> 275728.78 | D4: =262099.6015*(1+$N$2) -> 275728.78 | G4: Tipo II | H4: =98014.03066668*(1+$N$2) -> 103110.76 | I4: =26222.67548178*(1+$N$2) -> 27586.255 | J4: =119562.49505524*(1+$N$2) -> 125779.74 | K4: =42157.66342524*(1+$N$2) -> 44349.862 | L4: =94765.6295813*(1+$N$2) -> 99693.442
A5: TIPO IV | B5: =479878.9419*(1+$N$2) -> 504832.65 | C5: =455882.9625*(1+$N$2) -> 479588.88 | D5: =370911.6746*(1+$N$2) -> 390199.08 | G5: Tipo III | H5: =189140.9827006*(1+$N$2) -> 198976.31 | I5: =26222.67548178*(1+$N$2) -> 27586.255 | J5: =200461.60194168*(1+$N$2) -> 210885.61 | K5: =42157.66342524*(1+$N$2) -> 44349.862 | L5: =171492.68108896*(1+$N$2) -> 180410.3
A6: Destino Aéreo | B6: =939603.5767*(1+$N$2) -> 988462.96 | C6: a partir del 5to servicio | G6: Tipo IV | H6: =461621.60109668*(1+$N$2) -> 485625.92 | I6: =26222.67548178*(1+$N$2) -> 27586.255 | J6: =461621.60109668*(1+$N$2) -> 485625.92 | K6: =42157.66342524*(1+$N$2) -> 44349.862 | L6: =461621.60109668*(1+$N$2) -> 485625.92
G7: * Tipo IV Especial Donde se requiera desplazamiento aéreo o fluvial será facturado el valor de la actividad y adicional el valor de $988.463 por cada 5 actividades de esta tipología
A8: Tarifas para día adicional de actividades:
A9: Tipificación | B9: Día adicional- menos de dos horas | C9: Medio día adicional | D9: Día adicional- más de 4 horas
A10: Tipo I | B10: =71384.4052*(1+$N$2) -> 75096.394 | C10: =133455.9267*(1+$N$2) -> 140395.63 | D10: =191225.1201*(1+$N$2) -> 201168.83 | G10: Actividad | H10: Unidad | I10: Valor Unitario
A11: Tipo II | B11: =133455.9267*(1+$N$2) -> 140395.63 | C11: =191225.1201*(1+$N$2) -> 201168.83 | D11: =257740.6152*(1+$N$2) -> 271143.13 | G11: Gestión telefónica y cierre de incidente de bloqueo | H11: Unidad | I11: =17639.19516086*(1+$N$2) -> 18556.433
A12: Tipo III | B12: =186821.7926*(1+$N$2) -> 196536.53 | C12: =248892.0824*(1+$N$2) -> 261834.47 | D12: =306662.5075*(1+$N$2) -> 322608.96 | G12: Servicio de cierre de incidente de bloqueo | H12: Unidad | I12: =4810.80785492*(1+$N$2) -> 5060.9699
A13: Tipo IV | B13: =186821.7926*(1+$N$2) -> 196536.53 | C13: =248892.0824*(1+$N$2) -> 261834.47 | D13: =306662.5075*(1+$N$2) -> 322608.96
A16: Servicio | B16: Tarifa actividad | D16: VALOR DE LA TERMINAL ADICIONAL | E16: VALOR DE INSTALACIÓN DE BASE EN "Y"
A17: Papelería – Tarifa única | B17: =34010.9321*(1+$N$2) -> 35779.501 | D17: =20537.3658*(1+$N$2) -> 21605.309 | E17: =10737.9606*(1+$N$2) -> 11296.335
A18: Papelería Tipo II - Visita técnica | B18: =64310*(1+$N$2) -> 67654.12
A19: Solución telefónica | B19: =39202.5476*(1+$N$2) -> 41241.08
A22: Traifas 2024
A23: Tipificación | B23: Implementaciones | C23: Incidentes – Ordenes de Cambio | D23: Fallida | G23: Tipificación | H23: Actividad sin cambio de datafono | J23: Actividad + adicional cambio de datafono | L23: Visita Fallida
A24: TIPO I | B24: 71384.405 | C24: 62699.688 | D24: 35693.434 | H24: Instalación Pinpad + HUB | I24: Segunda actividad en mismo comercio, misma visita | J24: Instalación Pinpad + HUB | K24: Segunda actividad en mismo comercio, misma visita
A25: TIPO II | B25: 155716.44 | C25: 137802.16 | D25: 117879.85 | G25: Tipo I | H25: 31819.24 | I25: 26222.675 | J25: 51196.466 | K25: 42157.663 | L25: 28948.106
A26: TIPO III | B26: 262099.6 | C26: 262099.6 | D26: 262099.6 | G26: Tipo II | H26: 98014.031 | I26: 26222.675 | J26: 119562.5 | K26: 42157.663 | L26: 94765.63
A27: TIPO IV | B27: 479878.94 | C27: 455882.96 | D27: 370911.67 | G27: Tipo III | H27: 189140.98 | I27: 26222.675 | J27: 200461.6 | K27: 42157.663 | L27: 171492.68
A28: Destino Aéreo | B28: 939603.58 | C28: a partir del 5to servicio | G28: Tipo IV | H28: 461621.6 | I28: 26222.675 | J28: 461621.6 | K28: 42157.663 | L28: 461621.6
G29: * Tipo IV Especial Donde se requiera desplazamiento aéreo o fluvial será facturado el valor de la actividad y adicional el valor de $939,604 por cada 5 actividades de esta tipología
A30: Tarifas para día adicional de actividades:
A31: Tipificación | B31: Día adicional- menos de dos horas | C31: Medio día adicional | D31: Día adicional- más de 4 horas
A32: Tipo I | B32: 71384.405 | C32: 133455.93 | D32: 191225.12 | G32: Actividad | H32: Unidad | I32: Valor Unitario
A33: Tipo II | B33: 133455.93 | C33: 191225.12 | D33: 257740.62 | G33: Gestión telefónica y cierre de incidente de bloqueo | H33: Unidad | I33: 17639.195
A34: Tipo III | B34: 186821.79 | C34: 248892.08 | D34: 306662.51 | G34: Servicio de cierre de incidente de bloqueo | H34: Unidad | I34: 4810.8079
A35: Tipo IV | B35: 186821.79 | C35: 248892.08 | D35: 306662.51
A38: Servicio | B38: Tarifa actividad | D38: VALOR DE LA TERMINAL ADICIONAL | E38: VALOR DE INSTALACIÓN DE BASE EN "Y"
A39: Papelería – Tarifa única | B39: 34010.932 | D39: 20537.366 | E39: 10737.961
A40: Papelería Tipo II - Visita técnica | B40: 64310
A41: Solución telefónica | B41: 39202.548

Sheet RESUMEN LIQUIDACION
B1: Fecha | C1: 46022
A3: FACTURACIÓN ACTIVIDADES REDEBAN CB BANCOLOMBIA Y AVAL
A4: =UPPER("01" & " al " & TEXT(DAY(EOMONTH(C1,0)),"00") & " de " & TEXT(C1,"MMMM") & " de " & YEAR(C1)) -> 01 AL 31 DE DICIEMBRE DE 2025
A6: CONCEPTOS | B6: CANTIDAD | C6: TOTAL
A7: Aperturas Bancolombia | B7: =(COUNTA(APERTURAS_BANCOLOMBIA!A:A)-1) -> 87 | C7: =SUM(APERTURAS_BANCOLOMBIA!$AC$2:$AC$1048576) -> 15991797
A8: Incidentes Bancolombia | B8: =(COUNTA(INCIDENTES_BANCOLOMBIA!A:A)-1) -> 786 | C8: =SUM(INCIDENTES_BANCOLOMBIA!$AF$2:$AF$1048576) -> 130519431
A9: Gestión de Campo Bancolombia | B9: =(COUNTA(OC_BANCOLOMBIA!A:A)-1) -> 258 | C9: =SUM(OC_BANCOLOMBIA!$AF$2:$AF$1048576) -> 47286096
A10: Soporte Papelería Bancolombia | B10: =(COUNTA(PAPELERIA!A:A)-1) -> 1151 | C10: =(SUM(PAPELERIA!$AE$2:$AE$1048576)) -> 51303620
A11: Aperturas Aval | B11: =(COUNTA(APERTURAS_AVAL!A:A)-1) -> 154 | C11: =SUM(APERTURAS_AVAL!$AB$2:$AB$1048576) -> 26836633
A12: Incidentes Aval | B12: =(COUNTA(INCIDENTES_AVAL!A:A)-1) -> 309 | C12: =SUM(INCIDENTES_AVAL!$AD$2:$AD$1048576) -> 37489862
A13: Gestión de Campo Aval | B13: =(COUNTA(OC_AVAL!A:A)-1) -> 117 | C13: =SUM(OC_AVAL!$AF$2:$AF$1048576) -> 17756347
A14: Aperturas BBVA | B14: =(COUNTA(APERTURAS_BBVA!A:A)-1) -> 16 | C14: =SUM(APERTURAS_BBVA!$AC$2:$AC$1048576) -> 1437352
A15: Gestión de Campo BBVA | B15: 0 | C15: =SUM(OC_BBVA!$AC$2:$AC$1048576) -> 0
A16: Incidentes BBVA | B16: 0 | C16: =SUM(INCIDENTES_BBVA!$AB$2:$AB$1048576) -> 0
A17: SUBTOTAL | C17: =SUM(C7:C16) -> 328621138
A18: Iva | C18: =C17*0.19 -> 62438016
A19: TOTAL | C19: =SUM(C17:C18) -> 3.9105915e+08

Sheet APERTURAS_BANCOLOMBIA
A1: CIUDAD SEDE | B1: ZONA | C1: CENTRO DE COSTOS LINEACOM | D1: CODIGO DANE | E1: TA/CODIGO ACTIVIDAD | F1: CODIGO CB | G1: ACTIVIDAD | H1: TIPO DE APERTURA | I1: DEPARTAMENTO | J1: CIUDAD | K1: NOMBRE DEL CB | L1: RED | M1: FO | N1: FECHA LISTA | O1: FECHA ULTIMA ACTUALIZACION | P1: FORMATO | Q1: CADENA | R1: ESTADO | S1: OBSERVACIONES CLIENTE | T1: FORMA DE ATENCION | U1: TERMINAL(ES) | V1: TIPIFICACION | W1: TIPO DE TRAYECTO | X1: NOMBRE DEL TECNICO | Y1: DIAS DE VISITA | Z1: DIA ADICIONAL | AA1: VALOR DIAS ACTIVIDAD FACTURABLES | AB1: VALOR DIAS ACOMPAÑAMIENTO FACTURABLES | AC1: VALOR TOTAL
A2: CUCUTA | B2: SANTANDERES | C2: 0004-0008 | D2: 54810 | E2: TA-25-1330512 | F2: 3007050974 | G2: APERTURA | H2: DATAFONO ADICIONAL - ALIANZA | I2: NORTE DE SANTANDER | J2: TIBU | K2: PTM TIBU VARIEDADES DUQUE ER | L2: REDEBAN | M2: FO-25-1884057 | N2: 45988.333 | O2: 46009.444 | P2: AGREGADOR | Q2: COMCARD - PTM | R2: EJECUTADO | S2: 26/11/2025 26-11 PROGRAMACION REALIZADA POR LA ALIANZA| INSTALACIÓN PROGRAMADA PARA EL 2025-12-04 | 04/12/2025 SE CONTACTA TELEFÓNICAMENTE AL COMERCIO, SE LE INFORMA AL SEÑOR JAVIER DUQUE QUE POR CUESTIONES DE ORDEN PÚBLICO NO ES POSIBLE DESPLAZARSE A LA ZONA PARA REALIZAR LA INSTALACIÓN Y POR LO TANTO SE REQUIERE QUE SE ACERCA A LA BODEGA EN LA CIUDAD DE CÚCUTA. EL SEÑOR JAVIER DUQUE INFORMA QUE EL DÍA DE MAÑANA 05/12 INDICARÁ VÍA WHATSAPP LA FECHA Y LOS DATOS DE LA PERSONA QUE SERÁ LA ENCARGADA DE RECIBIR LA INSTALACIÓN. 3214439731 | 10/12/2025 SE INTENTA CONTACTAR TELEFÓNICAMENTE AL CLIENTE PARA CONFIRMAR DATOS DE LA PERSONA QUE VA A RECIBIR EL EQUIPO EN BODEGA CÚCUTA PERO LA LÍNEA SE ENCUENTRA SIN SEÑAL, SE INTENTA CONTACTAR VÍA WHATSAPP PERO NO LE LLEGAN LOS MENSAJES AL CLIENTE. 3214439731 | 18/12/2025 POR MOTIVO DE ORDEN PÚBLICO, SE REALIZA ENTREGA DE DATAFONO ADICIONAL EN BODEGA CÚCUTA, SE INSTALA ÚLTIMA VERSIÓN, SE CREAN USUARIOS OK SE REALIZAN PRUEBAS Y CIERRES OK | T2: VISITA TECNICA | U2: OB004864 | V2: TIPO V | W2: TERRESTRE | X2: PACHECO BUITRAGO JAVIER ALONSO | Y2: 1 | Z2: 0 | AA2: 504833 | AB2: 196537 | AC2: 504833
A3: PASTO | B3: SUROCCIDENTE Y EJE CAFETERO | C3: 0004-0003 | D3: 86865 | E3: TA-25-1330515 | F3: 3007082070 | G3: APERTURA | H3: CB CRECIMIENTO ALIANZA - OTRAS LISTAS | I3: PUTUMAYO | J3: VALLE DEL GUAMUEZ | K3: DISTRICOL ESTILO REAL | L3: REDEBAN | M3: FO-25-1884068 | N3: 45988.333 | O3: 45993.773 | P3: AGREGADOR | Q3: DISTRICOL | R3: EJECUTADO | S3: 26/11/2025 26-11 PROGRAMACION REALIZADA POR LA ALIANZA| INSTALACIÓN PROGRAMADA PARA EL 2025-11-28 | 30/11/2025 SE REALIZARA DESPLAZAMIENTO EL DIA 1 DE DICIEMBRE YA QUE POR CIERRE DE VIA HACIA PUTUMAYO NO SE HA PODIDO REALIZAR | 22/12/2025 SE LLEGA A SITIO A REALIZAR INSTALACIÓN DE CORRESPONSAL BANCARIO SE CONFIGURA EQUIPO SE INICIALIZA SE REALIZA PRUEBAS DE FUNCIONAMIENTO FALLIDAS EQUIPO EN RECHAZO GENERAL SE REALIZA CAMBIO DE EQUIPO FALLA PERSISTE SE ESCALA A RBM MAIRA ALEJANDRO AUTORIZA CERRAR ORDEN POR POSIBLE BLOQUEO POR PARTE DE LA ENTIDAD SE LE INFORMA A CLIENTE QUE SE ESTÁ ALA ESPERA RESPUESTA PARA QUE PUEDA EMPEZAR A OPERAR INSTALACION DE PUBLICIDAD OK CAPACITACIÓN OK | T3: VISITA TECNICA | U3: OB004867 | V3: TIPO IV | W3: TERRESTRE | X3: BRAVO MADROÑERO OSCAR ESTEBAN | Y3: 1 | Z3: 0 | AA3: 504833 | AB3: 196537 | AC3: 504833
A4: VALLEDUPAR | B4: COSTA | C4: 0004-0001 | D4: 44279 | E4: TA-25-1341465 | F4: 3007028414 | G4: APERTURA | H4: DATAFONO ADICIONAL - ALIANZA | I4: LA GUAJIRA | J4: FONSECA | K4: DISTRICOL SEGUROS M M | L4: REDEBAN | M4: FO-25-1911533 | N4: 45993.333 | O4: 45993.99 | P4: AGREGADOR | Q4: DISTRICOL | R4: EJECUTADO | S4: 01/12/2025 01-12 PROGRAMACION REALIZADA POR LA ALIANZA| INSTALACIÓN PROGRAMADA PARA EL 2025-12-02 | 02/12/2025 SE REALIZA INSTALACIÓN DE DATAFONO ADICIONAL, SE INSTALA DATAFONO, LECTOR, SE ENTREGAN 40 ROLLOS, NO SE INSTALA PUBLICIDAD YA QUE EL CB CUENTA CON ELLA Y NO APLICA POR SER DATAFONO ADICIONAL, SE REALIZAN PRUEBAS DEJANDO SERVICIO FUNCIONAL AL 100 % | T4: VISITA TECNICA | U4: AE007353 | V4: TIPO II | W4: TERRESTRE | X4: MONTES DIAZ JOHN FRED | Y4: 1 | Z4: 0 | AA4: 163814 | AB4: 140396 | AC4: 163814
A5: VALLEDUPAR | B5: COSTA | C5: 0004-0001 | D5: 44378 | E5: TA-25-1341466 | F5: 3007057635 | G5: APERTURA | H5: DATAFONO ADICIONAL - ALIANZA | I5: LA GUAJIRA | J5: HATONUEVO | K5: MULTIPAGAS HATONUEVO | L5: REDEBAN | M5: FO-25-1921921 | FO-25-1911535 | N5: 45993.333 | O5: 45997.455 | P5: ROBUSTO | Q5: MULTIPAGAS | R5: EJECUTADO | EJECUTADO/CANCELADO | S5: [FO-25-1921921] 09/12/2025 SE REALIZA INSTALACIÓN DE DATAFONO ADICIONAL, SE INSTALA DATAFONO, LECTOR, PINPAD Y MAGICBOX 2600, SE ENTREGAN 40 ROLLOS, SE BRINDA CAPACITACIÓN, SE REALIZAN PRUEBAS DE TRANSACCIONES, DEJANDO SERVICIO FUNCIONAL AL 100 % || [FO-25-1911535] 01/12/2025 01-12 SE REALIZA LLAMADA AL CLIENTE, SE HABLA CON LA SRA TATIANA TOLOZA SE VALIDA DIRECCIÓN OK, CANAL OK, DISPONIBILIDAD TOTAL, LLAMAR EL DÍA LA INSTALACIÓN PARA CONFIRMAR VISITA | 03/12/2025 SE LLEGA A SITIO, COMERCIO INDICA QUE PARA PODER INGRESAR SE NECESITA LA AUTORIZACIÓN Y VALIDACION DE BANCOLOMBIA, PROCEDEN A LLAMAR A LA LINEA PERO ESTA NO RESPONDEN, SE INTENTA POR OTROS MEDIOS COMO WPP Y TAMPOCO CONTESTAN, SE LE INDICA AL JEFE DEL MULTIPAGAS QUE VAMOS A REALIZAR UNA INSTALACIÓN DE UN DATAFONO ADICIONAL Y ESTE INDICA QUE SIN LA AUTORIZACIÓN DEL BANCO, NO ME PERMITEN EL INGRESO, SE INTENTA COMUNICAR CON LA LINEA DE BANCOLOMBIA EN UN LAPSO DE TIEMPO DE UNA HORA Y MEDIA, Y NUNCA CONTESTARON, ME COMUNICO CON EL COORDINADOR JOSE HERNÁNDEZ Y ESTE MANIFIESTA QUE SE TIENE QUE REAGENDAR LA VISITA Y QUE ME RETIRE DEL SITIO | T5: VISITA TECNICA | U5: AE007354 | V5: TIPO III | W5: TERRESTRE | X5: MONTES DIAZ JOHN FRED | Y5: 1 | Z5: 0 | AA5: 275729 | AB5: 196537 | AC5: 275729
A6: SANTA MARTA | B6: COSTA | C6: 0004-0001 | D6: 47555 | E6: TA-25-1341467 | F6: 3007056043 | G6: APERTURA | H6: DATAFONO ADICIONAL - ALIANZA | I6: MAGDALENA | J6: PLATO | K6: REVAL PLATO | L6: REDEBAN | M6: FO-25-1911541 | N6: 45993.333 | O6: 45994.629 | P6: ROBUSTO | Q6: REVAL | R6: EJECUTADO | S6: 01/12/2025 01-12 SE REALIZA LLAMADA AL CLIENTE, SE HABLA CON EL SR RAFAEL ROYS SE VALIDA DIRECCIÓN OK, CANAL OK, DISPONIBILIDAD TOTAL, LLAMAR EL DÍA LA INSTALACIÓN PARA CONFIRMAR VISITA | 03/12/2025 SE VISITA SITIO SE VERIFICA INFORMACIÓN SE REALIZA INSTALACIÓN DE DATÁFONO ADICIONAL CON SU RESPECTIVO ESCANEAR FUENTE PODER, CABLE DE RED, MAGIC BOX, BASE SOPORTE, LECTURA DE CHIP OK, TECLADO OK, IMPRESIÓN. PRUEBAS TRX EXITOSAS. | T6: VISITA TECNICA | U6: 9CQZZ890 | V6: TIPO IV | W6: TERRESTRE | X6: SANTOS GUZMAN CHRISTIAN FELIPE | Y6: 1 | Z6: 0 | AA6: 504833 | AB6: 196537 | AC6: 504833
A7: MANIZALES | B7: SUROCCIDENTE Y EJE CAFETERO | C7: 0004-0002 | D7: 17001 | E7: TA-25-1382428 | F7: 3007082464 | G7: APERTURA | H7: CB CRECIMIENTO ALIANZA - NUEVO | I7: CALDAS | J7: MANIZALES | K7: DISTRICOL DROGUERIA GENERIK | L7: REDEBAN | M7: FO-25-1949034 | N7: 46001.333 | O7: 46002.708 | R7: EJECUTADO | S7: 09/12/2025 09-12 PROGRAMACION REALIZADA POR LA ALIANZA| INSTALACIÓN PROGRAMADA PARA EL 2025-12-11 | 11/12/2025 SE REALIZA INSTALACIÓN DE DATAFONO Y ACCESORIOS BASE LECTOR 40 ROLLOS Y PUBLICIDAD SE CAPACITA AL COMERCIO SE CREAN USUARIOS SE HACEN PRUEBAS DE CONSULTA DE SALDO SOLAMENTE YA QUE USUARIO NO CUENTA CON HERRAMIENTAS PARA REALIZAR RETIRO RECAUDO NI CONSIGNACIÓN SERVICIO OK | T7: VISITA TECNICA | U7: DA006233 | V7: TIPO I | W7: TERRESTRE | X7: AGUIRRE HENAO RAUL EDUARDO | Y7: 1 | Z7: 0 | AA7: 75096 | AB7: 75096 | AC7: 75096
A8: VALLEDUPAR | B8: COSTA | C8: 0004-0001 | D8: 20011 | E8: TA-25-1382429 | F8: 3007082460 | G8: APERTURA | H8: CB CRECIMIENTO ALIANZA - NUEVO | I8: CESAR | J8: AGUACHICA | K8: DISTRIOL PAPELERIA PERF ZAMI | L8: REDEBAN | M8: FO-25-1949036 | N8: 46001.333 | O8: 46002.521 | R8: EJECUTADO | S8: 09/12/2025 09-12 PROGRAMACION REALIZADA POR LA ALIANZA| INSTALACIÓN PROGRAMADA PARA EL 2025-12-11 | 11/12/2025 SE REALIZA APERTURA DE CB, SE INSTALA DATAFONO, LECTOR Y PINPAD, YA QUE CLIENTE CONTABA CON VIDRIO DE SEGURIDAD, SE INSTALA PUBLICIDAD, SE ENTREGAN 40 ROLLOS, SE BRINDA CAPACITACIÓN, SE REALIZAN PRUEBAS DE TRANSACCIONES, DEJANDO SERVICIO FUNCIONAL AL 100 % | T8: VISITA TECNICA | U8: DA006234 | V8: TIPO IV | W8: TERRESTRE | X8: MONTES DIAZ JOHN FRED | Y8: 1 | Z8: 0 | AA8: 504833 | AB8: 196537 | AC8: 504833
A9: PASTO | B9: SUROCCIDENTE Y EJE CAFETERO | C9: 0004-0003 | D9: 52001 | E9: TA-25-1382430 | F9: 3007082466 | G9: APERTURA | H9: CB CRECIMIENTO ALIANZA - NUEVO | I9: NARIÑO | J9: PASTO | K9: DISTRICOL CENTROMARKET | L9: REDEBAN | M9: FO-25-1949039 | N9: 46001.333 | O9: 46002.622 | R9: EJECUTADO | S9: 09/12/2025 09-12 PROGRAMACION REALIZADA POR LA ALIANZA| INSTALACIÓN PROGRAMADA PARA EL 2025-12-11 | 11/12/2025 SE REALIZÓ LA INSTALACIÓN DE EQUIPOS PUBLICIDAD Y ACCESORIOS PARA APERTURA CB BANCOLOMBIA SE DIO CAPACITACIÓN MANEJO DE DATÁFONO CB Y SOMOS BANCOLOMBIA SE EJECUTAN PRUEBAS TX EXITOSAS QUEDA OPERATIVO. | T9: VISITA TECNICA | U9: DA006235 | V9: TIPO I | W9: TERRESTRE | X9: REMICIO AMADO JOHN HEBER | Y9: 1 | Z9: 0 | AA9: 75096 | AB9: 75096 | AC9: 75096
A10: MEDELLIN | B10: NOROCCIDENTE | C10: 0004-0005 | D10: 5628 | E10: TA-25-1382432 | F10: 3007067237 | G10: APERTURA | H10: DATAFONO ADICIONAL - ALIANZA | I10: ANTIOQUIA | J10: SABANALARGA | K10: PTM SABANALARGA TU DROGUERIA | L10: REDEBAN | M10: FO-25-1949046 | N10: 46001.333 | O10: 46002.701 | P10: AGREGADOR | Q10: COMCARD - PTM | R10: EJECUTADO | S10: 09/12/2025 09-12 PROGRAMACION REALIZADA POR LA ALIANZA| INSTALACIÓN PROGRAMADA PARA EL 2025-12-11 | 11/12/2025 SE REALIZA INSTALACIÓN DE DATAFONO ADICIONAL OK | T10: VISITA TECNICA | U10: DA006237 | V10: TIPO III | W10: TERRESTRE | X10: QUINTERO SANCHEZ JUAN SEBASTIAN | Y10: 1 | Z10: 0 | AA10: 275729 | AB10: 196537 | AC10: 275729
A11: CUCUTA | B11: SANTANDERES | C11: 0004-0008 | D11: 54001 | E11: TA-25-1382439 | F11: 3007072968 | G11: APERTURA | H11: DATAFONO ADICIONAL - ALIANZA | I11: NORTE DE SANTANDER | J11: CUCUTA | K11: DISTRICOL DE TODITO YAYUYA | L11: REDEBAN | M11: FO-25-1949049 | N11: 46001.333 | O11: 46001.986 | P11: AGREGADOR | Q11: DISTRICOL | R11: EJECUTADO | S11: 09/12/2025 09-12 PROGRAMACION REALIZADA POR LA ALIANZA| INSTALACIÓN PROGRAMADA PARA EL 2025-12-10 | 10/12/2025 SE INSTALA DATAFONO LECTOR BASE Y ACCESORIOS SE DEJA NUEVA VERSIÓN CIERRES Y PRUEBAS OK | T11: VISITA TECNICA | U11: DA006238 | V11: TIPO I | W11: TERRESTRE | X11: DURAN ACOSTA FRANK YONNY | Y11: 1 | Z11: 0 | AA11: 75096 | AB11: 75096 | AC11: 75096
A12: MEDELLIN | B12: NOROCCIDENTE | C12: 0004-0005 | D12: 5001 | E12: TA-25-1393484 | F12: 3007082483 | G12: APERTURA | H12: CB CRECIMIENTO ALIANZA - NUEVO | I12: ANTIOQUIA | J12: MEDELLIN | K12: PTM MEDELLIN PLANET SHOPPING | L12: REDEBAN | M12: FO-25-1959628 | N12: 46003.333 | O12: 46003.681 | P12: AGREGADOR | Q12: COMCARD - PTM | R12: EJECUTADO | S12: 11/12/2025 11-12 PROGRAMACION REALIZADA POR LA ALIANZA| INSTALACIÓN PROGRAMADA PARA EL 2025-12-12 | 12/12/2025 INSTALACIÓN DE CB MIXTO OK PUBLICIDAD Y CAPACITACIÓN OK PRUEBAS SOLO CONSULTA DE SALDO NO HAY PARA MÁS CUBRE CLAVE OK NO TELECARGA | T12: VISITA TECNICA | U12: DA007308 | V12: TIPO I | W12: TERRESTRE | X12: PAREJA ECHAVARRIA JHON DAVID | Y12: 1 | Z12: 0 | AA12: 75096 | AB12: 75096 | AC12: 75096
A13: MEDELLIN | B13: NOROCCIDENTE | C13: 0004-0005 | D13: 5001 | E13: TA-25-1393485 | F13: 3007082484 | G13: APERTURA | H13: CB CRECIMIENTO ALIANZA - NUEVO | I13: ANTIOQUIA | J13: MEDELLIN | K13: PTM MEDELLIN SURTIBELLEZA LOS | L13: REDEBAN | M13: FO-25-1959631 | N13: 46003.333 | O13: 46003.581 | P13: AGREGADOR | Q13: COMCARD - PTM | R13: EJECUTADO | S13: 11/12/2025 11-12 PROGRAMACION REALIZADA POR LA ALIANZA| INSTALACIÓN PROGRAMADA PARA EL 2025-12-12 | 15/12/2025 INSTALACIÓN DE CB MIXTO OK PUBLICIDAD Y CAPACITACIÓN OK PRUEBAS SOLO CONSULTA SALDO NO HAY MAS CUBRE CLAVE OK NO TELECARGA | T13: VISITA TECNICA | U13: DA007309 | V13: TIPO I | W13: TERRESTRE | X13: PAREJA ECHAVARRIA JHON DAVID | Y13: 1 | Z13: 0 | AA13: 75096 | AB13: 75096 | AC13: 75096
A14: MEDELLIN | B14: NOROCCIDENTE | C14: 0004-0005 | D14: 5001 | E14: TA-25-1393486 | F14: 3007082485 | G14: APERTURA | H14: CB CRECIMIENTO ALIANZA - NUEVO | I14: ANTIOQUIA | J14: MEDELLIN | K14: PTM MEDELLIN MINIMERCADO EL MA | L14: REDEBAN | M14: FO-25-1959633 | N14: 46003.333 | O14: 46003.626 | P14: AGREGADOR | Q14: COMCARD - PTM | R14: EJECUTADO | S14: 11/12/2025 11-12 PROGRAMACION REALIZADA POR LA ALIANZA| INSTALACIÓN PROGRAMADA PARA EL 2025-12-12 | 12/12/2025 SE HACE APERTURA DE CB EXITOSAMENTE | T14: VISITA TECNICA | U14: DA007310 | V14: TIPO I | W14: TERRESTRE | X14: RUA ALVAREZ RICHARD ANDRES | Y14: 1 | Z14: 0 | AA14: 75096 | AB14: 75096 | AC14: 75096
A15: TUNJA | B15: SANTANDERES | C15: 0004-0008 | D15: 15516 | E15: TA-25-1393487 | F15: 3007082475 | G15: APERTURA | H15: CB CRECIMIENTO ALIANZA - NUEVO | I15: BOYACA | J15: PAIPA | K15: PTM PAIPA FARMA DIAZ MAS | L15: REDEBAN | M15: FO-25-1959638 | N15: 46003.333 | O15: 46006.638 | P15: AGREGADOR | Q15: COMCARD - PTM | R15: EJECUTADO | S15: 11/12/2025 11-12 PROGRAMACION REALIZADA POR LA ALIANZA| INSTALACIÓN PROGRAMADA PARA EL 2025-12-15 | 15/12/2025 SE REALIZA VISITA AL COMERCIO, SE INSTALAN EQUIPOS Y ACCESORIOS, SE CAPACITA AL CLIENTE Y SE HACEN PRUEBAS OK. | T15: VISITA TECNICA | U15: DA007311 | V15: TIPO II | W15: TERRESTRE | X15: SOLER HOYOS CRISTIAN LEONARDO | Y15: 1 | Z15: 0 | AA15: 163814 | AB15: 140396 | AC15: 163814
A16: BOGOTA | B16: CENTRO | C16: 0004-0004 | D16: 25269 | E16: TA-25-1393489 | F16: 3007082472 | G16: APERTURA | H16: CB CRECIMIENTO ALIANZA - NUEVO | I16: CUNDINAMARCA | J16: FACATATIVA | K16: PTM FACATATIVA AUTO SERVICIO E | L16: REDEBAN | M16: FO-25-1959649 | N16: 46003.333 | O16: 46003.578 | P16: AGREGADOR | Q16: COMCARD - PTM | R16: EJECUTADO | S16: 11/12/2025 11-12 PROGRAMACION REALIZADA POR LA ALIANZA| INSTALACIÓN PROGRAMADA PARA EL 2025-12-12 | 12/12/2025 APERTURA BANCOLOMBIA OK CAPACITACIÓN OK PUBLICIDAD OK SERVICIO OPERATIVO SE REALIZA PRUEBAS CON INFORMACIÓN QUE NOS SUMINISTRO EL CLIENTE | T16: VISITA TECNICA | U16: DA007314 - DA007184 | V16: TIPO II | W16: TERRESTRE | X16: HERNANDEZ NARANJO OSCAR EDUARDO | Y16: 1 | Z16: 0 | AA16: 163814 | AB16: 140396 | AC16: 163814
A17: BOGOTA | B17: CENTRO | C17: 0004-0004 | D17: 25473 | E17: TA-25-1393490 | F17: 3007082474 | G17: APERTURA | H17: CB CRECIMIENTO ALIANZA - NUEVO | I17: CUNDINAMARCA | J17: MOSQUERA | K17: PTM MOSQUERA PAPELERIA LISETTE | L17: REDEBAN | M17: FO-25-1959655 | N17: 46003.333 | O17: 46003.516 | P17: AGREGADOR | Q17: COMCARD - PTM | R17: EJECUTADO | S17: 11/12/2025 11-12 PROGRAMACION REALIZADA POR LA ALIANZA| INSTALACIÓN PROGRAMADA PARA EL 2025-12-12 | 12/12/2025 SE REALIZA INSTALACIÓN DE DATAFONO LECTOR BASE PUBLICIDAD COMPLETA SE CAPACITA COMERCIO SE REALIZAN PRUEBAS OK NO SE TIENE TARJETA DE BANCOLOMBIA | T17: VISITA TECNICA | U17: DA007315 | V17: TIPO I | W17: TERRESTRE | X17: SOTO LONDOÑO FREDY ALEXANDER | Y17: 1 | Z17: 0 | AA17: 75096 | AB17: 75096 | AC17: 75096
A18: BOGOTA | B18: CENTRO | C18: 0004-0004 | D18: 25817 | E18: TA-25-1393492 | F18: 3007082480 | G18: APERTURA | H18: CB CRECIMIENTO ALIANZA - NUEVO | I18: CUNDINAMARCA | J18: TOCANCIPA | K18: PTM TOCANCIPA LOKYAN DIVERTPAR | L18: REDEBAN | M18: FO-25-1959661 | N18: 46003.333 | O18: 46003.572 | P18: AGREGADOR | Q18: COMCARD - PTM | R18: EJECUTADO | S18: 11/12/2025 11-12 PROGRAMACION REALIZADA POR LA ALIANZA| INSTALACIÓN PROGRAMADA PARA EL 2025-12-12 | 12/12/2025 INSTALACIÓN BANCOLOMBIA CON PUBLICIDAD DATAFONO LECTORA ROLLOS BASE FUENTE DATOS SERVICIO OPERATIVO PRUEBAS OK CON UNA CONSULTA DE SALDO NO HAY VINO HACER CONSIGNACION O RETIRO TRNA RBM SE INSTALA CUBRE TECLADO | T18: VISITA TECNICA | U18: DA007316 | V18: TIPO II | W18: TERRESTRE | X18: BUSTOS MORA DIEGO MANUEL | Y18: 1 | Z18: 0 | AA18: 163814 | AB18: 140396 | AC18: 163814
A19: MEDELLIN | B19: NOROCCIDENTE | C19: 0004-0005 | D19: 27361 | E19: TA-25-1393494 | F19: 3007082473 | G19: APERTURA | H19: CB CRECIMIENTO ALIANZA - NUEVO | I19: CHOCO | J19: ISTMINA | K19: PTM ISTMINA TIENDA Y VARIEDADE | L19: REDEBAN | M19: FO-25-1959664 | N19: 46003.333 | O19: 46009.711 | P19: AGREGADOR | Q19: COMCARD - PTM | R19: EJECUTADO | S19: 11/12/2025 11-12 PROGRAMACION REALIZADA POR LA ALIANZA| INSTALACIÓN PROGRAMADA PARA EL 2025-12-18 | 19/12/2025 SE REALIZA INSTALACIÓN, CAPACITACION Y PRUEBAS CON EL CLIENTE YBEL CB QUEDA OPERATIVO | T19: VISITA TECNICA | U19: DA007188 - DA007317 | V19: TIPO V | W19: AEREO | X19: ROBLEDO DIAZ ANDRES FELIPE | Y19: 1 | Z19: 0 | AA19: 988463 | AB19: 196537 | AC19: 988463
A20: VILLAVICENCIO | B20: ORIENTE | C20: 0004-0007 | D20: 50573 | E20: TA-25-1393495 | F20: 3007082479 | G20: APERTURA | H20: CB CRECIMIENTO ALIANZA - NUEVO | I20: META | J20: PUERTO LOPEZ | K20: PTM META VARIEDADES JOBAP | L20: REDEBAN | M20: FO-25-1959667 | N20: 46003.333 | O20: 46006.558 | P20: AGREGADOR | Q20: COMCARD - PTM | R20: EJECUTADO | S20: 11/12/2025 11-12 PROGRAMACION REALIZADA POR LA ALIANZA| INSTALACIÓN PROGRAMADA PARA EL 2025-12-15 | 17/12/2025 SE REALIZA INSTALACION CORRESPONSAL BANCOLOMBIA, SE REALIZAN PRUEBAS Y CAPACITACIÓN TODO OK | T20: VISITA TECNICA | U20: DA007318 - DA007189 | V20: TIPO II | W20: TERRESTRE | X20: PEDREROS CONTRERAS MICHAEL STEVENS | Y20: 1 | Z20: 0 | AA20: 163814 | AB20: 140396 | AC20: 163814
A21: CALI | B21: SUROCCIDENTE | C21: 0004-0003 | D21: 76520 | E21: TA-25-1393496 | F21: 3007082476 | G21: APERTURA | H21: CB CRECIMIENTO ALIANZA - NUEVO | I21: VALLE DEL CAUCA | J21: PALMIRA | K21: PTM PALMIRA TIENDA Y VARIEDADE | L21: REDEBAN | M21: FO-25-1959673 | N21: 46003.333 | O21: 46006.28 | P21: AGREGADOR | Q21: COMCARD - PTM | R21: EJECUTADO | S21: 11/12/2025 11-12 PROGRAMACION REALIZADA POR LA ALIANZA| INSTALACIÓN PROGRAMADA PARA EL 2025-12-15 | 15/12/2025 SE REALIZÓ LA INSTALACIÓN DE EL CORRESPONSAL BANCOLOMBIA MIXTO, DATÁFONO, LECTOR, MAGIC BOX 2600 BASE SOPORTE DE EL DATÁFONO Y SE IMPLEMENTARON LOS ROLLOS Y LA PUBLICIDAD DE BANCOLOMBIA,SE BRINDA CAPACITACIÓN Y SE REALIZARON LAS PRUEBAS CON EL CLIENTE DEJANDO EL SERVICIO OPERANDO SIN FALLAS Y SIN NOVEDAD. | T21: VISITA TECNICA | U21: DA007320 -DA007190 | V21: TIPO I | W21: TERRESTRE | X21: SANCHEZ URREGO ROBINSON DAVID | Y21: 1 | Z21: 0 | AA21: 75096 | AB21: 75096 | AC21: 75096
... A42: CALI | B42: SUROCCIDENTE | C42: 0004-0003 | D42: 76001 | E42: TA-25-1429969 | F42: 3007082500 | G42: APERTURA | H42: CB CRECIMIENTO ALIANZA - NUEVO | I42: VALLE DEL CAUCA | J42: CALI | K42: PTM CALI MISCELANEA Y PAPELERI | L42: REDEBAN | M42: FO-25-1990033 | N42: 46009.333 | O42: 46009.59 | P42: AGREGADOR | Q42: COMCARD - PTM | R42: EJECUTADO | S42: 17/12/2025 17-12 PROGRAMACION REALIZADA POR LA ALIANZA| INSTALACIÓN PROGRAMADA PARA EL 2025-12-18 | 18/12/2025 SE LLAMA AL CLIENTE, SE VALIDA LA VISITA DE LA INSTALACION, DIRECCION Y DISPONIBILIDAD, SE VISITA EL COMERCIO, SE INSTALA DATAFONO, LECTORA, ACCESORIOS EN APERTURA CB BANCOLOMBIA MIXTO, INSTALÓ PUBLICIDAD, SE CAPACITA, PRUEBAS OK, TELECARGA TRNA | T42: VISITA TECNICA | U42: FB007698 | V42: TIPO I | W42: TERRESTRE | X42: HERRERA MONAR GEOVANNY | Y42: 1 | Z42: 0 | AA42: 75096 | AB42: 75096 | AC42: 75096
A43: CALI | B43: SUROCCIDENTE | C43: 0004-0003 | D43: 76834 | E43: TA-25-1429972 | F43: 3007082513 | G43: APERTURA | H43: CB CRECIMIENTO ALIANZA - NUEVO | I43: VALLE DEL CAUCA | J43: TULUA | K43: PTM TULUA CORREO Y DOMICILIOS | L43: REDEBAN | M43: FO-25-1999658 | FO-25-1990037 | N43: 46009.333 | O43: 46010.438 | P43: AGREGADOR | Q43: COMCARD - PTM | R43: EJECUTADO | S43: [FO-25-1999658] 19/12/2025 SE VISITA CORRESPONSAL Y SE PROCEDE A REALIZA INSTALACIÓN DE PIN PAD. TRANSACCIONES DE PRUEBA EXITOSAS || [FO-25-1990037] 17/12/2025 17-12 PROGRAMACION REALIZADA POR LA ALIANZA| INSTALACIÓN PROGRAMADA PARA EL 2025-12-18 | 18/12/2025 SE VISITA ESTABLECIMIENTO, SE REALIZA INSTALACIÓN CORRESPONSAL BANCOLOMBIA. TRANSACCIONES DE PRUEBA EXITOSAS SOLO CON LAS QUE DISPONE EL CLIENTE Y SE REALIZARON PRUEBAS CON TARJETA DE OTRO BANCO PARA SIMULAR PROCESO . SE INSTALA PUBLICIDAD COMPLETA Y SE CAPACITA. | T43: VISITA TECNICA | V43: TIPO II | W43: TERRESTRE | X43: BOLAÑOS TABORDA JORGE ENRIQUE | Y43: 2 | Z43: 0 | AA43: 327628 | AB43: 140396 | AC43: 327628
A44: YOPAL | B44: ORIENTE | C44: 0004-0007 | D44: 85001 | E44: TA-25-1429974 | F44: 3007082515 | G44: APERTURA | H44: CB CRECIMIENTO ALIANZA - NUEVO | I44: CASANARE | J44: YOPAL | K44: DISTRICOL MISCELANEA LAVADERO | L44: REDEBAN | M44: FO-25-1990041 | N44: 46009.333 | O44: 46009.7 | P44: AGREGADOR | Q44: DISTRICOL | R44: EJECUTADO | S44: 17/12/2025 17-12 PROGRAMACION REALIZADA POR LA ALIANZA| INSTALACIÓN PROGRAMADA PARA EL 2025-12-18 | 18/12/2025 SE VISITA COMERCIO, SE INSTALA DATÁFONO LECTOR BASE Y CUBRE TECLADO. PRUEBAS OK. OPERATIVO EL SERVICIO. SOMOS BANCOLOMBIA OK. SE CAPACITA CLIENTE. NO SE REALIZA PRUEBA DE TRANSFERENCIA NO SE CUENTA CON TARJETA | T44: VISITA TECNICA | U44: FB007700 | V44: TIPO I | W44: TERRESTRE | X44: BERNAL ELAICA EDGAR ALEXIS | Y44: 1 | Z44: 0 | AA44: 75096 | AB44: 75096 | AC44: 75096
A45: YOPAL | B45: ORIENTE | C45: 0004-0007 | D45: 85001 | E45: TA-25-1429976 | F45: 3007082516 | G45: APERTURA | H45: CB CRECIMIENTO ALIANZA - NUEVO | I45: CASANARE | J45: YOPAL | K45: DISTRICOL CASFARMA YOPAL | L45: REDEBAN | M45: FO-25-1990045 | N45: 46009.333 | O45: 46010.604 | P45: AGREGADOR | Q45: DISTRICOL | R45: EJECUTADO | S45: 17/12/2025 17-12 PROGRAMACION REALIZADA POR LA ALIANZA| INSTALACIÓN PROGRAMADA PARA EL 2025-12-19 | 20/12/2025 SE VISITA COMERCIO, SE INSTALA DATÁFONO LECTOR BASE Y CUBRE TECLADO. PRUEBAS OK. OPERATIVO EL SERVICIO. SE CAPACITA CLIENTE SOMOS BANCOLOMBIA OK. NO SE REALIZA PRUEBA DE TRANSFERENCIA NO SE CUENTA CON TARJETA | T45: VISITA TECNICA | U45: FB007701 | V45: TIPO I | W45: TERRESTRE | X45: BERNAL ELAICA EDGAR ALEXIS | Y45: 1 | Z45: 0 | AA45: 75096 | AB45: 75096 | AC45: 75096
A46: BOGOTA | B46: CENTRO | C46: 0004-0004 | D46: 11001 | E46: TA-25-1429979 | F46: 3007082498 | G46: APERTURA | H46: CB CRECIMIENTO ALIANZA - NUEVO | I46: CUNDINAMARCA | J46: BOGOTA | K46: PTM BOGOTA MTG PRINCIPAL | L46: REDEBAN | M46: FO-25-1990054 | N46: 46009.333 | O46: 46010.503 | P46: AGREGADOR | Q46: COMCARD - PTM | R46: EJECUTADO | S46: 17/12/2025 17-12 PROGRAMACION REALIZADA POR LA ALIANZA| INSTALACIÓN PROGRAMADA PARA EL 2025-12-19 | 26/12/2025 SE REALIZA APERTURA DE CORRESPONSAL BANCOLOMBIA, SE INSTALA PUBLICIDAD, EQUIPOS . SE REALIZA CAPACITACIÓN AL RESPONSABLE DEL CB Y SE ENTREGAN LOS ROLLOS PARA EL PUNTO | T46: VISITA TECNICA | U46: FB007702 | V46: TIPO I | W46: TERRESTRE | X46: ALARCON AREVALO JOHAN STIVEN | Y46: 1 | Z46: 0 | AA46: 75096 | AB46: 75096 | AC46: 75096
A47: BOGOTA | B47: CENTRO | C47: 0004-0004 | D47: 11001 | E47: TA-25-1429983 | F47: 3007082496 | G47: APERTURA | H47: CB CRECIMIENTO ALIANZA - NUEVO | I47: CUNDINAMARCA | J47: BOGOTA | K47: PTM BOGOTA COMPU EMI | L47: REDEBAN | M47: FO-25-1990059 | N47: 46009.333 | O47: 46010.55 | P47: AGREGADOR | Q47: COMCARD - PTM | R47: EJECUTADO | S47: 17/12/2025 17-12 PROGRAMACION REALIZADA POR LA ALIANZA| INSTALACIÓN PROGRAMADA PARA EL 2025-12-19 | 19/12/2025 APERTURA BANCOLOMBIA OK CAPACITACIÓN OK PUBLICIDAD OK SERVICIO OPERATIVO | T47: VISITA TECNICA | U47: FB007703 | V47: TIPO I | W47: TERRESTRE | X47: HERNANDEZ NARANJO OSCAR EDUARDO | Y47: 1 | Z47: 0 | AA47: 75096 | AB47: 75096 | AC47: 75096
A48: MEDELLIN | B48: NOROCCIDENTE | C48: 0004-0005 | D48: 5001 | E48: TA-25-1429986 | F48: 3007038563 | G48: APERTURA | H48: DATAFONO ADICIONAL - ALIANZA | I48: ANTIOQUIA | J48: MEDELLIN | K48: DISTRICOL PAPELERIA TOBY | L48: REDEBAN | M48: FO-25-1990064 | N48: 46009.333 | O48: 46009.499 | P48: AGREGADOR | Q48: DISTRICOL | R48: EJECUTADO | S48: 17/12/2025 17-12 PROGRAMACION REALIZADA POR LA ALIANZA| INSTALACIÓN PROGRAMADA PARA EL 2025-12-18 | 18/12/2025 SE INSTALA DATAFONO ADICIONAL EXITOSAMENTE | T48: VISITA TECNICA | U48: FB007704 | V48: TIPO I | W48: TERRESTRE | X48: RUA ALVAREZ RICHARD ANDRES | Y48: 1 | Z48: 0 | AA48: 75096 | AB48: 75096 | AC48: 75096
A49: MEDELLIN | B49: NOROCCIDENTE | C49: 0004-0005 | D49: 5615 | E49: TA-25-1429989 | F49: 3007035275 | G49: APERTURA | H49: DATAFONO ADICIONAL - ALIANZA | I49: ANTIOQUIA | J49: RIONEGRO | K49: DISTRICOL MERCADOS BARCELONA | L49: REDEBAN | M49: FO-25-1990068 | N49: 46009.333 | O49: 46010.675 | P49: AGREGADOR | Q49: DISTRICOL | R49: EJECUTADO | S49: 17/12/2025 17-12 PROGRAMACION REALIZADA POR LA ALIANZA| INSTALACIÓN PROGRAMADA PARA EL 2025-12-19 | 19/12/2025 SE INSTALA DATAFONO ADICIONAL | T49: VISITA TECNICA | U49: FB007705 | V49: TIPO II | W49: TERRESTRE | X49: BADEL ACUÑA LUIS ALBERTO | Y49: 1 | Z49: 0 | AA49: 163814 | AB49: 140396 | AC49: 163814
A50: MONTERIA | B50: COSTA | C50: 0004-0001 | D50: 23555 | E50: TA-25-1429991 | F50: 3007035487 | G50: APERTURA | H50: DATAFONO ADICIONAL - ALIANZA | I50: CORDOBA | J50: PLANETA RICA | K50: DISTRICOL CAFETERIA COFFE HOUSE | L50: REDEBAN | M50: FO-25-1990071 | N50: 46009.333 | O50: 46009.602 | P50: AGREGADOR | Q50: DISTRICOL | R50: EJECUTADO | S50: 17/12/2025 17-12 PROGRAMACION REALIZADA POR LA ALIANZA| INSTALACIÓN PROGRAMADA PARA EL 2025-12-18 | 18/12/2025 SE REALIZA VISITA TÉCNICA PARA APERTURA, DATAFONO ADICIONAL, SE INSTALA DATAFONO PLACA 1196702, LECTORA SYMBOL PLACA 902751, CUBRE CLAVES Y ACCESORIOS, SE REALIZAN PRUEBAS OK, NO SE REALIZA CAPACITACIÓN YA QUE EL CB SE ENCUENTRA CAPACITADO. NOTA: NO SE INSTALA PUBLICIDAD YA QUE ES DATAFONO ADICIONAL. SE DEJA EQUIPO LISTO PARA OPERACIONES. | T50: VISITA TECNICA | U50: FB007706 | V50: TIPO II | W50: TERRESTRE | X50: CASSIANI PEREZ RAUL RAMIRO | Y50: 1 | Z50: 0 | AA50: 163814 | AB50: 140396 | AC50: 163814
A51: YOPAL | B51: ORIENTE | C51: 0004-0007 | D51: 85001 | E51: TA-25-1429993 | F51: 3007059188 | G51: APERTURA | H51: DATAFONO ADICIONAL - ALIANZA | I51: CASANARE | J51: YOPAL | K51: MULTIPAGAS YOPAL CENTRO | L51: REDEBAN | M51: FO-25-1990075 | N51: 46009.333 | O51: 46009.467 | P51: ROBUSTO | Q51: MULTIPAGAS | R51: EJECUTADO | S51: 17/12/2025 17-12 SE REALIZA LLAMADA AL CLIENTE, SE HABLA CON LA SRA EIDY RUIZ AL NUMERO 3223525164 SE VALIDA DIRECCIÓN OK, CANAL OK, DISPONIBILIDAD TOTAL, LLAMAR EL DÍA LA INSTALACIÓN PARA CONFIRMAR VISITA | 18/12/2025 SE VISITA COMERCIO, SE INSTALA DATÁFONO PINPAD Y LECTOR ADICIONAL. OPERATIVO EL SERVICIO. PRUEBAS OK. NO SE REALIZA PRUEBA DE TRANSFERENCIA NO SE CUENTA CON TARJETA. EIDY RUIZ INDICA NO REQUIERE BASE POR LA POSICIÓN Y EL ESPACIO ES MUY REDUCIDO. CB INDICA NO TENER ACCESO A DOCUMENTOS COMO CAMARA DE COMERCIO Y RECIBOS, MOTIVO QUE ES UN ROBUSTO Y ESOS DOCUMENTOS LO TIENEN OTRAS PERSONAS. | T51: VISITA TECNICA | U51: FB007707 | V51: TIPO I | W51: TERRESTRE | X51: BERNAL ELAICA EDGAR ALEXIS | Y51: 1 | Z51: 0 | AA51: 75096 | AB51: 75096 | AC51: 75096
A52: MEDELLIN | B52: NOROCCIDENTE | C52: 0004-0005 | D52: 5631 | E52: TA-25-1429995 | F52: 3007082468 | G52: APERTURA | H52: CB CRECIMIENTO ALIANZA - OTRAS LISTAS | I52: ANTIOQUIA | J52: SABANETA | K52: DISTRICOL PARENTESIS A&C | L52: REDEBAN | M52: FO-25-1990081 | N52: 46009.333 | O52: 46009.595 | P52: AGREGADOR | Q52: DISTRICOL | R52: EJECUTADO | S52: 17/12/2025 17-12 PROGRAMACION REALIZADA POR LA ALIANZA| INSTALACIÓN PROGRAMADA PARA EL 2025-12-18 | 18/12/2025 SE HACE IMPLEMENTACION OK EQUIPOS OPERATIVOS PRUEBAS EXITOSAS SOMOS BANCOLOMBIA ACTIVO, CAPACITACIÓN Y PUBLICIDAD OK | T52: VISITA TECNICA | U52: FB007708 | V52: TIPO I | W52: TERRESTRE | X52: DIAZ ZABALA FRANCIS DUBAN | Y52: 1 | Z52: 0 | AA52: 75096 | AB52: 75096 | AC52: 75096
A53: MEDELLIN | B53: NOROCCIDENTE | C53: 0004-0005 | D53: 5001 | E53: TA-25-1446312 | F53: 3007082585 | G53: APERTURA | H53: CB CRECIMIENTO ALIANZA - NUEVO | I53: ANTIOQUIA | J53: MEDELLIN | K53: DISTRICOL DROGUERIA SIRDALUD | L53: REDEBAN | M53: FO-25-2024417 | N53: 46015.333 | O53: 46015.463 | P53: AGREGADOR | Q53: DISTRICOL | R53: EJECUTADO | S53: 23/12/2025 23-12 PROGRAMACION REALIZADA POR LA ALIANZA| INSTALACIÓN PROGRAMADA PARA EL 2025-12-24 | 24/12/2025 INSTALACIÓN DE CB PURO OK PUBLICIDAD Y CAPACITACIÓN OK PRUEBAS SOLO CONSULTA DE SALDO NO HAY PARA MÁS CUBRE CLAVE OK NO TELECARGA | T53: VISITA TECNICA | U53: OB007835 | V53: TIPO I | W53: TERRESTRE | X53: PAREJA ECHAVARRIA JHON DAVID | Y53: 1 | Z53: 0 | AA53: 75096 | AB53: 75096 | AC53: 75096
A54: MEDELLIN | B54: NOROCCIDENTE | C54: 0004-0005 | D54: 5001 | E54: TA-25-1446314 | F54: 3007082586 | G54: APERTURA | H54: CB CRECIMIENTO ALIANZA - NUEVO | I54: ANTIOQUIA | J54: MEDELLIN | K54: DISTRICOL TIENDA DEL PELUQUERO | L54: REDEBAN | M54: FO-25-2024424 | N54: 46015.333 | O54: 46015.572 | P54: AGREGADOR | Q54: DISTRICOL | R54: EJECUTADO | S54: 23/12/2025 23-12 PROGRAMACION REALIZADA POR LA ALIANZA| INSTALACIÓN PROGRAMADA PARA EL 2025-12-24 | 24/12/2025 SE INSTALAN EQUIPOS OK | T54: VISITA TECNICA | U54: OB007836 | V54: TIPO I | W54: TERRESTRE | X54: QUINTERO SANCHEZ JUAN SEBASTIAN | Y54: 1 | Z54: 0 | AA54: 75096 | AB54: 75096 | AC54: 75096
A55: MEDELLIN | B55: NOROCCIDENTE | C55: 0004-0005 | D55: 5001 | E55: TA-25-1446315 | F55: 3007082587 | G55: APERTURA | H55: CB CRECIMIENTO ALIANZA - NUEVO | I55: ANTIOQUIA | J55: MEDELLIN | K55: DISTRICOL COMERCIALIZADORA KTE | L55: REDEBAN | M55: FO-25-2024425 | N55: 46015.333 | O55: 46015.54 | P55: AGREGADOR | Q55: DISTRICOL | R55: EJECUTADO | S55: 23/12/2025 23-12 PROGRAMACION REALIZADA POR LA ALIANZA| INSTALACIÓN PROGRAMADA PARA EL 2025-12-24 | 24/12/2025 INSTALACIÓN CB OK | T55: VISITA TECNICA | U55: OB007837 | V55: TIPO I | W55: TERRESTRE | X55: BADEL ACUÑA LUIS ALBERTO | Y55: 1 | Z55: 0 | AA55: 75096 | AB55: 75096 | AC55: 75096
... A88: MEDELLIN | B88: NOROCCIDENTE | C88: 0004-0005 | D88: 5789 | E88: TA-25-1463252 | F88: 3007021280 | G88: APERTURA | H88: DATAFONO ADICIONAL - ALIANZA | I88: ANTIOQUIA | J88: TAMESIS | K88: PTM TAMESIS TELECOM | L88: REDEBAN | M88: FO-25-2046848 | N88: 46020.333 | O88: 46021.575 | P88: AGREGADOR | Q88: COMCARD - PTM | R88: EJECUTADO | S88: 29/12/2025 29-12 SE REALIZA LLAMADA AL CLIENTE, SE HABLA CON EL SR DIEGO SALGADO AL NUMERO 3147338903 SE VALIDA DIRECCIÓN OK, CANAL OK, DISPONIBILIDAD TOTAL, LLAMAR EL DÍA LA INSTALACIÓN PARA CONFIRMAR VISITA | 02/01/2026 SE REALIZA LA INSTALACIÓN DE 1 DATAFONO ADICIONAL, 1 LECTOR, SE INSTALA BASE DE DATAFONO, 60 ROLLOS INSTALACION OK | T88: VISITA TECNICA | U88: AE00D133 | V88: TIPO III | W88: TERRESTRE | X88: MONTOYA VELEZ ANDRES FELIPE | Y88: 1 | Z88: 0 | AA88: 275729 | AB88: 196537 | AC88: 275729

Sheet INCIDENTES_BANCOLOMBIA
A1: CIUDAD SEDE | B1: ZONA | C1: CENTRO DE COSTOS LINEACOM | D1: CODIGO DANE | E1: TA/CODIGO ACTIVIDAD | F1: CODIGO CB | G1: ACTIVIDAD | H1: DEPARTAMENTO | I1: CIUDAD | J1: NOMBRE DEL CB | K1: RED | L1: FO | M1: FECHA ASIGNACION A LINEA COMUNICACIONES | N1: FECHA CIERRE DEL TICKET (DD/MM/AAAA HH:MM) | O1: ACOMETIDA | P1: GRUPO_FALLA | Q1: CATEGORIA | R1: FALLA | S1: FORMATO | T1: CADENA | U1: ESTADO | V1: OBSERVACION | W1: FORMA DE ATENCION | X1: TERMINAL(ES) | Y1: TIPIFICACION | Z1: TIPO DE TRAYECTO | AA1: NOMBRE DEL TECNICO | AB1: DIAS DE VISITA | AC1: DIA ADICIONAL | AD1: VALOR DIAS ACTIVIDAD FACTURABLES | AE1: VALOR DIAS ACOMPAÑAMIENTO FACTURABLES | AF1: VALOR TOTAL
A2: MONTERIA | B2: COSTA | C2: 0004-0001 | D2: 5495 | E2: 3040690 | F2: 3007060039 | G2: INCIDENTE | H2: ANTIOQUIA | I2: NECHI | J2: DISTRICOL DISTRIBUIDORA EL AHI | K2: REDEBAN | L2: FO-25-1851887 | M2: 45981.482 | N2: 45993.362 | P2: HARDWARE | Q2: IMPRESION | R2: NO AVANZA PAPEL | S2: AGREGADOR | T2: DISTRICOL | V2: 20/11/2025 SE ESCALA PARA VISITA. LLAMAR ANTES DE VISITAR, CONFIRMAR FALLA Y DATOS | 21/11/2025 SE LLEGA A MUNICIPIO DE NECHÍ - ANTIOQUIA, NO SE LOGRA CONTACTAR A LA PERSONA ENCARGADA DEL CB PARA VALIDAR PERMISOS DE INGRESO , AL CORREGIMIENTO QUÉ SE ENCUENTRA EN ZONA ROJA CON PROBLEMAS DE ORDEN PÚBLICO MOTIVO POR EL CUAL NO SE REALIZA DESPLAZAMIENTO DIRECTO, SE REPROGRAMA VISITA HASTA PODER CONTACTAR AL CLIENTE PARA GARANTIZAR LA INTEGRIDAD DEL PERSONAL TÉCNICO EN LA ZONA. | 02/12/2025 SE ESTABLECE COMUNICACIÓN TELEFÓNICA CON EL CLIENTE SEÑORA MARTA ROJAS QUIEN CONFIRMA QUE EL DATAFONO SE ENCUENTRA OPERATIVO REALIZÓ REINICIO DEL EQUIPO, CAMBIO PAPEL Y FUNCIONÓ, ACTUALMENTE SE CONFIRMA CON LA SEÑORA QUE SE ENCUENTRA OPERATIVO SIN NOVEDAD OK, SE PROCEDE A CERRAR LA ORDEN OK | W2: SOPORTE TELEFONICO | Y2: TIPO III | Z2: TERRESTRE | AA2: GONZALEZ FERRER JESUS ALEXANDER | AB2: 0 | AC2: 0 | AD2: 41241 | AE2: 0 | AF2: 41241
A3: YOPAL | B3: REMOTAS | C3: 0004-0007 | D3: 85001 | E3: 3073318 | F3: 3007034137 | G3: INCIDENTE | H3: CASANARE | I3: YOPAL | J3: BARRIO NUEVO HABITAT II YOPAL | K3: REDEBAN | L3: FO-25-1899408 | M3: 45988.668 | N3: 45993.65 | P3: HARDWARE | Q3: ALERT IRRUPTION | R3: ALERT IRRUPTION | S3: UNO A UNO | T3: CB UNO A UNO | V3: 27/11/2025 SE ESCALA PARA VISITA. LLAMAR ANTES DE VISITAR, CONFIRMAR FALLA Y DATOS | 02/12/2025 EN COMUNICACIÓN CON EL SEÑOR ARLEY OROZCO AL NUMERO 3208005960, INDICA NO REQUIERE LA VISITA, LE REALIZARON LA MIGRACIÓN A WOMPI Y YA NO UTILIZA EL DATAFONO DE RBM. INFORMA QUE TIENE OPERATIVO EL SERVICIO | W3: SOPORTE TELEFONICO | Y3: TIPO I | Z3: TERRESTRE | AA3: BERNAL ELAICA EDGAR ALEXIS | AB3: 0 | AC3: 0 | AD3: 41241 | AE3: 0 | AF3: 41241
A4: PASTO | B4: SUROCCIDENTE Y EJE CAFETERO | C4: 0004-0003 | D4: 52835 | E4: 3073329 | F4: 3007024652 | G4: INCIDENTE | H4: NARIÑO | I4: SAN ANDRES DE TUMACO | J4: BARRIO CALLE SUCRE SAN ANDRES | K4: REDEBAN | L4: FO-25-1899402 | M4: 45988.671 | N4: 45994.387 | O4: NO | P4: HARDWARE | Q4: IMPRESION | R4: NO IMPRIME UNO O VARIOS CARACTERES | S4: CB UNO A UNO | T4: CB UNO A UNO | U4: EJECUTADO | V4: 27/11/2025 SE ESCALA PARA VISITA. LLAMAR ANTES DE VISITAR, CONFIRMAR FALLA Y DATOS | 01/12/2025 NO SE PUEDE REALIZAR DESPLAZAMIENTO HOY HACIA TUMACO POR PROBLEMAS EN LA VIA, HACIA BARBACOAS, SE VALIDARA EL DIA DE MAÑANA | 03/12/2025 SE REALIZA CAMBIO DE DATÁFONO POR DAÑO EN IMPRESORA SE RECONFIGURA OK PARÁMETROS OK Y SE REALIZAN PRUEBAS EXITOSAS DE TRANSACCIONES | W4: VISITA TECNICA | X4: SA09Z857 | Y4: TIPO IV | Z4: TERRESTRE | AA4: PAZ MARTINEZ RICHARD HUMBERTO | AB4: 1 | AC4: 0 | AD4: 479589 | AE4: 196537 | AF4: 479589
A5: CALI | B5: SUROCCIDENTE Y EJE CAFETERO | C5: 0004-0003 | D5: 19075 | E5: 3073403 | F5: 3007059688 | G5: INCIDENTE | H5: CAUCA | I5: BALBOA | J5: BARRIO BOLIVAR BALBOA | K5: REDEBAN | L5: FO-25-1899405 | M5: 45988.669 | N5: 45992.417 | P5: HARDWARE | Q5: COMUNICACION | R5: MENSAJE CABLE DE RED DESCONECTADO | S5: CB UNO A UNO | T5: CB UNO A UNO | V5: 27/11/2025 SE ESCALA PARA VISITA. LLAMAR ANTES DE VISITAR, CONFIRMAR FALLA Y DATOS | 01/12/2025 SE REALIZA LLAMADA CON LA SEÑORA YAQUELINE VELASCO INFORMA YA EL DATAFONO FUNCIONA OK | W5: SOPORTE TELEFONICO | Y5: TIPO IV | Z5: TERRESTRE | AA5: GIMBUEL LASSO LUIS GERMAN | AB5: 0 | AC5: 0 | AD5: 41241 | AE5: 0 | AF5: 41241
A6: MONTERIA | B6: COSTA | C6: 0004-0001 | D6: 5250 | E6: 3073446 | F6: 3007058297 | G6: INCIDENTE | H6: ANTIOQUIA | I6: EL BAGRE | J6: BARRIO BRR EL PORVENIR EL BAGR | K6: REDEBAN | L6: FO-25-1899746 | M6: 45988.682 | N6: 45993.647 | O6: NO | P6: HARDWARE | Q6: PANTALLA | R6: DAÑO POS | S6: CB UNO A UNO | T6: CB UNO A UNO | U6: EJECUTADO | V6: 27/11/2025 SE ESCALA PARA VISITA. LLAMAR ANTES DE VISITAR, CONFIRMAR FALLA Y DATOS | 02/12/2025 SE REALIZA CAMBIO DE EQUIPO POR DAÑO, DISPLAY BLANCO E INTERMITENTE, ADICIONAL SE CAMBIA EN PINPAD POR COMPATIBILIDAD, SE RETIRA MAGICBOX OK, EQUIPOS Y ACCESORIOS INSTALADOS OPERATIVOS, PRUEBAS EXITOSAS, CLIENTE CB VALIDA SALDO ANTES Y DESPUÉS DEL MANTENIMIENTO OK, CB SE DEJA OPERATIVO SIN NOVEDAD OK | W6: VISITA TECNICA | X6: IMZZZ418 | Y6: TIPO IV | Z6: TERRESTRE | AA6: GONZALEZ FERRER JESUS ALEXANDER | AB6: 1 | AC6: 0 | AD6: 479589 | AE6: 196537 | AF6: 479589
A7: CALI | B7: SUROCCIDENTE Y EJE CAFETERO | C7: 0004-0003 | D7: 76001 | E7: 3074172 | F7: 3007014454 | G7: INCIDENTE | H7: VALLE DEL CAUCA | I7: CALI | J7: BARRIO EL JARDIN II CALI | K7: REDEBAN | L7: FO-25-1903340 | M7: 45989.345 | N7: 45993.548 | O7: NO | P7: SOFTWARE | Q7: ACTUALIZACION | R7: VERSION CARGA SO VR | S7: CB UNO A UNO | T7: CB UNO A UNO | U7: EJECUTADO | V7: 03/12/2025 SE INICIALIZA EL EQUIPO YA QUE SE CREA TERMINAL DE SERVIR PARA MIXTO POR SOLICITUD DE REDEBAN SE REALIZAN PRUEBAS EXITOSAS | W7: VISITA TECNICA | X7: AE007395 IZ00Q965 | Y7: TIPO I | Z7: TERRESTRE | AA7: PALACIOS GOMEZ BRAHIAN ANDRES | AB7: 1 | AC7: 0 | AD7: 65960 | AE7: 75096 | AF7: 65960
A8: IBAGUE | B8: REMOTAS | C8: 0004-0007 | D8: 73555 | E8: 3074742 | F8: 3007011707 | G8: INCIDENTE | H8: TOLIMA | I8: PLANADAS | J8: PLANADAS TOLIMA | K8: REDEBAN | L8: FO-25-1900998 | M8: 45989.36 | N8: 45993.401 | O8: NO | P8: HARDWARE | Q8: ALERT IRRUPTION | R8: ALERT IRRUPTION | S8: CB UNO A UNO | T8: CB UNO A UNO | U8: EJECUTADO | V8: 28/11/2025 SE ESCALA PARA VISITA. LLAMAR ANTES DE VISITAR, CONFIRMAR FALLA Y DATOS | 01/12/2025 DEBIDO LA POCA FRECUENCIA DE TRANSPORTE HACIA LA ZONA Y AL ESTADO DE LAS VÍAS HAY DEMORAS PARA LLEGAR AL MUNICIPIO DE PLANADAS | 02/12/2025 SE REALIZA CAMBIO DE EQUIPO ALERT IRRUPTION | W8: VISITA TECNICA | X8: JAAAE398 | Y8: TIPO IV | Z8: TERRESTRE | AA8: GUTIERREZ CAMILO ANDRES | AB8: 1 | AC8: 0 | AD8: 479589 | AE8: 196537 | AF8: 479589
A9: MEDELLIN | B9: NOROCCIDENTE | C9: 0004-0005 | D9: 5736 | E9: 3075174 | F9: 3007076067 | G9: INCIDENTE | H9: ANTIOQUIA | I9: SEGOVIA | J9: BARRIO GALAN SEGOVIA 1 | K9: REDEBAN | L9: FO-25-1901273 | M9: 45989.399 | N9: 45992.415 | P9: HARDWARE | Q9: CABLEADO | R9: DAÑO POS | S9: CB UNO A UNO | T9: CB UNO A UNO | V9: [FO-25-1901273] 28/11/2025 SE ESCALA PARA VISITA. LLAMAR ANTES DE VISITAR, CONFIRMAR FALLA Y DATOS | 01/12/2025 SE INTENTA COMUNICACIÓN CON CLIENTE AL 3137588872 SIN ÉXITO EN LLAMADA O WHATSAPP | 01/12/2025 SE COMUNICA CON CLIENTE E INFORMA QUE EL EQUIPO YA ESTÁ FUNCIONANDO CORRECTAMENTE DESPUÉS DE REINICIAR EL MÓDEM, SE CIERRA || [FO-25-1901273] 28/11/2025 SE ESCALA PARA VISITA. LLAMAR ANTES DE VISITAR, CONFIRMAR FALLA Y DATOS | 01/12/2025 SE INTENTA COMUNICACIÓN CON CLIENTE AL 3137588872 SIN ÉXITO EN LLAMADA O WHATSAPP | 01/12/2025 SE COMUNICA CON CLIENTE E INFORMA QUE EL EQUIPO YA ESTÁ FUNCIONANDO CORRECTAMENTE DESPUÉS DE REINICIAR EL MÓDEM, SE CIERRA | W9: SOPORTE TELEFONICO | Y9: TIPO IV | Z9: TERRESTRE | AA9: QUINTERO SANCHEZ JUAN SEBASTIAN | AB9: 0 | AC9: 0 | AD9: 82482 | AE9: 0 | AF9: 82482
A10: BOGOTA | B10: CUNDINAMARCA | C10: 0004-0004 | D10: 25843 | E10: 3075604 | F10: 3007079958 | G10: INCIDENTE | H10: CUNDINAMARCA | I10: VILLA DE SAN DIEGO DE UBATE | J10: BARRIO SIMON BOLIVAR VILLA DE SAN DIEGO DE UBATE 3 | K10: REDEBAN | L10: FO-25-1901795 | M10: 45989.43 | N10: 45992.629 | O10: NO | P10: HARDWARE | Q10: DETERIORO | R10: DATAFONO | S10: UNO A UNO | T10: UNO A UNO | U10: EJECUTADO | V10: 28/11/2025 SE ESCALA PARA VISITA. LLAMAR ANTES DE VISITAR, CONFIRMAR FALLA Y DATOS | 29/11/2025 DEBIDO A QUE NO HAY SOPORTE DE ACTIVOS REDEBAN Y POR DESPLAZAMIENTO, NO SE PUEDE VISITAR COMERCIO. SE HABLA LA SRA NORMA LETICIA 3123742690 M QUIEN INFORMA RECIBIR VISITA EL DÍA LUNES 01-12-2025 | 01/12/2025 SE VISITA COMERCIO CB BANCOLOMBIA, SE CAMBIA DATAFONO POR QUÉ TIENE EL PUERTO USB DETERIORADO Y EL CABLE DE LA LECTORA TAMBIÉN, SE DEJA EL EQUIPO NUEVO EN BUEN ESTADO CON LOS USUARIOS DEL CLIENTE, SE REALIZAN PRUEBAS OK, NO UPS. | W10: VISITA TECNICA | X10: SAUZZ586 | Y10: TIPO II | Z10: TERRESTRE | AA10: VEGA MANRIQUE JONATAN MAURICIO | AB10: 1 | AC10: 0 | AD10: 144968 | AE10: 140396 | AF10: 144968
A11: VILLAVICENCIO | B11: REMOTAS | C11: 0004-0007 | D11: 50568 | E11: 3076614 | F11: 3007081862 | G11: INCIDENTE | H11: META | I11: PUERTO GAITAN | J11: PTM PUERTO GAITAN DROGUERIA JA | K11: REDEBAN | L11: FO-25-1903554 | M11: 45989.538 | N11: 45992.722 | O11: NO | P11: HARDWARE | Q11: ALERT IRRUPTION | R11: ALERT IRRUPTION | S11: AGREGADOR | T11: COMCARD - PTM | U11: EJECUTADO | V11: 28/11/2025 SE ESCALA PARA VISITA. LLAMAR ANTES DE VISITAR, CONFIRMAR FALLA Y DATOS | 01/12/2025 SE REALIZA CAMBIO DE EQUIPO POR DAÑO SE ENCONTRABA ALERTADO | W11: VISITA TECNICA | X11: VWZZZ799 VTZZZ904 | Y11: TIPO III | Z11: TERRESTRE | AA11: ROZO JIMENEZ EDGAR ARMANDO | AB11: 1 | AC11: 0 | AD11: 275729 | AE11: 196537 | AF11: 275729
A12: BOGOTA | B12: CUNDINAMARCA | C12: 0004-0004 | D12: 11001 | E12: 3077409 | F12: 3007025523 | G12: INCIDENTE | H12: CUNDINAMARCA | I12: BOGOTA | J12: PAGAFACIL TERMINAL TRANSPORTE | K12: REDEBAN | L12: FO-25-1907819 | FO-25-1904338 | M12: 45989.652 | N12: 45992.549 | O12: NO | P12: SOFTWARE | Q12: PINPAD | R12: PINPAD DESCONFIGURADO | S12: ROBUSTO | T12: PAGAFACIL | U12: EJECUTADO | EJECUTADO / CANCELADO | V12: [FO-25-1907819] 01/12/2025 SE REALIZA REVISIÓN DE LOS EQUIPOS SE ENCUENTRA QUE EL CABLE DE CONEXIÓN DATÁFONO-PINPAD ESTÁ DAÑADO, FALLO MASIVO EN EL MOMENTO DE REALIZAR INCIDENTE SE PROCEDE A TOMAR FOTO DE LAS PRIMERAS TRANSACCIONES QUE SALIERON || [FO-25-1904338] 28/11/2025 SE ESCALA PARA VISITA. LLAMAR ANTES DE VISITAR, CONFIRMAR FALLA Y DATOS | 29/11/2025 SE REPROGRAMA VISITA PARA EL DÍA LUNES NO SE CUENTAN CON EQUIPOS DE BAKCUP EN DISPONIBILIDAD, ADICIONAL DEMORAS PARA CAMBIO DE EQUIPO. | W12: VISITA TECNICA | X12: BL0GZ758 | Y12: TIPO I | Z12: TERRESTRE | AA12: ALARCON AREVALO JOHAN STIVEN | AB12: 2 | AC12: 0 | AD12: 131920 | AE12: 75096 | AF12: 131920
A13: MONTERIA | B13: COSTA | C13: 0004-0001 | D13: 23500 | E13: 3077810 | F13: 3007042001 | G13: INCIDENTE | H13: CORDOBA | I13: MOÑITOS | J13: DISTRICOL AGROVETERINARIA JIRE | K13: REDEBAN | L13: FO-25-1904843 | M13: 45989.718 | N13: 45992.735 | O13: NO | P13: HARDWARE | Q13: TECLADO | R13: DAÑO POS | S13: AGREGADOR | T13: DISTRICOL | U13: EJECUTADO | V13: 28/11/2025 SE ESCALA PARA VISITA. LLAMAR ANTES DE VISITAR, CONFIRMAR FALLA Y DATOS | 01/12/2025 DEBIDO A INCONVENIENTE CON LOS CAMBIOS DE EQUIPO POR PARTE DE REDEBAN, NOS TENEMOS RETRASO PARA LLEGAR AL SITIO YA QUE NOS ENCONTRAMOS EN UN INCIDENTE REALIZANDO UN CAMBIO Y HAY INCONVENIENTES CON LOS CAMBIOS POR PARTE DE REDEBAN. TENIENDO EN CUENTA LAS NOTAS ACÁ TAMBIÉN SERÁ UN POSIBLE CAMBIO DE EQUIPO, LO QUE REQUIERE DEL TIEMPO REGLAMENTARIO PARA LA ATENCIÓN Y LA HORA LÍMITE ESTÁ A LAS 17:14. | 01/12/2025 SE REALIZA VISITA TÉCNICA Y SE CAMBIA DATAFONO POR DAÑO DE TECLADO, TECLAS BORROSA Y DURAS, SE INSTALA DATÁFONO PLACA 1255207 Y SE RETIRA DATAFONO PLACA 1173969, SE REALIZAN PRUEBAS Y SE DEJA EL SERVICIO FUNCIONANDO CORRECTAMENTE. | W13: VISITA TECNICA | X13: GZ0XZ403 | Y13: TIPO III | Z13: TERRESTRE | AA13: CASSIANI PEREZ RAUL RAMIRO | AB13: 1 | AC13: 0 | AD13: 275729 | AE13: 196537 | AF13: 275729
A14: CALI | B14: SUROCCIDENTE Y EJE CAFETERO | C14: 0004-0003 | D14: 19100 | E14: 3077881 | F14: 3007045599 | G14: INCIDENTE | H14: CAUCA | I14: BOLIVAR | J14: BARRIO NARINO BOLIVAR | K14: REDEBAN | L14: FO-25-1905863 | M14: 45990.384 | N14: 45993.604 | O14: NO | P14: HARDWARE | Q14: TECLADO | R14: DAÑO POS | S14: CB UNO A UNO | T14: CB UNO A UNO | U14: EJECUTADO | V14: 29/11/2025 SE ESCALA PARA VISITA. LLAMAR ANTES DE VISITAR, CONFIRMAR FALLA Y DATOS | 01/12/2025 POR TEMA DE ORDEN PUBLICO EN LA ZONA Y RIESGO SE CUADRA CON EL CB PARA ATENDER ACTIVIDAD EN UN LUGAR SEGURO SE GESTIONO CON EL CB A ESPERA DE LA PRONTA SOLUCION | 02/12/2025 SE INGRESA EQUIPO CON TECLADO DETERIORO DURO SE PROCEDE A CAMBIAR EQUIPO SE HACEN PRUEBAS OK TELECARG DRNA | W14: VISITA TECNICA | X14: AD000826 | Y14: TIPO IV | Z14: TERRESTRE | AA14: GIMBUEL LASSO LUIS GERMAN | AB14: 1 | AC14: 0 | AD14: 479589 | AE14: 196537 | AF14: 479589
A15: APARTADO | B15: NOROCCIDENTE | C15: 0004-0005 | D15: 5490 | E15: 3077889 | F15: 3007052873 | G15: INCIDENTE | H15: ANTIOQUIA | I15: NECOCLI | J15: BARRIO SIMON BOLIVAR NECOCLI | K15: REDEBAN | L15: FO-25-1906249 | M15: 45990.41 | N15: 45992.532 | O15: NO | P15: HARDWARE | Q15: DETERIORO | R15: DATAFONO | S15: CB UNO A UNO | T15: CB UNO A UNO | U15: EJECUTADO | V15: 29/11/2025 SE ESCALA PARA VISITA. LLAMAR ANTES DE VISITAR, CONFIRMAR FALLA Y DATOS | 01/12/2025 ESTAMOS EN DESPLAZAMIENTO PARA NECOCLI, CONDUCTORES MANIFIESTA QUE ALGUNOS NO ESTÁN LLEGANDO POR PROBLEMAS DE ORDEN PÚBLICO SOBRE UN PARO COMUNITARIO DEBIDO AL MAL ESTADO DE LA VIA. SE LLAMA A LA USUARIA EN DÓNDE SE LE INDICA LO SUCEDIDO Y QUE ESTAMOS EN CAMINO A ATENDER LA NOVEDAD. | 01/12/2025 DATÁFONO ATASCA EL PAPEL, SE VALIDA Y SE ENCUENTRA QUE LOS PIÑONES DE LA IMPRESORA ESTÁ DESGASTADOS SE HACE CAMBIO DE EQUIPO Y SE HACEN PRUEBAS DEJANDO TODO FUNCIONANDO CORRECTAMENTE | W15: VISITA TECNICA | X15: BA0IZ176 | Y15: TIPO II | Z15: TERRESTRE | AA15: SALDARRIAGA MIRANDA SANTIAGO | AB15: 1 | AC15: 0 | AD15: 144968 | AE15: 140396 | AF15: 144968
A16: MANIZALES | B16: SUROCCIDENTE Y EJE CAFETERO | C16: 0004-0002 | D16: 17614 | E16: 3077933 | F16: 3007029915 | G16: INCIDENTE | H16: CALDAS | I16: RIOSUCIO | J16: COMCARD RIOSUCIO LA CIGARRA | K16: REDEBAN | L16: FO-25-1904987 | M16: 45989.739 | N16: 45992.535 | O16: NO | P16: HARDWARE | Q16: IMPRESION | R16: NO IMPRIME UNO O VARIOS CARACTERES | S16: AGREGADOR | T16: COMCARD - PTM | U16: EJECUTADO | V16: 28/11/2025 SE ESCALA PARA VISITA. LLAMAR ANTES DE VISITAR, CONFIRMAR FALLA Y DATOS | 29/11/2025 EL CLIENTE REQUIERE CAMBIO DE EQUIPO SE DEBE VALIDAR VISITA A A PARTIR DEL DÍA LUNES | 01/12/2025 VISITAMOS COMERCIO EL DATÁFONO NO IMPRIME BIEN LAS TRX REALIZAMOS CAMBIO DE DATAFONO LO CONFIGURAMOS Y REALIZAMOS PRUEBAS PERO SALE RECHAZO GENERAL YA QUE BANCOLOMBIA ESTA PRESENTANDO FALLAS Y NO ES POSIBLE HACER NINGUNA TRANSACCIÓN ADJUNTAMOS LA TRANSACCIÓN DEL RECHAZO, SOLO ES POSIBLE HACER PRUEBAS EXITOSAS DE COMERCIO. | W16: VISITA TECNICA | X16: BBBUZ776 AB11O682 | Y16: TIPO II | Z16: TERRESTRE | AA16: ARROYAVE CANO MANUEL GUILLERMO | AB16: 1 | AC16: 0 | AD16: 144968 | AE16: 140396 | AF16: 144968
A17: NEIVA | B17: REMOTAS | C17: 0004-0007 | D17: 41078 | E17: 3077949 | F17: 3007048893 | G17: INCIDENTE | H17: HUILA | I17: BARAYA | J17: PTM PAGA TODO BARAYA | K17: REDEBAN | L17: FO-25-1904984 | M17: 45990.333 | N17: 45994.48 | O17: NO | P17: HARDWARE | Q17: DETERIORO | R17: DATAFONO | S17: AGREGADOR | T17: COMCARD - PTM | U17: EJECUTADO | V17: 28/11/2025 SE ESCALA PARA VISITA. LLAMAR ANTES DE VISITAR, CONFIRMAR FALLA Y DATOS | 03/12/2025 SE REALIZA CAMBIO DE EQUIPO YA QUE ESTE PRESENTA DESGASTE EN EL TECLADO, IMPRESORA Y PARTE DE LA CARCAZA , SE DEJA EQUIPO INSTALADO CON VR 9.90 PRUEBAS CB OK, CON OPERARIVO | W17: VISITA TECNICA | X17: AD00M825 | Y17: TIPO II | Z17: TERRESTRE | AA17: DEVIA REINOSO JUAN CARLOS | AB17: 1 | AC17: 0 | AD17: 144968 | AE17: 140396 | AF17: 144968
A18: VILLAVICENCIO | B18: REMOTAS | C18: 0004-0007 | D18: 50689 | E18: 3077964 | F18: 3007052948 | G18: INCIDENTE | H18: META | I18: SAN MARTIN | J18: PTM SAN MARTIN DROGERIA V&E | K18: REDEBAN | L18: FO-25-1905797 | M18: 45990.333 | N18: 45992.62 | O18: NO | P18: HARDWARE | Q18: LECTOR DE BARRAS | R18: DAÑO POS | S18: AGREGADOR | T18: COMCARD - PTM | U18: EJECUTADO | V18: 29/11/2025 SE ESCALA PARA VISITA. LLAMAR ANTES DE VISITAR, CONFIRMAR FALLA Y DATOS | 01/12/2025 SE REALIZA CAMBIO DE LECTOR DE BARRAS PRUEBAS OK SIN NOVEDADES | W18: VISITA TECNICA | X18: 9C0LZ863 | Y18: TIPO II | Z18: TERRESTRE | AA18: CASTRILLON URREA LONDIER LEANDRO | AB18: 1 | AC18: 0 | AD18: 144968 | AE18: 140396 | AF18: 144968
A19: MEDELLIN | B19: NOROCCIDENTE | C19: 0004-0005 | D19: 5360 | E19: 3078038 | F19: 3007032941 | G19: INCIDENTE | H19: ANTIOQUIA | I19: ITAGUI | J19: COMCARD ITAGUI PAPELERIA ASTUR | K19: REDEBAN | L19: FO-25-1904985 | M19: 45989.747 | N19: 45992.372 | O19: NO | P19: SOFTWARE | Q19: ACTUALIZACION | R19: VERSION CARGA SO VR | S19: AGREGADOR | T19: COMCARD - PTM | U19: EJECUTADO | V19: 28/11/2025 SE ESCALA PARA VISITA. LLAMAR ANTES DE VISITAR, CONFIRMAR FALLA Y DATOS | 01/12/2025 SE REALIZA INICIALIZACIÓN DE PARÁMETROS SE HACEN PRUEBAS OK | W19: VISITA TECNICA | X19: 11XZZ538 | Y19: TIPO I | Z19: TERRESTRE | AA19: MONTOYA VELEZ ANDRES FELIPE | AB19: 1 | AC19: 0 | AD19: 65960 | AE19: 75096 | AF19: 65960
A20: SANTA MARTA | B20: COSTA | C20: 0004-0001 | D20: 47288 | E20: 3078507 | F20: 3007069387 | G20: INCIDENTE | H20: MAGDALENA | I20: FUNDACION | J20: BARRIO SAN MARTIN FUNDACION | K20: REDEBAN | L20: FO-25-1905777 | M20: 45990.378 | N20: 45992.622 | O20: NO | P20: SOFTWARE | Q20: LLT | R20: LLT | S20: CB UNO A UNO | T20: CB UNO A UNO | U20: EJECUTADO | V20: 29/11/2025 SE ESCALA PARA VISITA. LLAMAR ANTES DE VISITAR, CONFIRMAR FALLA Y DATOS | 01/12/2025 SE REALI ALA VISITA SE ENCUENTRA EL ESTADO O CON PANTALLA AZUL Y ALERTADO, SE PROCEDE A CAMBIAR EL EQUIPO, SE REALIZAN PRUEBAS Y TODO OK | W20: VISITA TECNICA | X20: 10OZZ565 EF00X698 | Y20: TIPO III | Z20: TERRESTRE | AA20: THOMAS CAMPO SIGIFREDO SEGUNDO | AB20: 1 | AC20: 0 | AD20: 275729 | AE20: 196537 | AF20: 275729
A21: APARTADO | B21: NOROCCIDENTE | C21: 0004-0005 | D21: 5172 | E21: 3078508 | F21: 3007044603 | G21: INCIDENTE | H21: ANTIOQUIA | I21: CHIGORODO | J21: PTM CHIGORODO MISCELANEA BRISA | K21: REDEBAN | L21: FO-25-1905865 | M21: 45990.381 | N21: 45992.373 | O21: NO | P21: HARDWARE | Q21: IMPRESION | R21: TAPA IMPRESORA | S21: AGREGADOR | T21: COMCARD - PTM | U21: EJECUTADO | V21: 29/11/2025 SE ESCALA PARA VISITA. LLAMAR ANTES DE VISITAR, CONFIRMAR FALLA Y DATOS | 01/12/2025 DATAFONOS ATASCA PAPEL, SE VALIDA Y LA TAPA ESTÁ MALA. SE HACE CAMBIO POR UNA NUEVA TAPA Y SE CORRIGE LA FALLA. SE HACEN PRUEBAS DE IMPRESIÓN Y SE DEJA TODO OK | W21: VISITA TECNICA | X21: GA0AZ051 | Y21: TIPO II | Z21: TERRESTRE | AA21: SALDARRIAGA MIRANDA SANTIAGO | AB21: 1 | AC21: 0 | AD21: 144968 | AE21: 140396 | AF21: 144968
... A32: CALI | B32: SUROCCIDENTE Y EJE CAFETERO | C32: 0004-0003 | D32: 76001 | E32: 3079821 | F32: 3007081978 | G32: INCIDENTE | H32: VALLE DEL CAUCA | I32: CALI | J32: PTM CALI CENTRO DE SOLUCIONES | K32: REDEBAN | L32: FO-25-1910232 | M32: 45992.333 | N32: 45992.419 | O32: NO | P32: HARDWARE | Q32: IMPRESION | R32: NO IMPRIME UNO O VARIOS CARACTERES | S32: AGREGADOR | T32: COMCARD - PTM | U32: EJECUTADO | V32: 01/12/2025 SE ESCALA PARA VISITA. LLAMAR ANTES DE VISITAR, CONFIRMAR FALLA Y DATOS | 01/12/2025 TIRRILLA SALE BORROSA SE LIMPIA PORTARROLLOS Y QUEDA FUNCIONANDO CORRECTAMENTE | W32: VISITA TECNICA | X32: CA000711 CA000565 | Y32: TIPO I | Z32: TERRESTRE | AA32: CUERO RUIZ JHONNY | AB32: 1 | AC32: 0 | AD32: 65960 | AE32: 75096 | AF32: 65960
A33: MEDELLIN | B33: NOROCCIDENTE | C33: 0004-0005 | D33: 5001 | E33: 3079874 | F33: 3007059022 | G33: INCIDENTE | H33: ANTIOQUIA | I33: MEDELLIN | J33: BARRIO CISNEROS MEDELLIN | K33: REDEBAN | L33: FO-25-1910604 | M33: 45992.344 | N33: 45992.57 | P33: HARDWARE | Q33: PINPAD | R33: DAÑO POS | S33: CB UNO A UNO | T33: CB UNO A UNO | V33: 01/12/2025 SE ESCALA PARA VISITA. LLAMAR ANTES DE VISITAR, CONFIRMAR FALLA Y DATOS | 01/12/2025 SE REALIZÓ LLAMADA TELEFÓNICA AL CORRESPONSAL BANCOLOMBIA PARA CONFIRMAR EL REPORTE RELACIONADO CON EL PINPAD. EL USUARIO INFORMÓ QUE EL DISPOSITIVO PRESENTÓ UNA FALLA, PERO ACTUALMENTE SE ENCUENTRA OPERATIVO Y FUNCIONANDO CON NORMALIDAD. ASIMISMO, INDICÓ QUE NO ES NECESARIA DE UNA VISITA TÉCNICA, DADO QUE EL EQUIPO ESTÁ EN CONDICIONES ADECUADAS DE USO. | W33: SOPORTE TELEFONICO | Y33: TIPO I | Z33: TERRESTRE | AA33: MARTINEZ TOVAR OSCAR DAVID | AB33: 0 | AC33: 0 | AD33: 41241 | AE33: 0 | AF33: 41241
A34: MEDELLIN | B34: NOROCCIDENTE | C34: 0004-0005 | D34: 5001 | E34: 3080620 | F34: 3007038948 | G34: INCIDENTE | H34: ANTIOQUIA | I34: MEDELLIN | J34: DISTRICOL CLASE Y STYLO DEL PE | K34: REDEBAN | L34: FO-25-1910601 | M34: 45992.347 | N34: 45992.542 | O34: NO | P34: HARDWARE | Q34: IMPRESION | R34: NO AVANZA PAPEL | S34: AGREGADOR | T34: DISTRICOL | U34: EJECUTADO | V34: 01/12/2025 SE ESCALA PARA VISITA. LLAMAR ANTES DE VISITAR, CONFIRMAR FALLA Y DATOS | 01/12/2025 SE REALIZA VISITA TÉCNICA AL CORRESPONSAL BANCOLOMBIA POR INCIDENTE REPORTADO EN EL DATÁFONO. EL USUARIO CONFIRMA SU IDENTIFICACIÓN Y MANIFIESTA QUE EL EQUIPO PRESENTA DIFICULTAD PARA AVANZAR EL PAPEL. AL VALIDAR EL ESTADO DEL DISPOSITIVO, SE OBSERVA QUE LA FUENTE DE PODER SE ENCUENTRA DETERIORADA. SE PROCEDE AL REEMPLAZO DE LA FUENTE Y POSTERIORMENTE SE EJECUTAN PRUEBAS DE FUNCIONAMIENTO, LAS CUALES RESULTAN EXITOSAS, CONFIRMANDO LA NORMAL OPERACIÓN DEL DATÁFONO. | W34: VISITA TECNICA | X34: 1A00I157 | Y34: TIPO I | Z34: TERRESTRE | AA34: MARTINEZ TOVAR OSCAR DAVID | AB34: 1 | AC34: 0 | AD34: 65960 | AE34: 75096 | AF34: 65960
A35: MONTERIA | B35: COSTA | C35: 0004-0001 | D35: 23675 | E35: 3080825 | F35: 3007060281 | G35: INCIDENTE | H35: CORDOBA | I35: SAN BERNARDO DEL VIENTO | J35: DISTRICOL DROGUERIA AISHA | K35: REDEBAN | L35: FO-25-1911084 | M35: 45992.361 | N35: 45992.663 | O35: NO | P35: HARDWARE | Q35: IMPRESION | R35: TAPA IMPRESORA | S35: AGREGADOR | T35: DISTRICOL | U35: EJECUTADO | V35: 01/12/2025 SE ESCALA PARA VISITA. LLAMAR ANTES DE VISITAR, CONFIRMAR FALLA Y DATOS | 01/12/2025 SE REALIZA VISITA TÉCNICA Y SE HACE NECESARIO EL CAMBIO DE DATAFONO, YA QUE LA TAPA DE LA IMPRESORA ESTÁ PARTIDA Y ELECANISMO DE IMPRESIÓN DIFICULTA LA CORRECTA FUNCIONALIDAD DE EQUIPO, SE INSTALA DATAFONO PLACA 1191952 Y SE RETIRA DATAFONO PLACA 1057755, SE REALIZAN PRUEBAS Y SE DEJA EL SERVICIO FUNCIONANDO CORRECTAMENTE. | W35: VISITA TECNICA | X35: 9OZZZ178 | Y35: TIPO II | Z35: TERRESTRE | AA35: CASSIANI PEREZ RAUL RAMIRO | AB35: 1 | AC35: 0 | AD35: 144968 | AE35: 140396 | AF35: 144968
A36: BOGOTA | B36: CUNDINAMARCA | C36: 0004-0004 | D36: 99001 | E36: 3081078 | F36: 3007037352 | G36: INCIDENTE | H36: VICHADA | I36: PUERTO CARREÑO | J36: BARRIO LA PLAZUELA PUERTO CARR | K36: REDEBAN | L36: FO-25-1911381 | M36: 45992.379 | N36: 46002.415 | O36: NO | P36: HARDWARE | Q36: ALERT IRRUPTION | R36: ALERT IRRUPTION | S36: CB UNO A UNO | T36: CB UNO A UNO | U36: EJECUTADO | V36: 01/12/2025 EN COMUNICACION CON EL SRA NELLY AL NUMERO 3108959280 ... SE CONFIRMAR FALLA Y DATOS . SE ESCALA PARA VISITA. | 02/12/2025 SE REALIZA ESCALAMIENTO PARA UN VUELO, PARA PODER LLEGAR AL COMERCIO, SE PROGRAMA EL VUELO PARA DÍA 11 DE DICIEMBRE 2025. | 11/12/2025 A LA ESPERA PARA ABORDAR EL AVIÓN. | 11/12/2025 SE LLEGA A COMERCIO, SE VALIDA EQUIPO, NOS ARROJA ALERT INTERRUPTOR, SE PROCEDE A REALIZAR EL CAMBIO, SE REALIZAN PRUEBAS OK SIN NOVEDAD | W36: VISITA TECNICA | X36: 9A00X252 | Y36: TIPO V | Z36: AEREO | AA36: ARIAS QUILINDO JULIAN | AB36: 1 | AC36: 0 | AD36: 988463 | AE36: 196537 | AF36: 988463
A37: PEREIRA | B37: SUROCCIDENTE Y EJE CAFETERO | C37: 0004-0002 | D37: 66170 | E37: 3081766 | F37: 3007055907 | G37: INCIDENTE | H37: RISARALDA | I37: DOSQUEBRADAS | J37: PTM DOSQUEBRADAS AUTOSERVICIO | K37: REDEBAN | L37: FO-25-1911760 | M37: 45992.405 | N37: 45992.733 | O37: NO | P37: HARDWARE | Q37: DETERIORO | R37: DATAFONO | S37: AGREGADOR | T37: COMCARD - PTM | U37: EJECUTADO | V37: 01/12/2025 SE ESCALA PARA VISITA. LLAMAR ANTES DE VISITAR, CONFIRMAR FALLA Y DATOS | 01/12/2025 SE CAMBIA EQUIPO POR DAÑO EN EL PUERTO USB, SE REALIZAN PRUEBAS OK. | W37: VISITA TECNICA | X37: 9BKZZ314 IIJZZ272 | Y37: TIPO I | Z37: TERRESTRE | AA37: FRANCO CAÑAVERAL YAMID RAUL | AB37: 1 | AC37: 0 | AD37: 65960 | AE37: 75096 | AF37: 65960
A38: MONTERIA | B38: COSTA | C38: 0004-0001 | D38: 5154 | E38: 3081982 | F38: 3007044348 | G38: INCIDENTE | H38: ANTIOQUIA | I38: CAUCASIA | J38: DISTRICOL VALENET PUNTO DE SER | K38: REDEBAN | L38: FO-25-1911759 | M38: 45992.412 | N38: 45993.517 | O38: NO | P38: HARDWARE | Q38: TECLADO | R38: DAÑO POS | S38: AGREGADOR | T38: DISTRICOL | U38: EJECUTADO | V38: 01/12/2025 SE ESCALA PARA VISITA. LLAMAR ANTES DE VISITAR, CONFIRMAR FALLA Y DATOS | 02/12/2025 SE REALIZA CAMBIO DE DOS EQUIPOS POR DAÑO EN EL TECLADO, TODOS DOS TIENE LAS TECLAS BORROSAS NO SE VEN LOS NÚMEROS, ADICIONAL SE REINICIA CONSTANTEMENTE AL INGRESAR LAS TARJETAS O DIGITAR CLAVES, TAMBIÉN SE CAMBIA PINPAD POR COMPATIBILIDAD Y SE INSTALA MAGICBOX OK, EQUIPOS Y ACCESORIOS INSTADOS OPERATIVOS, SE REALIZAN PRUEBAS EXITOSAS, CLIENTE CB VALIDA SALDO ANTES Y DESPUÉS DEL MANTENIMIENTO OK, PUNTO SE DEJA OPERATIVO OK. | W38: VISITA TECNICA | X38: AB19Z324 | Y38: TIPO II | Z38: TERRESTRE | AA38: GONZALEZ FERRER JESUS ALEXANDER | AB38: 1 | AC38: 0 | AD38: 144968 | AE38: 140396 | AF38: 144968
A39: BARRANQUILLA | B39: COSTA | C39: 0004-0001 | D39: 8001 | E39: 3082776 | F39: 3007077298 | G39: INCIDENTE | H39: ATLANTICO | I39: BARRANQUILLA | J39: BARRIO EVARISTO SOURDIS BARRAN | K39: REDEBAN | L39: FO-25-1912125 | M39: 45992.444 | N39: 45992.744 | O39: NO | P39: HARDWARE | Q39: NO ENCIENDE | R39: DAÑO POS | S39: CB UNO A UNO | T39: CB UNO A UNO | U39: EJECUTADO | V39: 01/12/2025 SE ESCALA PARA VISITA. LLAMAR ANTES DE VISITAR, CONFIRMAR FALLA Y DATOS | 01/12/2025 SE LLEGA AL CB YA QUE INFORMABA QUE EL DATAFONO NO PRENDÍA, SE TRATA DE COMUNICAR AL NÚMERO 3002252920, PERO NO SE LOGRA COMUNICACIÓN, AL LLEGAR A SITIO ME INFORMAN QUE YA ESTÁ OK, QUE EL TOMA DONDE ESTABA CONECTADO ESTABA SULFATO, SE CAMBIA DE TOMA Y QUEDA FUNCIONANDO OK | W39: VISITA TECNICA | X39: FACZZ875 | Y39: TIPO I | Z39: TERRESTRE | AA39: DE AVILA SIADES ALBERTO ENRIQUE | AB39: 1 | AC39: 0 | AD39: 65960 | AE39: 75096 | AF39: 65960
A40: IBAGUE | B40: REMOTAS | C40: 0004-0007 | D40: 17380 | E40: 3083033 | F40: 3007047743 | G40: INCIDENTE | H40: CALDAS | I40: LA DORADA | J40: BARRIO GUARINOCITO LA DORADA | K40: REDEBAN | L40: FO-25-1912231 | M40: 45992.453 | N40: 45993.606 | O40: NO | P40: HARDWARE | Q40: ALERT IRRUPTION | R40: ALERT IRRUPTION | S40: CB UNO A UNO | T40: CB UNO A UNO | U40: EJECUTADO | V40: 01/12/2025 SE ESCALA PARA VISITA. LLAMAR ANTES DE VISITAR, CONFIRMAR FALLA Y DATOS | 02/12/2025 SE CAMBIA DATÁFONO POR ALERT IRRUPTION. SE HACEN LAS PRUEBAS DE TRANSACCIONES TODO OK | W40: VISITA TECNICA | X40: XP00F490 | Y40: TIPO III | Z40: TERRESTRE | AA40: VARGAS HERRERA JHON JAIRO | AB40: 1 | AC40: 0 | AD40: 275729 | AE40: 196537 | AF40: 275729
A41: MEDELLIN | B41: NOROCCIDENTE | C41: 0004-0005 | D41: 5001 | E41: 3083130 | F41: 3007039365 | G41: INCIDENTE | H41: ANTIOQUIA | I41: MEDELLIN | J41: DISTRICOL KAIROS | K41: REDEBAN | L41: FO-25-1912479 | M41: 45992.457 | N41: 45992.665 | O41: NO | P41: HARDWARE | Q41: NO ENCIENDE | R41: DAÑO POS | S41: AGREGADOR | T41: DISTRICOL | U41: EJECUTADO | V41: 01/12/2025 SE ESCALA PARA VISITA. LLAMAR ANTES DE VISITAR, CONFIRMAR FALLA Y DATOS | 01/12/2025 SE CAMBIA EQUIPO POR DAÑO EN PUERTO ENERGÍA | W41: VISITA TECNICA | X41: AA08Z454 | Y41: TIPO I | Z41: TERRESTRE | AA41: ALVAREZ ARENAS VICTOR HUGO | AB41: 1 | AC41: 0 | AD41: 65960 | AE41: 75096 | AF41: 65960
A42: CUCUTA | B42: SANTANDERES | C42: 0004-0008 | D42: 54001 | E42: 3083139 | F42: 3007061712 | G42: INCIDENTE | H42: NORTE DE SANTANDER | I42: CUCUTA | J42: PTM CUCUTA VARIEDADES REYMAR 3 | K42: REDEBAN | L42: FO-25-1912470 | M42: 45992.46 | N42: 45993.435 | O42: NO | P42: HARDWARE | Q42: PINPAD | R42: DAÑO POS | S42: AGREGADOR | T42: COMCARD - PTM | U42: EJECUTADO | V42: 01/12/2025 SE ESCALA PARA VISITA. LLAMAR ANTES DE VISITAR, CONFIRMAR FALLA Y DATOS | 02/12/2025 SE REALIZA VISITA AL COMERCIO Y SE EVIDENCIA QUE EL PINPAC NO LEE TARJETAS SE REALIZA CAMBIO DE PINPAC PRUEBAS EXITOSAS | W42: VISITA TECNICA | X42: FUA0L506 FUA0L603 | Y42: TIPO I | Z42: TERRESTRE | AA42: MORA VEGA JEAMPIER | AB42: 1 | AC42: 0 | AD42: 65960 | AE42: 75096 | AF42: 65960
A43: MEDELLIN | B43: NOROCCIDENTE | C43: 0004-0005 | D43: 5615 | E43: 3083142 | F43: 3007078985 | G43: INCIDENTE | H43: ANTIOQUIA | I43: RIONEGRO | J43: PTM RIONEGRO SUPERMERCADO SANT | K43: REDEBAN | L43: FO-25-1912469 | M43: 45992.461 | N43: 45992.559 | O43: NO | P43: HARDWARE | Q43: LECTOR DE TARJETAS | R43: MENSAJE RETIRE TARJETA | S43: AGREGADOR | T43: COMCARD - PTM | U43: EJECUTADO | V43: 01/12/2025 SE ESCALA PARA VISITA. LLAMAR ANTES DE VISITAR, CONFIRMAR FALLA Y DATOS | 01/12/2025 SE HACE MANTENIMIENTO OK SE LIMPIA LECTOR DE TARJETA NO SE PUEDE REALIZAR PRUEBAS EXITOSAS YA QUÉ BCO ESTA CAÍDO | W43: VISITA TECNICA | X43: FATZZ893 FATZZ518 | Y43: TIPO II | Z43: TERRESTRE | AA43: DIAZ ZABALA FRANCIS DUBAN | AB43: 1 | AC43: 0 | AD43: 144968 | AE43: 140396 | AF43: 144968
A44: TUNJA | B44: SANTANDERES | C44: 0004-0008 | D44: 15759 | E44: 3083590 | F44: 3007053870 | G44: INCIDENTE | H44: BOYACA | I44: SOGAMOSO | J44: BARRIO SAN RAFAEL SOGAMOSO | K44: REDEBAN | L44: FO-25-1912814 | M44: 45992.487 | N44: 45993.544 | O44: NO | P44: HARDWARE | Q44: COMUNICACION | R44: MENSAJE CABLE DE RED DESCONECTADO | S44: CB UNO A UNO | T44: CB UNO A UNO | U44: EJECUTADO | V44: 01/12/2025 SE ESCALA PARA VISITA. LLAMAR ANTES DE VISITAR, CONFIRMAR FALLA Y DATOS | 02/12/2025 SE REALIZA VISITA AL COMERCIO, SE REALIZA PONCHADO DEL CABLE DE RED YA QUE PRESENTABA FALLAS Y CAMBIO DE MAGIC BOX, PRUEBAS OK. | W44: VISITA TECNICA | X44: UV00N437 | Y44: TIPO II | Z44: TERRESTRE | AA44: SOLER HOYOS CRISTIAN LEONARDO | AB44: 1 | AC44: 0 | AD44: 144968 | AE44: 140396 | AF44: 144968
A45: PASTO | B45: SUROCCIDENTE Y EJE CAFETERO | C45: 0004-0003 | D45: 86568 | E45: 3083774 | F45: 3007057321 | G45: INCIDENTE | H45: PUTUMAYO | I45: PUERTO ASIS | J45: BARRIO VDA LA CARMELITA PUERTO | K45: REDEBAN | L45: FO-25-1912809 | M45: 45992.489 | N45: 45994.613 | O45: NO | P45: HARDWARE | Q45: IMPRESION | R45: RODILLO AVERIADO | S45: CB UNO A UNO | T45: CB UNO A UNO | U45: EJECUTADO | V45: 01/12/2025 SE ESCALA PARA VISITA. LLAMAR ANTES DE VISITAR, CONFIRMAR FALLA Y DATOS | 03/12/2025 SE REALIZA CAMBIO DE EQUIPO POR DAÑO EN RODILLOS SE CONFIGURA NUEVO EQUIPO SE INSTALA VERSION SE CONFIGURA PARÁMETROS SE INICIALIZA SE REALIZA PRUEBAS DE FUNCIONAMIENTO EXITOSAS CB QUEDA OPERATIVO | W45: VISITA TECNICA | X45: TRSZZ888 | Y45: TIPO IV | Z45: TERRESTRE | AA45: BRAVO MADROÑERO OSCAR ESTEBAN | AB45: 1 | AC45: 0 | AD45: 479589 | AE45: 196537 | AF45: 479589
... A57: BARRANQUILLA | B57: COSTA | C57: 0004-0001 | D57: 8001 | E57: 3086078 | F57: 3007034328 | G57: INCIDENTE | H57: ATLANTICO | I57: BARRANQUILLA | J57: BARRIO PRADERA BARRANQUILLA 1 | K57: REDEBAN | L57: FO-25-1915067 | M57: 45992.65 | N57: 45993.528 | O57: NO | P57: HARDWARE | Q57: LECTOR DE BARRAS | R57: CABLE LECTORA AVERIADO | S57: CB UNO A UNO | T57: CB UNO A UNO | U57: EJECUTADO | V57: 01/12/2025 SE ESCALA PARA VISITA. LLAMAR ANTES DE VISITAR, CONFIRMAR FALLA Y DATOS | 02/12/2025 SE REMPLAZA LECTOR DE BARRAS, EL QUE TENÍA APAGABA AL MOVER EL CABLE | W57: VISITA TECNICA | X57: 6ZZZZ712 | Y57: TIPO I | Z57: TERRESTRE | AA57: DE AVILA SIADES ALBERTO ENRIQUE | AB57: 1 | AC57: 0 | AD57: 65960 | AE57: 75096 | AF57: 65960
A58: CARTAGENA | B58: COSTA | C58: 0004-0001 | D58: 13001 | E58: 3086092 | F58: 3007025260 | G58: INCIDENTE | H58: BOLIVAR | I58: CARTAGENA | J58: ARA0113 CARTAGENA TESCA | K58: REDEBAN | L58: FO-25-1915108 | M58: 45992.656 | N58: 45992.688 | P58: SOFTWARE | Q58: ACTUALIZACION | R58: VERSION CARGA SO VR | S58: RETAIL | T58: TIENDAS ARA | V58: 01/12/2025 SE PROCEDE A CERRAR YA QUE CASO PERTENECE A LA CADENA ARA Y NO ES ATENDIDO POR PARTE NUESTRA. SE ESCALA A SERVICIO AL CLIENTE | 01/12/2025 SE PROCEDE A CERRAR YA QUE CASO PERTENECE A LA CADENA ARA Y NO ES ATENDIDO POR PARTE NUESTRA. SE ESCALA A SERVICIO AL CLIENTE | 01/12/2025 SE PROCEDE A CERRAR YA QUE CASO PERTENECE A LA CADENA ARA Y NO ES ATENDIDO POR PARTE NUESTRA. SE ESCALA A SERVICIO AL CLIENTE | W58: SOPORTE TELEFONICO | Y58: TIPO I | Z58: TERRESTRE | AA58: TORO CARDONA ELIZABETH | AB58: 0 | AC58: 0 | AD58: 41241 | AE58: 0 | AF58: 41241
A59: MEDELLIN | B59: NOROCCIDENTE | C59: 0004-0005 | D59: 5001 | E59: 3086344 | F59: 3007024600 | G59: INCIDENTE | H59: ANTIOQUIA | I59: MEDELLIN | J59: REDY MEDELLIN MORAVIA | K59: REDEBAN | L59: FO-25-1915225 | M59: 45992.673 | N59: 45993.703 | O59: NO | P59: HARDWARE | Q59: LECTOR DE BARRAS | R59: DAÑO POS | S59: ROBUSTO | T59: REDY | U59: EJECUTADO | V59: 01/12/2025 SE ESCALA PARA VISITA. LLAMAR ANTES DE VISITAR, CONFIRMAR FALLA Y DATOS | 02/12/2025 RETRASO DEBIDO A MUCHO TRANCON POR EL CENTRO DE LA CIUDAD | 02/12/2025 SE REALIZA CAMBIO DE LECTORA DEBIDO A DAÑO REINICIOS Y NO TRASMITE DATA, PRUEBAS OK | W59: VISITA TECNICA | X59: A00IZ755 | Y59: TIPO I | Z59: TERRESTRE | AA59: QUINTERO SANCHEZ JUAN SEBASTIAN | AB59: 1 | AC59: 0 | AD59: 65960 | AE59: 75096 | AF59: 65960
A60: VALLEDUPAR | B60: COSTA | C60: 0004-0001 | D60: 20238 | E60: 3086349 | F60: 3007053121 | G60: INCIDENTE | H60: CESAR | I60: EL COPEY | J60: BARRIO CENTRO EL COPEY 3 | K60: REDEBAN | L60: FO-25-1915223 | M60: 45992.674 | N60: 45994.53 | O60: NO | P60: HARDWARE | Q60: TECLADO | R60: DAÑO POS | S60: CB UNO A UNO | T60: CB UNO A UNO | U60: EJECUTADO | V60: 01/12/2025 SE ESCALA PARA VISITA. LLAMAR ANTES DE VISITAR, CONFIRMAR FALLA Y DATOS | 03/12/2025 SE REALIZA CAMBIO DE DATAFONO, YA QUE NO LE FUNCIONABAN ALGUNAS TECLAS, SE REALIZAN PRUEBAS DEJANDO SERVICIO FUNCIONAL AL 100 % | W60: VISITA TECNICA | X60: LN00S796 | Y60: TIPO II | Z60: TERRESTRE | AA60: MONTES DIAZ JOHN FRED | AB60: 1 | AC60: 0 | AD60: 144968 | AE60: 140396 | AF60: 144968
A61: APARTADO | B61: NOROCCIDENTE | C61: 0004-0005 | D61: 5045 | E61: 3086378 | F61: 3007081726 | G61: INCIDENTE | H61: ANTIOQUIA | I61: APARTADO | J61: DISTRICOL FERRETERIA SHADDAY | K61: REDEBAN | L61: FO-25-1915261 | M61: 45992.681 | N61: 45993.433 | O61: NO | P61: HARDWARE | Q61: IMPRESION | R61: NO IMPRIME UNO O VARIOS CARACTERES | S61: AGREGADOR | T61: DISTRICOL | U61: EJECUTADO | V61: 01/12/2025 SE ESCALA PARA VISITA. LLAMAR ANTES DE VISITAR, CONFIRMAR FALLA Y DATOS | 02/12/2025 DATAFONOS SACA COMPROBANTE CON RAYAS EN EL MEDIO, SE PROCEDE A HACER LIMPIEZA EN EL DEPÓSITO DEL PAPEL Y SE CORRIGE LA FALLA SE HACEN PRUEBAS DE IMPRESIÓN Y SE DEJA TODO FUNCIONANDO CORRECTAMENTE | W61: VISITA TECNICA | X61: SUZZZ696 | Y61: TIPO I | Z61: TERRESTRE | AA61: SALDARRIAGA MIRANDA SANTIAGO | AB61: 1 | AC61: 0 | AD61: 65960 | AE61: 75096 | AF61: 65960
A62: APARTADO | B62: NOROCCIDENTE | C62: 0004-0005 | D62: 5837 | E62: 3087109 | F62: 3007041224 | G62: INCIDENTE | H62: ANTIOQUIA | I62: TURBO | J62: BARRIO EL 3 TURBO | K62: REDEBAN | L62: FO-25-1915439 | M62: 45992.711 | N62: 45994.602 | O62: NO | P62: HARDWARE | Q62: IMPRESION | R62: NO AVANZA PAPEL | S62: CB UNO A UNO | T62: CB UNO A UNO | U62: EJECUTADO | V62: 01/12/2025 SE ESCALA PARA VISITA. LLAMAR ANTES DE VISITAR, CONFIRMAR FALLA Y DATOS | 03/12/2025 DATAFONO NO AVANZA PAPEL, YA SE LE CAMBIÓ TAPA IMPRESORA EN VISITAS ANTERIORES Y SIGUE LA FALLA, SE CAMBIA DATAFONOS, SE HACEN PRUEBAS Y SE DEJA TODO FUNCIONANDO CORRECTAMENTE | W62: VISITA TECNICA | X62: 9L8ZZ665 | Y62: TIPO II | Z62: TERRESTRE | AA62: SALDARRIAGA MIRANDA SANTIAGO | AB62: 1 | AC62: 0 | AD62: 144968 | AE62: 140396 | AF62: 144968
A63: MONTERIA | B63: COSTA | C63: 0004-0001 | D63: 23001 | E63: 3087318 | F63: 3007048699 | G63: INCIDENTE | H63: CORDOBA | I63: MONTERIA | J63: DISTRICOL DROGUERIA LA NOVENA | K63: REDEBAN | L63: FO-25-1915497 | M63: 45992.736 | N63: 45993.523 | O63: NO | P63: HARDWARE | Q63: LECTOR DE TARJETAS | R63: DAÑO POS | S63: AGREGADOR | T63: DISTRICOL | U63: EJECUTADO | V63: 01/12/2025 SE ESCALA PARA VISITA. LLAMAR ANTES DE VISITAR, CONFIRMAR FALLA Y DATOS | 02/12/2025 SE REALIZA INSPECCIÓN DEL EQUIPO DONDE EVIDENCIA EL ERROR QUE PRESENTA CON ALGUNAS TARJETAS EN PROCESO DE RETIRO (RETIRE TARJETAS) TAMBIÉN SE EVIDENCIA QUE EL TECLADO SE ENCUENTRA EN DETERIORO ALGUNOS NUMERO NO SE VISUALIZAN, SE PROCEDE A REALIZAR CAMBIO DE EQUIPO CREAMOS USUARIO OPERATIVO Y ADMINISTRATIVOS SE REALIZAN PRUEBAS RESULTADO EXITOSO, EL CB QUEDA OPERANDO CON NORMALIDAD | W63: VISITA TECNICA | X63: BA00L833 | Y63: TIPO I | Z63: TERRESTRE | AA63: ARRAZOLA HERNANDEZ NICOLAS AUGUSTO | AB63: 1 | AC63: 0 | AD63: 65960 | AE63: 75096 | AF63: 65960
A64: CALI | B64: SUROCCIDENTE Y EJE CAFETERO | C64: 0004-0003 | D64: 76111 | E64: 3087383 | F64: 3007041711 | G64: INCIDENTE | H64: VALLE DEL CAUCA | I64: GUADALAJARA DE BUGA | J64: BARRIO CENTRO GUADALAJARA DE B | K64: REDEBAN | L64: FO-25-1916928 | M64: 45993.333 | N64: 45994.51 | O64: NO | P64: SOFTWARE | Q64: DATOS DESACTUALIZADOS | R64: FECHA DIRECCION DESACTUALZADA | S64: UNO A UNO | T64: CB UNO A UNO | U64: EJECUTADO / CANCELADO | V64: 02/12/2025 SE ESCALA PARA VISITA. LLAMAR ANTES DE VISITAR, CONFIRMAR FALLA Y DATOS | 03/12/2025 VISITA FALLIDA, NO AUTORIZARON MANIPULAR EL EQUIPO, PORQUE LA CLIENTA NO SE PUDO COMUNICAR CON LA LÍNEA DE ATENCIÓN DEL BANCO PARA VALIDAR LOS DATOS DEL TÉCNICO, LA CLIENTA INFORMO QUE EN LA LINEA LE INDICARON NO DEJAR MANIPULAR EL EQUIPO | W64: VISITA TECNICA | X64: VISITA FALLI | Y64: TIPO II | Z64: TERRESTRE | AA64: PAREDES CASTILLO DIEGO | AB64: 1 | AC64: 0 | AD64: 144968 | AE64: 140396 | AF64: 144968
A65: MONTERIA | B65: COSTA | C65: 0004-0001 | D65: 5154 | E65: 3087385 | F65: 3007077747 | G65: INCIDENTE | H65: ANTIOQUIA | I65: CAUCASIA | J65: PTM CAUCASIA TIENDA AHORRE MAS | K65: REDEBAN | L65: FO-25-1916924 | M65: 45993.333 | N65: 45994.403 | O65: NO | P65: SOFTWARE | Q65: CIERRE | R65: CIERRE NO HABILITADO | S65: AGREGADOR | T65: COMCARD - PTM | U65: EJECUTADO | V65: 02/12/2025 SE ESCALA PARA VISITA. LLAMAR ANTES DE VISITAR, CONFIRMAR FALLA Y DATOS | 03/12/2025 SE REALIZA MANTENIMIENTO AL SISTEMA OPERATIVO Y VERSIÓN, INSTALACIÓN DE NUEVA VERSIÓN Y SISTEMA POR USB OK, CONFIGURACIÓN OK, INICIALIZACIÓN EXITOSAS, HABILITACIÓN DE CIERRES OK, PRUEBAS CB OK, PRUEBAS COMERCIO OK, CLIENTE CB VALIDA SALDO ANTES Y DESPUÉS DEL MANTENIMIENTO OK, CB SE DEJA OPERATIVO SIN NOVEDAD | W65: VISITA TECNICA | X65: 10NZZ037 KA00J126 | Y65: TIPO II | Z65: TERRESTRE | AA65: GONZALEZ FERRER JESUS ALEXANDER | AB65: 1 | AC65: 0 | AD65: 144968 | AE65: 140396 | AF65: 144968
A66: MEDELLIN | B66: NOROCCIDENTE | C66: 0004-0005 | D66: 5360 | E66: 3087583 | F66: 3007032941 | G66: INCIDENTE | H66: ANTIOQUIA | I66: ITAGUI | J66: COMCARD ITAGUI PAPELERIA ASTUR | K66: REDEBAN | L66: FO-25-1916917 | M66: 45993.333 | N66: 45993.52 | O66: NO | P66: HARDWARE | Q66: COMUNICACION | R66: DAÑO POS | S66: AGREGADOR | T66: COMCARD - PTM | U66: EJECUTADO | V66: 02/12/2025 SE ESCALA ACTIVIDAD PARA GESTION WOMPI | 02/12/2025 SE REALIZA CAMBIO DE EQUIPO POR PUERTO ETH MALO SE HACEN PRUEBAS OK | W66: VISITA TECNICA | X66: 11XZZ538 | Y66: TIPO I | Z66: TERRESTRE | AA66: MONTOYA VELEZ ANDRES FELIPE | AB66: 1 | AC66: 0 | AD66: 65960 | AE66: 75096 | AF66: 65960
A67: BUCARAMANGA | B67: SANTANDERES | C67: 0004-0008 | D67: 68081 | E67: 3088908 | F67: 3007047189 | G67: INCIDENTE | H67: SANTANDER | I67: BARRANCABERMEJA | J67: PTM BARRANCABERMEJA VARIEDADE | K67: REDEBAN | L67: FO-25-1917475 | M67: 45993.375 | N67: 45994.572 | O67: NO | P67: HARDWARE | Q67: TECLADO | R67: DAÑO POS | S67: AGREGADOR | T67: COMCARD - PTM | U67: EJECUTADO | V67: 02/12/2025 SE INTENTA COMUNICACIÓN EN VARIASOASIONES CON LA SEÑORA JESSICA GABRIELA LOZANO ECHEVERRI AL NUMERO 3142063652 PARA CONFIRMAR FALLA Y DATOS PERO NO FUE POSIBLE, SE ESCALA AL COORDINADOR DE LA ZONA PAR VALIDAR EN SITIO | 03/12/2025 SE REALIZA VISITA, SE CAMBIA EQUIPO POR DETERIORO EN TECLADO SE REALIZAN PRUEBAS EXITOSA | W67: VISITA TECNICA | X67: AD00C939 | Y67: TIPO III | Z67: TERRESTRE | AA67: PEÑA DIAZ IVAN YESID | AB67: 1 | AC67: 0 | AD67: 275729 | AE67: 196537 | AF67: 275729
A68: BOGOTA | B68: CUNDINAMARCA | C68: 0004-0004 | D68: 11001 | E68: 3089008 | F68: 3007072338 | G68: INCIDENTE | H68: CUNDINAMARCA | I68: BOGOTA | J68: PTM MALU PET | K68: REDEBAN | L68: FO-25-1917473 | M68: 45993.378 | N68: 45994.358 | O68: NO | P68: HARDWARE | Q68: ALERT IRRUPTION | R68: ALERT IRRUPTION | S68: AGREGADOR | T68: COMCARD - PTM | U68: CANCELADO | V68: 02/12/2025 SE ESCALA PARA VISITA. LLAMAR ANTES DE VISITAR, CONFIRMAR FALLA Y DATOS | 03/12/2025 SE VISITA COMERCIO PERO ESTÁ CERRADO PARA HACER LA ACTIVIDAD SE ESTÁ ESPERANDO ES SITIO | 03/12/2025 SE VISITA COMERCIO PERO ESTÁ CERRADO INDICA LA PERSONA QUE HABLE EN LAS HORAS DE LA TARDES SE INDICA QUE TIENE QUE VOLVER A PEDIR EL SERVICIO | W68: VISITA TECNICA | Y68: TIPO I | Z68: TERRESTRE | AA68: LEAL POVEDA YOHAN SEBASTIAN | AB68: 1 | AC68: 0 | AD68: 65960 | AE68: 75096 | AF68: 65960
A69: MEDELLIN | B69: NOROCCIDENTE | C69: 0004-0005 | D69: 5360 | E69: 3089331 | F69: 3007066371 | G69: INCIDENTE | H69: ANTIOQUIA | I69: ITAGUI | J69: DISTRICOL FRUTAS Y VERDURAS | K69: REDEBAN | L69: FO-25-1917472 | M69: 45993.396 | N69: 45993.565 | O69: NO | P69: HARDWARE | Q69: IMPRESION | R69: NO IMPRIME UNO O VARIOS CARACTERES | S69: AGREGADOR | T69: DISTRICOL | U69: EJECUTADO | V69: 02/12/2025 SE ESCALA PARA VISITA. LLAMAR ANTES DE VISITAR, CONFIRMAR FALLA Y DATOS | 02/12/2025 SE REALIZA CAMBIO DE DATAFONO PORQUE IMPRIME BORROSO SE HACEN PRUEBAS OK | W69: VISITA TECNICA | X69: 1A00Q871 | Y69: TIPO I | Z69: TERRESTRE | AA69: MONTOYA VELEZ ANDRES FELIPE | AB69: 1 | AC69: 0 | AD69: 65960 | AE69: 75096 | AF69: 65960
A70: MEDELLIN | B70: NOROCCIDENTE | C70: 0004-0005 | D70: 5001 | E70: 3089544 | F70: 3007079006 | G70: INCIDENTE | H70: ANTIOQUIA | I70: MEDELLIN | J70: PTM CARIBE MEDELLIN ALMACEN Y | K70: REDEBAN | L70: FO-25-1917808 | M70: 45993.414 | N70: 45993.546 | O70: NO | P70: HARDWARE | Q70: CABLEADO | R70: DAÑO POS | S70: AGREGADOR | T70: COMCARD - PTM | U70: EJECUTADO | V70: 02/12/2025 SE ESCALA PARA VISITA. LLAMAR ANTES DE VISITAR, CONFIRMAR FALLA Y DATOS | 02/12/2025 FUENTE DE PODER DAÑADA, SE CAMBIA, EQUIPOS OPERATIVOS | W70: VISITA TECNICA | X70: FATZZ880 FATZZ493 | Y70: TIPO I | Z70: TERRESTRE | AA70: BADEL ACUÑA LUIS ALBERTO | AB70: 1 | AC70: 0 | AD70: 65960 | AE70: 75096 | AF70: 65960
A71: NEIVA | B71: REMOTAS | C71: 0004-0007 | D71: 41298 | E71: 3090761 | F71: 3007030513 | G71: INCIDENTE | H71: HUILA | I71: GARZON | J71: DISTRICOL DEPOSITO Y SUPERMERC | K71: REDEBAN | L71: FO-25-1918846 | M71: 45993.486 | N71: 45994.688 | O71: NO | P71: HARDWARE | Q71: IMPRESION | R71: NO AVANZA PAPEL | S71: AGREGADOR | T71: DISTRICOL | U71: EJECUTADO | V71: 02/12/2025 SE INTENTA COMUNICACION CON EL USUARIO AL NUMERO 3202758939 NO CONTESTAN SE ESCALA PARA VISITA. LLAMAR ANTES DE VISITAR, CONFIRMAR FALLA Y DATOS | 03/12/2025 NO SE EVIDENCIA FALLA , PERO CLIENTE INSISTE EN EL CAMBIO DATAFONO , SE REALIZA CAMBIO EQUIPO , SE CONFIGURA E INICIALIZA DATAFONO, SE CREA USUARIO Y CLAVE CON EL CLIENTE, SE REALIZA PRUEBAS OK | W71: VISITA TECNICA | X71: BIZZZ865 | Y71: TIPO III | Z71: TERRESTRE | AA71: ANDRADE HERNANDEZ JUAN CARLOS | AB71: 1 | AC71: 0 | AD71: 275729 | AE71: 196537 | AF71: 275729
A72: VALLEDUPAR | B72: COSTA | C72: 0004-0001 | D72: 20001 | E72: 3090858 | F72: 3007069837 | G72: INCIDENTE | H72: CESAR | I72: VALLEDUPAR | J72: PTM VALLEDUPAR DISTRIBUCIONES | K72: REDEBAN | L72: FO-25-1918845 | M72: 45993.486 | N72: 45993.727 | O72: NO | P72: HARDWARE | Q72: ALERT IRRUPTION | R72: ALERT IRRUPTION | S72: AGREGADOR | T72: COMCARD - PTM | U72: EJECUTADO | V72: 02/12/2025 SE ESCALA PARA VISITA. LLAMAR ANTES DE VISITAR, CONFIRMAR FALLA Y DATOS | 02/12/2025 SE VISITA CB Y SE LE HACE CAMBIO DE DATAFONO POR ERROR EN PANTALLA | W72: VISITA TECNICA | X72: ON004690 ON004829 | Y72: TIPO I | Z72: TERRESTRE | AA72: BENITEZ CARVAJAL ALVARO JAVIER | AB72: 1 | AC72: 0 | AD72: 65960 | AE72: 75096 | AF72: 65960
A73: MEDELLIN | B73: NOROCCIDENTE | C73: 0004-0005 | D73: 5284 | E73: 3091419 | F73: 3007066053 | G73: INCIDENTE | H73: ANTIOQUIA | I73: FRONTINO | J73: DISTRICOL AGROPECUARIA EL BODE | K73: REDEBAN | L73: FO-25-1919358 | M73: 45993.515 | N73: 45994.413 | O73: NO | P73: HARDWARE | Q73: ALERT IRRUPTION | R73: ALERT IRRUPTION | S73: AGREGADOR | T73: DISTRICOL | U73: EJECUTADO | V73: 02/12/2025 SE ESCALA PARA VISITA. LLAMAR ANTES DE VISITAR, CONFIRMAR FALLA Y DATOS | 03/12/2025 SE CAMBIA EQUIPO POR ALERTA INTERRUPTION TODO QUEDA OK | W73: VISITA TECNICA | X73: 7A00K515 | Y73: TIPO IV | Z73: TERRESTRE | AA73: ALVAREZ ARENAS VICTOR HUGO | AB73: 1 | AC73: 0 | AD73: 479589 | AE73: 196537 | AF73: 479589
A74: MANIZALES | B74: SUROCCIDENTE Y EJE CAFETERO | C74: 0004-0002 | D74: 17001 | E74: 3091520 | F74: 3007066757 | G74: INCIDENTE | H74: CALDAS | I74: MANIZALES | J74: DISTRICOL PAPEL Y VAR LUPITA | K74: REDEBAN | L74: FO-25-1919552 | M74: 45993.56 | N74: 45994.423 | O74: NO | P74: HARDWARE | Q74: NO ENCIENDE SE REINICIA | R74: FUENTE PODER AVERIADA | S74: AGREGADOR | T74: DISTRICOL | U74: EJECUTADO | V74: 02/12/2025 SE ESCALA PARA VISITA. LLAMAR ANTES DE VISITAR, CONFIRMAR FALLA Y DATOS | 03/12/2025 SE REALIZA VISITA SE CAMBIA FUENTE DE PODER YA QUE NO ENCIENDE, SE HACEN PRUEBAS SERVICIO OK | W74: VISITA TECNICA | X74: 3A0CZ717 | Y74: TIPO I | Z74: TERRESTRE | AA74: AGUIRRE HENAO RAUL EDUARDO | AB74: 1 | AC74: 0 | AD74: 65960 | AE74: 75096 | AF74: 65960
A75: BUCARAMANGA | B75: SANTANDERES | C75: 0004-0008 | D75: 81001 | E75: 3093085 | F75: 3007059562 | G75: INCIDENTE | H75: ARAUCA | I75: ARAUCA | J75: PTM ARAUCA PAPELERIA CENTRO DE | K75: REDEBAN | L75: FO-25-1921111 | M75: 45993.675 | N75: 45995.394 | O75: NO | P75: HARDWARE | Q75: TECLADO | R75: DAÑO POS | S75: AGREGADOR | T75: COMCARD - PTM | U75: EJECUTADO | V75: 02/12/2025 EN COMUNICACION CON EL SR@ MIGUEL BENAVIDEZ AL NUMERO 3185621593 NO CONTESTAN LLAMAR PARA CONFIRMAR FALLA Y DATOS . SE ESCALA PARA VISITA. | 04/12/2025 SE CAMBIA EQUIPO DEBIDO TECLADO BORROSO SE REALIZA INYECCIÓN DE SISTEMA Y VERSIÓN INICIALIZADA OK PRUEBAS OK CUBRE CLAVE OK | W75: VISITA TECNICA | X75: HA008115 | Y75: TIPO V | Z75: AEREO | AA75: HERRERA LUQUE SAUL JAVIER | AB75: 1 | AC75: 0 | AD75: 988463 | AE75: 196537 | AF75: 988463
A76: YOPAL | B76: REMOTAS | C76: 0004-0007 | D76: 85001 | E76: 3093163 | F76: 3007075008 | G76: INCIDENTE | H76: CASANARE | I76: YOPAL | J76: DISTRICOL CACHARRERÍA Y PAPELE | K76: REDEBAN | L76: FO-25-1921878 | M76: 45993.685 | N76: 45995.488 | O76: NO | P76: HARDWARE | Q76: DETERIORO | R76: DATAFONO | S76: AGREGADOR | T76: DISTRICOL | U76: EJECUTADO | V76: 02/12/2025 SE ESCALA PARA VISITA. LLAMAR ANTES DE VISITAR, CONFIRMAR FALLA Y DATOS | 03/12/2025 SE SALIO A RUTA EN HORAS DE LA MAÑANA PARA ACTIVIDADES, AL MOMENTO DE RETORNO SE ENCUENTRA CON LA VIA CERRADA POR PROTESTAS DE TAXISTAS Y COMUNIDAD, NO HAY INGRESO A CIUDAD ORIGEN. POR TAL MOTIVO NO SE PUEDE ATENDER ACTIVIDAD DE YOPAL. | 04/12/2025 SE VISITA COMERCIO, SE REALIZA CAMBIO DE DATAFONO, NO IMPRIME VARIOS CARACTERES. OPERATIVO EL SERVICIO. PRUEBAS OK | W76: VISITA TECNICA | X76: LAYZZ458 | Y76: TIPO I | Z76: TERRESTRE | AA76: BERNAL ELAICA EDGAR ALEXIS | AB76: 1 | AC76: 0 | AD76: 65960 | AE76: 75096 | AF76: 65960
A77: MANIZALES | B77: SUROCCIDENTE Y EJE CAFETERO | C77: 0004-0002 | D77: 17001 | E77: 3093655 | F77: 3007082335 | G77: INCIDENTE | H77: CALDAS | I77: MANIZALES | J77: PTM MANIZALES DROGUERIA FARMAM | K77: REDEBAN | L77: FO-25-1921901 | M77: 45993.723 | N77: 45994.508 | O77: NO | P77: HARDWARE | Q77: ALERT IRRUPTION | R77: ALERT IRRUPTION | U77: EJECUTADO | V77: 02/12/2025 SE ESCALA PARA VISITA. LLAMAR ANTES DE VISITAR, CONFIRMAR FALLA Y DATOS | 03/12/2025 SE REALIZA VISITA SE CAMBIA DATAFONO POR MENSAJE ALERT IRRUPTION SE CREAN USUARIOS SE HACEN PRUEBAS SERVICIO OK | W77: VISITA TECNICA | X77: OB004847 OB004165 | Y77: TIPO I | Z77: TERRESTRE | AA77: AGUIRRE HENAO RAUL EDUARDO | AB77: 1 | AC77: 0 | AD77: 65960 | AE77: 75096 | AF77: 65960
A78: BUCARAMANGA | B78: SANTANDERES | C78: 0004-0008 | D78: 68001 | E78: 3093910 | F78: 3007044063 | G78: INCIDENTE | H78: SANTANDER | I78: BUCARAMANGA | J78: COLOMBIANA DE COMERCIO S A | K78: REDEBAN | L78: FO-25-1923399 | M78: 45994.333 | N78: 45994.594 | O78: NO | P78: SOFTWARE | Q78: ACTUALIZACION | R78: VERSION CARGA SO VR | S78: RETAIL | T78: CONTIGO / ALKOMPRAR | U78: EJECUTADO | V78: 03/12/2025 SE ESCALA PARA VISITA. LLAMAR ANTES DE VISITAR, CONFIRMAR FALLA Y DATOS | 03/12/2025 SE FORMATEAR 5 DATAFONIS SE ACTUALIZA S. O Y VERSION 9.90 SE HACEN PRUEBAS OK VISITA EXITOSA | W78: VISITA TECNICA | X78: 9AWZZ702-GZUZZ192-9AWZZ706-9AWZZ704-9AWZZ705 | Y78: TIPO I | Z78: TERRESTRE | AA78: GELVEZ MOGOLLON JOSE ELISEO | AB78: 1 | AC78: 0 | AD78: 65960 | AE78: 75096 | AF78: 65960
A79: MEDELLIN | B79: NOROCCIDENTE | C79: 0004-0005 | D79: 5088 | E79: 3093943 | F79: 3007059337 | G79: INCIDENTE | H79: ANTIOQUIA | I79: BELLO | J79: DISTRICOL TIENDA FERSAN | K79: REDEBAN | L79: FO-25-1923390 | M79: 45994.333 | N79: 45994.565 | P79: HARDWARE | Q79: IMPRESION | R79: NO IMPRIME UNO O VARIOS CARACTERES | S79: AGREGADOR | T79: DISTRICOL | V79: 03/12/2025 SE ESCALA PARA VISITA. LLAMAR ANTES DE VISITAR, CONFIRMAR FALLA Y DATOS | 03/12/2025 SE REALIZÓ LLAMADA TELEFÓNICA AL CORRESPONSAL BANCOLOMBIA PARA CONFIRMAR EL INCIDENTE REPORTADO CON EL DATÁFONO. EL USUARIO INDICÓ QUE LA NOVEDAD PERSISTE; SIN EMBARGO, INFORMÓ QUE EN LA FECHA DE HOY NO SE ENCUENTRA PRESENTE EN EL PUNTO DE ATENCIÓN. POR ESTA RAZÓN, NO SERÁ POSIBLE EFECTUAR LA VISITA TÉCNICA PROGRAMADA. | W79: SOPORTE TELEFONICO | Y79: TIPO I | Z79: TERRESTRE | AA79: MARTINEZ TOVAR OSCAR DAVID | AB79: 0 | AC79: 0 | AD79: 41241 | AE79: 0 | AF79: 41241
A80: CALI | B80: SUROCCIDENTE Y EJE CAFETERO | C80: 0004-0003 | D80: 76001 | E80: 3094011 | F80: 3007077988 | G80: INCIDENTE | H80: VALLE DEL CAUCA | I80: CALI | J80: PTM CALI VARIEDADES LA 8A | K80: REDEBAN | L80: FO-25-1923395 | M80: 45994.333 | N80: 45994.528 | O80: NO | P80: HARDWARE | Q80: LECTOR DE BARRAS | R80: DAÑO POS | S80: AGREGADOR | T80: COMCARD - PTM | U80: EJECUTADO | V80: 03/12/2025 SE ESCALA PARA VISITA. LLAMAR ANTES DE VISITAR, CONFIRMAR FALLA Y DATOS | 16/12/2025 SE REALIZA CAMBIO DE DATAFONO DEBIDO A PUERTO USB DAÑADO, SE REALIZA CAMBIO DEL EQUIPO NUEVO DEBIDO A DAÑO EN LA IMPRESORA, SE REALIZAN PRUEBAS OK | W80: VISITA TECNICA | X80: LMLZZ086 | Y80: TIPO I | Z80: TERRESTRE | AA80: MONTERO MUESES GIAN CARLO | AB80: 1 | AC80: 0 | AD80: 65960 | AE80: 75096 | AF80: 65960
A81: BOGOTA | B81: CUNDINAMARCA | C81: 0004-0004 | D81: 25290 | E81: 3094029 | F81: 3007023055 | G81: INCIDENTE | H81: CUNDINAMARCA | I81: FUSAGASUGA | J81: BARRIO CENTRO III FUSAGASUGA | K81: REDEBAN | L81: FO-25-1923392 | M81: 45994.333 | N81: 45995.366 | O81: NO | P81: HARDWARE | Q81: LECTOR DE BARRAS | R81: CABLE LECTORA AVERIADO | S81: CB UNO A UNO | T81: CB UNO A UNO | U81: EJECUTADO | V81: 03/12/2025 SE ESCALA PARA VISITA. LLAMAR ANTES DE VISITAR, CONFIRMAR FALLA Y DATOS | 04/12/2025 SE LLEGA A COMERCIO, ENCUENTRO QUE LA LECTORA TIENE EL CABLE AVERIADO, SE PROCEDE A REALIZAR EL CAMBIO, SE REALIZAN PRUEBAS SIN NOVEDAD. | W81: VISITA TECNICA | X81: GZZZZ645 | Y81: TIPO II | Z81: TERRESTRE | AA81: ARIAS QUILINDO JULIAN | AB81: 1 | AC81: 0 | AD81: 144968 | AE81: 140396 | AF81: 144968
A82: PEREIRA | B82: SUROCCIDENTE Y EJE CAFETERO | C82: 0004-0002 | D82: 66682 | E82: 3094039 | F82: 3007044209 | G82: INCIDENTE | H82: RISARALDA | I82: SANTA ROSA DE CABAL | J82: DISTRICOL PAPELERIA LA HERMOSA | K82: REDEBAN | L82: FO-25-1923389 | M82: 45994.333 | N82: 45994.512 | O82: NO | P82: HARDWARE | Q82: LECTOR DE BARRAS | R82: CABLE LECTORA AVERIADO | S82: AGREGADOR | T82: DISTRICOL | U82: EJECUTADO | V82: 03/12/2025 SE ESCALA PARA VISITA. LLAMAR ANTES DE VISITAR, CONFIRMAR FALLA Y DATOS | 03/12/2025 SE VISITA COMERCIO SE IDENTIFICA CABLE DE LECTORA AVERIADO SE REALIZA CAMBIO DE LECTORA SE REALIZA PRUEBAS OK | W82: VISITA TECNICA | X82: AC04Z206 | Y82: TIPO I | Z82: TERRESTRE | AA82: LOAIZA LOPEZ JHON FREDDY | AB82: 1 | AC82: 0 | AD82: 65960 | AE82: 75096 | AF82: 65960
A83: BOGOTA | B83: CUNDINAMARCA | C83: 0004-0004 | D83: 25151 | E83: 3094711 | F83: 3007050561 | G83: INCIDENTE | H83: CUNDINAMARCA | I83: CAQUEZA | J83: PTM CAQUEZA DROGAS CASA ORTIZ | K83: REDEBAN | L83: FO-25-1923568 | M83: 45994.345 | N83: 45995.647 | O83: NO | P83: HARDWARE | Q83: TECLADO | R83: DAÑO POS | S83: AGREGADOR | T83: COMCARD - PTM | U83: EJECUTADO | V83: 03/12/2025 SE ESCALA PARA VISITA. LLAMAR ANTES DE VISITAR, CONFIRMAR FALLA Y DATOS | 05/12/2025 SE REALIZA CAMBIO DE POS POR TECLADO DAÑADO | W83: VISITA TECNICA | X83: AAL0H212 | Y83: TIPO II | Z83: TERRESTRE | AA83: GONZALEZ FANDIÑO SANTIAGO ERNESTO | AB83: 1 | AC83: 0 | AD83: 144968 | AE83: 140396 | AF83: 144968
A84: BUCARAMANGA | B84: SANTANDERES | C84: 0004-0008 | D84: 68001 | E84: 3094721 | F84: 3007066749 | G84: INCIDENTE | H84: SANTANDER | I84: BUCARAMANGA | J84: PTM BUCARAMANGA DROGUERIA DAN | K84: REDEBAN | L84: FO-25-1923565 | M84: 45994.347 | N84: 45994.676 | O84: NO | P84: HARDWARE | Q84: LECTOR DE BARRAS | R84: DAÑO POS | S84: AGREGADOR | T84: COMCARD - PTM | U84: EJECUTADO | V84: 03/12/2025 SE ESCALA PARA VISITA. LLAMAR ANTES DE VISITAR, CONFIRMAR FALLA Y DATOS | 03/12/2025 SE ENCUENTRA PUERTO USB DAÑADO, SE PROCEDE REALIZAR CAMBIO DE DATAFONO, SE DEJA DSK 3500 CON VERSION 9.90 SE HACEN PRUEBAS OK VISITA EXITOSA DATAFONO OPERATIVO | W84: VISITA TECNICA | X84: 3A0CZ709 3A0CZ394 | Y84: TIPO I | Z84: TERRESTRE | AA84: GELVEZ MOGOLLON JOSE ELISEO | AB84: 1 | AC84: 0 | AD84: 65960 | AE84: 75096 | AF84: 65960
A85: BOGOTA | B85: CUNDINAMARCA | C85: 0004-0004 | D85: 11001 | E85: 3094844 | F85: 3007072123 | G85: INCIDENTE | H85: CUNDINAMARCA | I85: BOGOTA | J85: PTM BOGOTA DON PAGO FENIX | K85: REDEBAN | L85: FO-25-1923713 | M85: 45994.362 | N85: 45994.597 | O85: NO | P85: HARDWARE | Q85: PANTALLA | R85: DAÑO POS | S85: AGREGADOR | T85: COMCARD - PTM | U85: EJECUTADO | V85: 03/12/2025 SE ESCALA PARA VISITA. LLAMAR ANTES DE VISITAR, CONFIRMAR FALLA Y DATOS | 03/12/2025 SE REALIZA VISITA A CB PARA ATENDER INCIDENTE SE REALIZA CAMBIO DE DATAFONO POR FALLA EN PANTALLA CON PUNTOS Y DEJ AVER INFORMACIÓN,SE CAMBIA PINPAD POR TECNOLOGÍA,SE REALIZAN PRUEBAS OK | W85: VISITA TECNICA | X85: NN00K662 EG00A255 | Y85: TIPO I | Z85: TERRESTRE | AA85: GALINDO ROJAS LUIS FELIPE | AB85: 1 | AC85: 0 | AD85: 65960 | AE85: 75096 | AF85: 65960
A86: VALLEDUPAR | B86: COSTA | C86: 0004-0001 | D86: 20228 | E86: 3095345 | F86: 3007069507 | G86: INCIDENTE | H86: CESAR | I86: CURUMANI | J86: PTM CURUMANI CESAR PAPELERIA E | K86: REDEBAN | L86: FO-25-1924472 | M86: 45994.386 | N86: 45994.544 | O86: NO | P86: SOFTWARE | Q86: DATOS DESACTUALIZADOS | R86: FECHA DIRECCION DESACTUALZADA | S86: AGREGADOR | T86: COMCARD - PTM | U86: EJECUTADO | V86: 03/12/2025 NO SE LOGRA COMUNICACION LLAMAR ANTES DE LA VISITA PARA CONFIRMAR FALLA Y DATOS | 03/12/2025 SE VISITA CB Y SE LE HACE ACTUALIZACIÓN DE HORA YA QUE ESTABA 2 MINUTOS ATRASADO | W86: VISITA TECNICA | X86: EG001876 | Y86: TIPO III | Z86: TERRESTRE | AA86: BENITEZ CARVAJAL ALVARO JAVIER | AB86: 1 | AC86: 0 | AD86: 275729 | AE86: 196537 | AF86: 275729
A87: CALI | B87: SUROCCIDENTE Y EJE CAFETERO | C87: 0004-0003 | D87: 76109 | E87: 3095543 | F87: 3007029116 | G87: INCIDENTE | H87: VALLE DEL CAUCA | I87: BUENAVENTURA | J87: PAGAFACIL BUENAVENTURA CENTRO | K87: REDEBAN | L87: FO-25-1924463 | M87: 45994.398 | N87: 45995.735 | O87: NO | P87: SOFTWARE | Q87: ACTUALIZACION | R87: VERSION CARGA SO VR | S87: ROBUSTO | T87: PAGAFACIL | U87: EJECUTADO / CANCELADO | V87: 03/12/2025 EN COMUNICACION CON EL SR@ DANIELA ULABARES AL NUMERO 3162995845 SE CONFIRMAR FALLA Y DATOS . SE ESCALA PARA VISITA. | 04/12/2025 ‎SE LLEGA A SITIO Y POR MOTIVO QUE LA LINEA DE BANCOLOMBIA ESTA CAIDA, NO AUN FORMA QUE EL PERSONAL DEL CB. ME AUTORICE LA ENTRADA. ‎SE LE INDICA A EL CB VOLVER A COMUNICARSE PARA UNA NUEVA VISITA TÉCNICA. | W87: VISITA TECNICA | X87: 00000000 | Y87: TIPO III | Z87: TERRESTRE | AA87: TORRES GARCIA JENDRY JOSE | AB87: 1 | AC87: 0 | AD87: 275729 | AE87: 196537 | AF87: 275729
A88: VALLEDUPAR | B88: COSTA | C88: 0004-0001 | D88: 20550 | E88: 3095640 | F88: 3007032970 | G88: INCIDENTE | H88: CESAR | I88: PELAYA | J88: BARRIO CENTRO PELAYA 1 | K88: REDEBAN | L88: FO-25-1924447 | M88: 45994.409 | N88: 45995.664 | O88: NO | P88: HARDWARE | Q88: LECTOR DE TARJETAS | R88: DAÑO POS | S88: CB UNO A UNO | T88: CB UNO A UNO | U88: EJECUTADO | V88: 03/12/2025 SE ESCALA PARA VISITA. LLAMAR ANTES DE VISITAR, CONFIRMAR FALLA Y DATOS | 04/12/2025 BUENAS TARDES SE VISITA CB Y SE LE HACE CAMBIO DE PIN PAD Y TAMBIÉN DE HUB YA QUE ESTÁ PRESENTANDO MOLESTIAS. SE DEJA TODO FUNCIONANDO OK | W88: VISITA TECNICA | X88: XP9ZZ201 | Y88: TIPO IV | Z88: TERRESTRE | AA88: BENITEZ CARVAJAL ALVARO JAVIER | AB88: 1 | AC88: 0 | AD88: 479589 | AE88: 196537 | AF88: 479589
A89: MEDELLIN | B89: NOROCCIDENTE | C89: 0004-0005 | D89: 5440 | E89: 3095708 | F89: 3007081516 | G89: INCIDENTE | H89: ANTIOQUIA | I89: MARINILLA | J89: DISTRICOL SCENTI SOLUCIONES | K89: REDEBAN | L89: FO-25-1924451 | M89: 45994.402 | N89: 45995.736 | O89: NO | P89: HARDWARE | Q89: LECTOR DE BARRAS | R89: DAÑO POS | S89: AGREGADOR | T89: DISTRICOL | U89: EJECUTADO | V89: 03/12/2025 SE ESCALA PARA VISITA. LLAMAR ANTES DE VISITAR, CONFIRMAR FALLA Y DATOS | 04/12/2025 SE HACE MANTENIMIENTO OK SE CAMBIA DATÁFONO POR FALLAS EN PUERTO USB. EQUIPOS NUEVO QUDAA OPERATIVO | W89: VISITA TECNICA | X89: FSZZZ874 | Y89: TIPO II | Z89: TERRESTRE | AA89: DIAZ ZABALA FRANCIS DUBAN | AB89: 1 | AC89: 0 | AD89: 144968 | AE89: 140396 | AF89: 144968
A90: BOGOTA | B90: CUNDINAMARCA | C90: 0004-0004 | D90: 11001 | E90: 3096010 | F90: 3007048444 | G90: INCIDENTE | H90: CUNDINAMARCA | I90: BOGOTA | J90: PTM BOGOTA VIVERES LA HORMIGA | K90: REDEBAN | L90: FO-25-1924489 | M90: 45994.422 | N90: 45994.599 | O90: NO | P90: HARDWARE | Q90: PINPAD | R90: ALERTADO | S90: AGREGADOR | T90: COMCARD - PTM | U90: EJECUTADO | V90: 03/12/2025 SE ESCALA PARA VISITA. LLAMAR ANTES DE VISITAR, CONFIRMAR FALLA Y DATOS | 03/12/2025 CAMBIO DE PIN PAD EN DAÑO Y HUB EN MAL ESTADO PRUEBAS CON TARJETA OK | W90: VISITA TECNICA | X90: XP00J157 | Y90: TIPO I | Z90: TERRESTRE | AA90: GOMEZ VEGA DAVID SNEYDER | AB90: 1 | AC90: 0 | AD90: 65960 | AE90: 75096 | AF90: 65960
A91: BOGOTA | B91: CUNDINAMARCA | C91: 0004-0004 | D91: 11001 | E91: 3096375 | F91: 3007072338 | G91: INCIDENTE | H91: CUNDINAMARCA | I91: BOGOTA | J91: PTM MALU PET | K91: REDEBAN | L91: FO-25-1924784 | M91: 45994.447 | N91: 45994.547 | O91: NO | P91: HARDWARE | Q91: ALERT IRRUPTION | R91: ALERT IRRUPTION | S91: AGREGADOR | T91: COMCARD - PTM | U91: EJECUTADO | V91: 03/12/2025 SE ESCALA PARA VISITA. LLAMAR ANTES DE VISITAR, CONFIRMAR FALLA Y DATOS | 03/12/2025 SE REALIZA VISITA A CB PARA ATENDER INCIDENTE SE REALIZA CAMBIO DE DATAFONO POR FALLA ALERTADO ,SE REALIZAN PRUEBAS OK | W91: VISITA TECNICA | X91: ON00N784 | Y91: TIPO I | Z91: TERRESTRE | AA91: GALINDO ROJAS LUIS FELIPE | AB91: 1 | AC91: 0 | AD91: 65960 | AE91: 75096 | AF91: 65960
... A94: CALI | B94: SUROCCIDENTE Y EJE CAFETERO | C94: 0004-0003 | D94: 76001 | E94: 3096786 | F94: 3007081638 | G94: INCIDENTE | H94: VALLE DEL CAUCA | I94: CALI | J94: DISTRICOL DYSAR | K94: REDEBAN | L94: FO-25-1925287 | M94: 45994.477 | N94: 45994.606 | O94: NO | P94: HARDWARE | Q94: IMPRESION | R94: NO AVANZA PAPEL | S94: AGREGADOR | T94: DISTRICOL | U94: EJECUTADO | V94: 03/12/2025 SE ESCALA PARA VISITA. LLAMAR ANTES DE VISITAR, CONFIRMAR FALLA Y DATOS | 03/12/2025 SE REALIZA REINICIO DEL EQUIPO DEBIDO A BLOQUEO DE LA BATERÍA LO QUE OCASIONABA QUE NO IMPRIMIERA. SE REALIZAN PRUEBAS OK. | W94: VISITA TECNICA | X94: FWZZZ483 | Y94: TIPO I | Z94: TERRESTRE | AA94: MONTERO MUESES GIAN CARLO | AB94: 1 | AC94: 0 | AD94: 65960 | AE94: 75096 | AF94: 65960
A95: APARTADO | B95: NOROCCIDENTE | C95: 0004-0005 | D95: 27800 | E95: 3096970 | F95: 3007012115 | G95: INCIDENTE | H95: CHOCO | I95: UNGUIA | J95: UNGUIA - CHOCO | K95: REDEBAN | L95: FO-25-1925285 | M95: 45994.487 | N95: 45994.633 | P95: HARDWARE | Q95: IMPRESION | R95: NO AVANZA PAPEL | S95: CB UNO A UNO | T95: CB UNO A UNO | V95: 03/12/2025 SE ESCALA PARA VISITA. LLAMAR ANTES DE VISITAR, CONFIRMAR FALLA Y DATOS | 03/12/2025 EN LA REFERENCIA DE DATAFONO DESK 2600 SE VIENE PRESENTANDO EN VARIOS CLIENTES ATASCAS EN LA IMPRESORA. SE LE HA CAPACITADO AL CLIENTE POR VIDEO LLAMADA COMO DEBE OPERAR Y USAR EL DATAFONO PARA QUE EL PAPEL NO SE ATASQUE, CON ESTA ACCIÓN SE MINIMIZA EL GASTO DE PAPEL Y LA ESPERA DE LOS CLIENTES. | W95: SOPORTE TELEFONICO | Y95: TIPO V | Z95: FLUVIAL | AA95: CASTRO HENAO DANIEL ESTEBAN | AB95: 0 | AC95: 0 | AD95: 41241 | AE95: 0 | AF95: 41241
A96: CUCUTA | B96: SANTANDERES | C96: 0004-0008 | D96: 54001 | E96: 3097116 | F96: 3007067239 | G96: INCIDENTE | H96: NORTE DE SANTANDER | I96: CUCUTA | J96: PTM CUCUTA VARIEDADES Y PAPELE | K96: REDEBAN | L96: FO-25-1925846 | M96: 45994.488 | N96: 45995.454 | O96: NO | P96: HARDWARE | Q96: ALERT IRRUPTION | R96: ALERT IRRUPTION | S96: AGREGADOR | T96: COMCARD - PTM | U96: EJECUTADO | V96: 03/12/2025 SE ESCALA PARA VISITA. LLAMAR ANTES DE VISITAR, CONFIRMAR FALLA Y DATOS | 04/12/2025 SE REALIZA VISITA AL COMERCIO Y SE ENCUENTRA DATAFONO MODO ALERTADO, SE REALIZA CAMBIO DE EQUIPO, PRUEBAS EXITOSAS | W96: VISITA TECNICA | X96: AAJ05693 AAJ05241 | Y96: TIPO I | Z96: TERRESTRE | AA96: MORA VEGA JEAMPIER | AB96: 1 | AC96: 0 | AD96: 65960 | AE96: 75096 | AF96: 65960
A97: CUCUTA | B97: SANTANDERES | C97: 0004-0008 | D97: 54405 | E97: 3097126 | F97: 3007049406 | G97: INCIDENTE | H97: NORTE DE SANTANDER | I97: LOS PATIOS | J97: DISTRICOL DISTR CALZD CASTILLO | K97: REDEBAN | L97: FO-25-1925838 | M97: 45994.492 | N97: 45995.483 | O97: NO | P97: HARDWARE | Q97: LECTOR DE BARRAS | R97: CABLE LECTORA AVERIADO | S97: AGREGADOR | T97: DISTRICOL | U97: EJECUTADO | V97: 03/12/2025 SE ESCALA PARA VISITA. LLAMAR ANTES DE VISITAR, CONFIRMAR FALLA Y DATOS | 03/12/2025 SE CONTACTA TELEFÓNICAMENTE AL CLIENTE, LA SEÑORA ANGÉLICA SOLICITA QUE SE REALICE LA VISITA MAÑANA 04/12 EN LA MAÑANA YA QUE NO SE ENCUENTRA EN EL LOCAL PARA ATENDER LA VISITA. SE REPROGRAMA POR SOLICITUD DEL CLIENTE. 3162204800 | 04/12/2025 SE REALIZA VISITA, SE ENCUENTRA LECTOR DE BARRAS EN DAÑO, SE REALIZA CAMBIO, SE REALIZAN PRUEBAS Y CIERRES OK | W97: VISITA TECNICA | X97: AD00P256 | Y97: TIPO I | Z97: TERRESTRE | AA97: PACHECO BUITRAGO JAVIER ALONSO | AB97: 1 | AC97: 0 | AD97: 65960 | AE97: 75096 | AF97: 65960
A98: SANTA MARTA | B98: COSTA | C98: 0004-0001 | D98: 47245 | E98: 3097162 | F98: 3007021042 | G98: INCIDENTE | H98: MAGDALENA | I98: EL BANCO | J98: COMCARD EL BANCO CEYOL | K98: REDEBAN | L98: FO-25-1925678 | M98: 45994.502 | N98: 45995.665 | O98: NO | P98: HARDWARE | Q98: TECLADO | R98: DAÑO POS | S98: AGREGADOR | T98: COMCARD - PTM | U98: EJECUTADO | V98: 03/12/2025 SE ESCALA PARA VISITA. LLAMAR ANTES DE VISITAR, CONFIRMAR FALLA Y DATOS | 04/12/2025 SE REALIZA CAMBIO DE DATAFONO, YA QUE TENIA EL TECLADO BORROSO Y ALGUNAS TECLAS DURAS, SE REALIZAN PRUEBAS DEJANDO SERVICIO FUNCIONAL AL 100 % | W98: VISITA TECNICA | X98: AAAOZ377 | Y98: TIPO IV | Z98: TERRESTRE | AA98: MONTES DIAZ JOHN FRED | AB98: 1 | AC98: 0 | AD98: 479589 | AE98: 196537 | AF98: 479589
A99: MEDELLIN | B99: NOROCCIDENTE | C99: 0004-0005 | D99: 5615 | E99: 3097345 | F99: 3007068770 | G99: INCIDENTE | H99: ANTIOQUIA | I99: RIONEGRO | J99: PTM RIONEGRO BLOOMERS STORE | K99: REDEBAN | L99: FO-25-1925676 | M99: 45994.525 | N99: 45995.707 | O99: NO | P99: HARDWARE | Q99: LECTOR DE TARJETAS | R99: DAÑO POS | S99: AGREGADOR | T99: COMCARD - PTM | U99: EJECUTADO | V99: 03/12/2025 SE ESCALA PARA VISITA. LLAMAR ANTES DE VISITAR, CONFIRMAR FALLA Y DATOS | 04/12/2025 SE DETECTA OBSTRUCCIÓN EN LECTOR CHIP SE LIMPIA OBSTRUCCIÓN Y LIMPIA CONTACTO CHIP SE HACEN PRUEBAS PERO NO FUNCIONÓ POR LO QUE SE CAMBIA PINPAD Y EQUIPO EL EQUIPO POR COMPATIBILIDAD CON PINPAD 1600 | W99: VISITA TECNICA | X99: AALUZ196 AALUZ354 | Y99: TIPO II | Z99: TERRESTRE | AA99: ALVAREZ ARENAS VICTOR HUGO | AB99: 1 | AC99: 0 | AD99: 144968 | AE99: 140396 | AF99: 144968
A100: MEDELLIN | B100: NOROCCIDENTE | C100: 0004-0005 | D100: 27361 | E100: 3097369 | F100: 3007060839 | G100: INCIDENTE | H100: CHOCO | I100: ISTMINA | J100: BARRIO CUBIS ISTMINA 12 | K100: REDEBAN | L100: FO-25-1925832 | M100: 45994.542 | N100: 45996.399 | O100: NO | P100: HARDWARE | Q100: LECTOR DE TARJETAS | R100: DAÑO POS | S100: CB UNO A UNO | T100: CB UNO A UNO | U100: EJECUTADO | V100: 03/12/2025 SE ESCALA PARA VISITA. LLAMAR ANTES DE VISITAR, CONFIRMAR FALLA Y DATOS | 05/12/2025 SE REALIZA CAMBIO DE EEUIPO POR DAÑO, SE REALIZAN PRUEBAS Y EL CB QUEDA OPERATIVO | W100: VISITA TECNICA | X100: FUA0G723 | Y100: TIPO V | Z100: AEREO | AA100: ROBLEDO DIAZ ANDRES FELIPE | AB100: 1 | AC100: 0 | AD100: 988463 | AE100: 196537 | AF100: 988463
A101: SANTA MARTA | B101: COSTA | C101: 0004-0001 | D101: 47318 | E101: 3097395 | F101: 3007080270 | G101: INCIDENTE | H101: MAGDALENA | I101: GUAMAL | J101: BARRIO CENTRO GUAMAL 4 | K101: REDEBAN | L101: FO-25-1926620 | M101: 45994.569 | N101: 45995.753 | O101: NO | P101: HARDWARE | Q101: IMPRESION | R101: NO AVANZA PAPEL | S101: UNO A UNO | T101: UNO A UNO | U101: EJECUTADO | V101: 03/12/2025 SE ESCALA PARA VISITA. LLAMAR ANTES DE VISITAR, CONFIRMAR FALLA Y DATOS | 04/12/2025 SE REALIZA CAMBIO DE DATAFONO, YA QUE NO AVANZABA EL PAPEL EN OCACIONES, SE DEJA EL MISMO CABLEADO, SE REALIZAN PRUEBAS DEJANDO SERVICIO FUNCIONAL AL 100 % | W101: VISITA TECNICA | X101: FAZZZ529 | Y101: TIPO IV | Z101: TERRESTRE | AA101: MONTES DIAZ JOHN FRED | AB101: 1 | AC101: 0 | AD101: 479589 | AE101: 196537 | AF101: 479589
A102: SANTA MARTA | B102: COSTA | C102: 0004-0001 | D102: 44430 | E102: 3097446 | F102: 3007059091 | G102: INCIDENTE | H102: LA GUAJIRA | I102: MAICAO | J102: PTM MAICAO MASIVOS EXPRESS | K102: REDEBAN | L102: FO-25-1925677 | M102: 45994.514 | N102: 45996.512 | O102: NO | P102: HARDWARE | Q102: LECTOR DE BARRAS | R102: CABLE LECTORA AVERIADO | S102: AGREGADOR | T102: COMCARD - PTM | U102: EJECUTADO | V102: 03/12/2025 SE ESCALA PARA VISITA. LLAMAR ANTES DE VISITAR, CONFIRMAR FALLA Y DATOS | 05/12/2025 SE REALIZA LA VISITA SE ENCUENTRA EL EL CABLE DEL LECTOR DE CÓDIGO DE BARRAS AVERIADO Y CON CINTA LO CUAL NO PERMITE EL BUEN FUNCIONAMIENTO DEL DISPOSITIVO SE PROCEDE A CAMBIAR EL CABLE SE REALIZAN PRUEBAS Y QUEDA EL ACCESORIO OKAY | W102: VISITA TECNICA | X102: OA001622 FUA02712 | Y102: TIPO IV | Z102: TERRESTRE | AA102: THOMAS CAMPO SIGIFREDO SEGUNDO | AB102: 1 | AC102: 0 | AD102: 479589 | AE102: 196537 | AF102: 479589
A103: CALI | B103: SUROCCIDENTE Y EJE CAFETERO | C103: 0004-0003 | D103: 19532 | E103: 3097508 | F103: 3007039575 | G103: INCIDENTE | H103: CAUCA | I103: PATIA | J103: DISTRICOL CIELO RODRIGUEZ IBAR | K103: REDEBAN | L103: FO-25-1925836 | M103: 45994.527 | N103: 46000.682 | O103: NO | P103: HARDWARE | Q103: SE REINICIA | R103: DAÑO POS | S103: AGREGADOR | T103: DISTRICOL | U103: EJECUTADO | V103: 03/12/2025 SE ESCALA PARA VISITA. LLAMAR ANTES DE VISITAR, CONFIRMAR FALLA Y DATOS | 06/12/2025 SE DEBE REALIZAR VISITA EL DIA MARTES YA QUE SE REQUIERE CAMBIO DE EQUIPO Y POR DESPLZAZMIENTO EL SITIO NO SE PUEDDE REALIZAR ANTES | 09/12/2025 SE INGRESA EQUIPO CON PROBLEMAS DE ENERGIA SE CAMBIA DE TOMA SE HACEN PRUEBAS OK | W103: VISITA TECNICA | X103: 9A0CZ400 | Y103: TIPO IV | Z103: TERRESTRE | AA103: GIMBUEL LASSO LUIS GERMAN | AB103: 1 | AC103: 0 | AD103: 479589 | AE103: 196537 | AF103: 479589
A104: MEDELLIN | B104: NOROCCIDENTE | C104: 0004-0005 | D104: 5631 | E104: 3097509 | F104: 3007016056 | G104: INCIDENTE | H104: ANTIOQUIA | I104: SABANETA | J104: ALKOMPRAR MAYORCA | K104: REDEBAN | L104: FO-25-1925833 | M104: 45994.528 | N104: 45994.69 | O104: NO | P104: HARDWARE | Q104: COMUNICACION | R104: DAÑO POS | S104: RETAIL | T104: CONTIGO / ALKOMPRAR | U104: EJECUTADO | V104: 03/12/2025 SE ESCALA PARA VISITA. LLAMAR ANTES DE VISITAR, CONFIRMAR FALLA Y DATOS | 03/12/2025 SE CAMBIA EQUIPO PORQUE NO QUISO DAR LA COMUNICACIÓN, SE REALIZAN PRUEBAS OK | W104: VISITA TECNICA | X104: JAXZZ840 | Y104: TIPO I | Z104: TERRESTRE | AA104: RUA ALVAREZ RICHARD ANDRES | AB104: 1 | AC104: 0 | AD104: 65960 | AE104: 75096 | AF104: 65960
A105: CALI | B105: SUROCCIDENTE Y EJE CAFETERO | C105: 0004-0003 | D105: 19001 | E105: 3097552 | F105: 3007081483 | G105: INCIDENTE | H105: CAUCA | I105: POPAYAN | J105: PTM POPAYAN TIENDA Y PAPELERIA | K105: REDEBAN | L105: FO-25-1937755 | FO-25-1926618 | M105: 45994.581 | N105: 45996.699 | O105: NO | P105: SOFTWARE | Q105: ERROR DE TRANSACCIONES | R105: RECHAZO GENERAL | S105: AGREGADOR | T105: COMCARD - PTM | U105: EJECUTADO | V105: [FO-25-1937755] 05/12/2025 SE REGRESA AL CB SE FORMATIO EQUIPO SE INICIALIZA TERMINAL DE CB PRUEBAS OK CREACION TELECARGA DRNA || [FO-25-1926618] 03/12/2025 SE ESCALA PARA VISITA. LLAMAR ANTES DE VISITAR, CONFIRMAR FALLA Y DATOS | 05/12/2025 SE INGRESA CB CON PRIBLEMAS DE TERMINAL DE CB SE HACEN PRUEBAS DE COMERCIO OK SE FORMATIO EQUIPO SE HACE NUEVMENTE PRUEBAS DE COERCIO TEMINAL CB NO INICIALIZA MENSJE WEB TERMINAL NO HABILITADA SE REPORTA A RBM | W105: VISITA TECNICA | X105: JVZZZ917 | Y105: TIPO III | Z105: TERRESTRE | AA105: GIMBUEL LASSO LUIS GERMAN | AB105: 2 | AC105: 0 | AD105: 551458 | AE105: 196537 | AF105: 551458
A106: BOGOTA | B106: CUNDINAMARCA | C106: 0004-0004 | D106: 11001 | E106: 3097564 | F106: 3007011805 | G106: INCIDENTE | H106: CUNDINAMARCA | I106: BOGOTA | J106: REVAL BOGOTA SUR | K106: REDEBAN | L106: FO-25-1926609 | M106: 45994.587 | N106: 45995.579 | O106: NO | P106: HARDWARE | Q106: LECTOR DE BARRAS | R106: CABLE LECTORA AVERIADO | S106: ROBUSTO | T106: REVAL | U106: EJECUTADO | V106: 03/12/2025 SE ESCALA PARA VISITA. LLAMAR ANTES DE VISITAR, CONFIRMAR FALLA Y DATOS | 04/12/2025 SE REALIZA CAMBIO DE LECTOR POR DAÑO EN EL CABLE SE INSTALA SYMBOL SE REALIZAN PRUEBAS OK | W106: VISITA TECNICA | X106: JARZZ631 | Y106: TIPO I | Z106: TERRESTRE | AA106: SOTO LONDOÑO FREDY ALEXANDER | AB106: 1 | AC106: 0 | AD106: 65960 | AE106: 75096 | AF106: 65960
A107: BUCARAMANGA | B107: SANTANDERES | C107: 0004-0008 | D107: 68081 | E107: 3097705 | F107: 3007052195 | G107: INCIDENTE | H107: SANTANDER | I107: BARRANCABERMEJA | J107: DISTRICOL VARI Y PAPEL BRAYAN | K107: REDEBAN | L107: FO-25-1925964 | M107: 45994.551 | N107: 45995.443 | O107: NO | P107: HARDWARE | Q107: COMUNICACION | R107: MENSAJE CABLE DE RED DESCONECTADO | S107: AGREGADOR | T107: DISTRICOL | U107: EJECUTADO | V107: 03/12/2025 SE ESCALA PARA VISITA. LLAMAR ANTES DE VISITAR, CONFIRMAR FALLA Y DATOS | 04/12/2025 CAMBIO DE EQUIPO POR ERROR EN COMUNICACIÓN, CAMBIO DE PINPAD POR TECNOLOGÍA | W107: VISITA TECNICA | X107: GB0DZ021 | Y107: TIPO III | Z107: TERRESTRE | AA107: PEÑA DIAZ IVAN YESID | AB107: 1 | AC107: 0 | AD107: 275729 | AE107: 196537 | AF107: 275729
... A120: VILLAVICENCIO | B120: REMOTAS | C120: 0004-0007 | D120: 50006 | E120: 3099365 | F120: 3007024828 | G120: INCIDENTE | H120: META | I120: ACACIAS | J120: BARRIO LAS FERIAS ACACIAS | K120: REDEBAN | L120: FO-25-1927765 | M120: 45994.73 | N120: 45995.656 | O120: NO | P120: HARDWARE | Q120: NO ENCIENDE | R120: DAÑO POS | S120: UNO A UNO | T120: CB UNO A UNO | U120: EJECUTADO | V120: 03/12/2025 SE ESCALA PARA VISITA. LLAMAR ANTES DE VISITAR, CONFIRMAR FALLA Y DATOS | 04/12/2025 SE VISITA CB Y SE REALIZA CAMBIO DE DATÁFONO Y FUENTE DE PODER POR DAÑO. SE INSTALA NUEVO EQUIPO SE CONFIGURA POS SE INICIALIZA SE CREAN USUARIOS CORRECTAMENTE Y SE REALIZA PRUEBAS EXITOSAS PRUEBAS OK | W120: VISITA TECNICA | X120: ABGZZ357 | Y120: TIPO II | Z120: TERRESTRE | AA120: GARZON RUIZ LUIS MIGUEL | AB120: 1 | AC120: 0 | AD120: 144968 | AE120: 140396 | AF120: 144968
A121: TUNJA | B121: SANTANDERES | C121: 0004-0008 | D121: 15491 | E121: 3099368 | F121: 3007062597 | G121: INCIDENTE | H121: BOYACA | I121: NOBSA | J121: BARRIO NAZARETH NOBSA 4 | K121: REDEBAN | L121: FO-25-1927763 | M121: 45994.732 | N121: 45995.537 | P121: SOFTWARE | Q121: SE REINICIA | R121: AL REALIZAR CIERRE CARGA VERSION | S121: CB UNO A UNO | T121: CB UNO A UNO | V121: 03/12/2025 SE ESCALA PARA VISITA. LLAMAR ANTES DE VISITAR, CONFIRMAR FALLA Y DATOS | 04/12/2025 SE INTENTA ESTABLECER COMUNICACIÓN TELEFÓNICA CON EL SEÑOR SEBASTIAN GUARIN AL NÚMERO DE CONTACTO 3124042044 CLIENTE NO RESPONDE SE DEJA MENSAJE POR WHATSAPP INDICANDO SOBRE LA VISITA CLIENTE RESPONDE MANIFESTANDO QUE LA ORDEN GENERADA FUE DEBIDO A QUE EL DÍA DE AYER EL EQUIPO LE PRESENTÓ REINICIOS CLIENTE REALIZA LAS VALIDACIONES CORRESPONDIENTES EL DÍA DE HOY VALIDANDO QUE EL EQUIPO ESTÁ OPERATIVO Y FUNCIONANDO CORRECTAMENTE SE LE INDICA QUE SE PROCEDERÁ CON EL CIERRE DE LA ORDEN CLIENTE CONFORME. | W121: SOPORTE TELEFONICO | Y121: TIPO II | Z121: TERRESTRE | AA121: RODRIGUEZ MURCIA YERSON IVAN | AB121: 0 | AC121: 0 | AD121: 41241 | AE121: 0 | AF121: 41241
A122: PASTO | B122: SUROCCIDENTE Y EJE CAFETERO | C122: 0004-0003 | D122: 52693 | E122: 3099580 | F122: 3007021755 | G122: INCIDENTE | H122: NARIÑO | I122: SAN PABLO | J122: BARRIO LOURDES SAN PABLO | K122: REDEBAN | L122: FO-25-1927806 | M122: 45994.743 | N122: 45997.488 | P122: SOFTWARE | Q122: CIERRE | R122: CIERRE NO HABILITADO | S122: CB UNO A UNO | T122: CB UNO A UNO | V122: 03/12/2025 SE ESCALA PARA VISITA. LLAMAR ANTES DE VISITAR, CONFIRMAR FALLA Y DATOS | 06/12/2025 SE HABLA CON EL CLIENTE ,QUIEN INDICA QUE YA PUDO REALIZAR CIERRES Y VERIFICACIONES CON LA CLAVE , INDICA QUE TAL VEZ LO ESTABA REALIZANDO MAL POR QUE EL DIA DE AYER INTENTO Y YA LE DEJO FUNCIONAR SIN PROBLEMA | W122: SOPORTE TELEFONICO | Y122: TIPO IV | Z122: TERRESTRE | AA122: HENAO CARDONA DIEGO FERNANDO | AB122: 0 | AC122: 0 | AD122: 41241 | AE122: 0 | AF122: 41241
A123: MONTERIA | B123: COSTA | C123: 0004-0001 | D123: 23855 | E123: 3099780 | F123: 3007047644 | G123: INCIDENTE | H123: CORDOBA | I123: VALENCIA | J123: DISTRICOL MISCELANEA LA PERLA | K123: REDEBAN | L123: FO-25-1928606 | M123: 45995.333 | N123: 45996.566 | O123: NO | P123: HARDWARE | Q123: IMPRESION | R123: NO AVANZA PAPEL | S123: AGREGADOR | T123: DISTRICOL | U123: EJECUTADO | V123: 04/12/2025 SE ESCALA PARA VISITA. LLAMAR ANTES DE VISITAR, CONFIRMAR FALLA Y DATOS | 05/12/2025 SE REALIZA MANTENIMIENTO Y LIMPIEZA A RODILLO DE DESK3500, SE REALIZAN PRUEBAS EXITOSAS, CLIENTE CONFIRMA EQUIPO OPERATIVO. | W123: VISITA TECNICA | X123: XP00F390 | Y123: TIPO III | Z123: TERRESTRE | AA123: MARQUEZ HOYOS JEYSON DANIEL | AB123: 1 | AC123: 0 | AD123: 275729 | AE123: 196537 | AF123: 275729
A124: MEDELLIN | B124: NOROCCIDENTE | C124: 0004-0005 | D124: 5001 | E124: 3099934 | F124: 3007039734 | G124: INCIDENTE | H124: ANTIOQUIA | I124: MEDELLIN | J124: PTM MED MOMENTO MC | K124: REDEBAN | L124: FO-25-1928611 | M124: 45995.333 | N124: 45995.528 | O124: NO | P124: HARDWARE | Q124: HUB | R124: DETERIORO CABLE | S124: AGREGADOR | T124: COMCARD - PTM | U124: EJECUTADO | V124: 04/12/2025 SE ESCALA PARA VISITA. LLAMAR ANTES DE VISITAR, CONFIRMAR FALLA Y DATOS | 04/12/2025 SE REALIZA VISITA TÉCNICA AL CORRESPONSAL BANCOLOMBIA, DONDE EL USUARIO CONFIRMA SU IDENTIFICACIÓN E INFORMA QUE EL DATÁFONO SE REINICIA CONSTANTEMENTE. AL VALIDAR EL EQUIPO, SE OBSERVA DETERIORO EN EL CABLE DE CONEXIÓN, LA FUENTE DE PODER Y EL ENSORTIJADO, LO QUE OCASIONA LA FALLA REPORTADA. SE PROCEDE AL REEMPLAZO DE LOS CABLES DEFECTUOSOS Y AL CAMBIO DEL HUB POR UNO NUEVO. FINALIZADA LA INTERVENCIÓN, EL DATÁFONO QUEDA OPERATIVO Y EN CORRECTO FUNCIONAMIENTO PARA LA REALIZACIÓN DE TRANSACCIONES. | W124: VISITA TECNICA | X124: 9A0JZ479 XPSZZ100 | Y124: TIPO I | Z124: TERRESTRE | AA124: MARTINEZ TOVAR OSCAR DAVID | AB124: 1 | AC124: 0 | AD124: 65960 | AE124: 75096 | AF124: 65960
A125: MEDELLIN | B125: NOROCCIDENTE | C125: 0004-0005 | D125: 5001 | E125: 3100212 | F125: 3007050145 | G125: INCIDENTE | H125: ANTIOQUIA | I125: MEDELLIN | J125: PTM MEDELLIN GRANERO MIXTO EL | K125: REDEBAN | L125: FO-25-1928625 | M125: 45995.333 | N125: 45995.471 | O125: NO | P125: HARDWARE | Q125: TECLADO | R125: DAÑO POS | S125: AGREGADOR | T125: COMCARD - PTM | U125: EJECUTADO | V125: 04/12/2025 SE ESCALA PARA VISITA. LLAMAR ANTES DE VISITAR, CONFIRMAR FALLA Y DATOS | 04/12/2025 SE CAMBIA EQUIPO POR TECLADO BORROSO | W125: VISITA TECNICA | X125: GB00V335 | Y125: TIPO I | Z125: TERRESTRE | AA125: RUA ALVAREZ RICHARD ANDRES | AB125: 1 | AC125: 0 | AD125: 65960 | AE125: 75096 | AF125: 65960
A126: CUCUTA | B126: SANTANDERES | C126: 0004-0008 | D126: 54001 | E126: 3101320 | F126: 3007034261 | G126: INCIDENTE | H126: NORTE DE SANTANDER | I126: CUCUTA | J126: PAGAFACIL DIAGONAL SANTANDER | K126: REDEBAN | L126: FO-25-1929322 | M126: 45995.385 | N126: 45995.703 | O126: NO | P126: SOFTWARE | Q126: COMUNICACION | R126: PARAMETROS DE CONFIGURACION EN POS | S126: ROBUSTO | T126: PAGAFACIL | U126: EJECUTADO | V126: 04/12/2025 SE ESCALA PARA VISITA. LLAMAR ANTES DE VISITAR, CONFIRMAR FALLA Y DATOS | 04/12/2025 SE REALIZA VISITA AL COMERCIO Y SE REALIZA MANTENIMIENTO GENERAL AL DATAFONO, SE REALIZAN PRUEBAS ÉXITOSAS | W126: VISITA TECNICA | X126: 1UZZZ572 | Y126: TIPO I | Z126: TERRESTRE | AA126: MORA VEGA JEAMPIER | AB126: 1 | AC126: 0 | AD126: 65960 | AE126: 75096 | AF126: 65960
A127: MEDELLIN | B127: NOROCCIDENTE | C127: 0004-0005 | D127: 5088 | E127: 3101887 | F127: 3007063960 | G127: INCIDENTE | H127: ANTIOQUIA | I127: BELLO | J127: DISTRICOL MERCADOS HATO NUEVO | K127: REDEBAN | L127: FO-25-1929860 | M127: 45995.427 | N127: 45996.424 | O127: NO | P127: HARDWARE | Q127: ALERT IRRUPTION | R127: ALERT IRRUPTION | S127: AGREGADOR | T127: DISTRICOL | U127: EJECUTADO | V127: 04/12/2025 SE ESCALA PARA VISITA. LLAMAR ANTES DE VISITAR, CONFIRMAR FALLA Y DATOS | 05/12/2025 SE PRESENTA MOVILIDAD REDUCIDA EN LA ENTRADA DEL MUNICIPIO DE BELLO POR FUERTES LLUVIAS | 05/12/2025 APENAS LOGRAMOS LLEGAR AL SITIO NOS ENCONTRAMOS DANDO SOLUCIÓN, SE DEBE CAMBIAR DATAFONO | 05/12/2025 SE PROCESO EN CAMBIO DE DATÁFONO PERO AUN NO SUBE, SIGUE SALIENDO EN RECHAZO A LA ESPERA DE RESPUESTA DEL ESTABLECIMIENTO | 05/12/2025 SE HACE MANTENIMIENTO SE OK SE CAMBIA DATÁFONO POR ALERT INTERRUTION PRUEBA EXITOSAS | W127: VISITA TECNICA | X127: NA00Y798 | Y127: TIPO I | Z127: TERRESTRE | AA127: DIAZ ZABALA FRANCIS DUBAN | AB127: 1 | AC127: 0 | AD127: 65960 | AE127: 75096 | AF127: 65960
A128: TUNJA | B128: SANTANDERES | C128: 0004-0008 | D128: 15001 | E128: 3101996 | F128: 3007070877 | G128: INCIDENTE | H128: BOYACA | I128: TUNJA | J128: DISTRICOL DTV ELECTRONICS | K128: REDEBAN | L128: FO-25-1930049 | M128: 45995.437 | N128: 45995.51 | O128: NO | P128: HARDWARE | Q128: LECTOR DE BARRAS | R128: CABLE LECTORA AVERIADO | S128: AGREGADOR | T128: DISTRICOL | U128: EJECUTADO | V128: 04/12/2025 SE ESCALA PARA VISITA. LLAMAR ANTES DE VISITAR, CONFIRMAR FALLA Y DATOS | 04/12/2025 SE REALIZA CAMBIO DE LECTOR POR FALLA CABLE DEFECTUOSO PRUEBAS OK CLIENTE CONFORME | W128: VISITA TECNICA | X128: EF00E838 | Y128: TIPO I | Z128: TERRESTRE | AA128: RODRIGUEZ MURCIA YERSON IVAN | AB128: 1 | AC128: 0 | AD128: 65960 | AE128: 75096 | AF128: 65960
A129: PASTO | B129: SUROCCIDENTE Y EJE CAFETERO | C129: 0004-0003 | D129: 52215 | E129: 3102102 | F129: 3007067325 | G129: INCIDENTE | H129: NARIÑO | I129: CORDOBA | J129: DISTRICOL VAR ISABELITA | K129: REDEBAN | L129: FO-25-1929964 | M129: 45995.432 | N129: 45996.551 | O129: NO | P129: HARDWARE | Q129: IMPRESION | R129: NO IMPRIME UNO O VARIOS CARACTERES | S129: AGREGADOR | T129: DISTRICOL | U129: EJECUTADO | V129: 04/12/2025 SE ESCALA PARA VISITA. LLAMAR ANTES DE VISITAR, CONFIRMAR FALLA Y DATOS | 05/12/2025 SE VISITA CB. SE ENCUENTRA DATAFONO CON IMPRESORA AVERIADA, NO IMPRIME VARIOS CARACTERES. SE REALIZA CAMBIO DE EQUIPO. SE REALIZAN PRUEBAS TX EXITOSAS. QUEDA OPERATIVO | W129: VISITA TECNICA | X129: 6A0TZ913 | Y129: TIPO II | Z129: TERRESTRE | AA129: CASTILLO HERRERA ALEX RICARDO | AB129: 1 | AC129: 0 | AD129: 144968 | AE129: 140396 | AF129: 144968
A130: TUNJA | B130: SANTANDERES | C130: 0004-0008 | D130: 15632 | E130: 3102202 | F130: 3007044175 | G130: INCIDENTE | H130: BOYACA | I130: SABOYA | J130: DISTRICOL VARIEDADES KOKO | K130: REDEBAN | L130: FO-25-1930050 | M130: 45995.436 | N130: 45996.651 | O130: NO | P130: HARDWARE | Q130: LECTOR DE BARRAS | R130: DAÑO POS | S130: AGREGADOR | T130: DISTRICOL | U130: EJECUTADO | V130: 04/12/2025 SE ESCALA PARA VISITA. LLAMAR ANTES DE VISITAR, CONFIRMAR FALLA Y DATOS | 05/12/2025 SE REALIZA CAMBIO DE EQUIPO POR DAÑO PUERTO USB MALO SE CAMBIA LECTOR SIN PLACA DE IGUAL MANERA EL EQUIPO , DEJANDO PRUEBAS OK SIN TELECARGA NO AUTORIZADA SE CONSULTA INVENTARIO CON LA RED | W130: VISITA TECNICA | X130: AC03Z710 | Y130: TIPO II | Z130: TERRESTRE | AA130: ALVARADO MORENO CRISTHIAN | AB130: 1 | AC130: 0 | AD130: 144968 | AE130: 140396 | AF130: 144968
A131: MEDELLIN | B131: NOROCCIDENTE | C131: 0004-0005 | D131: 5031 | E131: 3102287 | F131: 3007037114 | G131: INCIDENTE | H131: ANTIOQUIA | I131: AMALFI | J131: DISTRICOL GM STORE AMALFI | K131: REDEBAN | L131: FO-25-1930302 | M131: 45995.458 | N131: 45996.659 | O131: NO | P131: HARDWARE | Q131: IMPRESION | R131: NO IMPRIME UNO O VARIOS CARACTERES | S131: AGREGADOR | T131: DISTRICOL | U131: EJECUTADO | V131: 04/12/2025 SE INTENTA COMUNICACION CON EL USUARIO AL NUMERO 3197928048 SE ESCALA PARA VISITA. LLAMAR ANTES DE VISITAR, CONFIRMAR FALLA Y DATOS | 05/12/2025 SE CAMBIA EQUIPO POR DAÑO EN IMPRESORA | W131: VISITA TECNICA | X131: 9A00L272 | Y131: TIPO IV | Z131: TERRESTRE | AA131: BADEL ACUÑA LUIS ALBERTO | AB131: 1 | AC131: 0 | AD131: 479589 | AE131: 196537 | AF131: 479589
A132: BOGOTA | B132: CUNDINAMARCA | C132: 0004-0004 | D132: 11001 | E132: 3102367 | F132: 3007034385 | G132: INCIDENTE | H132: CUNDINAMARCA | I132: BOGOTA | J132: REVAL MULTIPLAZA | K132: REDEBAN | L132: FO-25-1930250 | M132: 45995.449 | N132: 45996.394 | O132: NO | P132: SOFTWARE | Q132: ACTUALIZACION | R132: TECNOLOGIA | S132: ROBUSTO | T132: REVAL | U132: EJECUTADO / CANCELADO | V132: 04/12/2025 SE ESCALA PARA VISITA. LLAMAR ANTES DE VISITAR, CONFIRMAR FALLA Y DATOS | 05/12/2025 SE REALIZA VISITA DE CAMPO ENCONTRADO QUE COMERCIO ESTA CERRADO, SE INDAGA CON GUARDAS DE SEGURIDAD QUIENES MANIFIESTAN QUE NO HAY NADIE EN EL PUNTO Y EL HORARIO AL PÚBLICO ES APARTAR DE LAS 10 DE.LA MAÑANA, SE INTENTA CONTACTO A LA LÍNEA 3226007909 PERO NO HAY RESPUESTA, SE INFORMA A SUPERVISOR QUIEN AUTORIZA CIERRE DE SOLICITUD. | W132: VISITA TECNICA | Y132: TIPO I | Z132: TERRESTRE | AA132: LOZADA ROJAS CHRISTIAN ANDRES | AB132: 1 | AC132: 0 | AD132: 65960 | AE132: 75096 | AF132: 65960
A133: BARRANQUILLA | B133: COSTA | C133: 0004-0001 | D133: 8001 | E133: 3102420 | F133: 3007053261 | G133: INCIDENTE | H133: ATLANTICO | I133: BARRANQUILLA | J133: PTM BARRANQUILLA MISCELANEA SH | K133: REDEBAN | L133: FO-25-1930378 | M133: 45995.462 | N133: 45995.567 | O133: NO | P133: HARDWARE | Q133: PINPAD | R133: DAÑO POS | S133: AGREGADOR | T133: COMCARD - PTM | U133: EJECUTADO | V133: 04/12/2025 SE ESCALA PARA VISITA. LLAMAR ANTES DE VISITAR, CONFIRMAR FALLA Y DATOS | 04/12/2025 SE REALIZA VISITA TÉCNICA, SE CAMBIA LA PIN PAD, SE REALIZAN PRUEBAS EXITOSAS, EQUIPO FUNCIONA CORRECTAMENTE, CB QUEDA OPERATIVO. | W133: VISITA TECNICA | X133: TR0MZ953 9C0LZ852 | Y133: TIPO I | Z133: TERRESTRE | AA133: DE AGUAS MUÑOZ DAVID JOSE | AB133: 1 | AC133: 0 | AD133: 65960 | AE133: 75096 | AF133: 65960
A134: CARTAGENA | B134: COSTA | C134: 0004-0001 | D134: 13001 | E134: 3102513 | F134: 3007066684 | G134: INCIDENTE | H134: BOLIVAR | I134: CARTAGENA | J134: PAGAFACIL RAMBLAS | K134: REDEBAN | L134: FO-25-1930379 | M134: 45995.462 | N134: 45995.704 | O134: NO | P134: HARDWARE | Q134: NO ENCIENDE SE REINICIA | R134: FUENTE PODER AVERIADA | S134: ROBUSTO | T134: PAGAFACIL | U134: EJECUTADO | V134: 04/12/2025 SE ESCALA PARA VISITA. LLAMAR ANTES DE VISITAR, CONFIRMAR FALLA Y DATOS | 04/12/2025 SE REALIZA CAMBIO DE CARGADOR POR PROBLEMAS SE VALIDA CONEXIONES Y DE DEJA TODO OK PRUEBA EXITOSA | W134: VISITA TECNICA | X134: 2A0EZ225 | Y134: TIPO I | Z134: TERRESTRE | AA134: MARTINEZ SALGUEDO ANDRES AUGUSTO | AB134: 1 | AC134: 0 | AD134: 65960 | AE134: 75096 | AF134: 65960
A135: MEDELLIN | B135: NOROCCIDENTE | C135: 0004-0005 | D135: 5088 | E135: 3102573 | F135: 3007042180 | G135: INCIDENTE | H135: ANTIOQUIA | I135: BELLO | J135: PTM BELLO CINCO ESQUINAS | K135: REDEBAN | L135: FO-25-1930591 | M135: 45995.483 | N135: 45995.651 | O135: NO | P135: HARDWARE | Q135: IMPRESION | R135: NO AVANZA PAPEL | S135: AGREGADOR | T135: COMCARD - PTM | U135: EJECUTADO | V135: 04/12/2025 SE ESCALA PARA VISITA. LLAMAR ANTES DE VISITAR, CONFIRMAR FALLA Y DATOS | 04/12/2025 EL PAPEL NO AVANZA SE REALIZA MANTENIMIENTO Y LA FALLA PERSISTE. SE REALIZA CAMBIO DE EQUIPO SE REALIZAN PRUEBAS EXITOSAS SERVICIO OPERATIVO OK | W135: VISITA TECNICA | X135: 9A2ZZ461 | Y135: TIPO I | Z135: TERRESTRE | AA135: ZAPATA LOPEZ EDWARD ASDRUBAL | AB135: 1 | AC135: 0 | AD135: 65960 | AE135: 75096 | AF135: 65960
...

Sheet OC_BANCOLOMBIA
A1: CIUDAD SEDE | B1: ZONA | C1: CENTRO DE COSTOS LINEACOM | D1: CODIGO DANE | E1: TA/CODIGO ACTIVIDAD | F1: CODIGO CB | G1: ACTIVIDAD | H1: DEPARTAMENTO | I1: CIUDAD | J1: NOMBRE DEL CB | K1: RED | L1: FO | M1: FECHA ASIGNACION A LINEA COMUNICACIONES | N1: FECHA CIERRE DEL TICKET (DD/MM/AAAA HH:MM) | O1: ACOMETIDA | P1: SOLICITUD | Q1: DESCRIPCION | R1: FORMATO | S1: CADENA | T1: ESTADO | U1: CAUSAL ESTADO | V1: OBSERVACION | W1: FORMA DE ATENCION | X1: TERMINAL(ES) | Y1: TIPIFICACION | Z1: TIPO DE TRAYECTO | AA1: NOMBRE DEL TECNICO | AB1: DIAS DE VISITA | AC1: DIA ADICIONAL | AD1: VALOR DIAS ACTIVIDAD FACTURABLES | AE1: VALOR DIAS ACOMPAÑAMIENTO FACTURABLES | AF1: VALOR TOTAL
A2: MEDELLIN | B2: NOROCCIDENTE | C2: 0004-0005 | D2: 5790 | E2: 3067513 | F2: 3007064065 | G2: OC BASE DATAFONO | H2: ANTIOQUIA | I2: TARAZA | J2: BARRIO CENTRO TARAZA | K2: REDEBAN | L2: FO-25-1885296 | M2: 45987.621 | N2: 45995.464 | O2: NO | P2: BASEDATAFONO | Q2: BASE DATAFONO | R2: CB UNO A UNO | S2: CB UNO A UNO | T2: EJECUTADO | U2: EJECUTADO EXITOSO | V2: 26/11/2025 POR FAVOR, COMUNICARSE CON USUARIO PARA CONFIRMAR UBICACION, SOLICITUD Y PROGRAMAR VISITA TECNICA | 03/12/2025 SE SALE MEDELLÍN EN EL BUS DE LAS 11:30 Y DEBIDO A ALTO TRÁFICO SE DEMORA EN SALIR DE LA CIUDAD, YA SE ESTÁ EN CAMINO Y SE COMUNICA CON USUARIO QUE SE LLEGA UN POCO TARDE PERO QUE SE ATIENDE INCIDENTE HOY | 03/12/2025 APENAS SE LLEGA A TARAZÁ DEBIDO A RETRASO CAUSADO POR ACCIDENTE EN VÍA Y CLIENTE INFORMA QUE YA CERRÓ EL COMERCIO, SE APLAZA PARA MAÑANA | 04/12/2025 SE INSTALA BASE DEBIDO A DAÑO EN PATA DE LA BASE | W2: VISITA TECNICA | X2: OA00O678 | Y2: TIPO IV | Z2: TERRESTRE | AA2: QUINTERO SANCHEZ JUAN SEBASTIAN | AB2: 1 | AC2: 0 | AD2: 479589 | AE2: 196537 | AF2: 479589
A3: CALI | B3: SUROCCIDENTE Y EJE CAFETERO | C3: 0004-0003 | D3: 76834 | E3: 3074200 | F3: 3007055362 | G3: OC BASE DATAFONO | H3: VALLE DEL CAUCA | I3: TULUA | J3: DISTRICOL JMC DISTRIBUIDORA | K3: REDEBAN | L3: FO-25-1900620 | M3: 45989.333 | N3: 45992.647 | O3: NO | P3: BASEDATAFONO | Q3: BASE DATAFONO | R3: AGREGADOR | S3: DISTRICOL | T3: EJECUTADO / CANCELADO | U3: PETICIÓN USUARIO | V3: 28/11/2025 POR FAVOR, COMUNICARSE CON USUARIO PARA CONFIRMAR UBICACION, SOLICITUD Y PROGRAMAR VISITA TECNICA | 01/12/2025 SE VISITA CORRESPONSAL Y SE ENCONTRÓ CERRADO, SE LLAMA AL CONTACTO Y DICE QUE NO PUDO ABRES POR DILIGENCIA PERSONAL. SE INFORMA DE LA VISITA Y QUE SE QUE SE CIERRA CASO. | W3: VISITA TECNICA | X3: TRDZZ744 | Y3: TIPO II | Z3: TERRESTRE | AA3: BOLAÑOS TABORDA JORGE ENRIQUE | AB3: 1 | AC3: 0 | AD3: 144968 | AE3: 140396 | AF3: 144968
A4: IBAGUE | B4: REMOTAS | C4: 0004-0007 | D4: 17380 | E4: 3084118 | F4: 3007075541 | G4: OC BASE DATAFONO | H4: CALDAS | I4: LA DORADA | J4: PTM LA DORADA MULTISERVICIOS J | K4: REDEBAN | L4: FO-25-1913000 | M4: 45992.49 | N4: 45994.5 | O4: NO | P4: BASEDATAFONO | Q4: BASE DATAFONO | R4: AGREGADOR | S4: COMCARD - PTM | T4: EJECUTADO | U4: EJECUTADO EXITOSO | V4: 01/12/2025 POR FAVOR, COMUNICARSE CON USUARIO PARA CONFIRMAR UBICACION, SOLICITUD Y PROGRAMAR VISITA TECNICA | 02/12/2025 SE INSTALA BASE PARA DATÁFONO SIN NOVEDAD PORQUE LA ANTERIOR SE PARTIÓ. | W4: VISITA TECNICA | X4: SX00J098 | Y4: TIPO III | Z4: TERRESTRE | AA4: VARGAS HERRERA JHON JAIRO | AB4: 1 | AC4: 0 | AD4: 275729 | AE4: 196537 | AF4: 275729
A5: CALI | B5: SUROCCIDENTE Y EJE CAFETERO | C5: 0004-0003 | D5: 76834 | E5: 3084393 | F5: 3007082349 | G5: OC BASE DATAFONO | H5: VALLE DEL CAUCA | I5: TULUA | J5: PTM TULUA RAPITIENDA HEDMONDT | K5: REDEBAN | L5: FO-25-1914231 | M5: 45992.552 | N5: 45993.749 | O5: NO | P5: BASEDATAFONO | Q5: BASE DATAFONO | T5: EJECUTADO | U5: EJECUTADO EXITOSO | V5: 01/12/2025 POR FAVOR, COMUNICARSE CON USUARIO PARA CONFIRMAR UBICACION, SOLICITUD Y PROGRAMAR VISITA TECNICA | 02/12/2025 EN LA VISITA TÉCNICA SE REALIZÓ LA INSTALACIÓN DE LA BASE SOPORTE DE EL DATÁFONO,SE PEGÓ CON CINTA DOBLE FAZ DE LA BASE YA QUE SE HABÍA DESPEGADO. | W5: VISITA TECNICA | X5: OB004860 | Y5: TIPO II | Z5: TERRESTRE | AA5: SANCHEZ URREGO ROBINSON DAVID | AB5: 1 | AC5: 0 | AD5: 144968 | AE5: 140396 | AF5: 144968
A6: BOGOTA | B6: CUNDINAMARCA | C6: 0004-0004 | D6: 25151 | E6: 3085132 | F6: 3007050561 | G6: OC BASE DATAFONO | H6: CUNDINAMARCA | I6: CAQUEZA | J6: PTM CAQUEZA DROGAS CASA ORTIZ | K6: REDEBAN | L6: FO-25-1914229 | M6: 45992.597 | N6: 45993.458 | O6: NO | P6: BASEDATAFONO | Q6: BASE DATAFONO | R6: AGREGADOR | S6: COMCARD - PTM | T6: EJECUTADO | U6: EJECUTADO EXITOSO | V6: 01/12/2025 POR FAVOR, COMUNICARSE CON USUARIO PARA CONFIRMAR UBICACION, SOLICITUD Y PROGRAMAR VISITA TECNICA | 02/12/2025 INSTALACIÓN BASE DATÁFONO | W6: VISITA TECNICA | X6: AAL0H212 | Y6: TIPO II | Z6: TERRESTRE | AA6: ARIAS QUILINDO JULIAN | AB6: 1 | AC6: 0 | AD6: 144968 | AE6: 140396 | AF6: 144968
A7: PEREIRA | B7: SUROCCIDENTE Y EJE CAFETERO | C7: 0004-0002 | D7: 66001 | E7: 3086796 | F7: 3007049275 | G7: OC BASE DATAFONO | H7: RISARALDA | I7: PEREIRA | J7: DISTRICOL TIENDA NUEVA VILLA | K7: REDEBAN | L7: FO-25-1916517 | M7: 45992.724 | N7: 45994.52 | O7: NO | P7: BASEDATAFONO | Q7: BASE DATAFONO | R7: AGREGADOR | S7: DISTRICOL | T7: EJECUTADO | U7: EJECUTADO EXITOSO | V7: 02/12/2025 POR FAVOR, COMUNICARSE CON USUARIO PARA CONFIRMAR UBICACION, SOLICITUD Y PROGRAMAR VISITA TECNICA | 03/12/2025 SE INSTALA BASE DE DATÁFONO, YA QUE LA BASE ANTERIOR SE DAÑO | W7: VISITA TECNICA | X7: 9C00Q125 | Y7: TIPO I | Z7: TERRESTRE | AA7: FRANCO CAÑAVERAL YAMID RAUL | AB7: 1 | AC7: 0 | AD7: 65960 | AE7: 75096 | AF7: 65960
A8: APARTADO | B8: NOROCCIDENTE | C8: 0004-0005 | D8: 5837 | E8: 3087118 | F8: 3007041224 | G8: OC BASE DATAFONO | H8: ANTIOQUIA | I8: TURBO | J8: BARRIO EL 3 TURBO | K8: REDEBAN | L8: FO-25-1916519 | M8: 45992.713 | N8: 46000.617 | O8: NO | P8: BASEDATAFONO | Q8: BASE DATAFONO | R8: CB UNO A UNO | S8: CB UNO A UNO | T8: EJECUTADO | U8: EJECUTADO EXITOSO | V8: 02/12/2025 POR FAVOR, COMUNICARSE CON USUARIO PARA CONFIRMAR UBICACION, SOLICITUD Y PROGRAMAR VISITA TECNICA | 10/12/2025 USUARIO NO TIENE BASE LA ANTERIOR SE DAÑÓ, SE INSTALA NUEVA BASE DATAFONO | W8: VISITA TECNICA | X8: 9L8ZZ665 | Y8: TIPO II | Z8: TERRESTRE | AA8: SALDARRIAGA MIRANDA SANTIAGO | AB8: 1 | AC8: 0 | AD8: 144968 | AE8: 140396 | AF8: 144968
A9: BOGOTA | B9: CUNDINAMARCA | C9: 0004-0004 | D9: 11001 | E9: 3088785 | F9: 3007072338 | G9: OC BASE DATAFONO | H9: CUNDINAMARCA | I9: BOGOTA | J9: PTM MALU PET | K9: REDEBAN | L9: FO-25-1925221 | FO-25-1917554 | M9: 45993.383 | N9: 45994.587 | O9: NO | P9: BASEDATAFONO | Q9: BASE DATAFONO | R9: AGREGADOR | S9: COMCARD - PTM | T9: EJECUTADO | EJECUTADO / CANCELADO | U9: EJECUTADO EXITOSO | V9: [FO-25-1925221] 03/12/2025 SE REALIZA INSTALACIÓN DE BASE YA QUE LA ANTERIOR SE CALLO Y SE ROMPIÓ || [FO-25-1917554] 02/12/2025 POR FAVOR, COMUNICARSE CON USUARIO PARA CONFIRMAR UBICACION, SOLICITUD Y PROGRAMAR VISITA TECNICA | 03/12/2025 SE VISITA COMERCIO ESTÁ CERRADO SE LLAMA PERO INDICA QUE NO ESTÁ EN EL PUNTO Y SE DEMORA | W9: VISITA TECNICA | X9: ON00N784 | Y9: TIPO I | Z9: TERRESTRE | AA9: GALINDO ROJAS LUIS FELIPE | AB9: 2 | AC9: 0 | AD9: 131920 | AE9: 75096 | AF9: 131920
A10: BARRANQUILLA | B10: COSTA | C10: 0004-0001 | D10: 8001 | E10: 3096153 | F10: 3007075581 | G10: OC BASE DATAFONO | H10: ATLANTICO | I10: BARRANQUILLA | J10: PTM BARRANQUILLA FARMA EXPRESS | K10: REDEBAN | L10: FO-25-1925212 | M10: 45994.435 | N10: 46000.91 | O10: NO | P10: BASEDATAFONO | Q10: BASE DATAFONO | R10: AGREGADOR | S10: COMCARD - PTM | T10: EJECUTADO | U10: EJECUTADO EXITOSO | V10: 03/12/2025 POR FAVOR, COMUNICARSE CON USUARIO PARA CONFIRMAR UBICACION, SOLICITUD Y PROGRAMAR VISITA TECNICA | 09/12/2025 SE REALIZA VISITA SE PROCEDE A PEGARLE LA BASE AL CLIENTE Y TODO OK EQUIPOS OPERATIVO | W10: VISITA TECNICA | X10: A400L272-A400M951 | Y10: TIPO I | Z10: TERRESTRE | AA10: PORRAS CASTRO DARLON NASCK | AB10: 1 | AC10: 0 | AD10: 65960 | AE10: 75096 | AF10: 65960
A11: BOGOTA | B11: CUNDINAMARCA | C11: 0004-0004 | D11: 97001 | E11: 3097129 | F11: 3007022566 | G11: OC BASE DATAFONO | H11: VAUPES | I11: MITU | J11: CENTRO MITU II VAUPES | K11: REDEBAN | L11: FO-25-1926453 | M11: 45994.492 | N11: 45996.537 | O11: NO | P11: BASEDATAFONO | Q11: BASE DATAFONO | R11: CB UNO A UNO | S11: CB UNO A UNO | T11: EJECUTADO / CANCELADO | U11: CANCELADO POR EL USUARIO | V11: 03/12/2025 POR FAVOR, COMUNICARSE CON USUARIO PARA CONFIRMAR UBICACION, SOLICITUD Y PROGRAMAR VISITA TECNICA | 05/12/2025 SE REALIZA COMUNICACIÓN CON LA SEÑORA CARMEN SANDOVAL AL NÚMERO 3132610860 CLIENTE INDICA QUE NO SOLICITO BASE SI NO UN INCIDENTE ,PERO CLIENTE INDICA QUE LE QUITARON EL INTERNET QUE LE HABÍAN DADO POR MEDIO DEL BANCO PERO YA SE CONECTO POR MEDIO DE OTRO INTERNET Y FUNCIONÓ | W11: SOPORTE TELEFONICO | X11: NO | Y11: TIPO V | Z11: AEREO | AA11: GALINDO ROJAS LUIS FELIPE | AB11: 0 | AC11: 0 | AD11: 41241 | AE11: 0 | AF11: 41241
A12: MEDELLIN | B12: NOROCCIDENTE | C12: 0004-0005 | D12: 5001 | E12: 3099925 | F12: 3007050145 | G12: OC BASE DATAFONO | H12: ANTIOQUIA | I12: MEDELLIN | J12: PTM MEDELLIN GRANERO MIXTO EL | K12: REDEBAN | L12: FO-25-1930200 | M12: 45995.333 | N12: 45996.54 | O12: NO | P12: BASEDATAFONO | Q12: BASE DATAFONO | R12: AGREGADOR | S12: COMCARD - PTM | T12: EJECUTADO | U12: EJECUTADO EXITOSO | V12: 04/12/2025 POR FAVOR, COMUNICARSE CON USUARIO PARA CONFIRMAR UBICACION, SOLICITUD Y PROGRAMAR VISITA TECNICA | 05/12/2025 SE INSTALA BASE NUEVA DEBIDO A ROTURA EN LA PATA DE LA BASE | W12: VISITA TECNICA | X12: GB00V335 | Y12: TIPO I | Z12: TERRESTRE | AA12: QUINTERO SANCHEZ JUAN SEBASTIAN | AB12: 1 | AC12: 0 | AD12: 65960 | AE12: 75096 | AF12: 65960
A13: BOGOTA | B13: CUNDINAMARCA | C13: 0004-0004 | D13: 11001 | E13: 3104068 | F13: 3007037525 | G13: OC BASE DATAFONO | H13: CUNDINAMARCA | I13: BOGOTA | J13: BARRIO SIMON BOLIVAR BOGOTA 1 | K13: REDEBAN | L13: FO-25-1932283 | M13: 45995.635 | N13: 46000.911 | O13: NO | P13: BASEDATAFONO | Q13: BASE DATAFONO | R13: CB UNO A UNO | S13: CB UNO A UNO | T13: EJECUTADO | U13: EJECUTADO EXITOSO | V13: 04/12/2025 POR FAVOR, COMUNICARSE CON USUARIO PARA CONFIRMAR UBICACION, SOLICITUD Y PROGRAMAR VISITA TECNICA | 09/12/2025 SEREALIZA INSTALACIÓN DE BASE POR SOLICITUD DEL CLIENTE YA QUE LA ANTERIOR SE CALLO Y SE PARTIÓ | W13: VISITA TECNICA | X13: 1A007122-AC00Z830 | Y13: TIPO I | Z13: TERRESTRE | AA13: GALINDO ROJAS LUIS FELIPE | AB13: 1 | AC13: 0 | AD13: 65960 | AE13: 75096 | AF13: 65960
A14: BOGOTA | B14: CUNDINAMARCA | C14: 0004-0004 | D14: 11001 | E14: 3105212 | F14: 3007026553 | G14: OC BASE DATAFONO | H14: CUNDINAMARCA | I14: BOGOTA | J14: REDY 20 DE JULIO | K14: REDEBAN | L14: FO-25-1936140 | M14: 45995.715 | N14: 45997.538 | O14: NO | P14: BASEDATAFONO | Q14: BASE DATAFONO | R14: ROBUSTO | S14: REDY | T14: EJECUTADO | U14: EJECUTADO EXITOSO | V14: 05/12/2025 POR FAVOR, COMUNICARSE CON USUARIO PARA CONFIRMAR UBICACION, SOLICITUD Y PROGRAMAR VISITA TECNICA | 06/12/2025 SE REALIZA INSTALACIÓN DE BASE PARA DATÁFONO | W14: VISITA TECNICA | X14: 1A00N233 | Y14: TIPO I | Z14: TERRESTRE | AA14: MICHELI LOPEZ MIGUEL ANGEL | AB14: 1 | AC14: 0 | AD14: 65960 | AE14: 75096 | AF14: 65960
A15: APARTADO | B15: NOROCCIDENTE | C15: 0004-0005 | D15: 27615 | E15: 3105738 | F15: 3007015734 | G15: OC BASE DATAFONO | H15: CHOCO | I15: RIOSUCIO | J15: BELEN DE BAJIRA IV CHOCO | K15: REDEBAN | L15: FO-25-1936134 | M15: 45996.336 | N15: 46002.387 | O15: NO | P15: BASEDATAFONO | Q15: BASE DATAFONO | R15: CB UNO A UNO | S15: CB UNO A UNO | T15: EJECUTADO | U15: EJECUTADO EXITOSO | V15: 05/12/2025 POR FAVOR, COMUNICARSE CON USUARIO PARA CONFIRMAR UBICACION, SOLICITUD Y PROGRAMAR VISITA TECNICA | 11/12/2025 SE INSTALA BASE DATÁFONO DESK 2600 YA QUE LA ANTERIOR NO ERA COMPATIBLE Y AL MOMENTO DE ABASTECER EL ROLLO SE PARTIÓ. SE LE INSTALO UNA NUEVA COMPATIBLE CON EL EQUIPO. | W15: VISITA TECNICA | X15: A00DZ261 | Y15: TIPO V | Z15: TERRESTRE/FLUVIAL | AA15: SALDARRIAGA MIRANDA SANTIAGO | AB15: 1 | AC15: 0 | AD15: 479589 | AE15: 196537 | AF15: 479589
A16: VALLEDUPAR | B16: COSTA | C16: 0004-0001 | D16: 20517 | E16: 3106565 | F16: 3007060946 | G16: OC BASE DATAFONO | H16: CESAR | I16: PAILITAS | J16: BARRIO EL BOSQUE PAILITAS | K16: REDEBAN | L16: FO-25-1936131 | M16: 45996.405 | N16: 45997.505 | O16: NO | P16: BASEDATAFONO | Q16: BASE DATAFONO | R16: CB UNO A UNO | S16: CB UNO A UNO | T16: EJECUTADO | U16: EJECUTADO EXITOSO | V16: 05/12/2025 POR FAVOR, COMUNICARSE CON USUARIO PARA CONFIRMAR UBICACION, SOLICITUD Y PROGRAMAR VISITA TECNICA | 06/12/2025 BUENOS DÍAS SE VISITA CB Y SE LE HACE INSTALACIÓN DE BASE DE DATAFONO | W16: VISITA TECNICA | X16: KA00F847 | Y16: TIPO IV | Z16: TERRESTRE | AA16: BENITEZ CARVAJAL ALVARO JAVIER | AB16: 1 | AC16: 0 | AD16: 479589 | AE16: 196537 | AF16: 479589
A17: BOGOTA | B17: CUNDINAMARCA | C17: 0004-0004 | D17: 11001 | E17: 3108900 | F17: 3007013194 | G17: OC BASE DATAFONO | H17: CUNDINAMARCA | I17: BOGOTA | J17: CENTRO COMERCIAL DIVER PLAZA | K17: REDEBAN | L17: FO-25-1937466 | M17: 45996.581 | N17: 45997.54 | O17: NO | P17: BASEDATAFONO | Q17: BASE DATAFONO | R17: ROBUSTO | S17: OPRAP | T17: EJECUTADO | U17: EJECUTADO EXITOSO | V17: 05/12/2025 POR FAVOR, COMUNICARSE CON USUARIO PARA CONFIRMAR UBICACION, SOLICITUD Y PROGRAMAR VISITA TECNICA | 06/12/2025 SE VISITA COMERCIO CB BANCOLOMBIA, CLIENTE INDICA QUE LA BASE NUEVA QUE LE HABÍAN INSTALADO ES MUY ENDEBLE Y NO SE MANTIENE ESTABLE, SE CAMBIA BASE, SE DEJAN LA NUEVA FUNCIONANDO OK, NO SE MANIPULAN EQUIPOS. | W17: VISITA TECNICA | X17: V1ZZZ970 | Y17: TIPO I | Z17: TERRESTRE | AA17: VEGA MANRIQUE JONATAN MAURICIO | AB17: 1 | AC17: 0 | AD17: 65960 | AE17: 75096 | AF17: 65960
... A36: MEDELLIN | B36: NOROCCIDENTE | C36: 0004-0005 | D36: 5212 | E36: 3146283 | F36: 3007030570 | G36: OC BASE DATAFONO | H36: ANTIOQUIA | I36: COPACABANA | J36: ARRIO VILLA NUEVA COPACABANA | K36: REDEBAN | L36: FO-25-1985639 | M36: 46008.333 | N36: 46011.424 | O36: NO | P36: BASEDATAFONO | Q36: BASE DATAFONO | R36: CB UNO A UNO | S36: CB UNO A UNO | T36: EJECUTADO | U36: EJECUTADO EXITOSO | V36: 17/12/2025 SE ESCALA PARA VISITA. LLAMAR ANTES DE VISITAR, CONFIRMAR FALLA Y DATOS | 20/12/2025 SE REALIZA INSTALACIÓN DE BASE YA QUE LA ANTERIOR SE DAÑÓ | W36: VISITA TECNICA | X36: BL01Y284 | Y36: TIPO I | Z36: TERRESTRE | AA36: ZAPATA LOPEZ EDWARD ASDRUBAL | AB36: 1 | AC36: 0 | AD36: 65960 | AE36: 75096 | AF36: 65960
A37: CALI | B37: SUROCCIDENTE Y EJE CAFETERO | C37: 0004-0003 | D37: 76001 | E37: 3150763 | F37: 3007063111 | G37: OC BASE DATAFONO | H37: VALLE DEL CAUCA | I37: CALI | J37: PAGAFACIL PARQUE DE LA CANA | K37: REDEBAN | L37: FO-25-2001410 | M37: 46008.671 | N37: 46010.57 | O37: NO | P37: BASEDATAFONO | Q37: BASE DATAFONO | R37: ROBUSTO | S37: PAGAFACIL | T37: EJECUTADO | U37: EJECUTADO EXITOSO | V37: 19/12/2025 SE ENTREGAN 140 ROLLOS A YURI FAJARDO | W37: VISITA TECNICA | Y37: TIPO I | Z37: TERRESTRE | AA37: CUERO RUIZ JHONNY | AB37: 1 | AC37: 0 | AD37: 65960 | AE37: 75096 | AF37: 65960
A38: PEREIRA | B38: SUROCCIDENTE Y EJE CAFETERO | C38: 0004-0002 | D38: 63001 | E38: 3151066 | F38: 3007018910 | G38: OC BASE DATAFONO | H38: QUINDIO | I38: ARMENIA | J38: MULTIPAGAS ARMENIA | K38: REDEBAN | L38: FO-25-1994261 | M38: 46008.682 | N38: 46011.605 | O38: NO | P38: BASEDATAFONO | Q38: BASE DATAFONO | R38: ROBUSTO | S38: MULTIPAGAS | T38: EJECUTADO | U38: EJECUTADO EXITOSO | V38: 18/12/2025 SE ESCALA PARA VISITA. LLAMAR ANTES DE VISITAR, CONFIRMAR FALLA Y DATOS | 20/12/2025 SE VISITA COMERCIO SE REALIZÓ INSTALACION DE BASE, ANTERIOR BASE CON DAÑO FÍSICO. | W38: VISITA TECNICA | X38: GZ0OZ597 | Y38: TIPO II | Z38: TERRESTRE | AA38: SANCHEZ SOLORZANO JUAN SEBASTIAN | AB38: 1 | AC38: 0 | AD38: 144968 | AE38: 140396 | AF38: 144968
A39: MEDELLIN | B39: NOROCCIDENTE | C39: 0004-0005 | D39: 5001 | E39: 3153189 | F39: 3007073877 | G39: OC BASE DATAFONO | H39: ANTIOQUIA | I39: MEDELLIN | J39: DISTRICOL EL MEJOR SERVICIO 1 | K39: REDEBAN | L39: FO-25-1995849 | M39: 46009.407 | N39: 46011.447 | O39: NO | P39: BASEDATAFONO | Q39: BASE DATAFONO | R39: AGREGADOR | S39: DISTRICOL | T39: EJECUTADO / CANCELADO | U39: CB CERRADO - DESOCUPADO | V39: 18/12/2025 SE ESCALA PARA VISITA. LLAMAR ANTES DE VISITAR, CONFIRMAR FALLA Y DATOS | 20/12/2025 SE VISITA COMERCIO Y SE ENCUENTRA LOCAL CERRADO, NO SE LOGRA COMUNICACIÓN CON EL USUARIO | W39: VISITA TECNICA | X39: NA | Y39: TIPO I | Z39: TERRESTRE | AA39: DIAZ ZABALA FRANCIS DUBAN | AB39: 1 | AC39: 0 | AD39: 65960 | AE39: 75096 | AF39: 65960
A40: MEDELLIN | B40: NOROCCIDENTE | C40: 0004-0005 | D40: 5088 | E40: 3153809 | F40: 3007015615 | G40: OC BASE DATAFONO | H40: ANTIOQUIA | I40: BELLO | J40: PAGAFACIL PARQUE DE BELLO | K40: REDEBAN | L40: FO-25-1995847 | M40: 46009.442 | N40: 46013.549 | O40: NO | P40: BASEDATAFONO | Q40: BASE DATAFONO | R40: ROBUSTO | S40: PAGAFACIL | T40: EJECUTADO | U40: EJECUTADO EXITOSO | V40: 18/12/2025 SE ESCALA PARA VISITA. LLAMAR ANTES DE VISITAR, CONFIRMAR FALLA Y DATOS | 22/12/2025 SE REALIZA INSTALACIÓN DE BASE DE DATAFONO YA QUE LA ANTERIOR SE DAÑÓ | W40: VISITA TECNICA | X40: JAUZZ004 | Y40: TIPO I | Z40: TERRESTRE | AA40: ZAPATA LOPEZ EDWARD ASDRUBAL | AB40: 1 | AC40: 0 | AD40: 65960 | AE40: 75096 | AF40: 65960
A41: MEDELLIN | B41: NOROCCIDENTE | C41: 0004-0005 | D41: 5001 | E41: 3158548 | F41: 3007074181 | G41: OC BASE DATAFONO | H41: ANTIOQUIA | I41: MEDELLIN | J41: BARRIO SAN JAVIER MEDELLIN 8 | K41: REDEBAN | L41: FO-25-2001462 | M41: 46010.428 | N41: 46013.552 | O41: NO | P41: BASEDATAFONO | Q41: BASE DATAFONO | R41: CB UNO A UNO | S41: CB UNO A UNO | T41: EJECUTADO | U41: EJECUTADO EXITOSO | V41: 19/12/2025 SE ESCALA PARA VISITA. LLAMAR ANTES DE VISITAR, CONFIRMAR FALLA Y DATOS | 22/12/2025 SR INSTALA BASE PARA DATAFONO | W41: VISITA TECNICA | X41: EG2ZZ979 | Y41: TIPO I | Z41: TERRESTRE | AA41: BADEL ACUÑA LUIS ALBERTO | AB41: 1 | AC41: 0 | AD41: 65960 | AE41: 75096 | AF41: 65960
A42: MEDELLIN | B42: NOROCCIDENTE | C42: 0004-0005 | D42: 5148 | E42: 3159846 | F42: 3007042558 | G42: OC BASE DATAFONO | H42: ANTIOQUIA | I42: EL CARMEN DE VIBORAL | J42: DISTRICOL MISCELANEA LA MORENI | K42: REDEBAN | L42: FO-25-2007559 | M42: 46010.572 | N42: 46018.349 | O42: NO | P42: BASEDATAFONO | Q42: BASE DATAFONO | R42: AGREGADOR | S42: DISTRICOL | T42: EJECUTADO | U42: EJECUTADO EXITOSO | V42: 19/12/2025 SE ESCALA PARA VISITA. LLAMAR ANTES DE VISITAR, CONFIRMAR FALLA Y DATOS | 26/12/2025 SE VISITA PUNTO Y CLIENTE INFORMA QUE ES PARA PEGARLA BASE YA QUE SE DESPEGO, SE CAMBIA LA PEGA Y QUEDA TODO OK | W42: VISITA TECNICA | X42: GZ5ZZ006 | Y42: TIPO II | Z42: TERRESTRE | AA42: QUINTERO SANCHEZ JUAN SEBASTIAN | AB42: 1 | AC42: 0 | AD42: 144968 | AE42: 140396 | AF42: 144968
A43: MEDELLIN | B43: NOROCCIDENTE | C43: 0004-0005 | D43: 5607 | E43: 3160979 | F43: 3007014258 | G43: OC BASE DATAFONO | H43: ANTIOQUIA | I43: RETIRO | J43: MULTIPAGAS EL RETIRO | K43: REDEBAN | L43: FO-25-2008169 | M43: 46010.695 | N43: 46011.61 | O43: NO | P43: BASEDATAFONO | Q43: BASE DATAFONO | R43: ROBUSTO | S43: MULTIPAGAS | T43: EJECUTADO | U43: EJECUTADO EXITOSO | V43: 19/12/2025 SE ESCALA PARA VISITA. LLAMAR ANTES DE VISITAR, CONFIRMAR FALLA Y DATOS | 20/12/2025 SE REALIZÓ INSTALACIÓN DE BASE PARA DATAFONO | W43: VISITA TECNICA | X43: JACZZ456 | Y43: TIPO II | Z43: TERRESTRE | AA43: CASTAÑEDA PALACIO CARLOS FELIPE | AB43: 1 | AC43: 0 | AD43: 144968 | AE43: 140396 | AF43: 144968
A44: PEREIRA | B44: SUROCCIDENTE Y EJE CAFETERO | C44: 0004-0002 | D44: 76147 | E44: 3161589 | F44: 3007079831 | G44: OC BASE DATAFONO | H44: VALLE DEL CAUCA | I44: CARTAGO | J44: PTM CARTAGO RESIDENCIA MI CAS | K44: REDEBAN | L44: FO-25-2009922 | M44: 46011.454 | N44: 46015.353 | O44: NO | P44: BASEDATAFONO | Q44: BASE DATAFONO | R44: AGREGADOR | S44: COMCARD - PTM | T44: EJECUTADO | U44: EJECUTADO EXITOSO | V44: 20/12/2025 SE ESCALA PARA VISITA. LLAMAR ANTES DE VISITAR, CONFIRMAR FALLA Y DATOS | 23/12/2025 SE VISITA COMERCIO SE REALIZA INSTALACIÓN DE BASE | W44: VISITA TECNICA | X44: FAVZZ676 | Y44: TIPO I | Z44: TERRESTRE | AA44: LOAIZA LOPEZ JHON FREDDY | AB44: 1 | AC44: 0 | AD44: 65960 | AE44: 75096 | AF44: 65960
A45: BUCARAMANGA | B45: SANTANDERES | C45: 0004-0008 | D45: 68001 | E45: 3164537 | F45: 3007020727 | G45: OC BASE DATAFONO | H45: SANTANDER | I45: BUCARAMANGA | J45: MULTIPAGAS MEGAMALL | K45: REDEBAN | L45: FO-25-2014783 | M45: 46013.43 | N45: 46014.353 | O45: NO | P45: BASEDATAFONO | Q45: BASE DATAFONO | R45: ROBUSTO | S45: MULTIPAGAS | T45: EJECUTADO | U45: EJECUTADO EXITOSO | V45: 22/12/2025 SE ESCALA PARA VISITA. LLAMAR ANTES DE VISITAR, CONFIRMAR FALLA Y DATOS | 22/12/2025 SE REALIZA INSTALACIÓN DE 4 BASES PARA DATAFONO NI SE INTERVIENEN TERMINALES SERVICIO OPERATIVO | W45: VISITA TECNICA | X45: AB0FZ242-AAAAX230-AAAAX228-AB0FZ241 | Y45: TIPO I | Z45: TERRESTRE | AA45: REYES RAMIREZ DIEGO ALEXANDER | AB45: 1 | AC45: 0 | AD45: 65960 | AE45: 75096 | AF45: 65960
A46: APARTADO | B46: NOROCCIDENTE | C46: 0004-0005 | D46: 5172 | E46: 3164947 | F46: 3007038651 | G46: OC BASE DATAFONO | H46: ANTIOQUIA | I46: CHIGORODO | J46: ARRIO CHIGORODO CHIGORODO | K46: REDEBAN | L46: FO-25-2014899 | M46: 46013.446 | N46: 46017.659 | O46: NO | P46: BASEDATAFONO | Q46: BASE DATAFONO | R46: CB UNO A UNO | S46: CB UNO A UNO | T46: EJECUTADO | U46: EJECUTADO EXITOSO | V46: 22/12/2025 SE ESCALA PARA VISITA. LLAMAR ANTES DE VISITAR, CONFIRMAR FALLA Y DATOS | 26/12/2025 SE INSTALA BASE DE DATAFONO YA QUE LA USUARIA NO CONTABA CON UNA, MANIFIESTA QUE LA ANTERIOR SE DAÑÓ HACE MUCHO TIEMPO | W46: VISITA TECNICA | X46: GZ00Z204 | Y46: TIPO II | Z46: TERRESTRE | AA46: SALDARRIAGA MIRANDA SANTIAGO | AB46: 1 | AC46: 0 | AD46: 144968 | AE46: 140396 | AF46: 144968
A47: CUCUTA | B47: SANTANDERES | C47: 0004-0008 | D47: 54001 | E47: 3165624 | F47: 3007079069 | G47: OC BASE DATAFONO | H47: NORTE DE SANTANDER | I47: CUCUTA | J47: BARRIO GUAIMARAL CUCUTA 12 | K47: REDEBAN | L47: FO-25-2015415 | M47: 46013.482 | N47: 46014.516 | O47: NO | P47: BASEDATAFONO | Q47: BASE DATAFONO | R47: CB UNO A UNO | S47: CB UNO A UNO | T47: EJECUTADO | U47: EJECUTADO EXITOSO | V47: 22/12/2025 SE ESCALA PARA VISITA. LLAMAR ANTES DE VISITAR, CONFIRMAR FALLA Y DATOS | 23/12/2025 SE REALIZA VISITA, SE REALIZA CAMBIO DE BASE POR DAÑO. | W47: VISITA TECNICA | X47: SASZZ644 | Y47: TIPO I | Z47: TERRESTRE | AA47: PACHECO BUITRAGO JAVIER ALONSO | AB47: 1 | AC47: 0 | AD47: 65960 | AE47: 75096 | AF47: 65960
A48: MEDELLIN | B48: NOROCCIDENTE | C48: 0004-0005 | D48: 5088 | E48: 3168375 | F48: 3007075015 | G48: OC BASE DATAFONO | H48: ANTIOQUIA | I48: BELLO | J48: PTM MEDELLIN DMU | K48: REDEBAN | L48: FO-25-2020912 | M48: 46014.333 | N48: 46019.457 | O48: NO | P48: BASEDATAFONO | Q48: BASE DATAFONO | R48: AGREGADOR | S48: COMCARD - PTM | T48: CANCELADO | U48: PETICIÓN USUARIO | V48: 23/12/2025 SE ESCALA PARA VISITA. LLAMAR ANTES DE VISITAR, CONFIRMAR FALLA Y DATOS | 26/12/2025 SE LLEGA AL SITIO Y SE ENCONTRÓ CERRADO, SE REALIZA GESTIÓN TELEFÓNICA LA NÚMERO 3122946560 Y NO CONTESTAN | W48: VISITA TECNICA | Y48: TIPO I | Z48: TERRESTRE | AA48: BARRIENTOS HERNANDEZ CRISTIAN HORACIO | AB48: 1 | AC48: 0 | AD48: 65960 | AE48: 75096 | AF48: 65960
A49: APARTADO | B49: NOROCCIDENTE | C49: 0004-0005 | D49: 27615 | E49: 3169369 | F49: 3007015734 | G49: OC BASE DATAFONO | H49: CHOCO | I49: RIOSUCIO | J49: BELEN DE BAJIRA IV CHOCO | K49: REDEBAN | L49: FO-25-2021883 | M49: 46014.375 | N49: 46017.519 | O49: NO | P49: BASEDATAFONO | Q49: BASE DATAFONO | R49: CB UNO A UNO | S49: CB UNO A UNO | T49: EJECUTADO | U49: EJECUTADO EXITOSO | V49: 23/12/2025 SE ESCALA PARA VISITA. LLAMAR ANTES DE VISITAR, CONFIRMAR FALLA Y DATOS | 26/12/2025 SE INSTALA BASE NUEVA YA QUE LA ANTERIOR UN CLIENTE AL MOMENTO DE PONER LA CABLE DAÑO LA BASE. | W49: VISITA TECNICA | X49: A00DZ261 | Y49: TIPO V | Z49: TERRESTRE/FLUVIAL | AA49: SALDARRIAGA MIRANDA SANTIAGO | AB49: 1 | AC49: 0 | AD49: 479589 | AE49: 196537 | AF49: 479589
A50: CARTAGENA | B50: COSTA | C50: 0004-0001 | D50: 13836 | E50: 3175203 | F50: 3007048796 | G50: OC BASE DATAFONO | H50: BOLIVAR | I50: TURBACO | J50: PTM TURBACO DROGUERIA LA GRAN | K50: REDEBAN | L50: FO-25-2027457 | M50: 46015.456 | N50: 46019.466 | O50: NO | P50: BASEDATAFONO | Q50: BASE DATAFONO | R50: AGREGADOR | S50: COMCARD - PTM | T50: EJECUTADO / CANCELADO | U50: PETICIÓN USUARIO | V50: 24/12/2025 SE ESCALA PARA VISITA. LLAMAR ANTES DE VISITAR, CONFIRMAR FALLA Y DATOS | 27/12/2025 SE LLEGO AL SITIO Y SE ENCONTRÓ CERRADO CLIENTE INFORMO QUE NO PODÍA IR ABRIR EL LOCAL POR QUE SE LE VARO EL CARRO Y YA POR EL DIA NO CREE QUE ABRA MAS Y TAMBIEN INFORMA QUE EN TODA LA SEMANA NO VA ABRIR Y QUE ABRE NUEVAMENTE EL 5 DE ENERO POR LO QUE INFORMA QUE VA VOLVER A LLAMAR PARA SOLICITAR LA VISITA POR LO TANTO SE CANCELA | 27/12/2025 SE LLEGO AL SITIO Y SE ENCONTRÓ CERRADO CLIENTE INFORMO QUE NO PODÍA IR ABRIR EL LOCAL POR QUE SE LE VARO EL CARRO Y YA POR EL DIA NO CREE QUE ABRA MAS Y TAMBIEN INFORMA QUE EN TODA LA SEMANA NO VA ABRIR Y QUE ABRE NUEVAMENTE EL 5 DE ENERO POR LO QUE INFORMA QUE VA VOLVER A LLAMAR PARA SOLICITAR LA VISITA POR LO TANTO SE CANCELA | W50: VISITA TECNICA | X50: NA | Y50: TIPO II | Z50: TERRESTRE | AA50: MARTINEZ SALGUEDO ANDRES AUGUSTO | AB50: 1 | AC50: 0 | AD50: 144968 | AE50: 140396 | AF50: 144968
A51: CARTAGENA | B51: COSTA | C51: 0004-0001 | D51: 13683 | E51: 3176289 | F51: 3007050677 | G51: OC BASE DATAFONO | H51: BOLIVAR | I51: SANTA ROSA | J51: BARRIO EL TAMARINDO SANTA ROSA | K51: REDEBAN | L51: FO-25-2029467 | M51: 46017.352 | N51: 46018.574 | O51: NO | P51: BASEDATAFONO | Q51: BASE DATAFONO | R51: CB UNO A UNO | S51: CB UNO A UNO | T51: EJECUTADO | U51: EJECUTADO EXITOSO | V51: 26/12/2025 SE ESCALA PARA VISITA. LLAMAR ANTES DE VISITAR, CONFIRMAR FALLA Y DATOS | 27/12/2025 SE REALIZA ENTREGA DE BASE DE DATAFONO REDEBAN | W51: VISITA TECNICA | X51: BA00Y377 | Y51: TIPO II | Z51: TERRESTRE | AA51: AVILA DE HORTA FERNANDO JOSE | AB51: 1 | AC51: 0 | AD51: 144968 | AE51: 140396 | AF51: 144968
A52: BARRANQUILLA | B52: COSTA | C52: 0004-0001 | D52: 8001 | E52: 3178334 | F52: 3007053261 | G52: OC BASE DATAFONO | H52: ATLANTICO | I52: BARRANQUILLA | J52: PTM BARRANQUILLA MISCELANEA SH | K52: REDEBAN | L52: FO-25-2030356 | M52: 46017.439 | N52: 46021.66 | O52: NO | P52: BASEDATAFONO | Q52: BASE DATAFONO | R52: AGREGADOR | S52: COMCARD - PTM | T52: EJECUTADO | U52: EJECUTADO EXITOSO | V52: 26/12/2025 SE ESCALA PARA VISITA. LLAMAR ANTES DE VISITAR, CONFIRMAR FALLA Y DATOS | 30/12/2025 SE HACE ENTREGA DE LA BASE DEL DATÁFONO DE MANERA EXITOSA | W52: VISITA TECNICA | X52: TR0MZ953 | Y52: TIPO I | Z52: TERRESTRE | AA52: ORTEGA TORRES JUAN SEBASTIAN | AB52: 1 | AC52: 0 | AD52: 65960 | AE52: 75096 | AF52: 65960
A53: PEREIRA | B53: SUROCCIDENTE Y EJE CAFETERO | C53: 0004-0002 | D53: 66170 | E53: 3181726 | F53: 3007049524 | G53: OC BASE DATAFONO | H53: RISARALDA | I53: DOSQUEBRADAS | J53: DISTRICOL PRODUCTOS AGRICOLAS | K53: REDEBAN | L53: FO-25-2042638 | M53: 46020.333 | N53: 46020.41 | O53: NO | P53: BASEDATAFONO | Q53: BASE DATAFONO | R53: AGREGADOR | S53: DISTRICOL | T53: EJECUTADO | U53: EJECUTADO EXITOSO | V53: 28/12/2025 SE ESCALA PARA VISITA. LLAMAR ANTES DE VISITAR, CONFIRMAR FALLA Y DATOS | 29/12/2025 SE INSTALA NUEVA BASE, YA QUE LA ANTERIOR BASE SE PARTIÓ. | W53: VISITA TECNICA | X53: AD00Q102 | Y53: TIPO I | Z53: TERRESTRE | AA53: FRANCO CAÑAVERAL YAMID RAUL | AB53: 1 | AC53: 0 | AD53: 65960 | AE53: 75096 | AF53: 65960
A54: BOGOTA | B54: CUNDINAMARCA | C54: 0004-0004 | D54: 11001 | E54: 3186106 | F54: 3007072196 | G54: OC BASE DATAFONO | H54: CUNDINAMARCA | I54: BOGOTA | J54: PTM BOGOTA GAROTOS KIDS | K54: REDEBAN | L54: FO-25-2048605 | M54: 46020.631 | N54: 46021.624 | O54: NO | P54: BASEDATAFONO | Q54: BASE DATAFONO | R54: AGREGADOR | S54: COMCARD - PTM | T54: EJECUTADO | U54: EJECUTADO EXITOSO | V54: 29/12/2025 SE ESCALA PARA VISITA. LLAMAR ANTES DE VISITAR, CONFIRMAR FALLA Y DATOS | 30/12/2025 SE INSTALA BASE | W54: VISITA TECNICA | X54: NN00N665 | Y54: TIPO I | Z54: TERRESTRE | AA54: INFANTE SIERRA MANUEL FERNANDO | AB54: 1 | AC54: 0 | AD54: 65960 | AE54: 75096 | AF54: 65960
A55: PASTO | B55: SUROCCIDENTE Y EJE CAFETERO | C55: 0004-0003 | D55: 52110 | E55: LC-CS-25-004388 | F55: 3007039878 | G55: OC CIERRE | H55: NARIÑO | I55: BUESACO | J55: DISTRICOL DROGUERIA VILLA MORE | K55: REDEBAN | L55: FO-25-1874717 | M55: 45986.353 | N55: 45992.605 | O55: NO | P55: CIERRE | Q55: CIERRE | R55: AGREGADOR | S55: DISTRICOL | T55: EJECUTADO | U55: CIERRE EXITOSO | V55: 25/11/2025 SE ESCALA PARA VISITA. CONFIRMAR DATOS PARA LA RECOLECCION DE EQUIPOS | 01/12/2025 SE VISITA EL COMERCIO PARA REALIZAR CIERRE DEL CORRESPONSAL, SE RETIRA DATÁFONO CON LECTORA, MAGIC BOX, NO SE RETIRA ROLLOS NI PUBLICIDAD, CLIENTE SOLO CONTABA CON FLANGED AMARILLO, FUE DESTRUIDO, CIERRE OK | W55: VISITA TECNICA | X55: AB0DZ315 | Y55: TIPO II | Z55: TERRESTRE | AA55: GUERRERO RAMIREZ OSCAR DARIO | AB55: 1 | AC55: 0 | AD55: 144968 | AE55: 140396 | AF55: 144968
A56: PASTO | B56: SUROCCIDENTE Y EJE CAFETERO | C56: 0004-0003 | D56: 52001 | E56: LC-CS-25-004390 | F56: 3007074016 | G56: OC CIERRE | H56: NARIÑO | I56: PASTO | J56: DISTRICOL MINIMARKET LA 42 | K56: REDEBAN | L56: FO-25-1874713 | M56: 45986.353 | N56: 45992.466 | O56: NO | P56: CIERRE | Q56: CIERRE | R56: AGREGADOR | S56: DISTRICOL | T56: EJECUTADO | U56: CIERRE EXITOSO | V56: 25/11/2025 SE ESCALA PARA VISITA. CONFIRMAR DATOS PARA LA RECOLECCION DE EQUIPOS | 01/12/2025 SE REALIZA CIERRE DE CB SE RETIRA DATÁFONO CON BASE Y LECTORA COMPLETOS Y EN BUEN ESTADO, CIERRE OK | W56: VISITA TECNICA | X56: MN0SZ921 | Y56: TIPO I | Z56: TERRESTRE | AA56: PAZ MARTINEZ RICHARD HUMBERTO | AB56: 1 | AC56: 0 | AD56: 65960 | AE56: 75096 | AF56: 65960
A57: BUCARAMANGA | B57: SANTANDERES | C57: 0004-0008 | D57: 68406 | E57: LC-CS-25-004393 | F57: 3007032023 | G57: OC CIERRE | H57: SANTANDER | I57: LEBRIJA | J57: COMCARD LEBRIJA ARIES | K57: REDEBAN | L57: FO-25-1874721 | M57: 45986.353 | N57: 45992.467 | O57: NO | P57: CIERRE | Q57: CIERRE | R57: AGREGADOR | S57: COMCARD - PTM | T57: EJECUTADO | U57: CIERRE EXITOSO | V57: 25/11/2025 SE ESCALA PARA VISITA. CONFIRMAR DATOS PARA LA RECOLECCION DE EQUIPOS | 01/12/2025 SE REALIZA VISITA A COMERCIO Y SE RETIRA DTAAFONO LECTORA Y FUENTE, SE REALIZA DESMONTE Y DESTRUCCIÓN DE AVISO EXTERIOR. | W57: VISITA TECNICA | X57: 1111X138 | Y57: TIPO II | Z57: TERRESTRE | AA57: SANTOS GONZALEZ JOHAN FABIAN | AB57: 1 | AC57: 0 | AD57: 144968 | AE57: 140396 | AF57: 144968
A58: CALI | B58: SUROCCIDENTE Y EJE CAFETERO | C58: 0004-0003 | D58: 19001 | E58: LC-CS-25-004398 | F58: 3007081092 | G58: OC CIERRE | H58: CAUCA | I58: POPAYAN | J58: BARRIO LA ESMERALDA POPAYAN 8 | K58: REDEBAN | L58: FO-25-1874735 | M58: 45986.351 | N58: 45992.608 | O58: NO | P58: CIERRE | Q58: CIERRE | R58: UNO A UNO | S58: UNO A UNO | T58: EJECUTADO | U58: CIERRE EXITOSO | V58: 25/11/2025 SE ESCALA PARA VISITA. CONFIRMAR DATOS PARA LA RECOLECCION DE EQUIPOS | 01/12/2025 SE INGRESA SE RECOGE DATAFONO Y LECTOR ESTADO OK SE RECOGE AVISO EXTERIOR SE DESTRUYE EN SITIO | W58: VISITA TECNICA | X58: SGZZZ980 | Y58: TIPO III | Z58: TERRESTRE | AA58: GIMBUEL LASSO LUIS GERMAN | AB58: 1 | AC58: 0 | AD58: 275729 | AE58: 196537 | AF58: 275729
A59: CALI | B59: SUROCCIDENTE Y EJE CAFETERO | C59: 0004-0003 | D59: 76563 | E59: LC-CS-25-010011 | F59: 3007076914 | G59: OC CIERRE | H59: VALLE DEL CAUCA | I59: PRADERA | J59: BARRIO PUERTO NUEVO PRADERA 1 | K59: REDEBAN | L59: FO-25-1888747 | M59: 45988.333 | N59: 45993.708 | O59: NO | P59: CIERRE | Q59: CIERRE | R59: CB UNO A UNO | S59: CB UNO A UNO | T59: EJECUTADO | U59: CIERRE EXITOSO | V59: 26/11/2025 SE ESCALA PARA VISITA. CONFIRMAR DATOS PARA LA RECOLECCION DE EQUIPOS | 02/12/2025 SE REALIZA RETIRO DEL CB SIN NOVEDAD, SE RETIRAN 10 ROLLOS TÉRMICOS. PUBLICIDAD SE DESTRUYE EN SITIO. FLANGER Y DISPLEY SE DESTRUYEN EN SITIO. | W59: VISITA TECNICA | X59: A16ZZ214 | Y59: TIPO II | Z59: TERRESTRE | AA59: TORRES GARCIA JENDRY JOSE | AB59: 1 | AC59: 0 | AD59: 144968 | AE59: 140396 | AF59: 144968
A60: NEIVA | B60: REMOTAS | C60: 0004-0007 | D60: 41001 | E60: LC-CS-25-010013 | F60: 3007076740 | G60: OC CIERRE | H60: HUILA | I60: NEIVA | J60: BARRIO CENTRO NEIVA 28 | K60: REDEBAN | L60: FO-25-1888755 | M60: 45988.333 | N60: 45993.369 | O60: NO | P60: CIERRE | Q60: CIERRE | R60: CB UNO A UNO | S60: CB UNO A UNO | T60: EJECUTADO | U60: CIERRE EXITOSO | V60: 01/12/2025 SE ESCALA PARA VISITA. CONFIRMAR DATOS PARA LA RECOLECCION DE EQUIPOS | 01/12/2025 SE RETIRA DATAFONO, LECTOR DE BARRAS Y ACCESORIOS | W60: VISITA TECNICA | X60: SA2ZZ152 | Y60: TIPO I | Z60: TERRESTRE | AA60: DIAZ VARGAS JONATHAN MIGUEL | AB60: 1 | AC60: 0 | AD60: 65960 | AE60: 75096 | AF60: 65960
... A199: BOGOTA | B199: CUNDINAMARCA | C199: 0004-0004 | D199: 11001 | E199: TA-25-1427965 | F199: 3007017164 | G199: OC CIERRE | H199: CUNDINAMARCA | I199: BOGOTA | J199: BARRIO SUBA LA FONTANA BOGOTA | K199: REDEBAN | L199: FO-25-1987984 | M199: 46008.478 | N199: 46008.669 | O199: NO | P199: CIERRE | Q199: RETIRO VOLUNTARIO | R199: CB UNO A UNO | S199: CB UNO A UNO | T199: EJECUTADO | U199: CIERRE EXITOSO | V199: 17/12/2025 SE VISITA COMERCIO CB BANCOLOMBIA, SE RETIRAN EQUIPOS REDEBAN DATAFONO, LECTOR DE BARRAS, BASE Y CABLEADO, NO HAY PUBLICIDAD A RETIRAR, NO UPS, NO SE MANIPULAN EQUIPOS. USUARIO INDICA QUE NO TIENE ROLLOS | W199: VISITA TECNICA | X199: 1118Z113 | Y199: TIPO I | Z199: TERRESTRE | AA199: VEGA MANRIQUE JONATAN MAURICIO | AB199: 1 | AC199: 0 | AD199: 65960 | AE199: 75096 | AF199: 65960
A200: NEIVA | B200: REMOTAS | C200: 0004-0007 | D200: 18592 | E200: TA-25-1429256 | F200: 3007070924 | G200: OC CIERRE | H200: CAQUETA | I200: PUERTO RICO | J200: BARRIO SANTA FE PUERTO RICO 1 | K200: REDEBAN | L200: FO-25-1989221 | M200: 46008.507 | N200: 46008.665 | O200: NO | P200: CIERRE | Q200: RETIRO VOLUNTARIO | T200: EJECUTADO | U200: CIERRE EXITOSO | V200: 17/12/2025 OK | 17/12/2025 CLIENTE ENTREGA DE FORMA VOLUNTARIA DATAFONO CON SOPORTE, LECTOR DE BARRAS, CABLE MAGIC BOX, FUENTE DE PODER DATÁFONO, ROLLOS NO HAY, PUBLICIDAD DETERIORADA, SE DESTRUYE EN SITIO | W200: VISITA TECNICA | X200: LN00D259 | Y200: TIPO V | Z200: TERRESTRE | AA200: ANDRADE HERNANDEZ JUAN CARLOS | AB200: 1 | AC200: 0 | AD200: 479589 | AE200: 196537 | AF200: 479589
A201: CALI | B201: SUROCCIDENTE Y EJE CAFETERO | C201: 0004-0003 | D201: 76001 | E201: TA-25-1436336 | F201: 3007051670 | G201: OC CIERRE | H201: VALLE DEL CAUCA | I201: CALI | J201: PTM CALI SERVI TG | K201: REDEBAN | L201: FO-25-2001416 | M201: 46010.447 | N201: 46010.493 | O201: NO | P201: CIERRE | Q201: RETIRO VOLUNTARIO | R201: AGREGADOR | S201: COMCARD - PTM | T201: EJECUTADO | U201: CIERRE EXITOSO | V201: 19/12/2025 CONFIRMA DISPONIBILIDAD | 19/12/2025 SE REALIZA CIERRE DE CB BANCOLOMBIA MIXTO, DE RETIRAN EQUIPOS, ACCESORIOS Y PUBLICIDAD, CLIENTE INDICA NO CONTAR CON PAPELERÍA, EL AVISO EXTERIOR ES DESTRUIDO EN SITIO SEGÚN INDICACIONES DE ENTIDAD. LOS EQUIPOS SON ENTREGADOS EN BODEGA DE LINEA COMUNICACIONES SEDE CALI. | W201: VISITA TECNICA | X201: 9C0AZ617 - EF03Z232 | Y201: TIPO I | Z201: TERRESTRE | AA201: MONTERO MUESES GIAN CARLO | AB201: 1 | AC201: 0 | AD201: 65960 | AE201: 75096 | AF201: 65960
A202: BOGOTA | B202: CUNDINAMARCA | C202: 0004-0004 | D202: 11001 | E202: TA-25-1436880 | F202: 3007079540 | G202: OC CIERRE | H202: CUNDINAMARCA | I202: BOGOTA | J202: BARRIO RUBI ROMA BOGOTA | K202: REDEBAN | L202: FO-25-2005545 | M202: 46010.544 | N202: 46010.567 | O202: NO | P202: CIERRE | Q202: RETIRO VOLUNTARIO | R202: CB UNO A UNO | S202: CB UNO A UNO | T202: EJECUTADO | U202: CIERRE EXITOSO | V202: 19/12/2025 SE REALIZA RETIRO VOLUNTARIO DE DATAFONO Y LECTOR . CB NO ENTREGA PAPELERÍA. NO SE RETIRA PUBLICIDAD YA QUE EL CB SE ENCUENTRA MIGRADO A WOMPI | W202: VISITA TECNICA | X202: LMUZZ974 | Y202: TIPO I | Z202: TERRESTRE | AA202: GARCIA PASTRANA KEVIN FERNANDO | AB202: 1 | AC202: 0 | AD202: 65960 | AE202: 75096 | AF202: 65960
A203: PASTO | B203: SUROCCIDENTE Y EJE CAFETERO | C203: 0004-0003 | D203: 52381 | E203: TA-25-1445540 | F203: 3007063799 | G203: OC CIERRE | H203: NARIÑO | I203: LA FLORIDA | J203: BARRIO SECTOR LA INMACULADA LA | K203: REDEBAN | L203: FO-25-2022573 | M203: 46014.451 | N203: 46021.628 | O203: NO | P203: CIERRE | Q203: RETIRO VOLUNTARIO | R203: UNO A UNO | S203: CB UNO A UNO | T203: EJECUTADO | U203: CIERRE EXITOSO | V203: 27/12/2025 SE CONTACTA PARA RETIRO VOLUNTARIO | 30/12/2025 SE CONTACTA CON LA SEÑORA PATRICIA BRAVO LA CUAL INFORMA QUE HARÁ ENTREGA VOLUNTARIA DE LOS EQUIPOS EN LA CIUDAD DE PASTO, POR LO CUAL HACE ENTREGA VOLUNTARIA DE LOS EQUIPOS DATÁFONO CON BASE Y LECTORA EN LA CIUDAD DE PASTO SE RECIBEN EQUIPOS | W203: VISITA TECNICA | X203: JA00X307 | Y203: TIPO II | Z203: TERRESTRE | AA203: PAZ MARTINEZ RICHARD HUMBERTO | AB203: 1 | AC203: 0 | AD203: 144968 | AE203: 140396 | AF203: 144968
A204: BARRANQUILLA | B204: COSTA | C204: 0004-0001 | D204: 8758 | E204: TA-25-1460719 | F204: 3007069884 | G204: OC CIERRE | H204: ATLANTICO | I204: SOLEDAD | J204: BARRIO VILLA CATANGA SOLEDAD 1 | K204: REDEBAN | L204: FO-25-2040684 | M204: 46018.471 | N204: 46018.497 | O204: NO | P204: CIERRE | Q204: RETIRO VOLUNTARIO | R204: CB UNO A UNO | S204: CB UNO A UNO | T204: EJECUTADO | U204: CIERRE EXITOSO | V204: 27/12/2025 NO SÉ REALIZA LLAMADA TELEFÓNICA DEBIDO A QUE EL CB ESTÁ ACTIVO. | 27/12/2025 SE REALIZA VISITA TÉCNICA, SE RETIRA DEL SITIO DATAFONO Y LECTOR DE BARRAS, EQUIPOS SE ENVÍAN A BODEGA DE LÍNEA COMUNICACIONES EN LA CIUDAD DE BARRANQUILLA. | W204: VISITA TECNICA | X204: TV000645 | Y204: TIPO I | Z204: TERRESTRE | AA204: DE AGUAS MUÑOZ DAVID JOSE | AB204: 1 | AC204: 0 | AD204: 65960 | AE204: 75096 | AF204: 65960
A205: IBAGUE | B205: REMOTAS | C205: 0004-0007 | D205: 73001 | E205: TA-25-1462566 | F205: 3007064869 | G205: OC CIERRE | H205: TOLIMA | I205: IBAGUE | J205: PTM IBAGUE MISCELANEA DULCE AM | K205: REDEBAN | L205: FO-25-2045983 | M205: 46020.463 | N205: 46020.569 | O205: NO | P205: CIERRE | Q205: RETIRO VOLUNTARIO | R205: AGREGADOR | S205: COMCARD - PTM | T205: EJECUTADO | U205: CIERRE EXITOSO | V205: 29/12/2025 SE ESCALA PARA VISITA. CONFIRMAR DATOS PARA LA RECOLECCION DE EQUIPOS | 29/12/2025 SE REALIZA CIERRE DE CB CON ACCESORIOS | W205: VISITA TECNICA | X205: 5A002491 - 5A002661 | Y205: TIPO I | Z205: TERRESTRE | AA205: HERNANDEZ CHAVARRIA JUAN CAMILO | AB205: 1 | AC205: 0 | AD205: 65960 | AE205: 75096 | AF205: 65960
A206: IBAGUE | B206: REMOTAS | C206: 0004-0007 | D206: 73001 | E206: TA-25-1462576 | F206: 3007060446 | G206: OC CIERRE | H206: TOLIMA | I206: IBAGUE | J206: PTM IBAGUE PAPELERIA NELLA | K206: REDEBAN | L206: FO-25-2045987 | M206: 46020.463 | N206: 46020.573 | O206: NO | P206: CIERRE | Q206: RETIRO VOLUNTARIO | R206: AGREGADOR | S206: COMCARD - PTM | T206: EJECUTADO | U206: CIERRE EXITOSO | V206: 29/12/2025 PROGRAMADO | 29/12/2025 SE REALIZA CIERRE DE CB CON ACCESORIOS, USUARIO INDICA QUE NO TIENE ROLLOS | W206: VISITA TECNICA | X206: KA00C827 - KA00C933 | Y206: TIPO I | Z206: TERRESTRE | AA206: HERNANDEZ CHAVARRIA JUAN CAMILO | AB206: 1 | AC206: 0 | AD206: 65960 | AE206: 75096 | AF206: 65960
A207: MEDELLIN | B207: NOROCCIDENTE | C207: 0004-0005 | D207: 5001 | E207: TA-25-1462579 | F207: 3007074667 | G207: OC CIERRE | H207: ANTIOQUIA | I207: MEDELLIN | J207: PTM MEDELLIN IMPRESIONES Y VAR | K207: REDEBAN | L207: FO-25-2045997 | M207: 46020.463 | N207: 46020.572 | O207: NO | P207: CIERRE | Q207: RETIRO VOLUNTARIO | R207: AGREGADOR | S207: COMCARD - PTM | T207: EJECUTADO | U207: CIERRE EXITOSO | V207: 29/12/2025 SE ESCALA PARA VISITA. CONFIRMAR DATOS PARA LA RECOLECCION DE EQUIPOS | 29/12/2025 SE REALIZA CIERRE DE CB CON ACCESORIOS | W207: VISITA TECNICA | X207: ON00A034 - EGQZZ159 | Y207: TIPO I | Z207: TERRESTRE | AA207: HERNANDEZ CHAVARRIA JUAN CAMILO | AB207: 1 | AC207: 0 | AD207: 65960 | AE207: 75096 | AF207: 65960
A208: CALI | B208: SUROCCIDENTE Y EJE CAFETERO | C208: 0004-0003 | D208: 19821 | E208: TA-25-1463345 | F208: 3007040116 | G208: OC CIERRE | H208: CAUCA | I208: TORIBIO | J208: PTM TORIBIO ATICO | K208: REDEBAN | L208: FO-25-2047030 | M208: 46020.572 | N208: 46020.711 | O208: NO | P208: CIERRE | Q208: RETIRO VOLUNTARIO | R208: AGREGADOR | S208: COMCARD - PTM | T208: EJECUTADO | U208: CIERRE EXITOSO | V208: 29/12/2025 SE ESCALA PARA VISITA. CONFIRMAR DATOS PARA LA RECOLECCION DE EQUIPOS | 29/12/2025 SE REALIZA CIERRE DE CB CON ACCESORIOS | W208: VISITA TECNICA | X208: GZ0FZ946 | Y208: TIPO III | Z208: TERRESTRE | AA208: HERNANDEZ CHAVARRIA JUAN CAMILO | AB208: 1 | AC208: 0 | AD208: 275729 | AE208: 196537 | AF208: 275729
A209: CARTAGENA | B209: COSTA | C209: 0004-0001 | D209: 13001 | E209: TA-25-1468572 | F209: 3007075777 | G209: OC CIERRE | H209: BOLIVAR | I209: CARTAGENA | J209: BARRIO EL POZON CARGENA DE IND | K209: REDEBAN | L209: FO-25-2051952 | M209: 46021.456 | N209: 46021.501 | O209: NO | P209: CIERRE | Q209: RETIRO VOLUNTARIO | R209: CB UNO A UNO | S209: CB UNO A UNO | T209: EJECUTADO | U209: CIERRE EXITOSO | V209: 30/12/2025 NO | 30/12/2025 SE RECIBE EQUIPO POR PARTE DEL VECINO INFORMA QUE ELLA SE FUE DEL PAÍS Y DEJÓ LOS EQUIPOS PARA SER ENTREGADOS SE RECIBE SOLO LOS EQUIPOS SIN PUBLICIDAD Y SIN PAPELERÍA TODO OK | W209: VISITA TECNICA | X209: F100V522 | Y209: TIPO I | Z209: TERRESTRE | AA209: MARTINEZ SALGUEDO ANDRES AUGUSTO | AB209: 1 | AC209: 0 | AD209: 65960 | AE209: 75096 | AF209: 65960
A210: CUCUTA | B210: SANTANDERES | C210: 0004-0008 | D210: 54099 | E210: TA-25-1468625 | F210: 3007078899 | G210: OC CIERRE | H210: NORTE DE SANTANDER | I210: BOCHALEMA | J210: BARRIO LOS TANQUES 3 BOCHALEMA | K210: REDEBAN | L210: FO-25-2052176 | M210: 46021.476 | N210: 46021.509 | O210: NO | P210: CIERRE | Q210: RETIRO VOLUNTARIO | R210: UNO A UNO | S210: UNO A UNO | T210: EJECUTADO | U210: CIERRE EXITOSO | V210: 30/12/2025 VISITA | 30/12/2025 SE RETIRÓ DATAFONO LECTOR BASE Y ACCESORIOS ROLLOS USADOS POR EL COMERCIO | W210: VISITA TECNICA | X210: F1SZZ772 | Y210: TIPO II | Z210: TERRESTRE | AA210: DURAN ACOSTA FRANK YONNY | AB210: 1 | AC210: 0 | AD210: 144968 | AE210: 140396 | AF210: 144968
A211: PASTO | B211: SUROCCIDENTE Y EJE CAFETERO | C211: 0004-0003 | D211: 52001 | E211: 14396711 | F211: 3007040058 | G211: OC PINPAD | H211: NARIÑO | I211: PASTO | J211: DISTRICOL DROGUERIA SAN ANDRES | K211: REDEBAN | L211: FO-25-1995770 | M211: 46008.619 | N211: 46010.525 | O211: NO | P211: PINPAD | Q211: PINPAD | R211: AGREGADOR | S211: DISTRICOL | T211: EJECUTADO | U211: EJECUTADO EXITOSO | V211: 19/12/2025 SE REALIZA INSTALACIÓN DE PINPAD SE REALIZA CONFIGURACIÓN PRUEBAS DE FUNCIONAMIENTO CON PINPAD EXITOSAS CB QUEDA OPERATIVO | W211: VISITA TECNICA | X211: AB0FZ064 | Y211: TIPO I | Z211: TERRESTRE | AA211: BRAVO MADROÑERO OSCAR ESTEBAN | AB211: 1 | AC211: 0 | AD211: 65960 | AE211: 75096 | AF211: 65960
A212: MONTERIA | B212: COSTA | C212: 0004-0001 | D212: 23555 | E212: 14396717 | F212: 3007035595 | G212: OC PINPAD | H212: CORDOBA | I212: PLANETA RICA | J212: DISTRICOL MULTIYA PARQUE | K212: REDEBAN | L212: FO-25-1995776 | M212: 46008.619 | N212: 46010.534 | O212: NO | P212: PINPAD | Q212: PINPAD | R212: AGREGADOR | S212: DISTRICOL | T212: EJECUTADO | U212: EJECUTADO EXITOSO | V212: 19/12/2025 SE REALIZA LA INSTALACIÓN DE PIN PAD DESK /1600.SE REALIZAN PRUEBAS OK | W212: VISITA TECNICA | X212: FB001825 | Y212: TIPO II | Z212: TERRESTRE | AA212: ARRAZOLA HERNANDEZ NICOLAS AUGUSTO | AB212: 1 | AC212: 0 | AD212: 144968 | AE212: 140396 | AF212: 144968
... A219: BUCARAMANGA | B219: SANTANDERES | C219: 0004-0008 | D219: 68001 | E219: 14571909 | F219: 3007031585 | G219: OC PINPAD | H219: SANTANDER | I219: BUCARAMANGA | J219: COMCARD B MANGA ELLITA | K219: REDEBAN | L219: FO-25-1995778 | M219: 46008.619 | N219: 46010.476 | O219: NO | P219: PINPAD | Q219: PINPAD | R219: AGREGADOR | S219: COMCARD - PTM | T219: EJECUTADO | U219: EJECUTADO EXITOSO | V219: 18/12/2025 SE REALIZARON VARIOS INTENTOS PARA REALIZAR LA VERIFICACION Y ACTUALIZACION DE DATOS AL NUMERO 3186159944,3157268328PERO EN NINGUNO DE LOS INTENTOS LA COMUNICACION FUE EXITOSA.POR FAVOR LLAMAR ANTES DE REALIZAR LA GESTION | 19/12/2025 SE HACE PRESENCIA EN COMERCIO SE REALIZA INSTALACIÓN DE 1 PIN PAD SE REALIZA PRUEBA CONSULTA DE SALDO OK | W219: VISITA TECNICA | X219: 1111G418 - HA006439 | Y219: TIPO I | Z219: TERRESTRE | AA219: BARRERA ORTEGA MARLON STWAR | AB219: 1 | AC219: 0 | AD219: 65960 | AE219: 75096 | AF219: 65960
A220: CALI | B220: SUROCCIDENTE Y EJE CAFETERO | C220: 0004-0003 | D220: 19001 | E220: 14580591 | F220: 3007059575 | G220: OC PINPAD | H220: CAUCA | I220: POPAYAN | J220: DISTRICOL RECAUDO EL ENCUENTRO | K220: REDEBAN | L220: FO-25-2027265 | M220: 46014.724 | N220: 46019.464 | O220: NO | P220: PINPAD | Q220: PINPAD | R220: AGREGADOR | S220: DISTRICOL | T220: EJECUTADO | U220: PETICIÓN USUARIO | V220: 24/12/2025 SE REALIZAN VARIOS INTENTOS DE COMUNICACION CON EL SEÑOR LUIS ERAZO PERO NO FUERON EXITOSOS.POR FAVOR LLAMAR ANTES DE REALIZAR LA GESTION | 27/12/2025 SE LLEGA AL SITIO SE ENCUENTRA CERRADO CB SE LLAMA AL SEÑOR LUIS QUE EL DIA DE HOY NO PUEDE ATENDER VISITA TECNICA POR MOTIVO PERSONAL | 27/12/2025 SE LLEGA AL SITIO SE ENCUENTRA CERRADO SE CONTACTA AL SEÑOR LUIS INFORMA EL DIA DE HOY NO PUEDE ESTAR DISPONIBLE PARA ATENDER VISITA TECNICA POR MOTIVO PERSONAL | W220: VISITA TECNICA | Y220: TIPO III | Z220: TERRESTRE | AA220: GIMBUEL LASSO LUIS GERMAN | AB220: 1 | AC220: 0 | AD220: 275729 | AE220: 196537 | AF220: 275729
A221: MONTERIA | B221: COSTA | C221: 0004-0001 | D221: 23672 | E221: 14405477 | F221: 3007017875 | G221: OC TRASLADO | H221: CORDOBA | I221: SAN ANTERO | J221: CALLE REAL SAN ANTERO CORDOBA | K221: REDEBAN | L221: FO-25-1900628 | M221: 45988.717 | N221: 45992.518 | O221: NO | P221: TRASLADO | Q221: TRASLADO EXTERNO | R221: CB UNO A UNO | S221: CB UNO A UNO | T221: EJECUTADO | U221: EJECUTADO EXITOSO | V221: 28/11/2025 POR FAVOR, COMUNICARSE CON USUARIO PARA CONFIRMAR UBICACION, SOLICITUD Y PROGRAMAR VISITA TECNICA | 01/12/2025 SE REALIZA VISITA TÉCNICA PARA TRASLADO DE CB, SE TRASLADA DATAFONO PLACA 917653, LECTOR PLACA 525912, SE TRASLADA PUBLICIDAD ENCONTRADA, SE INICIALIZA TERMINAL, PARA TOMAR NUEVA DIRECCIÓN. NOTA: EL CB SE ENCUENTRA BLOQUEADO POR LO LO QUE SE INFORMA AL CLIENTE COMUNICACIÓN CON EL BANCO PARA SU DESBLOQUEO Y PUEDAN OPERAR NUEVAMENTE, SE ANEXAN BAUCHER DE ANTES Y DESPUÉS DEL CAMBIO DE DIRECCIÓN CON RECHAZO GENERAL POR EL BLOQUEO DE CB. | W221: VISITA TECNICA | X221: JRZZZ842 | Y221: TIPO II | Z221: TERRESTRE | AA221: CASSIANI PEREZ RAUL RAMIRO | AB221: 1 | AC221: 0 | AD221: 144968 | AE221: 140396 | AF221: 144968
A222: BUCARAMANGA | B222: SANTANDERES | C222: 0004-0008 | D222: 81001 | E222: 14406809 | F222: 3007065648 | G222: OC TRASLADO | H222: ARAUCA | I222: ARAUCA | J222: BARRIO SIETE DE AGOSTO ARAUCA | K222: REDEBAN | L222: FO-25-1900662 | M222: 45988.717 | N222: 45996.531 | O222: NO | P222: TRASLADO | Q222: TRASLADO EXTERNO | R222: CB UNO A UNO | S222: CB UNO A UNO | T222: EJECUTADO | U222: EJECUTADO EXITOSO | V222: 28/11/2025 POR FAVOR, COMUNICARSE CON USUARIO PARA CONFIRMAR UBICACION, SOLICITUD Y PROGRAMAR VISITA TECNICA | 03/12/2025 SE LLEGA A SITIO , AL VALIDAR EL EQUIPO SE ENCUENTRA SIN PLACA , EQUIPO ALERTADO. , SE ESCALA CON COORDINADOR DE ZONA INDICA CAMBIAR EQUIPO | 04/12/2025 SE LLAMA AL CLIENTE SE LE INDICA, QUE AÚN PERSISTE EL ERROR , QUE EN EL MOMENTO REDEBAN SE ENCUENTRA INTENTANDO DAR SOLUCIÓN , COORDINADOR Y RBM INDICA QUE AÚN SIGUE EN FALLAS B24 , INDICA ESPERAR SOLUCIÓN | 05/12/2025 SE VISITA COMERCIO SE REALIZA TRASLADO CAMBIO DE DIRECCIÓN OK , NO SE REALIZA PRUEBAS DEBIDO COMERCIO SE ENCUENTRA BLOQUEADO POR INACTIVIDAD , ENTIDAD LE INDICA QUE EL DESBLOQUEO SE REALIZA DESPUÉS DE UN DÍA HÁBIL | W222: VISITA TECNICA | X222: CA005502 | Y222: TIPO V | Z222: AEREO | AA222: HERRERA LUQUE SAUL JAVIER | AB222: 1 | AC222: 0 | AD222: 988463 | AE222: 196537 | AF222: 988463
A223: NEIVA | B223: REMOTAS | C223: 0004-0007 | D223: 41551 | E223: 14406889 | F223: 3007080799 | G223: OC TRASLADO | H223: HUILA | I223: PITALITO | J223: BARRIO PARAISO PITALITO | K223: REDEBAN | L223: FO-25-1900657 | M223: 45988.717 | N223: 45994.596 | O223: NO | P223: TRASLADO | Q223: TRASLADO EXTERNO | R223: UNO A UNO | S223: UNO A UNO | T223: EJECUTADO | U223: EJECUTADO EXITOSO | V223: 28/11/2025 POR FAVOR, COMUNICARSE CON USUARIO PARA CONFIRMAR UBICACION, SOLICITUD Y PROGRAMAR VISITA TECNICA | 03/12/2025 SE LLEGA A DIRECCIÓN ANTERIOR , SE BAJA AVISO EXTERIOR Y SE LLEVA A LA NUEVA DIRECCIÓN DONDE SE INSTALA, SE TRASLADA EQUIPOS , SE FORMATEA , CONFIGURA E INICIALIZA DATAFONO, SE CREA USUARIO Y CLAVE CON EL CLIENTE, SE REALIZA PRUEBAS OK | W223: VISITA TECNICA | X223: F8ZZZ037 | Y223: TIPO III | Z223: TERRESTRE | AA223: ANDRADE HERNANDEZ JUAN CARLOS | AB223: 1 | AC223: 0 | AD223: 275729 | AE223: 196537 | AF223: 275729
A224: IBAGUE | B224: REMOTAS | C224: 0004-0007 | D224: 73616 | E224: 14406950 | F224: 3007047761 | G224: OC TRASLADO | H224: TOLIMA | I224: RIOBLANCO | J224: BARRIO CENTRO RIOBLANCO 6 | K224: REDEBAN | L224: FO-25-1900649 | M224: 45988.717 | N224: 45994.592 | O224: NO | P224: TRASLADO | Q224: TRASLADO EXTERNO | R224: CB UNO A UNO | S224: CB UNO A UNO | T224: EJECUTADO | U224: EJECUTADO EXITOSO | V224: 28/11/2025 POR FAVOR, COMUNICARSE CON USUARIO PARA CONFIRMAR UBICACION, SOLICITUD Y PROGRAMAR VISITA TECNICA | 03/12/2025 SE REALIZA CONFIGURACIÓN DE PARÁMETROS DE COMUNICACIÓN,E INICIALIZA EQUIPOS PARA TOMAR NUEVA DIRECCIÓN TRANSACIONES DE CB NO FUERON APROBADOS YA QUE PRESENTA BLOQUEO POR PARTE DE LA ENTIDAD TRANSACCIÓN DE ADQUIRENCIA EXITOSA, SOLICITA SOPORTE POR PARTE DE REDEBAN CON LA SEÑORITA PAOLA QUIEN AUTORIZA RETIRO E INFORMANDO AL CB QUE DEBE COMUNICARSE CON LA ENTIDAD PARA DESBLOQUEO | W224: VISITA TECNICA | X224: XP00F508/JA00K122 | Y224: TIPO IV | Z224: TERRESTRE | AA224: GUTIERREZ CAMILO ANDRES | AB224: 1 | AC224: 0 | AD224: 479589 | AE224: 196537 | AF224: 479589
A225: VILLAVICENCIO | B225: REMOTAS | C225: 0004-0007 | D225: 50006 | E225: 14408075 | F225: 3007067760 | G225: OC TRASLADO | H225: META | I225: ACACIAS | J225: BARRIO BACHUE ACACIAS 11 | K225: REDEBAN | L225: FO-25-1900656 | M225: 45988.717 | N225: 45992.667 | O225: NO | P225: TRASLADO | Q225: TRASLADO EXTERNO | R225: CB UNO A UNO | S225: CB UNO A UNO | T225: EJECUTADO | U225: EJECUTADO EXITOSO | V225: 28/11/2025 POR FAVOR, COMUNICARSE CON USUARIO PARA CONFIRMAR UBICACION, SOLICITUD Y PROGRAMAR VISITA TECNICA | 01/12/2025 SE REALIZA TRASLADO OK | W225: VISITA TECNICA | X225: 6A8ZZ276 | Y225: TIPO II | Z225: TERRESTRE | AA225: CASTRILLON URREA LONDIER LEANDRO | AB225: 1 | AC225: 0 | AD225: 144968 | AE225: 140396 | AF225: 144968
A226: CUCUTA | B226: SANTANDERES | C226: 0004-0008 | D226: 54001 | E226: 14412510 | F226: 3007080941 | G226: OC TRASLADO | H226: NORTE DE SANTANDER | I226: CUCUTA | J226: BARRIO URB NIZA CUCUTA 2 | K226: REDEBAN | L226: FO-25-1900630 | M226: 45988.717 | N226: 45993.629 | O226: NO | P226: TRASLADO | Q226: TRASLADO EXTERNO | R226: UNO A UNO | S226: UNO A UNO | T226: EJECUTADO | U226: EJECUTADO EXITOSO | V226: 28/11/2025 POR FAVOR, COMUNICARSE CON USUARIO PARA CONFIRMAR UBICACION, SOLICITUD Y PROGRAMAR VISITA TECNICA | 01/12/2025 SE HABLÓ CON EL SR JAVIER MANIFIESTA QUE EL DÍA DE HOY NO VA ESTAR DISPONIBLE Y EL ENCARGADO DE LA RED PRINCIPAL PARA LOS DATOS Y CLAVES LLEGA MAÑANA, SOLICITA PROGRAMACIÓN DE VISITA PARA EL DÍA DE MAÑANA A LA ESPERA DE DISPONIBILIDAD DEL ENCARGADO DE LA RED PRINCIPAL DEL COMERCIO | 02/12/2025 SE REALIZA TRASLADO SE INSTALA NUEVA VERSIÓN CIERRES Y PRUEBAS OK | W226: VISITA TECNICA | X226: FIZZZ322 | Y226: TIPO I | Z226: TERRESTRE | AA226: DURAN ACOSTA FRANK YONNY | AB226: 1 | AC226: 0 | AD226: 65960 | AE226: 75096 | AF226: 65960
A227: MEDELLIN | B227: NOROCCIDENTE | C227: 0004-0005 | D227: 5088 | E227: 14425321 | F227: 3007037218 | G227: OC TRASLADO | H227: ANTIOQUIA | I227: BELLO | J227: PTM BELLO MILLER | K227: REDEBAN | L227: FO-25-1906319 | M227: 45988.732 | N227: 45993.746 | O227: NO | P227: TRASLADO | Q227: TRASLADO EXTERNO | R227: AGREGADOR | S227: COMCARD - PTM | T227: EJECUTADO | U227: EJECUTADO EXITOSO | V227: 29/11/2025 POR FAVOR, COMUNICARSE CON USUARIO PARA CONFIRMAR UBICACION, SOLICITUD Y PROGRAMAR VISITA TECNICA | 02/12/2025 DURANTE LA VISITA TÉCNICA REALIZADA PARA EL TRASLADO EXTERNO DEL CORRESPONSAL BANCOLOMBIA, USUARIO INICIA EL PROCESO CON LA VERIFICACIÓN DE IDENTIDAD DEL TECNICO CONFIRMANDO LA VALIDEZ DE LA INFORMACIÓN SUMINISTRADA. UNA VEZ VALIDADO EL PUNTO Y CONSTATADO QUE LAS CONDICIONES INICIALES ERAN ADECUADAS, SE PROCEDE CON LA INSTALACIÓN Y ACTUALIZACIÓN DE LOS EQUIPOS Y SERVICIOS REQUERIDOS. POSTERIORMENTE, SE EJECUTAN PRUEBAS DE FUNCIONAMIENTO PARA GARANTIZAR LA OPERATIVIDAD DEL SISTEMA. SIN EMBARGO, SE DETECTA QUE EL PUNTO CONTINÚA BLOQUEADO POR LA ENTIDAD, LO QUE IMPIDE LA HABILITACIÓN COMPLETA DEL SERVICIO. SE DOCUMENTAN Y ANEXAN LAS EVIDENCIAS CORRESPONDIENTES, INCLUYENDO LOS RECHAZOS GENERADOS DURANTE LAS PRUEBAS, CON EL FIN DE DEJAR CONSTANCIA DEL ESTADO ACTUAL Y FACILITAR EL SEGUIMIENTO POR PARTE DE LAS ÁREAS RESPONSABLES | W227: VISITA TECNICA | X227: GZ00K464 | Y227: TIPO I | Z227: TERRESTRE | AA227: MARTINEZ TOVAR OSCAR DAVID | AB227: 1 | AC227: 0 | AD227: 65960 | AE227: 75096 | AF227: 65960
A228: VALLEDUPAR | B228: COSTA | C228: 0004-0001 | D228: 20228 | E228: 14425495 | F228: 3007075969 | G228: OC TRASLADO | H228: CESAR | I228: CURUMANI | J228: PTM CURUMANI VARIEDADES XIOMMI | K228: REDEBAN | L228: FO-25-1906326 | M228: 45988.732 | N228: 45994.667 | O228: NO | P228: TRASLADO | Q228: TRASLADO EXTERNO | R228: AGREGADOR | S228: COMCARD - PTM | T228: EJECUTADO | U228: EJECUTADO EXITOSO | V228: 29/11/2025 POR FAVOR, COMUNICARSE CON USUARIO PARA CONFIRMAR UBICACION, SOLICITUD Y PROGRAMAR VISITA TECNICA | 03/12/2025 BUENAS TARDES SE VISITA CB Y SE LE HACE TRASLADO OK. SE HACEN PRUEBAS DE TRANSACCIONES PERO SALE RECHAZO GENERAL POR EL BLOQUEO DEL BANCO, PERO YA QUEDA ACTUALIZADA LA DIRECCIÓN. | W228: VISITA TECNICA | X228: FA09Z498 | Y228: TIPO III | Z228: TERRESTRE | AA228: BENITEZ CARVAJAL ALVARO JAVIER | AB228: 1 | AC228: 0 | AD228: 275729 | AE228: 196537 | AF228: 275729
A229: BOGOTA | B229: CUNDINAMARCA | C229: 0004-0004 | D229: 11001 | E229: 14428959 | F229: 3007043127 | G229: OC TRASLADO | H229: CUNDINAMARCA | I229: BOGOTA | J229: BARRIO CASTELLANA BOGOTA | K229: REDEBAN | L229: FO-25-1900645 | M229: 45988.717 | N229: 45993.466 | O229: NO | P229: TRASLADO | Q229: TRASLADO EXTERNO | R229: UNO A UNO | S229: CB UNO A UNO | T229: EJECUTADO | U229: EJECUTADO EXITOSO | V229: 28/11/2025 POR FAVOR, COMUNICARSE CON USUARIO PARA CONFIRMAR UBICACION, SOLICITUD Y PROGRAMAR VISITA TECNICA | 02/12/2025 SE REALIZA INICIALIZACIÓN DE EQUIPO DESK 3500, USUARIO YA HABÍA TRASLADADO EQUIPO Y PUBLICIDAD | W229: VISITA TECNICA | X229: 9ABZZ043 | Y229: TIPO I | Z229: TERRESTRE | AA229: LEON GUERRERO CRISTIAN JOHAN | AB229: 1 | AC229: 0 | AD229: 65960 | AE229: 75096 | AF229: 65960
A230: NEIVA | B230: REMOTAS | C230: 0004-0007 | D230: 41006 | E230: 14439124 | F230: 3007042732 | G230: OC TRASLADO | H230: HUILA | I230: ACEVEDO | J230: PTM ACEVEDO PAPELERIA DANA | K230: REDEBAN | L230: FO-25-1906323 | M230: 45988.732 | N230: 45994.597 | O230: NO | P230: TRASLADO | Q230: TRASLADO EXTERNO | R230: AGREGADOR | S230: COMCARD - PTM | T230: EJECUTADO | U230: EJECUTADO EXITOSO | V230: 29/11/2025 POR FAVOR, COMUNICARSE CON USUARIO PARA CONFIRMAR UBICACION, SOLICITUD Y PROGRAMAR VISITA TECNICA | 03/12/2025 CLIENTE TIENE EQUIPOS Y PUBLICIDAD EN LA NUEVA DIRECCIÓN ,SE INSTALA PUBLICIDAD , SE FORMATEA , CONFIGURA E INICIALIZA DATAFONO, SE CREA USUARIO Y CLAVE CON EL CLIENTE, SE REALIZA PRUEBAS PERO SALE RG , SE LLAMA A LA LINEA CB 018000953344 PARA SOLICITAR DESBLOQUEO TEMPORAL PARA REALIZAR PRUEBAS , LA SEÑORITA ROCÍO SUÁREZ ATIENDE LA LLAMADA Y ENVÍA NOVEDAD DE DESBLOQUEO AL ÁREA ENCARGADA , PIDE EN 20 MINUTOS REALIZAR PRUEBAS Y DESPUÉS DE ESTE TIEMPO EL CORRESPONSAL VUELVE A BLOQUEARSE AUTOMÁTICAMENTE, SE REALIZA PRUEBAS PASADO EL TIEMPO Y PERSISTE EL RECHAZO GENERAL. | W230: VISITA TECNICA | X230: 9A8ZZ560 | Y230: TIPO III | Z230: TERRESTRE | AA230: ANDRADE HERNANDEZ JUAN CARLOS | AB230: 1 | AC230: 0 | AD230: 275729 | AE230: 196537 | AF230: 275729
A231: BOGOTA | B231: CUNDINAMARCA | C231: 0004-0004 | D231: 11001 | E231: 14439358 | F231: 3007073647 | G231: OC TRASLADO | H231: CUNDINAMARCA | I231: BOGOTA | J231: BARRIO SAN VICENTE FERRER BOGO | K231: REDEBAN | L231: FO-25-1900640 | M231: 45988.717 | N231: 45993.347 | O231: NO | P231: TRASLADO | Q231: TRASLADO EXTERNO | R231: CB UNO A UNO | S231: CB UNO A UNO | T231: EJECUTADO | U231: EJECUTADO EXITOSO | V231: 28/11/2025 POR FAVOR, COMUNICARSE CON USUARIO PARA CONFIRMAR UBICACION, SOLICITUD Y PROGRAMAR VISITA TECNICA | 02/12/2025 SE VISITA COMERCIO, SE REVISA DIRECCION , SE REPISAN PARÁMETRO SE INICIALIZA DATAFONO, SE REALIZAN PRUEBAS, PRUEBAS OK | W231: VISITA TECNICA | X231: EF02Z324 | Y231: TIPO I | Z231: TERRESTRE | AA231: ORTIZ YARA FRANKLYN ISRAEL | AB231: 1 | AC231: 0 | AD231: 65960 | AE231: 75096 | AF231: 65960
A232: TUNJA | B232: SANTANDERES | C232: 0004-0008 | D232: 15087 | E232: 14445186 | F232: 3007062596 | G232: OC TRASLADO | H232: BOYACA | I232: BELEN | J232: BARRIO CENTRO BELEN 8 | K232: REDEBAN | L232: FO-25-1918304 | M232: 45992.738 | N232: 45994.598 | O232: NO | P232: TRASLADO | Q232: TRASLADO EXTERNO | R232: CB UNO A UNO | S232: CB UNO A UNO | T232: EJECUTADO | U232: EJECUTADO EXITOSO | V232: 02/12/2025 POR FAVOR, COMUNICARSE CON USUARIO PARA CONFIRMAR UBICACION, SOLICITUD Y PROGRAMAR VISITA TECNICA | 02/12/2025 SE INTENTA CONTACTAR A LA SEÑORA FLORALBA MOLINA AL NÚMERO DE CONTACTO 3143265622 PARA CONFIRMACIÓN DE LA ORDEN GENERADA NÚMERO DE CONTACTO APAGADO A ESPERA QUE EL CLIENTE RESPONDA. | 02/12/2025 SE ESTABLECE COMUNICACIÓN CON LA SEÑORA FLORALBA MOLINA AL NÚMERO DE CONTACTO 3143265622 CLIENTE CONFIRMA VISITA PARA REALIZAR EL TRASLADO EXTERNO PARA EL DÍA DE MAÑANA EN HORAS AM | 03/12/2025 SE EJECUTA TRASLADO EXTERNO INSTALANDO EQUIPOS Y PUBLICIDAD NO SE REALIZAN CIERRES EQUIPO CON MEMORIA ACUMULADA CLIENTE AUTORIZA REALIZAR BORRADO PRUEBAS OK CLIENTE CONFORME. | W232: VISITA TECNICA | X232: LA00O224 | Y232: TIPO II | Z232: TERRESTRE | AA232: RODRIGUEZ MURCIA YERSON IVAN | AB232: 1 | AC232: 0 | AD232: 144968 | AE232: 140396 | AF232: 144968
... A259: BUCARAMANGA | B259: SANTANDERES | C259: 0004-0008 | D259: 68001 | E259: 14583589 | F259: 3007069682 | G259: OC TRASLADO | H259: SANTANDER | I259: BUCARAMANGA | J259: PTM BUCARAMANGA INTEGRALES EN | K259: REDEBAN | L259: FO-25-2055830 | M259: 46021.701 | N259: 46022.546 | O259: NO | P259: TRASLADO | Q259: TRASLADO EXTERNO | R259: AGREGADOR | S259: COMCARD - PTM | T259: EJECUTADO | U259: EJECUTADO EXITOSO | V259: 31/12/2025 SE ESCALA PARA VISITA. LLAMAR ANTES DE VISITAR, CONFIRMAR FALLA Y DATOS | 31/12/2025 SE REALIZA TRASLADO EXTERNO, CAMBIO DE DIRECCIÓN EXITOSA , SE DEJA INSTALADO DATAFONO LECTOR DE BARRAS BASE DE DATÁFONO PINPAD HUB , NO SE REALIZA PRUEBAS COMERCIO SE ENCUENTRA BLOQUEADO POR ENTIDAD | W259: VISITA TECNICA | X259: MN000410 - MN000645 | Y259: TIPO I | Z259: TERRESTRE | AA259: HERRERA LUQUE SAUL JAVIER | AB259: 1 | AC259: 0 | AD259: 65960 | AE259: 75096 | AF259: 65960

Sheet PAPELERIA
A1: CIUDAD SEDE | B1: ZONA | C1: CENTRO DE COSTOS LINEACOM | D1: CODIGO DANE | E1: TA/CODIGO ACTIVIDAD | F1: CODIGO CB | G1: ACTIVIDAD | H1: DEPARTAMENTO | I1: CIUDAD | J1: NOMBRE DEL CB | K1: RED | L1: FO | M1: FECHA ASIGNACION A LINEA COMUNICACIONES | N1: FECHA CIERRE DEL TICKET (DD/MM/AAAA HH:MM) | O1: ACOMETIDA | P1: SOLICITUD | Q1: DESCRIPCION | R1: FORMATO | S1: CADENA | T1: ESTADO | U1: CAUSAL ESTADO | V1: OBSERVACION | W1: FORMA DE ATENCION | X1: TERMINAL(ES) | Y1: TIPIFICACION | Z1: TIPO DE TRAYECTO | AA1: NOMBRE DEL TECNICO | AB1: DIAS DE VISITA | AC1: VALOR DIAS ACTIVIDAD FACTURABLES | AD1: VALOR DIAS ACOMPAÑAMIENTO FACTURABLES | AE1: VALOR TOTAL
A2: PASTO | B2: SUROCCIDENTE Y EJE CAFETERO | C2: 0004-0003 | D2: 86568 | E2: 3014489 | F2: 3007032486 | G2: OC ENVIO ROLLOS | H2: PUTUMAYO | I2: PUERTO ASIS | J2: DISTRICOL SERVIPLOTTER PUERTO | K2: REDEBAN | L2: FO-25-1823295 | M2: 45974.467 | N2: 46002.522 | P2: ENVIO | R2: AGREGADOR | S2: DISTRICOL | V2: 15/11/2025 SE REALIZA ENVIO DE ROLLOS CON OPERADOR LOGISTICO | 11/12/2025 SE REALIZA ENVIO DE 30 ROLLOS, CON LA GUIA 2248145392. SE CONFIRMA ENTREGA EXITOSA POR PARTE DE LA TRANSPORTADORA | W2: ENVIO | Y2: TIPO IV | Z2: TERRESTRE | AB2: 1 | AC2: 35780 | AD2: 0 | AE2: 35780
A3: MEDELLIN | B3: NOROCCIDENTE | C3: 0004-0005 | D3: 5001 | E3: 3037946 | F3: 3007028074 | G3: OC VISITA ROLLOS | H3: ANTIOQUIA | I3: MEDELLIN | J3: BARRIO MORAVIA MEDELLIN | K3: REDEBAN | L3: FO-25-1858878 | M3: 45981.333 | N3: 45992.415 | P3: VISITA | Q3: ROLLOS | R3: CB UNO A UNO | S3: CB UNO A UNO | U3: EJECUTADO EXITOSO | V3: 21/11/2025 SE ESCALA AL COORDINADOR DE LA ZONA PARA ENTREGA EN SITIO | 02/12/2025 SE REALIZA ENTREGA DE 290 ROLLOS POR EL OPERADOR CABIFY CON LA GUIA V4001852148 | W3: VISITA TECNICA | Y3: TIPO I | Z3: TERRESTRE | AA3: ALVAREZ LOPEZ MARIANA | AB3: 1 | AC3: 35780 | AD3: 75096 | AE3: 35780
A4: PASTO | B4: SUROCCIDENTE Y EJE CAFETERO | C4: 0004-0003 | D4: 86569 | E4: 3045188 | F4: 3007044997 | G4: OC ENVIO ROLLOS | H4: PUTUMAYO | I4: PUERTO CAICEDO | J4: DISTRICOL MERCACENTRO J&M | K4: REDEBAN | L4: FO-25-1859307 | M4: 45982.422 | N4: 45994.654 | P4: ENVIO | R4: AGREGADOR | S4: DISTRICOL | U4: EJECUTADO EXITOSO | V4: 21/11/2025 SE REALIZA ENVIO DE ROLLOS CON OPERADOR LOGISTICO | 27/11/2025 EN COMUNICACIÓN CON EL USUARIO NOS CONFIRMA QUE AUN NO HA RECIBIDO LOS ROLLOS | 03/12/2025 SE REALIZA ENVIO DE 100 ROLLOS, CON LA GUIA 2248145425 SERVIENTREGA. SE CONFIRMA ENTREGA EXITOSA POR PARTE DE LA TRANSPORTADORA | W4: ENVIO | Y4: TIPO IV | Z4: TERRESTRE | AB4: 1 | AC4: 35780 | AD4: 0 | AE4: 35780
A5: IBAGUE | B5: REMOTAS | C5: 0004-0007 | D5: 73319 | E5: 3047914 | F5: 3007070201 | G5: OC VISITA ROLLOS | H5: TOLIMA | I5: GUAMO | J5: BARRIO VEREDA LA CHAMBA | K5: REDEBAN | L5: FO-25-1860951 | M5: 45982.662 | N5: 45996.369 | R5: UNO A UNO | S5: CB UNO A UNO | T5: EJECUTADO | U5: EJECUTADO EXITOSO | V5: 21/11/2025 SE ESCALA AL COORDINADOR DE LA ZONA PARA ENTREGA EN SITIO | 05/12/2025 SE REALIZA VISITA AL PUNTO, SE ENTREGAN 30 ROLLOS PAPEL RBM. CLIENTE RECIBE A SATISFACCIÓN | W5: VISITA TECNICA | Y5: TIPO II | Z5: TERRESTRE | AA5: DEVIA REINOSO JUAN CARLOS | AB5: 1 | AC5: 67654 | AD5: 140396 | AE5: 67654
A6: MONTERIA | B6: COSTA | C6: 0004-0001 | D6: 5250 | E6: 3049363 | F6: 3007058224 | G6: OC ENVIO ROLLOS | H6: ANTIOQUIA | I6: EL BAGRE | J6: PTM EL BAGRE ACCESORIOS JRBP | K6: REDEBAN | L6: FO-25-1878794 | M6: 45983.46 | N6: 45997.415 | P6: ENVIO | R6: AGREGADOR | S6: COMCARD - PTM | U6: EJECUTADO EXITOSO | V6: 25/11/2025 SE CONFIRMAN DATOS, SE REALIZA ENVIO POR OPERADOR LOGISTICO | 28/11/2025 SE LE INFORMA AL USUARIO EL NUMERO DE GUIA, PENDIENTE CONFIRMACION | 06/12/2025 SE REALIZA ENVIO DE 50 ROLLOS, CON LA GUIA 2265100524 SERVIENTREGA. SE CONFIRMA ENTREGA EXITOSA POR PARTE DE LA TRANSPORTADORA | W6: ENVIO | Y6: TIPO IV | Z6: TERRESTRE | AB6: 1 | AC6: 35780 | AD6: 0 | AE6: 35780
A7: CARTAGENA | B7: COSTA | C7: 0004-0001 | D7: 13430 | E7: 3049917 | F7: 3007082045 | G7: OC ENVIO ROLLOS | H7: BOLIVAR | I7: MAGANGUE | J7: DISTRICOL RESTAURANTE TERMINAL | K7: REDEBAN | L7: FO-25-1869999 | M7: 45985.333 | N7: 45995.444 | P7: ENVIO | R7: AGREGADOR | S7: DISTRICOL | U7: EJECUTADO EXITOSO | V7: 24/11/2025 SE CONFIRMAN DATOS, SE REALIZA ENVIO POR OPERADOR LOGISTICO | 04/12/2025 SE REALIZA ENVIO DE 20 ROLLOS, CON LA GUIA 2277307834 SERVIENTREGA. SE CONFIRMA ENTREGA EXITOSA POR PARTE DE LA TRANSPORTADORA | W7: ENVIO | Y7: TIPO IV | Z7: TERRESTRE | AB7: 1 | AC7: 35780 | AD7: 0 | AE7: 35780
A8: APARTADO | B8: NOROCCIDENTE | C8: 0004-0005 | D8: 5480 | E8: 3052206 | F8: 3007030486 | G8: OC VISITA ROLLOS | H8: ANTIOQUIA | I8: MUTATA | J8: BARRIO CENTRO CALLE PRINCIPAL | K8: REDEBAN | L8: FO-25-1869543 | M8: 45985.396 | N8: 45992.335 | P8: VISITA | Q8: ROLLOS | R8: CB UNO A UNO | S8: CB UNO A UNO | T8: EJECUTADO | U8: EJECUTADO EXITOSO | V8: 24/11/2025 SE ESCALA AL COORDINADOR DE LA ZONA PARA ENTREGA EN SITIO | 01/12/2025 SE ENVÍAN 10 ROLLOS CON EL CONDUCTOR Y SE COMPARTE INFORMACIÓN CON LA USUARIA Y CONFIRMA EL RECIBIDO DE LOS ROLLOS | W8: ENVIO FLOTA - OPERADOR LOGISTICO | Y8: TIPO II | Z8: TERRESTRE | AA8: SALDARRIAGA MIRANDA SANTIAGO | AB8: 1 | AC8: 67654 | AD8: 140396 | AE8: 67654
A9: APARTADO | B9: NOROCCIDENTE | C9: 0004-0005 | D9: 5172 | E9: 3052673 | F9: 3007073417 | G9: OC VISITA ROLLOS | H9: ANTIOQUIA | I9: CHIGORODO | J9: BARRIO EL JARDIN CHIGORODO 1 | K9: REDEBAN | L9: FO-25-1870105 | M9: 45985.429 | N9: 45992.377 | P9: VISITA | Q9: ROLLOS | R9: CB UNO A UNO | S9: CB UNO A UNO | T9: EJECUTADO | U9: EJECUTADO EXITOSO | V9: 24/11/2025 SE ESCALA AL COORDINADOR DE LA ZONA PARA ENTREGA EN SITIO | 01/12/2025 SE DEJAN LOS 30 ROLLOS EN UN COMERCIO VECINO YA QUE EL USUARIO NO SE ENCUENTRA EN LA ZONA POR UN PARO QUE ESTÁ EN LA ZONA DE NECOCLI. NOS INDICA QUE LO DEJEMOS EN LA FERRETERÍA QUE ESTÁ DIAGONAL AL COMERCIO. | W9: VISITA TECNICA | Y9: TIPO II | Z9: TERRESTRE | AA9: SALDARRIAGA MIRANDA SANTIAGO | AB9: 1 | AC9: 67654 | AD9: 140396 | AE9: 67654
A10: BUCARAMANGA | B10: SANTANDERES | C10: 0004-0008 | D10: 68872 | E10: 3057141 | F10: 3007081487 | G10: OC ENVIO ROLLOS | H10: SANTANDER | I10: VILLANUEVA | J10: PTM VILLANUEVA BENYI STORE | K10: REDEBAN | L10: FO-25-1875978 | M10: 45986.333 | N10: 45992.662 | P10: ENVIO | R10: AGREGADOR | S10: COMCARD - PTM | U10: EJECUTADO EXITOSO | V10: 25/11/2025 SE CONFIRMAN DATOS, SE REALIZA ENVIO POR OPERADOR LOGISTICO | 01/12/2025 SE REALIZA ENVIO DE 10 ROLLOS, CON LA GUIA 2187690968 SERVIENTREGA. SE CONFIRMA ENTREGA EXITOSA POR PARTE DE LA TRANSPORTADORA | W10: ENVIO | Y10: TIPO III | Z10: TERRESTRE | AB10: 1 | AC10: 35780 | AD10: 0 | AE10: 35780
A11: SANTA MARTA | B11: COSTA | C11: 0004-0001 | D11: 47980 | E11: 3057150 | F11: 3007077719 | G11: OC VISITA ROLLOS | H11: MAGDALENA | I11: ZONA BANANERA | J11: BARRIO SOPLADOR ZONA BANANERA | K11: REDEBAN | L11: FO-25-1874870 | M11: 45986.333 | N11: 45992.674 | P11: VISITA | Q11: ROLLOS | R11: CB UNO A UNO | S11: CB UNO A UNO | T11: EJECUTADO | U11: EJECUTADO EXITOSO | V11: 25/11/2025 SE ESCALA AL COORDINADOR DE LA ZONA PARA ENTREGA EN SITIO | 01/12/2025 SE REALIZA ENTREGA DE 20 ROLLOS PARA DATÁFONO A SATISFACCIÓN DEL CLIENTE SE ACUERDA UN PUNTO DE ENCUENTRO CON EL USUARIO EN SAN JOSÉ SEVILLA YA QUE EL ACCESO A SOPLADOR ES RIESGOSO SIN UN ACOMPAÑANTE | W11: VISITA TECNICA | Y11: TIPO II | Z11: TERRESTRE | AA11: THOMAS CAMPO SIGIFREDO SEGUNDO | AB11: 1 | AC11: 67654 | AD11: 140396 | AE11: 67654
A12: IBAGUE | B12: REMOTAS | C12: 0004-0007 | D12: 73504 | E12: 3058194 | F12: 3007053991 | G12: OC ENVIO ROLLOS | H12: TOLIMA | I12: ORTEGA | J12: BARRIO EL VERGEL ORTEGA | K12: REDEBAN | L12: FO-25-1875959 | M12: 45986.372 | N12: 45994.637 | P12: ENVIO | R12: UNO A UNO | S12: CB UNO A UNO | U12: EJECUTADO EXITOSO | V12: 25/11/2025 SE CONFIRMAN DATOS, SE REALIZA ENVIO POR OPERADOR LOGISTICO | 03/12/2025 SE REALIZA ENVIO DE 10 ROLLOS, CON LA GUIA 2235596811 SERVIENTREGA. SE CONFIRMA ENTREGA EXITOSA POR PARTE DE LA TRANSPORTADORA | W12: ENVIO | Y12: TIPO III | Z12: TERRESTRE | AB12: 1 | AC12: 35780 | AD12: 0 | AE12: 35780
A13: SINCELEJO | B13: COSTA | C13: 0004-0001 | D13: 70429 | E13: 3058418 | F13: 3007061570 | G13: OC ENVIO ROLLOS | H13: SUCRE | I13: MAJAGUAL | J13: BARRIO CENTRO MAJAGUAL 3 | K13: REDEBAN | L13: FO-25-1875958 | M13: 45986.376 | N13: 45992.596 | P13: ENVIO | R13: CB UNO A UNO | S13: CB UNO A UNO | U13: EJECUTADO EXITOSO | V13: 25/11/2025 SE CONFIRMAN DATOS, SE REALIZA ENVIO POR OPERADOR LOGISTICO | 01/12/2025 SE REALIZA ENVIO DE 30 ROLLOS, CON LA GUIA 2265100522 SERVIENTREGA. SE CONFIRMA ENTREGA EXITOSA POR PARTE DE LA TRANSPORTADORA | W13: ENVIO | Y13: TIPO IV | Z13: FLUVIAL | AB13: 1 | AC13: 35780 | AD13: 0 | AE13: 35780
A14: PASTO | B14: SUROCCIDENTE Y EJE CAFETERO | C14: 0004-0003 | D14: 86865 | E14: 3059788 | F14: 3007046863 | G14: OC ENVIO ROLLOS | H14: PUTUMAYO | I14: VALLE DEL GUAMUEZ | J14: DISTRICOL PAPELERIA JAVIER | K14: REDEBAN | L14: FO-25-1878738 | M14: 45986.477 | N14: 45998.701 | P14: ENVIO | R14: AGREGADOR | S14: DISTRICOL | U14: EJECUTADO EXITOSO | V14: 07/12/2025 SE REALIZA ENVIO DE 20 ROLLOS, CON LA GUIA 2248145446 SERVIENTREGA. SE CONFIRMA ENTREGA EXITOSA POR PARTE DE LA TRANSPORTADORA | W14: ENVIO | Y14: TIPO IV | Z14: TERRESTRE | AB14: 1 | AC14: 35780 | AD14: 0 | AE14: 35780
A15: MEDELLIN | B15: NOROCCIDENTE | C15: 0004-0005 | D15: 5001 | E15: 3062297 | F15: 3007079020 | G15: OC VISITA ROLLOS | H15: ANTIOQUIA | I15: MEDELLIN | J15: PTM MEDELLIN DONDE LUISA | K15: REDEBAN | L15: FO-25-1879898 | M15: 45986.667 | N15: 45992.415 | P15: VISITA | Q15: ROLLOS | R15: AGREGADOR | S15: COMCARD - PTM | U15: EJECUTADO EXITOSO | V15: 25/11/2025 SE ESCALA AL COORDINADOR DE LA ZONA PARA ENTREGA EN SITIO | 01/12/2025 SE REALIZA ENTREGA DE 30 ROLLOS POR EL OPERADOR CABIFY CON LA GUIA V4001880013 | W15: VISITA TECNICA | Y15: TIPO I | Z15: TERRESTRE | AA15: ALVAREZ LOPEZ MARIANA | AB15: 1 | AC15: 35780 | AD15: 75096 | AE15: 35780
A16: MEDELLIN | B16: NOROCCIDENTE | C16: 0004-0005 | D16: 5001 | E16: 3062587 | F16: 3007082075 | G16: OC VISITA ROLLOS | H16: ANTIOQUIA | I16: MEDELLIN | J16: DISTRICOL CELUACCESORIOS SANTA | K16: REDEBAN | L16: FO-25-1879889 | M16: 45986.68 | N16: 45992.414 | P16: VISITA | Q16: ROLLOS | R16: AGREGADOR | S16: DISTRICOL | U16: EJECUTADO EXITOSO | V16: 25/11/2025 SE ESCALA AL COORDINADOR DE LA ZONA PARA ENTREGA EN SITIO | 01/12/2025 SE REALIZA ENTREGA DE ROLLOS POR EL OPERADOR CABIFY CON LA GUIA V4001880014 | W16: VISITA TECNICA | Y16: TIPO I | Z16: TERRESTRE | AA16: ALVAREZ LOPEZ MARIANA | AB16: 1 | AC16: 35780 | AD16: 75096 | AE16: 35780
A17: MANIZALES | B17: SUROCCIDENTE Y EJE CAFETERO | C17: 0004-0002 | D17: 17662 | E17: 3062943 | F17: 3007078014 | G17: OC ENVIO ROLLOS | H17: CALDAS | I17: SAMANA | J17: BARRIO FLORENCIA SAMANA | K17: REDEBAN | L17: FO-25-1882356 | M17: 45986.72 | N17: 46000.937 | P17: ENVIO | R17: CB UNO A UNO | S17: CB UNO A UNO | U17: EJECUTADO EXITOSO | V17: 01/12/2025 SE REALIZA ENVIO DE ROLLOS POR OPERADOR LOGISTICO | W17: ENVIO | Y17: TIPO IV | Z17: TERRESTRE | AB17: 1 | AC17: 35780 | AD17: 0 | AE17: 35780
