Workbook

Sheet RESUMEN
A1: FACTURACIÓN ACTIVIDADES CORRESPONSAL BANCARIO WOMPI | E1: FACTURACIÓN SERVICIOS ADICIONALES
A2: 1 AL 30 DE OCTUBRE 2025 | E2: 1 AL 30 DE OCTUBRE 2025
A4: CONCEPTOS | B4: CANTIDAD | C4: TOTAL | E4: CONCEPTOS | F4: CANTIDAD | G4: VALOR UNITARIO | H4: TOTAL
A5: Aperturas | B5: =COUNTA(APERTURAS!A:A)-1 -> 150 | C5: =APERTURAS!Y152 -> 74829004 | E5: Acometida de datos (ML)-CB 45522 | F5: 12 | G5: ='TARIFAS 2025'!B18 -> 16235 | H5: =F5*G5 -> 194820
A6: Incidentes | B6: =COUNTA(INCIDENTES!A:A)-1 -> 567 | C6: =INCIDENTES!AA569 -> 41590853
A7: OC Papelería | B7: =COUNTA('OC PAPALERÍA'!A:A)-1 -> 2330 | C7: ='OC PAPALERÍA'!AA2332 -> 78241253
A8: OC Cierres | B8: =COUNTA('OC CIERRES'!A:A)-1 -> 40 | C8: ='OC CIERRES'!AA42 -> 9070672
A9: OC Publicidad | B9: =COUNTA('OC PUBLICIDAD'!A:A)-1 -> 29 | C9: ='OC PUBLICIDAD'!AA31 -> 4765410
A10: OC Traslados | B10: =COUNTA('OC TRASLADOS'!A:A)-1 -> 12 | C10: ='OC TRASLADOS'!AA14 -> 2446663 | H10: =SUM(H5:H9) -> 194820
A11: Servicios Adicionales | C11: =H10 -> 194820
A12: SUBTOTAL | C12: =SUM(C5:C11) -> 211138675
A13: Iva | C13: =C12*0.19 -> 40116348
A14: TOTAL | C14: =SUM(C12:C13) -> 2.5125502e+08

Sheet TD
A1: ACTIVIDAD | B1: APERTURA
A3: DESCRIPCION CENTRO DE COSTOS | B3: Suma de VALOR TOTAL | C3: CENTRO DE COSTOS | D3: VALOR
A4: Wompi Centro | B4: 14539661 | C4: =A4 -> Wompi Centro | D4: =B4 -> 14539661 | H4: CENTRO DE COSTOS | I4: Suma de VALOR
A5: Wompi Costa | B5: 9031931 | C5: =A5 -> Wompi Costa | D5: =B5 -> 9031931 | H5: Wompi Centro | I5: 36483158
A6: Wompi Eje Cafetero | B6: 7686309 | C6: =A6 -> Wompi Eje Cafetero | D6: =B6 -> 7686309 | H6: Wompi Costa | I6: 26943227
A7: Wompi Noroccidente | B7: 5835873 | C7: =A7 -> Wompi Noroccidente | D7: =B7 -> 5835873 | H7: Wompi Eje Cafetero | I7: 15752402
A8: Wompi Oriente | B8: 8678589 | C8: =A8 -> Wompi Oriente | D8: =B8 -> 8678589 | H8: Wompi Noroccidente | I8: 32205102
A9: Wompi Santander | B9: 14025509 | C9: =A9 -> Wompi Santander | D9: =B9 -> 14025509 | H9: Wompi Oriente | I9: 26764391
A10: Wompi Suroccidente | B10: 15031132 | C10: =A10 -> Wompi Suroccidente | D10: =B10 -> 15031132 | H10: Wompi Santander | I10: 34579886
A11: Total general | B11: 74829004 | H11: Wompi Suroccidente | I11: 38215689
H12: Total general | I12: 210943855
A15: ACTIVIDAD | B15: INCIDENTE
A17: DESCRIPCION CENTRO DE COSTOS | B17: Suma de VALOR TOTAL
A18: Wompi Centro | B18: 7149102 | C18: =A18 -> Wompi Centro | D18: =B18 -> 7149102
A19: Wompi Costa | B19: 6553224 | C19: =A19 -> Wompi Costa | D19: =B19 -> 6553224
A20: Wompi Eje Cafetero | B20: 2103611 | C20: =A20 -> Wompi Eje Cafetero | D20: =B20 -> 2103611
A21: Wompi Noroccidente | B21: 5966201 | C21: =A21 -> Wompi Noroccidente | D21: =B21 -> 5966201
A22: Wompi Oriente | B22: 5627328 | C22: =A22 -> Wompi Oriente | D22: =B22 -> 5627328
A23: Wompi Santander | B23: 5997673 | C23: =A23 -> Wompi Santander | D23: =B23 -> 5997673
A24: Wompi Suroccidente | B24: 8193714 | C24: =A24 -> Wompi Suroccidente | D24: =B24 -> 8193714
A25: Total general | B25: 41590853
A29: ACTIVIDAD | B29: ORDEN DE CAMBIO
A30: SOLICITUD | B30: ROLLOS
A32: DESCRIPCION CENTRO DE COSTOS | B32: Suma de VALOR TOTAL
A33: Wompi Centro | B33: 12738595 | C33: =A33 -> Wompi Centro | D33: =B33 -> 12738595
A34: Wompi Costa | B34: 10005932 | C34: =A34 -> Wompi Costa | D34: =B34 -> 10005932
A35: Wompi Eje Cafetero | B35: 5184656 | C35: =A35 -> Wompi Eje Cafetero | D35: =B35 -> 5184656
A36: Wompi Noroccidente | B36: 16237033 | C36: =A36 -> Wompi Noroccidente | D36: =B36 -> 16237033
A37: Wompi Oriente | B37: 9499872 | C37: =A37 -> Wompi Oriente | D37: =B37 -> 9499872
A38: Wompi Santander | B38: 12610038 | C38: =A38 -> Wompi Santander | D38: =B38 -> 12610038
A39: Wompi Suroccidente | B39: 11965127 | C39: =A39 -> Wompi Suroccidente | D39: =B39 -> 11965127
A40: Total general | B40: 78241253
A44: ACTIVIDAD | B44: ORDEN DE CAMBIO
A45: SOLICITUD | B45: CIERRE
A47: DESCRIPCION CENTRO DE COSTOS | B47: Suma de VALOR TOTAL
A48: Wompi Centro | B48: 1362264 | C48: =A48 -> Wompi Centro | D48: =B48 -> 1362264
A49: Wompi Costa | B49: 203532 | C49: =A49 -> Wompi Costa | D49: =B49 -> 203532
A50: Wompi Noroccidente | B50: 2914958 | C50: =A50 -> Wompi Noroccidente | D50: =B50 -> 2914958
A51: Wompi Oriente | B51: 2228348 | C51: =A51 -> Wompi Oriente | D51: =B51 -> 2228348
A52: Wompi Santander | B52: 1636106 | C52: =A52 -> Wompi Santander | D52: =B52 -> 1636106
A53: Wompi Suroccidente | B53: 521932 | C53: =A53 -> Wompi Suroccidente | D53: =B53 -> 521932
A54: Wompi Eje Cafetero | B54: 203532 | C54: =A54 -> Wompi Eje Cafetero | D54: =B54 -> 203532
A55: Total general | B55: 9070672
A58: ACTIVIDAD | B58: ORDEN DE CAMBIO
A59: SOLICITUD | B59: PUBLICIDAD
A61: DESCRIPCION CENTRO DE COSTOS | B61: Suma de VALOR TOTAL
A62: Wompi Centro | B62: 574634 | C62: =A62 -> Wompi Centro | D62: =B62 -> 574634
A63: Wompi Costa | B63: 1148608 | C63: =A63 -> Wompi Costa | D63: =B63 -> 1148608
A64: Wompi Noroccidente | B64: 670123 | C64: =A64 -> Wompi Noroccidente | D64: =B64 -> 670123
A65: Wompi Oriente | B65: 670803 | C65: =A65 -> Wompi Oriente | D65: =B65 -> 670803
A66: Wompi Santander | B66: 191658 | C66: =A66 -> Wompi Santander | D66: =B66 -> 191658
A67: Wompi Eje Cafetero | B67: 574294 | C67: =A67 -> Wompi Eje Cafetero | D67: =B67 -> 574294
A68: Wompi Suroccidente | B68: 935290 | C68: =A68 -> Wompi Suroccidente | D68: =B68 -> 935290
A69: Total general | B69: 4765410
A73: ACTIVIDAD | B73: ORDEN DE CAMBIO
A74: SOLICITUD | B74: TRASLADO
A76: DESCRIPCION CENTRO DE COSTOS | B76: Suma de VALOR TOTAL
A77: Wompi Centro | B77: 118902 | C77: =A77 -> Wompi Centro | D77: =B77 -> 118902
A78: Wompi Noroccidente | B78: 580914 | C78: =A78 -> Wompi Noroccidente | D78: =B78 -> 580914
A79: Wompi Oriente | B79: 59451 | C79: =A79 -> Wompi Oriente | D79: =B79 -> 59451
A80: Wompi Santander | B80: 118902 | C80: =A80 -> Wompi Santander | D80: =B80 -> 118902
A81: Wompi Suroccidente | B81: 1568494 | C81: =A81 -> Wompi Suroccidente | D81: =B81 -> 1568494
A82: Total general | B82: 2446663

Sheet TARIFAS 2025
A1: TIPO ACTIVIDAD | B1: PRINCIPAL | C1: INTERMEDIA | D1: LEJANA
A2: ENVIO DATAFONO | B2: 39706 | C2: 49474 | D2: 51412
A3: ENVIO VISITA DATAFONO | B3: 59451 | C3: 182458 | D3: 462012
A4: INSTALACIÓN DATAFONO | B4: 130010 | C4: 222882 | D4: 474719
A5: INSTALACIÓN DATAFONO Y MATERIAL POP | B5: 367716 | C5: 488953 | D5: 598334
A6: LOGISTICA INVERSA DATAFONO | B6: 49274 | C6: 188826 | D6: 454487
A7: LOGISTICA INVERSA MATERIAL POP | B7: 95829 | C7: 287147 | D7: 551974
A8: SOPORTE TÉCNICO | B8: 51282 | C8: 172989 | D8: 452148
A9: ORDENES DE CAMBIO_CIERRES DESTRUCCIÓN DE POP EN SITIO | B9: 71290 | C9: 206527 | D9: 602411
A10: ORDENES DE CAMBIO_CIERRES RETORNO DE POP A BODEGA | B10: 101766 | C10: 318400 | D10: 707110
A11: ORDENES DE CAMBIO_PAPELERÍA | B11: 31419 | C11: 36351 | D11: 40250
A12: ORDENES DE CAMBIO_PUBLICIDAD | B12: 95829 | C12: 287147 | D12: 551974
A13: ORDENES DE CAMBIO_OTRAS | B13: 59451 | C13: 182458 | D13: 462012
A14: SOPORTE TELEFÓNICO | B14: 22000 | C14: 22000 | D14: 22000
A16: SERVICIOS ADICIONALES EN SITIO | B16: Estos valores aplican en las actividades que se requieran, previa autorización de Wompi.
A17: Acometida eléctrica 3N12 Cu THHN (ml) | B17: 21000 | C17: 21000 | D17: 21000
A18: Acometida de datos (ML) | B18: 16235 | C18: 16235 | D18: 16235
A19: Switch | B19: 257392 | C19: 257392 | D19: 257392
A20: Router | B20: 306552 | C20: 306552 | D20: 306552

Sheet CENTROS DE COSTOS
A1: CIUDAD | B1: CENTRO_COSTO | C1: DESCRIPCION CENTRO DE COSTOS | D1: COORDINADOR DE ZONA
A2: APARTADO | B2: 0036-0005 | C2: Wompi Noroccidente | D2: JUAN SEBASTIÁN RÍOS CASTRILLÓN
A3: BARRANQUILLA | B3: 0036-0001 | C3: Wompi Costa | D3: JOSE MAURICIO HERNANDEZ ROJAS
A4: BOGOTA | B4: 0036-0004 | C4: Wompi Centro | D4: WILLIAM ASDRUBAL ROZO ROZO
A5: BUCARAMANGA | B5: 0036-0007 | C5: Wompi Santander | D5: MIGUEL JULIÁN HERNÁNDEZ GUARÍN
A6: CALI | B6: 0036-0003 | C6: Wompi Suroccidente | D6: DIEGO FERNANDO HENAO CARDONA
A7: CARTAGENA | B7: 0036-0001 | C7: Wompi Costa | D7: JOSE MAURICIO HERNANDEZ ROJAS
A8: CUCUTA | B8: 0036-0007 | C8: Wompi Santander | D8: MIGUEL JULIÁN HERNÁNDEZ GUARÍN
A9: FLORENCIA | B9: 0036-0006 | C9: Wompi Oriente | D9: KEVIN ALEXIS CORZO BUSTOS
A10: IBAGUE | B10: 0036-0006 | C10: Wompi Oriente | D10: KEVIN ALEXIS CORZO BUSTOS
A11: MANIZALES | B11: 0036-0002 | C11: Wompi Eje Cafetero | D11: DIEGO FERNANDO HENAO CARDONA
A12: MEDELLIN | B12: 0036-0005 | C12: Wompi Noroccidente | D12: JUAN SEBASTIÁN RÍOS CASTRILLÓN
... A23: YOPAL | B23: 0036-0006 | C23: Wompi Oriente | D23: KEVIN ALEXIS CORZO BUSTOS

Sheet TIPOLOGIA
A1: COD. CIUDAD | B1: CIUDAD | C1: DEPARTAMENTO | D1: DESDE DONDE SE ATIENDE | E1: TIPOLOGIA WOMPI | F1: TIPO DE TRAYECTO | G1: BODEGA WOMPI
A2: 91430 | B2: LA VICTORIA | C2: AMAZONAS | D2: BOGOTA | E2: LEJANA | F2: AEREO | G2: BOGOTA
A3: 91669 | B3: PUERTO SANTANDER | C3: AMAZONAS | D3: BOGOTA | E3: LEJANA | F3: AEREO | G3: BOGOTA
A4: 91263 | B4: EL ENCANTO | C4: AMAZONAS | D4: BOGOTA | E4: LEJANA | F4: AEREO | G4: BOGOTA
A5: 91405 | B5: LA CHORRERA | C5: AMAZONAS | D5: BOGOTA | E5: LEJANA | F5: AEREO | G5: BOGOTA
A6: 91407 | B6: LA PEDRERA | C6: AMAZONAS | D6: BOGOTA | E6: LEJANA | F6: AEREO | G6: BOGOTA
A7: 91001 | B7: LETICIA | C7: AMAZONAS | D7: BOGOTA | E7: LEJANA | F7: AEREO | G7: BOGOTA
A8: 91460 | B8: MIRITI - PARANA | C8: AMAZONAS | D8: BOGOTA | E8: LEJANA | F8: AEREO | G8: BOGOTA
A9: 91530 | B9: PUERTO ALEGRIA | C9: AMAZONAS | D9: BOGOTA | E9: LEJANA | F9: AEREO | G9: BOGOTA
A10: 91536 | B10: PUERTO ARICA | C10: AMAZONAS | D10: BOGOTA | E10: LEJANA | F10: AEREO | G10: BOGOTA
A11: 91540 | B11: PUERTO NARIÑO | C11: AMAZONAS | D11: BOGOTA | E11: LEJANA | F11: AEREO | G11: BOGOTA
A12: 91798 | B12: TARAPACA | C12: AMAZONAS | D12: BOGOTA | E12: LEJANA | F12: AEREO | G12: BOGOTA
A13: 5055 | B13: ARGELIA | C13: ANTIOQUIA | D13: MEDELLIN | E13: LEJANA | F13: TERRESTRE | G13: MEDELLIN
... A1124: 23682 | B1124: SAN JOSE DE URE | C1124: CORDOBA | D1124: MONTERIA | E1124: LEJANA | F1124: TERRESTRE | G1124: MONTERIA

Sheet APERTURAS
A1: CIUDAD SEDE | B1: CENTRO_COSTO | C1: DESCRIPCION CENTRO DE COSTOS | D1: CÓDIGO DANE | E1: TA/CODIGO ACTIVIDAD | F1: CODIGO CB | G1: ACTIVIDAD | H1: TIPO DE APERTURA | I1: DEPARTAMENTO | J1: CIUDAD | K1: NOMBRE DEL CB | L1: RED | M1: FO | N1: FECHA LISTA | O1: FECHA ULTIMA ACTUALIZACION | P1: ESTADO | Q1: OBSERVACIONES CLIENTE | R1: FORMA DE ATENCIÓN | S1: TERMINALES | T1: TIPOLOGIA | U1: TIPO DE TRAYECTO | V1: NOMBRE DEL TECNICO | W1: DIAS DE VISITA | X1: VALOR DIAS ACTIVIDAD | Y1: VALOR TOTAL
A2: CALI | B2: =VLOOKUP(A2,'CENTROS DE COSTOS'!A:D,2,0) -> 0036-0003 | C2: =VLOOKUP(A2,'CENTROS DE COSTOS'!A:D,3,0) -> Wompi Suroccidente | D2: 76520 | E2: TA-25-1046221 | F2: 81148 | G2: APERTURA | H2: CB CRECIMIENTO - OTRAS LISTAS | I2: VALLE DEL CAUCA | J2: PALMIRA | K2: BARRIO LA SULTANA PALMIRA | L2: WOMPI | M2: FO-25-1457847 | N2: 45901 | O2: 45939 | P2: EJECUTADO | Q2: 12-09 SE REALIZA LLAMADA AL CLIENTE, SE HABLA CON AURA ELENA BENAVIDES ROJAS EL CUAL INDICA QUE EL CORREO CON LAS CREDENCIALES POR PARTE DE WOMPI AUN NO HA LLEGADO 22-09 SE HABLA CON LA SRA AURA ELENA BENAVIDES ROJAS LA CUAL INDICA QUE AUN NO TIENE EL CORREO 08-10 SE REALIZA LLAMADA AL CLIENTE, SE HABLA CON LA SRA AURA ELENA BENAVIDES ROJAS. SE VALIDA DIRECCIÓN OK, CANAL OK, DISPONIBILIDAD TOTAL, LLAMAR EL DÍA LA INSTALACIÓN PARA CONFIRMAR VISITA, AVISO EXTERIOR ALTURA APROX 2 METROS; CREDENCIALES: NO 9/10/2025 SE REALIZA INSTALACIÓN DE CORRESPONSAL, SE INSTALAN EQUIPOS CON PRUEBAS EXITOSAS, SE CAPACITA Y SE EVALÚA AL CLIENTE, SE INSTALA PUBLICIDAD COMPLETA, CB QUEDA OPERATIVO. USUARIO SOMOS BANCOLOMBIA ACTIVO | R2: VISITA_TÉCNICA | S2: 254MMD4X2530 | T2: PRINCIPAL | U2: TERRESTRE | V2: MONTERO MUESES GIAN CARLO | W2: 1 | X2: =IF(T2="PRINCIPAL",'TARIFAS 2025'!$B$5,IF(T2="INTERMEDIA",'TARIFAS 2025'!$C$5,IF(T2="LEJANA",'TARIFAS 2025'!$D$5))) -> 367716 | Y2: =X2*W2 -> 367716
A3: PEREIRA | B3: =VLOOKUP(A3,'CENTROS DE COSTOS'!A:D,2,0) -> 0036-0002 | C3: =VLOOKUP(A3,'CENTROS DE COSTOS'!A:D,3,0) -> Wompi Eje Cafetero | D3: 66001 | E3: TA-25-1187978 | F3: 81418 | G3: APERTURA | H3: CB CRECIMIENTO - NUEVO | I3: RISARALDA | J3: PEREIRA | K3: BARRIO LOS ANGELES PEREIRA | L3: WOMPI | M3: FO-25-1646754 | N3: 45908 | O3: 45939 | P3: EJECUTADO | Q3: 12-09 SE REALIZA LLAMADA AL CLIENTE, SE HABLA CON LA SRA MARIA MANUELA LARGO SOTO EL CUAL INDICA QUE EL CORREO CON LAS CREDENCIALES POR PARTE DE WOMPI AUN NO HA LLEGADO // 22/09/2025 SE REALIZA LLAMADA AL NUMERO DE LA LISTA SE HABLA CON LA SEÑORA MARIA QUIEN INDICA QUE NO LES HA LLEGADO EL CORREO CON LAS CREDENCIALES, YA BUSCARON EN TODO EL BUZON Y NADA 08-10 SE REALIZA LLAMADA AL CLIENTE, SE HABLA CON LA SRA MARIA MANUELA LARGO SOTO. SE VALIDA DIRECCIÓN OK, CANAL OK, DISPONIBILIDAD TOTAL, LLAMAR EL DÍA LA INSTALACIÓN PARA CONFIRMAR VISITA, AVISO EXTERIOR ALTURA APROX 1 METROS; CREDENCIALES: SI 9/10/2025 SE REALIZA INSTALACIÓN DE CORRESPONSAL, SE INSTALAN EQUIPOS CON PRUEBAS EXITOSAS, SE CAPACITA Y SE EVALÚA AL CLIENTE, SE INSTALA PUBLICIDAD COMPLETA, CB QUEDA OPERATIVO. USUARIO SOMOS BANCOLOMBIA ACTIVO | R3: VISITA_TÉCNICA | S3: 254MMD4X0196 | T3: PRINCIPAL | U3: TERRESTRE | V3: ARROYAVE CANO MANUEL GUILLERMO | W3: 1 | X3: =IF(T3="PRINCIPAL",'TARIFAS 2025'!$B$5,IF(T3="INTERMEDIA",'TARIFAS 2025'!$C$5,IF(T3="LEJANA",'TARIFAS 2025'!$D$5))) -> 367716 | Y3: =X3*W3 -> 367716
A4: BOGOTA | B4: =VLOOKUP(A4,'CENTROS DE COSTOS'!A:D,2,0) -> 0036-0004 | C4: =VLOOKUP(A4,'CENTROS DE COSTOS'!A:D,3,0) -> Wompi Centro | D4: 25843 | E4: TA-25-1100744 | F4: 81453 | G4: APERTURA | H4: CB CRECIMIENTO - NUEVO | I4: CUNDINAMARCA | J4: VILLA DE SAN DIEGO DE UBATE | K4: BARRIO JUAN JOSE NEIRA VILLA DE SAN DIEGO DE UBATE 5 | L4: WOMPI | M4: FO-25-1668980 | N4: 45908 | O4: 45960 | P4: EJECUTADO | Q4: 12-09 SE REALIZA LLAMADA AL CLIENTE, SE HABLA CON LA SR JHON FERNANDO GONZALEZ LANCHEROS SE VALIDA DIRECCIÓN OK, CANAL OK, DISPONIBILIDAD TOTAL, USUARIO Y CONTRASEÑA WOMPI OK, LLAMAR EL DÍA LA INSTALACIÓN PARA CONFIRMAR VISITA, AVISO EXTERIOR ALTURA APROX 2 METROS 16-09 SE VISITA COMERCIO, EN EL SITIO EL CLIENTE NOS MANIFIESTA QUE NO LE HA LLEGADO EL CORREO DE WOMPI PARA HABILITAR LAS CREDENCIALES, POR LO QUE SE ESCALA AL COORDINADOR DANDO LOS DATOS DEL CLIENTE JUNTO CON EL CORREO PERO TAMBIÉN SE EVIDENCIA YA EN EL EQUIPO QUE EL CORREO QUE TOMARON AL PARECER POR PARTE DE WOMPI ESTÁ MAL (CORREO CORRECTO: GONZALEZJOHN046@GMAIL.COM) (CORREO ERRADO: GONZALEZJHONN04@GMAIL.COM), SE ESCALA PARA QUE SE RESUELVA EL DATO PERO INDICAN TIEMPO DE RESPUESTA DE 1 A 3 DÍAS HÁBILES POR LO QUE SE ESPERARA RESPUESTA DEL ÁREA ENCARGADA Y SE REPROGRAMADA ACTIVIDAD. 19-09 EL DÍA DE HOY LLEGA CORREO CON LA SIGUIENTE RESPUESTA: "CASO N° 465292, CON ASUNTO CORREO SATURADO DEL COMERCIO, NO TIENE LAS CREDENCIALES HA SIDO SOLUCIONADO" EN COMUNICACIÓN CON EL COMERCIO, MANIFIESTA NO LE HA LLEGADO CORREO CON LA INFORMACIÓN 08-10 SE REALIZA LLAMADA AL CLIENTE, SE HABLA CON LA SRA NELLY OPAYOME. SE VALIDA DIRECCIÓN OK, CANAL OK, DISPONIBILIDAD TOTAL, LLAMAR EL DÍA LA INSTALACIÓN PARA CONFIRMAR VISITA, AVISO EXTERIOR ALTURA APROX 2 METROS; CREDENCIALES: NO 10-10 RESUMEN DEL CASO: SE REALIZA APERTURA WOMPI DONDE AL LLEGAR AL COMERCIO CLIENTE CONFIRMA NO HA RECIBIDO CORREO DE COMPLETA TU REGISTRO AL VALIDAR EL CORREO REGISTRADO EN EL DATÁFONO REGISTRA GONZALEZJHONN04@GMAIL.COM Y EL CORREO CORRECTO ES GONZALEZJOHN046@GMAIL.COM POR LO QUE NO LLEGA EL CORREO DE ACTIVACION EN CREDENCIALES SERIAL: 254UMX3181 TICKET N° (471570), | EN NUEVA COMUNICACIÓN CON EL USUARIO INDICA QUE YA TIENE EL CORREO POR PARTE DE WOMPI, ALTURA DEL AVISO 2 MT | 30/10/2025 SE REALIZA INSTALACIÓN DE CORRESPONSAL, SE INSTALAN EQUIPOS CON PRUEBAS EXITOSAS, SE CAPACITA Y SE EVALÚA AL CLIENTE, SE INSTALA PUBLICIDAD COMPLETA, CB QUEDA OPERATIVO. USUARIO SOMOS BANCOLOMBIA ACTIVO | R4: VISITA_TÉCNICA | S4: 254MMD4X3181 | T4: INTERMEDIA | U4: TERRESTRE | V4: ROMERO ROJAS BREIDY JHOHAN | W4: 3 | X4: =IF(T4="PRINCIPAL",'TARIFAS 2025'!$B$5,IF(T4="INTERMEDIA",'TARIFAS 2025'!$C$5,IF(T4="LEJANA",'TARIFAS 2025'!$D$5))) -> 488953 | Y4: =X4*W4 -> 1466859
A5: MONTERIA | B5: =VLOOKUP(A5,'CENTROS DE COSTOS'!A:D,2,0) -> 0036-0001 | C5: =VLOOKUP(A5,'CENTROS DE COSTOS'!A:D,3,0) -> Wompi Costa | D5: 23670 | E5: TA-25-1100787 | F5: 81431 | G5: APERTURA | H5: CB CRECIMIENTO - NUEVO | I5: CORDOBA | J5: SAN ANDRES SOTAVENTO | K5: BARRIO BOCA CANOA SAN ANDRES DE SOTAVENTO | L5: WOMPI | M5: FO-25-1554843 | N5: 45908 | O5: 45940 | P5: EJECUTADO | Q5: 12-09 SE REALIZA LLAMADA AL CLIENTE, SE HABLA CON LA SRA DIANA RAMIREZ HOYOS SE VALIDA DIRECCIÓN OK, CANAL OK, DISPONIBILIDAD TOTAL, USUARIO Y CONTRASEÑA WOMPI OK, LLAMAR EL DÍA LA INSTALACIÓN PARA CONFIRMAR VISITA, AVISO EXTERIOR ALTURA APROX 3.5 METROS - COMUNICACIÓN POR WPP 16/09/2025 SE VISITA COMERCIO PERO NO ES POSIBLE REALIZAR LA INSTALACIÓN, SE CREAN CREDENCIALES, SE INGRESA A LA APLICACIÓN CON EL USUARIO PERO NO MUESTRA EL MENÚ TRANSACCIONAL EN EL EQUIPO, SE HACE ESCALAMIENTO MEDIANTE AL TICKET N° (465381), DESPUÉS DE 40 MINUTOS NO TUVIMOS RESPUESTA, POR LO QUE EL COORDINADOR NOS INDICA QUE NOS PODEMOS RETIRAR DEL SITIO. 08-10 SE SE PROGRAMA ACTIVIDAD POR SOLICITUD DE WOMPI, INDICAN QUE YA ESTA TODO LISTO PARA CONFIGURAR EL EQUIPO 10-10 SE REALIZA INSTALACIÓN DE CORRESPONSAL, SE INSTALAN EQUIPOS CON PRUEBAS EXITOSAS, SE CAPACITA Y SE EVALÚA AL CLIENTE, SE INSTALA PUBLICIDAD COMPLETA, CB QUEDA OPERATIVO. USUARIO SOMOS BANCOLOMBIA ACTIVO | R5: VISITA_TÉCNICA | S5: 254UMD4X8138 | T5: INTERMEDIA | U5: TERRESTRE | V5: CACERES HERNANDEZ ANDRES | W5: 2 | X5: =IF(T5="PRINCIPAL",'TARIFAS 2025'!$B$5,IF(T5="INTERMEDIA",'TARIFAS 2025'!$C$5,IF(T5="LEJANA",'TARIFAS 2025'!$D$5))) -> 488953 | Y5: =X5*W5 -> 977906
A6: NEIVA | B6: =VLOOKUP(A6,'CENTROS DE COSTOS'!A:D,2,0) -> 0036-0006 | C6: =VLOOKUP(A6,'CENTROS DE COSTOS'!A:D,3,0) -> Wompi Oriente | D6: 41001 | E6: TA-25-1187980 | F6: 81412 | G6: APERTURA | H6: CB CRECIMIENTO - NUEVO | I6: HUILA | J6: NEIVA | K6: BARRIO LA GAITANA NEIVA 1 | L6: WOMPI | M6: FO-25-1659812 | N6: 45908 | O6: 45960 | P6: EJECUTADO | Q6: 12-09 SE REALIZA LLAMADA AL CLIENTE, SE HABLA CON LA SRA DANIELA RUBIANO VASQUEZ LA CUAL INDICA QUE NO PUEDE VERIFICAR LOS DATOS POR QUE SE ENCUNTRA OCUPADA Y QUE ELLA NO HA RECIBIDO HASTA AHORA NINGUN CORREO - COMUNICACIÓN POR WPP // 22/09/2025 SE REALIZA LLAMADA AL NUMERO DE LA LISTA SE HABLA CON EL ESPOSO DE LA SEÑORA DANIELA QUIEN INDICA QUE EL CORREO CON EL QUE HICIERON LA SOLICITUD TIENE NOVEDAD, SOLICITA QUE LE CAMBIEN EL CORREO PARA PODER RECIBIR LA APERTURA (rubivadani@gmail.com) 08-10 SE SE PROGRAMA ACTIVIDAD POR SOLICITUD DE WOMPI, INDICAN QUE YA ESTA TODO LISTO PARA CONFIGURAR EL EQUIPO 9/10/2025 SE VISTA EL CB PARA IMPLEMENTACIÓN, PERO EL USUARIO INDICA QUE EL CORREO REGISTRADO LO PERDIÓ, POR LO QUE NO FUE POSIBLE ACCEDER Y ACTIVAR LAS CREDENCIALES, EL USUARIO INDICA QUE EL CORREO QUE TIENE ACTUALMENTE ES RUBIVADANI@GMAIL.COM. | 28/10/2025 EN NUEVA COMUNIACIÓN CON LA USUARIA POR WPP INDICA QUE YA TIENE EL CORREO POR PARTE DE WOMPI - COMUNICACIÓN POR WPP | 30-10 SE REALIZA INSTALACIÓN DE CORRESPONSAL, SE INSTALAN EQUIPOS CON PRUEBAS EXITOSAS, SE CAPACITA Y SE EVALÚA AL CLIENTE, SE INSTALA PUBLICIDAD COMPLETA, CB QUEDA OPERATIVO. USUARIO SOMOS BANCOLOMBIA ACTIVO | R6: VISITA_TÉCNICA | S6: 254UMD4X6246 | T6: PRINCIPAL | U6: TERRESTRE | V6: DEVIA REINOSO JUAN CARLOS | W6: 2 | X6: =IF(T6="PRINCIPAL",'TARIFAS 2025'!$B$5,IF(T6="INTERMEDIA",'TARIFAS 2025'!$C$5,IF(T6="LEJANA",'TARIFAS 2025'!$D$5))) -> 367716 | Y6: =X6*W6 -> 735432
A7: BUCARAMANGA | B7: =VLOOKUP(A7,'CENTROS DE COSTOS'!A:D,2,0) -> 0036-0007 | C7: =VLOOKUP(A7,'CENTROS DE COSTOS'!A:D,3,0) -> Wompi Santander | D7: 68001 | E7: TA-25-1187982 | F7: 81380 | G7: APERTURA | H7: CB CRECIMIENTO - NUEVO | I7: SANTANDER | J7: BUCARAMANGA | K7: BARRIO SAN FRANCISCO BUCARAMANGA 20 | L7: WOMPI | M7: FO-25-1646760 | N7: 45908 | O7: 45961 | P7: EJECUTADO | Q7: 12-09 SE REALIZA LLAMADA AL CLIENTE, SE HABLA CON LA SRA LENIS DAYANA DURAN FARFAN LA CUAL INIDCA QUE EL CORREO ESTA ERRADO, EL CORREO CORRECTO ES lenis120417@gmail.com 22-09 SE REALIZA LLAMADA AL CLIENTE, SE HABLA CON LA SRA LENIS DAYANA DURAN FARFAN LA CUAL INDICA QUE NO TIENE EL CORREO POR PARTE DE WOMPI 08-10 SE REALIZA CONTACTO POR WPP CON LA SRA LENIS DAYANA DURAN FARFAN. SE VALIDA DIRECCIÓN OK, CANAL OK, DISPONIBILIDAD TOTAL, LLAMAR EL DÍA LA INSTALACIÓN PARA CONFIRMAR VISITA, AVISO EXTERIOR ALTURA APROX 2.5 METROS; CREDENCIALES: SI 09/10/2025 RESUMEN DEL CASO: CLIENTE INDICA QUE NO LE HA LLEGADO CORREO CON LAS CREDENCIALES INFORMA QUE EL CORREO NO ES EL CORRECTO CORREO EXACTO ES LENIS120417@GMAIL.COM SE REALIZAN PRUEBAS A DICHO CORREO EXITOSAS SE INTENTA REGISTRO A WOMPI POR MEDIO DEL LINK Y NO DEJA ESCRIBIR SERIAL: 254MMD4W8890 TICKET N° (471140), | 28-10 EN NUEVA COMUNICACIÓN CON EL USUARIO INDICA QUE YA TIENE EL CORREO DE WOMPI, ALTURA DEL AVISO 3.5 MT | 31/10/2025 SE REALIZA INSTALACIÓN DE CORRESPONSAL, SE INSTALAN EQUIPOS CON PRUEBAS EXITOSAS, SE CAPACITA Y SE EVALÚA AL CLIENTE, SE INSTALA PUBLICIDAD COMPLETA, CB QUEDA OPERATIVO. USUARIO SOMOS BANCOLOMBIA ACTIVO | R7: VISITA_TÉCNICA | S7: 254MMD4W8890 | T7: PRINCIPAL | U7: TERRESTRE | V7: MARIÑO PABON JORGE ENRIQUE | W7: 1 | X7: =IF(T7="PRINCIPAL",'TARIFAS 2025'!$B$5,IF(T7="INTERMEDIA",'TARIFAS 2025'!$C$5,IF(T7="LEJANA",'TARIFAS 2025'!$D$5))) -> 367716 | Y7: =X7*W7 -> 367716
A8: BOGOTA | B8: =VLOOKUP(A8,'CENTROS DE COSTOS'!A:D,2,0) -> 0036-0004 | C8: =VLOOKUP(A8,'CENTROS DE COSTOS'!A:D,3,0) -> Wompi Centro | D8: 11001 | E8: TA-25-1100805 | F8: 81375 | G8: APERTURA | H8: CB CRECIMIENTO - NUEVO | I8: CUNDINAMARCA | J8: BOGOTA | K8: BARRIO EL TROPEZON BOGOTA 1 | L8: WOMPI | M8: FO-25-1554883 | N8: 45908 | O8: 45939 | P8: EJECUTADO | Q8: 12-09 SE REALIZA LLAMDA AL CLIENTE, SE HABLA CON EL SR ISAAC KAMILO VALERA MORENO DIRECCIÓN OK, CANAL OK, DISPONIBILIDAD TOTAL, USUARIO Y CONTRASEÑA WOMPI OK, LLAMAR EL DÍA LA INSTALACIÓN PARA CONFIRMAR VISITA, AVISO EXTERIOR ALTURA APROX 2 METROS 16/09/2025 SE REALIZA CIERRE DE VISITA YA QUE NO HAN LLEGADO CORREO DE CREDENCIALES INDICA QUE LO RECIBIO PERO ELIMINO UNOS CORREOS Y NO SE DIO CUENTA. SE ESCALA CASO A COORDINADOR WILLIAM ROZO QUIEN AUTORIZA TICKET 465275 19-09 EL DÍA DE HOY LLEGA CORREO CON LA SIGUIENTE RESPUESTA: "SU CASO N° 465275, CON ASUNTO COMERCIO INFORMA NO LE LLEGARON LAS CREDENCIALES HA SIDO SOLUCIONADO" DE ACUERDO CON LA VALIDACIÓN CON EL COMERCIO, INFORMA NO LE HA LLEGADO INFORMACIÓN COMO LO DICE EL CORREO, ACTIVIDAD SIGUE PENDIENTE 08-10 SE REALIZA LLAMADA AL CLIENTE, SE HABLA CON EL SR ISAAC KAMILO VALERA MORENO. SE VALIDA DIRECCIÓN OK, CANAL OK, DISPONIBILIDAD TOTAL, LLAMAR EL DÍA LA INSTALACIÓN PARA CONFIRMAR VISITA, AVISO EXTERIOR ALTURA APROX 2.5 METROS; CREDENCIALES: NO 9/10/2025 SE REALIZA INSTALACIÓN DE CORRESPONSAL, SE INSTALAN EQUIPOS CON PRUEBAS EXITOSAS, SE CAPACITA Y SE EVALÚA AL CLIENTE, SE INSTALA PUBLICIDAD COMPLETA, CB QUEDA OPERATIVO. USUARIO SOMOS BANCOLOMBIA NO ACTIVO , SE CAPACITA CON EL DE PRUEBA | R8: VISITA_TÉCNICA | S8: 254MMD4X3304 | T8: PRINCIPAL | U8: TERRESTRE | V8: HERNANDEZ NARANJO OSCAR EDUARDO | W8: 2 | X8: =IF(T8="PRINCIPAL",'TARIFAS 2025'!$B$5,IF(T8="INTERMEDIA",'TARIFAS 2025'!$C$5,IF(T8="LEJANA",'TARIFAS 2025'!$D$5))) -> 367716 | Y8: =X8*W8 -> 735432
A9: VILLAVICENCIO | B9: =VLOOKUP(A9,'CENTROS DE COSTOS'!A:D,2,0) -> 0036-0006 | C9: =VLOOKUP(A9,'CENTROS DE COSTOS'!A:D,3,0) -> Wompi Oriente | D9: 50568 | E9: TA-25-1187984 | F9: 81424 | G9: APERTURA | H9: CB CRECIMIENTO - NUEVO | I9: META | J9: PUERTO GAITAN | K9: BARRIO ALTOS DEL MANACACIAS PUERTO GAITAN | L9: WOMPI | M9: FO-25-1646763 | N9: 45908 | O9: 45940 | P9: EJECUTADO | Q9: 12-09 EN COMUNICACIÓN VIA WHATSAPP, SE HABLA CON LA SRA YINEHT SELENA BARRERA MURCIA SE VALIDA DIRECCIÓN OK, CANAL OK, DISPONIBILIDAD TOTAL, USUARIO Y CONTRASEÑA WOMPI NO LE HA LLEGADO, INDICA QUE EL CORREO QUE SE ENCUENTRA EN LA LISTA DE CHEQUEO ESTÁ ERRADO, SU CORREO Selenabm18@gmail.com // 22/09/2025 SE REALIZA LLAMADA AL NUMERO DE LA LISTA SE HABLA CON LA SEÑORA SELENA SOLICITA QUE LE CAMBIEN EL CORREO (Selenabm18@gmail.com), EL OTRO ESTA ERRADO 08-10 SE REALIZA LLAMADA AL CLIENTE, SE HABLA CON LA SRA YINEHT SELENA BARRERA MURCIA SE VALIDA DIRECCIÓN OK, CANAL OK, DISPONIBILIDAD TOTAL 10/10/2025 SE REALIZA INSTALACIÓN DE CORRESPONSAL, SE INSTALAN EQUIPOS CON PRUEBAS EXITOSAS, SE CAPACITA Y SE EVALÚA AL CLIENTE, SE INSTALA PUBLICIDAD COMPLETA, CB QUEDA OPERATIVO. USUARIO SOMOS BANCOLOMBIA ACTIVO. COMERCIO SIN AVISO PUBLICITARIO, SIN EMBARGO SI ES EL MISMO OBJETIVO COMERCIAL, LA DIRECCION COINCIDE Y LA CÁMARA DE COMERCIO TAMBIEN TIENE EL MISMO NOMBRE DE LISTA DE CHEQUEO. | R9: VISITA_TÉCNICA | S9: 254UMD4X8310 | T9: LEJANA | U9: TERRESTRE | V9: ROZO JIMENEZ EDGAR ARMANDO | W9: 1 | X9: =IF(T9="PRINCIPAL",'TARIFAS 2025'!$B$5,IF(T9="INTERMEDIA",'TARIFAS 2025'!$C$5,IF(T9="LEJANA",'TARIFAS 2025'!$D$5))) -> 598334 | Y9: =X9*W9 -> 598334
A10: MONTERIA | B10: =VLOOKUP(A10,'CENTROS DE COSTOS'!A:D,2,0) -> 0036-0001 | C10: =VLOOKUP(A10,'CENTROS DE COSTOS'!A:D,3,0) -> Wompi Costa | D10: 23001 | E10: TA-25-1187986 | F10: 81410 | G10: APERTURA | H10: CB CRECIMIENTO - NUEVO | I10: CORDOBA | J10: MONTERIA | K10: BARRIO CENTRO MONTERIA 61 | L10: WOMPI | M10: FO-25-1646765 | N10: 45908 | O10: 45939 | P10: EJECUTADO | Q10: 12-09 SE REALIZA LLAMADA AL CLIENTE, SE HABLA CON EL SR JAMIS JABID MARTINEZ ORTEGA SE VALIDA DIRECCIÓN OK, CANAL OK, DISPONIBILIDAD TOTAL, USUARIO Y CONTRASEÑA WOMPI NO LE HA LLEGADO-INSTALACIÓN SIN PROGRAMAR // 22/09/2025 SE REALIZA LLAMADA AL NUMERO DE LA LISTA SE HABLA CON EL SEÑOR JAMIS, SE LE CONFIRMA EL CORREO INDICA ESTAR BIEN, SE PREGUNTA POR CORREO DE WOMPI ME DICE QUE NO LE HA LLEGADO, HACE BUSQUEDA POR EL BUSCADOR Y ME SIGUE INDICANDO QUE NO LO TIENEN EN NINGUNA BANDEJA DE MENSAJES 08-10 SE REALIZA LLAMADA AL CLIENTE, SE HABLA CON LA SR JAMIS JABID MARTINEZ ORTEGA SE VALIDA DIRECCIÓN OK, CANAL OK, DISPONIBILIDAD TOTAL, YA TIENE CORREO CON CREDENCIALES 9/10/2025 SE REALIZA INSTALACIÓN DE CORRESPONSAL, SE INSTALAN EQUIPOS CON PRUEBAS EXITOSAS, SE CAPACITA Y SE EVALÚA AL CLIENTE, SE INSTALA PUBLICIDAD COMPLETA, CB QUEDA OPERATIVO. USUARIO SOMOS BANCOLOMBIA NO ACTIVO, SE CAPACITA CON EL DE PRUEBA | R10: VISITA_TÉCNICA | S10: 254UMD4X8492 | T10: PRINCIPAL | U10: TERRESTRE | V10: COGOLLO VERTEL EDER LUIS | W10: 1 | X10: =IF(T10="PRINCIPAL",'TARIFAS 2025'!$B$5,IF(T10="INTERMEDIA",'TARIFAS 2025'!$C$5,IF(T10="LEJANA",'TARIFAS 2025'!$D$5))) -> 367716 | Y10: =X10*W10 -> 367716
A11: BUCARAMANGA | B11: =VLOOKUP(A11,'CENTROS DE COSTOS'!A:D,2,0) -> 0036-0007 | C11: =VLOOKUP(A11,'CENTROS DE COSTOS'!A:D,3,0) -> Wompi Santander | D11: 68092 | E11: TA-25-1100984 | F11: 81369 | G11: APERTURA | H11: CB CRECIMIENTO - NUEVO | I11: SANTANDER | J11: BETULIA | K11: SAN BERNARDO BETULIA | L11: WOMPI | M11: FO-25-1554914 | N11: 45908 | O11: 45940 | P11: EJECUTADO | Q11: 12-09 EN COMUNICACIÓN VIA WHATSAPP, SE HABLA CON LA SRA PAULA ANDREA GARCIA CRUZSE VALIDA DIRECCIÓN OK, CANAL OK, DISPONIBILIDAD TOTAL, USUARIO Y CONTRASEÑA WOMPI OK, LLAMAR EL DÍA LA INSTALACIÓN PARA CONFIRMAR VISITA, AVISO EXTERIOR ALTURA APROX 2.5 METROS 17/09/2025 SE LLEGA AL SITIO Y SE REALIZA EL PROCESO DE IDENTIFICACIÓN. SE ACCEDE CORRECTAMENTE AL CORREO ELECTRÓNICO DEL USUARIO. SE GENERA EL LINK PARA LA ACTIVACIÓN DEL CORRESPONSAL. AL MOMENTO DE INGRESAR AL ENLACE, LA APLICACIÓN NO PERMITE MODIFICAR NI DIGITAR LOS SIGUIENTES CAMPOS: NOMBRE DE USUARIO, CORREO ELECTRÓNICO, WHATSAPP. ACCIONES REALIZADAS: SE EJECUTA BORRADO DE CACHÉ DE LA APLICACIÓN WOMPI. SE REALIZA LA ACTUALIZACIÓN DE LA APLICACIÓN A LA ÚLTIMA VERSIÓN DISPONIBLE. SE LOGRA EL CAMBIO DE CONTRASEÑA CORRECTAMENTE. SIN EMBARGO, AL INTENTAR COMPLETAR LA ACTIVACIÓN, LA APP MUESTRA EL SIGUIENTE MENSAJE DE ERROR: "¡UPS! ALGO SALIÓ MAL". EL PROCESO NO SE PUEDE COMPLETAR DEBIDO A UN POSIBLE FALLO EN LA PLATAFORMA O CONFLICTO CON LA APP, PESE A QUE LOS PASOS ANTERIORES SE EJECUTARON CORRECTAMENTE. ESCALAR EL CASO AL SOPORTE TÉCNICO DE WOMPI PARA SU REVISIÓN Y SOLUCIÓN. 08-10 SE REALIZA LLAMADA AL CLIENTE, SE HABLA CON LA SRA PAULA ANDREA GARCIA CRUZ ORTEGA SE VALIDA DIRECCIÓN OK, CANAL OK, DISPONIBILIDAD TOTAL, YA TIENE CORREO CON CREDENCIALES 09-10 SE COMUNICA CON LA SEÑORITA CON LA SEÑORITA PAULA AL NÚMERO DE TELÉFONO 3138266161 , SE CONFIRMA QUE LA USUARIA CUENTA CON LAS CREDENCIALES WOMPI, SE VALIDA EN OFICINA CON COORDINADOR Y SI DEJA INGRESAR, SE PROCEDE A REALIZAR LA APERTURA EN BETULIA 10-10 SE REALIZA INSTALACIÓN DE CORRESPONSAL, SE INSTALAN EQUIPOS CON PRUEBAS EXITOSAS, SE CAPACITA Y SE EVALÚA AL CLIENTE, SE INSTALA PUBLICIDAD COMPLETA, CB QUEDA OPERATIVO. USUARIO SOMOS BANCOLOMBIA ACTIVO | R11: VISITA_TÉCNICA | S11: 254MMD4W8945 | T11: LEJANA | U11: TERRESTRE | V11: HERRERA LUQUE SAUL JAVIER | W11: 1 | X11: =IF(T11="PRINCIPAL",'TARIFAS 2025'!$B$5,IF(T11="INTERMEDIA",'TARIFAS 2025'!$C$5,IF(T11="LEJANA",'TARIFAS 2025'!$D$5))) -> 598334 | Y11: =X11*W11 -> 598334
A12: TUNJA | B12: =VLOOKUP(A12,'CENTROS DE COSTOS'!A:D,2,0) -> 0036-0007 | C12: =VLOOKUP(A12,'CENTROS DE COSTOS'!A:D,3,0) -> Wompi Santander | D12: 15001 | E12: TA-25-1187992 | F12: 81446 | G12: APERTURA | H12: CB CRECIMIENTO - NUEVO | I12: BOYACA | J12: TUNJA | K12: BARRIO SAN CARLOS TUNJA 3 | L12: WOMPI | M12: FO-25-1646768 | N12: 45908 | O12: 45961 | P12: EJECUTADO/CANCELADO | Q12: 12-09 SE REALIZA LLAMADA AL CLIENTE, SE HABLA CON LA SRA JENNY ANGELICA MORENO CALDAS SE VALIDA DIRECCIÓN OK, CANAL OK, DISPONIBILIDAD TOTAL, USUARIO Y CONTRASEÑA WOMPI NO LE HA LLEGADO-INSTALACIÓN SIN PROGRAMAR 22-09 SE REALIZA LLAMADA AL CLIENTE, SE HABLA CON LA SRA JENNY ANGELICA MORENO CALDAS LA CUAL INDICA EL CORREO CORRECTO ES angelicamoreno83@hotmail.com NO TIENE ACCESO AL OTRO CORREO 08-10 SE REALIZA LLAMADA AL CLIENTE, SE HABLA CON LA SRA JENNY ANGELICA MORENO CALDAS SE VALIDA DIRECCIÓN OK, CANAL OK, DISPONIBILIDAD TOTAL, CORREO ESTA ERRADO 09-10 RESUMEN DEL CASO: CLIENTE INFORMA QUE EL CORREO DE LA ACTIVIDAD DEBE SER ANGELICAMORENO83@HOTMAIL.COM, YA QUE EL OTRO CORREO NO LE SIRVE. ACTUALIZAR CORREO A ANGELICAMORENO83@HOTMAIL.COM SERIAL: 254MMD4W7987 TICKET N° (471147) | 28/10/2025 EN NUEVA COMUNICACIÓN CON LA USUARIA INDICA QUE YA TIENE EL CORREO POR PARTE DE WOMPI, NO IDNICA ALTURA DEL AVISO | 31/10/2025 VISITAMOS EL SITIO Y VERIFICAMOS QUE LA DIRECCIÓN REGISTRADA EN LA ORDEN CORRESPONDE A CL 6 SUR #7–09, SAN CARLOS, LA MISMA QUE FIGURA EN LA CÁMARA DE COMERCIO. SIN EMBARGO, AL VALIDAR LA NOMENCLATURA DIRECTAMENTE EN EL SITIO, SE EVIDENCIA QUE LA DIRECCIÓN CORRECTA ES CL 6 SUR #9–07. SE CANCELA ACTIVIDAD POR DIRECCION ERRADA | R12: VISITA_TÉCNICA | S12: 254MMD4W7987 | T12: PRINCIPAL | U12: TERRESTRE | V12: HERRERA GARZON JEYSON STEVENT | W12: 1 | X12: =IF(T12="PRINCIPAL",'TARIFAS 2025'!$B$5,IF(T12="INTERMEDIA",'TARIFAS 2025'!$C$5,IF(T12="LEJANA",'TARIFAS 2025'!$D$5))) -> 367716 | Y12: =X12*W12 -> 367716
A13: BOGOTA | B13: =VLOOKUP(A13,'CENTROS DE COSTOS'!A:D,2,0) -> 0036-0004 | C13: =VLOOKUP(A13,'CENTROS DE COSTOS'!A:D,3,0) -> Wompi Centro | D13: 11001 | E13: TA-25-1187994 | F13: 81373 | G13: APERTURA | H13: CB CRECIMIENTO - NUEVO | I13: CUNDINAMARCA | J13: BOGOTA | K13: BARRIO NUEVA MARSELLA BOGOTA 3 | L13: WOMPI | M13: FO-25-1646770 | N13: 45908 | O13: 45939 | P13: EJECUTADO | Q13: 12-09 SE REALIZA LLAMADA AL CLIENTE, SE HABLA CON LA SRA BETTY YAJAIRA GRAZZIANI HERNANDEZ SE VALIDA DIRECCIÓN OK, CANAL OK, DISPONIBILIDAD TOTAL, USUARIO Y CONTRASEÑA WOMPI NO LE HA LLEGADO-INSTALACIÓN SIN PROGRAMAR 22-09 SE REALIZA LLAMADA AL CLIENTE, SE HABLA CON LA SRA BETTY YAJAIRA GRAZZIANI HERNANDEZ LA CUAL INDICA QUE AUN NO TIENE EL CORREO DE PARTE DE WOMPI 08-10 SE REALIZA LLAMADA AL CLIENTE, SE HABLA CON LA SRA BETTY YAJAIRA GRAZZIANI HERNANDEZ SE VALIDA DIRECCIÓN OK, CANAL OK, DISPONIBILIDAD TOTAL 9/10/2025 SE REALIZA INSTALACIÓN DE CORRESPONSAL, SE INSTALAN EQUIPOS CON PRUEBAS EXITOSAS, SE CAPACITA Y SE EVALÚA AL CLIENTE, SE INSTALA PUBLICIDAD COMPLETA, CB QUEDA OPERATIVO. USUARIO SOMOS BANCOLOMBIA ACTIVO. COMERCIO SIN AVISO COMERCIAL | R13: VISITA_TÉCNICA | S13: 254UMD4X6466 | T13: PRINCIPAL | U13: TERRESTRE | V13: HERNANDEZ NARANJO OSCAR EDUARDO | W13: 1 | X13: =IF(T13="PRINCIPAL",'TARIFAS 2025'!$B$5,IF(T13="INTERMEDIA",'TARIFAS 2025'!$C$5,IF(T13="LEJANA",'TARIFAS 2025'!$D$5))) -> 367716 | Y13: =X13*W13 -> 367716
... A151: TUNJA | B151: =VLOOKUP(A151,'CENTROS DE COSTOS'!A:D,2,0) -> 0036-0007 | C151: =VLOOKUP(A151,'CENTROS DE COSTOS'!A:D,3,0) -> Wompi Santander | D151: 15599 | E151: TA-25-1246673 | F151: 81595 | G151: APERTURA | H151: CB CRECIMIENTO - OTRAS LISTAS | I151: BOYACA | J151: RAMIRIQUI | K151: BARRIO CENTRO RAMIRIQUI 3 | L151: WOMPI | M151: FO-25-1748452 | N151: 45952 | O151: 45960 | P151: EJECUTADO | Q151: 23/10/2025 SE ESTABLECE COMUNICACIÓN CON FARIDES RASEDA PÉREZ VIA WPP, EL CUAL INDICA QUE EL CORREO ESTA BIEN PERO NO LE HA LLEGADO CORREO PARA COMPLETAR REGISTRO POR PARTE DE WOMPI // 28-10 SE REALIZA CONTACTO POR WHATSAPP AL CLIENTE, SE HABLA CON EL SR FARIDES RASEDA PÉREZ SE VALIDA DIRECCIÓN OK, CANAL OK, DISPONIBILIDAD TOTAL, USUARIO Y CONTRASEÑA WOMPI OK, LLAMAR EL DÍA LA INSTALACIÓN PARA CONFIRMAR VISITA, AVISO EXTERIOR ALTURA APROX 2 METROS | 30/10/2025 SE REALIZA INSTALACIÓN DE CORRESPONSAL, SE INSTALAN EQUIPOS CON PRUEBAS EXITOSAS, SE CAPACITA Y SE EVALÚA AL CLIENTE, SE INSTALA PUBLICIDAD COMPLETA, CB QUEDA OPERATIVO. USUARIO SOMOS BANCOLOMBIA ACTIVO | R151: VISITA_TÉCNICA | S151: 254MMD4W8952 | T151: INTERMEDIA | U151: TERRESTRE | V151: RODRIGUEZ MURCIA YERSON IVAN | W151: 1 | X151: =IF(T151="PRINCIPAL",'TARIFAS 2025'!$B$5,IF(T151="INTERMEDIA",'TARIFAS 2025'!$C$5,IF(T151="LEJANA",'TARIFAS 2025'!$D$5))) -> 488953 | Y151: =X151*W151 -> 488953
Y152: =SUM(Y2:Y151) -> 74829004

Sheet INCIDENTES
A1: CIUDAD SEDE | B1: CENTRO_COSTO | C1: DESCRIPCION CENTRO DE COSTOS | D1: CÓDIGO DANE | E1: TA/CODIGO ACTIVIDAD | F1: CODIGO CB | G1: ACTIVIDAD | H1: DEPARTAMENTO | I1: CIUDAD | J1: NOMBRE DEL CB | K1: RED | L1: FO | M1: FECHA ASIGNACION A LINEA COMUNICACIONES | N1: FECHA DEL CIERRE DEL TICKET (DD/MM/AAAA) | O1: SOLICITUD | P1: GRUPO_FALLA | Q1: CATEGORÍA | R1: FALLA | S1: OBSERVACION | T1: FORMA DE ATENCIÓN | U1: INVENTARIO ACTUAL DE ROLLOS | V1: TIPOLOGIA | W1: TIPO DE TRAYECTO | X1: NOMBRE DEL TECNICO | Y1: DIAS DE ACTIVIDAD | Z1: VALOR DIAS ACTIVIDAD | AA1: VALOR TOTAL
A2: MEDELLIN | B2: =VLOOKUP(A2,'CENTROS DE COSTOS'!A:D,2,0) -> 0036-0005 | C2: =VLOOKUP(A2,'CENTROS DE COSTOS'!A:D,3,0) -> Wompi Noroccidente | D2: 5088 | E2: 2777957 | F2: 21427 | G2: INCIDENTE | H2: ANTIOQUIA | I2: BELLO | J2: JHOMAR | K2: WOMPI | L2: FO-25-1573859 | FO-25-1568169 | M2: 45923.333 | N2: 45931.358 | O2: INCIDENTE | P2: LECTURA | Q2: NO LEE NINGUNA FACTURA | R2: SUCIEDAD EN LA CAMARA | S2: 23/09/2025 SE EVIDENCIA QUE EL EQUIPO NO LEE FACTURAS EPM NI DEL FONDO NACIONAL DEL AHORRO, OTRAS SI, DATÁFONO ACTUALIZADO, SE ESCALA A WOMPI CON TICKET 467172. 01/10/2025 ELECTRÓNICO. JESUS DAVID JUVINAO PEREZ (WOMPI COLOMBIA) 30 SEPT 2025, 8:58 A. M. GMT-5 HOLA BROLIN, ¿CÓMO ESTÁS? QUIERO COMENTARTE QUE JUNTO CON EL EQUIPO HEMOS REVISADO EN DETALLE LA SITUACIÓN QUE NOS REPORTASTE Y, TRAS EL ANÁLISIS, IDENTIFICAMOS EL PROBLEMA. ACTUALMENTE YA SE ESTÁ TRABAJANDO EN UNA SOLUCIÓN DEFINITIVA, NO SOLO PARA ESTE CASO PUNTUAL, SINO TAMBIÉN PARA OTROS INCONVENIENTES RELACIONADOS CON EL FUNCIONAMIENTO DEL LECTOR DE CÓDIGOS DE BARRAS. MIENTRAS TANTO, COMO MEDIDA TEMPORAL Y RÁPIDA, LES RECOMENDAMOS REINICIAR EL DATÁFONO ANTES DE REALIZAR CADA LECTURA. ESTO PERMITE LIBERAR MEMORIA Y EVITAR QUE SE GENERE RUIDO EN LA CAPTURA DE LA IMAGEN, LO CUAL PUEDE PROVOCAR QUE EL ESCANEO SE VEA BORROSO O NO SE LEA CORRECTAMENTE. TAMBIÉN ES IMPORTANTE ASEGURARSE DE CONTAR CON UNA BUENA ILUMINACIÓN AL MOMENTO DE ES | T2: VISITA_TÉCNICA | U2: 40 | V2: PRINCIPAL | W2: TERRESTRE | X2: CARDONA MOLINA BROLIN STIVEN | Y2: 2 | Z2: =IF(T2="SOPORTE_TELEFÓNICO",'TARIFAS 2025'!$B$14,IF(V2="PRINCIPAL",'TARIFAS 2025'!$B$8,IF(V2="INTERMEDIA",'TARIFAS 2025'!$C$8,IF(V2="LEJANA",'TARIFAS 2025'!$D$8)))) -> 51282 | AA2: =Z2*Y2 -> 102564
A3: BUCARAMANGA | B3: =VLOOKUP(A3,'CENTROS DE COSTOS'!A:D,2,0) -> 0036-0007 | C3: =VLOOKUP(A3,'CENTROS DE COSTOS'!A:D,3,0) -> Wompi Santander | D3: 68001 | E3: 2814842 | F3: 74106 | G3: INCIDENTE | H3: SANTANDER | I3: BUCARAMANGA | J3: BARRIO REAL DE MINAS BUCARAMANGA 3 | K3: WOMPI | L3: FO-25-1604069 | M3: 45930.453 | N3: 45931.36 | O3: INCIDENTE | P3: CREDENCIALES DE ACCESO (USUARIO/CONTRASEÑA) | Q3: INGRESO DE CREDENCIALES ERRADAS | R3: EL USUARIO NO RECUERDA LA CONTRASEÑA O EL USUARIO | S3: 01/10/2025 EN COMUNICACIÓN TELEFÓNICA AL NÚMERO 3187878933 SE ESTABLECE COMUNICACIÓN CON LA SEÑORA MILENA JIMÉNEZ LO CUAL NOS INDICA QUE NO ES NECESARIO REALIZAR LA VISITA TÉCNICA DEBIDO A QUE YA ESTÁ FUNCIONANDO CORRECTAMENTE EL DATAFONO INDICA QUE LLAMO A LA LÍNEA PARA CANCELAR LA VISITA TÉCNICA | T3: SOPORTE_TELEFÓNICO | U3: 32 | V3: PRINCIPAL | W3: TERRESTRE | X3: MARIÑO PABON JORGE ENRIQUE | Y3: 1 | Z3: =IF(T3="SOPORTE_TELEFÓNICO",'TARIFAS 2025'!$B$14,IF(V3="PRINCIPAL",'TARIFAS 2025'!$B$8,IF(V3="INTERMEDIA",'TARIFAS 2025'!$C$8,IF(V3="LEJANA",'TARIFAS 2025'!$D$8)))) -> 22000 | AA3: =Z3*Y3 -> 22000
A4: PEREIRA | B4: =VLOOKUP(A4,'CENTROS DE COSTOS'!A:D,2,0) -> 0036-0002 | C4: =VLOOKUP(A4,'CENTROS DE COSTOS'!A:D,3,0) -> Wompi Eje Cafetero | D4: 66001 | E4: 2801979 | F4: 64295 | G4: INCIDENTE | H4: RISARALDA | I4: PEREIRA | J4: DISTRIBUIDORA SAN MIGUEL O | K4: WOMPI | L4: FO-25-1593834 | FO-25-1591064 | M4: 45927.375 | N4: 45931.365 | O4: INCIDENTE | P4: NAVEGACION LENTA | Q4: USUARIO NO PUEDE NAVEGAR ENTRE PANTALLAS O LA APP NO ABRE SE QUEDA CARGANDO | R4: CACHE | S4: 27/09/2025 SE LLEGA AL PUNTO, SE REPROGRAMA ACTIVIDAD YA QUE TOCA ESCALARLO CON WOMPI , SE EVIDENCIA QUE EL EQUIPO TRABAJA LENTO YA SEA CONECTADO CON EL WIFI DEL PUNTO O CON LA RED COMPARTIDA DEL TELÉFONO PERSONAL, SE REALIZA TRX DEPÓSITO Y EN SOMOS SALE COMO SI SE HUBIERA REALIZADO DOS VECES LA MISMA TRANSACCIÓN, SE PRUEBA UN RETIRO DE NEQUI Y EN EL DATÁFONO SALE RECHAZO, PERO AL REVISAR EN SOMOS SALE APROBADO. 01/10/2025 EN COMUNICACIÓN CON LA SR SE LE INDICA QUE WOMPI DICE QUE EL PROBLEMA NO ES DEL EQUIPO, NI DEL CANAL DE INTERNET DEL COMERCIO, EL PROBLEMA ES DEL APLICATIVO DE WOMPI Y QUE SE DEBE ESPERAR A LA ACTUALIZACIÓN DE LA APP | T4: VISITA_TÉCNICA | U4: 40 | V4: PRINCIPAL | W4: TERRESTRE | X4: FRANCO CAÑAVERAL YAMID RAUL | Y4: 2 | Z4: =IF(T4="SOPORTE_TELEFÓNICO",'TARIFAS 2025'!$B$14,IF(V4="PRINCIPAL",'TARIFAS 2025'!$B$8,IF(V4="INTERMEDIA",'TARIFAS 2025'!$C$8,IF(V4="LEJANA",'TARIFAS 2025'!$D$8)))) -> 51282 | AA4: =Z4*Y4 -> 102564
A5: CALI | B5: =VLOOKUP(A5,'CENTROS DE COSTOS'!A:D,2,0) -> 0036-0003 | C5: =VLOOKUP(A5,'CENTROS DE COSTOS'!A:D,3,0) -> Wompi Suroccidente | D5: 76001 | E5: 2815169 | F5: 78269 | G5: INCIDENTE | H5: VALLE DEL CAUCA | I5: CALI | J5: H.J IMPRESORES | K5: WOMPI | L5: FO-25-1604472 | M5: 45930.482 | N5: 45931.397 | O5: INCIDENTE | P5: CONEXIÓN | Q5: CONEXIÓN DEFICIENTE WIFI | R5: WIFI | S5: 01/10/2025 SE LLEGA AL COMERCIO CLIENTE ME MUESTRA VIDEOS DE QUE EL EQUIPO DURO 5 MINUTOS EN SACAR TIRILLA SE REVISA EL EQUIPO Y SE HACEN PRUEBAS TIRILLA SALE A LOS 5 SEGUNDO SE LE EXPLICA AL CLIENTE QUE PODRÍA SER QUE EN ESE MOMENTO EL INTERNET ESTABA LENTO QUEDA FUNCIONANDO CORRECTAMENTE | T5: VISITA_TÉCNICA | U5: 32 | V5: PRINCIPAL | W5: TERRESTRE | X5: CUERO RUIZ JHONNY | Y5: 1 | Z5: =IF(T5="SOPORTE_TELEFÓNICO",'TARIFAS 2025'!$B$14,IF(V5="PRINCIPAL",'TARIFAS 2025'!$B$8,IF(V5="INTERMEDIA",'TARIFAS 2025'!$C$8,IF(V5="LEJANA",'TARIFAS 2025'!$D$8)))) -> 51282 | AA5: =Z5*Y5 -> 51282
A6: VILLAVICENCIO | B6: =VLOOKUP(A6,'CENTROS DE COSTOS'!A:D,2,0) -> 0036-0006 | C6: =VLOOKUP(A6,'CENTROS DE COSTOS'!A:D,3,0) -> Wompi Oriente | D6: 50001 | E6: 2814599 | F6: 58407 | G6: INCIDENTE | H6: META | I6: VILLAVICENCIO | J6: MECELL | K6: WOMPI | L6: FO-25-1604081 | M6: 45930.446 | N6: 45931.401 | O6: INCIDENTE | P6: CONEXIÓN | Q6: CONEXIÓN DEFICIENTE WIFI | R6: WIFI | S6: 01/10/2025 SE REALIZA VISITA A COMERCIO SE REALIZA ACTUALIZACIÓN DE SISTEMA OPERATIVO SE REALIZA BORRADO DE CACHÉ SE LE BRINDA ASESORÍA TÉCNICA A CLIENTE SOBRE EL CORRECTO USO DEL DATÁFONO | T6: VISITA_TÉCNICA | U6: 64 | V6: PRINCIPAL | W6: TERRESTRE | X6: CASTRILLON URREA LONDIER LEANDRO | Y6: 1 | Z6: =IF(T6="SOPORTE_TELEFÓNICO",'TARIFAS 2025'!$B$14,IF(V6="PRINCIPAL",'TARIFAS 2025'!$B$8,IF(V6="INTERMEDIA",'TARIFAS 2025'!$C$8,IF(V6="LEJANA",'TARIFAS 2025'!$D$8)))) -> 51282 | AA6: =Z6*Y6 -> 51282
A7: NEIVA | B7: =VLOOKUP(A7,'CENTROS DE COSTOS'!A:D,2,0) -> 0036-0006 | C7: =VLOOKUP(A7,'CENTROS DE COSTOS'!A:D,3,0) -> Wompi Oriente | D7: 41001 | E7: TA-25-1160168 | F7: 62389 | G7: INCIDENTE | H7: HUILA | I7: NEIVA | J7: FOTOCOPIAS HELIO'S | K7: WOMPI | L7: FO-25-1602438 | M7: 45925.674 | N7: 45931.422 | O7: INCIDENTE | P7: SOFTWARE | Q7: APP ELIMINADA | R7: APP ELIMINADA POR EL CB | S7: 01/10/2025 SE REALIZA CAMBIO DE QUIPO POR AUTORIZACION DE WOMPI | T7: VISITA_TÉCNICA | U7: 24 | V7: PRINCIPAL | W7: TERRESTRE | X7: DIAZ VARGAS JONATHAN MIGUEL | Y7: 1 | Z7: =IF(T7="SOPORTE_TELEFÓNICO",'TARIFAS 2025'!$B$14,IF(V7="PRINCIPAL",'TARIFAS 2025'!$B$8,IF(V7="INTERMEDIA",'TARIFAS 2025'!$C$8,IF(V7="LEJANA",'TARIFAS 2025'!$D$8)))) -> 51282 | AA7: =Z7*Y7 -> 51282
A8: CUCUTA | B8: =VLOOKUP(A8,'CENTROS DE COSTOS'!A:D,2,0) -> 0036-0007 | C8: =VLOOKUP(A8,'CENTROS DE COSTOS'!A:D,3,0) -> Wompi Santander | D8: 54001 | E8: 2798806 | F8: 67824 | G8: INCIDENTE | H8: NORTE DE SANTANDER | I8: CUCUTA | J8: TECNICELL CASI TODO | K8: WOMPI | L8: FO-25-1591907 | FO-25-1588202 | M8: 45926.431 | N8: 45931.448 | O8: INCIDENTE | P8: IMPRESIÓN | Q8: DAÑO FÍSICO DE LA IMPRESORA | R8: MALA MANIPULACIÓN DEL DATAFONO | S8: 26/09/2025 INCIDENTE CB: 67824 RESUMEN DEL CASO: REPORTE TÉCNICO RESUMEN DE ACTIVIDAD: SE REALIZÓ ACTUALIZACIÓN DE VERSIÓN DEL SISTEMA OK SE PROCEDIÓ CON EL BORRADO DE CACHÉ DEL DISPOSITIVO. SE CONECTÓ EL EQUIPO A DATOS MÓVILES. SE EFECTUARON PRUEBAS FUNCIONALES EXITOSAS (CONECTIVIDAD, MENÚS, OPERACIONES, ETC.). INCIDENCIA DETECTADA: AL MOMENTO DE ENVIAR LA IMPRESIÓN DEL RECIBO, EL EQUIPO SE REINICIÓ INESPERADAMENTE. SE REALIZARON PRUEBAS CON VARIOS ROLLOS DE PAPEL TÉRMICO. CLIENTE INDICA QUE EL EQUIPO DEJÓ DE IMPRIMIR COMPLETAMENTE. AL INTENTAR IMPRIMIR NUEVAMENTE, LA IMPRESIÓN SALE EN BLANCO (ROLLO AVANZA PERO NO IMPRIME CONTENIDO). ? GESTIÓN REALIZADA: SE BRINDÓ ASISTENCIA TELEFÓNICA AL CLIENTE PARA PRUEBAS Y VERIFICACIÓN DE FALLAS. SIN EXITO SE REALIZÓ VISITA TÉCNICA PRESENCIAL EN ESTA GESTIÓN. . SERIAL: 254MMD4W8169 TICKET 468198 01/10/2025 SE REALIZA CAMBIO DE DATAFONO POR DAÑO EN LA IMPRESORA, PRUEBAS OK | T8: VISITA_TÉCNICA | U8: 32 | V8: PRINCIPAL | W8: TERRESTRE | X8: DURAN ACOSTA FRANK YONNY | Y8: 2 | Z8: =IF(T8="SOPORTE_TELEFÓNICO",'TARIFAS 2025'!$B$14,IF(V8="PRINCIPAL",'TARIFAS 2025'!$B$8,IF(V8="INTERMEDIA",'TARIFAS 2025'!$C$8,IF(V8="LEJANA",'TARIFAS 2025'!$D$8)))) -> 51282 | AA8: =Z8*Y8 -> 102564
A9: MEDELLIN | B9: =VLOOKUP(A9,'CENTROS DE COSTOS'!A:D,2,0) -> 0036-0005 | C9: =VLOOKUP(A9,'CENTROS DE COSTOS'!A:D,3,0) -> Wompi Noroccidente | D9: 5001 | E9: 2818691 | F9: 27011 | G9: INCIDENTE | H9: ANTIOQUIA | I9: MEDELLÍN | J9: MERCADO UNION 2 | K9: WOMPI | L9: FO-25-1608433 | M9: 45931.333 | N9: 45931.453 | O9: INCIDENTE | P9: NAVEGACION LENTA | Q9: USUARIO NO PUEDE NAVEGAR ENTRE PANTALLAS O LA APP NO ABRE SE QUEDA CARGANDO | R9: CACHE | S9: 01/10/2025 ANTES EL DATÁFONO ESTABA CON EL SISTEMA LENTO Y NO DEJABA INGRESAR EL USUARIO, APARTIR DE HOY AUNQUE SIGUE LENTO FUNCIONA CORRECTAMENTE. | T9: VISITA_TÉCNICA | U9: 32 | V9: PRINCIPAL | W9: TERRESTRE | X9: HENAO JARAMILLO JUAN JOSE | Y9: 1 | Z9: =IF(T9="SOPORTE_TELEFÓNICO",'TARIFAS 2025'!$B$14,IF(V9="PRINCIPAL",'TARIFAS 2025'!$B$8,IF(V9="INTERMEDIA",'TARIFAS 2025'!$C$8,IF(V9="LEJANA",'TARIFAS 2025'!$D$8)))) -> 51282 | AA9: =Z9*Y9 -> 51282
A10: MEDELLIN | B10: =VLOOKUP(A10,'CENTROS DE COSTOS'!A:D,2,0) -> 0036-0005 | C10: =VLOOKUP(A10,'CENTROS DE COSTOS'!A:D,3,0) -> Wompi Noroccidente | D10: 5088 | E10: 2818710 | F10: 74187 | G10: INCIDENTE | H10: ANTIOQUIA | I10: BELLO | J10: DOCTORFARMA NORTE | K10: WOMPI | L10: FO-25-1608456 | M10: 45931.333 | N10: 45931.456 | O10: INCIDENTE | P10: NAVEGACION LENTA | Q10: USUARIO NO PUEDE NAVEGAR ENTRE PANTALLAS O LA APP NO ABRE SE QUEDA CARGANDO | R10: CACHE | S10: 01/10/2025 SE REALIZA ACTUALIZACIÓN Y BORRADO DE CACHÉ YA QUE INFORMABA QUE NO LE DABA AYER EL ACCESO A LA APLICACIÓN, ADICIONAL EN OCASIONES BUSCA NÚMERO DE CONVENIO DE EPM Y NO SALE, PERO TODO YA ESTÁ FUNCIONANDO CORRECTAMENTE. | T10: VISITA_TÉCNICA | U10: 48 | V10: PRINCIPAL | W10: TERRESTRE | X10: RAMIREZ TABARES JUAN DIEGO | Y10: 1 | Z10: =IF(T10="SOPORTE_TELEFÓNICO",'TARIFAS 2025'!$B$14,IF(V10="PRINCIPAL",'TARIFAS 2025'!$B$8,IF(V10="INTERMEDIA",'TARIFAS 2025'!$C$8,IF(V10="LEJANA",'TARIFAS 2025'!$D$8)))) -> 51282 | AA10: =Z10*Y10 -> 51282
A11: CALI | B11: =VLOOKUP(A11,'CENTROS DE COSTOS'!A:D,2,0) -> 0036-0003 | C11: =VLOOKUP(A11,'CENTROS DE COSTOS'!A:D,3,0) -> Wompi Suroccidente | D11: 76001 | E11: 2817239 | F11: 64018 | G11: INCIDENTE | H11: VALLE DEL CAUCA | I11: CALI | J11: ESTILO LIBRE PELUQUERIA UNISEX | K11: WOMPI | L11: FO-25-1606542 | M11: 45930.644 | N11: 45931.458 | O11: INCIDENTE | P11: IMPRESIÓN | Q11: ROLLO MAL PUESTO | R11: MALA MANIPULACIÓN DEL DATAFONO | S11: 01/10/2025 SE LLEGA AL COMERCIO CLIENTE INDICA QUE TIENE QUE CORTAR EL RECIBO CON TIJERAS YA QUE EL BAUCHER QUEDA ATASCADO SE LE EXPLICA LA MANERA CORRECTA DE CORTAR LA TIRILLA HACE PRUEVAS Y QUEDA OK SE LE EXPLICA COMO SE DEBE DE PONER EL EQUIPO PARA QUE LEA LOS CODIGOS DE BARRAS HACE PRUEBAS QUEDA OK EL DATAFONO QUEDA FUNCIONANDO CORRECTAMENTE | T11: VISITA_TÉCNICA | U11: 24 | V11: PRINCIPAL | W11: TERRESTRE | X11: CUERO RUIZ JHONNY | Y11: 1 | Z11: =IF(T11="SOPORTE_TELEFÓNICO",'TARIFAS 2025'!$B$14,IF(V11="PRINCIPAL",'TARIFAS 2025'!$B$8,IF(V11="INTERMEDIA",'TARIFAS 2025'!$C$8,IF(V11="LEJANA",'TARIFAS 2025'!$D$8)))) -> 51282 | AA11: =Z11*Y11 -> 51282
A12: BOGOTA | B12: =VLOOKUP(A12,'CENTROS DE COSTOS'!A:D,2,0) -> 0036-0004 | C12: =VLOOKUP(A12,'CENTROS DE COSTOS'!A:D,3,0) -> Wompi Centro | D12: 11001 | E12: 2817195 | F12: 59897 | G12: INCIDENTE | H12: CUNDINAMARCA | I12: BOGOTÁ | J12: DROGUERIA SU SALUD PRIMERO | K12: WOMPI | L12: FO-25-1606282 | M12: 45930.644 | N12: 45931.461 | O12: INCIDENTE | P12: CONEXIÓN | Q12: CONEXIÓN DEFICIENTE WIFI | R12: FALLAS EN CANAL DE COMUNICACIÓN DEL CLIENTE (INTERNET) | S12: 01/10/2025 SE LLEGA COMERCIO SE REALIZAN VALIDACIONES DE WIFI DEL CLIENTE SE LE INFLA QUE EL MODNE ESTÁ A MUCHA DISTANCIA ADICIONAL ESTÁ CON MUCHOS OBSTÁCULOS METÁLICOS DEL COMERCIO SE LE REALIZAN PRUEBAS CERCA AL MÓDEM OK Y CON LOS DATOS MOVILES OK SE LE REALIZA ACTUALIZACIÓN VERSIÓN Y PRUEBAS OK | T12: VISITA_TÉCNICA | U12: 32 | V12: PRINCIPAL | W12: TERRESTRE | X12: GOMEZ VEGA DAVID SNEYDER | Y12: 1 | Z12: =IF(T12="SOPORTE_TELEFÓNICO",'TARIFAS 2025'!$B$14,IF(V12="PRINCIPAL",'TARIFAS 2025'!$B$8,IF(V12="INTERMEDIA",'TARIFAS 2025'!$C$8,IF(V12="LEJANA",'TARIFAS 2025'!$D$8)))) -> 51282 | AA12: =Z12*Y12 -> 51282
A13: BARRANQUILLA | B13: =VLOOKUP(A13,'CENTROS DE COSTOS'!A:D,2,0) -> 0036-0001 | C13: =VLOOKUP(A13,'CENTROS DE COSTOS'!A:D,3,0) -> Wompi Costa | D13: 8001 | E13: 2816012 | F13: 60460 | G13: INCIDENTE | H13: ATLANTICO | I13: BARRANQUILLA | J13: PORTAL DE CEVILLAR | K13: WOMPI | L13: FO-25-1605140 | M13: 45930.547 | N13: 45931.465 | O13: INCIDENTE | P13: CONEXIÓN | Q13: CONEXIÓN DEFICIENTE WIFI | R13: WIFI | S13: 01/10/2025 SE REALIZA VISITA AL COMERCIO SE ENCUENTRA DATÁFONO CON PROBLEMAS DE LENTITUD POR INTERNET VERIFICO QUE EL MÓDEM SE ENCUENTRA RETIRADO DEL DATAFONO COMO A 5 METROS SE REALIZA UNA PRUEBA CERCA AL MÓDEM Y SALE PERFECTAMENTE SE LE DICE AL CLIENTE SI PUEDE RODAR EL MÓDEM LO CUAL ME MANIFIESTA QUE VA LLEMAR A SU PRESTADOR DE SERVICIO SE REALIZAN PRUEBAS Y EL CB QUEDA OPERATIVO | T13: VISITA_TÉCNICA | U13: 56 | V13: PRINCIPAL | W13: TERRESTRE | X13: PEÑALOZA GUTIERREZ RAFAEL GUSTAVO | Y13: 1 | Z13: =IF(T13="SOPORTE_TELEFÓNICO",'TARIFAS 2025'!$B$14,IF(V13="PRINCIPAL",'TARIFAS 2025'!$B$8,IF(V13="INTERMEDIA",'TARIFAS 2025'!$C$8,IF(V13="LEJANA",'TARIFAS 2025'!$D$8)))) -> 51282 | AA13: =Z13*Y13 -> 51282
A14: TUNJA | B14: =VLOOKUP(A14,'CENTROS DE COSTOS'!A:D,2,0) -> 0036-0007 | C14: =VLOOKUP(A14,'CENTROS DE COSTOS'!A:D,3,0) -> Wompi Santander | D14: 15001 | E14: 2760623 | F14: 69853 | G14: INCIDENTE | H14: BOYACA | I14: TUNJA | J14: SUPERMERCADO LOS HÉROES | K14: WOMPI | L14: FO-25-1553187 | FO-25-1548594 | M14: 45918.472 | N14: 45931.47 | O14: INCIDENTE | P14: CONEXION AL DATAFONO | Q14: USUARIO NO PUEDE NAVEGAR ENTRE PANTALLAS O LA APP NO ABRE SE QUEDA CARGANDO | R14: MALA MANIPULACION DEL ESTABLECIMIENTO | S14: 19/09/2025 SE LLEGA AL SITIO Y SE CONFIRMA EL BORRADO DE LA APP POR PARTE DEL CLIENTE. SE PROCEDE A ESCALAR EL CASO COMO INCIDENTE. CASO ESCALADO. SE ENVÍA FORMATO DE ORDEN (FO) Y SE REPROGRAMA LA VISITA SEGÚN INDICACIONES DE WOMPI. CB:69853 RESUMEN DEL CASO: LA APP DE WOMPI FUE BORRADA DEL SISTEMA, NO APARECE HACIENDO TEM CALL SERIAL:254MMD4X2815 ECALADO QUEREMOS CONTARLE QUE CREAMOS EL TICKET N° (466214), PARA DAR SEGUIMIENTO A LA ATENCIÓN DE SU COMERCI 01/10/2025 SE LLAMA A LA LÍNEA DE CONTACTO 3106666976 CLIENTE CONFIRMA QUE EL SERVICIO FUNCIONA PERFECTAMENTE, COMPARTE BAUCHER VÍA WHATSAPP, SE CIERRA ORDEN EXITOSA | T14: VISITA_TÉCNICA | U14: 16 | V14: PRINCIPAL | W14: TERRESTRE | X14: HERNANDEZ GUARIN MIGUEL JULIAN | Y14: 2 | Z14: =IF(T14="SOPORTE_TELEFÓNICO",'TARIFAS 2025'!$B$14,IF(V14="PRINCIPAL",'TARIFAS 2025'!$B$8,IF(V14="INTERMEDIA",'TARIFAS 2025'!$C$8,IF(V14="LEJANA",'TARIFAS 2025'!$D$8)))) -> 51282 | AA14: =Z14*Y14 -> 102564
A15: MEDELLIN | B15: =VLOOKUP(A15,'CENTROS DE COSTOS'!A:D,2,0) -> 0036-0005 | C15: =VLOOKUP(A15,'CENTROS DE COSTOS'!A:D,3,0) -> Wompi Noroccidente | D15: 5761 | E15: 2818456 | F15: 62255 | G15: INCIDENTE | H15: ANTIOQUIA | I15: SOPETRAN | J15: BARRIO SOPETRAN SOPETRAN | K15: WOMPI | L15: FO-25-1607193 | M15: 45931.333 | N15: 45931.476 | O15: INCIDENTE | P15: NAVEGACION LENTA | Q15: USUARIO NO PUEDE NAVEGAR ENTRE PANTALLAS O LA APP NO ABRE SE QUEDA CARGANDO | R15: CACHE | S15: 01/10/2025 SE REALIZA VERIFICACIÓN DE EQUIPO PRESENTA CONSUMÓ NORMAL DE BATERÍA, SE INDICA A USUARIO QUE EL CONSUMÓ ES NORMAL EN MOMENTOS QUE HACE MÁS USO DEL EQUIPO | T15: VISITA_TÉCNICA | U15: 64 | V15: INTERMEDIA | W15: TERRESTRE | X15: HERNANDEZ CHAVARRIA JUAN CAMILO | Y15: 1 | Z15: =IF(T15="SOPORTE_TELEFÓNICO",'TARIFAS 2025'!$B$14,IF(V15="PRINCIPAL",'TARIFAS 2025'!$B$8,IF(V15="INTERMEDIA",'TARIFAS 2025'!$C$8,IF(V15="LEJANA",'TARIFAS 2025'!$D$8)))) -> 172989 | AA15: =Z15*Y15 -> 172989
A16: BOGOTA | B16: =VLOOKUP(A16,'CENTROS DE COSTOS'!A:D,2,0) -> 0036-0004 | C16: =VLOOKUP(A16,'CENTROS DE COSTOS'!A:D,3,0) -> Wompi Centro | D16: 11001 | E16: 2820364 | F16: 44901 | G16: INCIDENTE | H16: CUNDINAMARCA | I16: BOGOTÁ | J16: TODO REPUESTOS HB SAS | K16: WOMPI | L16: FO-25-1609208 | M16: 45931.38 | N16: 45931.49 | O16: INCIDENTE | P16: SOFTWARE | Q16: VERSIÓN DESACTUALIZADA | R16: VERSIÓN NO ACTUALIZADA | S16: 01/10/2025 SE REALIZA VISITA A COMERCIO SE REALIZA ACTUALIZACIÓN DE APLICACION SE BORRA CACHE. SE REALIZAN PRUEBAS DE TRANSACCIÓN | T16: VISITA_TÉCNICA | U16: 16 | V16: PRINCIPAL | W16: TERRESTRE | X16: JAIMES VALERO NELSON RICARDO | Y16: 1 | Z16: =IF(T16="SOPORTE_TELEFÓNICO",'TARIFAS 2025'!$B$14,IF(V16="PRINCIPAL",'TARIFAS 2025'!$B$8,IF(V16="INTERMEDIA",'TARIFAS 2025'!$C$8,IF(V16="LEJANA",'TARIFAS 2025'!$D$8)))) -> 51282 | AA16: =Z16*Y16 -> 51282
A17: CALI | B17: =VLOOKUP(A17,'CENTROS DE COSTOS'!A:D,2,0) -> 0036-0003 | C17: =VLOOKUP(A17,'CENTROS DE COSTOS'!A:D,3,0) -> Wompi Suroccidente | D17: 76001 | E17: 2815722 | F17: 33042 | G17: INCIDENTE | H17: VALLE DEL CAUCA | I17: CALI | J17: BARRIO HOLGUINES CALI 1 | K17: WOMPI | L17: FO-25-1604818 | M17: 45930.512 | N17: 45931.499 | O17: INCIDENTE | P17: NAVEGACION LENTA | Q17: USUARIO NO PUEDE NAVEGAR ENTRE PANTALLAS O LA APP NO ABRE SE QUEDA CARGANDO | R17: CACHE | S17: 01/10/2025 SE REALIZA ACTUALIZACIÓN DE APLICACIÓN WPI CON BORRADO DE CACHÉ Y REINICIO EL DISPOSITIVO SE REALIZAN PRUEBAS Y LOS DISPOSITIVOS QUEDAN OK | T17: VISITA_TÉCNICA | U17: 64 | V17: PRINCIPAL | W17: TERRESTRE | X17: ESCOBAR LENIS JUAN SEBASTIAN | Y17: 1 | Z17: =IF(T17="SOPORTE_TELEFÓNICO",'TARIFAS 2025'!$B$14,IF(V17="PRINCIPAL",'TARIFAS 2025'!$B$8,IF(V17="INTERMEDIA",'TARIFAS 2025'!$C$8,IF(V17="LEJANA",'TARIFAS 2025'!$D$8)))) -> 51282 | AA17: =Z17*Y17 -> 51282
A18: MEDELLIN | B18: =VLOOKUP(A18,'CENTROS DE COSTOS'!A:D,2,0) -> 0036-0005 | C18: =VLOOKUP(A18,'CENTROS DE COSTOS'!A:D,3,0) -> Wompi Noroccidente | D18: 5001 | E18: 2815940 | F18: 79677 | G18: INCIDENTE | H18: ANTIOQUIA | I18: MEDELLÍN | J18: MOTO Z | K18: WOMPI | L18: FO-25-1605133 | M18: 45930.553 | N18: 45931.506 | O18: INCIDENTE | P18: LECTOR DE TARJETAS | Q18: NO LEE TARJETAS | R18: DAÑO DEL LECTOR DE TARJETAS | S18: 01/10/2025 SE LLAMA A CLIENTE PARA CONFIRMAR VISITA Y SE HABLA CON EL SEÑOR ANDRES ZAPATA Y COMENTA QUE EL DATAFONO YA FUNCIONA CORRECTAMENTE | T18: SOPORTE_TELEFÓNICO | U18: 16 | V18: PRINCIPAL | W18: TERRESTRE | X18: BADEL ACUÑA LUIS ALBERTO | Y18: 1 | Z18: =IF(T18="SOPORTE_TELEFÓNICO",'TARIFAS 2025'!$B$14,IF(V18="PRINCIPAL",'TARIFAS 2025'!$B$8,IF(V18="INTERMEDIA",'TARIFAS 2025'!$C$8,IF(V18="LEJANA",'TARIFAS 2025'!$D$8)))) -> 22000 | AA18: =Z18*Y18 -> 22000
A19: CALI | B19: =VLOOKUP(A19,'CENTROS DE COSTOS'!A:D,2,0) -> 0036-0003 | C19: =VLOOKUP(A19,'CENTROS DE COSTOS'!A:D,3,0) -> Wompi Suroccidente | D19: 76001 | E19: 2758595 | F19: 73384 | G19: INCIDENTE | H19: VALLE DEL CAUCA | I19: CALI | J19: VARIEDADES ROSSY CALI | K19: WOMPI | L19: FO-25-1547354 | M19: 45918.365 | N19: 45931.514 | O19: INCIDENTE | P19: CREDENCIALES DE ACCESO (USUARIO/CONTRASEÑA) | Q19: NO FUNCIONA EL USUARIO O CONTRASEÑA | R19: HAY UNA FALLA EN LA OPCIÓN DE OLVIDO DE CONTRASEÑA O USUARIO | S19: 01/10/2025 CLIENTE TENÍA PROBLEMAS DE CREDENCIALES SE LE LLAMA EL DÍA DE HOY Y CONFIRMA QUE YA PUEDE INGRESAR A HACER TRANSACCIONES | T19: SOPORTE_TELEFÓNICO | U19: 48 | V19: PRINCIPAL | W19: TERRESTRE | X19: CUERO RUIZ JHONNY | Y19: 1 | Z19: =IF(T19="SOPORTE_TELEFÓNICO",'TARIFAS 2025'!$B$14,IF(V19="PRINCIPAL",'TARIFAS 2025'!$B$8,IF(V19="INTERMEDIA",'TARIFAS 2025'!$C$8,IF(V19="LEJANA",'TARIFAS 2025'!$D$8)))) -> 22000 | AA19: =Z19*Y19 -> 22000
... A163: PASTO | B163: =VLOOKUP(A163,'CENTROS DE COSTOS'!A:D,2,0) -> 0036-0003 | C163: =VLOOKUP(A163,'CENTROS DE COSTOS'!A:D,3,0) -> Wompi Suroccidente | D163: 52001 | E163: 2858520 | F163: 19074 | G163: INCIDENTE | H163: NARIÑO | I163: PASTO | J163: ASESORÍAS EN SEGUROS AMP | K163: WOMPI | L163: FO-25-1647779 | M163: 45938.601 | N163: 45938.744 | O163: INCIDENTE | P163: IMPRESIÓN | Q163: FALTA DE ROLLO | R163: MALA MANIPULACIÓN DEL DATAFONO | S163: 08/10/2025 SE VISITA CB. SE ENCUENTRA DATAFONO SIN ROLLOS DE PAPEL, POR LO TANTO LA OPCIÓN IMPRIMIR RECIBO APARECE INACTIVA. SE INSTALA ROLLO NUEVO. SE REALIZAN PRUEBAS TX EXITOSAS. QUEDA OPERATIVO CLIENTE PIDE SE LE ENVÍEN ROLLOS WOMPI, SE LE ESTÁN TERMINANDO, SE LE INDICA FORMA DE SOLICITAR | T163: VISITA_TÉCNICA | U163: 16 | V163: PRINCIPAL | W163: TERRESTRE | X163: CASTILLO HERRERA ALEX RICARDO | Y163: 1 | Z163: =IF(T163="SOPORTE_TELEFÓNICO",'TARIFAS 2025'!$B$14,IF(V163="PRINCIPAL",'TARIFAS 2025'!$B$8,IF(V163="INTERMEDIA",'TARIFAS 2025'!$C$8,IF(V163="LEJANA",'TARIFAS 2025'!$D$8)))) -> 51282 | AA163: =Z163*Y163 -> 51282
A164: MEDELLIN | B164: =VLOOKUP(A164,'CENTROS DE COSTOS'!A:D,2,0) -> 0036-0005 | C164: =VLOOKUP(A164,'CENTROS DE COSTOS'!A:D,3,0) -> Wompi Noroccidente | D164: 5001 | E164: TA-25-1186670 | F164: 49302 | G164: INCIDENTE | H164: ANTIOQUIA | I164: MEDELLÍN | J164: SMART PLUS AE | K164: WOMPI | L164: FO-25-1644227 | M164: 45938.333 | N164: 45938.751 | O164: INCIDENTE | P164: CONEXIÓN | Q164: APARECEN ERRORES EN PANTALLA: HUBO UNA DESCONEXION DE LA RED | R164: WIFI | S164: 08/10/2025 SE CAMBIA DATÁFONO POR FALLAS REPORTADAS POR EL USUARIO, DESCONEXIÓN REPENTINA CON EL WIFI, LENTITUD EN EL SISTEMA, NO IMPRIME BAUCHER, AUTORIZA EL CAMBIO DE EQUIPO CENTRO DE GESTIÓN WOMPI | T164: VISITA_TÉCNICA | U164: 64 | V164: PRINCIPAL | W164: TERRESTRE | X164: BARRIENTOS HERNANDEZ CRISTIAN HORACIO | Y164: 1 | Z164: =IF(T164="SOPORTE_TELEFÓNICO",'TARIFAS 2025'!$B$14,IF(V164="PRINCIPAL",'TARIFAS 2025'!$B$8,IF(V164="INTERMEDIA",'TARIFAS 2025'!$C$8,IF(V164="LEJANA",'TARIFAS 2025'!$D$8)))) -> 51282 | AA164: =Z164*Y164 -> 51282
A165: BOGOTA | B165: =VLOOKUP(A165,'CENTROS DE COSTOS'!A:D,2,0) -> 0036-0004 | C165: =VLOOKUP(A165,'CENTROS DE COSTOS'!A:D,3,0) -> Wompi Centro | D165: 11001 | E165: TA-25-1187371 | F165: 31442 | G165: INCIDENTE | H165: CUNDINAMARCA | I165: BOGOTÁ | J165: MULTISERVICIOS EDUARDOÑO | K165: WOMPI | L165: FO-25-1645330 | M165: 45938.426 | N165: 45938.753 | O165: INCIDENTE | P165: NAVEGACION LENTA | Q165: USUARIO NO PUEDE NAVEGAR ENTRE PANTALLAS O LA APP NO ABRE SE QUEDA CARGANDO | R165: CANAL DE COMUNICACIÓN | S165: 08/10/2025 SE REALIZA VISITA PARA VALIDAR ERROR DE CONEXIÓN AUN DESPUÉS DE ACTUALIZAR SE VALIDA VERSIÓN 26.0.2 EL EQUIPO TRANSA CORRECTO HASTA LA TERCERA O QUINTA TRANSACCIÓN LUEGO DA ERROR DE CONEXIÓN Y NO DEJA SE CIERRA SESIÓN Y YA NO DEJA ABRIRLA NUEVAMENTE SE DEBE REINICIAR EL DATAFONO PARA QUE FUNCIONE INGRESANDO LAS MISMAS CREDENCIALES, SE HACE SOPORTE CON WOMPI SE DESINSTALA APLICACION Y SE VUELVE A REINSTALAR Y SE HACE SEGUIMIENTONY EMPIEZA A DEMORARSE LAS TRANSACCIONES Y VUELVE OTRA VEZ A DAR ERROR SE CIERRA SESIÓN Y NO INGRESA SOLO. FUNCIONA SI SE VUELVE A REINICIAR EL DATAFONO ADEMÁS DE NOTARSE LENTITUD SE ESCALA A WOMPI, CUANDO NO SALE LA TRANSACCIÓN SE REALIZA BORRADO DE CACHE Y STOP EN LA APP Y VUELVE A FUNCIONAR | T165: VISITA_TÉCNICA | U165: 40 | V165: PRINCIPAL | W165: TERRESTRE | X165: JAIMES VALERO NELSON RICARDO | Y165: 1 | Z165: =IF(T165="SOPORTE_TELEFÓNICO",'TARIFAS 2025'!$B$14,IF(V165="PRINCIPAL",'TARIFAS 2025'!$B$8,IF(V165="INTERMEDIA",'TARIFAS 2025'!$C$8,IF(V165="LEJANA",'TARIFAS 2025'!$D$8)))) -> 51282 | AA165: =Z165*Y165 -> 51282
A166: IBAGUE | B166: =VLOOKUP(A166,'CENTROS DE COSTOS'!A:D,2,0) -> 0036-0006 | C166: =VLOOKUP(A166,'CENTROS DE COSTOS'!A:D,3,0) -> Wompi Oriente | D166: 73001 | E166: 2857811 | F166: 66444 | G166: INCIDENTE | H166: TOLIMA | I166: IBAGUE | J166: PUCHYS | K166: WOMPI | L166: FO-25-1646717 | M166: 45938.513 | N166: 45939.396 | O166: INCIDENTE | P166: CONEXIÓN | Q166: CONEXIÓN DEFICIENTE WIFI | R166: FALLAS EN CANAL DE COMUNICACIÓN DEL CLIENTE (INTERNET) | S166: 09/10/2025 SE REALIZA RECUPERACIÓN DE CONTRASEÑA, EL CLIENTE MANIFIESTA QUE DESDE QUE LE HICIERON LA MIGRACIÓN NO A PODIDO UTILIZAR EL EQUIPO WOMPI, SE CONECTA A RED WIFI DEL COMERCIO NO ES FUNCIONAL, SE REALIZA CONEXIÓN CON DISPOSITIVO MÓVIL "CELULAR" FUNCIONANDO EQUIPO WOMPI SE LE RECOMIENDA AL CLIENTE SOLICITAR REVISIÓN POR PARTE DEL OPERADOR DE INTERNET YA QUE NO PERMITE CONECTAR EQUIPO POR LA RED WIFI DEL CLIENTE | T166: VISITA_TÉCNICA | U166: 16 | V166: PRINCIPAL | W166: TERRESTRE | X166: GUTIERREZ CAMILO ANDRES | Y166: 1 | Z166: =IF(T166="SOPORTE_TELEFÓNICO",'TARIFAS 2025'!$B$14,IF(V166="PRINCIPAL",'TARIFAS 2025'!$B$8,IF(V166="INTERMEDIA",'TARIFAS 2025'!$C$8,IF(V166="LEJANA",'TARIFAS 2025'!$D$8)))) -> 51282 | AA166: =Z166*Y166 -> 51282
A167: BUCARAMANGA | B167: =VLOOKUP(A167,'CENTROS DE COSTOS'!A:D,2,0) -> 0036-0007 | C167: =VLOOKUP(A167,'CENTROS DE COSTOS'!A:D,3,0) -> Wompi Santander | D167: 68001 | E167: 2856504 | F167: 74163 | G167: INCIDENTE | H167: SANTANDER | I167: BUCARAMANGA | J167: BARRIO COLORADOS BUCARAMANGA | K167: WOMPI | L167: FO-25-1645269 | M167: 45938.416 | N167: 45939.397 | O167: INCIDENTE | P167: CONEXIÓN | Q167: CONEXIÓN DEFICIENTE WIFI | R167: WIFI | S167: 09/10/2025 SE COMUNICA CON EL CLIENTE , SE LE INDICA COMO ACTUALIZAR APP , COMO BORRAR CACHÉ , SE LE ENTREGA CONTRASEÑA DE USUARIO, SE LE INDICA COMO CAMBIAR CONTRASEÑA WIFI, PRUEBAS OK | T167: SOPORTE_TELEFÓNICO | U167: 32 | V167: PRINCIPAL | W167: TERRESTRE | X167: BARRERA ORTEGA MARLON STWAR | Y167: 1 | Z167: =IF(T167="SOPORTE_TELEFÓNICO",'TARIFAS 2025'!$B$14,IF(V167="PRINCIPAL",'TARIFAS 2025'!$B$8,IF(V167="INTERMEDIA",'TARIFAS 2025'!$C$8,IF(V167="LEJANA",'TARIFAS 2025'!$D$8)))) -> 22000 | AA167: =Z167*Y167 -> 22000
A168: MANIZALES | B168: =VLOOKUP(A168,'CENTROS DE COSTOS'!A:D,2,0) -> 0036-0002 | C168: =VLOOKUP(A168,'CENTROS DE COSTOS'!A:D,3,0) -> Wompi Eje Cafetero | D168: 17001 | E168: 2856387 | F168: 19208 | G168: INCIDENTE | H168: CALDAS | I168: MANIZALES | J168: LOS NAVEGANTES NRO 2 | K168: WOMPI | L168: FO-25-1645445 | M168: 45938.428 | N168: 45939.42 | O168: INCIDENTE | P168: LECTURA | Q168: NO LEE NINGUNA FACTURA | R168: NO LEE CODIGOS DE BARRAS CORTOS | S168: 09/10/2025 SE REALIZA VISITA SE EVIDENCIA QUE DATÁFONO LEÉ FACTURAS CON NORMALIDAD, SE LE EXPLICA AL USUARIO COMO REALIZAR LECTURA DE LAS FACTURAS SERVICIO OK | T168: VISITA_TÉCNICA | U168: 16 | V168: PRINCIPAL | W168: TERRESTRE | X168: AGUIRRE HENAO RAUL EDUARDO | Y168: 1 | Z168: =IF(T168="SOPORTE_TELEFÓNICO",'TARIFAS 2025'!$B$14,IF(V168="PRINCIPAL",'TARIFAS 2025'!$B$8,IF(V168="INTERMEDIA",'TARIFAS 2025'!$C$8,IF(V168="LEJANA",'TARIFAS 2025'!$D$8)))) -> 51282 | AA168: =Z168*Y168 -> 51282
A169: CALI | B169: =VLOOKUP(A169,'CENTROS DE COSTOS'!A:D,2,0) -> 0036-0003 | C169: =VLOOKUP(A169,'CENTROS DE COSTOS'!A:D,3,0) -> Wompi Suroccidente | D169: 76001 | E169: 2857416 | F169: 64018 | G169: INCIDENTE | H169: VALLE DEL CAUCA | I169: CALI | J169: ESTILO LIBRE PELUQUERIA UNISEX | K169: WOMPI | L169: FO-25-1646548 | M169: 45938.476 | N169: 45939.436 | O169: INCIDENTE | P169: LECTURA | Q169: NO LEE NINGUNA FACTURA | R169: SUCIEDAD EN LA CAMARA | S169: 09/10/2025 CLIENTE TIENE PROBLEMAS CON EL LECTOR DE BARRAS DICE QUE NO LEE LA MAYORIA DE RECIBOS QUE DE 10 RECIBOS LEE 6 DICE QUE NO LEE RECIBOS QUE ESTAN EN EL TELEFONO HAGO PRUEBAS Y SI ME FUNCIONA SI ME LEE RECIBOS EN TELEFONO Y FISICO SE LE EXPLICA QUE ES UNA CAMARA NO UN LACER EL EQUIPO ME FUNCIONO BIEN EL CLIENTE HACE PRUEBAS Y TAMBIÉN LE FUNCIONA BIEN SE HACEN PRUEBAS CON RECIBOS DE CLIENTES Y TODO QUEDA FUNCIONANDO CORRECTAMENTE | T169: VISITA_TÉCNICA | U169: 24 | V169: PRINCIPAL | W169: TERRESTRE | X169: CUERO RUIZ JHONNY | Y169: 1 | Z169: =IF(T169="SOPORTE_TELEFÓNICO",'TARIFAS 2025'!$B$14,IF(V169="PRINCIPAL",'TARIFAS 2025'!$B$8,IF(V169="INTERMEDIA",'TARIFAS 2025'!$C$8,IF(V169="LEJANA",'TARIFAS 2025'!$D$8)))) -> 51282 | AA169: =Z169*Y169 -> 51282
A170: IBAGUE | B170: =VLOOKUP(A170,'CENTROS DE COSTOS'!A:D,2,0) -> 0036-0006 | C170: =VLOOKUP(A170,'CENTROS DE COSTOS'!A:D,3,0) -> Wompi Oriente | D170: 73001 | E170: 2857678 | F170: 68291 | G170: INCIDENTE | H170: TOLIMA | I170: IBAGUE | J170: PAPELERIA Y CACHARRERIA GRANADA | K170: WOMPI | L170: FO-25-1647211 | M170: 45938.515 | N170: 45939.437 | O170: INCIDENTE | P170: SOFTWARE | Q170: APP ELIMINADA | R170: APP ELIMINADA POR EL CB | S170: 09/10/2025 SE COMUNICA AL NÚMERO 3166664119, EL SEÑOR HAROLD DANIEL GUZMÁN INDICA HABER BORRADO LA APLICACIÓN DE WOMPI POR ERROR; SE LE BRINDA SOPORTE TELEFÓNICO INDICANDO COMO REALIZAR DESCARGA DE ACTUALIZACIÓN Y BORRADO DE CACHÉ. SE VALIDA FUNCIONAMIENTO DEL EQUIPO OK. | T170: SOPORTE_TELEFÓNICO | U170: 24 | V170: PRINCIPAL | W170: TERRESTRE | X170: BARRAGAN TAFUR EDWIN ESTEBAN | Y170: 1 | Z170: =IF(T170="SOPORTE_TELEFÓNICO",'TARIFAS 2025'!$B$14,IF(V170="PRINCIPAL",'TARIFAS 2025'!$B$8,IF(V170="INTERMEDIA",'TARIFAS 2025'!$C$8,IF(V170="LEJANA",'TARIFAS 2025'!$D$8)))) -> 22000 | AA170: =Z170*Y170 -> 22000
A171: MANIZALES | B171: =VLOOKUP(A171,'CENTROS DE COSTOS'!A:D,2,0) -> 0036-0002 | C171: =VLOOKUP(A171,'CENTROS DE COSTOS'!A:D,3,0) -> Wompi Eje Cafetero | D171: 17001 | E171: 2857673 | F171: 28121 | G171: INCIDENTE | H171: CALDAS | I171: MANIZALES | J171: BARRIO CAROLA MANIZALES | K171: WOMPI | L171: FO-25-1646714 | M171: 45938.513 | N171: 45939.442 | O171: INCIDENTE | P171: SOFTWARE | Q171: APP ELIMINADA | R171: APP ELIMINADA POR EL CB | S171: 09/10/2025 SE REALIZA LLAMADA CON USUARIO EL CUAL INDICA QUE YA SE ENCUENTRA EN BUEN ESTADO, Y TRABAJANDO CON NORMALIDAD SERVICIO OK | T171: SOPORTE_TELEFÓNICO | U171: 40 | V171: PRINCIPAL | W171: TERRESTRE | X171: AGUIRRE HENAO RAUL EDUARDO | Y171: 1 | Z171: =IF(T171="SOPORTE_TELEFÓNICO",'TARIFAS 2025'!$B$14,IF(V171="PRINCIPAL",'TARIFAS 2025'!$B$8,IF(V171="INTERMEDIA",'TARIFAS 2025'!$C$8,IF(V171="LEJANA",'TARIFAS 2025'!$D$8)))) -> 22000 | AA171: =Z171*Y171 -> 22000
A172: MEDELLIN | B172: =VLOOKUP(A172,'CENTROS DE COSTOS'!A:D,2,0) -> 0036-0005 | C172: =VLOOKUP(A172,'CENTROS DE COSTOS'!A:D,3,0) -> Wompi Noroccidente | D172: 5001 | E172: 2858246 | F172: 45335 | G172: INCIDENTE | H172: ANTIOQUIA | I172: MEDELLÍN | J172: YESOS Y COLORES | K172: WOMPI | L172: FO-25-1647381 | M172: 45938.583 | N172: 45939.444 | O172: INCIDENTE | P172: NAVEGACION LENTA | Q172: USUARIO NO PUEDE NAVEGAR ENTRE PANTALLAS O LA APP NO ABRE SE QUEDA CARGANDO | R172: CACHE | S172: 09/10/2025 SE VISITA PUNTO Y SE REALIZA TEM CALL, BORRADO DE CACHE Y REINICIO, SE ESPERA 20 MIN Y SE REALIZAN PRUEBAS OK, NO SE REALENTIZA | T172: VISITA_TÉCNICA | U172: 64 | V172: PRINCIPAL | W172: TERRESTRE | X172: QUINTERO SANCHEZ JUAN SEBASTIAN | Y172: 1 | Z172: =IF(T172="SOPORTE_TELEFÓNICO",'TARIFAS 2025'!$B$14,IF(V172="PRINCIPAL",'TARIFAS 2025'!$B$8,IF(V172="INTERMEDIA",'TARIFAS 2025'!$C$8,IF(V172="LEJANA",'TARIFAS 2025'!$D$8)))) -> 51282 | AA172: =Z172*Y172 -> 51282
A173: MEDELLIN | B173: =VLOOKUP(A173,'CENTROS DE COSTOS'!A:D,2,0) -> 0036-0005 | C173: =VLOOKUP(A173,'CENTROS DE COSTOS'!A:D,3,0) -> Wompi Noroccidente | D173: 5079 | E173: 2851146 | F173: 19184 | G173: INCIDENTE | H173: ANTIOQUIA | I173: BARBOSA | J173: TECNICEL JC | K173: WOMPI | L173: FO-25-1645288 | FO-25-1640620 | M173: 45937.477 | N173: 45939.45 | O173: INCIDENTE | P173: LECTURA | Q173: ERROR LECTURA CODIGO DE BARRAS | R173: NO LEE CODIGOS DE BARRAS CORTOS | S173: 08/10/2025 SE VISITA PUNTO Y SE ENCUENTRA LOCAL CERRADO, EN COMUNICACIÓN CON EL USUARIO NOS INDICA QUE LOS MIÉRCOLES NO SE TRABAJA EN EL CB POR DESCANSO 09/10/2025 SE REALIZA VISITA TÉCNICA EN ATENCIÓN AL INCIDENTE REPORTADO POR EL CORRESPONSAL BANCOLOMBIA RELACIONADO CON EL DATÁFONO WOMPI. EL USUARIO CONFIRMA SU IDENTIFICACIÓN Y MANIFIESTA QUE EL DISPOSITIVO NO ESTÁ LEYENDO LAS FACTURAS CON CÓDIGO DE BARRAS. DURANTE LA VALIDACIÓN, SE DETECTA QUE EL INCONVENIENTE SE DEBE A UNA MANIPULACIÓN INCORRECTA POR PARTE DEL CLIENTE AL MOMENTO DE ESCANEAR LOS CÓDIGOS. SE LE BRINDA ORIENTACIÓN SOBRE EL PROCEDIMIENTO ADECUADO PARA LA LECTURA DE CÓDIGOS DE BARRAS. TRAS LA EXPLICACIÓN, SE REALIZA PRUEBA FUNCIONAL Y SE CONFIRMA QUE EL DATÁFONO QUEDA OPERATIVO. | T173: VISITA_TÉCNICA | U173: 56 | V173: INTERMEDIA | W173: TERRESTRE | X173: MARTINEZ TOVAR OSCAR DAVID | Y173: 2 | Z173: =IF(T173="SOPORTE_TELEFÓNICO",'TARIFAS 2025'!$B$14,IF(V173="PRINCIPAL",'TARIFAS 2025'!$B$8,IF(V173="INTERMEDIA",'TARIFAS 2025'!$C$8,IF(V173="LEJANA",'TARIFAS 2025'!$D$8)))) -> 172989 | AA173: =Z173*Y173 -> 345978
A174: CALI | B174: =VLOOKUP(A174,'CENTROS DE COSTOS'!A:D,2,0) -> 0036-0003 | C174: =VLOOKUP(A174,'CENTROS DE COSTOS'!A:D,3,0) -> Wompi Suroccidente | D174: 76520 | E174: 2857755 | F174: 50529 | G174: INCIDENTE | H174: VALLE DEL CAUCA | I174: PALMIRA | J174: BARRIO CENTRO PALMIRA 8 | K174: WOMPI | L174: FO-25-1646722 | M174: 45938.51 | N174: 45939.451 | O174: INCIDENTE | P174: NAVEGACION LENTA | Q174: USUARIO NO PUEDE NAVEGAR ENTRE PANTALLAS O LA APP NO ABRE SE QUEDA CARGANDO | R174: CANAL DE COMUNICACIÓN | S174: 09/10/2025 EN LA VISITA TÉCNICA SE REALIZÓ BORRADO DE CACHÉ Y SE LE EXPLICÓ A LA USUARIA LA MANERA CORRECTA DE LEER LOS CÓDIGOS DE BARRAS, LA USUARIA MANIFIESTA INCONFORMIDAD CON LA LENTITUD QUE LE HA PRESENTADO EL DATÁFONO PARA HACER LAS OPERACIONES, LUEGO DE REVISAR LA VERSIÓN Y BORRADO DE CACHÉ SE REALIZARON PRUEBAS DEJANDO EL SERVICIO OPERATIVO SIN FALLAS. | T174: VISITA_TÉCNICA | U174: 0 | V174: PRINCIPAL | W174: TERRESTRE | X174: SANCHEZ URREGO ROBINSON DAVID | Y174: 1 | Z174: =IF(T174="SOPORTE_TELEFÓNICO",'TARIFAS 2025'!$B$14,IF(V174="PRINCIPAL",'TARIFAS 2025'!$B$8,IF(V174="INTERMEDIA",'TARIFAS 2025'!$C$8,IF(V174="LEJANA",'TARIFAS 2025'!$D$8)))) -> 51282 | AA174: =Z174*Y174 -> 51282
A175: BOGOTA | B175: =VLOOKUP(A175,'CENTROS DE COSTOS'!A:D,2,0) -> 0036-0004 | C175: =VLOOKUP(A175,'CENTROS DE COSTOS'!A:D,3,0) -> Wompi Centro | D175: 11001 | E175: 2857765 | F175: 60679 | G175: INCIDENTE | H175: CUNDINAMARCA | I175: BOGOTÁ | J175: COPY EXPRESS CEDRITOS | K175: WOMPI | L175: FO-25-1646712 | M175: 45938.515 | N175: 45939.453 | O175: INCIDENTE | P175: NAVEGACION LENTA | Q175: USUARIO NO PUEDE NAVEGAR ENTRE PANTALLAS O LA APP NO ABRE SE QUEDA CARGANDO - CONEXIÓN DEFICIENTE WIFI | R175: CACHE | S175: 09/10/2025 SE VISITA COMERCIO POR LENTITUD EN NAVEGACIÓN Y DE APP DE WOMPI Y LENTITUD EN TRANSACCIONES , SE PROCEDE A VALIDAR VERSIÓN 26.0.2-NEXT.0 SE REALIZA BORRADO DE CACHÉ Y BORRADO DE RED WIFI , SE CONECTA NUEVAMENTE A RED , SE REINICIA EQUIPO Y SE INDICA A CLIENTE INGRESAR A LA APP SE REALIZAN DOS TRANSACCIONES DE PRUEBA Y LAS TRANSACCIONES MEJORARON CONSIDERABLEMENTE ,SE INDICA A CLIENTE PROCESOS E BORRADO DE CACHÉ Y SE FINALIZA ACTIVIDAD SIN MÁS NOVEDAD | T175: VISITA_TÉCNICA | U175: 16 | V175: PRINCIPAL | W175: TERRESTRE | X175: ROMERO ROJAS BREIDY JHOHAN | Y175: 1 | Z175: =IF(T175="SOPORTE_TELEFÓNICO",'TARIFAS 2025'!$B$14,IF(V175="PRINCIPAL",'TARIFAS 2025'!$B$8,IF(V175="INTERMEDIA",'TARIFAS 2025'!$C$8,IF(V175="LEJANA",'TARIFAS 2025'!$D$8)))) -> 51282 | AA175: =Z175*Y175 -> 51282
A176: BOGOTA | B176: =VLOOKUP(A176,'CENTROS DE COSTOS'!A:D,2,0) -> 0036-0004 | C176: =VLOOKUP(A176,'CENTROS DE COSTOS'!A:D,3,0) -> Wompi Centro | D176: 11001 | E176: 2858156 | F176: 26955 | G176: INCIDENTE | H176: CUNDINAMARCA | I176: BOGOTÁ | J176: CAFETERIA Y CIGARRERIA EL CANEY | K176: WOMPI | L176: FO-25-1647403 | M176: 45938.579 | N176: 45939.458 | O176: INCIDENTE | P176: NAVEGACION LENTA | Q176: USUARIO NO PUEDE NAVEGAR ENTRE PANTALLAS O LA APP NO ABRE SE QUEDA CARGANDO | R176: MEMORIA LLENA | S176: 09/10/2025 SE REALIZA VISITA A CB PARA ATENDER INCIDENTE SE REALIZA BORRADO DE MEMORIA CACHÉ Y ALMACENAMIENTO, SE REALIZAN PRUEBAS OK | T176: VISITA_TÉCNICA | U176: 64 | V176: PRINCIPAL | W176: TERRESTRE | X176: GALINDO ROJAS LUIS FELIPE | Y176: 1 | Z176: =IF(T176="SOPORTE_TELEFÓNICO",'TARIFAS 2025'!$B$14,IF(V176="PRINCIPAL",'TARIFAS 2025'!$B$8,IF(V176="INTERMEDIA",'TARIFAS 2025'!$C$8,IF(V176="LEJANA",'TARIFAS 2025'!$D$8)))) -> 51282 | AA176: =Z176*Y176 -> 51282
A177: PASTO | B177: =VLOOKUP(A177,'CENTROS DE COSTOS'!A:D,2,0) -> 0036-0003 | C177: =VLOOKUP(A177,'CENTROS DE COSTOS'!A:D,3,0) -> Wompi Suroccidente | D177: 52001 | E177: 2858910 | F177: 40639 | G177: INCIDENTE | H177: NARIÑO | I177: PASTO | J177: DROGUERIA MEJOR SALUD | K177: WOMPI | L177: FO-25-1647975 | M177: 45938.62 | N177: 45939.46 | O177: INCIDENTE | P177: SOFTWARE | Q177: CONFIGURACIÓN GENERAL | R177: IDIOMA | S177: 09/10/2025 SE VERIFICÓ FALLA DE TX SALE RECHAZO GENERAL, AL VERIFICAR LA TX FUNCIONA CORRECTAMENTE PERO PRESENTA UN MENSAJE DE TX REPRESADAS O PENDIENTES POR PROBAR, SE VERIFICO VERSIÓN DE LA APP SE ENCUENTRA ACTUALIZADA, SE BORRO CACHE SE REINICIO SISTEMA, SE PREINSTALO ACTUALIZACIÓN, PERO EL MENSAJE SIGUE APARECIENDO POR LO CUAL SE ESCALÓ NOVEDAD CON WOMPI EL CUAL VA REALIZAR UNA REINSTALACIÓN DE APP DE FORMA REMOTA, SE LE EXPLICO AL CLIENTE EL PROCESO DE BORRADO DE CACHE, SE EJECUTAN PRUEBAS TX EXITOSAS QUEDA OPERATIVO. | T177: VISITA_TÉCNICA | U177: 64 | V177: PRINCIPAL | W177: TERRESTRE | X177: REMICIO AMADO JOHN HEBER | Y177: 1 | Z177: =IF(T177="SOPORTE_TELEFÓNICO",'TARIFAS 2025'!$B$14,IF(V177="PRINCIPAL",'TARIFAS 2025'!$B$8,IF(V177="INTERMEDIA",'TARIFAS 2025'!$C$8,IF(V177="LEJANA",'TARIFAS 2025'!$D$8)))) -> 51282 | AA177: =Z177*Y177 -> 51282
... A383: BOGOTA | B383: =VLOOKUP(A383,'CENTROS DE COSTOS'!A:D,2,0) -> 0036-0004 | C383: =VLOOKUP(A383,'CENTROS DE COSTOS'!A:D,3,0) -> Wompi Centro | D383: 11001 | E383: 2909787 | F383: 51547 | G383: INCIDENTE | H383: CUNDINAMARCA | I383: BOGOTA | J383: TIENDA MINUTOS EL MONO | K383: WOMPI | L383: FO-25-1709177 | M383: 45951.333 | N383: 45951.524 | O383: INCIDENTE | P383: SOFTWARE | Q383: APP ELIMINADA | R383: APP ELIMINADA POR EL CB | S383: 21/10/2025 DURANTE LA VISITA TECNICA EN ATENCIÓN DE INCIDENTE DE INCIDENTE SE EVIDENCIA QUE APP FUE BORRADA POR EL COMERCIO SE REALIZAN EN REPETIDAS OCASIONES LA DESCARGA POR LA APP TEM CALL DE LA APP WOMPI SIN TENER RESPUESTA POSITIVA SE REALIZA ESCALAMIENTO A LA ENTIDAD DANDO COMO RESPUESTA LA INSTALACIÓN DE LA APP SE REALIZAN PRUEBAS QUEDANDO SERVICIO OK SALDO OK | T383: VISITA_TÉCNICA | U383: 64 | V383: PRINCIPAL | W383: TERRESTRE | X383: GALEANO SORIANO JUAN DAVID | Y383: 1 | Z383: =IF(T383="SOPORTE_TELEFÓNICO",'TARIFAS 2025'!$B$14,IF(V383="PRINCIPAL",'TARIFAS 2025'!$B$8,IF(V383="INTERMEDIA",'TARIFAS 2025'!$C$8,IF(V383="LEJANA",'TARIFAS 2025'!$D$8)))) -> 51282 | AA383: =Z383*Y383 -> 51282
A384: MEDELLIN | B384: =VLOOKUP(A384,'CENTROS DE COSTOS'!A:D,2,0) -> 0036-0005 | C384: =VLOOKUP(A384,'CENTROS DE COSTOS'!A:D,3,0) -> Wompi Noroccidente | D384: 5001 | E384: TA-25-1218923 | F384: 45522 | G384: INCIDENTE | H384: ANTIOQUIA | I384: MEDELLÍN | J384: EL CASTILLO DE LOS HELADOS DEL BOSQUE | K384: WOMPI | L384: FO-25-1701837 | M384: 45948.448 | N384: 45951.547 | O384: INCIDENTE | P384: NAVEGACION LENTA | Q384: USUARIO NO PUEDE NAVEGAR ENTRE PANTALLAS O LA APP NO ABRE SE QUEDA CARGANDO | R384: CANAL DE COMUNICACIÓN | S384: 21/10/2025 SE ATIENDE MANTENIMIENTO OK SE CAMBIA DATÁFONO POR DX4000 POR UNOS DX4000 DE ESCRITORIO. PRUEBAS EXITOSAS | T384: VISITA_TÉCNICA | U384: 64 | V384: PRINCIPAL | W384: TERRESTRE | X384: DIAZ ZABALA FRANCIS DUBAN | Y384: 1 | Z384: =IF(T384="SOPORTE_TELEFÓNICO",'TARIFAS 2025'!$B$14,IF(V384="PRINCIPAL",'TARIFAS 2025'!$B$8,IF(V384="INTERMEDIA",'TARIFAS 2025'!$C$8,IF(V384="LEJANA",'TARIFAS 2025'!$D$8)))) -> 51282 | AA384: =Z384*Y384 -> 51282
A385: MEDELLIN | B385: =VLOOKUP(A385,'CENTROS DE COSTOS'!A:D,2,0) -> 0036-0005 | C385: =VLOOKUP(A385,'CENTROS DE COSTOS'!A:D,3,0) -> Wompi Noroccidente | D385: 5001 | E385: 2913657 | F385: 74439 | G385: INCIDENTE | H385: ANTIOQUIA | I385: MEDELLÍN | J385: CAFE ANTOJA2 | K385: WOMPI | L385: FO-25-1711975 | M385: 45951.506 | N385: 45951.606 | O385: INCIDENTE | P385: SOFTWARE | Q385: APP ELIMINADA | R385: APP ELIMINADA POR EL CB | S385: 21/10/2025 SE LLAMAL AL CLIENTE AL 3015567127Y INDICA QUE REALIZÓ EL PROCESO DE TELL CALL Y LE FUNCIONÓ Y LE VOLVIÓ APARCERES EL APLICATIVO POR LO QUE SE CIERRA ACTIVIDADE | T385: SOPORTE_TELEFÓNICO | U385: 24 | V385: PRINCIPAL | W385: TERRESTRE | X385: ALVAREZ ARENAS VICTOR HUGO | Y385: 1 | Z385: =IF(T385="SOPORTE_TELEFÓNICO",'TARIFAS 2025'!$B$14,IF(V385="PRINCIPAL",'TARIFAS 2025'!$B$8,IF(V385="INTERMEDIA",'TARIFAS 2025'!$C$8,IF(V385="LEJANA",'TARIFAS 2025'!$D$8)))) -> 22000 | AA385: =Z385*Y385 -> 22000
A386: CUCUTA | B386: =VLOOKUP(A386,'CENTROS DE COSTOS'!A:D,2,0) -> 0036-0007 | C386: =VLOOKUP(A386,'CENTROS DE COSTOS'!A:D,3,0) -> Wompi Santander | D386: 54001 | E386: 2897364 | F386: 75403 | G386: INCIDENTE | H386: NORTE DE SANTANDER | I386: CUCUTA | J386: QUINCALLERIA TÁCHIRA | K386: WOMPI | L386: FO-25-1699040 | M386: 45947.586 | N386: 45951.631 | O386: INCIDENTE | P386: NAVEGACION LENTA | Q386: USUARIO NO PUEDE NAVEGAR ENTRE PANTALLAS O LA APP NO ABRE SE QUEDA CARGANDO | R386: CACHE | S386: 21/10/2025 SE LLAMA AL CLIENTE Y NOS INFORMA QUE DESDE EL DÍA 18/10 QUE SE REALIZO EL BORRADO DE CACHE Y ACTUALIZACION DE LA APP EL DATÁFONO LE QUEDÓ TRABAJANDO BIEN, TODO OK. | T386: SOPORTE_TELEFÓNICO | U386: 16 | V386: PRINCIPAL | W386: TERRESTRE | X386: TORRES MANTILLA JOSE DANIEL | Y386: 1 | Z386: =IF(T386="SOPORTE_TELEFÓNICO",'TARIFAS 2025'!$B$14,IF(V386="PRINCIPAL",'TARIFAS 2025'!$B$8,IF(V386="INTERMEDIA",'TARIFAS 2025'!$C$8,IF(V386="LEJANA",'TARIFAS 2025'!$D$8)))) -> 22000 | AA386: =Z386*Y386 -> 22000
A387: MEDELLIN | B387: =VLOOKUP(A387,'CENTROS DE COSTOS'!A:D,2,0) -> 0036-0005 | C387: =VLOOKUP(A387,'CENTROS DE COSTOS'!A:D,3,0) -> Wompi Noroccidente | D387: 5088 | E387: 2879055 | F387: 50310 | G387: INCIDENTE | H387: ANTIOQUIA | I387: BELLO | J387: BARRIO MADERA BELLO 2 | K387: WOMPI | L387: FO-25-1683943 | FO-25-1681658 | M387: 45944.59 | N387: 45951.649 | O387: INCIDENTE | P387: LECTURA | Q387: NO LEE NINGUNA FACTURA | R387: NO LEE CODIGOS DE BARRAS LARGOS | S387: 14/10/2025 SE ESCALA A WOMPI PARA CAMBIO DE EQUIPO PORQUE NO LEE NINGÚN CÓDIGO DE BARRAS, SE ESCALA CON TICKET N° (472178) 21/10/2025 WOMPI INFORMA: HEMOS VERIFICADO QUE EL DATÁFONO HA ESCANEADO CORRECTAMENTE VARIOS CÓDIGOS DE BARRAS, INCLUYENDO ALGUNOS DE GRAN LONGITUD. TE COMPARTO LA EVIDENCIA CORRESPONDIENTE. ADICIONALMENTE, TE CONFIRMAMOS QUE NO SE REALIZARÁ EL CAMBIO DE DATÁFONO, YA QUE ESTE NO RESOLVERÍA EL INCONVENIENTE CON LA LECTURA DE LOS CÓDIGOS. EL ORIGEN DEL PROBLEMA NO ESTÁ EN EL DISPOSITIVO, SINO EN UN TEMA TÉCNICO QUE NUESTRO EQUIPO DE DESARROLLO SE ENCUENTRA REVISANDO. EN RESUMEN, EL CAMBIO DEL DATÁFONO NO ES VIABLE, DADO QUE NO APORTARÍA UNA SOLUCIÓN AL CASO. SE CIERRA TICKET SEGÚN INFORMACIÓN FACILITADA POR WOMPI. | T387: VISITA_TÉCNICA | U387: 16 | V387: PRINCIPAL | W387: TERRESTRE | X387: RAMIREZ TABARES JUAN DIEGO | Y387: 2 | Z387: =IF(T387="SOPORTE_TELEFÓNICO",'TARIFAS 2025'!$B$14,IF(V387="PRINCIPAL",'TARIFAS 2025'!$B$8,IF(V387="INTERMEDIA",'TARIFAS 2025'!$C$8,IF(V387="LEJANA",'TARIFAS 2025'!$D$8)))) -> 51282 | AA387: =Z387*Y387 -> 102564
A388: SANTA MARTA | B388: =VLOOKUP(A388,'CENTROS DE COSTOS'!A:D,2,0) -> 0036-0001 | C388: =VLOOKUP(A388,'CENTROS DE COSTOS'!A:D,3,0) -> Wompi Costa | D388: 47001 | E388: 2827582 | F388: 60190 | G388: INCIDENTE | H388: MAGDALENA | I388: SANTA MARTA | J388: BARRIO PORVENIR SANTA MARTA 2 | K388: WOMPI | L388: FO-25-1617571 | FO-25-1614202 | M388: 45932.374 | N388: 45951.651 | O388: INCIDENTE | P388: VOUCHER | Q388: INFORMACIÓN DEL CB ERRADA | R388: HAY INFORMACIÓN ERRADA EN EL VOUCHER | S388: 02/10/2025 SE REALIZA LA VISITA, SE ENCUENTRA EL USUARIO CON LA DIRECCIÓN ERRADA EL USUARIO INFORMA QUE CUANDO TENÍA EL DATÁFONO DE REDEBAN APARECÍA LA DIRECCIÓN CORRECTA PERO AHORA CON EL DE WOMPI APARECE LA DIRRECCIÓN ANTERIOR SE PROCEDE A ACTUALIZAR LA APLICACIÓN PERO EL PROBLEMA PERSISTEA SE ESCALA EL CASO CON EL COORDINADOR A ESPERAS DE RESPUESTA DE WOMPI PARA ACTUALIZACIÓN DE INFORMACIÓN EN BAUCHER 21/10/2025 SE REALIZA CONTACTO POR WHATSAPP AL 3016209896 YA QUE NO RESPONDE LLAMADA PARA CONFIRMAR ACTUALIZACION DE DATOS CLIENTE INDICA QUE YA LE ACTUALIZARON LA DIRECCIÓN ENVIA VOUCHER DE EVIDENCIA Y SE CIERRA ORDEN | T388: VISITA_TÉCNICA | U388: 32 | V388: PRINCIPAL | W388: TERRESTRE | X388: THOMAS CAMPO SIGIFREDO SEGUNDO | Y388: 2 | Z388: =IF(T388="SOPORTE_TELEFÓNICO",'TARIFAS 2025'!$B$14,IF(V388="PRINCIPAL",'TARIFAS 2025'!$B$8,IF(V388="INTERMEDIA",'TARIFAS 2025'!$C$8,IF(V388="LEJANA",'TARIFAS 2025'!$D$8)))) -> 51282 | AA388: =Z388*Y388 -> 102564
A389: CUCUTA | B389: =VLOOKUP(A389,'CENTROS DE COSTOS'!A:D,2,0) -> 0036-0007 | C389: =VLOOKUP(A389,'CENTROS DE COSTOS'!A:D,3,0) -> Wompi Santander | D389: 54001 | E389: 2913707 | F389: 40083 | G389: INCIDENTE | H389: NORTE DE SANTANDER | I389: CUCUTA | J389: DROGUERIA FARMA OSPINA PEREZ | K389: WOMPI | L389: FO-25-1711927 | M389: 45951.498 | N389: 45951.687 | O389: INCIDENTE | P389: IMPRESIÓN | Q389: ROLLO MAL PUESTO | R389: MALA MANIPULACIÓN DEL DATAFONO | S389: 21/10/2025 SE REALIZA GESTION TELEFONICA, CLIENTE INFORMA QUE LA FALLA YA SE SOLUCIONO YA QUE HABIA PUESTO MAL EL ROLLO. | T389: SOPORTE_TELEFÓNICO | U389: 64 | V389: PRINCIPAL | W389: TERRESTRE | X389: NARANJO AFANADOR RUBEN JESUS | Y389: 1 | Z389: =IF(T389="SOPORTE_TELEFÓNICO",'TARIFAS 2025'!$B$14,IF(V389="PRINCIPAL",'TARIFAS 2025'!$B$8,IF(V389="INTERMEDIA",'TARIFAS 2025'!$C$8,IF(V389="LEJANA",'TARIFAS 2025'!$D$8)))) -> 22000 | AA389: =Z389*Y389 -> 22000
A390: YOPAL | B390: =VLOOKUP(A390,'CENTROS DE COSTOS'!A:D,2,0) -> 0036-0006 | C390: =VLOOKUP(A390,'CENTROS DE COSTOS'!A:D,3,0) -> Wompi Oriente | D390: 85162 | E390: 2907619 | F390: 58965 | G390: INCIDENTE | H390: CASANARE | I390: MONTERREY | J390: BARRIO CENTRO MONTERREY 4 | K390: WOMPI | L390: FO-25-1707504 | M390: 45950.624 | N390: 45951.697 | O390: INCIDENTE | P390: CONEXIÓN | Q390: CONEXIÓN DEFICIENTE WIFI | R390: WIFI | S390: 21/10/2025 EN COMUNICACIÓN CON LA ALEJANDRA VANEGAS AL NUMERO 3124186169, INDICA SE ENCUENTRA OPERATIVO EL SERVICIO, EL DIA DE HOY SE ENCUENTRA CON NORMALIDAD EL SERVICIO. SE ORIENTA PARA EL BORRADO DE CACHE Y REINICIO EN CASO DE PRESENTAR LENTITUD EN OPERACIONES | T390: SOPORTE_TELEFÓNICO | U390: 48 | V390: INTERMEDIA | W390: TERRESTRE | X390: BERNAL ELAICA EDGAR ALEXIS | Y390: 1 | Z390: =IF(T390="SOPORTE_TELEFÓNICO",'TARIFAS 2025'!$B$14,IF(V390="PRINCIPAL",'TARIFAS 2025'!$B$8,IF(V390="INTERMEDIA",'TARIFAS 2025'!$C$8,IF(V390="LEJANA",'TARIFAS 2025'!$D$8)))) -> 22000 | AA390: =Z390*Y390 -> 22000
A391: CALI | B391: =VLOOKUP(A391,'CENTROS DE COSTOS'!A:D,2,0) -> 0036-0003 | C391: =VLOOKUP(A391,'CENTROS DE COSTOS'!A:D,3,0) -> Wompi Suroccidente | D391: 19001 | E391: 2857759 | F391: 41914 | G391: INCIDENTE | H391: CAUCA | I391: POPAYAN | J391: BARRIO LA ESMERALDA POPAYAN 2 | K391: WOMPI | L391: FO-25-1646720 | M391: 45938.512 | N391: 45952.344 | O391: INCIDENTE | P391: CREDENCIALES DE ACCESO (USUARIO/CONTRASEÑA) | Q391: NO FUNCIONA EL USUARIO O CONTRASEÑA | R391: ERROR INICIO DE SESIÓN | S391: 21/10/2025 SE VALIDA Y SE REALIZA ESCALAMIENTO A WOMPI, DESPUES DE LA RESPUESTA SE VALIDA CON EL CLIENTE QUIEN SE ENCONTRABA POR FUERA DE LA CIUDAD Y CUANDO REGRESA AL VALIDAR YA INDICA QUE LE PERMITE EL INGRESO Y REALIZAR TTANSACCIONES POR LO CUAL SE CIERRA EL CASO | T391: SOPORTE_TELEFÓNICO | U391: 56 | V391: LEJANA | W391: TERRESTRE | X391: HENAO CARDONA DIEGO FERNANDO | Y391: 1 | Z391: =IF(T391="SOPORTE_TELEFÓNICO",'TARIFAS 2025'!$B$14,IF(V391="PRINCIPAL",'TARIFAS 2025'!$B$8,IF(V391="INTERMEDIA",'TARIFAS 2025'!$C$8,IF(V391="LEJANA",'TARIFAS 2025'!$D$8)))) -> 22000 | AA391: =Z391*Y391 -> 22000
A392: CUCUTA | B392: =VLOOKUP(A392,'CENTROS DE COSTOS'!A:D,2,0) -> 0036-0007 | C392: =VLOOKUP(A392,'CENTROS DE COSTOS'!A:D,3,0) -> Wompi Santander | D392: 54498 | E392: 2867893 | F392: 43075 | G392: INCIDENTE | H392: NORTE DE SANTANDER | I392: OCAÑA | J392: BARRIO EL CENTRO OCAÑA 2 | K392: WOMPI | L392: FO-25-1665894 | M392: 45940.415 | N392: 45952.358 | O392: INCIDENTE | P392: CREDENCIALES DE ACCESO (USUARIO/CONTRASEÑA) | Q392: NO FUNCIONA EL USUARIO O CONTRASEÑA | R392: ERROR INICIO DE SESIÓN | S392: 22/10/2025 EN COMUNICACIÓN CON EL CLIENTE ME INFORMA LA SRA LILIANA PACHECO QUE EL ERROR YA SE SOLUCIONÓ QUE REINICIO EL DATAFONO Y YA LE DEJO INGRESAR CON NORMALIDAD QUE EL DÍA DE HOY ESTÁ LABORANDO SIN NOVEDAD | T392: SOPORTE_TELEFÓNICO | U392: 0 | V392: LEJANA | W392: TERRESTRE | X392: DURAN ACOSTA FRANK YONNY | Y392: 1 | Z392: =IF(T392="SOPORTE_TELEFÓNICO",'TARIFAS 2025'!$B$14,IF(V392="PRINCIPAL",'TARIFAS 2025'!$B$8,IF(V392="INTERMEDIA",'TARIFAS 2025'!$C$8,IF(V392="LEJANA",'TARIFAS 2025'!$D$8)))) -> 22000 | AA392: =Z392*Y392 -> 22000
A393: CALI | B393: =VLOOKUP(A393,'CENTROS DE COSTOS'!A:D,2,0) -> 0036-0003 | C393: =VLOOKUP(A393,'CENTROS DE COSTOS'!A:D,3,0) -> Wompi Suroccidente | D393: 76130 | E393: 2868724 | F393: 22203 | G393: INCIDENTE | H393: VALLE DEL CAUCA | I393: CANDELARIA | J393: BARRIO CENTRAL II - CANDELARIA | K393: WOMPI | L393: FO-25-1666543 | M393: 45940.462 | N393: 45952.363 | O393: INCIDENTE | P393: TRANSACCION ERROR | Q393: UNA MISMA TRX ESTA PRESENTANDO FALLAS | R393: AFECTACIÓN GENERALIZADA DE LOS SERVICIOS | S393: 21/10/2025 SE REALIZA ESCALAMIENTO A WOMPI Y SEGUN RESPUESTA Y VALIDACION CON USUARIO YA LAS TRANSACCIONES DE NEQUI LE ESTAN PERMITIENDO POR LO CUAL SE CIERRA CASO | T393: SOPORTE_TELEFÓNICO | U393: 64 | V393: INTERMEDIA | W393: TERRESTRE | X393: HENAO CARDONA DIEGO FERNANDO | Y393: 1 | Z393: =IF(T393="SOPORTE_TELEFÓNICO",'TARIFAS 2025'!$B$14,IF(V393="PRINCIPAL",'TARIFAS 2025'!$B$8,IF(V393="INTERMEDIA",'TARIFAS 2025'!$C$8,IF(V393="LEJANA",'TARIFAS 2025'!$D$8)))) -> 22000 | AA393: =Z393*Y393 -> 22000
A394: PASTO | B394: =VLOOKUP(A394,'CENTROS DE COSTOS'!A:D,2,0) -> 0036-0003 | C394: =VLOOKUP(A394,'CENTROS DE COSTOS'!A:D,3,0) -> Wompi Suroccidente | D394: 52381 | E394: 2870837 | F394: 31897 | G394: INCIDENTE | H394: NARIÑO | I394: LA FLORIDA | J394: BARRIO EL BOSQUE LA FLORIDA | K394: WOMPI | L394: FO-25-1668347 | M394: 45940.662 | N394: 45952.369 | O394: INCIDENTE | P394: EQUIPO | Q394: DATAFONO NO ENCIENDE | R394: FUENTE DE PODER | S394: 21/10/2025 SE HABLA CON EL CLIENTE Y SE VALIDA PROBLEMAS DE CARGA EN EL DATAFONO EL CLIENTE INDICA QUE LO CARGA CON EL CARGADOR QUE LE LLEGO PERO CARGA MUY RAPIDO Y ASI MISMO SE DESCARGA, SE LE INDICA CARGAR CON EL CARGADOR DEL CELULAR YA QUE NO TENEMOS ESTE ACCESORIO AUN PARA CAMBIO SI SE REQUIERE, EL CLIENTE SEGUIRA CARGANDOLO CON EL CARGADOR DEL CELULAR HABER COMO SIGUE TRABAJANDO | T394: SOPORTE_TELEFÓNICO | U394: 0 | V394: INTERMEDIA | W394: TERRESTRE | X394: HENAO CARDONA DIEGO FERNANDO | Y394: 1 | Z394: =IF(T394="SOPORTE_TELEFÓNICO",'TARIFAS 2025'!$B$14,IF(V394="PRINCIPAL",'TARIFAS 2025'!$B$8,IF(V394="INTERMEDIA",'TARIFAS 2025'!$C$8,IF(V394="LEJANA",'TARIFAS 2025'!$D$8)))) -> 22000 | AA394: =Z394*Y394 -> 22000
A395: PEREIRA | B395: =VLOOKUP(A395,'CENTROS DE COSTOS'!A:D,2,0) -> 0036-0002 | C395: =VLOOKUP(A395,'CENTROS DE COSTOS'!A:D,3,0) -> Wompi Eje Cafetero | D395: 66001 | E395: 2870978 | F395: 74598 | G395: INCIDENTE | H395: RISARALDA | I395: PEREIRA | J395: BARRIO VENECIA PEREIRA 2 | K395: WOMPI | L395: FO-25-1668440 | M395: 45940.677 | N395: 45952.374 | O395: INCIDENTE | P395: EQUIPO | Q395: DATAFONO NO ENCIENDE | R395: FUENTE DE PODER | S395: 21/10/2025 SE REALIZA VALIDACION CON EL CLIENTE Y SE LE INFORMA QUE POR AHORA NO CONTAMOS EL CARGADO COMO ACCESORIO PARA CAMBIO SE ESTA EN ESPERA DE LA LLEGADA DE ESTE PARA PROCEDER CON LOS CAMBIOS, POR AHORA SE DEBE SEGUIR REALIZANDO LA LABOR DE CARGA CON EL CARGADOR DEL CELULAR | T395: SOPORTE_TELEFÓNICO | U395: 32 | V395: PRINCIPAL | W395: TERRESTRE | X395: HENAO CARDONA DIEGO FERNANDO | Y395: 1 | Z395: =IF(T395="SOPORTE_TELEFÓNICO",'TARIFAS 2025'!$B$14,IF(V395="PRINCIPAL",'TARIFAS 2025'!$B$8,IF(V395="INTERMEDIA",'TARIFAS 2025'!$C$8,IF(V395="LEJANA",'TARIFAS 2025'!$D$8)))) -> 22000 | AA395: =Z395*Y395 -> 22000
A396: VILLAVICENCIO | B396: =VLOOKUP(A396,'CENTROS DE COSTOS'!A:D,2,0) -> 0036-0006 | C396: =VLOOKUP(A396,'CENTROS DE COSTOS'!A:D,3,0) -> Wompi Oriente | D396: 50001 | E396: 2913180 | F396: 57258 | G396: INCIDENTE | H396: META | I396: VILLAVICENCIO | J396: BARRIO 8VA ETAPA ESPERANZA VILLAVICENCIO | K396: WOMPI | L396: FO-25-1711692 | M396: 45951.476 | N396: 45952.401 | O396: INCIDENTE | P396: SOFTWARE | Q396: APP ELIMINADA | R396: APP ELIMINADA POR EL CB | S396: 22/10/2025 SE REALIZA DESCARGA REMORA POR TELCALL SE CARGA ARCHIVOS SE ENTREGA ALA SEÑORA MARTHA FUENTE NÚMERO DE CONTACTO 3103815664 SE REALIZA VISITA TECNICA REINSTALAR APP SE REALIZA PRUEBAS BÁSICAS SIN NOVEDAS | T396: VISITA_TÉCNICA | U396: 16 | V396: PRINCIPAL | W396: TERRESTRE | X396: ROZO JIMENEZ EDGAR ARMANDO | Y396: 1 | Z396: =IF(T396="SOPORTE_TELEFÓNICO",'TARIFAS 2025'!$B$14,IF(V396="PRINCIPAL",'TARIFAS 2025'!$B$8,IF(V396="INTERMEDIA",'TARIFAS 2025'!$C$8,IF(V396="LEJANA",'TARIFAS 2025'!$D$8)))) -> 51282 | AA396: =Z396*Y396 -> 51282
... A568: NEIVA | B568: =VLOOKUP(A568,'CENTROS DE COSTOS'!A:D,2,0) -> 0036-0006 | C568: =VLOOKUP(A568,'CENTROS DE COSTOS'!A:D,3,0) -> Wompi Oriente | D568: 41132 | E568: 2958333 | F568: 27629 | G568: INCIDENTE | H568: HUILA | I568: CAMPOALEGRE | J568: LA GUIPA | K568: WOMPI | L568: FO-25-1760218 | M568: 45960.46 | N568: 45961.691 | O568: INCIDENTE | P568: NAVEGACION LENTA | Q568: USUARIO NO PUEDE NAVEGAR ENTRE PANTALLAS O LA APP NO ABRE SE QUEDA CARGANDO | R568: CACHE | S568: 31/10/2025 EN LLAMADA CON EL SEÑOR HUGO URRUTIA AL NÚMERO 3188276024 INFORMA QUE EL DATAFONO YA SE ENCUENTRA TRABAJANDO NORMALMENTE. | T568: SOPORTE_TELEFÓNICO | U568: 24 | V568: INTERMEDIA | W568: TERRESTRE | X568: DIAZ VARGAS JONATHAN MIGUEL | Y568: 1 | Z568: =IF(T568="SOPORTE_TELEFÓNICO",'TARIFAS 2025'!$B$14,IF(V568="PRINCIPAL",'TARIFAS 2025'!$B$8,IF(V568="INTERMEDIA",'TARIFAS 2025'!$C$8,IF(V568="LEJANA",'TARIFAS 2025'!$D$8)))) -> 22000 | AA568: =Z568*Y568 -> 22000
AA569: =SUM(AA2:AA568) -> 41590853

Sheet OC PAPALERÍA
A1: CIUDAD SEDE | B1: CENTRO_COSTO | C1: DESCRIPCION CENTRO DE COSTOS | D1: CÓDIGO DANE | E1: TA/CODIGO ACTIVIDAD | F1: CODIGO CB | G1: ACTIVIDAD | H1: DEPARTAMENTO | I1: CIUDAD | J1: NOMBRE DEL CB | K1: RED | L1: FO | M1: FECHA ASIGNACION A LINEA COMUNICACIONES | N1: FECHA DEL CIERRE DEL TICKET (DD/MM/AAAA) | O1: SOLICITUD | P1: DESCRIPCIÓN | Q1: ESTADO | R1: CAUSAL ESTADO | S1: OBSERVACION | T1: FORMA DE ATENCIÓN | U1: CANTIDAD DE ROLLOS | V1: TIPOLOGIA | W1: TIPO DE TRAYECTO | X1: NOMBRE DEL TECNICO | Y1: DIAS DE ACTIVIDAD | Z1: VALOR DIAS ACTIVIDAD | AA1: VALOR TOTAL
A2: MONTERIA | B2: =VLOOKUP(A2,'CENTROS DE COSTOS'!A:D,2,0) -> 0036-0001 | C2: =VLOOKUP(A2,'CENTROS DE COSTOS'!A:D,3,0) -> Wompi Costa | D2: 23001 | E2: 2803122 | F2: 74154 | G2: ORDEN DE CAMBIO | H2: CORDOBA | I2: MONTERIA | J2: TIENDA MARIA JOSE 03 | K2: WOMPI | L2: FO-25-1593539 | M2: 45929.333 | N2: 45931.342 | O2: ROLLOS | P2: ROLLOS | Q2: EJECUTADO_EXITOSO | R2: EJECUTADO EXITOSO | S2: 27/09/2025 SE ESCALA AL COORDINADOR DE ZONA PARA ENTREGA DE ROLLOS EN SITIO | 30/09/2025 SE REALIZA VISITA TÉCNICA PARA ENTREGA DE 56 ROLLOS PARA DATÁFONO, NO SE INTERVIENE TERMINAL Y LA ENTREGA SE REALIZA SIN NOVEDAD. | T2: VISITA_TÉCNICA | U2: 56 | V2: PRINCIPAL | W2: =VLOOKUP(D2,TIPOLOGIA!A:F,6,0) -> TERRESTRE | X2: TÉCNICO DE CAMPO | Y2: 1 | Z2: =IF(T2="SOPORTE_TELEFÓNICO",'TARIFAS 2025'!$B$14,IF(V2="PRINCIPAL",'TARIFAS 2025'!$B$11,IF(V2="INTERMEDIA",'TARIFAS 2025'!$C$11,IF(V2="LEJANA",'TARIFAS 2025'!$D$11)))) -> 31419 | AA2: =Z2*Y2 -> 31419
A3: SINCELEJO | B3: =VLOOKUP(A3,'CENTROS DE COSTOS'!A:D,2,0) -> 0036-0001 | C3: =VLOOKUP(A3,'CENTROS DE COSTOS'!A:D,3,0) -> Wompi Costa | D3: 70001 | E3: 2803153 | F3: 79137 | G3: ORDEN DE CAMBIO | H3: SUCRE | I3: SINCELEJO | J3: BARRIO VILLA MADY SINCELEJO | K3: WOMPI | L3: FO-25-1593528 | M3: 45929.333 | N3: 45931.344 | O3: ROLLOS | P3: ROLLOS | Q3: EJECUTADO_EXITOSO | R3: EJECUTADO EXITOSO | S3: 27/09/2025 SE ESCALA AL COORDINADOR DE ZONA PARA ENTREGA DE ROLLOS EN SITIO | 30/09/2025 SE VISITA COMERCIO Y SE HACE ENTREGA DE 32 ROLLOS A LA SEÑORA DURLY GÓMEZ. | T3: VISITA_TÉCNICA | U3: 32 | V3: PRINCIPAL | W3: =VLOOKUP(D3,TIPOLOGIA!A:F,6,0) -> TERRESTRE | X3: CASSIANI PEREZ RAUL RAMIRO | Y3: 1 | Z3: =IF(T3="SOPORTE_TELEFÓNICO",'TARIFAS 2025'!$B$14,IF(V3="PRINCIPAL",'TARIFAS 2025'!$B$11,IF(V3="INTERMEDIA",'TARIFAS 2025'!$C$11,IF(V3="LEJANA",'TARIFAS 2025'!$D$11)))) -> 31419 | AA3: =Z3*Y3 -> 31419
A4: CUCUTA | B4: =VLOOKUP(A4,'CENTROS DE COSTOS'!A:D,2,0) -> 0036-0007 | C4: =VLOOKUP(A4,'CENTROS DE COSTOS'!A:D,3,0) -> Wompi Santander | D4: 54001 | E4: 2808678 | F4: 77662 | G4: ORDEN DE CAMBIO | H4: NORTE DE SANTANDER | I4: CUCUTA | J4: BARRIO COMUNEROS CUCUTA 13 | K4: WOMPI | L4: FO-25-1599059 | M4: 45929.536 | N4: 45931.356 | O4: ROLLOS | P4: ROLLOS | Q4: EJECUTADO_EXITOSO | R4: EJECUTADO EXITOSO | S4: 29/09/2025 SE ESCALA AL COORDINADOR DE ZONA PARA ENTREGA DE ROLLOS EN SITIO | 30/09/2025 SE REALIZA ENTREGA DE 32 ROLLOS WOMPI OK | T4: VISITA_TÉCNICA | U4: 32 | V4: PRINCIPAL | W4: =VLOOKUP(D4,TIPOLOGIA!A:F,6,0) -> TERRESTRE | X4: CACERES HERNANDEZ ANDRES | Y4: 1 | Z4: =IF(T4="SOPORTE_TELEFÓNICO",'TARIFAS 2025'!$B$14,IF(V4="PRINCIPAL",'TARIFAS 2025'!$B$11,IF(V4="INTERMEDIA",'TARIFAS 2025'!$C$11,IF(V4="LEJANA",'TARIFAS 2025'!$D$11)))) -> 31419 | AA4: =Z4*Y4 -> 31419
A5: CUCUTA | B5: =VLOOKUP(A5,'CENTROS DE COSTOS'!A:D,2,0) -> 0036-0007 | C5: =VLOOKUP(A5,'CENTROS DE COSTOS'!A:D,3,0) -> Wompi Santander | D5: 54001 | E5: 2812665 | F5: 40083 | G5: ORDEN DE CAMBIO | H5: NORTE DE SANTANDER | I5: CUCUTA | J5: DROGUERIA FARMA OSPINA PEREZ | K5: WOMPI | L5: FO-25-1601892 | M5: 45930.355 | N5: 45931.362 | O5: ROLLOS | P5: ROLLOS | Q5: EJECUTADO_EXITOSO | R5: EJECUTADO EXITOSO | S5: 30/09/2025 SE ESCALA AL COORDINADOR DE ZONA PARA ENTREGA DE ROLLOS EN SITIO | 30/09/2025 SE REALIZA ENTREGA DE 64 ROLLOS WOMPI OK | T5: VISITA_TÉCNICA | U5: 64 | V5: PRINCIPAL | W5: =VLOOKUP(D5,TIPOLOGIA!A:F,6,0) -> TERRESTRE | X5: DURAN ACOSTA FRANK YONNY | Y5: 1 | Z5: =IF(T5="SOPORTE_TELEFÓNICO",'TARIFAS 2025'!$B$14,IF(V5="PRINCIPAL",'TARIFAS 2025'!$B$11,IF(V5="INTERMEDIA",'TARIFAS 2025'!$C$11,IF(V5="LEJANA",'TARIFAS 2025'!$D$11)))) -> 31419 | AA5: =Z5*Y5 -> 31419
A6: IBAGUE | B6: =VLOOKUP(A6,'CENTROS DE COSTOS'!A:D,2,0) -> 0036-0006 | C6: =VLOOKUP(A6,'CENTROS DE COSTOS'!A:D,3,0) -> Wompi Oriente | D6: 73001 | E6: 2812794 | F6: 48408 | G6: ORDEN DE CAMBIO | H6: TOLIMA | I6: IBAGUE | J6: OFFICE SYA SERVICES | K6: WOMPI | L6: FO-25-1602539 | M6: 45930.365 | N6: 45931.365 | O6: ROLLOS | P6: ROLLOS | Q6: EJECUTADO_EXITOSO | R6: EJECUTADO EXITOSO | S6: 30/09/2025 SE ESCALA AL COORDINADOR DE ZONA PARA ENTREGA DE ROLLOS EN SITIO | 30/09/2025 SE HACE ENTREGA DE 16 ROLLOS WOMPI EN DIRECCIÓN INDICADA | T6: VISITA_TÉCNICA | U6: 16 | V6: PRINCIPAL | W6: =VLOOKUP(D6,TIPOLOGIA!A:F,6,0) -> TERRESTRE | X6: DURAN ACOSTA FRANK YONNY | Y6: 1 | Z6: =IF(T6="SOPORTE_TELEFÓNICO",'TARIFAS 2025'!$B$14,IF(V6="PRINCIPAL",'TARIFAS 2025'!$B$11,IF(V6="INTERMEDIA",'TARIFAS 2025'!$C$11,IF(V6="LEJANA",'TARIFAS 2025'!$D$11)))) -> 31419 | AA6: =Z6*Y6 -> 31419
A7: CUCUTA | B7: =VLOOKUP(A7,'CENTROS DE COSTOS'!A:D,2,0) -> 0036-0007 | C7: =VLOOKUP(A7,'CENTROS DE COSTOS'!A:D,3,0) -> Wompi Santander | D7: 54405 | E7: 2813765 | F7: 46663 | G7: ORDEN DE CAMBIO | H7: NORTE DE SANTANDER | I7: LOS PATIOS | J7: DROGUERIA CENTRAL PLUS SAS | K7: WOMPI | L7: FO-25-1602738 | M7: 45930.41 | N7: 45931.367 | O7: ROLLOS | P7: ROLLOS | Q7: EJECUTADO_EXITOSO | R7: EJECUTADO EXITOSO | S7: 30/09/2025 SE ESCALA AL COORDINADOR DE ZONA PARA ENTREGA DE ROLLOS EN SITIO | 30/09/2025 SE VISITA COMERCIO Y SE ENTREGAN 48 ROLLOS OK. | T7: VISITA_TÉCNICA | U7: 48 | V7: PRINCIPAL | W7: =VLOOKUP(D7,TIPOLOGIA!A:F,6,0) -> TERRESTRE | X7: GUTIERREZ CAMILO ANDRES | Y7: 1 | Z7: =IF(T7="SOPORTE_TELEFÓNICO",'TARIFAS 2025'!$B$14,IF(V7="PRINCIPAL",'TARIFAS 2025'!$B$11,IF(V7="INTERMEDIA",'TARIFAS 2025'!$C$11,IF(V7="LEJANA",'TARIFAS 2025'!$D$11)))) -> 31419 | AA7: =Z7*Y7 -> 31419
A8: BUCARAMANGA | B8: =VLOOKUP(A8,'CENTROS DE COSTOS'!A:D,2,0) -> 0036-0007 | C8: =VLOOKUP(A8,'CENTROS DE COSTOS'!A:D,3,0) -> Wompi Santander | D8: 68276 | E8: 2818143 | F8: 71549 | G8: ORDEN DE CAMBIO | H8: SANTANDER | I8: FLORIDABLANCA | J8: BARRIO LAGOS 1 FLORIDABLANCA | K8: WOMPI | L8: FO-25-1607025 | M8: 45930.708 | N8: 45931.388 | O8: ROLLOS | P8: ROLLOS | Q8: EJECUTADO_EXITOSO | R8: EJECUTADO EXITOSO | S8: 30/09/2025 SE ESCALA AL COORDINADOR DE ZONA PARA ENTREGA DE ROLLOS EN SITIO | 01/10/2025 ENTREGA DE 16 ROLLOS PARA DATAFONO | T8: VISITA_TÉCNICA | U8: 16 | V8: PRINCIPAL | W8: =VLOOKUP(D8,TIPOLOGIA!A:F,6,0) -> TERRESTRE | X8: TORRES MANTILLA JOSE DANIEL | Y8: 1 | Z8: =IF(T8="SOPORTE_TELEFÓNICO",'TARIFAS 2025'!$B$14,IF(V8="PRINCIPAL",'TARIFAS 2025'!$B$11,IF(V8="INTERMEDIA",'TARIFAS 2025'!$C$11,IF(V8="LEJANA",'TARIFAS 2025'!$D$11)))) -> 31419 | AA8: =Z8*Y8 -> 31419
A9: MEDELLIN | B9: =VLOOKUP(A9,'CENTROS DE COSTOS'!A:D,2,0) -> 0036-0005 | C9: =VLOOKUP(A9,'CENTROS DE COSTOS'!A:D,3,0) -> Wompi Noroccidente | D9: 5467 | E9: 2795410 | F9: 38048 | G9: ORDEN DE CAMBIO | H9: ANTIOQUIA | I9: MONTEBELLO | J9: BARRIO LA GRANJA MONTEBELLO | K9: WOMPI | L9: FO-25-1585680 | M9: 45925.655 | N9: 45931.396 | O9: ROLLOS | P9: ROLLOS | Q9: EJECUTADO_EXITOSO | R9: EJECUTADO EXITOSO | S9: 25/09/2025 SE ESCALA AL COORDINADOR DE ZONA PARA ENTREGA DE ROLLOS EN SITIO | 30/09/2025 SE ENVÍAS 16 ROLLOS WOMPI POR FLOTA MONTEBELLO. SE CONFIRMÓ RECEPCIÓN CON USUARIO SEÑOR NELSON CUERVO | T9: ENVÍO | U9: 16 | V9: INTERMEDIA | W9: =VLOOKUP(D9,TIPOLOGIA!A:F,6,0) -> TERRESTRE | X9: PEÑA DIAZ IVAN YESID | Y9: 1 | Z9: =IF(T9="SOPORTE_TELEFÓNICO",'TARIFAS 2025'!$B$14,IF(V9="PRINCIPAL",'TARIFAS 2025'!$B$11,IF(V9="INTERMEDIA",'TARIFAS 2025'!$C$11,IF(V9="LEJANA",'TARIFAS 2025'!$D$11)))) -> 36351 | AA9: =Z9*Y9 -> 36351
A10: MEDELLIN | B10: =VLOOKUP(A10,'CENTROS DE COSTOS'!A:D,2,0) -> 0036-0005 | C10: =VLOOKUP(A10,'CENTROS DE COSTOS'!A:D,3,0) -> Wompi Noroccidente | D10: 5001 | E10: 2790246 | F10: 55292 | G10: ORDEN DE CAMBIO | H10: ANTIOQUIA | I10: MEDELLÍN | J10: DROGUERIA MARIANA GM | K10: WOMPI | L10: FO-25-1580825 | M10: 45925.333 | N10: 45931.412 | O10: ROLLOS | P10: ROLLOS | Q10: EJECUTADO_EXITOSO | R10: EJECUTADO EXITOSO | S10: 25/09/2025 SE ESCALA AL COORDINADOR DE ZONA PARA ENTREGA DE ROLLOS EN SITIO | 01/10/2025 SE REALIZA ENTREGA DE 48 ROLLOS POR EL OPERADOR LOGISTICO VELOCES CON LA GUIA V4001596065 | T10: VISITA_TÉCNICA | U10: 48 | V10: PRINCIPAL | W10: =VLOOKUP(D10,TIPOLOGIA!A:F,6,0) -> TERRESTRE | X10: BARRIENTOS HERNANDEZ CRISTIAN HORACIO | Y10: 1 | Z10: =IF(T10="SOPORTE_TELEFÓNICO",'TARIFAS 2025'!$B$14,IF(V10="PRINCIPAL",'TARIFAS 2025'!$B$11,IF(V10="INTERMEDIA",'TARIFAS 2025'!$C$11,IF(V10="LEJANA",'TARIFAS 2025'!$D$11)))) -> 31419 | AA10: =Z10*Y10 -> 31419
A11: MEDELLIN | B11: =VLOOKUP(A11,'CENTROS DE COSTOS'!A:D,2,0) -> 0036-0005 | C11: =VLOOKUP(A11,'CENTROS DE COSTOS'!A:D,3,0) -> Wompi Noroccidente | D11: 5001 | E11: 2798139 | F11: 69281 | G11: ORDEN DE CAMBIO | H11: ANTIOQUIA | I11: MEDELLIN | J11: LAURELES- LORENA | K11: WOMPI | L11: FO-25-1587437 | M11: 45926.397 | N11: 45931.412 | O11: ROLLOS | P11: ROLLOS | Q11: EJECUTADO_EXITOSO | R11: EJECUTADO EXITOSO | S11: 26/09/2025 SE ESCALA AL COORDINADOR DE ZONA PARA ENTREGA DE ROLLOS EN SITIO | 01/10/2025 SE REALIZA ENTREGA DE 56 ROLLOS POR EL OPERADOR LOGISTICO VELOCES CON LA GUIA V4001603496 | T11: VISITA_TÉCNICA | U11: 56 | V11: PRINCIPAL | W11: =VLOOKUP(D11,TIPOLOGIA!A:F,6,0) -> TERRESTRE | X11: RIOS CASTRILLON JUAN SEBASTIAN | Y11: 1 | Z11: =IF(T11="SOPORTE_TELEFÓNICO",'TARIFAS 2025'!$B$14,IF(V11="PRINCIPAL",'TARIFAS 2025'!$B$11,IF(V11="INTERMEDIA",'TARIFAS 2025'!$C$11,IF(V11="LEJANA",'TARIFAS 2025'!$D$11)))) -> 31419 | AA11: =Z11*Y11 -> 31419
A12: MEDELLIN | B12: =VLOOKUP(A12,'CENTROS DE COSTOS'!A:D,2,0) -> 0036-0005 | C12: =VLOOKUP(A12,'CENTROS DE COSTOS'!A:D,3,0) -> Wompi Noroccidente | D12: 5001 | E12: 2798628 | F12: 37783 | G12: ORDEN DE CAMBIO | H12: ANTIOQUIA | I12: MEDELLIN | J12: BARRIO CAMPO VALDES MEDELLIN 2 | K12: WOMPI | L12: FO-25-1588697 | M12: 45926.419 | N12: 45931.415 | O12: ROLLOS | P12: ROLLOS | Q12: EJECUTADO_EXITOSO | R12: EJECUTADO EXITOSO | S12: 26/09/2025 SE ESCALA AL COORDINADOR DE ZONA PARA ENTREGA DE ROLLOS EN SITIO | 01/10/2025 SE REALIZA ENTREGA DE 56 ROLLOS POR EL OPERADOR LOGISTICO VELOCES CON LA GUIA V4001603497 | T12: VISITA_TÉCNICA | U12: 56 | V12: PRINCIPAL | W12: =VLOOKUP(D12,TIPOLOGIA!A:F,6,0) -> TERRESTRE | X12: BETANCUR AGUIRRE EDGAR AUGUSTO | Y12: 1 | Z12: =IF(T12="SOPORTE_TELEFÓNICO",'TARIFAS 2025'!$B$14,IF(V12="PRINCIPAL",'TARIFAS 2025'!$B$11,IF(V12="INTERMEDIA",'TARIFAS 2025'!$C$11,IF(V12="LEJANA",'TARIFAS 2025'!$D$11)))) -> 31419 | AA12: =Z12*Y12 -> 31419
A13: MEDELLIN | B13: =VLOOKUP(A13,'CENTROS DE COSTOS'!A:D,2,0) -> 0036-0005 | C13: =VLOOKUP(A13,'CENTROS DE COSTOS'!A:D,3,0) -> Wompi Noroccidente | D13: 5001 | E13: 2799271 | F13: 68506 | G13: ORDEN DE CAMBIO | H13: ANTIOQUIA | I13: MEDELLÍN | J13: AUTOSERVICIO EL CARACOL TM | K13: WOMPI | L13: FO-25-1588690 | M13: 45926.471 | N13: 45931.415 | O13: ROLLOS | P13: ROLLOS | Q13: EJECUTADO_EXITOSO | R13: EJECUTADO EXITOSO | S13: 26/09/2025 SE ESCALA AL COORDINADOR DE ZONA PARA ENTREGA DE ROLLOS EN SITIO | 01/10/2025 SE REALIZA ENTREGA DE 64 ROLLOS POR EL OPERADOR LOGISTICO VELOCES CON LA GUIA V4001603498 | T13: VISITA_TÉCNICA | U13: 64 | V13: PRINCIPAL | W13: =VLOOKUP(D13,TIPOLOGIA!A:F,6,0) -> TERRESTRE | X13: BETANCUR AGUIRRE EDGAR AUGUSTO | Y13: 1 | Z13: =IF(T13="SOPORTE_TELEFÓNICO",'TARIFAS 2025'!$B$14,IF(V13="PRINCIPAL",'TARIFAS 2025'!$B$11,IF(V13="INTERMEDIA",'TARIFAS 2025'!$C$11,IF(V13="LEJANA",'TARIFAS 2025'!$D$11)))) -> 31419 | AA13: =Z13*Y13 -> 31419
... A169: CALI | B169: =VLOOKUP(A169,'CENTROS DE COSTOS'!A:D,2,0) -> 0036-0003 | C169: =VLOOKUP(A169,'CENTROS DE COSTOS'!A:D,3,0) -> Wompi Suroccidente | D169: 19001 | E169: 2824503 | F169: 42270 | G169: ORDEN DE CAMBIO | H169: CAUCA | I169: POPAYAN | J169: PIKIÑA COMERCIALIZADORA | K169: WOMPI | L169: FO-25-1612731 | M169: 45931.637 | N169: 45932.731 | O169: ROLLOS | P169: ROLLOS | Q169: EJECUTADO_EXITOSO | R169: EJECUTADO EXITOSO | S169: 01/10/2025 SE ESCALA AL COORDINADOR DE ZONA PARA ENTREGA DE ROLLOS EN SITIO | 02/10/2025 SE INGRESA Y SE ENTREGA 16 ROLLOS DE WOMPI | T169: VISITA_TÉCNICA | U169: 16 | V169: LEJANA | W169: =VLOOKUP(D169,TIPOLOGIA!A:F,6,0) -> TERRESTRE | X169: THOMAS CAMPO SIGIFREDO SEGUNDO | Y169: 1 | Z169: =IF(T169="SOPORTE_TELEFÓNICO",'TARIFAS 2025'!$B$14,IF(V169="PRINCIPAL",'TARIFAS 2025'!$B$11,IF(V169="INTERMEDIA",'TARIFAS 2025'!$C$11,IF(V169="LEJANA",'TARIFAS 2025'!$D$11)))) -> 40250 | AA169: =Z169*Y169 -> 40250
A170: BOGOTA | B170: =VLOOKUP(A170,'CENTROS DE COSTOS'!A:D,2,0) -> 0036-0004 | C170: =VLOOKUP(A170,'CENTROS DE COSTOS'!A:D,3,0) -> Wompi Centro | D170: 11001 | E170: 2798500 | F170: 32880 | G170: ORDEN DE CAMBIO | H170: CUNDINAMARCA | I170: BOGOTÁ | J170: MAGDA ELIZABETH ZABALETA GALINDO | K170: WOMPI | L170: FO-25-1588037 | FO-25-1596595 | M170: 45926.411 | N170: 45933.384 | O170: ROLLOS | P170: ROLLOS | Q170: EJECUTADO_EXITOSO | R170: EJECUTADO EXITOSO | S170: 26/09/2025 SE ESCALA AL COORDINADOR DE ZONA PARA ENTREGA DE ROLLOS EN SITIO | 27/09/2025 COMERCIO SE ENCUENTRA CERRADO SE COMUNICA CON EL CLIENTE DICE QUE SE ENCUENTRA EN CITA MEDICA Y HOY NO PUEDE | T170: VISITA_TÉCNICA | U170: 16 | V170: PRINCIPAL | W170: =VLOOKUP(D170,TIPOLOGIA!A:F,6,0) -> TERRESTRE | Y170: 2 | Z170: =IF(T170="SOPORTE_TELEFÓNICO",'TARIFAS 2025'!$B$14,IF(V170="PRINCIPAL",'TARIFAS 2025'!$B$11,IF(V170="INTERMEDIA",'TARIFAS 2025'!$C$11,IF(V170="LEJANA",'TARIFAS 2025'!$D$11)))) -> 31419 | AA170: =Z170*Y170 -> 62838
A171: CALI | B171: =VLOOKUP(A171,'CENTROS DE COSTOS'!A:D,2,0) -> 0036-0003 | C171: =VLOOKUP(A171,'CENTROS DE COSTOS'!A:D,3,0) -> Wompi Suroccidente | D171: 19001 | E171: 2815341 | F171: 71191 | G171: ORDEN DE CAMBIO | H171: CAUCA | I171: POPAYAN | J171: LA TIENDA DE LUZ MARY NORTE | K171: WOMPI | L171: FO-25-1604714 | M171: 45930.49 | N171: 45933.392 | O171: ROLLOS | P171: ROLLOS | Q171: EJECUTADO_EXITOSO | R171: EJECUTADO EXITOSO | S171: 30/09/2025 SE ESCALA AL COORDINADOR DE ZONA PARA ENTREGA DE ROLLOS EN SITIO | 02/10/2025 SE INGRESA Y SE ENTREGAN 32 ROLLOS DE WOMPI | T171: VISITA_TÉCNICA | U171: 32 | V171: LEJANA | W171: =VLOOKUP(D171,TIPOLOGIA!A:F,6,0) -> TERRESTRE | X171: BARRAGAN LAGOS JUAN MANUEL | GONZALEZ FANDIÑO SANTIAGO ERNESTO | Y171: 1 | Z171: =IF(T171="SOPORTE_TELEFÓNICO",'TARIFAS 2025'!$B$14,IF(V171="PRINCIPAL",'TARIFAS 2025'!$B$11,IF(V171="INTERMEDIA",'TARIFAS 2025'!$C$11,IF(V171="LEJANA",'TARIFAS 2025'!$D$11)))) -> 40250 | AA171: =Z171*Y171 -> 40250
A172: CALI | B172: =VLOOKUP(A172,'CENTROS DE COSTOS'!A:D,2,0) -> 0036-0003 | C172: =VLOOKUP(A172,'CENTROS DE COSTOS'!A:D,3,0) -> Wompi Suroccidente | D172: 19001 | E172: 2817833 | F172: 71818 | G172: ORDEN DE CAMBIO | H172: CAUCA | I172: POPAYAN | J172: CAUCA POPAYAN 1 | K172: WOMPI | L172: FO-25-1606996 | M172: 45930.681 | N172: 45933.393 | O172: ROLLOS | P172: ROLLOS | Q172: EJECUTADO_EXITOSO | R172: EJECUTADO EXITOSO | S172: 30/09/2025 SE ESCALA AL COORDINADOR DE ZONA PARA ENTREGA DE ROLLOS EN SITIO | 02/10/2025 SE INGRESA Y SE ENTREGAN 16 ROLLOS DE WOMPI | T172: VISITA_TÉCNICA | U172: 16 | V172: LEJANA | W172: =VLOOKUP(D172,TIPOLOGIA!A:F,6,0) -> TERRESTRE | X172: INZANDARA MENDEZ JAIME ALEXANDER | Y172: 1 | Z172: =IF(T172="SOPORTE_TELEFÓNICO",'TARIFAS 2025'!$B$14,IF(V172="PRINCIPAL",'TARIFAS 2025'!$B$11,IF(V172="INTERMEDIA",'TARIFAS 2025'!$C$11,IF(V172="LEJANA",'TARIFAS 2025'!$D$11)))) -> 40250 | AA172: =Z172*Y172 -> 40250
A173: CUCUTA | B173: =VLOOKUP(A173,'CENTROS DE COSTOS'!A:D,2,0) -> 0036-0007 | C173: =VLOOKUP(A173,'CENTROS DE COSTOS'!A:D,3,0) -> Wompi Santander | D173: 54001 | E173: 2828521 | F173: 68382 | G173: ORDEN DE CAMBIO | H173: NORTE DE SANTANDER | I173: CUCUTA | J173: BOTELLO FERNANDEZ GROUP | K173: WOMPI | L173: FO-25-1614737 | M173: 45932.415 | N173: 45933.394 | O173: ROLLOS | P173: ROLLOS | Q173: EJECUTADO_EXITOSO | R173: EJECUTADO EXITOSO | S173: 02/10/2025 SE ESCALA AL COORDINADOR DE ZONA PARA ENTREGA DE ROLLOS EN SITIO | 02/10/2025 SE REALIZA VISITA, SE ENTREGAN 16 ROLLOS | T173: VISITA_TÉCNICA | U173: 16 | V173: PRINCIPAL | W173: =VLOOKUP(D173,TIPOLOGIA!A:F,6,0) -> TERRESTRE | X173: INZANDARA MENDEZ JAIME ALEXANDER | Y173: 1 | Z173: =IF(T173="SOPORTE_TELEFÓNICO",'TARIFAS 2025'!$B$14,IF(V173="PRINCIPAL",'TARIFAS 2025'!$B$11,IF(V173="INTERMEDIA",'TARIFAS 2025'!$C$11,IF(V173="LEJANA",'TARIFAS 2025'!$D$11)))) -> 31419 | AA173: =Z173*Y173 -> 31419
A174: NEIVA | B174: =VLOOKUP(A174,'CENTROS DE COSTOS'!A:D,2,0) -> 0036-0006 | C174: =VLOOKUP(A174,'CENTROS DE COSTOS'!A:D,3,0) -> Wompi Oriente | D174: 41001 | E174: 2828791 | F174: 24005 | G174: ORDEN DE CAMBIO | H174: HUILA | I174: NEIVA | J174: MULTISERVICIOS ROBERT | K174: WOMPI | L174: FO-25-1617565 | M174: 45932.439 | N174: 45933.395 | O174: ROLLOS | P174: ROLLOS | Q174: EJECUTADO_CANCELADO | R174: PETICIÓN RED | S174: 02/10/2025 SE ESCALA AL COORDINADOR DE ZONA PARA ENTREGA DE ROLLOS EN SITIO | 03/10/2025 SE LLEGA AL PUNTO , SE EVIDENCIA CORRESPONSAL DEL GRUPO AVAL , NO SE REALIZA ENTREGA DE ROLLOS . | T174: VISITA_TÉCNICA | V174: PRINCIPAL | W174: =VLOOKUP(D174,TIPOLOGIA!A:F,6,0) -> TERRESTRE | X174: PACHECO BUITRAGO JAVIER ALONSO | Y174: 1 | Z174: =IF(T174="SOPORTE_TELEFÓNICO",'TARIFAS 2025'!$B$14,IF(V174="PRINCIPAL",'TARIFAS 2025'!$B$11,IF(V174="INTERMEDIA",'TARIFAS 2025'!$C$11,IF(V174="LEJANA",'TARIFAS 2025'!$D$11)))) -> 31419 | AA174: =Z174*Y174 -> 31419
A175: BUCARAMANGA | B175: =VLOOKUP(A175,'CENTROS DE COSTOS'!A:D,2,0) -> 0036-0007 | C175: =VLOOKUP(A175,'CENTROS DE COSTOS'!A:D,3,0) -> Wompi Santander | D175: 68001 | E175: 2831113 | F175: 79985 | G175: ORDEN DE CAMBIO | H175: SANTANDER | I175: BUCARAMANGA | J175: BARRIO SAN FRANCISCO BUCARAMANGA 19 | K175: WOMPI | L175: FO-25-1617062 | M175: 45932.603 | N175: 45933.396 | O175: ROLLOS | P175: ROLLOS | Q175: EJECUTADO_EXITOSO | R175: EJECUTADO EXITOSO | S175: 02/10/2025 SE ESCALA AL COORDINADOR DE ZONA PARA ENTREGA DE ROLLOS EN SITIO | 03/10/2025 SE REALIZA VISITA A COMERCIO Y SE ENTREGAN 16 ROLLOS | T175: VISITA_TÉCNICA | U175: 16 | V175: PRINCIPAL | W175: =VLOOKUP(D175,TIPOLOGIA!A:F,6,0) -> TERRESTRE | X175: ANDRADE HERNANDEZ JUAN CARLOS | Y175: 1 | Z175: =IF(T175="SOPORTE_TELEFÓNICO",'TARIFAS 2025'!$B$14,IF(V175="PRINCIPAL",'TARIFAS 2025'!$B$11,IF(V175="INTERMEDIA",'TARIFAS 2025'!$C$11,IF(V175="LEJANA",'TARIFAS 2025'!$D$11)))) -> 31419 | AA175: =Z175*Y175 -> 31419
A176: IBAGUE | B176: =VLOOKUP(A176,'CENTROS DE COSTOS'!A:D,2,0) -> 0036-0006 | C176: =VLOOKUP(A176,'CENTROS DE COSTOS'!A:D,3,0) -> Wompi Oriente | D176: 73001 | E176: 2822817 | F176: 72072 | G176: ORDEN DE CAMBIO | H176: TOLIMA | I176: IBAGUE | J176: CAFÉ DE PASO WANDA | K176: WOMPI | L176: FO-25-1610456 | M176: 45931.506 | N176: 45933.397 | O176: ROLLOS | P176: ROLLOS | Q176: EJECUTADO_EXITOSO | R176: EJECUTADO EXITOSO | S176: 01/10/2025 SE ESCALA AL COORDINADOR DE ZONA PARA ENTREGA DE ROLLOS EN SITIO | 03/10/2025 SE HACE ENTREGA DE 16 ROLLOS WOMPI EN DIRECCIÓN INDICADA | T176: VISITA_TÉCNICA | U176: 16 | V176: PRINCIPAL | W176: =VLOOKUP(D176,TIPOLOGIA!A:F,6,0) -> TERRESTRE | X176: SANTOS GONZALEZ JOHAN FABIAN | Y176: 1 | Z176: =IF(T176="SOPORTE_TELEFÓNICO",'TARIFAS 2025'!$B$14,IF(V176="PRINCIPAL",'TARIFAS 2025'!$B$11,IF(V176="INTERMEDIA",'TARIFAS 2025'!$C$11,IF(V176="LEJANA",'TARIFAS 2025'!$D$11)))) -> 31419 | AA176: =Z176*Y176 -> 31419
A177: IBAGUE | B177: =VLOOKUP(A177,'CENTROS DE COSTOS'!A:D,2,0) -> 0036-0006 | C177: =VLOOKUP(A177,'CENTROS DE COSTOS'!A:D,3,0) -> Wompi Oriente | D177: 73001 | E177: 2828646 | F177: 48408 | G177: ORDEN DE CAMBIO | H177: TOLIMA | I177: IBAGUE | J177: OFFICE SYA SERVICES | K177: WOMPI | L177: FO-25-1617570 | M177: 45932.417 | N177: 45933.425 | O177: ROLLOS | P177: ROLLOS | Q177: EJECUTADO_EXITOSO | R177: EJECUTADO EXITOSO | S177: 02/10/2025 SE ESCALA AL COORDINADOR DE ZONA PARA ENTREGA DE ROLLOS EN SITIO | 03/10/2025 SE REALIZA ENTREGA DE 64 ROLLOS WOMPI POR SOLICITUD DEL CLIENTE. | T177: VISITA_TÉCNICA | U177: 64 | V177: PRINCIPAL | W177: =VLOOKUP(D177,TIPOLOGIA!A:F,6,0) -> TERRESTRE | X177: GUTIERREZ CAMILO ANDRES | Y177: 1 | Z177: =IF(T177="SOPORTE_TELEFÓNICO",'TARIFAS 2025'!$B$14,IF(V177="PRINCIPAL",'TARIFAS 2025'!$B$11,IF(V177="INTERMEDIA",'TARIFAS 2025'!$C$11,IF(V177="LEJANA",'TARIFAS 2025'!$D$11)))) -> 31419 | AA177: =Z177*Y177 -> 31419
A178: BUCARAMANGA | B178: =VLOOKUP(A178,'CENTROS DE COSTOS'!A:D,2,0) -> 0036-0007 | C178: =VLOOKUP(A178,'CENTROS DE COSTOS'!A:D,3,0) -> Wompi Santander | D178: 68001 | E178: 2829415 | F178: 74601 | G178: ORDEN DE CAMBIO | H178: SANTANDER | I178: BUCARAMANGA | J178: BARRIO CENTRO BUCARAMANGA 70 | K178: WOMPI | L178: FO-25-1615382 | M178: 45932.456 | N178: 45933.426 | O178: ROLLOS | P178: ROLLOS | Q178: EJECUTADO_EXITOSO | R178: EJECUTADO EXITOSO | S178: 02/10/2025 SE ESCALA AL COORDINADOR DE ZONA PARA ENTREGA DE ROLLOS EN SITIO | 03/10/2025 SE HACE PRESENCIA EN COMERCIO SE REALIZA ENTREGA DE 16 ROLLOS | T178: VISITA_TÉCNICA | U178: 16 | V178: PRINCIPAL | W178: =VLOOKUP(D178,TIPOLOGIA!A:F,6,0) -> TERRESTRE | X178: BARRAGAN TAFUR EDWIN ESTEBAN | Y178: 1 | Z178: =IF(T178="SOPORTE_TELEFÓNICO",'TARIFAS 2025'!$B$14,IF(V178="PRINCIPAL",'TARIFAS 2025'!$B$11,IF(V178="INTERMEDIA",'TARIFAS 2025'!$C$11,IF(V178="LEJANA",'TARIFAS 2025'!$D$11)))) -> 31419 | AA178: =Z178*Y178 -> 31419
A179: BOGOTA | B179: =VLOOKUP(A179,'CENTROS DE COSTOS'!A:D,2,0) -> 0036-0004 | C179: =VLOOKUP(A179,'CENTROS DE COSTOS'!A:D,3,0) -> Wompi Centro | D179: 11001 | E179: 2830056 | F179: 47420 | G179: ORDEN DE CAMBIO | H179: CUNDINAMARCA | I179: BOGOTA | J179: BARRIO RESTREPO BOGOTA 9 | K179: WOMPI | L179: FO-25-1615674 | M179: 45932.492 | N179: 45933.428 | O179: ROLLOS | P179: ROLLOS | Q179: EJECUTADO_EXITOSO | R179: EJECUTADO EXITOSO | S179: 02/10/2025 SE ESCALA AL COORDINADOR DE ZONA PARA ENTREGA DE ROLLOS EN SITIO | 03/10/2025 ENTREGA DE 24 ROLLOS EJECUTADO OK | T179: VISITA_TÉCNICA | U179: 24 | V179: PRINCIPAL | W179: =VLOOKUP(D179,TIPOLOGIA!A:F,6,0) -> TERRESTRE | X179: BARRERA ORTEGA MARLON STWAR | Y179: 1 | Z179: =IF(T179="SOPORTE_TELEFÓNICO",'TARIFAS 2025'!$B$14,IF(V179="PRINCIPAL",'TARIFAS 2025'!$B$11,IF(V179="INTERMEDIA",'TARIFAS 2025'!$C$11,IF(V179="LEJANA",'TARIFAS 2025'!$D$11)))) -> 31419 | AA179: =Z179*Y179 -> 31419
A180: MONTERIA | B180: =VLOOKUP(A180,'CENTROS DE COSTOS'!A:D,2,0) -> 0036-0001 | C180: =VLOOKUP(A180,'CENTROS DE COSTOS'!A:D,3,0) -> Wompi Costa | D180: 23001 | E180: 2831405 | F180: 61827 | G180: ORDEN DE CAMBIO | H180: CORDOBA | I180: MONTERIA | J180: MULTISERVICIOS 10.5 | K180: WOMPI | L180: FO-25-1617547 | M180: 45932.618 | N180: 45933.428 | O180: ROLLOS | P180: ROLLOS | Q180: EJECUTADO_EXITOSO | R180: EJECUTADO EXITOSO | S180: 02/10/2025 SE ESCALA AL COORDINADOR DE ZONA PARA ENTREGA DE ROLLOS EN SITIO | 03/10/2025 SE REALIZA ENTREGA DE 64 ROLLOS A CORRESPONSAL WOMPI. | T180: VISITA_TÉCNICA | U180: 64 | V180: PRINCIPAL | W180: =VLOOKUP(D180,TIPOLOGIA!A:F,6,0) -> TERRESTRE | X180: GOMEZ VEGA DAVID SNEYDER | Y180: 1 | Z180: =IF(T180="SOPORTE_TELEFÓNICO",'TARIFAS 2025'!$B$14,IF(V180="PRINCIPAL",'TARIFAS 2025'!$B$11,IF(V180="INTERMEDIA",'TARIFAS 2025'!$C$11,IF(V180="LEJANA",'TARIFAS 2025'!$D$11)))) -> 31419 | AA180: =Z180*Y180 -> 31419
A181: BUCARAMANGA | B181: =VLOOKUP(A181,'CENTROS DE COSTOS'!A:D,2,0) -> 0036-0007 | C181: =VLOOKUP(A181,'CENTROS DE COSTOS'!A:D,3,0) -> Wompi Santander | D181: 68276 | E181: 2831470 | F181: 51907 | G181: ORDEN DE CAMBIO | H181: SANTANDER | I181: FLORIDABLANCA | J181: BARRIO EL BOSQUE FLORIDABLANCA | K181: WOMPI | L181: FO-25-1617142 | M181: 45932.629 | N181: 45933.43 | O181: ROLLOS | P181: ROLLOS | Q181: EJECUTADO_EXITOSO | R181: EJECUTADO EXITOSO | S181: 02/10/2025 SE ESCALA AL COORDINADOR DE ZONA PARA ENTREGA DE ROLLOS EN SITIO | 03/10/2025 ENTREGA DE 24 ROLLOS PARA DATAFONO | T181: VISITA_TÉCNICA | U181: 24 | V181: PRINCIPAL | W181: =VLOOKUP(D181,TIPOLOGIA!A:F,6,0) -> TERRESTRE | X181: MARQUEZ HOYOS JEYSON DANIEL | Y181: 1 | Z181: =IF(T181="SOPORTE_TELEFÓNICO",'TARIFAS 2025'!$B$14,IF(V181="PRINCIPAL",'TARIFAS 2025'!$B$11,IF(V181="INTERMEDIA",'TARIFAS 2025'!$C$11,IF(V181="LEJANA",'TARIFAS 2025'!$D$11)))) -> 31419 | AA181: =Z181*Y181 -> 31419
A182: MONTERIA | B182: =VLOOKUP(A182,'CENTROS DE COSTOS'!A:D,2,0) -> 0036-0001 | C182: =VLOOKUP(A182,'CENTROS DE COSTOS'!A:D,3,0) -> Wompi Costa | D182: 23001 | E182: 2827206 | F182: 78088 | G182: ORDEN DE CAMBIO | H182: CORDOBA | I182: MONTERIA | J182: DULCE EMI | K182: WOMPI | L182: FO-25-1613901 | M182: 45932.353 | N182: 45933.434 | O182: ROLLOS | P182: ROLLOS | Q182: EJECUTADO_EXITOSO | R182: EJECUTADO EXITOSO | S182: 02/10/2025 SE ESCALA AL COORDINADOR DE ZONA PARA ENTREGA DE ROLLOS EN SITIO | 03/10/2025 SE REALIZA ENTREGA DE 16 ROLLO A CORRESPONSAL WOMPI. | T182: VISITA_TÉCNICA | U182: 16 | V182: PRINCIPAL | W182: =VLOOKUP(D182,TIPOLOGIA!A:F,6,0) -> TERRESTRE | X182: PEÑA DIAZ IVAN YESID | Y182: 1 | Z182: =IF(T182="SOPORTE_TELEFÓNICO",'TARIFAS 2025'!$B$14,IF(V182="PRINCIPAL",'TARIFAS 2025'!$B$11,IF(V182="INTERMEDIA",'TARIFAS 2025'!$C$11,IF(V182="LEJANA",'TARIFAS 2025'!$D$11)))) -> 31419 | AA182: =Z182*Y182 -> 31419
A183: VILLAVICENCIO | B183: =VLOOKUP(A183,'CENTROS DE COSTOS'!A:D,2,0) -> 0036-0006 | C183: =VLOOKUP(A183,'CENTROS DE COSTOS'!A:D,3,0) -> Wompi Oriente | D183: 50001 | E183: 2828330 | F183: 57262 | G183: ORDEN DE CAMBIO | H183: META | I183: VILLAVICENCIO | J183: GAMA ALTA STORE | K183: WOMPI | L183: FO-25-1617573 | M183: 45932.402 | N183: 45933.435 | O183: ROLLOS | P183: ROLLOS | Q183: EJECUTADO_EXITOSO | R183: EJECUTADO EXITOSO | S183: 02/10/2025 SE ESCALA AL COORDINADOR DE ZONA PARA ENTREGA DE ROLLOS EN SITIO | 03/10/2025 SE REALIZÓ LA VISTA AL CB POR SOLICITUD DE 48 ROLLOS, SE ENTREGAN SIN NOVEDAD TODO OK | T183: VISITA_TÉCNICA | U183: 48 | V183: PRINCIPAL | W183: =VLOOKUP(D183,TIPOLOGIA!A:F,6,0) -> TERRESTRE | X183: MARQUEZ HOYOS JEYSON DANIEL | Y183: 1 | Z183: =IF(T183="SOPORTE_TELEFÓNICO",'TARIFAS 2025'!$B$14,IF(V183="PRINCIPAL",'TARIFAS 2025'!$B$11,IF(V183="INTERMEDIA",'TARIFAS 2025'!$C$11,IF(V183="LEJANA",'TARIFAS 2025'!$D$11)))) -> 31419 | AA183: =Z183*Y183 -> 31419
A184: PASTO | B184: =VLOOKUP(A184,'CENTROS DE COSTOS'!A:D,2,0) -> 0036-0003 | C184: =VLOOKUP(A184,'CENTROS DE COSTOS'!A:D,3,0) -> Wompi Suroccidente | D184: 52001 | E184: 2826062 | F184: 31317 | G184: ORDEN DE CAMBIO | H184: NARIÑO | I184: PASTO | J184: SUPERTIENDA SU AMIGA | K184: WOMPI | L184: FO-25-1617576 | M184: 45932.333 | N184: 45933.436 | O184: ROLLOS | P184: ROLLOS | Q184: EJECUTADO_EXITOSO | R184: EJECUTADO EXITOSO | S184: 02/10/2025 SE ESCALA AL COORDINADOR DE ZONA PARA ENTREGA DE ROLLOS EN SITIO | 03/10/2025 SE REALIZA ENTREGA DE 64 ROLLOS WOMPI NO SE MANIPULA DATAFONO | T184: VISITA_TÉCNICA | U184: 64 | V184: PRINCIPAL | W184: =VLOOKUP(D184,TIPOLOGIA!A:F,6,0) -> TERRESTRE | X184: MOLINA CASTRO JAVIER ALBERTO | Y184: 1 | Z184: =IF(T184="SOPORTE_TELEFÓNICO",'TARIFAS 2025'!$B$14,IF(V184="PRINCIPAL",'TARIFAS 2025'!$B$11,IF(V184="INTERMEDIA",'TARIFAS 2025'!$C$11,IF(V184="LEJANA",'TARIFAS 2025'!$D$11)))) -> 31419 | AA184: =Z184*Y184 -> 31419
A185: MEDELLIN | B185: =VLOOKUP(A185,'CENTROS DE COSTOS'!A:D,2,0) -> 0036-0005 | C185: =VLOOKUP(A185,'CENTROS DE COSTOS'!A:D,3,0) -> Wompi Noroccidente | D185: 5360 | E185: 2813992 | F185: 76064 | G185: ORDEN DE CAMBIO | H185: ANTIOQUIA | I185: ITAGÜÍ | J185: FZ BELLEZA PERFECTA LU | K185: WOMPI | L185: FO-25-1602896 | M185: 45930.419 | N185: 45933.447 | O185: ROLLOS | P185: ROLLOS | Q185: EJECUTADO_EXITOSO | R185: EJECUTADO EXITOSO | S185: 30/09/2025 SE ESCALA AL COORDINADOR DE ZONA PARA ENTREGA DE ROLLOS EN SITIO | 03/10/2025 SE REALIZA ENTREGA DE 32 ROLLOS POR EL OPERADOR LOGISTICO VELOCES CON LA GUIA V4001617656 | T185: VISITA_TÉCNICA | U185: 32 | V185: PRINCIPAL | W185: =VLOOKUP(D185,TIPOLOGIA!A:F,6,0) -> TERRESTRE | X185: BRAVO MADROÑERO OSCAR ESTEBAN | Y185: 1 | Z185: =IF(T185="SOPORTE_TELEFÓNICO",'TARIFAS 2025'!$B$14,IF(V185="PRINCIPAL",'TARIFAS 2025'!$B$11,IF(V185="INTERMEDIA",'TARIFAS 2025'!$C$11,IF(V185="LEJANA",'TARIFAS 2025'!$D$11)))) -> 31419 | AA185: =Z185*Y185 -> 31419
A186: MEDELLIN | B186: =VLOOKUP(A186,'CENTROS DE COSTOS'!A:D,2,0) -> 0036-0005 | C186: =VLOOKUP(A186,'CENTROS DE COSTOS'!A:D,3,0) -> Wompi Noroccidente | D186: 5088 | E186: 2802987 | F186: 56909 | G186: ORDEN DE CAMBIO | H186: ANTIOQUIA | I186: BELLO | J186: BARRIO ALCALA DE BELLO BELLO | K186: WOMPI | L186: FO-25-1593537 | M186: 45929.333 | N186: 45933.447 | O186: ROLLOS | P186: ROLLOS | Q186: EJECUTADO_EXITOSO | R186: EJECUTADO EXITOSO | S186: 27/09/2025 SE ESCALA AL COORDINADOR DE ZONA PARA ENTREGA DE ROLLOS EN SITIO | 03/10/2025 SE REALIZA ENTREGA DE 64 ROLLOS POR EL OPERADOR LOGISTICO VELOCES CON LA GUIA V4001606781 | T186: VISITA_TÉCNICA | U186: 64 | V186: PRINCIPAL | W186: =VLOOKUP(D186,TIPOLOGIA!A:F,6,0) -> TERRESTRE | X186: BETANCUR AGUIRRE EDGAR AUGUSTO | Y186: 1 | Z186: =IF(T186="SOPORTE_TELEFÓNICO",'TARIFAS 2025'!$B$14,IF(V186="PRINCIPAL",'TARIFAS 2025'!$B$11,IF(V186="INTERMEDIA",'TARIFAS 2025'!$C$11,IF(V186="LEJANA",'TARIFAS 2025'!$D$11)))) -> 31419 | AA186: =Z186*Y186 -> 31419
... A281: BARRANQUILLA | B281: =VLOOKUP(A281,'CENTROS DE COSTOS'!A:D,2,0) -> 0036-0001 | C281: =VLOOKUP(A281,'CENTROS DE COSTOS'!A:D,3,0) -> Wompi Costa | D281: 8758 | E281: 2838030 | F281: 65424 | G281: ORDEN DE CAMBIO | H281: ATLANTICO | I281: SOLEDAD | J281: PINTICOS BABY KIDS | K281: WOMPI | L281: FO-25-1626751 | M281: 45933.679 | N281: 45934.559 | O281: ROLLOS | P281: ROLLOS | Q281: EJECUTADO_EXITOSO | R281: EJECUTADO EXITOSO | S281: 03/10/2025 SE ESCALA AL COORDINADOR DE ZONA PARA ENTREGA DE ROLLOS EN SITIO | 04/10/2025 SE HACE ENTREGA DE 64 ROLLOS WOMPI, CALLE 22B 31 149 HIPÓDROMO | T281: VISITA_TÉCNICA | U281: 64 | V281: PRINCIPAL | W281: =VLOOKUP(D281,TIPOLOGIA!A:F,6,0) -> TERRESTRE | X281: TORRES MANTILLA JOSE DANIEL | Y281: 1 | Z281: =IF(T281="SOPORTE_TELEFÓNICO",'TARIFAS 2025'!$B$14,IF(V281="PRINCIPAL",'TARIFAS 2025'!$B$11,IF(V281="INTERMEDIA",'TARIFAS 2025'!$C$11,IF(V281="LEJANA",'TARIFAS 2025'!$D$11)))) -> 31419 | AA281: =Z281*Y281 -> 31419
A282: NEIVA | B282: =VLOOKUP(A282,'CENTROS DE COSTOS'!A:D,2,0) -> 0036-0006 | C282: =VLOOKUP(A282,'CENTROS DE COSTOS'!A:D,3,0) -> Wompi Oriente | D282: 41001 | E282: 2837246 | F282: 62389 | G282: ORDEN DE CAMBIO | H282: HUILA | I282: NEIVA | J282: FOTOCOPIAS HELIO'S | K282: WOMPI | L282: FO-25-1626318 | M282: 45933.616 | N282: 45934.561 | O282: ROLLOS | P282: ROLLOS | Q282: EJECUTADO_CANCELADO | R282: CB CERRADO - DESOCUPADO | S282: 03/10/2025 SE ESCALA AL COORDINADOR DE ZONA PARA ENTREGA DE ROLLOS EN SITIO | 04/10/2025 SE REALIZA VISITA AL PUNTO, SE EVIDENCIA COMERCIÓ SE ENCUENTRA CERRADO SE INTENTA COMUNICACIÓN AL NÚMERO INDICAD EN LA ORDEN PERO NO HAY RESPUESTA. | T282: VISITA_TÉCNICA | V282: PRINCIPAL | W282: =VLOOKUP(D282,TIPOLOGIA!A:F,6,0) -> TERRESTRE | X282: ORTEGA TORRES JUAN SEBASTIAN | Y282: 1 | Z282: =IF(T282="SOPORTE_TELEFÓNICO",'TARIFAS 2025'!$B$14,IF(V282="PRINCIPAL",'TARIFAS 2025'!$B$11,IF(V282="INTERMEDIA",'TARIFAS 2025'!$C$11,IF(V282="LEJANA",'TARIFAS 2025'!$D$11)))) -> 31419 | AA282: =Z282*Y282 -> 31419
A283: VILLAVICENCIO | B283: =VLOOKUP(A283,'CENTROS DE COSTOS'!A:D,2,0) -> 0036-0006 | C283: =VLOOKUP(A283,'CENTROS DE COSTOS'!A:D,3,0) -> Wompi Oriente | D283: 50001 | E283: 2835543 | F283: 76214 | G283: ORDEN DE CAMBIO | H283: META | I283: VILLAVICENCIO | J283: AUTOSERVICIO MATHI | K283: WOMPI | L283: FO-25-1626319 | M283: 45933.456 | N283: 45934.564 | O283: ROLLOS | P283: ROLLOS | Q283: EJECUTADO_EXITOSO | R283: EJECUTADO EXITOSO | S283: 03/10/2025 SE ESCALA AL COORDINADOR DE ZONA PARA ENTREGA DE ROLLOS EN SITIO | 04/10/2025 SE REALIZA ENTREGA EN SITIO DE 16 ROLLOS WOMPI | T283: VISITA_TÉCNICA | U283: 16 | V283: PRINCIPAL | W283: =VLOOKUP(D283,TIPOLOGIA!A:F,6,0) -> TERRESTRE | X283: DEVIA REINOSO JUAN CARLOS | Y283: 1 | Z283: =IF(T283="SOPORTE_TELEFÓNICO",'TARIFAS 2025'!$B$14,IF(V283="PRINCIPAL",'TARIFAS 2025'!$B$11,IF(V283="INTERMEDIA",'TARIFAS 2025'!$C$11,IF(V283="LEJANA",'TARIFAS 2025'!$D$11)))) -> 31419 | AA283: =Z283*Y283 -> 31419
A284: VILLAVICENCIO | B284: =VLOOKUP(A284,'CENTROS DE COSTOS'!A:D,2,0) -> 0036-0006 | C284: =VLOOKUP(A284,'CENTROS DE COSTOS'!A:D,3,0) -> Wompi Oriente | D284: 50001 | E284: 2835652 | F284: 79430 | G284: ORDEN DE CAMBIO | H284: META | I284: VILLAVICENCIO | J284: BARRIO PORTALES EL LLANO VILLAVICENCIO | K284: WOMPI | L284: FO-25-1622048 | M284: 45933.47 | N284: 45934.567 | O284: ROLLOS | P284: ROLLOS | Q284: EJECUTADO_EXITOSO | R284: EJECUTADO EXITOSO | S284: 03/10/2025 SE ESCALA AL COORDINADOR DE ZONA PARA ENTREGA DE ROLLOS EN SITIO | 04/10/2025 SE REALIZA ENTREGA EN SITIO DE 24 ROLLOS WOMPI OK SIN NOVEDAD | T284: VISITA_TÉCNICA | U284: 24 | V284: PRINCIPAL | W284: =VLOOKUP(D284,TIPOLOGIA!A:F,6,0) -> TERRESTRE | X284: PEDREROS CONTRERAS MICHAEL STEVENS | Y284: 1 | Z284: =IF(T284="SOPORTE_TELEFÓNICO",'TARIFAS 2025'!$B$14,IF(V284="PRINCIPAL",'TARIFAS 2025'!$B$11,IF(V284="INTERMEDIA",'TARIFAS 2025'!$C$11,IF(V284="LEJANA",'TARIFAS 2025'!$D$11)))) -> 31419 | AA284: =Z284*Y284 -> 31419
A285: BOGOTA | B285: =VLOOKUP(A285,'CENTROS DE COSTOS'!A:D,2,0) -> 0036-0004 | C285: =VLOOKUP(A285,'CENTROS DE COSTOS'!A:D,3,0) -> Wompi Centro | D285: 11001 | E285: 2832696 | F285: 56210 | G285: ORDEN DE CAMBIO | H285: CUNDINAMARCA | I285: BOGOTA | J285: BARRIO SANTA RITA BOGOTA 3 | K285: WOMPI | L285: FO-25-1619638 | M285: 45933.333 | N285: 45934.568 | O285: ROLLOS | P285: ROLLOS | Q285: EJECUTADO_EXITOSO | R285: EJECUTADO EXITOSO | S285: 03/10/2025 SE ESCALA AL COORDINADOR DE ZONA PARA ENTREGA DE ROLLOS EN SITIO | 04/10/2025 SE VISITA COMERCIO CB BANCOLOMBIA WOMPI, SE ENTREGAN ROLLOS DE PAPELERÍA SOLICITADOS PARA EL DATAFONO, NO UPS, NO SE MANIPULAN EQUIPOS. | T285: VISITA_TÉCNICA | U285: 24 | V285: PRINCIPAL | W285: =VLOOKUP(D285,TIPOLOGIA!A:F,6,0) -> TERRESTRE | X285: CASTRILLON URREA LONDIER LEANDRO | Y285: 1 | Z285: =IF(T285="SOPORTE_TELEFÓNICO",'TARIFAS 2025'!$B$14,IF(V285="PRINCIPAL",'TARIFAS 2025'!$B$11,IF(V285="INTERMEDIA",'TARIFAS 2025'!$C$11,IF(V285="LEJANA",'TARIFAS 2025'!$D$11)))) -> 31419 | AA285: =Z285*Y285 -> 31419
A286: CALI | B286: =VLOOKUP(A286,'CENTROS DE COSTOS'!A:D,2,0) -> 0036-0003 | C286: =VLOOKUP(A286,'CENTROS DE COSTOS'!A:D,3,0) -> Wompi Suroccidente | D286: 76001 | E286: 2835026 | F286: 78269 | G286: ORDEN DE CAMBIO | H286: VALLE DEL CAUCA | I286: CALI | J286: H.J IMPRESORES | K286: WOMPI | L286: FO-25-1620824 | M286: 45933.414 | N286: 45934.569 | O286: ROLLOS | P286: ROLLOS | Q286: EJECUTADO_EXITOSO | R286: EJECUTADO EXITOSO | S286: 03/10/2025 SE ESCALA AL COORDINADOR DE ZONA PARA ENTREGA DE ROLLOS EN SITIO | 04/10/2025 SE REALIZA ENTREGA DE 32 ROLLOS WOMPI CON VISITA, NO SE INTERVIENE EQUIPOS | T286: VISITA_TÉCNICA | U286: 32 | V286: PRINCIPAL | W286: =VLOOKUP(D286,TIPOLOGIA!A:F,6,0) -> TERRESTRE | X286: VEGA MANRIQUE JONATAN MAURICIO | Y286: 1 | Z286: =IF(T286="SOPORTE_TELEFÓNICO",'TARIFAS 2025'!$B$14,IF(V286="PRINCIPAL",'TARIFAS 2025'!$B$11,IF(V286="INTERMEDIA",'TARIFAS 2025'!$C$11,IF(V286="LEJANA",'TARIFAS 2025'!$D$11)))) -> 31419 | AA286: =Z286*Y286 -> 31419
A287: CUCUTA | B287: =VLOOKUP(A287,'CENTROS DE COSTOS'!A:D,2,0) -> 0036-0007 | C287: =VLOOKUP(A287,'CENTROS DE COSTOS'!A:D,3,0) -> Wompi Santander | D287: 54001 | E287: 2836032 | F287: 79765 | G287: ORDEN DE CAMBIO | H287: NORTE DE SANTANDER | I287: CUCUTA | J287: NORTUREX | K287: WOMPI | L287: FO-25-1622010 | M287: 45933.488 | N287: 45934.571 | O287: ROLLOS | P287: ROLLOS | Q287: EJECUTADO_EXITOSO | R287: EJECUTADO EXITOSO | S287: 03/10/2025 SE ESCALA AL COORDINADOR DE ZONA PARA ENTREGA DE ROLLOS EN SITIO | 04/10/2025 SE VISITA COMERCIO Y SE ENTREGAN 8 ROLLOS OK. | T287: VISITA_TÉCNICA | U287: 8 | V287: PRINCIPAL | W287: =VLOOKUP(D287,TIPOLOGIA!A:F,6,0) -> TERRESTRE | X287: HERRERA MONAR GEOVANNY | Y287: 1 | Z287: =IF(T287="SOPORTE_TELEFÓNICO",'TARIFAS 2025'!$B$14,IF(V287="PRINCIPAL",'TARIFAS 2025'!$B$11,IF(V287="INTERMEDIA",'TARIFAS 2025'!$C$11,IF(V287="LEJANA",'TARIFAS 2025'!$D$11)))) -> 31419 | AA287: =Z287*Y287 -> 31419
A288: BOGOTA | B288: =VLOOKUP(A288,'CENTROS DE COSTOS'!A:D,2,0) -> 0036-0004 | C288: =VLOOKUP(A288,'CENTROS DE COSTOS'!A:D,3,0) -> Wompi Centro | D288: 11001 | E288: 2832848 | F288: 48563 | G288: ORDEN DE CAMBIO | H288: CUNDINAMARCA | I288: BOGOTA | J288: BARRIO PORTALES DEL NORTE BOGOTA | K288: WOMPI | L288: FO-25-1619631 | M288: 45933.333 | N288: 45934.573 | O288: ROLLOS | P288: ROLLOS | Q288: EJECUTADO_EXITOSO | R288: EJECUTADO EXITOSO | S288: 03/10/2025 SE ESCALA AL COORDINADOR DE ZONA PARA ENTREGA DE ROLLOS EN SITIO | 04/10/2025 SE REALIZA VISITA A COMERCIO SE ENTREGAN 24 ROLLOS WOMPI | T288: VISITA_TÉCNICA | U288: 24 | V288: PRINCIPAL | W288: =VLOOKUP(D288,TIPOLOGIA!A:F,6,0) -> TERRESTRE | X288: TORRES MANTILLA JOSE DANIEL | Y288: 1 | Z288: =IF(T288="SOPORTE_TELEFÓNICO",'TARIFAS 2025'!$B$14,IF(V288="PRINCIPAL",'TARIFAS 2025'!$B$11,IF(V288="INTERMEDIA",'TARIFAS 2025'!$C$11,IF(V288="LEJANA",'TARIFAS 2025'!$D$11)))) -> 31419 | AA288: =Z288*Y288 -> 31419
A289: BOGOTA | B289: =VLOOKUP(A289,'CENTROS DE COSTOS'!A:D,2,0) -> 0036-0004 | C289: =VLOOKUP(A289,'CENTROS DE COSTOS'!A:D,3,0) -> Wompi Centro | D289: 11001 | E289: 2836265 | F289: 37197 | G289: ORDEN DE CAMBIO | H289: CUNDINAMARCA | I289: BOGOTÁ | J289: MULTISERVICIOS JYM LA LA 7° | K289: WOMPI | L289: FO-25-1622622 | M289: 45933.512 | N289: 45934.574 | O289: ROLLOS | P289: ROLLOS | Q289: EJECUTADO_EXITOSO | R289: EJECUTADO EXITOSO | S289: 03/10/2025 SE ESCALA AL COORDINADOR DE ZONA PARA ENTREGA DE ROLLOS EN SITIO | 04/10/2025 SE ENTREGAN ROLLOS | T289: VISITA_TÉCNICA | U289: 32 | V289: PRINCIPAL | W289: =VLOOKUP(D289,TIPOLOGIA!A:F,6,0) -> TERRESTRE | X289: JAIMES VALERO NELSON RICARDO | Y289: 1 | Z289: =IF(T289="SOPORTE_TELEFÓNICO",'TARIFAS 2025'!$B$14,IF(V289="PRINCIPAL",'TARIFAS 2025'!$B$11,IF(V289="INTERMEDIA",'TARIFAS 2025'!$C$11,IF(V289="LEJANA",'TARIFAS 2025'!$D$11)))) -> 31419 | AA289: =Z289*Y289 -> 31419
A290: VILLAVICENCIO | B290: =VLOOKUP(A290,'CENTROS DE COSTOS'!A:D,2,0) -> 0036-0006 | C290: =VLOOKUP(A290,'CENTROS DE COSTOS'!A:D,3,0) -> Wompi Oriente | D290: 50001 | E290: 2836583 | F290: 61566 | G290: ORDEN DE CAMBIO | H290: META | I290: VILLAVICENCIO | J290: SERVÍTODO JYT | K290: WOMPI | L290: FO-25-1623783 | M290: 45933.558 | N290: 45934.576 | O290: ROLLOS | P290: ROLLOS | Q290: EJECUTADO_EXITOSO | R290: EJECUTADO EXITOSO | S290: 03/10/2025 SE ESCALA AL COORDINADOR DE ZONA PARA ENTREGA DE ROLLOS EN SITIO | 04/10/2025 SE REALIZA ENTREGA EN SITIO DE 16 ROLLOS WOMPI OK SIN NOVEDAD | T290: VISITA_TÉCNICA | U290: 16 | V290: PRINCIPAL | W290: =VLOOKUP(D290,TIPOLOGIA!A:F,6,0) -> TERRESTRE | X290: BARRAGAN LAGOS JUAN MANUEL | Y290: 1 | Z290: =IF(T290="SOPORTE_TELEFÓNICO",'TARIFAS 2025'!$B$14,IF(V290="PRINCIPAL",'TARIFAS 2025'!$B$11,IF(V290="INTERMEDIA",'TARIFAS 2025'!$C$11,IF(V290="LEJANA",'TARIFAS 2025'!$D$11)))) -> 31419 | AA290: =Z290*Y290 -> 31419
A291: BOGOTA | B291: =VLOOKUP(A291,'CENTROS DE COSTOS'!A:D,2,0) -> 0036-0004 | C291: =VLOOKUP(A291,'CENTROS DE COSTOS'!A:D,3,0) -> Wompi Centro | D291: 11001 | E291: 2836106 | F291: 66961 | G291: ORDEN DE CAMBIO | H291: CUNDINAMARCA | I291: BOGOTÁ | J291: PAPELERIA LA 42 | K291: WOMPI | L291: FO-25-1622021 | FO-25-1626423 | M291: 45933.483 | N291: 45934.58 | O291: ROLLOS | P291: ROLLOS | Q291: EJECUTADO_EXITOSO | R291: EJECUTADO EXITOSO | S291: 04/10/2025 SE REALIZA VISITA DE CAMPO ENCONTRADO QUE COMERCIO ESTA CERRADO SE REALIZA COMUNICACIÓN A LA LÍNEA 3002683028 NO HAY RESPUESTA, SE INFORMA A SUPERVISOR QUE ES SEGUNDA VISITA Y AUTORIZA CIERRE DE LA MISMA | T291: VISITA_TÉCNICA | V291: PRINCIPAL | W291: =VLOOKUP(D291,TIPOLOGIA!A:F,6,0) -> TERRESTRE | X291: CASTRILLON URREA LONDIER LEANDRO | Y291: 2 | Z291: =IF(T291="SOPORTE_TELEFÓNICO",'TARIFAS 2025'!$B$14,IF(V291="PRINCIPAL",'TARIFAS 2025'!$B$11,IF(V291="INTERMEDIA",'TARIFAS 2025'!$C$11,IF(V291="LEJANA",'TARIFAS 2025'!$D$11)))) -> 31419 | AA291: =Z291*Y291 -> 62838
A292: PASTO | B292: =VLOOKUP(A292,'CENTROS DE COSTOS'!A:D,2,0) -> 0036-0003 | C292: =VLOOKUP(A292,'CENTROS DE COSTOS'!A:D,3,0) -> Wompi Suroccidente | D292: 52001 | E292: 2833097 | F292: 63795 | G292: ORDEN DE CAMBIO | H292: NARIÑO | I292: PASTO | J292: BARRIO VILLA FLOR II PASTO | K292: WOMPI | L292: FO-25-1619608 | M292: 45933.333 | N292: 45934.582 | O292: ROLLOS | P292: ROLLOS | Q292: EJECUTADO_EXITOSO | R292: EJECUTADO EXITOSO | S292: 03/10/2025 SE ESCALA AL COORDINADOR DE ZONA PARA ENTREGA DE ROLLOS EN SITIO | 04/10/2025 SE REALIZA ENTREGA DE 64 ROLLOS WOMPI NO SE MANIPULA DATAFONO | T292: VISITA_TÉCNICA | U292: 64 | V292: PRINCIPAL | W292: =VLOOKUP(D292,TIPOLOGIA!A:F,6,0) -> TERRESTRE | X292: GARCIA PASTRANA KEVIN FERNANDO | LOZADA ROJAS CHRISTIAN ANDRES | Y292: 1 | Z292: =IF(T292="SOPORTE_TELEFÓNICO",'TARIFAS 2025'!$B$14,IF(V292="PRINCIPAL",'TARIFAS 2025'!$B$11,IF(V292="INTERMEDIA",'TARIFAS 2025'!$C$11,IF(V292="LEJANA",'TARIFAS 2025'!$D$11)))) -> 31419 | AA292: =Z292*Y292 -> 31419
A293: CUCUTA | B293: =VLOOKUP(A293,'CENTROS DE COSTOS'!A:D,2,0) -> 0036-0007 | C293: =VLOOKUP(A293,'CENTROS DE COSTOS'!A:D,3,0) -> Wompi Santander | D293: 54001 | E293: 2831894 | F293: 71610 | G293: ORDEN DE CAMBIO | H293: NORTE DE SANTANDER | I293: CUCUTA | J293: BARRIO CARLOS RAMIRES PARIS CUCUTA | K293: WOMPI | L293: FO-25-1617445 | M293: 45932.658 | N293: 45934.584 | O293: ROLLOS | P293: ROLLOS | Q293: EJECUTADO_EXITOSO | R293: EJECUTADO EXITOSO | S293: 02/10/2025 SE ESCALA AL COORDINADOR DE ZONA PARA ENTREGA DE ROLLOS EN SITIO | 04/10/2025 SE REALIZA ENTREGA DE 32 ROLLOS WOMPI | T293: VISITA_TÉCNICA | U293: 32 | V293: PRINCIPAL | W293: =VLOOKUP(D293,TIPOLOGIA!A:F,6,0) -> TERRESTRE | X293: BRAVO MADROÑERO OSCAR ESTEBAN | Y293: 1 | Z293: =IF(T293="SOPORTE_TELEFÓNICO",'TARIFAS 2025'!$B$14,IF(V293="PRINCIPAL",'TARIFAS 2025'!$B$11,IF(V293="INTERMEDIA",'TARIFAS 2025'!$C$11,IF(V293="LEJANA",'TARIFAS 2025'!$D$11)))) -> 31419 | AA293: =Z293*Y293 -> 31419
A294: CARTAGENA | B294: =VLOOKUP(A294,'CENTROS DE COSTOS'!A:D,2,0) -> 0036-0001 | C294: =VLOOKUP(A294,'CENTROS DE COSTOS'!A:D,3,0) -> Wompi Costa | D294: 13001 | E294: 2831898 | F294: 27489 | G294: ORDEN DE CAMBIO | H294: BOLIVAR | I294: CARTAGENA | J294: DROGUERIA LA MAGISTRAL PLUS | K294: WOMPI | L294: FO-25-1617443 | M294: 45932.658 | N294: 45934.585 | O294: ROLLOS | P294: ROLLOS | Q294: EJECUTADO_EXITOSO | R294: EJECUTADO EXITOSO | S294: 02/10/2025 SE ESCALA AL COORDINADOR DE ZONA PARA ENTREGA DE ROLLOS EN SITIO | 04/10/2025 SE ENTREGAN 16 ROLLOS | T294: VISITA_TÉCNICA | U294: 16 | V294: PRINCIPAL | W294: =VLOOKUP(D294,TIPOLOGIA!A:F,6,0) -> TERRESTRE | X294: DURAN ACOSTA FRANK YONNY | Y294: 1 | Z294: =IF(T294="SOPORTE_TELEFÓNICO",'TARIFAS 2025'!$B$14,IF(V294="PRINCIPAL",'TARIFAS 2025'!$B$11,IF(V294="INTERMEDIA",'TARIFAS 2025'!$C$11,IF(V294="LEJANA",'TARIFAS 2025'!$D$11)))) -> 31419 | AA294: =Z294*Y294 -> 31419
A295: PEREIRA | B295: =VLOOKUP(A295,'CENTROS DE COSTOS'!A:D,2,0) -> 0036-0002 | C295: =VLOOKUP(A295,'CENTROS DE COSTOS'!A:D,3,0) -> Wompi Eje Cafetero | D295: 66001 | E295: 2834298 | F295: 75526 | G295: ORDEN DE CAMBIO | H295: RISARALDA | I295: PEREIRA | J295: BARRIO KENNEDY PEREIRA | K295: WOMPI | L295: FO-25-1619566 | M295: 45933.381 | N295: 45934.586 | O295: ROLLOS | P295: ROLLOS | Q295: EJECUTADO_EXITOSO | R295: EJECUTADO EXITOSO | S295: 03/10/2025 SE ESCALA AL COORDINADOR DE ZONA PARA ENTREGA DE ROLLOS EN SITIO | 04/10/2025 SE VISITA COMERCIO SE REALIZA ENTREGA DE 40 ROLLOS DE PAPEL PARA DATÁFONO WOMPI | T295: VISITA_TÉCNICA | U295: 40 | V295: PRINCIPAL | W295: =VLOOKUP(D295,TIPOLOGIA!A:F,6,0) -> TERRESTRE | X295: CANEDO HERRERA ALEXANDER | Y295: 1 | Z295: =IF(T295="SOPORTE_TELEFÓNICO",'TARIFAS 2025'!$B$14,IF(V295="PRINCIPAL",'TARIFAS 2025'!$B$11,IF(V295="INTERMEDIA",'TARIFAS 2025'!$C$11,IF(V295="LEJANA",'TARIFAS 2025'!$D$11)))) -> 31419 | AA295: =Z295*Y295 -> 31419
A296: VILLAVICENCIO | B296: =VLOOKUP(A296,'CENTROS DE COSTOS'!A:D,2,0) -> 0036-0006 | C296: =VLOOKUP(A296,'CENTROS DE COSTOS'!A:D,3,0) -> Wompi Oriente | D296: 50001 | E296: 2836584 | F296: 80078 | G296: ORDEN DE CAMBIO | H296: META | I296: VILLAVICENCIO | J296: BARRIO EL RECREO VILLAVICENCIO 1 | K296: WOMPI | L296: FO-25-1625871 | M296: 45933.558 | N296: 45934.589 | O296: ROLLOS | P296: ROLLOS | Q296: EJECUTADO_EXITOSO | R296: EJECUTADO EXITOSO | S296: 03/10/2025 SE ESCALA AL COORDINADOR DE ZONA PARA ENTREGA DE ROLLOS EN SITIO | 04/10/2025 SE REALIZA ENTREGA EN SITIO DE 32 ROLLOS | T296: VISITA_TÉCNICA | U296: 32 | V296: PRINCIPAL | W296: =VLOOKUP(D296,TIPOLOGIA!A:F,6,0) -> TERRESTRE | X296: LOAIZA LOPEZ JHON FREDDY | Y296: 1 | Z296: =IF(T296="SOPORTE_TELEFÓNICO",'TARIFAS 2025'!$B$14,IF(V296="PRINCIPAL",'TARIFAS 2025'!$B$11,IF(V296="INTERMEDIA",'TARIFAS 2025'!$C$11,IF(V296="LEJANA",'TARIFAS 2025'!$D$11)))) -> 31419 | AA296: =Z296*Y296 -> 31419
A297: BOGOTA | B297: =VLOOKUP(A297,'CENTROS DE COSTOS'!A:D,2,0) -> 0036-0004 | C297: =VLOOKUP(A297,'CENTROS DE COSTOS'!A:D,3,0) -> Wompi Centro | D297: 11001 | E297: 2837852 | F297: 71418 | G297: ORDEN DE CAMBIO | H297: CUNDINAMARCA | I297: BOGOTÁ | J297: PAPELERIA Y MISCELANEA MAKANEY | K297: WOMPI | L297: FO-25-1626627 | M297: 45933.667 | N297: 45934.592 | O297: ROLLOS | P297: ROLLOS | Q297: EJECUTADO_EXITOSO | R297: EJECUTADO EXITOSO | S297: 03/10/2025 SE ESCALA AL COORDINADOR DE ZONA PARA ENTREGA DE ROLLOS EN SITIO | 04/10/2025 SE ENTREGAN ROLLOS | T297: VISITA_TÉCNICA | U297: 24 | V297: PRINCIPAL | W297: =VLOOKUP(D297,TIPOLOGIA!A:F,6,0) -> TERRESTRE | X297: CASTRILLON URREA LONDIER LEANDRO | Y297: 1 | Z297: =IF(T297="SOPORTE_TELEFÓNICO",'TARIFAS 2025'!$B$14,IF(V297="PRINCIPAL",'TARIFAS 2025'!$B$11,IF(V297="INTERMEDIA",'TARIFAS 2025'!$C$11,IF(V297="LEJANA",'TARIFAS 2025'!$D$11)))) -> 31419 | AA297: =Z297*Y297 -> 31419
A298: PASTO | B298: =VLOOKUP(A298,'CENTROS DE COSTOS'!A:D,2,0) -> 0036-0003 | C298: =VLOOKUP(A298,'CENTROS DE COSTOS'!A:D,3,0) -> Wompi Suroccidente | D298: 52001 | E298: 2811637 | F298: 79315 | G298: ORDEN DE CAMBIO | H298: NARIÑO | I298: PASTO | J298: SUPERTIENDA LOS PAISAS | K298: WOMPI | L298: FO-25-1601012 | M298: 45930.333 | N298: 45934.593 | O298: ROLLOS | P298: ROLLOS | Q298: EJECUTADO_EXITOSO | R298: EJECUTADO EXITOSO | S298: 29/09/2025 SE ESCALA AL COORDINADOR DE ZONA PARA ENTREGA DE ROLLOS EN SITIO | 04/10/2025 SE REALIZA ENTREGA DE 32 ROLLOS WOMPI NO SE MANIPULA DATAFONO | T298: VISITA_TÉCNICA | U298: 32 | V298: PRINCIPAL | W298: =VLOOKUP(D298,TIPOLOGIA!A:F,6,0) -> TERRESTRE | X298: BARRAGAN LAGOS JUAN MANUEL | Y298: 1 | Z298: =IF(T298="SOPORTE_TELEFÓNICO",'TARIFAS 2025'!$B$14,IF(V298="PRINCIPAL",'TARIFAS 2025'!$B$11,IF(V298="INTERMEDIA",'TARIFAS 2025'!$C$11,IF(V298="LEJANA",'TARIFAS 2025'!$D$11)))) -> 31419 | AA298: =Z298*Y298 -> 31419
A299: MONTERIA | B299: =VLOOKUP(A299,'CENTROS DE COSTOS'!A:D,2,0) -> 0036-0001 | C299: =VLOOKUP(A299,'CENTROS DE COSTOS'!A:D,3,0) -> Wompi Costa | D299: 23686 | E299: 2827341 | F299: 64436 | G299: ORDEN DE CAMBIO | H299: CORDOBA | I299: SAN PELAYO | J299: BARRIO CRISTO REY SAN PELAYO 1 | K299: WOMPI | L299: FO-25-1614633 | M299: 45932.358 | N299: 45934.596 | O299: ROLLOS | P299: ROLLOS | Q299: EJECUTADO_EXITOSO | R299: EJECUTADO EXITOSO | S299: 02/10/2025 SE ESCALA AL COORDINADOR DE ZONA PARA ENTREGA DE ROLLOS EN SITIO | 04/10/2025 SE REALIZA ENTREGA DE 16 ROLLOS WOMPI EN EL PUNTO SIN NOVEDAD. | T299: VISITA_TÉCNICA | U299: 16 | V299: INTERMEDIA | W299: =VLOOKUP(D299,TIPOLOGIA!A:F,6,0) -> TERRESTRE | X299: BRAVO MADROÑERO OSCAR ESTEBAN | Y299: 1 | Z299: =IF(T299="SOPORTE_TELEFÓNICO",'TARIFAS 2025'!$B$14,IF(V299="PRINCIPAL",'TARIFAS 2025'!$B$11,IF(V299="INTERMEDIA",'TARIFAS 2025'!$C$11,IF(V299="LEJANA",'TARIFAS 2025'!$D$11)))) -> 36351 | AA299: =Z299*Y299 -> 36351
A300: PEREIRA | B300: =VLOOKUP(A300,'CENTROS DE COSTOS'!A:D,2,0) -> 0036-0002 | C300: =VLOOKUP(A300,'CENTROS DE COSTOS'!A:D,3,0) -> Wompi Eje Cafetero | D300: 63001 | E300: 2802992 | F300: 72298 | G300: ORDEN DE CAMBIO | H300: QUINDIO | I300: ARMENIA | J300: BARRIO VILLA CAROLINA ARMENIA 1 | K300: WOMPI | L300: FO-25-1594141 | M300: 45929.333 | N300: 45934.598 | O300: ROLLOS | P300: ROLLOS | Q300: EJECUTADO_EXITOSO | R300: EJECUTADO EXITOSO | S300: 27/09/2025 SE ESCALA AL COORDINADOR DE ZONA PARA ENTREGA DE ROLLOS EN SITIO | 04/10/2025 SE VISITA COMERCIO SE REALIZÓ ENTREGA DE 32 ROLLOS WOMPI | T300: VISITA_TÉCNICA | U300: 32 | V300: INTERMEDIA | W300: =VLOOKUP(D300,TIPOLOGIA!A:F,6,0) -> TERRESTRE | X300: GONZALEZ FERRER JESUS ALEXANDER | Y300: 1 | Z300: =IF(T300="SOPORTE_TELEFÓNICO",'TARIFAS 2025'!$B$14,IF(V300="PRINCIPAL",'TARIFAS 2025'!$B$11,IF(V300="INTERMEDIA",'TARIFAS 2025'!$C$11,IF(V300="LEJANA",'TARIFAS 2025'!$D$11)))) -> 36351 | AA300: =Z300*Y300 -> 36351
A301: BARRANQUILLA | B301: =VLOOKUP(A301,'CENTROS DE COSTOS'!A:D,2,0) -> 0036-0001 | C301: =VLOOKUP(A301,'CENTROS DE COSTOS'!A:D,3,0) -> Wompi Costa | D301: 8001 | E301: 2832697 | F301: 66128 | G301: ORDEN DE CAMBIO | H301: ATLANTICO | I301: BARRANQUILLA | J301: MINEVIS ESTHER OROZCO NIEBLES | K301: WOMPI | L301: FO-25-1619642 | M301: 45933.333 | N301: 45934.6 | O301: ROLLOS | P301: ROLLOS | Q301: EJECUTADO_EXITOSO | R301: EJECUTADO EXITOSO | S301: 03/10/2025 SE ESCALA AL COORDINADOR DE ZONA PARA ENTREGA DE ROLLOS EN SITIO | 04/10/2025 SE HACE ENTREGA DE 24 ROLLOS WOMPI, CARRERA 21 48 28 LOCAL 2 | T301: VISITA_TÉCNICA | U301: 24 | V301: PRINCIPAL | W301: =VLOOKUP(D301,TIPOLOGIA!A:F,6,0) -> TERRESTRE | X301: SANCHEZ SOLORZANO JUAN SEBASTIAN | Y301: 1 | Z301: =IF(T301="SOPORTE_TELEFÓNICO",'TARIFAS 2025'!$B$14,IF(V301="PRINCIPAL",'TARIFAS 2025'!$B$11,IF(V301="INTERMEDIA",'TARIFAS 2025'!$C$11,IF(V301="LEJANA",'TARIFAS 2025'!$D$11)))) -> 31419 | AA301: =Z301*Y301 -> 31419
A302: BARRANQUILLA | B302: =VLOOKUP(A302,'CENTROS DE COSTOS'!A:D,2,0) -> 0036-0001 | C302: =VLOOKUP(A302,'CENTROS DE COSTOS'!A:D,3,0) -> Wompi Costa | D302: 8001 | E302: 2837265 | F302: 28098 | G302: ORDEN DE CAMBIO | H302: ATLANTICO | I302: BARRANQUILLA | J302: TIENDA Y MISCELÁNEA EL PORTALÓN | K302: WOMPI | L302: FO-25-1626314 | M302: 45933.62 | N302: 45934.626 | O302: ROLLOS | P302: ROLLOS | Q302: EJECUTADO_EXITOSO | R302: EJECUTADO EXITOSO | S302: 03/10/2025 SE ESCALA AL COORDINADOR DE ZONA PARA ENTREGA DE ROLLOS EN SITIO | 04/10/2025 SE ENTREGAN 40 ROLLOS | T302: VISITA_TÉCNICA | U302: 40 | V302: PRINCIPAL | W302: =VLOOKUP(D302,TIPOLOGIA!A:F,6,0) -> TERRESTRE | X302: ORTEGA TORRES JUAN SEBASTIAN | Y302: 1 | Z302: =IF(T302="SOPORTE_TELEFÓNICO",'TARIFAS 2025'!$B$14,IF(V302="PRINCIPAL",'TARIFAS 2025'!$B$11,IF(V302="INTERMEDIA",'TARIFAS 2025'!$C$11,IF(V302="LEJANA",'TARIFAS 2025'!$D$11)))) -> 31419 | AA302: =Z302*Y302 -> 31419
A303: CARTAGENA | B303: =VLOOKUP(A303,'CENTROS DE COSTOS'!A:D,2,0) -> 0036-0001 | C303: =VLOOKUP(A303,'CENTROS DE COSTOS'!A:D,3,0) -> Wompi Costa | D303: 13001 | E303: 2830850 | F303: 78420 | G303: ORDEN DE CAMBIO | H303: BOLIVAR | I303: CARTAGENA | J303: BARRIO CENTRO EDIFICIO MARA CARTAGENA DE INDIAS | K303: WOMPI | L303: FO-25-1616589 | M303: 45932.595 | N303: 45934.629 | O303: ROLLOS | P303: ROLLOS | Q303: EJECUTADO_EXITOSO | R303: EJECUTADO EXITOSO | S303: 02/10/2025 SE ESCALA AL COORDINADOR DE ZONA PARA ENTREGA DE ROLLOS EN SITIO | 04/10/2025 SE ENTREGAN 16 ROLLOS | T303: VISITA_TÉCNICA | U303: 16 | V303: PRINCIPAL | W303: =VLOOKUP(D303,TIPOLOGIA!A:F,6,0) -> TERRESTRE | X303: DE AVILA SIADES ALBERTO ENRIQUE | Y303: 1 | Z303: =IF(T303="SOPORTE_TELEFÓNICO",'TARIFAS 2025'!$B$14,IF(V303="PRINCIPAL",'TARIFAS 2025'!$B$11,IF(V303="INTERMEDIA",'TARIFAS 2025'!$C$11,IF(V303="LEJANA",'TARIFAS 2025'!$D$11)))) -> 31419 | AA303: =Z303*Y303 -> 31419
... A582: BUCARAMANGA | B582: =VLOOKUP(A582,'CENTROS DE COSTOS'!A:D,2,0) -> 0036-0007 | C582: =VLOOKUP(A582,'CENTROS DE COSTOS'!A:D,3,0) -> Wompi Santander | D582: 68001 | E582: 2849454 | F582: 79878 | G582: ORDEN DE CAMBIO | H582: SANTANDER | I582: BUCARAMANGA | J582: BARRIO MUTUALIDAD BUCARAMANGA 1 | K582: WOMPI | L582: FO-25-1642435 | M582: 45937.38 | N582: 45939.708 | O582: ROLLOS | P582: ROLLOS | Q582: EJECUTADO_EXITOSO | R582: EJECUTADO EXITOSO | S582: 07/10/2025 SE ESCALA AL COORDINADOR DE ZONA PARA ENTREGA DE ROLLOS EN SITIO | 08/10/2025 SE REALIZA ENTREGA DE 8 ROLLOS A LA SRA MARINA QUINTERO | T582: VISITA_TÉCNICA | U582: 8 | V582: PRINCIPAL | W582: =VLOOKUP(D582,TIPOLOGIA!A:F,6,0) -> TERRESTRE | X582: ESCOBAR LENIS JUAN SEBASTIAN | Y582: 1 | Z582: =IF(T582="SOPORTE_TELEFÓNICO",'TARIFAS 2025'!$B$14,IF(V582="PRINCIPAL",'TARIFAS 2025'!$B$11,IF(V582="INTERMEDIA",'TARIFAS 2025'!$C$11,IF(V582="LEJANA",'TARIFAS 2025'!$D$11)))) -> 31419 | AA582: =Z582*Y582 -> 31419
A583: NEIVA | B583: =VLOOKUP(A583,'CENTROS DE COSTOS'!A:D,2,0) -> 0036-0006 | C583: =VLOOKUP(A583,'CENTROS DE COSTOS'!A:D,3,0) -> Wompi Oriente | D583: 41001 | E583: 2850420 | F583: 70487 | G583: ORDEN DE CAMBIO | H583: HUILA | I583: NEIVA | J583: MULTISERVICIOS DE TODITO | K583: WOMPI | L583: FO-25-1640976 | M583: 45937.434 | N583: 45939.71 | O583: ROLLOS | P583: ROLLOS | Q583: EJECUTADO_EXITOSO | R583: EJECUTADO EXITOSO | S583: 07/10/2025 SE ESCALA AL COORDINADOR DE ZONA PARA ENTREGA DE ROLLOS EN SITIO | 08/10/2025 SE LLEGA AL PUNTO SE EVIDENCIA MARCAS COMPARTIDAS , SE CANCELA ENTREGA DE ROLLOS WOMPI | T583: VISITA_TÉCNICA | V583: PRINCIPAL | W583: =VLOOKUP(D583,TIPOLOGIA!A:F,6,0) -> TERRESTRE | X583: GONZALEZ ESTUPIÑAN YEISON WALTER ANTONIO | Y583: 1 | Z583: =IF(T583="SOPORTE_TELEFÓNICO",'TARIFAS 2025'!$B$14,IF(V583="PRINCIPAL",'TARIFAS 2025'!$B$11,IF(V583="INTERMEDIA",'TARIFAS 2025'!$C$11,IF(V583="LEJANA",'TARIFAS 2025'!$D$11)))) -> 31419 | AA583: =Z583*Y583 -> 31419
A584: CALI | B584: =VLOOKUP(A584,'CENTROS DE COSTOS'!A:D,2,0) -> 0036-0003 | C584: =VLOOKUP(A584,'CENTROS DE COSTOS'!A:D,3,0) -> Wompi Suroccidente | D584: 76001 | E584: 2842275 | F584: 66669 | G584: ORDEN DE CAMBIO | H584: VALLE DEL CAUCA | I584: CALI | J584: UNIFARMA DE OCCIDENTE | K584: WOMPI | L584: FO-25-1633738 | M584: 45936.388 | N584: 45939.715 | O584: ROLLOS | P584: ROLLOS | Q584: EJECUTADO_EXITOSO | R584: EJECUTADO EXITOSO | S584: 06/10/2025 EXITOSA | 08/10/2025 SE ENTREGAN 24 ROLLOS EN BUEN ESTADO | T584: VISITA_TÉCNICA | U584: 24 | V584: PRINCIPAL | W584: =VLOOKUP(D584,TIPOLOGIA!A:F,6,0) -> TERRESTRE | X584: ANDRADE HERNANDEZ JUAN CARLOS | Y584: 1 | Z584: =IF(T584="SOPORTE_TELEFÓNICO",'TARIFAS 2025'!$B$14,IF(V584="PRINCIPAL",'TARIFAS 2025'!$B$11,IF(V584="INTERMEDIA",'TARIFAS 2025'!$C$11,IF(V584="LEJANA",'TARIFAS 2025'!$D$11)))) -> 31419 | AA584: =Z584*Y584 -> 31419
A585: MEDELLIN | B585: =VLOOKUP(A585,'CENTROS DE COSTOS'!A:D,2,0) -> 0036-0005 | C585: =VLOOKUP(A585,'CENTROS DE COSTOS'!A:D,3,0) -> Wompi Noroccidente | D585: 5440 | E585: 2830626 | F585: 33426 | G585: ORDEN DE CAMBIO | H585: ANTIOQUIA | I585: MARINILLA | J585: BARRIO SECTOR LA RAMADA AUTOPISTA MARINILLA | K585: WOMPI | L585: FO-25-1628996 | M585: 45932.542 | N585: 45939.719 | O585: ROLLOS | P585: ROLLOS | Q585: EJECUTADO_EXITOSO | R585: EJECUTADO EXITOSO | S585: 08/10/2025 SE REALIZA ENVIO DE ROLLOS CON GUIA | 09/10/2025 AUN NO HA LLEGADO | 09/10/2025 SE CONFIRMA ENTREGA EXITOSA POR PARTE DE LA TRANSPORTADORA MANDAR Y SERVIR CON LA GUIA 6345301357931 | T585: ENVÍO | U585: 16 | V585: INTERMEDIA | W585: =VLOOKUP(D585,TIPOLOGIA!A:F,6,0) -> TERRESTRE | X585: ESCOBAR LENIS JUAN SEBASTIAN | Y585: 1 | Z585: =IF(T585="SOPORTE_TELEFÓNICO",'TARIFAS 2025'!$B$14,IF(V585="PRINCIPAL",'TARIFAS 2025'!$B$11,IF(V585="INTERMEDIA",'TARIFAS 2025'!$C$11,IF(V585="LEJANA",'TARIFAS 2025'!$D$11)))) -> 36351 | AA585: =Z585*Y585 -> 36351
A586: NEIVA | B586: =VLOOKUP(A586,'CENTROS DE COSTOS'!A:D,2,0) -> 0036-0006 | C586: =VLOOKUP(A586,'CENTROS DE COSTOS'!A:D,3,0) -> Wompi Oriente | D586: 41001 | E586: 2844838 | F586: 79111 | G586: ORDEN DE CAMBIO | H586: HUILA | I586: NEIVA | J586: SALSAMENTARIA METROPOL S | K586: WOMPI | L586: FO-25-1637548 | M586: 45936.508 | N586: 45939.721 | O586: ROLLOS | P586: ROLLOS | Q586: EJECUTADO_EXITOSO | R586: EJECUTADO EXITOSO | S586: 06/10/2025 SE ESCALA AL COORDINADOR DE ZONA PARA ENTREGA DE ROLLOS EN SITIO | 08/10/2025 SE ENTREGA 16 ROLLOS SIN NOVEDAD | T586: VISITA_TÉCNICA | U586: 16 | V586: PRINCIPAL | W586: =VLOOKUP(D586,TIPOLOGIA!A:F,6,0) -> TERRESTRE | X586: BETANCUR AGUIRRE EDGAR AUGUSTO | Y586: 1 | Z586: =IF(T586="SOPORTE_TELEFÓNICO",'TARIFAS 2025'!$B$14,IF(V586="PRINCIPAL",'TARIFAS 2025'!$B$11,IF(V586="INTERMEDIA",'TARIFAS 2025'!$C$11,IF(V586="LEJANA",'TARIFAS 2025'!$D$11)))) -> 31419 | AA586: =Z586*Y586 -> 31419
A587: MEDELLIN | B587: =VLOOKUP(A587,'CENTROS DE COSTOS'!A:D,2,0) -> 0036-0005 | C587: =VLOOKUP(A587,'CENTROS DE COSTOS'!A:D,3,0) -> Wompi Noroccidente | D587: 5440 | E587: 2835278 | F587: 75639 | G587: ORDEN DE CAMBIO | H587: ANTIOQUIA | I587: MARINILLA | J587: BARRIO MARINILLA LA RAMADA MARINILLA | K587: WOMPI | L587: FO-25-1631619 | M587: 45933.444 | N587: 45939.721 | O587: ROLLOS | P587: ROLLOS | Q587: EJECUTADO_EXITOSO | R587: EJECUTADO EXITOSO | S587: 05/10/2025 SE REALIZA ENVIO DE ROLLOS CON GUIA | 09/10/2025 SE CONFIRMA ENTREGA EXITOSA POR PARTE DE LA TRANSPORTADORA MANDAR Y SERVIR CON LA GUIA 6345301357979 | T587: ENVÍO | U587: 56 | V587: INTERMEDIA | W587: =VLOOKUP(D587,TIPOLOGIA!A:F,6,0) -> TERRESTRE | X587: ANDRADE HERNANDEZ JUAN CARLOS | Y587: 1 | Z587: =IF(T587="SOPORTE_TELEFÓNICO",'TARIFAS 2025'!$B$14,IF(V587="PRINCIPAL",'TARIFAS 2025'!$B$11,IF(V587="INTERMEDIA",'TARIFAS 2025'!$C$11,IF(V587="LEJANA",'TARIFAS 2025'!$D$11)))) -> 36351 | AA587: =Z587*Y587 -> 36351
A588: TUNJA | B588: =VLOOKUP(A588,'CENTROS DE COSTOS'!A:D,2,0) -> 0036-0007 | C588: =VLOOKUP(A588,'CENTROS DE COSTOS'!A:D,3,0) -> Wompi Santander | D588: 15238 | E588: 2832900 | F588: 61811 | G588: ORDEN DE CAMBIO | H588: BOYACA | I588: DUITAMA | J588: TIENDA DJC | K588: WOMPI | L588: FO-25-1631629 | M588: 45933.333 | N588: 45939.723 | O588: ROLLOS | P588: ROLLOS | Q588: EJECUTADO_EXITOSO | R588: EJECUTADO EXITOSO | S588: 05/10/2025 SE REALIZA ENVIO DE ROLLOS CON GUIA | 09/10/2025 SE REALIZA ENVIO DE 16 ROLLOS, CON LA GUIA 2235596141 SERVIENTREGA. SE CONFIRMA ENTREGA EXITOSA POR PARTE DEL USUARIO | T588: ENVÍO | U588: 16 | V588: INTERMEDIA | W588: =VLOOKUP(D588,TIPOLOGIA!A:F,6,0) -> TERRESTRE | X588: BETANCUR AGUIRRE EDGAR AUGUSTO | Y588: 1 | Z588: =IF(T588="SOPORTE_TELEFÓNICO",'TARIFAS 2025'!$B$14,IF(V588="PRINCIPAL",'TARIFAS 2025'!$B$11,IF(V588="INTERMEDIA",'TARIFAS 2025'!$C$11,IF(V588="LEJANA",'TARIFAS 2025'!$D$11)))) -> 36351 | AA588: =Z588*Y588 -> 36351
A589: BARRANQUILLA | B589: =VLOOKUP(A589,'CENTROS DE COSTOS'!A:D,2,0) -> 0036-0001 | C589: =VLOOKUP(A589,'CENTROS DE COSTOS'!A:D,3,0) -> Wompi Costa | D589: 8001 | E589: 2839327 | F589: 50450 | G589: ORDEN DE CAMBIO | H589: ATLANTICO | I589: BARRANQUILLA | J589: BARRIO VILLA SAN PABLO CARIBE VERDE BARRANQUILLA | K589: WOMPI | L589: FO-25-1630984 | M589: 45936.333 | N589: 45939.724 | O589: ROLLOS | P589: ROLLOS | Q589: EJECUTADO_EXITOSO | R589: EJECUTADO EXITOSO | S589: 05/10/2025 SE ESCALA AL COORDINADOR DE ZONA PARA ENTREGA DE ROLLOS EN SITIO | 08/10/2025 SE REALIZA VISITA SE ENTREGA 48 ROLLOS | T589: VISITA_TÉCNICA | U589: 48 | V589: PRINCIPAL | W589: =VLOOKUP(D589,TIPOLOGIA!A:F,6,0) -> TERRESTRE | X589: GOMEZ FERRARO JOHANA | Y589: 1 | Z589: =IF(T589="SOPORTE_TELEFÓNICO",'TARIFAS 2025'!$B$14,IF(V589="PRINCIPAL",'TARIFAS 2025'!$B$11,IF(V589="INTERMEDIA",'TARIFAS 2025'!$C$11,IF(V589="LEJANA",'TARIFAS 2025'!$D$11)))) -> 31419 | AA589: =Z589*Y589 -> 31419
A590: PEREIRA | B590: =VLOOKUP(A590,'CENTROS DE COSTOS'!A:D,2,0) -> 0036-0002 | C590: =VLOOKUP(A590,'CENTROS DE COSTOS'!A:D,3,0) -> Wompi Eje Cafetero | D590: 63001 | E590: 2843034 | F590: 76490 | G590: ORDEN DE CAMBIO | H590: QUINDIO | I590: ARMENIA | J590: BARRIO LA PATRIA ARMENIA | K590: WOMPI | L590: FO-25-1634712 | M590: 45936.417 | N590: 45939.726 | O590: ROLLOS | P590: ROLLOS | Q590: EJECUTADO_CANCELADO | R590: CB CERRADO - DESOCUPADO | S590: 08/10/2025 VISITAMOS PUNTO PERO NO ES POSIBLE REALIZAR LA ENTREGAR DE LOS ROLLOS YA QUE EL COMERCIO SE TRASLADO DE DIRECCIÓN SE REALIZA ESCALAMIENTO Y NOS INDICAN QUE SE CANCELA LA ENTREGA. | T590: VISITA_TÉCNICA | V590: INTERMEDIA | W590: =VLOOKUP(D590,TIPOLOGIA!A:F,6,0) -> TERRESTRE | X590: VILLACOB VILLACOB ELKIN EDUARDO | Y590: 1 | Z590: =IF(T590="SOPORTE_TELEFÓNICO",'TARIFAS 2025'!$B$14,IF(V590="PRINCIPAL",'TARIFAS 2025'!$B$11,IF(V590="INTERMEDIA",'TARIFAS 2025'!$C$11,IF(V590="LEJANA",'TARIFAS 2025'!$D$11)))) -> 36351 | AA590: =Z590*Y590 -> 36351
A591: BOGOTA | B591: =VLOOKUP(A591,'CENTROS DE COSTOS'!A:D,2,0) -> 0036-0004 | C591: =VLOOKUP(A591,'CENTROS DE COSTOS'!A:D,3,0) -> Wompi Centro | D591: 25286 | E591: 2832828 | F591: 54140 | G591: ORDEN DE CAMBIO | H591: CUNDINAMARCA | I591: FUNZA | J591: BARRIO MARTINEZ RICO FUNZA | K591: WOMPI | L591: FO-25-1631630 | M591: 45933.333 | N591: 45939.728 | O591: ROLLOS | P591: ROLLOS | Q591: EJECUTADO_EXITOSO | R591: EJECUTADO EXITOSO | S591: 05/10/2025 SE REALIZA ENVIO DE ROLLOS CON GUIA | 09/10/2025 SE REALIZA ENVIO DE 16 ROLLOS, CON LA GUIA 2235596142 SERVIENTREGA. SE CONFIRMA ENTREGA EXITOSA POR PARTE DE LA TRANSPORTADORA | T591: ENVÍO | U591: 16 | V591: INTERMEDIA | W591: =VLOOKUP(D591,TIPOLOGIA!A:F,6,0) -> TERRESTRE | X591: ARROYAVE CANO MANUEL GUILLERMO | Y591: 1 | Z591: =IF(T591="SOPORTE_TELEFÓNICO",'TARIFAS 2025'!$B$14,IF(V591="PRINCIPAL",'TARIFAS 2025'!$B$11,IF(V591="INTERMEDIA",'TARIFAS 2025'!$C$11,IF(V591="LEJANA",'TARIFAS 2025'!$D$11)))) -> 36351 | AA591: =Z591*Y591 -> 36351
A592: CUCUTA | B592: =VLOOKUP(A592,'CENTROS DE COSTOS'!A:D,2,0) -> 0036-0007 | C592: =VLOOKUP(A592,'CENTROS DE COSTOS'!A:D,3,0) -> Wompi Santander | D592: 54498 | E592: 2834317 | F592: 40365 | G592: ORDEN DE CAMBIO | H592: NORTE DE SANTANDER | I592: OCAÑA | J592: BARRIO EL CARMEN OCAÑA | K592: WOMPI | L592: FO-25-1629366 | M592: 45933.371 | N592: 45940.34 | O592: ROLLOS | P592: ROLLOS | Q592: EJECUTADO_EXITOSO | R592: EJECUTADO EXITOSO | S592: 04/10/2025 SE REALIZA ENVIO DE ROLLOS CON GUIA | 10/10/2025 SE REALIZA ENVIO DE 8 ROLLOS, CON LA GUIA 2187690737 SERVIENTREGA. SE CONFIRMA ENTREGA EXITOSA POR PARTE DE LA TRANSPORTADORA | T592: ENVÍO | U592: 8 | V592: LEJANA | W592: =VLOOKUP(D592,TIPOLOGIA!A:F,6,0) -> TERRESTRE | X592: GOMEZ FERRARO JOHANA | Y592: 1 | Z592: =IF(T592="SOPORTE_TELEFÓNICO",'TARIFAS 2025'!$B$14,IF(V592="PRINCIPAL",'TARIFAS 2025'!$B$11,IF(V592="INTERMEDIA",'TARIFAS 2025'!$C$11,IF(V592="LEJANA",'TARIFAS 2025'!$D$11)))) -> 40250 | AA592: =Z592*Y592 -> 40250
A593: BOGOTA | B593: =VLOOKUP(A593,'CENTROS DE COSTOS'!A:D,2,0) -> 0036-0004 | C593: =VLOOKUP(A593,'CENTROS DE COSTOS'!A:D,3,0) -> Wompi Centro | D593: 25430 | E593: 2834042 | F593: 27429 | G593: ORDEN DE CAMBIO | H593: CUNDINAMARCA | I593: MADRID | J593: BARRIO CENTRO II - MADRID | K593: WOMPI | L593: FO-25-1631623 | M593: 45933.362 | N593: 45940.342 | O593: ROLLOS | P593: ROLLOS | Q593: EJECUTADO_EXITOSO | R593: EJECUTADO EXITOSO | S593: 05/10/2025 SE REALIZA ENVIO DE ROLLOS CON GUIA | 10/10/2025 SE REALIZA ENVIO DE 64 ROLLOS, CON LA GUIA 2235596140 SERVIENTREGA. SE CONFIRMA ENTREGA EXITOSA POR PARTE DE LA TRANSPORTADORA | T593: ENVÍO | U593: 64 | V593: INTERMEDIA | W593: =VLOOKUP(D593,TIPOLOGIA!A:F,6,0) -> TERRESTRE | X593: HERNANDEZ GUARIN MIGUEL JULIAN | Y593: 1 | Z593: =IF(T593="SOPORTE_TELEFÓNICO",'TARIFAS 2025'!$B$14,IF(V593="PRINCIPAL",'TARIFAS 2025'!$B$11,IF(V593="INTERMEDIA",'TARIFAS 2025'!$C$11,IF(V593="LEJANA",'TARIFAS 2025'!$D$11)))) -> 36351 | AA593: =Z593*Y593 -> 36351
A594: BARRANQUILLA | B594: =VLOOKUP(A594,'CENTROS DE COSTOS'!A:D,2,0) -> 0036-0001 | C594: =VLOOKUP(A594,'CENTROS DE COSTOS'!A:D,3,0) -> Wompi Costa | D594: 8001 | E594: 2853282 | F594: 45896 | G594: ORDEN DE CAMBIO | H594: ATLANTICO | I594: BARRANQUILLA | J594: BARRIO ALTO PRADO BARRANQUILLA 2 | K594: WOMPI | L594: FO-25-1643126 | M594: 45937.66 | N594: 45940.365 | O594: ROLLOS | P594: ROLLOS | Q594: EJECUTADO_EXITOSO | R594: EJECUTADO EXITOSO | S594: 07/10/2025 SE ESCALA AL COORDINADOR DE ZONA PARA ENTREGA DE ROLLOS EN SITIO | 09/10/2025 SE HACE ENTREGA DE 24 ROLLOS WOMPI EN LA CALLE 92 49C 258 ALTO PRADO | T594: VISITA_TÉCNICA | U594: 24 | V594: PRINCIPAL | W594: =VLOOKUP(D594,TIPOLOGIA!A:F,6,0) -> TERRESTRE | X594: GOMEZ FERRARO JOHANA | Y594: 1 | Z594: =IF(T594="SOPORTE_TELEFÓNICO",'TARIFAS 2025'!$B$14,IF(V594="PRINCIPAL",'TARIFAS 2025'!$B$11,IF(V594="INTERMEDIA",'TARIFAS 2025'!$C$11,IF(V594="LEJANA",'TARIFAS 2025'!$D$11)))) -> 31419 | AA594: =Z594*Y594 -> 31419
A595: BUCARAMANGA | B595: =VLOOKUP(A595,'CENTROS DE COSTOS'!A:D,2,0) -> 0036-0007 | C595: =VLOOKUP(A595,'CENTROS DE COSTOS'!A:D,3,0) -> Wompi Santander | D595: 68679 | E595: 2835304 | F595: 62775 | G595: ORDEN DE CAMBIO | H595: SANTANDER | I595: SAN GIL | J595: BARRIO CENTRO SAN GIL 13 | K595: WOMPI | L595: FO-25-1631621 | M595: 45933.435 | N595: 45940.369 | O595: ROLLOS | P595: ROLLOS | Q595: EJECUTADO_EXITOSO | R595: EJECUTADO EXITOSO | S595: 05/10/2025 SE REALIZA ENVIO DE ROLLOS CON GUIA | 10/10/2025 SE REALIZA ENVIO DE 48 ROLLOS, CON LA GUIA 2187690741 SERVIENTREGA. SE CONFIRMA ENTREGA EXITOSA POR PARTE DE LA TRANSPORTADORA | T595: ENVÍO | U595: 48 | V595: INTERMEDIA | W595: =VLOOKUP(D595,TIPOLOGIA!A:F,6,0) -> TERRESTRE | X595: ORTEGA TORRES JUAN SEBASTIAN | Y595: 1 | Z595: =IF(T595="SOPORTE_TELEFÓNICO",'TARIFAS 2025'!$B$14,IF(V595="PRINCIPAL",'TARIFAS 2025'!$B$11,IF(V595="INTERMEDIA",'TARIFAS 2025'!$C$11,IF(V595="LEJANA",'TARIFAS 2025'!$D$11)))) -> 36351 | AA595: =Z595*Y595 -> 36351
A596: BOGOTA | B596: =VLOOKUP(A596,'CENTROS DE COSTOS'!A:D,2,0) -> 0036-0004 | C596: =VLOOKUP(A596,'CENTROS DE COSTOS'!A:D,3,0) -> Wompi Centro | D596: 25286 | E596: 2835272 | F596: 31793 | G596: ORDEN DE CAMBIO | H596: CUNDINAMARCA | I596: FUNZA | J596: BARRIO C.C. GERONA FUNZA | K596: WOMPI | L596: FO-25-1631620 | M596: 45933.442 | N596: 45940.371 | O596: ROLLOS | P596: ROLLOS | Q596: EJECUTADO_EXITOSO | R596: EJECUTADO EXITOSO | S596: 05/10/2025 SE REALIZA ENVIO DE ROLLOS CON GUIA | 10/10/2025 SE REALIZA ENVIO DE 24 ROLLOS, CON LA GUIA 2235596139 SERVIENTREGA. SE CONFIRMA ENTREGA EXITOSA POR PARTE DE LA TRANSPORTADORA | T596: ENVÍO | U596: 24 | V596: INTERMEDIA | W596: =VLOOKUP(D596,TIPOLOGIA!A:F,6,0) -> TERRESTRE | X596: HERNANDEZ GUARIN MIGUEL JULIAN | Y596: 1 | Z596: =IF(T596="SOPORTE_TELEFÓNICO",'TARIFAS 2025'!$B$14,IF(V596="PRINCIPAL",'TARIFAS 2025'!$B$11,IF(V596="INTERMEDIA",'TARIFAS 2025'!$C$11,IF(V596="LEJANA",'TARIFAS 2025'!$D$11)))) -> 36351 | AA596: =Z596*Y596 -> 36351
A597: VALLEDUPAR | B597: =VLOOKUP(A597,'CENTROS DE COSTOS'!A:D,2,0) -> 0036-0001 | C597: =VLOOKUP(A597,'CENTROS DE COSTOS'!A:D,3,0) -> Wompi Costa | D597: 20621 | E597: 2835448 | F597: 63766 | G597: ORDEN DE CAMBIO | H597: CESAR | I597: LA PAZ | J597: BARRIO SAN FRANCISCO LA PAZ | K597: WOMPI | L597: FO-25-1631618 | M597: 45933.448 | N597: 45940.372 | O597: ROLLOS | P597: ROLLOS | Q597: EJECUTADO_EXITOSO | R597: EJECUTADO EXITOSO | S597: 05/10/2025 SE REALIZA ENVIO DE ROLLOS CON GUIA | 10/10/2025 SE REALIZA ENVIO DE 64 ROLLOS, CON LA GUIA 2205447217 SERVIENTREGA. SE CONFIRMA ENTREGA EXITOSA POR PARTE DE LA TRANSPORTADORA | T597: ENVÍO | U597: 64 | V597: INTERMEDIA | W597: =VLOOKUP(D597,TIPOLOGIA!A:F,6,0) -> TERRESTRE | X597: GOMEZ FERRARO JOHANA | Y597: 1 | Z597: =IF(T597="SOPORTE_TELEFÓNICO",'TARIFAS 2025'!$B$14,IF(V597="PRINCIPAL",'TARIFAS 2025'!$B$11,IF(V597="INTERMEDIA",'TARIFAS 2025'!$C$11,IF(V597="LEJANA",'TARIFAS 2025'!$D$11)))) -> 36351 | AA597: =Z597*Y597 -> 36351
A598: BUCARAMANGA | B598: =VLOOKUP(A598,'CENTROS DE COSTOS'!A:D,2,0) -> 0036-0007 | C598: =VLOOKUP(A598,'CENTROS DE COSTOS'!A:D,3,0) -> Wompi Santander | D598: 68001 | E598: 2859954 | F598: 60361 | G598: ORDEN DE CAMBIO | H598: SANTANDER | I598: BUCARAMANGA | J598: GUERRERO PULIDO MARY DANELLY | K598: WOMPI | L598: FO-25-1649782 | M598: 45938.7 | N598: 45940.408 | O598: ROLLOS | P598: ROLLOS | Q598: EJECUTADO_EXITOSO | R598: EJECUTADO EXITOSO | S598: 09/10/2025 SE ESCALA AL COORDINADOR DE ZONA PARA ENTREGA DE ROLLOS EN SITIO | 09/10/2025 SE VISITA COMERCIO SE HACE ENTREGA DE 32 ROLLOS | T598: VISITA_TÉCNICA | U598: 32 | V598: PRINCIPAL | W598: =VLOOKUP(D598,TIPOLOGIA!A:F,6,0) -> TERRESTRE | X598: GOMEZ FERRARO JOHANA | Y598: 1 | Z598: =IF(T598="SOPORTE_TELEFÓNICO",'TARIFAS 2025'!$B$14,IF(V598="PRINCIPAL",'TARIFAS 2025'!$B$11,IF(V598="INTERMEDIA",'TARIFAS 2025'!$C$11,IF(V598="LEJANA",'TARIFAS 2025'!$D$11)))) -> 31419 | AA598: =Z598*Y598 -> 31419
A599: MEDELLIN | B599: =VLOOKUP(A599,'CENTROS DE COSTOS'!A:D,2,0) -> 0036-0005 | C599: =VLOOKUP(A599,'CENTROS DE COSTOS'!A:D,3,0) -> Wompi Noroccidente | D599: 5001 | E599: 2847089 | F599: 12867 | G599: ORDEN DE CAMBIO | H599: ANTIOQUIA | I599: MEDELLÍN | J599: DEPOSITO Y FERRETERIA LA HONDA | K599: WOMPI | L599: FO-25-1637082 | M599: 45936.67 | N599: 45940.413 | O599: ROLLOS | P599: ROLLOS | Q599: EJECUTADO_EXITOSO | R599: EJECUTADO EXITOSO | S599: 09/10/2025 SE ESCALA AL COORDINADOR DE ZONA PARA ENTREGA DE ROLLOS EN SITIO | 09/10/2025 SE REALIZA ENTREGA EFECTIVA DE 64 ROLLOS | T599: VISITA_TÉCNICA | U599: 64 | V599: PRINCIPAL | W599: =VLOOKUP(D599,TIPOLOGIA!A:F,6,0) -> TERRESTRE | X599: GELVEZ MOGOLLON JOSE ELISEO | Y599: 1 | Z599: =IF(T599="SOPORTE_TELEFÓNICO",'TARIFAS 2025'!$B$14,IF(V599="PRINCIPAL",'TARIFAS 2025'!$B$11,IF(V599="INTERMEDIA",'TARIFAS 2025'!$C$11,IF(V599="LEJANA",'TARIFAS 2025'!$D$11)))) -> 31419 | AA599: =Z599*Y599 -> 31419
A600: BARRANQUILLA | B600: =VLOOKUP(A600,'CENTROS DE COSTOS'!A:D,2,0) -> 0036-0001 | C600: =VLOOKUP(A600,'CENTROS DE COSTOS'!A:D,3,0) -> Wompi Costa | D600: 8758 | E600: 2847737 | F600: 41639 | G600: ORDEN DE CAMBIO | H600: ATLANTICO | I600: SOLEDAD | J600: BARRIO LOS NOGALES SOLEDAD | K600: WOMPI | L600: FO-25-1637511 | M600: 45937.333 | N600: 45940.418 | O600: ROLLOS | P600: ROLLOS | Q600: EJECUTADO_EXITOSO | R600: EJECUTADO EXITOSO | S600: 06/10/2025 SE ESCALA AL COORDINADOR DE ZONA PARA ENTREGA DE ROLLOS EN SITIO | 08/10/2025 SE HACE ENTREGA DE 40 ROLLOS WOMPI EN LA CARRERA 12 76A 52 | T600: VISITA_TÉCNICA | U600: 40 | V600: PRINCIPAL | W600: =VLOOKUP(D600,TIPOLOGIA!A:F,6,0) -> TERRESTRE | X600: MARIN PIEDRAHITA JIMMY ALEXIS | Y600: 1 | Z600: =IF(T600="SOPORTE_TELEFÓNICO",'TARIFAS 2025'!$B$14,IF(V600="PRINCIPAL",'TARIFAS 2025'!$B$11,IF(V600="INTERMEDIA",'TARIFAS 2025'!$C$11,IF(V600="LEJANA",'TARIFAS 2025'!$D$11)))) -> 31419 | AA600: =Z600*Y600 -> 31419
A601: MONTERIA | B601: =VLOOKUP(A601,'CENTROS DE COSTOS'!A:D,2,0) -> 0036-0001 | C601: =VLOOKUP(A601,'CENTROS DE COSTOS'!A:D,3,0) -> Wompi Costa | D601: 23001 | E601: 2849584 | F601: 79193 | G601: ORDEN DE CAMBIO | H601: CORDOBA | I601: MONTERIA | J601: BARRIO CENTRO MONTERIA 1OK | K601: WOMPI | L601: FO-25-1642329 | M601: 45937.399 | N601: 45940.421 | O601: ROLLOS | P601: ROLLOS | Q601: EJECUTADO_EXITOSO | R601: EJECUTADO EXITOSO | S601: 07/10/2025 SE ESCALA AL COORDINADOR DE ZONA PARA ENTREGA DE ROLLOS EN SITIO | 08/10/2025 SE REALIZA VISITA PARA ENTREGA DE 8 ROLLOS A CORRESPONSAL WOMPI, LOCAL SE ENCUENTRA CERRADO, LOCALES ALREDEDOR INDICAN QUE EL DÍA DE HOY NO HAN REALIZADO APERTURA, NO SE LOGRA ESTABLECER COMUNICACIÓN CON EL CONTACTO ASOCIADO(LLAMADA A CORREO DE VOZ) SE PROCEDE A DEJAR LOS ROLLOS EN EL SIGUIENTE LOCAL(COMERCIALIZADORA Y RETROVENTAS LOS 3 DIAMANTES) SR. KAREN LEAL. | T601: VISITA_TÉCNICA | U601: 8 | V601: PRINCIPAL | W601: =VLOOKUP(D601,TIPOLOGIA!A:F,6,0) -> TERRESTRE | X601: ORTEGA TORRES JUAN SEBASTIAN | Y601: 1 | Z601: =IF(T601="SOPORTE_TELEFÓNICO",'TARIFAS 2025'!$B$14,IF(V601="PRINCIPAL",'TARIFAS 2025'!$B$11,IF(V601="INTERMEDIA",'TARIFAS 2025'!$C$11,IF(V601="LEJANA",'TARIFAS 2025'!$D$11)))) -> 31419 | AA601: =Z601*Y601 -> 31419
A602: CUCUTA | B602: =VLOOKUP(A602,'CENTROS DE COSTOS'!A:D,2,0) -> 0036-0007 | C602: =VLOOKUP(A602,'CENTROS DE COSTOS'!A:D,3,0) -> Wompi Santander | D602: 54405 | E602: 2858783 | F602: 40085 | G602: ORDEN DE CAMBIO | H602: NORTE DE SANTANDER | I602: LOS PATIOS | J602: ESTACION DE SERVICIO COROZAL JORGE SANCHEZ | K602: WOMPI | L602: FO-25-1648626 | M602: 45938.624 | N602: 45940.427 | O602: ROLLOS | P602: ROLLOS | Q602: EJECUTADO_EXITOSO | R602: EJECUTADO EXITOSO | S602: 08/10/2025 SE ESCALA AL COORDINADOR DE ZONA PARA ENTREGA DE ROLLOS EN SITIO | 09/10/2025 SE REALIZA VISITA, SE ENTREGAN 56 ROLLOS | T602: VISITA_TÉCNICA | U602: 56 | V602: PRINCIPAL | W602: =VLOOKUP(D602,TIPOLOGIA!A:F,6,0) -> TERRESTRE | X602: MARQUEZ HOYOS JEYSON DANIEL | Y602: 1 | Z602: =IF(T602="SOPORTE_TELEFÓNICO",'TARIFAS 2025'!$B$14,IF(V602="PRINCIPAL",'TARIFAS 2025'!$B$11,IF(V602="INTERMEDIA",'TARIFAS 2025'!$C$11,IF(V602="LEJANA",'TARIFAS 2025'!$D$11)))) -> 31419 | AA602: =Z602*Y602 -> 31419
... A669: TUNJA | B669: =VLOOKUP(A669,'CENTROS DE COSTOS'!A:D,2,0) -> 0036-0007 | C669: =VLOOKUP(A669,'CENTROS DE COSTOS'!A:D,3,0) -> Wompi Santander | D669: 15001 | E669: 2851944 | F669: 70726 | G669: ORDEN DE CAMBIO | H669: BOYACA | I669: TUNJA | J669: LOS MUICAS TUNJA | K669: WOMPI | L669: FO-25-1642327 | M669: 45937.558 | N669: 45940.669 | O669: ROLLOS | P669: ROLLOS | Q669: EJECUTADO_EXITOSO | R669: EJECUTADO EXITOSO | S669: 07/10/2025 SE ESCALA AL COORDINADOR DE ZONA PARA ENTREGA DE ROLLOS EN SITIO | 08/10/2025 ENTREGA DE 32 ROLLOS WOMPI CON VISITA EXITOSA | T669: VISITA_TÉCNICA | U669: 32 | V669: PRINCIPAL | W669: =VLOOKUP(D669,TIPOLOGIA!A:F,6,0) -> TERRESTRE | X669: BETANCUR AGUIRRE EDGAR AUGUSTO | Y669: 1 | Z669: =IF(T669="SOPORTE_TELEFÓNICO",'TARIFAS 2025'!$B$14,IF(V669="PRINCIPAL",'TARIFAS 2025'!$B$11,IF(V669="INTERMEDIA",'TARIFAS 2025'!$C$11,IF(V669="LEJANA",'TARIFAS 2025'!$D$11)))) -> 31419 | AA669: =Z669*Y669 -> 31419
A670: NEIVA | B670: =VLOOKUP(A670,'CENTROS DE COSTOS'!A:D,2,0) -> 0036-0006 | C670: =VLOOKUP(A670,'CENTROS DE COSTOS'!A:D,3,0) -> Wompi Oriente | D670: 41001 | E670: 2850431 | F670: 52526 | G670: ORDEN DE CAMBIO | H670: HUILA | I670: NEIVA | J670: TIENDA MICROSWEB | K670: WOMPI | L670: FO-25-1640961 | M670: 45937.435 | N670: 45940.671 | O670: ROLLOS | P670: ROLLOS | Q670: EJECUTADO_EXITOSO | R670: EJECUTADO EXITOSO | S670: 07/10/2025 SE ESCALA AL COORDINADOR DE ZONA PARA ENTREGA DE ROLLOS EN SITIO | 08/10/2025 SE REALIZA VISITA AL PUNTO SE EVIDENCIA COMERCIO CERRADO. | T670: VISITA_TÉCNICA | V670: PRINCIPAL | W670: =VLOOKUP(D670,TIPOLOGIA!A:F,6,0) -> TERRESTRE | X670: HERRERA GARZON JEYSON STEVENT | Y670: 1 | Z670: =IF(T670="SOPORTE_TELEFÓNICO",'TARIFAS 2025'!$B$14,IF(V670="PRINCIPAL",'TARIFAS 2025'!$B$11,IF(V670="INTERMEDIA",'TARIFAS 2025'!$C$11,IF(V670="LEJANA",'TARIFAS 2025'!$D$11)))) -> 31419 | AA670: =Z670*Y670 -> 31419
A671: BARRANQUILLA | B671: =VLOOKUP(A671,'CENTROS DE COSTOS'!A:D,2,0) -> 0036-0001 | C671: =VLOOKUP(A671,'CENTROS DE COSTOS'!A:D,3,0) -> Wompi Costa | D671: 8758 | E671: 2851771 | F671: 65862 | G671: ORDEN DE CAMBIO | H671: ATLANTICO | I671: SOLEDAD | J671: VARIEDADES Y MISCELANEA MH | K671: WOMPI | L671: FO-25-1642425 | M671: 45937.533 | N671: 45940.678 | O671: ROLLOS | P671: ROLLOS | Q671: EJECUTADO_EXITOSO | R671: EJECUTADO EXITOSO | S671: 07/10/2025 SE ESCALA AL COORDINADOR DE ZONA PARA ENTREGA DE ROLLOS EN SITIO | 08/10/2025 SE HACE ENTREGA DE 24 ROLLOS WOMPI EN LA CALLE 41 13 69 | T671: VISITA_TÉCNICA | U671: 24 | V671: PRINCIPAL | W671: =VLOOKUP(D671,TIPOLOGIA!A:F,6,0) -> TERRESTRE | X671: DEVIA REINOSO JUAN CARLOS | Y671: 1 | Z671: =IF(T671="SOPORTE_TELEFÓNICO",'TARIFAS 2025'!$B$14,IF(V671="PRINCIPAL",'TARIFAS 2025'!$B$11,IF(V671="INTERMEDIA",'TARIFAS 2025'!$C$11,IF(V671="LEJANA",'TARIFAS 2025'!$D$11)))) -> 31419 | AA671: =Z671*Y671 -> 31419
A672: MEDELLIN | B672: =VLOOKUP(A672,'CENTROS DE COSTOS'!A:D,2,0) -> 0036-0005 | C672: =VLOOKUP(A672,'CENTROS DE COSTOS'!A:D,3,0) -> Wompi Noroccidente | D672: 5697 | E672: 2839584 | F672: 35625 | G672: ORDEN DE CAMBIO | H672: ANTIOQUIA | I672: EL SANTUARIO | J672: BARRIO SANTUARIO EL SANTUARIO 1 | K672: WOMPI | L672: FO-25-1643330 | M672: 45936.333 | N672: 45940.683 | O672: ROLLOS | P672: ROLLOS | Q672: EJECUTADO_EXITOSO | R672: EJECUTADO EXITOSO | S672: 07/10/2025 SE CONFIRMAN DATOS. SE REALIZA ENVIO DE ROLLOS CON GUIA | 10/10/2025 SE CONFIRMA ENTREGA EXITOSA POR PARTE DE LA TRANSPORTADORA MANDAR Y SERVIR CON LA GUIA 6345301360098 | T672: ENVÍO | U672: 64 | V672: INTERMEDIA | W672: =VLOOKUP(D672,TIPOLOGIA!A:F,6,0) -> TERRESTRE | X672: ORTEGA TORRES JUAN SEBASTIAN | Y672: 1 | Z672: =IF(T672="SOPORTE_TELEFÓNICO",'TARIFAS 2025'!$B$14,IF(V672="PRINCIPAL",'TARIFAS 2025'!$B$11,IF(V672="INTERMEDIA",'TARIFAS 2025'!$C$11,IF(V672="LEJANA",'TARIFAS 2025'!$D$11)))) -> 36351 | AA672: =Z672*Y672 -> 36351
A673: MEDELLIN | B673: =VLOOKUP(A673,'CENTROS DE COSTOS'!A:D,2,0) -> 0036-0005 | C673: =VLOOKUP(A673,'CENTROS DE COSTOS'!A:D,3,0) -> Wompi Noroccidente | D673: 5440 | E673: 2845895 | F673: 35835 | G673: ORDEN DE CAMBIO | H673: ANTIOQUIA | I673: MARINILLA | J673: BARRIO LA RAMADA MARINILLA | K673: WOMPI | L673: FO-25-1640734 | M673: 45936.617 | N673: 45940.699 | O673: ROLLOS | P673: ROLLOS | Q673: EJECUTADO_EXITOSO | R673: EJECUTADO EXITOSO | S673: 07/10/2025 SE REALIZA ENVIO DE ROLLOS CON GUIA | 10/10/2025 SE CONFIRMA ENTREGA EXITOSA POR PARTE DE LA TRANSPORTADORA MANDAR Y SERVIR CON LA GUIA 6345301359322 | T673: ENVÍO | U673: 32 | V673: INTERMEDIA | W673: =VLOOKUP(D673,TIPOLOGIA!A:F,6,0) -> TERRESTRE | X673: BETANCUR AGUIRRE EDGAR AUGUSTO | Y673: 1 | Z673: =IF(T673="SOPORTE_TELEFÓNICO",'TARIFAS 2025'!$B$14,IF(V673="PRINCIPAL",'TARIFAS 2025'!$B$11,IF(V673="INTERMEDIA",'TARIFAS 2025'!$C$11,IF(V673="LEJANA",'TARIFAS 2025'!$D$11)))) -> 36351 | AA673: =Z673*Y673 -> 36351
A674: MEDELLIN | B674: =VLOOKUP(A674,'CENTROS DE COSTOS'!A:D,2,0) -> 0036-0005 | C674: =VLOOKUP(A674,'CENTROS DE COSTOS'!A:D,3,0) -> Wompi Noroccidente | D674: 5664 | E674: 2839919 | F674: 33434 | G674: ORDEN DE CAMBIO | H674: ANTIOQUIA | I674: SAN PEDRO DE LOS MILAGROS | J674: BARRIO PARQUE SAN PEDRO DE LOS MILAGROS 1 | K674: WOMPI | L674: FO-25-1640209 | M674: 45936.333 | N674: 45940.711 | O674: ROLLOS | P674: ROLLOS | Q674: EJECUTADO_EXITOSO | R674: EJECUTADO EXITOSO | S674: 07/10/2025 SE REALIZA ENVIO DE ROLLOS CON GUIA | 10/10/2025 SE CONFIRMA ENTREGA EXITOSA POR PARTE DE LA TRANSPORTADORA MANDAR Y SERVIR CON LA GUIA 6345301359316 | T674: ENVÍO | U674: 64 | V674: INTERMEDIA | W674: =VLOOKUP(D674,TIPOLOGIA!A:F,6,0) -> TERRESTRE | X674: BETANCUR AGUIRRE EDGAR AUGUSTO | Y674: 1 | Z674: =IF(T674="SOPORTE_TELEFÓNICO",'TARIFAS 2025'!$B$14,IF(V674="PRINCIPAL",'TARIFAS 2025'!$B$11,IF(V674="INTERMEDIA",'TARIFAS 2025'!$C$11,IF(V674="LEJANA",'TARIFAS 2025'!$D$11)))) -> 36351 | AA674: =Z674*Y674 -> 36351
A675: CALI | B675: =VLOOKUP(A675,'CENTROS DE COSTOS'!A:D,2,0) -> 0036-0003 | C675: =VLOOKUP(A675,'CENTROS DE COSTOS'!A:D,3,0) -> Wompi Suroccidente | D675: 76001 | E675: 2839524 | F675: 77007 | G675: ORDEN DE CAMBIO | H675: VALLE DEL CAUCA | I675: CALI | J675: SERVIAMIGOS.COM | K675: WOMPI | L675: FO-25-1630973 | M675: 45936.333 | N675: 45940.713 | O675: ROLLOS | P675: ROLLOS | Q675: EJECUTADO_EXITOSO | R675: EJECUTADO EXITOSO | S675: 05/10/2025 EXITOSA | 08/10/2025 SE ENTREGAN 24 ROLLOS EN BUEN ESTADO | T675: VISITA_TÉCNICA | U675: 24 | V675: PRINCIPAL | W675: =VLOOKUP(D675,TIPOLOGIA!A:F,6,0) -> TERRESTRE | X675: BETANCUR AGUIRRE EDGAR AUGUSTO | Y675: 1 | Z675: =IF(T675="SOPORTE_TELEFÓNICO",'TARIFAS 2025'!$B$14,IF(V675="PRINCIPAL",'TARIFAS 2025'!$B$11,IF(V675="INTERMEDIA",'TARIFAS 2025'!$C$11,IF(V675="LEJANA",'TARIFAS 2025'!$D$11)))) -> 31419 | AA675: =Z675*Y675 -> 31419
A676: MEDELLIN | B676: =VLOOKUP(A676,'CENTROS DE COSTOS'!A:D,2,0) -> 0036-0005 | C676: =VLOOKUP(A676,'CENTROS DE COSTOS'!A:D,3,0) -> Wompi Noroccidente | D676: 5079 | E676: 2842812 | F676: 79624 | G676: ORDEN DE CAMBIO | H676: ANTIOQUIA | I676: BARBOSA | J676: RAPIAGRO | K676: WOMPI | L676: FO-25-1640199 | M676: 45936.408 | N676: 45940.715 | O676: ROLLOS | P676: ROLLOS | Q676: EJECUTADO_EXITOSO | R676: EJECUTADO EXITOSO | S676: 07/10/2025 SE REALIZA ENVIO DE ROLLOS CON GUIA | 10/10/2025 SE CONFIRMA ENTREGA EXITOSA POR PARTE DE LA TRANSPORTADORA MANDAR Y SERVIR CON LA GUIA 6345301359301 | T676: ENVÍO | U676: 24 | V676: INTERMEDIA | W676: =VLOOKUP(D676,TIPOLOGIA!A:F,6,0) -> TERRESTRE | X676: ESCOBAR LENIS JUAN SEBASTIAN | Y676: 1 | Z676: =IF(T676="SOPORTE_TELEFÓNICO",'TARIFAS 2025'!$B$14,IF(V676="PRINCIPAL",'TARIFAS 2025'!$B$11,IF(V676="INTERMEDIA",'TARIFAS 2025'!$C$11,IF(V676="LEJANA",'TARIFAS 2025'!$D$11)))) -> 36351 | AA676: =Z676*Y676 -> 36351
A677: MEDELLIN | B677: =VLOOKUP(A677,'CENTROS DE COSTOS'!A:D,2,0) -> 0036-0005 | C677: =VLOOKUP(A677,'CENTROS DE COSTOS'!A:D,3,0) -> Wompi Noroccidente | D677: 5809 | E677: 2842629 | F677: 66016 | G677: ORDEN DE CAMBIO | H677: ANTIOQUIA | I677: TITIRIBI | J677: BARRIO TITIRIBI TITIRIBI 1 | K677: WOMPI | L677: FO-25-1640203 | M677: 45936.395 | N677: 45940.717 | O677: ROLLOS | P677: ROLLOS | Q677: EJECUTADO_EXITOSO | R677: EJECUTADO EXITOSO | S677: 07/10/2025 SE REALIZA ENVIO DE ROLLOS CON GUIA | 10/10/2025 SE CONFIRMA ENTREGA EXITOSA POR PARTE DE LA TRANSPORTADORA MANDAR Y SERVIR CON LA GUIA 6345301359304 | T677: ENVÍO | U677: 64 | V677: INTERMEDIA | W677: =VLOOKUP(D677,TIPOLOGIA!A:F,6,0) -> TERRESTRE | X677: BETANCUR AGUIRRE EDGAR AUGUSTO | Y677: 1 | Z677: =IF(T677="SOPORTE_TELEFÓNICO",'TARIFAS 2025'!$B$14,IF(V677="PRINCIPAL",'TARIFAS 2025'!$B$11,IF(V677="INTERMEDIA",'TARIFAS 2025'!$C$11,IF(V677="LEJANA",'TARIFAS 2025'!$D$11)))) -> 36351 | AA677: =Z677*Y677 -> 36351
A678: MEDELLIN | B678: =VLOOKUP(A678,'CENTROS DE COSTOS'!A:D,2,0) -> 0036-0005 | C678: =VLOOKUP(A678,'CENTROS DE COSTOS'!A:D,3,0) -> Wompi Noroccidente | D678: 5237 | E678: 2831187 | F678: 18129 | G678: ORDEN DE CAMBIO | H678: ANTIOQUIA | I678: DON MATIAS | J678: ZONA INDUSTRIAL DON MATIAS | K678: WOMPI | L678: FO-25-1631639 | M678: 45932.616 | N678: 45940.719 | O678: ROLLOS | P678: ROLLOS | Q678: EJECUTADO_EXITOSO | R678: EJECUTADO EXITOSO | S678: 05/10/2025 SE REALIZA ENVIO DE ROLLOS CON GUIA | 09/10/2025 EL ENVIO ESTA EN PROCESO | 10/10/2025 SE CONFIRMA ENTREGA EXITOSA POR PARTE DE LA TRANSPORTADORA MANDAR Y SERVIR CON LA GUIA 6345301358010 | T678: ENVÍO | U678: 24 | V678: INTERMEDIA | W678: =VLOOKUP(D678,TIPOLOGIA!A:F,6,0) -> TERRESTRE | X678: BETANCUR AGUIRRE EDGAR AUGUSTO | Y678: 1 | Z678: =IF(T678="SOPORTE_TELEFÓNICO",'TARIFAS 2025'!$B$14,IF(V678="PRINCIPAL",'TARIFAS 2025'!$B$11,IF(V678="INTERMEDIA",'TARIFAS 2025'!$C$11,IF(V678="LEJANA",'TARIFAS 2025'!$D$11)))) -> 36351 | AA678: =Z678*Y678 -> 36351
A679: BARRANQUILLA | B679: =VLOOKUP(A679,'CENTROS DE COSTOS'!A:D,2,0) -> 0036-0001 | C679: =VLOOKUP(A679,'CENTROS DE COSTOS'!A:D,3,0) -> Wompi Costa | D679: 8758 | E679: 2844529 | F679: 75454 | G679: ORDEN DE CAMBIO | H679: ATLANTICO | I679: SOLEDAD | J679: BARRIO GAVIOTAS SOLEDAD | K679: WOMPI | L679: FO-25-1634832 | M679: 45936.487 | N679: 45940.722 | O679: ROLLOS | P679: ROLLOS | Q679: EJECUTADO_EXITOSO | R679: EJECUTADO EXITOSO | S679: 06/10/2025 SE ESCALA AL COORDINADOR DE ZONA PARA ENTREGA DE ROLLOS EN SITIO | 08/10/2025 SE REALIZA VISITA SE ENTREGA 32 ROLLOS | T679: VISITA_TÉCNICA | U679: 32 | V679: PRINCIPAL | W679: =VLOOKUP(D679,TIPOLOGIA!A:F,6,0) -> TERRESTRE | X679: BETANCUR AGUIRRE EDGAR AUGUSTO | Y679: 1 | Z679: =IF(T679="SOPORTE_TELEFÓNICO",'TARIFAS 2025'!$B$14,IF(V679="PRINCIPAL",'TARIFAS 2025'!$B$11,IF(V679="INTERMEDIA",'TARIFAS 2025'!$C$11,IF(V679="LEJANA",'TARIFAS 2025'!$D$11)))) -> 31419 | AA679: =Z679*Y679 -> 31419
A680: PEREIRA | B680: =VLOOKUP(A680,'CENTROS DE COSTOS'!A:D,2,0) -> 0036-0002 | C680: =VLOOKUP(A680,'CENTROS DE COSTOS'!A:D,3,0) -> Wompi Eje Cafetero | D680: 63001 | E680: 2844695 | F680: 55936 | G680: ORDEN DE CAMBIO | H680: QUINDIO | I680: ARMENIA | J680: BARRIO LA ISABELA ARMENIA | K680: WOMPI | L680: FO-25-1635159 | M680: 45936.506 | N680: 45940.722 | O680: ROLLOS | P680: ROLLOS | Q680: EJECUTADO_EXITOSO | R680: EJECUTADO EXITOSO | S680: 06/10/2025 SE ESCALA AL COORDINADOR DE ZONA PARA ENTREGA DE ROLLOS EN SITIO | 09/10/2025 SE VISITA COMERCIO SE REALIZÓ ENTREGA DE 40 ROLLOS WOMPI | T680: VISITA_TÉCNICA | U680: 40 | V680: INTERMEDIA | W680: =VLOOKUP(D680,TIPOLOGIA!A:F,6,0) -> TERRESTRE | X680: VILLACOB VILLACOB ELKIN EDUARDO | Y680: 1 | Z680: =IF(T680="SOPORTE_TELEFÓNICO",'TARIFAS 2025'!$B$14,IF(V680="PRINCIPAL",'TARIFAS 2025'!$B$11,IF(V680="INTERMEDIA",'TARIFAS 2025'!$C$11,IF(V680="LEJANA",'TARIFAS 2025'!$D$11)))) -> 36351 | AA680: =Z680*Y680 -> 36351
A681: MEDELLIN | B681: =VLOOKUP(A681,'CENTROS DE COSTOS'!A:D,2,0) -> 0036-0005 | C681: =VLOOKUP(A681,'CENTROS DE COSTOS'!A:D,3,0) -> Wompi Noroccidente | D681: 5664 | E681: 2838416 | F681: 21444 | G681: ORDEN DE CAMBIO | H681: ANTIOQUIA | I681: SAN PEDRO DE LOS MILAGROS | J681: CL PRINCIPAL SAN PEDRO | K681: WOMPI | L681: FO-25-1629606 | M681: 45936.333 | N681: 45940.722 | O681: ROLLOS | P681: ROLLOS | Q681: EJECUTADO_EXITOSO | R681: EJECUTADO EXITOSO | S681: 04/10/2025 SE CONFIRMA ENVIO CON LA SEÑORA JHON AVENDAÑO | 10/10/2025 SE CONFIRMA ENTREGA EXITOSA POR PARTE DE LA TRANSPORTADORA MANDAR Y SERVIR CON LA GUIA 6345301357940 | T681: ENVÍO | U681: 24 | V681: INTERMEDIA | W681: =VLOOKUP(D681,TIPOLOGIA!A:F,6,0) -> TERRESTRE | X681: SANCHEZ SOLORZANO JUAN SEBASTIAN | Y681: 1 | Z681: =IF(T681="SOPORTE_TELEFÓNICO",'TARIFAS 2025'!$B$14,IF(V681="PRINCIPAL",'TARIFAS 2025'!$B$11,IF(V681="INTERMEDIA",'TARIFAS 2025'!$C$11,IF(V681="LEJANA",'TARIFAS 2025'!$D$11)))) -> 36351 | AA681: =Z681*Y681 -> 36351
A682: BARRANQUILLA | B682: =VLOOKUP(A682,'CENTROS DE COSTOS'!A:D,2,0) -> 0036-0001 | C682: =VLOOKUP(A682,'CENTROS DE COSTOS'!A:D,3,0) -> Wompi Costa | D682: 8001 | E682: 2844774 | F682: 79737 | G682: ORDEN DE CAMBIO | H682: ATLANTICO | I682: BARRANQUILLA | J682: ACCESORIOS DIGITALES GABY | K682: WOMPI | L682: FO-25-1635156 | M682: 45936.512 | N682: 45940.724 | O682: ROLLOS | P682: ROLLOS | Q682: EJECUTADO_EXITOSO | R682: EJECUTADO EXITOSO | S682: 06/10/2025 SE ESCALA AL COORDINADOR DE ZONA PARA ENTREGA DE ROLLOS EN SITIO | 08/10/2025 SE HACE ENTREGA DE 16 ROLLOS WOMPI EN LA CALLE 108 13 10 | T682: VISITA_TÉCNICA | U682: 16 | V682: PRINCIPAL | W682: =VLOOKUP(D682,TIPOLOGIA!A:F,6,0) -> TERRESTRE | X682: BETANCUR AGUIRRE EDGAR AUGUSTO | Y682: 1 | Z682: =IF(T682="SOPORTE_TELEFÓNICO",'TARIFAS 2025'!$B$14,IF(V682="PRINCIPAL",'TARIFAS 2025'!$B$11,IF(V682="INTERMEDIA",'TARIFAS 2025'!$C$11,IF(V682="LEJANA",'TARIFAS 2025'!$D$11)))) -> 31419 | AA682: =Z682*Y682 -> 31419
... A746: IBAGUE | B746: =VLOOKUP(A746,'CENTROS DE COSTOS'!A:D,2,0) -> 0036-0006 | C746: =VLOOKUP(A746,'CENTROS DE COSTOS'!A:D,3,0) -> Wompi Oriente | D746: 73001 | E746: 2865890 | F746: 79095 | G746: ORDEN DE CAMBIO | H746: TOLIMA | I746: IBAGUE | J746: RED Y COMUNICACIONES | K746: WOMPI | L746: FO-25-1663949 | M746: 45940.333 | N746: 45942.46 | O746: ROLLOS | P746: ROLLOS | Q746: EJECUTADO_EXITOSO | R746: EJECUTADO EXITOSO | S746: 09/10/2025 SE ESCALA AL COORDINADOR DE ZONA PARA ENTREGA DE ROLLOS EN SITIO | 11/10/2025 SE TE ENTREGA DE 56 ROLLOS WOMPI POR SOLICITUD DEL. | T746: VISITA_TÉCNICA | U746: 56 | V746: PRINCIPAL | W746: =VLOOKUP(D746,TIPOLOGIA!A:F,6,0) -> TERRESTRE | X746: THOMAS CAMPO SIGIFREDO SEGUNDO | Y746: 1 | Z746: =IF(T746="SOPORTE_TELEFÓNICO",'TARIFAS 2025'!$B$14,IF(V746="PRINCIPAL",'TARIFAS 2025'!$B$11,IF(V746="INTERMEDIA",'TARIFAS 2025'!$C$11,IF(V746="LEJANA",'TARIFAS 2025'!$D$11)))) -> 31419 | AA746: =Z746*Y746 -> 31419
A747: CARTAGENA | B747: =VLOOKUP(A747,'CENTROS DE COSTOS'!A:D,2,0) -> 0036-0001 | C747: =VLOOKUP(A747,'CENTROS DE COSTOS'!A:D,3,0) -> Wompi Costa | D747: 13001 | E747: 2846589 | F747: 50317 | G747: ORDEN DE CAMBIO | H747: BOLIVAR | I747: CARTAGENA | J747: TRANSCRIPCOPIAS L.A | K747: WOMPI | L747: FO-25-1642440 | M747: 45936.647 | N747: 45942.462 | O747: ROLLOS | P747: ROLLOS | Q747: EJECUTADO_CANCELADO | R747: CB CERRADO - DESOCUPADO | S747: 07/10/2025 SE ESCALA AL COORDINADOR DE ZONA PARA ENTREGA DE ROLLOS EN SITIO | 11/10/2025 SE LLEGA AL SITIO Y SE ENCUENTRA CERRADO SE LLAMA AL CONTACTO Y NO HAY RESPUESTA NI POR WATHSAPP NO FUE POSIBLE ENTREGAR LOS ROLLOS | T747: VISITA_TÉCNICA | V747: PRINCIPAL | W747: =VLOOKUP(D747,TIPOLOGIA!A:F,6,0) -> TERRESTRE | X747: BARRAGAN TAFUR EDWIN ESTEBAN | Y747: 1 | Z747: =IF(T747="SOPORTE_TELEFÓNICO",'TARIFAS 2025'!$B$14,IF(V747="PRINCIPAL",'TARIFAS 2025'!$B$11,IF(V747="INTERMEDIA",'TARIFAS 2025'!$C$11,IF(V747="LEJANA",'TARIFAS 2025'!$D$11)))) -> 31419 | AA747: =Z747*Y747 -> 31419
A748: PEREIRA | B748: =VLOOKUP(A748,'CENTROS DE COSTOS'!A:D,2,0) -> 0036-0002 | C748: =VLOOKUP(A748,'CENTROS DE COSTOS'!A:D,3,0) -> Wompi Eje Cafetero | D748: 66001 | E748: 2854259 | F748: 55937 | G748: ORDEN DE CAMBIO | H748: RISARALDA | I748: PEREIRA | J748: BARRIO VILLA ELISA PEREIRA | K748: WOMPI | L748: FO-25-1644540 | M748: 45938.333 | N748: 45942.465 | O748: ROLLOS | P748: ROLLOS | Q748: EJECUTADO_EXITOSO | R748: EJECUTADO EXITOSO | S748: 08/10/2025 SE ESCALA AL COORDINADOR DE ZONA PARA ENTREGA DE ROLLOS EN SITIO | 11/10/2025 SE VISITA COMERCIO SE REALIZA ENTREGA DE 56 ROLLOS DE PAPEL PARA DATÁFONO WOMPI | T748: VISITA_TÉCNICA | U748: 56 | V748: PRINCIPAL | W748: =VLOOKUP(D748,TIPOLOGIA!A:F,6,0) -> TERRESTRE | X748: MARTINEZ SALGUEDO ANDRES AUGUSTO | Y748: 1 | Z748: =IF(T748="SOPORTE_TELEFÓNICO",'TARIFAS 2025'!$B$14,IF(V748="PRINCIPAL",'TARIFAS 2025'!$B$11,IF(V748="INTERMEDIA",'TARIFAS 2025'!$C$11,IF(V748="LEJANA",'TARIFAS 2025'!$D$11)))) -> 31419 | AA748: =Z748*Y748 -> 31419
A749: VILLAVICENCIO | B749: =VLOOKUP(A749,'CENTROS DE COSTOS'!A:D,2,0) -> 0036-0006 | C749: =VLOOKUP(A749,'CENTROS DE COSTOS'!A:D,3,0) -> Wompi Oriente | D749: 50001 | E749: 2862695 | F749: 70226 | G749: ORDEN DE CAMBIO | H749: META | I749: VILLAVICENCIO | J749: BARRIO ACAPULCO VILLAVICENCIO 1 | K749: WOMPI | L749: FO-25-1654912 | M749: 45939.46 | N749: 45942.469 | O749: ROLLOS | P749: ROLLOS | Q749: EJECUTADO_EXITOSO | R749: EJECUTADO EXITOSO | S749: 09/10/2025 SE ESCALA AL COORDINADOR DE ZONA PARA ENTREGA DE ROLLOS EN SITIO | 10/10/2025 SE VISITA CB Y SE REALIZA ENTREGA DE 24 ROLLOS DE PAPEL TERMICO PARA DATÁFONO WOMPI | T749: VISITA_TÉCNICA | U749: 24 | V749: PRINCIPAL | W749: =VLOOKUP(D749,TIPOLOGIA!A:F,6,0) -> TERRESTRE | X749: LOAIZA LOPEZ JHON FREDDY | Y749: 1 | Z749: =IF(T749="SOPORTE_TELEFÓNICO",'TARIFAS 2025'!$B$14,IF(V749="PRINCIPAL",'TARIFAS 2025'!$B$11,IF(V749="INTERMEDIA",'TARIFAS 2025'!$C$11,IF(V749="LEJANA",'TARIFAS 2025'!$D$11)))) -> 31419 | AA749: =Z749*Y749 -> 31419
A750: VILLAVICENCIO | B750: =VLOOKUP(A750,'CENTROS DE COSTOS'!A:D,2,0) -> 0036-0006 | C750: =VLOOKUP(A750,'CENTROS DE COSTOS'!A:D,3,0) -> Wompi Oriente | D750: 50001 | E750: 2862624 | F750: 70549 | G750: ORDEN DE CAMBIO | H750: META | I750: VILLAVICENCIO | J750: SUPERTIENDA JHOJAN | K750: WOMPI | L750: FO-25-1654982 | M750: 45939.44 | N750: 45942.472 | O750: ROLLOS | P750: ROLLOS | Q750: EJECUTADO_EXITOSO | R750: EJECUTADO EXITOSO | S750: 09/10/2025 SE ESCALA AL COORDINADOR DE ZONA PARA ENTREGA DE ROLLOS EN SITIO | 10/10/2025 SE VISITA CB Y SE REALIZA ENTREGA DE 40 ROLLOS DE PAPEL TERMICO PARA DATÁFONO WOMPI | T750: VISITA_TÉCNICA | U750: 40 | V750: PRINCIPAL | W750: =VLOOKUP(D750,TIPOLOGIA!A:F,6,0) -> TERRESTRE | X750: GARZON RUIZ LUIS MIGUEL | Y750: 1 | Z750: =IF(T750="SOPORTE_TELEFÓNICO",'TARIFAS 2025'!$B$14,IF(V750="PRINCIPAL",'TARIFAS 2025'!$B$11,IF(V750="INTERMEDIA",'TARIFAS 2025'!$C$11,IF(V750="LEJANA",'TARIFAS 2025'!$D$11)))) -> 31419 | AA750: =Z750*Y750 -> 31419
A751: CARTAGENA | B751: =VLOOKUP(A751,'CENTROS DE COSTOS'!A:D,2,0) -> 0036-0001 | C751: =VLOOKUP(A751,'CENTROS DE COSTOS'!A:D,3,0) -> Wompi Costa | D751: 13001 | E751: 2844177 | F751: 17204 | G751: ORDEN DE CAMBIO | H751: BOLIVAR | I751: CARTAGENA | J751: BARRIO MAMONAL II CARTAGENA | K751: WOMPI | L751: FO-25-1634839 | M751: 45936.477 | N751: 45942.474 | O751: ROLLOS | P751: ROLLOS | Q751: EJECUTADO_EXITOSO | R751: EJECUTADO EXITOSO | S751: 06/10/2025 SE ESCALA AL COORDINADOR DE ZONA PARA ENTREGA DE ROLLOS EN SITIO | 11/10/2025 SE ENTREGAN 32 ROLLOS | T751: VISITA_TÉCNICA | U751: 32 | V751: PRINCIPAL | W751: =VLOOKUP(D751,TIPOLOGIA!A:F,6,0) -> TERRESTRE | X751: GARZON RUIZ LUIS MIGUEL | Y751: 1 | Z751: =IF(T751="SOPORTE_TELEFÓNICO",'TARIFAS 2025'!$B$14,IF(V751="PRINCIPAL",'TARIFAS 2025'!$B$11,IF(V751="INTERMEDIA",'TARIFAS 2025'!$C$11,IF(V751="LEJANA",'TARIFAS 2025'!$D$11)))) -> 31419 | AA751: =Z751*Y751 -> 31419
A752: BOGOTA | B752: =VLOOKUP(A752,'CENTROS DE COSTOS'!A:D,2,0) -> 0036-0004 | C752: =VLOOKUP(A752,'CENTROS DE COSTOS'!A:D,3,0) -> Wompi Centro | D752: 11001 | E752: 2859340 | F752: 41872 | G752: ORDEN DE CAMBIO | H752: CUNDINAMARCA | I752: BOGOTÁ | J752: IBC COMPUTADORES | K752: WOMPI | L752: FO-25-1648604 | M752: 45938.66 | N752: 45942.478 | O752: ROLLOS | P752: ROLLOS | Q752: EJECUTADO_EXITOSO | R752: EJECUTADO EXITOSO | S752: 08/10/2025 SE ESCALA AL COORDINADOR DE ZONA PARA ENTREGA DE ROLLOS EN SITIO | 11/10/2025 SE REALIZA LA ENTREGA DE 16 ROLLOS WOMPI | T752: VISITA_TÉCNICA | U752: 16 | V752: PRINCIPAL | W752: =VLOOKUP(D752,TIPOLOGIA!A:F,6,0) -> TERRESTRE | X752: CANEDO HERRERA ALEXANDER | Y752: 1 | Z752: =IF(T752="SOPORTE_TELEFÓNICO",'TARIFAS 2025'!$B$14,IF(V752="PRINCIPAL",'TARIFAS 2025'!$B$11,IF(V752="INTERMEDIA",'TARIFAS 2025'!$C$11,IF(V752="LEJANA",'TARIFAS 2025'!$D$11)))) -> 31419 | AA752: =Z752*Y752 -> 31419
A753: BOGOTA | B753: =VLOOKUP(A753,'CENTROS DE COSTOS'!A:D,2,0) -> 0036-0004 | C753: =VLOOKUP(A753,'CENTROS DE COSTOS'!A:D,3,0) -> Wompi Centro | D753: 25754 | E753: 2865460 | F753: 79324 | G753: ORDEN DE CAMBIO | H753: CUNDINAMARCA | I753: SOACHA | J753: BARRIO SAN NICOLAS SOACHA 6 | K753: WOMPI | L753: FO-25-1663964 | M753: 45939.684 | N753: 45942.48 | O753: ROLLOS | P753: ROLLOS | Q753: EJECUTADO_EXITOSO | R753: EJECUTADO EXITOSO | S753: 09/10/2025 SE ESCALA AL COORDINADOR DE ZONA PARA ENTREGA DE ROLLOS EN SITIO | 11/10/2025 DURANTE LA VISITA TECNICA PARA REALIZA ENTREGA DE ROLLOS PARA DATÁFONO CORRESPONSAL SE ENCUENTRA CERRADO SE LLAMA AL CELULAR EL CUAL CLIENTE INDICA POR LLAMADA LA ENTREGA DE ROLLOS EN UN DIRECCIÓN ALEDAÑA AL CORRESPONSAL | T753: VISITA_TÉCNICA | U753: 56 | V753: PRINCIPAL | W753: =VLOOKUP(D753,TIPOLOGIA!A:F,6,0) -> TERRESTRE | X753: ALARCON AREVALO JOHAN STIVEN | Y753: 1 | Z753: =IF(T753="SOPORTE_TELEFÓNICO",'TARIFAS 2025'!$B$14,IF(V753="PRINCIPAL",'TARIFAS 2025'!$B$11,IF(V753="INTERMEDIA",'TARIFAS 2025'!$C$11,IF(V753="LEJANA",'TARIFAS 2025'!$D$11)))) -> 31419 | AA753: =Z753*Y753 -> 31419
A754: CALI | B754: =VLOOKUP(A754,'CENTROS DE COSTOS'!A:D,2,0) -> 0036-0003 | C754: =VLOOKUP(A754,'CENTROS DE COSTOS'!A:D,3,0) -> Wompi Suroccidente | D754: 19001 | E754: 2839872 | F754: 48071 | G754: ORDEN DE CAMBIO | H754: CAUCA | I754: POPAYAN | J754: TIENDA LOS PAISAS LA 70N | K754: WOMPI | L754: FO-25-1631598 | M754: 45936.333 | N754: 45942.482 | O754: ROLLOS | P754: ROLLOS | Q754: EJECUTADO_EXITOSO | R754: EJECUTADO EXITOSO | S754: 05/10/2025 SE ESCALA AL COORDINADOR DE ZONA PARA ENTREGA DE ROLLOS EN SITIO | 11/10/2025 SE ENTREGA 48 ROLLOS WOMPI | T754: VISITA_TÉCNICA | U754: 48 | V754: LEJANA | W754: =VLOOKUP(D754,TIPOLOGIA!A:F,6,0) -> TERRESTRE | X754: GALEANO SORIANO JUAN DAVID | Y754: 1 | Z754: =IF(T754="SOPORTE_TELEFÓNICO",'TARIFAS 2025'!$B$14,IF(V754="PRINCIPAL",'TARIFAS 2025'!$B$11,IF(V754="INTERMEDIA",'TARIFAS 2025'!$C$11,IF(V754="LEJANA",'TARIFAS 2025'!$D$11)))) -> 40250 | AA754: =Z754*Y754 -> 40250
A755: PEREIRA | B755: =VLOOKUP(A755,'CENTROS DE COSTOS'!A:D,2,0) -> 0036-0002 | C755: =VLOOKUP(A755,'CENTROS DE COSTOS'!A:D,3,0) -> Wompi Eje Cafetero | D755: 66001 | E755: 2850565 | F755: 45906 | G755: ORDEN DE CAMBIO | H755: RISARALDA | I755: PEREIRA | J755: BARRIO CUBA PEREIRA 4 | K755: WOMPI | L755: FO-25-1640933 | M755: 45937.447 | N755: 45942.485 | O755: ROLLOS | P755: ROLLOS | Q755: EJECUTADO_EXITOSO | R755: EJECUTADO EXITOSO | S755: 07/10/2025 SE ESCALA AL COORDINADOR DE ZONA PARA ENTREGA DE ROLLOS EN SITIO | 11/10/2025 SE VISITA COMERCIO SE REALIZA ENTREGA DE 40 ROLLOS DE PAPEL PARA DATÁFONO WOMPI | T755: VISITA_TÉCNICA | U755: 40 | V755: PRINCIPAL | W755: =VLOOKUP(D755,TIPOLOGIA!A:F,6,0) -> TERRESTRE | X755: GIMBUEL LASSO LUIS GERMAN | Y755: 1 | Z755: =IF(T755="SOPORTE_TELEFÓNICO",'TARIFAS 2025'!$B$14,IF(V755="PRINCIPAL",'TARIFAS 2025'!$B$11,IF(V755="INTERMEDIA",'TARIFAS 2025'!$C$11,IF(V755="LEJANA",'TARIFAS 2025'!$D$11)))) -> 31419 | AA755: =Z755*Y755 -> 31419
A756: PEREIRA | B756: =VLOOKUP(A756,'CENTROS DE COSTOS'!A:D,2,0) -> 0036-0002 | C756: =VLOOKUP(A756,'CENTROS DE COSTOS'!A:D,3,0) -> Wompi Eje Cafetero | D756: 66001 | E756: 2850473 | F756: 65799 | G756: ORDEN DE CAMBIO | H756: RISARALDA | I756: PEREIRA | J756: BARRIO LA FLORIDA PEREIRA | K756: WOMPI | L756: FO-25-1640954 | M756: 45937.44 | N756: 45942.489 | O756: ROLLOS | P756: ROLLOS | Q756: EJECUTADO_EXITOSO | R756: EJECUTADO EXITOSO | S756: 07/10/2025 SE ESCALA AL COORDINADOR DE ZONA PARA ENTREGA DE ROLLOS EN SITIO | 11/10/2025 VISITAMOS COMERCIO REALIZAMOS ENTREGA DE 24 ROLLOS. | T756: VISITA_TÉCNICA | U756: 24 | V756: PRINCIPAL | W756: =VLOOKUP(D756,TIPOLOGIA!A:F,6,0) -> TERRESTRE | X756: LOAIZA LOPEZ JHON FREDDY | Y756: 1 | Z756: =IF(T756="SOPORTE_TELEFÓNICO",'TARIFAS 2025'!$B$14,IF(V756="PRINCIPAL",'TARIFAS 2025'!$B$11,IF(V756="INTERMEDIA",'TARIFAS 2025'!$C$11,IF(V756="LEJANA",'TARIFAS 2025'!$D$11)))) -> 31419 | AA756: =Z756*Y756 -> 31419
...

Sheet OC CIERRES
A1: CIUDAD SEDE | B1: CENTRO_COSTO | C1: DESCRIPCION CENTRO DE COSTOS | D1: CÓDIGO DANE | E1: TA/CODIGO ACTIVIDAD | F1: CODIGO CB | G1: ACTIVIDAD | H1: DEPARTAMENTO | I1: CIUDAD | J1: NOMBRE DEL CB | K1: RED | L1: FO | M1: FECHA ASIGNACION A LINEA COMUNICACIONES | N1: FECHA DEL CIERRE DEL TICKET (DD/MM/AAAA) | O1: SOLICITUD | P1: DESCRIPCIÓN | Q1: ESTADO | R1: CAUSAL ESTADO | S1: OBSERVACION | T1: FORMA DE ATENCIÓN | U1: CANTIDAD DE ROLLOS | V1: TIPOLOGIA | W1: TIPO DE TRAYECTO | X1: NOMBRE DEL TECNICO | Y1: DIAS DE ACTIVIDAD | Z1: VALOR DIAS ACTIVIDAD | AA1: VALOR TOTAL
A2: VILLAVICENCIO | B2: =VLOOKUP(A2,'CENTROS DE COSTOS'!A:D,2,0) -> 0036-0006 | C2: =VLOOKUP(A2,'CENTROS DE COSTOS'!A:D,3,0) -> Wompi Oriente | D2: 50001 | E2: LC-CS-25-000634 | F2: 57543 | G2: ORDEN DE CAMBIO | H2: META | I2: VILLAVICENCIO | J2: DROGUERÍA MAXIMEDICAL | K2: WOMPI | L2: FO-25-1605772 | M2: 45930.605 | N2: 45931.434 | O2: CIERRE | P2: RECUPERACION DE EQUIPOS | Q2: EJECUTADO_EXITOSO | R2: CIERRE EXITOSO | S2: 01/10/2025 SE REALIZA CIERRE CB WOMPI SE RECUPERA DATÁFONO OK SIN NOVEDADES | T2: VISITA_TÉCNICA | U2: 0 | V2: PRINCIPAL | W2: LEJANA | X2: CASTRILLON URREA LONDIER LEANDRO | Y2: 1 | Z2: =IF(T2="SOPORTE_TELEFÓNICO",'TARIFAS 2025'!$B$14,IF(V2="PRINCIPAL",'TARIFAS 2025'!$B$10,IF(V2="INTERMEDIA",'TARIFAS 2025'!$C$10,IF(V2="LEJANA",'TARIFAS 2025'!$D$10)))) -> 101766 | AA2: =Z2*Y2 -> 101766
A3: IBAGUE | B3: =VLOOKUP(A3,'CENTROS DE COSTOS'!A:D,2,0) -> 0036-0006 | C3: =VLOOKUP(A3,'CENTROS DE COSTOS'!A:D,3,0) -> Wompi Oriente | D3: 73001 | E3: LC-CS-25-000633 | F3: 74796 | G3: ORDEN DE CAMBIO | H3: TOLIMA | I3: IBAGUE | J3: MERCAECONO | K3: WOMPI | L3: FO-25-1605775 | M3: 45930.605 | N3: 45931.582 | O3: CIERRE | P3: RECUPERACION DE EQUIPOS | Q3: EJECUTADO_EXITOSO | R3: CIERRE EXITOSO | S3: 01/10/2025 SE RETIRA DATÁFONO Y CARGADOR. CLIENTE HACE DISPOSICIÓN FINAL DE PUBLICIDAD. NO SE TOMA FOTO DE TIRILLA PORQUE EL CLIENTE NO SE ACUERDA DE USUARIO Y CONTRASEÑA. | T3: VISITA_TÉCNICA | U3: 0 | V3: PRINCIPAL | W3: LEJANA | X3: VARGAS HERRERA JHON JAIRO | Y3: 1 | Z3: =IF(T3="SOPORTE_TELEFÓNICO",'TARIFAS 2025'!$B$14,IF(V3="PRINCIPAL",'TARIFAS 2025'!$B$10,IF(V3="INTERMEDIA",'TARIFAS 2025'!$C$10,IF(V3="LEJANA",'TARIFAS 2025'!$D$10)))) -> 101766 | AA3: =Z3*Y3 -> 101766
A4: MEDELLIN | B4: =VLOOKUP(A4,'CENTROS DE COSTOS'!A:D,2,0) -> 0036-0005 | C4: =VLOOKUP(A4,'CENTROS DE COSTOS'!A:D,3,0) -> Wompi Noroccidente | D4: 5631 | E4: LC-CS-25-000630 | F4: 70991 | G4: ORDEN DE CAMBIO | H4: ANTIOQUIA | I4: SABANETA | J4: DROGUERIA ALIADAS | K4: WOMPI | L4: FO-25-1605004 | M4: 45930.534 | N4: 45931.586 | O4: CIERRE | P4: CIERRE | Q4: EJECUTADO_EXITOSO | R4: CIERRE EXITOSO | S4: 01/10/2025 CIERRE EXITOSO SIN PUBLICIDAD CB INFORMA QUE LE DIÓ DISPOSICIÓN FINAL NO SE LOGRA SACAR TIRILLA YA QUE CORRESPONSAL NUNCA LO USO Y NO RECUERDA LAS CREDENCIALES | T4: VISITA_TÉCNICA | U4: 0 | V4: PRINCIPAL | W4: PRINCIPAL | X4: CASTAÑEDA PALACIO CARLOS FELIPE | Y4: 1 | Z4: =IF(T4="SOPORTE_TELEFÓNICO",'TARIFAS 2025'!$B$14,IF(V4="PRINCIPAL",'TARIFAS 2025'!$B$10,IF(V4="INTERMEDIA",'TARIFAS 2025'!$C$10,IF(V4="LEJANA",'TARIFAS 2025'!$D$10)))) -> 101766 | AA4: =Z4*Y4 -> 101766
A5: CUCUTA | B5: =VLOOKUP(A5,'CENTROS DE COSTOS'!A:D,2,0) -> 0036-0007 | C5: =VLOOKUP(A5,'CENTROS DE COSTOS'!A:D,3,0) -> Wompi Santander | D5: 54405 | E5: LC-CS-25-000631 | F5: 58424 | G5: ORDEN DE CAMBIO | H5: NORTE DE SANTANDER | I5: LOS PATIOS | J5: SUPERMARKET SOBRENATURAL | K5: WOMPI | L5: FO-25-1605766 | M5: 45930.605 | N5: 45931.688 | O5: CIERRE | P5: RECUPERACION DE EQUIPOS | Q5: EJECUTADO_EXITOSO | R5: CIERRE EXITOSO | S5: 01/10/2025 SE VISITA COMERCIO Y SE RETIRA DATAFONO OK, COMERCIO NO CUENTA CON PUBLICIDAD. | T5: VISITA_TÉCNICA | U5: 0 | V5: PRINCIPAL | W5: LEJANA | X5: TORRES MANTILLA JOSE DANIEL | Y5: 1 | Z5: =IF(T5="SOPORTE_TELEFÓNICO",'TARIFAS 2025'!$B$14,IF(V5="PRINCIPAL",'TARIFAS 2025'!$B$10,IF(V5="INTERMEDIA",'TARIFAS 2025'!$C$10,IF(V5="LEJANA",'TARIFAS 2025'!$D$10)))) -> 101766 | AA5: =Z5*Y5 -> 101766
A6: IBAGUE | B6: =VLOOKUP(A6,'CENTROS DE COSTOS'!A:D,2,0) -> 0036-0006 | C6: =VLOOKUP(A6,'CENTROS DE COSTOS'!A:D,3,0) -> Wompi Oriente | D6: 73001 | E6: LC-CS-25-000632 | F6: 59987 | G6: ORDEN DE CAMBIO | H6: TOLIMA | I6: IBAGUE | J6: ALLPAY | K6: WOMPI | L6: FO-25-1605757 | M6: 45930.605 | N6: 45932.431 | O6: CIERRE | P6: RECUPERACION DE EQUIPOS | Q6: EJECUTADO_EXITOSO | R6: CIERRE EXITOSO | S6: 01/10/2025 SE REALIZA CIERRE POR SOLICITUD DE LA ENTIDAD, SE RETIRA DATÁFONO WOMPI CON ACCESORIOS; NO SE RETIRA PUBLICIDAD DEBIDO A QUE EL CLIENTE SIGUE OPERANDO CON RED REDEBAN. | T6: VISITA_TÉCNICA | U6: 0 | V6: PRINCIPAL | W6: LEJANA | X6: BARRAGAN TAFUR EDWIN ESTEBAN | Y6: 1 | Z6: =IF(T6="SOPORTE_TELEFÓNICO",'TARIFAS 2025'!$B$14,IF(V6="PRINCIPAL",'TARIFAS 2025'!$B$10,IF(V6="INTERMEDIA",'TARIFAS 2025'!$C$10,IF(V6="LEJANA",'TARIFAS 2025'!$D$10)))) -> 101766 | AA6: =Z6*Y6 -> 101766
A7: CUCUTA | B7: =VLOOKUP(A7,'CENTROS DE COSTOS'!A:D,2,0) -> 0036-0007 | C7: =VLOOKUP(A7,'CENTROS DE COSTOS'!A:D,3,0) -> Wompi Santander | D7: 54001 | E7: LC-CS-25-000636 | F7: 63803 | G7: ORDEN DE CAMBIO | H7: NORTE DE SANTANDER | I7: CUCUTA | J7: DROGUERIA FER PLUS | K7: WOMPI | L7: FO-25-1619269 | FO-25-1605752 | M7: 45930.605 | N7: 45934.433 | O7: CIERRE | P7: RECUPERACION DE EQUIPOS | Q7: EJECUTADO_EXITOSO | R7: CIERRE EXITOSO | S7: 01/10/2025 SE INTENTA COMUNICACIÓN A EL NUMERO 3006027714 SUENA PERO NO HAY CONTACTO, SE INTENTARÁ NUEVAMENTE | 02/10/2025 SE INTENTA COMUNICACIÓN A EL NUMERO 3006027714 SUENA PERO NO HAY CONTACTO, SE INTENTARÁ NUEVAMENTE | 01/10/2025 SE REALIZÓ LLAMADA TELEFÓNICA AL NÚMERO 3006027714 SE HABLÓ CON LA SRA JENNIFER MANIFIESTA QUE SE ENCUENTRA DELICADA DE SALUD QUE PROGRAMEMOS LA VISITA PARA EL DÍA VIERNES 03/10/2025 | 02/10/2025 SE REALIZA VISITA, NO SE UBICA EL COMERCIO, SE CONTACTA TELEFÓNICAMENTE AL CLIENTE, INFORMA QUE YA HABÍA AGENDADO VISITA PARA EL DÍA VIERNES. SE REAGENDA VISITA POR SOLICITUD DEL CLIENTE. 03/10/2025 SE REALIZA VISITA, SE RETIRA DATAFONO WOMPI | T7: VISITA_TÉCNICA | U7: 0 | V7: PRINCIPAL | W7: LEJANA | X7: HERNANDEZ GUARIN MIGUEL JULIAN | Y7: 2 | Z7: =IF(T7="SOPORTE_TELEFÓNICO",'TARIFAS 2025'!$B$14,IF(V7="PRINCIPAL",'TARIFAS 2025'!$B$10,IF(V7="INTERMEDIA",'TARIFAS 2025'!$C$10,IF(V7="LEJANA",'TARIFAS 2025'!$D$10)))) -> 101766 | AA7: =Z7*Y7 -> 203532
A8: VALLEDUPAR | B8: =VLOOKUP(A8,'CENTROS DE COSTOS'!A:D,2,0) -> 0036-0001 | C8: =VLOOKUP(A8,'CENTROS DE COSTOS'!A:D,3,0) -> Wompi Costa | D8: 20001 | E8: LC-CS-25-000488 | F8: 75428 | G8: ORDEN DE CAMBIO | H8: CESAR | I8: VALLEDUPAR | J8: DROGUERIA SURTIMEDIC JIMFARMA | K8: WOMPI | L8: FO-25-1609079 | FO-25-1556314 | M8: 45931.669 | N8: 45937.506 | O8: CIERRE | P8: CIERRE | Q8: EJECUTADO_EXITOSO | R8: CIERRE EXITOSO | S8: 19/09/2025 SE INTENTA COMUNICACIÓN AL NÚMERO 3106026030 SUENA PERO NO HAY CONTACTO, SE INTENTARÁ NUEVAMENTE | 19/09/2025 SE INTENTA COMUNICACIÓN AL NÚMERO 3106026030 SUENA PERO NO HAY CONTACTO, SE INTENTARÁ NUEVAMENTE | 20/09/2025 SE REALIZA VISITA POR CIERRE DE CORRESPONSAL LA CUAL SE LLEGA AL SITIO Y COMERCIO SE ENCUENTRA CERRADO SE REALIZA GESTIÓN TELEFÓNICA Y CLIENTE NO ATIENDE LLAMADA 07/10/2025 SE REALIZA DESMONTÉ DE CB, SE RETIRA SOLAMENTE EQUIPO EN DIRECCIÓN DE CB | T8: VISITA_TÉCNICA | U8: 0 | V8: PRINCIPAL | W8: LEJANA | X8: MAESTRE MENGUAL EDGAR ENRIQUE | Y8: 2 | Z8: =IF(T8="SOPORTE_TELEFÓNICO",'TARIFAS 2025'!$B$14,IF(V8="PRINCIPAL",'TARIFAS 2025'!$B$10,IF(V8="INTERMEDIA",'TARIFAS 2025'!$C$10,IF(V8="LEJANA",'TARIFAS 2025'!$D$10)))) -> 101766 | AA8: =Z8*Y8 -> 203532
A9: CALI | B9: =VLOOKUP(A9,'CENTROS DE COSTOS'!A:D,2,0) -> 0036-0003 | C9: =VLOOKUP(A9,'CENTROS DE COSTOS'!A:D,3,0) -> Wompi Suroccidente | D9: 76001 | E9: LC-CS-25-000666 | F9: 76886 | G9: ORDEN DE CAMBIO | H9: VALLE DEL CAUCA | I9: CALI | J9: INTERNET Y PAPELERIA DANYK | K9: WOMPI | L9: FO-25-1640807 | M9: 45937.453 | N9: 45937.666 | O9: CIERRE | P9: CIERRE | Q9: EJECUTADO_EXITOSO | R9: CIERRE EXITOSO | S9: 07/10/2025 EN COMUNICACION CON LA SEÑORA LUZ ALBA GUATECHA AL NUMERO 3206180624, CONFIRMA DATOS OK PARA LA RECOLECCION DE EQUIPOS. SE ESCALA PARA VISITA | 07/10/2025 SE DESINSTALA DATAFONO SE DESTRUYE PUBLICIDAD EN SITIO | T9: VISITA_TÉCNICA | U9: 0 | V9: PRINCIPAL | W9: PRINCIPAL | X9: CUERO RUIZ JHONNY | Y9: 1 | Z9: =IF(T9="SOPORTE_TELEFÓNICO",'TARIFAS 2025'!$B$14,IF(V9="PRINCIPAL",'TARIFAS 2025'!$B$10,IF(V9="INTERMEDIA",'TARIFAS 2025'!$C$10,IF(V9="LEJANA",'TARIFAS 2025'!$D$10)))) -> 101766 | AA9: =Z9*Y9 -> 101766
A10: MEDELLIN | B10: =VLOOKUP(A10,'CENTROS DE COSTOS'!A:D,2,0) -> 0036-0005 | C10: =VLOOKUP(A10,'CENTROS DE COSTOS'!A:D,3,0) -> Wompi Noroccidente | D10: 5001 | E10: LC-CS-25-000663 | F10: 67522 | G10: ORDEN DE CAMBIO | H10: ANTIOQUIA | I10: MEDELLÍN | J10: SANLLY 2 | K10: WOMPI | L10: FO-25-1640815 | M10: 45937.453 | N10: 45939.478 | O10: CIERRE | P10: CIERRE | Q10: EJECUTADO_EXITOSO | R10: CIERRE EXITOSO | S10: 07/10/2025 EN COMUNICACION CON LA SEÑORA LILLY YANETH HIGUITA CARDONA AL NUMERO 3016409050, CONFIRMA DATOS OK PARA LA RECOLECCION DE EQUIPOS. SE ESCALA PARA VISITA | 09/10/2025 SE RETIRA EQUIPO WOMPI OK, SE DESTRUYE FLANGER | T10: VISITA_TÉCNICA | U10: 0 | V10: PRINCIPAL | W10: PRINCIPAL | X10: QUINTERO SANCHEZ JUAN SEBASTIAN | Y10: 1 | Z10: =IF(T10="SOPORTE_TELEFÓNICO",'TARIFAS 2025'!$B$14,IF(V10="PRINCIPAL",'TARIFAS 2025'!$B$10,IF(V10="INTERMEDIA",'TARIFAS 2025'!$C$10,IF(V10="LEJANA",'TARIFAS 2025'!$D$10)))) -> 101766 | AA10: =Z10*Y10 -> 101766
A11: MEDELLIN | B11: =VLOOKUP(A11,'CENTROS DE COSTOS'!A:D,2,0) -> 0036-0005 | C11: =VLOOKUP(A11,'CENTROS DE COSTOS'!A:D,3,0) -> Wompi Noroccidente | D11: 5664 | E11: LC-CS-25-000667 | F11: 81554 | G11: ORDEN DE CAMBIO | H11: ANTIOQUIA | I11: SAN PEDRO DE LOS MILAGROS | J11: INVERJOTAEME | K11: WOMPI | L11: FO-25-1640810 | M11: 45937.453 | N11: 45939.549 | O11: CIERRE | P11: CIERRE | Q11: EJECUTADO_EXITOSO | R11: CIERRE EXITOSO | S11: 07/10/2025 EN COMUNICACION CON EL SEÑOR JUAN FERNANDO RESTREPO AL NUMERO 3002430349, CONFIRMA DATOS OK PARA LA RECOLECCION DE EQUIPOS. SE ESCALA PARA VISITA | 09/10/2025 SE REALIZA RETIRO DE DATAFONO WOMPI OK SOLO SE RETIRA DISPLAY HORARIO | T11: VISITA_TÉCNICA | U11: 0 | V11: INTERMEDIA | W11: INTERMEDIA | X11: PAREJA ECHAVARRIA JHON DAVID | Y11: 1 | Z11: =IF(T11="SOPORTE_TELEFÓNICO",'TARIFAS 2025'!$B$14,IF(V11="PRINCIPAL",'TARIFAS 2025'!$B$10,IF(V11="INTERMEDIA",'TARIFAS 2025'!$C$10,IF(V11="LEJANA",'TARIFAS 2025'!$D$10)))) -> 318400 | AA11: =Z11*Y11 -> 318400
A12: MEDELLIN | B12: =VLOOKUP(A12,'CENTROS DE COSTOS'!A:D,2,0) -> 0036-0005 | C12: =VLOOKUP(A12,'CENTROS DE COSTOS'!A:D,3,0) -> Wompi Noroccidente | D12: 5001 | E12: LC-CS-25-000665 | F12: 76780 | G12: ORDEN DE CAMBIO | H12: ANTIOQUIA | I12: MEDELLÍN | J12: VARIEDADES SIEMPRE BELLA | K12: WOMPI | L12: FO-25-1640824 | M12: 45937.453 | N12: 45939.562 | O12: CIERRE | P12: CIERRE | Q12: EJECUTADO_EXITOSO | R12: CIERRE EXITOSO | S12: 07/10/2025 EN COMUNICACION CON LA SEÑORA MARTA BERENICE ALZATE GIRALDO AL NUMERO 3206805623, CONFIRMA DATOS OK PARA LA RECOLECCION DE EQUIPOS. SE ESCALA PARA VISITA | 09/10/2025 SE REALIZA RECOGIDA DE EQUIPOS POR CIERRE CB, USUARIO REALIZA DISPOSICIÓN FINAL DE LA PUBLICIDAD | T12: VISITA_TÉCNICA | U12: 0 | V12: PRINCIPAL | W12: PRINCIPAL | X12: RAMIREZ TABARES JUAN DIEGO | Y12: 1 | Z12: =IF(T12="SOPORTE_TELEFÓNICO",'TARIFAS 2025'!$B$14,IF(V12="PRINCIPAL",'TARIFAS 2025'!$B$10,IF(V12="INTERMEDIA",'TARIFAS 2025'!$C$10,IF(V12="LEJANA",'TARIFAS 2025'!$D$10)))) -> 101766 | AA12: =Z12*Y12 -> 101766
A13: MEDELLIN | B13: =VLOOKUP(A13,'CENTROS DE COSTOS'!A:D,2,0) -> 0036-0005 | C13: =VLOOKUP(A13,'CENTROS DE COSTOS'!A:D,3,0) -> Wompi Noroccidente | D13: 5360 | E13: LC-CS-25-000723 | F13: 27931 | G13: ORDEN DE CAMBIO | H13: ANTIOQUIA | I13: ITAGUI | J13: BARRIO TABLAZO - ITAGÜÍ | K13: WOMPI | L13: FO-25-1648650 | M13: 45938.66 | N13: 45939.632 | O13: CIERRE | P13: CIERRE | Q13: EJECUTADO_EXITOSO | R13: CIERRE EXITOSO | S13: 09/10/2025 SE REALIZA CIERRE DE CB | T13: VISITA_TÉCNICA | U13: 0 | V13: PRINCIPAL | W13: PRINCIPAL | X13: HERNANDEZ CHAVARRIA JUAN CAMILO | Y13: 1 | Z13: =IF(T13="SOPORTE_TELEFÓNICO",'TARIFAS 2025'!$B$14,IF(V13="PRINCIPAL",'TARIFAS 2025'!$B$10,IF(V13="INTERMEDIA",'TARIFAS 2025'!$C$10,IF(V13="LEJANA",'TARIFAS 2025'!$D$10)))) -> 101766 | AA13: =Z13*Y13 -> 101766
... A41: BOGOTA | B41: =VLOOKUP(A41,'CENTROS DE COSTOS'!A:D,2,0) -> 0036-0004 | C41: =VLOOKUP(A41,'CENTROS DE COSTOS'!A:D,3,0) -> Wompi Centro | D41: 11001 | E41: LC-CS-25-004084 | F41: 14389 | G41: ORDEN DE CAMBIO | H41: CUNDINAMARCA | I41: BOGOTA | J41: BARRIO AURORA BOGOTA | K41: WOMPI | L41: FO-25-1747302 | M41: 45958.633 | N41: 45961.536 | O41: CIERRE | P41: RECUPERACION DE EQUIPOS | Q41: EJECUTADO_EXITOSO | R41: CIERRE EXITOSO | S41: 28/10/2025 SE ESCALA PARA VISITA. CONFIRMAR DATOS PARA LA RECOLECCION DE EQUIPOS | 31/10/2025 SE RETIRA DATÁFONO WOMPI, SOLO SE RECIBE DATÁFONO | T41: VISITA_TÉCNICA | U41: 0 | V41: PRINCIPAL | W41: PRINCIPAL | X41: ORTIZ YARA FRANKLYN ISRAEL | Y41: 1 | Z41: =IF(T41="SOPORTE_TELEFÓNICO",'TARIFAS 2025'!$B$14,IF(V41="PRINCIPAL",'TARIFAS 2025'!$B$10,IF(V41="INTERMEDIA",'TARIFAS 2025'!$C$10,IF(V41="LEJANA",'TARIFAS 2025'!$D$10)))) -> 101766 | AA41: =Z41*Y41 -> 101766
AA42: =SUM(AA2:AA41) -> 9070672

Sheet OC PUBLICIDAD
A1: CIUDAD SEDE | B1: CENTRO_COSTO | C1: DESCRIPCION CENTRO DE COSTOS | D1: CÓDIGO DANE | E1: TA/CODIGO ACTIVIDAD | F1: CODIGO CB | G1: ACTIVIDAD | H1: DEPARTAMENTO | I1: CIUDAD | J1: NOMBRE DEL CB | K1: RED | L1: FO | M1: FECHA ASIGNACION A LINEA COMUNICACIONES | N1: FECHA DEL CIERRE DEL TICKET (DD/MM/AAAA) | O1: SOLICITUD | P1: DESCRIPCIÓN | Q1: ESTADO | R1: CAUSAL ESTADO | S1: OBSERVACION | T1: FORMA DE ATENCIÓN | U1: CANTIDAD DE ROLLOS | V1: TIPOLOGIA | W1: TIPO DE TRAYECTO | X1: NOMBRE DEL TECNICO | Y1: DIAS DE ACTIVIDAD | Z1: VALOR DIAS ACTIVIDAD | AA1: VALOR TOTAL
A2: MEDELLIN | B2: =VLOOKUP(A2,'CENTROS DE COSTOS'!A:D,2,0) -> 0036-0005 | C2: =VLOOKUP(A2,'CENTROS DE COSTOS'!A:D,3,0) -> Wompi Noroccidente | D2: 5440 | E2: 2815744 | F2: 29778 | G2: ORDEN DE CAMBIO | H2: ANTIOQUIA | I2: MARINILLA | J2: BARRIO MARINILLA ANTIOQUIA | K2: WOMPI | L2: FO-25-1605228 | M2: 45930.521 | N2: 45931.706 | O2: PUBLICIDAD | P2: AVISO EXTERIOR | Q2: EJECUTADO_EXITOSO | R2: EJECUTADO EXITOSO | S2: 30/09/2025 POR FAVOR, COMUNICARSE CON USUARIO PARA CONFIRMAR UBICACION, SOLICITUD Y PROGRAMAR VISITA TECNICA | 01/10/2025 INSTALACIÓN DE PUBLICIDAD OK | T2: VISITA_TÉCNICA | U2: 0 | V2: INTERMEDIA | W2: TERRESTRE | X2: CARDONA MOLINA BROLIN STIVEN | Y2: 1 | Z2: =IF(T2="SOPORTE_TELEFÓNICO",'TARIFAS 2025'!$B$14,IF(V2="PRINCIPAL",'TARIFAS 2025'!$B$12,IF(V2="INTERMEDIA",'TARIFAS 2025'!$C$12,IF(V2="LEJANA",'TARIFAS 2025'!$D$12)))) -> 287147 | AA2: =Z2*Y2 -> 287147
