Workbook
Name A: #REF!
Name ACTIVIDAD: [1]Hoja2!$P$2:$P$30
Name Actividad: [2]Formulas!$H$2:$H$5000
Name arearesponsable: '[3]Listas desplegables'!$BB$2:$BB$100
Name Clientes: [4]Clientes!$A$2:$A$100
Name Clientes: [2]Clientes!$A$2:$A$100
Name COORDINADOR: [1]Hoja2!$D$2:$D$30
Name Coordinadores: [5]Coordinadores!$A$2:$A$1000
Name Coordinadores: [2]Coordinadores!$A$2:$A$1000
Name DOCUMENTADOR: [1]Hoja2!$A$2:$A$30
Name ES: [1]Hoja2!$K$2:$K$30
Name ESS: [1]Hoja2!$K$2:$K$30
Name Estado: [4]Formulas!$K$2:$K$5000
Name Estado: [2]Formulas!$K$2:$K$5000
Name ESTADOACTIVIDAD: [1]Hoja2!$M$2:$M$30
Name ESTADOS: '[6]Listas desplegables'!$B$1:$D$1
Name ESTADOSCIERRES: '[7]lista desplegable'!$CX$1:$DA$1
Name Facturacion: '[8]Listas desplegables'!$AO$1:$AR$1
Name FACTURACIÓN: '[6]Listas desplegables'!$Y$1:$AB$1
Name falla: #REF!
Name Fallas: '[9]Listas desplegables'!$F$2:$L$2
Name Grupo_Falla: '[10]Listas Desplegables'!$CH$2:$CH$5
Name inconservmanager: '[11]Listas desplegables'!$BC$2:$BC$100
Name INCUMPLIMIENTO: '[3]Listas desplegables'!$AK$1:$AN$1
Name LISTA: [12]Dptos!$A$1139:$A$1171
Name LISTA2: #REF!
Name LOLO: [13]Coordinadores!$A$2:$A$1000
Name solicitudes: '[8]Listas desplegables'!$U$1:$AF$1
Name solicitudes: '[14]Listas desplegables'!$AF$1:$AQ$1
Name Tecnicos: [4]Tecnicos!$A$2:$A$1000
Name Tecnicos: [2]Tecnicos!$A$2:$A$1000
Name Version: [2]Formulas!$I$2:$I$3

Sheet RESUMEN
A1: LÍNEA COMUNICACIONES S.A.S | F1: FACTURACIÓN CORRESPONSALES BANCARIOS TIQUIETES AEREOS
A2: FACTURACIÓN PROYECTO CB BANCOLOMBIA | F2: =A3 -> 45899
A3: 45899
F4: CONCEPTOS | G4: TRAYECTOS | H4: TOTAL | I4: % Administración | J4: TOTAL
A5: CONCEPTOS | B5: CANTIDAD | C5: VALOR UNITARIO | D5: VALOR TOTAL | I5: =H5*0.12 -> 0 | J5: =H5+I5 -> 0
A6: Adecuaciones CB | B6: =COUNTA(ADECUACIONES!A:A)-1 -> 50 | C6: 0 | D6: =ADECUACIONES!AE52 -> 9390985.8 | I6: =H6*0.12 -> 0 | J6: =H6+I6 -> 0
A7: Incidentes | B7: =COUNTA(INCIDENTES!A:A)-1 -> 184 | C7: 0 | D7: =INCIDENTES!AG187 -> 20560730 | I7: =H7*0.12 -> 0 | J7: =H7+I7 -> 0
A8: Ordenes de Cambio | B8: =COUNTA(OC!A:A)-1 -> 9 | C8: 0 | D8: =OC!AG11 -> 565588.44 | I8: =H8*0.12 -> 0 | J8: =H8+I8 -> 0
A9: Tiquetes | B9: 0 | C9: 0 | D9: =J12 -> 0 | I9: =H9*0.12 -> 0 | J9: =H9+I9 -> 0
A10: SUBTOTAL | D10: =SUM(D6:D9) -> 30517305 | I10: =H10*0.12 -> 0 | J10: =H10+I10 -> 0
A11: Iva | D11: =D10*0.19 -> 5798287.9 | I11: =H11*0.12 -> 0 | J11: =H11+I11 -> 0
A12: TOTAL | D12: =D10+D11 -> 36315593 | F12: TOTAL | H12: =SUM(H5:H11) -> 0 | I12: =SUM(I5:I11) -> 0 | J12: =SUM(J5:J11) -> 0

Sheet BASE LIQUIDACION
A1: TARIFAS 2025 | E1: Incremento 2025
A2: Tipificación | B2: Descripción | C2: Dia actividad Exitosa | D2: Dia actividad Fallida | E2: 0.052
A3: Tipo I | B3: Metropolitano | C3: =62700.07*(1+$E$2) -> 65960.474 | D3: =42357.4*(1+$E$2) -> 44559.985
A4: Tipo II | B4: Hasta 3 horas | C4: =155716.31*(1+$E$2) -> 163813.56 | D4: =127766.53*(1+$E$2) -> 134410.39
A5: Tipo III | B5: De 3 a 5 horas | C5: =262099.22*(1+$E$2) -> 275728.38 | D5: =211886.19*(1+$E$2) -> 222904.27
A6: Tipo IV | B6: Más de 5 horas | C6: =455883.78*(1+$E$2) -> 479589.74 | D6: =441833.68*(1+$E$2) -> 464809.03
A7: Destino aereo | B7: No incluye valor del Tiquete | C7: =455883.78*(1+$E$2) -> 479589.74 | D7: =441833.68*(1+$E$2) -> 464809.03
A8: *Donde se requiera transporte aéreo o fluvial se factura adicional a tarifa TIPO IV el valor del tiquete + el 12% de admon.
A10: Gestión Telefónica | B10: =36031.04*(1+$E$2) -> 37904.654
A11: Mts Acometida electrica | B11: =30182.1*(1+$E$2) -> 31751.569
A12: Mts Acometida datos | B12: =15432.22*(1+$E$2) -> 16234.695
A13: switche | B13: =244669.03*(1+$E$2) -> 257391.82
A14: Router | B14: =291399.51*(1+$E$2) -> 306552.28
A15: Envio operador Logistico | B15: =53547.34*(1+$E$2) -> 56331.802
D16: 37905

Sheet Tablas dinámicas
A2: ADECUACIONES | J2: NOMBRE CC | K2: Suma de VALOR | L2: Suma de VALOR2
A3: COORDINADOR | B3: CENTRO DE COSTOS LÍNEACOM | C3: % | D3: $ | E3: NOMBRE CC | F3: VALOR | J3: Redeban Centro ( Bogotá) | K3: 2212350.5 | L3: 0.072494951
A4: DIEGO FERNANDO HENAO CARDONA | B4: 0004-0002 | C4: 0.046717726 | D4: 438725.5 | E4: =VLOOKUP(B4,'CENTRO DE COSTOS'!B:C,2,0) -> Redeban Eje Cafetero (Pereira) | F4: =D4 -> 438725.5 | J4: Redeban Costa (Barranqullla) | K4: 2874053.7 | L4: 0.094177834
B5: 0004-0003 | C5: 0.28224146 | D5: 2650525.6 | E5: =VLOOKUP(B5,'CENTRO DE COSTOS'!B:C,2,0) -> Redeban Suroccidente (Cali) | F5: =D5 -> 2650525.6 | J5: Redeban Eje Cafetero (Pereira) | K5: 2184768.3 | L5: 0.071591128
A6: JOSE MAURICIO HERNANDEZ ROJAS | B6: 0004-0001 | C6: 0.022032505 | D6: 206906.94 | E6: =VLOOKUP(B6,'CENTRO DE COSTOS'!B:C,2,0) -> Redeban Costa (Barranqullla) | F6: =D6 -> 206906.94 | J6: Redeban Noroccidente (Medellín) | K6: 8975285.7 | L6: 0.2941048
A7: JUAN SEBASTIÁN RÍOS CASTRILLÓN | B7: 0004-0005 | C7: 0.25193016 | D7: 2365872.6 | E7: =VLOOKUP(B7,'CENTRO DE COSTOS'!B:C,2,0) -> Redeban Noroccidente (Medellín) | F7: =D7 -> 2365872.6 | J7: Redeban Oriente (Otros) | K7: 3944468 | L7: 0.12925348
A8: KEVIN ALEXIS CORZO BUSTOS | B8: 0004-0007 | C8: 0.14727076 | D8: 1383017.6 | E8: =VLOOKUP(B8,'CENTRO DE COSTOS'!B:C,2,0) -> Redeban Oriente (Otros) | F8: =D8 -> 1383017.6 | J8: Redeban Santander | K8: 6147592.3 | L8: 0.20144611
A9: MIGUEL JULIÁN HERNÁNDEZ GUARÍN | B9: 0004-0008 | C9: 0.19488717 | D9: 1830182.7 | E9: =VLOOKUP(B9,'CENTRO DE COSTOS'!B:C,2,0) -> Redeban Santander | F9: =D9 -> 1830182.7 | J9: Redeban Suroccidente (Cali) | K9: 4178786.3 | L9: 0.1369317
A10: WILLIAM ASDRUBAL ROZO ROZO | B10: 0004-0004 | C10: 0.054920206 | D10: 515754.88 | E10: =VLOOKUP(B10,'CENTRO DE COSTOS'!B:C,2,0) -> Redeban Centro ( Bogotá) | F10: =D10 -> 515754.88 | J10: Total general | K10: 30517305 | L10: 1
A11: Total general | C11: 1 | D11: 9390985.8
A15: INCIDENTES
A16: COORDINADOR | B16: CENTRO DE COSTOS LÍNEACOM | C16: % | D16: $ | E16: NOMBRE CC
A17: DIEGO FERNANDO HENAO CARDONA | B17: 0004-0002 | C17: 0.081713162 | D17: 1680082.3 | E17: =VLOOKUP(B17,'CENTRO DE COSTOS'!B:C,2,0) -> Redeban Eje Cafetero (Pereira) | F17: =D17 -> 1680082.3
B18: 0004-0003 | C18: 0.06927748 | D18: 1424395.6 | E18: =VLOOKUP(B18,'CENTRO DE COSTOS'!B:C,2,0) -> Redeban Suroccidente (Cali) | F18: =D18 -> 1424395.6
A19: JOSE MAURICIO HERNANDEZ ROJAS | B19: 0004-0001 | C19: 0.12972043 | D19: 2667146.7 | E19: =VLOOKUP(B19,'CENTRO DE COSTOS'!B:C,2,0) -> Redeban Costa (Barranqullla) | F19: =D19 -> 2667146.7
A20: JUAN SEBASTIÁN RÍOS CASTRILLÓN | B20: 0004-0005 | C20: 0.32145809 | D20: 6609413.1 | E20: =VLOOKUP(B20,'CENTRO DE COSTOS'!B:C,2,0) -> Redeban Noroccidente (Medellín) | F20: =D20 -> 6609413.1
A21: KEVIN ALEXIS CORZO BUSTOS | B21: 0004-0007 | C21: 0.12137165 | D21: 2495489.9 | E21: =VLOOKUP(B21,'CENTRO DE COSTOS'!B:C,2,0) -> Redeban Oriente (Otros) | F21: =D21 -> 2495489.9
A22: MIGUEL JULIÁN HERNÁNDEZ GUARÍN | B22: 0004-0008 | C22: 0.2067752 | D22: 4251449.1 | E22: =VLOOKUP(B22,'CENTRO DE COSTOS'!B:C,2,0) -> Redeban Santander | F22: =D22 -> 4251449.1
A23: WILLIAM ASDRUBAL ROZO ROZO | B23: 0004-0004 | C23: 0.06968399 | D23: 1432753.7 | E23: =VLOOKUP(B23,'CENTRO DE COSTOS'!B:C,2,0) -> Redeban Centro ( Bogotá) | F23: =D23 -> 1432753.7
A24: Total general | C24: 1 | D24: 20560730
A29: OC
A30: COORDINADOR | B30: CENTRO DE COSTOS LÍNEACOM | C30: % | D30: $ | E30: NOMBRE CC
A31: DIEGO FERNANDO HENAO CARDONA | B31: 0004-0003 | C31: 0.18364082 | D31: 103865.13 | E31: =VLOOKUP(B31,'CENTRO DE COSTOS'!B:C,2,0) -> Redeban Suroccidente (Cali) | F31: =D31 -> 103865.13
B32: 0004-0002 | C32: 0.11662274 | D32: 65960.474 | E32: =VLOOKUP(B32,'CENTRO DE COSTOS'!B:C,2,0) -> Redeban Eje Cafetero (Pereira) | F32: =D32 -> 65960.474
A33: KEVIN ALEXIS CORZO BUSTOS | B33: 0004-0007 | C33: 0.11662274 | D33: 65960.474 | E33: =VLOOKUP(B33,'CENTRO DE COSTOS'!B:C,2,0) -> Redeban Oriente (Otros) | F33: =D33 -> 65960.474
A34: MIGUEL JULIÁN HERNÁNDEZ GUARÍN | B34: 0004-0008 | C34: 0.11662274 | D34: 65960.474 | E34: =VLOOKUP(B34,'CENTRO DE COSTOS'!B:C,2,0) -> Redeban Santander | F34: =D34 -> 65960.474
A35: WILLIAM ASDRUBAL ROZO ROZO | B35: 0004-0004 | C35: 0.46649096 | D35: 263841.89 | E35: =VLOOKUP(B35,'CENTRO DE COSTOS'!B:C,2,0) -> Redeban Centro ( Bogotá) | F35: =D35 -> 263841.89
A36: Total general | C36: 1 | D36: 565588.44 | E36: =VLOOKUP(B36,'CENTRO DE COSTOS'!B:C,2,0) -> #N/A | F36: =D36 -> 565588.44

Sheet ADECUACIONES
A1: 1 | B1: =A1+1 -> 2 | C1: =B1+1 -> 3 | D1: =C1+1 -> 4 | E1: =D1+1 -> 5 | F1: =E1+1 -> 6 | G1: =F1+1 -> 7 | H1: =G1+1 -> 8 | I1: =H1+1 -> 9 | ... AE1: =AD1+1 -> 31
A2: CIUDAD SEDE | B2: COORDINADOR | C2: CENTRO DE COSTOS LÍNEACOM | D2: CÓDIGO DANE | E2: TA/CODIGO ACTIVIDAD | F2: CODIGO CB | G2: ACTIVIDAD | H2: TIPO DE APERTURA | I2: DEPARTAMENTO | J2: CIUDAD | K2: NOMBRE DEL CB | L2: RED | M2: FO | N2: FECHA LISTA | O2: FECHA ULTIMA ACTUALIZACION | P2: FORMATO | Q2: CADENA | R2: ESTADO | S2: OBSERVACIONES CLIENTE | T2: FORMA DE ATENCIÓN | U2: TERMINALES | V2: TIPIFICACION | W2: TIPO DE TRAYECTO | X2: NOMBRE DEL TECNICO | Y2: ACOMETIDA DATOS | Z2: ACOMETIDA ELECTRICA | AA2: SWITCH | AB2: ROUTER | AC2: VALOR DIAS ACTIVIDAD FACTURABLES | AD2: DIAS ACTIVIDAD FACTURABLES | AE2: VALOR TOTAL INSTALACION DE PUBLICIDAD
A3: MEDELLIN | B3: =VLOOKUP(A3,'CENTRO DE COSTOS'!A:D,4,FALSE) -> JUAN SEBASTIÁN RÍOS CASTRILLÓN | C3: =VLOOKUP(A3,'CENTRO DE COSTOS'!A:C,2,FALSE) -> 0004-0005 | D3: 5001 | E3: TA-25-904105 | F3: 80761 | G3: APERTURA | H3: CB CRECIMIENTO - NUEVO | I3: ANTIOQUIA | J3: MEDELLIN | K3: BARRIO CAICEDO MEDELLIN 17 | L3: REDEBAN | M3: FO-25-1305113 | N3: 45868 | O3: 45870 | P3: UNO A UNO | Q3: UNO A UNO | R3: EJECUTADO | S3: 30-07 SE REALIZA LLAMADA AL CLIENTE, SE HABLA CON LA SRA GEISER LUCILA PALACIO CORDOBA SE VALIDA DIRECCIÓN OK, CANAL OK, DISPONIBILIDAD TOTAL, LLAMAR EL DÍA LA INSTALACIÓN PARA CONFIRMAR VISITA, AVISO EXTERIOR ALTURA; NO INDICA ALTURA; TOMACORRIENTE CERCANO: SI; TIENE CABINA DE SEGURIDAD: NO - COMUNICACIÓN POR WPP - EL MODEM ESTA A 7 MT 01-08 SE REALIZA INSTALACIÓN DE CORRESPONSAL, SE INSTALAN EQUIPOS CON PRUEBAS EXITOSAS, SE CAPACITA Y SE EVALÚA AL CLIENTE, SE INSTALA PUBLICIDAD COMPLETA, CB QUEDA OPERATIVO. USUARIO SOMOS BANCOLOMBIA ACTIVO. SE INSTALAN 15 MT DE CABLE UTP | T3: VISITA _TECNICA | U3: VAZZZ393 | V3: TIPO I | W3: TERRESTRE | X3: PAREJA ECHAVARRIA JHON DAVID | Y3: 15 | Z3: 0 | AA3: 0 | AB3: 0 | AC3: 0 | AD3: =IF(V3="TIPO I",'BASE LIQUIDACION'!$D$3,IF(V3="TIPO II",'BASE LIQUIDACION'!$D$4,IF(V3="TIPO III",'BASE LIQUIDACION'!$D$5,'BASE LIQUIDACION'!$D$7))) -> 44559.985 | AE3: =Y3*'BASE LIQUIDACION'!$B$12+Z3*'BASE LIQUIDACION'!$B$11+AA3*'BASE LIQUIDACION'!$B$13+AB3*'BASE LIQUIDACION'!$B$14+AC3*AD3 -> 243520.43
A4: BOGOTA | B4: =VLOOKUP(A4,'CENTRO DE COSTOS'!A:D,4,FALSE) -> WILLIAM ASDRUBAL ROZO ROZO | C4: =VLOOKUP(A4,'CENTRO DE COSTOS'!A:C,2,FALSE) -> 0004-0004 | D4: 11001 | E4: TA-25-915468 | F4: 80772 | G4: APERTURA | H4: CB CRECIMIENTO - NUEVO | I4: CUNDINAMARCA | J4: BOGOTA | K4: BARRIO LA ISABELLA BOGOTA | L4: REDEBAN | M4: FO-25-1328346 | N4: 45870 | O4: 45874 | P4: UNO A UNO | Q4: UNO A UNO | R4: EJECUTADO | S4: 01-08-2025 SE REALIZA LLAMADA AL CLIENTE, SE HABLA CON EL SR JOHN ALEXANDER CUERVO RUBIANO SE VALIDA DIRECCIÓN OK, CANAL OK, DISPONIBILIDAD TOTAL, LLAMAR EL DÍA LA INSTALACIÓN PARA CONFIRMAR VISITA, AVISO EXTERIOR ALTURA APROX 2 METROS; TOMACORRIENTE CERCANO: SI; TIENE CABINA DE SEGURIDAD: NO // CONTACTO REALIZADO POR LA APP 4/08/2025 SE DEBE REPROGRAMAR ACTIVIDAD, EL COMERCIO ES AL INTERIOR DE UN CONJUNTO RESIDENCIAL, SE REQUIEREN PERMISOS DE ADMINISTRACIÓN PARA LA INSTALACIÓN DE LA PUBLICIDAD, SE INFORMA NOVEDAD A COORDINACIÓN QUIEN INDICA REPROGRAMAR PARA MAÑANA 05-08-2025, SE RETORNA PUBLICIDAD A BODEGA. 05-08 SE REALIZA INSTALACIÓN DE CORRESPONSAL, SE INSTALAN EQUIPOS CON PRUEBAS EXITOSAS, SE CAPACITA Y SE EVALÚA AL CLIENTE, SE INSTALA PUBLICIDAD COMPLETA, CB QUEDA OPERATIVO. USUARIO SOMOS BANCOLOMBIA ACTIVO. SE INSTALAN 8 MT DE CABLE UTP | T4: VISITA _TECNICA | U4: F8ZZZ008 | V4: TIPO I | W4: TERRESTRE | X4: GALINDO ROJAS LUIS FELIPE | Y4: 8 | Z4: 0 | AA4: 0 | AB4: 0 | AC4: 1 | AD4: =IF(V4="TIPO I",'BASE LIQUIDACION'!$D$3,IF(V4="TIPO II",'BASE LIQUIDACION'!$D$4,IF(V4="TIPO III",'BASE LIQUIDACION'!$D$5,'BASE LIQUIDACION'!$D$7))) -> 44559.985 | AE4: =Y4*'BASE LIQUIDACION'!$B$12+Z4*'BASE LIQUIDACION'!$B$11+AA4*'BASE LIQUIDACION'!$B$13+AB4*'BASE LIQUIDACION'!$B$14+AC4*AD4 -> 174437.55
A5: PEREIRA | B5: =VLOOKUP(A5,'CENTRO DE COSTOS'!A:D,4,FALSE) -> DIEGO FERNANDO HENAO CARDONA | C5: =VLOOKUP(A5,'CENTRO DE COSTOS'!A:C,2,FALSE) -> 0004-0002 | D5: 66001 | E5: TA-25-915501 | F5: 80798 | G5: APERTURA | H5: CB CRECIMIENTO - NUEVO | I5: RISARALDA | J5: PEREIRA | K5: BARRIO EL JARDIN ETAPA 3 PEREIRA | L5: REDEBAN | M5: FO-25-1316441 | N5: 45870 | O5: 45873 | P5: UNO A UNO | Q5: UNO A UNO | R5: EJECUTADO | S5: 01-08-2025 SE REALIZA LLAMADA AL CLIENTE, SE HABLA CON LA SRA ANDREA TORRES PAREJA DEL SR RONAL ALEXANDER RODRIGUEZ MUR, SE VALIDA DIRECCIÓN OK, CANAL OK, DISPONIBILIDAD TOTAL, LLAMAR EL DÍA LA INSTALACIÓN PARA CONFIRMAR VISITA, AVISO EXTERIOR ALTURA APROX 2 METROS; TOMACORRIENTE CERCANO: SI; TIENE CABINA DE SEGURIDAD: SI 4/08/2025 SE REALIZA INSTALACIÓN DE CORRESPONSAL, SE INSTALAN EQUIPOS CON PRUEBAS EXITOSAS, SE CAPACITA Y SE EVALÚA AL CLIENTE, SE INSTALA PUBLICIDAD COMPLETA, CB QUEDA OPERATIVO. USUARIO SOMOS BANCOLOMBIA ACTIVO. SE INSTALAN 8 MT DE CABLE UTP | T5: VISITA _TECNICA | U5: F8ZZZ033 | V5: TIPO I | W5: TERRESTRE | X5: FRANCO CAÑAVERAL YAMID RAUL | Y5: 8 | Z5: 0 | AA5: 0 | AB5: 0 | AC5: 0 | AD5: =IF(V5="TIPO I",'BASE LIQUIDACION'!$D$3,IF(V5="TIPO II",'BASE LIQUIDACION'!$D$4,IF(V5="TIPO III",'BASE LIQUIDACION'!$D$5,'BASE LIQUIDACION'!$D$7))) -> 44559.985 | AE5: =Y5*'BASE LIQUIDACION'!$B$12+Z5*'BASE LIQUIDACION'!$B$11+AA5*'BASE LIQUIDACION'!$B$13+AB5*'BASE LIQUIDACION'!$B$14+AC5*AD5 -> 129877.56
A6: CALI | B6: =VLOOKUP(A6,'CENTRO DE COSTOS'!A:D,4,FALSE) -> DIEGO FERNANDO HENAO CARDONA | C6: =VLOOKUP(A6,'CENTRO DE COSTOS'!A:C,2,FALSE) -> 0004-0003 | D6: 76001 | E6: TA-25-929470 | F6: 80871 | G6: APERTURA | H6: CB CRECIMIENTO - NUEVO | I6: VALLE DEL CAUCA | J6: CALI | K6: BARRIO TERRON COLORADO CALI 2 | L6: REDEBAN | M6: FO-25-1337707 | N6: 45875 | O6: 45877 | P6: UNO A UNO | Q6: UNO A UNO | R6: EJECUTADO | S6: 06-08 SE REALIZA LLAMADA AL CLIENTE, SE HABLA CON LA SRA JHENIFER CAROLINA VANEGAS RODRIGUEZ SE VALIDA DIRECCIÓN OK, CANAL OK, DISPONIBILIDAD TOTAL, LLAMAR EL DÍA LA INSTALACIÓN PARA CONFIRMAR VISITA, AVISO EXTERIOR ALTURA: NO INDICA ALTURA; TOMACORRIENTE CERCANO: SI; TIENE CABINA DE SEGURIDAD: SI 08-08 SE REALIZA INSTALACIÓN DE CORRESPONSAL, SE INSTALAN EQUIPOS CON PRUEBAS EXITOSAS, SE CAPACITA Y SE EVALÚA AL CLIENTE, SE INSTALA PUBLICIDAD COMPLETA, CB QUEDA OPERATIVO. USUARIO SOMOS BANCOLOMBIA ACTIVO. SE INSTALAN 5 MT DE CABLE UTP | T6: VISITA _TECNICA | U6: FGZZZ906 | V6: TIPO I | W6: TERRESTRE | X6: BOLAÑOS TABORDA JORGE ENRIQUE | Y6: 5 | Z6: 0 | AA6: 0 | AB6: 0 | AC6: 0 | AD6: =IF(V6="TIPO I",'BASE LIQUIDACION'!$D$3,IF(V6="TIPO II",'BASE LIQUIDACION'!$D$4,IF(V6="TIPO III",'BASE LIQUIDACION'!$D$5,'BASE LIQUIDACION'!$D$7))) -> 44559.985 | AE6: =Y6*'BASE LIQUIDACION'!$B$12+Z6*'BASE LIQUIDACION'!$B$11+AA6*'BASE LIQUIDACION'!$B$13+AB6*'BASE LIQUIDACION'!$B$14+AC6*AD6 -> 81173.477
A7: TUNJA | B7: =VLOOKUP(A7,'CENTRO DE COSTOS'!A:D,4,FALSE) -> MIGUEL JULIÁN HERNÁNDEZ GUARÍN | C7: =VLOOKUP(A7,'CENTRO DE COSTOS'!A:C,2,FALSE) -> 0004-0008 | D7: 15776 | E7: TA-25-929577 | F7: 80912 | G7: APERTURA | H7: CB CRECIMIENTO - NUEVO | I7: BOYACA | J7: SUTAMARCHAN | K7: BARRIO CENTRO SUTAMARCHAN 4 | L7: REDEBAN | M7: FO-25-1337775 | N7: 45875 | O7: 45881 | P7: UNO A UNO | Q7: UNO A UNO | R7: EJECUTADO | S7: 06-08-2025 SE REALIZA LLAMADA AL CLIENTE, SE HABLA CON LA SRA DIANA MARCELA GALVIS RODRÍGUEZ, SE VALIDA DIRECCIÓN OK, CANAL OK, DISPONIBILIDAD TOTAL, LLAMAR EL DÍA LA INSTALACIÓN PARA CONFIRMAR VISITA, AVISO EXTERIOR ALTURA APROX DONDE EL TECNICO LO VEA CONVENIENTE; TOMACORRIENTE CERCANO: SI; TIENE CABINA DE SEGURIDAD: SI 11-08 POR TEMAS RELACIONADO AL PARO DE MINEROS PRESENTADO EN EL DEPARTAMENTO LA ORDEN SE REPROGRAMA HASTA NUEVA ORDEN 12/08/2025 SE REALIZA INSTALACIÓN DE CORRESPONSAL, SE INSTALAN EQUIPOS CON PRUEBAS EXITOSAS, SE CAPACITA Y SE EVALÚA AL CLIENTE, SE INSTALA PUBLICIDAD COMPLETA, CB QUEDA OPERATIVO. USUARIO SOMOS BANCOLOMBIA ACTIVO | T7: VISITA _TECNICA | U7: FGZZZ909 | V7: TIPO II | W7: TERRESTRE | X7: RODRIGUEZ MURCIA YERSON IVAN | Y7: 20 | Z7: 0 | AA7: 0 | AB7: 0 | AC7: 0 | AD7: =IF(V7="TIPO I",'BASE LIQUIDACION'!$D$3,IF(V7="TIPO II",'BASE LIQUIDACION'!$D$4,IF(V7="TIPO III",'BASE LIQUIDACION'!$D$5,'BASE LIQUIDACION'!$D$7))) -> 134410.39 | AE7: =Y7*'BASE LIQUIDACION'!$B$12+Z7*'BASE LIQUIDACION'!$B$11+AA7*'BASE LIQUIDACION'!$B$13+AB7*'BASE LIQUIDACION'!$B$14+AC7*AD7 -> 324693.91
A8: TUNJA | B8: =VLOOKUP(A8,'CENTRO DE COSTOS'!A:D,4,FALSE) -> MIGUEL JULIÁN HERNÁNDEZ GUARÍN | C8: =VLOOKUP(A8,'CENTRO DE COSTOS'!A:C,2,FALSE) -> 0004-0008 | D8: 15367 | E8: TA-25-931159 | F8: 80894 | G8: APERTURA | H8: CB CRECIMIENTO - NUEVO | I8: BOYACA | J8: JENESANO | K8: BARRIO CENTRO JENESANO 7 | L8: REDEBAN | M8: FO-25-1339047 | N8: 45875 | O8: 45880 | P8: UNO A UNO | Q8: UNO A UNO | R8: EJECUTADO | S8: 06-08-2025 SE REALIZA LLAMADA AL CLIENTE, SE HABLA CON LA SRA YURY ROCIO PARRA APONTE, SE VALIDA DIRECCIÓN OK, CANAL OK, DISPONIBILIDAD TOTAL, LLAMAR EL DÍA LA INSTALACIÓN PARA CONFIRMAR VISITA, AVISO EXTERIOR ALTURA APROX 3 METROS; TOMACORRIENTE CERCANO: SI; TIENE CABINA DE SEGURIDAD: NO 11/08/2025 SE REALIZA INSTALACIÓN DE CORRESPONSAL, SE INSTALAN EQUIPOS CON PRUEBAS EXITOSAS, SE CAPACITA Y SE EVALÚA AL CLIENTE, SE INSTALA PUBLICIDAD COMPLETA, CB QUEDA OPERATIVO. USUARIO SOMOS BANCOLOMBIA ACTIVO. SE INSTALAN 10 MT DE CABLE UTP | T8: VISITA _TECNICA | U8: FGZZZ912 | V8: TIPO II | W8: TERRESTRE | X8: SOLER HOYOS CRISTIAN LEONARDO | Y8: 10 | Z8: 0 | AA8: 0 | AB8: 0 | AC8: 0 | AD8: =IF(V8="TIPO I",'BASE LIQUIDACION'!$D$3,IF(V8="TIPO II",'BASE LIQUIDACION'!$D$4,IF(V8="TIPO III",'BASE LIQUIDACION'!$D$5,'BASE LIQUIDACION'!$D$7))) -> 134410.39 | AE8: =Y8*'BASE LIQUIDACION'!$B$12+Z8*'BASE LIQUIDACION'!$B$11+AA8*'BASE LIQUIDACION'!$B$13+AB8*'BASE LIQUIDACION'!$B$14+AC8*AD8 -> 162346.95
A9: IBAGUE | B9: =VLOOKUP(A9,'CENTRO DE COSTOS'!A:D,4,FALSE) -> KEVIN ALEXIS CORZO BUSTOS | C9: =VLOOKUP(A9,'CENTRO DE COSTOS'!A:C,2,FALSE) -> 0004-0007 | D9: 73001 | E9: TA-25-931161 | F9: 80888 | G9: APERTURA | H9: CB CRECIMIENTO - NUEVO | I9: TOLIMA | J9: IBAGUE | K9: BARRIO GAITAN IBAGUE | L9: REDEBAN | M9: FO-25-1339064 | N9: 45875 | O9: 45880 | P9: UNO A UNO | Q9: UNO A UNO | R9: EJECUTADO | S9: 06-08-2025 SE REALIZA LLAMADA AL CLIENTE, SE HABLA CON EL SR DEIBY BRAVO BRAVO, SE VALIDA DIRECCIÓN OK, CANAL OK, DISPONIBILIDAD TOTAL, LLAMAR EL DÍA LA INSTALACIÓN PARA CONFIRMAR VISITA, AVISO EXTERIOR ALTURA APROX DONDE EL TECNICO LO VEA CONVENIENTE; TOMACORRIENTE CERCANO: SI; TIENE CABINA DE SEGURIDAD: NO 08-08 SE COMUNICA TELEFÓNICAMENTE CON EL SEÑOR DEIBY BRAVO BRAVO AL NÚMERO TELEFÓNICO # 3133548286 PARA REALIZAR LA INSTALACIÓN DE CORRESPONSAL INFORMA QUE NO ES POSIBLE RECIBIR LA INSTALACIÓN DEL CB EL DÍA DE HOY SOLICITA QUE SE REALICE EL DÍA LUNES 11 AGOSTO 11-08 SE REALIZA INSTALACIÓN DE CORRESPONSAL, SE INSTALAN EQUIPOS CON PRUEBAS EXITOSAS, SE CAPACITA Y SE EVALÚA AL CLIENTE, SE INSTALA PUBLICIDAD COMPLETA, CB QUEDA OPERATIVO. USUARIO SOMOS BANCOLOMBIA ACTIVO. SE INSTALAN 10 MT DE CABLE UTP | T9: VISITA _TECNICA | U9: FGZZZ914 | V9: TIPO I | W9: TERRESTRE | X9: GUTIERREZ CAMILO ANDRES | Y9: 10 | Z9: 0 | AA9: 0 | AB9: 0 | AC9: 0 | AD9: =IF(V9="TIPO I",'BASE LIQUIDACION'!$D$3,IF(V9="TIPO II",'BASE LIQUIDACION'!$D$4,IF(V9="TIPO III",'BASE LIQUIDACION'!$D$5,'BASE LIQUIDACION'!$D$7))) -> 44559.985 | AE9: =Y9*'BASE LIQUIDACION'!$B$12+Z9*'BASE LIQUIDACION'!$B$11+AA9*'BASE LIQUIDACION'!$B$13+AB9*'BASE LIQUIDACION'!$B$14+AC9*AD9 -> 162346.95
A10: IBAGUE | B10: =VLOOKUP(A10,'CENTRO DE COSTOS'!A:D,4,FALSE) -> KEVIN ALEXIS CORZO BUSTOS | C10: =VLOOKUP(A10,'CENTRO DE COSTOS'!A:C,2,FALSE) -> 0004-0007 | D10: 73001 | E10: TA-25-931163 | F10: 80889 | G10: APERTURA | H10: CB CRECIMIENTO - NUEVO | I10: TOLIMA | J10: IBAGUE | K10: BARRIO SAN REMO IBAGUE | L10: REDEBAN | M10: FO-25-1339083 | N10: 45875 | O10: 45880 | P10: UNO A UNO | Q10: UNO A UNO | R10: EJECUTADO | S10: 06-08-2025 SE REALIZA LLAMADA AL CLIENTE, SE HABLA CON LA SRA DIANA MARCELA PATIÑO HERNANDEZ, SE VALIDA DIRECCIÓN OK, CANAL OK, DISPONIBILIDAD TOTAL, LLAMAR EL DÍA LA INSTALACIÓN PARA CONFIRMAR VISITA, AVISO EXTERIOR ALTURA APROX 2,50 METROS; TOMACORRIENTE CERCANO: SI; TIENE CABINA DE SEGURIDAD: NO// MODEM A 5 METROS 11/08/2025 SE REALIZA INSTALACIÓN DE CORRESPONSAL, SE INSTALAN EQUIPOS CON PRUEBAS EXITOSAS, SE CAPACITA Y SE EVALÚA AL CLIENTE, SE INSTALA PUBLICIDAD COMPLETA, CB QUEDA OPERATIVO. USUARIO SOMOS BANCOLOMBIA ACTIVO. SE INSTALAN 15 MT DE CABLE UTP | T10: VISITA _TECNICA | U10: FGZZZ916 | V10: TIPO I | W10: TERRESTRE | X10: BARRAGAN TAFUR EDWIN ESTEBAN | Y10: 15 | Z10: 0 | AA10: 0 | AB10: 0 | AC10: 0 | AD10: =IF(V10="TIPO I",'BASE LIQUIDACION'!$D$3,IF(V10="TIPO II",'BASE LIQUIDACION'!$D$4,IF(V10="TIPO III",'BASE LIQUIDACION'!$D$5,'BASE LIQUIDACION'!$D$7))) -> 44559.985 | AE10: =Y10*'BASE LIQUIDACION'!$B$12+Z10*'BASE LIQUIDACION'!$B$11+AA10*'BASE LIQUIDACION'!$B$13+AB10*'BASE LIQUIDACION'!$B$14+AC10*AD10 -> 243520.43
A11: BUCARAMANGA | B11: =VLOOKUP(A11,'CENTRO DE COSTOS'!A:D,4,FALSE) -> MIGUEL JULIÁN HERNÁNDEZ GUARÍN | C11: =VLOOKUP(A11,'CENTRO DE COSTOS'!A:C,2,FALSE) -> 0004-0008 | D11: 68169 | E11: TA-25-931184 | F11: 80877 | G11: APERTURA | H11: CB CRECIMIENTO - NUEVO | I11: SANTANDER | J11: CHARTA | K11: BARRIO EL CARMEN CHARTA | L11: REDEBAN | M11: FO-25-1339209 | N11: 45875 | O11: 45880 | P11: UNO A UNO | Q11: UNO A UNO | R11: EJECUTADO | S11: 06-08 SE REALIZA LLAMADA AL CLIENTE, SE HABLA CON LA SRA ALICIA PABON DE VILLABONA SE VALIDA DIRECCIÓN OK, CANAL OK, DISPONIBILIDAD TOTAL, LLAMAR EL DÍA LA INSTALACIÓN PARA CONFIRMAR VISITA, AVISO EXTERIOR ALTURA APROX 2 METROS; TOMACORRIENTE CERCANO: SI; TIENE CABINA DE SEGURIDAD: NO - EL MODEM ESTA A 5 MT 11/08/2025 SE REALIZA INSTALACIÓN DE CORRESPONSAL, SE INSTALAN EQUIPOS CON PRUEBAS EXITOSAS, SE CAPACITA Y SE EVALÚA AL CLIENTE, SE INSTALA PUBLICIDAD COMPLETA, CB QUEDA OPERATIVO. USUARIO SOMOS BANCOLOMBIA ACTIVO. SE INSTALAN 10 MT DE CABLE UTP | T11: VISITA _TECNICA | U11: FGZZZ936 | V11: TIPO II | W11: TERRESTRE | X11: SANTOS GONZALEZ JOHAN FABIAN | Y11: 10 | Z11: 0 | AA11: 0 | AB11: 0 | AC11: 0 | AD11: =IF(V11="TIPO I",'BASE LIQUIDACION'!$D$3,IF(V11="TIPO II",'BASE LIQUIDACION'!$D$4,IF(V11="TIPO III",'BASE LIQUIDACION'!$D$5,'BASE LIQUIDACION'!$D$7))) -> 134410.39 | AE11: =Y11*'BASE LIQUIDACION'!$B$12+Z11*'BASE LIQUIDACION'!$B$11+AA11*'BASE LIQUIDACION'!$B$13+AB11*'BASE LIQUIDACION'!$B$14+AC11*AD11 -> 162346.95
A12: YOPAL | B12: =VLOOKUP(A12,'CENTRO DE COSTOS'!A:D,4,FALSE) -> KEVIN ALEXIS CORZO BUSTOS | C12: =VLOOKUP(A12,'CENTRO DE COSTOS'!A:C,2,FALSE) -> 0004-0007 | D12: 85010 | E12: TA-25-931186 | F12: 80862 | G12: APERTURA | H12: CB CRECIMIENTO - NUEVO | I12: CASANARE | J12: AGUAZUL | K12: BARRIO LA ESPIGA AGUAZUL | L12: REDEBAN | M12: FO-25-1339221 | N12: 45875 | O12: 45881 | P12: UNO A UNO | Q12: UNO A UNO | R12: EJECUTADO | S12: 06-08 SE REALIZA LLAMADA AL CLIENTE, SE HABLA CON LA SR RAFAEL SE VALIDA DIRECCIÓN OK, CANAL OK, DISPONIBILIDAD TOTAL, LLAMAR EL DÍA LA INSTALACIÓN PARA CONFIRMAR VISITA, AVISO EXTERIOR ALTURA APROX 2 METROS; TOMACORRIENTE CERCANO: SI; TIENE CABINA DE SEGURIDAD: SI - EL MODEM ESTA A 6 MT 09-08 EN COMUNICACIÓN CON EL SEÑOR RAFAEL CORONEL AL NUMERO 3209171697, INDICA POR TEMAS PERSONALES Y DISPOSICION NO PUEDE RECIBIRNOS HOY. INDICA NOS ATIENDE EL DIA 12-8-2025. 12/08/2025 SE REALIZA INSTALACIÓN DE CORRESPONSAL, SE INSTALAN EQUIPOS CON PRUEBAS EXITOSAS, SE CAPACITA Y SE EVALÚA AL CLIENTE, SE INSTALA PUBLICIDAD COMPLETA, CB QUEDA OPERATIVO. USUARIO SOMOS BANCOLOMBIA ACTIVO. SE INSTALAN 15 MT DE CABLE UTP | T12: VISITA _TECNICA | U12: FGZZZ940 | V12: TIPO II | W12: TERRESTRE | X12: BERNAL ELAICA EDGAR ALEXIS | Y12: 15 | Z12: 0 | AA12: 0 | AB12: 0 | AC12: 0 | AD12: =IF(V12="TIPO I",'BASE LIQUIDACION'!$D$3,IF(V12="TIPO II",'BASE LIQUIDACION'!$D$4,IF(V12="TIPO III",'BASE LIQUIDACION'!$D$5,'BASE LIQUIDACION'!$D$7))) -> 134410.39 | AE12: =Y12*'BASE LIQUIDACION'!$B$12+Z12*'BASE LIQUIDACION'!$B$11+AA12*'BASE LIQUIDACION'!$B$13+AB12*'BASE LIQUIDACION'!$B$14+AC12*AD12 -> 243520.43
A13: TUNJA | B13: =VLOOKUP(A13,'CENTRO DE COSTOS'!A:D,4,FALSE) -> MIGUEL JULIÁN HERNÁNDEZ GUARÍN | C13: =VLOOKUP(A13,'CENTRO DE COSTOS'!A:C,2,FALSE) -> 0004-0008 | D13: 15238 | E13: TA-25-931187 | F13: 80882 | G13: APERTURA | H13: CB CRECIMIENTO - NUEVO | I13: BOYACA | J13: DUITAMA | K13: BARRIO ALAMOS DUITAMA | L13: REDEBAN | M13: FO-25-1339227 | N13: 45875 | O13: 45883 | P13: UNO A UNO | Q13: UNO A UNO | R13: EJECUTADO | S13: 06-08 SE REALIZA LLAMADA AL CLIENTE, SE HABLA CON LA SR JHON JAIRO ESTUPIÑAN DIAZ SE VALIDA DIRECCIÓN OK, CANAL OK, DISPONIBILIDAD TOTAL, LLAMAR EL DÍA LA INSTALACIÓN PARA CONFIRMAR VISITA, AVISO EXTERIOR ALTURA APROX 2.5 METROS; TOMACORRIENTE CERCANO: SI; TIENE CABINA DE SEGURIDAD: NO - EL MODEM ESTA A 4 MT 08-08 POR TEMAS RELACIONADOS AL PARO DE MINEROS PRESENTADO EN EL DEPARTAMENTO LA ORDEN SE REPROGRAMA HASTA NUEVA ORDEN 14/08/2025 SE REALIZA INSTALACIÓN DE CORRESPONSAL, SE INSTALAN EQUIPOS CON PRUEBAS EXITOSAS, SE CAPACITA Y SE EVALÚA AL CLIENTE, SE INSTALA PUBLICIDAD COMPLETA, CB QUEDA OPERATIVO. USUARIO SOMOS BANCOLOMBIA ACTIVO. SE INSTALAN 10 MT DE CABLE UTP | T13: VISITA _TECNICA | U13: FGZZZ941 | V13: TIPO II | W13: TERRESTRE | X13: MARTINEZ FLOREZ DONIS ALBERTO | Y13: 10 | Z13: 0 | AA13: 0 | AB13: 0 | AC13: 0 | AD13: =IF(V13="TIPO I",'BASE LIQUIDACION'!$D$3,IF(V13="TIPO II",'BASE LIQUIDACION'!$D$4,IF(V13="TIPO III",'BASE LIQUIDACION'!$D$5,'BASE LIQUIDACION'!$D$7))) -> 134410.39 | AE13: =Y13*'BASE LIQUIDACION'!$B$12+Z13*'BASE LIQUIDACION'!$B$11+AA13*'BASE LIQUIDACION'!$B$13+AB13*'BASE LIQUIDACION'!$B$14+AC13*AD13 -> 162346.95
A14: TUNJA | B14: =VLOOKUP(A14,'CENTRO DE COSTOS'!A:D,4,FALSE) -> MIGUEL JULIÁN HERNÁNDEZ GUARÍN | C14: =VLOOKUP(A14,'CENTRO DE COSTOS'!A:C,2,FALSE) -> 0004-0008 | D14: 15723 | E14: TA-25-951739 | F14: 80975 | G14: APERTURA | H14: CB CRECIMIENTO - NUEVO | I14: BOYACA | J14: SATIVASUR | K14: BARRIO CENTRO SATIVASUR | L14: REDEBAN | M14: FO-25-1359836 | N14: 45880 | O14: 45883 | P14: UNO A UNO | Q14: UNO A UNO | R14: EJECUTADO | S14: 11-08-2025 SE REALIZA LLAMADA AL CLIENTE, SE HABLA CON LA SRA LINA LEONOR PATIÑO DURAN SE VALIDA DIRECCIÓN OK, CANAL OK, DISPONIBILIDAD TOTAL, LLAMAR EL DÍA LA INSTALACIÓN PARA CONFIRMAR VISITA, AVISO EXTERIOR ALTURA APROX 2,50 METROS; TOMACORRIENTE CERCANO: SI; TIENE CABINA DE SEGURIDAD: SI // CONTACTO REALIZADO POR LA APP // CLIENTE INDICA QUE PARA EL DIA DE MIERCOLES TIENE CITA MEDICA FUERA DE LA CIUDAD, SOLICITA VISITAR EL 14/08 14-08 SE REALIZA INSTALACIÓN DE CORRESPONSAL, SE INSTALAN EQUIPOS CON PRUEBAS EXITOSAS, SE CAPACITA Y SE EVALÚA AL CLIENTE, SE INSTALA PUBLICIDAD COMPLETA, CB QUEDA OPERATIVO. USUARIO SOMOS BANCOLOMBIA ACTIVO. SE INSTALAN 10 MT DE CABLE UTP | T14: VISITA _TECNICA | U14: FIZZZ273 | V14: TIPO III | W14: TERRESTRE | X14: SOLER HOYOS CRISTIAN LEONARDO | Y14: 10 | Z14: 0 | AA14: 0 | AB14: 0 | AC14: 0 | AD14: =IF(V14="TIPO I",'BASE LIQUIDACION'!$D$3,IF(V14="TIPO II",'BASE LIQUIDACION'!$D$4,IF(V14="TIPO III",'BASE LIQUIDACION'!$D$5,'BASE LIQUIDACION'!$D$7))) -> 222904.27 | AE14: =Y14*'BASE LIQUIDACION'!$B$12+Z14*'BASE LIQUIDACION'!$B$11+AA14*'BASE LIQUIDACION'!$B$13+AB14*'BASE LIQUIDACION'!$B$14+AC14*AD14 -> 162346.95
... A24: CALI | B24: =VLOOKUP(A24,'CENTRO DE COSTOS'!A:D,4,FALSE) -> DIEGO FERNANDO HENAO CARDONA | C24: =VLOOKUP(A24,'CENTRO DE COSTOS'!A:C,2,FALSE) -> 0004-0003 | D24: 76606 | E24: TA-25-1034028 | F24: 81244 | G24: APERTURA | H24: CB CRECIMIENTO - NUEVO | I24: VALLE DEL CAUCA | J24: RESTREPO | K24: BARRIO CENTRO RESTREPO 8 | L24: REDEBAN | M24: FO-25-1433218 | N24: 45896 | O24: 45898 | P24: UNO A UNO | Q24: UNO A UNO | R24: EJECUTADO | S24: 27-08 SE REALIZA LLAMADA AL CLIENTE, SE HABLA CON LA SRA JULIO ERNESTO SALAZAR SALAZAR SE VALIDA DIRECCIÓN OK, CANAL OK, DISPONIBILIDAD TOTAL, LLAMAR EL DÍA LA INSTALACIÓN PARA CONFIRMAR VISITA, AVISO EXTERIOR ALTURA APROX 2.5 METROS; TOMACORRIENTE CERCANO: SI; TIENE CABINA DE SEGURIDAD: NO - EL MODEM ESTA A 5 MT 29-08 SE REALIZA INSTALACIÓN DE CORRESPONSAL, SE INSTALAN EQUIPOS CON PRUEBAS EXITOSAS, SE CAPACITA Y SE EVALÚA AL CLIENTE, SE INSTALA PUBLICIDAD COMPLETA, CB QUEDA OPERATIVO. USUARIO SOMOS BANCOLOMBIA ACTIVO. SE INSTALAN 7 MT DE CABLE UTP | T24: VISITA _TECNICA | U24: FKZZZ674 | V24: TIPO II | W24: TERRESTRE | X24: MONTERO MUESES GIAN CARLO | Y24: 9 | Z24: 0 | AA24: 0 | AB24: 0 | AC24: 0 | AD24: =IF(V24="TIPO I",'BASE LIQUIDACION'!$D$3,IF(V24="TIPO II",'BASE LIQUIDACION'!$D$4,IF(V24="TIPO III",'BASE LIQUIDACION'!$D$5,'BASE LIQUIDACION'!$D$7))) -> 134410.39 | AE24: =Y24*'BASE LIQUIDACION'!$B$12+Z24*'BASE LIQUIDACION'!$B$11+AA24*'BASE LIQUIDACION'!$B$13+AB24*'BASE LIQUIDACION'!$B$14+AC24*AD24 -> 146112.26
A25: CALI | B25: =VLOOKUP(A25,'CENTRO DE COSTOS'!A:D,4,FALSE) -> DIEGO FERNANDO HENAO CARDONA | C25: =VLOOKUP(A25,'CENTRO DE COSTOS'!A:C,2,FALSE) -> 0004-0003 | D25: 76001 | E25: TA-25-915476 | F25: 80778 | G25: APERTURA | H25: CB CRECIMIENTO - NUEVO | I25: VALLE DEL CAUCA | J25: CALI | K25: BARRIO FELIDIA CALI | M25: FO-25-1316363 | N25: 45870 | O25: 45873 | P25: UNO A UNO | Q25: UNO A UNO | R25: EJECUTADO | S25: 01-08-2025 SE REALIZA LLAMADA AL CLIENTE, SE HABLA CON EL ESPOSO DE LA SRA MARITZA DEL CARMEN MEDINA PEREIRA, SE VALIDA DIRECCIÓN OK, CANAL OK, DISPONIBILIDAD TOTAL, LLAMAR EL DÍA LA INSTALACIÓN PARA CONFIRMAR VISITA, AVISO EXTERIOR ALTURA APROX DONDE EL TECNICO LO VEA CONVENIENTE; TOMACORRIENTE CERCANO: SI; TIENE CABINA DE SEGURIDAD: SI 4/08/2025 SE REALIZA INSTALACIÓN DE CORRESPONSAL, SE INSTALAN EQUIPOS CON PRUEBAS EXITOSAS, SE CAPACITA Y SE EVALÚA AL CLIENTE, SE INSTALA PUBLICIDAD COMPLETA, CB QUEDA OPERATIVO. USUARIO SOMOS BANCOLOMBIA ACTIVO | U25: F8ZZZ017 | V25: TIPO I | W25: TERRESTRE | X25: BOLAÑOS TABORDA JORGE ENRIQUE | Y25: 10 | Z25: 0 | AA25: 0 | AB25: 0 | AC25: 0 | AD25: =IF(V25="TIPO I",'BASE LIQUIDACION'!$D$3,IF(V25="TIPO II",'BASE LIQUIDACION'!$D$4,IF(V25="TIPO III",'BASE LIQUIDACION'!$D$5,'BASE LIQUIDACION'!$D$7))) -> 44559.985 | AE25: =Y25*'BASE LIQUIDACION'!$B$12+Z25*'BASE LIQUIDACION'!$B$11+AA25*'BASE LIQUIDACION'!$B$13+AB25*'BASE LIQUIDACION'!$B$14+AC25*AD25 -> 162346.95
A26: CALI | B26: =VLOOKUP(A26,'CENTRO DE COSTOS'!A:D,4,FALSE) -> DIEGO FERNANDO HENAO CARDONA | C26: =VLOOKUP(A26,'CENTRO DE COSTOS'!A:C,2,FALSE) -> 0004-0003 | D26: 76520 | E26: TA-25-952397 | F26: 80952 | G26: APERTURA | H26: CB CRECIMIENTO - NUEVO | I26: VALLE DEL CAUCA | J26: PALMIRA | K26: BARRIO ALTAMIRA PALMIRA 3 | M26: FO-25-1360278 | N26: 45880 | O26: 45881 | P26: UNO A UNO | Q26: UNO A UNO | R26: EJECUTADO | S26: 11-08 SE REALIZA LLAMADA AL CLIENTE, SE HABLA CON LA SR EDUARD ALEJANDRO ORTEGA SANCHEZ SE VALIDA DIRECCIÓN OK, CANAL OK, DISPONIBILIDAD TOTAL, LLAMAR EL DÍA LA INSTALACIÓN PARA CONFIRMAR VISITA, AVISO EXTERIOR ALTURA : NO INDICA ALTURA; TOMACORRIENTE CERCANO: SI; TIENE CABINA DE SEGURIDAD: SI - EL MODEM ESTA A 4 MT 12-08 SE REALIZA INSTALACIÓN DE CORRESPONSAL, SE INSTALAN EQUIPOS CON PRUEBAS EXITOSAS, SE CAPACITA Y SE EVALÚA AL CLIENTE, SE INSTALA PUBLICIDAD COMPLETA, CB QUEDA OPERATIVO. USUARIO SOMOS BANCOLOMBIA ACTIVO | U26: FIZZZ297 | V26: TIPO I | W26: TERRESTRE | X26: SANCHEZ URREGO ROBINSON DAVID | Y26: 7 | Z26: 0 | AA26: 0 | AB26: 0 | AC26: 0 | AD26: =IF(V26="TIPO I",'BASE LIQUIDACION'!$D$3,IF(V26="TIPO II",'BASE LIQUIDACION'!$D$4,IF(V26="TIPO III",'BASE LIQUIDACION'!$D$5,'BASE LIQUIDACION'!$D$7))) -> 44559.985 | AE26: =Y26*'BASE LIQUIDACION'!$B$12+Z26*'BASE LIQUIDACION'!$B$11+AA26*'BASE LIQUIDACION'!$B$13+AB26*'BASE LIQUIDACION'!$B$14+AC26*AD26 -> 113642.87
A27: BUCARAMANGA | B27: =VLOOKUP(A27,'CENTRO DE COSTOS'!A:D,4,FALSE) -> MIGUEL JULIÁN HERNÁNDEZ GUARÍN | C27: =VLOOKUP(A27,'CENTRO DE COSTOS'!A:C,2,FALSE) -> 0004-0008 | D27: 68547 | E27: TA-25-1005062 | F27: 81172 | G27: APERTURA | H27: CB CRECIMIENTO - NUEVO | I27: SANTANDER | J27: PIEDECUESTA | K27: BARRIO VILLANUEVA PIEDECUESTA 1 | L27: REDEBAN | M27: FO-25-1418990 | N27: 45894 | O27: 45895 | P27: UNO A UNO | Q27: UNO A UNO | R27: EJECUTADO | S27: 25-08 SE REALIZA LLAMADA AL CLIENTE, SE HABLA CON EL SR CAMILO ESTEBAN JAIMES VILLAMIZAR SE VALIDA DIRECCIÓN OK, CANAL OK, DISPONIBILIDAD TOTAL, LLAMAR EL DÍA DE LA INSTALACIÓN PARA CONFIRMAR VISITA, AVISO EXTERIOR 2,5 METROS APROX; TOMACORRIENTE CERCANO: SI; TIENE CABINA DE SEGURIDAD: NO 26/08/2025 SE REALIZA INSTALACIÓN DE CORRESPONSAL, SE INSTALAN EQUIPOS CON PRUEBAS EXITOSAS, SE CAPACITA Y SE EVALÚA AL CLIENTE, SE INSTALA PUBLICIDAD COMPLETA, CB QUEDA OPERATIVO. USUARIO SOMOS BANCOLOMBIA ACTIVO. SE INSTALA SWITCH 223C4S6013230 | T27: VISITA _TECNICA | U27: VBZZZ276 | V27: TIPO II | W27: TERRESTRE | X27: ORTEBARRERAGA MARLON STWAR | Y27: 0 | Z27: 0 | AA27: 1 | AB27: 0 | AC27: 0 | AD27: =IF(V27="TIPO I",'BASE LIQUIDACION'!$D$3,IF(V27="TIPO II",'BASE LIQUIDACION'!$D$4,IF(V27="TIPO III",'BASE LIQUIDACION'!$D$5,'BASE LIQUIDACION'!$D$7))) -> 134410.39 | AE27: =Y27*'BASE LIQUIDACION'!$B$12+Z27*'BASE LIQUIDACION'!$B$11+AA27*'BASE LIQUIDACION'!$B$13+AB27*'BASE LIQUIDACION'!$B$14+AC27*AD27 -> 257391.82
A28: CALI | B28: =VLOOKUP(A28,'CENTRO DE COSTOS'!A:D,4,FALSE) -> DIEGO FERNANDO HENAO CARDONA | C28: =VLOOKUP(A28,'CENTRO DE COSTOS'!A:C,2,FALSE) -> 0004-0003 | D28: 76001 | E28: TA-25-1005079 | F28: 81060 | G28: APERTURA | H28: CB CRECIMIENTO - OTRAS LISTAS | I28: VALLE DEL CAUCA | J28: CALI | K28: BARRIO SANTA ISABEL CALI 3 | L28: REDEBAN | M28: FO-25-1419047 | N28: 45894 | O28: 45895 | P28: UNO A UNO | Q28: UNO A UNO | R28: EJECUTADO | S28: 25-08 SE REALIZA LLAMADA AL CLIENTE, SE HABLA CON LA SRA VALENTINA LOPEZ MONDOL SE VALIDA DIRECCIÓN OK, CANAL OK, DISPONIBILIDAD TOTAL, LLAMAR EL DÍA DE LA INSTALACIÓN PARA CONFIRMAR VISITA, AVISO EXTERIOR APROX 3 METROS; TOMACORRIENTE CERCANO: SI; TIENE CABINA DE SEGURIDAD: SI 26/08/2025 SE REALIZA INSTALACIÓN DE CORRESPONSAL, SE INSTALAN EQUIPOS CON PRUEBAS EXITOSAS, SE CAPACITA Y SE EVALÚA AL CLIENTE, SE INSTALA PUBLICIDAD COMPLETA, CB QUEDA OPERATIVO. USUARIO SOMOS BANCOLOMBIA ACTIVO. SE INSTALAN SWITCCHH 221C1Q3006448 | T28: VISITA _TECNICA | U28: VBZZZ286 | V28: TIPO I | W28: TERRESTRE | X28: MONTERO MUESES GIAN CARLO | Y28: 0 | Z28: 0 | AA28: 1 | AB28: 0 | AC28: 0 | AD28: =IF(V28="TIPO I",'BASE LIQUIDACION'!$D$3,IF(V28="TIPO II",'BASE LIQUIDACION'!$D$4,IF(V28="TIPO III",'BASE LIQUIDACION'!$D$5,'BASE LIQUIDACION'!$D$7))) -> 44559.985 | AE28: =Y28*'BASE LIQUIDACION'!$B$12+Z28*'BASE LIQUIDACION'!$B$11+AA28*'BASE LIQUIDACION'!$B$13+AB28*'BASE LIQUIDACION'!$B$14+AC28*AD28 -> 257391.82
A29: BOGOTA | B29: =VLOOKUP(A29,'CENTRO DE COSTOS'!A:D,4,FALSE) -> WILLIAM ASDRUBAL ROZO ROZO | C29: =VLOOKUP(A29,'CENTRO DE COSTOS'!A:C,2,FALSE) -> 0004-0004 | D29: 25899 | E29: TA-25-915496 | F29: 80823 | G29: APERTURA | H29: CB CRECIMIENTO - NUEVO | I29: CUNDINAMARCA | J29: ZIPAQUIRA | K29: BARRIO SAN PABLO ZIPAQUIRA 3 | L29: REDEBAN | M29: FO-25-1316424 | N29: 45870 | O29: 45874 | P29: UNO A UNO | Q29: UNO A UNO | R29: EJECUTADO/CANCELADO | S29: 01-08-2025 SE REALIZA LLAMADA AL CLIENTE, SE HABLA CON EL SR JHONNATAN SAMUEL GONZALEZ MARTINEZ SE VALIDA DIRECCIÓN OK, CANAL OK, DISPONIBILIDAD TOTAL, LLAMAR EL DÍA LA INSTALACIÓN PARA CONFIRMAR VISITA, AVISO EXTERIOR ALTURA APROX 3 METROS; TOMACORRIENTE CERCANO: SI; TIENE CABINA DE SEGURIDAD: SI// MODEM A 6 METROS 5/08/2025 SE REALIZA VISITA PARA EJECUTAR LA IMPLEMENTACIÓN DE CORRESPONSAL BANCARIO PERO AL LLEGAR NO ES POSIBLE REALIZAR YA QUE EL SR JHONATAN SE LE PRESENTÓ UNA CALAMIDAD POR EL CUAL NO LE ES POSIBLE ATENDER SE BRINDA INFORMACIÓN PARA REALIZA LA NUEVA SOLICITUD DE INSTALACIÓN | T29: VISITA _TECNICA | U29: F8ZZZ027 | V29: TIPO II | W29: TERRESTRE | X29: GALEANO SORIANO JUAN DAVID | Y29: 0 | Z29: 0 | AA29: 0 | AB29: 0 | AC29: 1 | AD29: =IF(V29="TIPO I",'BASE LIQUIDACION'!$D$3,IF(V29="TIPO II",'BASE LIQUIDACION'!$D$4,IF(V29="TIPO III",'BASE LIQUIDACION'!$D$5,'BASE LIQUIDACION'!$D$7))) -> 134410.39 | AE29: =Y29*'BASE LIQUIDACION'!$B$12+Z29*'BASE LIQUIDACION'!$B$11+AA29*'BASE LIQUIDACION'!$B$13+AB29*'BASE LIQUIDACION'!$B$14+AC29*AD29 -> 134410.39
A30: CARTAGENA | B30: =VLOOKUP(A30,'CENTRO DE COSTOS'!A:D,4,FALSE) -> JOSE MAURICIO HERNANDEZ ROJAS | C30: =VLOOKUP(A30,'CENTRO DE COSTOS'!A:C,2,FALSE) -> 0004-0001 | D30: 13001 | E30: TA-25-915508 | F30: 80781 | G30: APERTURA | H30: CB CRECIMIENTO - NUEVO | I30: BOLIVAR | J30: CARTAGENA | K30: BARRIO VILLA ESTRELLA CARTAGENA 3 | L30: REDEBAN | M30: FO-25-1316456 | N30: 45870 | O30: 45873 | P30: UNO A UNO | Q30: UNO A UNO | R30: EJECUTADO/CANCELADO | S30: 01-08 SE REALIZA LLAMADA AL CLIENTE, SE HABLA CON LA SRA ALEXANDRA ANGULO ANDRADE SE VALIDA DIRECCIÓN OK, CANAL OK, DISPONIBILIDAD TOTAL, LLAMAR EL DÍA LA INSTALACIÓN PARA CONFIRMAR VISITA, AVISO EXTERIOR ALTURA APROX 2 METROS; TOMACORRIENTE CERCANO: SI; TIENE CABINA DE SEGURIDAD: NO 4/08/2025 SE ESCALA EL SIGUIENTE CASO, DONDE SE VA INSTALAR EN UN APARTAMENTO DEL SEGUNDO PISO, TORRE 2 DEL CONJUNTO RESIDENCIAL “CONDOMIO IPANEMA”, INDICAN QUE EL AVISO SE PUEDE INSTALAR EN EL PASILLO DEL EDIFICIO, A LA ENTRADA DEL APARTAMENTO. SE EVIDENCIA TAMBIÉN QUE EL COMERCIO ES UNA VIVIENDA CON UNA VITRINA PEQUEÑA CON ACCESORIOS DE CELULARES. / PROCEDEMOS A ESCALAR A ENTIDAD LA SITUACIÓN, YA QUE SE TIENE PREVISTA LA INSTALACIÓN EN UN APARTAMENTO QUE NO CUENTA CON AVISO PUBLICITARIO, LO CUAL PUEDE GENERAR DIFICULTADES EN LA IDENTIFICACIÓN DEL PUNTO. // ENTIDAD SOLICITA CANCELAR LA ACTIVIDAD | T30: VISITA _TECNICA | U30: F8ZZZ036 | V30: TIPO I | W30: TERRESTRE | X30: CANEDO HERRERA ALEXANDER | Y30: 0 | Z30: 0 | AA30: 0 | AB30: 0 | AC30: 1 | AD30: =IF(V30="TIPO I",'BASE LIQUIDACION'!$D$3,IF(V30="TIPO II",'BASE LIQUIDACION'!$D$4,IF(V30="TIPO III",'BASE LIQUIDACION'!$D$5,'BASE LIQUIDACION'!$D$7))) -> 44559.985 | AE30: =Y30*'BASE LIQUIDACION'!$B$12+Z30*'BASE LIQUIDACION'!$B$11+AA30*'BASE LIQUIDACION'!$B$13+AB30*'BASE LIQUIDACION'!$B$14+AC30*AD30 -> 44559.985
A31: CUCUTA | B31: =VLOOKUP(A31,'CENTRO DE COSTOS'!A:D,4,FALSE) -> MIGUEL JULIÁN HERNÁNDEZ GUARÍN | C31: =VLOOKUP(A31,'CENTRO DE COSTOS'!A:C,2,FALSE) -> 0004-0008 | D31: 54874 | E31: TA-25-915525 | F31: 80816 | G31: APERTURA | H31: CB CRECIMIENTO - NUEVO | I31: NORTE DE SANTANDER | J31: VILLA DEL ROSARIO | K31: BARRIO LA PARADA VILLA DEL ROSARIO 11 | L31: REDEBAN | M31: FO-25-1316487 | N31: 45870 | O31: 45873 | P31: UNO A UNO | Q31: UNO A UNO | R31: EJECUTADO/CANCELADO | S31: 01-08 SE REALIZA LLAMADA AL CLIENTE, SE HABLA CON LA SRA LEDYS ANDREA ESCALANTE BERBESI SE VALIDA DIRECCIÓN OK, CANAL OK, DISPONIBILIDAD TOTAL, LLAMAR EL DÍA LA INSTALACIÓN PARA CONFIRMAR VISITA, AVISO EXTERIOR ALTURA: NO INDICA ALTURA; TOMACORRIENTE CERCANO: SI; TIENE CABINA DE SEGURIDAD: NO 4/08/2025 SE REALIZÓ VISITA AL COMERCIO Y CLIENTE NO ACEPTA LA ACTIVIDAD DE IMPLEMENTACIÓN DE CORRESPONSAL, QUE EN OTRO MOMENTO SE COMUNICARA CON EL BANCO PARA SOLICITARLO EN CASO QUE LO LLEGARA A NECESITAR. | T31: VISITA _TECNICA | U31: F8ZZZ043 | V31: TIPO I | W31: TERRESTRE | X31: MORA VEGA JEAMPIER | Y31: 0 | Z31: 0 | AA31: 0 | AB31: 0 | AC31: 1 | AD31: =IF(V31="TIPO I",'BASE LIQUIDACION'!$D$3,IF(V31="TIPO II",'BASE LIQUIDACION'!$D$4,IF(V31="TIPO III",'BASE LIQUIDACION'!$D$5,'BASE LIQUIDACION'!$D$7))) -> 44559.985 | AE31: =Y31*'BASE LIQUIDACION'!$B$12+Z31*'BASE LIQUIDACION'!$B$11+AA31*'BASE LIQUIDACION'!$B$13+AB31*'BASE LIQUIDACION'!$B$14+AC31*AD31 -> 44559.985
A32: MEDELLIN | B32: =VLOOKUP(A32,'CENTRO DE COSTOS'!A:D,4,FALSE) -> JUAN SEBASTIÁN RÍOS CASTRILLÓN | C32: =VLOOKUP(A32,'CENTRO DE COSTOS'!A:C,2,FALSE) -> 0004-0005 | D32: 5642 | E32: TA-25-930981 | F32: 80842 | G32: APERTURA | H32: CB CRECIMIENTO ALIANZA - NUEVO | I32: ANTIOQUIA | J32: SALGAR | K32: PTM SALGAR NATULIGHT TIENDA NA | L32: REDEBAN | M32: FO-25-1338801 | N32: 45875 | O32: 45880 | P32: AGREGADOR | Q32: COMCARD - PTM | R32: EJECUTADO/CANCELADO | S32: 06-08 PROGRAMACIÓN REALIZADA POR LA ALIANZA 11/08/2025 REPORTAMOS NOVEDAD DE INSTALACIÓN.VISITAMOS COMERCIO ENCONTRANDO CERCANÍA CON 2 PUNTOS: PUNTO EXISTENTE 1: 3007029991 BARRIO PARQUE 2 SALGAR. COORDENADAS 5.963714 -75.979253 PUNTO EXISTENTE 2: 3007037617 DISTRICOL CELULARES JU. COORDENADAS 5.963669 -75.979412 COORDENADAS PUNTO A INSTALAR HOY: 5.963799 -75.979332 / ENTIDAD SOLICITA CANCELAR ACTIVIDAD | T32: VISITA _TECNICA | U32: FHZZZ002 | V32: TIPO II | W32: TERRESTRE | X32: CASTAÑEDA PALACIO CARLOS FELIPE | Y32: 0 | Z32: 0 | AA32: 0 | AB32: 0 | AC32: 1 | AD32: =IF(V32="TIPO I",'BASE LIQUIDACION'!$D$3,IF(V32="TIPO II",'BASE LIQUIDACION'!$D$4,IF(V32="TIPO III",'BASE LIQUIDACION'!$D$5,'BASE LIQUIDACION'!$D$7))) -> 134410.39 | AE32: =Y32*'BASE LIQUIDACION'!$B$12+Z32*'BASE LIQUIDACION'!$B$11+AA32*'BASE LIQUIDACION'!$B$13+AB32*'BASE LIQUIDACION'!$B$14+AC32*AD32 -> 134410.39
A33: VILLAVICENCIO | B33: =VLOOKUP(A33,'CENTRO DE COSTOS'!A:D,4,FALSE) -> KEVIN ALEXIS CORZO BUSTOS | C33: =VLOOKUP(A33,'CENTRO DE COSTOS'!A:C,2,FALSE) -> 0004-0007 | D33: 50006 | E33: TA-25-929391 | F33: 80861 | G33: APERTURA | H33: CB CRECIMIENTO - NUEVO | I33: META | J33: ACACIAS | K33: BARRIO INDEPENDENCIA ACACIAS 1 | L33: REDEBAN | M33: FO-25-1367708 | N33: 45875 | O33: 45884 | P33: UNO A UNO | Q33: UNO A UNO | R33: EJECUTADO | S33: 06-08-2025 SE REALIZA LLAMADA AL CLIENTE, SE HABLA CON LA SRA LEIDY VIVIANA CICUA JIMENEZ SE VALIDA DIRECCIÓN OK, CANAL OK, DISPONIBILIDAD TOTAL, LLAMAR EL DÍA LA INSTALACIÓN PARA CONFIRMAR VISITA, AVISO EXTERIOR ALTURA APROX 1,70 METROS; TOMACORRIENTE CERCANO: SI; TIENE CABINA DE SEGURIDAD: SI // CONTACTO REALIZADO POR WHATSAPP 8/08/2025SE REALIZA VISITA PARA IMPLEMENTACIÓN DEL CB “80861” A LA DIRECCIÓN RELACIONADA EN LA LISTA DE CHEQUEO, PERO AL CONSULTAR LA PLACA EN LA WEB DE INICIALIZACIONES EL CÓDIGO ÚNICO 3007080861 Y TERMINAL FGZZZ886 COINCIDEN CON EL CB RELACIONADO EN LISTA DE CHEQUEO, SIN EMBARGO LA DIRECCIÓN Y NOMBRE NO; ESTOS SON DE OTRO CB “80925” DE OTRA ZONA. @HDMURCIA SEGÚN LO CONVERSADO SE CANCELA INSTALACIÓN PARA EL CB 80861. 12/08/2025 A PETICIÓN DE LA ENTIDAD, POR FAVOR REALICEMOS NUEVAMENTE LA VISITA AL PUNTO E IMPLEMENTEMOS, YA QUE LA DIRECCIÓN HA SIDO ACTUALIZADA CORRECTAMENTE. 15/08/2025 SE REALIZA INSTALACIÓN DE CORRESPONSAL, SE INSTALAN EQUIPOS CON PRUEBAS EXITOSAS, SE CAPACITA Y SE EVALÚA AL CLIENTE, SE INSTALA PUBLICIDAD COMPLETA, CB QUEDA OPERATIVO. USUARIO SOMOS BANCOLOMBIA ACTIVO | T33: VISITA _TECNICA | U33: FGZZZ886 | V33: TIPO II | W33: TERRESTRE | X33: CASTRILLON URREA LONDIER LEANDRO | Y33: 0 | Z33: 0 | AA33: 0 | AB33: 0 | AC33: 1 | AD33: =IF(V33="TIPO I",'BASE LIQUIDACION'!$D$3,IF(V33="TIPO II",'BASE LIQUIDACION'!$D$4,IF(V33="TIPO III",'BASE LIQUIDACION'!$D$5,'BASE LIQUIDACION'!$D$7))) -> 134410.39 | AE33: =Y33*'BASE LIQUIDACION'!$B$12+Z33*'BASE LIQUIDACION'!$B$11+AA33*'BASE LIQUIDACION'!$B$13+AB33*'BASE LIQUIDACION'!$B$14+AC33*AD33 -> 134410.39
A34: YOPAL | B34: =VLOOKUP(A34,'CENTRO DE COSTOS'!A:D,4,FALSE) -> KEVIN ALEXIS CORZO BUSTOS | C34: =VLOOKUP(A34,'CENTRO DE COSTOS'!A:C,2,FALSE) -> 0004-0007 | D34: 85250 | E34: TA-25-931177 | F34: 80906 | G34: APERTURA | H34: CB CRECIMIENTO - NUEVO | I34: CASANARE | J34: PAZ DE ARIPORO | K34: BARRIO EL PALMAR PAZ DE ARIPORO 2 | L34: REDEBAN | M34: FO-25-1339174 | N34: 45875 | O34: 45880 | P34: UNO A UNO | Q34: UNO A UNO | R34: EJECUTADO/CANCELADO | S34: 06-08 SE REALIZA LLAMADA AL CLIENTE, SE HABLA CON LA SRA DIANA YULIETH SARAVIA MARTINEZ SE VALIDA DIRECCIÓN OK, CANAL OK, DISPONIBILIDAD TOTAL, LLAMAR EL DÍA LA INSTALACIÓN PARA CONFIRMAR VISITA, AVISO EXTERIOR ALTURA: NO INDICA ALTURA TOMACORRIENTE CERCANO: SI; TIENE CABINA DE SEGURIDAD: NO 11/08/2025 SE VISITA COMERCIO, LA SEÑORA DIANA SARAVIA INDICA QUE POR TEMAS DE REMODELACION DEL LOCAL, ESTE ESTARÁ LISTO HASTA LA PROXIMA SEMANA, POR TAL MOTIVO SE ESCALA A COORDINADOR Y SE CANCELA, SE LE INDICA AL USUARIO QUE UNA VEZ ESTE EL LOCAL LISTO LLAME A LA ENTIDAD. | T34: VISITA _TECNICA | U34: FGZZZ928 | V34: TIPO II | W34: TERRESTRE | X34: BERNAL ELAICA EDGAR ALEXIS | Y34: 0 | Z34: 0 | AA34: 0 | AB34: 0 | AC34: 1 | AD34: =IF(V34="TIPO I",'BASE LIQUIDACION'!$D$3,IF(V34="TIPO II",'BASE LIQUIDACION'!$D$4,IF(V34="TIPO III",'BASE LIQUIDACION'!$D$5,'BASE LIQUIDACION'!$D$7))) -> 134410.39 | AE34: =Y34*'BASE LIQUIDACION'!$B$12+Z34*'BASE LIQUIDACION'!$B$11+AA34*'BASE LIQUIDACION'!$B$13+AB34*'BASE LIQUIDACION'!$B$14+AC34*AD34 -> 134410.39
A35: CALI | B35: =VLOOKUP(A35,'CENTRO DE COSTOS'!A:D,4,FALSE) -> DIEGO FERNANDO HENAO CARDONA | C35: =VLOOKUP(A35,'CENTRO DE COSTOS'!A:C,2,FALSE) -> 0004-0003 | D35: 19845 | E35: TA-25-931178 | F35: 80922 | G35: APERTURA | H35: CB CRECIMIENTO - NUEVO | I35: CAUCA | J35: VILLA RICA | K35: BARRIO CENTRO VILLA RICA 5 | L35: REDEBAN | M35: FO-25-1350933 | N35: 45875 | O35: 45882 | P35: UNO A UNO | Q35: UNO A UNO | R35: EJECUTADO | S35: 06-08 SE REALIZA LLAMADA AL CLIENTE, SE HABLA CON LA SR JANIER JULIAN VALENCIA ESCOBAR SE VALIDA DIRECCIÓN OK, CANAL OK, DISPONIBILIDAD TOTAL, LLAMAR EL DÍA LA INSTALACIÓN PARA CONFIRMAR VISITA, AVISO EXTERIOR ALTURA: NO INDICA ALTURA; TOMACORRIENTE CERCANO: SI; TIENE CABINA DE SEGURIDAD: SI 8/08/2025SE LLEGA A SITIO PARA REALIZA LA INSTALACIÓN CB Y LA ENERGIA SE FUE HACE APROXIMADAMENTE 90 MINUTOS. EL DATÁFONO QUEDA CONFIGURADO SIN HABER REALIZADO NINGUNA TRANSACCIÓN DE PRUEBA. 13/08/2025 SE REALIZA INSTALACIÓN DE CORRESPONSAL, SE INSTALAN EQUIPOS CON PRUEBAS EXITOSAS, SE CAPACITA Y SE EVALÚA AL CLIENTE, SE INSTALA PUBLICIDAD COMPLETA, CB QUEDA OPERATIVO. USUARIO SOMOS BANCOLOMBIA ACTIVO | T35: VISITA _TECNICA | U35: FGZZZ929 | V35: TIPO IV | W35: TERRESTRE | X35: TORRES GARCIA JENDRY JOSE | Y35: 0 | Z35: 0 | AA35: 0 | AB35: 0 | AC35: 1 | AD35: =IF(V35="TIPO I",'BASE LIQUIDACION'!$D$3,IF(V35="TIPO II",'BASE LIQUIDACION'!$D$4,IF(V35="TIPO III",'BASE LIQUIDACION'!$D$5,'BASE LIQUIDACION'!$D$7))) -> 464809.03 | AE35: =Y35*'BASE LIQUIDACION'!$B$12+Z35*'BASE LIQUIDACION'!$B$11+AA35*'BASE LIQUIDACION'!$B$13+AB35*'BASE LIQUIDACION'!$B$14+AC35*AD35 -> 464809.03
A36: TUNJA | B36: =VLOOKUP(A36,'CENTRO DE COSTOS'!A:D,4,FALSE) -> MIGUEL JULIÁN HERNÁNDEZ GUARÍN | C36: =VLOOKUP(A36,'CENTRO DE COSTOS'!A:C,2,FALSE) -> 0004-0008 | D36: 15272 | E36: TA-25-931181 | F36: 80893 | G36: APERTURA | H36: CB CRECIMIENTO - NUEVO | I36: BOYACA | J36: FIRAVITOBA | K36: BARRIO CENTRO FIRAVITOBA 2 | L36: REDEBAN | M36: FO-25-1339192 | N36: 45875 | O36: 45881 | P36: UNO A UNO | Q36: UNO A UNO | R36: EJECUTADO/CANCELADO | S36: 06-08 SE REALIZA LLAMADA AL CLIENTE, SE HABLA CON LA SR RONALD MANUEL SUAREZ CORREA SE VALIDA DIRECCIÓN OK, CANAL OK, DISPONIBILIDAD TOTAL, LLAMAR EL DÍA LA INSTALACIÓN PARA CONFIRMAR VISITA, AVISO EXTERIOR ALTURA APROX 2.5 METROS; TOMACORRIENTE CERCANO: SI; TIENE CABINA DE SEGURIDAD: SI 08-08 POR TEMAS RELACIONADOS AL PARO DE MINEROS PRESENTADO EN EL DEPARTAMENTO, LA ORDEN SE REPROGRAMA HASTA NUEVA ORDEN 12/08/2025 SE VISITA DIRECCIÓN COMERCIO , NO SE PROCEDE A EJECUTAR INSTALACIÓN POR DIRECCIÓN ERRADA ,SE VALIDA CÁMARA DE COMERCIO DIRECCIÓN COINCIDE CON LA ORDEN DE TRABAJO PERO SE VÁLIDA QUE LA DIRECCIÓN LE CORRESPONDE A OTRO PREDIO QUE ESTA UBICADO EN LA CASA DE AL LADO DE DONDE SE INSTALARÍA, SE LE INDICA AL CLIENTE QUE DEBE ACTUALIZAR CAMARA DE COMERCIO | T36: VISITA _TECNICA | U36: FGZZZ933 | V36: TIPO II | W36: TERRESTRE | X36: ALVARADO MORENO CRISTHIAN | Y36: 0 | Z36: 0 | AA36: 0 | AB36: 0 | AC36: 1 | AD36: =IF(V36="TIPO I",'BASE LIQUIDACION'!$D$3,IF(V36="TIPO II",'BASE LIQUIDACION'!$D$4,IF(V36="TIPO III",'BASE LIQUIDACION'!$D$5,'BASE LIQUIDACION'!$D$7))) -> 134410.39 | AE36: =Y36*'BASE LIQUIDACION'!$B$12+Z36*'BASE LIQUIDACION'!$B$11+AA36*'BASE LIQUIDACION'!$B$13+AB36*'BASE LIQUIDACION'!$B$14+AC36*AD36 -> 134410.39
A37: BOGOTA | B37: =VLOOKUP(A37,'CENTRO DE COSTOS'!A:D,4,FALSE) -> WILLIAM ASDRUBAL ROZO ROZO | C37: =VLOOKUP(A37,'CENTRO DE COSTOS'!A:C,2,FALSE) -> 0004-0004 | D37: 11001 | E37: TA-25-952495 | F37: 80934 | G37: APERTURA | H37: CB CRECIMIENTO - NUEVO | I37: CUNDINAMARCA | J37: BOGOTA | K37: BARRIO BOSA CARBONEL BOGOTA 1 | L37: REDEBAN | M37: FO-25-1374679 | N37: 45880 | O37: 45883 | P37: UNO A UNO | Q37: UNO A UNO | R37: EJECUTADO | S37: 11-08 SE REALIZA LLAMADA AL CLIENTE, SE HABLA CON EL SRA JOHANNA PAOLA CASTAÑO MARTINEZ SE VALIDA DIRECCIÓN OK, CANAL OK, DISPONIBILIDAD TOTAL, LLAMAR EL DÍA LA INSTALACIÓN PARA CONFIRMAR VISITA, AVISO EXTERIOR ALTURA APROX 3 METROS; TOMACORRIENTE CERCANO: SI; TIENE CABINA DE SEGURIDAD: NO - COMUNICACIÓN POR WPP / EL MODEM ESTA A 4 MT 12/08/2025 SE ESCALA NOVEDAD EN APERTURA REDEBAN 3007080934 BARRIO BOSA CARBONEL BOGOTA 1, LA CUAL AL LLEGAR AL SITIO, SE ENCUENTRA UN CORRESPONSAL INSTALADO A 34 METROS SEGÚN MAPS. ADJUNTO REGISTRO FOTOGRÁFICO DATOS DE CB EXISTENTE (ADJUNTO COPIA TIRILA) NOMBRE: PTM BOGOTA DROGUERIA A CÓDIGO ÚNICO: 3007058171 DIRECCIÓN: CR 78C 71C SUR 40 COORDENADAS: 4.603577 -74.196202 14/08/2025 ENTIDAD APRUEBA INSTALACION 14/08/2025 SE REALIZA INSTALACIÓN DE CORRESPONSAL, SE INSTALAN EQUIPOS CON PRUEBAS EXITOSAS, SE CAPACITA Y SE EVALÚA AL CLIENTE, SE INSTALA PUBLICIDAD COMPLETA, CB QUEDA OPERATIVO. USUARIO SOMOS BANCOLOMBIA ACTIVO | T37: VISITA _TECNICA | U37: FIZZZ320 | V37: TIPO I | W37: TERRESTRE | X37: LOZADA ROJAS CHRISTIAN ANDRES | Y37: 0 | Z37: 0 | AA37: 0 | AB37: 0 | AC37: 1 | AD37: =IF(V37="TIPO I",'BASE LIQUIDACION'!$D$3,IF(V37="TIPO II",'BASE LIQUIDACION'!$D$4,IF(V37="TIPO III",'BASE LIQUIDACION'!$D$5,'BASE LIQUIDACION'!$D$7))) -> 44559.985 | AE37: =Y37*'BASE LIQUIDACION'!$B$12+Z37*'BASE LIQUIDACION'!$B$11+AA37*'BASE LIQUIDACION'!$B$13+AB37*'BASE LIQUIDACION'!$B$14+AC37*AD37 -> 44559.985
A38: MEDELLIN | B38: =VLOOKUP(A38,'CENTRO DE COSTOS'!A:D,4,FALSE) -> JUAN SEBASTIÁN RÍOS CASTRILLÓN | C38: =VLOOKUP(A38,'CENTRO DE COSTOS'!A:C,2,FALSE) -> 0004-0005 | D38: 5790 | E38: TA-25-952496 | F38: 80964 | G38: APERTURA | H38: CB CRECIMIENTO - NUEVO | I38: ANTIOQUIA | J38: TARAZA | K38: BARRIO SAN NICOLAS TARAZA 1 | L38: REDEBAN | M38: FO-25-1360406 | N38: 45880 | O38: 45883 | P38: UNO A UNO | Q38: UNO A UNO | R38: EJECUTADO/CANCELADO | S38: 10-08 SE REALIZA LLAMADA AL CLIENTE, SE HABLA CON LA SR FERNEY ANTONIO CASTILLO PASTRANA SE VALIDA DIRECCIÓN OK, CANAL OK, DISPONIBILIDAD TOTAL, LLAMAR EL DÍA LA INSTALACIÓN PARA CONFIRMAR VISITA, AVISO EXTERIOR ALTURA APROX 2 METROS; TOMACORRIENTE CERCANO: SI; TIENE CABINA DE SEGURIDAD: NO 12/08/2025 VISITAMOS PUNTO PARA INSTALACIÓN ENCONTRANDO QUE YA HAY OTRO EXISTENTE A MEDIA CUADRA CON CODIGO 3007077869 PTM SAN NICOLAS TARAZA. ESTE PUNTO FUE TRASLADADO HACE UN MES A ESTA NUEVA DIRECCIÓN. USUARIO DE INSTALACIÓN DE HOY COMENTA QUE CUANDO PASÓ LOS PAPELES PARA SOLICITAR EL CORRESPONSAL NO EXISTÍA ESE OTRO CB EN ESTA DIRECCIÓN SINO QUE SE TRASLADÓ COMO COMENTAMOS ANTERIORMENTE. COORDENADAS PUNTO EXISTENTE: 7.584959 -75.400686 COORDENADAS PUNTO NUEVO: 7.584725 -75.400914 14/08/2025 ENTIDAD SOLICITA CANCELAR | T38: VISITA _TECNICA | U38: FIZZZ321 | V38: TIPO IV | W38: TERRESTRE | X38: BADEL ACUÑA LUIS ALBERTO | Y38: 0 | Z38: 0 | AA38: 0 | AB38: 0 | AC38: 1 | AD38: =IF(V38="TIPO I",'BASE LIQUIDACION'!$D$3,IF(V38="TIPO II",'BASE LIQUIDACION'!$D$4,IF(V38="TIPO III",'BASE LIQUIDACION'!$D$5,'BASE LIQUIDACION'!$D$7))) -> 464809.03 | AE38: =Y38*'BASE LIQUIDACION'!$B$12+Z38*'BASE LIQUIDACION'!$B$11+AA38*'BASE LIQUIDACION'!$B$13+AB38*'BASE LIQUIDACION'!$B$14+AC38*AD38 -> 464809.03
... A50: MEDELLIN | B50: =VLOOKUP(A50,'CENTRO DE COSTOS'!A:D,4,FALSE) -> JUAN SEBASTIÁN RÍOS CASTRILLÓN | C50: =VLOOKUP(A50,'CENTRO DE COSTOS'!A:C,2,FALSE) -> 0004-0005 | D50: 5031 | E50: TA-25-1034477 | F50: 81225 | G50: APERTURA | H50: CB CRECIMIENTO ALIANZA - NUEVO | I50: ANTIOQUIA | J50: AMALFI | K50: DISTRICOL TIENDA A MAR | L50: REDEBAN | M50: FO-25-1433936 | N50: 45896 | O50: 45897 | P50: AGREGADOR | Q50: DISTRICOL | R50: EJECUTADO/CANCELADO | S50: 27-08 PROGRAMACIÓN REALIZADA POR LA ALIANZA 28/08/2025 VISITAMOS PUNTO ENCONTRANDO OTRO CB EN EL LOCAL CONTIGUO. CODIGO EXISTENTE 71566 BARRIO EL CAMELLON AMALFI. ADICIONALMENTE HAY UNA NOVEDAD CON LA DIRECCIÓN. COMERCIO ESTÁ UBICADO EN CALLE 20 PERO CON CARRERA 17. | T50: VISITA _TECNICA | U50: FKZZZ696 | V50: TIPO IV | W50: TERRESTRE | X50: QUINTERO SANCHEZ JUAN SEBASTIAN | Y50: 0 | Z50: 0 | AA50: 0 | AB50: 0 | AC50: 1 | AD50: =IF(V50="TIPO I",'BASE LIQUIDACION'!$D$3,IF(V50="TIPO II",'BASE LIQUIDACION'!$D$4,IF(V50="TIPO III",'BASE LIQUIDACION'!$D$5,'BASE LIQUIDACION'!$D$7))) -> 464809.03 | AE50: =Y50*'BASE LIQUIDACION'!$B$12+Z50*'BASE LIQUIDACION'!$B$11+AA50*'BASE LIQUIDACION'!$B$13+AB50*'BASE LIQUIDACION'!$B$14+AC50*AD50 -> 464809.03
A51: CUCUTA | B51: =VLOOKUP(A51,'CENTRO DE COSTOS'!A:D,4,FALSE) -> MIGUEL JULIÁN HERNÁNDEZ GUARÍN | C51: =VLOOKUP(A51,'CENTRO DE COSTOS'!A:C,2,FALSE) -> 0004-0008 | D51: 54498 | E51: TA-25-904094 | F51: 80745 | G51: APERTURA | H51: CB CRECIMIENTO - NUEVO | I51: NORTE DE SANTANDER | J51: OCAÑA | K51: BARRIO JUAN 23 OCAÑA | M51: FO-25-1305075 | N51: 45868 | O51: 45870 | P51: UNO A UNO | Q51: UNO A UNO | R51: EJECUTADO | S51: 30-07-2025 SE REALIZA LLAMADA AL CLIENTE, SE HABLA CON LA SRA ERIKA CAROLINA RAMIREZ QUINTERO, VALIDA DIRECCIÓN OK, CANAL OK, DISPONIBILIDAD TOTAL, LLAMAR EL DÍA LA INSTALACIÓN PARA CONFIRMAR VISITA, AVISO EXTERIOR ALTURA APROX DONDE EL TECNICO LO VEA CONVENIENTE; TOMACORRIENTE CERCANO: SI; TIENE CABINA DE SEGURIDAD: SI 1/08/2025 SE REALIZA INSTALACIÓN DE CORRESPONSAL, SE INSTALAN EQUIPOS CON PRUEBAS EXITOSAS, SE CAPACITA Y SE EVALÚA AL CLIENTE, SE INSTALA PUBLICIDAD COMPLETA, CB QUEDA OPERATIVO. USUARIO SOMOS BANCOLOMBIA ACTIVO. SE INSTALA SWITCH 223C4S6013109 | T51: VISITA _TECNICA | U51: VAZZZ384 | V51: TIPO IV | W51: TERRESTRE | X51: GELVEZ MOGOLLON JOSE ELISEO | Y51: 0 | Z51: 0 | AA51: 1 | AB51: 0 | AC51: 0 | AD51: =IF(V51="TIPO I",'BASE LIQUIDACION'!$D$3,IF(V51="TIPO II",'BASE LIQUIDACION'!$D$4,IF(V51="TIPO III",'BASE LIQUIDACION'!$D$5,'BASE LIQUIDACION'!$D$7))) -> 464809.03 | AE51: =Y51*'BASE LIQUIDACION'!$B$12+Z51*'BASE LIQUIDACION'!$B$11+AA51*'BASE LIQUIDACION'!$B$13+AB51*'BASE LIQUIDACION'!$B$14+AC51*AD51 -> 257391.82
AE52: =SUM(AE3:AE51) -> 9390985.8

Sheet Hoja1
A1: CIUDAD SEDE | B1: COORDINADOR | C1: CENTRO DE COSTOS LÍNEACOM | D1: CÓDIGO DANE | E1: TA/CODIGO ACTIVIDAD | F1: CODIGO CB | G1: ACTIVIDAD | H1: TIPO DE APERTURA | I1: DEPARTAMENTO | J1: CIUDAD | K1: NOMBRE DEL CB | L1: RED | M1: FO | N1: FECHA LISTA | O1: FECHA ULTIMA ACTUALIZACION | P1: FORMATO | Q1: CADENA | R1: ESTADO | S1: OBSERVACIONES CLIENTE | T1: FORMA DE ATENCIÓN | U1: TERMINALES | V1: TIPIFICACION | W1: TIPO DE TRAYECTO | X1: NOMBRE DEL TECNICO | Y1: ACOMETIDA DATOS | Z1: ACOMETIDA ELECTRICA | AA1: SWITCH | AB1: ROUTER | AC1: VALOR DIAS ACTIVIDAD FACTURABLES | AD1: DIAS ACTIVIDAD FACTURABLES | AE1: VALOR TOTAL INSTALACION DE PUBLICIDAD
A2: MEDELLIN | C2: 0004-0005 | D2: 5360 | E2: TA-25-1165179 | F2: 3007081728 | G2: APERTURA | H2: CB CRECIMIENTO ALIANZA - NUEVO | I2: ANTIOQUIA | J2: ITAGUI | K2: DISTRICOL RG | L2: BANCOLOMBIA | M2: FO-25-1624400 | FO-25-1611140 | P2: AGREGADOR | Q2: DISTRICOL | R2: EJECUTADO | EJECUTADO/CANCELADO | S2: 06/10/2025 SE INSTALA CORRESPONSAL OK | T2: VISITA TECNICA | V2: TIPO I | W2: TERRESTRE | X2: RUA ALVAREZ RICHARD ANDRES | Y2: 0 | Z2: 0 | AA2: 0 | AB2: 0 | AC2: 1 | AD2: 44560 | AE2: 44560
A5: MEDELLIN | C5: 0004-0005 | D5: 5360 | E5: TA-25-1165179 | F5: 3007081728 | G5: APERTURA | H5: CB CRECIMIENTO ALIANZA - NUEVO | I5: ANTIOQUIA | J5: ITAGUI | K5: DISTRICOL RG | L5: BANCOLOMBIA | M5: FO-25-1624400 | FO-25-1611140 | P5: AGREGADOR | Q5: DISTRICOL | R5: EJECUTADO | EJECUTADO/CANCELADO | S5: 06/10/2025 SE INSTALA CORRESPONSAL OK | T5: VISITA TECNICA | V5: TIPO I | W5: TERRESTRE | X5: RUA ALVAREZ RICHARD ANDRES | Y5: 200000 | Z5: 0 | AA5: 0 | AB5: 0 | AC5: 2 | AD5: 0 | AE5: 244560

Sheet TIPOLOGIAS
A1: COD. CIUDAD | B1: CIUDAD | C1: DEPARTAMENTO | D1: DESDE DONDE SE ATIENDE | E1: TIPO DE TRAYECTO NUEVO | F1: TIPOLOGIA NUEVA
A2: 91430 | B2: LA VICTORIA | C2: AMAZONAS | D2: BOGOTA | E2: AEREO | F2: TIPO IV ESPECIAL
A3: 91669 | B3: PUERTO SANTANDER | C3: AMAZONAS | D3: BOGOTA | E3: AEREO | F3: TIPO IV ESPECIAL
A4: 91263 | B4: EL ENCANTO | C4: AMAZONAS | D4: BOGOTA | E4: AEREO | F4: TIPO IV ESPECIAL
A5: 91405 | B5: LA CHORRERA | C5: AMAZONAS | D5: BOGOTA | E5: AEREO | F5: TIPO IV ESPECIAL
A6: 91407 | B6: LA PEDRERA | C6: AMAZONAS | D6: BOGOTA | E6: AEREO | F6: TIPO IV ESPECIAL
A7: 91001 | B7: LETICIA | C7: AMAZONAS | D7: BOGOTA | E7: AEREO | F7: TIPO IV ESPECIAL
A8: 91460 | B8: MIRITI - PARANA | C8: AMAZONAS | D8: BOGOTA | E8: AEREO | F8: TIPO IV ESPECIAL
A9: 91530 | B9: PUERTO ALEGRIA | C9: AMAZONAS | D9: BOGOTA | E9: AEREO | F9: TIPO IV ESPECIAL
A10: 91536 | B10: PUERTO ARICA | C10: AMAZONAS | D10: BOGOTA | E10: AEREO | F10: TIPO IV ESPECIAL
A11: 91540 | B11: PUERTO NARIÑO | C11: AMAZONAS | D11: BOGOTA | E11: AEREO | F11: TIPO IV ESPECIAL
A12: 91798 | B12: TARAPACA | C12: AMAZONAS | D12: BOGOTA | E12: AEREO | F12: TIPO IV ESPECIAL
A13: 5055 | B13: ARGELIA | C13: ANTIOQUIA | D13: MEDELLIN | E13: TERRESTRE | F13: TIPO IV
... A1124: 23682 | B1124: SAN JOSE DE URE | C1124: CORDOBA | D1124: MONTERIA | E1124: TERRESTRE | F1124: TIPO III

Sheet INCIDENTES
A1: CIUDAD SEDE | B1: COORDINADOR | C1: CENTRO DE COSTOS LÍNEACOM | D1: CÓDIGO DANE | E1: TA/CODIGO ACTIVIDAD | F1: CODIGO CB | G1: ACTIVIDAD | H1: DEPARTAMENTO | I1: CIUDAD | J1: NOMBRE DEL CB | K1: RED | L1: FO | M1: FECHA ASIGNACIÓN A LÍNEA COMUNICACIONES (DD/MM/AAAA HH:MM) | N1: FECHA CIERRE DEL TICKET (DD/MM/AAAA HH:MM) | O1: ACOMETIDA | P1: GRUPO_FALLA | Q1: CATEGORÍA | R1: FALLA | S1: FORMATO | T1: CADENA | U1: ESTADO | V1: OBSERVACION | W1: FORMA DE ATENCIÓN | X1: TERMINAL | Y1: TIPIFICACION | Z1: TIPO DE TRAYECTO | AA1: NOMBRE DEL TECNICO | AB1: DIAS DE VISITA | AC1: ACOMETIDA DATOS | AD1: ACOMETIDA ELÉCTRICA | AE1: SWITCH | AF1: VALOR DIAS ACTIVIDAD FACTURABLES | AG1: VALOR DIAS ACOMPAÑAMIENTO FACTURABLES
AF2: VALOR DIAS ACTIVIDAD FACTURABLES TC | AG2: VALOR DIAS ACOMPAÑAMIENTO FACTURABLES TC
A3: CIUDAD SEDE | B3: COORDINADOR | C3: CENTRO DE COSTOS LINEACOM | D3: CODIGO DANE | E3: TA/CODIGO ACTIVIDAD | F3: CODIGO CB | G3: ACTIVIDAD | H3: DEPARTAMENTO | I3: CIUDAD | J3: NOMBRE DEL CB | K3: RED | L3: FO | M3: FECHA ASIGNACION A LINEA COMUNICACIONES | N3: FECHA CIERRE DEL TICKET (DD/MM/AAAA HH:MM) | O3: ACOMETIDA DATOS | P3: GRUPO_FALLA | Q3: CATEGORIA | R3: FALLA | S3: FORMATO | T3: CADENA | U3: ESTADO | V3: OBSERVACIONES CLIENTE | W3: FORMA DE ATENCION | X3: TERMINAL(ES) | Y3: TIPIFICACION | Z3: TIPO DE TRAYECTO | AA3: NOMBRE DEL TECNICO | AB3: DIAS DE VISITA | AC3: ACOMETIDA DATOS | AD3: ACOMETIDA ELECTRICA | AE3: SWITCH | AF3: VALOR DIAS ACTIVIDAD FACTURABLES TE | AG3: VALOR DIAS ACOMPAÑAMIENTO FACTURABLES TE
A4: MEDELLIN | B4: =VLOOKUP(A4,'CENTRO DE COSTOS'!A:D,4,FALSE) -> JUAN SEBASTIÁN RÍOS CASTRILLÓN | C4: =VLOOKUP(A4,'CENTRO DE COSTOS'!A:D,2,FALSE) -> 0004-0005 | D4: 5001 | E4: 2538428 | F4: 75951 | G4: INCIDENTE | H4: ANTIOQUIA | I4: MEDELLIN | J4: BARRIO BELENCITO MEDELLIN | K4: REDEBAN | L4: FO-25-1315516 | M4: 45870.409 | N4: 45870.467 | O4: NO | P4: USUARIO | Q4: MANTENIMIENTO | R4: MANTENIMIENTO GENERAL | S4: CB UNO A UNO | T4: CB UNO A UNO | U4: CERRADO | V4: 01/08/2025 01-08 SE ESCALA PARA VISITA. LLAMAR ANTES DE VISITAR, CONFIRMAR FALLA Y DATOS | 01/08/2025 SE HACE MANTENIMIENTO DE EQUIPO | W4: VISITA_TÉCNICA | X4: FA09Z480 | Y4: TIPO I | Z4: TERRESTRE | AA4: MORENO MEDINA JUAN PABLO | AB4: 1 | AC4: 0 | AD4: 0 | AE4: 0 | AF4: =IF(W4="SOPORTE_TELEFÓNICO",'BASE LIQUIDACION'!$B$10,IF(Y4="TIPO I",'BASE LIQUIDACION'!$C$3,IF(Y4="TIPO II",'BASE LIQUIDACION'!$C$4,IF(Y4="TIPO III",'BASE LIQUIDACION'!$C$5,'BASE LIQUIDACION'!$C$7)))) -> 65960.474 | AG4: =IF(W4="SOPORTE_TELEFÓNICO",'BASE LIQUIDACION'!$B$10,(AB4*AF4+AC4*'BASE LIQUIDACION'!$B$12+AD4*'BASE LIQUIDACION'!$B$11+INCIDENTES!AE4*'BASE LIQUIDACION'!$B$13)) -> 65960.474
A5: BARRANQUILLA | B5: =VLOOKUP(A5,'CENTRO DE COSTOS'!A:D,4,FALSE) -> JOSE MAURICIO HERNANDEZ ROJAS | C5: =VLOOKUP(A5,'CENTRO DE COSTOS'!A:D,2,FALSE) -> 0004-0001 | D5: 8001 | E5: 2535994 | F5: 69017 | G5: INCIDENTE | H5: ATLANTICO | I5: BARRANQUILLA | J5: BARRIO VILLANUEVA BARRANQUILLA | K5: REDEBAN | L5: FO-25-1313938 | M5: 45870.333 | N5: 45870.494 | O5: NO | P5: USUARIO | Q5: COMUNICACION | R5: CANAL DEL COMERCIO | S5: CB UNO A UNO | T5: CB UNO A UNO | U5: CERRADO | V5: 01/08/2025 CLIENTE CAMBIO DE MODENS DE INTERNET Y TOCÓ CAMBIAR LAS IP DEL DATAFONO, SE HACEN HACEN PRUEBAS Y QUEDA OK | W5: VISITA_TÉCNICA | X5: 9T1ZZ282 | Y5: TIPO I | Z5: TERRESTRE | AA5: DE AVILA SIADES ALBERTO ENRIQUE | AB5: 1 | AC5: 0 | AD5: 0 | AE5: 0 | AF5: =IF(W5="SOPORTE_TELEFÓNICO",'BASE LIQUIDACION'!$B$10,IF(Y5="TIPO I",'BASE LIQUIDACION'!$C$3,IF(Y5="TIPO II",'BASE LIQUIDACION'!$C$4,IF(Y5="TIPO III",'BASE LIQUIDACION'!$C$5,'BASE LIQUIDACION'!$C$7)))) -> 65960.474 | AG5: =IF(W5="SOPORTE_TELEFÓNICO",'BASE LIQUIDACION'!$B$10,(AB5*AF5+AC5*'BASE LIQUIDACION'!$B$12+AD5*'BASE LIQUIDACION'!$B$11+INCIDENTES!AE5*'BASE LIQUIDACION'!$B$13)) -> 65960.474
A6: MEDELLIN | B6: =VLOOKUP(A6,'CENTRO DE COSTOS'!A:D,4,FALSE) -> JUAN SEBASTIÁN RÍOS CASTRILLÓN | C6: =VLOOKUP(A6,'CENTRO DE COSTOS'!A:D,2,FALSE) -> 0004-0005 | D6: 5607 | E6: 2523682 | F6: 31280 | G6: INCIDENTE | H6: ANTIOQUIA | I6: RETIRO | J6: BARRIO EL PINO | K6: REDEBAN | L6: FO-25-1303505 | M6: 45868.333 | N6: 45870.511 | O6: NO | P6: USUARIO | Q6: LECTOR DE TARJETAS | R6: OBSTRUCCION DEL LECTOR | S6: CB UNO A UNO | T6: CB UNO A UNO | U6: CERRADO | V6: 30/07/2025 30-07 SE ESCALA PARA VISITA. LLAMAR ANTES DE VISITAR, CONFIRMAR FALLA Y DATOS | 31/07/2025 COLABORADOR ASIGNADO PARA ACTIVIDAD PRESENTÓ NOVEDAD EN RIONEGRO Y NO PUDO DESPLAZARSE A REALIZAR INCIDENTE EN EL RETIRO. DEBIDO A DAÑO ESTRUCTURAL EN LA INSTALACIÓN QUE ESTABA REALIZANDO NO PUDO DESPLAZARSE A RETIRO. NO SE LOGRA ACTIVIDAD POR CAPACIDAD OPERATIVA. | 01/08/2025 SE REALIZA MANTENIMIENTO GENERAL AL EQUIPO, SE REALIZAN PRUEBAS PERTINENTES CON TARJETAS, TODO OK | W6: VISITA_TÉCNICA | X6: 9C001337 | Y6: TIPO II | Z6: TERRESTRE | AA6: HERNANDEZ CHAVARRIA JUAN CAMILO | AB6: 1 | AC6: 0 | AD6: 0 | AE6: 0 | AF6: =IF(W6="SOPORTE_TELEFÓNICO",'BASE LIQUIDACION'!$B$10,IF(Y6="TIPO I",'BASE LIQUIDACION'!$C$3,IF(Y6="TIPO II",'BASE LIQUIDACION'!$C$4,IF(Y6="TIPO III",'BASE LIQUIDACION'!$C$5,'BASE LIQUIDACION'!$C$7)))) -> 163813.56 | AG6: =IF(W6="SOPORTE_TELEFÓNICO",'BASE LIQUIDACION'!$B$10,(AB6*AF6+AC6*'BASE LIQUIDACION'!$B$12+AD6*'BASE LIQUIDACION'!$B$11+INCIDENTES!AE6*'BASE LIQUIDACION'!$B$13)) -> 163813.56
A7: BARRANQUILLA | B7: =VLOOKUP(A7,'CENTRO DE COSTOS'!A:D,4,FALSE) -> JOSE MAURICIO HERNANDEZ ROJAS | C7: =VLOOKUP(A7,'CENTRO DE COSTOS'!A:D,2,FALSE) -> 0004-0001 | D7: 8001 | E7: 2536376 | F7: 41635 | G7: INCIDENTE | H7: ATLANTICO | I7: BARRANQUILLA | J7: BARRIO 20 DE JULIO BARRANQUILL | K7: REDEBAN | L7: FO-25-1314593 | M7: 45870.333 | N7: 45870.553 | O7: NO | P7: ENTIDAD | Q7: ERROR DE TRANSACCIONES | R7: TRANSACCION NO PERMITIDA | S7: CB UNO A UNO | T7: CB UNO A UNO | U7: CERRADO | V7: 01/08/2025 01-08 SE ESCALA PARA VISITA. LLAMAR ANTES DE VISITAR, CONFIRMAR FALLA Y DATOS | 01/08/2025 CLIENTE MANIFESTÓ QUE EL DÍA DE AYER EN QUINCENA LE SALÍA EN MENSAJE RECHAZO GENERAL Y NO LE DEJABA HACER RETIROS CON TARJETAS, PERO HOY SE HACEN PRUEBAS Y ELLA CONFIRMA QUE HA ESTADO TRABAJANDO MUY BIEN EL DÍA DE HOY TAMBIÉN SE CAMBIA TAPA DE IMPRESIÓN DEL DATAFONO, ESTABA PARTIDA | W7: VISITA_TÉCNICA | X7: AB0WZ798 | Y7: TIPO I | Z7: TERRESTRE | AA7: DE AVILA SIADES ALBERTO ENRIQUE | AB7: 1 | AC7: 0 | AD7: 0 | AE7: 0 | AF7: =IF(W7="SOPORTE_TELEFÓNICO",'BASE LIQUIDACION'!$B$10,IF(Y7="TIPO I",'BASE LIQUIDACION'!$C$3,IF(Y7="TIPO II",'BASE LIQUIDACION'!$C$4,IF(Y7="TIPO III",'BASE LIQUIDACION'!$C$5,'BASE LIQUIDACION'!$C$7)))) -> 65960.474 | AG7: =IF(W7="SOPORTE_TELEFÓNICO",'BASE LIQUIDACION'!$B$10,(AB7*AF7+AC7*'BASE LIQUIDACION'!$B$12+AD7*'BASE LIQUIDACION'!$B$11+INCIDENTES!AE7*'BASE LIQUIDACION'!$B$13)) -> 65960.474
A8: BOGOTA | B8: =VLOOKUP(A8,'CENTRO DE COSTOS'!A:D,4,FALSE) -> WILLIAM ASDRUBAL ROZO ROZO | C8: =VLOOKUP(A8,'CENTRO DE COSTOS'!A:D,2,FALSE) -> 0004-0004 | D8: 11001 | E8: 2535930 | F8: 74491 | G8: INCIDENTE | H8: CUNDINAMARCA | I8: BOGOTA | J8: BARRIO CIUDAD GRANADA PATIO BO | K8: REDEBAN | L8: FO-25-1313760 | M8: 45869.71 | N8: 45870.556 | O8: NO | P8: ENTIDAD | Q8: ERROR DE TRANSACCIONES | R8: TRANSACCION NO PERMITIDA | S8: CB UNO A UNO | T8: CB UNO A UNO | U8: CERRADO | V8: 31/07/2025 31-07 SE ESCALA PARA VISITA. LLAMAR ANTES DE VISITAR, CONFIRMAR FALLA Y DATOS | 01/08/2025 SE REALIZA VISITA DE CAMPO DONDE CLIENTE MANIFIESTA QUE EL EQUIPO ESTÁ FUNCIONANDO CON NORMALIDAD, NO SE MANIPULA EQUIPOS, NO ESTÁ ENCARGADO. | W8: VISITA_TÉCNICA | X8: SVFZZ058 | Y8: TIPO I | Z8: TERRESTRE | AA8: LOZADA ROJAS CHRISTIAN ANDRES | AB8: 1 | AC8: 0 | AD8: 0 | AE8: 0 | AF8: =IF(W8="SOPORTE_TELEFÓNICO",'BASE LIQUIDACION'!$B$10,IF(Y8="TIPO I",'BASE LIQUIDACION'!$C$3,IF(Y8="TIPO II",'BASE LIQUIDACION'!$C$4,IF(Y8="TIPO III",'BASE LIQUIDACION'!$C$5,'BASE LIQUIDACION'!$C$7)))) -> 65960.474 | AG8: =IF(W8="SOPORTE_TELEFÓNICO",'BASE LIQUIDACION'!$B$10,(AB8*AF8+AC8*'BASE LIQUIDACION'!$B$12+AD8*'BASE LIQUIDACION'!$B$11+INCIDENTES!AE8*'BASE LIQUIDACION'!$B$13)) -> 65960.474
A9: BOGOTA | B9: =VLOOKUP(A9,'CENTRO DE COSTOS'!A:D,4,FALSE) -> WILLIAM ASDRUBAL ROZO ROZO | C9: =VLOOKUP(A9,'CENTRO DE COSTOS'!A:D,2,FALSE) -> 0004-0004 | D9: 25754 | E9: 2538319 | F9: 68735 | G9: INCIDENTE | H9: CUNDINAMARCA | I9: SOACHA | J9: LA FRAGUA 2 | K9: REDEBAN | L9: FO-25-1315428 | M9: 45870.406 | N9: 45870.578 | O9: NO | P9: USUARIO | Q9: COMUNICACION | R9: CONEXIONES DE COMERCIO | S9: CB UNO A UNO | T9: CB UNO A UNO | U9: CERRADO | V9: 01/08/2025 01-08 SE ESCALA PARA VISITA. LLAMAR ANTES DE VISITAR, CONFIRMAR FALLA Y DATOS | 01/08/2025 SE REALIZA VALIDACIÓN DE SERVICIO POR FALLA EN CONEXIÓN DE RED AL VALIDAR DE ENCUENTRA FALLA EN UN CABLE DEL CLIENTE QUE VIENE DESDE EL TERCER PISO HASTA EL PRIMER Y CONECTA UN SWITCH DONDE SE CONECTA EL DATAFONO SERVICIO OPERATIVO PRUEBAS OK TRNA RBM SE INDICA A CLIENTE CAMBIO DE ESTE | W9: VISITA_TÉCNICA | X9: 9L0UZ989 | Y9: TIPO I | Z9: TERRESTRE | AA9: BUSTOS MORA DIEGO MANUEL | AB9: 1 | AC9: 0 | AD9: 0 | AE9: 0 | AF9: =IF(W9="SOPORTE_TELEFÓNICO",'BASE LIQUIDACION'!$B$10,IF(Y9="TIPO I",'BASE LIQUIDACION'!$C$3,IF(Y9="TIPO II",'BASE LIQUIDACION'!$C$4,IF(Y9="TIPO III",'BASE LIQUIDACION'!$C$5,'BASE LIQUIDACION'!$C$7)))) -> 65960.474 | AG9: =IF(W9="SOPORTE_TELEFÓNICO",'BASE LIQUIDACION'!$B$10,(AB9*AF9+AC9*'BASE LIQUIDACION'!$B$12+AD9*'BASE LIQUIDACION'!$B$11+INCIDENTES!AE9*'BASE LIQUIDACION'!$B$13)) -> 65960.474
A10: TUNJA | B10: =VLOOKUP(A10,'CENTRO DE COSTOS'!A:D,4,FALSE) -> MIGUEL JULIÁN HERNÁNDEZ GUARÍN | C10: =VLOOKUP(A10,'CENTRO DE COSTOS'!A:D,2,FALSE) -> 0004-0008 | D10: 25745 | E10: 2533523 | F10: 35747 | G10: INCIDENTE | H10: CUNDINAMARCA | I10: SIMIJACA | J10: BARRIO CENTRO SIMIJACA | K10: REDEBAN | L10: FO-25-1311547 | M10: 45869.494 | N10: 45870.674 | O10: NO | P10: USUARIO | Q10: COMUNICACION | R10: CANAL DEL COMERCIO | S10: CB UNO A UNO | T10: CB UNO A UNO | U10: CERRADO | V10: 31/07/2025 31-07 SE INTENTA COMUNICACION CON EL SEÑOR JAVIER FUQENE AL NUMERO 3003711599, PERO NO CONTESTA LA LLAMADA. SE ESCALA PARA VISITA, CONFIRMAR FALLA Y DATOS | 01/08/2025 SE LLEGA MUNICIPIO DE SIMIJACA , SE LLEGA A REFERENCIA DE DIRECCIÓN AL PARECER ERRRADA COMERCIO NO EXISTE , SE INTENTA COMUNICACIÓN CON EL SEÑOR JAVIER AL NUMERO CELULAR 3003711599 PARA CONFIRMAR DIRECCIÓN Y NO ES POSIBLE , BUZON DE VOZ , SE DEJA MENSAJE VÍA WHATSAPP Y TAMPOCO HAY RESPUESTA , SE SEGUIRA REALIZANDO GESTIÓN | 01/08/2025 SE LOGRA COMUNICACIÓN CON EL CLIENTE AL NÚMERO CELULAR 3003711599 SEÑOR JAVIER FUQUENE, EL CUAL SEÑOR JAVIER INDICA QUE NO REQUIERE VISITA YA QUE EL CORRESPONSAL ESTA TRABAJANDO CORRECTAMENTE Y ENVIA BAUCHE TRX DE PRUEBA , ADEMAS TAMBIEN INDICA QUE VA A REALIZAR PROCESO DE ACTUALIZACIÓN DE DIRECCIÓN , SE CIERRA ORDEN , CORRESPONSAL OPERATIVO | W10: SOPORTE_TELEFÓNICO | X10: 0 | Y10: TIPO III | Z10: TERRESTRE | AA10: ALVARADO MORENO CRISTHIAN | AB10: 0 | AC10: 0 | AD10: 0 | AE10: 0 | AF10: =IF(W10="SOPORTE_TELEFÓNICO",'BASE LIQUIDACION'!$B$10,IF(Y10="TIPO I",'BASE LIQUIDACION'!$C$3,IF(Y10="TIPO II",'BASE LIQUIDACION'!$C$4,IF(Y10="TIPO III",'BASE LIQUIDACION'!$C$5,'BASE LIQUIDACION'!$C$7)))) -> 37904.654 | AG10: =IF(W10="SOPORTE_TELEFÓNICO",'BASE LIQUIDACION'!$B$10,(AB10*AF10+AC10*'BASE LIQUIDACION'!$B$12+AD10*'BASE LIQUIDACION'!$B$11+INCIDENTES!AE10*'BASE LIQUIDACION'!$B$13)) -> 37904.654
A11: CUCUTA | B11: =VLOOKUP(A11,'CENTRO DE COSTOS'!A:D,4,FALSE) -> MIGUEL JULIÁN HERNÁNDEZ GUARÍN | C11: =VLOOKUP(A11,'CENTRO DE COSTOS'!A:D,2,FALSE) -> 0004-0008 | D11: 54660 | E11: 2536062 | F11: 79219 | G11: INCIDENTE | H11: NORTE DE SANTANDER | I11: SALAZAR | J11: BARRIO PUENTE FORTUL SALAZAR | K11: REDEBAN | L11: FO-25-1313903 | M11: 45869.728 | N11: 45870.679 | O11: NO | P11: USUARIO | Q11: MANTENIMIENTO | R11: MANTENIMIENTO GENERAL | S11: CB UNO A UNO | T11: CB UNO A UNO | U11: CERRADO | V11: 01/08/2025 SE REALIZA VISITA, SE REALIZA MANTENIMIENTO, SE REALIZAN PRUEBAS Y CIERRES OK. | W11: VISITA_TÉCNICA | X11: A4WZZ096 | Y11: TIPO II | Z11: TERRESTRE | AA11: PACHECO BUITRAGO JAVIER ALONSO | AB11: 1 | AC11: 0 | AD11: 0 | AE11: 0 | AF11: =IF(W11="SOPORTE_TELEFÓNICO",'BASE LIQUIDACION'!$B$10,IF(Y11="TIPO I",'BASE LIQUIDACION'!$C$3,IF(Y11="TIPO II",'BASE LIQUIDACION'!$C$4,IF(Y11="TIPO III",'BASE LIQUIDACION'!$C$5,'BASE LIQUIDACION'!$C$7)))) -> 163813.56 | AG11: =IF(W11="SOPORTE_TELEFÓNICO",'BASE LIQUIDACION'!$B$10,(AB11*AF11+AC11*'BASE LIQUIDACION'!$B$12+AD11*'BASE LIQUIDACION'!$B$11+INCIDENTES!AE11*'BASE LIQUIDACION'!$B$13)) -> 163813.56
A12: VILLAVICENCIO | B12: =VLOOKUP(A12,'CENTRO DE COSTOS'!A:D,4,FALSE) -> KEVIN ALEXIS CORZO BUSTOS | C12: =VLOOKUP(A12,'CENTRO DE COSTOS'!A:D,2,FALSE) -> 0004-0007 | D12: 50150 | E12: 2531509 | F12: 72286 | G12: INCIDENTE | H12: META | I12: CASTILLA LA NUEVA | J12: CASTILLA LA NUEVA META 2 | K12: REDEBAN | L12: FO-25-1310125 | M12: 45869.386 | N12: 45871.364 | O12: NO | P12: USUARIO | Q12: COMUNICACION | R12: CANAL DEL COMERCIO | S12: CB UNO A UNO | T12: CB UNO A UNO | U12: CERRADO | V12: 31/07/2025 31-07 SE ESCALA PARA VISITA. LLAMAR ANTES DE VISITAR, CONFIRMAR FALLA Y DATOS | 01/08/2025 SE CONTACTA A LA SEÑORA EDIT ROZÓ E INFORMA QUE EL DATAFONO SE ENCUENTRA FUNCIONANDO CORRECTAMENTE SIN NOVEDAD | W12: SOPORTE_TELEFÓNICO | X12: 0 | Y12: TIPO II | Z12: TERRESTRE | AA12: ROZO JIMENEZ EDGAR ARMANDO | AB12: 0 | AC12: 0 | AD12: 0 | AE12: 0 | AF12: =IF(W12="SOPORTE_TELEFÓNICO",'BASE LIQUIDACION'!$B$10,IF(Y12="TIPO I",'BASE LIQUIDACION'!$C$3,IF(Y12="TIPO II",'BASE LIQUIDACION'!$C$4,IF(Y12="TIPO III",'BASE LIQUIDACION'!$C$5,'BASE LIQUIDACION'!$C$7)))) -> 37904.654 | AG12: =IF(W12="SOPORTE_TELEFÓNICO",'BASE LIQUIDACION'!$B$10,(AB12*AF12+AC12*'BASE LIQUIDACION'!$B$12+AD12*'BASE LIQUIDACION'!$B$11+INCIDENTES!AE12*'BASE LIQUIDACION'!$B$13)) -> 37904.654
A13: VALLEDUPAR | B13: =VLOOKUP(A13,'CENTRO DE COSTOS'!A:D,4,FALSE) -> JOSE MAURICIO HERNANDEZ ROJAS | C13: =VLOOKUP(A13,'CENTRO DE COSTOS'!A:D,2,FALSE) -> 0004-0001 | D13: 13042 | E13: 2522948 | F13: 47919 | G13: INCIDENTE | H13: BOLIVAR | I13: ARENAL | J13: DISTRICOL COOPERATIVA DE TRANS | K13: REDEBAN | L13: FO-25-1302300 | M13: 45867.681 | N13: 45871.442 | O13: NO | P13: USUARIO | Q13: MANTENIMIENTO | R13: MANTENIMIENTO GENERAL | S13: AGREGADOR | T13: AGREGADOR | U13: CERRADO | V13: 29/07/2025 29-07 EN COMUNICACION CON LA SEÑORA YOLEINE VILLEGAS AL NUMERO 3186434644, CONFIRMA FALLA, DATOS CORRECTOS. SE ESCALA PARA VISITA | 02/08/2025 SE REALIZA GESTIÓN VIA WSP AL NÚMERO 3186434644 ATENDIENDO LA SRA YOLEINE VILLEGAS HERNÁNDEZ INDICÁNDONOS QUE ESTE SABADO NO ATIENDE YA QUE ELLA SE ENCUENTRA ESTUDIADO LOS DIAS SABADOS POR TAL MOTIVÓ NO OUEDE RECIBIR VISITA TÉCNICA,SE LE INDICA QUE DEBE SOLICITAR NUEVAMENTE LA VISITA TÉCNICA | W13: SOPORTE_TELEFÓNICO | X13: 0 | Y13: TIPO IV | Z13: TERRESTRE | AA13: MAESTRE MENGUAL EDGAR ENRIQUE | AB13: 0 | AC13: 0 | AD13: 0 | AE13: 0 | AF13: =IF(W13="SOPORTE_TELEFÓNICO",'BASE LIQUIDACION'!$B$10,IF(Y13="TIPO I",'BASE LIQUIDACION'!$C$3,IF(Y13="TIPO II",'BASE LIQUIDACION'!$C$4,IF(Y13="TIPO III",'BASE LIQUIDACION'!$C$5,'BASE LIQUIDACION'!$C$7)))) -> 37904.654 | AG13: =IF(W13="SOPORTE_TELEFÓNICO",'BASE LIQUIDACION'!$B$10,(AB13*AF13+AC13*'BASE LIQUIDACION'!$B$12+AD13*'BASE LIQUIDACION'!$B$11+INCIDENTES!AE13*'BASE LIQUIDACION'!$B$13)) -> 37904.654
A14: BOGOTA | B14: =VLOOKUP(A14,'CENTRO DE COSTOS'!A:D,4,FALSE) -> WILLIAM ASDRUBAL ROZO ROZO | C14: =VLOOKUP(A14,'CENTRO DE COSTOS'!A:D,2,FALSE) -> 0004-0004 | D14: 25572 | E14: 2524688 | F14: 32406 | G14: INCIDENTE | H14: CUNDINAMARCA | I14: PUERTO SALGAR | J14: BARRIO PUERTO LIBRE PUERTO SAL | K14: REDEBAN | L14: FO-25-1303854 | M14: 45868.363 | N14: 45871.46 | O14: NO | P14: USUARIO | Q14: COMUNICACION | R14: CONEXIONES DE COMERCIO | S14: CB UNO A UNO | T14: CB UNO A UNO | U14: CERRADO | V14: 30/07/2025 30-07 SE INTENTA COMUNICACION CON EL SEÑOR JULIAN ANDRES GUZMAN AL NUMERO 3505888942, PERO NO CONTESTA LA LLAMADA. SE ESCALA PARA VISITA, CONFIRMAR FALLA Y DATOS | 01/08/2025 SE VISITA COMERCIO POR FALLAS EN CONEXIÓN DE INTERNET AL LLEGAR AL PUNTO SE EVIDENCIA ERROR EN CONEXIONES DEL CABLE DE RED SE PROCEDE A MODIFICAR CONEXIONES EN LA SEITCH REALIZANDO PRUEBAS DE COMUNICACIÓN OK , SE REALIZAN TRANSACCIONES DE PRUEBA OK Y SE DEJA CB OPERANDO SIN NOVEDAD | W14: VISITA_TÉCNICA | X14: AA000284 | Y14: TIPO IV | Z14: TERRESTRE | AA14: ROMERO ROJAS BREIDY JHOHAN | AB14: 1 | AC14: 0 | AD14: 0 | AE14: 0 | AF14: =IF(W14="SOPORTE_TELEFÓNICO",'BASE LIQUIDACION'!$B$10,IF(Y14="TIPO I",'BASE LIQUIDACION'!$C$3,IF(Y14="TIPO II",'BASE LIQUIDACION'!$C$4,IF(Y14="TIPO III",'BASE LIQUIDACION'!$C$5,'BASE LIQUIDACION'!$C$7)))) -> 479589.74 | AG14: =IF(W14="SOPORTE_TELEFÓNICO",'BASE LIQUIDACION'!$B$10,(AB14*AF14+AC14*'BASE LIQUIDACION'!$B$12+AD14*'BASE LIQUIDACION'!$B$11+INCIDENTES!AE14*'BASE LIQUIDACION'!$B$13)) -> 479589.74
A15: PEREIRA | B15: =VLOOKUP(A15,'CENTRO DE COSTOS'!A:D,4,FALSE) -> DIEGO FERNANDO HENAO CARDONA | C15: =VLOOKUP(A15,'CENTRO DE COSTOS'!A:D,2,FALSE) -> 0004-0002 | D15: 66001 | E15: 2542562 | F15: 79900 | G15: INCIDENTE | H15: RISARALDA | I15: PEREIRA | J15: DISTRICOL PERLA HORIZONTE | K15: REDEBAN | L15: FO-25-1319510 | M15: 45871.333 | N15: 45871.524 | O15: NO | P15: USUARIO | Q15: MANTENIMIENTO | R15: MANTENIMIENTO GENERAL | S15: AGREGADOR | T15: AGREGADOR | U15: CERRADO | V15: 02/08/2025 01-08 SE ESCALA PARA VISITA. LLAMAR ANTES DE VISITAR, CONFIRMAR FALLA Y DATOS | 02/08/2025 EL CLIENTE INDICA QUE EL EQUIPO YA ESTÁ FUNCIONANDO CORRECTAMENTE, SE REALIZAN PRUEBAS OK. | W15: VISITA_TÉCNICA | X15: SAUZZ966 | Y15: TIPO I | Z15: TERRESTRE | AA15: FRANCO CAÑAVERAL YAMID RAUL | AB15: 1 | AC15: 0 | AD15: 0 | AE15: 0 | AF15: =IF(W15="SOPORTE_TELEFÓNICO",'BASE LIQUIDACION'!$B$10,IF(Y15="TIPO I",'BASE LIQUIDACION'!$C$3,IF(Y15="TIPO II",'BASE LIQUIDACION'!$C$4,IF(Y15="TIPO III",'BASE LIQUIDACION'!$C$5,'BASE LIQUIDACION'!$C$7)))) -> 65960.474 | AG15: =IF(W15="SOPORTE_TELEFÓNICO",'BASE LIQUIDACION'!$B$10,(AB15*AF15+AC15*'BASE LIQUIDACION'!$B$12+AD15*'BASE LIQUIDACION'!$B$11+INCIDENTES!AE15*'BASE LIQUIDACION'!$B$13)) -> 65960.474
A16: NEIVA | B16: =VLOOKUP(A16,'CENTRO DE COSTOS'!A:D,4,FALSE) -> KEVIN ALEXIS CORZO BUSTOS | C16: =VLOOKUP(A16,'CENTRO DE COSTOS'!A:D,2,FALSE) -> 0004-0007 | D16: 73483 | E16: 2542477 | F16: 70322 | G16: INCIDENTE | H16: TOLIMA | I16: NATAGAIMA | J16: BARRIO RICAURTE NATAGAIMA | K16: REDEBAN | L16: FO-25-1318728 | M16: 45870.743 | N16: 45871.533 | O16: NO | P16: USUARIO | Q16: USUARIOS | R16: USUARIOS BLOQUEADOS | S16: CB UNO A UNO | T16: CB UNO A UNO | U16: CERRADO | V16: 01/08/2025 01-08 SE ESCALA PARA VISITA. LLAMAR ANTES DE VISITAR, CONFIRMAR FALLA Y DATOS | 02/08/2025 EN COMUNICACIÓN CON LA SEÑORA YOLANDA SE LE INDICA COMO RESTABLECER USUARIO Y CLAVE, SE RESTAURA Y PRUEBAS EXITOSAS. | W16: SOPORTE_TELEFÓNICO | X16: 0 | Y16: TIPO II | Z16: TERRESTRE | AA16: CORZO BUSTO KEVIN ALEXIS | AB16: 0 | AC16: 0 | AD16: 0 | AE16: 0 | AF16: =IF(W16="SOPORTE_TELEFÓNICO",'BASE LIQUIDACION'!$B$10,IF(Y16="TIPO I",'BASE LIQUIDACION'!$C$3,IF(Y16="TIPO II",'BASE LIQUIDACION'!$C$4,IF(Y16="TIPO III",'BASE LIQUIDACION'!$C$5,'BASE LIQUIDACION'!$C$7)))) -> 37904.654 | AG16: =IF(W16="SOPORTE_TELEFÓNICO",'BASE LIQUIDACION'!$B$10,(AB16*AF16+AC16*'BASE LIQUIDACION'!$B$12+AD16*'BASE LIQUIDACION'!$B$11+INCIDENTES!AE16*'BASE LIQUIDACION'!$B$13)) -> 37904.654
A17: MEDELLIN | B17: =VLOOKUP(A17,'CENTRO DE COSTOS'!A:D,4,FALSE) -> JUAN SEBASTIÁN RÍOS CASTRILLÓN | C17: =VLOOKUP(A17,'CENTRO DE COSTOS'!A:D,2,FALSE) -> 0004-0005 | D17: 5615 | E17: 2540012 | F17: 76768 | G17: INCIDENTE | H17: ANTIOQUIA | I17: RIONEGRO | J17: BARRIO QUEBRADA ARRIBA RIONEGR | K17: REDEBAN | L17: FO-25-1316734 | M17: 45870.498 | N17: 45871.539 | O17: NO | P17: USUARIO | Q17: COMUNICACION | R17: CONEXIONES DE COMERCIO | S17: CB UNO A UNO | T17: CB UNO A UNO | U17: CERRADO | V17: 01/08/2025 01-08 SE ESCALA PARA VISITA. LLAMAR ANTES DE VISITAR, CONFIRMAR FALLA Y DATOS | 02/08/2025 CLIENTE COMUNICA QUE ESTA TRABAJANDO SI PROBLEMAS, CONFIRMA QUE NO ES NECESARIA LA VISITA | W17: SOPORTE_TELEFÓNICO | X17: 0 | Y17: TIPO II | Z17: TERRESTRE | AA17: HERNANDEZ CHAVARRIA JUAN CAMILO | AB17: 0 | AC17: 0 | AD17: 0 | AE17: 0 | AF17: =IF(W17="SOPORTE_TELEFÓNICO",'BASE LIQUIDACION'!$B$10,IF(Y17="TIPO I",'BASE LIQUIDACION'!$C$3,IF(Y17="TIPO II",'BASE LIQUIDACION'!$C$4,IF(Y17="TIPO III",'BASE LIQUIDACION'!$C$5,'BASE LIQUIDACION'!$C$7)))) -> 37904.654 | AG17: =IF(W17="SOPORTE_TELEFÓNICO",'BASE LIQUIDACION'!$B$10,(AB17*AF17+AC17*'BASE LIQUIDACION'!$B$12+AD17*'BASE LIQUIDACION'!$B$11+INCIDENTES!AE17*'BASE LIQUIDACION'!$B$13)) -> 37904.654
A18: PEREIRA | B18: =VLOOKUP(A18,'CENTRO DE COSTOS'!A:D,4,FALSE) -> DIEGO FERNANDO HENAO CARDONA | C18: =VLOOKUP(A18,'CENTRO DE COSTOS'!A:D,2,FALSE) -> 0004-0002 | D18: 63001 | E18: 2543563 | F18: 25343 | G18: INCIDENTE | H18: QUINDIO | I18: ARMENIA | J18: ARA0086 CASA FOGATA | K18: REDEBAN | L18: FO-25-1321018 | M18: 45871.5 | N18: 45872.415 | O18: NO | P18: USUARIO | Q18: MANTENIMIENTO | R18: MANTENIMIENTO GENERAL | S18: RETAIL | T18: RETAIL | U18: CERRADO | V18: 02/08/2025 01-08 SE ESCALA PARA VISITA. LLAMAR ANTES DE VISITAR, CONFIRMAR FALLA Y DATOS | 03/08/2025 03-08 SE ESCALA A LA RED, SE PROCEDE A CERRAR YA QUE NO ATENDEMOS CADENA ARA - 04-08 TU SOLICITUD REFERENTE A GENERACIÓN DE CASOS CB ARA BANCOLOMBIA QUEDÓ RADICADA BAJO EL TICKET NÚMERO XXXXXXX AL ÁREA ENCARGADA. | W18: SOPORTE_TELEFÓNICO | X18: 0 | Y18: TIPO II | Z18: TERRESTRE | AA18: AYALA ROMERO MAYKOL DANILO | AB18: 0 | AC18: 0 | AD18: 0 | AE18: 0 | AF18: =IF(W18="SOPORTE_TELEFÓNICO",'BASE LIQUIDACION'!$B$10,IF(Y18="TIPO I",'BASE LIQUIDACION'!$C$3,IF(Y18="TIPO II",'BASE LIQUIDACION'!$C$4,IF(Y18="TIPO III",'BASE LIQUIDACION'!$C$5,'BASE LIQUIDACION'!$C$7)))) -> 37904.654 | AG18: =IF(W18="SOPORTE_TELEFÓNICO",'BASE LIQUIDACION'!$B$10,(AB18*AF18+AC18*'BASE LIQUIDACION'!$B$12+AD18*'BASE LIQUIDACION'!$B$11+INCIDENTES!AE18*'BASE LIQUIDACION'!$B$13)) -> 37904.654
A19: VALLEDUPAR | B19: =VLOOKUP(A19,'CENTRO DE COSTOS'!A:D,4,FALSE) -> JOSE MAURICIO HERNANDEZ ROJAS | C19: =VLOOKUP(A19,'CENTRO DE COSTOS'!A:D,2,FALSE) -> 0004-0001 | D19: 20001 | E19: 2544453 | F19: 77497 | G19: INCIDENTE | H19: CESAR | I19: VALLEDUPAR | J19: BARRIO BELLO HORIZONTE VALLLED | K19: REDEBAN | L19: FO-25-1322842 | M19: 45872.48 | N19: 45873.387 | O19: NO | P19: USUARIO | Q19: COMUNICACION | R19: CONEXIONES DE COMERCIO | S19: CB UNO A UNO | T19: CB UNO A UNO | U19: CERRADO | V19: 03/08/2025 03-08 SE ESCALA PARA VISITA. LLAMAR ANTES DE VISITAR, CONFIRMAR FALLA Y DATOS | 04/08/2025 SE LLEGA A CB POR SOLICITUD DE CLIENTE LA CUAL MANIFIESTA QUE LE APARECE RECHAZO GENERAL EN TODAS LAS TX , SE LLEGA A SITIO SE VALIDAN CONEXIONES Y CONFIGURADO DE EQUIPO DEJANDOLO OK ,SE REALIZAN PRUEBAS Y EQUIPO SE ENCUENTRA FUNCIONANDO AL 100% | W19: VISITA_TÉCNICA | X19: A4IZZ040 | Y19: TIPO I | Z19: TERRESTRE | AA19: MAESTRE MENGUAL EDGAR ENRIQUE | AB19: 1 | AC19: 0 | AD19: 0 | AE19: 0 | AF19: =IF(W19="SOPORTE_TELEFÓNICO",'BASE LIQUIDACION'!$B$10,IF(Y19="TIPO I",'BASE LIQUIDACION'!$C$3,IF(Y19="TIPO II",'BASE LIQUIDACION'!$C$4,IF(Y19="TIPO III",'BASE LIQUIDACION'!$C$5,'BASE LIQUIDACION'!$C$7)))) -> 65960.474 | AG19: =IF(W19="SOPORTE_TELEFÓNICO",'BASE LIQUIDACION'!$B$10,(AB19*AF19+AC19*'BASE LIQUIDACION'!$B$12+AD19*'BASE LIQUIDACION'!$B$11+INCIDENTES!AE19*'BASE LIQUIDACION'!$B$13)) -> 65960.474
A20: PASTO | B20: =VLOOKUP(A20,'CENTRO DE COSTOS'!A:D,4,FALSE) -> DIEGO FERNANDO HENAO CARDONA | C20: =VLOOKUP(A20,'CENTRO DE COSTOS'!A:D,2,FALSE) -> 0004-0003 | D20: 52399 | E20: 2539138 | F20: 30931 | G20: INCIDENTE | H20: NARIÑO | I20: LA UNION | J20: BARRIO EDUARDO SANTOS | K20: REDEBAN | L20: FO-25-1315993 | M20: 45870.449 | N20: 45873.412 | O20: NO | P20: USUARIO | Q20: COMUNICACION | R20: CANAL DEL COMERCIO | S20: CB UNO A UNO | T20: CB UNO A UNO | U20: CERRADO | V20: 01/08/2025 01-08 EN COMUNICACION CON LA SEÑORA FABIOLA GAMBOA AL NUMERO 3116420599, CONFIRMA FALLA, DATOS CORRECTOS. SE ESCALA PARA VISITA | 04/08/2025 SE REALIZÓ COMUNICACIÓN TELEFÓNICA CON LA USUARIA EL DIA DE HOY Y MANIFESTÓ QUE EL SERVICIO YA SE ENCUENTRA OPERATIVO Y FUNCIONANDO, SOLO FUE UNA CAIDA DEL SERVICIO DE INTERNET EN EL CB, YA SE ENCUENTRA OPERATIVO | W20: SOPORTE_TELEFÓNICO | X20: 0 | Y20: valo | Z20: TERRESTRE | AA20: GUERRERO RAMIREZ OSCAR DARIO | AB20: 0 | AC20: 0 | AD20: 0 | AE20: 0 | AF20: =IF(W20="SOPORTE_TELEFÓNICO",'BASE LIQUIDACION'!$B$10,IF(Y20="TIPO I",'BASE LIQUIDACION'!$C$3,IF(Y20="TIPO II",'BASE LIQUIDACION'!$C$4,IF(Y20="TIPO III",'BASE LIQUIDACION'!$C$5,'BASE LIQUIDACION'!$C$7)))) -> 37904.654 | AG20: =IF(W20="SOPORTE_TELEFÓNICO",'BASE LIQUIDACION'!$B$10,(AB20*AF20+AC20*'BASE LIQUIDACION'!$B$12+AD20*'BASE LIQUIDACION'!$B$11+INCIDENTES!AE20*'BASE LIQUIDACION'!$B$13)) -> 37904.654
A21: BARRANQUILLA | B21: =VLOOKUP(A21,'CENTRO DE COSTOS'!A:D,4,FALSE) -> JOSE MAURICIO HERNANDEZ ROJAS | C21: =VLOOKUP(A21,'CENTRO DE COSTOS'!A:D,2,FALSE) -> 0004-0001 | D21: 8001 | E21: 2544379 | F21: 51072 | G21: INCIDENTE | H21: ATLANTICO | I21: BARRANQUILLA | J21: BARRIO LAS NIEVES BARRANQUILLA | K21: REDEBAN | L21: FO-25-1323061 | M21: 45872.567 | N21: 45873.431 | O21: NO | P21: USUARIO | Q21: USUARIOS | R21: USUARIOS BLOQUEADOS | S21: CB UNO A UNO | T21: CB UNO A UNO | U21: CERRADO | V21: 03/08/2025 03-08 SE ESCALA PARA VISITA. LLAMAR ANTES DE VISITAR, CONFIRMAR FALLA Y DATOS | 04/08/2025 SE REALIZA VISITA TÉCNICA, SE EVIDENCIA QUE EL CLIENTE NO PODÍA HACER EL CIERRE POR QUÉ LE SALÍA CLAVE INCORRECTA, SÉ CONFIGURA LA CLAVE DE SUPERVISOR SE REALIZA EL CIERRE Y EQUIPO QUEDA FUNCIONANDO CORRECTAMENTE. | W21: VISITA_TÉCNICA | X21: BA02Z982 | Y21: TIPO I | Z21: TERRESTRE | AA21: DE AGUAS MUÑOZ DAVID JOSE | AB21: 1 | AC21: 0 | AD21: 0 | AE21: 0 | AF21: =IF(W21="SOPORTE_TELEFÓNICO",'BASE LIQUIDACION'!$B$10,IF(Y21="TIPO I",'BASE LIQUIDACION'!$C$3,IF(Y21="TIPO II",'BASE LIQUIDACION'!$C$4,IF(Y21="TIPO III",'BASE LIQUIDACION'!$C$5,'BASE LIQUIDACION'!$C$7)))) -> 65960.474 | AG21: =IF(W21="SOPORTE_TELEFÓNICO",'BASE LIQUIDACION'!$B$10,(AB21*AF21+AC21*'BASE LIQUIDACION'!$B$12+AD21*'BASE LIQUIDACION'!$B$11+INCIDENTES!AE21*'BASE LIQUIDACION'!$B$13)) -> 65960.474
A22: MEDELLIN | B22: =VLOOKUP(A22,'CENTRO DE COSTOS'!A:D,4,FALSE) -> JUAN SEBASTIÁN RÍOS CASTRILLÓN | C22: =VLOOKUP(A22,'CENTRO DE COSTOS'!A:D,2,FALSE) -> 0004-0005 | D22: 5001 | E22: 2546162 | F22: 23781 | G22: INCIDENTE | H22: ANTIOQUIA | I22: MEDELLIN | J22: BARRIO MANRIQUE GUADALUPE MEDE | K22: REDEBAN | L22: FO-25-1324567 | M22: 45873.382 | N22: 45873.528 | O22: NO | P22: USUARIO | Q22: MANTENIMIENTO | R22: MANTENIMIENTO GENERAL | S22: CB UNO A UNO | T22: CB UNO A UNO | U22: CERRADO | V22: 04/08/2025 04-08 SE ESCALA PARA VISITA. LLAMAR ANTES DE VISITAR, CONFIRMAR FALLA Y DATOS | 04/08/2025 SE HACE MANTENIMIENTO OK SE LE EXPLICA AL CLIENTE QUE LA TÉCNICA 2600 TIENE LAS TECLAS MÁS DURAS Y QUE LA BANDA YA NO ESTÁ EN EL LATERAL SI NO EN LA PARTE INFERIOR | W22: VISITA_TÉCNICA | X22: ABC0L387 | Y22: TIPO I | Z22: TERRESTRE | AA22: DIAZ ZABALA FRANCIS DUBAN | AB22: 1 | AC22: 0 | AD22: 0 | AE22: 0 | AF22: =IF(W22="SOPORTE_TELEFÓNICO",'BASE LIQUIDACION'!$B$10,IF(Y22="TIPO I",'BASE LIQUIDACION'!$C$3,IF(Y22="TIPO II",'BASE LIQUIDACION'!$C$4,IF(Y22="TIPO III",'BASE LIQUIDACION'!$C$5,'BASE LIQUIDACION'!$C$7)))) -> 65960.474 | AG22: =IF(W22="SOPORTE_TELEFÓNICO",'BASE LIQUIDACION'!$B$10,(AB22*AF22+AC22*'BASE LIQUIDACION'!$B$12+AD22*'BASE LIQUIDACION'!$B$11+INCIDENTES!AE22*'BASE LIQUIDACION'!$B$13)) -> 65960.474
A23: CALI | B23: =VLOOKUP(A23,'CENTRO DE COSTOS'!A:D,4,FALSE) -> DIEGO FERNANDO HENAO CARDONA | C23: =VLOOKUP(A23,'CENTRO DE COSTOS'!A:D,2,FALSE) -> 0004-0003 | D23: 76001 | E23: 2543683 | F23: 73907 | G23: INCIDENTE | H23: VALLE DEL CAUCA | I23: CALI | J23: REVAL JARDÍN PLAZA II | K23: REDEBAN | L23: FO-25-1321113 | M23: 45871.526 | N23: 45873.585 | O23: NO | P23: USUARIO | Q23: CIERRE | R23: COMERCIO NO REALIZA CIERRE | S23: ROBUSTO | T23: ROBUSTO | U23: CERRADO | V23: 02/08/2025 SE DEBE PROGRAMAR VISITA PARA EL DIA LUNES CLIENTE SOLO LABORA HASTA LA 1 PM | 04/08/2025 SE REALIZA CONFIGURACIÓN DE CLAVE DE SUPERVISOR A 1526 DEBIDO A QUE POR ERROR SE CAMBIÓ | W23: VISITA_TÉCNICA | X23: ON0IZ819 | Y23: TIPO I | Z23: TERRESTRE | AA23: MONTERO MUESES GIAN CARLO | AB23: 1 | AC23: 0 | AD23: 0 | AE23: 0 | AF23: =IF(W23="SOPORTE_TELEFÓNICO",'BASE LIQUIDACION'!$B$10,IF(Y23="TIPO I",'BASE LIQUIDACION'!$C$3,IF(Y23="TIPO II",'BASE LIQUIDACION'!$C$4,IF(Y23="TIPO III",'BASE LIQUIDACION'!$C$5,'BASE LIQUIDACION'!$C$7)))) -> 65960.474 | AG23: =IF(W23="SOPORTE_TELEFÓNICO",'BASE LIQUIDACION'!$B$10,(AB23*AF23+AC23*'BASE LIQUIDACION'!$B$12+AD23*'BASE LIQUIDACION'!$B$11+INCIDENTES!AE23*'BASE LIQUIDACION'!$B$13)) -> 65960.474
A24: VALLEDUPAR | B24: =VLOOKUP(A24,'CENTRO DE COSTOS'!A:D,4,FALSE) -> JOSE MAURICIO HERNANDEZ ROJAS | C24: =VLOOKUP(A24,'CENTRO DE COSTOS'!A:D,2,FALSE) -> 0004-0001 | D24: 20011 | E24: 2547762 | F24: 48994 | G24: INCIDENTE | H24: CESAR | I24: AGUACHICA | J24: DISTRICOL EDS NEW NOREAN | K24: REDEBAN | L24: FO-25-1325749 | M24: 45873.444 | N24: 45873.62 | O24: NO | P24: USUARIO | Q24: COMUNICACION | R24: CONEXIONES DE COMERCIO | S24: AGREGADOR | T24: AGREGADOR | U24: CERRADO | V24: 04/08/2025 04-08 EN COMUNICACION CON LA SEÑORA YANDRY ORTIZ AL NÚMERO 3233950896 INDICA QUE EL DATAFONO LE ARROJA ERROR DE CONEXIÓN, EL INTERNET FUNCIONA BIEN EN OTROS DISPOSITIVOS, CONFIRMA DATOS, SE ESCALA PARA VISITA | 04/08/2025 SE LLEGA A SITIO Y SE OBSERVA QUE EL DATAFONO NO TIENE CONEXIÓN A INTERNET, SE REALIZAN PRUEBAS Y SE EVIDENCIA QUE EL SISTEMA DE INTERNET DEL LUGAR ESTA CAIDO Y NO PERMITE NAVEGACION, SE HACE PRUEBA CON UN CABLE DE RED POR MEDIO DE LOS DATOS DEL TELÉFONO Y TODO FUNCIONA CON NORMALIDAD, SE LE INDICA AL CLIENTE QUE SE COMUNIQUE CON LA EMPRESA DE INTERNET Y QUE ELLOS VERIFIQUEN LA FALLA | W24: VISITA_TÉCNICA | X24: AD00O631 | Y24: TIPO IV | Z24: TERRESTRE | AA24: MONTES DIAZ JOHN FRED | AB24: 1 | AC24: 0 | AD24: 0 | AE24: 0 | AF24: =IF(W24="SOPORTE_TELEFÓNICO",'BASE LIQUIDACION'!$B$10,IF(Y24="TIPO I",'BASE LIQUIDACION'!$C$3,IF(Y24="TIPO II",'BASE LIQUIDACION'!$C$4,IF(Y24="TIPO III",'BASE LIQUIDACION'!$C$5,'BASE LIQUIDACION'!$C$7)))) -> 479589.74 | AG24: =IF(W24="SOPORTE_TELEFÓNICO",'BASE LIQUIDACION'!$B$10,(AB24*AF24+AC24*'BASE LIQUIDACION'!$B$12+AD24*'BASE LIQUIDACION'!$B$11+INCIDENTES!AE24*'BASE LIQUIDACION'!$B$13)) -> 479589.74
A25: IBAGUE | B25: =VLOOKUP(A25,'CENTRO DE COSTOS'!A:D,4,FALSE) -> KEVIN ALEXIS CORZO BUSTOS | C25: =VLOOKUP(A25,'CENTRO DE COSTOS'!A:D,2,FALSE) -> 0004-0007 | D25: 17380 | E25: 2543662 | F25: 75541 | G25: INCIDENTE | H25: CALDAS | I25: LA DORADA | J25: PTM LA DORADA MULTISERVICIOS J | K25: REDEBAN | L25: FO-25-1321021 | M25: 45871.499 | N25: 45873.653 | O25: NO | P25: USUARIO | Q25: COMUNICACION | R25: CONEXIONES DE COMERCIO | S25: AGREGADOR | T25: AGREGADOR | U25: CERRADO | V25: 02/08/2025 01-08 SE ESCALA PARA VISITA. LLAMAR ANTES DE VISITAR, CONFIRMAR FALLA Y DATOS | 04/08/2025 SE HABLA CON LA SEÑORA HANNA LÓPEZ, AL NÚMERO DE TELÉFONO 3205599637, ME INDICA QUE EL DATÁFONO ESTÁ TRABAJANDO DE MANERA CORRECTA | W25: SOPORTE_TELEFÓNICO | X25: 0 | Y25: TIPO III | Z25: TERRESTRE | AA25: VARGAS HERRERA JHON JAIRO | AB25: 0 | AC25: 0 | AD25: 0 | AE25: 0 | AF25: =IF(W25="SOPORTE_TELEFÓNICO",'BASE LIQUIDACION'!$B$10,IF(Y25="TIPO I",'BASE LIQUIDACION'!$C$3,IF(Y25="TIPO II",'BASE LIQUIDACION'!$C$4,IF(Y25="TIPO III",'BASE LIQUIDACION'!$C$5,'BASE LIQUIDACION'!$C$7)))) -> 37904.654 | AG25: =IF(W25="SOPORTE_TELEFÓNICO",'BASE LIQUIDACION'!$B$10,(AB25*AF25+AC25*'BASE LIQUIDACION'!$B$12+AD25*'BASE LIQUIDACION'!$B$11+INCIDENTES!AE25*'BASE LIQUIDACION'!$B$13)) -> 37904.654
A26: BUCARAMANGA | B26: =VLOOKUP(A26,'CENTRO DE COSTOS'!A:D,4,FALSE) -> MIGUEL JULIÁN HERNÁNDEZ GUARÍN | C26: =VLOOKUP(A26,'CENTRO DE COSTOS'!A:D,2,FALSE) -> 0004-0008 | D26: 68001 | E26: 2547961 | F26: 45682 | G26: INCIDENTE | H26: SANTANDER | I26: BUCARAMANGA | J26: BARRIO CABECERA BUCARAMANGA 10 | K26: REDEBAN | L26: FO-25-1325719 | M26: 45873.451 | N26: 45873.715 | O26: NO | P26: USUARIO | Q26: COMUNICACION | R26: CONEXIONES DE COMERCIO | S26: CB UNO A UNO | T26: CB UNO A UNO | U26: CERRADO | V26: 04/08/2025 04-08 SE ESCALA PARA VISITA. LLAMAR ANTES DE VISITAR, CONFIRMAR FALLA Y DATOS | 04/08/2025 SE REALIZA VERIFICACIÓN DEL EQUIPO EL CUAL YA ESTÁ FUNCIONANDO CON NORMALIDAD LUEGO DE REALIZAR AJUSTE DE CONEXIÓNES FÍSICAS SERVICIO OPERATIVO CLIENTA INDICADA NO REQUERIR SERVICIO TÉCNICO | W26: VISITA_TÉCNICA | X26: AD001930 | Y26: TIPO I | Z26: TERRESTRE | AA26: REYES RAMIREZ DIEGO ALEXANDER | AB26: 1 | AC26: 0 | AD26: 0 | AE26: 0 | AF26: =IF(W26="SOPORTE_TELEFÓNICO",'BASE LIQUIDACION'!$B$10,IF(Y26="TIPO I",'BASE LIQUIDACION'!$C$3,IF(Y26="TIPO II",'BASE LIQUIDACION'!$C$4,IF(Y26="TIPO III",'BASE LIQUIDACION'!$C$5,'BASE LIQUIDACION'!$C$7)))) -> 65960.474 | AG26: =IF(W26="SOPORTE_TELEFÓNICO",'BASE LIQUIDACION'!$B$10,(AB26*AF26+AC26*'BASE LIQUIDACION'!$B$12+AD26*'BASE LIQUIDACION'!$B$11+INCIDENTES!AE26*'BASE LIQUIDACION'!$B$13)) -> 65960.474
A27: APARTADO | B27: =VLOOKUP(A27,'CENTRO DE COSTOS'!A:D,4,FALSE) -> JUAN SEBASTIÁN RÍOS CASTRILLÓN | C27: =VLOOKUP(A27,'CENTRO DE COSTOS'!A:D,2,FALSE) -> 0004-0005 | D27: 5147 | E27: 2548117 | F27: 57488 | G27: INCIDENTE | H27: ANTIOQUIA | I27: CAREPA | J27: PTM CAREPA THE ARMY FORCE | K27: REDEBAN | L27: FO-25-1325725 | M27: 45873.449 | N27: 45873.723 | O27: NO | P27: USUARIO | Q27: COMUNICACION | R27: CANAL DEL COMERCIO | S27: AGREGADOR | T27: AGREGADOR | U27: CERRADO | V27: 04/08/2025 04-08 SE ESCALA PARA VISITA. LLAMAR ANTES DE VISITAR, CONFIRMAR FALLA Y DATOS | 04/08/2025 CLIENTE TIENE SWITCH AL PARECER MALO, SE CONECTA DATAFONO DIRECTAMENTE A MÓDEM ROUTER Y FUNCIONA | W27: VISITA_TÉCNICA | X27: IIWZZ549 | Y27: TIPO I | Z27: TERRESTRE | AA27: CASTRO HENAO DANIEL ESTEBAN | AB27: 1 | AC27: 0 | AD27: 0 | AE27: 0 | AF27: =IF(W27="SOPORTE_TELEFÓNICO",'BASE LIQUIDACION'!$B$10,IF(Y27="TIPO I",'BASE LIQUIDACION'!$C$3,IF(Y27="TIPO II",'BASE LIQUIDACION'!$C$4,IF(Y27="TIPO III",'BASE LIQUIDACION'!$C$5,'BASE LIQUIDACION'!$C$7)))) -> 65960.474 | AG27: =IF(W27="SOPORTE_TELEFÓNICO",'BASE LIQUIDACION'!$B$10,(AB27*AF27+AC27*'BASE LIQUIDACION'!$B$12+AD27*'BASE LIQUIDACION'!$B$11+INCIDENTES!AE27*'BASE LIQUIDACION'!$B$13)) -> 65960.474
A28: PASTO | B28: =VLOOKUP(A28,'CENTRO DE COSTOS'!A:D,4,FALSE) -> DIEGO FERNANDO HENAO CARDONA | C28: =VLOOKUP(A28,'CENTRO DE COSTOS'!A:D,2,FALSE) -> 0004-0003 | D28: 52399 | E28: 2549237 | F28: 80379 | G28: INCIDENTE | H28: NARIÑO | I28: LA UNION | J28: BARRIO LAS AMERICAS LA UNION 1 | K28: REDEBAN | L28: FO-25-1326490 | M28: 45873.515 | N28: 45874.406 | O28: NO | P28: USUARIO | Q28: COMUNICACION | R28: CANAL DEL COMERCIO | S28: CB UNO A UNO | T28: CB UNO A UNO | U28: CERRADO | V28: 04/08/2025 04-08 SE ESCALA PARA VISITA. LLAMAR ANTES DE VISITAR, CONFIRMAR FALLA Y DATOS | 05/08/2025 SE REALIZO COMUNICACIÓN CON LA ENCARGADA DEL CB PARA VALIDAR FALLA DEL DATAFONO, INDICA QUE AL MOMENTO SE ENCUENTRA OPERATIVO, EL ERROR DE CONEXIÓN FUE DEBIDO A UNA CAÍDA DEL SERVICIO DE INTERNET, EL CB ESTA OPERATIVO | W28: SOPORTE_TELEFÓNICO | X28: 0 | Y28: TIPO III | Z28: TERRESTRE | AA28: GUERRERO RAMIREZ OSCAR DARIO | AB28: 0 | AC28: 0 | AD28: 0 | AE28: 0 | AF28: =IF(W28="SOPORTE_TELEFÓNICO",'BASE LIQUIDACION'!$B$10,IF(Y28="TIPO I",'BASE LIQUIDACION'!$C$3,IF(Y28="TIPO II",'BASE LIQUIDACION'!$C$4,IF(Y28="TIPO III",'BASE LIQUIDACION'!$C$5,'BASE LIQUIDACION'!$C$7)))) -> 37904.654 | AG28: =IF(W28="SOPORTE_TELEFÓNICO",'BASE LIQUIDACION'!$B$10,(AB28*AF28+AC28*'BASE LIQUIDACION'!$B$12+AD28*'BASE LIQUIDACION'!$B$11+INCIDENTES!AE28*'BASE LIQUIDACION'!$B$13)) -> 37904.654
A29: SINCELEJO | B29: =VLOOKUP(A29,'CENTRO DE COSTOS'!A:D,4,FALSE) -> JOSE MAURICIO HERNANDEZ ROJAS | C29: =VLOOKUP(A29,'CENTRO DE COSTOS'!A:D,2,FALSE) -> 0004-0001 | D29: 70001 | E29: 2551445 | F29: 54273 | G29: INCIDENTE | H29: SUCRE | I29: SINCELEJO | J29: BARRIO EL PROGRESO SINCELEJO 1 | K29: REDEBAN | L29: FO-25-1328383 | M29: 45873.665 | N29: 45874.59 | O29: NO | P29: USUARIO | Q29: USUARIOS | R29: TAPA MAL ASEGURADA | S29: CB UNO A UNO | T29: CB UNO A UNO | U29: CERRADO | V29: 04/08/2024 04-08 SE ESCALA PARA VISITA. LLAMAR ANTES DE VISITAR, CONFIRMAR FALLA Y DATOS | 05/08/2025 SE VISITA COMERCIO POR UNA FALLA, SE VISUALIZA QUE LA TAPA ESTÁ MAL ASEGURADA POR ESO NO LE ESTÁBA IMPRIMIENDO, SE DEJA CON LA VERSIÓN 10.3, SE REALIZAN PRUEBAS OK, COMERCIO MIXTO TERMINAL XPEZZ053 CU 19218049 | W29: VISITA_TÉCNICA | X29: 9C6ZZ525 - XPEZZ053 | Y29: TIPO I | Z29: TERRESTRE | AA29: CACERES HERNANDEZ ANDRES | AB29: 1 | AC29: 0 | AD29: 0 | AE29: 0 | AF29: =IF(W29="SOPORTE_TELEFÓNICO",'BASE LIQUIDACION'!$B$10,IF(Y29="TIPO I",'BASE LIQUIDACION'!$C$3,IF(Y29="TIPO II",'BASE LIQUIDACION'!$C$4,IF(Y29="TIPO III",'BASE LIQUIDACION'!$C$5,'BASE LIQUIDACION'!$C$7)))) -> 65960.474 | AG29: =IF(W29="SOPORTE_TELEFÓNICO",'BASE LIQUIDACION'!$B$10,(AB29*AF29+AC29*'BASE LIQUIDACION'!$B$12+AD29*'BASE LIQUIDACION'!$B$11+INCIDENTES!AE29*'BASE LIQUIDACION'!$B$13)) -> 65960.474
A30: APARTADO | B30: =VLOOKUP(A30,'CENTRO DE COSTOS'!A:D,4,FALSE) -> JUAN SEBASTIÁN RÍOS CASTRILLÓN | C30: =VLOOKUP(A30,'CENTRO DE COSTOS'!A:D,2,FALSE) -> 0004-0005 | D30: 5045 | E30: 2552479 | F30: 10035 | G30: INCIDENTE | H30: ANTIOQUIA | I30: APARTADO | J30: BARRIO ALFONSO LOPEZ | K30: REDEBAN | L30: FO-25-1329234 | M30: 45874.333 | N30: 45874.68 | O30: NO | P30: USUARIO | Q30: MANTENIMIENTO | R30: MANTENIMIENTO GENERAL | S30: CB UNO A UNO | T30: CB UNO A UNO | U30: CERRADO | V30: 05/08/2025 05-08 SE ESCALA PARA VISITA. LLAMAR ANTES DE VISITAR, CONFIRMAR FALLA Y DATOS | 05/08/2025 SE HABLA CON SEÑOR HERNAN, SE DAN INDICACIONES PARA INGRESO, SE REALIZA PRUEBA DE CIERRE Y FUNCIONA SIN NOVEDAD, SE REALIZAN CIERRES PARCIAL Y GENERAL Y CB QUEDA OPERATIVO. SE CIERRA INCIDENTE. | W30: SOPORTE_TELEFÓNICO | X30: 0 | Y30: TIPO I | Z30: TERRESTRE | AA30: MORENO MEDINA JUAN PABLO | AB30: 0 | AC30: 0 | AD30: 0 | AE30: 0 | AF30: =IF(W30="SOPORTE_TELEFÓNICO",'BASE LIQUIDACION'!$B$10,IF(Y30="TIPO I",'BASE LIQUIDACION'!$C$3,IF(Y30="TIPO II",'BASE LIQUIDACION'!$C$4,IF(Y30="TIPO III",'BASE LIQUIDACION'!$C$5,'BASE LIQUIDACION'!$C$7)))) -> 37904.654 | AG30: =IF(W30="SOPORTE_TELEFÓNICO",'BASE LIQUIDACION'!$B$10,(AB30*AF30+AC30*'BASE LIQUIDACION'!$B$12+AD30*'BASE LIQUIDACION'!$B$11+INCIDENTES!AE30*'BASE LIQUIDACION'!$B$13)) -> 37904.654
A31: BUCARAMANGA | B31: =VLOOKUP(A31,'CENTRO DE COSTOS'!A:D,4,FALSE) -> MIGUEL JULIÁN HERNÁNDEZ GUARÍN | C31: =VLOOKUP(A31,'CENTRO DE COSTOS'!A:D,2,FALSE) -> 0004-0008 | D31: 68679 | E31: 2549161 | F31: 80714 | G31: INCIDENTE | H31: SANTANDER | I31: SAN GIL | J31: DISTRICOL MISCELANEA Y DROGUER | K31: REDEBAN | L31: FO-25-1326485 | M31: 45873.515 | N31: 45874.722 | O31: NO | P31: USUARIO | Q31: COMUNICACION | R31: CONEXIONES DE COMERCIO | S31: AGREGADOR | T31: AGREGADOR | U31: CERRADO | V31: 04/08/2025 04-08 SE ESCALA PARA VISITA. LLAMAR ANTES DE VISITAR, CONFIRMAR FALLA Y DATOS | 05/08/2025 SE COMUNICA CON LA SEÑORITA LUZ AL NÚMERO DE TELÉFONO 3015265469 ,SE VALIDA DISPONIBLIDAD PERO CLIENTE SOLICITA CANCELAR LA VISITA TÉCNICA DEBÍDO QUE LA FALLA YA FUE SOLUCIONADA, INDICA QUE ERA LA CONEXIÓN DEL COMERCIO | W31: SOPORTE_TELEFÓNICO | X31: 0 | Y31: TIPO II | Z31: TERRESTRE | AA31: HERRERA LUQUE SAUL JAVIER | AB31: 0 | AC31: 0 | AD31: 0 | AE31: 0 | AF31: =IF(W31="SOPORTE_TELEFÓNICO",'BASE LIQUIDACION'!$B$10,IF(Y31="TIPO I",'BASE LIQUIDACION'!$C$3,IF(Y31="TIPO II",'BASE LIQUIDACION'!$C$4,IF(Y31="TIPO III",'BASE LIQUIDACION'!$C$5,'BASE LIQUIDACION'!$C$7)))) -> 37904.654 | AG31: =IF(W31="SOPORTE_TELEFÓNICO",'BASE LIQUIDACION'!$B$10,(AB31*AF31+AC31*'BASE LIQUIDACION'!$B$12+AD31*'BASE LIQUIDACION'!$B$11+INCIDENTES!AE31*'BASE LIQUIDACION'!$B$13)) -> 37904.654
A32: NEIVA | B32: =VLOOKUP(A32,'CENTRO DE COSTOS'!A:D,4,FALSE) -> KEVIN ALEXIS CORZO BUSTOS | C32: =VLOOKUP(A32,'CENTRO DE COSTOS'!A:D,2,FALSE) -> 0004-0007 | D32: 41668 | E32: 2545301 | F32: 56152 | G32: INCIDENTE | H32: HUILA | I32: SAN AGUSTIN | J32: REVAL SAN AGUSTIN | K32: REDEBAN | L32: FO-25-1323968 | M32: 45873.333 | N32: 45874.74 | O32: NO | P32: USUARIO | Q32: COMUNICACION | R32: CONEXIONES DE COMERCIO | S32: ROBUSTO | T32: ROBUSTO | U32: CERRADO | V32: 04/08/2025 4-08 EN COMUNICACION CON LA SEÑORA KAREN VIVIANA CUSTIAN AL NUMERO 3134057013 INDICA QUE LOS DOS DATAFONOS LE ARROJA ERROR DE COMUNICACIION, VERIFICAR PARAMETROS, CONFIRMA DATOS, SE ESCALA PARA VISITA | 05/08/2025 SE REVISA CONFIGURACIÓN Y CONEXIÓN DE LOS EQUIPOS PLACA 930681 CON TERMINAL XPMZZ117, EQUIPO PLACA 1230876 CON TERMINAL XPMZZ116, SE CORRIGE PARÁMETROS Y SE REALIZA PRUEBAS OK | W32: VISITA_TÉCNICA | X32: XPMZZ117-XPMZZ116 | Y32: TIPO IV | Z32: TERRESTRE | AA32: ANDRADE HERNANDEZ JUAN CARLOS | AB32: 1 | AC32: 0 | AD32: 0 | AE32: 0 | AF32: =IF(W32="SOPORTE_TELEFÓNICO",'BASE LIQUIDACION'!$B$10,IF(Y32="TIPO I",'BASE LIQUIDACION'!$C$3,IF(Y32="TIPO II",'BASE LIQUIDACION'!$C$4,IF(Y32="TIPO III",'BASE LIQUIDACION'!$C$5,'BASE LIQUIDACION'!$C$7)))) -> 479589.74 | AG32: =IF(W32="SOPORTE_TELEFÓNICO",'BASE LIQUIDACION'!$B$10,(AB32*AF32+AC32*'BASE LIQUIDACION'!$B$12+AD32*'BASE LIQUIDACION'!$B$11+INCIDENTES!AE32*'BASE LIQUIDACION'!$B$13)) -> 479589.74
A33: TUNJA | B33: =VLOOKUP(A33,'CENTRO DE COSTOS'!A:D,4,FALSE) -> MIGUEL JULIÁN HERNÁNDEZ GUARÍN | C33: =VLOOKUP(A33,'CENTRO DE COSTOS'!A:D,2,FALSE) -> 0004-0008 | D33: 15176 | E33: 2554822 | F33: 75048 | G33: INCIDENTE | H33: BOYACA | I33: CHIQUINQUIRA | J33: BARRIO GUARIN CHIQUINQUIRA | K33: REDEBAN | L33: FO-25-1330772 | M33: 45874.418 | N33: 45874.762 | O33: NO | P33: ENTIDAD | Q33: ERROR DE TRANSACCIONES | R33: TRANSACCION NO PERMITIDA | S33: CB UNO A UNO | T33: CB UNO A UNO | U33: CERRADO | V33: 05/08/2025 05-08 SE ESCALA PARA VISITA. LLAMAR ANTES DE VISITAR, CONFIRMAR FALLA Y DATOS | 05/08/2025 SE VISITA CB MANTENIMIENTO DE EQUIPO, CLIENTE MANIFIESTA QUE HUBO CAIDA DE SISTEMA POR PARTE DE ENTIDAD Y EQUIPO YA SE ENCUENTRA FUNCIONANDO CORRECTAMENTE | W33: VISITA_TÉCNICA | X33: NRZZZ532 | Y33: TIPO III | Z33: TERRESTRE | AA33: GONZALEZ GONZALEZ MARIO ALBERTO | AB33: 1 | AC33: 0 | AD33: 0 | AE33: 0 | AF33: =IF(W33="SOPORTE_TELEFÓNICO",'BASE LIQUIDACION'!$B$10,IF(Y33="TIPO I",'BASE LIQUIDACION'!$C$3,IF(Y33="TIPO II",'BASE LIQUIDACION'!$C$4,IF(Y33="TIPO III",'BASE LIQUIDACION'!$C$5,'BASE LIQUIDACION'!$C$7)))) -> 275728.38 | AG33: =IF(W33="SOPORTE_TELEFÓNICO",'BASE LIQUIDACION'!$B$10,(AB33*AF33+AC33*'BASE LIQUIDACION'!$B$12+AD33*'BASE LIQUIDACION'!$B$11+INCIDENTES!AE33*'BASE LIQUIDACION'!$B$13)) -> 275728.38
A34: VALLEDUPAR | B34: =VLOOKUP(A34,'CENTRO DE COSTOS'!A:D,4,FALSE) -> JOSE MAURICIO HERNANDEZ ROJAS | C34: =VLOOKUP(A34,'CENTRO DE COSTOS'!A:D,2,FALSE) -> 0004-0001 | D34: 20750 | E34: 2556949 | F34: 29150 | G34: INCIDENTE | H34: CESAR | I34: SAN DIEGO | J34: BARRIO CENTRO 2 SAN DIEGO | K34: REDEBAN | L34: FO-25-1332635 | M34: 45874.572 | N34: 45875.404 | O34: NO | P34: USUARIO | Q34: COMUNICACION | R34: CONEXIONES DE COMERCIO | S34: CB UNO A UNO | T34: CB UNO A UNO | U34: CERRADO | V34: 06/08/2025 SE REALIZA GESTIÓN TELEFÓNICA ATIENDE EL SEÑOR EDILBERTO GONZÁLEZ EL CUAL, NOS INDICA DE QUE TIENE PROBLEMA CON UN SWITCH 5 PUERTOS DEL COMERCIO,SE LE INFORMA AL CLIENTE QUE NOSOTROS NO MANEJAMOS ESE TIPO DE EQUIPOS POR LO CUAL REQUIERE QUE EL COMERCIO REALICE EL CAMBIO DEL DISPOSITIVO PARA EL BUEN FUNCIONAMIENTO DEL DATÁFONO | W34: SOPORTE_TELEFÓNICO | X34: 0 | Y34: TIPO II | Z34: TERRESTRE | AA34: MAESTRE MENGUAL EDGAR ENRIQUE | AB34: 0 | AC34: 0 | AD34: 0 | AE34: 0 | AF34: =IF(W34="SOPORTE_TELEFÓNICO",'BASE LIQUIDACION'!$B$10,IF(Y34="TIPO I",'BASE LIQUIDACION'!$C$3,IF(Y34="TIPO II",'BASE LIQUIDACION'!$C$4,IF(Y34="TIPO III",'BASE LIQUIDACION'!$C$5,'BASE LIQUIDACION'!$C$7)))) -> 37904.654 | AG34: =IF(W34="SOPORTE_TELEFÓNICO",'BASE LIQUIDACION'!$B$10,(AB34*AF34+AC34*'BASE LIQUIDACION'!$B$12+AD34*'BASE LIQUIDACION'!$B$11+INCIDENTES!AE34*'BASE LIQUIDACION'!$B$13)) -> 37904.654
A35: MONTERIA | B35: =VLOOKUP(A35,'CENTRO DE COSTOS'!A:D,4,FALSE) -> JOSE MAURICIO HERNANDEZ ROJAS | C35: =VLOOKUP(A35,'CENTRO DE COSTOS'!A:D,2,FALSE) -> 0004-0001 | D35: 23001 | E35: 2555533 | F35: 75558 | G35: INCIDENTE | H35: CORDOBA | I35: MONTERIA | J35: PTM MONTERIA NUEVO AMANECER C | K35: REDEBAN | L35: FO-25-1331263 | M35: 45874.444 | N35: 45875.424 | O35: NO | P35: ENTIDAD | Q35: ERROR DE TRANSACCIONES | R35: TRANSACCION NO PERMITIDA | S35: AGREGADOR | T35: AGREGADOR | U35: CERRADO | V35: 05/08/2025 05-08 SE ESCALA PARA VISITA. LLAMAR ANTES DE VISITAR, CONFIRMAR FALLA Y DATOS | 06/08/2025 SE REALIZA VISITA TÉCNICA Y SE ENCUENTRA ESTABLECIMIENTO TRABAJANDO CORRECTAMENTE, SE VERIFICO FUNCIONALIDAD, USUARIO MANIFIESTA QUE EL INCONVENIENTE SE DEBIÓ A FALLAS CON LA ENTIDAD, LA CUÁL YA FUE CORREGIDA, SE VERIFICO Y SE DEJÓ EL SERVICIO OK. | W35: VISITA_TÉCNICA | X35: SX00J115 | Y35: TIPO I | Z35: TERRESTRE | AA35: CASSIANI PEREZ RAUL RAMIRO | AB35: 1 | AC35: 0 | AD35: 0 | AE35: 0 | AF35: =IF(W35="SOPORTE_TELEFÓNICO",'BASE LIQUIDACION'!$B$10,IF(Y35="TIPO I",'BASE LIQUIDACION'!$C$3,IF(Y35="TIPO II",'BASE LIQUIDACION'!$C$4,IF(Y35="TIPO III",'BASE LIQUIDACION'!$C$5,'BASE LIQUIDACION'!$C$7)))) -> 65960.474 | AG35: =IF(W35="SOPORTE_TELEFÓNICO",'BASE LIQUIDACION'!$B$10,(AB35*AF35+AC35*'BASE LIQUIDACION'!$B$12+AD35*'BASE LIQUIDACION'!$B$11+INCIDENTES!AE35*'BASE LIQUIDACION'!$B$13)) -> 65960.474
A36: NEIVA | B36: =VLOOKUP(A36,'CENTRO DE COSTOS'!A:D,4,FALSE) -> KEVIN ALEXIS CORZO BUSTOS | C36: =VLOOKUP(A36,'CENTRO DE COSTOS'!A:D,2,FALSE) -> 0004-0007 | D36: 41524 | E36: 2560013 | F36: 44290 | G36: INCIDENTE | H36: HUILA | I36: PALERMO | J36: DISTRICOL MARIA LUZ ROJAS DUSS | K36: REDEBAN | L36: FO-25-1334838 | M36: 45875.333 | N36: 45875.514 | O36: NO | P36: USUARIO | Q36: COMUNICACION | R36: CANAL DEL COMERCIO | S36: AGREGADOR | T36: AGREGADOR | U36: CERRADO | V36: 06/08/2025 05-08 SE ESCALA PARA VISITA. LLAMAR ANTES DE VISITAR, CONFIRMAR FALLA Y DATOS | 06/08/2025 SE REALIZA VISITA AL PUNTO, SE EVIDENCIA EQUIPO NO COMUNICA, SE EVIDENCIA DAÑO EN EL CANAL DE COMUNICACIÓN DEL CLIENTE EL INTERNET ESTA MUY INTERMITENTE, SE REALIZAN PRUEBAS CON INTERNET DE OTRO PUNTO Y FUNCIONA TODO OK, SE LE INDICA AL CLIENTE QUE TIENE QUE SOLICITAR VISITA TÉCNICA DE INTERNET. PRUEBAS OK, EQUIPO OK | W36: VISITA_TÉCNICA | X36: 9B05Z126 | Y36: TIPO I | Z36: TERRESTRE | AA36: DEVIA REINOSO JUAN CARLOS | AB36: 1 | AC36: 0 | AD36: 0 | AE36: 0 | AF36: =IF(W36="SOPORTE_TELEFÓNICO",'BASE LIQUIDACION'!$B$10,IF(Y36="TIPO I",'BASE LIQUIDACION'!$C$3,IF(Y36="TIPO II",'BASE LIQUIDACION'!$C$4,IF(Y36="TIPO III",'BASE LIQUIDACION'!$C$5,'BASE LIQUIDACION'!$C$7)))) -> 65960.474 | AG36: =IF(W36="SOPORTE_TELEFÓNICO",'BASE LIQUIDACION'!$B$10,(AB36*AF36+AC36*'BASE LIQUIDACION'!$B$12+AD36*'BASE LIQUIDACION'!$B$11+INCIDENTES!AE36*'BASE LIQUIDACION'!$B$13)) -> 65960.474
A37: MEDELLIN | B37: =VLOOKUP(A37,'CENTRO DE COSTOS'!A:D,4,FALSE) -> JUAN SEBASTIÁN RÍOS CASTRILLÓN | C37: =VLOOKUP(A37,'CENTRO DE COSTOS'!A:D,2,FALSE) -> 0004-0005 | D37: 5001 | E37: 2559160 | F37: 73590 | G37: INCIDENTE | H37: ANTIOQUIA | I37: MEDELLIN | J37: PTM MEDELLIN SALSAMENTARIA MO | K37: REDEBAN | L37: FO-25-1334337 | M37: 45875.333 | N37: 45875.515 | O37: NO | P37: USUARIO | Q37: LECTOR DE TARJETAS | R37: OBSTRUCCION DEL LECTOR | S37: AGREGADOR | T37: AGREGADOR | U37: CERRADO | V37: 06/08/2025 05-08 SE ESCALA PARA VISITA. LLAMAR ANTES DE VISITAR, CONFIRMAR FALLA Y DATOS | 06/08/2025 SE REALIZA MANTENIMIENTO GENERAL AL EQUIPO, SE REALIZA PRUEBAS PERTINENTES, TODAS OK | W37: VISITA_TÉCNICA | X37: SV00W515 - NN00E822 | Y37: TIPO I | Z37: TERRESTRE | AA37: HERNANDEZ CHAVARRIA JUAN CAMILO | AB37: 1 | AC37: 0 | AD37: 0 | AE37: 0 | AF37: =IF(W37="SOPORTE_TELEFÓNICO",'BASE LIQUIDACION'!$B$10,IF(Y37="TIPO I",'BASE LIQUIDACION'!$C$3,IF(Y37="TIPO II",'BASE LIQUIDACION'!$C$4,IF(Y37="TIPO III",'BASE LIQUIDACION'!$C$5,'BASE LIQUIDACION'!$C$7)))) -> 65960.474 | AG37: =IF(W37="SOPORTE_TELEFÓNICO",'BASE LIQUIDACION'!$B$10,(AB37*AF37+AC37*'BASE LIQUIDACION'!$B$12+AD37*'BASE LIQUIDACION'!$B$11+INCIDENTES!AE37*'BASE LIQUIDACION'!$B$13)) -> 65960.474
A38: MEDELLIN | B38: =VLOOKUP(A38,'CENTRO DE COSTOS'!A:D,4,FALSE) -> JUAN SEBASTIÁN RÍOS CASTRILLÓN | C38: =VLOOKUP(A38,'CENTRO DE COSTOS'!A:D,2,FALSE) -> 0004-0005 | D38: 5079 | E38: 2554843 | F38: 19653 | G38: INCIDENTE | H38: ANTIOQUIA | I38: BARBOSA | J38: BARRIO SEGUNDO PARQUE BARBOSA | K38: REDEBAN | L38: FO-25-1330757 | M38: 45874.422 | N38: 45875.526 | O38: NO | P38: USUARIO | Q38: MANTENIMIENTO | R38: MANTENIMIENTO GENERAL | S38: CB UNO A UNO | T38: CB UNO A UNO | U38: CERRADO | V38: 05/08/2025 05-08 SE ESCALA PARA VISITA. LLAMAR ANTES DE VISITAR, CONFIRMAR FALLA Y DATOS | 06/08/2025 SE REALIZÓ MANTENIMIENTO GENERAL DEL EQUIPO, SE LE EXPLICÓ AL USUARIO FUNCIONAMIENTO DEL NUEVO EQUIPO POS, FUNCIONA NORMALMENTE | W38: VISITA_TÉCNICA | X38: AAAAH126 | Y38: TIPO II | Z38: TERRESTRE | AA38: CASTAÑEDA PALACIO CARLOS FELIPE | AB38: 1 | AC38: 0 | AD38: 0 | AE38: 0 | AF38: =IF(W38="SOPORTE_TELEFÓNICO",'BASE LIQUIDACION'!$B$10,IF(Y38="TIPO I",'BASE LIQUIDACION'!$C$3,IF(Y38="TIPO II",'BASE LIQUIDACION'!$C$4,IF(Y38="TIPO III",'BASE LIQUIDACION'!$C$5,'BASE LIQUIDACION'!$C$7)))) -> 163813.56 | AG38: =IF(W38="SOPORTE_TELEFÓNICO",'BASE LIQUIDACION'!$B$10,(AB38*AF38+AC38*'BASE LIQUIDACION'!$B$12+AD38*'BASE LIQUIDACION'!$B$11+INCIDENTES!AE38*'BASE LIQUIDACION'!$B$13)) -> 163813.56
A39: VALLEDUPAR | B39: =VLOOKUP(A39,'CENTRO DE COSTOS'!A:D,4,FALSE) -> JOSE MAURICIO HERNANDEZ ROJAS | C39: =VLOOKUP(A39,'CENTRO DE COSTOS'!A:D,2,FALSE) -> 0004-0001 | D39: 20013 | E39: 2559069 | F39: 10637 | G39: INCIDENTE | H39: CESAR | I39: AGUSTIN CODAZZI | J39: AGUSTIN CODAZZI III - CESAR | K39: REDEBAN | L39: FO-25-1333986 | M39: 45874.742 | N39: 45875.555 | O39: NO | P39: USUARIO | Q39: MANTENIMIENTO | R39: MANTENIMIENTO GENERAL | S39: CB UNO A UNO | T39: CB UNO A UNO | U39: CERRADO | V39: 05/08/2025 05-08 SE ESCALA PARA VISITA. LLAMAR ANTES DE VISITAR, CONFIRMAR FALLA Y DATOS | 06/08/2025 06/08/2025 SE REALIZA GESTIÓN TELEFÓNICA ATIENDE EL SEÑOR NIXON, EL CUAL NOS INDICA DE QUE HACE POCO LE REALIZARON CAMBIO DE DATÁFONO Y NOS INDICA QUE EL DATÁFONO NUEVO QUE LE INSTALARON TIENE LAS TECLAS UN POCO MÁS DURAS QUE EL ANTERIOR, SE VALIDA LA CUAL NOS DA DE REFERENCIA QUE ES UN EQUIPO DESK 2600, ESA REFERENCIA DE EQUIPO LAS TECLAS SON UN POCO MÁS RÍGIDAS QUE LOS ANTERIORES EQUIPOS, SE LE COMENTA QUE ES NORMAL Y SE LE EXPLICA DE QUE SI DESEA SE LE REALIZA CAMBIO DE EQUIPO PERO SE LE INSTALARIA UNO DE LA MISMA TECNOLOGIA. EL CLIENTE NOS INDICA DE QUE NO ES NECESARIO QUE NO HAY NINGÚN INCONVENIENTE QUE DEJEN EL EQUIPO ACTUAL | W39: SOPORTE_TELEFÓNICO | X39: 0 | Y39: TIPO II | Z39: TERRESTRE | AA39: MAESTRE MENGUAL EDGAR ENRIQUE | AB39: 0 | AC39: 0 | AD39: 0 | AE39: 0 | AF39: =IF(W39="SOPORTE_TELEFÓNICO",'BASE LIQUIDACION'!$B$10,IF(Y39="TIPO I",'BASE LIQUIDACION'!$C$3,IF(Y39="TIPO II",'BASE LIQUIDACION'!$C$4,IF(Y39="TIPO III",'BASE LIQUIDACION'!$C$5,'BASE LIQUIDACION'!$C$7)))) -> 37904.654 | AG39: =IF(W39="SOPORTE_TELEFÓNICO",'BASE LIQUIDACION'!$B$10,(AB39*AF39+AC39*'BASE LIQUIDACION'!$B$12+AD39*'BASE LIQUIDACION'!$B$11+INCIDENTES!AE39*'BASE LIQUIDACION'!$B$13)) -> 37904.654
A40: VILLAVICENCIO | B40: =VLOOKUP(A40,'CENTRO DE COSTOS'!A:D,4,FALSE) -> KEVIN ALEXIS CORZO BUSTOS | C40: =VLOOKUP(A40,'CENTRO DE COSTOS'!A:D,2,FALSE) -> 0004-0007 | D40: 50223 | E40: 2552832 | F40: 80364 | G40: INCIDENTE | H40: META | I40: CUBARRAL | J40: BARRIO EL JARDIN CUBARRAL | K40: REDEBAN | L40: FO-25-1329228 | M40: 45874.333 | N40: 45875.681 | O40: NO | P40: USUARIO | Q40: COMUNICACION | R40: CONEXIONES DE COMERCIO | S40: CB UNO A UNO | T40: CB UNO A UNO | U40: CERRADO | V40: 05/08/2025 05-08 SE ESCALA PARA VISITA. LLAMAR ANTES DE VISITAR, CONFIRMAR FALLA Y DATOS | 06/08/2025 SE REALIZA VISITA A COMERCIO, SEÑORA HERLINDA MANIFIESTA SERVICIO OPERATIVO OK SIN NOVEDADES | W40: VISITA_TÉCNICA | X40: LBZZZ622 | Y40: TIPO II | Z40: TERRESTRE | AA40: CASTRILLON URREA LONDIER LEANDRO | AB40: 1 | AC40: 0 | AD40: 0 | AE40: 0 | AF40: =IF(W40="SOPORTE_TELEFÓNICO",'BASE LIQUIDACION'!$B$10,IF(Y40="TIPO I",'BASE LIQUIDACION'!$C$3,IF(Y40="TIPO II",'BASE LIQUIDACION'!$C$4,IF(Y40="TIPO III",'BASE LIQUIDACION'!$C$5,'BASE LIQUIDACION'!$C$7)))) -> 163813.56 | AG40: =IF(W40="SOPORTE_TELEFÓNICO",'BASE LIQUIDACION'!$B$10,(AB40*AF40+AC40*'BASE LIQUIDACION'!$B$12+AD40*'BASE LIQUIDACION'!$B$11+INCIDENTES!AE40*'BASE LIQUIDACION'!$B$13)) -> 163813.56
A41: SINCELEJO | B41: =VLOOKUP(A41,'CENTRO DE COSTOS'!A:D,4,FALSE) -> JOSE MAURICIO HERNANDEZ ROJAS | C41: =VLOOKUP(A41,'CENTRO DE COSTOS'!A:D,2,FALSE) -> 0004-0001 | D41: 70215 | E41: 2559126 | F41: 78757 | G41: INCIDENTE | H41: SUCRE | I41: COROZAL | J41: DISTRICOL DROGUERIVARIEDAD21 | K41: REDEBAN | L41: FO-25-1333988 | M41: 45874.741 | N41: 45875.694 | O41: NO | P41: USUARIO | Q41: LECTOR DE TARJETAS | R41: OBSTRUCCION DEL LECTOR | S41: AGREGADOR | T41: AGREGADOR | U41: CERRADO | V41: 05/08/2025 05-08 SE ESCALA PARA VISITA. LLAMAR ANTES DE VISITAR, CONFIRMAR FALLA Y DATOS | 06/08/2025 SE VISITA SITIO, SE VERIFICA INFORMACIÓN, SE REALIZA LIMPIEZA DEL LECTOR, SE RESTAURA LA OBSTRUCCIÓN, SE REALIZA PRUEBA TRX EXITOSA, TECLADO OK, IMPRESIÓN OK, SELLOS OK | W41: VISITA_TÉCNICA | X41: SXRZZ981 | Y41: TIPO II | Z41: TERRESTRE | AA41: SANTOS GUZMAN CHRISTIAN FELIPE | AB41: 1 | AC41: 0 | AD41: 0 | AE41: 0 | AF41: =IF(W41="SOPORTE_TELEFÓNICO",'BASE LIQUIDACION'!$B$10,IF(Y41="TIPO I",'BASE LIQUIDACION'!$C$3,IF(Y41="TIPO II",'BASE LIQUIDACION'!$C$4,IF(Y41="TIPO III",'BASE LIQUIDACION'!$C$5,'BASE LIQUIDACION'!$C$7)))) -> 163813.56 | AG41: =IF(W41="SOPORTE_TELEFÓNICO",'BASE LIQUIDACION'!$B$10,(AB41*AF41+AC41*'BASE LIQUIDACION'!$B$12+AD41*'BASE LIQUIDACION'!$B$11+INCIDENTES!AE41*'BASE LIQUIDACION'!$B$13)) -> 163813.56
A42: MEDELLIN | B42: =VLOOKUP(A42,'CENTRO DE COSTOS'!A:D,4,FALSE) -> JUAN SEBASTIÁN RÍOS CASTRILLÓN | C42: =VLOOKUP(A42,'CENTRO DE COSTOS'!A:D,2,FALSE) -> 0004-0005 | D42: 5604 | E42: 2561346 | F42: 70814 | G42: INCIDENTE | H42: ANTIOQUIA | I42: REMEDIOS | J42: 7 AGOSTO REMEDIO | K42: REDEBAN | L42: FO-25-1336823 | M42: 45875.412 | N42: 45875.721 | O42: NO | P42: USUARIO | Q42: COMUNICACION | R42: CONEXIONES DE COMERCIO | S42: CB UNO A UNO | T42: CB UNO A UNO | U42: CERRADO | V42: 06/08/2025 6-08 10:36 SE INTENTA COMUNICACION EN VARIAS OPORTUNIDADES CON EL SEÑOR ARLEY MENDEZ A LOS NUMERO 3127330177-3137475677 PERO NO FUE POSIBLE, SE ESCALA AL COORDINADOR DE LA ZONA PARA VALIDAR EN SITIO | 06/08/2025 CABLE DE RED MAL CONECTADO, SE ORGANIZA, EQUIPOS OPERATIVOS | W42: VISITA_TÉCNICA | X42: EF00B344 | Y42: TIPO IV | Z42: TERRESTRE | AA42: BADEL ACUÑA LUIS ALBERTO | AB42: 1 | AC42: 0 | AD42: 0 | AE42: 0 | AF42: =IF(W42="SOPORTE_TELEFÓNICO",'BASE LIQUIDACION'!$B$10,IF(Y42="TIPO I",'BASE LIQUIDACION'!$C$3,IF(Y42="TIPO II",'BASE LIQUIDACION'!$C$4,IF(Y42="TIPO III",'BASE LIQUIDACION'!$C$5,'BASE LIQUIDACION'!$C$7)))) -> 479589.74 | AG42: =IF(W42="SOPORTE_TELEFÓNICO",'BASE LIQUIDACION'!$B$10,(AB42*AF42+AC42*'BASE LIQUIDACION'!$B$12+AD42*'BASE LIQUIDACION'!$B$11+INCIDENTES!AE42*'BASE LIQUIDACION'!$B$13)) -> 479589.74
A43: MANIZALES | B43: =VLOOKUP(A43,'CENTRO DE COSTOS'!A:D,4,FALSE) -> DIEGO FERNANDO HENAO CARDONA | C43: =VLOOKUP(A43,'CENTRO DE COSTOS'!A:D,2,FALSE) -> 0004-0002 | D43: 17001 | E43: 2563378 | F43: 12642 | G43: INCIDENTE | H43: CALDAS | I43: MANIZALES | J43: BARRIO EL CABLE MANIZALEZ | K43: REDEBAN | L43: FO-25-1339359 | M43: 45875.558 | N43: 45875.738 | O43: NO | P43: USUARIO | Q43: COMUNICACION | R43: CANAL DEL COMERCIO | S43: CB UNO A UNO | T43: CB UNO A UNO | U43: CERRADO | V43: 06/08/2025 06-08 SE ESCALA PARA VISITA. LLAMAR ANTES DE VISITAR, CONFIRMAR FALLA Y DATOS | 06/08/2025 SE REVISA LAS CONEXIONES DEL COMERCIO LAS CUALES SE ENCUENTRAN EN BUEN ESTADO, SE VÁLIDA EL FUNCIONAMIENTO DEL EQUIPO Y SE ENCUENTRA TRABAJANDO BIEN, EL CLIENTE INDICA QUE EL HACE CUATRO MESES LE CAMBIARON EL EQUIPO POR EL MISMO PROBLEMA, SE REALIZAN PRUEBAS OK Y SE LE INDICA AL CLIENTE SOLICITAR VISITA TÉCNICA DEL PROVEEDOR DE INTERNET YA QUE NO SE ENCUENTRA FALLAS EN EL EQUIPO | W43: VISITA_TÉCNICA | X43: JAAAX615 | Y43: TIPO I | Z43: TERRESTRE | AA43: FRANCO CAÑAVERAL YAMID RAUL | AB43: 1 | AC43: 0 | AD43: 0 | AE43: 0 | AF43: =IF(W43="SOPORTE_TELEFÓNICO",'BASE LIQUIDACION'!$B$10,IF(Y43="TIPO I",'BASE LIQUIDACION'!$C$3,IF(Y43="TIPO II",'BASE LIQUIDACION'!$C$4,IF(Y43="TIPO III",'BASE LIQUIDACION'!$C$5,'BASE LIQUIDACION'!$C$7)))) -> 65960.474 | AG43: =IF(W43="SOPORTE_TELEFÓNICO",'BASE LIQUIDACION'!$B$10,(AB43*AF43+AC43*'BASE LIQUIDACION'!$B$12+AD43*'BASE LIQUIDACION'!$B$11+INCIDENTES!AE43*'BASE LIQUIDACION'!$B$13)) -> 65960.474
A44: PEREIRA | B44: =VLOOKUP(A44,'CENTRO DE COSTOS'!A:D,4,FALSE) -> DIEGO FERNANDO HENAO CARDONA | C44: =VLOOKUP(A44,'CENTRO DE COSTOS'!A:D,2,FALSE) -> 0004-0002 | D44: 63001 | E44: 2563159 | F44: 35540 | G44: INCIDENTE | H44: QUINDIO | I44: ARMENIA | J44: BARRIO ZULDEMAYDA ARMENIA | K44: REDEBAN | L44: FO-25-1338191 | M44: 45875.523 | N44: 45875.74 | O44: NO | P44: USUARIO | Q44: MANTENIMIENTO | R44: MANTENIMIENTO GENERAL | S44: CB UNO A UNO | T44: CB UNO A UNO | U44: CERRADO | V44: 06/08/2025 06-08 SE ESCALA PARA VISITA. LLAMAR ANTES DE VISITAR, CONFIRMAR FALLA Y DATOS | 06/08/2025 SE VISITA COMERCIO SE REALIZÓ VERIFICACIÓN Y CONFIGURACIÓN DE CLAVE SUPERVISOR PRUEBAS OK | W44: VISITA_TÉCNICA | X44: 9A0TZ995 | Y44: TIPO II | Z44: TERRESTRE | AA44: SANCHEZ SOLORZANO JUAN SEBASTIAN | AB44: 1 | AC44: 0 | AD44: 0 | AE44: 0 | AF44: =IF(W44="SOPORTE_TELEFÓNICO",'BASE LIQUIDACION'!$B$10,IF(Y44="TIPO I",'BASE LIQUIDACION'!$C$3,IF(Y44="TIPO II",'BASE LIQUIDACION'!$C$4,IF(Y44="TIPO III",'BASE LIQUIDACION'!$C$5,'BASE LIQUIDACION'!$C$7)))) -> 163813.56 | AG44: =IF(W44="SOPORTE_TELEFÓNICO",'BASE LIQUIDACION'!$B$10,(AB44*AF44+AC44*'BASE LIQUIDACION'!$B$12+AD44*'BASE LIQUIDACION'!$B$11+INCIDENTES!AE44*'BASE LIQUIDACION'!$B$13)) -> 163813.56
A45: CALI | B45: =VLOOKUP(A45,'CENTRO DE COSTOS'!A:D,4,FALSE) -> DIEGO FERNANDO HENAO CARDONA | C45: =VLOOKUP(A45,'CENTRO DE COSTOS'!A:D,2,FALSE) -> 0004-0003 | D45: 76001 | E45: 2563957 | F45: 71364 | G45: INCIDENTE | H45: VALLE DEL CAUCA | I45: CALI | J45: DISTRICOL LA CANASTA MAX BARAT | K45: REDEBAN | L45: FO-25-1339671 | M45: 45875.599 | N45: 45875.744 | O45: NO | P45: USUARIO | Q45: COMUNICACION | R45: CANAL DEL COMERCIO | S45: AGREGADOR | T45: AGREGADOR | U45: CERRADO | V45: 06/08/2025 06-08 SE ESCALA PARA VISITA. LLAMAR ANTES DE VISITAR, CONFIRMAR FALLA Y DATOS | 06/08/2025 SE REALIZA VALIDACION CON EL CLIENTE Y SE ENCUENTRA QUE EL CANAL DEL CLIENTE ESTA CON PROBLEMAS, CLIENTE REALIZA REINICIO DE LOS DISPOSITIVOS Y SEGUIDAMENTE REALIZAR PRUEBAS EXITOSAS EN EL DATAFONO | W45: SOPORTE_TELEFÓNICO | X45: 0 | Y45: TIPO I | Z45: TERRESTRE | AA45: HENAO CARDONA DIEGO FERNANDO | AB45: 0 | AC45: 0 | AD45: 0 | AE45: 0 | AF45: =IF(W45="SOPORTE_TELEFÓNICO",'BASE LIQUIDACION'!$B$10,IF(Y45="TIPO I",'BASE LIQUIDACION'!$C$3,IF(Y45="TIPO II",'BASE LIQUIDACION'!$C$4,IF(Y45="TIPO III",'BASE LIQUIDACION'!$C$5,'BASE LIQUIDACION'!$C$7)))) -> 37904.654 | AG45: =IF(W45="SOPORTE_TELEFÓNICO",'BASE LIQUIDACION'!$B$10,(AB45*AF45+AC45*'BASE LIQUIDACION'!$B$12+AD45*'BASE LIQUIDACION'!$B$11+INCIDENTES!AE45*'BASE LIQUIDACION'!$B$13)) -> 37904.654
A46: BUCARAMANGA | B46: =VLOOKUP(A46,'CENTRO DE COSTOS'!A:D,4,FALSE) -> MIGUEL JULIÁN HERNÁNDEZ GUARÍN | C46: =VLOOKUP(A46,'CENTRO DE COSTOS'!A:D,2,FALSE) -> 0004-0008 | D46: 68307 | E46: 2561377 | F46: 34487 | G46: INCIDENTE | H46: SANTANDER | I46: GIRON | J46: COMCARD GIRON D´ANGEL | K46: REDEBAN | L46: FO-25-1336816 | M46: 45875.416 | N46: 45875.763 | O46: NO | P46: USUARIO | Q46: LECTOR DE BARRAS | R46: ERROR PAGOS PARCIALES DE FACTURAS | S46: AGREGADOR | T46: AGREGADOR | U46: CERRADO | V46: 06/08/2025 06-08 SE ESCALA PARA VISITA. LLAMAR ANTES DE VISITAR, CONFIRMAR FALLA Y DATOS | 06/08/2025 SE LLEGA SITIO, SE HACE VALIDACIÓN DE LECTOR DE BARRAS, SE LE INDICA AL CLIENTE QUE, BANCOLOMBIA NO TIENE CONVENIO CON LAS FACTURAS DE AGUA, GAS, MOVISTAR Y CLARO POR TAL MOTIVO NO LES PERMITE RECAUDAR ESOS RECIBOS, SE HACEN PRUEBAS, CON OTRAS CÓDIGOS DE BARRAS EXITOSO. CN MIXTO TERMINAL II00S895, CU 17833419 | W46: VISITA_TÉCNICA | X46: BL014332 - II00S895 | Y46: TIPO I | Z46: TERRESTRE | AA46: MARTINEZ FLOREZ DONIS ALBERTO | AB46: 1 | AC46: 0 | AD46: 0 | AE46: 0 | AF46: =IF(W46="SOPORTE_TELEFÓNICO",'BASE LIQUIDACION'!$B$10,IF(Y46="TIPO I",'BASE LIQUIDACION'!$C$3,IF(Y46="TIPO II",'BASE LIQUIDACION'!$C$4,IF(Y46="TIPO III",'BASE LIQUIDACION'!$C$5,'BASE LIQUIDACION'!$C$7)))) -> 65960.474 | AG46: =IF(W46="SOPORTE_TELEFÓNICO",'BASE LIQUIDACION'!$B$10,(AB46*AF46+AC46*'BASE LIQUIDACION'!$B$12+AD46*'BASE LIQUIDACION'!$B$11+INCIDENTES!AE46*'BASE LIQUIDACION'!$B$13)) -> 65960.474
A47: BUCARAMANGA | B47: =VLOOKUP(A47,'CENTRO DE COSTOS'!A:D,4,FALSE) -> MIGUEL JULIÁN HERNÁNDEZ GUARÍN | C47: =VLOOKUP(A47,'CENTRO DE COSTOS'!A:D,2,FALSE) -> 0004-0008 | D47: 68001 | E47: 2563170 | F47: 75991 | G47: INCIDENTE | H47: SANTANDER | I47: BUCARAMANGA | J47: BARRIO ALFONSO LOPEZ BUCARAMAN | K47: REDEBAN | L47: FO-25-1338198 | M47: 45875.526 | N47: 45876.407 | O47: NO | P47: USUARIO | Q47: COMUNICACION | R47: CONEXIONES DE COMERCIO | S47: CB UNO A UNO | T47: CB UNO A UNO | U47: CERRADO | V47: 06/08/2025 06-08 SE ESCALA PARA VISITA. LLAMAR ANTES DE VISITAR, CONFIRMAR FALLA Y DATOS | 06/08/2025 SE VISITA COMERCIO Y SE ENCUENTRA ERROR EN LA COMUNICACIÓN DEBIDO A UNA FALLA EN EL CANAL DE COMUNICACIONES DEL COMERCIO SE LE INDICA AL CLIENTE Y SE REALIZA PRUEBA EN OTRO MÓDEM PARA VERIFICAR EL FUNCIONAMIENTO CORRECTO DEL DATÁFONO | W47: VISITA_TÉCNICA | X47: LM0BZ635 | Y47: TIPO I | Z47: TERRESTRE | AA47: PEÑA DIAZ IVAN YESID | AB47: 1 | AC47: 0 | AD47: 0 | AE47: 0 | AF47: =IF(W47="SOPORTE_TELEFÓNICO",'BASE LIQUIDACION'!$B$10,IF(Y47="TIPO I",'BASE LIQUIDACION'!$C$3,IF(Y47="TIPO II",'BASE LIQUIDACION'!$C$4,IF(Y47="TIPO III",'BASE LIQUIDACION'!$C$5,'BASE LIQUIDACION'!$C$7)))) -> 65960.474 | AG47: =IF(W47="SOPORTE_TELEFÓNICO",'BASE LIQUIDACION'!$B$10,(AB47*AF47+AC47*'BASE LIQUIDACION'!$B$12+AD47*'BASE LIQUIDACION'!$B$11+INCIDENTES!AE47*'BASE LIQUIDACION'!$B$13)) -> 65960.474
A48: MEDELLIN | B48: =VLOOKUP(A48,'CENTRO DE COSTOS'!A:D,4,FALSE) -> JUAN SEBASTIÁN RÍOS CASTRILLÓN | C48: =VLOOKUP(A48,'CENTRO DE COSTOS'!A:D,2,FALSE) -> 0004-0005 | D48: 5686 | E48: 2558392 | F48: 31779 | G48: INCIDENTE | H48: ANTIOQUIA | I48: SANTA ROSA DE OSOS | J48: BARRIO LA TERMINAL SANTA ROSA | K48: REDEBAN | L48: FO-25-1333735 | M48: 45874.675 | N48: 45876.478 | O48: NO | P48: USUARIO | Q48: MANTENIMIENTO | R48: MANTENIMIENTO GENERAL | S48: CB UNO A UNO | T48: CB UNO A UNO | U48: CERRADO | V48: 05/08/2025 05-08 SE ESCALA PARA VISITA. LLAMAR ANTES DE VISITAR, CONFIRMAR FALLA Y DATOS | 07/08/2025 SE HACE MANTENIMIENTO SE OK SE CONFIGURA PARÁMETROS DE DATÁFONO OK PRUEBAS EXITOSAS | W48: VISITA_TÉCNICA | X48: BL08Z839 | Y48: TIPO II | Z48: TERRESTRE | AA48: DIAZ ZABALA FRANCIS DUBAN | AB48: 1 | AC48: 0 | AD48: 0 | AE48: 0 | AF48: =IF(W48="SOPORTE_TELEFÓNICO",'BASE LIQUIDACION'!$B$10,IF(Y48="TIPO I",'BASE LIQUIDACION'!$C$3,IF(Y48="TIPO II",'BASE LIQUIDACION'!$C$4,IF(Y48="TIPO III",'BASE LIQUIDACION'!$C$5,'BASE LIQUIDACION'!$C$7)))) -> 163813.56 | AG48: =IF(W48="SOPORTE_TELEFÓNICO",'BASE LIQUIDACION'!$B$10,(AB48*AF48+AC48*'BASE LIQUIDACION'!$B$12+AD48*'BASE LIQUIDACION'!$B$11+INCIDENTES!AE48*'BASE LIQUIDACION'!$B$13)) -> 163813.56
A49: CUCUTA | B49: =VLOOKUP(A49,'CENTRO DE COSTOS'!A:D,4,FALSE) -> MIGUEL JULIÁN HERNÁNDEZ GUARÍN | C49: =VLOOKUP(A49,'CENTRO DE COSTOS'!A:D,2,FALSE) -> 0004-0008 | D49: 54001 | E49: 2567232 | F49: 65491 | G49: INCIDENTE | H49: NORTE DE SANTANDER | I49: CUCUTA | J49: BARRIO LOS OLIVOS CUCUTA | K49: REDEBAN | L49: FO-25-1345269 | M49: 45876.524 | N49: 45877.39 | O49: NO | P49: USUARIO | Q49: MANTENIMIENTO | R49: MANTENIMIENTO GENERAL | S49: CB UNO A UNO | T49: CB UNO A UNO | U49: CERRADO | V49: 07/08/2025 07-08 SE ESCALA PARA VISITA. LLAMAR ANTES DE VISITAR, CONFIRMAR FALLA Y DATOS | 08/08/2025 SE REALIZÓ VISITA AL COMERCIO Y SE ENCUENTRA DATAFONO CON RECHAZO GENERAL EN RETIROS SE REPOSAN PARÁMETROS, SE REPOSA LLAVE PRUEBAS EXITOSAS | W49: VISITA_TÉCNICA | X49: 7A00B348 | Y49: TIPO I | Z49: TERRESTRE | AA49: MORA VEGA JEAMPIER | AB49: 1 | AC49: 0 | AD49: 0 | AE49: 0 | AF49: =IF(W49="SOPORTE_TELEFÓNICO",'BASE LIQUIDACION'!$B$10,IF(Y49="TIPO I",'BASE LIQUIDACION'!$C$3,IF(Y49="TIPO II",'BASE LIQUIDACION'!$C$4,IF(Y49="TIPO III",'BASE LIQUIDACION'!$C$5,'BASE LIQUIDACION'!$C$7)))) -> 65960.474 | AG49: =IF(W49="SOPORTE_TELEFÓNICO",'BASE LIQUIDACION'!$B$10,(AB49*AF49+AC49*'BASE LIQUIDACION'!$B$12+AD49*'BASE LIQUIDACION'!$B$11+INCIDENTES!AE49*'BASE LIQUIDACION'!$B$13)) -> 65960.474
A50: CALI | B50: =VLOOKUP(A50,'CENTRO DE COSTOS'!A:D,4,FALSE) -> DIEGO FERNANDO HENAO CARDONA | C50: =VLOOKUP(A50,'CENTRO DE COSTOS'!A:D,2,FALSE) -> 0004-0003 | D50: 76001 | E50: 2566211 | F50: 76951 | G50: INCIDENTE | H50: VALLE DEL CAUCA | I50: CALI | J50: BARRIO CENTRAL CALI | K50: REDEBAN | L50: FO-25-1342306 | M50: 45876.333 | N50: 45877.402 | O50: NO | P50: USUARIO | Q50: COMUNICACION | R50: CONEXIONES DE COMERCIO | S50: CB UNO A UNO | T50: CB UNO A UNO | U50: CERRADO | V50: 07/08/2025 07-08 SE ESCALA PARA VISITA. LLAMAR ANTES DE VISITAR, CONFIRMAR FALLA Y DATOS | 07/08/2025 SE HABLA CON EL CLIENTE PARA VALIDAR ATENCION, CLIENTE INDICA QUE SE PUEDE REALIZAR VISITA EL DIA VIERNES, EN HORAS DE LA MAÑANA QUE VOLVERA NUEVAMENTE AL LOCAL | 08/08/2025 SE LLEGA AL COMERCIO SE REVISA CABLEADO SE HACEN PRUEBAS Y TODO ESTA OK QUEDA FUNCIONANDO CORRECTAMENTE | W50: VISITA_TÉCNICA | X50: A18ZZ388 | Y50: TIPO I | Z50: TERRESTRE | AA50: CUERO RUIZ JHONNY | AB50: 1 | AC50: 0 | AD50: 0 | AE50: 0 | AF50: =IF(W50="SOPORTE_TELEFÓNICO",'BASE LIQUIDACION'!$B$10,IF(Y50="TIPO I",'BASE LIQUIDACION'!$C$3,IF(Y50="TIPO II",'BASE LIQUIDACION'!$C$4,IF(Y50="TIPO III",'BASE LIQUIDACION'!$C$5,'BASE LIQUIDACION'!$C$7)))) -> 65960.474 | AG50: =IF(W50="SOPORTE_TELEFÓNICO",'BASE LIQUIDACION'!$B$10,(AB50*AF50+AC50*'BASE LIQUIDACION'!$B$12+AD50*'BASE LIQUIDACION'!$B$11+INCIDENTES!AE50*'BASE LIQUIDACION'!$B$13)) -> 65960.474
A51: CALI | B51: =VLOOKUP(A51,'CENTRO DE COSTOS'!A:D,4,FALSE) -> DIEGO FERNANDO HENAO CARDONA | C51: =VLOOKUP(A51,'CENTRO DE COSTOS'!A:D,2,FALSE) -> 0004-0003 | D51: 76001 | E51: 2568506 | F51: 33764 | G51: INCIDENTE | H51: VALLE DEL CAUCA | I51: CALI | J51: BARRIO VILLACOLOMBIA CALI | K51: REDEBAN | L51: FO-25-1347941 | M51: 45877.36 | N51: 45877.443 | O51: NO | P51: USUARIO | Q51: CIERRE | R51: COMERCIO NO REALIZA CIERRE | S51: CB UNO A UNO | T51: CB UNO A UNO | U51: CERRADO | V51: 08/08/2025 08-08 SE ESCALA PARA VISITA. LLAMAR ANTES DE VISITAR, CONFIRMAR FALLA Y DATOS | 08/08/2025 CLIENTE NO TENIA CLAVE DE SUPERVISOR SE LE ASIGNÓ UNA Y QUEDA FUNCIONANDO CORRECTAMENTE | W51: VISITA_TÉCNICA | X51: 1FZZZ149 | Y51: TIPO I | Z51: TERRESTRE | AA51: CUERO RUIZ JHONNY | AB51: 1 | AC51: 0 | AD51: 0 | AE51: 0 | AF51: =IF(W51="SOPORTE_TELEFÓNICO",'BASE LIQUIDACION'!$B$10,IF(Y51="TIPO I",'BASE LIQUIDACION'!$C$3,IF(Y51="TIPO II",'BASE LIQUIDACION'!$C$4,IF(Y51="TIPO III",'BASE LIQUIDACION'!$C$5,'BASE LIQUIDACION'!$C$7)))) -> 65960.474 | AG51: =IF(W51="SOPORTE_TELEFÓNICO",'BASE LIQUIDACION'!$B$10,(AB51*AF51+AC51*'BASE LIQUIDACION'!$B$12+AD51*'BASE LIQUIDACION'!$B$11+INCIDENTES!AE51*'BASE LIQUIDACION'!$B$13)) -> 65960.474
A52: BOGOTA | B52: =VLOOKUP(A52,'CENTRO DE COSTOS'!A:D,4,FALSE) -> WILLIAM ASDRUBAL ROZO ROZO | C52: =VLOOKUP(A52,'CENTRO DE COSTOS'!A:D,2,FALSE) -> 0004-0004 | D52: 11001 | E52: 2567244 | F52: 74518 | G52: INCIDENTE | H52: CUNDINAMARCA | I52: BOGOTA | J52: BARRIO AURES 2 BOGOTA 3 | K52: REDEBAN | L52: FO-25-1345259 | M52: 45876.531 | N52: 45877.467 | O52: NO | P52: ENTIDAD | Q52: ERROR DE TRANSACCIONES | R52: TRANSACCION NO PERMITIDA | S52: CB UNO A UNO | T52: CB UNO A UNO | U52: CERRADO | V52: 07/08/2025 07-08 SE ESCALA PARA VISITA. LLAMAR ANTES DE VISITAR, CONFIRMAR FALLA Y DATOS | 08/08/2025 SE REALIZA VISITA A DIRECCIÓN DE COMERCIO, ATIENDE EL SR. WILMAR ROMERO QUIEN INFORMA QUE EL DÍA DE HOY EL DATAFONO ESTÁ FUNCIONANDO DE FORMA CORRECTA, SE REALIZA ACOMPAÑAMIENTO Y VALIDACIÓN DE FUNCIONAMIENTO SIN NOVEDAD, NO SE MANIPULA EQUIPOS | W52: VISITA_TÉCNICA | X52: TVDZZ282 | Y52: TIPO I | Z52: TERRESTRE | AA52: MURCIA HERNANDEZ HARVEY IGNACIO | AB52: 1 | AC52: 0 | AD52: 0 | AE52: 0 | AF52: =IF(W52="SOPORTE_TELEFÓNICO",'BASE LIQUIDACION'!$B$10,IF(Y52="TIPO I",'BASE LIQUIDACION'!$C$3,IF(Y52="TIPO II",'BASE LIQUIDACION'!$C$4,IF(Y52="TIPO III",'BASE LIQUIDACION'!$C$5,'BASE LIQUIDACION'!$C$7)))) -> 65960.474 | AG52: =IF(W52="SOPORTE_TELEFÓNICO",'BASE LIQUIDACION'!$B$10,(AB52*AF52+AC52*'BASE LIQUIDACION'!$B$12+AD52*'BASE LIQUIDACION'!$B$11+INCIDENTES!AE52*'BASE LIQUIDACION'!$B$13)) -> 65960.474
A53: MEDELLIN | B53: =VLOOKUP(A53,'CENTRO DE COSTOS'!A:D,4,FALSE) -> JUAN SEBASTIÁN RÍOS CASTRILLÓN | C53: =VLOOKUP(A53,'CENTRO DE COSTOS'!A:D,2,FALSE) -> 0004-0005 | D53: 5001 | E53: 2564850 | F53: 68192 | G53: INCIDENTE | H53: ANTIOQUIA | I53: MEDELLIN | J53: CENTRO MEDELLIN ANTIOQUIA | K53: REDEBAN | L53: FO-25-1340704 | M53: 45875.65 | N53: 45877.599 | O53: NO | P53: USUARIO | Q53: LECTOR DE TARJETAS | R53: OBSTRUCCION DEL LECTOR | S53: CB UNO A UNO | T53: CB UNO A UNO | U53: CERRADO | V53: 06/08/2025 06-08 SE ESCALA PARA VISITA. LLAMAR ANTES DE VISITAR, CONFIRMAR FALLA Y DATOS | 07/08/2025 SE LLAMA A CLIENTE PARA CONFIRMAR VISITA Y COMENTA QUE EL LOCAL NO TIENEN SERVICIO DOMINGOS NI FESTIVOS, SE DEBE REAGENDAR VISITA PARA UN DÍA HÁBIL E INDICA QUE ABRE COMERCIO DESPUÉS DE 9 AM | 08/08/2025 SE REALIZA LIMPIEZA DE LECTOR CHIP CON OBSTRUCCIÓN OK PRUEBAS OK | W53: VISITA_TÉCNICA | X53: A1006413 | Y53: TIPO I | Z53: TERRESTRE | AA53: PAREJA ECHAVARRIA JHON DAVID | AB53: 1 | AC53: 0 | AD53: 0 | AE53: 0 | AF53: =IF(W53="SOPORTE_TELEFÓNICO",'BASE LIQUIDACION'!$B$10,IF(Y53="TIPO I",'BASE LIQUIDACION'!$C$3,IF(Y53="TIPO II",'BASE LIQUIDACION'!$C$4,IF(Y53="TIPO III",'BASE LIQUIDACION'!$C$5,'BASE LIQUIDACION'!$C$7)))) -> 65960.474 | AG53: =IF(W53="SOPORTE_TELEFÓNICO",'BASE LIQUIDACION'!$B$10,(AB53*AF53+AC53*'BASE LIQUIDACION'!$B$12+AD53*'BASE LIQUIDACION'!$B$11+INCIDENTES!AE53*'BASE LIQUIDACION'!$B$13)) -> 65960.474
A54: MEDELLIN | B54: =VLOOKUP(A54,'CENTRO DE COSTOS'!A:D,4,FALSE) -> JUAN SEBASTIÁN RÍOS CASTRILLÓN | C54: =VLOOKUP(A54,'CENTRO DE COSTOS'!A:D,2,FALSE) -> 0004-0005 | D54: 5674 | E54: 2566131 | F54: 66871 | G54: INCIDENTE | H54: ANTIOQUIA | I54: SAN VICENTE | J54: BARRIO CENTRO SAN VICENTE FERR | K54: REDEBAN | L54: FO-25-1342302 | M54: 45876.333 | N54: 45877.64 | O54: NO | P54: USUARIO | Q54: MANTENIMIENTO | R54: MANTENIMIENTO GENERAL | S54: CB UNO A UNO | T54: CB UNO A UNO | U54: CERRADO | V54: 07/08/2025 07-08 SE ESCALA PARA VISITA. LLAMAR ANTES DE VISITAR, CONFIRMAR FALLA Y DATOS | 08/08/2025 SE LLEGA AL SITIO Y SE VERIFICA EQUIPOS, SE ENCUENTRA APAGADO SE REALIZA CAMBIO DE FUENTE DE PODER SE REALIZAN PRUEBAS EXITOSAS SERVICIO OPERATIVO OK | W54: VISITA_TÉCNICA | X54: 4A0AZ399 | Y54: TIPO II | Z54: TERRESTRE | AA54: ZAPATA LOPEZ EDWARD ASDRUBAL | AB54: 1 | AC54: 0 | AD54: 0 | AE54: 0 | AF54: =IF(W54="SOPORTE_TELEFÓNICO",'BASE LIQUIDACION'!$B$10,IF(Y54="TIPO I",'BASE LIQUIDACION'!$C$3,IF(Y54="TIPO II",'BASE LIQUIDACION'!$C$4,IF(Y54="TIPO III",'BASE LIQUIDACION'!$C$5,'BASE LIQUIDACION'!$C$7)))) -> 163813.56 | AG54: =IF(W54="SOPORTE_TELEFÓNICO",'BASE LIQUIDACION'!$B$10,(AB54*AF54+AC54*'BASE LIQUIDACION'!$B$12+AD54*'BASE LIQUIDACION'!$B$11+INCIDENTES!AE54*'BASE LIQUIDACION'!$B$13)) -> 163813.56
A55: CUCUTA | B55: =VLOOKUP(A55,'CENTRO DE COSTOS'!A:D,4,FALSE) -> MIGUEL JULIÁN HERNÁNDEZ GUARÍN | C55: =VLOOKUP(A55,'CENTRO DE COSTOS'!A:D,2,FALSE) -> 0004-0008 | D55: 54810 | E55: 2570971 | F55: 47219 | G55: INCIDENTE | H55: NORTE DE SANTANDER | I55: TIBU | J55: BARRIO FUERA DEL MUNICIPIO DE | K55: REDEBAN | L55: FO-25-1350348 | M55: 45877.527 | N55: 45877.658 | O55: NO | P55: USUARIO | Q55: COMUNICACION | R55: CONEXIONES DE COMERCIO | S55: CB UNO A UNO | T55: CB UNO A UNO | U55: CERRADO | V55: 08/08/2025 8-08 EN COMUNICACIÓN CON EL SEÑOR LUIS RAMÓN RIVEROS TORRADO AL NUMERO 3222170523 INDICA QUE EL DATAFONO NO ESTA IMPRIMIENDO LOS VAUCHER DE MANERA RAPIDA Y LA INFORMACIÓN ESTA MUY BORROSA, CONFIRMA LOS DATOS, SE ESCALA PARA VISITA | 08/08/2025 SE COMUNICA CON EL CLIENTE LUIS RIVEROS, AL # 3222170523, SE LE DA SOPORTE TELEFONICO, NOS INFORMA QUE SE SOLUCIONA EL PROBLEMA, CB OPERATIVO, SE ANEXA TIRILLA ENVIADA POR EL CLIENTE | W55: SOPORTE_TELEFÓNICO | Y55: TIPO IV ESPECIAL | Z55: TERRESTRE | AA55: NARANJO AFANADOR RUBEN JESUS | AB55: 0 | AC55: 0 | AD55: 0 | AE55: 0 | AF55: =IF(W55="SOPORTE_TELEFÓNICO",'BASE LIQUIDACION'!$B$10,IF(Y55="TIPO I",'BASE LIQUIDACION'!$C$3,IF(Y55="TIPO II",'BASE LIQUIDACION'!$C$4,IF(Y55="TIPO III",'BASE LIQUIDACION'!$C$5,'BASE LIQUIDACION'!$C$7)))) -> 37904.654 | AG55: =IF(W55="SOPORTE_TELEFÓNICO",'BASE LIQUIDACION'!$B$10,(AB55*AF55+AC55*'BASE LIQUIDACION'!$B$12+AD55*'BASE LIQUIDACION'!$B$11+INCIDENTES!AE55*'BASE LIQUIDACION'!$B$13)) -> 37904.654
A56: MANIZALES | B56: =VLOOKUP(A56,'CENTRO DE COSTOS'!A:D,4,FALSE) -> DIEGO FERNANDO HENAO CARDONA | C56: =VLOOKUP(A56,'CENTRO DE COSTOS'!A:D,2,FALSE) -> 0004-0002 | D56: 17001 | E56: 2569607 | F56: 46201 | G56: INCIDENTE | H56: CALDAS | I56: MANIZALES | J56: PAGAFACIL TERMINAL MANIZALES | K56: REDEBAN | L56: FO-25-1349445 | M56: 45877.416 | N56: 45878.44 | O56: NO | P56: USUARIO | Q56: MANTENIMIENTO | R56: MANTENIMIENTO GENERAL | S56: ROBUSTO | T56: ROBUSTO | U56: CERRADO | V56: 08/08/2025 08-08 SE ESCALA PARA VISITA. LLAMAR ANTES DE VISITAR, CONFIRMAR FALLA Y DATOS | 08/08/2025 NO SE REALIZA VISITA EL DIA DE HOY YA QUE SE TENIA AGENDADA UNA APERTURA Y POR EL INCONVENIENTE DE LA ASIGNACIÓN DE LAS PLACAS NO SE PUDO VISITAR TEMPRANO, SE VISITARA EL DIA SABADO TENIENDO EN CUENTA QUE LOS CAMBIOS SE REALIZARN A PARTIR DE LAS 9 AM | 09/08/2025 SE REALIZA VISITA SE VALIDA IMPRESION UN POCO BORROSA, SE REALIZA MANTENIMIENTO Y LIMPIEZA QUEDA OPERANDO E IMPRIMIENDO EN BUEN ESTADO SERVICIO OK | W56: VISITA_TÉCNICA | X56: II003202 | Y56: TIPO I | Z56: TERRESTRE | AA56: AGUIRRE HENAO RAUL EDUARDO | AB56: 1 | AC56: 0 | AD56: 0 | AE56: 0 | AF56: =IF(W56="SOPORTE_TELEFÓNICO",'BASE LIQUIDACION'!$B$10,IF(Y56="TIPO I",'BASE LIQUIDACION'!$C$3,IF(Y56="TIPO II",'BASE LIQUIDACION'!$C$4,IF(Y56="TIPO III",'BASE LIQUIDACION'!$C$5,'BASE LIQUIDACION'!$C$7)))) -> 65960.474 | AG56: =IF(W56="SOPORTE_TELEFÓNICO",'BASE LIQUIDACION'!$B$10,(AB56*AF56+AC56*'BASE LIQUIDACION'!$B$12+AD56*'BASE LIQUIDACION'!$B$11+INCIDENTES!AE56*'BASE LIQUIDACION'!$B$13)) -> 65960.474
A57: MEDELLIN | B57: =VLOOKUP(A57,'CENTRO DE COSTOS'!A:D,4,FALSE) -> JUAN SEBASTIÁN RÍOS CASTRILLÓN | C57: =VLOOKUP(A57,'CENTRO DE COSTOS'!A:D,2,FALSE) -> 0004-0005 | D57: 5001 | E57: 2574055 | F57: 41161 | G57: INCIDENTE | H57: ANTIOQUIA | I57: MEDELLIN | J57: PAGAFACIL ARKADIA | K57: REDEBAN | L57: FO-25-1353618 | M57: 45878.41 | N57: 45878.597 | O57: NO | P57: USUARIO | Q57: LECTOR DE TARJETAS | R57: OBSTRUCCION DEL LECTOR | S57: ROBUSTO | T57: ROBUSTO | U57: CERRADO | V57: 09/08/2025 09-08 SE ESCALA PARA VISITA. LLAMAR ANTES DE VISITAR, CONFIRMAR FALLA Y DATOS | 09/08/2025 SE REALIZÓ LIMPIEZA DE LECTOR CHIP | W57: VISITA_TÉCNICA | X57: GZ0OZ428 | Y57: TIPO I | Z57: TERRESTRE | AA57: CASTAÑEDA PALACIO CARLOS FELIPE | AB57: 1 | AC57: 0 | AD57: 0 | AE57: 0 | AF57: =IF(W57="SOPORTE_TELEFÓNICO",'BASE LIQUIDACION'!$B$10,IF(Y57="TIPO I",'BASE LIQUIDACION'!$C$3,IF(Y57="TIPO II",'BASE LIQUIDACION'!$C$4,IF(Y57="TIPO III",'BASE LIQUIDACION'!$C$5,'BASE LIQUIDACION'!$C$7)))) -> 65960.474 | AG57: =IF(W57="SOPORTE_TELEFÓNICO",'BASE LIQUIDACION'!$B$10,(AB57*AF57+AC57*'BASE LIQUIDACION'!$B$12+AD57*'BASE LIQUIDACION'!$B$11+INCIDENTES!AE57*'BASE LIQUIDACION'!$B$13)) -> 65960.474
A58: CALI | B58: =VLOOKUP(A58,'CENTRO DE COSTOS'!A:D,4,FALSE) -> DIEGO FERNANDO HENAO CARDONA | C58: =VLOOKUP(A58,'CENTRO DE COSTOS'!A:D,2,FALSE) -> 0004-0003 | D58: 76670 | E58: 2572074 | F58: 80302 | G58: INCIDENTE | H58: VALLE DEL CAUCA | I58: SAN PEDRO | J58: BARRIO JARDIN SAN PEDRO | K58: REDEBAN | L58: FO-25-1351690 | M58: 45877.636 | N58: 45878.619 | O58: NO | P58: USUARIO | Q58: MANTENIMIENTO | R58: MANTENIMIENTO GENERAL | S58: CB UNO A UNO | T58: CB UNO A UNO | U58: CERRADO | V58: 08/08/2025 08-08 SE ESCALA PARA VISITA. LLAMAR ANTES DE VISITAR, CONFIRMAR FALLA Y DATOS | 09/08/2025 EN LA VISITA TÉCNICA SE REALIZÓ LA REVISIÓN DEL DATÁFONO ENCONTRANDO QUE EL USUARIO ESTABA PONIENDO EL ROLLO DE MANERA ERRADA Y POR ESTE MOTIVO NO SE IMPRIMÍA LA INFORMACIÓN EN LA TIRILLA,SE LE EXPLICÓ COMO POBER EL ROLLO DE MANERA CORRECTA, TAMBIÉN SE REALIZÓ LA REVISIÓN A TODOS LOS EQUIPOS Y ACCESORIOS ENCONTRANDO Y DEJANDO EL SERVICIO OPERANDO DE MANERA CORRECTA Y SIN NOVEDAD | W58: VISITA_TÉCNICA | X58: SAZZZ778 | Y58: TIPO II | Z58: TERRESTRE | AA58: SANCHEZ URREGO ROBINSON DAVID | AB58: 1 | AC58: 0 | AD58: 0 | AE58: 0 | AF58: =IF(W58="SOPORTE_TELEFÓNICO",'BASE LIQUIDACION'!$B$10,IF(Y58="TIPO I",'BASE LIQUIDACION'!$C$3,IF(Y58="TIPO II",'BASE LIQUIDACION'!$C$4,IF(Y58="TIPO III",'BASE LIQUIDACION'!$C$5,'BASE LIQUIDACION'!$C$7)))) -> 163813.56 | AG58: =IF(W58="SOPORTE_TELEFÓNICO",'BASE LIQUIDACION'!$B$10,(AB58*AF58+AC58*'BASE LIQUIDACION'!$B$12+AD58*'BASE LIQUIDACION'!$B$11+INCIDENTES!AE58*'BASE LIQUIDACION'!$B$13)) -> 163813.56
A59: BOGOTA | B59: =VLOOKUP(A59,'CENTRO DE COSTOS'!A:D,4,FALSE) -> WILLIAM ASDRUBAL ROZO ROZO | C59: =VLOOKUP(A59,'CENTRO DE COSTOS'!A:D,2,FALSE) -> 0004-0004 | D59: 25290 | E59: 2574234 | F59: 23055 | G59: INCIDENTE | H59: CUNDINAMARCA | I59: FUSAGASUGA | J59: BARRIO CENTRO III FUSAGASUGA | K59: REDEBAN | L59: FO-25-1354442 | M59: 45878.481 | N59: 45878.625 | O59: NO | P59: USUARIO | Q59: USUARIOS | R59: CREACION DE USUARIOS | S59: CB UNO A UNO | T59: CB UNO A UNO | U59: CERRADO | V59: 09/08/2025 09-08 SE ESCALA PARA VISITA. LLAMAR ANTES DE VISITAR, CONFIRMAR FALLA Y DATOS | 09/08/2025 DURANTE LA VISITA DE TECNICA ENCONTRAMOS QUE DATÁFONO NO LE PERMITE INGRESO AL PANEL DE CORRESPONSAL SE REALIZA CREACIÓN DE USUARIOS CON PRUEBAS OK PARÁMETROS OKAY CIERRE OK USUARIOS OK A CONFORMIDAD DE CORRESPONSAL | W59: VISITA_TÉCNICA | X59: GZZZZ645 | Y59: TIPO II | Z59: TERRESTRE | AA59: GALEANO SORIANO JUAN DAVID | AB59: 1 | AC59: 0 | AD59: 0 | AE59: 0 | AF59: =IF(W59="SOPORTE_TELEFÓNICO",'BASE LIQUIDACION'!$B$10,IF(Y59="TIPO I",'BASE LIQUIDACION'!$C$3,IF(Y59="TIPO II",'BASE LIQUIDACION'!$C$4,IF(Y59="TIPO III",'BASE LIQUIDACION'!$C$5,'BASE LIQUIDACION'!$C$7)))) -> 163813.56 | AG59: =IF(W59="SOPORTE_TELEFÓNICO",'BASE LIQUIDACION'!$B$10,(AB59*AF59+AC59*'BASE LIQUIDACION'!$B$12+AD59*'BASE LIQUIDACION'!$B$11+INCIDENTES!AE59*'BASE LIQUIDACION'!$B$13)) -> 163813.56
A60: CUCUTA | B60: =VLOOKUP(A60,'CENTRO DE COSTOS'!A:D,4,FALSE) -> MIGUEL JULIÁN HERNÁNDEZ GUARÍN | C60: =VLOOKUP(A60,'CENTRO DE COSTOS'!A:D,2,FALSE) -> 0004-0008 | D60: 54874 | E60: 2574501 | F60: 75547 | G60: INCIDENTE | H60: NORTE DE SANTANDER | I60: VILLA DEL ROSARIO | J60: PTM VILLA DEL ROSARIO PLASTIC | K60: REDEBAN | L60: FO-25-1355420 | M60: 45878.635 | N60: 45879.36 | O60: NO | P60: USUARIO | Q60: MANTENIMIENTO | R60: MANTENIMIENTO GENERAL | S60: AGREGADOR | T60: AGREGADOR | U60: CERRADO | V60: 09/08/2025 SE REALIZÓ LLAMADA TELEFÓNICA AL NÚMERO 3505921617 SE HABLÓ CON EL SR RICHARD INDICA QUE YA SOLUCIONO EL INCONVENIENTE CON EL BRILLO DEL DATAFONO Y MANIFIESTA QUE NO DESEA QUE SE REALICE LA VISITA TÉCNICA | W60: SOPORTE_TELEFÓNICO | Y60: TIPO I | Z60: TERRESTRE | AA60: MORA VEGA JEAMPIER | AB60: 0 | AC60: 0 | AD60: 0 | AE60: 0 | AF60: =IF(W60="SOPORTE_TELEFÓNICO",'BASE LIQUIDACION'!$B$10,IF(Y60="TIPO I",'BASE LIQUIDACION'!$C$3,IF(Y60="TIPO II",'BASE LIQUIDACION'!$C$4,IF(Y60="TIPO III",'BASE LIQUIDACION'!$C$5,'BASE LIQUIDACION'!$C$7)))) -> 37904.654 | AG60: =IF(W60="SOPORTE_TELEFÓNICO",'BASE LIQUIDACION'!$B$10,(AB60*AF60+AC60*'BASE LIQUIDACION'!$B$12+AD60*'BASE LIQUIDACION'!$B$11+INCIDENTES!AE60*'BASE LIQUIDACION'!$B$13)) -> 37904.654
A61: MEDELLIN | B61: =VLOOKUP(A61,'CENTRO DE COSTOS'!A:D,4,FALSE) -> JUAN SEBASTIÁN RÍOS CASTRILLÓN | C61: =VLOOKUP(A61,'CENTRO DE COSTOS'!A:D,2,FALSE) -> 0004-0005 | D61: 5001 | E61: 2574381 | F61: 79674 | G61: INCIDENTE | H61: ANTIOQUIA | I61: MEDELLIN | J61: BARRIO CASTILLA MEDELLIN 17 | K61: REDEBAN | L61: FO-25-1354964 | M61: 45878.576 | N61: 45879.412 | O61: NO | P61: USUARIO | Q61: COMUNICACION | R61: CANAL DEL COMERCIO | S61: CB UNO A UNO | T61: CB UNO A UNO | U61: CERRADO | V61: 09/08/2025 09-08 SE ESCALA PARA VISITA. LLAMAR ANTES DE VISITAR, CONFIRMAR FALLA Y DATOS | 10/08/2025 SE REALIZÓ GESTIÓN TELEFÓNICA SE HABLO CON LA SEÑORA FLOR, NOS INDICA QUE LA FALLA SE DEBÍA AL PROVEEDOR DE INTERNET, DESDE EL DÍA DE AYER ESTÁ FUNCIONANDO NORMALMENTE | W61: SOPORTE_TELEFÓNICO | Y61: TIPO I | Z61: TERRESTRE | AA61: CASTAÑEDA PALACIO CARLOS FELIPE | AB61: 0 | AC61: 0 | AD61: 0 | AE61: 0 | AF61: =IF(W61="SOPORTE_TELEFÓNICO",'BASE LIQUIDACION'!$B$10,IF(Y61="TIPO I",'BASE LIQUIDACION'!$C$3,IF(Y61="TIPO II",'BASE LIQUIDACION'!$C$4,IF(Y61="TIPO III",'BASE LIQUIDACION'!$C$5,'BASE LIQUIDACION'!$C$7)))) -> 37904.654 | AG61: =IF(W61="SOPORTE_TELEFÓNICO",'BASE LIQUIDACION'!$B$10,(AB61*AF61+AC61*'BASE LIQUIDACION'!$B$12+AD61*'BASE LIQUIDACION'!$B$11+INCIDENTES!AE61*'BASE LIQUIDACION'!$B$13)) -> 37904.654
A62: MEDELLIN | B62: =VLOOKUP(A62,'CENTRO DE COSTOS'!A:D,4,FALSE) -> JUAN SEBASTIÁN RÍOS CASTRILLÓN | C62: =VLOOKUP(A62,'CENTRO DE COSTOS'!A:D,2,FALSE) -> 0004-0005 | D62: 5001 | E62: 2574160 | F62: 68701 | G62: INCIDENTE | H62: ANTIOQUIA | I62: MEDELLIN | J62: CYBER PLUS COMPUTADORES SAS | K62: REDEBAN | L62: FO-25-1354427 | M62: 45878.485 | N62: 45880.502 | O62: NO | P62: USUARIO | Q62: MANTENIMIENTO | R62: MANTENIMIENTO GENERAL | S62: CB UNO A UNO | T62: CB UNO A UNO | U62: CERRADO | V62: 09/08/2025 09-08 SE ESCALA PARA VISITA. LLAMAR ANTES DE VISITAR, CONFIRMAR FALLA Y DATOS | 10/08/2025 SE REALIZÓ GESTIÓN TELEFÓNICA SE HABLO CON LA SEÑORA ERIKA RODRÍGUEZ EN EL 3016841115 NOS INFORMA QUE LOS DÍAS DOMINGOS NO PRESENTAN ATENCIÓN AL PÚBLICO | 11/08/2025 SE VERIFICA EQUIPO, SE HACEN PRUEBAS PERTINENTES TODAS OK | W62: VISITA_TÉCNICA | X62: 9L0UZ955 | Y62: TIPO I | Z62: TERRESTRE | AA62: HERNANDEZ CHAVARRIA JUAN CAMILO | AB62: 1 | AC62: 0 | AD62: 0 | AE62: 0 | AF62: =IF(W62="SOPORTE_TELEFÓNICO",'BASE LIQUIDACION'!$B$10,IF(Y62="TIPO I",'BASE LIQUIDACION'!$C$3,IF(Y62="TIPO II",'BASE LIQUIDACION'!$C$4,IF(Y62="TIPO III",'BASE LIQUIDACION'!$C$5,'BASE LIQUIDACION'!$C$7)))) -> 65960.474 | AG62: =IF(W62="SOPORTE_TELEFÓNICO",'BASE LIQUIDACION'!$B$10,(AB62*AF62+AC62*'BASE LIQUIDACION'!$B$12+AD62*'BASE LIQUIDACION'!$B$11+INCIDENTES!AE62*'BASE LIQUIDACION'!$B$13)) -> 65960.474
A63: MEDELLIN | B63: =VLOOKUP(A63,'CENTRO DE COSTOS'!A:D,4,FALSE) -> JUAN SEBASTIÁN RÍOS CASTRILLÓN | C63: =VLOOKUP(A63,'CENTRO DE COSTOS'!A:D,2,FALSE) -> 0004-0005 | D63: 5001 | E63: 2574610 | F63: 76844 | G63: INCIDENTE | H63: ANTIOQUIA | I63: MEDELLIN | J63: PTM MEDELLIN MINI MERCADO ARI | K63: REDEBAN | L63: FO-25-1355953 | M63: 45878.728 | N63: 45880.505 | O63: NO | P63: USUARIO | Q63: MANTENIMIENTO | R63: MANTENIMIENTO GENERAL | S63: AGREGADOR | T63: AGREGADOR | U63: CERRADO | V63: 10/08/2025 10-08 SE ESCALA PARA VISITA. LLAMAR ANTES DE VISITAR, CONFIRMAR FALLA Y DATOS | 10/08/2025 SE REALIZÓ GESTIÓN TELEFÓNICA SE HABLO CON EL SEÑOR WILMER FELIPE VANEGAS CHAVERRA EN EL 3216037515 SE DESCONECTA EN VARIAS VECES EL DATÁFONO CONTINUA CON LA PANTALLA EN BLANCO SIN PODER VISUALIZAR LA INFORMACIÓN, SE REQUIERE CAMBIO DE EQUIPO SE POSPONE VISITA PARA EL DÍA LUNES YA QUE LOS DOMINGOS REDEBAN NO TIENE SOPORTE PARA CAMBIAR EL EQUIPO | 11/08/2025 SE LLEGA A PUNTO, USUARIO NO ESTÁ DISPONIBLE, SOLAMENTE DESPUÉS DE MEDIO DIA | W63: VISITA_TÉCNICA | X63: NONE | Y63: TIPO I | Z63: TERRESTRE | AA63: HERNANDEZ CHAVARRIA JUAN CAMILO | AB63: 1 | AC63: 0 | AD63: 0 | AE63: 0 | AF63: =IF(W63="SOPORTE_TELEFÓNICO",'BASE LIQUIDACION'!$B$10,IF(Y63="TIPO I",'BASE LIQUIDACION'!$C$3,IF(Y63="TIPO II",'BASE LIQUIDACION'!$C$4,IF(Y63="TIPO III",'BASE LIQUIDACION'!$C$5,'BASE LIQUIDACION'!$C$7)))) -> 65960.474 | AG63: =IF(W63="SOPORTE_TELEFÓNICO",'BASE LIQUIDACION'!$B$10,(AB63*AF63+AC63*'BASE LIQUIDACION'!$B$12+AD63*'BASE LIQUIDACION'!$B$11+INCIDENTES!AE63*'BASE LIQUIDACION'!$B$13)) -> 65960.474
A64: MEDELLIN | B64: =VLOOKUP(A64,'CENTRO DE COSTOS'!A:D,4,FALSE) -> JUAN SEBASTIÁN RÍOS CASTRILLÓN | C64: =VLOOKUP(A64,'CENTRO DE COSTOS'!A:D,2,FALSE) -> 0004-0005 | D64: 5209 | E64: 2574453 | F64: 31970 | G64: INCIDENTE | H64: ANTIOQUIA | I64: CONCORDIA | J64: COMCARD CONCORDIA MUNDO MOVIL | K64: REDEBAN | L64: FO-25-1355948 | M64: 45878.746 | N64: 45880.544 | O64: NO | P64: USUARIO | Q64: LECTOR DE TARJETAS | R64: OBSTRUCCION DEL LECTOR | S64: AGREGADOR | T64: AGREGADOR | U64: CERRADO | V64: 10/08/2025 10-08 SE ESCALA PARA VISITA. LLAMAR ANTES DE VISITAR, CONFIRMAR FALLA Y DATOS | 11/08/2025 SE REALIZÓ LIMPIEZA DE LECTOR CHIP | W64: VISITA_TÉCNICA | X64: 1111W622 | Y64: TIPO III | Z64: TERRESTRE | AA64: CASTAÑEDA PALACIO CARLOS FELIPE | AB64: 1 | AC64: 0 | AD64: 0 | AE64: 0 | AF64: =IF(W64="SOPORTE_TELEFÓNICO",'BASE LIQUIDACION'!$B$10,IF(Y64="TIPO I",'BASE LIQUIDACION'!$C$3,IF(Y64="TIPO II",'BASE LIQUIDACION'!$C$4,IF(Y64="TIPO III",'BASE LIQUIDACION'!$C$5,'BASE LIQUIDACION'!$C$7)))) -> 275728.38 | AG64: =IF(W64="SOPORTE_TELEFÓNICO",'BASE LIQUIDACION'!$B$10,(AB64*AF64+AC64*'BASE LIQUIDACION'!$B$12+AD64*'BASE LIQUIDACION'!$B$11+INCIDENTES!AE64*'BASE LIQUIDACION'!$B$13)) -> 275728.38
A65: IBAGUE | B65: =VLOOKUP(A65,'CENTRO DE COSTOS'!A:D,4,FALSE) -> KEVIN ALEXIS CORZO BUSTOS | C65: =VLOOKUP(A65,'CENTRO DE COSTOS'!A:D,2,FALSE) -> 0004-0007 | D65: 73268 | E65: 2576101 | F65: 31812 | G65: INCIDENTE | H65: TOLIMA | I65: ESPINAL | J65: BARRIO CABALLERO Y GONGORA ESP | K65: REDEBAN | L65: FO-25-1357818 | M65: 45880.348 | N65: 45880.554 | O65: NO | P65: USUARIO | Q65: COMUNICACION | R65: CONEXIONES DE COMERCIO | S65: CB UNO A UNO | T65: CB UNO A UNO | U65: CERRADO | V65: 11/08/2025 11-08 SE ESCALA PARA VISITA. LLAMAR ANTES DE VISITAR, CONFIRMAR FALLA Y DATOS | 11/08/2025 SE LLEGA AL CORRESPONSAL Y LA SEÑORA NURY VARGAS, ME INDICA QUE EL DATÁFONO ESTÁ FUNCIONANDO CORRECTAMENTE. LE EXPLICO COMO MANEJAR CORRECTAMENTE EL DATÁFONO Y SU APAGADO PARA QUE NO VUELVA A MOLESTAR LAS IMPRESIONES. SE HACEN PRUEBAS DE TRANSACCIONES TODO OK | W65: VISITA_TÉCNICA | X65: 1111K887 - II1ZZ069 | Y65: TIPO II | Z65: TERRESTRE | AA65: VARGAS HERRERA JHON JAIRO | AB65: 1 | AC65: 0 | AD65: 0 | AE65: 0 | AF65: =IF(W65="SOPORTE_TELEFÓNICO",'BASE LIQUIDACION'!$B$10,IF(Y65="TIPO I",'BASE LIQUIDACION'!$C$3,IF(Y65="TIPO II",'BASE LIQUIDACION'!$C$4,IF(Y65="TIPO III",'BASE LIQUIDACION'!$C$5,'BASE LIQUIDACION'!$C$7)))) -> 163813.56 | AG65: =IF(W65="SOPORTE_TELEFÓNICO",'BASE LIQUIDACION'!$B$10,(AB65*AF65+AC65*'BASE LIQUIDACION'!$B$12+AD65*'BASE LIQUIDACION'!$B$11+INCIDENTES!AE65*'BASE LIQUIDACION'!$B$13)) -> 163813.56
A66: MEDELLIN | B66: =VLOOKUP(A66,'CENTRO DE COSTOS'!A:D,4,FALSE) -> JUAN SEBASTIÁN RÍOS CASTRILLÓN | C66: =VLOOKUP(A66,'CENTRO DE COSTOS'!A:D,2,FALSE) -> 0004-0005 | D66: 5129 | E66: 2578493 | F66: 56995 | G66: INCIDENTE | H66: ANTIOQUIA | I66: CALDAS | J66: DISTRICOL TEXTURAS DE PAPEL | K66: REDEBAN | L66: FO-25-1359458 | M66: 45880.463 | N66: 45880.706 | O66: NO | P66: USUARIO | Q66: LECTOR DE TARJETAS | R66: OBSTRUCCION DEL LECTOR | S66: AGREGADOR | T66: AGREGADOR | U66: CERRADO | V66: 23/09/2025 11-08 SE ESCALA PARA VISITA. LLAMAR ANTES DE VISITAR, CONFIRMAR FALLA Y DATOS | 11/08/2025 SE REALIZÓ LIMPIEZA DE LECTOR CHIP | W66: VISITA_TÉCNICA | X66: XPRZZ661 | Y66: TIPO I | Z66: TERRESTRE | AA66: CASTAÑEDA PALACIO CARLOS FELIPE | AB66: 1 | AC66: 0 | AD66: 0 | AE66: 0 | AF66: =IF(W66="SOPORTE_TELEFÓNICO",'BASE LIQUIDACION'!$B$10,IF(Y66="TIPO I",'BASE LIQUIDACION'!$C$3,IF(Y66="TIPO II",'BASE LIQUIDACION'!$C$4,IF(Y66="TIPO III",'BASE LIQUIDACION'!$C$5,'BASE LIQUIDACION'!$C$7)))) -> 65960.474 | AG66: =IF(W66="SOPORTE_TELEFÓNICO",'BASE LIQUIDACION'!$B$10,(AB66*AF66+AC66*'BASE LIQUIDACION'!$B$12+AD66*'BASE LIQUIDACION'!$B$11+INCIDENTES!AE66*'BASE LIQUIDACION'!$B$13)) -> 65960.474
A67: MEDELLIN | B67: =VLOOKUP(A67,'CENTRO DE COSTOS'!A:D,4,FALSE) -> JUAN SEBASTIÁN RÍOS CASTRILLÓN | C67: =VLOOKUP(A67,'CENTRO DE COSTOS'!A:D,2,FALSE) -> 0004-0005 | D67: 5360 | E67: 2580932 | F67: 61338 | G67: INCIDENTE | H67: ANTIOQUIA | I67: ITAGUI | J67: BARRIO SAN FRANCISCO ITAGUI 2 | K67: REDEBAN | L67: FO-25-1361988 | M67: 45880.644 | N67: 45881.445 | O67: NO | P67: USUARIO | Q67: COMUNICACION | R67: CONEXIONES DE COMERCIO | S67: CB UNO A UNO | T67: CB UNO A UNO | U67: CERRADO | V67: 11/08/2025 11-08 SE ESCALA PARA VISITA. LLAMAR ANTES DE VISITAR, CONFIRMAR FALLA Y DATOS | 12/08/2025 E REVISA EQUIPO Y PARÁMETROS TODO OK, TEST DE COMUNICACIÓN EXITOSO, CLIENTE CONFIRMA TRABAJAR SIN PROBLEMAS PROBLEMAS | W67: VISITA_TÉCNICA | X67: HA00J521 | Y67: TIPO I | Z67: TERRESTRE | AA67: HERNANDEZ CHAVARRIA JUAN CAMILO | AB67: 1 | AC67: 0 | AD67: 0 | AE67: 0 | AF67: =IF(W67="SOPORTE_TELEFÓNICO",'BASE LIQUIDACION'!$B$10,IF(Y67="TIPO I",'BASE LIQUIDACION'!$C$3,IF(Y67="TIPO II",'BASE LIQUIDACION'!$C$4,IF(Y67="TIPO III",'BASE LIQUIDACION'!$C$5,'BASE LIQUIDACION'!$C$7)))) -> 65960.474 | AG67: =IF(W67="SOPORTE_TELEFÓNICO",'BASE LIQUIDACION'!$B$10,(AB67*AF67+AC67*'BASE LIQUIDACION'!$B$12+AD67*'BASE LIQUIDACION'!$B$11+INCIDENTES!AE67*'BASE LIQUIDACION'!$B$13)) -> 65960.474
A68: MONTERIA | B68: =VLOOKUP(A68,'CENTRO DE COSTOS'!A:D,4,FALSE) -> JOSE MAURICIO HERNANDEZ ROJAS | C68: =VLOOKUP(A68,'CENTRO DE COSTOS'!A:D,2,FALSE) -> 0004-0001 | D68: 5154 | E68: 2576357 | F68: 52871 | G68: INCIDENTE | H68: ANTIOQUIA | I68: CAUCASIA | J68: BARRIO CARACOLI CAUCASIA | K68: REDEBAN | L68: FO-25-1358508 | M68: 45880.369 | N68: 45881.485 | O68: NO | P68: USUARIO | Q68: COMUNICACION | R68: CANAL DEL COMERCIO | S68: CB UNO A UNO | T68: CB UNO A UNO | U68: CERRADO | V68: 11/08/2025 11-08 SE ESCALA PARA VISITA. LLAMAR ANTES DE VISITAR, CONFIRMAR FALLA Y DATOS | 12/08/2025 SE VISITA SITIO, SE ENCUENTRA DATAFONO OPERATIVO, POSIBLE PROBLEMA CON CANAL DE COMUNICACIÓN DEL CB SE REALIZAN AJUSTEN EN CONEXIONES OK. PRUEBAS EXITOSAS | W68: VISITA_TÉCNICA | X68: BA0IZ174 | Y68: TIPO II | Z68: TERRESTRE | AA68: COGOLLO VERTEL EDER LUIS | AB68: 1 | AC68: 0 | AD68: 0 | AE68: 0 | AF68: =IF(W68="SOPORTE_TELEFÓNICO",'BASE LIQUIDACION'!$B$10,IF(Y68="TIPO I",'BASE LIQUIDACION'!$C$3,IF(Y68="TIPO II",'BASE LIQUIDACION'!$C$4,IF(Y68="TIPO III",'BASE LIQUIDACION'!$C$5,'BASE LIQUIDACION'!$C$7)))) -> 163813.56 | AG68: =IF(W68="SOPORTE_TELEFÓNICO",'BASE LIQUIDACION'!$B$10,(AB68*AF68+AC68*'BASE LIQUIDACION'!$B$12+AD68*'BASE LIQUIDACION'!$B$11+INCIDENTES!AE68*'BASE LIQUIDACION'!$B$13)) -> 163813.56
A69: CALI | B69: =VLOOKUP(A69,'CENTRO DE COSTOS'!A:D,4,FALSE) -> DIEGO FERNANDO HENAO CARDONA | C69: =VLOOKUP(A69,'CENTRO DE COSTOS'!A:D,2,FALSE) -> 0004-0003 | D69: 76001 | E69: 2580867 | F69: 74005 | G69: INCIDENTE | H69: VALLE DEL CAUCA | I69: CALI | J69: BARRIO OBRERO CALI 6 | K69: REDEBAN | L69: FO-25-1361991 | M69: 45880.643 | N69: 45881.508 | O69: NO | P69: USUARIO | Q69: COMUNICACION | R69: CONEXIONES DE COMERCIO | S69: CB UNO A UNO | T69: CB UNO A UNO | U69: CERRADO | V69: 11/08/2025 11-08 SE ESCALA PARA VISITA. LLAMAR ANTES DE VISITAR, CONFIRMAR FALLA Y DATOS | 12/08/2025 SE REVISA CABLEADO TODO ESTA OK SE LE HACE MANTENIMIENTO AL EQUIPO Y QUEDA FUNCIONANDO CORRECTAMENTE | W69: VISITA_TÉCNICA | X69: MM0SZ910 | Y69: TIPO I | Z69: TERRESTRE | AA69: CUERO RUIZ JHONNY | AB69: 1 | AC69: 0 | AD69: 0 | AE69: 0 | AF69: =IF(W69="SOPORTE_TELEFÓNICO",'BASE LIQUIDACION'!$B$10,IF(Y69="TIPO I",'BASE LIQUIDACION'!$C$3,IF(Y69="TIPO II",'BASE LIQUIDACION'!$C$4,IF(Y69="TIPO III",'BASE LIQUIDACION'!$C$5,'BASE LIQUIDACION'!$C$7)))) -> 65960.474 | AG69: =IF(W69="SOPORTE_TELEFÓNICO",'BASE LIQUIDACION'!$B$10,(AB69*AF69+AC69*'BASE LIQUIDACION'!$B$12+AD69*'BASE LIQUIDACION'!$B$11+INCIDENTES!AE69*'BASE LIQUIDACION'!$B$13)) -> 65960.474
A70: MONTERIA | B70: =VLOOKUP(A70,'CENTRO DE COSTOS'!A:D,4,FALSE) -> JOSE MAURICIO HERNANDEZ ROJAS | C70: =VLOOKUP(A70,'CENTRO DE COSTOS'!A:D,2,FALSE) -> 0004-0001 | D70: 23855 | E70: 2582605 | F70: 75531 | G70: INCIDENTE | H70: CORDOBA | I70: VALENCIA | J70: PTM VALENCIA BARUEK CAFETERIA | K70: REDEBAN | L70: FO-25-1363392 | M70: 45881.333 | N70: 45881.577 | O70: NO | P70: USUARIO | Q70: USUARIOS | R70: USUARIOS BLOQUEADOS | S70: AGREGADOR | T70: AGREGADOR | U70: CERRADO | V70: 12/08/2025 11-08 SE ESCALA PARA VISITA. LLAMAR ANTES DE VISITAR, CONFIRMAR FALLA Y DATOS | 12/08/2025 SE REALIZA VISITA TÉCNICA Y SE CONFIGURAN NUEVAMENTE LOS USUARIOS LOS CUALES SE ENCUENTRAN BLOQUEADOS, S CREAN NUEVAMENTE Y SE DEJA EL SERVICIO FUNCIONANDO CORRECTAMENTE . | W70: VISITA_TÉCNICA | X70: SX00J088 | Y70: TIPO III | Z70: TERRESTRE | AA70: CASSIANI PEREZ RAUL RAMIRO | AB70: 1 | AC70: 0 | AD70: 0 | AE70: 0 | AF70: =IF(W70="SOPORTE_TELEFÓNICO",'BASE LIQUIDACION'!$B$10,IF(Y70="TIPO I",'BASE LIQUIDACION'!$C$3,IF(Y70="TIPO II",'BASE LIQUIDACION'!$C$4,IF(Y70="TIPO III",'BASE LIQUIDACION'!$C$5,'BASE LIQUIDACION'!$C$7)))) -> 275728.38 | AG70: =IF(W70="SOPORTE_TELEFÓNICO",'BASE LIQUIDACION'!$B$10,(AB70*AF70+AC70*'BASE LIQUIDACION'!$B$12+AD70*'BASE LIQUIDACION'!$B$11+INCIDENTES!AE70*'BASE LIQUIDACION'!$B$13)) -> 275728.38
A71: APARTADO | B71: =VLOOKUP(A71,'CENTRO DE COSTOS'!A:D,4,FALSE) -> JUAN SEBASTIÁN RÍOS CASTRILLÓN | C71: =VLOOKUP(A71,'CENTRO DE COSTOS'!A:D,2,FALSE) -> 0004-0005 | D71: 27615 | E71: 2574432 | F71: 34023 | G71: INCIDENTE | H71: CHOCO | I71: RIOSUCIO | J71: DISTRICOL TRILLADORA AGROCENTR | K71: REDEBAN | L71: FO-25-1355965 | M71: 45878.672 | N71: 45881.688 | O71: NO | P71: USUARIO | Q71: COMUNICACION | R71: CONEXIONES DE COMERCIO | S71: AGREGADOR | T71: AGREGADOR | U71: CERRADO | V71: 10/08/2025 10-08 SE ESCALA PARA VISITA. LLAMAR ANTES DE VISITAR, CONFIRMAR FALLA Y DATOS | 12/08/2025 SE REPISA PARÁMETROS Y DATAFONO QUEDA OPERATIVO. | W71: VISITA_TÉCNICA | X71: 9A00Q589 | Y71: TIPO IV ESPECIAL | Z71: TERRESTRE/FLUVIAL | AA71: CASTRO HENAO DANIEL ESTEBAN | AB71: 1 | AC71: 0 | AD71: 0 | AE71: 0 | AF71: =IF(W71="SOPORTE_TELEFÓNICO",'BASE LIQUIDACION'!$B$10,IF(Y71="TIPO I",'BASE LIQUIDACION'!$C$3,IF(Y71="TIPO II",'BASE LIQUIDACION'!$C$4,IF(Y71="TIPO III",'BASE LIQUIDACION'!$C$5,'BASE LIQUIDACION'!$C$7)))) -> 479589.74 | AG71: =IF(W71="SOPORTE_TELEFÓNICO",'BASE LIQUIDACION'!$B$10,(AB71*AF71+AC71*'BASE LIQUIDACION'!$B$12+AD71*'BASE LIQUIDACION'!$B$11+INCIDENTES!AE71*'BASE LIQUIDACION'!$B$13)) -> 479589.74
A72: SINCELEJO | B72: =VLOOKUP(A72,'CENTRO DE COSTOS'!A:D,4,FALSE) -> JOSE MAURICIO HERNANDEZ ROJAS | C72: =VLOOKUP(A72,'CENTRO DE COSTOS'!A:D,2,FALSE) -> 0004-0001 | D72: 70001 | E72: 2583342 | F72: 38719 | G72: INCIDENTE | H72: SUCRE | I72: SINCELEJO | J72: BARRIO EL CORTIJO SINCELEJO | K72: REDEBAN | L72: FO-25-1363786 | M72: 45881.351 | N72: 45881.698 | O72: NO | P72: USUARIO | Q72: COMUNICACION | R72: CANAL DEL COMERCIO | S72: CB UNO A UNO | T72: CB UNO A UNO | U72: CERRADO | V72: 12/08/2025 11-08 17:47 EN COMUNICACIÓN CON LA SEÑORA ELIZBETH JIMENEZ AL NUMERO 3107839160 INDICA QUE EL DATAFONO LE ARROJA CONECTANDO Y LUEGO LE DICE ERROR DE CONEXIÓN, CONFIRMA DATOS, SE ESCALA PARA VISITA | 12/08/2025 SE VISITA COMERCIO, SE VERIFICAN LOS DATAFONOS PERO ESTÁN FUNCIONANDO CORRECTAMENTE, EN LA MAÑANA TUVIERON UN PROBLEMA DE CONEXIÓN PERO YA SE SOLUCIONÓ, SE REALIZAN PRUEBAS OK. | W72: VISITA_TÉCNICA | X72: EG0IZ237 - GZ00Z040 | Y72: TIPO I | Z72: TERRESTRE | AA72: CACERES HERNANDEZ ANDRES | AB72: 1 | AC72: 0 | AD72: 0 | AE72: 0 | AF72: =IF(W72="SOPORTE_TELEFÓNICO",'BASE LIQUIDACION'!$B$10,IF(Y72="TIPO I",'BASE LIQUIDACION'!$C$3,IF(Y72="TIPO II",'BASE LIQUIDACION'!$C$4,IF(Y72="TIPO III",'BASE LIQUIDACION'!$C$5,'BASE LIQUIDACION'!$C$7)))) -> 65960.474 | AG72: =IF(W72="SOPORTE_TELEFÓNICO",'BASE LIQUIDACION'!$B$10,(AB72*AF72+AC72*'BASE LIQUIDACION'!$B$12+AD72*'BASE LIQUIDACION'!$B$11+INCIDENTES!AE72*'BASE LIQUIDACION'!$B$13)) -> 65960.474
A73: BUCARAMANGA | B73: =VLOOKUP(A73,'CENTRO DE COSTOS'!A:D,4,FALSE) -> MIGUEL JULIÁN HERNÁNDEZ GUARÍN | C73: =VLOOKUP(A73,'CENTRO DE COSTOS'!A:D,2,FALSE) -> 0004-0008 | D73: 68307 | E73: 2584645 | F73: 73607 | G73: INCIDENTE | H73: SANTANDER | I73: GIRON | J73: PTM LA REPUBLICA GIRON SUPERME | K73: REDEBAN | L73: FO-25-1364630 | M73: 45881.421 | N73: 45881.713 | O73: NO | P73: USUARIO | Q73: NO ENCIENDE | R73: CONEXIONES DE COMERCIO | S73: AGREGADOR | T73: AGREGADOR | U73: CERRADO | V73: 12/08/2025 12-08 SE ESCALA PARA VISITA. LLAMAR ANTES DE VISITAR, CONFIRMAR FALLA Y DATOS | 12/08/2025 EN COMUNICACIÓN CON LA SEÑORA MARYI AL MOVIL 3212449499, SE CONFIRMA QUE EL EQUIPO ESTA OPERANDO CORRECTAMENTE Y NO REQUIERE DE VISITA TECNICA. | W73: SOPORTE_TELEFÓNICO | X73: 0 | Y73: TIPO I | Z73: TERRESTRE | AA73: SANTOS GONZALEZ JOHAN FABIAN | AB73: 0 | AC73: 0 | AD73: 0 | AE73: 0 | AF73: =IF(W73="SOPORTE_TELEFÓNICO",'BASE LIQUIDACION'!$B$10,IF(Y73="TIPO I",'BASE LIQUIDACION'!$C$3,IF(Y73="TIPO II",'BASE LIQUIDACION'!$C$4,IF(Y73="TIPO III",'BASE LIQUIDACION'!$C$5,'BASE LIQUIDACION'!$C$7)))) -> 37904.654 | AG73: =IF(W73="SOPORTE_TELEFÓNICO",'BASE LIQUIDACION'!$B$10,(AB73*AF73+AC73*'BASE LIQUIDACION'!$B$12+AD73*'BASE LIQUIDACION'!$B$11+INCIDENTES!AE73*'BASE LIQUIDACION'!$B$13)) -> 37904.654
A74: CALI | B74: =VLOOKUP(A74,'CENTRO DE COSTOS'!A:D,4,FALSE) -> DIEGO FERNANDO HENAO CARDONA | C74: =VLOOKUP(A74,'CENTRO DE COSTOS'!A:D,2,FALSE) -> 0004-0003 | D74: 76364 | E74: 2580599 | F74: 41053 | G74: INCIDENTE | H74: VALLE DEL CAUCA | I74: JAMUNDI | J74: PTM JAMUNDI SARAPA | K74: REDEBAN | L74: FO-25-1362006 | M74: 45880.635 | N74: 45881.722 | O74: NO | P74: USUARIO | Q74: COMUNICACION | R74: CANAL DEL COMERCIO | S74: AGREGADOR | T74: AGREGADOR | U74: CERRADO | V74: 11/08/2025 11-08 SE ESCALA PARA VISITA. LLAMAR ANTES DE VISITAR, CONFIRMAR FALLA Y DATOS | 12/08/2025 SE REALIZA GESTIÓN TELEFÓNICA ANTES DE REALIZAR LA VISITA Y LA SRA. GLORIA GÓMEZ INDICA QUE EL CB YA SE ENCUENTRA OPERANDO CON NORMALIDAD DEBIDO A QUE LA FALLA PROVENÍA DEL INTERNET LOCAL. | W74: SOPORTE_TELEFÓNICO | X74: 0 | Y74: TIPO II | Z74: TERRESTRE | AA74: MONTERO MUESES GIAN CARLO | AB74: 0 | AC74: 0 | AD74: 0 | AE74: 0 | AF74: =IF(W74="SOPORTE_TELEFÓNICO",'BASE LIQUIDACION'!$B$10,IF(Y74="TIPO I",'BASE LIQUIDACION'!$C$3,IF(Y74="TIPO II",'BASE LIQUIDACION'!$C$4,IF(Y74="TIPO III",'BASE LIQUIDACION'!$C$5,'BASE LIQUIDACION'!$C$7)))) -> 37904.654 | AG74: =IF(W74="SOPORTE_TELEFÓNICO",'BASE LIQUIDACION'!$B$10,(AB74*AF74+AC74*'BASE LIQUIDACION'!$B$12+AD74*'BASE LIQUIDACION'!$B$11+INCIDENTES!AE74*'BASE LIQUIDACION'!$B$13)) -> 37904.654
A75: MEDELLIN | B75: =VLOOKUP(A75,'CENTRO DE COSTOS'!A:D,4,FALSE) -> JUAN SEBASTIÁN RÍOS CASTRILLÓN | C75: =VLOOKUP(A75,'CENTRO DE COSTOS'!A:D,2,FALSE) -> 0004-0005 | D75: 5266 | E75: 2584198 | F75: 39215 | G75: INCIDENTE | H75: ANTIOQUIA | I75: ENVIGADO | J75: BARRIO BARRIO MESA ENVIGADO | K75: REDEBAN | L75: FO-25-1364356 | M75: 45881.401 | N75: 45882.372 | O75: NO | P75: USUARIO | Q75: LECTOR DE TARJETAS | R75: OBSTRUCCION DEL LECTOR | S75: CB UNO A UNO | T75: CB UNO A UNO | U75: CERRADO | V75: 12/08/2025 11-08 SE ESCALA PARA VISITA. LLAMAR ANTES DE VISITAR, CONFIRMAR FALLA Y DATOS | 13/08/2025 SE REALIZÓ LIMPIEZA DE LECTOR DE CHIP | W75: VISITA_TÉCNICA | X75: GZ05Z998 | Y75: TIPO I | Z75: TERRESTRE | AA75: CASTAÑEDA PALACIO CARLOS FELIPE | AB75: 1 | AC75: 0 | AD75: 0 | AE75: 0 | AF75: =IF(W75="SOPORTE_TELEFÓNICO",'BASE LIQUIDACION'!$B$10,IF(Y75="TIPO I",'BASE LIQUIDACION'!$C$3,IF(Y75="TIPO II",'BASE LIQUIDACION'!$C$4,IF(Y75="TIPO III",'BASE LIQUIDACION'!$C$5,'BASE LIQUIDACION'!$C$7)))) -> 65960.474 | AG75: =IF(W75="SOPORTE_TELEFÓNICO",'BASE LIQUIDACION'!$B$10,(AB75*AF75+AC75*'BASE LIQUIDACION'!$B$12+AD75*'BASE LIQUIDACION'!$B$11+INCIDENTES!AE75*'BASE LIQUIDACION'!$B$13)) -> 65960.474
A76: BARRANQUILLA | B76: =VLOOKUP(A76,'CENTRO DE COSTOS'!A:D,4,FALSE) -> JOSE MAURICIO HERNANDEZ ROJAS | C76: =VLOOKUP(A76,'CENTRO DE COSTOS'!A:D,2,FALSE) -> 0004-0001 | D76: 8001 | E76: 2585253 | F76: 25226 | G76: INCIDENTE | H76: ATLANTICO | I76: BARRANQUILLA | J76: ARA0103 BARRANQUILLA LA PRADER | K76: REDEBAN | L76: FO-25-1364981 | M76: 45881.448 | N76: 45882.398 | O76: NO | P76: USUARIO | Q76: MANTENIMIENTO | R76: MANTENIMIENTO GENERAL | S76: RETAIL | T76: RETAIL | U76: CERRADO | V76: 13/08/2025 13-08 SE ESCALA A LA RED, SE PROCEDE A CERRAR YA QUE NO ATENDEMOS CADENA ARA - XX-08 TU SOLICITUD REFERENTE A GENERACIÓN DE CASOS CB ARA BANCOLOMBIA QUEDÓ RADICADA BAJO EL TICKET NÚMERO XXXXXX AL ÁREA ENCARGADA. | 13/08/2025 13-08 SE ESCALA A LA RED, SE PROCEDE A CERRAR YA QUE NO ATENDEMOS CADENA ARA - 13-08 TU SOLICITUD REFERENTE A GENERACIÓN DE CASOS CB ARA BANCOLOMBIA QUEDÓ RADICADA BAJO EL TICKET NÚMERO 5755587 AL ÁREA ENCARGADA. | W76: SOPORTE_TELEFÓNICO | Y76: TIPO I | Z76: TERRESTRE | AA76: AYALA ROMERO MAYKOL DANILO | AB76: 0 | AC76: 0 | AD76: 0 | AE76: 0 | AF76: =IF(W76="SOPORTE_TELEFÓNICO",'BASE LIQUIDACION'!$B$10,IF(Y76="TIPO I",'BASE LIQUIDACION'!$C$3,IF(Y76="TIPO II",'BASE LIQUIDACION'!$C$4,IF(Y76="TIPO III",'BASE LIQUIDACION'!$C$5,'BASE LIQUIDACION'!$C$7)))) -> 37904.654 | AG76: =IF(W76="SOPORTE_TELEFÓNICO",'BASE LIQUIDACION'!$B$10,(AB76*AF76+AC76*'BASE LIQUIDACION'!$B$12+AD76*'BASE LIQUIDACION'!$B$11+INCIDENTES!AE76*'BASE LIQUIDACION'!$B$13)) -> 37904.654
A77: MEDELLIN | B77: =VLOOKUP(A77,'CENTRO DE COSTOS'!A:D,4,FALSE) -> JUAN SEBASTIÁN RÍOS CASTRILLÓN | C77: =VLOOKUP(A77,'CENTRO DE COSTOS'!A:D,2,FALSE) -> 0004-0005 | D77: 5679 | E77: 2581583 | F77: 34543 | G77: INCIDENTE | H77: ANTIOQUIA | I77: SANTA BARBARA | J77: BARRIO CENTRO SANTA BARBARA 1 | K77: REDEBAN | L77: FO-25-1362367 | M77: 45880.685 | N77: 45882.451 | O77: NO | P77: USUARIO | Q77: MANTENIMIENTO | R77: MANTENIMIENTO GENERAL | S77: CB UNO A UNO | T77: CB UNO A UNO | U77: CERRADO | V77: 11/08/2025 11-08 SE ESCALA PARA VISITA. LLAMAR ANTES DE VISITAR, CONFIRMAR FALLA Y DATOS | 13/08/2025 SE REALIZA CAMBIO DE TAPA DE IMPRESORA PORQUE ESTA ROTA | W77: VISITA_TÉCNICA | X77: BL01B620 | Y77: TIPO II | Z77: TERRESTRE | AA77: HERNANDEZ CHAVARRIA JUAN CAMILO | AB77: 1 | AC77: 0 | AD77: 0 | AE77: 0 | AF77: =IF(W77="SOPORTE_TELEFÓNICO",'BASE LIQUIDACION'!$B$10,IF(Y77="TIPO I",'BASE LIQUIDACION'!$C$3,IF(Y77="TIPO II",'BASE LIQUIDACION'!$C$4,IF(Y77="TIPO III",'BASE LIQUIDACION'!$C$5,'BASE LIQUIDACION'!$C$7)))) -> 163813.56 | AG77: =IF(W77="SOPORTE_TELEFÓNICO",'BASE LIQUIDACION'!$B$10,(AB77*AF77+AC77*'BASE LIQUIDACION'!$B$12+AD77*'BASE LIQUIDACION'!$B$11+INCIDENTES!AE77*'BASE LIQUIDACION'!$B$13)) -> 163813.56
A78: BOGOTA | B78: =VLOOKUP(A78,'CENTRO DE COSTOS'!A:D,4,FALSE) -> WILLIAM ASDRUBAL ROZO ROZO | C78: =VLOOKUP(A78,'CENTRO DE COSTOS'!A:D,2,FALSE) -> 0004-0004 | D78: 11001 | E78: 2590360 | F78: 79279 | G78: INCIDENTE | H78: CUNDINAMARCA | I78: BOGOTA | J78: BARRIO SANTA MARIA DEL LAGO BO | K78: REDEBAN | L78: FO-25-1370148 | M78: 45882.383 | N78: 45882.575 | O78: NO | P78: USUARIO | Q78: MANTENIMIENTO | R78: MANTENIMIENTO GENERAL | S78: CB UNO A UNO | T78: CB UNO A UNO | U78: CERRADO | V78: 13/08/2025 13-08 SE ESCALA PARA VISITA. LLAMAR ANTES DE VISITAR, CONFIRMAR FALLA Y DATOS | 13/08/2025 SE REALIZA DESPLAZAMIENTO A DIRECCIÓN DE COMERCIO, AL LLEGAR SE ENCUENTRA CERRADO, SE REALIZA LLAMADA DE VALIDACIÓN SE HABLA CON LA SRTA.NATALIA NIÑO QUIEN INFORMA QUE REGRESA AL COMERCIO A LAS 2:15, SE INFORMA A COORDINACIÓN DE PROYECTO QUIEN INDICA CERRAR LA TAREA E INFORMAR AL CLIENTE QUE DEBE SOLICITAR EL SERVICIO DE NUEVO. | W78: VISITA_TÉCNICA | X78: A4WZZ806 | Y78: TIPO I | Z78: TERRESTRE | AA78: MURCIA HERNANDEZ HARVEY IGNACIO | AB78: 1 | AC78: 0 | AD78: 0 | AE78: 0 | AF78: =IF(W78="SOPORTE_TELEFÓNICO",'BASE LIQUIDACION'!$B$10,IF(Y78="TIPO I",'BASE LIQUIDACION'!$C$3,IF(Y78="TIPO II",'BASE LIQUIDACION'!$C$4,IF(Y78="TIPO III",'BASE LIQUIDACION'!$C$5,'BASE LIQUIDACION'!$C$7)))) -> 65960.474 | AG78: =IF(W78="SOPORTE_TELEFÓNICO",'BASE LIQUIDACION'!$B$10,(AB78*AF78+AC78*'BASE LIQUIDACION'!$B$12+AD78*'BASE LIQUIDACION'!$B$11+INCIDENTES!AE78*'BASE LIQUIDACION'!$B$13)) -> 65960.474
A79: TUNJA | B79: =VLOOKUP(A79,'CENTRO DE COSTOS'!A:D,4,FALSE) -> MIGUEL JULIÁN HERNÁNDEZ GUARÍN | C79: =VLOOKUP(A79,'CENTRO DE COSTOS'!A:D,2,FALSE) -> 0004-0008 | D79: 15176 | E79: 2588890 | F79: 70551 | G79: INCIDENTE | H79: BOYACA | I79: CHIQUINQUIRA | J79: BARRIO BOYACA BAJO CHIQUINQUIR | K79: REDEBAN | L79: FO-25-1369242 | M79: 45882.333 | N79: 45882.647 | O79: NO | P79: USUARIO | Q79: CIERRE | R79: COMERCIO NO REALIZA CIERRE | S79: CB UNO A UNO | T79: CB UNO A UNO | U79: CERRADO | V79: 13/08/2025 13-08 SE ESCALA PARA VISITA. LLAMAR ANTES DE VISITAR, CONFIRMAR FALLA Y DATOS | 13/08/2025 SE VISITA PUNTO EVIDENCIANDO QUE EL EQUIPO TIENE ACOMULADO EL CIERRE EQUIPO NO ARROJA EL CIERRE CLIENTE AUTORIZA RELIZAR BORRADO SE RELIZAR MANTENIMIENTO GENERAL AL EQUIPO PRUEBAS OK SE LE INDICA AL CLIENTE LA FORMA CORRECTA DE REALIZAR LOS CIERRES DIARIOS CLIENTE CONFORME | W79: VISITA_TÉCNICA | X79: SV005489 | Y79: TIPO III | Z79: TERRESTRE | AA79: RODRIGUEZ MURCIA YERSON IVAN | AB79: 1 | AC79: 0 | AD79: 0 | AE79: 0 | AF79: =IF(W79="SOPORTE_TELEFÓNICO",'BASE LIQUIDACION'!$B$10,IF(Y79="TIPO I",'BASE LIQUIDACION'!$C$3,IF(Y79="TIPO II",'BASE LIQUIDACION'!$C$4,IF(Y79="TIPO III",'BASE LIQUIDACION'!$C$5,'BASE LIQUIDACION'!$C$7)))) -> 275728.38 | AG79: =IF(W79="SOPORTE_TELEFÓNICO",'BASE LIQUIDACION'!$B$10,(AB79*AF79+AC79*'BASE LIQUIDACION'!$B$12+AD79*'BASE LIQUIDACION'!$B$11+INCIDENTES!AE79*'BASE LIQUIDACION'!$B$13)) -> 275728.38
A80: PEREIRA | B80: =VLOOKUP(A80,'CENTRO DE COSTOS'!A:D,4,FALSE) -> DIEGO FERNANDO HENAO CARDONA | C80: =VLOOKUP(A80,'CENTRO DE COSTOS'!A:D,2,FALSE) -> 0004-0002 | D80: 66001 | E80: 2592357 | F80: 80907 | G80: INCIDENTE | H80: RISARALDA | I80: PEREIRA | J80: BARRIO CENTRO PEREIRA 52 | K80: REDEBAN | L80: FO-25-1371302 | M80: 45882.499 | N80: 45882.659 | O80: NO | P80: USUARIO | Q80: COMUNICACION | R80: CANAL DEL COMERCIO | S80: CB UNO A UNO | T80: CB UNO A UNO | U80: CERRADO | V80: 13/08/2025 13-08 SE ESCALA PARA VISITA. LLAMAR ANTES DE VISITAR, CONFIRMAR FALLA Y DATOS | 13/08/2025 SE VISITA COMERCIO SE IDENTIFICA DATÁFONO SIN CONEXIÓN SE REINICIA ROUTER PRUEBA DE CONEXIÓN OK SE REALIZA PRUEBAS OK | W80: VISITA_TÉCNICA | X80: FGZZZ931 | Y80: TIPO I | Z80: TERRESTRE | AA80: LOAIZA LOPEZ JHON FREDDY | AB80: 1 | AC80: 0 | AD80: 0 | AE80: 0 | AF80: =IF(W80="SOPORTE_TELEFÓNICO",'BASE LIQUIDACION'!$B$10,IF(Y80="TIPO I",'BASE LIQUIDACION'!$C$3,IF(Y80="TIPO II",'BASE LIQUIDACION'!$C$4,IF(Y80="TIPO III",'BASE LIQUIDACION'!$C$5,'BASE LIQUIDACION'!$C$7)))) -> 65960.474 | AG80: =IF(W80="SOPORTE_TELEFÓNICO",'BASE LIQUIDACION'!$B$10,(AB80*AF80+AC80*'BASE LIQUIDACION'!$B$12+AD80*'BASE LIQUIDACION'!$B$11+INCIDENTES!AE80*'BASE LIQUIDACION'!$B$13)) -> 65960.474
A81: TUNJA | B81: =VLOOKUP(A81,'CENTRO DE COSTOS'!A:D,4,FALSE) -> MIGUEL JULIÁN HERNÁNDEZ GUARÍN | C81: =VLOOKUP(A81,'CENTRO DE COSTOS'!A:D,2,FALSE) -> 0004-0008 | D81: 15806 | E81: 2587952 | F81: 34861 | G81: INCIDENTE | H81: BOYACA | I81: TIBASOSA | J81: BARRIO SECTOR PUERTO AREPAS TI | K81: REDEBAN | L81: FO-25-1368254 | M81: 45881.665 | N81: 45882.739 | O81: NO | P81: USUARIO | Q81: COMUNICACION | R81: CANAL DEL COMERCIO | S81: CB UNO A UNO | T81: CB UNO A UNO | U81: CERRADO | V81: 12/08/2025 12-08 SE ESCALA PARA VISITA. LLAMAR ANTES DE VISITAR, CONFIRMAR FALLA Y DATOS | 13/08/2025 EN COMUNICACIÓN CON EL ADMINISTRADOR WILLIAM JAVIER MONTIER AL CELULAR 3208398637, PARA VERIFICAR DIRECCIÓN, INFORMA QUE YA NO NECESITA LA VISITA TÉCNICA, QUE YA LE ESTÁ FUNCIONANDO CORRECTAMENTE EL DATÁFONO, QUE LA FALLA LA TENÍA EN EL PROVEEDOR DEL INTERNET, SE PROCEDE A CERRAR ORDEN CANCELADA POR ADMINISTRADOR, SE INFORMA QUE SI LE PRESTA ALGUNA FALLA DEBE VOLVER A SOLICITAR NUEVA VISITA. | W81: SOPORTE_TELEFÓNICO | X81: 0 | Y81: TIPO II | Z81: TERRESTRE | AA81: MARTINEZ FLOREZ DONIS ALBERTO | AB81: 0 | AC81: 0 | AD81: 0 | AE81: 0 | AF81: =IF(W81="SOPORTE_TELEFÓNICO",'BASE LIQUIDACION'!$B$10,IF(Y81="TIPO I",'BASE LIQUIDACION'!$C$3,IF(Y81="TIPO II",'BASE LIQUIDACION'!$C$4,IF(Y81="TIPO III",'BASE LIQUIDACION'!$C$5,'BASE LIQUIDACION'!$C$7)))) -> 37904.654 | AG81: =IF(W81="SOPORTE_TELEFÓNICO",'BASE LIQUIDACION'!$B$10,(AB81*AF81+AC81*'BASE LIQUIDACION'!$B$12+AD81*'BASE LIQUIDACION'!$B$11+INCIDENTES!AE81*'BASE LIQUIDACION'!$B$13)) -> 37904.654
A82: BUCARAMANGA | B82: =VLOOKUP(A82,'CENTRO DE COSTOS'!A:D,4,FALSE) -> MIGUEL JULIÁN HERNÁNDEZ GUARÍN | C82: =VLOOKUP(A82,'CENTRO DE COSTOS'!A:D,2,FALSE) -> 0004-0008 | D82: 68307 | E82: 2593197 | F82: 41893 | G82: INCIDENTE | H82: SANTANDER | I82: GIRON | J82: BARRIO CENTRO INDUSTRIAL SAN J | K82: REDEBAN | L82: FO-25-1372471 | M82: 45882.612 | N82: 45883.419 | O82: NO | P82: ENTIDAD | Q82: ERROR DE TRANSACCIONES | R82: SIN CUPO HABILITADO | S82: CB UNO A UNO | T82: CB UNO A UNO | U82: CERRADO | V82: 13/08/2025 13-08 SE ESCALA PARA VISITA. LLAMAR ANTES DE VISITAR, CONFIRMAR FALLA Y DATOS | 14/08/2025 EN COMUNICACIÓN CON LA SEÑORA KAREN AL MOVIL 3164540006, INDICA QUE NO TIENE NINGUNA FALLA TÉCNICA, QUE ELLA TIENE ES UN BLOQUEO A DE MARCA NO HABILITADA POR PARTE DEL BANCO YA QUE NO HAN RECIBIDO LA FACTURA DEL MES DE JUNIO, INDICA QUE YA ESTA EN EL PROCESO DE DESBLOQUEO CON EL BANCO, INDICA QUE NO REQUIERE DE LA VISITA TÉCNICA, SE LE INFORMA QUE SE PROCEDERÁ A CERRAR LA ORDEN Y SI LLEGA A NECESITAR DEL SERVICIO TECNICO DEBERÁ LLAMAR Y PEDIR UNA NUEVA VISITA, CLIENTE CONFORME. | W82: SOPORTE_TELEFÓNICO | X82: 0 | Y82: TIPO I | Z82: TERRESTRE | AA82: SANTOS GONZALEZ JOHAN FABIAN | AB82: 0 | AC82: 0 | AD82: 0 | AE82: 0 | AF82: =IF(W82="SOPORTE_TELEFÓNICO",'BASE LIQUIDACION'!$B$10,IF(Y82="TIPO I",'BASE LIQUIDACION'!$C$3,IF(Y82="TIPO II",'BASE LIQUIDACION'!$C$4,IF(Y82="TIPO III",'BASE LIQUIDACION'!$C$5,'BASE LIQUIDACION'!$C$7)))) -> 37904.654 | AG82: =IF(W82="SOPORTE_TELEFÓNICO",'BASE LIQUIDACION'!$B$10,(AB82*AF82+AC82*'BASE LIQUIDACION'!$B$12+AD82*'BASE LIQUIDACION'!$B$11+INCIDENTES!AE82*'BASE LIQUIDACION'!$B$13)) -> 37904.654
A83: MEDELLIN | B83: =VLOOKUP(A83,'CENTRO DE COSTOS'!A:D,4,FALSE) -> JUAN SEBASTIÁN RÍOS CASTRILLÓN | C83: =VLOOKUP(A83,'CENTRO DE COSTOS'!A:D,2,FALSE) -> 0004-0005 | D83: 5001 | E83: 2593016 | F83: 27658 | G83: INCIDENTE | H83: ANTIOQUIA | I83: MEDELLIN | J83: DISTRICOL WORLDCEL | K83: REDEBAN | L83: FO-25-1372345 | M83: 45882.591 | N83: 45883.441 | O83: NO | P83: USUARIO | Q83: LECTOR DE TARJETAS | R83: OBSTRUCCION DEL LECTOR | S83: AGREGADOR | T83: AGREGADOR | U83: CERRADO | V83: 13/08/2025 13-08 SE ESCALA PARA VISITA. LLAMAR ANTES DE VISITAR, CONFIRMAR FALLA Y DATOS | 14/08/2025 SE HACE MANTENIMIENTO GENERAL, SE REALIZAN PRUEBAS PERTINENTES, ESTÁN OK | W83: VISITA_TÉCNICA | X83: 99WZZ760 | Y83: TIPO I | Z83: TERRESTRE | AA83: HERNANDEZ CHAVARRIA JUAN CAMILO | AB83: 1 | AC83: 0 | AD83: 0 | AE83: 0 | AF83: =IF(W83="SOPORTE_TELEFÓNICO",'BASE LIQUIDACION'!$B$10,IF(Y83="TIPO I",'BASE LIQUIDACION'!$C$3,IF(Y83="TIPO II",'BASE LIQUIDACION'!$C$4,IF(Y83="TIPO III",'BASE LIQUIDACION'!$C$5,'BASE LIQUIDACION'!$C$7)))) -> 65960.474 | AG83: =IF(W83="SOPORTE_TELEFÓNICO",'BASE LIQUIDACION'!$B$10,(AB83*AF83+AC83*'BASE LIQUIDACION'!$B$12+AD83*'BASE LIQUIDACION'!$B$11+INCIDENTES!AE83*'BASE LIQUIDACION'!$B$13)) -> 65960.474
A84: TUNJA | B84: =VLOOKUP(A84,'CENTRO DE COSTOS'!A:D,4,FALSE) -> MIGUEL JULIÁN HERNÁNDEZ GUARÍN | C84: =VLOOKUP(A84,'CENTRO DE COSTOS'!A:D,2,FALSE) -> 0004-0008 | D84: 15753 | E84: 2586083 | F84: 60980 | G84: INCIDENTE | H84: BOYACA | I84: SOATA | J84: BARRIO CENTRO SOATA 2 | K84: REDEBAN | L84: FO-25-1366532 | M84: 45881.519 | N84: 45883.45 | O84: NO | P84: USUARIO | Q84: MANTENIMIENTO | R84: MANTENIMIENTO GENERAL | S84: CB UNO A UNO | T84: CB UNO A UNO | U84: CERRADO | V84: 12/08/2025 12-08 SE ESCALA PARA VISITA. LLAMAR ANTES DE VISITAR, CONFIRMAR FALLA Y DATOS | 14/08/2025 SE VISITA COMERCIO , SE VALIDA EQUIPO TRABAJANDO CORRECTAMENTE, IMPRIMIENDO CORRECTAMENTE , POR MANTENIMIENTO PREVENTIVO SE REALIZA AJUSTE DE TONALIDAD DE TINTA EN LA IMPRESIÓN DEJANDO PRUEBAS OK SIN TELECARGA NO AUTORIZADA, SE REALIZA BORRADO DE EQUIPO LIBERANDO MEMORIA YA QUE AVECES SE DEMORA EN EJECUTAR EL CIERRE , | W84: VISITA_TÉCNICA | X84: JA00G851 | Y84: TIPO III | Z84: TERRESTRE | AA84: ALVARADO MORENO CRISTHIAN | AB84: 1 | AC84: 0 | AD84: 0 | AE84: 0 | AF84: =IF(W84="SOPORTE_TELEFÓNICO",'BASE LIQUIDACION'!$B$10,IF(Y84="TIPO I",'BASE LIQUIDACION'!$C$3,IF(Y84="TIPO II",'BASE LIQUIDACION'!$C$4,IF(Y84="TIPO III",'BASE LIQUIDACION'!$C$5,'BASE LIQUIDACION'!$C$7)))) -> 275728.38 | AG84: =IF(W84="SOPORTE_TELEFÓNICO",'BASE LIQUIDACION'!$B$10,(AB84*AF84+AC84*'BASE LIQUIDACION'!$B$12+AD84*'BASE LIQUIDACION'!$B$11+INCIDENTES!AE84*'BASE LIQUIDACION'!$B$13)) -> 275728.38
A85: MEDELLIN | B85: =VLOOKUP(A85,'CENTRO DE COSTOS'!A:D,4,FALSE) -> JUAN SEBASTIÁN RÍOS CASTRILLÓN | C85: =VLOOKUP(A85,'CENTRO DE COSTOS'!A:D,2,FALSE) -> 0004-0005 | D85: 5001 | E85: 2593873 | F85: 15100 | G85: INCIDENTE | H85: ANTIOQUIA | I85: MEDELLIN | J85: BARRIO PICACHO III MEDELLIN | K85: REDEBAN | L85: FO-25-1372808 | M85: 45882.652 | N85: 45883.501 | O85: NO | P85: USUARIO | Q85: MANTENIMIENTO | R85: MANTENIMIENTO GENERAL | S85: CB UNO A UNO | T85: CB UNO A UNO | U85: CERRADO | V85: 13/08/2025 13-08 SE ESCALA PARA VISITA. LLAMAR ANTES DE VISITAR, CONFIRMAR FALLA Y DATOS | 14/08/2025 SE REALIZA CAMBIO DE CABLES DE RED PORQUÉ ESTÁN EN MAL ESTADO | W85: VISITA_TÉCNICA | X85: A00JZ287 | Y85: TIPO I | Z85: TERRESTRE | AA85: HERNANDEZ CHAVARRIA JUAN CAMILO | AB85: 1 | AC85: 0 | AD85: 0 | AE85: 0 | AF85: =IF(W85="SOPORTE_TELEFÓNICO",'BASE LIQUIDACION'!$B$10,IF(Y85="TIPO I",'BASE LIQUIDACION'!$C$3,IF(Y85="TIPO II",'BASE LIQUIDACION'!$C$4,IF(Y85="TIPO III",'BASE LIQUIDACION'!$C$5,'BASE LIQUIDACION'!$C$7)))) -> 65960.474 | AG85: =IF(W85="SOPORTE_TELEFÓNICO",'BASE LIQUIDACION'!$B$10,(AB85*AF85+AC85*'BASE LIQUIDACION'!$B$12+AD85*'BASE LIQUIDACION'!$B$11+INCIDENTES!AE85*'BASE LIQUIDACION'!$B$13)) -> 65960.474
A86: CUCUTA | B86: =VLOOKUP(A86,'CENTRO DE COSTOS'!A:D,4,FALSE) -> MIGUEL JULIÁN HERNÁNDEZ GUARÍN | C86: =VLOOKUP(A86,'CENTRO DE COSTOS'!A:D,2,FALSE) -> 0004-0008 | D86: 54001 | E86: 2593230 | F86: 80005 | G86: INCIDENTE | H86: NORTE DE SANTANDER | I86: CUCUTA | J86: BARRIO EL LLANO CUCUTA 19 | K86: REDEBAN | L86: FO-25-1372405 | M86: 45882.604 | N86: 45883.508 | O86: NO | P86: USUARIO | Q86: MANTENIMIENTO | R86: MANTENIMIENTO GENERAL | S86: CB UNO A UNO | T86: CB UNO A UNO | U86: CERRADO | V86: 13/08/2025 13-08 SE ESCALA PARA VISITA. LLAMAR ANTES DE VISITAR, CONFIRMAR FALLA Y DATOS | 14/08/2025 SE REALIZA VISITA, SE REALIZA MANTENIMIENTO, SE REALIZAN PRUEBAS Y CIERRES OK. | W86: VISITA_TÉCNICA | X86: SAWZZ919 | Y86: TIPO I | Z86: TERRESTRE | AA86: PACHECO BUITRAGO JAVIER ALONSO | AB86: 1 | AC86: 0 | AD86: 0 | AE86: 0 | AF86: =IF(W86="SOPORTE_TELEFÓNICO",'BASE LIQUIDACION'!$B$10,IF(Y86="TIPO I",'BASE LIQUIDACION'!$C$3,IF(Y86="TIPO II",'BASE LIQUIDACION'!$C$4,IF(Y86="TIPO III",'BASE LIQUIDACION'!$C$5,'BASE LIQUIDACION'!$C$7)))) -> 65960.474 | AG86: =IF(W86="SOPORTE_TELEFÓNICO",'BASE LIQUIDACION'!$B$10,(AB86*AF86+AC86*'BASE LIQUIDACION'!$B$12+AD86*'BASE LIQUIDACION'!$B$11+INCIDENTES!AE86*'BASE LIQUIDACION'!$B$13)) -> 65960.474
A87: TUNJA | B87: =VLOOKUP(A87,'CENTRO DE COSTOS'!A:D,4,FALSE) -> MIGUEL JULIÁN HERNÁNDEZ GUARÍN | C87: =VLOOKUP(A87,'CENTRO DE COSTOS'!A:D,2,FALSE) -> 0004-0008 | D87: 15001 | E87: 2596903 | F87: 80972 | G87: INCIDENTE | H87: BOYACA | I87: TUNJA | J87: BARRIO LOS MUISCAS TUNJA 9 | K87: REDEBAN | L87: FO-25-1375100 | M87: 45883.414 | N87: 45883.519 | O87: NO | P87: USUARIO | Q87: NO ENCIENDE | R87: CONEXIONES DE COMERCIO | S87: CB UNO A UNO | T87: CB UNO A UNO | U87: CERRADO | V87: 14/08/2025 14-08 SE ESCALA PARA VISITA. LLAMAR ANTES DE VISITAR, CONFIRMAR FALLA Y DATOS | 14/08/2025 SE VISITA CB MANTENIMIENTO DE EQUIPO.... FALLA CANAL DE COMERCIO EQUIPO FUNCIONANDO CORRECTAMENTE PRUEBAS EXITOSAS | W87: VISITA_TÉCNICA | X87: FIZZZ314 | Y87: TIPO I | Z87: TERRESTRE | AA87: GONZALEZ GONZALEZ MARIO ALBERTO | AB87: 1 | AC87: 0 | AD87: 0 | AE87: 0 | AF87: =IF(W87="SOPORTE_TELEFÓNICO",'BASE LIQUIDACION'!$B$10,IF(Y87="TIPO I",'BASE LIQUIDACION'!$C$3,IF(Y87="TIPO II",'BASE LIQUIDACION'!$C$4,IF(Y87="TIPO III",'BASE LIQUIDACION'!$C$5,'BASE LIQUIDACION'!$C$7)))) -> 65960.474 | AG87: =IF(W87="SOPORTE_TELEFÓNICO",'BASE LIQUIDACION'!$B$10,(AB87*AF87+AC87*'BASE LIQUIDACION'!$B$12+AD87*'BASE LIQUIDACION'!$B$11+INCIDENTES!AE87*'BASE LIQUIDACION'!$B$13)) -> 65960.474
A88: MEDELLIN | B88: =VLOOKUP(A88,'CENTRO DE COSTOS'!A:D,4,FALSE) -> JUAN SEBASTIÁN RÍOS CASTRILLÓN | C88: =VLOOKUP(A88,'CENTRO DE COSTOS'!A:D,2,FALSE) -> 0004-0005 | D88: 5001 | E88: 2595250 | F88: 25421 | G88: INCIDENTE | H88: ANTIOQUIA | I88: MEDELLIN | J88: COMCARD KASMAR FP | K88: REDEBAN | L88: FO-25-1373763 | M88: 45883.333 | N88: 45883.522 | O88: NO | P88: USUARIO | Q88: CIERRE | R88: COMERCIO NO REALIZA CIERRE | S88: AGREGADOR | T88: AGREGADOR | U88: CERRADO | V88: 14/08/2025 14-08 SE ESCALA PARA VISITA. LLAMAR ANTES DE VISITAR, CONFIRMAR FALLA Y DATOS | 14/08/2025 SE HABLA CON SEÑORA SABRINA, SE DAN INDICACIONES PARA INGRESAR Y REALIZAR PRUEBAS Y COMENTA QUE YA FUÉ SOLUCIONADA LA NOVEDAD. SE REALIZA PRUEBA DE INGRESO PARA REALIZAR CIERRE Y FUNCIONA SIN NOVEDAD. CB OPERATIVO, SE CIERRA INCIDENTE. | W88: SOPORTE_TELEFÓNICO | X88: 0 | Y88: TIPO I | Z88: TERRESTRE | AA88: HERNANDEZ CHAVARRIA JUAN CAMILO | AB88: 0 | AC88: 0 | AD88: 0 | AE88: 0 | AF88: =IF(W88="SOPORTE_TELEFÓNICO",'BASE LIQUIDACION'!$B$10,IF(Y88="TIPO I",'BASE LIQUIDACION'!$C$3,IF(Y88="TIPO II",'BASE LIQUIDACION'!$C$4,IF(Y88="TIPO III",'BASE LIQUIDACION'!$C$5,'BASE LIQUIDACION'!$C$7)))) -> 37904.654 | AG88: =IF(W88="SOPORTE_TELEFÓNICO",'BASE LIQUIDACION'!$B$10,(AB88*AF88+AC88*'BASE LIQUIDACION'!$B$12+AD88*'BASE LIQUIDACION'!$B$11+INCIDENTES!AE88*'BASE LIQUIDACION'!$B$13)) -> 37904.654
A89: MEDELLIN | B89: =VLOOKUP(A89,'CENTRO DE COSTOS'!A:D,4,FALSE) -> JUAN SEBASTIÁN RÍOS CASTRILLÓN | C89: =VLOOKUP(A89,'CENTRO DE COSTOS'!A:D,2,FALSE) -> 0004-0005 | D89: 5001 | E89: 2594276 | F89: 11915 | G89: INCIDENTE | H89: ANTIOQUIA | I89: MEDELLIN | J89: SAN CRISTOBAL PARQUE - ANTIOQU | K89: REDEBAN | L89: FO-25-1373134 | M89: 45882.685 | N89: 45883.59 | O89: NO | P89: USUARIO | Q89: MANTENIMIENTO | R89: MANTENIMIENTO GENERAL | S89: CB UNO A UNO | T89: CB UNO A UNO | U89: CERRADO | V89: 13/08/2025 13-08 SE ESCALA PARA VISITA. LLAMAR ANTES DE VISITAR, CONFIRMAR FALLA Y DATOS | 14/08/2025 SE REALIZA IMICIALIZACION DE EQUIPO PORQUE PRESENTA RECHAZO GENERAL | W89: VISITA_TÉCNICA | X89: JAAAE212 | Y89: TIPO I | Z89: TERRESTRE | AA89: HERNANDEZ CHAVARRIA JUAN CAMILO | AB89: 1 | AC89: 0 | AD89: 0 | AE89: 0 | AF89: =IF(W89="SOPORTE_TELEFÓNICO",'BASE LIQUIDACION'!$B$10,IF(Y89="TIPO I",'BASE LIQUIDACION'!$C$3,IF(Y89="TIPO II",'BASE LIQUIDACION'!$C$4,IF(Y89="TIPO III",'BASE LIQUIDACION'!$C$5,'BASE LIQUIDACION'!$C$7)))) -> 65960.474 | AG89: =IF(W89="SOPORTE_TELEFÓNICO",'BASE LIQUIDACION'!$B$10,(AB89*AF89+AC89*'BASE LIQUIDACION'!$B$12+AD89*'BASE LIQUIDACION'!$B$11+INCIDENTES!AE89*'BASE LIQUIDACION'!$B$13)) -> 65960.474
A90: MEDELLIN | B90: =VLOOKUP(A90,'CENTRO DE COSTOS'!A:D,4,FALSE) -> JUAN SEBASTIÁN RÍOS CASTRILLÓN | C90: =VLOOKUP(A90,'CENTRO DE COSTOS'!A:D,2,FALSE) -> 0004-0005 | D90: 5001 | E90: 2597874 | F90: 80708 | G90: INCIDENTE | H90: ANTIOQUIA | I90: MEDELLIN | J90: BARRIO GUAYABAL MEDELLIN 14 | K90: REDEBAN | L90: FO-25-1375799 | M90: 45883.476 | N90: 45883.636 | O90: NO | P90: USUARIO | Q90: MANTENIMIENTO | R90: MANTENIMIENTO GENERAL | S90: CB UNO A UNO | T90: CB UNO A UNO | U90: CERRADO | V90: 14/08/2025 14-08 SE ESCALA PARA VISITA. LLAMAR ANTES DE VISITAR, CONFIRMAR FALLA Y DATOS | 14/08/2025 SE COMUNICA CON USUARIO Y SE INDICA QUE REALICE UN REINICIO EN EL EQUIPO, COMENTA QUE FUNCIONA CORRECTAMENTE, TODO OK | W90: SOPORTE_TELEFÓNICO | X90: 0 | Y90: TIPO I | Z90: TERRESTRE | AA90: QUINTERO SANCHEZ JUAN SEBASTIAN | AB90: 0 | AC90: 0 | AD90: 0 | AE90: 0 | AF90: =IF(W90="SOPORTE_TELEFÓNICO",'BASE LIQUIDACION'!$B$10,IF(Y90="TIPO I",'BASE LIQUIDACION'!$C$3,IF(Y90="TIPO II",'BASE LIQUIDACION'!$C$4,IF(Y90="TIPO III",'BASE LIQUIDACION'!$C$5,'BASE LIQUIDACION'!$C$7)))) -> 37904.654 | AG90: =IF(W90="SOPORTE_TELEFÓNICO",'BASE LIQUIDACION'!$B$10,(AB90*AF90+AC90*'BASE LIQUIDACION'!$B$12+AD90*'BASE LIQUIDACION'!$B$11+INCIDENTES!AE90*'BASE LIQUIDACION'!$B$13)) -> 37904.654
A91: TUNJA | B91: =VLOOKUP(A91,'CENTRO DE COSTOS'!A:D,4,FALSE) -> MIGUEL JULIÁN HERNÁNDEZ GUARÍN | C91: =VLOOKUP(A91,'CENTRO DE COSTOS'!A:D,2,FALSE) -> 0004-0008 | D91: 15248 | E91: 2582200 | F91: 11094 | G91: INCIDENTE | H91: BOYACA | I91: EL ESPINO | J91: EL ESPINO - BOYACA | K91: REDEBAN | L91: FO-25-1362684 | M91: 45880.722 | N91: 45883.694 | O91: NO | P91: USUARIO | Q91: MANTENIMIENTO | R91: MANTENIMIENTO GENERAL | S91: CB UNO A UNO | T91: CB UNO A UNO | U91: CERRADO | V91: 11/08/2025 11-08 17:47 EN COMUNICACIÓN CON LA SEÑORA ELIZBETH JIMENEZ AL NUMERO 3107839160 INDICA QUE EL DATAFONO LE ARROJA CONECTANDO Y LUEGO LE DICE ERROR DE CONEXIÓN, CONFIRMA DATOS, SE ESCALA PARA VISITA | 14/08/2025 SE VISITA COMERCIO , SE VALIDA QUE EL CORRESPONSAL ESTA OPERATIVO COMUNICACIÓN EXITOSA POR EL INTERNET SUMINISTRADO POR EL BANCO AUN QUE SE EVIDENCIA QUE LA RESPUESTA DEL INTERNET ES MUY LENTA PARA EJECUTAR LA TRANSACCIÓN DEBEN VALIDAR INTERNET DEL BANCO,SE CAMBIA CABLE PACTH CORD 3 Y CABLE ENTORCHADO POR MANTENIMIENTO PREVENTIVO YA QUE SE ENCUENTRA PACTH CORD EN MAL ESTADO , SE REALIZA BORRADO DE EQUIPO CARGANDO VERSIÓN 9_90 PARA LIBERAR MEMORIA YA QUE SE DEMORA EN EJECUTAR EL CIERRE DEJANDO PRUEBAS OK SIN TELECARGA NO AUTORIZADA | W91: VISITA_TÉCNICA | X91: IZ8ZZ080 | Y91: TIPO IV | Z91: TERRESTRE | AA91: ALVARADO MORENO CRISTHIAN | AB91: 1 | AC91: 0 | AD91: 0 | AE91: 0 | AF91: =IF(W91="SOPORTE_TELEFÓNICO",'BASE LIQUIDACION'!$B$10,IF(Y91="TIPO I",'BASE LIQUIDACION'!$C$3,IF(Y91="TIPO II",'BASE LIQUIDACION'!$C$4,IF(Y91="TIPO III",'BASE LIQUIDACION'!$C$5,'BASE LIQUIDACION'!$C$7)))) -> 479589.74 | AG91: =IF(W91="SOPORTE_TELEFÓNICO",'BASE LIQUIDACION'!$B$10,(AB91*AF91+AC91*'BASE LIQUIDACION'!$B$12+AD91*'BASE LIQUIDACION'!$B$11+INCIDENTES!AE91*'BASE LIQUIDACION'!$B$13)) -> 479589.74
A92: MEDELLIN | B92: =VLOOKUP(A92,'CENTRO DE COSTOS'!A:D,4,FALSE) -> JUAN SEBASTIÁN RÍOS CASTRILLÓN | C92: =VLOOKUP(A92,'CENTRO DE COSTOS'!A:D,2,FALSE) -> 0004-0005 | D92: 5001 | E92: 2595248 | F92: 34519 | G92: INCIDENTE | H92: ANTIOQUIA | I92: MEDELLIN | J92: BARRIO ENCISO MEDELLIN 3 | K92: REDEBAN | L92: FO-25-1373770 | M92: 45883.333 | N92: 45884.395 | O92: NO | P92: USUARIO | Q92: CIERRE | R92: COMERCIO NO REALIZA CIERRE | S92: CB UNO A UNO | T92: CB UNO A UNO | U92: CERRADO | V92: 14/08/2025 14-08 SE ESCALA PARA VISITA. LLAMAR ANTES DE VISITAR, CONFIRMAR FALLA Y DATOS | 14/08/2025 SE LE EXPLICA AL USUARIO POR SOPORTE TELEFÓNICO COMO REALIZA EL CIERRE CORRECTAMENTE PARA EVITAR ERROR. SE REALIZA LOS CIERRES Y SERVICIO OPERATIVO | W92: SOPORTE_TELEFÓNICO | X92: 0 | Y92: TIPO I | Z92: TERRESTRE | AA92: ZAPATA LOPEZ EDWARD ASDRUAL | AB92: 0 | AC92: 0 | AD92: 0 | AE92: 0 | AF92: =IF(W92="SOPORTE_TELEFÓNICO",'BASE LIQUIDACION'!$B$10,IF(Y92="TIPO I",'BASE LIQUIDACION'!$C$3,IF(Y92="TIPO II",'BASE LIQUIDACION'!$C$4,IF(Y92="TIPO III",'BASE LIQUIDACION'!$C$5,'BASE LIQUIDACION'!$C$7)))) -> 37904.654 | AG92: =IF(W92="SOPORTE_TELEFÓNICO",'BASE LIQUIDACION'!$B$10,(AB92*AF92+AC92*'BASE LIQUIDACION'!$B$12+AD92*'BASE LIQUIDACION'!$B$11+INCIDENTES!AE92*'BASE LIQUIDACION'!$B$13)) -> 37904.654
A93: VALLEDUPAR | B93: =VLOOKUP(A93,'CENTRO DE COSTOS'!A:D,4,FALSE) -> JOSE MAURICIO HERNANDEZ ROJAS | C93: =VLOOKUP(A93,'CENTRO DE COSTOS'!A:D,2,FALSE) -> 0004-0001 | D93: 20750 | E93: 2597004 | F93: 43043 | G93: INCIDENTE | H93: CESAR | I93: SAN DIEGO | J93: BARRIO CORR DE MEDIA LUNA SAN | K93: REDEBAN | L93: FO-25-1375141 | M93: 45883.417 | N93: 45884.399 | O93: NO | P93: USUARIO | Q93: COMUNICACION | R93: CONEXIONES DE COMERCIO | S93: CB UNO A UNO | T93: CB UNO A UNO | U93: CERRADO | V93: 14/08/2025 14-08 SE ESCALA PARA VISITA. LLAMAR ANTES DE VISITAR, CONFIRMAR FALLA Y DATOS | 15/08/2025 SE LLAMA A LA SEÑORA SORAIDA GONZÁLEZ E INDICA QUE EL SERVICIO EL DIA DE AYER PRESENTABA FALLAS COMO DE CONEXIÓN PERO QUE AYER MISMO SE RESTABLECIO EL SERVICIO Y POR ENDE NO REQUIERE LA VISITA TÉCNICA | W93: SOPORTE_TELEFÓNICO | X93: 0 | Y93: TIPO II | Z93: TERRESTRE | AA93: MONTES DIAZ JOHN FRED | AB93: 0 | AC93: 0 | AD93: 0 | AE93: 0 | AF93: =IF(W93="SOPORTE_TELEFÓNICO",'BASE LIQUIDACION'!$B$10,IF(Y93="TIPO I",'BASE LIQUIDACION'!$C$3,IF(Y93="TIPO II",'BASE LIQUIDACION'!$C$4,IF(Y93="TIPO III",'BASE LIQUIDACION'!$C$5,'BASE LIQUIDACION'!$C$7)))) -> 37904.654 | AG93: =IF(W93="SOPORTE_TELEFÓNICO",'BASE LIQUIDACION'!$B$10,(AB93*AF93+AC93*'BASE LIQUIDACION'!$B$12+AD93*'BASE LIQUIDACION'!$B$11+INCIDENTES!AE93*'BASE LIQUIDACION'!$B$13)) -> 37904.654
A94: CUCUTA | B94: =VLOOKUP(A94,'CENTRO DE COSTOS'!A:D,4,FALSE) -> MIGUEL JULIÁN HERNÁNDEZ GUARÍN | C94: =VLOOKUP(A94,'CENTRO DE COSTOS'!A:D,2,FALSE) -> 0004-0008 | D94: 54498 | E94: 2589851 | F94: 70662 | G94: INCIDENTE | H94: NORTE DE SANTANDER | I94: OCAÑA | J94: LA PRIMAVERA OCANA 5 | K94: REDEBAN | L94: FO-25-1369622 | M94: 45882.351 | N94: 45884.406 | O94: NO | P94: USUARIO | Q94: CIERRE | R94: COMERCIO NO REALIZA CIERRE | S94: CB UNO A UNO | T94: CB UNO A UNO | U94: CERRADO | V94: 13/08/2025 13-08 SE ESCALA PARA VISITA. LLAMAR ANTES DE VISITAR, CONFIRMAR FALLA Y DATOS | 14/08/2025 SE LLEGA AL MUNICIPIO DE OCAÑA SE COMUNICA CON EL CLIENTE JAIRO PA CONFIRRMAR VISITA AL # 3158052100, NOS INFORMA QUE YA SALIO DE LA OFICINA, QUE PASEN EL DIA DE MAÑANA, SE PROGRAMA VISITA 15/08 | 15/08/2025 SE VISITA COMERCIO, SE REALIZA MANTENIMIENTO, SE HACEN PRUEBAS OK. | W94: VISITA_TÉCNICA | X94: UV008404 | Y94: TIPO IV | Z94: TERRESTRE | AA94: NARANJO AFANADOR RUBEN JESUS | AB94: 1 | AC94: 0 | AD94: 0 | AE94: 0 | AF94: =IF(W94="SOPORTE_TELEFÓNICO",'BASE LIQUIDACION'!$B$10,IF(Y94="TIPO I",'BASE LIQUIDACION'!$C$3,IF(Y94="TIPO II",'BASE LIQUIDACION'!$C$4,IF(Y94="TIPO III",'BASE LIQUIDACION'!$C$5,'BASE LIQUIDACION'!$C$7)))) -> 479589.74 | AG94: =IF(W94="SOPORTE_TELEFÓNICO",'BASE LIQUIDACION'!$B$10,(AB94*AF94+AC94*'BASE LIQUIDACION'!$B$12+AD94*'BASE LIQUIDACION'!$B$11+INCIDENTES!AE94*'BASE LIQUIDACION'!$B$13)) -> 479589.74
A95: SINCELEJO | B95: =VLOOKUP(A95,'CENTRO DE COSTOS'!A:D,4,FALSE) -> JOSE MAURICIO HERNANDEZ ROJAS | C95: =VLOOKUP(A95,'CENTRO DE COSTOS'!A:D,2,FALSE) -> 0004-0001 | D95: 70708 | E95: 2600164 | F95: 48599 | G95: INCIDENTE | H95: SUCRE | I95: SAN MARCOS | J95: DISTRICOL DROGUERIA LA UNION S | K95: REDEBAN | L95: FO-25-1378253 | M95: 45883.688 | N95: 45884.411 | O95: NO | P95: USUARIO | Q95: CIERRE | R95: COMERCIO NO REALIZA CIERRE | S95: AGREGADOR | T95: AGREGADOR | U95: CERRADO | V95: 14/08/2025 SE ESCALA PARA VISITA. LLAMAR ANTES DE VISITAR, CONFIRMAR FALLA Y DATOS | 15/08/2025 EN COMUNICACIÓN CON LA SEÑORA YARLEDYS, ME INFORMA QUE ESTOS DÍAS NO HABÍA PODIDO SACAR EL CIERRE, SE LE INDICA EL PROCESO DE CIERRE Y LO REALIZA CORRECTAMENTE. | W95: SOPORTE_TELEFÓNICO | X95: 0 | Y95: TIPO III | Z95: TERRESTRE | AA95: CACERES HERNANDEZ ANDRES | AB95: 0 | AC95: 0 | AD95: 0 | AE95: 0 | AF95: =IF(W95="SOPORTE_TELEFÓNICO",'BASE LIQUIDACION'!$B$10,IF(Y95="TIPO I",'BASE LIQUIDACION'!$C$3,IF(Y95="TIPO II",'BASE LIQUIDACION'!$C$4,IF(Y95="TIPO III",'BASE LIQUIDACION'!$C$5,'BASE LIQUIDACION'!$C$7)))) -> 37904.654 | AG95: =IF(W95="SOPORTE_TELEFÓNICO",'BASE LIQUIDACION'!$B$10,(AB95*AF95+AC95*'BASE LIQUIDACION'!$B$12+AD95*'BASE LIQUIDACION'!$B$11+INCIDENTES!AE95*'BASE LIQUIDACION'!$B$13)) -> 37904.654
A96: MEDELLIN | B96: =VLOOKUP(A96,'CENTRO DE COSTOS'!A:D,4,FALSE) -> JUAN SEBASTIÁN RÍOS CASTRILLÓN | C96: =VLOOKUP(A96,'CENTRO DE COSTOS'!A:D,2,FALSE) -> 0004-0005 | D96: 5030 | E96: 2592015 | F96: 80254 | G96: INCIDENTE | H96: ANTIOQUIA | I96: AMAGA | J96: BARRIO VRD VILLA DIANA AMAGA | K96: REDEBAN | L96: FO-25-1371208 | M96: 45882.474 | N96: 45884.44 | O96: NO | P96: USUARIO | Q96: COMUNICACION | R96: CONEXIONES DE COMERCIO | S96: CB UNO A UNO | T96: CB UNO A UNO | U96: CERRADO | V96: 13/08/2025 13-08 SE ESCALA PARA VISITA. LLAMAR ANTES DE VISITAR, CONFIRMAR FALLA Y DATOS | 15/08/2025 SE REALIZA CAMBIO DE ENTRADA DEL CABLE PODER POR MAL PASO DE ENERGIA | W96: VISITA_TÉCNICA | X96: FAZZZ495 | Y96: TIPO II | Z96: TERRESTRE | AA96: HERNANDEZ CHAVARRIA JUAN CAMILO | AB96: 1 | AC96: 0 | AD96: 0 | AE96: 0 | AF96: =IF(W96="SOPORTE_TELEFÓNICO",'BASE LIQUIDACION'!$B$10,IF(Y96="TIPO I",'BASE LIQUIDACION'!$C$3,IF(Y96="TIPO II",'BASE LIQUIDACION'!$C$4,IF(Y96="TIPO III",'BASE LIQUIDACION'!$C$5,'BASE LIQUIDACION'!$C$7)))) -> 163813.56 | AG96: =IF(W96="SOPORTE_TELEFÓNICO",'BASE LIQUIDACION'!$B$10,(AB96*AF96+AC96*'BASE LIQUIDACION'!$B$12+AD96*'BASE LIQUIDACION'!$B$11+INCIDENTES!AE96*'BASE LIQUIDACION'!$B$13)) -> 163813.56
A97: BOGOTA | B97: =VLOOKUP(A97,'CENTRO DE COSTOS'!A:D,4,FALSE) -> WILLIAM ASDRUBAL ROZO ROZO | C97: =VLOOKUP(A97,'CENTRO DE COSTOS'!A:D,2,FALSE) -> 0004-0004 | D97: 25817 | E97: 2600762 | F97: 66805 | G97: INCIDENTE | H97: CUNDINAMARCA | I97: TOCANCIPA | J97: BARRIO ALPES TOCANCIPA | K97: REDEBAN | L97: FO-25-1378549 | M97: 45884.333 | N97: 45884.614 | O97: NO | P97: USUARIO | Q97: CIERRE | R97: COMERCIO NO REALIZA CIERRE | S97: CB UNO A UNO | T97: CB UNO A UNO | U97: CERRADO | V97: 15/08/2025 SE ESCALA PARA VISITA. LLAMAR ANTES DE VISITAR, CONFIRMAR FALLA Y DATOS | 15/08/2025 SE VISITA CB BANCOLOMBIA, SE VERIFICA QUE EL CLIENTE NO REALIZA LOS CIERRES CORRECTAMENTE, SE LIBERA MEMORIA PARA QUE EL EQUIPO REALICE EL CIERRE MÁS RÁPIDO, SE LE EXPLICA COMO DEBE DE HACER EL CIERRE, SE REALIZAN PRUEBAS OK, NO UPS. | W97: VISITA_TÉCNICA | X97: 3A0CZ765 | Y97: TIPO II | Z97: TERRESTRE | AA97: VEGA MANRIQUE JONATAN MAURICIO | AB97: 1 | AC97: 0 | AD97: 0 | AE97: 0 | AF97: =IF(W97="SOPORTE_TELEFÓNICO",'BASE LIQUIDACION'!$B$10,IF(Y97="TIPO I",'BASE LIQUIDACION'!$C$3,IF(Y97="TIPO II",'BASE LIQUIDACION'!$C$4,IF(Y97="TIPO III",'BASE LIQUIDACION'!$C$5,'BASE LIQUIDACION'!$C$7)))) -> 163813.56 | AG97: =IF(W97="SOPORTE_TELEFÓNICO",'BASE LIQUIDACION'!$B$10,(AB97*AF97+AC97*'BASE LIQUIDACION'!$B$12+AD97*'BASE LIQUIDACION'!$B$11+INCIDENTES!AE97*'BASE LIQUIDACION'!$B$13)) -> 163813.56
A98: MEDELLIN | B98: =VLOOKUP(A98,'CENTRO DE COSTOS'!A:D,4,FALSE) -> JUAN SEBASTIÁN RÍOS CASTRILLÓN | C98: =VLOOKUP(A98,'CENTRO DE COSTOS'!A:D,2,FALSE) -> 0004-0005 | D98: 5631 | E98: 2606100 | F98: 76870 | G98: INCIDENTE | H98: ANTIOQUIA | I98: SABANETA | J98: BARRIO SABANETA SABANETA 12 | K98: REDEBAN | L98: FO-25-1383172 | M98: 45885.333 | N98: 45885.43 | O98: NO | P98: USUARIO | Q98: CIERRE | R98: COMERCIO NO REALIZA CIERRE | S98: CB UNO A UNO | T98: CB UNO A UNO | U98: CERRADO | V98: 16/08/2025 SE ESCALA PARA VISITA. LLAMAR ANTES DE VISITAR, CONFIRMAR FALLA Y DATOS | 16/08/2025 SE HABLA CON SEÑORA ELIANA, SE VERIFICA INGRESO Y REALIZACION DE PRUEBAS Y CONFIRMA QUE YA SE SOLUCIONÓ LA INCIDENCIA. SE REALIZA PRUEBA DE INGRESO PARA REALIZAR CIERRE Y FUNCIONA SIN NOVEDAD. CB OPERATIVO, SE CIERRA INCIDENTE. | W98: SOPORTE_TELEFÓNICO | X98: 0 | Y98: TIPO I | Z98: TERRESTRE | AA98: QUINTERO SANCHEZ JUAN SEBASTIAN | AB98: 0 | AC98: 0 | AD98: 0 | AE98: 0 | AF98: =IF(W98="SOPORTE_TELEFÓNICO",'BASE LIQUIDACION'!$B$10,IF(Y98="TIPO I",'BASE LIQUIDACION'!$C$3,IF(Y98="TIPO II",'BASE LIQUIDACION'!$C$4,IF(Y98="TIPO III",'BASE LIQUIDACION'!$C$5,'BASE LIQUIDACION'!$C$7)))) -> 37904.654 | AG98: =IF(W98="SOPORTE_TELEFÓNICO",'BASE LIQUIDACION'!$B$10,(AB98*AF98+AC98*'BASE LIQUIDACION'!$B$12+AD98*'BASE LIQUIDACION'!$B$11+INCIDENTES!AE98*'BASE LIQUIDACION'!$B$13)) -> 37904.654
A99: MEDELLIN | B99: =VLOOKUP(A99,'CENTRO DE COSTOS'!A:D,4,FALSE) -> JUAN SEBASTIÁN RÍOS CASTRILLÓN | C99: =VLOOKUP(A99,'CENTRO DE COSTOS'!A:D,2,FALSE) -> 0004-0005 | D99: 5667 | E99: 2605907 | F99: 34542 | G99: INCIDENTE | H99: ANTIOQUIA | I99: SAN RAFAEL | J99: BARRIO PARQUE PRINCIPAL SAN RA | K99: REDEBAN | L99: FO-25-1382599 | M99: 45884.745 | N99: 45885.506 | O99: NO | P99: USUARIO | Q99: MANTENIMIENTO | R99: MANTENIMIENTO GENERAL | S99: CB UNO A UNO | T99: CB UNO A UNO | U99: CERRADO | V99: 15/08/2025 SE ESCALA PARA VISITA. LLAMAR ANTES DE VISITAR, CONFIRMAR FALLA Y DATOS | 16/08/2025 SE LLEGA A PUNTO Y CLIENTE ESTÁ OPERANDO CON NORMALIDAD NOS DICE QUE ES QUE EL DATAFONO TIENE LAS TECLAS MUY DURAS. SE LE EXPLICA QUE ASÍ ES EL DATAFONO. LA TECNOLOGÍA DESK2600 ES ASÍ LAS TECLAS DURAS. EQUIPOS OPERATIVOS | W99: VISITA_TÉCNICA | X99: UV002109 | Y99: TIPO III | Z99: TERRESTRE | AA99: DIAZ ZABALA FRANCIS DUBAN | AB99: 1 | AC99: 0 | AD99: 0 | AE99: 0 | AF99: =IF(W99="SOPORTE_TELEFÓNICO",'BASE LIQUIDACION'!$B$10,IF(Y99="TIPO I",'BASE LIQUIDACION'!$C$3,IF(Y99="TIPO II",'BASE LIQUIDACION'!$C$4,IF(Y99="TIPO III",'BASE LIQUIDACION'!$C$5,'BASE LIQUIDACION'!$C$7)))) -> 275728.38 | AG99: =IF(W99="SOPORTE_TELEFÓNICO",'BASE LIQUIDACION'!$B$10,(AB99*AF99+AC99*'BASE LIQUIDACION'!$B$12+AD99*'BASE LIQUIDACION'!$B$11+INCIDENTES!AE99*'BASE LIQUIDACION'!$B$13)) -> 275728.38
A100: APARTADO | B100: =VLOOKUP(A100,'CENTRO DE COSTOS'!A:D,4,FALSE) -> JUAN SEBASTIÁN RÍOS CASTRILLÓN | C100: =VLOOKUP(A100,'CENTRO DE COSTOS'!A:D,2,FALSE) -> 0004-0005 | D100: 5172 | E100: 2606563 | F100: 72551 | G100: INCIDENTE | H100: ANTIOQUIA | I100: CHIGORODO | J100: PTM CHIGORODO PUNTOSERVIS CH | K100: REDEBAN | L100: FO-25-1383952 | M100: 45885.449 | N100: 45886.528 | O100: NO | P100: ENTIDAD | Q100: ERROR DE TRANSACCIONES | R100: TRANSACCION NO PERMITIDA | S100: AGREGADOR | T100: AGREGADOR | U100: CERRADO | V100: 16/08/2025 SE ESCALA PARA VISITA. LLAMAR ANTES DE VISITAR, CONFIRMAR FALLA Y DATOS | 17/08/2025 USUARIO REPORTO NOVEDAD DE RECHAZO GENERAL, SE REALIZA LLAMADA Y CONFIRMA QUE HOY AMANECIÓ TRABAJANDO SIN PROBLEMA Y COMENTA QUE LLAMO A LA LINEA A REPORTAR QUE YA ESTABA TODO EN ORDEN. SE CIERRA INCIDENTE, CB OPERATIVO. | W100: SOPORTE_TELEFÓNICO | X100: 0 | Y100: TIPO II | Z100: TERRESTRE | AA100: SALDARRIAGA MIRANDA SANTIAGO | AB100: 0 | AC100: 0 | AD100: 0 | AE100: 0 | AF100: =IF(W100="SOPORTE_TELEFÓNICO",'BASE LIQUIDACION'!$B$10,IF(Y100="TIPO I",'BASE LIQUIDACION'!$C$3,IF(Y100="TIPO II",'BASE LIQUIDACION'!$C$4,IF(Y100="TIPO III",'BASE LIQUIDACION'!$C$5,'BASE LIQUIDACION'!$C$7)))) -> 37904.654 | AG100: =IF(W100="SOPORTE_TELEFÓNICO",'BASE LIQUIDACION'!$B$10,(AB100*AF100+AC100*'BASE LIQUIDACION'!$B$12+AD100*'BASE LIQUIDACION'!$B$11+INCIDENTES!AE100*'BASE LIQUIDACION'!$B$13)) -> 37904.654
...

Sheet OC
A1: CIUDAD SEDE | B1: COORDINADOR | C1: CENTRO DE COSTOS LÍNEACOM | D1: CÓDIGO DANE | E1: TA/CODIGO ACTIVIDAD | F1: CODIGO CB | G1: ACTIVIDAD | H1: DEPARTAMENTO | I1: CIUDAD | J1: NOMBRE DEL CB | K1: RED | L1: FO | M1: FECHA ASIGNACION A LINEA COMUNICACIONES | N1: FECHA DEL CIERRE DEL TICKET (DD/MM/AAAA) | O1: ACOMETIDA | P1: SOLICITUD | Q1: DESCRIPCIÓN | R1: FORMATO | S1: CADENA | T1: ESTADO | U1: CAUSAL ESTADO | V1: OBSERVACION | W1: FORMA DE ATENCIÓN | X1: TERMINAL | Y1: TIPIFICACION | Z1: TIPO DE TRAYECTO | AA1: NOMBRE DEL TECNICO | AB1: DIAS DE VISITA | AC1: SWITCH | AD1: ACOMETIDA DATOS | AE1: ACOMETIDA ELECTRICA | AF1: VALOR ACTIVIDAD | AG1: VALOR TOTAL
A2: CIUDAD SEDE | B2: COORDINADOR | C2: CENTRO DE COSTOS LINEACOM | D2: CODIGO DANE | E2: TA/CODIGO ACTIVIDAD | F2: CODIGO CB | G2: ACTIVIDAD | H2: DEPARTAMENTO | I2: CIUDAD | J2: NOMBRE DEL CB | K2: RED | L2: FO | M2: FECHA ASIGNACION A LINEA COMUNICACIONES | N2: FECHA CIERRE DEL TICKET (DD/MM/AAAA HH:MM) | O2: ACOMETIDA DATOS | P2: SOLICITUD | Q2: DESCRIPCION | R2: FORMATO | S2: CADENA | T2: ESTADO | U2: CAUSAL ESTADO | V2: OBSERVACIONES CLIENTE | W2: FORMA DE ATENCION | X2: TERMINAL(ES) | Y2: TIPIFICACION | Z2: TIPO DE TRAYECTO | AA2: NOMBRE DEL TECNICO | AB2: DIAS DE VISITA | AC2: SWITCH | AD2: ACOMETIDA DATOS | AE2: ACOMETIDA ELECTRICA | AF2: VALOR ACTIVIDAD TE | AG2: VALOR TOTAL TE
A3: VILLAVICENCIO | B3: =VLOOKUP(A3,'CENTRO DE COSTOS'!A:D,4,FALSE) -> KEVIN ALEXIS CORZO BUSTOS | C3: =VLOOKUP(A3,'CENTRO DE COSTOS'!A:D,2,FALSE) -> 0004-0007 | D3: 50001 | E3: 13784392 | F3: 67754 | G3: ORDEN DE CAMBIO | H3: META | I3: VILLAVICENCIO | J3: BARRIO URB CASTILLA VILLAVICEN | K3: REDEBAN | L3: FO-25-1320573 | M3: 45870.703 | N3: 45874.572 | P3: TRASLADO | Q3: TRASLADO EXTERNO | R3: CB UNO A UNO | S3: CB UNO A UNO | T3: EJECUTADO_CANCELADO | U3: DIRECCION ERRADA | V3: SOLICITUD DE TRASLADO EXTERNO 0 04/08/2025 Se llega la comercio y se válidas que la dirección de la orden no es la misma indicada por el comercio Dirección correcta es cll 34 # 39 13 y dirección programada en orden es kr 34 # 39 13 se le inform al jefe de zona para procedes con el cierre y se le informa al cliente que debe realizar los debidos ajuste para el traslado | W3: VISITA_TÉCNICA | X3: 0 | Y3: TIPO I | Z3: =VLOOKUP(D3,TIPOLOGIAS!A:F,5,0) -> TERRESTRE | AA3: ROZO JIMENEZ EDGAR ARMANDO | AB3: 1 | AC3: 0 | AD3: 0 | AE3: 0 | AF3: =IF(W3="SOPORTE_TELEFÓNICO",'BASE LIQUIDACION'!$B$10,IF(Y3="TIPO I",'BASE LIQUIDACION'!$C$3,IF(Y3="TIPO II",'BASE LIQUIDACION'!$C$4,IF(Y3="TIPO III",'BASE LIQUIDACION'!$C$5,'BASE LIQUIDACION'!$C$7)))) -> 65960.474 | AG3: =IF(W3="SOPORTE_TELEFÓNICO",'BASE LIQUIDACION'!$B$10,(AB3*AF3+AC3*'BASE LIQUIDACION'!$B$13+AD3*'BASE LIQUIDACION'!$B$12+AE3*'BASE LIQUIDACION'!$B$11)) -> 65960.474
A4: CALI | B4: =VLOOKUP(A4,'CENTRO DE COSTOS'!A:D,4,FALSE) -> DIEGO FERNANDO HENAO CARDONA | C4: =VLOOKUP(A4,'CENTRO DE COSTOS'!A:D,2,FALSE) -> 0004-0003 | D4: 76001 | E4: 13874868 | F4: 74347 | G4: ORDEN DE CAMBIO | H4: VALLE DEL CAUCA | I4: CALI | J4: PTM CALI MISCELANEA GABYTA | K4: REDEBAN | L4: FO-25-1366681 | M4: 45882.333 | N4: 45882.406 | P4: TRASLADO | Q4: TRASLADO | R4: AGREGADOR | S4: COMCARD - PTM | T4: GESTIÓN_TELEFÓNICA | U4: CANCELADO POR EL USUARIO | V4: 12/08/2025 12-08 POR FAVOR COMUNICARSE CON CB PARA CONFIRMAR SOLICITUD, UBICACION Y PROGRAMAR VISITA TECNICA - 13-08 SE LLAMA AL NÚMERO DE CONTACTO 3175384954 Y CONTESTA LA SEÑORA MÓNICA RODRÍGUEZ, SE LE PREGUNTA POR DISPONIBILIDAD PARA REALIZAR EL TRASLADO DEL CORRESPONSAL Y ELLA INFORMA QUE NO HAY SOLICITADO TRASLADO. A DEMÁS HAY NOVEDAD EN EL NOMBRE DEL CLIENTE EN LA ORDEN DE TRABAJO Y DIRECCIÓN DE ACTIVIDAD COMO TAMBIÉN DE BARRIO. SE PROCEDE A CERRAR ACTIVIDAD POR NO SOLICITUD DEL CLIENTE ADEMÁS DE NOVEDAD EN ORDEN DE TRABAJO | W4: SOPORTE_TELEFÓNICO | Y4: TIPO I | Z4: =VLOOKUP(D4,TIPOLOGIAS!A:F,5,0) -> TERRESTRE | AA4: BOLAÑOS TABORDA JORGE ENRIQUE | AB4: 0 | AC4: 0 | AD4: 0 | AE4: 0 | AF4: =IF(W4="SOPORTE_TELEFÓNICO",'BASE LIQUIDACION'!$B$10,IF(Y4="TIPO I",'BASE LIQUIDACION'!$C$3,IF(Y4="TIPO II",'BASE LIQUIDACION'!$C$4,IF(Y4="TIPO III",'BASE LIQUIDACION'!$C$5,'BASE LIQUIDACION'!$C$7)))) -> 37904.654 | AG4: =IF(W4="SOPORTE_TELEFÓNICO",'BASE LIQUIDACION'!$B$10,(AB4*AF4+AC4*'BASE LIQUIDACION'!$B$13+AD4*'BASE LIQUIDACION'!$B$12+AE4*'BASE LIQUIDACION'!$B$11)) -> 37904.654
A5: BOGOTA | B5: =VLOOKUP(A5,'CENTRO DE COSTOS'!A:D,4,FALSE) -> WILLIAM ASDRUBAL ROZO ROZO | C5: =VLOOKUP(A5,'CENTRO DE COSTOS'!A:D,2,FALSE) -> 0004-0004 | D5: 11001 | E5: 13849471 | F5: 73244 | G5: ORDEN DE CAMBIO | H5: CUNDINAMARCA | I5: BOGOTA | J5: DISTRICOL PAPELERIA LA ESQUINA | K5: REDEBAN | L5: FO-25-1371322 | FO-25-1336542 | M5: 45875.357 | N5: 45883.349 | P5: TRASLADO | Q5: TRASLADO | R5: AGREGADOR | S5: DISTRICOL | T5: EJECUTADO_EXITOSO | U5: EJECUTADO EXITOSO | V5: 14/08/2025 A LA ESPERA DE INGRESO CLIENTE EN COMUNICACIÓN CON LÍNEA DE BANCOLOLMBIA | 14/08/2025 SE REALIZA VISITA DE CAMPO DONDE SE TRASLADARON EQUIPOS DE ACUERDO A INDICACIONES DEL CLIENTE PRUEBAS CUPO Y USUARIO OK, NO SE INTALA PUBLICIDAD DEBIDO A QUE NO ESTA EN EL PUNTO. | W5: VISITA_TÉCNICA | X5: SV00T124 | Y5: TIPO I | Z5: =VLOOKUP(D5,TIPOLOGIAS!A:F,5,0) -> TERRESTRE | AA5: LOZADA ROJAS CHRISTIAN ANDRES | AB5: 1 | AC5: 0 | AD5: 0 | AE5: 0 | AF5: =IF(W5="SOPORTE_TELEFÓNICO",'BASE LIQUIDACION'!$B$10,IF(Y5="TIPO I",'BASE LIQUIDACION'!$C$3,IF(Y5="TIPO II",'BASE LIQUIDACION'!$C$4,IF(Y5="TIPO III",'BASE LIQUIDACION'!$C$5,'BASE LIQUIDACION'!$C$7)))) -> 65960.474 | AG5: =IF(W5="SOPORTE_TELEFÓNICO",'BASE LIQUIDACION'!$B$10,(AB5*AF5+AC5*'BASE LIQUIDACION'!$B$13+AD5*'BASE LIQUIDACION'!$B$12+AE5*'BASE LIQUIDACION'!$B$11)) -> 65960.474
A6: BOGOTA | B6: =VLOOKUP(A6,'CENTRO DE COSTOS'!A:D,4,FALSE) -> WILLIAM ASDRUBAL ROZO ROZO | C6: =VLOOKUP(A6,'CENTRO DE COSTOS'!A:D,2,FALSE) -> 0004-0004 | D6: 11001 | E6: 13842774 | F6: 32053 | G6: ORDEN DE CAMBIO | H6: CUNDINAMARCA | I6: BOGOTA | J6: BARRIO RESTREPO 13 BOGOTA | K6: REDEBAN | L6: FO-25-1362450 | FO-25-1353058 | M6: 45877.715 | N6: 45883.502 | P6: TRASLADO | Q6: TRASLADO | R6: CB UNO A UNO | S6: CB UNO A UNO | T6: EJECUTADO_CANCELADO | U6: PETICIÓN USUARIO | V6: 09/08/2025 9-08 8:59 EN COMUNICACIÓN ON LA SEÑORA DIANA DAZA AL NUMERO 3142711836 CONFIRMA SOLICITUD DE TRASLADO EXTERNO, CONFIRMA DATOS E INDICA QUE CUENTA CON TODAS LAS ADECUACIONES Y QUE LOS EQUIPOS SE ENCUENTRAN EN LA NUEVA DIRECCION, SE ESCALA PARA VISITA | 11/08/2025 DURANTE LA VISITA TÉCNICA PARA EJECUTAR EL TRASLADO DEL CORRESPONSAL AL LLEGAR SE EVIDENCIA QUE LA DIRECCIÓN SE ENCUENTRA ERRADA SE LLAMA EL NÚMERO DEL CORRESPONSAL DE CONTACTO 3134013834 EL CUAL NO RESPONDE EL SEÑOR CÉSAR MILLÁN Y NO INDICA UNA DIRECCIÓN DIFERENTE CL 81C SUR 6C 22 ESTE SE PROCEDE A VALIDAR CON SUPERVISOR LA DIRECCIÓN QUE TENEMOS EN LISTA DE CHEQUEO LA CUAL NO CORRESPONDE, SE PROCEDE A BRINDARLE INFORMACIÓN A CB PARA QUE SOLICITE UNA NUEVA VISITA CON LA DIRECCIÓN CORRECTA 14/08/2025 SE LLEGA DIRECCIÓN PARA EJECUTAR TRASLADO ENCONTRANDO CERRADO, SE INTENTA CONTACTO AL NÚMERO 3142711836 NO CONTESTAN SE VALIDA QUE EN DIAGONAL A LA DIRECCIÓN YA EXISTE UN CB BANCOLOMBIA EL CUAL SE INDAGA ES UN PTM CÓDIGO 62060 S | W6: VISITA_TÉCNICA | X6: 0 | Y6: TIPO I | Z6: =VLOOKUP(D6,TIPOLOGIAS!A:F,5,0) -> TERRESTRE | AA6: BUSTOS MORA DIEGO MANUEL | AB6: 2 | AC6: 0 | AD6: 0 | AE6: 0 | AF6: =IF(W6="SOPORTE_TELEFÓNICO",'BASE LIQUIDACION'!$B$10,IF(Y6="TIPO I",'BASE LIQUIDACION'!$C$3,IF(Y6="TIPO II",'BASE LIQUIDACION'!$C$4,IF(Y6="TIPO III",'BASE LIQUIDACION'!$C$5,'BASE LIQUIDACION'!$C$7)))) -> 65960.474 | AG6: =IF(W6="SOPORTE_TELEFÓNICO",'BASE LIQUIDACION'!$B$10,(AB6*AF6+AC6*'BASE LIQUIDACION'!$B$13+AD6*'BASE LIQUIDACION'!$B$12+AE6*'BASE LIQUIDACION'!$B$11)) -> 131920.95
