Workbook
Name A: #REF!
Name A: #REF!
Name ACTIVIDAD: [1]Hoja2!$P$2:$P$30
Name Actividad: [2]Formulas!$H$2:$H$5000
Name Analistas: '[3]Listas Desplegables'!$T$2:$T$7
Name arearesponsable: '[4]Listas desplegables'!$BB$2:$BB$100
Name CCO: [5]Tecnicos!$A$2:$A$1000
Name Clientes: [6]Clientes!$A$2:$A$100
Name Clientes: [2]Clientes!$A$2:$A$100
Name COORDINADOR: [1]Hoja2!$D$2:$D$30
Name Coordinadores: [7]Coordinadores!$A$2:$A$1000
Name Coordinadores: [2]Coordinadores!$A$2:$A$1000
Name DOCUMENTADOR: [1]Hoja2!$A$2:$A$30
Name ES: [1]Hoja2!$K$2:$K$30
Name ESS: [1]Hoja2!$K$2:$K$30
Name Estado: [6]Formulas!$K$2:$K$5000
Name Estado: [2]Formulas!$K$2:$K$5000
Name ESTADOACTIVIDAD: [1]Hoja2!$M$2:$M$30
Name ESTADOS: '[8]Listas desplegables'!$B$1:$D$1
Name ESTADOS: '[9]Listas desplegables'!$B$1:$D$1
Name ESTADOSCIERRES: '[10]lista desplegable'!$CX$1:$DA$1
Name Facturacion: '[11]Listas desplegables'!$AO$1:$AR$1
Name FACTURACIÓN: '[8]Listas desplegables'!$Y$1:$AB$1
Name FACTURACIÓN: '[9]Listas desplegables'!$Y$1:$AB$1
Name falla: #REF!
Name Fallas: '[12]Listas desplegables'!$F$2:$L$2
Name Fallas: '[13]Listas desplegables'!$F$2:$L$2
Name Grupo_Falla: '[14]Listas Desplegables'!$CH$2:$CH$5
Name Grupo_Falla: '[15]Listas Desplegables'!$CH$2:$CH$5
Name inconservmanager: '[16]Listas desplegables'!$BC$2:$BC$100
Name inconservmanager: '[4]Listas desplegables'!$BC$2:$BC$100
Name INCUMPLIMIENTO: '[4]Listas desplegables'!$AK$1:$AN$1
Name INCUMPLIMIENTO: '[17]Listas desplegables'!$AT$1:$AX$1
Name LISTA: [18]Dptos!$A$1139:$A$1171
Name LISTA: [19]Dptos!$A$1139:$A$1171
Name LISTA2: #REF!
Name LISTA2: #REF!
Name LOLO: [20]Coordinadores!$A$2:$A$1000
Name solicitudes: '[11]Listas desplegables'!$U$1:$AF$1
Name solicitudes: '[21]Listas desplegables'!$AF$1:$AQ$1
Name Tecnicos: [6]Tecnicos!$A$2:$A$1000
Name Tecnicos: [2]Tecnicos!$A$2:$A$1000
Name Version: [22]Formulas!$I$2:$I$3
Name Version: [2]Formulas!$I$2:$I$3

Sheet Detalle REDEBAN
A1: FACTURACIÓN ACTIVIDADES REDEBAN CB BANCOLOMBIA Y AVAL
A2: 1 AL 30 DE AGOSTO 2025
A4: CONCEPTOS | B4: CANTIDAD | C4: TOTAL
A5: Aperturas Bancolombia | B5: =COUNTA('APERTURAS BANCOLOMBIA'!$A:$A)-1 -> 508 | C5: ='APERTURAS BANCOLOMBIA'!AC510 -> 94349557
A6: Incidentes Bancolombia | B6: =COUNTA('INCIDENTES BANCOLOMBIA'!A:A)-1 -> 1268 | C6: ='INCIDENTES BANCOLOMBIA'!AF1270 -> 1.9300888e+08
A7: Gestión de Campo Bancolombia | B7: =COUNTA('OC BANCOLOMBIA'!A:A)-1 -> 449 | C7: ='OC BANCOLOMBIA'!AF451 -> 72797755
A8: Soporte Papelería Bancolombia | B8: =COUNTA(PAPELERIA!A:A)-1 -> 2113 | C8: =PAPELERIA!AE2115 -> 88607824
A9: Aperturas Aval | B9: =COUNTA('APERTURAS AVAL'!A:A)-1 -> 151 | C9: ='APERTURAS AVAL'!AB153 -> 23187291
A10: Incidentes Aval | B10: =COUNTA('INCIDENTES AVAL'!A:A)-1 -> 303 | C10: ='INCIDENTES AVAL'!AD305 -> 35001862
A11: Gestión de Campo Aval | B11: =COUNTA('OC AVAL'!A:A)-1 -> 92 | C11: ='OC AVAL'!AF94 -> 12141358
A12: Aperturas BBVA | B12: =COUNTA('APERTURAS BBVA'!A:A)-1 -> 0 | C12: ='APERTURAS BBVA'!AH3 -> 0
A13: Gestión de Campo BBVA | B13: =COUNTA('OC BBVA'!A:A)-1 -> 2 | C13: ='OC BBVA'!AF4 -> 289935.74
A14: Incidentes BBVA | B14: =COUNTA('INCIDENTES BBVA'!A:A)-1 -> 0 | C14: ='INCIDENTES BBVA'!AD5 -> 0
A15: SUBTOTAL | C15: =SUM(C5:C14) -> 5.1938446e+08
A16: Iva | C16: =C15*0.19 -> 98683047
A17: TOTAL | B17: TOTAL | C17: =C15+C16 -> 6.1806751e+08

Sheet BASE LIQUIDACION REDEBAN 2025
A1: Tipificación | B1: Implementaciones | C1: Incidentes – Ordenes de Cambio | D1: Fallida | G1: Tipificación | H1: Actividad sin cambio de datafono | J1: Actividad + adicional cambio de datafono | L1: Visita Fallida | N1: Incremento 2025
A2: TIPO I | B2: =71384.4052*(1+$N$2) -> 75096.394 | C2: =62699.6885*(1+$N$2) -> 65960.072 | D2: =35693.4343*(1+$N$2) -> 37549.493 | H2: Instalación Pinpad + HUB | I2: Segunda actividad en mismo comercio, misma visita | J2: Instalación Pinpad + HUB | K2: Segunda actividad en mismo comercio, misma visita | N2: 0.052
A3: TIPO II | B3: =155716.4408*(1+$N$2) -> 163813.7 | C3: =137802.16*(1+$N$2) -> 144967.87 | D3: =117879.8485*(1+$N$2) -> 124009.6 | G3: Tipo I | H3: =31819.23994686*(1+$N$2) -> 33473.84 | I3: =26222.67548178*(1+$N$2) -> 27586.255 | J3: =51196.46628516*(1+$N$2) -> 53858.683 | K3: =42157.66342524*(1+$N$2) -> 44349.862 | L3: =28948.10610808*(1+$N$2) -> 30453.408
A4: TIPO III | B4: =262099.6015*(1+$N$2) -> 275728.78 | C4: =262099.6015*(1+$N$2) -> 275728.78 | D4: =262099.6015*(1+$N$2) -> 275728.78 | G4: Tipo II | H4: =98014.03066668*(1+$N$2) -> 103110.76 | I4: =26222.67548178*(1+$N$2) -> 27586.255 | J4: =119562.49505524*(1+$N$2) -> 125779.74 | K4: =42157.66342524*(1+$N$2) -> 44349.862 | L4: =94765.6295813*(1+$N$2) -> 99693.442
A5: TIPO IV | B5: =479878.9419*(1+$N$2) -> 504832.65 | C5: =455882.9625*(1+$N$2) -> 479588.88 | D5: =370911.6746*(1+$N$2) -> 390199.08 | G5: Tipo III | H5: =189140.9827006*(1+$N$2) -> 198976.31 | I5: =26222.67548178*(1+$N$2) -> 27586.255 | J5: =200461.60194168*(1+$N$2) -> 210885.61 | K5: =42157.66342524*(1+$N$2) -> 44349.862 | L5: =171492.68108896*(1+$N$2) -> 180410.3
A6: Destino Aéreo | B6: =939603.5767*(1+$N$2) -> 988462.96 | C6: a partir del 5to servicio | G6: Tipo IV | H6: =461621.60109668*(1+$N$2) -> 485625.92 | I6: =26222.67548178*(1+$N$2) -> 27586.255 | J6: =461621.60109668*(1+$N$2) -> 485625.92 | K6: =42157.66342524*(1+$N$2) -> 44349.862 | L6: =461621.60109668*(1+$N$2) -> 485625.92
G7: * Tipo IV Especial Donde se requiera desplazamiento aéreo o fluvial será facturado el valor de la actividad y adicional el valor de $988.463 por cada 5 actividades de esta tipología
A8: Tarifas para día adicional de actividades:
A9: Tipificación | B9: Día adicional- menos de dos horas | C9: Medio día adicional | D9: Día adicional- más de 4 horas
A10: Tipo I | B10: =71384.4052*(1+$N$2) -> 75096.394 | C10: =133455.9267*(1+$N$2) -> 140395.63 | D10: =191225.1201*(1+$N$2) -> 201168.83 | G10: Actividad | H10: Unidad | I10: Valor Unitario
A11: Tipo II | B11: =133455.9267*(1+$N$2) -> 140395.63 | C11: =191225.1201*(1+$N$2) -> 201168.83 | D11: =257740.6152*(1+$N$2) -> 271143.13 | G11: Gestión telefónica y cierre de incidente de bloqueo | H11: Unidad | I11: =17639.19516086*(1+$N$2) -> 18556.433
A12: Tipo III | B12: =186821.7926*(1+$N$2) -> 196536.53 | C12: =248892.0824*(1+$N$2) -> 261834.47 | D12: =306662.5075*(1+$N$2) -> 322608.96 | G12: Servicio de cierre de incidente de bloqueo | H12: Unidad | I12: =4810.80785492*(1+$N$2) -> 5060.9699
A13: Tipo IV | B13: =186821.7926*(1+$N$2) -> 196536.53 | C13: =248892.0824*(1+$N$2) -> 261834.47 | D13: =306662.5075*(1+$N$2) -> 322608.96
A16: Servicio | B16: Tarifa actividad | D16: VALOR DE LA TERMINAL ADICIONAL | E16: VALOR DE INSTALACIÓN DE BASE EN "Y"
A17: Papelería – Tarifa única | B17: =34010.9321*(1+$N$2) -> 35779.501 | D17: =20537.3658*(1+$N$2) -> 21605.309 | E17: =10737.9606*(1+$N$2) -> 11296.335
A18: Papelería Tipo II - Visita técnica | B18: =64310*(1+$N$2) -> 67654.12
A19: Solución telefónica | B19: =39202.5476*(1+$N$2) -> 41241.08
A22: Traifas 2024
A23: Tipificación | B23: Implementaciones | C23: Incidentes – Ordenes de Cambio | D23: Fallida | G23: Tipificación | H23: Actividad sin cambio de datafono | J23: Actividad + adicional cambio de datafono | L23: Visita Fallida
A24: TIPO I | B24: 71384.405 | C24: 62699.689 | D24: 35693.434 | H24: Instalación Pinpad + HUB | I24: Segunda actividad en mismo comercio, misma visita | J24: Instalación Pinpad + HUB | K24: Segunda actividad en mismo comercio, misma visita
A25: TIPO II | B25: 155716.44 | C25: 137802.16 | D25: 117879.85 | G25: Tipo I | H25: 31819.24 | I25: 26222.675 | J25: 51196.466 | K25: 42157.663 | L25: 28948.106
A26: TIPO III | B26: 262099.6 | C26: 262099.6 | D26: 262099.6 | G26: Tipo II | H26: 98014.031 | I26: 26222.675 | J26: 119562.5 | K26: 42157.663 | L26: 94765.63
A27: TIPO IV | B27: 479878.94 | C27: 455882.96 | D27: 370911.67 | G27: Tipo III | H27: 189140.98 | I27: 26222.675 | J27: 200461.6 | K27: 42157.663 | L27: 171492.68
A28: Destino Aéreo | B28: 939603.58 | C28: a partir del 5to servicio | G28: Tipo IV | H28: 461621.6 | I28: 26222.675 | J28: 461621.6 | K28: 42157.663 | L28: 461621.6
G29: * Tipo IV Especial Donde se requiera desplazamiento aéreo o fluvial será facturado el valor de la actividad y adicional el valor de $939,604 por cada 5 actividades de esta tipología
A30: Tarifas para día adicional de actividades:
A31: Tipificación | B31: Día adicional- menos de dos horas | C31: Medio día adicional | D31: Día adicional- más de 4 horas
A32: Tipo I | B32: 71384.405 | C32: 133455.93 | D32: 191225.12 | G32: Actividad | H32: Unidad | I32: Valor Unitario
A33: Tipo II | B33: 133455.93 | C33: 191225.12 | D33: 257740.62 | G33: Gestión telefónica y cierre de incidente de bloqueo | H33: Unidad | I33: 17639.195
A34: Tipo III | B34: 186821.79 | C34: 248892.08 | D34: 306662.51 | G34: Servicio de cierre de incidente de bloqueo | H34: Unidad | I34: 4810.8079
A35: Tipo IV | B35: 186821.79 | C35: 248892.08 | D35: 306662.51
A38: Servicio | B38: Tarifa actividad | D38: VALOR DE LA TERMINAL ADICIONAL | E38: VALOR DE INSTALACIÓN DE BASE EN "Y"
A39: Papelería – Tarifa única | B39: 34010.932 | D39: 20537.366 | E39: 10737.961
A40: Papelería Tipo II - Visita técnica | B40: 64310
A41: Solución telefónica | B41: 39202.548

Sheet CENTRO DE COSTOS
A1: CIUDAD | B1: CENTRO_COSTO | C1: DESCRIPCION | D1: COORDINADOR
A2: APARTADO | B2: 0004-0005 | C2: Redeban Noroccidente (Medellín) | D2: JUAN SEBASTIÁN RÍOS CASTRILLÓN
A3: BARRANQUILLA | B3: 0004-0001 | C3: Redeban Costa (Barranqullla) | D3: JOSE MAURICIO HERNANDEZ ROJAS
A4: BOGOTA | B4: 0004-0004 | C4: Redeban Centro ( Bogotá) | D4: WILLIAM ASDRUBAL ROZO ROZO
A5: BUCARAMANGA | B5: 0004-0008 | C5: Redeban Santander | D5: MIGUEL JULIÁN HERNÁNDEZ GUARÍN
A6: CALI | B6: 0004-0003 | C6: Redeban Suroccidente (Cali) | D6: DIEGO FERNANDO HENAO CARDONA
A7: CARTAGENA | B7: 0004-0001 | C7: Redeban Costa (Barranqullla) | D7: JOSE MAURICIO HERNANDEZ ROJAS
A8: CUCUTA | B8: 0004-0008 | C8: Redeban Santander | D8: MIGUEL JULIÁN HERNÁNDEZ GUARÍN
A9: FLORENCIA | B9: 0004-0007 | C9: Redeban Oriente (Otros) | D9: KEVIN ALEXIS CORZO BUSTOS
A10: IBAGUE | B10: 0004-0007 | C10: Redeban Oriente (Otros) | D10: KEVIN ALEXIS CORZO BUSTOS
A11: MANIZALES | B11: 0004-0002 | C11: Redeban Eje Cafetero (Pereira) | D11: DIEGO FERNANDO HENAO CARDONA
A12: MEDELLIN | B12: 0004-0005 | C12: Redeban Noroccidente (Medellín) | D12: JUAN SEBASTIÁN RÍOS CASTRILLÓN
... A23: YOPAL | B23: 0004-0007 | C23: Redeban Oriente (Otros) | D23: KEVIN ALEXIS CORZO BUSTOS

Sheet Tablas dinámicas
A1: APERTURAS BANCOLOMBIA | G1: NOMBRE DE CC | H1: Suma de VALOR CC | I1: Suma de VALOR CC2
A2: COORDINADOR | B2: CENTRO DE COSTOS LÍNEACOM | C2: Suma de VALOR FACTURABLE A LA RED | D2: NOMBRE DE CC | E2: VALOR CC | G2: Redeban Centro ( Bogotá) | H2: 58483522 | I2: 0.1126016
A3: DIEGO FERNANDO HENAO CARDONA | B3: 0004-0002 | C3: 5822339.2 | D3: =VLOOKUP(B3,'CENTRO DE COSTOS'!B:C,2,0) -> Redeban Eje Cafetero (Pereira) | E3: =C3 -> 5822339.2 | G3: Redeban Costa (Barranqullla) | H3: 87388554 | I3: 0.16825408
B4: 0004-0003 | C4: 16230338 | D4: =VLOOKUP(B4,'CENTRO DE COSTOS'!B:C,2,0) -> Redeban Suroccidente (Cali) | E4: =C4 -> 16230338 | G4: Redeban Eje Cafetero (Pereira) | H4: 22430644 | I4: 0.043186976
A5: JOSE MAURICIO HERNANDEZ ROJAS | B5: 0004-0001 | C5: 16690174 | D5: =VLOOKUP(B5,'CENTRO DE COSTOS'!B:C,2,0) -> Redeban Costa (Barranqullla) | E5: =C5 -> 16690174 | G5: Redeban Noroccidente (Medellín) | H5: 1.0264108e+08 | I5: 0.19762062
A6: JUAN SEBASTIÁN RÍOS CASTRILLÓN | B6: 0004-0005 | C6: 15826985 | D6: =VLOOKUP(B6,'CENTRO DE COSTOS'!B:C,2,0) -> Redeban Noroccidente (Medellín) | E6: =C6 -> 15826985 | G6: Redeban Oriente (Otros) | H6: 76399104 | I6: 0.14709548
A7: KEVIN ALEXIS CORZO BUSTOS | B7: 0004-0007 | C7: 12991593 | D7: =VLOOKUP(B7,'CENTRO DE COSTOS'!B:C,2,0) -> Redeban Oriente (Otros) | E7: =C7 -> 12991593 | G7: Redeban Santander | H7: 96753187 | I7: 0.18628433
A8: MIGUEL JULIÁN HERNÁNDEZ GUARÍN | B8: 0004-0008 | C8: 19062375 | D8: =VLOOKUP(B8,'CENTRO DE COSTOS'!B:C,2,0) -> Redeban Santander | E8: =C8 -> 19062375 | G8: Redeban Suroccidente (Cali) | H8: 75288369 | I8: 0.14495691
A9: WILLIAM ASDRUBAL ROZO ROZO | B9: 0004-0004 | C9: 7725752.1 | D9: =VLOOKUP(B9,'CENTRO DE COSTOS'!B:C,2,0) -> Redeban Centro ( Bogotá) | E9: =C9 -> 7725752.1 | G9: Total general | H9: 5.1938446e+08 | I9: 1
A10: Total general | C10: 94349557
A15: INCIDENTES BANCOLOMBIA
A16: COORDINADOR | B16: CENTRO DE COSTOS LÍNEACOM | C16: Suma de VALOR FACTURABLE A LA RED | D16: NOMBRE DE CC | E16: VALOR CC
A17: DIEGO FERNANDO HENAO CARDONA | B17: 0004-0002 | C17: 7597782.2 | D17: =VLOOKUP(B17,'CENTRO DE COSTOS'!B:C,2,0) -> Redeban Eje Cafetero (Pereira) | E17: =C17 -> 7597782.2
B18: 0004-0003 | C18: 25923885 | D18: =VLOOKUP(B18,'CENTRO DE COSTOS'!B:C,2,0) -> Redeban Suroccidente (Cali) | E18: =C18 -> 25923885
A19: JOSE MAURICIO HERNANDEZ ROJAS | B19: 0004-0001 | C19: 38090363 | D19: =VLOOKUP(B19,'CENTRO DE COSTOS'!B:C,2,0) -> Redeban Costa (Barranqullla) | E19: =C19 -> 38090363
A20: JUAN SEBASTIÁN RÍOS CASTRILLÓN | B20: 0004-0005 | C20: 44541702 | D20: =VLOOKUP(B20,'CENTRO DE COSTOS'!B:C,2,0) -> Redeban Noroccidente (Medellín) | E20: =C20 -> 44541702
A21: KEVIN ALEXIS CORZO BUSTOS | B21: 0004-0007 | C21: 27986392 | D21: =VLOOKUP(B21,'CENTRO DE COSTOS'!B:C,2,0) -> Redeban Oriente (Otros) | E21: =C21 -> 27986392
A22: MIGUEL JULIÁN HERNÁNDEZ GUARÍN | B22: 0004-0008 | C22: 32605647 | D22: =VLOOKUP(B22,'CENTRO DE COSTOS'!B:C,2,0) -> Redeban Santander | E22: =C22 -> 32605647
A23: WILLIAM ASDRUBAL ROZO ROZO | B23: 0004-0004 | C23: 16263108 | D23: =VLOOKUP(B23,'CENTRO DE COSTOS'!B:C,2,0) -> Redeban Centro ( Bogotá) | E23: =C23 -> 16263108
A24: Total general | C24: 1.9300888e+08
A30: ORDENES DE CAMBIO BANCOLOMBIA
A31: COORDINADOR | B31: CENTRO DE COSTOS LÍNEACOM | C31: Suma de VALOR TOTAL | D31: NOMBRE DE CC | E31: VALOR CC
A32: DIEGO FERNANDO HENAO CARDONA | B32: 0004-0002 | C32: 2817155.6 | D32: =VLOOKUP(B32,'CENTRO DE COSTOS'!B:C,2,0) -> Redeban Eje Cafetero (Pereira) | E32: =C32 -> 2817155.6
B33: 0004-0003 | C33: 9402777.1 | D33: =VLOOKUP(B33,'CENTRO DE COSTOS'!B:C,2,0) -> Redeban Suroccidente (Cali) | E33: =C33 -> 9402777.1
A34: JOSE MAURICIO HERNANDEZ ROJAS | B34: 0004-0001 | C34: 9215551.5 | D34: =VLOOKUP(B34,'CENTRO DE COSTOS'!B:C,2,0) -> Redeban Costa (Barranqullla) | E34: =C34 -> 9215551.5
A35: JUAN SEBASTIÁN RÍOS CASTRILLÓN | B35: 0004-0005 | C35: 15480396 | D35: =VLOOKUP(B35,'CENTRO DE COSTOS'!B:C,2,0) -> Redeban Noroccidente (Medellín) | E35: =C35 -> 15480396
A36: KEVIN ALEXIS CORZO BUSTOS | B36: 0004-0007 | C36: 11899557 | D36: =VLOOKUP(B36,'CENTRO DE COSTOS'!B:C,2,0) -> Redeban Oriente (Otros) | E36: =C36 -> 11899557
A37: MIGUEL JULIÁN HERNÁNDEZ GUARÍN | B37: 0004-0008 | C37: 16002255 | D37: =VLOOKUP(B37,'CENTRO DE COSTOS'!B:C,2,0) -> Redeban Santander | E37: =C37 -> 16002255
A38: WILLIAM ASDRUBAL ROZO ROZO | B38: 0004-0004 | C38: 7980063.8 | D38: =VLOOKUP(B38,'CENTRO DE COSTOS'!B:C,2,0) -> Redeban Centro ( Bogotá) | E38: =C38 -> 7980063.8
A39: Total general | C39: 72797755
A45: PAPELERIA BANCOLOMBIA
A46: COORDINADOR | B46: CENTRO DE COSTOS LÍNEACOM | C46: Suma de VALOR TOTAL | D46: NOMBRE DE CC | E46: VALOR CC
A47: DIEGO FERNANDO HENAO CARDONA | B47: 0004-0002 | C47: 4394975.5 | D47: =VLOOKUP(B47,'CENTRO DE COSTOS'!B:C,2,0) -> Redeban Eje Cafetero (Pereira) | E47: =C47 -> 4394975.5
B48: 0004-0003 | C48: 12183386 | D48: =VLOOKUP(B48,'CENTRO DE COSTOS'!B:C,2,0) -> Redeban Suroccidente (Cali) | E48: =C48 -> 12183386
A49: JOSE MAURICIO HERNANDEZ ROJAS | B49: 0004-0001 | C49: 17391768 | D49: =VLOOKUP(B49,'CENTRO DE COSTOS'!B:C,2,0) -> Redeban Costa (Barranqullla) | E49: =C49 -> 17391768
A50: JUAN SEBASTIÁN RÍOS CASTRILLÓN | B50: 0004-0005 | C50: 20563599 | D50: =VLOOKUP(B50,'CENTRO DE COSTOS'!B:C,2,0) -> Redeban Noroccidente (Medellín) | E50: =C50 -> 20563599
A51: KEVIN ALEXIS CORZO BUSTOS | B51: 0004-0007 | C51: 9461601.8 | D51: =VLOOKUP(B51,'CENTRO DE COSTOS'!B:C,2,0) -> Redeban Oriente (Otros) | E51: =C51 -> 9461601.8
A52: MIGUEL JULIÁN HERNÁNDEZ GUARÍN | B52: 0004-0008 | C52: 13964993 | D52: =VLOOKUP(B52,'CENTRO DE COSTOS'!B:C,2,0) -> Redeban Santander | E52: =C52 -> 13964993
A53: WILLIAM ASDRUBAL ROZO ROZO | B53: 0004-0004 | C53: 10647501 | D53: =VLOOKUP(B53,'CENTRO DE COSTOS'!B:C,2,0) -> Redeban Centro ( Bogotá) | E53: =C53 -> 10647501
A54: Total general | C54: 88607824
A60: APERTURAS BBVA
A61: COORDINADOR | B61: CENTRO DE COSTOS | C61: Suma de VALOR FACTURABLE A LA RED | D61: NOMBRE DE CC | E61: VALOR CC
A62: Total general | D62: =VLOOKUP(B62,'CENTRO DE COSTOS'!B:C,2,0) -> #N/A | E62: =C62 -> 0
A67: OC BBVA
A68: COORDINADOR | B68: CENTRO DE COSTOS | C68: Suma de VALOR FACTURABLE A LA RED | D68: NOMBRE DE CC | E68: VALOR CC
A69: DIEGO FERNANDO HENAO CARDONA | B69: 0004-0002 | C69: 289935.74 | D69: =VLOOKUP(B69,'CENTRO DE COSTOS'!B:C,2,0) -> Redeban Eje Cafetero (Pereira) | E69: =C69 -> 289935.74
A70: Total general | C70: 289935.74
A75: INCIDENTE BBVA
A76: COORDINADOR | B76: CENTRO DE COSTOS LÍNEACOM | C76: Suma de VALOR FACTURABLE A LA RED | D76: NOMBRE DE CC | E76: VALOR CC
A77: Total general | D77: =VLOOKUP(B77,'CENTRO DE COSTOS'!B:C,2,0) -> #N/A | E77: =C77 -> 0
A83: APERTURAS AVAL
A84: COORDINADOR | B84: CENTRO DE COSTOS LÍNEACOM | C84: Suma de VALOR FACTURABLE A LA RED | D84: NOMBRE DE CC | E84: VALOR CC
A85: DIEGO FERNANDO HENAO CARDONA | B85: 0004-0002 | C85: 819068.48 | D85: =VLOOKUP(B85,'CENTRO DE COSTOS'!B:C,2,0) -> Redeban Eje Cafetero (Pereira) | E85: =C85 -> 819068.48
B86: 0004-0003 | C86: 4475898.5 | D86: =VLOOKUP(B86,'CENTRO DE COSTOS'!B:C,2,0) -> Redeban Suroccidente (Cali) | E86: =C86 -> 4475898.5
A87: JOSE MAURICIO HERNANDEZ ROJAS | B87: 0004-0001 | C87: 1105833.1 | D87: =VLOOKUP(B87,'CENTRO DE COSTOS'!B:C,2,0) -> Redeban Costa (Barranqullla) | E87: =C87 -> 1105833.1
A88: JUAN SEBASTIÁN RÍOS CASTRILLÓN | B88: 0004-0005 | C88: 965217.24 | D88: =VLOOKUP(B88,'CENTRO DE COSTOS'!B:C,2,0) -> Redeban Noroccidente (Medellín) | E88: =C88 -> 965217.24
A89: KEVIN ALEXIS CORZO BUSTOS | B89: 0004-0007 | C89: 6385387.2 | D89: =VLOOKUP(B89,'CENTRO DE COSTOS'!B:C,2,0) -> Redeban Oriente (Otros) | E89: =C89 -> 6385387.2
A90: MIGUEL JULIÁN HERNÁNDEZ GUARÍN | B90: 0004-0008 | C90: 3975109.9 | D90: =VLOOKUP(B90,'CENTRO DE COSTOS'!B:C,2,0) -> Redeban Santander | E90: =C90 -> 3975109.9
A91: WILLIAM ASDRUBAL ROZO ROZO | B91: 0004-0004 | C91: 5460776.1 | D91: =VLOOKUP(B91,'CENTRO DE COSTOS'!B:C,2,0) -> Redeban Centro ( Bogotá) | E91: =C91 -> 5460776.1
A92: Total general | C92: 23187291
A97: INCIDENTES AVAL
A98: COORDINADOR | B98: CENTRO DE COSTOS LÍNEACOM | C98: Suma de VALOR FACTURABLE A LA RED | D98: NOMBRE DE CC | E98: VALOR CC
A99: DIEGO FERNANDO HENAO CARDONA | B99: 0004-0002 | C99: 413658.98 | D99: =VLOOKUP(B99,'CENTRO DE COSTOS'!B:C,2,0) -> Redeban Eje Cafetero (Pereira) | E99: =C99 -> 413658.98
B100: 0004-0003 | C100: 5764336.3 | D100: =VLOOKUP(B100,'CENTRO DE COSTOS'!B:C,2,0) -> Redeban Suroccidente (Cali) | E100: =C100 -> 5764336.3
A101: JOSE MAURICIO HERNANDEZ ROJAS | B101: 0004-0001 | C101: 3419529 | D101: =VLOOKUP(B101,'CENTRO DE COSTOS'!B:C,2,0) -> Redeban Costa (Barranqullla) | E101: =C101 -> 3419529
A102: JUAN SEBASTIÁN RÍOS CASTRILLÓN | B102: 0004-0005 | C102: 3751458 | D102: =VLOOKUP(B102,'CENTRO DE COSTOS'!B:C,2,0) -> Redeban Noroccidente (Medellín) | E102: =C102 -> 3751458
A103: KEVIN ALEXIS CORZO BUSTOS | B103: 0004-0007 | C103: 6488013.1 | D103: =VLOOKUP(B103,'CENTRO DE COSTOS'!B:C,2,0) -> Redeban Oriente (Otros) | E103: =C103 -> 6488013.1
A104: MIGUEL JULIÁN HERNÁNDEZ GUARÍN | B104: 0004-0008 | C104: 8792338.4 | D104: =VLOOKUP(B104,'CENTRO DE COSTOS'!B:C,2,0) -> Redeban Santander | E104: =C104 -> 8792338.4
A105: WILLIAM ASDRUBAL ROZO ROZO | B105: 0004-0004 | C105: 6372527.9 | D105: =VLOOKUP(B105,'CENTRO DE COSTOS'!B:C,2,0) -> Redeban Centro ( Bogotá) | E105: =C105 -> 6372527.9
A106: Total general | C106: 35001862
A111: OC AVAL
A112: COORDINADOR | B112: CENTRO DE COSTOS LÍNEACOM | C112: Suma de VALOR FACTURABLE A LA RED | D112: NOMBRE DE CC | E112: VALOR CC
A113: DIEGO FERNANDO HENAO CARDONA | B113: 0004-0002 | C113: 275728.78 | D113: =VLOOKUP(B113,'CENTRO DE COSTOS'!B:C,2,0) -> Redeban Eje Cafetero (Pereira) | E113: =C113 -> 275728.78
B114: 0004-0003 | C114: 1307747.4 | D114: =VLOOKUP(B114,'CENTRO DE COSTOS'!B:C,2,0) -> Redeban Suroccidente (Cali) | E114: =C114 -> 1307747.4
A115: JOSE MAURICIO HERNANDEZ ROJAS | B115: 0004-0001 | C115: 1475336.4 | D115: =VLOOKUP(B115,'CENTRO DE COSTOS'!B:C,2,0) -> Redeban Costa (Barranqullla) | E115: =C115 -> 1475336.4
A116: JUAN SEBASTIÁN RÍOS CASTRILLÓN | B116: 0004-0005 | C116: 1511723.3 | D116: =VLOOKUP(B116,'CENTRO DE COSTOS'!B:C,2,0) -> Redeban Noroccidente (Medellín) | E116: =C116 -> 1511723.3
A117: KEVIN ALEXIS CORZO BUSTOS | B117: 0004-0007 | C117: 1186559.9 | D117: =VLOOKUP(B117,'CENTRO DE COSTOS'!B:C,2,0) -> Redeban Oriente (Otros) | E117: =C117 -> 1186559.9
A118: MIGUEL JULIÁN HERNÁNDEZ GUARÍN | B118: 0004-0008 | C118: 2350469 | D118: =VLOOKUP(B118,'CENTRO DE COSTOS'!B:C,2,0) -> Redeban Santander | E118: =C118 -> 2350469
A119: WILLIAM ASDRUBAL ROZO ROZO | B119: 0004-0004 | C119: 4033793.3 | D119: =VLOOKUP(B119,'CENTRO DE COSTOS'!B:C,2,0) -> Redeban Centro ( Bogotá) | E119: =C119 -> 4033793.3
A120: Total general | C120: 12141358

Sheet APERTURAS BANCOLOMBIA
A1: CIUDAD SEDE | B1: COORDINADOR | C1: CENTRO DE COSTOS LÍNEACOM | D1: CÓDIGO DANE | E1: TA/CODIGO ACTIVIDAD | F1: CODIGO CB | G1: ACTIVIDAD | H1: TIPO DE APERTURA | I1: DEPARTAMENTO | J1: CIUDAD | K1: NOMBRE DEL CB | L1: RED | M1: FO | N1: FECHA LISTA | O1: FECHA ULTIMA ACTUALIZACION | P1: FORMATO | Q1: CADENA | R1: ESTADO | S1: OBSERVACIONES CLIENTE | T1: FORMA DE ATENCIÓN | U1: TERMINALES | V1: TIPO DE ATENCION | W1: TIPO DE TRAYECTO | X1: NOMBRE DEL TECNICO | Y1: DIAS DE VISITA | Z1: DIA ADICIONAL | AA1: VALOR DIAS ACTIVIDAD FACTURABLES A LA RED | AB1: VALOR DIAS ACOMPAÑAMIENTO FACTURABLES | AC1: VALOR FACTURABLE A LA RED | AD1: CU CB | AE1: COBRO ENTIDAD | AF1: ESTADO | AG1: TIPO | AH1: VAL TIPO | AI1: VAL COSTO | AJ1: OBSERVACIONES | AK1: OBSERVACIONES LINEA
A2: NEIVA | B2: =VLOOKUP(A2,'CENTRO DE COSTOS'!A:D,4,FALSE) -> KEVIN ALEXIS CORZO BUSTOS | C2: =VLOOKUP(A2,'CENTRO DE COSTOS'!A:D,2,FALSE) -> 0004-0007 | D2: 18001 | E2: TA-25-897275 | F2: 80665 | G2: APERTURA | H2: CB CRECIMIENTO - NUEVO | I2: CAQUETA | J2: FLORENCIA | K2: BARRIO BUENOS AIRES FLORENCIA 1 | L2: REDEBAN | M2: FO-25-1293630 | N2: 45866 | O2: 45870 | P2: UNO A UNO | Q2: UNO A UNO | R2: EJECUTADO | S2: 28-07-2025 SE REALIZA LLAMADA AL CLIENTE, SE HABLA CON CON EL ESPOSO DE LA SRA LEIDY VERONICA CARVAJAL BARRETO SE VALIDA DIRECCIÓN OK, CANAL OK, DISPONIBILIDAD TOTAL, LLAMAR EL DÍA LA INSTALACIÓN PARA CONFIRMAR VISITA, AVISO EXTERIOR ALTURA APROX 3,30 METROS; TOMACORRIENTE CERCANO: SI; TIENE CABINA DE SEGURIDAD: NO // CONTACTO REALIZADO POR LA APP 01-0 SE REALIZA INSTALACIÓN DE CORRESPONSAL, SE INSTALAN EQUIPOS CON PRUEBAS EXITOSAS, SE CAPACITA Y SE EVALÚA AL CLIENTE, SE INSTALA PUBLICIDAD COMPLETA, CB QUEDA OPERATIVO. USUARIO SOMOS BANCOLOMBIA ACTIVO | T2: VISITA_TECNICA | U2: V8ZZZ345 | V2: TIPO IV | W2: TERRESTRE | X2: DEVIA REINOSO JUAN CARLOS | Y2: 1 | Z2: 0 | AA2: =IF(V2="TIPO I",'BASE LIQUIDACION REDEBAN 2025'!$B$2,IF(V2="TIPO II",'BASE LIQUIDACION REDEBAN 2025'!$B$3,IF(V2="TIPO III",'BASE LIQUIDACION REDEBAN 2025'!$B$4,IF(V2="TIPO IV",'BASE LIQUIDACION REDEBAN 2025'!$B$5,IF(W2="AEREO",'BASE LIQUIDACION REDEBAN 2025'!$B$6,'BASE LIQUIDACION REDEBAN 2025'!$B$5))))) -> 504832.65 | AB2: =IF(V2="TIPO I",'BASE LIQUIDACION REDEBAN 2025'!$B$10,IF(V2="TIPO II",'BASE LIQUIDACION REDEBAN 2025'!$B$11,IF(V2="TIPO III",'BASE LIQUIDACION REDEBAN 2025'!$B$12,'BASE LIQUIDACION REDEBAN 2025'!$B$13))) -> 196536.53 | AC2: =Y2*AA2+Z2*AB2 -> 504832.65
A3: NEIVA | B3: =VLOOKUP(A3,'CENTRO DE COSTOS'!A:D,4,FALSE) -> KEVIN ALEXIS CORZO BUSTOS | C3: =VLOOKUP(A3,'CENTRO DE COSTOS'!A:D,2,FALSE) -> 0004-0007 | D3: 18001 | E3: TA-25-897283 | F3: 80664 | G3: APERTURA | H3: CB CRECIMIENTO - NUEVO | I3: CAQUETA | J3: FLORENCIA | K3: BARRIO SIETE DE AGOSTO FLORENCIA 7 | L3: REDEBAN | M3: FO-25-1293646 | N3: 45866 | O3: 45870 | P3: UNO A UNO | Q3: UNO A UNO | R3: EJECUTADO | S3: 28-07-2025 SE REALIZA LLAMADA AL CLIENTE, SE HABLA CON CON EL SR LUIS MIGUEL BAHAMON ROJAS SE VALIDA DIRECCIÓN OK, CANAL OK, DISPONIBILIDAD TOTAL, LLAMAR EL DÍA LA INSTALACIÓN PARA CONFIRMAR VISITA, AVISO EXTERIOR ALTURA APROX 2 METROS; TOMACORRIENTE CERCANO: SI; TIENE CABINA DE SEGURIDAD: SI // CONTACTO REALIZADO POR LA APP 1/08/2025 SE REALIZA INSTALACIÓN DE CORRESPONSAL, SE INSTALAN EQUIPOS CON PRUEBAS EXITOSAS, SE CAPACITA Y SE EVALÚA AL CLIENTE, SE INSTALA PUBLICIDAD COMPLETA, CB QUEDA OPERATIVO. USUARIO SOMOS BANCOLOMBIA ACTIVO | T3: VISITA_TECNICA | U3: V8ZZZ349 | V3: TIPO IV | W3: TERRESTRE | X3: DEVIA REINOSO JUAN CARLOS | Y3: 1 | Z3: 0 | AA3: =IF(V3="TIPO I",'BASE LIQUIDACION REDEBAN 2025'!$B$2,IF(V3="TIPO II",'BASE LIQUIDACION REDEBAN 2025'!$B$3,IF(V3="TIPO III",'BASE LIQUIDACION REDEBAN 2025'!$B$4,IF(V3="TIPO IV",'BASE LIQUIDACION REDEBAN 2025'!$B$5,IF(W3="AEREO",'BASE LIQUIDACION REDEBAN 2025'!$B$6,'BASE LIQUIDACION REDEBAN 2025'!$B$5))))) -> 504832.65 | AB3: =IF(V3="TIPO I",'BASE LIQUIDACION REDEBAN 2025'!$B$10,IF(V3="TIPO II",'BASE LIQUIDACION REDEBAN 2025'!$B$11,IF(V3="TIPO III",'BASE LIQUIDACION REDEBAN 2025'!$B$12,'BASE LIQUIDACION REDEBAN 2025'!$B$13))) -> 196536.53 | AC3: =Y3*AA3+Z3*AB3 -> 504832.65
A4: PASTO | B4: =VLOOKUP(A4,'CENTRO DE COSTOS'!A:D,4,FALSE) -> DIEGO FERNANDO HENAO CARDONA | C4: =VLOOKUP(A4,'CENTRO DE COSTOS'!A:D,2,FALSE) -> 0004-0003 | D4: 52427 | E4: TA-25-897342 | F4: 80676 | G4: APERTURA | H4: CB CRECIMIENTO - NUEVO | I4: NARIÑO | J4: MAGUI | K4: BARRIO CRR BRISAS DE HAMBURGO MAGUI | L4: REDEBAN | M4: FO-25-1293775 | N4: 45866 | O4: 45883 | P4: UNO A UNO | Q4: UNO A UNO | R4: EJECUTADO | S4: 28-07 SE REALIZA LLAMADA AL CLIENTE, SE HABLA CON LA SRA KAROL NATALIA ANGULO CORTES SE VALIDA DIRECCIÓN OK, CANAL OK, DISPONIBILIDAD TOTAL, LLAMAR EL DÍA LA INSTALACIÓN PARA CONFIRMAR VISITA, AVISO EXTERIOR ALTURA APROX 4 METROS; TOMACORRIENTE CERCANO: SI; TIENE CABINA DE SEGURIDAD: SI 06-08 DADO QUE EL SITIO SE DEBE REALIZAR DESPLAZAMIENTO MARITIMO, SE REALIZARA EL DIA LUNES 11 POR DISPONIBILIDAD DE TRANSPORTE. 11-08 SÉ ALCANZO A LLEGAR HASTA POR DEMORAS EN EL TRANSPORTE (LANCHA) 12-08 SE ESTA PENDIENTE DEL TRANSPORTE EN LANCHA PARA LLEGAR AL SITIO, NOS ENCONTRAMOS EN LA ZONA EN DESPLAZAMIENTO 13-08 SE LLEGA TARDE AL MUNICIPIO Y POR ENDE NO SE ALCANCANZA A REALIZAR LA INSTALACIÓN, SE PROGRAMA PARA EL DIA SIGUIENTE 14/08/2025 SE REALIZA INSTALACIÓN DE CORRESPONSAL, SE INSTALAN EQUIPOS CON PRUEBAS EXITOSAS, SE CAPACITA Y SE EVALÚA AL CLIENTE, SE INSTALA PUBLICIDAD COMPLETA, CB QUEDA OPERATIVO. USUARIO SOMOS BANCOLOMBIA ACTIVO | T4: VISITA_TECNICA | U4: V8ZZZ380 | V4: TIPO IV ESPECIAL | W4: FLUVIAL | X4: PAZ MARTINEZ RICHARD HUMBERTO | Y4: 1 | Z4: 0 | AA4: =IF(V4="TIPO I",'BASE LIQUIDACION REDEBAN 2025'!$B$2,IF(V4="TIPO II",'BASE LIQUIDACION REDEBAN 2025'!$B$3,IF(V4="TIPO III",'BASE LIQUIDACION REDEBAN 2025'!$B$4,IF(V4="TIPO IV",'BASE LIQUIDACION REDEBAN 2025'!$B$5,IF(W4="AEREO",'BASE LIQUIDACION REDEBAN 2025'!$B$6,'BASE LIQUIDACION REDEBAN 2025'!$B$5))))) -> 504832.65 | AB4: =IF(V4="TIPO I",'BASE LIQUIDACION REDEBAN 2025'!$B$10,IF(V4="TIPO II",'BASE LIQUIDACION REDEBAN 2025'!$B$11,IF(V4="TIPO III",'BASE LIQUIDACION REDEBAN 2025'!$B$12,'BASE LIQUIDACION REDEBAN 2025'!$B$13))) -> 196536.53 | AC4: =Y4*AA4+Z4*AB4 -> 504832.65
A5: PASTO | B5: =VLOOKUP(A5,'CENTRO DE COSTOS'!A:D,4,FALSE) -> DIEGO FERNANDO HENAO CARDONA | C5: =VLOOKUP(A5,'CENTRO DE COSTOS'!A:D,2,FALSE) -> 0004-0003 | D5: 52427 | E5: TA-25-897364 | F5: 80675 | G5: APERTURA | H5: CB CRECIMIENTO - NUEVO | I5: NARIÑO | J5: MAGUI | K5: BARRIO LA PISTA MAGUI | L5: REDEBAN | M5: FO-25-1293834 | N5: 45866 | O5: 45883 | P5: UNO A UNO | Q5: UNO A UNO | R5: EJECUTADO | S5: 28-07 SE REALIZA LLAMADA AL CLIENTE, SE HABLA CON LA SRA DAYAN YORELY ANGULO CORTES SE VALIDA DIRECCIÓN OK, CANAL OK, DISPONIBILIDAD TOTAL, LLAMAR EL DÍA LA INSTALACIÓN PARA CONFIRMAR VISITA, AVISO EXTERIOR ALTURA APROX 4 METROS; TOMACORRIENTE CERCANO: SI; TIENE CABINA DE SEGURIDAD: SI - COMUNICACIÓN POR WPP 06-08 DEBIDO A QUE EL DESPLAZAMIENTO ES VIA MARITIMA, DADO DISPONIBILIDAD DE TRANSPORTE SE REALIZARA EL DIA LUNES 11-08 SÉ ALCANZO A LLEGAR HASTA POR DEMORAS EN EL TRANSPORTE (LANCHA) 12-08 SE ESTA PENDIENTE DEL TRANSPORTE EN LANCHA PARA LLEGAR AL SITIO, NOS ENCONTRAMOS EN LA ZONA EN DESPLAZAMIENTO 13-08 SE LLEGA TARDE AL MUNICIPIO Y POR ENDE NO SE ALCANCANZA A REALIZAR LA INSTALACIÓN, SE PROGRAMA PARA EL DIA SIGUIENTE 14/08/2025 SE REALIZA INSTALACIÓN DE CORRESPONSAL, SE INSTALAN EQUIPOS CON PRUEBAS EXITOSAS, SE CAPACITA Y SE EVALÚA AL CLIENTE, SE INSTALA PUBLICIDAD COMPLETA, CB QUEDA OPERATIVO. USUARIO SOMOS BANCOLOMBIA ACTIVO | T5: VISITA_TECNICA | U5: V8ZZZ393 | V5: TIPO IV ESPECIAL | W5: FLUVIAL | X5: PAZ MARTINEZ RICHARD HUMBERTO | Y5: 1 | Z5: 0 | AA5: =IF(V5="TIPO I",'BASE LIQUIDACION REDEBAN 2025'!$B$2,IF(V5="TIPO II",'BASE LIQUIDACION REDEBAN 2025'!$B$3,IF(V5="TIPO III",'BASE LIQUIDACION REDEBAN 2025'!$B$4,IF(V5="TIPO IV",'BASE LIQUIDACION REDEBAN 2025'!$B$5,IF(W5="AEREO",'BASE LIQUIDACION REDEBAN 2025'!$B$6,'BASE LIQUIDACION REDEBAN 2025'!$B$5))))) -> 504832.65 | AB5: =IF(V5="TIPO I",'BASE LIQUIDACION REDEBAN 2025'!$B$10,IF(V5="TIPO II",'BASE LIQUIDACION REDEBAN 2025'!$B$11,IF(V5="TIPO III",'BASE LIQUIDACION REDEBAN 2025'!$B$12,'BASE LIQUIDACION REDEBAN 2025'!$B$13))) -> 196536.53 | AC5: =Y5*AA5+Z5*AB5 -> 504832.65
A6: YOPAL | B6: =VLOOKUP(A6,'CENTRO DE COSTOS'!A:D,4,FALSE) -> KEVIN ALEXIS CORZO BUSTOS | C6: =VLOOKUP(A6,'CENTRO DE COSTOS'!A:D,2,FALSE) -> 0004-0007 | D6: 85001 | E6: TA-25-897375 | F6: 80709 | G6: APERTURA | H6: CB CRECIMIENTO - NUEVO | I6: CASANARE | J6: YOPAL | K6: BARRIO LA ESPERANZA YOPAL 6 | L6: REDEBAN | M6: FO-25-1293877 | N6: 45866 | O6: 45870 | P6: UNO A UNO | Q6: UNO A UNO | R6: EJECUTADO | S6: 28-07 SE REALIZA COMUNICACION CON LA SRA ZULEIMA SIERRA ZAPATA, SE VALIDA DIRECCIÓN OK, CANAL OK, DISPONIBILIDAD TOTAL, LLAMAR EL DÍA LA INSTALACIÓN PARA CONFIRMAR VISITA, AVISO EXTERIOR ALTURA APROX DONDE EL TECNICO LO VEA CONVENIENTE; TOMACORRIENTE CERCANO: SI; TIENE CABINA DE SEGURIDAD: SI// MODEM A 5 METROS 29-07 EN COMUNICACIÓN CON LA SEÑORA ZULEIMA SIERRA AL NUMERO 3228924900, INDICA QUE POR TEMAS PERSONALES NO PUEDE ATENDER HOY LA INSTALACIÓN, INDICA NOS ATIENDE EL DIA 31-7-2025 31-07 EN COMUNICACIÓN CON LA SEÑORA ZULEIMA SIERRA AL NÚMERO 3228924900, INDICA NOS ATIENDE EL DIA 2-8-2025 1/08/2025 SE REALIZA INSTALACIÓN DE CORRESPONSAL, SE INSTALAN EQUIPOS CON PRUEBAS EXITOSAS, SE CAPACITA Y SE EVALÚA AL CLIENTE, SE INSTALA PUBLICIDAD COMPLETA, CB QUEDA OPERATIVO. USUARIO SOMOS BANCOLOMBIA ACTIVO | T6: VISITA_TECNICA | U6: V8ZZZ402 | V6: TIPO I | W6: TERRESTRE | X6: BERNAL ELAICA EDGAR ALEXIS | Y6: 1 | Z6: 0 | AA6: =IF(V6="TIPO I",'BASE LIQUIDACION REDEBAN 2025'!$B$2,IF(V6="TIPO II",'BASE LIQUIDACION REDEBAN 2025'!$B$3,IF(V6="TIPO III",'BASE LIQUIDACION REDEBAN 2025'!$B$4,IF(V6="TIPO IV",'BASE LIQUIDACION REDEBAN 2025'!$B$5,IF(W6="AEREO",'BASE LIQUIDACION REDEBAN 2025'!$B$6,'BASE LIQUIDACION REDEBAN 2025'!$B$5))))) -> 75096.394 | AB6: =IF(V6="TIPO I",'BASE LIQUIDACION REDEBAN 2025'!$B$10,IF(V6="TIPO II",'BASE LIQUIDACION REDEBAN 2025'!$B$11,IF(V6="TIPO III",'BASE LIQUIDACION REDEBAN 2025'!$B$12,'BASE LIQUIDACION REDEBAN 2025'!$B$13))) -> 75096.394 | AC6: =Y6*AA6+Z6*AB6 -> 75096.394
A7: MEDELLIN | B7: =VLOOKUP(A7,'CENTRO DE COSTOS'!A:D,4,FALSE) -> JUAN SEBASTIÁN RÍOS CASTRILLÓN | C7: =VLOOKUP(A7,'CENTRO DE COSTOS'!A:D,2,FALSE) -> 0004-0005 | D7: 5001 | E7: TA-25-904686 | F7: 80717 | G7: APERTURA | H7: CB CRECIMIENTO ALIANZA - NUEVO | I7: ANTIOQUIA | J7: MEDELLIN | K7: DISTRICOL VARIEDADES Y DETALLE | L7: REDEBAN | M7: FO-25-1306012 | N7: 45868 | O7: 45870 | P7: AGREGADOR | Q7: DISTRICOL | R7: EJECUTADO | S7: 30/07/2025 PROGRAMACIÓN REALIZADA POR LA ALIANZA 1/08/2025 SE REALIZA INSTALACIÓN DE CORRESPONSAL, SE INSTALAN EQUIPOS CON PRUEBAS EXITOSAS, SE CAPACITA Y SE EVALÚA AL CLIENTE, SE INSTALA PUBLICIDAD COMPLETA, CB QUEDA OPERATIVO. USUARIO SOMOS BANCOLOMBIA ACTIVO | T7: VISITA_TECNICA | U7: VAZZZ340 | V7: TIPO I | W7: TERRESTRE | X7: BARRIENTOS HERNANDEZ CRISTIAN HORACIO | Y7: 1 | Z7: 0 | AA7: =IF(V7="TIPO I",'BASE LIQUIDACION REDEBAN 2025'!$B$2,IF(V7="TIPO II",'BASE LIQUIDACION REDEBAN 2025'!$B$3,IF(V7="TIPO III",'BASE LIQUIDACION REDEBAN 2025'!$B$4,IF(V7="TIPO IV",'BASE LIQUIDACION REDEBAN 2025'!$B$5,IF(W7="AEREO",'BASE LIQUIDACION REDEBAN 2025'!$B$6,'BASE LIQUIDACION REDEBAN 2025'!$B$5))))) -> 75096.394 | AB7: =IF(V7="TIPO I",'BASE LIQUIDACION REDEBAN 2025'!$B$10,IF(V7="TIPO II",'BASE LIQUIDACION REDEBAN 2025'!$B$11,IF(V7="TIPO III",'BASE LIQUIDACION REDEBAN 2025'!$B$12,'BASE LIQUIDACION REDEBAN 2025'!$B$13))) -> 75096.394 | AC7: =Y7*AA7+Z7*AB7 -> 75096.394
A8: MEDELLIN | B8: =VLOOKUP(A8,'CENTRO DE COSTOS'!A:D,4,FALSE) -> JUAN SEBASTIÁN RÍOS CASTRILLÓN | C8: =VLOOKUP(A8,'CENTRO DE COSTOS'!A:D,2,FALSE) -> 0004-0005 | D8: 5001 | E8: TA-25-904688 | F8: 80718 | G8: APERTURA | H8: CB CRECIMIENTO ALIANZA - NUEVO | I8: ANTIOQUIA | J8: MEDELLIN | K8: DISTRICOL PAPELERIA LA PIZARRA | L8: REDEBAN | M8: FO-25-1306018 | N8: 45868 | O8: 45870 | P8: AGREGADOR | Q8: DISTRICOL | R8: EJECUTADO | S8: 30/07/2025 PROGRAMACIÓN REALIZADA POR LA ALIANZA 1/08/2025 SE REALIZA INSTALACIÓN DE CORRESPONSAL, SE INSTALAN EQUIPOS CON PRUEBAS EXITOSAS, SE CAPACITA Y SE EVALÚA AL CLIENTE, SE INSTALA PUBLICIDAD COMPLETA, CB QUEDA OPERATIVO. USUARIO SOMOS BANCOLOMBIA ACTIVO | T8: VISITA_TECNICA | U8: VAZZZ341 | V8: TIPO I | W8: TERRESTRE | X8: PAREJA ECHAVARRIA JHON DAVID | Y8: 1 | Z8: 0 | AA8: =IF(V8="TIPO I",'BASE LIQUIDACION REDEBAN 2025'!$B$2,IF(V8="TIPO II",'BASE LIQUIDACION REDEBAN 2025'!$B$3,IF(V8="TIPO III",'BASE LIQUIDACION REDEBAN 2025'!$B$4,IF(V8="TIPO IV",'BASE LIQUIDACION REDEBAN 2025'!$B$5,IF(W8="AEREO",'BASE LIQUIDACION REDEBAN 2025'!$B$6,'BASE LIQUIDACION REDEBAN 2025'!$B$5))))) -> 75096.394 | AB8: =IF(V8="TIPO I",'BASE LIQUIDACION REDEBAN 2025'!$B$10,IF(V8="TIPO II",'BASE LIQUIDACION REDEBAN 2025'!$B$11,IF(V8="TIPO III",'BASE LIQUIDACION REDEBAN 2025'!$B$12,'BASE LIQUIDACION REDEBAN 2025'!$B$13))) -> 75096.394 | AC8: =Y8*AA8+Z8*AB8 -> 75096.394
A9: MEDELLIN | B9: =VLOOKUP(A9,'CENTRO DE COSTOS'!A:D,4,FALSE) -> JUAN SEBASTIÁN RÍOS CASTRILLÓN | C9: =VLOOKUP(A9,'CENTRO DE COSTOS'!A:D,2,FALSE) -> 0004-0005 | D9: 5088 | E9: TA-25-904689 | F9: 80715 | G9: APERTURA | H9: CB CRECIMIENTO ALIANZA - NUEVO | I9: ANTIOQUIA | J9: BELLO | K9: DISTRICOL ABARROTES EL PUERTO | L9: REDEBAN | M9: FO-25-1306022 | N9: 45868 | O9: 45870 | P9: AGREGADOR | Q9: DISTRICOL | R9: EJECUTADO | S9: 30/07/2025 PROGRAMACIÓN REALIZADA POR LA ALIANZA 1/08/2025 SE REALIZA INSTALACIÓN DE CORRESPONSAL, SE INSTALAN EQUIPOS CON PRUEBAS EXITOSAS, SE CAPACITA Y SE EVALÚA AL CLIENTE, SE INSTALA PUBLICIDAD COMPLETA, CB QUEDA OPERATIVO. USUARIO SOMOS BANCOLOMBIA ACTIVO | T9: VISITA_TECNICA | U9: VAZZZ342 | V9: TIPO I | W9: TERRESTRE | X9: BARRIENTOS HERNANDEZ CRISTIAN HORACIO | Y9: 1 | Z9: 0 | AA9: =IF(V9="TIPO I",'BASE LIQUIDACION REDEBAN 2025'!$B$2,IF(V9="TIPO II",'BASE LIQUIDACION REDEBAN 2025'!$B$3,IF(V9="TIPO III",'BASE LIQUIDACION REDEBAN 2025'!$B$4,IF(V9="TIPO IV",'BASE LIQUIDACION REDEBAN 2025'!$B$5,IF(W9="AEREO",'BASE LIQUIDACION REDEBAN 2025'!$B$6,'BASE LIQUIDACION REDEBAN 2025'!$B$5))))) -> 75096.394 | AB9: =IF(V9="TIPO I",'BASE LIQUIDACION REDEBAN 2025'!$B$10,IF(V9="TIPO II",'BASE LIQUIDACION REDEBAN 2025'!$B$11,IF(V9="TIPO III",'BASE LIQUIDACION REDEBAN 2025'!$B$12,'BASE LIQUIDACION REDEBAN 2025'!$B$13))) -> 75096.394 | AC9: =Y9*AA9+Z9*AB9 -> 75096.394
A10: NEIVA | B10: =VLOOKUP(A10,'CENTRO DE COSTOS'!A:D,4,FALSE) -> KEVIN ALEXIS CORZO BUSTOS | C10: =VLOOKUP(A10,'CENTRO DE COSTOS'!A:D,2,FALSE) -> 0004-0007 | D10: 18753 | E10: TA-25-904057 | F10: 31694 | G10: APERTURA | H10: DATAFONO ADICIONAL - ALIANZA | I10: CAQUETA | J10: SAN VICENTE DEL CAGUAN | K10: Multipagas - San Vicente del Caguan | L10: REDEBAN | M10: FO-25-1304946 | N10: 45868 | O10: 45875 | P10: ROBUSTO | Q10: MULTIPAGAS | R10: EJECUTADO | S10: 30-07-2025 SE REALIZA LLAMADA AL CLIENTE, SE HABLA CON LA SRA Tatiana Penagos SE VALIDA DIRECCIÓN OK, CANAL OK, DISPONIBILIDAD TOTAL, LLAMAR EL DÍA LA INSTALACIÓN PARA CONFIRMAR VISITA 6/08/2025 SE REALIZA INSTALACIÓN DE DAT ADICIONAL, PRUEBAS EXITOSAS, CB QUEDA OPERATIVO | T10: VISITA_TECNICA | U10: VAZZZ348 VAZZZ349 | V10: TIPO IV ESPECIAL | W10: TERRESTRE / AEREO | X10: BERMUDEZ SANCHEZ JOSE NEYBER | Y10: 1 | Z10: 0 | AA10: =IF(V10="TIPO I",'BASE LIQUIDACION REDEBAN 2025'!$B$2,IF(V10="TIPO II",'BASE LIQUIDACION REDEBAN 2025'!$B$3,IF(V10="TIPO III",'BASE LIQUIDACION REDEBAN 2025'!$B$4,IF(V10="TIPO IV",'BASE LIQUIDACION REDEBAN 2025'!$B$5,IF(W10="AEREO",'BASE LIQUIDACION REDEBAN 2025'!$B$6,'BASE LIQUIDACION REDEBAN 2025'!$B$5))))) -> 504832.65 | AB10: =IF(V10="TIPO I",'BASE LIQUIDACION REDEBAN 2025'!$B$10,IF(V10="TIPO II",'BASE LIQUIDACION REDEBAN 2025'!$B$11,IF(V10="TIPO III",'BASE LIQUIDACION REDEBAN 2025'!$B$12,'BASE LIQUIDACION REDEBAN 2025'!$B$13))) -> 196536.53 | AC10: =Y10*AA10+Z10*AB10 -> 504832.65
A11: CALI | B11: =VLOOKUP(A11,'CENTRO DE COSTOS'!A:D,4,FALSE) -> DIEGO FERNANDO HENAO CARDONA | C11: =VLOOKUP(A11,'CENTRO DE COSTOS'!A:D,2,FALSE) -> 0004-0003 | D11: 76892 | E11: TA-25-904699 | F11: 66067 | G11: APERTURA | H11: DATAFONO ADICIONAL - ALIANZA | I11: VALLE DEL CAUCA | J11: YUMBO | K11: DISTRICOL DIST MISC THOVAJU | L11: REDEBAN | M11: FO-25-1306040 | N11: 45868 | O11: 45870 | P11: AGREGADOR | Q11: DISTRICOL | R11: EJECUTADO | S11: 30/07/2025 PROGRAMACIÓN REALIZADA POR LA ALIANZA 1/08/2025 SE REALIZA INSTALACIÓN DE DAT ADICIONAL, PRUEBAS EXITOSAS, CB QUEDA OPERATIVO | T11: VISITA_TECNICA | U11: VAZZZ351 | V11: TIPO I | W11: TERRESTRE | X11: MONTERO MUESES GIAN CARLO | Y11: 1 | Z11: 0 | AA11: =IF(V11="TIPO I",'BASE LIQUIDACION REDEBAN 2025'!$B$2,IF(V11="TIPO II",'BASE LIQUIDACION REDEBAN 2025'!$B$3,IF(V11="TIPO III",'BASE LIQUIDACION REDEBAN 2025'!$B$4,IF(V11="TIPO IV",'BASE LIQUIDACION REDEBAN 2025'!$B$5,IF(W11="AEREO",'BASE LIQUIDACION REDEBAN 2025'!$B$6,'BASE LIQUIDACION REDEBAN 2025'!$B$5))))) -> 75096.394 | AB11: =IF(V11="TIPO I",'BASE LIQUIDACION REDEBAN 2025'!$B$10,IF(V11="TIPO II",'BASE LIQUIDACION REDEBAN 2025'!$B$11,IF(V11="TIPO III",'BASE LIQUIDACION REDEBAN 2025'!$B$12,'BASE LIQUIDACION REDEBAN 2025'!$B$13))) -> 75096.394 | AC11: =Y11*AA11+Z11*AB11 -> 75096.394
A12: YOPAL | B12: =VLOOKUP(A12,'CENTRO DE COSTOS'!A:D,4,FALSE) -> KEVIN ALEXIS CORZO BUSTOS | C12: =VLOOKUP(A12,'CENTRO DE COSTOS'!A:D,2,FALSE) -> 0004-0007 | D12: 85162 | E12: TA-25-904063 | F12: 80742 | G12: APERTURA | H12: CB CRECIMIENTO - NUEVO | I12: CASANARE | J12: MONTERREY | K12: BARRIO ALCARAVANES MONTERREY 1 | L12: REDEBAN | M12: FO-25-1304972 | N12: 45868 | O12: 45874 | P12: UNO A UNO | Q12: UNO A UNO | R12: EJECUTADO | S12: 30-07-2025 SE REALIZA LLAMADA AL CLIENTE, SE HABLA CON EL SR EDWIN YESID SOSA BUITRAGO SE VALIDA DIRECCIÓN OK, CANAL OK, DISPONIBILIDAD TOTAL, LLAMAR EL DÍA LA INSTALACIÓN PARA CONFIRMAR VISITA, AVISO EXTERIOR ALTURA APROX SE VALIDA EL DIA DE LA APERTURA HAY ESPACIO SUFICIENTE; TOMACORRIENTE CERCANO: SI; TIENE CABINA DE SEGURIDAD: SI // CONTACTO REALIZADO POR LA APP 01-08 EN COMUNICACIÓN CON EL SEÑOR EDWIN SOSA AL NUMERO 3114659005, SE INFORMA QUE NO SE PUEDE REALIZAR LA APERTURA, MOTIVO CIERRE DE LA MARGINAL, CICLISMO VUELTA COLOMBIA. INDICA NOS ATIENDE EL 5-8-2025 5/08/2025 SE REALIZA INSTALACIÓN DE CORRESPONSAL, SE INSTALAN EQUIPOS CON PRUEBAS EXITOSAS, SE CAPACITA Y SE EVALÚA AL CLIENTE, SE INSTALA PUBLICIDAD COMPLETA, CB QUEDA OPERATIVO. USUARIO SOMOS BANCOLOMBIA ACTIVO | T12: VISITA_TECNICA | U12: VAZZZ361 | V12: TIPO II | W12: TERRESTRE | X12: BERNAL ELAICA EDGAR ALEXIS | Y12: 1 | Z12: 0 | AA12: =IF(V12="TIPO I",'BASE LIQUIDACION REDEBAN 2025'!$B$2,IF(V12="TIPO II",'BASE LIQUIDACION REDEBAN 2025'!$B$3,IF(V12="TIPO III",'BASE LIQUIDACION REDEBAN 2025'!$B$4,IF(V12="TIPO IV",'BASE LIQUIDACION REDEBAN 2025'!$B$5,IF(W12="AEREO",'BASE LIQUIDACION REDEBAN 2025'!$B$6,'BASE LIQUIDACION REDEBAN 2025'!$B$5))))) -> 163813.7 | AB12: =IF(V12="TIPO I",'BASE LIQUIDACION REDEBAN 2025'!$B$10,IF(V12="TIPO II",'BASE LIQUIDACION REDEBAN 2025'!$B$11,IF(V12="TIPO III",'BASE LIQUIDACION REDEBAN 2025'!$B$12,'BASE LIQUIDACION REDEBAN 2025'!$B$13))) -> 140395.63 | AC12: =Y12*AA12+Z12*AB12 -> 163813.7
A13: TUNJA | B13: =VLOOKUP(A13,'CENTRO DE COSTOS'!A:D,4,FALSE) -> MIGUEL JULIÁN HERNÁNDEZ GUARÍN | C13: =VLOOKUP(A13,'CENTRO DE COSTOS'!A:D,2,FALSE) -> 0004-0008 | D13: 15464 | E13: TA-25-904065 | F13: 80720 | G13: APERTURA | H13: CB CRECIMIENTO - NUEVO | I13: BOYACA | J13: MONGUA | K13: BARRIO CENTRO MONGUA 1 | L13: REDEBAN | M13: FO-25-1304982 | N13: 45868 | O13: 45870 | P13: UNO A UNO | Q13: UNO A UNO | R13: EJECUTADO | S13: 30-07-2025 SE REALIZA LLAMADA AL CLIENTE, SE HABLA CON LA SRA YESICA PAOLA MERCHAN CASTAÑEDA SE VALIDA DIRECCIÓN OK, CANAL OK, DISPONIBILIDAD TOTAL, LLAMAR EL DÍA LA INSTALACIÓN PARA CONFIRMAR VISITA, AVISO EXTERIOR ALTURA APROX 2,50 METROS; TOMACORRIENTE CERCANO: SI; TIENE CABINA DE SEGURIDAD: SI // CONTACTO REALIZADO POR LA APP 01-08 SE REALIZA INSTALACIÓN DE CORRESPONSAL, SE INSTALAN EQUIPOS CON PRUEBAS EXITOSAS, SE CAPACITA Y SE EVALÚA AL CLIENTE, SE INSTALA PUBLICIDAD COMPLETA, CB QUEDA OPERATIVO. USUARIO SOMOS BANCOLOMBIA ACTIVO | T13: VISITA_TECNICA | U13: VAZZZ363 | V13: TIPO II | W13: TERRESTRE | X13: SOLER HOYOS CRISTIAN LEONARDO | Y13: 1 | Z13: 0 | AA13: =IF(V13="TIPO I",'BASE LIQUIDACION REDEBAN 2025'!$B$2,IF(V13="TIPO II",'BASE LIQUIDACION REDEBAN 2025'!$B$3,IF(V13="TIPO III",'BASE LIQUIDACION REDEBAN 2025'!$B$4,IF(V13="TIPO IV",'BASE LIQUIDACION REDEBAN 2025'!$B$5,IF(W13="AEREO",'BASE LIQUIDACION REDEBAN 2025'!$B$6,'BASE LIQUIDACION REDEBAN 2025'!$B$5))))) -> 163813.7 | AB13: =IF(V13="TIPO I",'BASE LIQUIDACION REDEBAN 2025'!$B$10,IF(V13="TIPO II",'BASE LIQUIDACION REDEBAN 2025'!$B$11,IF(V13="TIPO III",'BASE LIQUIDACION REDEBAN 2025'!$B$12,'BASE LIQUIDACION REDEBAN 2025'!$B$13))) -> 140395.63 | AC13: =Y13*AA13+Z13*AB13 -> 163813.7
... A509: PEREIRA | B509: =VLOOKUP(A509,'CENTRO DE COSTOS'!A:D,4,FALSE) -> DIEGO FERNANDO HENAO CARDONA | C509: =VLOOKUP(A509,'CENTRO DE COSTOS'!A:D,2,FALSE) -> 0004-0002 | D509: 76147 | E509: TA-25-1034508 | F509: 67249 | G509: APERTURA | H509: DATAFONO ADICIONAL - ALIANZA | I509: VALLE DEL CAUCA | J509: CARTAGO | K509: DISTRICOL MISCELANEA Y PANADER | L509: REDEBAN | M509: FO-25-1433980 | N509: 45896 | O509: 45898 | P509: AGREGADOR | Q509: DISTRICOL | R509: EJECUTADO | S509: 27-08 PROGRAMACIÓN REALIZADA POR LA ALIANZA 29/08/2025 SE REALIZA INSTALACIÓN DE DAT ADICIONAL, PRUEBAS EXITOSAS, CB QUEDA OPERATIVO | T509: VISITA_TECNICA | U509: FKZZZ702 | V509: TIPO I | W509: TERRESTRE | X509: LOAIZA LOPEZ JHON FREDDY | Y509: 1 | Z509: 0 | AA509: =IF(V509="TIPO I",'BASE LIQUIDACION REDEBAN 2025'!$B$2,IF(V509="TIPO II",'BASE LIQUIDACION REDEBAN 2025'!$B$3,IF(V509="TIPO III",'BASE LIQUIDACION REDEBAN 2025'!$B$4,IF(V509="TIPO IV",'BASE LIQUIDACION REDEBAN 2025'!$B$5,IF(W509="AEREO",'BASE LIQUIDACION REDEBAN 2025'!$B$6,'BASE LIQUIDACION REDEBAN 2025'!$B$5))))) -> 75096.394 | AB509: =IF(V509="TIPO I",'BASE LIQUIDACION REDEBAN 2025'!$B$10,IF(V509="TIPO II",'BASE LIQUIDACION REDEBAN 2025'!$B$11,IF(V509="TIPO III",'BASE LIQUIDACION REDEBAN 2025'!$B$12,'BASE LIQUIDACION REDEBAN 2025'!$B$13))) -> 75096.394 | AC509: =Y509*AA509+Z509*AB509 -> 75096.394
AC510: =SUM(AC2:AC509) -> 94349557

Sheet INCIDENTES BANCOLOMBIA
A1: CIUDAD SEDE | B1: COORDINADOR | C1: CENTRO DE COSTOS LÍNEACOM | D1: CÓDIGO DANE | E1: TA/CODIGO ACTIVIDAD | F1: CODIGO CB | G1: ACTIVIDAD | H1: DEPARTAMENTO | I1: CIUDAD | J1: NOMBRE DEL CB | K1: RED | L1: FO | M1: FECHA ASIGNACIÓN A LÍNEA COMUNICACIONES (DD/MM/AAAA HH:MM) | N1: FECHA CIERRE DEL TICKET (DD/MM/AAAA HH:MM) | O1: ACOMETIDA | P1: GRUPO_FALLA | Q1: CATEGORÍA | R1: FALLA | S1: FORMATO | T1: CADENA | U1: ESTADO | V1: OBSERVACION | W1: FORMA DE ATENCIÓN | X1: TERMINAL | Y1: TIPIFICACION | Z1: TIPO DE TRAYECTO | AA1: NOMBRE DEL TECNICO | AB1: DIAS DE VISITA | AC1: DIA ADICIONAL | AD1: VALOR DIAS ACTIVIDAD FACTURABLES A LA RED | AE1: VALOR DIAS ACOMPAÑAMIENTO FACTURABLES A RED | AF1: VALOR FACTURABLE A LA RED | AG1: CU CB | AH1: COBRO ENTIDAD | AI1: ESTADO | AJ1: TIPO | AK1: VAL TIPO | AL1: VAL COSTO | AM1: OBSERVACIONES | AN1: Observaciones LINEA
A2: BUCARAMANGA | B2: =VLOOKUP(A2,'CENTRO DE COSTOS'!A:D,4,FALSE) -> MIGUEL JULIÁN HERNÁNDEZ GUARÍN | C2: =VLOOKUP(A2,'CENTRO DE COSTOS'!A:D,2,FALSE) -> 0004-0008 | D2: 68679 | E2: 2535859 | F2: 48929 | G2: INCIDENTE | H2: SANTANDER | I2: SAN GIL | J2: DISTRICOL COMUNICACIONES JIRET | K2: REDEBAN | L2: FO-25-1313905 | M2: 45869.72 | N2: 45870.369 | O2: NO | P2: HARDWARE | Q2: ACTUALIZACION | R2: VERSION CAMBIO POS | S2: AGREGADOR | U2: CERRADO | V2: 01/08/2025 SE REALIZA VISITA AL COMERCIO SE ACTUALIZA DATAFONO A LA VERSIÓN 9.90 SE REALIZAN PRUEBAS OK | W2: VISITA_TÉCNICA | X2: AD00M861 | Y2: TIPO II | Z2: TERRESTRE | AA2: MARIÑO PABON JORGE ENRIQUE | AB2: 1 | AC2: 0 | AD2: =IF(W2="SOPORTE_TELEFÓNICO",'BASE LIQUIDACION REDEBAN 2025'!$B$19,IF(W2="ENVÍO",'BASE LIQUIDACION REDEBAN 2025'!$C$2,IF(Y2="TIPO I",'BASE LIQUIDACION REDEBAN 2025'!$C$2,IF(Y2="TIPO II",'BASE LIQUIDACION REDEBAN 2025'!$C$3,IF(Y2="TIPO III",'BASE LIQUIDACION REDEBAN 2025'!$C$4,IF(Y2="TIPO IV",'BASE LIQUIDACION REDEBAN 2025'!$C$5,IF(Z2="AEREO",'BASE LIQUIDACION REDEBAN 2025'!$B$6,'BASE LIQUIDACION REDEBAN 2025'!$C$5))))))) -> 144967.87 | AE2: =IF(OR(W2="SOPORTE_TELEFÓNICO",W2="ENVÍO"),0,IF(Y2="TIPO I",'BASE LIQUIDACION REDEBAN 2025'!$B$10,IF(Y2="TIPO II",'BASE LIQUIDACION REDEBAN 2025'!$B$11,IF(Y2="TIPO III",'BASE LIQUIDACION REDEBAN 2025'!$B$12,'BASE LIQUIDACION REDEBAN 2025'!$B$13)))) -> 140395.63 | AF2: =IF(OR(W2="SOPORTE_TELEFÓNICO",W2="ENVÍO"),AD2,(AD2*AB2+AE2*AC2)) -> 144967.87
A3: CUCUTA | B3: =VLOOKUP(A3,'CENTRO DE COSTOS'!A:D,4,FALSE) -> MIGUEL JULIÁN HERNÁNDEZ GUARÍN | C3: =VLOOKUP(A3,'CENTRO DE COSTOS'!A:D,2,FALSE) -> 0004-0008 | D3: 54405 | E3: 2535436 | F3: 53530 | G3: INCIDENTE | H3: NORTE DE SANTANDER | I3: LOS PATIOS | J3: BARRIO SANTA ROSA DE LIMA LOS | K3: REDEBAN | L3: FO-25-1313417 | M3: 45869.669 | N3: 45870.374 | O3: NO | P3: HARDWARE | Q3: LECTOR DE BARRAS | R3: DAÑO POS | S3: CB UNO A UNO | U3: CERRADO | V3: 31/07/2025 31-07 SE ESCALA PARA VISITA. LLAMAR ANTES DE VISITAR, CONFIRMAR FALLA Y DATOS | 01/08/2025 SE REALIZÓ VISITA AL COMERCIO Y SE ENCUENTRA LECTORA DAÑADA, SE REALIZA CAMBIO DE EQUIPO PRUEBAS EXITOSAS | W3: VISITA_TÉCNICA | X3: TR0VZ607 | Y3: TIPO I | Z3: TERRESTRE | AA3: MORA VEGA JEAMPIER | AB3: 1 | AC3: 0 | AD3: =IF(W3="SOPORTE_TELEFÓNICO",'BASE LIQUIDACION REDEBAN 2025'!$B$19,IF(W3="ENVÍO",'BASE LIQUIDACION REDEBAN 2025'!$C$2,IF(Y3="TIPO I",'BASE LIQUIDACION REDEBAN 2025'!$C$2,IF(Y3="TIPO II",'BASE LIQUIDACION REDEBAN 2025'!$C$3,IF(Y3="TIPO III",'BASE LIQUIDACION REDEBAN 2025'!$C$4,IF(Y3="TIPO IV",'BASE LIQUIDACION REDEBAN 2025'!$C$5,IF(Z3="AEREO",'BASE LIQUIDACION REDEBAN 2025'!$B$6,'BASE LIQUIDACION REDEBAN 2025'!$C$5))))))) -> 65960.072 | AE3: =IF(OR(W3="SOPORTE_TELEFÓNICO",W3="ENVÍO"),0,IF(Y3="TIPO I",'BASE LIQUIDACION REDEBAN 2025'!$B$10,IF(Y3="TIPO II",'BASE LIQUIDACION REDEBAN 2025'!$B$11,IF(Y3="TIPO III",'BASE LIQUIDACION REDEBAN 2025'!$B$12,'BASE LIQUIDACION REDEBAN 2025'!$B$13)))) -> 75096.394 | AF3: =IF(OR(W3="SOPORTE_TELEFÓNICO",W3="ENVÍO"),AD3,(AD3*AB3+AE3*AC3)) -> 65960.072
A4: MEDELLIN | B4: =VLOOKUP(A4,'CENTRO DE COSTOS'!A:D,4,FALSE) -> JUAN SEBASTIÁN RÍOS CASTRILLÓN | C4: =VLOOKUP(A4,'CENTRO DE COSTOS'!A:D,2,FALSE) -> 0004-0005 | D4: 5890 | E4: 2531780 | F4: 76392 | G4: INCIDENTE | H4: ANTIOQUIA | I4: YOLOMBO | J4: PTM YOLOMBO DROGUERIA EL RUBI | K4: REDEBAN | L4: FO-25-1310322 | M4: 45869.403 | N4: 45870.382 | O4: NO | P4: HARDWARE | Q4: COMUNICACION | R4: DAÑO POS | S4: AGREGADOR | U4: CERRADO | V4: 31/07/2025 31-07 SE ESCALA PARA VISITA. LLAMAR ANTES DE VISITAR, CONFIRMAR FALLA Y DATOS | 31/07/2025 SE CAMBIA EQUIPO POR PUERTO DE RED MALO | W4: VISITA_TÉCNICA | X4: A10RZ489 - A10SZ735 | Y4: TIPO II | Z4: TERRESTRE | AA4: BADEL ACUÑA LUIS ALBERTO | AB4: 1 | AC4: 0 | AD4: =IF(W4="SOPORTE_TELEFÓNICO",'BASE LIQUIDACION REDEBAN 2025'!$B$19,IF(W4="ENVÍO",'BASE LIQUIDACION REDEBAN 2025'!$C$2,IF(Y4="TIPO I",'BASE LIQUIDACION REDEBAN 2025'!$C$2,IF(Y4="TIPO II",'BASE LIQUIDACION REDEBAN 2025'!$C$3,IF(Y4="TIPO III",'BASE LIQUIDACION REDEBAN 2025'!$C$4,IF(Y4="TIPO IV",'BASE LIQUIDACION REDEBAN 2025'!$C$5,IF(Z4="AEREO",'BASE LIQUIDACION REDEBAN 2025'!$B$6,'BASE LIQUIDACION REDEBAN 2025'!$C$5))))))) -> 144967.87 | AE4: =IF(OR(W4="SOPORTE_TELEFÓNICO",W4="ENVÍO"),0,IF(Y4="TIPO I",'BASE LIQUIDACION REDEBAN 2025'!$B$10,IF(Y4="TIPO II",'BASE LIQUIDACION REDEBAN 2025'!$B$11,IF(Y4="TIPO III",'BASE LIQUIDACION REDEBAN 2025'!$B$12,'BASE LIQUIDACION REDEBAN 2025'!$B$13)))) -> 140395.63 | AF4: =IF(OR(W4="SOPORTE_TELEFÓNICO",W4="ENVÍO"),AD4,(AD4*AB4+AE4*AC4)) -> 144967.87
A5: MEDELLIN | B5: =VLOOKUP(A5,'CENTRO DE COSTOS'!A:D,4,FALSE) -> JUAN SEBASTIÁN RÍOS CASTRILLÓN | C5: =VLOOKUP(A5,'CENTRO DE COSTOS'!A:D,2,FALSE) -> 0004-0005 | D5: 5088 | E5: 2534410 | F5: 30086 | G5: INCIDENTE | H5: ANTIOQUIA | I5: BELLO | J5: COMCARD BELLO MERCADOS LA CRUZ | K5: REDEBAN | L5: FO-25-1312972 | M5: 45869.602 | N5: 45870.401 | O5: NO | P5: HARDWARE | Q5: COMUNICACION | R5: MENSAJE CABLE DE RED DESCONECTADO | S5: AGREGADOR | U5: CERRADO | V5: 01/08/2025 SE REVISA EL CABLE DE RED Y SE ENCUENTRA EL MAL ESTADO SE REPONCHA EL CABLE DE RED REALIZAN PRUEBAS EXITOSAS SERVICIO OPERATIVO OK | W5: VISITA_TÉCNICA | X5: BBTZZ891 | Y5: TIPO I | Z5: TERRESTRE | AA5: ZAPATA LOPEZ EDWARD ASDRUBAL | AB5: 1 | AC5: 0 | AD5: =IF(W5="SOPORTE_TELEFÓNICO",'BASE LIQUIDACION REDEBAN 2025'!$B$19,IF(W5="ENVÍO",'BASE LIQUIDACION REDEBAN 2025'!$C$2,IF(Y5="TIPO I",'BASE LIQUIDACION REDEBAN 2025'!$C$2,IF(Y5="TIPO II",'BASE LIQUIDACION REDEBAN 2025'!$C$3,IF(Y5="TIPO III",'BASE LIQUIDACION REDEBAN 2025'!$C$4,IF(Y5="TIPO IV",'BASE LIQUIDACION REDEBAN 2025'!$C$5,IF(Z5="AEREO",'BASE LIQUIDACION REDEBAN 2025'!$B$6,'BASE LIQUIDACION REDEBAN 2025'!$C$5))))))) -> 65960.072 | AE5: =IF(OR(W5="SOPORTE_TELEFÓNICO",W5="ENVÍO"),0,IF(Y5="TIPO I",'BASE LIQUIDACION REDEBAN 2025'!$B$10,IF(Y5="TIPO II",'BASE LIQUIDACION REDEBAN 2025'!$B$11,IF(Y5="TIPO III",'BASE LIQUIDACION REDEBAN 2025'!$B$12,'BASE LIQUIDACION REDEBAN 2025'!$B$13)))) -> 75096.394 | AF5: =IF(OR(W5="SOPORTE_TELEFÓNICO",W5="ENVÍO"),AD5,(AD5*AB5+AE5*AC5)) -> 65960.072
A6: CARTAGENA | B6: =VLOOKUP(A6,'CENTRO DE COSTOS'!A:D,4,FALSE) -> JOSE MAURICIO HERNANDEZ ROJAS | C6: =VLOOKUP(A6,'CENTRO DE COSTOS'!A:D,2,FALSE) -> 0004-0001 | D6: 13001 | E6: 2534555 | F6: 33382 | G6: INCIDENTE | H6: BOLIVAR | I6: CARTAGENA | J6: PAGAFACIL BAZURTO | K6: REDEBAN | L6: FO-25-1313041 | M6: 45869.624 | N6: 45870.431 | O6: NO | P6: SOFTWARE | Q6: FLASH FULL | R6: ACTUALIZACION VERSION | S6: ROBUSTO | U6: CERRADO | V6: 01/08/2025 EN SITIO ESPERANDO AUTORIZACIÓN DE INGRESO | 01/08/2025 SE CAMBIA EQUIPO POR PROBLEMAS DE IMPRESORA SE CAMBIA PIN PAD POR TECNOLOGÍA | W6: VISITA_TÉCNICA | X6: 18ZZZ921 | Y6: TIPO I | Z6: TERRESTRE | AA6: MARTINEZ SALGUEDO ANDRES AUGUSTO | AB6: 1 | AC6: 0 | AD6: =IF(W6="SOPORTE_TELEFÓNICO",'BASE LIQUIDACION REDEBAN 2025'!$B$19,IF(W6="ENVÍO",'BASE LIQUIDACION REDEBAN 2025'!$C$2,IF(Y6="TIPO I",'BASE LIQUIDACION REDEBAN 2025'!$C$2,IF(Y6="TIPO II",'BASE LIQUIDACION REDEBAN 2025'!$C$3,IF(Y6="TIPO III",'BASE LIQUIDACION REDEBAN 2025'!$C$4,IF(Y6="TIPO IV",'BASE LIQUIDACION REDEBAN 2025'!$C$5,IF(Z6="AEREO",'BASE LIQUIDACION REDEBAN 2025'!$B$6,'BASE LIQUIDACION REDEBAN 2025'!$C$5))))))) -> 65960.072 | AE6: =IF(OR(W6="SOPORTE_TELEFÓNICO",W6="ENVÍO"),0,IF(Y6="TIPO I",'BASE LIQUIDACION REDEBAN 2025'!$B$10,IF(Y6="TIPO II",'BASE LIQUIDACION REDEBAN 2025'!$B$11,IF(Y6="TIPO III",'BASE LIQUIDACION REDEBAN 2025'!$B$12,'BASE LIQUIDACION REDEBAN 2025'!$B$13)))) -> 75096.394 | AF6: =IF(OR(W6="SOPORTE_TELEFÓNICO",W6="ENVÍO"),AD6,(AD6*AB6+AE6*AC6)) -> 65960.072
A7: VILLAVICENCIO | B7: =VLOOKUP(A7,'CENTRO DE COSTOS'!A:D,4,FALSE) -> KEVIN ALEXIS CORZO BUSTOS | C7: =VLOOKUP(A7,'CENTRO DE COSTOS'!A:D,2,FALSE) -> 0004-0007 | D7: 50568 | E7: 2525574 | F7: 58542 | G7: INCIDENTE | H7: META | I7: PUERTO GAITAN | J7: BARRIO CENTRO PUERTO GAITAN 9 | K7: REDEBAN | L7: FO-25-1304845 | M7: 45868.416 | N7: 45870.44 | O7: NO | P7: HARDWARE | Q7: NO ENCIENDE | R7: DAÑO POS | S7: CB UNO A UNO | U7: CERRADO | V7: 30/07/2025 30-07 EN COMUNICACION CON LA SEÑORA ANGIE ALVARADO AL NUMERO 3187565278, CONFIRMA FALLA, DATOS CORRECTOS. SE ESCALA PARA VISITA | 01/08/2025 SE REALIZA CAMBIO DE EQUIPO PRUEBAS OK SIN NOVEDADES | W7: VISITA_TÉCNICA | X7: TYZZZ661 | Y7: TIPO III | Z7: TERRESTRE | AA7: CASTRILLON URREA LONDIER LEANDRO | AB7: 1 | AC7: 0 | AD7: =IF(W7="SOPORTE_TELEFÓNICO",'BASE LIQUIDACION REDEBAN 2025'!$B$19,IF(W7="ENVÍO",'BASE LIQUIDACION REDEBAN 2025'!$C$2,IF(Y7="TIPO I",'BASE LIQUIDACION REDEBAN 2025'!$C$2,IF(Y7="TIPO II",'BASE LIQUIDACION REDEBAN 2025'!$C$3,IF(Y7="TIPO III",'BASE LIQUIDACION REDEBAN 2025'!$C$4,IF(Y7="TIPO IV",'BASE LIQUIDACION REDEBAN 2025'!$C$5,IF(Z7="AEREO",'BASE LIQUIDACION REDEBAN 2025'!$B$6,'BASE LIQUIDACION REDEBAN 2025'!$C$5))))))) -> 275728.78 | AE7: =IF(OR(W7="SOPORTE_TELEFÓNICO",W7="ENVÍO"),0,IF(Y7="TIPO I",'BASE LIQUIDACION REDEBAN 2025'!$B$10,IF(Y7="TIPO II",'BASE LIQUIDACION REDEBAN 2025'!$B$11,IF(Y7="TIPO III",'BASE LIQUIDACION REDEBAN 2025'!$B$12,'BASE LIQUIDACION REDEBAN 2025'!$B$13)))) -> 196536.53 | AF7: =IF(OR(W7="SOPORTE_TELEFÓNICO",W7="ENVÍO"),AD7,(AD7*AB7+AE7*AC7)) -> 275728.78
A8: BUCARAMANGA | B8: =VLOOKUP(A8,'CENTRO DE COSTOS'!A:D,4,FALSE) -> MIGUEL JULIÁN HERNÁNDEZ GUARÍN | C8: =VLOOKUP(A8,'CENTRO DE COSTOS'!A:D,2,FALSE) -> 0004-0008 | D8: 68615 | E8: 2530689 | F8: 69616 | G8: INCIDENTE | H8: SANTANDER | I8: RIONEGRO | J8: BARRIO UNIDO RIONEGRO | K8: REDEBAN | L8: FO-25-1309852 | M8: 45869.333 | N8: 45870.449 | O8: NO | P8: HARDWARE | Q8: LECTOR DE BARRAS | R8: FORMATO INVALIDO LECTOR DAÑADO | S8: CB UNO A UNO | U8: CERRADO | V8: 31/07/2025 31-07 SE ESCALA PARA VISITA. LLAMAR ANTES DE VISITAR, CONFIRMAR FALLA Y DATOS | 01/08/2025 SE REALIZA VISITA AL COMERCIO CB, SE VALIDA Y SE ENCUENTRA LECTOR DE BARRAS EN DAÑO SE REINICIA CONSTANTEMENTE, SE PROCEDE A HACER CAMBIO SE HACEN PRUEBAS DEJANDO TODO OK | W8: VISITA_TÉCNICA | X8: EG004608 | Y8: TIPO II | Z8: TERRESTRE | AA8: GONZALEZ ESTUPIÑAN YEISON WALTER ANTONIO | AB8: 1 | AC8: 0 | AD8: =IF(W8="SOPORTE_TELEFÓNICO",'BASE LIQUIDACION REDEBAN 2025'!$B$19,IF(W8="ENVÍO",'BASE LIQUIDACION REDEBAN 2025'!$C$2,IF(Y8="TIPO I",'BASE LIQUIDACION REDEBAN 2025'!$C$2,IF(Y8="TIPO II",'BASE LIQUIDACION REDEBAN 2025'!$C$3,IF(Y8="TIPO III",'BASE LIQUIDACION REDEBAN 2025'!$C$4,IF(Y8="TIPO IV",'BASE LIQUIDACION REDEBAN 2025'!$C$5,IF(Z8="AEREO",'BASE LIQUIDACION REDEBAN 2025'!$B$6,'BASE LIQUIDACION REDEBAN 2025'!$C$5))))))) -> 144967.87 | AE8: =IF(OR(W8="SOPORTE_TELEFÓNICO",W8="ENVÍO"),0,IF(Y8="TIPO I",'BASE LIQUIDACION REDEBAN 2025'!$B$10,IF(Y8="TIPO II",'BASE LIQUIDACION REDEBAN 2025'!$B$11,IF(Y8="TIPO III",'BASE LIQUIDACION REDEBAN 2025'!$B$12,'BASE LIQUIDACION REDEBAN 2025'!$B$13)))) -> 140395.63 | AF8: =IF(OR(W8="SOPORTE_TELEFÓNICO",W8="ENVÍO"),AD8,(AD8*AB8+AE8*AC8)) -> 144967.87
A9: VALLEDUPAR | B9: =VLOOKUP(A9,'CENTRO DE COSTOS'!A:D,4,FALSE) -> JOSE MAURICIO HERNANDEZ ROJAS | C9: =VLOOKUP(A9,'CENTRO DE COSTOS'!A:D,2,FALSE) -> 0004-0001 | D9: 20001 | E9: 2534424 | F9: 65049 | G9: INCIDENTE | H9: CESAR | I9: VALLEDUPAR | J9: BARRIO BELLA VISTA VALLEDUPAR | K9: REDEBAN | L9: FO-25-1312961 | M9: 45869.603 | N9: 45870.455 | O9: NO | P9: HARDWARE | Q9: CABLEADO | R9: DAÑO POS | S9: CB UNO A UNO | U9: CERRADO | V9: 31/07/2025 31-07 SE ESCALA PARA VISITA. LLAMAR ANTES DE VISITAR, CONFIRMAR FALLA Y DATOS | 01/08/2025 BUENOS DIAS SE HACE VISITA AL CB Y SE EVIDENCIA QUE EL CABLE DEL LECTOR ESTÁ AVERIADO POR QUE SE CAMBIA Y TAMBIÉN EL CABLE DEL PINPAD TIENE EL CONECTOR FLOJO, SE PROCEDE A HACER EL CAMBIO | W9: VISITA_TÉCNICA | X9: 6Z005717 | Y9: TIPO I | Z9: TERRESTRE | AA9: BENITEZ CARVAJAL ALVARO JAVIER | AB9: 1 | AC9: 0 | AD9: =IF(W9="SOPORTE_TELEFÓNICO",'BASE LIQUIDACION REDEBAN 2025'!$B$19,IF(W9="ENVÍO",'BASE LIQUIDACION REDEBAN 2025'!$C$2,IF(Y9="TIPO I",'BASE LIQUIDACION REDEBAN 2025'!$C$2,IF(Y9="TIPO II",'BASE LIQUIDACION REDEBAN 2025'!$C$3,IF(Y9="TIPO III",'BASE LIQUIDACION REDEBAN 2025'!$C$4,IF(Y9="TIPO IV",'BASE LIQUIDACION REDEBAN 2025'!$C$5,IF(Z9="AEREO",'BASE LIQUIDACION REDEBAN 2025'!$B$6,'BASE LIQUIDACION REDEBAN 2025'!$C$5))))))) -> 65960.072 | AE9: =IF(OR(W9="SOPORTE_TELEFÓNICO",W9="ENVÍO"),0,IF(Y9="TIPO I",'BASE LIQUIDACION REDEBAN 2025'!$B$10,IF(Y9="TIPO II",'BASE LIQUIDACION REDEBAN 2025'!$B$11,IF(Y9="TIPO III",'BASE LIQUIDACION REDEBAN 2025'!$B$12,'BASE LIQUIDACION REDEBAN 2025'!$B$13)))) -> 75096.394 | AF9: =IF(OR(W9="SOPORTE_TELEFÓNICO",W9="ENVÍO"),AD9,(AD9*AB9+AE9*AC9)) -> 65960.072
A10: VALLEDUPAR | B10: =VLOOKUP(A10,'CENTRO DE COSTOS'!A:D,4,FALSE) -> JOSE MAURICIO HERNANDEZ ROJAS | C10: =VLOOKUP(A10,'CENTRO DE COSTOS'!A:D,2,FALSE) -> 0004-0001 | D10: 20383 | E10: 2528990 | F10: 11416 | G10: INCIDENTE | H10: CESAR | I10: LA GLORIA | J10: LA GLORIA CESAR | K10: REDEBAN | L10: FO-25-1307791 | M10: 45868.663 | N10: 45870.462 | O10: NO | P10: HARDWARE | Q10: LECTOR DE BARRAS | R10: DAÑO POS | S10: CB UNO A UNO | U10: CERRADO | V10: 30/07/2025 30-07 EN COMUNICACION CON EL SEÑOR GUSTAVO PINO AL NUMERO 3175576521, CONFIRMA FALLA, DATOS CORRECTOS. SE ESCALA PARA VISITA | 01/08/2025 SE REALIZA VISITA POR SOLICITUD DE CLIENTE, SE LLEGA A SITIO SE VALIDA LECTOR DE BARRAS LA CUAL NO LLE LAS FACTURAS, SE REALIZA CAMBIÓ DE LECTOR QUEDANDO SERVICIO OPERÁTIVO AL 100% | W10: VISITA_TÉCNICA | X10: A00FZ861 | Y10: TIPO IV | Z10: TERRESTRE | AA10: MAESTRE MENGUAL EDGAR ENRIQUE | AB10: 1 | AC10: 0 | AD10: =IF(W10="SOPORTE_TELEFÓNICO",'BASE LIQUIDACION REDEBAN 2025'!$B$19,IF(W10="ENVÍO",'BASE LIQUIDACION REDEBAN 2025'!$C$2,IF(Y10="TIPO I",'BASE LIQUIDACION REDEBAN 2025'!$C$2,IF(Y10="TIPO II",'BASE LIQUIDACION REDEBAN 2025'!$C$3,IF(Y10="TIPO III",'BASE LIQUIDACION REDEBAN 2025'!$C$4,IF(Y10="TIPO IV",'BASE LIQUIDACION REDEBAN 2025'!$C$5,IF(Z10="AEREO",'BASE LIQUIDACION REDEBAN 2025'!$B$6,'BASE LIQUIDACION REDEBAN 2025'!$C$5))))))) -> 479588.88 | AE10: =IF(OR(W10="SOPORTE_TELEFÓNICO",W10="ENVÍO"),0,IF(Y10="TIPO I",'BASE LIQUIDACION REDEBAN 2025'!$B$10,IF(Y10="TIPO II",'BASE LIQUIDACION REDEBAN 2025'!$B$11,IF(Y10="TIPO III",'BASE LIQUIDACION REDEBAN 2025'!$B$12,'BASE LIQUIDACION REDEBAN 2025'!$B$13)))) -> 196536.53 | AF10: =IF(OR(W10="SOPORTE_TELEFÓNICO",W10="ENVÍO"),AD10,(AD10*AB10+AE10*AC10)) -> 479588.88
A11: CUCUTA | B11: =VLOOKUP(A11,'CENTRO DE COSTOS'!A:D,4,FALSE) -> MIGUEL JULIÁN HERNÁNDEZ GUARÍN | C11: =VLOOKUP(A11,'CENTRO DE COSTOS'!A:D,2,FALSE) -> 0004-0008 | D11: 54720 | E11: 2531280 | F11: 39109 | G11: INCIDENTE | H11: NORTE DE SANTANDER | I11: SARDINATA | J11: BARRIO SAN FRANCISCO SARDINATA | K11: REDEBAN | L11: FO-25-1310134 | M11: 45869.383 | N11: 45870.465 | O11: NO | P11: HARDWARE | Q11: PANTALLA | R11: DAÑO POS | S11: CB UNO A UNO | U11: CERRADO | V11: 31/07/2025 31-07 SE ESCALA PARA VISITA. LLAMAR ANTES DE VISITAR, CONFIRMAR FALLA Y DATOS | 01/08/2025 SE CAMBIO DATAFONO POR DAÑO EN LA PANTALLA SE INSTALA NUEVA VERSIÓN CIERRES Y PRUEBAS OK | W11: VISITA_TÉCNICA | X11: AA07Z118 | Y11: TIPO II | Z11: TERRESTRE | AA11: DURAN ACOSTA FRANK YONNY | AB11: 1 | AC11: 0 | AD11: =IF(W11="SOPORTE_TELEFÓNICO",'BASE LIQUIDACION REDEBAN 2025'!$B$19,IF(W11="ENVÍO",'BASE LIQUIDACION REDEBAN 2025'!$C$2,IF(Y11="TIPO I",'BASE LIQUIDACION REDEBAN 2025'!$C$2,IF(Y11="TIPO II",'BASE LIQUIDACION REDEBAN 2025'!$C$3,IF(Y11="TIPO III",'BASE LIQUIDACION REDEBAN 2025'!$C$4,IF(Y11="TIPO IV",'BASE LIQUIDACION REDEBAN 2025'!$C$5,IF(Z11="AEREO",'BASE LIQUIDACION REDEBAN 2025'!$B$6,'BASE LIQUIDACION REDEBAN 2025'!$C$5))))))) -> 144967.87 | AE11: =IF(OR(W11="SOPORTE_TELEFÓNICO",W11="ENVÍO"),0,IF(Y11="TIPO I",'BASE LIQUIDACION REDEBAN 2025'!$B$10,IF(Y11="TIPO II",'BASE LIQUIDACION REDEBAN 2025'!$B$11,IF(Y11="TIPO III",'BASE LIQUIDACION REDEBAN 2025'!$B$12,'BASE LIQUIDACION REDEBAN 2025'!$B$13)))) -> 140395.63 | AF11: =IF(OR(W11="SOPORTE_TELEFÓNICO",W11="ENVÍO"),AD11,(AD11*AB11+AE11*AC11)) -> 144967.87
A12: VALLEDUPAR | B12: =VLOOKUP(A12,'CENTRO DE COSTOS'!A:D,4,FALSE) -> JOSE MAURICIO HERNANDEZ ROJAS | C12: =VLOOKUP(A12,'CENTRO DE COSTOS'!A:D,2,FALSE) -> 0004-0001 | D12: 20001 | E12: 2534486 | F12: 60632 | G12: INCIDENTE | H12: CESAR | I12: VALLEDUPAR | J12: DISTRICOL VARIEDADES LA NENAYD | K12: REDEBAN | L12: FO-25-1312955 | M12: 45869.618 | N12: 45870.474 | O12: NO | P12: HARDWARE | Q12: CABLEADO | R12: DAÑO POS | S12: AGREGADOR | U12: CERRADO | V12: 31/07/2025 31-07 SE ESCALA PARA VISITA. LLAMAR ANTES DE VISITAR, CONFIRMAR FALLA Y DATOS | 01/08/2025 BUENOS DÍAS SE VISITA CB Y SE ENCUENTRA CABLE DEL LECTOR AVERIADO SE HACE CAMBIO DE ACCESORIO Y SE HACEN PRUEBAS | W12: VISITA_TÉCNICA | X12: MA00C921 | Y12: TIPO I | Z12: TERRESTRE | AA12: BENITEZ CARVAJAL ALVARO JAVIER | AB12: 1 | AC12: 0 | AD12: =IF(W12="SOPORTE_TELEFÓNICO",'BASE LIQUIDACION REDEBAN 2025'!$B$19,IF(W12="ENVÍO",'BASE LIQUIDACION REDEBAN 2025'!$C$2,IF(Y12="TIPO I",'BASE LIQUIDACION REDEBAN 2025'!$C$2,IF(Y12="TIPO II",'BASE LIQUIDACION REDEBAN 2025'!$C$3,IF(Y12="TIPO III",'BASE LIQUIDACION REDEBAN 2025'!$C$4,IF(Y12="TIPO IV",'BASE LIQUIDACION REDEBAN 2025'!$C$5,IF(Z12="AEREO",'BASE LIQUIDACION REDEBAN 2025'!$B$6,'BASE LIQUIDACION REDEBAN 2025'!$C$5))))))) -> 65960.072 | AE12: =IF(OR(W12="SOPORTE_TELEFÓNICO",W12="ENVÍO"),0,IF(Y12="TIPO I",'BASE LIQUIDACION REDEBAN 2025'!$B$10,IF(Y12="TIPO II",'BASE LIQUIDACION REDEBAN 2025'!$B$11,IF(Y12="TIPO III",'BASE LIQUIDACION REDEBAN 2025'!$B$12,'BASE LIQUIDACION REDEBAN 2025'!$B$13)))) -> 75096.394 | AF12: =IF(OR(W12="SOPORTE_TELEFÓNICO",W12="ENVÍO"),AD12,(AD12*AB12+AE12*AC12)) -> 65960.072
A13: MEDELLIN | B13: =VLOOKUP(A13,'CENTRO DE COSTOS'!A:D,4,FALSE) -> JUAN SEBASTIÁN RÍOS CASTRILLÓN | C13: =VLOOKUP(A13,'CENTRO DE COSTOS'!A:D,2,FALSE) -> 0004-0005 | D13: 5264 | E13: 2535903 | F13: 62252 | G13: INCIDENTE | H13: ANTIOQUIA | I13: ENTRERRIOS | J13: BARRIO LA TERMINAL ENTRERRIOS | K13: REDEBAN | L13: FO-25-1313778 | M13: 45869.701 | N13: 45870.486 | O13: NO | P13: HARDWARE | Q13: LECTOR DE BARRAS | R13: CABLE LECTORA AVERIADO | S13: CB UNO A UNO | U13: CERRADO | V13: 31/07/2025 31-07 SE ESCALA PARA VISITA. LLAMAR ANTES DE VISITAR, CONFIRMAR FALLA Y DATOS | 01/08/2025 SE CAMBIA CABLE DE LECTOR DE BARRAS | W13: VISITA_TÉCNICA | X13: NA00K026 | Y13: TIPO II | Z13: TERRESTRE | AA13: CASTAÑEDA PALACIO CARLOS FELIPE | AB13: 1 | AC13: 0 | AD13: =IF(W13="SOPORTE_TELEFÓNICO",'BASE LIQUIDACION REDEBAN 2025'!$B$19,IF(W13="ENVÍO",'BASE LIQUIDACION REDEBAN 2025'!$C$2,IF(Y13="TIPO I",'BASE LIQUIDACION REDEBAN 2025'!$C$2,IF(Y13="TIPO II",'BASE LIQUIDACION REDEBAN 2025'!$C$3,IF(Y13="TIPO III",'BASE LIQUIDACION REDEBAN 2025'!$C$4,IF(Y13="TIPO IV",'BASE LIQUIDACION REDEBAN 2025'!$C$5,IF(Z13="AEREO",'BASE LIQUIDACION REDEBAN 2025'!$B$6,'BASE LIQUIDACION REDEBAN 2025'!$C$5))))))) -> 144967.87 | AE13: =IF(OR(W13="SOPORTE_TELEFÓNICO",W13="ENVÍO"),0,IF(Y13="TIPO I",'BASE LIQUIDACION REDEBAN 2025'!$B$10,IF(Y13="TIPO II",'BASE LIQUIDACION REDEBAN 2025'!$B$11,IF(Y13="TIPO III",'BASE LIQUIDACION REDEBAN 2025'!$B$12,'BASE LIQUIDACION REDEBAN 2025'!$B$13)))) -> 140395.63 | AF13: =IF(OR(W13="SOPORTE_TELEFÓNICO",W13="ENVÍO"),AD13,(AD13*AB13+AE13*AC13)) -> 144967.87
... A51: MEDELLIN | B51: =VLOOKUP(A51,'CENTRO DE COSTOS'!A:D,4,FALSE) -> JUAN SEBASTIÁN RÍOS CASTRILLÓN | C51: =VLOOKUP(A51,'CENTRO DE COSTOS'!A:D,2,FALSE) -> 0004-0005 | D51: 5001 | E51: 2540141 | F51: 17698 | G51: INCIDENTE | H51: ANTIOQUIA | I51: MEDELLIN | J51: BARRIO CAMPO VALDES X MEDELLIN | K51: REDEBAN | L51: FO-25-1316886 | M51: 45870.51 | N51: 45870.69 | O51: NO | P51: HARDWARE | Q51: COMUNICACION | R51: DAÑO POS | S51: CB UNO A UNO | U51: CERRADO | V51: 01/08/2025 01-08 SE ESCALA PARA VISITA. LLAMAR ANTES DE VISITAR, CONFIRMAR FALLA Y DATOS | 01/08/2025 SE VISITA COMERCIO PERO LA EQUIPOS ESTÁN BLOQUEADOS, SE LLAMA AL BANCO Y CORROBORAN ESTA INFORMACIÓN, ESTÁN UTILIZANDO UN EQUIPO TÁCTIL | W51: VISITA_TÉCNICA | X51: KA00H930-LN3ZZ001 | Y51: TIPO I | Z51: TERRESTRE | AA51: RUA ALVAREZ RICHARD ANDRES | AB51: 1 | AC51: 0 | AD51: =IF(W51="SOPORTE_TELEFÓNICO",'BASE LIQUIDACION REDEBAN 2025'!$B$19,IF(W51="ENVÍO",'BASE LIQUIDACION REDEBAN 2025'!$C$2,IF(Y51="TIPO I",'BASE LIQUIDACION REDEBAN 2025'!$C$2,IF(Y51="TIPO II",'BASE LIQUIDACION REDEBAN 2025'!$C$3,IF(Y51="TIPO III",'BASE LIQUIDACION REDEBAN 2025'!$C$4,IF(Y51="TIPO IV",'BASE LIQUIDACION REDEBAN 2025'!$C$5,IF(Z51="AEREO",'BASE LIQUIDACION REDEBAN 2025'!$B$6,'BASE LIQUIDACION REDEBAN 2025'!$C$5))))))) -> 65960.072 | AE51: =IF(OR(W51="SOPORTE_TELEFÓNICO",W51="ENVÍO"),0,IF(Y51="TIPO I",'BASE LIQUIDACION REDEBAN 2025'!$B$10,IF(Y51="TIPO II",'BASE LIQUIDACION REDEBAN 2025'!$B$11,IF(Y51="TIPO III",'BASE LIQUIDACION REDEBAN 2025'!$B$12,'BASE LIQUIDACION REDEBAN 2025'!$B$13)))) -> 75096.394 | AF51: =IF(OR(W51="SOPORTE_TELEFÓNICO",W51="ENVÍO"),AD51,(AD51*AB51+AE51*AC51)) -> 65960.072
A52: MEDELLIN | B52: =VLOOKUP(A52,'CENTRO DE COSTOS'!A:D,4,FALSE) -> JUAN SEBASTIÁN RÍOS CASTRILLÓN | C52: =VLOOKUP(A52,'CENTRO DE COSTOS'!A:D,2,FALSE) -> 0004-0005 | D52: 5001 | E52: 2539026 | F52: 56991 | G52: INCIDENTE | H52: ANTIOQUIA | I52: MEDELLIN | J52: DISTRICOL MERCADOS PARQUEADERO | K52: REDEBAN | L52: FO-25-1315870 | M52: 45870.44 | N52: 45870.696 | O52: NO | P52: HARDWARE | Q52: SE REINICIA | R52: DAÑO POS | S52: AGREGADOR | U52: CERRADO | V52: 01/08/2025 01-08 SE ESCALA PARA VISITA. LLAMAR ANTES DE VISITAR, CONFIRMAR FALLA Y DATOS | 01/08/2025 SE LLAMA AL NÚMERO INDICADO Y LA SEÑORA WENDY INDICA QUE EL DATAFONO YA SE ENCUENTRA FUNCIONANDO CON NORMALIDAD | W52: SOPORTE_TELEFÓNICO | X52: 0 | Y52: TIPO I | Z52: TERRESTRE | AA52: RUA ALVAREZ RICHARD ANDRES | AB52: 0 | AC52: 0 | AD52: =IF(W52="SOPORTE_TELEFÓNICO",'BASE LIQUIDACION REDEBAN 2025'!$B$19,IF(W52="ENVÍO",'BASE LIQUIDACION REDEBAN 2025'!$C$2,IF(Y52="TIPO I",'BASE LIQUIDACION REDEBAN 2025'!$C$2,IF(Y52="TIPO II",'BASE LIQUIDACION REDEBAN 2025'!$C$3,IF(Y52="TIPO III",'BASE LIQUIDACION REDEBAN 2025'!$C$4,IF(Y52="TIPO IV",'BASE LIQUIDACION REDEBAN 2025'!$C$5,IF(Z52="AEREO",'BASE LIQUIDACION REDEBAN 2025'!$B$6,'BASE LIQUIDACION REDEBAN 2025'!$C$5))))))) -> 41241.08 | AE52: =IF(OR(W52="SOPORTE_TELEFÓNICO",W52="ENVÍO"),0,IF(Y52="TIPO I",'BASE LIQUIDACION REDEBAN 2025'!$B$10,IF(Y52="TIPO II",'BASE LIQUIDACION REDEBAN 2025'!$B$11,IF(Y52="TIPO III",'BASE LIQUIDACION REDEBAN 2025'!$B$12,'BASE LIQUIDACION REDEBAN 2025'!$B$13)))) -> 0 | AF52: =IF(OR(W52="SOPORTE_TELEFÓNICO",W52="ENVÍO"),AD52,(AD52*AB52+AE52*AC52)) -> 41241.08
A53: BUCARAMANGA | B53: =VLOOKUP(A53,'CENTRO DE COSTOS'!A:D,4,FALSE) -> MIGUEL JULIÁN HERNÁNDEZ GUARÍN | C53: =VLOOKUP(A53,'CENTRO DE COSTOS'!A:D,2,FALSE) -> 0004-0008 | D53: 68001 | E53: 2539184 | F53: 70595 | G53: INCIDENTE | H53: SANTANDER | I53: BUCARAMANGA | J53: MULTIPAGAS SAN ANDRESITO CENTR | K53: REDEBAN | L53: FO-25-1316293 | M53: 45870.458 | N53: 45870.709 | O53: NO | P53: HARDWARE | Q53: LECTOR DE BARRAS | R53: DAÑO POS | S53: ROBUSTO | U53: CERRADO | V53: 01/08/2025 01-08 SE ESCALA PARA VISITA. LLAMAR ANTES DE VISITAR, CONFIRMAR FALLA Y DATOS | 01/08/2025 SE REALIZA CAMBIO DE LECTOR DE BARRAS POR DAÑO, NO LEE FACTURAS, PRUEBAS Y LIMPIEZA DE EQUIPOS OK. | W53: VISITA_TÉCNICA | X53: UV006350 | Y53: TIPO I | Z53: TERRESTRE | AA53: MARTINEZ FLOREZ DONIS ALBERTO | AB53: 1 | AC53: 0 | AD53: =IF(W53="SOPORTE_TELEFÓNICO",'BASE LIQUIDACION REDEBAN 2025'!$B$19,IF(W53="ENVÍO",'BASE LIQUIDACION REDEBAN 2025'!$C$2,IF(Y53="TIPO I",'BASE LIQUIDACION REDEBAN 2025'!$C$2,IF(Y53="TIPO II",'BASE LIQUIDACION REDEBAN 2025'!$C$3,IF(Y53="TIPO III",'BASE LIQUIDACION REDEBAN 2025'!$C$4,IF(Y53="TIPO IV",'BASE LIQUIDACION REDEBAN 2025'!$C$5,IF(Z53="AEREO",'BASE LIQUIDACION REDEBAN 2025'!$B$6,'BASE LIQUIDACION REDEBAN 2025'!$C$5))))))) -> 65960.072 | AE53: =IF(OR(W53="SOPORTE_TELEFÓNICO",W53="ENVÍO"),0,IF(Y53="TIPO I",'BASE LIQUIDACION REDEBAN 2025'!$B$10,IF(Y53="TIPO II",'BASE LIQUIDACION REDEBAN 2025'!$B$11,IF(Y53="TIPO III",'BASE LIQUIDACION REDEBAN 2025'!$B$12,'BASE LIQUIDACION REDEBAN 2025'!$B$13)))) -> 75096.394 | AF53: =IF(OR(W53="SOPORTE_TELEFÓNICO",W53="ENVÍO"),AD53,(AD53*AB53+AE53*AC53)) -> 65960.072
A54: PEREIRA | B54: =VLOOKUP(A54,'CENTRO DE COSTOS'!A:D,4,FALSE) -> DIEGO FERNANDO HENAO CARDONA | C54: =VLOOKUP(A54,'CENTRO DE COSTOS'!A:D,2,FALSE) -> 0004-0002 | D54: 63130 | E54: 2540347 | F54: 73122 | G54: INCIDENTE | H54: QUINDIO | I54: CALARCA | J54: DISTRICOL LA BODEGA DE ALEJO | K54: REDEBAN | L54: FO-25-1317120 | M54: 45870.546 | N54: 45870.713 | O54: NO | P54: HARDWARE | Q54: LECTOR DE TARJETAS | R54: DAÑO POS | S54: AGREGADOR | U54: CERRADO | V54: 01/08/2025 01-08 SE ESCALA PARA VISITA. LLAMAR ANTES DE VISITAR, CONFIRMAR FALLA Y DATOS | 01/08/2025 SE VISITA COMERCIO SE REALIZÓ CAMBIO DE DATAFONO POR DAÑO EN LECTOR TARJETAS | W54: VISITA_TÉCNICA | X54: NN00P179 | Y54: TIPO II | Z54: TERRESTRE | AA54: SANCHEZ SOLORZANO JUAN SEBASTIAN | AB54: 1 | AC54: 0 | AD54: =IF(W54="SOPORTE_TELEFÓNICO",'BASE LIQUIDACION REDEBAN 2025'!$B$19,IF(W54="ENVÍO",'BASE LIQUIDACION REDEBAN 2025'!$C$2,IF(Y54="TIPO I",'BASE LIQUIDACION REDEBAN 2025'!$C$2,IF(Y54="TIPO II",'BASE LIQUIDACION REDEBAN 2025'!$C$3,IF(Y54="TIPO III",'BASE LIQUIDACION REDEBAN 2025'!$C$4,IF(Y54="TIPO IV",'BASE LIQUIDACION REDEBAN 2025'!$C$5,IF(Z54="AEREO",'BASE LIQUIDACION REDEBAN 2025'!$B$6,'BASE LIQUIDACION REDEBAN 2025'!$C$5))))))) -> 144967.87 | AE54: =IF(OR(W54="SOPORTE_TELEFÓNICO",W54="ENVÍO"),0,IF(Y54="TIPO I",'BASE LIQUIDACION REDEBAN 2025'!$B$10,IF(Y54="TIPO II",'BASE LIQUIDACION REDEBAN 2025'!$B$11,IF(Y54="TIPO III",'BASE LIQUIDACION REDEBAN 2025'!$B$12,'BASE LIQUIDACION REDEBAN 2025'!$B$13)))) -> 140395.63 | AF54: =IF(OR(W54="SOPORTE_TELEFÓNICO",W54="ENVÍO"),AD54,(AD54*AB54+AE54*AC54)) -> 144967.87
A55: MONTERIA | B55: =VLOOKUP(A55,'CENTRO DE COSTOS'!A:D,4,FALSE) -> JOSE MAURICIO HERNANDEZ ROJAS | C55: =VLOOKUP(A55,'CENTRO DE COSTOS'!A:D,2,FALSE) -> 0004-0001 | D55: 23001 | E55: 2536213 | F55: 75532 | G55: INCIDENTE | H55: CORDOBA | I55: MONTERIA | J55: PTM MONTERIA PAPELERIA +X- | K55: REDEBAN | L55: FO-25-1314605 | M55: 45870.333 | N55: 45870.729 | O55: NO | P55: HARDWARE | Q55: TECLADO | R55: DAÑO POS | S55: AGREGADOR | U55: CERRADO | V55: 01/08/2025 01-08 SE ESCALA PARA VISITA. LLAMAR ANTES DE VISITAR, CONFIRMAR FALLA Y DATOS | 01/08/2025 SE REALIZA CAMBIO DE EQUIPO POR DAÑO EN EL TECLADO, TECLAS BORROSAS, ADICIONAL SE REINICIA CONSTANTEMENTE, SE PROCEDE A INSTALAR NUEVO EQUIPO OPERATIVO SIN NOVEDAD, PRUEBAS EXITOSAS, CLIENTE CB VALIDA SALDO ANTES Y DESPUÉS DEL CAMBIO OK. CB SE DEJA OPERATIVO OK | W55: VISITA_TÉCNICA | X55: SX00J151 ; SX00J089 | Y55: TIPO I | Z55: TERRESTRE | AA55: GONZALEZ FERRER JESUS ALEXANDER | AB55: 1 | AC55: 0 | AD55: =IF(W55="SOPORTE_TELEFÓNICO",'BASE LIQUIDACION REDEBAN 2025'!$B$19,IF(W55="ENVÍO",'BASE LIQUIDACION REDEBAN 2025'!$C$2,IF(Y55="TIPO I",'BASE LIQUIDACION REDEBAN 2025'!$C$2,IF(Y55="TIPO II",'BASE LIQUIDACION REDEBAN 2025'!$C$3,IF(Y55="TIPO III",'BASE LIQUIDACION REDEBAN 2025'!$C$4,IF(Y55="TIPO IV",'BASE LIQUIDACION REDEBAN 2025'!$C$5,IF(Z55="AEREO",'BASE LIQUIDACION REDEBAN 2025'!$B$6,'BASE LIQUIDACION REDEBAN 2025'!$C$5))))))) -> 65960.072 | AE55: =IF(OR(W55="SOPORTE_TELEFÓNICO",W55="ENVÍO"),0,IF(Y55="TIPO I",'BASE LIQUIDACION REDEBAN 2025'!$B$10,IF(Y55="TIPO II",'BASE LIQUIDACION REDEBAN 2025'!$B$11,IF(Y55="TIPO III",'BASE LIQUIDACION REDEBAN 2025'!$B$12,'BASE LIQUIDACION REDEBAN 2025'!$B$13)))) -> 75096.394 | AF55: =IF(OR(W55="SOPORTE_TELEFÓNICO",W55="ENVÍO"),AD55,(AD55*AB55+AE55*AC55)) -> 65960.072
A56: MEDELLIN | B56: =VLOOKUP(A56,'CENTRO DE COSTOS'!A:D,4,FALSE) -> JUAN SEBASTIÁN RÍOS CASTRILLÓN | C56: =VLOOKUP(A56,'CENTRO DE COSTOS'!A:D,2,FALSE) -> 0004-0005 | D56: 5031 | E56: 2522545 | F56: 37862 | G56: INCIDENTE | H56: ANTIOQUIA | I56: AMALFI | J56: DISTRICOL DROGUERIA EMMANUEL | K56: REDEBAN | L56: FO-25-1301967 | M56: 45867.649 | N56: 45870.749 | O56: NO | P56: HARDWARE | Q56: TECLADO | R56: DAÑO POS | S56: AGREGADOR | U56: CERRADO | V56: 29/07/2025 29-07 SE INTENTA COMUNICACION CON LA SEÑORA GLADIS YARLEI OSPINA AL NUMERO 3217529300, PERO NO CONTESTA LA LLAMADA. SE ESCALA PARA VISITA, CONFIRMAR FALLA Y DATOS | 01/08/2025 SE CAMBIA EQUIPO POR TECLADO BORROSO. NOTA: HUBO DEMORAS EN LA ACTIVIDAD YA QUE SE HIZO CAMBIO DE EQUIPO Y SE CAYÓ EL INTERNET, ESTUVO INTERMITENTE TODA LA TARDE. | W56: VISITA_TÉCNICA | X56: GZ00R499 | Y56: TIPO IV | Z56: TERRESTRE | AA56: BADEL ACUÑA LUIS ALBERTO | AB56: 1 | AC56: 0 | AD56: =IF(W56="SOPORTE_TELEFÓNICO",'BASE LIQUIDACION REDEBAN 2025'!$B$19,IF(W56="ENVÍO",'BASE LIQUIDACION REDEBAN 2025'!$C$2,IF(Y56="TIPO I",'BASE LIQUIDACION REDEBAN 2025'!$C$2,IF(Y56="TIPO II",'BASE LIQUIDACION REDEBAN 2025'!$C$3,IF(Y56="TIPO III",'BASE LIQUIDACION REDEBAN 2025'!$C$4,IF(Y56="TIPO IV",'BASE LIQUIDACION REDEBAN 2025'!$C$5,IF(Z56="AEREO",'BASE LIQUIDACION REDEBAN 2025'!$B$6,'BASE LIQUIDACION REDEBAN 2025'!$C$5))))))) -> 479588.88 | AE56: =IF(OR(W56="SOPORTE_TELEFÓNICO",W56="ENVÍO"),0,IF(Y56="TIPO I",'BASE LIQUIDACION REDEBAN 2025'!$B$10,IF(Y56="TIPO II",'BASE LIQUIDACION REDEBAN 2025'!$B$11,IF(Y56="TIPO III",'BASE LIQUIDACION REDEBAN 2025'!$B$12,'BASE LIQUIDACION REDEBAN 2025'!$B$13)))) -> 196536.53 | AF56: =IF(OR(W56="SOPORTE_TELEFÓNICO",W56="ENVÍO"),AD56,(AD56*AB56+AE56*AC56)) -> 479588.88
A57: PEREIRA | B57: =VLOOKUP(A57,'CENTRO DE COSTOS'!A:D,4,FALSE) -> DIEGO FERNANDO HENAO CARDONA | C57: =VLOOKUP(A57,'CENTRO DE COSTOS'!A:D,2,FALSE) -> 0004-0002 | D57: 76147 | E57: 2539582 | F57: 42702 | G57: INCIDENTE | H57: VALLE DEL CAUCA | I57: CARTAGO | J57: MULTIPAGAS NUESTRO CARTAGO | K57: REDEBAN | L57: FO-25-1316570 | M57: 45870.475 | N57: 45870.756 | O57: NO | P57: HARDWARE | Q57: PINPAD | R57: ALERTADO | S57: ROBUSTO | U57: CERRADO | V57: 01/08/2025 01-08 SE ESCALA PARA VISITA. LLAMAR ANTES DE VISITAR, CONFIRMAR FALLA Y DATOS | 02/08/2025 SE CAMBIA EQUIPO (802914) YA QUE NO ES COMPATIBLE CON EL PIN PAD 1600, SE CAMBIA PIN PAD POR DAÑO ALERT INTERRUPTION, SE CAMBIA HUB DEL EQUIPO POR AVERÍA EN CABLE DE COMUNICACIÓN, SE REALIZAN PRUEBAS OK. | W57: VISITA_TÉCNICA | X57: GZ7ZZ167 | Y57: TIPO I | Z57: TERRESTRE | AA57: FRANCO CAÑAVERAL YAMID RAUL | AB57: 1 | AC57: 0 | AD57: =IF(W57="SOPORTE_TELEFÓNICO",'BASE LIQUIDACION REDEBAN 2025'!$B$19,IF(W57="ENVÍO",'BASE LIQUIDACION REDEBAN 2025'!$C$2,IF(Y57="TIPO I",'BASE LIQUIDACION REDEBAN 2025'!$C$2,IF(Y57="TIPO II",'BASE LIQUIDACION REDEBAN 2025'!$C$3,IF(Y57="TIPO III",'BASE LIQUIDACION REDEBAN 2025'!$C$4,IF(Y57="TIPO IV",'BASE LIQUIDACION REDEBAN 2025'!$C$5,IF(Z57="AEREO",'BASE LIQUIDACION REDEBAN 2025'!$B$6,'BASE LIQUIDACION REDEBAN 2025'!$C$5))))))) -> 65960.072 | AE57: =IF(OR(W57="SOPORTE_TELEFÓNICO",W57="ENVÍO"),0,IF(Y57="TIPO I",'BASE LIQUIDACION REDEBAN 2025'!$B$10,IF(Y57="TIPO II",'BASE LIQUIDACION REDEBAN 2025'!$B$11,IF(Y57="TIPO III",'BASE LIQUIDACION REDEBAN 2025'!$B$12,'BASE LIQUIDACION REDEBAN 2025'!$B$13)))) -> 75096.394 | AF57: =IF(OR(W57="SOPORTE_TELEFÓNICO",W57="ENVÍO"),AD57,(AD57*AB57+AE57*AC57)) -> 65960.072
A58: CARTAGENA | B58: =VLOOKUP(A58,'CENTRO DE COSTOS'!A:D,4,FALSE) -> JOSE MAURICIO HERNANDEZ ROJAS | C58: =VLOOKUP(A58,'CENTRO DE COSTOS'!A:D,2,FALSE) -> 0004-0001 | D58: 13001 | E58: 2536201 | F58: 17203 | G58: INCIDENTE | H58: BOLIVAR | I58: CARTAGENA | J58: BARRIO URBANIZACION HORIZONTE | K58: REDEBAN | L58: FO-25-1313935 | M58: 45870.333 | N58: 45870.765 | O58: NO | P58: HARDWARE | Q58: PANTALLA | R58: DAÑO POS | S58: CB UNO A UNO | U58: CERRADO | V58: 01/08/2025 SE CAMBIA DATAFONO POR ERROR WARRNING KEY SE DEJA UNO NUEVO TODO OK | W58: VISITA_TÉCNICA | X58: JKZZZ156 | Y58: TIPO I | Z58: TERRESTRE | AA58: MARTINEZ SALGUEDO ANDRES AUGUSTO | AB58: 1 | AC58: 0 | AD58: =IF(W58="SOPORTE_TELEFÓNICO",'BASE LIQUIDACION REDEBAN 2025'!$B$19,IF(W58="ENVÍO",'BASE LIQUIDACION REDEBAN 2025'!$C$2,IF(Y58="TIPO I",'BASE LIQUIDACION REDEBAN 2025'!$C$2,IF(Y58="TIPO II",'BASE LIQUIDACION REDEBAN 2025'!$C$3,IF(Y58="TIPO III",'BASE LIQUIDACION REDEBAN 2025'!$C$4,IF(Y58="TIPO IV",'BASE LIQUIDACION REDEBAN 2025'!$C$5,IF(Z58="AEREO",'BASE LIQUIDACION REDEBAN 2025'!$B$6,'BASE LIQUIDACION REDEBAN 2025'!$C$5))))))) -> 65960.072 | AE58: =IF(OR(W58="SOPORTE_TELEFÓNICO",W58="ENVÍO"),0,IF(Y58="TIPO I",'BASE LIQUIDACION REDEBAN 2025'!$B$10,IF(Y58="TIPO II",'BASE LIQUIDACION REDEBAN 2025'!$B$11,IF(Y58="TIPO III",'BASE LIQUIDACION REDEBAN 2025'!$B$12,'BASE LIQUIDACION REDEBAN 2025'!$B$13)))) -> 75096.394 | AF58: =IF(OR(W58="SOPORTE_TELEFÓNICO",W58="ENVÍO"),AD58,(AD58*AB58+AE58*AC58)) -> 65960.072
A59: CARTAGENA | B59: =VLOOKUP(A59,'CENTRO DE COSTOS'!A:D,4,FALSE) -> JOSE MAURICIO HERNANDEZ ROJAS | C59: =VLOOKUP(A59,'CENTRO DE COSTOS'!A:D,2,FALSE) -> 0004-0001 | D59: 13001 | E59: 2538591 | F59: 72090 | G59: INCIDENTE | H59: BOLIVAR | I59: CARTAGENA | J59: CARTAGENA DE INDIAS CORREGIMEN | K59: REDEBAN | L59: FO-25-1315875 | M59: 45870.432 | N59: 45871.417 | O59: NO | P59: HARDWARE | Q59: IMPRESION | R59: NO IMPRIME UNO O VARIOS CARACTERES | S59: CB UNO A UNO | U59: CERRADO | V59: 01/08/2025 01-08 SE ESCALA PARA VISITA. LLAMAR ANTES DE VISITAR, CONFIRMAR FALLA Y DATOS | 02/08/2025 SE LLEGA AL SITIO Y SE ENCUENTRA CERRADO SE LLAMA AL CLIENTE Y NO HAY RESPUESTA | 02/08/2025 NUMEROS DE CONTACTO SIN RESPUESTA NO CONTESTA | 02/08/2025 SE REALIZA CAMBIO DE EQUIPO POR PROBLEMAS DE IMPRESORA SE VALIDA TODO QUEDA OK | W59: VISITA_TÉCNICA | X59: NN00K629 | Y59: TIPO I | Z59: TERRESTRE | AA59: MARTINEZ SALGUEDO ANDRES AUGUSTO | AB59: 1 | AC59: 0 | AD59: =IF(W59="SOPORTE_TELEFÓNICO",'BASE LIQUIDACION REDEBAN 2025'!$B$19,IF(W59="ENVÍO",'BASE LIQUIDACION REDEBAN 2025'!$C$2,IF(Y59="TIPO I",'BASE LIQUIDACION REDEBAN 2025'!$C$2,IF(Y59="TIPO II",'BASE LIQUIDACION REDEBAN 2025'!$C$3,IF(Y59="TIPO III",'BASE LIQUIDACION REDEBAN 2025'!$C$4,IF(Y59="TIPO IV",'BASE LIQUIDACION REDEBAN 2025'!$C$5,IF(Z59="AEREO",'BASE LIQUIDACION REDEBAN 2025'!$B$6,'BASE LIQUIDACION REDEBAN 2025'!$C$5))))))) -> 65960.072 | AE59: =IF(OR(W59="SOPORTE_TELEFÓNICO",W59="ENVÍO"),0,IF(Y59="TIPO I",'BASE LIQUIDACION REDEBAN 2025'!$B$10,IF(Y59="TIPO II",'BASE LIQUIDACION REDEBAN 2025'!$B$11,IF(Y59="TIPO III",'BASE LIQUIDACION REDEBAN 2025'!$B$12,'BASE LIQUIDACION REDEBAN 2025'!$B$13)))) -> 75096.394 | AF59: =IF(OR(W59="SOPORTE_TELEFÓNICO",W59="ENVÍO"),AD59,(AD59*AB59+AE59*AC59)) -> 65960.072
A60: MEDELLIN | B60: =VLOOKUP(A60,'CENTRO DE COSTOS'!A:D,4,FALSE) -> JUAN SEBASTIÁN RÍOS CASTRILLÓN | C60: =VLOOKUP(A60,'CENTRO DE COSTOS'!A:D,2,FALSE) -> 0004-0005 | D60: 5001 | E60: 2541584 | F60: 77879 | G60: INCIDENTE | H60: ANTIOQUIA | I60: MEDELLIN | J60: PTM MEDELLIN VARIEDADES TEYEZ | K60: REDEBAN | L60: FO-25-1318159 | M60: 45870.66 | N60: 45871.429 | O60: NO | P60: HARDWARE | Q60: COMUNICACION | R60: MENSAJE CABLE DE RED DESCONECTADO | S60: AGREGADOR | U60: CERRADO | V60: 01/08/2025 01-08 SE ESCALA PARA VISITA. LLAMAR ANTES DE VISITAR, CONFIRMAR FALLA Y DATOS | 02/08/2025 LLAMO AL NÚMERO INDICADO PARA CONFIRMAR LA VISITA, Y LA SEÑORA YUDIS TELLEZ CON CC: 43896809 INFORMA QUE EL DATAFONO YA SE ENCUENTRA FUNCIONANDO CON NORMALIDAD EL PROBLEMA ERA EL INTERNET DEL COMERCIO | W60: SOPORTE_TELEFÓNICO | X60: 0 | Y60: TIPO I | Z60: TERRESTRE | AA60: RUA ALVAREZ RICHARD ANDRES | AB60: 0 | AC60: 0 | AD60: =IF(W60="SOPORTE_TELEFÓNICO",'BASE LIQUIDACION REDEBAN 2025'!$B$19,IF(W60="ENVÍO",'BASE LIQUIDACION REDEBAN 2025'!$C$2,IF(Y60="TIPO I",'BASE LIQUIDACION REDEBAN 2025'!$C$2,IF(Y60="TIPO II",'BASE LIQUIDACION REDEBAN 2025'!$C$3,IF(Y60="TIPO III",'BASE LIQUIDACION REDEBAN 2025'!$C$4,IF(Y60="TIPO IV",'BASE LIQUIDACION REDEBAN 2025'!$C$5,IF(Z60="AEREO",'BASE LIQUIDACION REDEBAN 2025'!$B$6,'BASE LIQUIDACION REDEBAN 2025'!$C$5))))))) -> 41241.08 | AE60: =IF(OR(W60="SOPORTE_TELEFÓNICO",W60="ENVÍO"),0,IF(Y60="TIPO I",'BASE LIQUIDACION REDEBAN 2025'!$B$10,IF(Y60="TIPO II",'BASE LIQUIDACION REDEBAN 2025'!$B$11,IF(Y60="TIPO III",'BASE LIQUIDACION REDEBAN 2025'!$B$12,'BASE LIQUIDACION REDEBAN 2025'!$B$13)))) -> 0 | AF60: =IF(OR(W60="SOPORTE_TELEFÓNICO",W60="ENVÍO"),AD60,(AD60*AB60+AE60*AC60)) -> 41241.08
A61: VILLAVICENCIO | B61: =VLOOKUP(A61,'CENTRO DE COSTOS'!A:D,4,FALSE) -> KEVIN ALEXIS CORZO BUSTOS | C61: =VLOOKUP(A61,'CENTRO DE COSTOS'!A:D,2,FALSE) -> 0004-0007 | D61: 50001 | E61: 2541887 | F61: 22179 | G61: INCIDENTE | H61: META | I61: VILLAVICENCIO | J61: BARRIO ANILLO VIAL VILLAVICENC | K61: REDEBAN | L61: FO-25-1318463 | M61: 45870.681 | N61: 45871.432 | O61: NO | P61: SOFTWARE | Q61: COMUNICACION | R61: VERIFIQUE PARAMETROS | S61: CB UNO A UNO | U61: CERRADO | V61: 01/08/2025 01-08 SE ESCALA PARA VISITA. LLAMAR ANTES DE VISITAR, CONFIRMAR FALLA Y DATOS | 02/08/2025 SE REALIZA AJUSTE SE COLOCA IP FIJA SE REALIZA PRUEBAS BÁSICAS SIN NOVEDAD | W61: VISITA_TÉCNICA | X61: ADZZZ515 | Y61: TIPO I | Z61: TERRESTRE | AA61: ROZO JIMENEZ EDGAR ARMANDO | AB61: 1 | AC61: 0 | AD61: =IF(W61="SOPORTE_TELEFÓNICO",'BASE LIQUIDACION REDEBAN 2025'!$B$19,IF(W61="ENVÍO",'BASE LIQUIDACION REDEBAN 2025'!$C$2,IF(Y61="TIPO I",'BASE LIQUIDACION REDEBAN 2025'!$C$2,IF(Y61="TIPO II",'BASE LIQUIDACION REDEBAN 2025'!$C$3,IF(Y61="TIPO III",'BASE LIQUIDACION REDEBAN 2025'!$C$4,IF(Y61="TIPO IV",'BASE LIQUIDACION REDEBAN 2025'!$C$5,IF(Z61="AEREO",'BASE LIQUIDACION REDEBAN 2025'!$B$6,'BASE LIQUIDACION REDEBAN 2025'!$C$5))))))) -> 65960.072 | AE61: =IF(OR(W61="SOPORTE_TELEFÓNICO",W61="ENVÍO"),0,IF(Y61="TIPO I",'BASE LIQUIDACION REDEBAN 2025'!$B$10,IF(Y61="TIPO II",'BASE LIQUIDACION REDEBAN 2025'!$B$11,IF(Y61="TIPO III",'BASE LIQUIDACION REDEBAN 2025'!$B$12,'BASE LIQUIDACION REDEBAN 2025'!$B$13)))) -> 75096.394 | AF61: =IF(OR(W61="SOPORTE_TELEFÓNICO",W61="ENVÍO"),AD61,(AD61*AB61+AE61*AC61)) -> 65960.072
A62: CUCUTA | B62: =VLOOKUP(A62,'CENTRO DE COSTOS'!A:D,4,FALSE) -> MIGUEL JULIÁN HERNÁNDEZ GUARÍN | C62: =VLOOKUP(A62,'CENTRO DE COSTOS'!A:D,2,FALSE) -> 0004-0008 | D62: 54001 | E62: 2541464 | F62: 69246 | G62: INCIDENTE | H62: NORTE DE SANTANDER | I62: CUCUTA | J62: DISTRICOLSALA BELLEZA VIANISA | K62: REDEBAN | L62: FO-25-1317911 | M62: 45870.639 | N62: 45871.44 | O62: NO | P62: HARDWARE | Q62: SE REINICIA | R62: DAÑO POS | S62: AGREGADOR | U62: CERRADO | V62: 01/08/2025 01-08 SE ESCALA PARA VISITA. LLAMAR ANTES DE VISITAR, CONFIRMAR FALLA Y DATOS | 02/08/2025 SE REALIZARON LLAMADAS TELEFÓNICA AL NÚMERO 3114830971 NO SE OBTIENE COMUNICACIÓN, SE DEJAN MSJ VÍA WHATSAPP Y SE PROCEDE A REALIZAR VISITA TÉCNICA | 02/08/2025 SE REALIZÓ VISITA AL COMERCIO Y SE ENCUENTRA DATAFONO REINICIANDOSE, SE REALIZA CAMBIO DE DATAFONO PRUEBAS EXITOSAS | W62: VISITA_TÉCNICA | X62: A303Z055 | Y62: TIPO I | Z62: TERRESTRE | AA62: MORA VEGA JEAMPIER | AB62: 1 | AC62: 0 | AD62: =IF(W62="SOPORTE_TELEFÓNICO",'BASE LIQUIDACION REDEBAN 2025'!$B$19,IF(W62="ENVÍO",'BASE LIQUIDACION REDEBAN 2025'!$C$2,IF(Y62="TIPO I",'BASE LIQUIDACION REDEBAN 2025'!$C$2,IF(Y62="TIPO II",'BASE LIQUIDACION REDEBAN 2025'!$C$3,IF(Y62="TIPO III",'BASE LIQUIDACION REDEBAN 2025'!$C$4,IF(Y62="TIPO IV",'BASE LIQUIDACION REDEBAN 2025'!$C$5,IF(Z62="AEREO",'BASE LIQUIDACION REDEBAN 2025'!$B$6,'BASE LIQUIDACION REDEBAN 2025'!$C$5))))))) -> 65960.072 | AE62: =IF(OR(W62="SOPORTE_TELEFÓNICO",W62="ENVÍO"),0,IF(Y62="TIPO I",'BASE LIQUIDACION REDEBAN 2025'!$B$10,IF(Y62="TIPO II",'BASE LIQUIDACION REDEBAN 2025'!$B$11,IF(Y62="TIPO III",'BASE LIQUIDACION REDEBAN 2025'!$B$12,'BASE LIQUIDACION REDEBAN 2025'!$B$13)))) -> 75096.394 | AF62: =IF(OR(W62="SOPORTE_TELEFÓNICO",W62="ENVÍO"),AD62,(AD62*AB62+AE62*AC62)) -> 65960.072
A63: MONTERIA | B63: =VLOOKUP(A63,'CENTRO DE COSTOS'!A:D,4,FALSE) -> JOSE MAURICIO HERNANDEZ ROJAS | C63: =VLOOKUP(A63,'CENTRO DE COSTOS'!A:D,2,FALSE) -> 0004-0001 | D63: 23162 | E63: 2539447 | F63: 65471 | G63: INCIDENTE | H63: CORDOBA | I63: CERETE | J63: BARRIO EL SOCORRO CERETE 1 | K63: REDEBAN | L63: FO-25-1316284 | M63: 45870.468 | N63: 45871.448 | O63: NO | P63: SOFTWARE | Q63: ERROR DE TRANSACCIONES | R63: RECHAZO GENERAL | S63: CB UNO A UNO | U63: CERRADO | V63: 01/08/2025 01-08 SE ESCALA PARA VISITA. LLAMAR ANTES DE VISITAR, CONFIRMAR FALLA Y DATOS | 02/08/2025 SE REALIZA VISITA AL PUNTO PARA MANTENIMIENTO REPORTADO POR EL CLIENTE, SE LLEGA AL PUNTO Y SE ENCONTRÓ CERRADO ES ESTABLECIMIENTO COMERCIAL, SE REALIZAN LLAMAS AL NÚMEROS SUMIISTEDOS Y NO RESPONDEN. | W63: VISITA_TÉCNICA | X63: NO INTERVENIDA | Y63: TIPO I | Z63: TERRESTRE | AA63: GONZALEZ FERRER JESUS ALEXANDER | AB63: 1 | AC63: 0 | AD63: =IF(W63="SOPORTE_TELEFÓNICO",'BASE LIQUIDACION REDEBAN 2025'!$B$19,IF(W63="ENVÍO",'BASE LIQUIDACION REDEBAN 2025'!$C$2,IF(Y63="TIPO I",'BASE LIQUIDACION REDEBAN 2025'!$C$2,IF(Y63="TIPO II",'BASE LIQUIDACION REDEBAN 2025'!$C$3,IF(Y63="TIPO III",'BASE LIQUIDACION REDEBAN 2025'!$C$4,IF(Y63="TIPO IV",'BASE LIQUIDACION REDEBAN 2025'!$C$5,IF(Z63="AEREO",'BASE LIQUIDACION REDEBAN 2025'!$B$6,'BASE LIQUIDACION REDEBAN 2025'!$C$5))))))) -> 65960.072 | AE63: =IF(OR(W63="SOPORTE_TELEFÓNICO",W63="ENVÍO"),0,IF(Y63="TIPO I",'BASE LIQUIDACION REDEBAN 2025'!$B$10,IF(Y63="TIPO II",'BASE LIQUIDACION REDEBAN 2025'!$B$11,IF(Y63="TIPO III",'BASE LIQUIDACION REDEBAN 2025'!$B$12,'BASE LIQUIDACION REDEBAN 2025'!$B$13)))) -> 75096.394 | AF63: =IF(OR(W63="SOPORTE_TELEFÓNICO",W63="ENVÍO"),AD63,(AD63*AB63+AE63*AC63)) -> 65960.072
A64: BOGOTA | B64: =VLOOKUP(A64,'CENTRO DE COSTOS'!A:D,4,FALSE) -> WILLIAM ASDRUBAL ROZO ROZO | C64: =VLOOKUP(A64,'CENTRO DE COSTOS'!A:D,2,FALSE) -> 0004-0004 | D64: 11001 | E64: 2539701 | F64: 25841 | G64: INCIDENTE | H64: CUNDINAMARCA | I64: BOGOTA | J64: REDY SANTA HELENITA | K64: REDEBAN | L64: FO-25-1316559 | M64: 45870.478 | N64: 45871.451 | O64: NO | P64: HARDWARE | Q64: DETERIORO | R64: DATAFONO | S64: ROBUSTO | U64: CERRADO | V64: 01/08/2025 01-08 SE ESCALA PARA VISITA. LLAMAR ANTES DE VISITAR, CONFIRMAR FALLA Y DATOS | 02/08/2025 SE REALIZA CAMBIO DE DATAFONO POR DAÑO EN TECLADO, SE CREA USUARIOS, PRUEBAS OK. | W64: VISITA_TÉCNICA | X64: 9C0FZ086 | Y64: TIPO I | Z64: TERRESTRE | AA64: MURCIA HERNANDEZ HARVEY IGNACIO | AB64: 1 | AC64: 0 | AD64: =IF(W64="SOPORTE_TELEFÓNICO",'BASE LIQUIDACION REDEBAN 2025'!$B$19,IF(W64="ENVÍO",'BASE LIQUIDACION REDEBAN 2025'!$C$2,IF(Y64="TIPO I",'BASE LIQUIDACION REDEBAN 2025'!$C$2,IF(Y64="TIPO II",'BASE LIQUIDACION REDEBAN 2025'!$C$3,IF(Y64="TIPO III",'BASE LIQUIDACION REDEBAN 2025'!$C$4,IF(Y64="TIPO IV",'BASE LIQUIDACION REDEBAN 2025'!$C$5,IF(Z64="AEREO",'BASE LIQUIDACION REDEBAN 2025'!$B$6,'BASE LIQUIDACION REDEBAN 2025'!$C$5))))))) -> 65960.072 | AE64: =IF(OR(W64="SOPORTE_TELEFÓNICO",W64="ENVÍO"),0,IF(Y64="TIPO I",'BASE LIQUIDACION REDEBAN 2025'!$B$10,IF(Y64="TIPO II",'BASE LIQUIDACION REDEBAN 2025'!$B$11,IF(Y64="TIPO III",'BASE LIQUIDACION REDEBAN 2025'!$B$12,'BASE LIQUIDACION REDEBAN 2025'!$B$13)))) -> 75096.394 | AF64: =IF(OR(W64="SOPORTE_TELEFÓNICO",W64="ENVÍO"),AD64,(AD64*AB64+AE64*AC64)) -> 65960.072
A65: BOGOTA | B65: =VLOOKUP(A65,'CENTRO DE COSTOS'!A:D,4,FALSE) -> WILLIAM ASDRUBAL ROZO ROZO | C65: =VLOOKUP(A65,'CENTRO DE COSTOS'!A:D,2,FALSE) -> 0004-0004 | D65: 25572 | E65: 2523623 | F65: 50304 | G65: INCIDENTE | H65: CUNDINAMARCA | I65: PUERTO SALGAR | J65: BARRIO PUERTO SALGAR PUERTO SA | K65: REDEBAN | L65: FO-25-1302768 | M65: 45867.731 | N65: 45871.457 | O65: NO | P65: HARDWARE | Q65: COMUNICACION | R65: DAÑO POS | S65: CB UNO A UNO | U65: CERRADO | V65: 29/07/2025 29-07 SE ESCALA PARA VISITA. LLAMAR ANTES DE VISITAR, CONFIRMAR FALLA Y DATOS | 02/08/2025 SE VISITA COMERCIO POR FALLEN EN COMUNICACIÓN CABLE DESCONECTADO ALMVALIDAR EQUIPO SE EVIDENCIA QUE EL PUERTO ETHERNET DEL DATÁFONO ESTÁ DAÑADO SE PROCEDE A GENERAR CAMBIO DE EQUIPO Y POR TECNOLOGÍA SE INSTALA PINPAD Y MAGICBOX CON S/N 241597317561324755901283 SE REALIZAN TRANSACCIONES DE PRUEBA OKAY SE DEJA CB OPERANDO SIN NOVEDAD | W65: VISITA_TÉCNICA | X65: XP00W429 | Y65: TIPO IV | Z65: TERRESTRE | AA65: ROMERO ROJAS BREIDY JHOHAN | AB65: 1 | AC65: 0 | AD65: =IF(W65="SOPORTE_TELEFÓNICO",'BASE LIQUIDACION REDEBAN 2025'!$B$19,IF(W65="ENVÍO",'BASE LIQUIDACION REDEBAN 2025'!$C$2,IF(Y65="TIPO I",'BASE LIQUIDACION REDEBAN 2025'!$C$2,IF(Y65="TIPO II",'BASE LIQUIDACION REDEBAN 2025'!$C$3,IF(Y65="TIPO III",'BASE LIQUIDACION REDEBAN 2025'!$C$4,IF(Y65="TIPO IV",'BASE LIQUIDACION REDEBAN 2025'!$C$5,IF(Z65="AEREO",'BASE LIQUIDACION REDEBAN 2025'!$B$6,'BASE LIQUIDACION REDEBAN 2025'!$C$5))))))) -> 479588.88 | AE65: =IF(OR(W65="SOPORTE_TELEFÓNICO",W65="ENVÍO"),0,IF(Y65="TIPO I",'BASE LIQUIDACION REDEBAN 2025'!$B$10,IF(Y65="TIPO II",'BASE LIQUIDACION REDEBAN 2025'!$B$11,IF(Y65="TIPO III",'BASE LIQUIDACION REDEBAN 2025'!$B$12,'BASE LIQUIDACION REDEBAN 2025'!$B$13)))) -> 196536.53 | AF65: =IF(OR(W65="SOPORTE_TELEFÓNICO",W65="ENVÍO"),AD65,(AD65*AB65+AE65*AC65)) -> 479588.88
A66: CALI | B66: =VLOOKUP(A66,'CENTRO DE COSTOS'!A:D,4,FALSE) -> DIEGO FERNANDO HENAO CARDONA | C66: =VLOOKUP(A66,'CENTRO DE COSTOS'!A:D,2,FALSE) -> 0004-0003 | D66: 19001 | E66: 2528851 | F66: 63865 | G66: INCIDENTE | H66: CAUCA | I66: POPAYAN | J66: BARRIO LA PAMBA POPAYAN 1 | K66: REDEBAN | L66: FO-25-1307651 | M66: 45868.644 | N66: 45871.468 | O66: NO | P66: HARDWARE | Q66: COMUNICACION | R66: MENSAJE CABLE DE RED DESCONECTADO | S66: CB UNO A UNO | U66: CERRADO | V66: 30/07/2025 30-07 EN COMUNICACION CON LA SEÑORA VICTORIA CUELLAR AL NUMERO 3173664961, CONFIRMA FALLA, DATOS CORRECTOS. SE ESCALA PARA VISITA | 02/08/2025 SE LLEGA AL SITIO DENTRO DE LA INSTALACIÓN INFORMA VIGILANTE QUE LA SEÑORA AÚN NO HA LLEGADO SE ESPERÓ EN SITIO NO LLEGA LA PERSONA NI CONTESTA EL CELULAR POR TANTO SE CIERRA LA VISITA | W66: VISITA_TÉCNICA | X66: NO APLICA | Y66: TIPO III | Z66: TERRESTRE | AA66: GIMBUEL LASSO LUIS GERMAN | AB66: 1 | AC66: 0 | AD66: =IF(W66="SOPORTE_TELEFÓNICO",'BASE LIQUIDACION REDEBAN 2025'!$B$19,IF(W66="ENVÍO",'BASE LIQUIDACION REDEBAN 2025'!$C$2,IF(Y66="TIPO I",'BASE LIQUIDACION REDEBAN 2025'!$C$2,IF(Y66="TIPO II",'BASE LIQUIDACION REDEBAN 2025'!$C$3,IF(Y66="TIPO III",'BASE LIQUIDACION REDEBAN 2025'!$C$4,IF(Y66="TIPO IV",'BASE LIQUIDACION REDEBAN 2025'!$C$5,IF(Z66="AEREO",'BASE LIQUIDACION REDEBAN 2025'!$B$6,'BASE LIQUIDACION REDEBAN 2025'!$C$5))))))) -> 275728.78 | AE66: =IF(OR(W66="SOPORTE_TELEFÓNICO",W66="ENVÍO"),0,IF(Y66="TIPO I",'BASE LIQUIDACION REDEBAN 2025'!$B$10,IF(Y66="TIPO II",'BASE LIQUIDACION REDEBAN 2025'!$B$11,IF(Y66="TIPO III",'BASE LIQUIDACION REDEBAN 2025'!$B$12,'BASE LIQUIDACION REDEBAN 2025'!$B$13)))) -> 196536.53 | AF66: =IF(OR(W66="SOPORTE_TELEFÓNICO",W66="ENVÍO"),AD66,(AD66*AB66+AE66*AC66)) -> 275728.78
A67: CARTAGENA | B67: =VLOOKUP(A67,'CENTRO DE COSTOS'!A:D,4,FALSE) -> JOSE MAURICIO HERNANDEZ ROJAS | C67: =VLOOKUP(A67,'CENTRO DE COSTOS'!A:D,2,FALSE) -> 0004-0001 | D67: 13430 | E67: 2530756 | F67: 60167 | G67: INCIDENTE | H67: BOLIVAR | I67: MAGANGUE | J67: BARRIO CENTRO MAGANGUE 7 | K67: REDEBAN | L67: FO-25-1309857 | M67: 45869.333 | N67: 45871.471 | O67: NO | P67: SOFTWARE | Q67: LECTOR DE BARRAS | R67: LECTOR DESCONFIGURADO | S67: CB UNO A UNO | U67: CERRADO | V67: 31/07/2025 31-07 EN COMUNICACION CON LA SEÑORA BERTHA RANGEL AL NUMERO 3145318764, CONFIRMA DATOS CORRECTOS. SE ESCALA PARA VISITA DE RECOLECCION | 02/08/2025 SE VISITA COMERCIO POR FALLA, SE CONFIGURA LECTOR Y SE ACOMODA BIEN EN EL DATÁFONO, SE LE INDICA QUE MANTENGA EL LECTOR CONECTADO, NO SE REALIZA CIERRE, SE REALIZAN PRUEBAS OK. | W67: VISITA_TÉCNICA | X67: UV00L431 | Y67: TIPO IV | Z67: TERRESTRE | AA67: CACERES HERNANDEZ ANDRES | AB67: 1 | AC67: 0 | AD67: =IF(W67="SOPORTE_TELEFÓNICO",'BASE LIQUIDACION REDEBAN 2025'!$B$19,IF(W67="ENVÍO",'BASE LIQUIDACION REDEBAN 2025'!$C$2,IF(Y67="TIPO I",'BASE LIQUIDACION REDEBAN 2025'!$C$2,IF(Y67="TIPO II",'BASE LIQUIDACION REDEBAN 2025'!$C$3,IF(Y67="TIPO III",'BASE LIQUIDACION REDEBAN 2025'!$C$4,IF(Y67="TIPO IV",'BASE LIQUIDACION REDEBAN 2025'!$C$5,IF(Z67="AEREO",'BASE LIQUIDACION REDEBAN 2025'!$B$6,'BASE LIQUIDACION REDEBAN 2025'!$C$5))))))) -> 479588.88 | AE67: =IF(OR(W67="SOPORTE_TELEFÓNICO",W67="ENVÍO"),0,IF(Y67="TIPO I",'BASE LIQUIDACION REDEBAN 2025'!$B$10,IF(Y67="TIPO II",'BASE LIQUIDACION REDEBAN 2025'!$B$11,IF(Y67="TIPO III",'BASE LIQUIDACION REDEBAN 2025'!$B$12,'BASE LIQUIDACION REDEBAN 2025'!$B$13)))) -> 196536.53 | AF67: =IF(OR(W67="SOPORTE_TELEFÓNICO",W67="ENVÍO"),AD67,(AD67*AB67+AE67*AC67)) -> 479588.88
A68: CUCUTA | B68: =VLOOKUP(A68,'CENTRO DE COSTOS'!A:D,4,FALSE) -> MIGUEL JULIÁN HERNÁNDEZ GUARÍN | C68: =VLOOKUP(A68,'CENTRO DE COSTOS'!A:D,2,FALSE) -> 0004-0008 | D68: 54001 | E68: 2539789 | F68: 41889 | G68: INCIDENTE | H68: NORTE DE SANTANDER | I68: CUCUTA | J68: BARRIO NINA CECI CUCUTA 1 | K68: REDEBAN | L68: FO-25-1316713 | M68: 45870.496 | N68: 45871.482 | O68: NO | P68: SOFTWARE | Q68: COMUNICACION | R68: PARAMETROS DE CONFIGURACION EN POS | S68: CB UNO A UNO | U68: CERRADO | V68: 01/08/2025 01-08 SE ESCALA PARA VISITA. LLAMAR ANTES DE VISITAR, CONFIRMAR FALLA Y DATOS | 02/08/2025 SE VISITA COMERCIO, SE REPISAN PARAMETROS DE COMUNICACION, SE HACEN PRUEBAS EXITOSA, CB OPERATIVO. | W68: VISITA_TÉCNICA | X68: 9A0ZZ015 | Y68: TIPO I | Z68: TERRESTRE | AA68: NARANJO AFANADOR RUBEN JESUS | AB68: 1 | AC68: 0 | AD68: =IF(W68="SOPORTE_TELEFÓNICO",'BASE LIQUIDACION REDEBAN 2025'!$B$19,IF(W68="ENVÍO",'BASE LIQUIDACION REDEBAN 2025'!$C$2,IF(Y68="TIPO I",'BASE LIQUIDACION REDEBAN 2025'!$C$2,IF(Y68="TIPO II",'BASE LIQUIDACION REDEBAN 2025'!$C$3,IF(Y68="TIPO III",'BASE LIQUIDACION REDEBAN 2025'!$C$4,IF(Y68="TIPO IV",'BASE LIQUIDACION REDEBAN 2025'!$C$5,IF(Z68="AEREO",'BASE LIQUIDACION REDEBAN 2025'!$B$6,'BASE LIQUIDACION REDEBAN 2025'!$C$5))))))) -> 65960.072 | AE68: =IF(OR(W68="SOPORTE_TELEFÓNICO",W68="ENVÍO"),0,IF(Y68="TIPO I",'BASE LIQUIDACION REDEBAN 2025'!$B$10,IF(Y68="TIPO II",'BASE LIQUIDACION REDEBAN 2025'!$B$11,IF(Y68="TIPO III",'BASE LIQUIDACION REDEBAN 2025'!$B$12,'BASE LIQUIDACION REDEBAN 2025'!$B$13)))) -> 75096.394 | AF68: =IF(OR(W68="SOPORTE_TELEFÓNICO",W68="ENVÍO"),AD68,(AD68*AB68+AE68*AC68)) -> 65960.072
A69: BOGOTA | B69: =VLOOKUP(A69,'CENTRO DE COSTOS'!A:D,4,FALSE) -> WILLIAM ASDRUBAL ROZO ROZO | C69: =VLOOKUP(A69,'CENTRO DE COSTOS'!A:D,2,FALSE) -> 0004-0004 | D69: 11001 | E69: 2542404 | F69: 27970 | G69: INCIDENTE | H69: CUNDINAMARCA | I69: BOGOTA | J69: OPRAP MICENTRO EL PORVENIR | K69: REDEBAN | L69: FO-25-1318638 | M69: 45870.715 | N69: 45871.489 | O69: NO | P69: HARDWARE | Q69: LECTOR DE BARRAS | R69: CABLE LECTORA AVERIADO | S69: ROBUSTO | U69: CERRADO | V69: 01/08/2025 01-08 SE ESCALA PARA VISITA. LLAMAR ANTES DE VISITAR, CONFIRMAR FALLA Y DATOS | 02/08/2025 CAMBIO DE LECTOR DE BARRAS SE REALIZA PRUEBAS OK SE ENTREGA SERVICIO OPERATIVO | W69: VISITA_TÉCNICA | X69: 9DZZZ739 | Y69: TIPO I | Z69: TERRESTRE | AA69: HERNANDEZ NARANJO OSCAR EDUARDO | AB69: 1 | AC69: 0 | AD69: =IF(W69="SOPORTE_TELEFÓNICO",'BASE LIQUIDACION REDEBAN 2025'!$B$19,IF(W69="ENVÍO",'BASE LIQUIDACION REDEBAN 2025'!$C$2,IF(Y69="TIPO I",'BASE LIQUIDACION REDEBAN 2025'!$C$2,IF(Y69="TIPO II",'BASE LIQUIDACION REDEBAN 2025'!$C$3,IF(Y69="TIPO III",'BASE LIQUIDACION REDEBAN 2025'!$C$4,IF(Y69="TIPO IV",'BASE LIQUIDACION REDEBAN 2025'!$C$5,IF(Z69="AEREO",'BASE LIQUIDACION REDEBAN 2025'!$B$6,'BASE LIQUIDACION REDEBAN 2025'!$C$5))))))) -> 65960.072 | AE69: =IF(OR(W69="SOPORTE_TELEFÓNICO",W69="ENVÍO"),0,IF(Y69="TIPO I",'BASE LIQUIDACION REDEBAN 2025'!$B$10,IF(Y69="TIPO II",'BASE LIQUIDACION REDEBAN 2025'!$B$11,IF(Y69="TIPO III",'BASE LIQUIDACION REDEBAN 2025'!$B$12,'BASE LIQUIDACION REDEBAN 2025'!$B$13)))) -> 75096.394 | AF69: =IF(OR(W69="SOPORTE_TELEFÓNICO",W69="ENVÍO"),AD69,(AD69*AB69+AE69*AC69)) -> 65960.072
A70: MONTERIA | B70: =VLOOKUP(A70,'CENTRO DE COSTOS'!A:D,4,FALSE) -> JOSE MAURICIO HERNANDEZ ROJAS | C70: =VLOOKUP(A70,'CENTRO DE COSTOS'!A:D,2,FALSE) -> 0004-0001 | D70: 23001 | E70: 2541666 | F70: 53175 | G70: INCIDENTE | H70: CORDOBA | I70: MONTERIA | J70: BARRIO LOS LAURELES MONTERIA 3 | K70: REDEBAN | L70: FO-25-1318152 | M70: 45870.664 | N70: 45871.492 | O70: NO | P70: SOFTWARE | Q70: LECTOR DE BARRAS | R70: LECTOR DESCONFIGURADO | S70: CB UNO A UNO | U70: CERRADO | V70: 01/08/2025 01-08 SE ESCALA PARA VISITA. LLAMAR ANTES DE VISITAR, CONFIRMAR FALLA Y DATOS | 02/08/2025 SE REALIZÓ CONFIGURACIÓN DE LECTOR DE CÓDIGO DE BARRAS OK, PRUEBAS OK, TELECARGA DRNA. | W70: VISITA_TÉCNICA | X70: XP0OZ131 | Y70: TIPO I | Z70: TERRESTRE | AA70: CALDERA SALCEDO CARLOS JULIO | AB70: 1 | AC70: 0 | AD70: =IF(W70="SOPORTE_TELEFÓNICO",'BASE LIQUIDACION REDEBAN 2025'!$B$19,IF(W70="ENVÍO",'BASE LIQUIDACION REDEBAN 2025'!$C$2,IF(Y70="TIPO I",'BASE LIQUIDACION REDEBAN 2025'!$C$2,IF(Y70="TIPO II",'BASE LIQUIDACION REDEBAN 2025'!$C$3,IF(Y70="TIPO III",'BASE LIQUIDACION REDEBAN 2025'!$C$4,IF(Y70="TIPO IV",'BASE LIQUIDACION REDEBAN 2025'!$C$5,IF(Z70="AEREO",'BASE LIQUIDACION REDEBAN 2025'!$B$6,'BASE LIQUIDACION REDEBAN 2025'!$C$5))))))) -> 65960.072 | AE70: =IF(OR(W70="SOPORTE_TELEFÓNICO",W70="ENVÍO"),0,IF(Y70="TIPO I",'BASE LIQUIDACION REDEBAN 2025'!$B$10,IF(Y70="TIPO II",'BASE LIQUIDACION REDEBAN 2025'!$B$11,IF(Y70="TIPO III",'BASE LIQUIDACION REDEBAN 2025'!$B$12,'BASE LIQUIDACION REDEBAN 2025'!$B$13)))) -> 75096.394 | AF70: =IF(OR(W70="SOPORTE_TELEFÓNICO",W70="ENVÍO"),AD70,(AD70*AB70+AE70*AC70)) -> 65960.072
A71: PEREIRA | B71: =VLOOKUP(A71,'CENTRO DE COSTOS'!A:D,4,FALSE) -> DIEGO FERNANDO HENAO CARDONA | C71: =VLOOKUP(A71,'CENTRO DE COSTOS'!A:D,2,FALSE) -> 0004-0002 | D71: 66001 | E71: 2541631 | F71: 49275 | G71: INCIDENTE | H71: RISARALDA | I71: PEREIRA | J71: DISTRICOL TIENDA NUEVA VILLA | K71: REDEBAN | L71: FO-25-1318163 | M71: 45870.653 | N71: 45871.494 | O71: NO | P71: HARDWARE | Q71: IMPRESION | R71: TAPA IMPRESORA | S71: AGREGADOR | U71: CERRADO | V71: 01/08/2025 01-08 SE ESCALA PARA VISITA. LLAMAR ANTES DE VISITAR, CONFIRMAR FALLA Y DATOS | 02/08/2025 SE CAMBIA EQUIPO POR DAÑO EN LA TAPA DE LA IMPRESORA, SE REALIZAN PRUEBAS OK. | W71: VISITA_TÉCNICA | X71: 9C00Q125 | Y71: TIPO I | Z71: TERRESTRE | AA71: FRANCO CAÑAVERAL YAMID RAUL | AB71: 1 | AC71: 0 | AD71: =IF(W71="SOPORTE_TELEFÓNICO",'BASE LIQUIDACION REDEBAN 2025'!$B$19,IF(W71="ENVÍO",'BASE LIQUIDACION REDEBAN 2025'!$C$2,IF(Y71="TIPO I",'BASE LIQUIDACION REDEBAN 2025'!$C$2,IF(Y71="TIPO II",'BASE LIQUIDACION REDEBAN 2025'!$C$3,IF(Y71="TIPO III",'BASE LIQUIDACION REDEBAN 2025'!$C$4,IF(Y71="TIPO IV",'BASE LIQUIDACION REDEBAN 2025'!$C$5,IF(Z71="AEREO",'BASE LIQUIDACION REDEBAN 2025'!$B$6,'BASE LIQUIDACION REDEBAN 2025'!$C$5))))))) -> 65960.072 | AE71: =IF(OR(W71="SOPORTE_TELEFÓNICO",W71="ENVÍO"),0,IF(Y71="TIPO I",'BASE LIQUIDACION REDEBAN 2025'!$B$10,IF(Y71="TIPO II",'BASE LIQUIDACION REDEBAN 2025'!$B$11,IF(Y71="TIPO III",'BASE LIQUIDACION REDEBAN 2025'!$B$12,'BASE LIQUIDACION REDEBAN 2025'!$B$13)))) -> 75096.394 | AF71: =IF(OR(W71="SOPORTE_TELEFÓNICO",W71="ENVÍO"),AD71,(AD71*AB71+AE71*AC71)) -> 65960.072
A72: MEDELLIN | B72: =VLOOKUP(A72,'CENTRO DE COSTOS'!A:D,4,FALSE) -> JUAN SEBASTIÁN RÍOS CASTRILLÓN | C72: =VLOOKUP(A72,'CENTRO DE COSTOS'!A:D,2,FALSE) -> 0004-0005 | D72: 5001 | E72: 2541086 | F72: 37968 | G72: INCIDENTE | H72: ANTIOQUIA | I72: MEDELLIN | J72: BARRIO BELEN LAS MERCEDES MED | K72: REDEBAN | L72: FO-25-1317816 | M72: 45870.624 | N72: 45871.499 | O72: NO | P72: HARDWARE | Q72: COMUNICACION | R72: DAÑO POS | S72: CB UNO A UNO | U72: CERRADO | V72: 01/08/2025 01-08 SE ESCALA PARA VISITA. LLAMAR ANTES DE VISITAR, CONFIRMAR FALLA Y DATOS | 02/08/2025 SE LLAMA AL NÚMERO INDICADO PARA CONFIRMAR LA VISITA, Y LA SEÑORA NATALIA SANCHEZ CON CC1078636661, INDICA QUE EL EQUIPO YA SE ENCUENTRA FUNCIONANDO CON TOTAL NORMALIDAD, EQUIPO OK | W72: SOPORTE_TELEFÓNICO | X72: 0 | Y72: TIPO I | Z72: TERRESTRE | AA72: RUA ALVAREZ RICHARD ANDRES | AB72: 0 | AC72: 0 | AD72: =IF(W72="SOPORTE_TELEFÓNICO",'BASE LIQUIDACION REDEBAN 2025'!$B$19,IF(W72="ENVÍO",'BASE LIQUIDACION REDEBAN 2025'!$C$2,IF(Y72="TIPO I",'BASE LIQUIDACION REDEBAN 2025'!$C$2,IF(Y72="TIPO II",'BASE LIQUIDACION REDEBAN 2025'!$C$3,IF(Y72="TIPO III",'BASE LIQUIDACION REDEBAN 2025'!$C$4,IF(Y72="TIPO IV",'BASE LIQUIDACION REDEBAN 2025'!$C$5,IF(Z72="AEREO",'BASE LIQUIDACION REDEBAN 2025'!$B$6,'BASE LIQUIDACION REDEBAN 2025'!$C$5))))))) -> 41241.08 | AE72: =IF(OR(W72="SOPORTE_TELEFÓNICO",W72="ENVÍO"),0,IF(Y72="TIPO I",'BASE LIQUIDACION REDEBAN 2025'!$B$10,IF(Y72="TIPO II",'BASE LIQUIDACION REDEBAN 2025'!$B$11,IF(Y72="TIPO III",'BASE LIQUIDACION REDEBAN 2025'!$B$12,'BASE LIQUIDACION REDEBAN 2025'!$B$13)))) -> 0 | AF72: =IF(OR(W72="SOPORTE_TELEFÓNICO",W72="ENVÍO"),AD72,(AD72*AB72+AE72*AC72)) -> 41241.08
A73: MEDELLIN | B73: =VLOOKUP(A73,'CENTRO DE COSTOS'!A:D,4,FALSE) -> JUAN SEBASTIÁN RÍOS CASTRILLÓN | C73: =VLOOKUP(A73,'CENTRO DE COSTOS'!A:D,2,FALSE) -> 0004-0005 | D73: 5310 | E73: 2536269 | F73: 10524 | G73: INCIDENTE | H73: ANTIOQUIA | I73: GOMEZ PLATA | J73: GOMEZ PLATA II - ANTIOQUIA | K73: REDEBAN | L73: FO-25-1314580 | M73: 45870.333 | N73: 45871.507 | O73: NO | P73: HARDWARE | Q73: PINPAD | R73: DAÑO POS | S73: CB UNO A UNO | U73: CERRADO | V73: 01/08/2025 01-08 SE ESCALA PARA VISITA. LLAMAR ANTES DE VISITAR, CONFIRMAR FALLA Y DATOS | 02/08/2025 SE CAMBIA PINPAD CON LECTOR CHIP MALO, SE CAMBIA DATÁFONO POR TECNOLOGÍA, SE DEJAN SERVICIOS FUNCIONANDO CORRECTAMENTE | W73: VISITA_TÉCNICA | X73: IZ0YZ155 | Y73: TIPO II | Z73: TERRESTRE | AA73: BARRIENTOS HERNANDEZ CRISTIAN HORACIO | AB73: 1 | AC73: 0 | AD73: =IF(W73="SOPORTE_TELEFÓNICO",'BASE LIQUIDACION REDEBAN 2025'!$B$19,IF(W73="ENVÍO",'BASE LIQUIDACION REDEBAN 2025'!$C$2,IF(Y73="TIPO I",'BASE LIQUIDACION REDEBAN 2025'!$C$2,IF(Y73="TIPO II",'BASE LIQUIDACION REDEBAN 2025'!$C$3,IF(Y73="TIPO III",'BASE LIQUIDACION REDEBAN 2025'!$C$4,IF(Y73="TIPO IV",'BASE LIQUIDACION REDEBAN 2025'!$C$5,IF(Z73="AEREO",'BASE LIQUIDACION REDEBAN 2025'!$B$6,'BASE LIQUIDACION REDEBAN 2025'!$C$5))))))) -> 144967.87 | AE73: =IF(OR(W73="SOPORTE_TELEFÓNICO",W73="ENVÍO"),0,IF(Y73="TIPO I",'BASE LIQUIDACION REDEBAN 2025'!$B$10,IF(Y73="TIPO II",'BASE LIQUIDACION REDEBAN 2025'!$B$11,IF(Y73="TIPO III",'BASE LIQUIDACION REDEBAN 2025'!$B$12,'BASE LIQUIDACION REDEBAN 2025'!$B$13)))) -> 140395.63 | AF73: =IF(OR(W73="SOPORTE_TELEFÓNICO",W73="ENVÍO"),AD73,(AD73*AB73+AE73*AC73)) -> 144967.87
A74: MEDELLIN | B74: =VLOOKUP(A74,'CENTRO DE COSTOS'!A:D,4,FALSE) -> JUAN SEBASTIÁN RÍOS CASTRILLÓN | C74: =VLOOKUP(A74,'CENTRO DE COSTOS'!A:D,2,FALSE) -> 0004-0005 | D74: 27001 | E74: 2530956 | F74: 36476 | G74: INCIDENTE | H74: CHOCO | I74: QUIBDO | J74: BARRIO CESAR CONTO QUIBDO 1 | K74: REDEBAN | L74: FO-25-1309833 | M74: 45869.355 | N74: 45871.51 | O74: NO | P74: SOFTWARE | Q74: INCOMPATIBILIDAD POR TECNOLOGIA | R74: PINPAD | S74: CB UNO A UNO | U74: CERRADO | V74: 31/07/2025 31-07 SE INTENTA COMUNICACION CON LA SEÑORA MARTA MARTINEZ AL NUMERO 3233588026, PERO NO CONTESTA LA LLAMADA. SE ESCALA PARA VISITA, CONFIRMAR FALLA Y DATOS | 02/08/2025 SE REALIZA CAMBIO DE EQUIPO POR DAÑO EN EL PIND PAD E INCOMPATIBILIDAD, SE REIALZAN PRUEBAS EL CB QUEDA OPERATIVO | W74: VISITA_TÉCNICA | X74: AA00D862 | Y74: TIPO IV ESPECIAL | Z74: AEREO | AA74: ROBLEDO DIAZ ANDRES FELIPE | AB74: 1 | AC74: 0 | AD74: =IF(W74="SOPORTE_TELEFÓNICO",'BASE LIQUIDACION REDEBAN 2025'!$B$19,IF(W74="ENVÍO",'BASE LIQUIDACION REDEBAN 2025'!$C$2,IF(Y74="TIPO I",'BASE LIQUIDACION REDEBAN 2025'!$C$2,IF(Y74="TIPO II",'BASE LIQUIDACION REDEBAN 2025'!$C$3,IF(Y74="TIPO III",'BASE LIQUIDACION REDEBAN 2025'!$C$4,IF(Y74="TIPO IV",'BASE LIQUIDACION REDEBAN 2025'!$C$5,IF(Z74="AEREO",'BASE LIQUIDACION REDEBAN 2025'!$B$6,'BASE LIQUIDACION REDEBAN 2025'!$C$5))))))) -> 988462.96 | AE74: =IF(OR(W74="SOPORTE_TELEFÓNICO",W74="ENVÍO"),0,IF(Y74="TIPO I",'BASE LIQUIDACION REDEBAN 2025'!$B$10,IF(Y74="TIPO II",'BASE LIQUIDACION REDEBAN 2025'!$B$11,IF(Y74="TIPO III",'BASE LIQUIDACION REDEBAN 2025'!$B$12,'BASE LIQUIDACION REDEBAN 2025'!$B$13)))) -> 196536.53 | AF74: =IF(OR(W74="SOPORTE_TELEFÓNICO",W74="ENVÍO"),AD74,(AD74*AB74+AE74*AC74)) -> 988462.96
A75: BUCARAMANGA | B75: =VLOOKUP(A75,'CENTRO DE COSTOS'!A:D,4,FALSE) -> MIGUEL JULIÁN HERNÁNDEZ GUARÍN | C75: =VLOOKUP(A75,'CENTRO DE COSTOS'!A:D,2,FALSE) -> 0004-0008 | D75: 68001 | E75: 2543350 | F75: 80422 | G75: INCIDENTE | H75: SANTANDER | I75: BUCARAMANGA | J75: BARRIO LAS AMERICAS BUCARAMANGA | K75: REDEBAN | L75: FO-25-1320045 | M75: 45871.394 | N75: 45871.513 | O75: NO | P75: SOFTWARE | Q75: COMUNICACION | R75: PARAMETROS DE CONFIGURACION EN POS | S75: CB UNO A UNO | U75: CERRADO | V75: 02/08/2025 01-08 SE ESCALA PARA VISITA. LLAMAR ANTES DE VISITAR, CONFIRMAR FALLA Y DATOS | 02/08/2025 SE REALIZA VISITA AL COMERCIO CB, SE VALIDA Y LA CLIENTE COMENTA QUE EL EQUIPO NO ENCENDIA HACE UNOS DIAS POR FALTA DE CARGA EN LA BATERIA, SE LE COMENTA QUE PASO DEBE SEGUIR PARA QUE NO SE LE PRESENTE DICHO INCONVENIENTE, SE FORMATEA Y SE DESCARGA SISTEMA OPERATIVO Y VERSION, SE CONFIGURA Y SE HACEN PRUEBAS DEJANDO TODO OK | W75: VISITA_TÉCNICA | X75: LDZZZ368 | Y75: TIPO I | Z75: TERRESTRE | AA75: GONZALEZ ESTUPIÑAN YEISON WALTER ANTONIO | AB75: 1 | AC75: 0 | AD75: =IF(W75="SOPORTE_TELEFÓNICO",'BASE LIQUIDACION REDEBAN 2025'!$B$19,IF(W75="ENVÍO",'BASE LIQUIDACION REDEBAN 2025'!$C$2,IF(Y75="TIPO I",'BASE LIQUIDACION REDEBAN 2025'!$C$2,IF(Y75="TIPO II",'BASE LIQUIDACION REDEBAN 2025'!$C$3,IF(Y75="TIPO III",'BASE LIQUIDACION REDEBAN 2025'!$C$4,IF(Y75="TIPO IV",'BASE LIQUIDACION REDEBAN 2025'!$C$5,IF(Z75="AEREO",'BASE LIQUIDACION REDEBAN 2025'!$B$6,'BASE LIQUIDACION REDEBAN 2025'!$C$5))))))) -> 65960.072 | AE75: =IF(OR(W75="SOPORTE_TELEFÓNICO",W75="ENVÍO"),0,IF(Y75="TIPO I",'BASE LIQUIDACION REDEBAN 2025'!$B$10,IF(Y75="TIPO II",'BASE LIQUIDACION REDEBAN 2025'!$B$11,IF(Y75="TIPO III",'BASE LIQUIDACION REDEBAN 2025'!$B$12,'BASE LIQUIDACION REDEBAN 2025'!$B$13)))) -> 75096.394 | AF75: =IF(OR(W75="SOPORTE_TELEFÓNICO",W75="ENVÍO"),AD75,(AD75*AB75+AE75*AC75)) -> 65960.072
A76: MEDELLIN | B76: =VLOOKUP(A76,'CENTRO DE COSTOS'!A:D,4,FALSE) -> JUAN SEBASTIÁN RÍOS CASTRILLÓN | C76: =VLOOKUP(A76,'CENTRO DE COSTOS'!A:D,2,FALSE) -> 0004-0005 | D76: 5001 | E76: 2542753 | F76: 71465 | G76: INCIDENTE | H76: ANTIOQUIA | I76: MEDELLIN | J76: PTM MEDELLIN GRANERO EL PANA | K76: REDEBAN | L76: FO-25-1319503 | M76: 45871.333 | N76: 45871.515 | O76: NO | P76: HARDWARE | Q76: NO ENCIENDE SE REINICIA | R76: FUENTE PODER AVERIADA | S76: AGREGADOR | U76: CERRADO | V76: 02/08/2025 01-08 SE ESCALA PARA VISITA. LLAMAR ANTES DE VISITAR, CONFIRMAR FALLA Y DATOS | 02/08/2025 CAMBIO DE FUENTE PODER MALA OK PRUEBAS OK NO TELECARGA | W76: VISITA_TÉCNICA | X76: UV00B367-NN00E772 | Y76: TIPO I | Z76: TERRESTRE | AA76: PAREJA ECHAVARRIA JHON DAVID | AB76: 1 | AC76: 0 | AD76: =IF(W76="SOPORTE_TELEFÓNICO",'BASE LIQUIDACION REDEBAN 2025'!$B$19,IF(W76="ENVÍO",'BASE LIQUIDACION REDEBAN 2025'!$C$2,IF(Y76="TIPO I",'BASE LIQUIDACION REDEBAN 2025'!$C$2,IF(Y76="TIPO II",'BASE LIQUIDACION REDEBAN 2025'!$C$3,IF(Y76="TIPO III",'BASE LIQUIDACION REDEBAN 2025'!$C$4,IF(Y76="TIPO IV",'BASE LIQUIDACION REDEBAN 2025'!$C$5,IF(Z76="AEREO",'BASE LIQUIDACION REDEBAN 2025'!$B$6,'BASE LIQUIDACION REDEBAN 2025'!$C$5))))))) -> 65960.072 | AE76: =IF(OR(W76="SOPORTE_TELEFÓNICO",W76="ENVÍO"),0,IF(Y76="TIPO I",'BASE LIQUIDACION REDEBAN 2025'!$B$10,IF(Y76="TIPO II",'BASE LIQUIDACION REDEBAN 2025'!$B$11,IF(Y76="TIPO III",'BASE LIQUIDACION REDEBAN 2025'!$B$12,'BASE LIQUIDACION REDEBAN 2025'!$B$13)))) -> 75096.394 | AF76: =IF(OR(W76="SOPORTE_TELEFÓNICO",W76="ENVÍO"),AD76,(AD76*AB76+AE76*AC76)) -> 65960.072
A77: MEDELLIN | B77: =VLOOKUP(A77,'CENTRO DE COSTOS'!A:D,4,FALSE) -> JUAN SEBASTIÁN RÍOS CASTRILLÓN | C77: =VLOOKUP(A77,'CENTRO DE COSTOS'!A:D,2,FALSE) -> 0004-0005 | D77: 5001 | E77: 2543263 | F77: 22446 | G77: INCIDENTE | H77: ANTIOQUIA | I77: MEDELLIN | J77: COMCARD MED MANRIQUE GARFIELD | K77: REDEBAN | L77: FO-25-1320040 | M77: 45871.394 | N77: 45871.528 | O77: NO | P77: SOFTWARE | Q77: COMUNICACION | R77: PARAMETROS DE CONFIGURACION EN POS | S77: AGREGADOR | U77: CERRADO | V77: 02/08/2025 01-08 SE ESCALA PARA VISITA. LLAMAR ANTES DE VISITAR, CONFIRMAR FALLA Y DATOS | 02/08/2025 SE REALIZA CONFIGURACIÓN DE PARÁMETROS DESCONTINUADOS POR REVERSO PENDIENTE PRUEBAS OK | W77: VISITA_TÉCNICA | X77: AIZZZ292-TRZZZ949 | Y77: TIPO I | Z77: TERRESTRE | AA77: PAREJA ECHAVARRIA JHON DAVID | AB77: 1 | AC77: 0 | AD77: =IF(W77="SOPORTE_TELEFÓNICO",'BASE LIQUIDACION REDEBAN 2025'!$B$19,IF(W77="ENVÍO",'BASE LIQUIDACION REDEBAN 2025'!$C$2,IF(Y77="TIPO I",'BASE LIQUIDACION REDEBAN 2025'!$C$2,IF(Y77="TIPO II",'BASE LIQUIDACION REDEBAN 2025'!$C$3,IF(Y77="TIPO III",'BASE LIQUIDACION REDEBAN 2025'!$C$4,IF(Y77="TIPO IV",'BASE LIQUIDACION REDEBAN 2025'!$C$5,IF(Z77="AEREO",'BASE LIQUIDACION REDEBAN 2025'!$B$6,'BASE LIQUIDACION REDEBAN 2025'!$C$5))))))) -> 65960.072 | AE77: =IF(OR(W77="SOPORTE_TELEFÓNICO",W77="ENVÍO"),0,IF(Y77="TIPO I",'BASE LIQUIDACION REDEBAN 2025'!$B$10,IF(Y77="TIPO II",'BASE LIQUIDACION REDEBAN 2025'!$B$11,IF(Y77="TIPO III",'BASE LIQUIDACION REDEBAN 2025'!$B$12,'BASE LIQUIDACION REDEBAN 2025'!$B$13)))) -> 75096.394 | AF77: =IF(OR(W77="SOPORTE_TELEFÓNICO",W77="ENVÍO"),AD77,(AD77*AB77+AE77*AC77)) -> 65960.072
A78: BOGOTA | B78: =VLOOKUP(A78,'CENTRO DE COSTOS'!A:D,4,FALSE) -> WILLIAM ASDRUBAL ROZO ROZO | C78: =VLOOKUP(A78,'CENTRO DE COSTOS'!A:D,2,FALSE) -> 0004-0004 | D78: 11001 | E78: 2542521 | F78: 62630 | G78: INCIDENTE | H78: CUNDINAMARCA | I78: BOGOTA | J78: PAGAFACIL SAN ANDRESITO SAN | K78: REDEBAN | L78: FO-25-1319525 | M78: 45871.333 | N78: 45871.531 | O78: NO | P78: SOFTWARE | Q78: ACTUALIZACION | R78: VERSION CARGA SO VR | S78: ROBUSTO | U78: CERRADO | V78: 02/08/2025 01-08 SE ESCALA PARA VISITA. LLAMAR ANTES DE VISITAR, CONFIRMAR FALLA Y DATOS | 02/08/2025 ACTUALIZACIÓN DE DATAFONO PRUEBAS OK | W78: VISITA_TÉCNICA | X78: FUA0P414 | Y78: TIPO I | Z78: TERRESTRE | AA78: GOMEZ VEGA DAVID SNEYDER | AB78: 1 | AC78: 0 | AD78: =IF(W78="SOPORTE_TELEFÓNICO",'BASE LIQUIDACION REDEBAN 2025'!$B$19,IF(W78="ENVÍO",'BASE LIQUIDACION REDEBAN 2025'!$C$2,IF(Y78="TIPO I",'BASE LIQUIDACION REDEBAN 2025'!$C$2,IF(Y78="TIPO II",'BASE LIQUIDACION REDEBAN 2025'!$C$3,IF(Y78="TIPO III",'BASE LIQUIDACION REDEBAN 2025'!$C$4,IF(Y78="TIPO IV",'BASE LIQUIDACION REDEBAN 2025'!$C$5,IF(Z78="AEREO",'BASE LIQUIDACION REDEBAN 2025'!$B$6,'BASE LIQUIDACION REDEBAN 2025'!$C$5))))))) -> 65960.072 | AE78: =IF(OR(W78="SOPORTE_TELEFÓNICO",W78="ENVÍO"),0,IF(Y78="TIPO I",'BASE LIQUIDACION REDEBAN 2025'!$B$10,IF(Y78="TIPO II",'BASE LIQUIDACION REDEBAN 2025'!$B$11,IF(Y78="TIPO III",'BASE LIQUIDACION REDEBAN 2025'!$B$12,'BASE LIQUIDACION REDEBAN 2025'!$B$13)))) -> 75096.394 | AF78: =IF(OR(W78="SOPORTE_TELEFÓNICO",W78="ENVÍO"),AD78,(AD78*AB78+AE78*AC78)) -> 65960.072
A79: PASTO | B79: =VLOOKUP(A79,'CENTRO DE COSTOS'!A:D,4,FALSE) -> DIEGO FERNANDO HENAO CARDONA | C79: =VLOOKUP(A79,'CENTRO DE COSTOS'!A:D,2,FALSE) -> 0004-0003 | D79: 52001 | E79: 2543327 | F79: 25208 | G79: INCIDENTE | H79: NARIÑO | I79: PASTO | J79: MULTIPAGAS UNICENTRO PASTO | K79: REDEBAN | L79: FO-25-1320061 | M79: 45871.378 | N79: 45871.532 | O79: NO | P79: HARDWARE | Q79: IMPRESION | R79: NO IMPRIME UNO O VARIOS CARACTERES | S79: ROBUSTO | U79: CERRADO | V79: 02/08/2025 01-08 SE ESCALA PARA VISITA. LLAMAR ANTES DE VISITAR, CONFIRMAR FALLA Y DATOS | 02/08/2025 SE VISITA CB. SE REALIZA CAMBIO DE EQUIPO POR IMPRESORA DAÑADA, NO IMPRIME ALGUNOS CARACTERES. SE REALIZAN PRUEBAS TX EXITOSAS. QUEDA OPERATIVO | W79: VISITA_TÉCNICA | X79: A000M364 | Y79: TIPO I | Z79: TERRESTRE | AA79: CASTILLO HERRERA ALEX RICARDO | AB79: 1 | AC79: 0 | AD79: =IF(W79="SOPORTE_TELEFÓNICO",'BASE LIQUIDACION REDEBAN 2025'!$B$19,IF(W79="ENVÍO",'BASE LIQUIDACION REDEBAN 2025'!$C$2,IF(Y79="TIPO I",'BASE LIQUIDACION REDEBAN 2025'!$C$2,IF(Y79="TIPO II",'BASE LIQUIDACION REDEBAN 2025'!$C$3,IF(Y79="TIPO III",'BASE LIQUIDACION REDEBAN 2025'!$C$4,IF(Y79="TIPO IV",'BASE LIQUIDACION REDEBAN 2025'!$C$5,IF(Z79="AEREO",'BASE LIQUIDACION REDEBAN 2025'!$B$6,'BASE LIQUIDACION REDEBAN 2025'!$C$5))))))) -> 65960.072 | AE79: =IF(OR(W79="SOPORTE_TELEFÓNICO",W79="ENVÍO"),0,IF(Y79="TIPO I",'BASE LIQUIDACION REDEBAN 2025'!$B$10,IF(Y79="TIPO II",'BASE LIQUIDACION REDEBAN 2025'!$B$11,IF(Y79="TIPO III",'BASE LIQUIDACION REDEBAN 2025'!$B$12,'BASE LIQUIDACION REDEBAN 2025'!$B$13)))) -> 75096.394 | AF79: =IF(OR(W79="SOPORTE_TELEFÓNICO",W79="ENVÍO"),AD79,(AD79*AB79+AE79*AC79)) -> 65960.072
A80: PEREIRA | B80: =VLOOKUP(A80,'CENTRO DE COSTOS'!A:D,4,FALSE) -> DIEGO FERNANDO HENAO CARDONA | C80: =VLOOKUP(A80,'CENTRO DE COSTOS'!A:D,2,FALSE) -> 0004-0002 | D80: 66170 | E80: 2542299 | F80: 19852 | G80: INCIDENTE | H80: RISARALDA | I80: DOSQUEBRADAS | J80: REVAL DOSQUEBRADAS | K80: REDEBAN | L80: FO-25-1319530 | M80: 45871.333 | N80: 45871.533 | O80: NO | P80: SOFTWARE | Q80: CIERRE | R80: CIERRE NO HABILITADO | S80: ROBUSTO | U80: CERRADO | V80: 02/08/2025 01-08 SE ESCALA PARA VISITA. LLAMAR ANTES DE VISITAR, CONFIRMAR FALLA Y DATOS | 02/08/2025 VISITAMOS COMERCIO EL DATÁFONO SE DEMORA EN REALIZAR EL CIERRE YA QUE ACUMULA DÍAS PASADOS, FORMATEAMOS EL DATAFONO LO CONFIGURAMOS NUEVAMENTE LO INICIALIZAMOS Y REALIZAMOS PRUEBAS OK. | W80: VISITA_TÉCNICA | X80: AAAAL098 | Y80: TIPO I | Z80: TERRESTRE | AA80: ARROYAVE CANO MANUEL GUILLERMO | AB80: 1 | AC80: 0 | AD80: =IF(W80="SOPORTE_TELEFÓNICO",'BASE LIQUIDACION REDEBAN 2025'!$B$19,IF(W80="ENVÍO",'BASE LIQUIDACION REDEBAN 2025'!$C$2,IF(Y80="TIPO I",'BASE LIQUIDACION REDEBAN 2025'!$C$2,IF(Y80="TIPO II",'BASE LIQUIDACION REDEBAN 2025'!$C$3,IF(Y80="TIPO III",'BASE LIQUIDACION REDEBAN 2025'!$C$4,IF(Y80="TIPO IV",'BASE LIQUIDACION REDEBAN 2025'!$C$5,IF(Z80="AEREO",'BASE LIQUIDACION REDEBAN 2025'!$B$6,'BASE LIQUIDACION REDEBAN 2025'!$C$5))))))) -> 65960.072 | AE80: =IF(OR(W80="SOPORTE_TELEFÓNICO",W80="ENVÍO"),0,IF(Y80="TIPO I",'BASE LIQUIDACION REDEBAN 2025'!$B$10,IF(Y80="TIPO II",'BASE LIQUIDACION REDEBAN 2025'!$B$11,IF(Y80="TIPO III",'BASE LIQUIDACION REDEBAN 2025'!$B$12,'BASE LIQUIDACION REDEBAN 2025'!$B$13)))) -> 75096.394 | AF80: =IF(OR(W80="SOPORTE_TELEFÓNICO",W80="ENVÍO"),AD80,(AD80*AB80+AE80*AC80)) -> 65960.072
A81: VALLEDUPAR | B81: =VLOOKUP(A81,'CENTRO DE COSTOS'!A:D,4,FALSE) -> JOSE MAURICIO HERNANDEZ ROJAS | C81: =VLOOKUP(A81,'CENTRO DE COSTOS'!A:D,2,FALSE) -> 0004-0001 | D81: 20013 | E81: 2541457 | F81: 10637 | G81: INCIDENTE | H81: CESAR | I81: AGUSTIN CODAZZI | J81: AGUSTIN CODAZZI III - CESAR | K81: REDEBAN | L81: FO-25-1317916 | M81: 45870.638 | N81: 45871.536 | O81: NO | P81: HARDWARE | Q81: SE REINICIA | R81: DAÑO POS | S81: CB UNO A UNO | U81: CERRADO | V81: 01/08/2025 01-08 SE ESCALA PARA VISITA. LLAMAR ANTES DE VISITAR, CONFIRMAR FALLA Y DATOS | 02/08/2025 BUENOS DÍAS SE VISITA CB Y SE ENCUENTRA FALLA EN EQUIPO 3500 QUE SE REINICIA Y TAMBIÉN TIENE LA TECLA HACIA ARRIBA MUY DURA, SE PROCEDE A HACER EL CAMBIO Y SE DEJA TODO OK SE HACEN PRUEBAS Y SE DEJA CB FUNCIONANDO. | W81: VISITA_TÉCNICA | X81: IZ2ZZ167 | Y81: TIPO II | Z81: TERRESTRE | AA81: BENITEZ CARVAJAL ALVARO JAVIER | AB81: 1 | AC81: 0 | AD81: =IF(W81="SOPORTE_TELEFÓNICO",'BASE LIQUIDACION REDEBAN 2025'!$B$19,IF(W81="ENVÍO",'BASE LIQUIDACION REDEBAN 2025'!$C$2,IF(Y81="TIPO I",'BASE LIQUIDACION REDEBAN 2025'!$C$2,IF(Y81="TIPO II",'BASE LIQUIDACION REDEBAN 2025'!$C$3,IF(Y81="TIPO III",'BASE LIQUIDACION REDEBAN 2025'!$C$4,IF(Y81="TIPO IV",'BASE LIQUIDACION REDEBAN 2025'!$C$5,IF(Z81="AEREO",'BASE LIQUIDACION REDEBAN 2025'!$B$6,'BASE LIQUIDACION REDEBAN 2025'!$C$5))))))) -> 144967.87 | AE81: =IF(OR(W81="SOPORTE_TELEFÓNICO",W81="ENVÍO"),0,IF(Y81="TIPO I",'BASE LIQUIDACION REDEBAN 2025'!$B$10,IF(Y81="TIPO II",'BASE LIQUIDACION REDEBAN 2025'!$B$11,IF(Y81="TIPO III",'BASE LIQUIDACION REDEBAN 2025'!$B$12,'BASE LIQUIDACION REDEBAN 2025'!$B$13)))) -> 140395.63 | AF81: =IF(OR(W81="SOPORTE_TELEFÓNICO",W81="ENVÍO"),AD81,(AD81*AB81+AE81*AC81)) -> 144967.87
A82: MEDELLIN | B82: =VLOOKUP(A82,'CENTRO DE COSTOS'!A:D,4,FALSE) -> JUAN SEBASTIÁN RÍOS CASTRILLÓN | C82: =VLOOKUP(A82,'CENTRO DE COSTOS'!A:D,2,FALSE) -> 0004-0005 | D82: 5212 | E82: 2540943 | F82: 40686 | G82: INCIDENTE | H82: ANTIOQUIA | I82: COPACABANA | J82: PTM COPACABANA SMOKESHOP | K82: REDEBAN | L82: FO-25-1317819 | M82: 45870.622 | N82: 45871.542 | O82: NO | P82: HARDWARE | Q82: LECTOR DE BARRAS | R82: FORMATO INVALIDO LECTOR DAÑADO | S82: AGREGADOR | U82: CERRADO | V82: 01/08/2025 01-08 SE ESCALA PARA VISITA. LLAMAR ANTES DE VISITAR, CONFIRMAR FALLA Y DATOS | 02/08/2025 SE REVISA LECTORA Y NO LEER SE RECONFIGURA Y EL FALLO CONTINÚA SE CAMBIE LECTORA SE REALIZAN PRUEBAS EXITOSAS SERVICIO OPERATIVO OK | W82: VISITA_TÉCNICA | X82: AA0NZ736 | Y82: TIPO I | Z82: TERRESTRE | AA82: ZAPATA LOPEZ EDWARD ASDRUBAL | AB82: 1 | AC82: 0 | AD82: =IF(W82="SOPORTE_TELEFÓNICO",'BASE LIQUIDACION REDEBAN 2025'!$B$19,IF(W82="ENVÍO",'BASE LIQUIDACION REDEBAN 2025'!$C$2,IF(Y82="TIPO I",'BASE LIQUIDACION REDEBAN 2025'!$C$2,IF(Y82="TIPO II",'BASE LIQUIDACION REDEBAN 2025'!$C$3,IF(Y82="TIPO III",'BASE LIQUIDACION REDEBAN 2025'!$C$4,IF(Y82="TIPO IV",'BASE LIQUIDACION REDEBAN 2025'!$C$5,IF(Z82="AEREO",'BASE LIQUIDACION REDEBAN 2025'!$B$6,'BASE LIQUIDACION REDEBAN 2025'!$C$5))))))) -> 65960.072 | AE82: =IF(OR(W82="SOPORTE_TELEFÓNICO",W82="ENVÍO"),0,IF(Y82="TIPO I",'BASE LIQUIDACION REDEBAN 2025'!$B$10,IF(Y82="TIPO II",'BASE LIQUIDACION REDEBAN 2025'!$B$11,IF(Y82="TIPO III",'BASE LIQUIDACION REDEBAN 2025'!$B$12,'BASE LIQUIDACION REDEBAN 2025'!$B$13)))) -> 75096.394 | AF82: =IF(OR(W82="SOPORTE_TELEFÓNICO",W82="ENVÍO"),AD82,(AD82*AB82+AE82*AC82)) -> 65960.072
A83: TUNJA | B83: =VLOOKUP(A83,'CENTRO DE COSTOS'!A:D,4,FALSE) -> MIGUEL JULIÁN HERNÁNDEZ GUARÍN | C83: =VLOOKUP(A83,'CENTRO DE COSTOS'!A:D,2,FALSE) -> 0004-0008 | D83: 15407 | E83: 2539458 | F83: 43303 | G83: INCIDENTE | H83: BOYACA | I83: VILLA DE LEYVA | J83: DISTRICOL LAS EFE SAS | K83: REDEBAN | L83: FO-25-1316397 | M83: 45870.471 | N83: 45871.543 | O83: NO | P83: HARDWARE | Q83: LECTOR DE TARJETAS | R83: DAÑO POS | S83: AGREGADOR | U83: CERRADO | V83: 01/08/2025 01-08 SE ESCALA PARA VISITA. LLAMAR ANTES DE VISITAR, CONFIRMAR FALLA Y DATOS | 02/08/2025 SE REALIZA CAMBIO DE EQUIPO POR DAÑO LECTOR CHIP DEJANDO PRUEBAS OK SIN TELECARGA NO AUTORIZADA | W83: VISITA_TÉCNICA | X83: ABAZZ464 | Y83: TIPO II | Z83: TERRESTRE | AA83: ALVARADO MORENO CRISTHIAN | AB83: 1 | AC83: 0 | AD83: =IF(W83="SOPORTE_TELEFÓNICO",'BASE LIQUIDACION REDEBAN 2025'!$B$19,IF(W83="ENVÍO",'BASE LIQUIDACION REDEBAN 2025'!$C$2,IF(Y83="TIPO I",'BASE LIQUIDACION REDEBAN 2025'!$C$2,IF(Y83="TIPO II",'BASE LIQUIDACION REDEBAN 2025'!$C$3,IF(Y83="TIPO III",'BASE LIQUIDACION REDEBAN 2025'!$C$4,IF(Y83="TIPO IV",'BASE LIQUIDACION REDEBAN 2025'!$C$5,IF(Z83="AEREO",'BASE LIQUIDACION REDEBAN 2025'!$B$6,'BASE LIQUIDACION REDEBAN 2025'!$C$5))))))) -> 144967.87 | AE83: =IF(OR(W83="SOPORTE_TELEFÓNICO",W83="ENVÍO"),0,IF(Y83="TIPO I",'BASE LIQUIDACION REDEBAN 2025'!$B$10,IF(Y83="TIPO II",'BASE LIQUIDACION REDEBAN 2025'!$B$11,IF(Y83="TIPO III",'BASE LIQUIDACION REDEBAN 2025'!$B$12,'BASE LIQUIDACION REDEBAN 2025'!$B$13)))) -> 140395.63 | AF83: =IF(OR(W83="SOPORTE_TELEFÓNICO",W83="ENVÍO"),AD83,(AD83*AB83+AE83*AC83)) -> 144967.87
A84: MEDELLIN | B84: =VLOOKUP(A84,'CENTRO DE COSTOS'!A:D,4,FALSE) -> JUAN SEBASTIÁN RÍOS CASTRILLÓN | C84: =VLOOKUP(A84,'CENTRO DE COSTOS'!A:D,2,FALSE) -> 0004-0005 | D84: 5615 | E84: 2537757 | F84: 12414 | G84: INCIDENTE | H84: ANTIOQUIA | I84: RIONEGRO | J84: BARRIO EL PORVENIR - RIONEGRO | K84: REDEBAN | L84: FO-25-1315140 | M84: 45870.381 | N84: 45871.547 | O84: NO | P84: HARDWARE | Q84: IMPRESION | R84: NO IMPRIME UNO O VARIOS CARACTERES | S84: CB UNO A UNO | U84: CERRADO | V84: 01/08/2025 01-08 SE ESCALA PARA VISITA. LLAMAR ANTES DE VISITAR, CONFIRMAR FALLA Y DATOS | 02/08/2025 SE REALIZA CAMBIO DE EQUIPO PORQ NO ESTA IMPRIMIENDO VARIOS CARACTERES Y TECLADO BORROSO | W84: VISITA_TÉCNICA | X84: IZ8ZZ970 - JAAAR106 | Y84: TIPO II | Z84: TERRESTRE | AA84: HERNANDEZ CHAVARRIA JUAN CAMILO | AB84: 1 | AC84: 0 | AD84: =IF(W84="SOPORTE_TELEFÓNICO",'BASE LIQUIDACION REDEBAN 2025'!$B$19,IF(W84="ENVÍO",'BASE LIQUIDACION REDEBAN 2025'!$C$2,IF(Y84="TIPO I",'BASE LIQUIDACION REDEBAN 2025'!$C$2,IF(Y84="TIPO II",'BASE LIQUIDACION REDEBAN 2025'!$C$3,IF(Y84="TIPO III",'BASE LIQUIDACION REDEBAN 2025'!$C$4,IF(Y84="TIPO IV",'BASE LIQUIDACION REDEBAN 2025'!$C$5,IF(Z84="AEREO",'BASE LIQUIDACION REDEBAN 2025'!$B$6,'BASE LIQUIDACION REDEBAN 2025'!$C$5))))))) -> 144967.87 | AE84: =IF(OR(W84="SOPORTE_TELEFÓNICO",W84="ENVÍO"),0,IF(Y84="TIPO I",'BASE LIQUIDACION REDEBAN 2025'!$B$10,IF(Y84="TIPO II",'BASE LIQUIDACION REDEBAN 2025'!$B$11,IF(Y84="TIPO III",'BASE LIQUIDACION REDEBAN 2025'!$B$12,'BASE LIQUIDACION REDEBAN 2025'!$B$13)))) -> 140395.63 | AF84: =IF(OR(W84="SOPORTE_TELEFÓNICO",W84="ENVÍO"),AD84,(AD84*AB84+AE84*AC84)) -> 144967.87
... A95: CALI | B95: =VLOOKUP(A95,'CENTRO DE COSTOS'!A:D,4,FALSE) -> DIEGO FERNANDO HENAO CARDONA | C95: =VLOOKUP(A95,'CENTRO DE COSTOS'!A:D,2,FALSE) -> 0004-0003 | D95: 76001 | E95: 2543184 | F95: 80440 | G95: INCIDENTE | H95: VALLE DEL CAUCA | I95: CALI | J95: BARRIO MODELO CALI | K95: REDEBAN | L95: FO-25-1320026 | M95: 45871.412 | N95: 45872.379 | O95: NO | P95: HARDWARE | Q95: IMPRESION | R95: DAÑO POS | S95: CB UNO A UNO | U95: CERRADO | V95: 02/08/2025 01-08 SE ESCALA PARA VISITA. LLAMAR ANTES DE VISITAR, CONFIRMAR FALLA Y DATOS | 02/08/2025 SE VISITA EL COMERCIO, SE ENCUENTRA DATAFONO NO IMPRIME LAS TRANSACCIONES, SE REVISA CONEXIONES ESTA FLOJO LA BATERÍA SE ACOMODA RESOLVIENDO EL PROBLEMA, PRUEBAS DE IMPRESIÓN OK, TELECARGA TRNA | W95: VISITA_TÉCNICA | X95: SAZZZ793 | Y95: TIPO I | Z95: TERRESTRE | AA95: HERRERA MONAR GEOVANNY | AB95: 1 | AC95: 0 | AD95: =IF(W95="SOPORTE_TELEFÓNICO",'BASE LIQUIDACION REDEBAN 2025'!$B$19,IF(W95="ENVÍO",'BASE LIQUIDACION REDEBAN 2025'!$C$2,IF(Y95="TIPO I",'BASE LIQUIDACION REDEBAN 2025'!$C$2,IF(Y95="TIPO II",'BASE LIQUIDACION REDEBAN 2025'!$C$3,IF(Y95="TIPO III",'BASE LIQUIDACION REDEBAN 2025'!$C$4,IF(Y95="TIPO IV",'BASE LIQUIDACION REDEBAN 2025'!$C$5,IF(Z95="AEREO",'BASE LIQUIDACION REDEBAN 2025'!$B$6,'BASE LIQUIDACION REDEBAN 2025'!$C$5))))))) -> 65960.072 | AE95: =IF(OR(W95="SOPORTE_TELEFÓNICO",W95="ENVÍO"),0,IF(Y95="TIPO I",'BASE LIQUIDACION REDEBAN 2025'!$B$10,IF(Y95="TIPO II",'BASE LIQUIDACION REDEBAN 2025'!$B$11,IF(Y95="TIPO III",'BASE LIQUIDACION REDEBAN 2025'!$B$12,'BASE LIQUIDACION REDEBAN 2025'!$B$13)))) -> 75096.394 | AF95: =IF(OR(W95="SOPORTE_TELEFÓNICO",W95="ENVÍO"),AD95,(AD95*AB95+AE95*AC95)) -> 65960.072
A96: VILLAVICENCIO | B96: =VLOOKUP(A96,'CENTRO DE COSTOS'!A:D,4,FALSE) -> KEVIN ALEXIS CORZO BUSTOS | C96: =VLOOKUP(A96,'CENTRO DE COSTOS'!A:D,2,FALSE) -> 0004-0007 | D96: 50001 | E96: 2543503 | F96: 70392 | G96: INCIDENTE | H96: META | I96: VILLAVICENCIO | J96: VILLAVICENCIO CENTRO II | K96: REDEBAN | L96: FO-25-1320500 | M96: 45871.425 | N96: 45872.381 | O96: NO | P96: HARDWARE | Q96: LECTOR DE BARRAS | R96: FORMATO INVALIDO LECTOR DAÑADO | S96: ROBUSTO | U96: CERRADO | V96: 02/08/2025 01-08 SE ESCALA PARA VISITA. LLAMAR ANTES DE VISITAR, CONFIRMAR FALLA Y DATOS | 02/08/2025 SE REALIZA CONTACTO TELEFÓNICO CON LA SEÑORA PILAR LA CUAL INDICA QUE REQUIERE CAMBIO DE LOS LECTORA POR TECNOLOGÍA SYMBOL, SE LE INFORMA QUE NO HAY DISPONIBILIDAD EN EL MOMENTO A LO QUE INDICA QUE NO ES NECESARIO VISITA | W96: SOPORTE_TELEFÓNICO | X96: 0 | Y96: TIPO I | Z96: TERRESTRE | AA96: PEDREROS CONTRERAS MICHAEL STEVENS | AB96: 0 | AC96: 0 | AD96: =IF(W96="SOPORTE_TELEFÓNICO",'BASE LIQUIDACION REDEBAN 2025'!$B$19,IF(W96="ENVÍO",'BASE LIQUIDACION REDEBAN 2025'!$C$2,IF(Y96="TIPO I",'BASE LIQUIDACION REDEBAN 2025'!$C$2,IF(Y96="TIPO II",'BASE LIQUIDACION REDEBAN 2025'!$C$3,IF(Y96="TIPO III",'BASE LIQUIDACION REDEBAN 2025'!$C$4,IF(Y96="TIPO IV",'BASE LIQUIDACION REDEBAN 2025'!$C$5,IF(Z96="AEREO",'BASE LIQUIDACION REDEBAN 2025'!$B$6,'BASE LIQUIDACION REDEBAN 2025'!$C$5))))))) -> 41241.08 | AE96: =IF(OR(W96="SOPORTE_TELEFÓNICO",W96="ENVÍO"),0,IF(Y96="TIPO I",'BASE LIQUIDACION REDEBAN 2025'!$B$10,IF(Y96="TIPO II",'BASE LIQUIDACION REDEBAN 2025'!$B$11,IF(Y96="TIPO III",'BASE LIQUIDACION REDEBAN 2025'!$B$12,'BASE LIQUIDACION REDEBAN 2025'!$B$13)))) -> 0 | AF96: =IF(OR(W96="SOPORTE_TELEFÓNICO",W96="ENVÍO"),AD96,(AD96*AB96+AE96*AC96)) -> 41241.08
A97: SINCELEJO | B97: =VLOOKUP(A97,'CENTRO DE COSTOS'!A:D,4,FALSE) -> JOSE MAURICIO HERNANDEZ ROJAS | C97: =VLOOKUP(A97,'CENTRO DE COSTOS'!A:D,2,FALSE) -> 0004-0001 | D97: 70215 | E97: 2541436 | F97: 78606 | G97: INCIDENTE | H97: SUCRE | I97: COROZAL | J97: BARRIO SAN MIGUEL COROZAL 2 | K97: REDEBAN | L97: FO-25-1317922 | M97: 45870.636 | N97: 45872.472 | O97: NO | P97: HARDWARE | Q97: LECTOR DE BARRAS | R97: DAÑO POS | S97: CB UNO A UNO | U97: CERRADO | V97: 01/08/2025 01-08 SE ESCALA PARA VISITA. LLAMAR ANTES DE VISITAR, CONFIRMAR FALLA Y DATOS | 03/08/2025 SE VISITA SITIO SE VERIFICA INFORMACIÓN, SE OBSERVA ESCÁNER CON DAÑO EN EL LENTE, DESPRENDIDO Y DAÑO LA ÓPTICA. SE CAMBIA ESCÁNER, SE REALIZA PRUEBA TRX EXITOSA. | W97: VISITA_TÉCNICA | X97: F1MZZ635 | Y97: TIPO II | Z97: TERRESTRE | AA97: SANTOS GUZMAN CHRISTIAN FELIPE | AB97: 1 | AC97: 0 | AD97: =IF(W97="SOPORTE_TELEFÓNICO",'BASE LIQUIDACION REDEBAN 2025'!$B$19,IF(W97="ENVÍO",'BASE LIQUIDACION REDEBAN 2025'!$C$2,IF(Y97="TIPO I",'BASE LIQUIDACION REDEBAN 2025'!$C$2,IF(Y97="TIPO II",'BASE LIQUIDACION REDEBAN 2025'!$C$3,IF(Y97="TIPO III",'BASE LIQUIDACION REDEBAN 2025'!$C$4,IF(Y97="TIPO IV",'BASE LIQUIDACION REDEBAN 2025'!$C$5,IF(Z97="AEREO",'BASE LIQUIDACION REDEBAN 2025'!$B$6,'BASE LIQUIDACION REDEBAN 2025'!$C$5))))))) -> 144967.87 | AE97: =IF(OR(W97="SOPORTE_TELEFÓNICO",W97="ENVÍO"),0,IF(Y97="TIPO I",'BASE LIQUIDACION REDEBAN 2025'!$B$10,IF(Y97="TIPO II",'BASE LIQUIDACION REDEBAN 2025'!$B$11,IF(Y97="TIPO III",'BASE LIQUIDACION REDEBAN 2025'!$B$12,'BASE LIQUIDACION REDEBAN 2025'!$B$13)))) -> 140395.63 | AF97: =IF(OR(W97="SOPORTE_TELEFÓNICO",W97="ENVÍO"),AD97,(AD97*AB97+AE97*AC97)) -> 144967.87
A98: CARTAGENA | B98: =VLOOKUP(A98,'CENTRO DE COSTOS'!A:D,4,FALSE) -> JOSE MAURICIO HERNANDEZ ROJAS | C98: =VLOOKUP(A98,'CENTRO DE COSTOS'!A:D,2,FALSE) -> 0004-0001 | D98: 13780 | E98: 2534952 | F98: 79421 | G98: INCIDENTE | H98: BOLIVAR | I98: TALAIGUA NUEVO | J98: BARRIO 10 DE ABRIL TALAIGUA NUEVO 1 | K98: REDEBAN | L98: FO-25-1313126 | M98: 45869.647 | N98: 45873.375 | O98: NO | P98: HARDWARE | Q98: ALERT IRRUPTION | R98: ALERT IRRUPTION | S98: CB UNO A UNO | U98: CERRADO | V98: 31/07/2025 31-07 EN COMUNICACION CON EL SEÑOR JAIME RODRIGUEZ AL NUMERO 3002842027, CONFIRMA FALLA, DATOS CORRECTOS. SE ESCALA PARA VISITA | 04/08/2025 SE VISITA COMERCIO POR UNA FALLA, SE HACE CAMBIO DE DATAFONO, CAUSAL A6 ALERT IRRUPTION, SE INSTALA MAGIC BOX DESK/2600, SE DEJA CON LA VERSIÓN 10.3, SE REALIZAN PRUEBAS OK, SE CREA USUARIO Y CONTRASEÑA | W98: VISITA_TÉCNICA | X98: 10XZZ959 | Y98: TIPO IV | Z98: TERRESTRE | AA98: CACERES HERNANDEZ ANDRES | AB98: 1 | AC98: 0 | AD98: =IF(W98="SOPORTE_TELEFÓNICO",'BASE LIQUIDACION REDEBAN 2025'!$B$19,IF(W98="ENVÍO",'BASE LIQUIDACION REDEBAN 2025'!$C$2,IF(Y98="TIPO I",'BASE LIQUIDACION REDEBAN 2025'!$C$2,IF(Y98="TIPO II",'BASE LIQUIDACION REDEBAN 2025'!$C$3,IF(Y98="TIPO III",'BASE LIQUIDACION REDEBAN 2025'!$C$4,IF(Y98="TIPO IV",'BASE LIQUIDACION REDEBAN 2025'!$C$5,IF(Z98="AEREO",'BASE LIQUIDACION REDEBAN 2025'!$B$6,'BASE LIQUIDACION REDEBAN 2025'!$C$5))))))) -> 479588.88 | AE98: =IF(OR(W98="SOPORTE_TELEFÓNICO",W98="ENVÍO"),0,IF(Y98="TIPO I",'BASE LIQUIDACION REDEBAN 2025'!$B$10,IF(Y98="TIPO II",'BASE LIQUIDACION REDEBAN 2025'!$B$11,IF(Y98="TIPO III",'BASE LIQUIDACION REDEBAN 2025'!$B$12,'BASE LIQUIDACION REDEBAN 2025'!$B$13)))) -> 196536.53 | AF98: =IF(OR(W98="SOPORTE_TELEFÓNICO",W98="ENVÍO"),AD98,(AD98*AB98+AE98*AC98)) -> 479588.88
A99: SANTA MARTA | B99: =VLOOKUP(A99,'CENTRO DE COSTOS'!A:D,4,FALSE) -> JOSE MAURICIO HERNANDEZ ROJAS | C99: =VLOOKUP(A99,'CENTRO DE COSTOS'!A:D,2,FALSE) -> 0004-0001 | D99: 47001 | E99: 2543450 | F99: 58669 | G99: INCIDENTE | H99: MAGDALENA | I99: SANTA MARTA | J99: BARRIO ALTOS DE SANTA MARTA SA | K99: REDEBAN | L99: FO-25-1321026 | M99: 45871.497 | N99: 45873.409 | O99: NO | P99: HARDWARE | Q99: IMPRESION | R99: TAPA IMPRESORA | S99: CB UNO A UNO | U99: CERRADO | V99: 02/08/2025 01-08 SE ESCALA PARA VISITA. LLAMAR ANTES DE VISITAR, CONFIRMAR FALLA Y DATOS | 03/08/2025 SE HACE GESTIÓN TELEFÓNICA, EL CLIENTE INFORMA QUE EL DÍA DOMINGO NO ABRE EL CORRESPONSAL, ADEMÁS INFORMA QUE UNA PIEZA INTERNA DEL DATÁFONO SE PARTIÓ Y NO PERMITE EL AJUSTE DE LA TAPA DE LA IMPRESORA, QUE SE LE PROGRAME LA VISITA PARA EL DÍA LUNES 4 DE AGOSTO | 04/08/2025 SE REALIZA LA VISITA SE ENCUENTRA LA TAPA DE LA IMPRESORA PARTIDA, SE PROCEDE A CAMBIARLA, SE REALIZAN PRUEBAS Y TODO OK | W99: VISITA_TÉCNICA | X99: IVZZZ984 | Y99: TIPO I | Z99: TERRESTRE | AA99: THOMAS CAMPO SIGIFREDO SEGUNDO | AB99: 1 | AC99: 0 | AD99: =IF(W99="SOPORTE_TELEFÓNICO",'BASE LIQUIDACION REDEBAN 2025'!$B$19,IF(W99="ENVÍO",'BASE LIQUIDACION REDEBAN 2025'!$C$2,IF(Y99="TIPO I",'BASE LIQUIDACION REDEBAN 2025'!$C$2,IF(Y99="TIPO II",'BASE LIQUIDACION REDEBAN 2025'!$C$3,IF(Y99="TIPO III",'BASE LIQUIDACION REDEBAN 2025'!$C$4,IF(Y99="TIPO IV",'BASE LIQUIDACION REDEBAN 2025'!$C$5,IF(Z99="AEREO",'BASE LIQUIDACION REDEBAN 2025'!$B$6,'BASE LIQUIDACION REDEBAN 2025'!$C$5))))))) -> 65960.072 | AE99: =IF(OR(W99="SOPORTE_TELEFÓNICO",W99="ENVÍO"),0,IF(Y99="TIPO I",'BASE LIQUIDACION REDEBAN 2025'!$B$10,IF(Y99="TIPO II",'BASE LIQUIDACION REDEBAN 2025'!$B$11,IF(Y99="TIPO III",'BASE LIQUIDACION REDEBAN 2025'!$B$12,'BASE LIQUIDACION REDEBAN 2025'!$B$13)))) -> 75096.394 | AF99: =IF(OR(W99="SOPORTE_TELEFÓNICO",W99="ENVÍO"),AD99,(AD99*AB99+AE99*AC99)) -> 65960.072
A100: CALI | B100: =VLOOKUP(A100,'CENTRO DE COSTOS'!A:D,4,FALSE) -> DIEGO FERNANDO HENAO CARDONA | C100: =VLOOKUP(A100,'CENTRO DE COSTOS'!A:D,2,FALSE) -> 0004-0003 | D100: 76001 | E100: 2544464 | F100: 35502 | G100: INCIDENTE | H100: VALLE DEL CAUCA | I100: CALI | J100: DISTRICOL ALMACEN Y AUTOSERVIC | K100: REDEBAN | L100: FO-25-1322989 | M100: 45872.517 | N100: 45873.428 | O100: NO | P100: HARDWARE | Q100: TECLADO | R100: DAÑO POS | S100: AGREGADOR | U100: CERRADO | V100: 03/08/2025 03-08 SE ESCALA PARA VISITA. LLAMAR ANTES DE VISITAR, CONFIRMAR FALLA Y DATOS | 04/08/2025 SE VISITARA EL DIA 4 DE AGOSTO YA QUE REQUIERE CAMNIO DE EQUIPOS | 04/08/2025 SE CAMBIA DATÁFONO YA QUE EL DEL CLIENTE TENIA LAS TECLAS BORROSAS | W100: VISITA_TÉCNICA | X100: GZ000348 | Y100: TIPO I | Z100: TERRESTRE | AA100: CUERO RUIZ JHONNY | AB100: 1 | AC100: 0 | AD100: =IF(W100="SOPORTE_TELEFÓNICO",'BASE LIQUIDACION REDEBAN 2025'!$B$19,IF(W100="ENVÍO",'BASE LIQUIDACION REDEBAN 2025'!$C$2,IF(Y100="TIPO I",'BASE LIQUIDACION REDEBAN 2025'!$C$2,IF(Y100="TIPO II",'BASE LIQUIDACION REDEBAN 2025'!$C$3,IF(Y100="TIPO III",'BASE LIQUIDACION REDEBAN 2025'!$C$4,IF(Y100="TIPO IV",'BASE LIQUIDACION REDEBAN 2025'!$C$5,IF(Z100="AEREO",'BASE LIQUIDACION REDEBAN 2025'!$B$6,'BASE LIQUIDACION REDEBAN 2025'!$C$5))))))) -> 65960.072 | AE100: =IF(OR(W100="SOPORTE_TELEFÓNICO",W100="ENVÍO"),0,IF(Y100="TIPO I",'BASE LIQUIDACION REDEBAN 2025'!$B$10,IF(Y100="TIPO II",'BASE LIQUIDACION REDEBAN 2025'!$B$11,IF(Y100="TIPO III",'BASE LIQUIDACION REDEBAN 2025'!$B$12,'BASE LIQUIDACION REDEBAN 2025'!$B$13)))) -> 75096.394 | AF100: =IF(OR(W100="SOPORTE_TELEFÓNICO",W100="ENVÍO"),AD100,(AD100*AB100+AE100*AC100)) -> 65960.072
A101: VALLEDUPAR | B101: =VLOOKUP(A101,'CENTRO DE COSTOS'!A:D,4,FALSE) -> JOSE MAURICIO HERNANDEZ ROJAS | C101: =VLOOKUP(A101,'CENTRO DE COSTOS'!A:D,2,FALSE) -> 0004-0001 | D101: 20250 | E101: 2532829 | F101: 51294 | G101: INCIDENTE | H101: CESAR | I101: EL PASO | J101: BARRIO DIVINO NINO EL PASO | K101: REDEBAN | L101: FO-25-1311112 | M101: 45869.458 | N101: 45873.471 | O101: NO | P101: HARDWARE | Q101: SE REINICIA | R101: DAÑO POS | S101: CB UNO A UNO | U101: CERRADO | V101: 31/07/2025 31-07 EN COMUNICACION CON EL SEÑOR LUIS PEÑA AL NUMERO 3205042044, CONFIRMA FALLA, DATOS CORRECTOS. SE ESCALA PARA VISITA | 02/08/2025 BUENAS TARDES ME COMUNICO CON EL CLIENTE LUIS PEÑA TELEFONICAMENTE E INDICA QUE NO ATIENDE LOS DIAS SÁBADO. SOLO TRABAJA DE DOMINGOS A VIERNES. | 04/08/2025 BUENOS DÍAS SE HACE VISITA AL CB Y SE ENCUENTRA NOVEDAD QUE EL DATAFONO DE ESTÁ REINICIANDO, SE PROCEDE A CAMBIAR EL EQUIPO Y TAMBIÉN EL PINPAD POR COMPATIBILIDAD, SE HACEN PRUEBAS Y SE DEJA SERVICIO OK. EL SERVICIO FUE GESTIÓNADO EL DIA 02 DE AGOSTO PERO EL CLIENTE VIA TELÉFONICA INFORMÓ QUE SOLO ATENDÍA DE DOMINGO A VIERNES | W101: VISITA_TÉCNICA | X101: BA05Z120 | Y101: TIPO III | Z101: TERRESTRE | AA101: BENITEZ CARVAJAL ALVARO JAVIER | AB101: 1 | AC101: 0 | AD101: =IF(W101="SOPORTE_TELEFÓNICO",'BASE LIQUIDACION REDEBAN 2025'!$B$19,IF(W101="ENVÍO",'BASE LIQUIDACION REDEBAN 2025'!$C$2,IF(Y101="TIPO I",'BASE LIQUIDACION REDEBAN 2025'!$C$2,IF(Y101="TIPO II",'BASE LIQUIDACION REDEBAN 2025'!$C$3,IF(Y101="TIPO III",'BASE LIQUIDACION REDEBAN 2025'!$C$4,IF(Y101="TIPO IV",'BASE LIQUIDACION REDEBAN 2025'!$C$5,IF(Z101="AEREO",'BASE LIQUIDACION REDEBAN 2025'!$B$6,'BASE LIQUIDACION REDEBAN 2025'!$C$5))))))) -> 275728.78 | AE101: =IF(OR(W101="SOPORTE_TELEFÓNICO",W101="ENVÍO"),0,IF(Y101="TIPO I",'BASE LIQUIDACION REDEBAN 2025'!$B$10,IF(Y101="TIPO II",'BASE LIQUIDACION REDEBAN 2025'!$B$11,IF(Y101="TIPO III",'BASE LIQUIDACION REDEBAN 2025'!$B$12,'BASE LIQUIDACION REDEBAN 2025'!$B$13)))) -> 196536.53 | AF101: =IF(OR(W101="SOPORTE_TELEFÓNICO",W101="ENVÍO"),AD101,(AD101*AB101+AE101*AC101)) -> 275728.78
A102: VILLAVICENCIO | B102: =VLOOKUP(A102,'CENTRO DE COSTOS'!A:D,4,FALSE) -> KEVIN ALEXIS CORZO BUSTOS | C102: =VLOOKUP(A102,'CENTRO DE COSTOS'!A:D,2,FALSE) -> 0004-0007 | D102: 50001 | E102: 2543574 | F102: 65160 | G102: INCIDENTE | H102: META | I102: VILLAVICENCIO | J102: PTM VILLAVICENCIO SERVIMOTORS | K102: REDEBAN | L102: FO-25-1321116 | M102: 45871.525 | N102: 45873.478 | O102: NO | P102: HARDWARE | Q102: COMUNICACION | R102: MENSAJE DE ERROR SOCKET | S102: AGREGADOR | U102: CERRADO | V102: 03/08/2025 POR HORARIO DE ATENCIÓN ATIENDE EL LUNES | 04/08/2025 SE REALIZA VISITA Y SE EVIDENCIA QUE CLIENTE NO CUENTA CON SERVICIO DE INTENET, EL DAÑO ES EN EL.MEDIO DE COMUNICACIÓN | W102: VISITA_TÉCNICA | X102: 2A008699 - 2A008508 | Y102: TIPO I | Z102: TERRESTRE | AA102: PEDREROS CONTRERAS MICHAEL STEVENS | AB102: 1 | AC102: 0 | AD102: =IF(W102="SOPORTE_TELEFÓNICO",'BASE LIQUIDACION REDEBAN 2025'!$B$19,IF(W102="ENVÍO",'BASE LIQUIDACION REDEBAN 2025'!$C$2,IF(Y102="TIPO I",'BASE LIQUIDACION REDEBAN 2025'!$C$2,IF(Y102="TIPO II",'BASE LIQUIDACION REDEBAN 2025'!$C$3,IF(Y102="TIPO III",'BASE LIQUIDACION REDEBAN 2025'!$C$4,IF(Y102="TIPO IV",'BASE LIQUIDACION REDEBAN 2025'!$C$5,IF(Z102="AEREO",'BASE LIQUIDACION REDEBAN 2025'!$B$6,'BASE LIQUIDACION REDEBAN 2025'!$C$5))))))) -> 65960.072 | AE102: =IF(OR(W102="SOPORTE_TELEFÓNICO",W102="ENVÍO"),0,IF(Y102="TIPO I",'BASE LIQUIDACION REDEBAN 2025'!$B$10,IF(Y102="TIPO II",'BASE LIQUIDACION REDEBAN 2025'!$B$11,IF(Y102="TIPO III",'BASE LIQUIDACION REDEBAN 2025'!$B$12,'BASE LIQUIDACION REDEBAN 2025'!$B$13)))) -> 75096.394 | AF102: =IF(OR(W102="SOPORTE_TELEFÓNICO",W102="ENVÍO"),AD102,(AD102*AB102+AE102*AC102)) -> 65960.072
A103: CALI | B103: =VLOOKUP(A103,'CENTRO DE COSTOS'!A:D,4,FALSE) -> DIEGO FERNANDO HENAO CARDONA | C103: =VLOOKUP(A103,'CENTRO DE COSTOS'!A:D,2,FALSE) -> 0004-0003 | D103: 76001 | E103: 2543694 | F103: 58165 | G103: INCIDENTE | H103: VALLE DEL CAUCA | I103: CALI | J103: PTM CALI EL ESQUINAZO DE LA 10 | K103: REDEBAN | L103: FO-25-1321443 | M103: 45871.553 | N103: 45873.481 | O103: NO | P103: HARDWARE | Q103: IMPRESION | R103: NO AVANZA PAPEL | S103: AGREGADOR | U103: CERRADO | V103: 02/08/2025 01-08 SE ESCALA PARA VISITA. LLAMAR ANTES DE VISITAR, CONFIRMAR FALLA Y DATOS | 03/08/2025 SE REPROGRAMA VISITA PARA EL DIA LUNES YA QUE SE REQUIERE CAMBIO DE EQUIPO Y NO HAY SOPORTE POR PARTE DE REDEBAN | 04/08/2025 SE CAMBIA DATÁFONO YA QUE EL PAPEL NO AVANZA | W103: VISITA_TÉCNICA | X103: TUZZZ356 - TUZZZ930 | Y103: TIPO I | Z103: TERRESTRE | AA103: CUERO RUIZ JHONNY | AB103: 1 | AC103: 0 | AD103: =IF(W103="SOPORTE_TELEFÓNICO",'BASE LIQUIDACION REDEBAN 2025'!$B$19,IF(W103="ENVÍO",'BASE LIQUIDACION REDEBAN 2025'!$C$2,IF(Y103="TIPO I",'BASE LIQUIDACION REDEBAN 2025'!$C$2,IF(Y103="TIPO II",'BASE LIQUIDACION REDEBAN 2025'!$C$3,IF(Y103="TIPO III",'BASE LIQUIDACION REDEBAN 2025'!$C$4,IF(Y103="TIPO IV",'BASE LIQUIDACION REDEBAN 2025'!$C$5,IF(Z103="AEREO",'BASE LIQUIDACION REDEBAN 2025'!$B$6,'BASE LIQUIDACION REDEBAN 2025'!$C$5))))))) -> 65960.072 | AE103: =IF(OR(W103="SOPORTE_TELEFÓNICO",W103="ENVÍO"),0,IF(Y103="TIPO I",'BASE LIQUIDACION REDEBAN 2025'!$B$10,IF(Y103="TIPO II",'BASE LIQUIDACION REDEBAN 2025'!$B$11,IF(Y103="TIPO III",'BASE LIQUIDACION REDEBAN 2025'!$B$12,'BASE LIQUIDACION REDEBAN 2025'!$B$13)))) -> 75096.394 | AF103: =IF(OR(W103="SOPORTE_TELEFÓNICO",W103="ENVÍO"),AD103,(AD103*AB103+AE103*AC103)) -> 65960.072
A104: MONTERIA | B104: =VLOOKUP(A104,'CENTRO DE COSTOS'!A:D,4,FALSE) -> JOSE MAURICIO HERNANDEZ ROJAS | C104: =VLOOKUP(A104,'CENTRO DE COSTOS'!A:D,2,FALSE) -> 0004-0001 | D104: 23670 | E104: 2543650 | F104: 76162 | G104: INCIDENTE | H104: CORDOBA | I104: SAN ANDRES SOTAVENTO | J104: BARRIO OTRO SAN ANDRES DE SOTA | K104: REDEBAN | L104: FO-25-1321031 | M104: 45871.489 | N104: 45873.484 | O104: NO | P104: HARDWARE | Q104: IMPRESION | R104: TAPA IMPRESORA | S104: CB UNO A UNO | U104: CERRADO | V104: 02/08/2025 01-08 SE ESCALA PARA VISITA. LLAMAR ANTES DE VISITAR, CONFIRMAR FALLA Y DATOS | 04/08/2025 SE VISITA SITIO, SE AJUSTA TAPA IMPRESORA Y CAMBIA BATERÍA OK. SE CAMBIA MAGIC BOX POR DETERIORO. SE REALIZAN PRUEBAS EXITOSAS | W104: VISITA_TÉCNICA | X104: SX0GZ313 | Y104: TIPO II | Z104: TERRESTRE | AA104: COGOLLO VERTEL EDER LUIS | AB104: 1 | AC104: 0 | AD104: =IF(W104="SOPORTE_TELEFÓNICO",'BASE LIQUIDACION REDEBAN 2025'!$B$19,IF(W104="ENVÍO",'BASE LIQUIDACION REDEBAN 2025'!$C$2,IF(Y104="TIPO I",'BASE LIQUIDACION REDEBAN 2025'!$C$2,IF(Y104="TIPO II",'BASE LIQUIDACION REDEBAN 2025'!$C$3,IF(Y104="TIPO III",'BASE LIQUIDACION REDEBAN 2025'!$C$4,IF(Y104="TIPO IV",'BASE LIQUIDACION REDEBAN 2025'!$C$5,IF(Z104="AEREO",'BASE LIQUIDACION REDEBAN 2025'!$B$6,'BASE LIQUIDACION REDEBAN 2025'!$C$5))))))) -> 144967.87 | AE104: =IF(OR(W104="SOPORTE_TELEFÓNICO",W104="ENVÍO"),0,IF(Y104="TIPO I",'BASE LIQUIDACION REDEBAN 2025'!$B$10,IF(Y104="TIPO II",'BASE LIQUIDACION REDEBAN 2025'!$B$11,IF(Y104="TIPO III",'BASE LIQUIDACION REDEBAN 2025'!$B$12,'BASE LIQUIDACION REDEBAN 2025'!$B$13)))) -> 140395.63 | AF104: =IF(OR(W104="SOPORTE_TELEFÓNICO",W104="ENVÍO"),AD104,(AD104*AB104+AE104*AC104)) -> 144967.87
A105: MEDELLIN | B105: =VLOOKUP(A105,'CENTRO DE COSTOS'!A:D,4,FALSE) -> JUAN SEBASTIÁN RÍOS CASTRILLÓN | C105: =VLOOKUP(A105,'CENTRO DE COSTOS'!A:D,2,FALSE) -> 0004-0005 | D105: 5240 | E105: 2543437 | F105: 40331 | G105: INCIDENTE | H105: ANTIOQUIA | I105: EBEJICO | J105: BARRIO CALLE EL COMERCIO EBEJI | K105: REDEBAN | L105: FO-25-1320736 | M105: 45871.473 | N105: 45873.486 | O105: NO | P105: HARDWARE | Q105: LECTOR DE BARRAS | R105: CABLE LECTORA AVERIADO | S105: CB UNO A UNO | U105: CERRADO | V105: 02/08/2025 01-08 SE ESCALA PARA VISITA. LLAMAR ANTES DE VISITAR, CONFIRMAR FALLA Y DATOS | 04/08/2025 SE CAMBIA LECTOR DE BARRAS POR DAÑO EN CABLE Y DATÁFONO CON LECTOR CHIP AVERIADO | W105: VISITA_TÉCNICA | X105: 9A0KZ168 | Y105: TIPO II | Z105: TERRESTRE | AA105: CASTAÑEDA PALACIO CARLOS FELIPE | AB105: 1 | AC105: 0 | AD105: =IF(W105="SOPORTE_TELEFÓNICO",'BASE LIQUIDACION REDEBAN 2025'!$B$19,IF(W105="ENVÍO",'BASE LIQUIDACION REDEBAN 2025'!$C$2,IF(Y105="TIPO I",'BASE LIQUIDACION REDEBAN 2025'!$C$2,IF(Y105="TIPO II",'BASE LIQUIDACION REDEBAN 2025'!$C$3,IF(Y105="TIPO III",'BASE LIQUIDACION REDEBAN 2025'!$C$4,IF(Y105="TIPO IV",'BASE LIQUIDACION REDEBAN 2025'!$C$5,IF(Z105="AEREO",'BASE LIQUIDACION REDEBAN 2025'!$B$6,'BASE LIQUIDACION REDEBAN 2025'!$C$5))))))) -> 144967.87 | AE105: =IF(OR(W105="SOPORTE_TELEFÓNICO",W105="ENVÍO"),0,IF(Y105="TIPO I",'BASE LIQUIDACION REDEBAN 2025'!$B$10,IF(Y105="TIPO II",'BASE LIQUIDACION REDEBAN 2025'!$B$11,IF(Y105="TIPO III",'BASE LIQUIDACION REDEBAN 2025'!$B$12,'BASE LIQUIDACION REDEBAN 2025'!$B$13)))) -> 140395.63 | AF105: =IF(OR(W105="SOPORTE_TELEFÓNICO",W105="ENVÍO"),AD105,(AD105*AB105+AE105*AC105)) -> 144967.87
A106: BOGOTA | B106: =VLOOKUP(A106,'CENTRO DE COSTOS'!A:D,4,FALSE) -> WILLIAM ASDRUBAL ROZO ROZO | C106: =VLOOKUP(A106,'CENTRO DE COSTOS'!A:D,2,FALSE) -> 0004-0004 | D106: 11001 | E106: 2543834 | F106: 47418 | G106: INCIDENTE | H106: CUNDINAMARCA | I106: BOGOTA | J106: BARRIO SAN ANTONIO NORTE BOGOT | K106: REDEBAN | L106: FO-25-1322397 | M106: 45871.655 | N106: 45873.502 | O106: NO | P106: HARDWARE | Q106: ALERT IRRUPTION | R106: ALERT IRRUPTION | S106: CB UNO A UNO | U106: CERRADO | V106: 03/08/2025 03-08 SE ESCALA PARA VISITA. LLAMAR ANTES DE VISITAR, CONFIRMAR FALLA Y DATOS | 03/08/2025 ESTABLECEMOS COMUNICACIÓN TELEFÓNICA CON LA SEÑORA SANDRA MATILLA AL 3158168979 LA CUAL NOS INDICA QUE POSIBLEMENTE NO DE APERTURA EL DÍA DE HOY Y APARTE QUIERE QUE SE LE CAMBIE EL DATAFONO SOLICITA SER VISITADA EL DÍA LUNES APARTIR DE LA 10:30 AM YA QUE ANTES DE ESA HORA SE LE DIFICULTA | 04/08/2025 CAMBIO DE DATAFONO EN DAÑO NO PRENDE SE REALIZAN PRUEBAS OK | W106: VISITA_TÉCNICA | X106: 9C00G064 | Y106: TIPO I | Z106: TERRESTRE | AA106: GOMEZ VEGA DAVID SNEYDER | AB106: 1 | AC106: 0 | AD106: =IF(W106="SOPORTE_TELEFÓNICO",'BASE LIQUIDACION REDEBAN 2025'!$B$19,IF(W106="ENVÍO",'BASE LIQUIDACION REDEBAN 2025'!$C$2,IF(Y106="TIPO I",'BASE LIQUIDACION REDEBAN 2025'!$C$2,IF(Y106="TIPO II",'BASE LIQUIDACION REDEBAN 2025'!$C$3,IF(Y106="TIPO III",'BASE LIQUIDACION REDEBAN 2025'!$C$4,IF(Y106="TIPO IV",'BASE LIQUIDACION REDEBAN 2025'!$C$5,IF(Z106="AEREO",'BASE LIQUIDACION REDEBAN 2025'!$B$6,'BASE LIQUIDACION REDEBAN 2025'!$C$5))))))) -> 65960.072 | AE106: =IF(OR(W106="SOPORTE_TELEFÓNICO",W106="ENVÍO"),0,IF(Y106="TIPO I",'BASE LIQUIDACION REDEBAN 2025'!$B$10,IF(Y106="TIPO II",'BASE LIQUIDACION REDEBAN 2025'!$B$11,IF(Y106="TIPO III",'BASE LIQUIDACION REDEBAN 2025'!$B$12,'BASE LIQUIDACION REDEBAN 2025'!$B$13)))) -> 75096.394 | AF106: =IF(OR(W106="SOPORTE_TELEFÓNICO",W106="ENVÍO"),AD106,(AD106*AB106+AE106*AC106)) -> 65960.072
A107: MEDELLIN | B107: =VLOOKUP(A107,'CENTRO DE COSTOS'!A:D,4,FALSE) -> JUAN SEBASTIÁN RÍOS CASTRILLÓN | C107: =VLOOKUP(A107,'CENTRO DE COSTOS'!A:D,2,FALSE) -> 0004-0005 | D107: 5282 | E107: 2543808 | F107: 27724 | G107: INCIDENTE | H107: ANTIOQUIA | I107: FREDONIA | J107: DISTRICOL PAPELERIA VENGA MIRE | K107: REDEBAN | L107: FO-25-1321439 | M107: 45871.589 | N107: 45873.512 | O107: NO | P107: HARDWARE | Q107: TECLADO | R107: DAÑO POS | S107: AGREGADOR | U107: CERRADO | V107: 02/08/2025 01-08 SE ESCALA PARA VISITA. LLAMAR ANTES DE VISITAR, CONFIRMAR FALLA Y DATOS | 04/08/2025 SE REALIZA CAMBIO DE EQUIPO POR TECLADO BORROSO | W107: VISITA_TÉCNICA | X107: 99WZZ907 | Y107: TIPO II | Z107: TERRESTRE | AA107: HERNANDEZ CHAVARRIA JUAN CAMILO | AB107: 1 | AC107: 0 | AD107: =IF(W107="SOPORTE_TELEFÓNICO",'BASE LIQUIDACION REDEBAN 2025'!$B$19,IF(W107="ENVÍO",'BASE LIQUIDACION REDEBAN 2025'!$C$2,IF(Y107="TIPO I",'BASE LIQUIDACION REDEBAN 2025'!$C$2,IF(Y107="TIPO II",'BASE LIQUIDACION REDEBAN 2025'!$C$3,IF(Y107="TIPO III",'BASE LIQUIDACION REDEBAN 2025'!$C$4,IF(Y107="TIPO IV",'BASE LIQUIDACION REDEBAN 2025'!$C$5,IF(Z107="AEREO",'BASE LIQUIDACION REDEBAN 2025'!$B$6,'BASE LIQUIDACION REDEBAN 2025'!$C$5))))))) -> 144967.87 | AE107: =IF(OR(W107="SOPORTE_TELEFÓNICO",W107="ENVÍO"),0,IF(Y107="TIPO I",'BASE LIQUIDACION REDEBAN 2025'!$B$10,IF(Y107="TIPO II",'BASE LIQUIDACION REDEBAN 2025'!$B$11,IF(Y107="TIPO III",'BASE LIQUIDACION REDEBAN 2025'!$B$12,'BASE LIQUIDACION REDEBAN 2025'!$B$13)))) -> 140395.63 | AF107: =IF(OR(W107="SOPORTE_TELEFÓNICO",W107="ENVÍO"),AD107,(AD107*AB107+AE107*AC107)) -> 144967.87
A108: CUCUTA | B108: =VLOOKUP(A108,'CENTRO DE COSTOS'!A:D,4,FALSE) -> MIGUEL JULIÁN HERNÁNDEZ GUARÍN | C108: =VLOOKUP(A108,'CENTRO DE COSTOS'!A:D,2,FALSE) -> 0004-0008 | D108: 54810 | E108: 2535076 | F108: 60498 | G108: INCIDENTE | H108: NORTE DE SANTANDER | I108: TIBU | J108: BARRIO FUERA DEL MUNICIPIO DE | K108: REDEBAN | L108: FO-25-1313232 | M108: 45869.658 | N108: 45873.516 | O108: NO | P108: HARDWARE | Q108: COMUNICACION | R108: DAÑO POS | S108: CB UNO A UNO | U108: CERRADO | V108: 31/07/2025 31-07 EN COMUNICACION CON EL SEÑOR OCTAVIO TORO AL NUMERO 3118333056, CONFIRMA FALLA, DATOS CORRECTOS. SE ESCALA PARA VISITA | 01/08/2025 POR ORDEN PÚBLICO EN EL CATATUMBO SE LE INFORMA AL CLIENTE QUE LOS CASOS SE ATIENDEN EN LA BODEGA CÚCUTA,ME INFORMA EL SR OCTAVIO TORO 3118333056 QUE VIAJARA EL DIA SÁBADO PARA LA ATENCIÓN DEL CASO SE PROGRAMA VISITA A LA ESPERA DE CONFIRMACIÓN DE LLEGADA DEL CLIENTE A LA CUIDAD | 02/08/2025 NO SÉ LOGRÓ COMUNICACIÓN CON EL SR SR OCTAVIO TORO 3118333056 PARA CONFIRMAR SI LOGRO VIAJAS A LA CUIDAD PARA LA ATENCIÓN DEL CASO EN BODEGA CÚCUTA,SE PROGRAMA VISITA PARA EL DÍA LUNES 04-08-25 A LA ESPERA DE CONFIRMACIÓN DEL CLIENTE | 04/08/2025 POR ORDEN PÚBLICO EN EL CATATUMBO CLIENTE BAJA EL EQUIPO PARA LA ATENCIÓN DEL CASO EN BODEGA CÚCUTA, SE CAMBIO DATAFONO POR DAÑO EN PUERTO DE INTERNET, SE INSTALA NUEVA VERSIÓN CIERRES Y PRUEBAS OK | W108: VISITA_TÉCNICA | X108: KA00C879 | Y108: TIPO IV ESPECIAL | Z108: TERRESTRE | AA108: DURAN ACOSTA FRANK YONNY | AB108: 1 | AC108: 0 | AD108: =IF(W108="SOPORTE_TELEFÓNICO",'BASE LIQUIDACION REDEBAN 2025'!$B$19,IF(W108="ENVÍO",'BASE LIQUIDACION REDEBAN 2025'!$C$2,IF(Y108="TIPO I",'BASE LIQUIDACION REDEBAN 2025'!$C$2,IF(Y108="TIPO II",'BASE LIQUIDACION REDEBAN 2025'!$C$3,IF(Y108="TIPO III",'BASE LIQUIDACION REDEBAN 2025'!$C$4,IF(Y108="TIPO IV",'BASE LIQUIDACION REDEBAN 2025'!$C$5,IF(Z108="AEREO",'BASE LIQUIDACION REDEBAN 2025'!$B$6,'BASE LIQUIDACION REDEBAN 2025'!$C$5))))))) -> 479588.88 | AE108: =IF(OR(W108="SOPORTE_TELEFÓNICO",W108="ENVÍO"),0,IF(Y108="TIPO I",'BASE LIQUIDACION REDEBAN 2025'!$B$10,IF(Y108="TIPO II",'BASE LIQUIDACION REDEBAN 2025'!$B$11,IF(Y108="TIPO III",'BASE LIQUIDACION REDEBAN 2025'!$B$12,'BASE LIQUIDACION REDEBAN 2025'!$B$13)))) -> 196536.53 | AF108: =IF(OR(W108="SOPORTE_TELEFÓNICO",W108="ENVÍO"),AD108,(AD108*AB108+AE108*AC108)) -> 479588.88
A109: MEDELLIN | B109: =VLOOKUP(A109,'CENTRO DE COSTOS'!A:D,4,FALSE) -> JUAN SEBASTIÁN RÍOS CASTRILLÓN | C109: =VLOOKUP(A109,'CENTRO DE COSTOS'!A:D,2,FALSE) -> 0004-0005 | D109: 5001 | E109: 2544728 | F109: 37696 | G109: INCIDENTE | H109: ANTIOQUIA | I109: MEDELLIN | J109: BARRIO ROBLEDO VILLA SOFIA MED | K109: REDEBAN | L109: FO-25-1323622 | M109: 45872.741 | N109: 45873.517 | O109: NO | P109: HARDWARE | Q109: PANTALLA | R109: DAÑO POS | S109: CB UNO A UNO | U109: CERRADO | V109: 04/08/2025 03-08 SE ESCALA PARA VISITA. LLAMAR ANTES DE VISITAR, CONFIRMAR FALLA Y DATOS | 04/08/2025 SE LLAMA AL SEÑOR DUBER AL 3114390803 PARA PREGUNTARLE BIEN LA UBICACION DEL CB YA QUE NO SE UBICABA, PERO ESTE INFORMO QUE SOLO FALLO AYER PERO QUE NO VOLVIÓ A MOLESTAR Y QUE NO NECESITA QUE LO VISITEMOS POR LO QUE SE CIERRA VISITA | W109: SOPORTE_TELEFÓNICO | X109: 0 | Y109: TIPO I | Z109: TERRESTRE | AA109: ALVAREZ ARENAS VICTOR HUGO | AB109: 0 | AC109: 0 | AD109: =IF(W109="SOPORTE_TELEFÓNICO",'BASE LIQUIDACION REDEBAN 2025'!$B$19,IF(W109="ENVÍO",'BASE LIQUIDACION REDEBAN 2025'!$C$2,IF(Y109="TIPO I",'BASE LIQUIDACION REDEBAN 2025'!$C$2,IF(Y109="TIPO II",'BASE LIQUIDACION REDEBAN 2025'!$C$3,IF(Y109="TIPO III",'BASE LIQUIDACION REDEBAN 2025'!$C$4,IF(Y109="TIPO IV",'BASE LIQUIDACION REDEBAN 2025'!$C$5,IF(Z109="AEREO",'BASE LIQUIDACION REDEBAN 2025'!$B$6,'BASE LIQUIDACION REDEBAN 2025'!$C$5))))))) -> 41241.08 | AE109: =IF(OR(W109="SOPORTE_TELEFÓNICO",W109="ENVÍO"),0,IF(Y109="TIPO I",'BASE LIQUIDACION REDEBAN 2025'!$B$10,IF(Y109="TIPO II",'BASE LIQUIDACION REDEBAN 2025'!$B$11,IF(Y109="TIPO III",'BASE LIQUIDACION REDEBAN 2025'!$B$12,'BASE LIQUIDACION REDEBAN 2025'!$B$13)))) -> 0 | AF109: =IF(OR(W109="SOPORTE_TELEFÓNICO",W109="ENVÍO"),AD109,(AD109*AB109+AE109*AC109)) -> 41241.08
A110: PEREIRA | B110: =VLOOKUP(A110,'CENTRO DE COSTOS'!A:D,4,FALSE) -> DIEGO FERNANDO HENAO CARDONA | C110: =VLOOKUP(A110,'CENTRO DE COSTOS'!A:D,2,FALSE) -> 0004-0002 | D110: 66001 | E110: 2543529 | F110: 68021 | G110: INCIDENTE | H110: RISARALDA | I110: PEREIRA | J110: DISTRICOL MISCELAN LA ESPIGA | K110: REDEBAN | L110: FO-25-1320482 | M110: 45871.454 | N110: 45873.519 | O110: NO | P110: HARDWARE | Q110: SE REINICIA | R110: DAÑO POS | S110: AGREGADOR | U110: CERRADO | V110: 02/08/2025 01-08 SE ESCALA PARA VISITA. LLAMAR ANTES DE VISITAR, CONFIRMAR FALLA Y DATOS | 02/08/2025 SE HABLA CON CLIENTE E INDICA REALIZAR VISITA EL DIA LUNES, YA QUE NO SE ENCUENTRA EN EL LOCAL | 04/08/2025 VISITAMOS COMERCIO REALIZAMOS CAMBIO DE DATAFONO YA QUE EN OCASIONES SE REINICIA LO CONFIGURAMOS Y REALIZAMOS PRUEBAS OK | W110: VISITA_TÉCNICA | X110: AAL0V571 | Y110: TIPO I | Z110: TERRESTRE | AA110: ARROYAVE CANO MANUEL GUILLERMO | AB110: 1 | AC110: 0 | AD110: =IF(W110="SOPORTE_TELEFÓNICO",'BASE LIQUIDACION REDEBAN 2025'!$B$19,IF(W110="ENVÍO",'BASE LIQUIDACION REDEBAN 2025'!$C$2,IF(Y110="TIPO I",'BASE LIQUIDACION REDEBAN 2025'!$C$2,IF(Y110="TIPO II",'BASE LIQUIDACION REDEBAN 2025'!$C$3,IF(Y110="TIPO III",'BASE LIQUIDACION REDEBAN 2025'!$C$4,IF(Y110="TIPO IV",'BASE LIQUIDACION REDEBAN 2025'!$C$5,IF(Z110="AEREO",'BASE LIQUIDACION REDEBAN 2025'!$B$6,'BASE LIQUIDACION REDEBAN 2025'!$C$5))))))) -> 65960.072 | AE110: =IF(OR(W110="SOPORTE_TELEFÓNICO",W110="ENVÍO"),0,IF(Y110="TIPO I",'BASE LIQUIDACION REDEBAN 2025'!$B$10,IF(Y110="TIPO II",'BASE LIQUIDACION REDEBAN 2025'!$B$11,IF(Y110="TIPO III",'BASE LIQUIDACION REDEBAN 2025'!$B$12,'BASE LIQUIDACION REDEBAN 2025'!$B$13)))) -> 75096.394 | AF110: =IF(OR(W110="SOPORTE_TELEFÓNICO",W110="ENVÍO"),AD110,(AD110*AB110+AE110*AC110)) -> 65960.072
A111: MEDELLIN | B111: =VLOOKUP(A111,'CENTRO DE COSTOS'!A:D,4,FALSE) -> JUAN SEBASTIÁN RÍOS CASTRILLÓN | C111: =VLOOKUP(A111,'CENTRO DE COSTOS'!A:D,2,FALSE) -> 0004-0005 | D111: 5001 | E111: 2543642 | F111: 33409 | G111: INCIDENTE | H111: ANTIOQUIA | I111: MEDELLIN | J111: COMCARD MED PELUQUERO PICACHO | K111: REDEBAN | L111: FO-25-1320728 | M111: 45871.478 | N111: 45873.524 | O111: NO | P111: HARDWARE | Q111: LECTOR DE TARJETAS | R111: DAÑO POS | S111: AGREGADOR | U111: CERRADO | V111: 02/08/2025 01-08 SE ESCALA PARA VISITA. LLAMAR ANTES DE VISITAR, CONFIRMAR FALLA Y DATOS | 02/08/2025 EN COMUNICACIÓN CON LA SEÑORITA DAYANA 3212969194, NOS IDICA QUE NO ES POSIBLE ATENDER LA VISITA EL DÍA DE HOY YA QUE ELLA CIERRA EL COMERCIO A LAS 12PM Y ABRE NUEVAMENTE A LAS 2PM SE ME INDICA QUE A ESA HORA NO SE TIENE SOPORTE PARA CAMBIOS DE EQUIPO Y NO MANIFIESTA QUE NO HAY PROBLEMA QUE PUEDE ATENDER EL LUNES A PRIMERA HORA. | 04/08/2025 SE LIMPIA CONTACTO CHIP SE HACEN PRUEBAS TODO QUEDA OK | W111: VISITA_TÉCNICA | X111: 17ZZZ957-NA001728 | Y111: TIPO I | Z111: TERRESTRE | AA111: ALVAREZ ARENAS VICTOR HUGO | AB111: 1 | AC111: 0 | AD111: =IF(W111="SOPORTE_TELEFÓNICO",'BASE LIQUIDACION REDEBAN 2025'!$B$19,IF(W111="ENVÍO",'BASE LIQUIDACION REDEBAN 2025'!$C$2,IF(Y111="TIPO I",'BASE LIQUIDACION REDEBAN 2025'!$C$2,IF(Y111="TIPO II",'BASE LIQUIDACION REDEBAN 2025'!$C$3,IF(Y111="TIPO III",'BASE LIQUIDACION REDEBAN 2025'!$C$4,IF(Y111="TIPO IV",'BASE LIQUIDACION REDEBAN 2025'!$C$5,IF(Z111="AEREO",'BASE LIQUIDACION REDEBAN 2025'!$B$6,'BASE LIQUIDACION REDEBAN 2025'!$C$5))))))) -> 65960.072 | AE111: =IF(OR(W111="SOPORTE_TELEFÓNICO",W111="ENVÍO"),0,IF(Y111="TIPO I",'BASE LIQUIDACION REDEBAN 2025'!$B$10,IF(Y111="TIPO II",'BASE LIQUIDACION REDEBAN 2025'!$B$11,IF(Y111="TIPO III",'BASE LIQUIDACION REDEBAN 2025'!$B$12,'BASE LIQUIDACION REDEBAN 2025'!$B$13)))) -> 75096.394 | AF111: =IF(OR(W111="SOPORTE_TELEFÓNICO",W111="ENVÍO"),AD111,(AD111*AB111+AE111*AC111)) -> 65960.072
A112: MEDELLIN | B112: =VLOOKUP(A112,'CENTRO DE COSTOS'!A:D,4,FALSE) -> JUAN SEBASTIÁN RÍOS CASTRILLÓN | C112: =VLOOKUP(A112,'CENTRO DE COSTOS'!A:D,2,FALSE) -> 0004-0005 | D112: 5001 | E112: 2546051 | F112: 51558 | G112: INCIDENTE | H112: ANTIOQUIA | I112: MEDELLIN | J112: BARRIO PLAZA DE FERIA MEDELLIN | K112: REDEBAN | L112: FO-25-1324452 | M112: 45873.379 | N112: 45873.535 | O112: NO | P112: HARDWARE | Q112: LECTOR DE TARJETAS | R112: MENSAJE RETIRE TARJETA | S112: CB UNO A UNO | U112: CERRADO | V112: 04/08/2025 04-08 SE ESCALA PARA VISITA. LLAMAR ANTES DE VISITAR, CONFIRMAR FALLA Y DATOS | 04/08/2025 SE LIMPIA CONTACTO CHIP SE HACEN PRUEBAS QUEDA OK | W112: VISITA_TÉCNICA | X112: TR08Z447 | Y112: TIPO I | Z112: TERRESTRE | AA112: ALVAREZ ARENAS VICTOR HUGO | AB112: 1 | AC112: 0 | AD112: =IF(W112="SOPORTE_TELEFÓNICO",'BASE LIQUIDACION REDEBAN 2025'!$B$19,IF(W112="ENVÍO",'BASE LIQUIDACION REDEBAN 2025'!$C$2,IF(Y112="TIPO I",'BASE LIQUIDACION REDEBAN 2025'!$C$2,IF(Y112="TIPO II",'BASE LIQUIDACION REDEBAN 2025'!$C$3,IF(Y112="TIPO III",'BASE LIQUIDACION REDEBAN 2025'!$C$4,IF(Y112="TIPO IV",'BASE LIQUIDACION REDEBAN 2025'!$C$5,IF(Z112="AEREO",'BASE LIQUIDACION REDEBAN 2025'!$B$6,'BASE LIQUIDACION REDEBAN 2025'!$C$5))))))) -> 65960.072 | AE112: =IF(OR(W112="SOPORTE_TELEFÓNICO",W112="ENVÍO"),0,IF(Y112="TIPO I",'BASE LIQUIDACION REDEBAN 2025'!$B$10,IF(Y112="TIPO II",'BASE LIQUIDACION REDEBAN 2025'!$B$11,IF(Y112="TIPO III",'BASE LIQUIDACION REDEBAN 2025'!$B$12,'BASE LIQUIDACION REDEBAN 2025'!$B$13)))) -> 75096.394 | AF112: =IF(OR(W112="SOPORTE_TELEFÓNICO",W112="ENVÍO"),AD112,(AD112*AB112+AE112*AC112)) -> 65960.072
A113: PEREIRA | B113: =VLOOKUP(A113,'CENTRO DE COSTOS'!A:D,4,FALSE) -> DIEGO FERNANDO HENAO CARDONA | C113: =VLOOKUP(A113,'CENTRO DE COSTOS'!A:D,2,FALSE) -> 0004-0002 | D113: 66170 | E113: 2543693 | F113: 51570 | G113: INCIDENTE | H113: RISARALDA | I113: DOSQUEBRADAS | J113: PTM DOSQUEBRADAS MINIMERCADO L | K113: REDEBAN | L113: FO-25-1321447 | M113: 45871.553 | N113: 45873.538 | O113: NO | P113: HARDWARE | Q113: DETERIORO | R113: DATAFONO | S113: AGREGADOR | U113: CERRADO | V113: 02/08/2025 01-08 SE ESCALA PARA VISITA. LLAMAR ANTES DE VISITAR, CONFIRMAR FALLA Y DATOS | 03/08/2025 EN COMUNICACIÓN CON LA SEÑORA YUDY MORALES INFORMA QUE DATÁFONO SE REINICIA AL INSERTAR TARJETAS SE REQUIERE CAMBIO DE DATÁFONO SE REAGENDAR POR FALTA DE TORRE DE CONTROL PARA GESTIONAR CAMBIO | 04/08/2025 VISITAMOS COMERCIO REALIZAMOS CAMBIO DE DATAFONO YA QUE SE REINICIA CUANDO INGRESAN LAS TARJETAS Y TAMBIÉN TIENE ALGUNAS TECLAS MUY PEGADAS, LO CONFIGURAMOS Y REALIZAMOS PRUEBAS CON EL NUEVO DATÁFONO OK. | W113: VISITA_TÉCNICA | X113: TR08Z459-HA006883 | Y113: TIPO I | Z113: TERRESTRE | AA113: ARROYAVE CANO MANUEL GUILLERMO | AB113: 1 | AC113: 0 | AD113: =IF(W113="SOPORTE_TELEFÓNICO",'BASE LIQUIDACION REDEBAN 2025'!$B$19,IF(W113="ENVÍO",'BASE LIQUIDACION REDEBAN 2025'!$C$2,IF(Y113="TIPO I",'BASE LIQUIDACION REDEBAN 2025'!$C$2,IF(Y113="TIPO II",'BASE LIQUIDACION REDEBAN 2025'!$C$3,IF(Y113="TIPO III",'BASE LIQUIDACION REDEBAN 2025'!$C$4,IF(Y113="TIPO IV",'BASE LIQUIDACION REDEBAN 2025'!$C$5,IF(Z113="AEREO",'BASE LIQUIDACION REDEBAN 2025'!$B$6,'BASE LIQUIDACION REDEBAN 2025'!$C$5))))))) -> 65960.072 | AE113: =IF(OR(W113="SOPORTE_TELEFÓNICO",W113="ENVÍO"),0,IF(Y113="TIPO I",'BASE LIQUIDACION REDEBAN 2025'!$B$10,IF(Y113="TIPO II",'BASE LIQUIDACION REDEBAN 2025'!$B$11,IF(Y113="TIPO III",'BASE LIQUIDACION REDEBAN 2025'!$B$12,'BASE LIQUIDACION REDEBAN 2025'!$B$13)))) -> 75096.394 | AF113: =IF(OR(W113="SOPORTE_TELEFÓNICO",W113="ENVÍO"),AD113,(AD113*AB113+AE113*AC113)) -> 65960.072
A114: NEIVA | B114: =VLOOKUP(A114,'CENTRO DE COSTOS'!A:D,4,FALSE) -> KEVIN ALEXIS CORZO BUSTOS | C114: =VLOOKUP(A114,'CENTRO DE COSTOS'!A:D,2,FALSE) -> 0004-0007 | D114: 41001 | E114: 2544983 | F114: 24005 | G114: INCIDENTE | H114: HUILA | I114: NEIVA | J114: BARRIO EL CENTRO NEIVA | K114: REDEBAN | L114: FO-25-1323616 | M114: 45873.333 | N114: 45873.542 | O114: NO | P114: HARDWARE | Q114: IMPRESION | R114: TAPA IMPRESORA | S114: CB UNO A UNO | U114: CERRADO | V114: 04/08/2025 03-08 SE ESCALA PARA VISITA. LLAMAR ANTES DE VISITAR, CONFIRMAR FALLA Y DATOS | 04/08/2025 SE REALIZA VISITA AL PUNTO, SE REALIZA AJUSTE DE TAPA IMPRESORA. PRUEBAS IMPRESIÓN OK, PRUEBAS MIXTAS OK ,CB OPERATIVO | W114: VISITA_TÉCNICA | X114: BL08Z709 | Y114: TIPO I | Z114: TERRESTRE | AA114: DEVIA REINOSO JUAN CARLOS | AB114: 1 | AC114: 0 | AD114: =IF(W114="SOPORTE_TELEFÓNICO",'BASE LIQUIDACION REDEBAN 2025'!$B$19,IF(W114="ENVÍO",'BASE LIQUIDACION REDEBAN 2025'!$C$2,IF(Y114="TIPO I",'BASE LIQUIDACION REDEBAN 2025'!$C$2,IF(Y114="TIPO II",'BASE LIQUIDACION REDEBAN 2025'!$C$3,IF(Y114="TIPO III",'BASE LIQUIDACION REDEBAN 2025'!$C$4,IF(Y114="TIPO IV",'BASE LIQUIDACION REDEBAN 2025'!$C$5,IF(Z114="AEREO",'BASE LIQUIDACION REDEBAN 2025'!$B$6,'BASE LIQUIDACION REDEBAN 2025'!$C$5))))))) -> 65960.072 | AE114: =IF(OR(W114="SOPORTE_TELEFÓNICO",W114="ENVÍO"),0,IF(Y114="TIPO I",'BASE LIQUIDACION REDEBAN 2025'!$B$10,IF(Y114="TIPO II",'BASE LIQUIDACION REDEBAN 2025'!$B$11,IF(Y114="TIPO III",'BASE LIQUIDACION REDEBAN 2025'!$B$12,'BASE LIQUIDACION REDEBAN 2025'!$B$13)))) -> 75096.394 | AF114: =IF(OR(W114="SOPORTE_TELEFÓNICO",W114="ENVÍO"),AD114,(AD114*AB114+AE114*AC114)) -> 65960.072
A115: CALI | B115: =VLOOKUP(A115,'CENTRO DE COSTOS'!A:D,4,FALSE) -> DIEGO FERNANDO HENAO CARDONA | C115: =VLOOKUP(A115,'CENTRO DE COSTOS'!A:D,2,FALSE) -> 0004-0003 | D115: 76001 | E115: 2544367 | F115: 46873 | G115: INCIDENTE | H115: VALLE DEL CAUCA | I115: CALI | J115: BARRIO REMANSOS DE COMFANDI CA | K115: REDEBAN | L115: FO-25-1322986 | M115: 45872.523 | N115: 45873.553 | O115: NO | P115: HARDWARE | Q115: LECTOR DE TARJETAS | R115: MENSAJE RETIRE TARJETA | S115: CB UNO A UNO | U115: CERRADO | V115: 03/08/2025 03-08 SE ESCALA PARA VISITA. LLAMAR ANTES DE VISITAR, CONFIRMAR FALLA Y DATOS | 04/08/2025 SE VISITARA EL DIA 4 DE AGOSTO YA QUE REQUIERE CAMBIO DE EQUIPO | 04/08/2025 SE LE HACE MANTENIMIENTO AL PINPAD Y QUEDA FUNCIONANDO CORRECTAMENTE | W115: VISITA_TÉCNICA | X115: AD00A034 | Y115: TIPO I | Z115: TERRESTRE | AA115: CUERO RUIZ JHONNY | AB115: 1 | AC115: 0 | AD115: =IF(W115="SOPORTE_TELEFÓNICO",'BASE LIQUIDACION REDEBAN 2025'!$B$19,IF(W115="ENVÍO",'BASE LIQUIDACION REDEBAN 2025'!$C$2,IF(Y115="TIPO I",'BASE LIQUIDACION REDEBAN 2025'!$C$2,IF(Y115="TIPO II",'BASE LIQUIDACION REDEBAN 2025'!$C$3,IF(Y115="TIPO III",'BASE LIQUIDACION REDEBAN 2025'!$C$4,IF(Y115="TIPO IV",'BASE LIQUIDACION REDEBAN 2025'!$C$5,IF(Z115="AEREO",'BASE LIQUIDACION REDEBAN 2025'!$B$6,'BASE LIQUIDACION REDEBAN 2025'!$C$5))))))) -> 65960.072 | AE115: =IF(OR(W115="SOPORTE_TELEFÓNICO",W115="ENVÍO"),0,IF(Y115="TIPO I",'BASE LIQUIDACION REDEBAN 2025'!$B$10,IF(Y115="TIPO II",'BASE LIQUIDACION REDEBAN 2025'!$B$11,IF(Y115="TIPO III",'BASE LIQUIDACION REDEBAN 2025'!$B$12,'BASE LIQUIDACION REDEBAN 2025'!$B$13)))) -> 75096.394 | AF115: =IF(OR(W115="SOPORTE_TELEFÓNICO",W115="ENVÍO"),AD115,(AD115*AB115+AE115*AC115)) -> 65960.072
A116: MONTERIA | B116: =VLOOKUP(A116,'CENTRO DE COSTOS'!A:D,4,FALSE) -> JOSE MAURICIO HERNANDEZ ROJAS | C116: =VLOOKUP(A116,'CENTRO DE COSTOS'!A:D,2,FALSE) -> 0004-0001 | D116: 23807 | E116: 2543651 | F116: 31872 | G116: INCIDENTE | H116: CORDOBA | I116: TIERRALTA | J116: PAGAFACIL TIERRALTA | K116: REDEBAN | L116: FO-25-1321028 | M116: 45871.49 | N116: 45873.558 | O116: NO | P116: HARDWARE | Q116: PINPAD | R116: DAÑO POS | S116: ROBUSTO | U116: CERRADO | V116: 02/08/2025 01-08 SE ESCALA PARA VISITA. LLAMAR ANTES DE VISITAR, CONFIRMAR FALLA Y DATOS | 03/08/2025 COMERCIO NO ATIENDE DOMINGO, NO FESTIVO, SE REAGENDA LUNES 04 AGOSTO | 04/08/2025 SE REALIZÓ CAMBIO DE EQUIPO OK, FUE NECESARIO CAMBIAR DATAFONO, PINPAD Y HUB POR COMPATIBILIDAD, USUARIOS OK, PRUEBAS OK, TELECARGA DRNA. | W116: VISITA_TÉCNICA | X116: 1111R587 | Y116: TIPO III | Z116: TERRESTRE | AA116: CALDERA SALCEDO CARLOS JULIO | AB116: 1 | AC116: 0 | AD116: =IF(W116="SOPORTE_TELEFÓNICO",'BASE LIQUIDACION REDEBAN 2025'!$B$19,IF(W116="ENVÍO",'BASE LIQUIDACION REDEBAN 2025'!$C$2,IF(Y116="TIPO I",'BASE LIQUIDACION REDEBAN 2025'!$C$2,IF(Y116="TIPO II",'BASE LIQUIDACION REDEBAN 2025'!$C$3,IF(Y116="TIPO III",'BASE LIQUIDACION REDEBAN 2025'!$C$4,IF(Y116="TIPO IV",'BASE LIQUIDACION REDEBAN 2025'!$C$5,IF(Z116="AEREO",'BASE LIQUIDACION REDEBAN 2025'!$B$6,'BASE LIQUIDACION REDEBAN 2025'!$C$5))))))) -> 275728.78 | AE116: =IF(OR(W116="SOPORTE_TELEFÓNICO",W116="ENVÍO"),0,IF(Y116="TIPO I",'BASE LIQUIDACION REDEBAN 2025'!$B$10,IF(Y116="TIPO II",'BASE LIQUIDACION REDEBAN 2025'!$B$11,IF(Y116="TIPO III",'BASE LIQUIDACION REDEBAN 2025'!$B$12,'BASE LIQUIDACION REDEBAN 2025'!$B$13)))) -> 196536.53 | AF116: =IF(OR(W116="SOPORTE_TELEFÓNICO",W116="ENVÍO"),AD116,(AD116*AB116+AE116*AC116)) -> 275728.78
A117: MEDELLIN | B117: =VLOOKUP(A117,'CENTRO DE COSTOS'!A:D,4,FALSE) -> JUAN SEBASTIÁN RÍOS CASTRILLÓN | C117: =VLOOKUP(A117,'CENTRO DE COSTOS'!A:D,2,FALSE) -> 0004-0005 | D117: 5001 | E117: 2544505 | F117: 26224 | G117: INCIDENTE | H117: ANTIOQUIA | I117: MEDELLIN | J117: COMCARD MED JF | K117: REDEBAN | L117: FO-25-1322740 | M117: 45872.441 | N117: 45873.565 | O117: NO | P117: HARDWARE | Q117: HUB | R117: SE REINICIA | S117: AGREGADOR | U117: CERRADO | V117: 03/08/2025 03-08 SE ESCALA PARA VISITA. LLAMAR ANTES DE VISITAR, CONFIRMAR FALLA Y DATOS | 03/08/2025 EN COMUNICACIÓN CON EL SEÑOR JOHAN HURTADO RIVERA AL NÚMERO 3016510407, INFORMA QUE NUNCA LE HAN CAMBIADO EL DATÁFONO Y QUE ESTÁ FALLANDO MUCHO, SE LE INDICA QUE DÍAS DOMINGOS NO SE PUEDE CAMBIAR EQUIPOS POR QUE NO HAY SISTEMA PARA CAMBIOS, VISITAR EL DÍA DE MAÑANA A PRIMERA HORA | 04/08/2025 SE LLAMA AL PUNTO PARA PEDIRLE INDICACIONES PERO EL CLIENTE INFORMA QUE LA PERSONA NO LLEGA AL PUNTO HASTA LAS 10:30 POR LO QUE SE APLAZA VISITA HASTA DESPUÉS DE LAS 10:30 | 04/08/2025 SE CAMBIA HUB POR CONSTANTE REINICIO | W117: VISITA_TÉCNICA | X117: 99990998-IINZZ659 | Y117: TIPO I | Z117: TERRESTRE | AA117: ALVAREZ ARENAS VICTOR HUGO | AB117: 1 | AC117: 0 | AD117: =IF(W117="SOPORTE_TELEFÓNICO",'BASE LIQUIDACION REDEBAN 2025'!$B$19,IF(W117="ENVÍO",'BASE LIQUIDACION REDEBAN 2025'!$C$2,IF(Y117="TIPO I",'BASE LIQUIDACION REDEBAN 2025'!$C$2,IF(Y117="TIPO II",'BASE LIQUIDACION REDEBAN 2025'!$C$3,IF(Y117="TIPO III",'BASE LIQUIDACION REDEBAN 2025'!$C$4,IF(Y117="TIPO IV",'BASE LIQUIDACION REDEBAN 2025'!$C$5,IF(Z117="AEREO",'BASE LIQUIDACION REDEBAN 2025'!$B$6,'BASE LIQUIDACION REDEBAN 2025'!$C$5))))))) -> 65960.072 | AE117: =IF(OR(W117="SOPORTE_TELEFÓNICO",W117="ENVÍO"),0,IF(Y117="TIPO I",'BASE LIQUIDACION REDEBAN 2025'!$B$10,IF(Y117="TIPO II",'BASE LIQUIDACION REDEBAN 2025'!$B$11,IF(Y117="TIPO III",'BASE LIQUIDACION REDEBAN 2025'!$B$12,'BASE LIQUIDACION REDEBAN 2025'!$B$13)))) -> 75096.394 | AF117: =IF(OR(W117="SOPORTE_TELEFÓNICO",W117="ENVÍO"),AD117,(AD117*AB117+AE117*AC117)) -> 65960.072
A118: VILLAVICENCIO | B118: =VLOOKUP(A118,'CENTRO DE COSTOS'!A:D,4,FALSE) -> KEVIN ALEXIS CORZO BUSTOS | C118: =VLOOKUP(A118,'CENTRO DE COSTOS'!A:D,2,FALSE) -> 0004-0007 | D118: 50313 | E118: 2546858 | F118: 54880 | G118: INCIDENTE | H118: META | I118: GRANADA | J118: BARRIO LAS DELICIAS GRANADA 4 | K118: REDEBAN | L118: FO-25-1324924 | M118: 45873.404 | N118: 45873.567 | O118: NO | P118: HARDWARE | Q118: SE REINICIA | R118: DAÑO POS | S118: CB UNO A UNO | U118: CERRADO | V118: 04/08/2025 04-08 SE ESCALA PARA VISITA. LLAMAR ANTES DE VISITAR, CONFIRMAR FALLA Y DATOS | 04/08/2025 SE REALIZA CAMBIO DE HUB SE AJUSTA TAPA IMPRESIÓN PRUEBAS OK SIN NOVEDADES | W118: VISITA_TÉCNICA | X118: II9ZZ859 | Y118: TIPO II | Z118: TERRESTRE | AA118: CASTRILLON URREA LONDIER LEANDRO | AB118: 1 | AC118: 0 | AD118: =IF(W118="SOPORTE_TELEFÓNICO",'BASE LIQUIDACION REDEBAN 2025'!$B$19,IF(W118="ENVÍO",'BASE LIQUIDACION REDEBAN 2025'!$C$2,IF(Y118="TIPO I",'BASE LIQUIDACION REDEBAN 2025'!$C$2,IF(Y118="TIPO II",'BASE LIQUIDACION REDEBAN 2025'!$C$3,IF(Y118="TIPO III",'BASE LIQUIDACION REDEBAN 2025'!$C$4,IF(Y118="TIPO IV",'BASE LIQUIDACION REDEBAN 2025'!$C$5,IF(Z118="AEREO",'BASE LIQUIDACION REDEBAN 2025'!$B$6,'BASE LIQUIDACION REDEBAN 2025'!$C$5))))))) -> 144967.87 | AE118: =IF(OR(W118="SOPORTE_TELEFÓNICO",W118="ENVÍO"),0,IF(Y118="TIPO I",'BASE LIQUIDACION REDEBAN 2025'!$B$10,IF(Y118="TIPO II",'BASE LIQUIDACION REDEBAN 2025'!$B$11,IF(Y118="TIPO III",'BASE LIQUIDACION REDEBAN 2025'!$B$12,'BASE LIQUIDACION REDEBAN 2025'!$B$13)))) -> 140395.63 | AF118: =IF(OR(W118="SOPORTE_TELEFÓNICO",W118="ENVÍO"),AD118,(AD118*AB118+AE118*AC118)) -> 144967.87
A119: BUCARAMANGA | B119: =VLOOKUP(A119,'CENTRO DE COSTOS'!A:D,4,FALSE) -> MIGUEL JULIÁN HERNÁNDEZ GUARÍN | C119: =VLOOKUP(A119,'CENTRO DE COSTOS'!A:D,2,FALSE) -> 0004-0008 | D119: 68081 | E119: 2539559 | F119: 61521 | G119: INCIDENTE | H119: SANTANDER | I119: BARRANCABERMEJA | J119: BARRIO TORCOROMA BARRANCABERME | K119: REDEBAN | L119: FO-25-1316389 | M119: 45870.472 | N119: 45873.574 | O119: NO | P119: HARDWARE | Q119: COMUNICACION | R119: MENSAJE CABLE DE RED DESCONECTADO | S119: CB UNO A UNO | U119: CERRADO | V119: 01/08/2025 01-08 EN COMUNICACION CON EL SEÑOR ADRIAN ZAMBRANO AL NUMERO 3124542809, CONFIRMA FALLA, DATOS CORRECTOS. SE ESCALA PARA VISITA | 04/08/2025 SE HACE PRESENCIA EN COMERCIO SE REALIZA CAMBIO DE EQUIPO DEBIDO A QUE NO COMUNICA CON EL MÓDEM DEL INTERNET SE REALIZAN PRUEBAS OK SE CREAN USUARIOS Y CONTRASEÑA | W119: VISITA_TÉCNICA | X119: JA00H773 | Y119: TIPO III | Z119: TERRESTRE | AA119: ORTEBARRERAGA MARLON STWAR | AB119: 1 | AC119: 0 | AD119: =IF(W119="SOPORTE_TELEFÓNICO",'BASE LIQUIDACION REDEBAN 2025'!$B$19,IF(W119="ENVÍO",'BASE LIQUIDACION REDEBAN 2025'!$C$2,IF(Y119="TIPO I",'BASE LIQUIDACION REDEBAN 2025'!$C$2,IF(Y119="TIPO II",'BASE LIQUIDACION REDEBAN 2025'!$C$3,IF(Y119="TIPO III",'BASE LIQUIDACION REDEBAN 2025'!$C$4,IF(Y119="TIPO IV",'BASE LIQUIDACION REDEBAN 2025'!$C$5,IF(Z119="AEREO",'BASE LIQUIDACION REDEBAN 2025'!$B$6,'BASE LIQUIDACION REDEBAN 2025'!$C$5))))))) -> 275728.78 | AE119: =IF(OR(W119="SOPORTE_TELEFÓNICO",W119="ENVÍO"),0,IF(Y119="TIPO I",'BASE LIQUIDACION REDEBAN 2025'!$B$10,IF(Y119="TIPO II",'BASE LIQUIDACION REDEBAN 2025'!$B$11,IF(Y119="TIPO III",'BASE LIQUIDACION REDEBAN 2025'!$B$12,'BASE LIQUIDACION REDEBAN 2025'!$B$13)))) -> 196536.53 | AF119: =IF(OR(W119="SOPORTE_TELEFÓNICO",W119="ENVÍO"),AD119,(AD119*AB119+AE119*AC119)) -> 275728.78
A120: BUCARAMANGA | B120: =VLOOKUP(A120,'CENTRO DE COSTOS'!A:D,4,FALSE) -> MIGUEL JULIÁN HERNÁNDEZ GUARÍN | C120: =VLOOKUP(A120,'CENTRO DE COSTOS'!A:D,2,FALSE) -> 0004-0008 | D120: 68276 | E120: 2546503 | F120: 43211 | G120: INCIDENTE | H120: SANTANDER | I120: FLORIDABLANCA | J120: BARRIO PRADOS DEL SUR FLORIDAB | K120: REDEBAN | L120: FO-25-1324562 | M120: 45873.386 | N120: 45873.587 | O120: NO | P120: SOFTWARE | Q120: COMUNICACION | R120: VERIFIQUE PARAMETROS | S120: CB UNO A UNO | U120: CERRADO | V120: 04/08/2025 04-08 SE ESCALA PARA VISITA. LLAMAR ANTES DE VISITAR, CONFIRMAR FALLA Y DATOS | 04/08/2025 SE REALIZA BORRADO EL INYECCIÓN DE VECINO A LOS DATÁFONO POR ERROR DE PARÁMETROS, MENSAJE DEBE INICIALIZAR, PRUEBAS Y LIMPIEZA DE EQUIPOS OK. | W120: VISITA_TÉCNICA | X120: GZFZZ783 - EG0IZ238 | Y120: TIPO I | Z120: TERRESTRE | AA120: MARTINEZ FLOREZ DONIS ALBERTO | AB120: 1 | AC120: 0 | AD120: =IF(W120="SOPORTE_TELEFÓNICO",'BASE LIQUIDACION REDEBAN 2025'!$B$19,IF(W120="ENVÍO",'BASE LIQUIDACION REDEBAN 2025'!$C$2,IF(Y120="TIPO I",'BASE LIQUIDACION REDEBAN 2025'!$C$2,IF(Y120="TIPO II",'BASE LIQUIDACION REDEBAN 2025'!$C$3,IF(Y120="TIPO III",'BASE LIQUIDACION REDEBAN 2025'!$C$4,IF(Y120="TIPO IV",'BASE LIQUIDACION REDEBAN 2025'!$C$5,IF(Z120="AEREO",'BASE LIQUIDACION REDEBAN 2025'!$B$6,'BASE LIQUIDACION REDEBAN 2025'!$C$5))))))) -> 65960.072 | AE120: =IF(OR(W120="SOPORTE_TELEFÓNICO",W120="ENVÍO"),0,IF(Y120="TIPO I",'BASE LIQUIDACION REDEBAN 2025'!$B$10,IF(Y120="TIPO II",'BASE LIQUIDACION REDEBAN 2025'!$B$11,IF(Y120="TIPO III",'BASE LIQUIDACION REDEBAN 2025'!$B$12,'BASE LIQUIDACION REDEBAN 2025'!$B$13)))) -> 75096.394 | AF120: =IF(OR(W120="SOPORTE_TELEFÓNICO",W120="ENVÍO"),AD120,(AD120*AB120+AE120*AC120)) -> 65960.072
A121: MEDELLIN | B121: =VLOOKUP(A121,'CENTRO DE COSTOS'!A:D,4,FALSE) -> JUAN SEBASTIÁN RÍOS CASTRILLÓN | C121: =VLOOKUP(A121,'CENTRO DE COSTOS'!A:D,2,FALSE) -> 0004-0005 | D121: 5001 | E121: 2544634 | F121: 71080 | G121: INCIDENTE | H121: ANTIOQUIA | I121: MEDELLIN | J121: DROGUERIA LA BOTIQUERIA | K121: REDEBAN | L121: FO-25-1323619 | M121: 45872.742 | N121: 45873.598 | O121: NO | P121: SOFTWARE | Q121: COMUNICACION | R121: PARAMETROS DE CONFIGURACION EN POS | S121: AGREGADOR | U121: CERRADO | V121: 04/08/2025 03-08 SE ESCALA PARA VISITA. LLAMAR ANTES DE VISITAR, CONFIRMAR FALLA Y DATOS | 04/08/2025 SE REALIZA CONFIGURACIÓN DE PARÁMETROS DE COMUNICACIÓN | W121: VISITA_TÉCNICA | X121: NN00B502 - NN00B988 | Y121: TIPO I | Z121: TERRESTRE | AA121: CASTAÑEDA PALACIO CARLOS FELIPE | AB121: 1 | AC121: 0 | AD121: =IF(W121="SOPORTE_TELEFÓNICO",'BASE LIQUIDACION REDEBAN 2025'!$B$19,IF(W121="ENVÍO",'BASE LIQUIDACION REDEBAN 2025'!$C$2,IF(Y121="TIPO I",'BASE LIQUIDACION REDEBAN 2025'!$C$2,IF(Y121="TIPO II",'BASE LIQUIDACION REDEBAN 2025'!$C$3,IF(Y121="TIPO III",'BASE LIQUIDACION REDEBAN 2025'!$C$4,IF(Y121="TIPO IV",'BASE LIQUIDACION REDEBAN 2025'!$C$5,IF(Z121="AEREO",'BASE LIQUIDACION REDEBAN 2025'!$B$6,'BASE LIQUIDACION REDEBAN 2025'!$C$5))))))) -> 65960.072 | AE121: =IF(OR(W121="SOPORTE_TELEFÓNICO",W121="ENVÍO"),0,IF(Y121="TIPO I",'BASE LIQUIDACION REDEBAN 2025'!$B$10,IF(Y121="TIPO II",'BASE LIQUIDACION REDEBAN 2025'!$B$11,IF(Y121="TIPO III",'BASE LIQUIDACION REDEBAN 2025'!$B$12,'BASE LIQUIDACION REDEBAN 2025'!$B$13)))) -> 75096.394 | AF121: =IF(OR(W121="SOPORTE_TELEFÓNICO",W121="ENVÍO"),AD121,(AD121*AB121+AE121*AC121)) -> 65960.072
... A124: TUNJA | B124: =VLOOKUP(A124,'CENTRO DE COSTOS'!A:D,4,FALSE) -> MIGUEL JULIÁN HERNÁNDEZ GUARÍN | C124: =VLOOKUP(A124,'CENTRO DE COSTOS'!A:D,2,FALSE) -> 0004-0008 | D124: 15051 | E124: 2547119 | F124: 78803 | G124: INCIDENTE | H124: BOYACA | I124: ARCABUCO | J124: BARRIO VEREDA QUIRBAQUIRA ARCABUCO 1 | K124: REDEBAN | L124: FO-25-1324926 | M124: 45873.411 | N124: 45873.624 | O124: NO | P124: HARDWARE | Q124: ALERT IRRUPTION | R124: ALERT IRRUPTION | S124: CB UNO A UNO | U124: CERRADO | V124: 04/08/2025 SE VISITA CB MANTENIMIENTO DE EQUIPO....CAMBIO DE POS POR DAÑO PRUEBAS EXITOSAS | W124: VISITA_TÉCNICA | X124: V1SZZ185 | Y124: TIPO II | Z124: TERRESTRE | AA124: GONZALEZ GONZALEZ MARIO ALBERTO | AB124: 1 | AC124: 0 | AD124: =IF(W124="SOPORTE_TELEFÓNICO",'BASE LIQUIDACION REDEBAN 2025'!$B$19,IF(W124="ENVÍO",'BASE LIQUIDACION REDEBAN 2025'!$C$2,IF(Y124="TIPO I",'BASE LIQUIDACION REDEBAN 2025'!$C$2,IF(Y124="TIPO II",'BASE LIQUIDACION REDEBAN 2025'!$C$3,IF(Y124="TIPO III",'BASE LIQUIDACION REDEBAN 2025'!$C$4,IF(Y124="TIPO IV",'BASE LIQUIDACION REDEBAN 2025'!$C$5,IF(Z124="AEREO",'BASE LIQUIDACION REDEBAN 2025'!$B$6,'BASE LIQUIDACION REDEBAN 2025'!$C$5))))))) -> 144967.87 | AE124: =IF(OR(W124="SOPORTE_TELEFÓNICO",W124="ENVÍO"),0,IF(Y124="TIPO I",'BASE LIQUIDACION REDEBAN 2025'!$B$10,IF(Y124="TIPO II",'BASE LIQUIDACION REDEBAN 2025'!$B$11,IF(Y124="TIPO III",'BASE LIQUIDACION REDEBAN 2025'!$B$12,'BASE LIQUIDACION REDEBAN 2025'!$B$13)))) -> 140395.63 | AF124: =IF(OR(W124="SOPORTE_TELEFÓNICO",W124="ENVÍO"),AD124,(AD124*AB124+AE124*AC124)) -> 144967.87
A125: MANIZALES | B125: =VLOOKUP(A125,'CENTRO DE COSTOS'!A:D,4,FALSE) -> DIEGO FERNANDO HENAO CARDONA | C125: =VLOOKUP(A125,'CENTRO DE COSTOS'!A:D,2,FALSE) -> 0004-0002 | D125: 17001 | E125: 2549526 | F125: 26570 | G125: INCIDENTE | H125: CALDAS | I125: MANIZALES | J125: BARRIO FANNY GONZALEZ MANIZALE | K125: REDEBAN | L125: FO-25-1326659 | M125: 45873.544 | N125: 45873.632 | O125: NO | P125: HARDWARE | Q125: TECLADO | R125: DAÑO POS | S125: CB UNO A UNO | U125: CERRADO | V125: 04/08/2025 04-08 SE ESCALA PARA VISITA. LLAMAR ANTES DE VISITAR, CONFIRMAR FALLA Y DATOS | 04/08/2025 SE REALIZA LLAMADA CON USUARIO PARA VALIDAR ATENCIÓN DE LA VISITA INDICA QUE NO PUEDE ATENDER EN EL MOMENTO, SE ENCUENTRA OCUPADA, SE LE INDICA QUE POR VENCIMIENTO DE LAS VISITAS DEBERA DE LLAMAR NUEVAMENTE PARA SOLICITAR EL SERVICIO, INDICA NO TENER INCONVENIENTES CON LLAMAR DE NUEVO PARA CUANDO TENGA DISPONIBILIDAD | W125: SOPORTE_TELEFÓNICO | X125: 0 | Y125: TIPO I | Z125: TERRESTRE | AA125: AGUIRRE HENAO RAUL EDUARDO | AB125: 0 | AC125: 0 | AD125: =IF(W125="SOPORTE_TELEFÓNICO",'BASE LIQUIDACION REDEBAN 2025'!$B$19,IF(W125="ENVÍO",'BASE LIQUIDACION REDEBAN 2025'!$C$2,IF(Y125="TIPO I",'BASE LIQUIDACION REDEBAN 2025'!$C$2,IF(Y125="TIPO II",'BASE LIQUIDACION REDEBAN 2025'!$C$3,IF(Y125="TIPO III",'BASE LIQUIDACION REDEBAN 2025'!$C$4,IF(Y125="TIPO IV",'BASE LIQUIDACION REDEBAN 2025'!$C$5,IF(Z125="AEREO",'BASE LIQUIDACION REDEBAN 2025'!$B$6,'BASE LIQUIDACION REDEBAN 2025'!$C$5))))))) -> 41241.08 | AE125: =IF(OR(W125="SOPORTE_TELEFÓNICO",W125="ENVÍO"),0,IF(Y125="TIPO I",'BASE LIQUIDACION REDEBAN 2025'!$B$10,IF(Y125="TIPO II",'BASE LIQUIDACION REDEBAN 2025'!$B$11,IF(Y125="TIPO III",'BASE LIQUIDACION REDEBAN 2025'!$B$12,'BASE LIQUIDACION REDEBAN 2025'!$B$13)))) -> 0 | AF125: =IF(OR(W125="SOPORTE_TELEFÓNICO",W125="ENVÍO"),AD125,(AD125*AB125+AE125*AC125)) -> 41241.08
A126: CALI | B126: =VLOOKUP(A126,'CENTRO DE COSTOS'!A:D,4,FALSE) -> DIEGO FERNANDO HENAO CARDONA | C126: =VLOOKUP(A126,'CENTRO DE COSTOS'!A:D,2,FALSE) -> 0004-0003 | D126: 76001 | E126: 2548440 | F126: 46250 | G126: INCIDENTE | H126: VALLE DEL CAUCA | I126: CALI | J126: BARRIO TRONCAL CALI | K126: REDEBAN | L126: FO-25-1325892 | M126: 45873.471 | N126: 45873.633 | O126: NO | P126: HARDWARE | Q126: LECTOR DE BARRAS | R126: CABLE LECTORA AVERIADO | S126: CB UNO A UNO | U126: CERRADO | V126: 04/08/2025 SE REALIZA CAMBIO DE LECTOR POR DAÑO EN EL CABLEADO. SE REALIZAN PRUEBAS OPERATIVAS SIN NOVEDAD | W126: VISITA_TÉCNICA | X126: 9C006208 | Y126: TIPO I | Z126: TERRESTRE | AA126: TORRES GARCIA JENDRY JOSE | AB126: 1 | AC126: 0 | AD126: =IF(W126="SOPORTE_TELEFÓNICO",'BASE LIQUIDACION REDEBAN 2025'!$B$19,IF(W126="ENVÍO",'BASE LIQUIDACION REDEBAN 2025'!$C$2,IF(Y126="TIPO I",'BASE LIQUIDACION REDEBAN 2025'!$C$2,IF(Y126="TIPO II",'BASE LIQUIDACION REDEBAN 2025'!$C$3,IF(Y126="TIPO III",'BASE LIQUIDACION REDEBAN 2025'!$C$4,IF(Y126="TIPO IV",'BASE LIQUIDACION REDEBAN 2025'!$C$5,IF(Z126="AEREO",'BASE LIQUIDACION REDEBAN 2025'!$B$6,'BASE LIQUIDACION REDEBAN 2025'!$C$5))))))) -> 65960.072 | AE126: =IF(OR(W126="SOPORTE_TELEFÓNICO",W126="ENVÍO"),0,IF(Y126="TIPO I",'BASE LIQUIDACION REDEBAN 2025'!$B$10,IF(Y126="TIPO II",'BASE LIQUIDACION REDEBAN 2025'!$B$11,IF(Y126="TIPO III",'BASE LIQUIDACION REDEBAN 2025'!$B$12,'BASE LIQUIDACION REDEBAN 2025'!$B$13)))) -> 75096.394 | AF126: =IF(OR(W126="SOPORTE_TELEFÓNICO",W126="ENVÍO"),AD126,(AD126*AB126+AE126*AC126)) -> 65960.072
A127: BUCARAMANGA | B127: =VLOOKUP(A127,'CENTRO DE COSTOS'!A:D,4,FALSE) -> MIGUEL JULIÁN HERNÁNDEZ GUARÍN | C127: =VLOOKUP(A127,'CENTRO DE COSTOS'!A:D,2,FALSE) -> 0004-0008 | D127: 68001 | E127: 2546947 | F127: 59329 | G127: INCIDENTE | H127: SANTANDER | I127: BUCARAMANGA | J127: DISTRICOL ASESORATE Y LUNAAZUL | K127: REDEBAN | L127: FO-25-1324916 | M127: 45873.412 | N127: 45873.636 | O127: NO | P127: HARDWARE | Q127: IMPRESION | R127: NO IMPRIME UNO O VARIOS CARACTERES | S127: AGREGADOR | U127: CERRADO | V127: 04/08/2025 | SE LLEGA A SITIO SE HACEN VALIDACIONES E IMPRIME BORROSO DEBIDO A QUE EL ROLLO SE ENCONTRABA EN MAL ESTADO, SE COLOCA UN ROLLO NUEVO Y SE HACEN PRUEBAS Y DATAFONO QUEDA OPERATIVO FUNCIONANDO CORRECTAMENTE, VISITA EXITOSA | W127: VISITA_TÉCNICA | X127: FUA05642 | Y127: TIPO I | Z127: TERRESTRE | AA127: GELVEZ MOGOLLON JOSE ELISEO | AB127: 1 | AC127: 0 | AD127: =IF(W127="SOPORTE_TELEFÓNICO",'BASE LIQUIDACION REDEBAN 2025'!$B$19,IF(W127="ENVÍO",'BASE LIQUIDACION REDEBAN 2025'!$C$2,IF(Y127="TIPO I",'BASE LIQUIDACION REDEBAN 2025'!$C$2,IF(Y127="TIPO II",'BASE LIQUIDACION REDEBAN 2025'!$C$3,IF(Y127="TIPO III",'BASE LIQUIDACION REDEBAN 2025'!$C$4,IF(Y127="TIPO IV",'BASE LIQUIDACION REDEBAN 2025'!$C$5,IF(Z127="AEREO",'BASE LIQUIDACION REDEBAN 2025'!$B$6,'BASE LIQUIDACION REDEBAN 2025'!$C$5))))))) -> 65960.072 | AE127: =IF(OR(W127="SOPORTE_TELEFÓNICO",W127="ENVÍO"),0,IF(Y127="TIPO I",'BASE LIQUIDACION REDEBAN 2025'!$B$10,IF(Y127="TIPO II",'BASE LIQUIDACION REDEBAN 2025'!$B$11,IF(Y127="TIPO III",'BASE LIQUIDACION REDEBAN 2025'!$B$12,'BASE LIQUIDACION REDEBAN 2025'!$B$13)))) -> 75096.394 | AF127: =IF(OR(W127="SOPORTE_TELEFÓNICO",W127="ENVÍO"),AD127,(AD127*AB127+AE127*AC127)) -> 65960.072
A128: MEDELLIN | B128: =VLOOKUP(A128,'CENTRO DE COSTOS'!A:D,4,FALSE) -> JUAN SEBASTIÁN RÍOS CASTRILLÓN | C128: =VLOOKUP(A128,'CENTRO DE COSTOS'!A:D,2,FALSE) -> 0004-0005 | D128: 5001 | E128: 2546808 | F128: 10314 | G128: INCIDENTE | H128: ANTIOQUIA | I128: MEDELLIN | J128: BARRIO POPULAR II | K128: REDEBAN | L128: FO-25-1324939 | M128: 45873.4 | N128: 45873.639 | O128: NO | P128: HARDWARE | Q128: LECTOR DE BARRAS | R128: FORMATO INVALIDO LECTOR DAÑADO | S128: CB UNO A UNO | U128: CERRADO | V128: 04/08/2025 | SE HACE MANTENIMIENTO SE OK SE CAMBIA FUENTE DE PODER | W128: VISITA_TÉCNICA | X128: JAAAC740 | Y128: TIPO I | Z128: TERRESTRE | AA128: DIAZ ZABALA FRANCIS DUBAN | AB128: 1 | AC128: 0 | AD128: =IF(W128="SOPORTE_TELEFÓNICO",'BASE LIQUIDACION REDEBAN 2025'!$B$19,IF(W128="ENVÍO",'BASE LIQUIDACION REDEBAN 2025'!$C$2,IF(Y128="TIPO I",'BASE LIQUIDACION REDEBAN 2025'!$C$2,IF(Y128="TIPO II",'BASE LIQUIDACION REDEBAN 2025'!$C$3,IF(Y128="TIPO III",'BASE LIQUIDACION REDEBAN 2025'!$C$4,IF(Y128="TIPO IV",'BASE LIQUIDACION REDEBAN 2025'!$C$5,IF(Z128="AEREO",'BASE LIQUIDACION REDEBAN 2025'!$B$6,'BASE LIQUIDACION REDEBAN 2025'!$C$5))))))) -> 65960.072 | AE128: =IF(OR(W128="SOPORTE_TELEFÓNICO",W128="ENVÍO"),0,IF(Y128="TIPO I",'BASE LIQUIDACION REDEBAN 2025'!$B$10,IF(Y128="TIPO II",'BASE LIQUIDACION REDEBAN 2025'!$B$11,IF(Y128="TIPO III",'BASE LIQUIDACION REDEBAN 2025'!$B$12,'BASE LIQUIDACION REDEBAN 2025'!$B$13)))) -> 75096.394 | AF128: =IF(OR(W128="SOPORTE_TELEFÓNICO",W128="ENVÍO"),AD128,(AD128*AB128+AE128*AC128)) -> 65960.072
A129: CARTAGENA | B129: =VLOOKUP(A129,'CENTRO DE COSTOS'!A:D,4,FALSE) -> JOSE MAURICIO HERNANDEZ ROJAS | C129: =VLOOKUP(A129,'CENTRO DE COSTOS'!A:D,2,FALSE) -> 0004-0001 | D129: 13001 | E129: 2546070 | F129: 35961 | G129: INCIDENTE | H129: BOLIVAR | I129: CARTAGENA | J129: BARRIO LA CONSOLATA SECT VILLA | K129: REDEBAN | L129: FO-25-1324572 | M129: 45873.381 | N129: 45873.643 | O129: NO | P129: HARDWARE | Q129: COMUNICACION | R129: DAÑO POS | S129: CB UNO A UNO | U129: CERRADO | V129: 04/08/2025 04-08 SE ESCALA PARA VISITA. LLAMAR ANTES DE VISITAR, CONFIRMAR FALLA Y DATOS | 04/08/2025 BUEN DIA SE REALIZA CAMBIO DE EQUIPO POR DAÑO DEL PUERTO DE RED , SE DEJA INSTALADO UNO NUEVO CON MAGIC BOX SE HACEN PRUEBAS Y TODO QUEDA OK | W129: VISITA_TÉCNICA | X129: GZ006871 | Y129: TIPO I | Z129: TERRESTRE | AA129: MARTINEZ SALGUEDO ANDRES AUGUSTO | AB129: 1 | AC129: 0 | AD129: =IF(W129="SOPORTE_TELEFÓNICO",'BASE LIQUIDACION REDEBAN 2025'!$B$19,IF(W129="ENVÍO",'BASE LIQUIDACION REDEBAN 2025'!$C$2,IF(Y129="TIPO I",'BASE LIQUIDACION REDEBAN 2025'!$C$2,IF(Y129="TIPO II",'BASE LIQUIDACION REDEBAN 2025'!$C$3,IF(Y129="TIPO III",'BASE LIQUIDACION REDEBAN 2025'!$C$4,IF(Y129="TIPO IV",'BASE LIQUIDACION REDEBAN 2025'!$C$5,IF(Z129="AEREO",'BASE LIQUIDACION REDEBAN 2025'!$B$6,'BASE LIQUIDACION REDEBAN 2025'!$C$5))))))) -> 65960.072 | AE129: =IF(OR(W129="SOPORTE_TELEFÓNICO",W129="ENVÍO"),0,IF(Y129="TIPO I",'BASE LIQUIDACION REDEBAN 2025'!$B$10,IF(Y129="TIPO II",'BASE LIQUIDACION REDEBAN 2025'!$B$11,IF(Y129="TIPO III",'BASE LIQUIDACION REDEBAN 2025'!$B$12,'BASE LIQUIDACION REDEBAN 2025'!$B$13)))) -> 75096.394 | AF129: =IF(OR(W129="SOPORTE_TELEFÓNICO",W129="ENVÍO"),AD129,(AD129*AB129+AE129*AC129)) -> 65960.072
A130: SANTA MARTA | B130: =VLOOKUP(A130,'CENTRO DE COSTOS'!A:D,4,FALSE) -> JOSE MAURICIO HERNANDEZ ROJAS | C130: =VLOOKUP(A130,'CENTRO DE COSTOS'!A:D,2,FALSE) -> 0004-0001 | D130: 47001 | E130: 2545507 | F130: 45850 | G130: INCIDENTE | H130: MAGDALENA | I130: SANTA MARTA | J130: DISTRICOL DROGUERIA VILLA DEL | K130: REDEBAN | L130: FO-25-1325532 | M130: 45873.348 | N130: 45873.647 | O130: NO | P130: HARDWARE | Q130: COMUNICACION | R130: MENSAJE CABLE DE RED DESCONECTADO | S130: AGREGADOR | U130: CERRADO | V130: 04/08/2025 SE REALIZA LA VISITA, SE ENCUENTRA EL DATÁFONO SIN INTERNET SE REVISA EL PUERTO EL CABLEADO Y CONFIGURACIÓN PERO EL PROBLEMA PERSISTE, EL CLIENTE INFORMA QUE SE DAÑO DESPUÉS DE UN FUERTE TRUENO EN EL SECTOR, SE PROCEDE A CAMBIAR EL EQUIPO, SE REALIZAN PRUEBAS Y TODO OK | W130: VISITA_TÉCNICA | X130: XP000823 | Y130: TIPO I | Z130: TERRESTRE | AA130: THOMAS CAMPO SIGIFREDO SEGUNDO | AB130: 2 | AC130: 0 | AD130: =IF(W130="SOPORTE_TELEFÓNICO",'BASE LIQUIDACION REDEBAN 2025'!$B$19,IF(W130="ENVÍO",'BASE LIQUIDACION REDEBAN 2025'!$C$2,IF(Y130="TIPO I",'BASE LIQUIDACION REDEBAN 2025'!$C$2,IF(Y130="TIPO II",'BASE LIQUIDACION REDEBAN 2025'!$C$3,IF(Y130="TIPO III",'BASE LIQUIDACION REDEBAN 2025'!$C$4,IF(Y130="TIPO IV",'BASE LIQUIDACION REDEBAN 2025'!$C$5,IF(Z130="AEREO",'BASE LIQUIDACION REDEBAN 2025'!$B$6,'BASE LIQUIDACION REDEBAN 2025'!$C$5))))))) -> 65960.072 | AE130: =IF(OR(W130="SOPORTE_TELEFÓNICO",W130="ENVÍO"),0,IF(Y130="TIPO I",'BASE LIQUIDACION REDEBAN 2025'!$B$10,IF(Y130="TIPO II",'BASE LIQUIDACION REDEBAN 2025'!$B$11,IF(Y130="TIPO III",'BASE LIQUIDACION REDEBAN 2025'!$B$12,'BASE LIQUIDACION REDEBAN 2025'!$B$13)))) -> 75096.394 | AF130: =IF(OR(W130="SOPORTE_TELEFÓNICO",W130="ENVÍO"),AD130,(AD130*AB130+AE130*AC130)) -> 131920.14
A131: CALI | B131: =VLOOKUP(A131,'CENTRO DE COSTOS'!A:D,4,FALSE) -> DIEGO FERNANDO HENAO CARDONA | C131: =VLOOKUP(A131,'CENTRO DE COSTOS'!A:D,2,FALSE) -> 0004-0003 | D131: 76248 | E131: 2545093 | F131: 21205 | G131: INCIDENTE | H131: VALLE DEL CAUCA | I131: EL CERRITO | J131: MULTIPAGAS CERRITO PARQUE | K131: REDEBAN | L131: FO-25-1323978 | M131: 45873.333 | N131: 45873.65 | O131: NO | P131: HARDWARE | Q131: ALERT IRRUPTION | R131: ALERT IRRUPTION | S131: ROBUSTO | U131: CERRADO | V131: 04/08/2025 04-08 SE ESCALA PARA VISITA. LLAMAR ANTES DE VISITAR, CONFIRMAR FALLA Y DATOS | 04/08/2025 EN LA VISITA TÉCNICA SE REALIZÓ EL CAMBIO DE DATÁFONO YA QUE SE ENCONTRÓ BLOQUEADO (ALERT IRRUPTION) SE INSTALO MAGIC BOX 2600, SE INSTALO EL SISTEMA OPERATIVO Y VERSIÓN 10.3N SE CREARON LOS USUARIOS Y SE REALIZARON LAS PRUEBAS OK, SE REALIZÓ LA CONFIGURACIÓN DEL LECTOR MOTOROLA SYMBOL Y SE REALIZARON LAS PRUEBAS DEJANDO EL SERVICIO OPERANDO SIN FALLAS Y SIN NOVEDAD | W131: VISITA_TÉCNICA | X131: AAAXZ468 | Y131: TIPO II | Z131: TERRESTRE | AA131: SANCHEZ URREGO ROBINSON DAVID | AB131: 1 | AC131: 0 | AD131: =IF(W131="SOPORTE_TELEFÓNICO",'BASE LIQUIDACION REDEBAN 2025'!$B$19,IF(W131="ENVÍO",'BASE LIQUIDACION REDEBAN 2025'!$C$2,IF(Y131="TIPO I",'BASE LIQUIDACION REDEBAN 2025'!$C$2,IF(Y131="TIPO II",'BASE LIQUIDACION REDEBAN 2025'!$C$3,IF(Y131="TIPO III",'BASE LIQUIDACION REDEBAN 2025'!$C$4,IF(Y131="TIPO IV",'BASE LIQUIDACION REDEBAN 2025'!$C$5,IF(Z131="AEREO",'BASE LIQUIDACION REDEBAN 2025'!$B$6,'BASE LIQUIDACION REDEBAN 2025'!$C$5))))))) -> 144967.87 | AE131: =IF(OR(W131="SOPORTE_TELEFÓNICO",W131="ENVÍO"),0,IF(Y131="TIPO I",'BASE LIQUIDACION REDEBAN 2025'!$B$10,IF(Y131="TIPO II",'BASE LIQUIDACION REDEBAN 2025'!$B$11,IF(Y131="TIPO III",'BASE LIQUIDACION REDEBAN 2025'!$B$12,'BASE LIQUIDACION REDEBAN 2025'!$B$13)))) -> 140395.63 | AF131: =IF(OR(W131="SOPORTE_TELEFÓNICO",W131="ENVÍO"),AD131,(AD131*AB131+AE131*AC131)) -> 144967.87
A132: MEDELLIN | B132: =VLOOKUP(A132,'CENTRO DE COSTOS'!A:D,4,FALSE) -> JUAN SEBASTIÁN RÍOS CASTRILLÓN | C132: =VLOOKUP(A132,'CENTRO DE COSTOS'!A:D,2,FALSE) -> 0004-0005 | D132: 5001 | E132: 2544438 | F132: 74179 | G132: INCIDENTE | H132: ANTIOQUIA | I132: MEDELLIN | J132: BARRIO BOSTON MEDELLI 5 | K132: REDEBAN | L132: FO-25-1322742 | M132: 45872.44 | N132: 45873.657 | O132: NO | P132: HARDWARE | Q132: LECTOR DE TARJETAS | R132: MENSAJE RETIRE TARJETA | S132: CB UNO A UNO | U132: CERRADO | V132: 03/08/2025 03-08 SE ESCALA PARA VISITA. LLAMAR ANTES DE VISITAR, CONFIRMAR FALLA Y DATOS | 03/08/2025 EN COMUNICACIÓN CON LA SEÑORA ADRIANA JARAMILLO AL NÚMERO 3113391198 INFORMA QUE REQUIERE CAMBIAR DATÁFONO YA QUE NO LEE NINGUNA TARJETA, SE LE INFORMA QUE EL DÍA DE HOY NO SE PUEDEN REALIZAR CAMBIOS DE EQUIPO YA QUE EL SISTEMA NO LO PERMITE, LA VISITA CON EL POSIBLE CAMBIO DE EQUIPO QUEDA PARA MAÑANA LUNES Y LA SEÑORA ACEPTA | 04/08/2025 SE REVISA EQUIPO, Y SE REALIZA MANTENIMIENTO Y SIGUE EL PROBLEMA SE REALIZA CAMBIO DE EQUIPO SE REALIZA PRUEBAS EXITOSAS SERVICIO OPERATIVO OK | W132: VISITA_TÉCNICA | X132: FAUZZ227 | Y132: TIPO I | Z132: TERRESTRE | AA132: ZAPATA LOPEZ EDWARD ASDRUBAL | AB132: 1 | AC132: 0 | AD132: =IF(W132="SOPORTE_TELEFÓNICO",'BASE LIQUIDACION REDEBAN 2025'!$B$19,IF(W132="ENVÍO",'BASE LIQUIDACION REDEBAN 2025'!$C$2,IF(Y132="TIPO I",'BASE LIQUIDACION REDEBAN 2025'!$C$2,IF(Y132="TIPO II",'BASE LIQUIDACION REDEBAN 2025'!$C$3,IF(Y132="TIPO III",'BASE LIQUIDACION REDEBAN 2025'!$C$4,IF(Y132="TIPO IV",'BASE LIQUIDACION REDEBAN 2025'!$C$5,IF(Z132="AEREO",'BASE LIQUIDACION REDEBAN 2025'!$B$6,'BASE LIQUIDACION REDEBAN 2025'!$C$5))))))) -> 65960.072 | AE132: =IF(OR(W132="SOPORTE_TELEFÓNICO",W132="ENVÍO"),0,IF(Y132="TIPO I",'BASE LIQUIDACION REDEBAN 2025'!$B$10,IF(Y132="TIPO II",'BASE LIQUIDACION REDEBAN 2025'!$B$11,IF(Y132="TIPO III",'BASE LIQUIDACION REDEBAN 2025'!$B$12,'BASE LIQUIDACION REDEBAN 2025'!$B$13)))) -> 75096.394 | AF132: =IF(OR(W132="SOPORTE_TELEFÓNICO",W132="ENVÍO"),AD132,(AD132*AB132+AE132*AC132)) -> 65960.072
A133: MEDELLIN | B133: =VLOOKUP(A133,'CENTRO DE COSTOS'!A:D,4,FALSE) -> JUAN SEBASTIÁN RÍOS CASTRILLÓN | C133: =VLOOKUP(A133,'CENTRO DE COSTOS'!A:D,2,FALSE) -> 0004-0005 | D133: 5001 | E133: 2543942 | F133: 61259 | G133: INCIDENTE | H133: ANTIOQUIA | I133: MEDELLIN | J133: BARRIO SANTA FE MEDELLIN 3 | K133: REDEBAN | L133: FO-25-1322391 | M133: 45872.333 | N133: 45873.66 | O133: NO | P133: HARDWARE | Q133: NO ENCIENDE | R133: DAÑO POS | S133: CB UNO A UNO | U133: CERRADO | V133: 03/08/2025 03-08 SE ESCALA PARA VISITA. LLAMAR ANTES DE VISITAR, CONFIRMAR FALLA Y DATOS | 03/08/2025 EN COMUNICACIÓN CON LA SRA. LOURDES DÍAZ INFORMA QUE EL DÍA DE HOY NO PRESTA SERVICIO Y NO ABRE EL COMERCIO | 04/08/2025 SE CAMBIA DATÁFONO CON PUERTO DE CARGA MALO | W133: VISITA_TÉCNICA | X133: FUA0H948 | Y133: TIPO I | Z133: TERRESTRE | AA133: CASTAÑEDA PALACIO CARLOS FELIPE | AB133: 1 | AC133: 0 | AD133: =IF(W133="SOPORTE_TELEFÓNICO",'BASE LIQUIDACION REDEBAN 2025'!$B$19,IF(W133="ENVÍO",'BASE LIQUIDACION REDEBAN 2025'!$C$2,IF(Y133="TIPO I",'BASE LIQUIDACION REDEBAN 2025'!$C$2,IF(Y133="TIPO II",'BASE LIQUIDACION REDEBAN 2025'!$C$3,IF(Y133="TIPO III",'BASE LIQUIDACION REDEBAN 2025'!$C$4,IF(Y133="TIPO IV",'BASE LIQUIDACION REDEBAN 2025'!$C$5,IF(Z133="AEREO",'BASE LIQUIDACION REDEBAN 2025'!$B$6,'BASE LIQUIDACION REDEBAN 2025'!$C$5))))))) -> 65960.072 | AE133: =IF(OR(W133="SOPORTE_TELEFÓNICO",W133="ENVÍO"),0,IF(Y133="TIPO I",'BASE LIQUIDACION REDEBAN 2025'!$B$10,IF(Y133="TIPO II",'BASE LIQUIDACION REDEBAN 2025'!$B$11,IF(Y133="TIPO III",'BASE LIQUIDACION REDEBAN 2025'!$B$12,'BASE LIQUIDACION REDEBAN 2025'!$B$13)))) -> 75096.394 | AF133: =IF(OR(W133="SOPORTE_TELEFÓNICO",W133="ENVÍO"),AD133,(AD133*AB133+AE133*AC133)) -> 65960.072
A134: MEDELLIN | B134: =VLOOKUP(A134,'CENTRO DE COSTOS'!A:D,4,FALSE) -> JUAN SEBASTIÁN RÍOS CASTRILLÓN | C134: =VLOOKUP(A134,'CENTRO DE COSTOS'!A:D,2,FALSE) -> 0004-0005 | D134: 5001 | E134: 2543919 | F134: 56908 | G134: INCIDENTE | H134: ANTIOQUIA | I134: MEDELLIN | J134: BARRIO ROBLEDO MEDELLIN 17 | K134: REDEBAN | L134: FO-25-1322394 | M134: 45871.656 | N134: 45873.667 | O134: NO | P134: HARDWARE | Q134: LECTOR DE TARJETAS | R134: DAÑO POS | S134: CB UNO A UNO | U134: CERRADO | V134: 03/08/2025 03-08 SE ESCALA PARA VISITA. LLAMAR ANTES DE VISITAR, CONFIRMAR FALLA Y DATOS | 03/08/2025 NO SE LOGRO CONTACTO CON EL CB PARA CONFIRMAR ATENCIÓN Y UBICACIÓN DEL COMERCIO, SEGÚN FALLA REPORTADA SE REQUIERE DE UN CAMBIO DE DATÁFONO POR FALLA EN EL PUERTO USB Y LOS DÍAS DOMINGOS NO ES POSIBLE CAMBIAR EQUIPOS | 04/08/2025 SE CAMBIA EQUIPO POR CONSTANTE PROBLEMA CON LECTOR CHIP YA LOS HABÍAN VISITADO POR LO MISMO TODO OK | W134: VISITA_TÉCNICA | X134: 9CQZZ666 | Y134: TIPO I | Z134: TERRESTRE | AA134: ALVAREZ ARENAS VICTOR HUGO | AB134: 1 | AC134: 0 | AD134: =IF(W134="SOPORTE_TELEFÓNICO",'BASE LIQUIDACION REDEBAN 2025'!$B$19,IF(W134="ENVÍO",'BASE LIQUIDACION REDEBAN 2025'!$C$2,IF(Y134="TIPO I",'BASE LIQUIDACION REDEBAN 2025'!$C$2,IF(Y134="TIPO II",'BASE LIQUIDACION REDEBAN 2025'!$C$3,IF(Y134="TIPO III",'BASE LIQUIDACION REDEBAN 2025'!$C$4,IF(Y134="TIPO IV",'BASE LIQUIDACION REDEBAN 2025'!$C$5,IF(Z134="AEREO",'BASE LIQUIDACION REDEBAN 2025'!$B$6,'BASE LIQUIDACION REDEBAN 2025'!$C$5))))))) -> 65960.072 | AE134: =IF(OR(W134="SOPORTE_TELEFÓNICO",W134="ENVÍO"),0,IF(Y134="TIPO I",'BASE LIQUIDACION REDEBAN 2025'!$B$10,IF(Y134="TIPO II",'BASE LIQUIDACION REDEBAN 2025'!$B$11,IF(Y134="TIPO III",'BASE LIQUIDACION REDEBAN 2025'!$B$12,'BASE LIQUIDACION REDEBAN 2025'!$B$13)))) -> 75096.394 | AF134: =IF(OR(W134="SOPORTE_TELEFÓNICO",W134="ENVÍO"),AD134,(AD134*AB134+AE134*AC134)) -> 65960.072
A135: BUCARAMANGA | B135: =VLOOKUP(A135,'CENTRO DE COSTOS'!A:D,4,FALSE) -> MIGUEL JULIÁN HERNÁNDEZ GUARÍN | C135: =VLOOKUP(A135,'CENTRO DE COSTOS'!A:D,2,FALSE) -> 0004-0008 | D135: 68406 | E135: 2543473 | F135: 64490 | G135: INCIDENTE | H135: SANTANDER | I135: LEBRIJA | J135: AAGAFACIL LEBRIJA | K135: REDEBAN | L135: FO-25-1321119 | M135: 45871.524 | N135: 45873.682 | O135: NO | P135: HARDWARE | Q135: TECLADO | R135: DAÑO POS | S135: ROBUSTO | U135: CERRADO | V135: 03/08/2025 SE COMUNICA CON LA SEÑORITA ANDREA ANGARITA AL NÚMERO DE TELÉFONO 3164747873 PARA VALIDAR DISPONIBILIDAD, CLIENTE SOLICITA QUE POR FAVOR LE CAMBIEN EL EQUIPO DEBIDO QUE EL TECLADO ESTÁ DURO Y MAL ESTADO, ADICIONAL INDICA QUE OTROS EQUIPOS ESTÁN FALLANDO, SE LE INFORMA QUE EN EL DÍA DE HOY NO TENEMOS SOPORTE DE REDEBAN PARA CAMBIOS Y SE ATENDERÁ EL DÍA DE MAÑANA LUNES 4/8/25 | 04/08/2025 CB CON DOS TERMINALES EN FALLA, TERMINAL CON VERSION ANTIGUA, TERMINAL CON TECLADO EN DAÑO, CAMBIO DE DTAAFONO, BORRADO E INYECCION DE SO +VER 9.90, CONFIGURACION CB OK, PRUEBAS OK | W135: VISITA_TÉCNICA | X135: 1A003963-1A003962 | Y135: TIPO II | Z135: TERRESTRE | AA135: SANTOS GONZALEZ JOHAN FABIAN | AB135: 1 | AC135: 0 | AD135: =IF(W135="SOPORTE_TELEFÓNICO",'BASE LIQUIDACION REDEBAN 2025'!$B$19,IF(W135="ENVÍO",'BASE LIQUIDACION REDEBAN 2025'!$C$2,IF(Y135="TIPO I",'BASE LIQUIDACION REDEBAN 2025'!$C$2,IF(Y135="TIPO II",'BASE LIQUIDACION REDEBAN 2025'!$C$3,IF(Y135="TIPO III",'BASE LIQUIDACION REDEBAN 2025'!$C$4,IF(Y135="TIPO IV",'BASE LIQUIDACION REDEBAN 2025'!$C$5,IF(Z135="AEREO",'BASE LIQUIDACION REDEBAN 2025'!$B$6,'BASE LIQUIDACION REDEBAN 2025'!$C$5))))))) -> 144967.87 | AE135: =IF(OR(W135="SOPORTE_TELEFÓNICO",W135="ENVÍO"),0,IF(Y135="TIPO I",'BASE LIQUIDACION REDEBAN 2025'!$B$10,IF(Y135="TIPO II",'BASE LIQUIDACION REDEBAN 2025'!$B$11,IF(Y135="TIPO III",'BASE LIQUIDACION REDEBAN 2025'!$B$12,'BASE LIQUIDACION REDEBAN 2025'!$B$13)))) -> 140395.63 | AF135: =IF(OR(W135="SOPORTE_TELEFÓNICO",W135="ENVÍO"),AD135,(AD135*AB135+AE135*AC135)) -> 144967.87
A136: BARRANQUILLA | B136: =VLOOKUP(A136,'CENTRO DE COSTOS'!A:D,4,FALSE) -> JOSE MAURICIO HERNANDEZ ROJAS | C136: =VLOOKUP(A136,'CENTRO DE COSTOS'!A:D,2,FALSE) -> 0004-0001 | D136: 8001 | E136: 2543284 | F136: 21409 | G136: INCIDENTE | H136: ATLANTICO | I136: BARRANQUILLA | J136: PAGAFACIL BARRANQUILLA | K136: REDEBAN | L136: FO-25-1320035 | M136: 45871.409 | N136: 45873.69 | O136: NO | P136: HARDWARE | Q136: SE REINICIA | R136: LECTOR BARRAS | S136: ROBUSTO | U136: CERRADO | V136: 02/08/2025 01-08 SE ESCALA PARA VISITA. LLAMAR ANTES DE VISITAR, CONFIRMAR FALLA Y DATOS | 03/08/2025 CORRESPONSAL ROBUSTO ESTA CERRADO FINES DE SEMANA | 04/08/2025 DATAFONO SE REINICIABA, SE FORMATEA SE INSTALA VERSIÓN Y SO Y QUEDA OK | W136: VISITA_TÉCNICA | X136: AALZZ249 | Y136: TIPO I | Z136: TERRESTRE | AA136: DE AVILA SIADES ALBERTO ENRIQUE | AB136: 1 | AC136: 0 | AD136: =IF(W136="SOPORTE_TELEFÓNICO",'BASE LIQUIDACION REDEBAN 2025'!$B$19,IF(W136="ENVÍO",'BASE LIQUIDACION REDEBAN 2025'!$C$2,IF(Y136="TIPO I",'BASE LIQUIDACION REDEBAN 2025'!$C$2,IF(Y136="TIPO II",'BASE LIQUIDACION REDEBAN 2025'!$C$3,IF(Y136="TIPO III",'BASE LIQUIDACION REDEBAN 2025'!$C$4,IF(Y136="TIPO IV",'BASE LIQUIDACION REDEBAN 2025'!$C$5,IF(Z136="AEREO",'BASE LIQUIDACION REDEBAN 2025'!$B$6,'BASE LIQUIDACION REDEBAN 2025'!$C$5))))))) -> 65960.072 | AE136: =IF(OR(W136="SOPORTE_TELEFÓNICO",W136="ENVÍO"),0,IF(Y136="TIPO I",'BASE LIQUIDACION REDEBAN 2025'!$B$10,IF(Y136="TIPO II",'BASE LIQUIDACION REDEBAN 2025'!$B$11,IF(Y136="TIPO III",'BASE LIQUIDACION REDEBAN 2025'!$B$12,'BASE LIQUIDACION REDEBAN 2025'!$B$13)))) -> 75096.394 | AF136: =IF(OR(W136="SOPORTE_TELEFÓNICO",W136="ENVÍO"),AD136,(AD136*AB136+AE136*AC136)) -> 65960.072
A137: MEDELLIN | B137: =VLOOKUP(A137,'CENTRO DE COSTOS'!A:D,4,FALSE) -> JUAN SEBASTIÁN RÍOS CASTRILLÓN | C137: =VLOOKUP(A137,'CENTRO DE COSTOS'!A:D,2,FALSE) -> 0004-0005 | D137: 5206 | E137: 2543130 | F137: 10414 | G137: INCIDENTE | H137: ANTIOQUIA | I137: CONCEPCION | J137: CONCEPCION - ANTIOQUIA | K137: REDEBAN | L137: FO-25-1319490 | M137: 45871.362 | N137: 45873.692 | O137: NO | P137: HARDWARE | Q137: SE REINICIA | R137: DAÑO POS | S137: CB UNO A UNO | U137: CERRADO | V137: 02/08/2025 01-08 SE ESCALA PARA VISITA. LLAMAR ANTES DE VISITAR, CONFIRMAR FALLA Y DATOS | 04/08/2025 ACTIVIDAD PENDIENTE POR CAPACIDAD OPERATIVA, FECHA ATENCION 4-08-2025 | 04/08/2025 CAMBIO EQUIPO POR DAÑO SE REINICIA PIN PAD POR COMPATIBILIDAD Y MAGIC BOX POR HUB PRUEBAS OK | W137: VISITA_TÉCNICA | X137: JAAAA305 | Y137: TIPO II | Z137: TERRESTRE | AA137: PAREJA ECHAVARRIA JHON DAVID | AB137: 1 | AC137: 0 | AD137: =IF(W137="SOPORTE_TELEFÓNICO",'BASE LIQUIDACION REDEBAN 2025'!$B$19,IF(W137="ENVÍO",'BASE LIQUIDACION REDEBAN 2025'!$C$2,IF(Y137="TIPO I",'BASE LIQUIDACION REDEBAN 2025'!$C$2,IF(Y137="TIPO II",'BASE LIQUIDACION REDEBAN 2025'!$C$3,IF(Y137="TIPO III",'BASE LIQUIDACION REDEBAN 2025'!$C$4,IF(Y137="TIPO IV",'BASE LIQUIDACION REDEBAN 2025'!$C$5,IF(Z137="AEREO",'BASE LIQUIDACION REDEBAN 2025'!$B$6,'BASE LIQUIDACION REDEBAN 2025'!$C$5))))))) -> 144967.87 | AE137: =IF(OR(W137="SOPORTE_TELEFÓNICO",W137="ENVÍO"),0,IF(Y137="TIPO I",'BASE LIQUIDACION REDEBAN 2025'!$B$10,IF(Y137="TIPO II",'BASE LIQUIDACION REDEBAN 2025'!$B$11,IF(Y137="TIPO III",'BASE LIQUIDACION REDEBAN 2025'!$B$12,'BASE LIQUIDACION REDEBAN 2025'!$B$13)))) -> 140395.63 | AF137: =IF(OR(W137="SOPORTE_TELEFÓNICO",W137="ENVÍO"),AD137,(AD137*AB137+AE137*AC137)) -> 144967.87
... A141: MEDELLIN | B141: =VLOOKUP(A141,'CENTRO DE COSTOS'!A:D,4,FALSE) -> JUAN SEBASTIÁN RÍOS CASTRILLÓN | C141: =VLOOKUP(A141,'CENTRO DE COSTOS'!A:D,2,FALSE) -> 0004-0005 | D141: 5001 | E141: 2548092 | F141: 71291 | G141: INCIDENTE | H141: ANTIOQUIA | I141: MEDELLIN | J141: PTM MEDELLIN DROGUERIA VILLA P | K141: REDEBAN | L141: FO-25-1325706 | M141: 45873.459 | N141: 45873.708 | O141: NO | P141: HARDWARE | Q141: SE REINICIA | R141: DAÑO POS | S141: AGREGADOR | U141: CERRADO | V141: 04/08/2025 04-08 SE ESCALA PARA VISITA. LLAMAR ANTES DE VISITAR, CONFIRMAR FALLA Y DATOS | 04/08/2025 SE REALIZA CAMBIO DE LECTORA POR REINICIOS Y SE EQUIPO DEBIDO A REINICIOS Y TECLADO MALO | W141: VISITA_TÉCNICA | X141: SV00C114 - NN00E764 | Y141: TIPO I | Z141: TERRESTRE | AA141: QUINTERO SANCHEZ JUAN SEBASTIAN | AB141: 1 | AC141: 0 | AD141: =IF(W141="SOPORTE_TELEFÓNICO",'BASE LIQUIDACION REDEBAN 2025'!$B$19,IF(W141="ENVÍO",'BASE LIQUIDACION REDEBAN 2025'!$C$2,IF(Y141="TIPO I",'BASE LIQUIDACION REDEBAN 2025'!$C$2,IF(Y141="TIPO II",'BASE LIQUIDACION REDEBAN 2025'!$C$3,IF(Y141="TIPO III",'BASE LIQUIDACION REDEBAN 2025'!$C$4,IF(Y141="TIPO IV",'BASE LIQUIDACION REDEBAN 2025'!$C$5,IF(Z141="AEREO",'BASE LIQUIDACION REDEBAN 2025'!$B$6,'BASE LIQUIDACION REDEBAN 2025'!$C$5))))))) -> 65960.072 | AE141: =IF(OR(W141="SOPORTE_TELEFÓNICO",W141="ENVÍO"),0,IF(Y141="TIPO I",'BASE LIQUIDACION REDEBAN 2025'!$B$10,IF(Y141="TIPO II",'BASE LIQUIDACION REDEBAN 2025'!$B$11,IF(Y141="TIPO III",'BASE LIQUIDACION REDEBAN 2025'!$B$12,'BASE LIQUIDACION REDEBAN 2025'!$B$13)))) -> 75096.394 | AF141: =IF(OR(W141="SOPORTE_TELEFÓNICO",W141="ENVÍO"),AD141,(AD141*AB141+AE141*AC141)) -> 65960.072
A142: CUCUTA | B142: =VLOOKUP(A142,'CENTRO DE COSTOS'!A:D,4,FALSE) -> MIGUEL JULIÁN HERNÁNDEZ GUARÍN | C142: =VLOOKUP(A142,'CENTRO DE COSTOS'!A:D,2,FALSE) -> 0004-0008 | D142: 54001 | E142: 2548112 | F142: 27376 | G142: INCIDENTE | H142: NORTE DE SANTANDER | I142: CUCUTA | J142: PAGAFACIL CC VENTURA PLAZA | K142: REDEBAN | L142: FO-25-1325729 | M142: 45873.449 | N142: 45873.726 | O142: NO | P142: HARDWARE | Q142: LECTOR DE BARRAS | R142: DAÑO POS | S142: ROBUSTO | U142: CERRADO | V142: 04/08/2025 04-08 EN COMUNICACION CON LA SEÑORA SOREYI AL NUMERO 3113868118 INDICA QUE EL DATFAONO LE ARROJA RECHAZO GENERAL, LECTOR DE TARJETAS, CONFIRMA DATOS, SE ESCALA PARA VISITA | 04/08/2025 SE REALIZÓ VISITA AL COMERCIO Y SE ENCUENTRA LECTORA DAÑADA, SE REALIZA CAMBIO DE LECTORA PRUEBAS EXITOSAS | W142: VISITA_TÉCNICA | X142: 0 | Y142: TIPO I | Z142: TERRESTRE | AA142: MORA VEGA JEAMPIER | AB142: 1 | AC142: 0 | AD142: =IF(W142="SOPORTE_TELEFÓNICO",'BASE LIQUIDACION REDEBAN 2025'!$B$19,IF(W142="ENVÍO",'BASE LIQUIDACION REDEBAN 2025'!$C$2,IF(Y142="TIPO I",'BASE LIQUIDACION REDEBAN 2025'!$C$2,IF(Y142="TIPO II",'BASE LIQUIDACION REDEBAN 2025'!$C$3,IF(Y142="TIPO III",'BASE LIQUIDACION REDEBAN 2025'!$C$4,IF(Y142="TIPO IV",'BASE LIQUIDACION REDEBAN 2025'!$C$5,IF(Z142="AEREO",'BASE LIQUIDACION REDEBAN 2025'!$B$6,'BASE LIQUIDACION REDEBAN 2025'!$C$5))))))) -> 65960.072 | AE142: =IF(OR(W142="SOPORTE_TELEFÓNICO",W142="ENVÍO"),0,IF(Y142="TIPO I",'BASE LIQUIDACION REDEBAN 2025'!$B$10,IF(Y142="TIPO II",'BASE LIQUIDACION REDEBAN 2025'!$B$11,IF(Y142="TIPO III",'BASE LIQUIDACION REDEBAN 2025'!$B$12,'BASE LIQUIDACION REDEBAN 2025'!$B$13)))) -> 75096.394 | AF142: =IF(OR(W142="SOPORTE_TELEFÓNICO",W142="ENVÍO"),AD142,(AD142*AB142+AE142*AC142)) -> 65960.072
A143: BUCARAMANGA | B143: =VLOOKUP(A143,'CENTRO DE COSTOS'!A:D,4,FALSE) -> MIGUEL JULIÁN HERNÁNDEZ GUARÍN | C143: =VLOOKUP(A143,'CENTRO DE COSTOS'!A:D,2,FALSE) -> 0004-0008 | D143: 68001 | E143: 2547781 | F143: 34113 | G143: INCIDENTE | H143: SANTANDER | I143: BUCARAMANGA | J143: COMCARD B MANGA TIENDA SHADDAY | K143: REDEBAN | L143: FO-25-1325735 | M143: 45873.447 | N143: 45873.732 | O143: NO | P143: HARDWARE | Q143: SE REINICIA | R143: DAÑO POS | S143: AGREGADOR | U143: CERRADO | V143: 04/08/2025 04-08 SE ESCALA PARA VISITA. LLAMAR ANTES DE VISITAR, CONFIRMAR FALLA Y DATOS | 04/08/2025 SE ESTABLECE CONTACTO TELEFÓNICO CON LA SEÑORA RUTH AL NÚMERO 3172187256 QUIEN NOS CONFIRMA QUE NOS PODRÁ ATENDER APARTIR DE LAS 15:00 HRS | W143: VISITA_TÉCNICA | X143: 1QZZZ217-II0XZ495 | Y143: TIPO I | Z143: TERRESTRE | AA143: REYES RAMIREZ DIEGO ALEXANDER | AB143: 1 | AC143: 0 | AD143: =IF(W143="SOPORTE_TELEFÓNICO",'BASE LIQUIDACION REDEBAN 2025'!$B$19,IF(W143="ENVÍO",'BASE LIQUIDACION REDEBAN 2025'!$C$2,IF(Y143="TIPO I",'BASE LIQUIDACION REDEBAN 2025'!$C$2,IF(Y143="TIPO II",'BASE LIQUIDACION REDEBAN 2025'!$C$3,IF(Y143="TIPO III",'BASE LIQUIDACION REDEBAN 2025'!$C$4,IF(Y143="TIPO IV",'BASE LIQUIDACION REDEBAN 2025'!$C$5,IF(Z143="AEREO",'BASE LIQUIDACION REDEBAN 2025'!$B$6,'BASE LIQUIDACION REDEBAN 2025'!$C$5))))))) -> 65960.072 | AE143: =IF(OR(W143="SOPORTE_TELEFÓNICO",W143="ENVÍO"),0,IF(Y143="TIPO I",'BASE LIQUIDACION REDEBAN 2025'!$B$10,IF(Y143="TIPO II",'BASE LIQUIDACION REDEBAN 2025'!$B$11,IF(Y143="TIPO III",'BASE LIQUIDACION REDEBAN 2025'!$B$12,'BASE LIQUIDACION REDEBAN 2025'!$B$13)))) -> 75096.394 | AF143: =IF(OR(W143="SOPORTE_TELEFÓNICO",W143="ENVÍO"),AD143,(AD143*AB143+AE143*AC143)) -> 65960.072
