Workbook
Name ACTIVIDAD: [1]Hoja2!$P$2:$P$30
Name Clientes: [2]Clientes!$A$2:$A$100
Name COORDINADOR: [1]Hoja2!$D$2:$D$30
Name Coordinadores: [3]Coordinadores!$A$2:$A$1000
Name DOCUMENTADOR: [1]Hoja2!$A$2:$A$30
Name ES: [1]Hoja2!$K$2:$K$30
Name ESS: [1]Hoja2!$K$2:$K$30
Name Estado: [2]Formulas!$K$2:$K$5000
Name ESTADOACTIVIDAD: [1]Hoja2!$M$2:$M$30
Name ESTADOSCIERRES: '[4]lista desplegable'!$CX$1:$DA$1
Name Facturacion: '[5]Listas desplegables'!$AO$1:$AR$1
Name solicitudes: '[5]Listas desplegables'!$U$1:$AF$1
Name Tecnicos: [2]Tecnicos!$A$2:$A$1000

Sheet RESUMEN
A1: LÍNEA COMUNICACIONES S.A.S | F1: FACTURACIÓN CORRESPONSALES BANCARIOS TIQUIETES AÉREOS
A2: FACTURACIÓN VISITAS FALLIDAS CORRESPONSALES BANCARIOS | F2: =A3 -> AGOSTO 2025
A3: AGOSTO 2025
F4: CONCEPTOS | G4: TRAYECTOS | H4: TOTAL | I4: % ADMINISTRACIÓN | J4: TOTAL
A5: CONCEPTOS | B5: CANT | D5: TOTAL | F5: ORDEN DE CAMBIO TA-25-941590 | G5: PASTO-MOGUI-PASTO | H5: 300000 | I5: =H5*0.12 -> 36000 | J5: =H5+I5 -> 336000
A6: =CONCATENATE("CIERRES NO EXITOSOS ",A3) -> CIERRES NO EXITOSOS AGOSTO 2025 | B6: =COUNTA(CIERRES!A:A)-1 -> 105 | D6: =CIERRES!AD107 -> 11052804 | I6: =H6*0.12 -> 0 | J6: =H6+I6 -> 0
A7: TIQUETES | B7: 1 | D7: =J10 -> 336000 | I7: =H7*0.12 -> 0 | J7: =H7+I7 -> 0
A8: SUBTOTAL | D8: =SUM(D6:D7) -> 11388804
A9: IVA | D9: =D8*0.19 -> 2163872.8
A10: TOTAL | D10: =SUM(D8:D9) -> 13552677 | F10: TOTAL | H10: =SUM(H5:H7) -> 300000 | I10: =SUM(I5:I7) -> 36000 | J10: =SUM(J5:J7) -> 336000

Sheet BASE DE LIQUIDACION 2025
A1: CIERRE CB - VISITAS FALLIDAS O CIERRES NO EXITOSOS TARIFAS 2024 | D1: Incremento 2025
A2: Tipificación | B2: Descripción | C2: Tarifa | D2: 0.052
A3: Tipo I | B3: Metropolitano | C3: =42357*(1+$D$2) -> 44559.564
A4: Tipo II | B4: Hasta 3 horas | C4: =127767*(1+$D$2) -> 134410.88
A5: Tipo III | B5: De 3 a 5 horas | C5: =211886*(1+$D$2) -> 222904.07
A6: Tipo IV | B6: Más de 5 horas | C6: =441834*(1+$D$2) -> 464809.37
A7: Trayecto Especial | B7: No incluye valor del Tiquete | C7: Valor de actividad Tipo IV + Valor tiquete aéreo (o fluvial) + 12% administración)
A9: Gestión telefonica | B9: =36031*(1+$D$2) -> 37904.612

Sheet Tabla Dinámica
A3: COORDINADOR | B3: CENTRO DE COSTOS LÍNEACOM | C3: % | D3: Suma de VALOR TOTAL2 | E3: NOMBRE CC
A4: DIEGO FERNANDO HENAO CARDONA | B4: 0004-0002 | C4: 0.024321589 | D4: 268821.77 | E4: =VLOOKUP(B4,'CENTRO DE COSTOS'!B:C,2,0) -> Redeban Eje Cafetero (Pereira)
B5: 0004-0003 | C5: 0.26918057 | D5: 2975200.1 | E5: =VLOOKUP(B5,'CENTRO DE COSTOS'!B:C,2,0) -> Redeban Suroccidente (Cali)
A6: JOSE MAURICIO HERNANDEZ ROJAS | B6: 0004-0001 | C6: 0.11350208 | D6: 1254516.3 | E6: =VLOOKUP(B6,'CENTRO DE COSTOS'!B:C,2,0) -> Redeban Costa (Barranqullla)
A7: JUAN SEBASTIÁN RÍOS CASTRILLÓN | B7: 0004-0005 | C7: 0.20171451 | D7: 2229511 | E7: =VLOOKUP(B7,'CENTRO DE COSTOS'!B:C,2,0) -> Redeban Noroccidente (Medellín)
A8: KEVIN ALEXIS CORZO BUSTOS | B8: 0004-0007 | C8: 0.14918363 | D8: 1648897.4 | E8: =VLOOKUP(B8,'CENTRO DE COSTOS'!B:C,2,0) -> Redeban Oriente (Otros)
A9: MIGUEL JULIÁN HERNÁNDEZ GUARÍN | B9: 0004-0008 | C9: 0.10481772 | D9: 1158529.7 | E9: =VLOOKUP(B9,'CENTRO DE COSTOS'!B:C,2,0) -> Redeban Santander
A10: WILLIAM ASDRUBAL ROZO ROZO | B10: 0004-0004 | C10: 0.13727991 | D10: 1517328 | E10: =VLOOKUP(B10,'CENTRO DE COSTOS'!B:C,2,0) -> Redeban Centro ( Bogotá)
A11: Total general | C11: 1 | D11: 11052804

Sheet CIERRES
A1: CIUDAD SEDE | B1: COORDINADOR | C1: CENTRO DE COSTOS LÍNEACOM | D1: CÓDIGO DANE | E1: TA/CODIGO ACTIVIDAD | F1: CODIGO CB | G1: ACTIVIDAD | H1: DEPARTAMENTO | I1: CIUDAD | J1: NOMBRE DEL CB | K1: RED | L1: FO | M1: FECHA ASIGNACION A LINEA COMUNICACIONES | N1: FECHA DEL CIERRE DEL TICKET (DD/MM/AAAA) | O1: ACOMETIDA | P1: SOLICITUD | Q1: DESCRIPCIÓN | R1: FORMATO | S1: CADENA | T1: ESTADO | U1: CAUSAL ESTADO | V1: OBSERVACION | W1: FORMA DE ATENCIÓN | X1: TERMINAL | Y1: TIPIFICACION | Z1: TIPO DE TRAYECTO | AA1: NOMBRE DEL TECNICO | AB1: DIAS DE VISITA | AC1: VALOR ACTIVIDAD | AD1: VALOR TOTAL
A2: APARTADO | B2: =VLOOKUP(A2,'CENTRO DE COSTOS'!A:D,4,FALSE) -> JUAN SEBASTIÁN RÍOS CASTRILLÓN | C2: =VLOOKUP(A2,'CENTRO DE COSTOS'!A:C,2,FALSE) -> 0004-0005 | D2: 27615 | E2: TA-25-899476 | F2: 58825 | G2: ORDEN DE CAMBIO | H2: CHOCO | I2: RIOSUCIO | J2: DISTRICOL MAYORISTA LA BODEGA | K2: REDEBAN | L2: FO-25-1297516 | M2: 45867.333 | N2: 45870.398 | P2: CIERRE | Q2: CIERRE | R2: AGREGADOR | S2: DISTRICOL | T2: NO_EXITOSO | U2: CB NO ENTREGA EQUIPO | V2: 0 0 01-08-2025 SE LLAMA AL CLIENTE PARA AVISAR QUE VAMOS HACER LA VISITA Y NOS INFORMA QUE EN LA VEREDA A LLOVIDO MUCHO Y QUE ESTA DIFICIL EL ACCESO HASTA EL CASERIO DE IGUAL FORMA NOS MANIFESTO QUE EL NO A SOLICITADO EL CIERRE Y QUE NO SE ENCUENTRA EN LA VDA. SE LE INFORMA QUE SE COMUNIQUE AL BANCO. EL USUARIO NO ENTREGARA EQUIPOS HASTA QUE EL HABLE CON EL BANCO PARA ACLARAR EL PORQUE LE ESTAN CERRANDO EL CB | W2: SOPORTE_TELEFÓNICO | X2: 0 | Y2: TIPO IV ESPECIAL | Z2: =VLOOKUP(D2,TIPOLOGIAS!A:F,5,0) -> TERRESTRE/FLUVIAL | AA2: SALDARRIAGA MIRANDA SANTIAGO | AB2: 0 | AC2: =IF(AND(W2="SOPORTE_TELEFÓNICO",OR(U2="SIN CONTACTO CON EL CB",U2="NÚMEROS DE CONTACTO ERRADOS")),0,IF(W2="SOPORTE_TELEFÓNICO",'BASE DE LIQUIDACION 2025'!$B$9,IF(Y2="TIPO I",'BASE DE LIQUIDACION 2025'!$C$3,IF(Y2="TIPO II",'BASE DE LIQUIDACION 2025'!$C$4,IF(Y2="TIPO III",'BASE DE LIQUIDACION 2025'!$C$5,'BASE DE LIQUIDACION 2025'!$C$6))))) -> 37904.612 | AD2: =IF(W2="SOPORTE_TELEFÓNICO",AC2,CIERRES!AB2*CIERRES!AC2) -> 37904.612
A3: CALI | B3: =VLOOKUP(A3,'CENTRO DE COSTOS'!A:D,4,FALSE) -> DIEGO FERNANDO HENAO CARDONA | C3: =VLOOKUP(A3,'CENTRO DE COSTOS'!A:C,2,FALSE) -> 0004-0003 | D3: 76001 | E3: TA-25-906330 | F3: 69764 | G3: ORDEN DE CAMBIO | H3: VALLE DEL CAUCA | I3: CALI | J3: BARRIO ALCAZAREZ CALI | K3: REDEBAN | L3: FO-25-1308290 | M3: 45868.666 | N3: 45870.415 | P3: CIERRE | Q3: CIERRE | R3: CB UNO A UNO | S3: CB UNO A UNO | T3: NO_EXITOSO | U3: CB NO ENTREGA EQUIPO | V3: 0 0 01-08-2025 SE LLEGA AL COMERCIO SE HABLA CON EL CLIENTE E INDICA QUE EL NO A SOLICITADO EL CIERRE Y QUE NO SE LE A NOTIFICADO QUE VA HABLAR CON EL BANCO PARA VALIDAR | W3: VISITA_TÉCNICA | X3: NN000790 | Y3: TIPO I | Z3: =VLOOKUP(D3,TIPOLOGIAS!A:F,5,0) -> TERRESTRE | AA3: CUERO RUIZ JHONNY | AB3: 1 | AC3: =IF(AND(W3="SOPORTE_TELEFÓNICO",OR(U3="SIN CONTACTO CON EL CB",U3="NÚMEROS DE CONTACTO ERRADOS")),0,IF(W3="SOPORTE_TELEFÓNICO",'BASE DE LIQUIDACION 2025'!$B$9,IF(Y3="TIPO I",'BASE DE LIQUIDACION 2025'!$C$3,IF(Y3="TIPO II",'BASE DE LIQUIDACION 2025'!$C$4,IF(Y3="TIPO III",'BASE DE LIQUIDACION 2025'!$C$5,'BASE DE LIQUIDACION 2025'!$C$6))))) -> 44559.564 | AD3: =IF(W3="SOPORTE_TELEFÓNICO",AC3,CIERRES!AB3*CIERRES!AC3) -> 44559.564
A4: VILLAVICENCIO | B4: =VLOOKUP(A4,'CENTRO DE COSTOS'!A:D,4,FALSE) -> KEVIN ALEXIS CORZO BUSTOS | C4: =VLOOKUP(A4,'CENTRO DE COSTOS'!A:C,2,FALSE) -> 0004-0007 | D4: 50568 | E4: TA-25-903370 | F4: 72483 | G4: ORDEN DE CAMBIO | H4: META | I4: PUERTO GAITAN | J4: BARRIO PUERTO GAITAN BATEAS | K4: REDEBAN | L4: FO-25-1303399 | M4: 45868.333 | N4: 45870.417 | P4: CIERRE | Q4: RECUPERACION DE EQUIPOS | R4: CB UNO A UNO | S4: CB UNO A UNO | T4: ILOCALIZADO | U4: CB CERRADO - DESOCUPADO | V4: 0 0 01-08-2025 SE REALIZA VISITA A COMERCIO CB NO EXISTE NO ES POSIBLE COMUNICACIÓN CON TITULAR ILOCALIZABLE | W4: VISITA_TÉCNICA | X4: 0 | Y4: TIPO III | Z4: =VLOOKUP(D4,TIPOLOGIAS!A:F,5,0) -> TERRESTRE | AA4: CASTRILLON URREA LONDIER LEANDRO | AB4: 1 | AC4: =IF(AND(W4="SOPORTE_TELEFÓNICO",OR(U4="SIN CONTACTO CON EL CB",U4="NÚMEROS DE CONTACTO ERRADOS")),0,IF(W4="SOPORTE_TELEFÓNICO",'BASE DE LIQUIDACION 2025'!$B$9,IF(Y4="TIPO I",'BASE DE LIQUIDACION 2025'!$C$3,IF(Y4="TIPO II",'BASE DE LIQUIDACION 2025'!$C$4,IF(Y4="TIPO III",'BASE DE LIQUIDACION 2025'!$C$5,'BASE DE LIQUIDACION 2025'!$C$6))))) -> 222904.07 | AD4: =IF(W4="SOPORTE_TELEFÓNICO",AC4,CIERRES!AB4*CIERRES!AC4) -> 222904.07
A5: IBAGUE | B5: =VLOOKUP(A5,'CENTRO DE COSTOS'!A:D,4,FALSE) -> KEVIN ALEXIS CORZO BUSTOS | C5: =VLOOKUP(A5,'CENTRO DE COSTOS'!A:C,2,FALSE) -> 0004-0007 | D5: 73671 | E5: TA-25-906329 | F5: 62416 | G5: ORDEN DE CAMBIO | H5: TOLIMA | I5: SALDAÑA | J5: BARRIO VIA SALDANA GUAMO SALDA | K5: REDEBAN | L5: FO-25-1308287 | M5: 45868.666 | N5: 45870.463 | P5: CIERRE | Q5: CIERRE | R5: CB UNO A UNO | S5: CB UNO A UNO | T5: NO_EXITOSO | U5: CB NO ENTREGA EQUIPO | V5: 0 0 01-08-2025 SE LLAMA A LA SEÑORA BIBIANA GOMEZ AL NÚMERO DE TELÉFONO 3124662530, ME INDICA QUE ELLA NO VA A ENTREGAR EQUIPOS PORQUE ESTÁ ESPERANDO LA CARTA DE RETIRO DE EFECTY PARA CONTINUAR CON EL CORRESPONSAL. QUE ELLA ESTÁ EN CONTACTO CON LA ASESORA DE BANCOLOMBIA PARA SEGUIR CON EL CORRESPONSAL. | W5: SOPORTE_TELEFÓNICO | X5: 0 | Y5: TIPO II | Z5: =VLOOKUP(D5,TIPOLOGIAS!A:F,5,0) -> TERRESTRE | AA5: VARGAS HERRERA JHON JAIRO | AB5: 0 | AC5: =IF(AND(W5="SOPORTE_TELEFÓNICO",OR(U5="SIN CONTACTO CON EL CB",U5="NÚMEROS DE CONTACTO ERRADOS")),0,IF(W5="SOPORTE_TELEFÓNICO",'BASE DE LIQUIDACION 2025'!$B$9,IF(Y5="TIPO I",'BASE DE LIQUIDACION 2025'!$C$3,IF(Y5="TIPO II",'BASE DE LIQUIDACION 2025'!$C$4,IF(Y5="TIPO III",'BASE DE LIQUIDACION 2025'!$C$5,'BASE DE LIQUIDACION 2025'!$C$6))))) -> 37904.612 | AD5: =IF(W5="SOPORTE_TELEFÓNICO",AC5,CIERRES!AB5*CIERRES!AC5) -> 37904.612
A6: MEDELLIN | B6: =VLOOKUP(A6,'CENTRO DE COSTOS'!A:D,4,FALSE) -> JUAN SEBASTIÁN RÍOS CASTRILLÓN | C6: =VLOOKUP(A6,'CENTRO DE COSTOS'!A:C,2,FALSE) -> 0004-0005 | D6: 5059 | E6: TA-25-917392 | F6: 16613 | G6: ORDEN DE CAMBIO | H6: ANTIOQUIA | I6: ARMENIA | J6: 366 SAN DIEGO PLAZA OLIMPICA | K6: REDEBAN | L6: FO-25-1322151 | M6: 45868.666 | N6: 45870.497 | P6: CIERRE | Q6: RECUPERACION DE EQUIPOS | R6: RETAIL | S6: OLIMPICA | T6: EJECUTADO_EXITOSO | U6: CIERRE EXITOSO | V6: SE REALIZA COMUNICACIÓN CON USUARIO. SE HABLA CON LILIANA GUIZA AL NÚMERO 3203261426. INDICA QUE LA SEMANA PASADA YA LE REALIZARON RETIRO DE EQUIPOS Y QUE YA NO TIENE MAS POR ENTREGAR DEL PUNTO 16613.SE ESCALA A LA RED //1/08 11:55 RESPUESTA DE LA RED: SE DOCUMENTA CASO: EJECUTADO EXITOSO. LA RECUPERACIÓN DE EQUIPOS FUE REALIZADA POR MEDIO DE LA GESTORÍA DE REDEBAN** RESPUESTA DE LA RED 0 | W6: SOPORTE_TELEFÓNICO | X6: 0 | Y6: TIPO II | Z6: =VLOOKUP(D6,TIPOLOGIAS!A:F,5,0) -> TERRESTRE | AA6: 0 | AB6: 0 | AC6: =IF(AND(W6="SOPORTE_TELEFÓNICO",OR(U6="SIN CONTACTO CON EL CB",U6="NÚMEROS DE CONTACTO ERRADOS")),0,IF(W6="SOPORTE_TELEFÓNICO",'BASE DE LIQUIDACION 2025'!$B$9,IF(Y6="TIPO I",'BASE DE LIQUIDACION 2025'!$C$3,IF(Y6="TIPO II",'BASE DE LIQUIDACION 2025'!$C$4,IF(Y6="TIPO III",'BASE DE LIQUIDACION 2025'!$C$5,'BASE DE LIQUIDACION 2025'!$C$6))))) -> 37904.612 | AD6: =IF(W6="SOPORTE_TELEFÓNICO",AC6,CIERRES!AB6*CIERRES!AC6) -> 37904.612
A7: BOGOTA | B7: =VLOOKUP(A7,'CENTRO DE COSTOS'!A:D,4,FALSE) -> WILLIAM ASDRUBAL ROZO ROZO | C7: =VLOOKUP(A7,'CENTRO DE COSTOS'!A:C,2,FALSE) -> 0004-0004 | D7: 11001 | E7: TA-25-906294 | F7: 56731 | G7: ORDEN DE CAMBIO | H7: CUNDINAMARCA | I7: BOGOTA | J7: DISTRICOL VARIEDADES TIN | K7: REDEBAN | L7: FO-25-1308178 | M7: 45868.666 | N7: 45870.582 | P7: CIERRE | Q7: CIERRE | R7: AGREGADOR | S7: DISTRICOL | T7: ILOCALIZADO | U7: CB CERRADO - DESOCUPADO | V7: 0 0 01-08-2025 DURANTE LA VISITA DE TECNICA PARA ATENDER CIERRE DE CORRESPONSAL BANCARIO LO CUAL NO ES POSIBLE PORQUE COMERCIO SE ENCUENTRA CERRADO Y NO SE EVIDENCIA LA EXISTENCIA DEL CB SE LLAMA AL CELULAR 3505304343 EL CUAL SE ENCUENTRA APAGADO SE PROCEDE AL CIERRE DE LA ACTIVIDAD | W7: VISITA_TÉCNICA | X7: 0 | Y7: TIPO I | Z7: =VLOOKUP(D7,TIPOLOGIAS!A:F,5,0) -> TERRESTRE | AA7: GALEANO SORIANO JUAN DAVID | AB7: 1 | AC7: =IF(AND(W7="SOPORTE_TELEFÓNICO",OR(U7="SIN CONTACTO CON EL CB",U7="NÚMEROS DE CONTACTO ERRADOS")),0,IF(W7="SOPORTE_TELEFÓNICO",'BASE DE LIQUIDACION 2025'!$B$9,IF(Y7="TIPO I",'BASE DE LIQUIDACION 2025'!$C$3,IF(Y7="TIPO II",'BASE DE LIQUIDACION 2025'!$C$4,IF(Y7="TIPO III",'BASE DE LIQUIDACION 2025'!$C$5,'BASE DE LIQUIDACION 2025'!$C$6))))) -> 44559.564 | AD7: =IF(W7="SOPORTE_TELEFÓNICO",AC7,CIERRES!AB7*CIERRES!AC7) -> 44559.564
A8: BOGOTA | B8: =VLOOKUP(A8,'CENTRO DE COSTOS'!A:D,4,FALSE) -> WILLIAM ASDRUBAL ROZO ROZO | C8: =VLOOKUP(A8,'CENTRO DE COSTOS'!A:C,2,FALSE) -> 0004-0004 | D8: 25817 | E8: TA-25-906311 | F8: 15820 | G8: ORDEN DE CAMBIO | H8: CUNDINAMARCA | I8: TOCANCIPA | J8: BARRIO VD LA FUENTE TOCANCIPA | K8: REDEBAN | L8: FO-25-1308234 | M8: 45868.666 | N8: 45870.607 | P8: CIERRE | Q8: CIERRE | R8: CB UNO A UNO | S8: CB UNO A UNO | T8: NO_EXITOSO | U8: CB NO ENTREGA EQUIPO | V8: 0 0 01-08-2025 CIERRE FALLIDO CLIENTE NO REALIZA ENTREGA DE LOS. EQUIPOS POR QUÉ NO LE HABÍA. AVISADO DEL CIERRE. DEL CB Y APARTE MANIFIESTA ESTAR EN UN PROCESO DE CONCILIACIÓN CON EL BANCO | W8: VISITA_TÉCNICA | X8: 7ZZZZ964 | Y8: TIPO II | Z8: =VLOOKUP(D8,TIPOLOGIAS!A:F,5,0) -> TERRESTRE | AA8: HERNANDEZ NARANJO OSCAR EDUARDO | AB8: 1 | AC8: =IF(AND(W8="SOPORTE_TELEFÓNICO",OR(U8="SIN CONTACTO CON EL CB",U8="NÚMEROS DE CONTACTO ERRADOS")),0,IF(W8="SOPORTE_TELEFÓNICO",'BASE DE LIQUIDACION 2025'!$B$9,IF(Y8="TIPO I",'BASE DE LIQUIDACION 2025'!$C$3,IF(Y8="TIPO II",'BASE DE LIQUIDACION 2025'!$C$4,IF(Y8="TIPO III",'BASE DE LIQUIDACION 2025'!$C$5,'BASE DE LIQUIDACION 2025'!$C$6))))) -> 134410.88 | AD8: =IF(W8="SOPORTE_TELEFÓNICO",AC8,CIERRES!AB8*CIERRES!AC8) -> 134410.88
A9: TUNJA | B9: =VLOOKUP(A9,'CENTRO DE COSTOS'!A:D,4,FALSE) -> MIGUEL JULIÁN HERNÁNDEZ GUARÍN | C9: =VLOOKUP(A9,'CENTRO DE COSTOS'!A:C,2,FALSE) -> 0004-0008 | D9: 15001 | E9: TA-25-906307 | F9: 62298 | G9: ORDEN DE CAMBIO | H9: BOYACA | I9: TUNJA | J9: BARRIO COEDUCADORES TUNJA 1 | K9: REDEBAN | L9: FO-25-1317256 | M9: 45868.666 | N9: 45870.695 | P9: CIERRE | Q9: CIERRE | R9: CB UNO A UNO | S9: CB UNO A UNO | T9: NO_EXITOSO | U9: CB NO ENTREGA EQUIPO | V9: 0 0 01-08-2025 SE VISITA PUNTO ENCONTRANDO EL COMERCIO CERRADO NÚMERO DE CONTACTO REGISTRADO FUERA DE SERVICIO SE GESTIONAN NÚMEROS EN VISITAS ANTERIORES SE LOGRA CONTACTO CON LA SEÑORA MARGARITA SUÁREZ QUIEN INDICA QUE SE ENCUENTRA REALIZANDO UNAS DILIGENCIAS PERSONALES INFORMA POSIBLE HORA DE ENTREGA EN HORAS PM EL DÍA DE HOY. 0 01-08-2025 SE VISITA PUNTO CLIENTE NO AUTORIZA EL RETIRO DE LOS EQUIPOS INDICAN QUE EL ASESOR DE LA ENTIDAD ESCALÓ EL CASO PARA QUE HABILITEN NUEVAMENTE EL CORRESPONSAL BANCARIO. | W9: VISITA_TÉCNICA | X9: OA00C217 | Y9: TIPO I | Z9: =VLOOKUP(D9,TIPOLOGIAS!A:F,5,0) -> TERRESTRE | AA9: RODRIGUEZ MURCIA YERSON IVAN | AB9: 1 | AC9: =IF(AND(W9="SOPORTE_TELEFÓNICO",OR(U9="SIN CONTACTO CON EL CB",U9="NÚMEROS DE CONTACTO ERRADOS")),0,IF(W9="SOPORTE_TELEFÓNICO",'BASE DE LIQUIDACION 2025'!$B$9,IF(Y9="TIPO I",'BASE DE LIQUIDACION 2025'!$C$3,IF(Y9="TIPO II",'BASE DE LIQUIDACION 2025'!$C$4,IF(Y9="TIPO III",'BASE DE LIQUIDACION 2025'!$C$5,'BASE DE LIQUIDACION 2025'!$C$6))))) -> 44559.564 | AD9: =IF(W9="SOPORTE_TELEFÓNICO",AC9,CIERRES!AB9*CIERRES!AC9) -> 44559.564
A10: BOGOTA | B10: =VLOOKUP(A10,'CENTRO DE COSTOS'!A:D,4,FALSE) -> WILLIAM ASDRUBAL ROZO ROZO | C10: =VLOOKUP(A10,'CENTRO DE COSTOS'!A:C,2,FALSE) -> 0004-0004 | D10: 11001 | E10: TA-25-906335 | F10: 58581 | G10: ORDEN DE CAMBIO | H10: CUNDINAMARCA | I10: BOGOTA | J10: BARRIO QUIRIGUA BOGOTQA | K10: REDEBAN | L10: FO-25-1308309 | M10: 45868.666 | N10: 45870.762 | P10: CIERRE | Q10: CIERRE | R10: CB UNO A UNO | S10: CB UNO A UNO | T10: NO_EXITOSO | U10: CB NO ENTREGA EQUIPO | V10: 0 0 01-08-2025 SE REALIZA VISITA A DIRECCIÓN DE COMERCIO, PERSONA QUE ATIENDE INDICA QUE LA SRA. YOVANA ANDREA GALLEGO LE VENDIÓ EL NEGOCIO, SE REALIZA LLAMADA TELEFÓNICA SE HABLA CON LA CLIENTE Y SE LE INDICA QUE DEBE COMUNICARSE A LA LÍNEA DE CORRESPONSAL BANCOLOMBIA Y SOLICITAR CITA PARA LA ENTREGA DE LOS EQUIPOS EN LA DIRECCIÓN DONDE LOS TENGA. | W10: VISITA_TÉCNICA | X10: 0 | Y10: TIPO I | Z10: =VLOOKUP(D10,TIPOLOGIAS!A:F,5,0) -> TERRESTRE | AA10: MURCIA HERNANDEZ HARVEY IGNACIO | AB10: 1 | AC10: =IF(AND(W10="SOPORTE_TELEFÓNICO",OR(U10="SIN CONTACTO CON EL CB",U10="NÚMEROS DE CONTACTO ERRADOS")),0,IF(W10="SOPORTE_TELEFÓNICO",'BASE DE LIQUIDACION 2025'!$B$9,IF(Y10="TIPO I",'BASE DE LIQUIDACION 2025'!$C$3,IF(Y10="TIPO II",'BASE DE LIQUIDACION 2025'!$C$4,IF(Y10="TIPO III",'BASE DE LIQUIDACION 2025'!$C$5,'BASE DE LIQUIDACION 2025'!$C$6))))) -> 44559.564 | AD10: =IF(W10="SOPORTE_TELEFÓNICO",AC10,CIERRES!AB10*CIERRES!AC10) -> 44559.564
A11: BOGOTA | B11: =VLOOKUP(A11,'CENTRO DE COSTOS'!A:D,4,FALSE) -> WILLIAM ASDRUBAL ROZO ROZO | C11: =VLOOKUP(A11,'CENTRO DE COSTOS'!A:C,2,FALSE) -> 0004-0004 | D11: 11001 | E11: TA-25-906337 | F11: 74001 | G11: ORDEN DE CAMBIO | H11: CUNDINAMARCA | I11: BOGOTA | J11: BARRIO ALAMOS BOGOTA 9 | K11: REDEBAN | L11: FO-25-1308315 | M11: 45868.666 | N11: 45870.772 | P11: CIERRE | Q11: CIERRE | R11: CB UNO A UNO | S11: CB UNO A UNO | T11: ILOCALIZADO | U11: CB CERRADO - DESOCUPADO | V11: 0 0 01-08-2025 SE REALIZA DESPLAZAMIENTO A DIRECCIÓN DE COMERCIO, COMERCIO NO EXISTE, TELÉFONO DE CONTACTO NO FUNCIONA. | W11: VISITA_TÉCNICA | X11: 0 | Y11: TIPO I | Z11: =VLOOKUP(D11,TIPOLOGIAS!A:F,5,0) -> TERRESTRE | AA11: MURCIA HERNANDEZ HARVEY IGNACIO | AB11: 1 | AC11: =IF(AND(W11="SOPORTE_TELEFÓNICO",OR(U11="SIN CONTACTO CON EL CB",U11="NÚMEROS DE CONTACTO ERRADOS")),0,IF(W11="SOPORTE_TELEFÓNICO",'BASE DE LIQUIDACION 2025'!$B$9,IF(Y11="TIPO I",'BASE DE LIQUIDACION 2025'!$C$3,IF(Y11="TIPO II",'BASE DE LIQUIDACION 2025'!$C$4,IF(Y11="TIPO III",'BASE DE LIQUIDACION 2025'!$C$5,'BASE DE LIQUIDACION 2025'!$C$6))))) -> 44559.564 | AD11: =IF(W11="SOPORTE_TELEFÓNICO",AC11,CIERRES!AB11*CIERRES!AC11) -> 44559.564
A12: BUCARAMANGA | B12: =VLOOKUP(A12,'CENTRO DE COSTOS'!A:D,4,FALSE) -> MIGUEL JULIÁN HERNÁNDEZ GUARÍN | C12: =VLOOKUP(A12,'CENTRO DE COSTOS'!A:C,2,FALSE) -> 0004-0008 | D12: 68235 | E12: TA-25-906324 | F12: 78424 | G12: ORDEN DE CAMBIO | H12: SANTANDER | I12: EL CARMEN DE CHUCURI | J12: BARRIO CENTRO EL CARMEN DE CHUCURI 2 | K12: REDEBAN | L12: FO-25-1308273 | M12: 45868.666 | N12: 45871.381 | P12: CIERRE | Q12: CIERRE | R12: CB UNO A UNO | S12: CB UNO A UNO | T12: NO_EXITOSO | U12: CB NO ENTREGA EQUIPO | V12: 0 01/08/2025 NO SE LOGRA COMUNICACIÓN CON LA LÍNEA SUMINISTRADA 3125576328, SE TRATA DE REALIZAR LLAMADA Y NO CONTESTA, SE DEJA MENSAJE VÍA CHAT SIN RESPUESTA POR PARTE DEL CLIENTE, SE LE INFORMA A COORDINADOR. 01/08/2025 NO SE LOGRA COMUNICACIÓN CON LA LÍNEA SUMINISTRADA 3125576328-3125249927 , SE TRATA DE REALIZAR LLAMADA Y NO CONTESTA, SE DEJA MENSAJE VÍA CHAT SIN RESPUESTA POR PARTE DEL CLIENTE, SE LE INFORMA A COORDINADOR. 02-08-2025 EN COMUNICACIÓN CON LA SEÑORA YEIMI VÍA CHAT A LA LINEA 3125576328, INDICA QUE VA HABLAR CON EL ASESOR PARA PODER GESTIONAR LA REACTIVACION DEL SERVICIO,SE LE INFORMA QUE TENDRÁ QUE GESTIONAR UNA NUEVA VISITA PARA RECOGER LOS EQUIPOS EN DADO CASO NO SE PUEDA REACTIVAR EL CB. | W12: SOPORTE_TELEFÓNICO | X12: 0 | Y12: TIPO IV | Z12: =VLOOKUP(D12,TIPOLOGIAS!A:F,5,0) -> TERRESTRE | AA12: SANTOS GONZALEZ JOHAN FABIAN | AB12: 0 | AC12: =IF(AND(W12="SOPORTE_TELEFÓNICO",OR(U12="SIN CONTACTO CON EL CB",U12="NÚMEROS DE CONTACTO ERRADOS")),0,IF(W12="SOPORTE_TELEFÓNICO",'BASE DE LIQUIDACION 2025'!$B$9,IF(Y12="TIPO I",'BASE DE LIQUIDACION 2025'!$C$3,IF(Y12="TIPO II",'BASE DE LIQUIDACION 2025'!$C$4,IF(Y12="TIPO III",'BASE DE LIQUIDACION 2025'!$C$5,'BASE DE LIQUIDACION 2025'!$C$6))))) -> 37904.612 | AD12: =IF(W12="SOPORTE_TELEFÓNICO",AC12,CIERRES!AB12*CIERRES!AC12) -> 37904.612
A13: BOGOTA | B13: =VLOOKUP(A13,'CENTRO DE COSTOS'!A:D,4,FALSE) -> WILLIAM ASDRUBAL ROZO ROZO | C13: =VLOOKUP(A13,'CENTRO DE COSTOS'!A:C,2,FALSE) -> 0004-0004 | D13: 11001 | E13: TA-25-906334 | F13: 57327 | G13: ORDEN DE CAMBIO | H13: CUNDINAMARCA | I13: BOGOTA | J13: BARRIO PINAR BOGOTA | K13: REDEBAN | L13: FO-25-1308307 | M13: 45868.666 | N13: 45871.485 | P13: CIERRE | Q13: CIERRE | R13: CB UNO A UNO | S13: CB UNO A UNO | T13: NO_EXITOSO | U13: CB NO ENTREGA EQUIPO | V13: 0 02/08/2025 SE LLAGA A LA DIRECCIÓN CLIENTE MANIFIESTA QUE BANCOLOMBIA TIENE UN SALDO DE EL Y QUE CON BANCOLOMBIA SE HABIA LLEGADO AL ACUERDO QUE CUANDO LE RETORNARAN EL SALDO SE RECOJIAN LOS EQUIPOS ENTONCES NO ENTREGA EQUIPOS 02-08-2025 SE LLAGA A LA DIRECCIÓN CLIENTE MANIFIESTA QUE BANCOLOMBIA TIENE UN SALDO DE EL Y QUE CON BANCOLOMBIA SE HABIA LLEGADO AL ACUERDO QUE CUANDO LE RETORNARAN EL SALDO SE RECOJIAN LOS EQUIPOS ENTONCES NO ENTREGA EQUIPOS. NO DA MAS INFORMACIÓN. | W13: VISITA_TÉCNICA | X13: 0 | Y13: TIPO I | Z13: =VLOOKUP(D13,TIPOLOGIAS!A:F,5,0) -> TERRESTRE | AA13: SOTO MUNAR DYLAN DAVID | AB13: 1 | AC13: =IF(AND(W13="SOPORTE_TELEFÓNICO",OR(U13="SIN CONTACTO CON EL CB",U13="NÚMEROS DE CONTACTO ERRADOS")),0,IF(W13="SOPORTE_TELEFÓNICO",'BASE DE LIQUIDACION 2025'!$B$9,IF(Y13="TIPO I",'BASE DE LIQUIDACION 2025'!$C$3,IF(Y13="TIPO II",'BASE DE LIQUIDACION 2025'!$C$4,IF(Y13="TIPO III",'BASE DE LIQUIDACION 2025'!$C$5,'BASE DE LIQUIDACION 2025'!$C$6))))) -> 44559.564 | AD13: =IF(W13="SOPORTE_TELEFÓNICO",AC13,CIERRES!AB13*CIERRES!AC13) -> 44559.564
A14: BOGOTA | B14: =VLOOKUP(A14,'CENTRO DE COSTOS'!A:D,4,FALSE) -> WILLIAM ASDRUBAL ROZO ROZO | C14: =VLOOKUP(A14,'CENTRO DE COSTOS'!A:C,2,FALSE) -> 0004-0004 | D14: 11001 | E14: TA-25-899547 | F14: 70302 | G14: ORDEN DE CAMBIO | H14: CUNDINAMARCA | I14: BOGOTA | J14: PTM BOGOTA DISTRI CASTEL SAS | K14: REDEBAN | L14: FO-25-1297618 | M14: 45867.333 | N14: 45871.511 | P14: CIERRE | Q14: RECUPERACION DE EQUIPOS | R14: AGREGADOR | S14: COMCARD - PTM | T14: ILOCALIZADO | U14: CB CERRADO - DESOCUPADO | V14: 0 02/08/2025 SE INTENTA LLAMAR AL CLIENTE Y NO CONTESTA, DE ESCRIBE POR WHATSAPP Y TAMPCO AHI RESPUESTA , AL LLEGAR AL PUNTO SE ENCUENTRA CERRADO 02-08-2025 SE INTENTA LLAMAR AL CLIENTE Y NO CONTESTA, DE ESCRIBE POR WHATSAPP Y TAMPCO AHI RESPUESTA , AL LLEGAR AL PUNTO SE ENCUENTRA CERRADO | W14: VISITA_TÉCNICA | X14: O | Y14: TIPO I | Z14: =VLOOKUP(D14,TIPOLOGIAS!A:F,5,0) -> TERRESTRE | AA14: SOTO MUNAR DYLAN DAVID | AB14: 1 | AC14: =IF(AND(W14="SOPORTE_TELEFÓNICO",OR(U14="SIN CONTACTO CON EL CB",U14="NÚMEROS DE CONTACTO ERRADOS")),0,IF(W14="SOPORTE_TELEFÓNICO",'BASE DE LIQUIDACION 2025'!$B$9,IF(Y14="TIPO I",'BASE DE LIQUIDACION 2025'!$C$3,IF(Y14="TIPO II",'BASE DE LIQUIDACION 2025'!$C$4,IF(Y14="TIPO III",'BASE DE LIQUIDACION 2025'!$C$5,'BASE DE LIQUIDACION 2025'!$C$6))))) -> 44559.564 | AD14: =IF(W14="SOPORTE_TELEFÓNICO",AC14,CIERRES!AB14*CIERRES!AC14) -> 44559.564
A15: NEIVA | B15: =VLOOKUP(A15,'CENTRO DE COSTOS'!A:D,4,FALSE) -> KEVIN ALEXIS CORZO BUSTOS | C15: =VLOOKUP(A15,'CENTRO DE COSTOS'!A:C,2,FALSE) -> 0004-0007 | D15: 41615 | E15: TA-25-906315 | F15: 78964 | G15: ORDEN DE CAMBIO | H15: HUILA | I15: RIVERA | J15: BARRIO CENTRO BAJO RIVERA 1 | K15: REDEBAN | L15: FO-25-1308245 | M15: 45868.666 | N15: 45871.569 | P15: CIERRE | Q15: CIERRE | R15: CB UNO A UNO | S15: CB UNO A UNO | T15: SOLICITUD_CANCELADA | U15: CANCELADO POR LA ENTIDAD | V15: 0 0 02-08-2025 SE LLEGA A SITIO, NO SE ENCUENTRA NADIE EN LA CASA, SE LLAMA A NÚMERO DE CONTACTO 3207128409 PERO NO RESPONDEN. | W15: VISITA_TÉCNICA | X15: 0 | Y15: TIPO I | Z15: =VLOOKUP(D15,TIPOLOGIAS!A:F,5,0) -> TERRESTRE | AA15: DIAZ VARGAS JONATHAN MIGUEL | AB15: 1 | AC15: =IF(AND(W15="SOPORTE_TELEFÓNICO",OR(U15="SIN CONTACTO CON EL CB",U15="NÚMEROS DE CONTACTO ERRADOS")),0,IF(W15="SOPORTE_TELEFÓNICO",'BASE DE LIQUIDACION 2025'!$B$9,IF(Y15="TIPO I",'BASE DE LIQUIDACION 2025'!$C$3,IF(Y15="TIPO II",'BASE DE LIQUIDACION 2025'!$C$4,IF(Y15="TIPO III",'BASE DE LIQUIDACION 2025'!$C$5,'BASE DE LIQUIDACION 2025'!$C$6))))) -> 44559.564 | AD15: =IF(W15="SOPORTE_TELEFÓNICO",AC15,CIERRES!AB15*CIERRES!AC15) -> 44559.564
A16: VILLAVICENCIO | B16: =VLOOKUP(A16,'CENTRO DE COSTOS'!A:D,4,FALSE) -> KEVIN ALEXIS CORZO BUSTOS | C16: =VLOOKUP(A16,'CENTRO DE COSTOS'!A:C,2,FALSE) -> 0004-0007 | D16: 50001 | E16: TA-25-906316 | F16: 63562 | G16: ORDEN DE CAMBIO | H16: META | I16: VILLAVICENCIO | J16: BARRIO RECREO VILLAVICENCIO 2 | K16: REDEBAN | L16: FO-25-1308249 | M16: 45868.666 | N16: 45873.344 | P16: CIERRE | Q16: CIERRE | R16: CB UNO A UNO | S16: CB UNO A UNO | T16: NO_EXITOSO | U16: CB NO ENTREGA EQUIPO | V16: 0 0 04-08-2025 SE REALIZA VISITA Y ENCARGADO INFORMA QUE NO TIENE CONOCIMIENTO QUE TOCA COMUNICARSE CON LOS DUEÑOS YA QUE ELLOS VENDIERON EL.NEGOCIO | W16: VISITA_TÉCNICA | X16: 0 | Y16: TIPO I | Z16: =VLOOKUP(D16,TIPOLOGIAS!A:F,5,0) -> TERRESTRE | AA16: PEDREROS CONTRERAS MICHAEL STEVENS | AB16: 1 | AC16: =IF(AND(W16="SOPORTE_TELEFÓNICO",OR(U16="SIN CONTACTO CON EL CB",U16="NÚMEROS DE CONTACTO ERRADOS")),0,IF(W16="SOPORTE_TELEFÓNICO",'BASE DE LIQUIDACION 2025'!$B$9,IF(Y16="TIPO I",'BASE DE LIQUIDACION 2025'!$C$3,IF(Y16="TIPO II",'BASE DE LIQUIDACION 2025'!$C$4,IF(Y16="TIPO III",'BASE DE LIQUIDACION 2025'!$C$5,'BASE DE LIQUIDACION 2025'!$C$6))))) -> 44559.564 | AD16: =IF(W16="SOPORTE_TELEFÓNICO",AC16,CIERRES!AB16*CIERRES!AC16) -> 44559.564
A17: APARTADO | B17: =VLOOKUP(A17,'CENTRO DE COSTOS'!A:D,4,FALSE) -> JUAN SEBASTIÁN RÍOS CASTRILLÓN | C17: =VLOOKUP(A17,'CENTRO DE COSTOS'!A:C,2,FALSE) -> 0004-0005 | D17: 5490 | E17: TA-25-899458 | F17: 71512 | G17: ORDEN DE CAMBIO | H17: ANTIOQUIA | I17: NECOCLI | J17: DISTRICOL LA 44 DE DORKI | K17: REDEBAN | L17: FO-25-1297487 | M17: 45867.333 | N17: 45873.353 | P17: CIERRE | Q17: CIERRE | R17: AGREGADOR | S17: DISTRICOL | T17: NO_EXITOSO | U17: CB NO ENTREGA EQUIPO | V17: 0 0 04-08-2025 SE LLAMA AL USUARIO PARA PROGRAMAR LA VISITA, EL USUARIO NOS MANIFIESTA QUE NO NOS PUEDE ANTENDER Y QUE VA A COMUNICARCE CON LA ALIANZA DISTRICOL PARA CAMBIAR EL MODO DEL CORRESPONSAL A PREPAGO. | W17: SOPORTE_TELEFÓNICO | X17: 0 | Y17: TIPO II | Z17: =VLOOKUP(D17,TIPOLOGIAS!A:F,5,0) -> TERRESTRE | AA17: SALDARRIAGA MIRANDA SANTIAGO | AB17: 0 | AC17: =IF(AND(W17="SOPORTE_TELEFÓNICO",OR(U17="SIN CONTACTO CON EL CB",U17="NÚMEROS DE CONTACTO ERRADOS")),0,IF(W17="SOPORTE_TELEFÓNICO",'BASE DE LIQUIDACION 2025'!$B$9,IF(Y17="TIPO I",'BASE DE LIQUIDACION 2025'!$C$3,IF(Y17="TIPO II",'BASE DE LIQUIDACION 2025'!$C$4,IF(Y17="TIPO III",'BASE DE LIQUIDACION 2025'!$C$5,'BASE DE LIQUIDACION 2025'!$C$6))))) -> 37904.612 | AD17: =IF(W17="SOPORTE_TELEFÓNICO",AC17,CIERRES!AB17*CIERRES!AC17) -> 37904.612
A18: APARTADO | B18: =VLOOKUP(A18,'CENTRO DE COSTOS'!A:D,4,FALSE) -> JUAN SEBASTIÁN RÍOS CASTRILLÓN | C18: =VLOOKUP(A18,'CENTRO DE COSTOS'!A:C,2,FALSE) -> 0004-0005 | D18: 5837 | E18: TA-25-899462 | F18: 37620 | G18: ORDEN DE CAMBIO | H18: ANTIOQUIA | I18: TURBO | J18: DISTRICOL PAPELERIA BEERM | K18: REDEBAN | L18: FO-25-1297489 | M18: 45867.333 | N18: 45873.36 | P18: CIERRE | Q18: CIERRE | R18: AGREGADOR | S18: DISTRICOL | T18: NO_EXITOSO | U18: CB NO ENTREGA EQUIPO | V18: 0 0 04-08-2025 USUARIO MANIFIESTA QUE YA HIZO LA ENTREGA DEL COMERCIO Y ENVIO LOS EQUIPOS A DISTRICOL MEDELLIN. NOS COMPARTE EVIDENCIA DE LOS EQUIPOS Y GUIA DEL ENVIO | W18: SOPORTE_TELEFÓNICO | X18: 0 | Y18: TIPO II | Z18: =VLOOKUP(D18,TIPOLOGIAS!A:F,5,0) -> TERRESTRE | AA18: SALDARRIAGA MIRANDA SANTIAGO | AB18: 0 | AC18: =IF(AND(W18="SOPORTE_TELEFÓNICO",OR(U18="SIN CONTACTO CON EL CB",U18="NÚMEROS DE CONTACTO ERRADOS")),0,IF(W18="SOPORTE_TELEFÓNICO",'BASE DE LIQUIDACION 2025'!$B$9,IF(Y18="TIPO I",'BASE DE LIQUIDACION 2025'!$C$3,IF(Y18="TIPO II",'BASE DE LIQUIDACION 2025'!$C$4,IF(Y18="TIPO III",'BASE DE LIQUIDACION 2025'!$C$5,'BASE DE LIQUIDACION 2025'!$C$6))))) -> 37904.612 | AD18: =IF(W18="SOPORTE_TELEFÓNICO",AC18,CIERRES!AB18*CIERRES!AC18) -> 37904.612
A19: MEDELLIN | B19: =VLOOKUP(A19,'CENTRO DE COSTOS'!A:D,4,FALSE) -> JUAN SEBASTIÁN RÍOS CASTRILLÓN | C19: =VLOOKUP(A19,'CENTRO DE COSTOS'!A:C,2,FALSE) -> 0004-0005 | D19: 5197 | E19: TA-25-899457 | F19: 59566 | G19: ORDEN DE CAMBIO | H19: ANTIOQUIA | I19: COCORNA | J19: DISTRICOL VARIEDADES ARCO IRIS | K19: REDEBAN | L19: FO-25-1297476 | M19: 45867.333 | N19: 45873.469 | P19: CIERRE | Q19: CIERRE | R19: AGREGADOR | S19: DISTRICOL | T19: NO_EXITOSO | U19: CB NO ENTREGA EQUIPO | V19: 0 04-08-2025 SE VISITA COMERCIO PERO ESTA DESOCUPADO, SE LLAMA AL NÚMERO INDICADO PERO LA SEÑORA VERÓNICA CANO INDICA QUE ELLA VA A ENTREGAR ELLA MISMA EL DATAFONO EN LAS OFICINAS DE DISTRICOL | W19: VISITA_TÉCNICA | X19: 0 | Y19: TIPO II | Z19: =VLOOKUP(D19,TIPOLOGIAS!A:F,5,0) -> TERRESTRE | AA19: RUA ALVAREZ RICHARD ANDRES | AB19: 1 | AC19: =IF(AND(W19="SOPORTE_TELEFÓNICO",OR(U19="SIN CONTACTO CON EL CB",U19="NÚMEROS DE CONTACTO ERRADOS")),0,IF(W19="SOPORTE_TELEFÓNICO",'BASE DE LIQUIDACION 2025'!$B$9,IF(Y19="TIPO I",'BASE DE LIQUIDACION 2025'!$C$3,IF(Y19="TIPO II",'BASE DE LIQUIDACION 2025'!$C$4,IF(Y19="TIPO III",'BASE DE LIQUIDACION 2025'!$C$5,'BASE DE LIQUIDACION 2025'!$C$6))))) -> 134410.88 | AD19: =IF(W19="SOPORTE_TELEFÓNICO",AC19,CIERRES!AB19*CIERRES!AC19) -> 134410.88
A20: BOGOTA | B20: =VLOOKUP(A20,'CENTRO DE COSTOS'!A:D,4,FALSE) -> WILLIAM ASDRUBAL ROZO ROZO | C20: =VLOOKUP(A20,'CENTRO DE COSTOS'!A:C,2,FALSE) -> 0004-0004 | D20: 25200 | E20: TA-25-906341 | F20: 37315 | G20: ORDEN DE CAMBIO | H20: CUNDINAMARCA | I20: COGUA | J20: BARRIO CENTRO COGUA 2 | K20: REDEBAN | L20: FO-25-1308339 | M20: 45868.666 | N20: 45873.635 | P20: CIERRE | Q20: RECUPERACION DE EQUIPOS | R20: CB UNO A UNO | S20: CB UNO A UNO | T20: NO_EXITOSO | U20: CB NO ENTREGA EQUIPO | V20: 0 04-08-2025 SE LLEGA A DIRECCIÓN REFERENCIADA EN ORDEN DE TRABAJO CL 1 B # 14 A - 2 SE GOLPEA. Y SE TIMBRA NADIE SALE, SE REALIZA INTENTOS DE COMUNICACIÓN CON CLIENTE RAFAEL RAMOS A NI.E REGISTRADO 3144520647 EL CUAL INFORMA QUE EN EL MOMENTO NO SE ENCUENTRA NADIE Y DAMAS . INFORMA QUE PARA PRÓXIMA VISITA QUE POR FAVOR PASAR DESPUÉS DE 2 DE LA TARDE Y LLAMAR CON ANTICIPACIÓN SE ESCALA Y SE CIERRA | W20: VISITA_TÉCNICA | X20: 0 | Y20: TIPO II | Z20: =VLOOKUP(D20,TIPOLOGIAS!A:F,5,0) -> TERRESTRE | AA20: ORTIZ MARTINEZ STIVEN | AB20: 1 | AC20: =IF(AND(W20="SOPORTE_TELEFÓNICO",OR(U20="SIN CONTACTO CON EL CB",U20="NÚMEROS DE CONTACTO ERRADOS")),0,IF(W20="SOPORTE_TELEFÓNICO",'BASE DE LIQUIDACION 2025'!$B$9,IF(Y20="TIPO I",'BASE DE LIQUIDACION 2025'!$C$3,IF(Y20="TIPO II",'BASE DE LIQUIDACION 2025'!$C$4,IF(Y20="TIPO III",'BASE DE LIQUIDACION 2025'!$C$5,'BASE DE LIQUIDACION 2025'!$C$6))))) -> 134410.88 | AD20: =IF(W20="SOPORTE_TELEFÓNICO",AC20,CIERRES!AB20*CIERRES!AC20) -> 134410.88
A21: CARTAGENA | B21: =VLOOKUP(A21,'CENTRO DE COSTOS'!A:D,4,FALSE) -> JOSE MAURICIO HERNANDEZ ROJAS | C21: =VLOOKUP(A21,'CENTRO DE COSTOS'!A:C,2,FALSE) -> 0004-0001 | D21: 13001 | E21: TA-25-904648 | F21: 43018 | G21: ORDEN DE CAMBIO | H21: BOLIVAR | I21: CARTAGENA | J21: BARRIO LA CORDIALIDAD CARTAGEN | K21: REDEBAN | L21: FO-25-1305901 | M21: 45868.523 | N21: 45873.674 | P21: CIERRE | Q21: RECUPERACION DE EQUIPOS | R21: CB UNO A UNO | S21: CB UNO A UNO | T21: NO_EXITOSO | U21: PARCIAL EXITOSO PTE. DATAFONO | V21: 30-07 DE ACUERDO A COMUNICACIÓN DE CONTACTO DE CB 43018 SR JAVIER DIAZ, CON COLABORADOR DE LINEA, INDICA QUE YA CUENTA CON LOS EQUIPOS PARA REALIZAR LOS CIERRES, ÉSTOS TENÍAN ORDEN DE CIERRE DESDE EL PASADO MES DE ABRIL, PERO NO ENTREGARON LOS EQUIPOS EN ESA FECHA 0 30-07-2025 SE REALIZA CIERRE DEL CB CLIENTE ENTREGA EQUIPO LECTORA HUB NO ENTREGA PUBLICIDAD HACE FALTA UNOS EQUIPOS LOS VAN A BUSCAR Y AVISAN CUANDO YA LOS TENGA PARA VENIRLOS A RECOGER | W21: VISITA_TÉCNICA | X21: AB9ZZ980 | Y21: TIPO I | Z21: =VLOOKUP(D21,TIPOLOGIAS!A:F,5,0) -> TERRESTRE | AA21: CANEDO HERRERA ALEXANDER | AB21: 1 | AC21: =IF(AND(W21="SOPORTE_TELEFÓNICO",OR(U21="SIN CONTACTO CON EL CB",U21="NÚMEROS DE CONTACTO ERRADOS")),0,IF(W21="SOPORTE_TELEFÓNICO",'BASE DE LIQUIDACION 2025'!$B$9,IF(Y21="TIPO I",'BASE DE LIQUIDACION 2025'!$C$3,IF(Y21="TIPO II",'BASE DE LIQUIDACION 2025'!$C$4,IF(Y21="TIPO III",'BASE DE LIQUIDACION 2025'!$C$5,'BASE DE LIQUIDACION 2025'!$C$6))))) -> 44559.564 | AD21: =IF(W21="SOPORTE_TELEFÓNICO",AC21,CIERRES!AB21*CIERRES!AC21) -> 44559.564
A22: VILLAVICENCIO | B22: =VLOOKUP(A22,'CENTRO DE COSTOS'!A:D,4,FALSE) -> KEVIN ALEXIS CORZO BUSTOS | C22: =VLOOKUP(A22,'CENTRO DE COSTOS'!A:C,2,FALSE) -> 0004-0007 | D22: 50001 | E22: TA-25-906338 | F22: 60579 | G22: ORDEN DE CAMBIO | H22: META | I22: VILLAVICENCIO | J22: BARRIO LA MADRID VILLAVICENCIO | K22: REDEBAN | L22: FO-25-1308322 | M22: 45868.666 | N22: 45874.359 | P22: CIERRE | Q22: CIERRE | R22: CB UNO A UNO | S22: CB UNO A UNO | T22: NO_EXITOSO | U22: CB NO ENTREGA EQUIPO | V22: 05/08/2025 SE REALIZA GESTIÓN TELEFÓNICA AL NÚMERO 6044619700 EL CUAL CONTESTA EL SEÑOR CARLOS OCAMPO CON CÉDULA 70326497 HIJO DE LA SEÑORA ROCÍO ARENAS DE OCAMPO Y MANIFIESTA QUE POR FAVOR REALIZAR LA RECOGIDA EL DÍA DE MAÑANA EN MEDELLÍN EN LA DIRECCIÓN CL.53 # 78-121 EN LOS EDIFICIOS PALMAR DE LOS COLORES, EL VIGILANTE ENTREGA LOS EQUIPOS. 05-08-2025 SE REALIZA GESTIÓN TELEFÓNICA AL NÚMERO 6044619700 EL CUAL CONTESTA EL SEÑOR CARLOS OCAMPO CON CÉDULA 70326497 HIJO DE LA SEÑORA ROCÍO ARENAS DE OCAMPO Y MANIFIESTA QUE POR FAVOR REALIZAR LA RECOGIDA EL DÍA DE MAÑANA EN MEDELLÍN EN LA DIRECCIÓN CL.53 # 78-121 EN LOS EDIFICIOS PALMAR DE LOS COLORES, EL VIGILANTE ENTREGA LOS EQUIPOS. | W22: SOPORTE_TELEFÓNICO | X22: 0 | Y22: TIPO I | Z22: =VLOOKUP(D22,TIPOLOGIAS!A:F,5,0) -> TERRESTRE | AA22: PEDREROS CONTRERAS MICHAEL STEVENS | AB22: 0 | AC22: =IF(AND(W22="SOPORTE_TELEFÓNICO",OR(U22="SIN CONTACTO CON EL CB",U22="NÚMEROS DE CONTACTO ERRADOS")),0,IF(W22="SOPORTE_TELEFÓNICO",'BASE DE LIQUIDACION 2025'!$B$9,IF(Y22="TIPO I",'BASE DE LIQUIDACION 2025'!$C$3,IF(Y22="TIPO II",'BASE DE LIQUIDACION 2025'!$C$4,IF(Y22="TIPO III",'BASE DE LIQUIDACION 2025'!$C$5,'BASE DE LIQUIDACION 2025'!$C$6))))) -> 37904.612 | AD22: =IF(W22="SOPORTE_TELEFÓNICO",AC22,CIERRES!AB22*CIERRES!AC22) -> 37904.612
A23: PASTO | B23: =VLOOKUP(A23,'CENTRO DE COSTOS'!A:D,4,FALSE) -> DIEGO FERNANDO HENAO CARDONA | C23: =VLOOKUP(A23,'CENTRO DE COSTOS'!A:C,2,FALSE) -> 0004-0003 | D23: 52083 | E23: TA-25-906320 | F23: 64590 | G23: ORDEN DE CAMBIO | H23: NARIÑO | I23: BELEN | J23: BARRIO AV LOS ESTUDIANTES BELE | K23: REDEBAN | L23: FO-25-1308262 | M23: 45868.666 | N23: 45875.408 | P23: CIERRE | Q23: CIERRE | R23: CB UNO A UNO | S23: CB UNO A UNO | T23: NO_EXITOSO | U23: CB NO ENTREGA EQUIPO | V23: 0 0 06-08-2025 SE HABLA CON EL SEÑOR MILCIADES QUIEN INDICA QUE SE ENCUENTRA EN UN PROCESO DE VALIDACION CON LA ENTIDAD PARA LA CONTINUIDAD DEL CORRESPONAL, POR TANTO POR AHORA NO DESEA LA ENTREGA DEL LOS EQUIPOS PUES ESTA EN ESPERA DE VALIDACIONES Y RESPUESTA DE LA ENTIDAD ANTE LA PETICION. | W23: SOPORTE_TELEFÓNICO | X23: 0 | Y23: TIPO III | Z23: =VLOOKUP(D23,TIPOLOGIAS!A:F,5,0) -> TERRESTRE | AA23: HENAO CARDONA DIEGO FERNANDO | AB23: 0 | AC23: =IF(AND(W23="SOPORTE_TELEFÓNICO",OR(U23="SIN CONTACTO CON EL CB",U23="NÚMEROS DE CONTACTO ERRADOS")),0,IF(W23="SOPORTE_TELEFÓNICO",'BASE DE LIQUIDACION 2025'!$B$9,IF(Y23="TIPO I",'BASE DE LIQUIDACION 2025'!$C$3,IF(Y23="TIPO II",'BASE DE LIQUIDACION 2025'!$C$4,IF(Y23="TIPO III",'BASE DE LIQUIDACION 2025'!$C$5,'BASE DE LIQUIDACION 2025'!$C$6))))) -> 37904.612 | AD23: =IF(W23="SOPORTE_TELEFÓNICO",AC23,CIERRES!AB23*CIERRES!AC23) -> 37904.612
A24: CUCUTA | B24: =VLOOKUP(A24,'CENTRO DE COSTOS'!A:D,4,FALSE) -> MIGUEL JULIÁN HERNÁNDEZ GUARÍN | C24: =VLOOKUP(A24,'CENTRO DE COSTOS'!A:C,2,FALSE) -> 0004-0008 | D24: 54001 | E24: TA-25-924046 | F24: 71022 | G24: ORDEN DE CAMBIO | H24: NORTE DE SANTANDER | I24: CUCUTA | J24: DISTRICOL CENTROPAG | K24: REDEBAN | L24: FO-25-1332781 | M24: 45874.597 | N24: 45875.671 | P24: CIERRE | Q24: RECUPERACION DE EQUIPOS | R24: AGREGADOR | S24: DISTRICOL | T24: NO_EXITOSO | U24: CB NO ENTREGA EQUIPO | V24: 0 06-08-2025 SE VISITA COMERCIO, PERSONA EN SITIO DICE QUE NO ESTA AUTORIZADA PARA ATENDER VISITA YA QUE NO ES LA DUEÑA, SE COMUNICA CON EL CLIENTE A LOS NUMEROS INDICADOS NO SE RESIVE RESPUESTA, SIN COMUNICACION. | W24: VISITA_TÉCNICA | X24: MN00C096 | Y24: TIPO I | Z24: =VLOOKUP(D24,TIPOLOGIAS!A:F,5,0) -> TERRESTRE | AA24: NARANJO AFANADOR RUBEN JESUS | AB24: 1 | AC24: =IF(AND(W24="SOPORTE_TELEFÓNICO",OR(U24="SIN CONTACTO CON EL CB",U24="NÚMEROS DE CONTACTO ERRADOS")),0,IF(W24="SOPORTE_TELEFÓNICO",'BASE DE LIQUIDACION 2025'!$B$9,IF(Y24="TIPO I",'BASE DE LIQUIDACION 2025'!$C$3,IF(Y24="TIPO II",'BASE DE LIQUIDACION 2025'!$C$4,IF(Y24="TIPO III",'BASE DE LIQUIDACION 2025'!$C$5,'BASE DE LIQUIDACION 2025'!$C$6))))) -> 44559.564 | AD24: =IF(W24="SOPORTE_TELEFÓNICO",AC24,CIERRES!AB24*CIERRES!AC24) -> 44559.564
A25: NEIVA | B25: =VLOOKUP(A25,'CENTRO DE COSTOS'!A:D,4,FALSE) -> KEVIN ALEXIS CORZO BUSTOS | C25: =VLOOKUP(A25,'CENTRO DE COSTOS'!A:C,2,FALSE) -> 0004-0007 | D25: 41001 | E25: TA-25-924053 | F25: 64929 | G25: ORDEN DE CAMBIO | H25: HUILA | I25: NEIVA | J25: DISTRICOL BEATIFUL NAILS | K25: REDEBAN | L25: FO-25-1332800 | M25: 45874.597 | N25: 45875.853 | P25: CIERRE | Q25: CIERRE | R25: AGREGADOR | S25: DISTRICOL | T25: NO_EXITOSO | U25: CB NO ENTREGA EQUIPO | V25: 0 06-08-2025 SE REALIZA VISITA AL PUNTO SE EVIDENCIA COEMECIO CERRADO, EN COMUNICACIÓN CON EL CLIENTE LA SEÑORA DANIELA RUBIANO, AL NÚMERO +57 322 3100611, INDICA QUE NO CUENTA CON LOS EQUIPOS, YA QUE LOS ENVIARON A LAS OFICINAS DE DISTRICOL EN MEDELLÍN, | W25: VISITA_TÉCNICA | X25: 0 | Y25: TIPO I | Z25: =VLOOKUP(D25,TIPOLOGIAS!A:F,5,0) -> TERRESTRE | AA25: DEVIA REINOSO JUAN CARLOS | AB25: 1 | AC25: =IF(AND(W25="SOPORTE_TELEFÓNICO",OR(U25="SIN CONTACTO CON EL CB",U25="NÚMEROS DE CONTACTO ERRADOS")),0,IF(W25="SOPORTE_TELEFÓNICO",'BASE DE LIQUIDACION 2025'!$B$9,IF(Y25="TIPO I",'BASE DE LIQUIDACION 2025'!$C$3,IF(Y25="TIPO II",'BASE DE LIQUIDACION 2025'!$C$4,IF(Y25="TIPO III",'BASE DE LIQUIDACION 2025'!$C$5,'BASE DE LIQUIDACION 2025'!$C$6))))) -> 44559.564 | AD25: =IF(W25="SOPORTE_TELEFÓNICO",AC25,CIERRES!AB25*CIERRES!AC25) -> 44559.564
A26: SANTA MARTA | B26: =VLOOKUP(A26,'CENTRO DE COSTOS'!A:D,4,FALSE) -> JOSE MAURICIO HERNANDEZ ROJAS | C26: =VLOOKUP(A26,'CENTRO DE COSTOS'!A:C,2,FALSE) -> 0004-0001 | D26: 47268 | E26: TA-25-941588 | F26: 53238 | G26: ORDEN DE CAMBIO | H26: MAGDALENA | I26: EL RETEN | J26: PTM EL RETEN SERVIFRIOMAR | K26: REDEBAN | L26: FO-25-1345215 | M26: 45875.721 | N26: 45877.719 | P26: CIERRE | Q26: CIERRE | R26: AGREGADOR | S26: COMCARD - PTM | T26: ILOCALIZADO | U26: CB CERRADO - DESOCUPADO | V26: 0 0 08-08-2025 SE HACE GESTIÓN TELEFÓNICA, EL USUARIO NO RESPONDE LAS.LLAMDAS, SE REALIZA LA VISITA, NO SE HAYA EL CORRESPONSAL EN EL PUNTO SE VALIDA LA UBICACIÓN DEL SITIO CON EL COORDINADOR PERO EN EL SITIO NO HAY CORRESPONSAL INSTALADO Y NADIE DA RAZÓN DEL USUARIO NI DEL CORRESPONSAL | W26: VISITA_TÉCNICA | X26: 0 | Y26: TIPO III | Z26: =VLOOKUP(D26,TIPOLOGIAS!A:F,5,0) -> TERRESTRE | AA26: THOMAS CAMPO SIGIFREDO SEGUNDO | AB26: 1 | AC26: =IF(AND(W26="SOPORTE_TELEFÓNICO",OR(U26="SIN CONTACTO CON EL CB",U26="NÚMEROS DE CONTACTO ERRADOS")),0,IF(W26="SOPORTE_TELEFÓNICO",'BASE DE LIQUIDACION 2025'!$B$9,IF(Y26="TIPO I",'BASE DE LIQUIDACION 2025'!$C$3,IF(Y26="TIPO II",'BASE DE LIQUIDACION 2025'!$C$4,IF(Y26="TIPO III",'BASE DE LIQUIDACION 2025'!$C$5,'BASE DE LIQUIDACION 2025'!$C$6))))) -> 222904.07 | AD26: =IF(W26="SOPORTE_TELEFÓNICO",AC26,CIERRES!AB26*CIERRES!AC26) -> 222904.07
A27: CALI | B27: =VLOOKUP(A27,'CENTRO DE COSTOS'!A:D,4,FALSE) -> DIEGO FERNANDO HENAO CARDONA | C27: =VLOOKUP(A27,'CENTRO DE COSTOS'!A:C,2,FALSE) -> 0004-0003 | D27: 76364 | E27: TA-25-941582 | F27: 36900 | G27: ORDEN DE CAMBIO | H27: VALLE DEL CAUCA | I27: JAMUNDI | J27: BARRIO JAMUNDI VALLE DEL CAUCA | K27: REDEBAN | L27: FO-25-1345200 | M27: 45875.724 | N27: 45878.501 | P27: CIERRE | Q27: RECUPERACION DE EQUIPOS | R27: CB UNO A UNO | S27: CB UNO A UNO | T27: ILOCALIZADO | U27: CB CERRADO - DESOCUPADO | V27: 0 0 09-08-2025 SE VISITA CORRESPONSAL Y SE ENCONTRÓ CERRADO, SE LLAMA AL CONTACTO EN REPETIDAS OCASIONES NO CONTESTA. | W27: VISITA_TÉCNICA | X27: MN0SZ859 | Y27: TIPO II | Z27: =VLOOKUP(D27,TIPOLOGIAS!A:F,5,0) -> TERRESTRE | AA27: BOLAÑOS TABORDA JORGE ENRIQUE | AB27: 1 | AC27: =IF(AND(W27="SOPORTE_TELEFÓNICO",OR(U27="SIN CONTACTO CON EL CB",U27="NÚMEROS DE CONTACTO ERRADOS")),0,IF(W27="SOPORTE_TELEFÓNICO",'BASE DE LIQUIDACION 2025'!$B$9,IF(Y27="TIPO I",'BASE DE LIQUIDACION 2025'!$C$3,IF(Y27="TIPO II",'BASE DE LIQUIDACION 2025'!$C$4,IF(Y27="TIPO III",'BASE DE LIQUIDACION 2025'!$C$5,'BASE DE LIQUIDACION 2025'!$C$6))))) -> 134410.88 | AD27: =IF(W27="SOPORTE_TELEFÓNICO",AC27,CIERRES!AB27*CIERRES!AC27) -> 134410.88
A28: NEIVA | B28: =VLOOKUP(A28,'CENTRO DE COSTOS'!A:D,4,FALSE) -> KEVIN ALEXIS CORZO BUSTOS | C28: =VLOOKUP(A28,'CENTRO DE COSTOS'!A:C,2,FALSE) -> 0004-0007 | D28: 41001 | E28: TA-25-948860 | F28: 33473 | G28: ORDEN DE CAMBIO | H28: HUILA | I28: NEIVA | J28: BARRIO CENTRO NEIVA 3 | K28: REDEBAN | L28: FO-25-1353510 | M28: 45878.7 | N28: 45878.501 | P28: CIERRE | Q28: CIERRE | R28: CB UNO A UNO | S28: CB UNO A UNO | T28: ILOCALIZADO | U28: CB CERRADO - DESOCUPADO | V28: 0 0 09-08-2025 SE LLEGA AL PUNTO , LOCAL VACÍO Y DISPONIBLE , SE PREGUNTA A VIGILANTE DEL EDIFICIO COMENTANDO QUE LLEVA MUCHO TIEMPO VACÍO , SE LLAMA AL NÚMERO NO CONTESTA , SE ESCRIBE POR WHATSAPP NO HAY RESPUESTA | W28: VISITA_TÉCNICA | X28: 17ZZZ823 | Y28: TIPO I | Z28: =VLOOKUP(D28,TIPOLOGIAS!A:F,5,0) -> TERRESTRE | AA28: ANDRADE HERNANDEZ JUAN CARLOS | AB28: 1 | AC28: =IF(AND(W28="SOPORTE_TELEFÓNICO",OR(U28="SIN CONTACTO CON EL CB",U28="NÚMEROS DE CONTACTO ERRADOS")),0,IF(W28="SOPORTE_TELEFÓNICO",'BASE DE LIQUIDACION 2025'!$B$9,IF(Y28="TIPO I",'BASE DE LIQUIDACION 2025'!$C$3,IF(Y28="TIPO II",'BASE DE LIQUIDACION 2025'!$C$4,IF(Y28="TIPO III",'BASE DE LIQUIDACION 2025'!$C$5,'BASE DE LIQUIDACION 2025'!$C$6))))) -> 44559.564 | AD28: =IF(W28="SOPORTE_TELEFÓNICO",AC28,CIERRES!AB28*CIERRES!AC28) -> 44559.564
A29: NEIVA | B29: =VLOOKUP(A29,'CENTRO DE COSTOS'!A:D,4,FALSE) -> KEVIN ALEXIS CORZO BUSTOS | C29: =VLOOKUP(A29,'CENTRO DE COSTOS'!A:C,2,FALSE) -> 0004-0007 | D29: 41001 | E29: TA-25-948862 | F29: 33475 | G29: ORDEN DE CAMBIO | H29: HUILA | I29: NEIVA | J29: BARRIO CENTRO NEIVA 5 | K29: REDEBAN | L29: FO-25-1353516 | M29: 45878.7 | N29: 45878.508 | P29: CIERRE | Q29: CIERRE | R29: CB UNO A UNO | S29: CB UNO A UNO | T29: ILOCALIZADO | U29: CB CERRADO - DESOCUPADO | V29: 0 0 09-08-2025 SE REALIZA VISITA A LA DIRECCIÓN INDICADA EN LA ORDEN, SE EVIDENCIARÁ COMERCIO ESTÁ CERRADO , SE INTENTA COMUNICACIÓN A NÚMERO INDICADO EN LA ORDEN PERO NO HAY REPSUESTA. | W29: VISITA_TÉCNICA | X29: 0 | Y29: TIPO I | Z29: =VLOOKUP(D29,TIPOLOGIAS!A:F,5,0) -> TERRESTRE | AA29: DEVIA REINOSO JUAN CARLOS | AB29: 1 | AC29: =IF(AND(W29="SOPORTE_TELEFÓNICO",OR(U29="SIN CONTACTO CON EL CB",U29="NÚMEROS DE CONTACTO ERRADOS")),0,IF(W29="SOPORTE_TELEFÓNICO",'BASE DE LIQUIDACION 2025'!$B$9,IF(Y29="TIPO I",'BASE DE LIQUIDACION 2025'!$C$3,IF(Y29="TIPO II",'BASE DE LIQUIDACION 2025'!$C$4,IF(Y29="TIPO III",'BASE DE LIQUIDACION 2025'!$C$5,'BASE DE LIQUIDACION 2025'!$C$6))))) -> 44559.564 | AD29: =IF(W29="SOPORTE_TELEFÓNICO",AC29,CIERRES!AB29*CIERRES!AC29) -> 44559.564
A30: NEIVA | B30: =VLOOKUP(A30,'CENTRO DE COSTOS'!A:D,4,FALSE) -> KEVIN ALEXIS CORZO BUSTOS | C30: =VLOOKUP(A30,'CENTRO DE COSTOS'!A:C,2,FALSE) -> 0004-0007 | D30: 41001 | E30: TA-25-948861 | F30: 33474 | G30: ORDEN DE CAMBIO | H30: HUILA | I30: NEIVA | J30: BARRIO CENTRO NEIVA 4 | K30: REDEBAN | L30: FO-25-1353513 | M30: 45878.7 | N30: 45878.51 | P30: CIERRE | Q30: CIERRE | R30: CB UNO A UNO | S30: CB UNO A UNO | T30: ILOCALIZADO | U30: CB CERRADO - DESOCUPADO | V30: 0 0 09-08-2025 SE REALIZA VISITA A LA DIRECCIÓN INDICADA EN LA ORDEN, SE EVIDENCIARÁ COMERCIO ESTÁ CERRADO , SE INTENTA COMUNICACIÓN A NÚMERO INDICADO EN LA ORDEN PERO NO HAY REPSUESTA. | W30: VISITA_TÉCNICA | X30: 0 | Y30: TIPO I | Z30: =VLOOKUP(D30,TIPOLOGIAS!A:F,5,0) -> TERRESTRE | AA30: DEVIA REINOSO JUAN CARLOS | AB30: 1 | AC30: =IF(AND(W30="SOPORTE_TELEFÓNICO",OR(U30="SIN CONTACTO CON EL CB",U30="NÚMEROS DE CONTACTO ERRADOS")),0,IF(W30="SOPORTE_TELEFÓNICO",'BASE DE LIQUIDACION 2025'!$B$9,IF(Y30="TIPO I",'BASE DE LIQUIDACION 2025'!$C$3,IF(Y30="TIPO II",'BASE DE LIQUIDACION 2025'!$C$4,IF(Y30="TIPO III",'BASE DE LIQUIDACION 2025'!$C$5,'BASE DE LIQUIDACION 2025'!$C$6))))) -> 44559.564 | AD30: =IF(W30="SOPORTE_TELEFÓNICO",AC30,CIERRES!AB30*CIERRES!AC30) -> 44559.564
A31: NEIVA | B31: =VLOOKUP(A31,'CENTRO DE COSTOS'!A:D,4,FALSE) -> KEVIN ALEXIS CORZO BUSTOS | C31: =VLOOKUP(A31,'CENTRO DE COSTOS'!A:C,2,FALSE) -> 0004-0007 | D31: 18592 | E31: TA-25-924060 | F31: 77695 | G31: ORDEN DE CAMBIO | H31: CAQUETA | I31: PUERTO RICO | J31: BARRIO SIETE DE AGOSTO PUERTO RICO | K31: REDEBAN | L31: FO-25-1332827 | M31: 45874.597 | N31: 45880.535 | P31: CIERRE | Q31: CIERRE | R31: CB UNO A UNO | S31: CB UNO A UNO | T31: ILOCALIZADO | U31: CB CERRADO - DESOCUPADO | V31: 0 0 11-08-2025 SE LLEGA AL ESTABLECIMIENTO PERO SE ENCUENTRA CERRADO Y DESOCUPADO, SE PREGUNTA A LAS PERSONAS DEL SECTOR Y MANIFIESTA QUE SE FUERON DE AHÍ DEL LUGAR, SE LLAMA Y SE ESCRIBE AL NÚMERO DE LA TA PERO NADIE RESPONDE, CIERRE FALLIDO. | W31: VISITA_TÉCNICA | X31: 10LZZ966 | Y31: TIPO IV ESPECIAL | Z31: =VLOOKUP(D31,TIPOLOGIAS!A:F,5,0) -> TERRESTRE | AA31: BERMUDEZ SANCHEZ JOSE NEYBER | AB31: 1 | AC31: =IF(AND(W31="SOPORTE_TELEFÓNICO",OR(U31="SIN CONTACTO CON EL CB",U31="NÚMEROS DE CONTACTO ERRADOS")),0,IF(W31="SOPORTE_TELEFÓNICO",'BASE DE LIQUIDACION 2025'!$B$9,IF(Y31="TIPO I",'BASE DE LIQUIDACION 2025'!$C$3,IF(Y31="TIPO II",'BASE DE LIQUIDACION 2025'!$C$4,IF(Y31="TIPO III",'BASE DE LIQUIDACION 2025'!$C$5,'BASE DE LIQUIDACION 2025'!$C$6))))) -> 464809.37 | AD31: =IF(W31="SOPORTE_TELEFÓNICO",AC31,CIERRES!AB31*CIERRES!AC31) -> 464809.37
A32: NEIVA | B32: =VLOOKUP(A32,'CENTRO DE COSTOS'!A:D,4,FALSE) -> KEVIN ALEXIS CORZO BUSTOS | C32: =VLOOKUP(A32,'CENTRO DE COSTOS'!A:C,2,FALSE) -> 0004-0007 | D32: 73483 | E32: TA-25-948868 | F32: 75471 | G32: ORDEN DE CAMBIO | H32: TOLIMA | I32: NATAGAIMA | J32: BARRIO CENTRO NATAGAIMA | K32: REDEBAN | L32: FO-25-1361975 | M32: 45878.7 | N32: 45880.698 | P32: CIERRE | Q32: CIERRE | R32: CB UNO A UNO | S32: CB UNO A UNO | T32: EJECUTADO_EXITOSO | U32: CIERRE EXITOSO | V32: 0 0 11-08-2025 SE LLEGA AL SITIO COMERCIO CERRADO , VECINOS MANIFIESTA QUE EL ALMACÉN FUE RECOGIDO Y LLEVADO A IBAGUÉ, SE MARCA AL CELULAR NO CONTESTA, SE ESCRIBE POR WHATSAPP NO HAY RESPUESTA , CLIENTE EN EL ÚLTIMO MINUTO DA RESPUESTA COMENTANDO QUE LOS EQUIPOS ESTÁN EN EL MUNICIPIO DE SALDAÑA , QUE SI PODEMOS RECOGERLOS ALLÍ SE ESCALA AL JEFE INMEDIATO DONDE AUTORIZA DESPLAZARNOS HASTA SALDAÑA. 0 11-08-2025 CLIENTE ENTREGA DATAFONO , LECTOR DE BARRAS,CABLE MAGIC BOX, FUENTE DE PODER DATÁFONO Y CABLE DE RED , PUBLICIDAD Y ROLLOS NO HAY | W32: VISITA_TÉCNICA | X32: V100C094-A406Z663 | Y32: TIPO II | Z32: =VLOOKUP(D32,TIPOLOGIAS!A:F,5,0) -> TERRESTRE | AA32: ANDRADE HERNANDEZ JUAN CARLOS | AB32: 1 | AC32: =IF(AND(W32="SOPORTE_TELEFÓNICO",OR(U32="SIN CONTACTO CON EL CB",U32="NÚMEROS DE CONTACTO ERRADOS")),0,IF(W32="SOPORTE_TELEFÓNICO",'BASE DE LIQUIDACION 2025'!$B$9,IF(Y32="TIPO I",'BASE DE LIQUIDACION 2025'!$C$3,IF(Y32="TIPO II",'BASE DE LIQUIDACION 2025'!$C$4,IF(Y32="TIPO III",'BASE DE LIQUIDACION 2025'!$C$5,'BASE DE LIQUIDACION 2025'!$C$6))))) -> 134410.88 | AD32: =IF(W32="SOPORTE_TELEFÓNICO",AC32,CIERRES!AB32*CIERRES!AC32) -> 134410.88
A33: VILLAVICENCIO | B33: =VLOOKUP(A33,'CENTRO DE COSTOS'!A:D,4,FALSE) -> KEVIN ALEXIS CORZO BUSTOS | C33: =VLOOKUP(A33,'CENTRO DE COSTOS'!A:C,2,FALSE) -> 0004-0007 | D33: 50001 | E33: TA-25-948865 | F33: 74538 | G33: ORDEN DE CAMBIO | H33: META | I33: VILLAVICENCIO | J33: BARRIO DOCE DE OCTUBRE VILLAVI | K33: REDEBAN | L33: FO-25-1353528 | M33: 45878.7 | N33: 45881.365 | P33: CIERRE | Q33: CIERRE | R33: CB UNO A UNO | S33: CB UNO A UNO | T33: ILOCALIZADO | U33: CB CERRADO - DESOCUPADO | V33: 0 0 12-08-2025 SE REALIZA VISITA A LA DIRECCIÓN DE CB Y COMERCIO NO EXISTE, SE PREGUNTA EN LA DIRECCION Y NOS INFORMAN NO CONOCER AL SEÑOR OSCAR VARGAS | W33: VISITA_TÉCNICA | X33: 0 | Y33: TIPO I | Z33: =VLOOKUP(D33,TIPOLOGIAS!A:F,5,0) -> TERRESTRE | AA33: PEDREROS CONTRERAS MICHAEL STEVENS | AB33: 1 | AC33: =IF(AND(W33="SOPORTE_TELEFÓNICO",OR(U33="SIN CONTACTO CON EL CB",U33="NÚMEROS DE CONTACTO ERRADOS")),0,IF(W33="SOPORTE_TELEFÓNICO",'BASE DE LIQUIDACION 2025'!$B$9,IF(Y33="TIPO I",'BASE DE LIQUIDACION 2025'!$C$3,IF(Y33="TIPO II",'BASE DE LIQUIDACION 2025'!$C$4,IF(Y33="TIPO III",'BASE DE LIQUIDACION 2025'!$C$5,'BASE DE LIQUIDACION 2025'!$C$6))))) -> 44559.564 | AD33: =IF(W33="SOPORTE_TELEFÓNICO",AC33,CIERRES!AB33*CIERRES!AC33) -> 44559.564
A34: CALI | B34: =VLOOKUP(A34,'CENTRO DE COSTOS'!A:D,4,FALSE) -> DIEGO FERNANDO HENAO CARDONA | C34: =VLOOKUP(A34,'CENTRO DE COSTOS'!A:C,2,FALSE) -> 0004-0003 | D34: 76520 | E34: TA-25-948870 | F34: 59729 | G34: ORDEN DE CAMBIO | H34: VALLE DEL CAUCA | I34: PALMIRA | J34: BARRIO EL CENTRO PALMIRA | K34: REDEBAN | L34: FO-25-1353541 | M34: 45878.7 | N34: 45881.369 | P34: CIERRE | Q34: CIERRE | R34: CB UNO A UNO | S34: CB UNO A UNO | T34: NO_EXITOSO | U34: CB NO ENTREGA EQUIPO | V34: 0 0 11-08-2025 EN LA VISITA TÉCNICA SE ENCONTRÓ EL LUGAR CERRADO, SE REALIZÓ GESTIÓN TELEFÓNICA Y LA USUARIA INFORMA QUE ÉL CB YA NO EXISTE EN ESTE LUGAR INFORMA QUE ELLA PIDIÓ UN TRASLADO, NO UN CIERRE, ADICIONAL NO PUEDE ATENDER PORQUE NO SE ENCUENTRA | W34: VISITA_TÉCNICA | X34: 0 | Y34: TIPO I | Z34: =VLOOKUP(D34,TIPOLOGIAS!A:F,5,0) -> TERRESTRE | AA34: SANCHEZ URREGO ROBINSON DAVID | AB34: 1 | AC34: =IF(AND(W34="SOPORTE_TELEFÓNICO",OR(U34="SIN CONTACTO CON EL CB",U34="NÚMEROS DE CONTACTO ERRADOS")),0,IF(W34="SOPORTE_TELEFÓNICO",'BASE DE LIQUIDACION 2025'!$B$9,IF(Y34="TIPO I",'BASE DE LIQUIDACION 2025'!$C$3,IF(Y34="TIPO II",'BASE DE LIQUIDACION 2025'!$C$4,IF(Y34="TIPO III",'BASE DE LIQUIDACION 2025'!$C$5,'BASE DE LIQUIDACION 2025'!$C$6))))) -> 44559.564 | AD34: =IF(W34="SOPORTE_TELEFÓNICO",AC34,CIERRES!AB34*CIERRES!AC34) -> 44559.564
A35: CALI | B35: =VLOOKUP(A35,'CENTRO DE COSTOS'!A:D,4,FALSE) -> DIEGO FERNANDO HENAO CARDONA | C35: =VLOOKUP(A35,'CENTRO DE COSTOS'!A:C,2,FALSE) -> 0004-0003 | D35: 76109 | E35: TA-25-941581 | F35: 76884 | G35: ORDEN DE CAMBIO | H35: VALLE DEL CAUCA | I35: BUENAVENTURA | J35: BARRIO BAHIA MALAGA | K35: REDEBAN | L35: FO-25-1345197 | M35: 45875.724 | N35: 45881.387 | P35: CIERRE | Q35: RECUPERACION DE EQUIPOS | R35: CB UNO A UNO | S35: CB UNO A UNO | T35: NO_EXITOSO | U35: CB NO ENTREGA EQUIPO | V35: 0 0 12-08-2025 SE REALIZA LLAMADA A LOS NUMEROS A LA SEÑORA LIZETH , CONTESTA PERO INDICA NO TENER CONOCIMIENTO DE QUE LE HABLAMOS NI DE NINGUN CORRESPONSAL BANCARIA EN BAHIA MALAGA, SE BUSCAN MAS NUMEROS DE CONTACTO , SE ENCUENTRA EL NUMERO 3153841106, LA PERSONA QUE CONTESTA NO DA EL NOMBRE INDICA QUE ELLA YA NO TRABAJA CON EL SEÑOR EDWIN MANZUERA QUIEN ERA EL ENCARGADO DEL CORRESPONSAL INDCIA QUE ELLOS SE FUERON DE LA ISLA SIN DAR RAZON Y SIN PAGARLES , NO TIENE CONOCIMIENTO DE DONDE ESTAN LOS EQUIPOS PUES ALLA EN LA ISLA YA NO HAY NADA, NOS DA EL NUMERO DE CONTACTO DEL SEÑOR EDWIN PERO NO HA SIDO POSIBLE ENTABLAR COMUNICACION. | W35: SOPORTE_TELEFÓNICO | X35: 0 | Y35: TIPO III | Z35: =VLOOKUP(D35,TIPOLOGIAS!A:F,5,0) -> TERRESTRE | AA35: HENAO CARDONA DIEGO FERNANDO | AB35: 0 | AC35: =IF(AND(W35="SOPORTE_TELEFÓNICO",OR(U35="SIN CONTACTO CON EL CB",U35="NÚMEROS DE CONTACTO ERRADOS")),0,IF(W35="SOPORTE_TELEFÓNICO",'BASE DE LIQUIDACION 2025'!$B$9,IF(Y35="TIPO I",'BASE DE LIQUIDACION 2025'!$C$3,IF(Y35="TIPO II",'BASE DE LIQUIDACION 2025'!$C$4,IF(Y35="TIPO III",'BASE DE LIQUIDACION 2025'!$C$5,'BASE DE LIQUIDACION 2025'!$C$6))))) -> 37904.612 | AD35: =IF(W35="SOPORTE_TELEFÓNICO",AC35,CIERRES!AB35*CIERRES!AC35) -> 37904.612
A36: IBAGUE | B36: =VLOOKUP(A36,'CENTRO DE COSTOS'!A:D,4,FALSE) -> KEVIN ALEXIS CORZO BUSTOS | C36: =VLOOKUP(A36,'CENTRO DE COSTOS'!A:C,2,FALSE) -> 0004-0007 | D36: 73001 | E36: TA-25-948867 | F36: 67287 | G36: ORDEN DE CAMBIO | H36: TOLIMA | I36: IBAGUE | J36: BARRIO PRADERAS DE SANTA RITA | K36: REDEBAN | L36: FO-25-1353534 | M36: 45878.7 | N36: 45881.409 | P36: CIERRE | Q36: CIERRE | R36: CB UNO A UNO | S36: CB UNO A UNO | T36: NO_EXITOSO | U36: CB NO ENTREGA EQUIPO | V36: 0 0 12-08-2025 SE LLEGA ALA DIRECCIÓN INDICADA EVIDENCIA QUE ESTÁ CERRADO SE COMUNICA TELEFÓNICAMENTE,CON LA SEÑORITA MARIA DE LOS MILAGROS LOZANO AL TELÉFONO 3154255999 QUIEN MANIFIESTA QUE NO SOLICITO CIERRE ELLA SOLICITO ES UN TRASLADO,SE ESTARÁ COMUNICANDO CON LA ASERSOR(A)DE LA ENTIDAD ,PARA VALIDAR EL POR QUÉ DEL CIERRE USUARIO NO PERMITE EL CIERRE | W36: VISITA_TÉCNICA | X36: 0 | Y36: TIPO I | Z36: =VLOOKUP(D36,TIPOLOGIAS!A:F,5,0) -> TERRESTRE | AA36: GUTIERREZ CAMILO ANDRES | AB36: 1 | AC36: =IF(AND(W36="SOPORTE_TELEFÓNICO",OR(U36="SIN CONTACTO CON EL CB",U36="NÚMEROS DE CONTACTO ERRADOS")),0,IF(W36="SOPORTE_TELEFÓNICO",'BASE DE LIQUIDACION 2025'!$B$9,IF(Y36="TIPO I",'BASE DE LIQUIDACION 2025'!$C$3,IF(Y36="TIPO II",'BASE DE LIQUIDACION 2025'!$C$4,IF(Y36="TIPO III",'BASE DE LIQUIDACION 2025'!$C$5,'BASE DE LIQUIDACION 2025'!$C$6))))) -> 44559.564 | AD36: =IF(W36="SOPORTE_TELEFÓNICO",AC36,CIERRES!AB36*CIERRES!AC36) -> 44559.564
A37: PASTO | B37: =VLOOKUP(A37,'CENTRO DE COSTOS'!A:D,4,FALSE) -> DIEGO FERNANDO HENAO CARDONA | C37: =VLOOKUP(A37,'CENTRO DE COSTOS'!A:C,2,FALSE) -> 0004-0003 | D37: 52203 | E37: TA-25-941578 | F37: 49060 | G37: ORDEN DE CAMBIO | H37: NARIÑO | I37: COLON | J37: BARRIO LA MILAGROSA CORR DE VI | K37: REDEBAN | L37: FO-25-1345190 | M37: 45875.724 | N37: 45881.423 | P37: CIERRE | Q37: CIERRE | R37: CB UNO A UNO | S37: CB UNO A UNO | T37: NO_EXITOSO | U37: CB NO ENTREGA EQUIPO | V37: 0 0 12-08-2025 SE HABLA CON LA SEÑORA MARIA, QUIEN INDICA QUE ELLA TIENE LOS EQUIPOS PAR ENTREGAR PERO NO ESTA EN LA VEREDA, INDICA QUE ELLA ESTARA LA PROXIMA SEMANA EN LA CIUDAD DE PASTO Y SE CONTACTARA CON NOSOTROS PARA LA ENTREGA, SE PROCEDE A CERRAR VISITA POR VENCIMIENTO A LA ESPERA DE CONTACTO DEL CLIENTE PARA GESTIONAR NUEVO CIERRE. | W37: SOPORTE_TELEFÓNICO | X37: 0 | Y37: TIPO IV | Z37: =VLOOKUP(D37,TIPOLOGIAS!A:F,5,0) -> TERRESTRE | AA37: HENAO CARDONA DIEGO FERNANDO | AB37: 0 | AC37: =IF(AND(W37="SOPORTE_TELEFÓNICO",OR(U37="SIN CONTACTO CON EL CB",U37="NÚMEROS DE CONTACTO ERRADOS")),0,IF(W37="SOPORTE_TELEFÓNICO",'BASE DE LIQUIDACION 2025'!$B$9,IF(Y37="TIPO I",'BASE DE LIQUIDACION 2025'!$C$3,IF(Y37="TIPO II",'BASE DE LIQUIDACION 2025'!$C$4,IF(Y37="TIPO III",'BASE DE LIQUIDACION 2025'!$C$5,'BASE DE LIQUIDACION 2025'!$C$6))))) -> 37904.612 | AD37: =IF(W37="SOPORTE_TELEFÓNICO",AC37,CIERRES!AB37*CIERRES!AC37) -> 37904.612
A38: PASTO | B38: =VLOOKUP(A38,'CENTRO DE COSTOS'!A:D,4,FALSE) -> DIEGO FERNANDO HENAO CARDONA | C38: =VLOOKUP(A38,'CENTRO DE COSTOS'!A:C,2,FALSE) -> 0004-0003 | D38: 52323 | E38: TA-25-941591 | F38: 45928 | G38: ORDEN DE CAMBIO | H38: NARIÑO | I38: GUALMATAN | J38: PTM GUALMATAN PUNTOSERVIS GU | K38: REDEBAN | L38: FO-25-1345223 | M38: 45875.721 | N38: 45881.428 | P38: CIERRE | Q38: CIERRE | R38: AGREGADOR | S38: COMCARD - PTM | T38: NO_EXITOSO | U38: CB NO ENTREGA EQUIPO | V38: 0 0 12-08-2025 SE REALIZA LLAMADA CONTESTA UNA PERSONA QUE SE NIEGA A DAR EL NOMBRE, SE LE INDICA QUE ES PARA EL CIERRE DEL CORRESPONSAL , INDICA QUE YA NO TIENE CONTACTO NI NADA QUE VER CON EL, QUE ESO SE CERRO HACE MUCHO, Y SEGUN ELLA TODO FUE DEVUELTO, NO NOS ENTREGA MAS INFORMACION, SE LE SOLICITA OTRO NUMERO DE CONTACTO NO NOS LO SUMINISTRA, SE LE PREGUNTA SI HAY EXISTE EL LOCAL EN EL MUNICIPIO INDICA QUE NO, SE CIERRE EL CASO. | W38: SOPORTE_TELEFÓNICO | X38: 0 | Y38: TIPO II | Z38: =VLOOKUP(D38,TIPOLOGIAS!A:F,5,0) -> TERRESTRE | AA38: HENAO CARDONA DIEGO FERNANDO | AB38: 0 | AC38: =IF(AND(W38="SOPORTE_TELEFÓNICO",OR(U38="SIN CONTACTO CON EL CB",U38="NÚMEROS DE CONTACTO ERRADOS")),0,IF(W38="SOPORTE_TELEFÓNICO",'BASE DE LIQUIDACION 2025'!$B$9,IF(Y38="TIPO I",'BASE DE LIQUIDACION 2025'!$C$3,IF(Y38="TIPO II",'BASE DE LIQUIDACION 2025'!$C$4,IF(Y38="TIPO III",'BASE DE LIQUIDACION 2025'!$C$5,'BASE DE LIQUIDACION 2025'!$C$6))))) -> 37904.612 | AD38: =IF(W38="SOPORTE_TELEFÓNICO",AC38,CIERRES!AB38*CIERRES!AC38) -> 37904.612
A39: CALI | B39: =VLOOKUP(A39,'CENTRO DE COSTOS'!A:D,4,FALSE) -> DIEGO FERNANDO HENAO CARDONA | C39: =VLOOKUP(A39,'CENTRO DE COSTOS'!A:C,2,FALSE) -> 0004-0003 | D39: 76834 | E39: TA-25-948872 | F39: 76243 | G39: ORDEN DE CAMBIO | H39: VALLE DEL CAUCA | I39: TULUA | J39: BARRIO EL CENTRO TULUA 1 | K39: REDEBAN | L39: FO-25-1353543 | M39: 45878.7 | N39: 45881.469 | P39: CIERRE | Q39: CIERRE | R39: CB UNO A UNO | S39: CB UNO A UNO | T39: ILOCALIZADO | U39: CB CERRADO - DESOCUPADO | V39: 0 0 12-08-2025 SE VISITÓ Y SE ENCONTRÓ LOCAL CERRADO. SE LLAMA AL CONTACTO EN REPETIDAS OCASIONES Y NO CONTESTA. | W39: VISITA_TÉCNICA | X39: A40NZ752 | Y39: TIPO II | Z39: =VLOOKUP(D39,TIPOLOGIAS!A:F,5,0) -> TERRESTRE | AA39: BOLAÑOS TABORDA JORGE ENRIQUE | AB39: 1 | AC39: =IF(AND(W39="SOPORTE_TELEFÓNICO",OR(U39="SIN CONTACTO CON EL CB",U39="NÚMEROS DE CONTACTO ERRADOS")),0,IF(W39="SOPORTE_TELEFÓNICO",'BASE DE LIQUIDACION 2025'!$B$9,IF(Y39="TIPO I",'BASE DE LIQUIDACION 2025'!$C$3,IF(Y39="TIPO II",'BASE DE LIQUIDACION 2025'!$C$4,IF(Y39="TIPO III",'BASE DE LIQUIDACION 2025'!$C$5,'BASE DE LIQUIDACION 2025'!$C$6))))) -> 134410.88 | AD39: =IF(W39="SOPORTE_TELEFÓNICO",AC39,CIERRES!AB39*CIERRES!AC39) -> 134410.88
A40: MONTERIA | B40: =VLOOKUP(A40,'CENTRO DE COSTOS'!A:D,4,FALSE) -> JOSE MAURICIO HERNANDEZ ROJAS | C40: =VLOOKUP(A40,'CENTRO DE COSTOS'!A:C,2,FALSE) -> 0004-0001 | D40: 23001 | E40: TA-25-948859 | F40: 78090 | G40: ORDEN DE CAMBIO | H40: CORDOBA | I40: MONTERIA | J40: BARRIO URBANIZACION VALLEJO MONTERIA 8 | K40: REDEBAN | L40: FO-25-1353504 | M40: 45878.7 | N40: 45881.503 | P40: CIERRE | Q40: CIERRE | R40: CB UNO A UNO | S40: CB UNO A UNO | T40: NO_EXITOSO | U40: CB NO ENTREGA EQUIPO | V40: 0 0 12-08-2025 VISITA FALLIDA, LA PERSONA EN SITIO NO TIENE AUTORIZACIÓN DE ENTREGAR LOS EQUIPOS.CLIENTE NO LOGRA COMUNICARSE CON EL PROPIETARIO PARA LE DE EL AVAL DEL CIERRE | W40: VISITA_TÉCNICA | X40: 0 | Y40: TIPO I | Z40: =VLOOKUP(D40,TIPOLOGIAS!A:F,5,0) -> TERRESTRE | AA40: CALDERA SALCEDO CARLOS JULIO | AB40: 1 | AC40: =IF(AND(W40="SOPORTE_TELEFÓNICO",OR(U40="SIN CONTACTO CON EL CB",U40="NÚMEROS DE CONTACTO ERRADOS")),0,IF(W40="SOPORTE_TELEFÓNICO",'BASE DE LIQUIDACION 2025'!$B$9,IF(Y40="TIPO I",'BASE DE LIQUIDACION 2025'!$C$3,IF(Y40="TIPO II",'BASE DE LIQUIDACION 2025'!$C$4,IF(Y40="TIPO III",'BASE DE LIQUIDACION 2025'!$C$5,'BASE DE LIQUIDACION 2025'!$C$6))))) -> 44559.564 | AD40: =IF(W40="SOPORTE_TELEFÓNICO",AC40,CIERRES!AB40*CIERRES!AC40) -> 44559.564
A41: BOGOTA | B41: =VLOOKUP(A41,'CENTRO DE COSTOS'!A:D,4,FALSE) -> WILLIAM ASDRUBAL ROZO ROZO | C41: =VLOOKUP(A41,'CENTRO DE COSTOS'!A:C,2,FALSE) -> 0004-0004 | D41: 11001 | E41: TA-25-963282 | F41: 78672 | G41: ORDEN DE CAMBIO | H41: CUNDINAMARCA | I41: BOGOTA | J41: PTM BOGOTA COMERCIALIZADORA Y | K41: REDEBAN | L41: FO-25-1365303 | M41: 45881.468 | N41: 45881.574 | P41: CIERRE | Q41: CAMBIO DE RAZÓN SOCIAL | R41: AGREGADOR | S41: COMCARD - PTM | T41: NO_EXITOSO | U41: CB NO ENTREGA EQUIPO | V41: 0 0 12-08-2025 SE VISITA COMERCIO POR CIERRE DE PUNTO POR CAMBIO DE RAZÓN SOCIAL YA QUE SE INSTALA CB 80935. PERO EN MEDIO DE LA INSTALACIÓN ENTIDAD BANCARIA NO AUTORIZA EL PROCESO DE APERTURA Y SOLICITA RECOGER EQUIPOS DE DICHO CAMBIO DE RAZÓN SOCIAL POR ENDE LA CLIENTE YA NO REALIZARÁ ENTREGA DEL CB MIENTRAS RECIBE RESPUESTA DEL NUEVO CB Y SE COMPLETA CIERRE SIN MÁS NOVEDAD | W41: VISITA_TÉCNICA | X41: 10RZZ176;10RZZ139 | Y41: TIPO I | Z41: =VLOOKUP(D41,TIPOLOGIAS!A:F,5,0) -> TERRESTRE | AA41: ROMERO ROJAS BREIDY JHOHAN | AB41: 1 | AC41: =IF(AND(W41="SOPORTE_TELEFÓNICO",OR(U41="SIN CONTACTO CON EL CB",U41="NÚMEROS DE CONTACTO ERRADOS")),0,IF(W41="SOPORTE_TELEFÓNICO",'BASE DE LIQUIDACION 2025'!$B$9,IF(Y41="TIPO I",'BASE DE LIQUIDACION 2025'!$C$3,IF(Y41="TIPO II",'BASE DE LIQUIDACION 2025'!$C$4,IF(Y41="TIPO III",'BASE DE LIQUIDACION 2025'!$C$5,'BASE DE LIQUIDACION 2025'!$C$6))))) -> 44559.564 | AD41: =IF(W41="SOPORTE_TELEFÓNICO",AC41,CIERRES!AB41*CIERRES!AC41) -> 44559.564
A42: TUNJA | B42: =VLOOKUP(A42,'CENTRO DE COSTOS'!A:D,4,FALSE) -> MIGUEL JULIÁN HERNÁNDEZ GUARÍN | C42: =VLOOKUP(A42,'CENTRO DE COSTOS'!A:C,2,FALSE) -> 0004-0008 | D42: 15272 | E42: TA-25-922763 | F42: 12066 | G42: ORDEN DE CAMBIO | H42: BOYACA | I42: FIRAVITOBA | J42: FIRAVITOBA - BOYACA | K42: REDEBAN | L42: FO-25-1331390 | M42: 45874.487 | N42: 45882.333 | P42: CIERRE | Q42: RECUPERACION DE EQUIPOS | R42: CB UNO A UNO | S42: CB UNO A UNO | T42: NO_EXITOSO | U42: PARCIAL EXITOSO PTE. DATAFONO | V42: 0 12/08/2025 SE RECIBE FO YA RECHAZADO POR CENTRO DE GESTIÓN EN EL FO CONTROL DE VISITA 12-08-2025 SE HACE PRESENCIA EN EL PUNTO Y SE IDENTIFICA QUE EL COMERCIO NO TIENE INTENCIÓN DE RETIRO. SE VERIFICA QUE CUENTA CON EL INVENTARIO COMPLETO SOLICITADO CON REDEBAN. SE PROCEDE A EJECUTAR EL PROCESO DE LEGALIZACIÓN DE ACTIVOS, YA QUE LA LECTORA CON SERIAL 805654 PERTENECE AL PUNTO VISITADO, AUNQUE FUE RETIRADA PREVIAMENTE EN EL CB: 3007046009 - PTM LA BELLEZA ACEITES Y LUB, CON LA TA: 25-899497. DE ACUERDO CON LA INFORMACIÓN SUMINISTRADA POR REDEBAN, SE DEJA EL ACTIVO LEGALIZADO EN EL PUNTO ACTUAL. | W42: VISITA_TÉCNICA | X42: 0 | Y42: TIPO II | Z42: =VLOOKUP(D42,TIPOLOGIAS!A:F,5,0) -> TERRESTRE | AA42: ALVARADO MORENO CRISTHIAN | AB42: 1 | AC42: =IF(AND(W42="SOPORTE_TELEFÓNICO",OR(U42="SIN CONTACTO CON EL CB",U42="NÚMEROS DE CONTACTO ERRADOS")),0,IF(W42="SOPORTE_TELEFÓNICO",'BASE DE LIQUIDACION 2025'!$B$9,IF(Y42="TIPO I",'BASE DE LIQUIDACION 2025'!$C$3,IF(Y42="TIPO II",'BASE DE LIQUIDACION 2025'!$C$4,IF(Y42="TIPO III",'BASE DE LIQUIDACION 2025'!$C$5,'BASE DE LIQUIDACION 2025'!$C$6))))) -> 134410.88 | AD42: =IF(W42="SOPORTE_TELEFÓNICO",AC42,CIERRES!AB42*CIERRES!AC42) -> 134410.88
A43: NEIVA | B43: =VLOOKUP(A43,'CENTRO DE COSTOS'!A:D,4,FALSE) -> KEVIN ALEXIS CORZO BUSTOS | C43: =VLOOKUP(A43,'CENTRO DE COSTOS'!A:C,2,FALSE) -> 0004-0007 | D43: 41551 | E43: TA-25-948863 | F43: 33477 | G43: ORDEN DE CAMBIO | H43: HUILA | I43: PITALITO | J43: BARRIO CENTRO PITALITO 1 | K43: REDEBAN | L43: FO-25-1353520 | M43: 45878.7 | N43: 45882.507 | P43: CIERRE | Q43: CIERRE | R43: CB UNO A UNO | S43: CB UNO A UNO | T43: NO_EXITOSO | U43: CB NO ENTREGA EQUIPO | V43: 0 0 13-08-2025 SE REALIZA VISITA AL PUNTO, PERSONA ENCARGADA INDICA QUE NO ESTA TIENE CONTACTO CON EL TITULAR E INDICA QUE ESOS EQUIPOS YA FUERON RETIRADOS DE ESA DIRECCION . | W43: VISITA_TÉCNICA | X43: NONE | Y43: TIPO III | Z43: =VLOOKUP(D43,TIPOLOGIAS!A:F,5,0) -> TERRESTRE | AA43: DEVIA REINOSO JUAN CARLOS | AB43: 1 | AC43: =IF(AND(W43="SOPORTE_TELEFÓNICO",OR(U43="SIN CONTACTO CON EL CB",U43="NÚMEROS DE CONTACTO ERRADOS")),0,IF(W43="SOPORTE_TELEFÓNICO",'BASE DE LIQUIDACION 2025'!$B$9,IF(Y43="TIPO I",'BASE DE LIQUIDACION 2025'!$C$3,IF(Y43="TIPO II",'BASE DE LIQUIDACION 2025'!$C$4,IF(Y43="TIPO III",'BASE DE LIQUIDACION 2025'!$C$5,'BASE DE LIQUIDACION 2025'!$C$6))))) -> 222904.07 | AD43: =IF(W43="SOPORTE_TELEFÓNICO",AC43,CIERRES!AB43*CIERRES!AC43) -> 222904.07
A44: VILLAVICENCIO | B44: =VLOOKUP(A44,'CENTRO DE COSTOS'!A:D,4,FALSE) -> KEVIN ALEXIS CORZO BUSTOS | C44: =VLOOKUP(A44,'CENTRO DE COSTOS'!A:C,2,FALSE) -> 0004-0007 | D44: 50001 | E44: TA-25-941579 | F44: 76622 | G44: ORDEN DE CAMBIO | H44: META | I44: VILLAVICENCIO | J44: BARRIO CATUMARE VILLAVICENCIO 1 | K44: REDEBAN | L44: FO-25-1345194 | M44: 45875.724 | N44: 45882.581 | P44: CIERRE | Q44: CIERRE | R44: CB UNO A UNO | S44: CB UNO A UNO | T44: ILOCALIZADO | U44: CB CERRADO - DESOCUPADO | V44: 0 0 13-08-2025 SE VISITA DIRECCIÓN DE COMERCIO PERO LA LLEGAR AL SITIO EL COMERCIO MO EXISTE..VECINOS INFORMAN QUE LA DOREGURIA LA QUITARON HCE VARIAS SEMANAS. SE LLAMA AL NÚMERO PERO PSA. A BUZÓN DE VOZ. NO ES POSIBLE CONTACTAR AL CLIENTE | W44: VISITA_TÉCNICA | X44: 0 | Y44: TIPO I | Z44: =VLOOKUP(D44,TIPOLOGIAS!A:F,5,0) -> TERRESTRE | AA44: GARZON RUIZ LUIS MIGUEL | AB44: 1 | AC44: =IF(AND(W44="SOPORTE_TELEFÓNICO",OR(U44="SIN CONTACTO CON EL CB",U44="NÚMEROS DE CONTACTO ERRADOS")),0,IF(W44="SOPORTE_TELEFÓNICO",'BASE DE LIQUIDACION 2025'!$B$9,IF(Y44="TIPO I",'BASE DE LIQUIDACION 2025'!$C$3,IF(Y44="TIPO II",'BASE DE LIQUIDACION 2025'!$C$4,IF(Y44="TIPO III",'BASE DE LIQUIDACION 2025'!$C$5,'BASE DE LIQUIDACION 2025'!$C$6))))) -> 44559.564 | AD44: =IF(W44="SOPORTE_TELEFÓNICO",AC44,CIERRES!AB44*CIERRES!AC44) -> 44559.564
A45: MEDELLIN | B45: =VLOOKUP(A45,'CENTRO DE COSTOS'!A:D,4,FALSE) -> JUAN SEBASTIÁN RÍOS CASTRILLÓN | C45: =VLOOKUP(A45,'CENTRO DE COSTOS'!A:C,2,FALSE) -> 0004-0005 | D45: 5440 | E45: TA-25-948846 | F45: 78230 | G45: ORDEN DE CAMBIO | H45: ANTIOQUIA | I45: MARINILLA | J45: DISTRICOL PAPELERIA Y REMATES | K45: REDEBAN | L45: FO-25-1353462 | M45: 45878.699 | N45: 45883.441 | P45: CIERRE | Q45: CIERRE | R45: AGREGADOR | S45: DISTRICOL | T45: NO_EXITOSO | U45: CB NO ENTREGA EQUIPO | V45: 0 0 14-08-2025 SE VISITÓ CORRESPONSAL LA SEÑORA LILIANA NOS INFORMA QUE PERSONAL DE DISTRICOL RECOGÍO EL EQUIPO | W45: VISITA_TÉCNICA | X45: 0 | Y45: TIPO II | Z45: =VLOOKUP(D45,TIPOLOGIAS!A:F,5,0) -> TERRESTRE | AA45: CASTAÑEDA PALACIO CARLOS FELIPE | AB45: 1 | AC45: =IF(AND(W45="SOPORTE_TELEFÓNICO",OR(U45="SIN CONTACTO CON EL CB",U45="NÚMEROS DE CONTACTO ERRADOS")),0,IF(W45="SOPORTE_TELEFÓNICO",'BASE DE LIQUIDACION 2025'!$B$9,IF(Y45="TIPO I",'BASE DE LIQUIDACION 2025'!$C$3,IF(Y45="TIPO II",'BASE DE LIQUIDACION 2025'!$C$4,IF(Y45="TIPO III",'BASE DE LIQUIDACION 2025'!$C$5,'BASE DE LIQUIDACION 2025'!$C$6))))) -> 134410.88 | AD45: =IF(W45="SOPORTE_TELEFÓNICO",AC45,CIERRES!AB45*CIERRES!AC45) -> 134410.88
A46: IBAGUE | B46: =VLOOKUP(A46,'CENTRO DE COSTOS'!A:D,4,FALSE) -> KEVIN ALEXIS CORZO BUSTOS | C46: =VLOOKUP(A46,'CENTRO DE COSTOS'!A:C,2,FALSE) -> 0004-0007 | D46: 73001 | E46: TA-25-941593 | F46: 60446 | G46: ORDEN DE CAMBIO | H46: TOLIMA | I46: IBAGUE | J46: PTM IBAGUE PAPELERIA NELLA | K46: REDEBAN | L46: FO-25-1345226 | M46: 45875.721 | N46: 45883.575 | P46: CIERRE | Q46: CIERRE | R46: AGREGADOR | S46: COMCARD - PTM | T46: ILOCALIZADO | U46: SIN CONTACTO CON EL CB | V46: 0 0 14-08-2025 SE LLAMA A LA SEÑORA ALEXANDRA BOCANEGRA, AL NÚMERO 3152871429 Y NO CONTESTA. SE ESCRIBE POR WHATSAPP AL MISMO NÚMERO 3152871429, SIN ENCONTRAR RESPUESTA, LE LLEGA LOS MENSAJES PERO NO LOS VE. LA DIRECCIÓN ESTÁ POR MANZANA Y NÚMERO DE CASA, PERO NO APARECE EL NOMBRE DEL BARRIO. SE AVERIGUA POR LA WEB CON NÚMERO DE PLACA Y TERMINAL, PARA SABER EL NOMBRE DEL BARRIO, PERO NO APARECE Y ES UN CORRESPONSAL MIXTO. | W46: SOPORTE_TELEFÓNICO | X46: 0 | Y46: TIPO I | Z46: =VLOOKUP(D46,TIPOLOGIAS!A:F,5,0) -> TERRESTRE | AA46: VARGAS HERRERA JHON JAIRO | AB46: 0 | AC46: =IF(AND(W46="SOPORTE_TELEFÓNICO",OR(U46="SIN CONTACTO CON EL CB",U46="NÚMEROS DE CONTACTO ERRADOS")),0,IF(W46="SOPORTE_TELEFÓNICO",'BASE DE LIQUIDACION 2025'!$B$9,IF(Y46="TIPO I",'BASE DE LIQUIDACION 2025'!$C$3,IF(Y46="TIPO II",'BASE DE LIQUIDACION 2025'!$C$4,IF(Y46="TIPO III",'BASE DE LIQUIDACION 2025'!$C$5,'BASE DE LIQUIDACION 2025'!$C$6))))) -> 0 | AD46: =IF(W46="SOPORTE_TELEFÓNICO",AC46,CIERRES!AB46*CIERRES!AC46) -> 0
A47: NEIVA | B47: =VLOOKUP(A47,'CENTRO DE COSTOS'!A:D,4,FALSE) -> KEVIN ALEXIS CORZO BUSTOS | C47: =VLOOKUP(A47,'CENTRO DE COSTOS'!A:C,2,FALSE) -> 0004-0007 | D47: 41001 | E47: TA-25-962678 | F47: 78548 | G47: ORDEN DE CAMBIO | H47: HUILA | I47: NEIVA | J47: BARRIO MONSERRATE NEIVA 1 | K47: REDEBAN | L47: FO-25-1369308 | M47: 45881.333 | N47: 45883.658 | P47: CIERRE | Q47: CIERRE | R47: CB UNO A UNO | S47: CB UNO A UNO | T47: EJECUTADO_EXITOSO | U47: CIERRE EXITOSO | V47: 0 0 12-08-2025 SE LLEGA A SITIO, NO SE ENCUENTRA NADIE EN COMERCIO, SE LLAMAN AL NÚMERO 3182375307 Y EN COMUNICACIÓN CON EL SEÑOR JOHN FREDY TIMOTE PERDOMO SOLICITA REALIZAR VISITA EL DÍA DE MAÑANA DESPUÉS DE LAS 4:30. 13/08/2025 EN LLAMADA CON CLIENTE JOHN FREDY TIMOTE PERDOMO AL NÚMERO 3182375307 SOLICITA REALIZAR VISITA EL DÍA DE MAÑANA. 14-08-2025 SE LLEGA A SITIO, SE RECOGE DATAFONO Y LECTOR DE BARRAS. | W47: VISITA_TÉCNICA | X47: F1LZZ956 | Y47: TIPO I | Z47: =VLOOKUP(D47,TIPOLOGIAS!A:F,5,0) -> TERRESTRE | AA47: DIAZ VARGAS JONATHAN MIGUEL | AB47: 1 | AC47: =IF(AND(W47="SOPORTE_TELEFÓNICO",OR(U47="SIN CONTACTO CON EL CB",U47="NÚMEROS DE CONTACTO ERRADOS")),0,IF(W47="SOPORTE_TELEFÓNICO",'BASE DE LIQUIDACION 2025'!$B$9,IF(Y47="TIPO I",'BASE DE LIQUIDACION 2025'!$C$3,IF(Y47="TIPO II",'BASE DE LIQUIDACION 2025'!$C$4,IF(Y47="TIPO III",'BASE DE LIQUIDACION 2025'!$C$5,'BASE DE LIQUIDACION 2025'!$C$6))))) -> 44559.564 | AD47: =IF(W47="SOPORTE_TELEFÓNICO",AC47,CIERRES!AB47*CIERRES!AC47) -> 44559.564
A48: CALI | B48: =VLOOKUP(A48,'CENTRO DE COSTOS'!A:D,4,FALSE) -> DIEGO FERNANDO HENAO CARDONA | C48: =VLOOKUP(A48,'CENTRO DE COSTOS'!A:C,2,FALSE) -> 0004-0003 | D48: 76001 | E48: TA-25-973870 | F48: 76363 | G48: ORDEN DE CAMBIO | H48: VALLE DEL CAUCA | I48: CALI | J48: BARRIO UNICENTRO CALI CALI | K48: REDEBAN | L48: FO-25-1375884 | M48: 45883.479 | N48: 45884.343 | P48: CIERRE | Q48: CIERRE | R48: CB UNO A UNO | S48: CB UNO A UNO | T48: ILOCALIZADO | U48: CB CERRADO - DESOCUPADO | V48: 0 0 14-08-2025 SE VISITA EL COMERCIO SE ENCUENTRA CERRADO, SE PREGUNTA A LOS VECINOS CERCANOS INFORMA QUE SE FUERON HACE 8 DÍAS, SE LLAMA AL CLIENTE AL NÚMERO 3155157165 ESTA APAGADO SE VA A BUZÓN, LA VISITA ES FALLIDA, CIERRE NO EXISITOSO | W48: VISITA_TÉCNICA | X48: A10RZ460 | Y48: TIPO I | Z48: =VLOOKUP(D48,TIPOLOGIAS!A:F,5,0) -> TERRESTRE | AA48: HERRERA MONAR GEOVANNY | AB48: 1 | AC48: =IF(AND(W48="SOPORTE_TELEFÓNICO",OR(U48="SIN CONTACTO CON EL CB",U48="NÚMEROS DE CONTACTO ERRADOS")),0,IF(W48="SOPORTE_TELEFÓNICO",'BASE DE LIQUIDACION 2025'!$B$9,IF(Y48="TIPO I",'BASE DE LIQUIDACION 2025'!$C$3,IF(Y48="TIPO II",'BASE DE LIQUIDACION 2025'!$C$4,IF(Y48="TIPO III",'BASE DE LIQUIDACION 2025'!$C$5,'BASE DE LIQUIDACION 2025'!$C$6))))) -> 44559.564 | AD48: =IF(W48="SOPORTE_TELEFÓNICO",AC48,CIERRES!AB48*CIERRES!AC48) -> 44559.564
A49: VALLEDUPAR | B49: =VLOOKUP(A49,'CENTRO DE COSTOS'!A:D,4,FALSE) -> JOSE MAURICIO HERNANDEZ ROJAS | C49: =VLOOKUP(A49,'CENTRO DE COSTOS'!A:C,2,FALSE) -> 0004-0001 | D49: 20787 | E49: TA-25-948858 | F49: 76650 | G49: ORDEN DE CAMBIO | H49: CESAR | I49: TAMALAMEQUE | J49: BARRIO FLORES DE SABANA TAMALAMEQUE | K49: REDEBAN | L49: FO-25-1353501 | M49: 45878.7 | N49: 45884.347 | P49: CIERRE | Q49: CIERRE | R49: CB UNO A UNO | S49: CB UNO A UNO | T49: NO_EXITOSO | U49: CB NO ENTREGA EQUIPO | V49: 0 0 14-08-2025 SE COMUNICA CON LA SEÑORA BILIVAL CALLE, LA CUAL INDICAN QUE EL CB SE ENCUENTRA A SU NOMBRE PERO QUE LA PERSONA ENCARGADA DEL CB TRASLADO DE MANERA INFORMAL EL CB PARA SANTA ROSA DEL SUR DE BOLIVAR, Y DICHA PERSONA NO TIENE INTENCIONES DE ENTREGAR LOS EQUIPOS, LA SEÑORA MANIFIESTA QUE VA A TRATAR DE SOLUCIONAR LA SITUACIÓNA PARA QUE ESA PERSONA ENTREGUE LOS EQUIPOS | W49: SOPORTE_TELEFÓNICO | X49: 0 | Y49: TIPO IV | Z49: =VLOOKUP(D49,TIPOLOGIAS!A:F,5,0) -> TERRESTRE | AA49: MONTES DIAZ JOHN FRED | AB49: 0 | AC49: =IF(AND(W49="SOPORTE_TELEFÓNICO",OR(U49="SIN CONTACTO CON EL CB",U49="NÚMEROS DE CONTACTO ERRADOS")),0,IF(W49="SOPORTE_TELEFÓNICO",'BASE DE LIQUIDACION 2025'!$B$9,IF(Y49="TIPO I",'BASE DE LIQUIDACION 2025'!$C$3,IF(Y49="TIPO II",'BASE DE LIQUIDACION 2025'!$C$4,IF(Y49="TIPO III",'BASE DE LIQUIDACION 2025'!$C$5,'BASE DE LIQUIDACION 2025'!$C$6))))) -> 37904.612 | AD49: =IF(W49="SOPORTE_TELEFÓNICO",AC49,CIERRES!AB49*CIERRES!AC49) -> 37904.612
A50: MEDELLIN | B50: =VLOOKUP(A50,'CENTRO DE COSTOS'!A:D,4,FALSE) -> JUAN SEBASTIÁN RÍOS CASTRILLÓN | C50: =VLOOKUP(A50,'CENTRO DE COSTOS'!A:C,2,FALSE) -> 0004-0005 | D50: 5308 | E50: TA-25-948855 | F50: 29502 | G50: ORDEN DE CAMBIO | H50: ANTIOQUIA | I50: GIRARDOTA | J50: BARRIO 0 GIRARDOTA | K50: REDEBAN | L50: FO-25-1353491 | M50: 45878.7 | N50: 45884.512 | P50: CIERRE | Q50: CIERRE | R50: CB UNO A UNO | S50: CB UNO A UNO | T50: SOLICITUD_CANCELADA | U50: CANCELADO POR LA ENTIDAD | V50: 0 0 15-08-2025 SE COMUNICA CON EL USUARIO PARA RECLAMAR LOS EQUIPOS DEL CORRESPONSAL BANCARIO, E INDICA QUE EN MOMENTO NO SE ENCUENTRA EN SITIO Y NO SABE CON EXACTITUD CUANDO ESTÉ DE REGRESO | W50: SOPORTE_TELEFÓNICO | X50: 0 | Y50: TIPO I | Z50: =VLOOKUP(D50,TIPOLOGIAS!A:F,5,0) -> TERRESTRE | AA50: ZAPATA LOPEZ EDWARD ASDRUBAL | AB50: 0 | AC50: =IF(AND(W50="SOPORTE_TELEFÓNICO",OR(U50="SIN CONTACTO CON EL CB",U50="NÚMEROS DE CONTACTO ERRADOS")),0,IF(W50="SOPORTE_TELEFÓNICO",'BASE DE LIQUIDACION 2025'!$B$9,IF(Y50="TIPO I",'BASE DE LIQUIDACION 2025'!$C$3,IF(Y50="TIPO II",'BASE DE LIQUIDACION 2025'!$C$4,IF(Y50="TIPO III",'BASE DE LIQUIDACION 2025'!$C$5,'BASE DE LIQUIDACION 2025'!$C$6))))) -> 37904.612 | AD50: =IF(W50="SOPORTE_TELEFÓNICO",AC50,CIERRES!AB50*CIERRES!AC50) -> 37904.612
A51: CUCUTA | B51: =VLOOKUP(A51,'CENTRO DE COSTOS'!A:D,4,FALSE) -> MIGUEL JULIÁN HERNÁNDEZ GUARÍN | C51: =VLOOKUP(A51,'CENTRO DE COSTOS'!A:C,2,FALSE) -> 0004-0008 | D51: 54001 | E51: TA-25-972854 | F51: 79630 | G51: ORDEN DE CAMBIO | H51: NORTE DE SANTANDER | I51: CUCUTA | J51: BARRIO LATINO CUCUTA 20 | K51: REDEBAN | L51: FO-25-1373985 | M51: 45883.338 | N51: 45884.64 | P51: CIERRE | Q51: CIERRE | R51: CB UNO A UNO | S51: CB UNO A UNO | T51: ILOCALIZADO | U51: CB CERRADO - DESOCUPADO | V51: 0 0 15-08-2025 SE REALIZÓ VISITA A LA DIRECCIÓN ASIGNADA Y SE ENCUENTRA QUE YA NO EXISTE EL COMERCIO, SE REALIZAN LLAMADAS TELEFÓNICA AL NÚMERO ASIGNADO Y SE NO SE OBTIENE RESPUESTA | W51: VISITA_TÉCNICA | X51: 0 | Y51: TIPO I | Z51: =VLOOKUP(D51,TIPOLOGIAS!A:F,5,0) -> TERRESTRE | AA51: MORA VEGA JEAMPIER | AB51: 1 | AC51: =IF(AND(W51="SOPORTE_TELEFÓNICO",OR(U51="SIN CONTACTO CON EL CB",U51="NÚMEROS DE CONTACTO ERRADOS")),0,IF(W51="SOPORTE_TELEFÓNICO",'BASE DE LIQUIDACION 2025'!$B$9,IF(Y51="TIPO I",'BASE DE LIQUIDACION 2025'!$C$3,IF(Y51="TIPO II",'BASE DE LIQUIDACION 2025'!$C$4,IF(Y51="TIPO III",'BASE DE LIQUIDACION 2025'!$C$5,'BASE DE LIQUIDACION 2025'!$C$6))))) -> 44559.564 | AD51: =IF(W51="SOPORTE_TELEFÓNICO",AC51,CIERRES!AB51*CIERRES!AC51) -> 44559.564
A52: MONTERIA | B52: =VLOOKUP(A52,'CENTRO DE COSTOS'!A:D,4,FALSE) -> JOSE MAURICIO HERNANDEZ ROJAS | C52: =VLOOKUP(A52,'CENTRO DE COSTOS'!A:C,2,FALSE) -> 0004-0001 | D52: 23068 | E52: LC-CS-25-000028 | F52: 72855 | G52: ORDEN DE CAMBIO | H52: CORDOBA | I52: AYAPEL | J52: SANTA ANA AYAPEL | K52: REDEBAN | L52: FO-25-1380888 | M52: 45884.528 | N52: 45884.655 | P52: CIERRE | Q52: CIERRE | R52: CB UNO A UNO | S52: CB UNO A UNO | T52: NO_EXITOSO | U52: CB NO ENTREGA EQUIPO | V52: 0 0 15-08-2025 SE LLEGÓ A SITIO Y LA SEÑORA MARIBEL CASTRO INFORMA QUE ELLA COMPENSÓ HACE UN MES APROXIMADAMENTE Y LE INFORMO AL BANCO QUÉ IBA A REALIZAR UNA REMODELACIÓN QUE TARDABA VARIOS DÍAS, POR TAL MOTIVO NO PERMITIÓ EL CIERRE Y QUIERE QUE EL BANCO LE ACTIVE EL CB PORQUE YA ESTÁ NUEVAMENTE EN OPERACIÓN EL LOCAL COMERCIAL, SE LE INFORMA QUE DEBE LLAMAR A LA LÍNEA DE ATENCIÓN 018000853344. | W52: VISITA_TÉCNICA | X52: 0 | Y52: TIPO III | Z52: =VLOOKUP(D52,TIPOLOGIAS!A:F,5,0) -> TERRESTRE | AA52: CALDERA SALCEDO CARLOS JULIO | AB52: 1 | AC52: =IF(AND(W52="SOPORTE_TELEFÓNICO",OR(U52="SIN CONTACTO CON EL CB",U52="NÚMEROS DE CONTACTO ERRADOS")),0,IF(W52="SOPORTE_TELEFÓNICO",'BASE DE LIQUIDACION 2025'!$B$9,IF(Y52="TIPO I",'BASE DE LIQUIDACION 2025'!$C$3,IF(Y52="TIPO II",'BASE DE LIQUIDACION 2025'!$C$4,IF(Y52="TIPO III",'BASE DE LIQUIDACION 2025'!$C$5,'BASE DE LIQUIDACION 2025'!$C$6))))) -> 222904.07 | AD52: =IF(W52="SOPORTE_TELEFÓNICO",AC52,CIERRES!AB52*CIERRES!AC52) -> 222904.07
A53: PASTO | B53: =VLOOKUP(A53,'CENTRO DE COSTOS'!A:D,4,FALSE) -> DIEGO FERNANDO HENAO CARDONA | C53: =VLOOKUP(A53,'CENTRO DE COSTOS'!A:C,2,FALSE) -> 0004-0003 | D53: 52427 | E53: TA-25-941590 | F53: 41473 | G53: ORDEN DE CAMBIO | H53: NARIÑO | I53: MAGUI | J53: PTM MAGUI DROGAS LA PLAYITA | K53: REDEBAN | L53: FO-25-1345220 | M53: 45875.721 | N53: 45885.362 | P53: CIERRE | Q53: CIERRE | R53: AGREGADOR | S53: COMCARD - PTM | T53: ILOCALIZADO | U53: CB CERRADO - DESOCUPADO | V53: 0 14/08/2025 SE REALIZA DESPLAZAMIENTO PERO COMO ES ZONA REMOTA Y DE DIFÍCIL ACCESO NO SE LLEGA A SITIO... 16-08-2025 SE REALIZA BÚSQUEDA DEL COMERCIO PERO NO SE LOGRA ENCONTRAR, SE LLAMA AL CLIENTE Y NO SE OBTIENE RESPUESTA EN EL NÚMERO SUMINISTRADO, SE AVERIGUA CON GENTE DEL LUGAR Y INFORMAN QUE SE ENCUENTRA DE VIAJE POR LO CUAL NO SE PUEDE HACER EL CIERRE... | W53: VISITA_TÉCNICA | X53: 0 | Y53: TIPO IV ESPECIAL | Z53: =VLOOKUP(D53,TIPOLOGIAS!A:F,5,0) -> FLUVIAL | AA53: PAZ MARTINEZ RICHARD HUMBERTO | AB53: 1 | AC53: =IF(AND(W53="SOPORTE_TELEFÓNICO",OR(U53="SIN CONTACTO CON EL CB",U53="NÚMEROS DE CONTACTO ERRADOS")),0,IF(W53="SOPORTE_TELEFÓNICO",'BASE DE LIQUIDACION 2025'!$B$9,IF(Y53="TIPO I",'BASE DE LIQUIDACION 2025'!$C$3,IF(Y53="TIPO II",'BASE DE LIQUIDACION 2025'!$C$4,IF(Y53="TIPO III",'BASE DE LIQUIDACION 2025'!$C$5,'BASE DE LIQUIDACION 2025'!$C$6))))) -> 464809.37 | AD53: =IF(W53="SOPORTE_TELEFÓNICO",AC53,CIERRES!AB53*CIERRES!AC53) -> 464809.37
A54: BUCARAMANGA | B54: =VLOOKUP(A54,'CENTRO DE COSTOS'!A:D,4,FALSE) -> MIGUEL JULIÁN HERNÁNDEZ GUARÍN | C54: =VLOOKUP(A54,'CENTRO DE COSTOS'!A:C,2,FALSE) -> 0004-0008 | D54: 68307 | E54: TA-25-973867 | F54: 63099 | G54: ORDEN DE CAMBIO | H54: SANTANDER | I54: GIRON | J54: BARRIO SAN ANTONIO DE CARRIZAL | K54: REDEBAN | L54: FO-25-1375874 | M54: 45883.479 | N54: 45885.394 | P54: CIERRE | Q54: CIERRE | R54: CB UNO A UNO | S54: CB UNO A UNO | T54: NO_EXITOSO | U54: CB NO ENTREGA EQUIPO | V54: 0 14/08/2025 EN COMUNICACIÓN CON LA SEÑORA KELLY BARRETO AL MOVIL 3123865977, INDICA QUE EL BANCO NO LE HAN INFORMADO DE ESTO Y ELLA NO PUEDE REALIZAR LA ENTREGA DE ESTOS EQUIPOS PORQUE NO LE HAN INFORMADO, INDICA QUE PRIMERO VA HABLAR CON EL BANCO Y NOS DARÁ UNA RESPUESTA SOBRE ESTA ORDEN. | 15/08/2025 EN COMUNICACIÓN CON LA SEÑORA KELLY BARRETO AL MOVIL 3123865977, INDICA QUE HASTA EL MOMENTO EL BANCO NO LE HA DADO RESPUESTA, INDICA QUE NOS COMUNIQUEMOS NUEVAMENTE EL DÍA DE MAÑANA PARA CONFIRMAR. 16-08-2025 EN COMUNICACIÓN CON LA SEÑORA KELLY BARRETO AL MOVIL 3123865977,INDICA QUE ELLA NO VA ENTREGAR LOS EQUIPOS AÚN, INDICA QUE YA SE COMUNICO CON LA ENTIDAD LA CUAL LE INFORMO QUE AÚN NO LE HAN DADO RESPUESTA DEBIDO A QUE NO HAY GESTOR EN SU LOCALIDAD Y YA GENERÓ UN RADICADO, CLIENTE SOLICITA CANCELAR VISITA, SE LE INFORMA QUE SE PROCEDERÁ A CANCELAR LA VISITA Y SI NO HAY UNA RESPUESTA POSITIVA POR PARTE DE LA ENTIDAD DEBERÁ LLAMAR Y SOLICITAR UNA ORDEN DE RECOGIDA DE EQUIPOS NUEVAMENTE. | W54: SOPORTE_TELEFÓNICO | X54: 0 | Y54: TIPO I | Z54: =VLOOKUP(D54,TIPOLOGIAS!A:F,5,0) -> TERRESTRE | AA54: SANTOS GONZALEZ JOHAN FABIAN | AB54: 0 | AC54: =IF(AND(W54="SOPORTE_TELEFÓNICO",OR(U54="SIN CONTACTO CON EL CB",U54="NÚMEROS DE CONTACTO ERRADOS")),0,IF(W54="SOPORTE_TELEFÓNICO",'BASE DE LIQUIDACION 2025'!$B$9,IF(Y54="TIPO I",'BASE DE LIQUIDACION 2025'!$C$3,IF(Y54="TIPO II",'BASE DE LIQUIDACION 2025'!$C$4,IF(Y54="TIPO III",'BASE DE LIQUIDACION 2025'!$C$5,'BASE DE LIQUIDACION 2025'!$C$6))))) -> 37904.612 | AD54: =IF(W54="SOPORTE_TELEFÓNICO",AC54,CIERRES!AB54*CIERRES!AC54) -> 37904.612
A55: CUCUTA | B55: =VLOOKUP(A55,'CENTRO DE COSTOS'!A:D,4,FALSE) -> MIGUEL JULIÁN HERNÁNDEZ GUARÍN | C55: =VLOOKUP(A55,'CENTRO DE COSTOS'!A:C,2,FALSE) -> 0004-0008 | D55: 54001 | E55: LC-CS-25-000012 | F55: 71022 | G55: ORDEN DE CAMBIO | H55: NORTE DE SANTANDER | I55: CUCUTA | J55: DISTRICOL CENTROPAG | K55: REDEBAN | L55: FO-25-1380519 | M55: 45884.483 | N55: 45885.413 | P55: CIERRE | Q55: RECUPERACION DE EQUIPOS | R55: AGREGADOR | S55: DISTRICOL | T55: ILOCALIZADO | U55: CB CERRADO - DESOCUPADO | V55: 0 0 16-08-2025 SE REALIZÓ VISITA A LA DIRECCIÓN ASIGNADA Y SE ENCUENTRA LOCAL CERRADO, SE REALIZARON LLAMADAS TELEFÓNICA AL NÚMERO ASIGNADO Y NO SE OBTIENE COMUNICACIÓN, SIN COMUNICACIÓN | W55: VISITA_TÉCNICA | X55: 0 | Y55: TIPO I | Z55: =VLOOKUP(D55,TIPOLOGIAS!A:F,5,0) -> TERRESTRE | AA55: MORA VEGA JEAMPIER | AB55: 1 | AC55: =IF(AND(W55="SOPORTE_TELEFÓNICO",OR(U55="SIN CONTACTO CON EL CB",U55="NÚMEROS DE CONTACTO ERRADOS")),0,IF(W55="SOPORTE_TELEFÓNICO",'BASE DE LIQUIDACION 2025'!$B$9,IF(Y55="TIPO I",'BASE DE LIQUIDACION 2025'!$C$3,IF(Y55="TIPO II",'BASE DE LIQUIDACION 2025'!$C$4,IF(Y55="TIPO III",'BASE DE LIQUIDACION 2025'!$C$5,'BASE DE LIQUIDACION 2025'!$C$6))))) -> 44559.564 | AD55: =IF(W55="SOPORTE_TELEFÓNICO",AC55,CIERRES!AB55*CIERRES!AC55) -> 44559.564
A56: VILLAVICENCIO | B56: =VLOOKUP(A56,'CENTRO DE COSTOS'!A:D,4,FALSE) -> KEVIN ALEXIS CORZO BUSTOS | C56: =VLOOKUP(A56,'CENTRO DE COSTOS'!A:C,2,FALSE) -> 0004-0007 | D56: 85440 | E56: LC-CS-25-000040 | F56: 34510 | G56: ORDEN DE CAMBIO | H56: CASANARE | I56: VILLANUEVA | J56: BARRIO FUNDADORES VILLANUEVA | K56: REDEBAN | L56: FO-25-1384541 | M56: 45884.528 | N56: 45885.465 | P56: CIERRE | Q56: CIERRE | R56: CB UNO A UNO | S56: CB UNO A UNO | T56: NO_EXITOSO | U56: CB NO ENTREGA EQUIPO | V56: 15/08/2025 SE INTENTA COMUNICACIÓN AL NÚMERO 3125533335 SUENA PERO NO HAY CONTACTO, SE INTENTARÁ NUEVAMENTE | 16/08/2025 SE CONTACTA AL SEÑOR YAMIT VARGAS E INFORMA QUE NO ESTÁ EN EL MUNICIPIO QUE SOLO PUEDE DE LUNES A VIERNES QUE NO SEA FESTIVO SE VALIDA CON JEFE DE ZONA | W56: SOPORTE_TELEFÓNICO | X56: 0 | Y56: TIPO III | Z56: =VLOOKUP(D56,TIPOLOGIAS!A:F,5,0) -> TERRESTRE | AA56: ROZO JIMENEZ EDGAR ARMANDO | AB56: 2 | AC56: =IF(AND(W56="SOPORTE_TELEFÓNICO",OR(U56="SIN CONTACTO CON EL CB",U56="NÚMEROS DE CONTACTO ERRADOS")),0,IF(W56="SOPORTE_TELEFÓNICO",'BASE DE LIQUIDACION 2025'!$B$9,IF(Y56="TIPO I",'BASE DE LIQUIDACION 2025'!$C$3,IF(Y56="TIPO II",'BASE DE LIQUIDACION 2025'!$C$4,IF(Y56="TIPO III",'BASE DE LIQUIDACION 2025'!$C$5,'BASE DE LIQUIDACION 2025'!$C$6))))) -> 37904.612 | AD56: =IF(W56="SOPORTE_TELEFÓNICO",AC56,CIERRES!AB56*CIERRES!AC56) -> 37904.612
A57: BOGOTA | B57: =VLOOKUP(A57,'CENTRO DE COSTOS'!A:D,4,FALSE) -> WILLIAM ASDRUBAL ROZO ROZO | C57: =VLOOKUP(A57,'CENTRO DE COSTOS'!A:C,2,FALSE) -> 0004-0004 | D57: 11001 | E57: LC-CS-25-000042 | F57: 77003 | G57: ORDEN DE CAMBIO | H57: CUNDINAMARCA | I57: BOGOTA | J57: BARRIO BOSA SAN BERNARDO BOGOTA 1 | K57: REDEBAN | L57: FO-25-1380912 | M57: 45884.528 | N57: 45885.48 | P57: CIERRE | Q57: CIERRE | R57: CB UNO A UNO | S57: CB UNO A UNO | T57: SOLICITUD_CANCELADA | U57: CANCELADO POR LA ENTIDAD | V57: 0 0 16-08-2025 SE REALIZA VISITA A LA DIRECCIÓN NOS ATIENDE LA SEÑORA SANDRA GELVES LA CUAL LOS INDICA QUE SE ENCUENTRA A LA ESPERA DE RESPUESTA DEL BANCO POR FACTURACIÓN POR ESO NO REALIZA ENTREGA DE LOS EQUIPOS - 22/08/2025 ENTIDAD SOLICITA CANCELAR CIERRE: SOLICITAMOS TU COLABORACIÓN PARA CAMBIAR EL ESTADO DE "NO EXITOSO" A "SOLICITUD CANCELADA" | W57: VISITA_TÉCNICA | X57: LM5ZZ628 | Y57: TIPO I | Z57: =VLOOKUP(D57,TIPOLOGIAS!A:F,5,0) -> TERRESTRE | AA57: HERNANDEZ NARANJO OSCAR EDUARDO | AB57: 1 | AC57: =IF(AND(W57="SOPORTE_TELEFÓNICO",OR(U57="SIN CONTACTO CON EL CB",U57="NÚMEROS DE CONTACTO ERRADOS")),0,IF(W57="SOPORTE_TELEFÓNICO",'BASE DE LIQUIDACION 2025'!$B$9,IF(Y57="TIPO I",'BASE DE LIQUIDACION 2025'!$C$3,IF(Y57="TIPO II",'BASE DE LIQUIDACION 2025'!$C$4,IF(Y57="TIPO III",'BASE DE LIQUIDACION 2025'!$C$5,'BASE DE LIQUIDACION 2025'!$C$6))))) -> 44559.564 | AD57: =IF(W57="SOPORTE_TELEFÓNICO",AC57,CIERRES!AB57*CIERRES!AC57) -> 44559.564
A58: CALI | B58: =VLOOKUP(A58,'CENTRO DE COSTOS'!A:D,4,FALSE) -> DIEGO FERNANDO HENAO CARDONA | C58: =VLOOKUP(A58,'CENTRO DE COSTOS'!A:C,2,FALSE) -> 0004-0003 | D58: 76001 | E58: LC-CS-25-000038 | F58: 67145 | G58: ORDEN DE CAMBIO | H58: VALLE DEL CAUCA | I58: CALI | J58: BARRIO ANDES CALI | K58: REDEBAN | L58: FO-25-1380864 | M58: 45884.528 | N58: 45885.522 | P58: CIERRE | Q58: CIERRE | R58: CB UNO A UNO | S58: CB UNO A UNO | T58: NO_EXITOSO | U58: CB NO ENTREGA EQUIPO | V58: 0 0 16-08-2025 EL CLIENTE EXPLICA A TENIDO INCONVENIENTES CON EL PAGO DE LAS COMISIONES MENSUALES, CLIENTE A ESTADO ENVIANDO PUNTUAL LA FACTURA MENSUAL PERO EL BANCO LE RECHAZA LA FACTURA PORQUE TIENE ALGÚN ERROR PERO CLIENTE LLAMO AL BANCO PARA QUE LE EXPLIQUEN DONDE ESTA EL ERROR NO LA SABEN ORIENTAR REVISA EL CORREO NO LE EXPLICAN CUAL ES EL ERROR DE LA FACTURA ENVIADA, LLEVA TRATANDO DE ENVIAR LA FACTURA VARIOS MESES, CLIENTE SIEMPRE HA ESTADO CON LA DISPOSICIÓN DE ENVIAR LA FACTURA HASTA 3 VECES AL MES LA ENVÍA PERO CUANDO LLAMA AL BANCO LE INFORMAN QUE NO PASA EL COBRO NO LE EXPLICAN EL MOTIVO ENVÍA EL CORREO LE DICEN EN LA LÍNEA QUE NO LES A LLEGADO Y REVISA QUE ESTÁ BIEN ENVIADO NO LE CORRIGEN EL ERROR, UNOS MESES SE LO PAGAN OTROS NO SE LOS PAGAN Y SE ENVÍAN DE LA MISMA FORMA EN LA LÍNEA DE ATENCIÓN NO SABE PORQUE PASA UN MES Y EL OTRO NO NO LO PAGAN, EXPLICA QUE ACUMULÓ TRES MESES POR ESE ERROR LA BLOQUEARON POR ELLO Y EL BANCO POR NO ESTAR OPERANDO EL CB POR MÁS DE QUINCE DÍAS, LE ENVÍO UN MENSAJE QUE SE IBA A CERRAR EL CB, CLIENTE ESTÁ INCONFORME CON EL SERVICIO PRESTADO POR LA LÍNEA DE ATENCIÓN NO LE RESOLVIERON LO DEL COBRO DE LAS COMISIONES SI ERA PUNTUAL CON EL ENVÍO MENSUAL DE LA FACTURA, EXPLICA CÓMO ELLA FUE ATENTA CON EL SERVICIO PRESTADO, LAS COMPENSACIONES PUNTALES ASÍ MISMO EXIGE QUE UN FUNCIONARIO DEL BANCO SE PRESENTE PARA QUE LE EXPLIQUEN EL MOTIVO DEL CIERRE O LAS CAUSALES QUE DIERON PARA QUE EL BANCO TOMARA LA DESICIÓN, CLIENTE DICE QUE ARBITRARIAMENTE LE CERRARON EL PUNTO SIN QUE ALGUIEN DEL BANCO SE PERSONALICE DEL CASO, CLIENTE VA ESPERAR QUE LE SOLUCIONEN O DONDE PUEDE HABLAR CON UN FUNCIONARIO O LA VISITEN Y QUE LE EXPLIQUEN LAS CAUSALES QUE EL BANCO TOMARA ESA DESICIÓN Y VA ESPERAR ALGUNA RESPUESTA PARA AUTORIZAR LA ENTREGA DE LOS EQUIPOS | W58: VISITA_TÉCNICA | X58: 0 | Y58: TIPO I | Z58: =VLOOKUP(D58,TIPOLOGIAS!A:F,5,0) -> TERRESTRE | AA58: HERRERA MONAR GEOVANNY | AB58: 1 | AC58: =IF(AND(W58="SOPORTE_TELEFÓNICO",OR(U58="SIN CONTACTO CON EL CB",U58="NÚMEROS DE CONTACTO ERRADOS")),0,IF(W58="SOPORTE_TELEFÓNICO",'BASE DE LIQUIDACION 2025'!$B$9,IF(Y58="TIPO I",'BASE DE LIQUIDACION 2025'!$C$3,IF(Y58="TIPO II",'BASE DE LIQUIDACION 2025'!$C$4,IF(Y58="TIPO III",'BASE DE LIQUIDACION 2025'!$C$5,'BASE DE LIQUIDACION 2025'!$C$6))))) -> 44559.564 | AD58: =IF(W58="SOPORTE_TELEFÓNICO",AC58,CIERRES!AB58*CIERRES!AC58) -> 44559.564
A59: MEDELLIN | B59: =VLOOKUP(A59,'CENTRO DE COSTOS'!A:D,4,FALSE) -> JUAN SEBASTIÁN RÍOS CASTRILLÓN | C59: =VLOOKUP(A59,'CENTRO DE COSTOS'!A:C,2,FALSE) -> 0004-0005 | D59: 5088 | E59: LC-CS-25-000021 | F59: 36435 | G59: ORDEN DE CAMBIO | H59: ANTIOQUIA | I59: BELLO | J59: BARRIO PEREZ BELLO 1 | K59: REDEBAN | L59: FO-25-1380875 | M59: 45884.528 | N59: 45886.6 | P59: CIERRE | Q59: CIERRE | R59: CB UNO A UNO | S59: CB UNO A UNO | T59: NO_EXITOSO | U59: CB NO ENTREGA EQUIPO | V59: 0 0 16-08-2025 USUARIO MANIFIESTA QUE SE QUEDÓ SIN TRABAJADORA, SE LE PASO HACER EL REPORTE A BANCOLOMBIA YA QUE NO ESTÁ EN EL PAÍS, PERO VA A SEGUIR OPERANDO EL CB. | W59: VISITA_TÉCNICA | X59: AA00D811 | Y59: TIPO I | Z59: =VLOOKUP(D59,TIPOLOGIAS!A:F,5,0) -> TERRESTRE | AA59: RAMIREZ TABARES JUAN DIEGO | AB59: 1 | AC59: =IF(AND(W59="SOPORTE_TELEFÓNICO",OR(U59="SIN CONTACTO CON EL CB",U59="NÚMEROS DE CONTACTO ERRADOS")),0,IF(W59="SOPORTE_TELEFÓNICO",'BASE DE LIQUIDACION 2025'!$B$9,IF(Y59="TIPO I",'BASE DE LIQUIDACION 2025'!$C$3,IF(Y59="TIPO II",'BASE DE LIQUIDACION 2025'!$C$4,IF(Y59="TIPO III",'BASE DE LIQUIDACION 2025'!$C$5,'BASE DE LIQUIDACION 2025'!$C$6))))) -> 44559.564 | AD59: =IF(W59="SOPORTE_TELEFÓNICO",AC59,CIERRES!AB59*CIERRES!AC59) -> 44559.564
A60: PASTO | B60: =VLOOKUP(A60,'CENTRO DE COSTOS'!A:D,4,FALSE) -> DIEGO FERNANDO HENAO CARDONA | C60: =VLOOKUP(A60,'CENTRO DE COSTOS'!A:C,2,FALSE) -> 0004-0003 | D60: 86749 | E60: TA-25-973871 | F60: 76649 | G60: ORDEN DE CAMBIO | H60: PUTUMAYO | I60: SIBUNDOY | J60: BARRIO COMERCIAL SIBUNDOY 1 | K60: REDEBAN | L60: FO-25-1375888 | M60: 45883.479 | N60: 45888.382 | P60: CIERRE | Q60: CIERRE | R60: CB UNO A UNO | S60: CB UNO A UNO | T60: NO_EXITOSO | U60: CB NO ENTREGA EQUIPO | V60: 0 0 19-08-2025 SE VISITA CB. CLIENTE INFORMA QUE ANTES DE DEVOLVER LOS EQUIPOS NECESITA DEJAR CLARO UN ASUNTO CON EL BANCO Y CON EL ASESOR DE BANCOLOMBIA PERO QUE NO HA PODIDO REALIZAR COMUNICACIÓN CON ELLOS. CLIENTE NO FIRMA | W60: VISITA_TÉCNICA | X60: LA2ZZ432 | Y60: TIPO III | Z60: =VLOOKUP(D60,TIPOLOGIAS!A:F,5,0) -> TERRESTRE | AA60: CASTILLO HERRERA ALEX RICARDO | AB60: 1 | AC60: =IF(AND(W60="SOPORTE_TELEFÓNICO",OR(U60="SIN CONTACTO CON EL CB",U60="NÚMEROS DE CONTACTO ERRADOS")),0,IF(W60="SOPORTE_TELEFÓNICO",'BASE DE LIQUIDACION 2025'!$B$9,IF(Y60="TIPO I",'BASE DE LIQUIDACION 2025'!$C$3,IF(Y60="TIPO II",'BASE DE LIQUIDACION 2025'!$C$4,IF(Y60="TIPO III",'BASE DE LIQUIDACION 2025'!$C$5,'BASE DE LIQUIDACION 2025'!$C$6))))) -> 222904.07 | AD60: =IF(W60="SOPORTE_TELEFÓNICO",AC60,CIERRES!AB60*CIERRES!AC60) -> 222904.07
A61: PASTO | B61: =VLOOKUP(A61,'CENTRO DE COSTOS'!A:D,4,FALSE) -> DIEGO FERNANDO HENAO CARDONA | C61: =VLOOKUP(A61,'CENTRO DE COSTOS'!A:C,2,FALSE) -> 0004-0003 | D61: 52051 | E61: LC-CS-25-000033 | F61: 36250 | G61: ORDEN DE CAMBIO | H61: NARIÑO | I61: ARBOLEDA | J61: BARRIO CENTRO ARBOLEDA | K61: REDEBAN | L61: FO-25-1380834 | M61: 45884.528 | N61: 45888.506 | P61: CIERRE | Q61: CIERRE | R61: CB UNO A UNO | S61: CB UNO A UNO | T61: ILOCALIZADO | U61: CB CERRADO - DESOCUPADO | V61: 0 0 19-08-2025 SE VISITA CB. SE ENCUENTRA LOCAL CERRADO, NO SE PUEDE ESTABLECER COMUNICACIÓN TELEFÓNICA CON EL CLIENTE, TELÉFONO APAGADO, VECINOS NO DAN INFORMACIÓN DEL SEÑOR JESÚS | W61: VISITA_TÉCNICA | X61: A301Z286 | Y61: TIPO II | Z61: =VLOOKUP(D61,TIPOLOGIAS!A:F,5,0) -> TERRESTRE | AA61: CASTILLO HERRERA ALEX RICARDO | AB61: 1 | AC61: =IF(AND(W61="SOPORTE_TELEFÓNICO",OR(U61="SIN CONTACTO CON EL CB",U61="NÚMEROS DE CONTACTO ERRADOS")),0,IF(W61="SOPORTE_TELEFÓNICO",'BASE DE LIQUIDACION 2025'!$B$9,IF(Y61="TIPO I",'BASE DE LIQUIDACION 2025'!$C$3,IF(Y61="TIPO II",'BASE DE LIQUIDACION 2025'!$C$4,IF(Y61="TIPO III",'BASE DE LIQUIDACION 2025'!$C$5,'BASE DE LIQUIDACION 2025'!$C$6))))) -> 134410.88 | AD61: =IF(W61="SOPORTE_TELEFÓNICO",AC61,CIERRES!AB61*CIERRES!AC61) -> 134410.88
A62: BUCARAMANGA | B62: =VLOOKUP(A62,'CENTRO DE COSTOS'!A:D,4,FALSE) -> MIGUEL JULIÁN HERNÁNDEZ GUARÍN | C62: =VLOOKUP(A62,'CENTRO DE COSTOS'!A:C,2,FALSE) -> 0004-0008 | D62: 68001 | E62: LC-CS-25-000061 | F62: 54639 | G62: ORDEN DE CAMBIO | H62: SANTANDER | I62: BUCARAMANGA | J62: PTM BUCARAMANGA PAPELERIA PAPE | K62: REDEBAN | L62: FO-25-1396999 | M62: 45888.595 | N62: 45888.703 | P62: CIERRE | Q62: CIERRE | R62: AGREGADOR | S62: COMCARD - PTM | T62: ILOCALIZADO | U62: CB CERRADO - DESOCUPADO | V62: 19/08/2025 EN COMUNICACIÓN CON LA SRA PAULA MARCELA RODRIGUEZ CRUZ AL NÚMERO 3154913400 NOS INDICA QUE LLEVA DOS MESES MAL DE SALLUD, POR LO CUAL NO HA PODIDO TRABAJAR EN EL CB, REFIERE NO TENER LA FORMA ACTUALMENTE DE ENTREGAR LOS EQUIPOS DEBIDO A SU ESTADO DE SALUD | 19/08/2025 SE HACE PRESENCIA EN COMERCIO SE OBSERVA CERRADO SE TRATA DE CONTACTAR AL CLIENTE AL NÚMERO 3186488209 NO SE OBTIENE RESPUESTA SE VALIDE QUE EL NÚMERO DE CONTACTO TENGA WHATSAPP Y SE LE DEJA EL MENSAJE AL CLIENTE SIN RESPUESTA SE PROCEDE A REPROGRAMAR ORDEN | W62: VISITA_TÉCNICA | X62: XP8ZZ968-XP9ZZ443 | Y62: TIPO I | Z62: =VLOOKUP(D62,TIPOLOGIAS!A:F,5,0) -> TERRESTRE | AA62: ORTEBARRERAGA MARLON STWAR | AB62: 2 | AC62: =IF(AND(W62="SOPORTE_TELEFÓNICO",OR(U62="SIN CONTACTO CON EL CB",U62="NÚMEROS DE CONTACTO ERRADOS")),0,IF(W62="SOPORTE_TELEFÓNICO",'BASE DE LIQUIDACION 2025'!$B$9,IF(Y62="TIPO I",'BASE DE LIQUIDACION 2025'!$C$3,IF(Y62="TIPO II",'BASE DE LIQUIDACION 2025'!$C$4,IF(Y62="TIPO III",'BASE DE LIQUIDACION 2025'!$C$5,'BASE DE LIQUIDACION 2025'!$C$6))))) -> 44559.564 | AD62: =IF(W62="SOPORTE_TELEFÓNICO",AC62,CIERRES!AB62*CIERRES!AC62) -> 89119.128
A63: CALI | B63: =VLOOKUP(A63,'CENTRO DE COSTOS'!A:D,4,FALSE) -> DIEGO FERNANDO HENAO CARDONA | C63: =VLOOKUP(A63,'CENTRO DE COSTOS'!A:C,2,FALSE) -> 0004-0003 | D63: 19548 | E63: TA-25-973860 | F63: 54135 | G63: ORDEN DE CAMBIO | H63: CAUCA | I63: PIENDAMO | J63: BARRIO FATIMA PIENDAMO | K63: REDEBAN | L63: FO-25-1375861 | M63: 45883.479 | N63: 45889.321 | P63: CIERRE | Q63: CIERRE | R63: CB UNO A UNO | S63: CB UNO A UNO | T63: ILOCALIZADO | U63: CB CERRADO - DESOCUPADO | V63: 0 0 19-08-2025 SE LLEGA A LA DIRECCION SE ENCUENTRA CERRADO COMERCIO | W63: VISITA_TÉCNICA | X63: 0 | Y63: TIPO III | Z63: =VLOOKUP(D63,TIPOLOGIAS!A:F,5,0) -> TERRESTRE | AA63: GIMBUEL LASSO LUIS GERMAN | AB63: 1 | AC63: =IF(AND(W63="SOPORTE_TELEFÓNICO",OR(U63="SIN CONTACTO CON EL CB",U63="NÚMEROS DE CONTACTO ERRADOS")),0,IF(W63="SOPORTE_TELEFÓNICO",'BASE DE LIQUIDACION 2025'!$B$9,IF(Y63="TIPO I",'BASE DE LIQUIDACION 2025'!$C$3,IF(Y63="TIPO II",'BASE DE LIQUIDACION 2025'!$C$4,IF(Y63="TIPO III",'BASE DE LIQUIDACION 2025'!$C$5,'BASE DE LIQUIDACION 2025'!$C$6))))) -> 222904.07 | AD63: =IF(W63="SOPORTE_TELEFÓNICO",AC63,CIERRES!AB63*CIERRES!AC63) -> 222904.07
A64: APARTADO | B64: =VLOOKUP(A64,'CENTRO DE COSTOS'!A:D,4,FALSE) -> JUAN SEBASTIÁN RÍOS CASTRILLÓN | C64: =VLOOKUP(A64,'CENTRO DE COSTOS'!A:C,2,FALSE) -> 0004-0005 | D64: 27810 | E64: LC-CS-25-000043 | F64: 38240 | G64: ORDEN DE CAMBIO | H64: CHOCO | I64: UNION PANAMERICANA | J64: BARRIO LOURDES UNION PANAMERICANA | K64: REDEBAN | L64: FO-25-1380827 | M64: 45884.528 | N64: 45889.44 | P64: CIERRE | Q64: CIERRE | R64: CB UNO A UNO | S64: CB UNO A UNO | T64: ILOCALIZADO | U64: CB CERRADO - DESOCUPADO | V64: 15/08/2025 SE INTENTA COMUNICACIÓN AL NÚMERO 3102233888 SUENA PERO NO HAY CONTACTO, SE INTENTARÁ NUEVAMENTE | 19/08/2025 SE INTENTA COMUNICACIÓN AL NÚMERO 3102233888 SUENA PERO NO HAY CONTACTO. SE INTENTARÁ NUEVAMENTE | 19/08/2025 SE INTENTA COMUNICACIÓN AL NÚMERO 3102233888 SUENA PERO NO HAY CONTACTO. | 20/08/2025 SE LLEGA A SITIO, PERSONAL QUE ATIENDE EL COMERCIO COMENTA QUE NO TIENE CONOCIMIENTO DE DATAFONOS Y EL EL DUEÑO NO SE ENCUENTRA Y NO SE ENTRA AUTOTOZADA A FIRMAR DOCUMENTOS SIN PREVIA AUTORIZACIÓN | W64: VISITA_TÉCNICA | X64: NO SUMINISTRA | Y64: TIPO IV | Z64: =VLOOKUP(D64,TIPOLOGIAS!A:F,5,0) -> TERRESTRE | AA64: ROBLEDO DIAZ ANDRES FELIPE | AB64: 1 | AC64: =IF(AND(W64="SOPORTE_TELEFÓNICO",OR(U64="SIN CONTACTO CON EL CB",U64="NÚMEROS DE CONTACTO ERRADOS")),0,IF(W64="SOPORTE_TELEFÓNICO",'BASE DE LIQUIDACION 2025'!$B$9,IF(Y64="TIPO I",'BASE DE LIQUIDACION 2025'!$C$3,IF(Y64="TIPO II",'BASE DE LIQUIDACION 2025'!$C$4,IF(Y64="TIPO III",'BASE DE LIQUIDACION 2025'!$C$5,'BASE DE LIQUIDACION 2025'!$C$6))))) -> 464809.37 | AD64: =IF(W64="SOPORTE_TELEFÓNICO",AC64,CIERRES!AB64*CIERRES!AC64) -> 464809.37
A65: APARTADO | B65: =VLOOKUP(A65,'CENTRO DE COSTOS'!A:D,4,FALSE) -> JUAN SEBASTIÁN RÍOS CASTRILLÓN | C65: =VLOOKUP(A65,'CENTRO DE COSTOS'!A:C,2,FALSE) -> 0004-0005 | D65: 27077 | E65: TA-25-962684 | F65: 50248 | G65: ORDEN DE CAMBIO | H65: CHOCO | I65: BAJO BAUDO | J65: BARRIO TRINIDAD Y PLAYITA BAJO BAUDO | K65: REDEBAN | L65: FO-25-1363671 | M65: 45881.333 | N65: 45889.466 | P65: CIERRE | Q65: RECUPERACION DE EQUIPOS | R65: CB UNO A UNO | S65: CB UNO A UNO | T65: NO_EXITOSO | U65: CB NO ENTREGA EQUIPO | V65: 0 14/08/2025 SE CONTACTA CON EL CLIENTE Y COMENTA Q UE NO SE ENCUENTRA CON LOS EQUIPO YA QUE ESTA EN UNA CITA MÉDICA CON LA PAREJA QUEDA EN LLAMAR AL TÉCNICO CUANDO TENGA LOS EQUIPOS A DISPOSICIÓN | 15/08/2025 SE CONTACTA CON EL CLIENTE Y COMENTA QUE EN EL MOMENTO NO SE ENCUENTRA OCUPADO QUEDA EN LLAMAR AL TÉCNICO CUANDO TENGA LOS EQUIPOS A DISPOSICIÓN 20-08-2025 SE CONTACTA EN REPETIDAS OCASIONES CON EL CLIENTE PARA ORGANIZAR LA ENTREGA DE LOS EQUIPOS NO FUE POSIBLE | W65: VISITA_TÉCNICA | X65: NO SUMINISTRA | Y65: TIPO IV ESPECIAL | Z65: =VLOOKUP(D65,TIPOLOGIAS!A:F,5,0) -> AEREO | AA65: ROBLEDO DIAZ ANDRES FELIPE | AB65: 1 | AC65: =IF(AND(W65="SOPORTE_TELEFÓNICO",OR(U65="SIN CONTACTO CON EL CB",U65="NÚMEROS DE CONTACTO ERRADOS")),0,IF(W65="SOPORTE_TELEFÓNICO",'BASE DE LIQUIDACION 2025'!$B$9,IF(Y65="TIPO I",'BASE DE LIQUIDACION 2025'!$C$3,IF(Y65="TIPO II",'BASE DE LIQUIDACION 2025'!$C$4,IF(Y65="TIPO III",'BASE DE LIQUIDACION 2025'!$C$5,'BASE DE LIQUIDACION 2025'!$C$6))))) -> 464809.37 | AD65: =IF(W65="SOPORTE_TELEFÓNICO",AC65,CIERRES!AB65*CIERRES!AC65) -> 464809.37
A66: MEDELLIN | B66: =VLOOKUP(A66,'CENTRO DE COSTOS'!A:D,4,FALSE) -> JUAN SEBASTIÁN RÍOS CASTRILLÓN | C66: =VLOOKUP(A66,'CENTRO DE COSTOS'!A:C,2,FALSE) -> 0004-0005 | D66: 5088 | E66: LC-CS-25-000022 | F66: 59809 | G66: ORDEN DE CAMBIO | H66: ANTIOQUIA | I66: BELLO | J66: BARRIO BELLO BELLO 5 | K66: REDEBAN | L66: FO-25-1380850 | M66: 45884.528 | N66: 45890.379 | P66: CIERRE | Q66: CIERRE | R66: CB UNO A UNO | S66: CB UNO A UNO | T66: ILOCALIZADO | U66: CB CERRADO - DESOCUPADO | V66: 15/08/2025 SE INTENTA COMUNICACIÓN AL NÚMERO 3246127130 SE ENCUENTRA APAGADO. SE INTENTARÁ NUEVAMENTE | 19/08/2025 SE INTENTA COMUNICACIÓN AL NÚMERO 3246127130 SE ENCUENTRA APAGADO. SE INTENTARÁ NUEVAMENTE | 19/08/2025 SE INTENTA COMUNICACIÓN AL NÚMERO 3246127130 SE ENCUENTRA APAGADO. | 20/08/2025 SE LLEGA AL SITIO Y EL COMERCIO YA NO EXISTE SE INTENTÓ COMUNICARSE CON EL USUARIO Y NO FUE POSIBLE. | W66: VISITA_TÉCNICA | X66: 0 | Y66: TIPO I | Z66: =VLOOKUP(D66,TIPOLOGIAS!A:F,5,0) -> TERRESTRE | AA66: ZAPATA LOPEZ EDWARD ASDRUBAL | AB66: 1 | AC66: =IF(AND(W66="SOPORTE_TELEFÓNICO",OR(U66="SIN CONTACTO CON EL CB",U66="NÚMEROS DE CONTACTO ERRADOS")),0,IF(W66="SOPORTE_TELEFÓNICO",'BASE DE LIQUIDACION 2025'!$B$9,IF(Y66="TIPO I",'BASE DE LIQUIDACION 2025'!$C$3,IF(Y66="TIPO II",'BASE DE LIQUIDACION 2025'!$C$4,IF(Y66="TIPO III",'BASE DE LIQUIDACION 2025'!$C$5,'BASE DE LIQUIDACION 2025'!$C$6))))) -> 44559.564 | AD66: =IF(W66="SOPORTE_TELEFÓNICO",AC66,CIERRES!AB66*CIERRES!AC66) -> 44559.564
A67: VALLEDUPAR | B67: =VLOOKUP(A67,'CENTRO DE COSTOS'!A:D,4,FALSE) -> JOSE MAURICIO HERNANDEZ ROJAS | C67: =VLOOKUP(A67,'CENTRO DE COSTOS'!A:C,2,FALSE) -> 0004-0001 | D67: 20001 | E67: LC-CS-25-000059 | F67: 75703 | G67: ORDEN DE CAMBIO | H67: CESAR | I67: VALLEDUPAR | J67: DISTRICOL DM SERVICIOS Y SUMIN | K67: REDEBAN | L67: FO-25-1392552 | M67: 45888.595 | N67: 45890.404 | P67: CIERRE | Q67: CIERRE | R67: AGREGADOR | S67: DISTRICOL | T67: ILOCALIZADO | U67: CB CERRADO - DESOCUPADO | V67: 19/08/2025 SE INTENTA COMUNICACIÓN AL NÚMERO 3226172324, SE ENCUENTRA APAGADO. SE INTENTARÁ NUEVAMENTE | 20/08/2025 SE INTENTA COMUNICACIÓN AL NÚMERO 3226172324, SE ENCUENTRA APAGADO. SE INTENTARÁ NUEVAMENTE | 20/08/2025 SE INTENTA COMUNICACIÓN AL NÚMERO 3226172324 SE ENCUENTRA APAGADO, SE INTENTA COMUNICACIÓN VIA WHATSAPP; NO LLEGAN LOS MENSAJES | 20/08/2025 BUENAS TARDES SE VISITA CB PERO SE ENCUENTRA CORRESPONSAL CERRADO, Y EL TELÉFONO DE CONTACTO SE VA A BUZÓN, SE GESTIÓNA COMO VISITA FALLIDA | W67: VISITA_TÉCNICA | X67: 1000R521 | Y67: TIPO I | Z67: =VLOOKUP(D67,TIPOLOGIAS!A:F,5,0) -> TERRESTRE | AA67: BENITEZ CARVAJAL ALVARO JAVIER | AB67: 1 | AC67: =IF(AND(W67="SOPORTE_TELEFÓNICO",OR(U67="SIN CONTACTO CON EL CB",U67="NÚMEROS DE CONTACTO ERRADOS")),0,IF(W67="SOPORTE_TELEFÓNICO",'BASE DE LIQUIDACION 2025'!$B$9,IF(Y67="TIPO I",'BASE DE LIQUIDACION 2025'!$C$3,IF(Y67="TIPO II",'BASE DE LIQUIDACION 2025'!$C$4,IF(Y67="TIPO III",'BASE DE LIQUIDACION 2025'!$C$5,'BASE DE LIQUIDACION 2025'!$C$6))))) -> 44559.564 | AD67: =IF(W67="SOPORTE_TELEFÓNICO",AC67,CIERRES!AB67*CIERRES!AC67) -> 44559.564
A68: PASTO | B68: =VLOOKUP(A68,'CENTRO DE COSTOS'!A:D,4,FALSE) -> DIEGO FERNANDO HENAO CARDONA | C68: =VLOOKUP(A68,'CENTRO DE COSTOS'!A:C,2,FALSE) -> 0004-0003 | D68: 52835 | E68: LC-CS-25-000089 | F68: 52418 | G68: ORDEN DE CAMBIO | H68: NARIÑO | I68: SAN ANDRES DE TUMACO | J68: BARRIO TUMACO SAN ANDRES DE TU | K68: REDEBAN | L68: FO-25-1397913 | M68: 45889.583 | N68: 45890.583 | P68: CIERRE | Q68: CIERRE | R68: CB UNO A UNO | S68: CB UNO A UNO | T68: NO_EXITOSO | U68: CB NO ENTREGA EQUIPO | V68: 20/08/2025 EN COMUNICACIÓN CON EL NÚMERO 3214547858 NOS INDICAN QUE EL CB SE ENCUENTRA EN CALI EN LA DIRECCIÓN CR 3 NORTE # 71 C 20 | 21/08/2025 SE VISITA EL COMERCIO EN LA DIRECCIÓN INDICADA POR EL CLIENTE EN CALI, SE VÁLIDA QUE NO TIENE EQUIPOS DE REDEBAN DEL PUNTO 52418 BARRIO TUMACO SAN ANDRÉS DE TUMACO PORQUE LA SEÑORA ANGIE MARIELA FIGUEROA GARCÍA Y EL SEÑOR DAGOBERTO FIGUEROA NO ES LA REPRESENTANTE LEGAL DE ESE PUNTO, INFORMA QUE LOS EQUIPOS QUE VA ENTREGAR ES DEL PUNTO 57562 BARRIO PASO DEL COMERCIO CALI | W68: VISITA_TÉCNICA | X68: NONE | Y68: TIPO IV | Z68: =VLOOKUP(D68,TIPOLOGIAS!A:F,5,0) -> TERRESTRE | AA68: HERRERA MONAR GEOVANNY | AB68: 1 | AC68: =IF(AND(W68="SOPORTE_TELEFÓNICO",OR(U68="SIN CONTACTO CON EL CB",U68="NÚMEROS DE CONTACTO ERRADOS")),0,IF(W68="SOPORTE_TELEFÓNICO",'BASE DE LIQUIDACION 2025'!$B$9,IF(Y68="TIPO I",'BASE DE LIQUIDACION 2025'!$C$3,IF(Y68="TIPO II",'BASE DE LIQUIDACION 2025'!$C$4,IF(Y68="TIPO III",'BASE DE LIQUIDACION 2025'!$C$5,'BASE DE LIQUIDACION 2025'!$C$6))))) -> 464809.37 | AD68: =IF(W68="SOPORTE_TELEFÓNICO",AC68,CIERRES!AB68*CIERRES!AC68) -> 464809.37
A69: BOGOTA | B69: =VLOOKUP(A69,'CENTRO DE COSTOS'!A:D,4,FALSE) -> WILLIAM ASDRUBAL ROZO ROZO | C69: =VLOOKUP(A69,'CENTRO DE COSTOS'!A:C,2,FALSE) -> 0004-0004 | D69: 25740 | E69: LC-CS-25-000062 | F69: 48232 | G69: ORDEN DE CAMBIO | H69: CUNDINAMARCA | I69: SIBATE | J69: DISTRICOL TABEEL | K69: REDEBAN | L69: FO-25-1392558 | M69: 45888.595 | N69: 45890.601 | P69: CIERRE | Q69: CIERRE | R69: AGREGADOR | S69: DISTRICOL | T69: ILOCALIZADO | U69: CB CERRADO - DESOCUPADO | V69: 19/08/2025 EN COMUNICACIÓN CON EL SR CRISTIAN TORRES AL NÚMERO 3195812689 NOS CONFIRMA LA SOLICITUD, DATOS CORRECTOS. SE ESCALA PARA VISITA | 21/08/2025 DURANTE LA VISITA TECNICA PARA REALIZAR CIERRE DE CORRESPONSAL BANCARIO AL LLEGAR SE EVIDENCIA QUE COMERCIO NO EXISTE EN DIRECCIÓN SE PREGUNTA EN COMERCIO ACTUAL EL CUAL INDICA QUE LA SRA SE PASO A LA DIRECCIÓN KR 8 10 71 EN DICHA DIRECCIÓN SE ENCUENTRA CERRADO EL CB SE LLAMA AL NUMERO DE CELULAR 3195812689 EN REPETIDAS OCASIONES SIN TENER RESPUESTA SE INFORMA A COORDINADOR Y SE PROCEDE AL CIERRE DE LA ACTIVIDAD | W69: VISITA_TÉCNICA | X69: 0 | Y69: TIPO II | Z69: =VLOOKUP(D69,TIPOLOGIAS!A:F,5,0) -> TERRESTRE | AA69: GALEANO SORIANO JUAN DAVID | AB69: 1 | AC69: =IF(AND(W69="SOPORTE_TELEFÓNICO",OR(U69="SIN CONTACTO CON EL CB",U69="NÚMEROS DE CONTACTO ERRADOS")),0,IF(W69="SOPORTE_TELEFÓNICO",'BASE DE LIQUIDACION 2025'!$B$9,IF(Y69="TIPO I",'BASE DE LIQUIDACION 2025'!$C$3,IF(Y69="TIPO II",'BASE DE LIQUIDACION 2025'!$C$4,IF(Y69="TIPO III",'BASE DE LIQUIDACION 2025'!$C$5,'BASE DE LIQUIDACION 2025'!$C$6))))) -> 134410.88 | AD69: =IF(W69="SOPORTE_TELEFÓNICO",AC69,CIERRES!AB69*CIERRES!AC69) -> 134410.88
A70: BUCARAMANGA | B70: =VLOOKUP(A70,'CENTRO DE COSTOS'!A:D,4,FALSE) -> MIGUEL JULIÁN HERNÁNDEZ GUARÍN | C70: =VLOOKUP(A70,'CENTRO DE COSTOS'!A:C,2,FALSE) -> 0004-0008 | D70: 68001 | E70: LC-CS-25-000072 | F70: 31325 | G70: ORDEN DE CAMBIO | H70: SANTANDER | I70: BUCARAMANGA | J70: BARRIO CIUDAD BOLIVAR | K70: REDEBAN | L70: FO-25-1393708 | M70: 45888.651 | N70: 45891.328 | P70: CIERRE | Q70: CIERRE | R70: CB UNO A UNO | S70: CB UNO A UNO | T70: ILOCALIZADO | U70: CB CERRADO - DESOCUPADO | V70: 19/08/2025 SE INTENTA COMUNICACIÓN AL NÚMERO 3184913235 SE ENCUENTRA APAGADO. SE INTENTARÁ NUEVAMENTE | 20/08/2025 SE INTENTA COMUNICACIÓN AL NÚMERO 3184913235 SE ENCUENTRA APAGADO. SE INTENTARÁ NUEVAMENTE | 21/08/2025 SE VISITA COMERCIO SE VERIFICA QUE SE ENCUENTRA CERRADO SE LLAMA EN REPETIDAS OCASIONES AL NUMERO 6440577 SIN RESPUESTA ALGUNA ,SE PREGUNTA A SUS ALREDEDORES Y NO DAN RAZON VISITA FALLIDA | W70: VISITA_TÉCNICA | X70: 11115906 | Y70: TIPO I | Z70: =VLOOKUP(D70,TIPOLOGIAS!A:F,5,0) -> TERRESTRE | AA70: BARAJAS BERMUDEZ YAHIR MAURICIO | AB70: 1 | AC70: =IF(AND(W70="SOPORTE_TELEFÓNICO",OR(U70="SIN CONTACTO CON EL CB",U70="NÚMEROS DE CONTACTO ERRADOS")),0,IF(W70="SOPORTE_TELEFÓNICO",'BASE DE LIQUIDACION 2025'!$B$9,IF(Y70="TIPO I",'BASE DE LIQUIDACION 2025'!$C$3,IF(Y70="TIPO II",'BASE DE LIQUIDACION 2025'!$C$4,IF(Y70="TIPO III",'BASE DE LIQUIDACION 2025'!$C$5,'BASE DE LIQUIDACION 2025'!$C$6))))) -> 44559.564 | AD70: =IF(W70="SOPORTE_TELEFÓNICO",AC70,CIERRES!AB70*CIERRES!AC70) -> 44559.564
A71: PASTO | B71: =VLOOKUP(A71,'CENTRO DE COSTOS'!A:D,4,FALSE) -> DIEGO FERNANDO HENAO CARDONA | C71: =VLOOKUP(A71,'CENTRO DE COSTOS'!A:C,2,FALSE) -> 0004-0003 | D71: 86569 | E71: LC-CS-25-000044 | F71: 55741 | G71: ORDEN DE CAMBIO | H71: PUTUMAYO | I71: PUERTO CAICEDO | J71: BARRIO SANTA BARBARA PUERTO CA | K71: REDEBAN | L71: FO-25-1380867 | M71: 45884.528 | N71: 45891.329 | P71: CIERRE | Q71: RECUPERACION DE EQUIPOS | R71: CB UNO A UNO | S71: CB UNO A UNO | T71: NO_EXITOSO | U71: CB NO ENTREGA EQUIPO | V71: 15/08/2025 EN COMUNICACIÓN CON LA SEÑORA DIANA YOLANDA LOMBANA AL NÚMERO 3188632650 SE CONFIRMA LA SOLICITUD, DATOS CORRECTOS, SE ESCALA PARA VISITA, LLAMAR ANTES DE DESPLAZARSE | 21/08/2025 SE LLEGA A MUNICIPIO PERO LA ENCARGADA DEL CB NO SE ENCUENTRA. SE REALIZA COMUNICACIÓN TELEFÓNICA E INFORMA QUE DEVOLVERA PERSONALMENTE LOS EQUIPOS A BANCOLOMBIA YA QUE SE LE DESCONTÓ UN DINERO POR ELLOS, Y QUIERE SABER CUNADO LE REINTEGRARAN DICHO DINERO. | W71: VISITA_TÉCNICA | X71: IIHZZ021 | Y71: TIPO IV | Z71: =VLOOKUP(D71,TIPOLOGIAS!A:F,5,0) -> TERRESTRE | AA71: GUERRERO RAMIREZ OSCAR DARIO | AB71: 1 | AC71: =IF(AND(W71="SOPORTE_TELEFÓNICO",OR(U71="SIN CONTACTO CON EL CB",U71="NÚMEROS DE CONTACTO ERRADOS")),0,IF(W71="SOPORTE_TELEFÓNICO",'BASE DE LIQUIDACION 2025'!$B$9,IF(Y71="TIPO I",'BASE DE LIQUIDACION 2025'!$C$3,IF(Y71="TIPO II",'BASE DE LIQUIDACION 2025'!$C$4,IF(Y71="TIPO III",'BASE DE LIQUIDACION 2025'!$C$5,'BASE DE LIQUIDACION 2025'!$C$6))))) -> 464809.37 | AD71: =IF(W71="SOPORTE_TELEFÓNICO",AC71,CIERRES!AB71*CIERRES!AC71) -> 464809.37
A72: CUCUTA | B72: =VLOOKUP(A72,'CENTRO DE COSTOS'!A:D,4,FALSE) -> MIGUEL JULIÁN HERNÁNDEZ GUARÍN | C72: =VLOOKUP(A72,'CENTRO DE COSTOS'!A:C,2,FALSE) -> 0004-0008 | D72: 54810 | E72: LC-CS-25-000056 | F72: 76045 | G72: ORDEN DE CAMBIO | H72: NORTE DE SANTANDER | I72: TIBU | J72: PTM TIBU J STORE | K72: REDEBAN | L72: FO-25-1392543 | M72: 45888.595 | N72: 45891.383 | P72: CIERRE | Q72: CIERRE | R72: AGREGADOR | S72: COMCARD - PTM | T72: NO_EXITOSO | U72: CB NO ENTREGA EQUIPO | V72: 19/08/2025 EN COMUNICACIÓN CON EL SR JAIRO ALONSO ROJAS CRIOLLO AL NÚMERO 3108624352 NOS COFIRMA LA SOLICITUD, DATOS CORRECTOS, SE ESCALA PARA VISITA. POR FAVOR LLAMAR ANTES DE DESPLAZARSE | 21/08/2025 EN COMUNICACIÓN CON EL CLIENTE EL SR JAIRO ALONSO ROJAS CRIOL 3108624352 SE LE INFORMA QUE POR ORDEN PÚBLICO NO SE PUEDE VIAJAR A LA ZONA DEL CATATUMBO SE LE INDICA QUE LOS EQUIPOS LOS PODRÍA ENVIAR A ALGUN FAMILIAR O EL PODER VIAJAR A ENTREGARLO PERSONALMENTE,ME INFORMA QUE OOR SEGURIDAD NO LES PERMITEN SALIR O ENVIAR NADA EN LA ZONA DONDE SE ENCUENTRAN | 22/08/2025 EN COMUNICACIÓN CON EL CLIENTE SE LE INFORMA QUE POR ORDEN PÚBLICO NO SE PUEDE VIAJAR A LA ZONA DEL CATATUMBO PARA LA RECOLECCIÓN DE EQUIPOS, SE LE INDICA QUE PODRÍA TRAERLOS A CÚCUTA O ENVIARLOS A ALGÚN FAMILIAR PARA LA ENTREGA,ME INDICO QUE POR SEGURIDAD Y ORDEN PÚBLICO NO PUEDE SALIR DE LA VEREDA Y TAMPOCO LES PERMITE REALIZAR ENVÍOS | W72: SOPORTE_TELEFÓNICO | X72: 0 | Y72: TIPO IV ESPECIAL | Z72: =VLOOKUP(D72,TIPOLOGIAS!A:F,5,0) -> TERRESTRE | AA72: DURAN ACOSTA FRANK YONNY | AB72: 0 | AC72: =IF(AND(W72="SOPORTE_TELEFÓNICO",OR(U72="SIN CONTACTO CON EL CB",U72="NÚMEROS DE CONTACTO ERRADOS")),0,IF(W72="SOPORTE_TELEFÓNICO",'BASE DE LIQUIDACION 2025'!$B$9,IF(Y72="TIPO I",'BASE DE LIQUIDACION 2025'!$C$3,IF(Y72="TIPO II",'BASE DE LIQUIDACION 2025'!$C$4,IF(Y72="TIPO III",'BASE DE LIQUIDACION 2025'!$C$5,'BASE DE LIQUIDACION 2025'!$C$6))))) -> 37904.612 | AD72: =IF(W72="SOPORTE_TELEFÓNICO",AC72,CIERRES!AB72*CIERRES!AC72) -> 37904.612
A73: PEREIRA | B73: =VLOOKUP(A73,'CENTRO DE COSTOS'!A:D,4,FALSE) -> DIEGO FERNANDO HENAO CARDONA | C73: =VLOOKUP(A73,'CENTRO DE COSTOS'!A:C,2,FALSE) -> 0004-0002 | D73: 63130 | E73: LC-CS-25-000103 | F73: 68002 | G73: ORDEN DE CAMBIO | H73: QUINDIO | I73: CALARCA | J73: BARRIO CENTRO CALARCA 11 | K73: REDEBAN | L73: FO-25-1406226 | M73: 45891.333 | N73: 45891.418 | P73: CIERRE | Q73: RECUPERACION DE EQUIPOS | R73: CB UNO A UNO | S73: CB UNO A UNO | T73: ILOCALIZADO | U73: CB CERRADO - DESOCUPADO | V73: 22/08/2025 SE INTENTA COMUNICACIÓN A LOS NÚMEROS 3148035888-3136730379, SE ENCUENTRAN APAGADOS. SE INTENTARÁ NUEVAMENTE | 22/08/2025 SE INTENTA COMUNICACIÓN A LOS NÚMEROS 3148035888-3136730379, SE ENCUENTRAN APAGADOS. SE INTENTARÁ NUEVAMENTE | 22/08/2025 SE VISITA COMERCIO, SE ENCUENTRA CERRADO, SE LLAMA A CONTACTOS NO HAY RESPUESTA, SE PREGUNTA A VECINOS POR EL COMERCIO INDICAN NO SABER NADA. | W73: VISITA_TÉCNICA | X73: 9L00V516 | Y73: TIPO II | Z73: =VLOOKUP(D73,TIPOLOGIAS!A:F,5,0) -> TERRESTRE | AA73: SANCHEZ SOLORZANO JUAN SEBASTIAN | AB73: 1 | AC73: =IF(AND(W73="SOPORTE_TELEFÓNICO",OR(U73="SIN CONTACTO CON EL CB",U73="NÚMEROS DE CONTACTO ERRADOS")),0,IF(W73="SOPORTE_TELEFÓNICO",'BASE DE LIQUIDACION 2025'!$B$9,IF(Y73="TIPO I",'BASE DE LIQUIDACION 2025'!$C$3,IF(Y73="TIPO II",'BASE DE LIQUIDACION 2025'!$C$4,IF(Y73="TIPO III",'BASE DE LIQUIDACION 2025'!$C$5,'BASE DE LIQUIDACION 2025'!$C$6))))) -> 134410.88 | AD73: =IF(W73="SOPORTE_TELEFÓNICO",AC73,CIERRES!AB73*CIERRES!AC73) -> 134410.88
A74: MEDELLIN | B74: =VLOOKUP(A74,'CENTRO DE COSTOS'!A:D,4,FALSE) -> JUAN SEBASTIÁN RÍOS CASTRILLÓN | C74: =VLOOKUP(A74,'CENTRO DE COSTOS'!A:C,2,FALSE) -> 0004-0005 | D74: 5318 | E74: LC-CS-25-000048 | F74: 69664 | G74: ORDEN DE CAMBIO | H74: ANTIOQUIA | I74: GUARNE | J74: PTM GUARNE MINIMERCADO LOS MA | K74: REDEBAN | L74: FO-25-1402428 | FO-25-1392601 | M74: 45888.595 | N74: 45891.441 | P74: CIERRE | Q74: CIERRE | R74: AGREGADOR | S74: COMCARD - PTM | T74: EJECUTADO_EXITOSO | U74: CIERRE EXITOSO | V74: 19/08/2025 EN COMUNICACIÓN CON LA SRA DIANA MARIA GARCIA TORO AL NÚMERO 3117942928 NOS CONFRIMA SOLICITUD, LA USUARIA INDICA QUE LA DIRECCIÓN PARA LA RECOLECCIÓN DE LOS EQUIPOS ES EN GUARNE CR 50 # 56-41 BARRIO SAN VICENTE | 21/08/2025 SE VISITA COMERCIO PERO SE ENCUENTRA CERRADO, SE LLAMA AL NÚMERO INDICADO PERO NO CONTESTAN, ESPERO POR UNOS MINUTOS (30) PERO NO ABREN 22/08/2025 SE REALIZA CIERRE DE CB | W74: VISITA_TÉCNICA | X74: MN000392 MN000606 - MN000392 | Y74: TIPO II | Z74: =VLOOKUP(D74,TIPOLOGIAS!A:F,5,0) -> TERRESTRE | AA74: HERNANDEZ CHAVARRIA JUAN CAMILO | AB74: 1 | AC74: =IF(AND(W74="SOPORTE_TELEFÓNICO",OR(U74="SIN CONTACTO CON EL CB",U74="NÚMEROS DE CONTACTO ERRADOS")),0,IF(W74="SOPORTE_TELEFÓNICO",'BASE DE LIQUIDACION 2025'!$B$9,IF(Y74="TIPO I",'BASE DE LIQUIDACION 2025'!$C$3,IF(Y74="TIPO II",'BASE DE LIQUIDACION 2025'!$C$4,IF(Y74="TIPO III",'BASE DE LIQUIDACION 2025'!$C$5,'BASE DE LIQUIDACION 2025'!$C$6))))) -> 134410.88 | AD74: =IF(W74="SOPORTE_TELEFÓNICO",AC74,CIERRES!AB74*CIERRES!AC74) -> 134410.88
A75: BOGOTA | B75: =VLOOKUP(A75,'CENTRO DE COSTOS'!A:D,4,FALSE) -> WILLIAM ASDRUBAL ROZO ROZO | C75: =VLOOKUP(A75,'CENTRO DE COSTOS'!A:C,2,FALSE) -> 0004-0004 | D75: 11001 | E75: LC-CS-25-000100 | F75: 23154 | G75: ORDEN DE CAMBIO | H75: CUNDINAMARCA | I75: BOGOTA | J75: BARRIO PUENTE ARANDA VIII BOGO | K75: REDEBAN | L75: FO-25-1406215 | M75: 45891.333 | N75: 45891.575 | P75: CIERRE | Q75: RECUPERACION DE EQUIPOS | R75: CB UNO A UNO | S75: CB UNO A UNO | T75: NO_EXITOSO | U75: CB NO ENTREGA EQUIPO | V75: 22/08/2025 EN COMUNICACIÓN CON EL SR NELSON FAUSTINO AL NÚMERO 3176393348 NOS CONFIRMA LA SOLICITUD, DATOS CORRECTOS. SE ESCALA PARA VISITA | 22/08/2025 SE REALIZA VISITA A CB PARA REALIZAR CIERRE EL SEÑOR LEONARDO INDICA QUE NO TIENE NINGÚN EQUIPO Y NO TIENEN CONOCIMIENTO SOBRE ELLOS | W75: VISITA_TÉCNICA | X75: NO | Y75: TIPO I | Z75: =VLOOKUP(D75,TIPOLOGIAS!A:F,5,0) -> TERRESTRE | AA75: GALINDO ROJAS LUIS FELIPE | AB75: 1 | AC75: =IF(AND(W75="SOPORTE_TELEFÓNICO",OR(U75="SIN CONTACTO CON EL CB",U75="NÚMEROS DE CONTACTO ERRADOS")),0,IF(W75="SOPORTE_TELEFÓNICO",'BASE DE LIQUIDACION 2025'!$B$9,IF(Y75="TIPO I",'BASE DE LIQUIDACION 2025'!$C$3,IF(Y75="TIPO II",'BASE DE LIQUIDACION 2025'!$C$4,IF(Y75="TIPO III",'BASE DE LIQUIDACION 2025'!$C$5,'BASE DE LIQUIDACION 2025'!$C$6))))) -> 44559.564 | AD75: =IF(W75="SOPORTE_TELEFÓNICO",AC75,CIERRES!AB75*CIERRES!AC75) -> 44559.564
A76: IBAGUE | B76: =VLOOKUP(A76,'CENTRO DE COSTOS'!A:D,4,FALSE) -> KEVIN ALEXIS CORZO BUSTOS | C76: =VLOOKUP(A76,'CENTRO DE COSTOS'!A:C,2,FALSE) -> 0004-0007 | D76: 73001 | E76: LC-CS-25-000124 | F76: 63213 | G76: ORDEN DE CAMBIO | H76: TOLIMA | I76: IBAGUE | J76: PTM IBAGUE DISTRIBUIDORA AYV | K76: REDEBAN | L76: FO-25-1410458 | M76: 45891.562 | N76: 45892.569 | P76: CIERRE | Q76: RECUPERACION DE EQUIPOS | R76: AGREGADOR | S76: COMCARD - PTM | T76: ILOCALIZADO | U76: CB CERRADO - DESOCUPADO | V76: 31/08/2025 EN COMUNICACIÓN CON EL SR VICTOR SANTOYA AL NÚMERO 3026622583 NOS CONFIRMA LA SOLICITUD Y DATOS CORRECTOS, SE ESCALA PARA VISITA, SIN EMBARGO LLAMAR ANTES DE DEPLAZARSE PARA DARLE INFORMACIÓN SOBRE LA DIRECCIÓN DE RCOLECCIÓN DE LOS EQUIPOS PORQUE EL USUARIO NO SE ENCUENTRA EN LA CIUDAD | 22/08/2025 SE LLEGA AL SITIO PERO EL COMERCIO NO EXISTE, SE VÁLIDA CONTACTO TELEFÓNICO AL NÚMERO 3026622583, NOS INDICAN ESTAR EQUIVOCADOS. | W76: VISITA_TÉCNICA | X76: 0 | Y76: TIPO I | Z76: =VLOOKUP(D76,TIPOLOGIAS!A:F,5,0) -> TERRESTRE | AA76: BARRAGAN TAFUR EDWIN ESTEBAN | AB76: 1 | AC76: =IF(AND(W76="SOPORTE_TELEFÓNICO",OR(U76="SIN CONTACTO CON EL CB",U76="NÚMEROS DE CONTACTO ERRADOS")),0,IF(W76="SOPORTE_TELEFÓNICO",'BASE DE LIQUIDACION 2025'!$B$9,IF(Y76="TIPO I",'BASE DE LIQUIDACION 2025'!$C$3,IF(Y76="TIPO II",'BASE DE LIQUIDACION 2025'!$C$4,IF(Y76="TIPO III",'BASE DE LIQUIDACION 2025'!$C$5,'BASE DE LIQUIDACION 2025'!$C$6))))) -> 44559.564 | AD76: =IF(W76="SOPORTE_TELEFÓNICO",AC76,CIERRES!AB76*CIERRES!AC76) -> 44559.564
A77: BOGOTA | B77: =VLOOKUP(A77,'CENTRO DE COSTOS'!A:D,4,FALSE) -> WILLIAM ASDRUBAL ROZO ROZO | C77: =VLOOKUP(A77,'CENTRO DE COSTOS'!A:C,2,FALSE) -> 0004-0004 | D77: 11001 | E77: LC-CS-25-000111 | F77: 32886 | G77: ORDEN DE CAMBIO | H77: CUNDINAMARCA | I77: BOGOTA | J77: BARRIO PERDOMO BOGOTA 5 | K77: REDEBAN | L77: FO-25-1410482 | M77: 45891.562 | N77: 45892.573 | P77: CIERRE | Q77: CIERRE | R77: CB UNO A UNO | S77: CB UNO A UNO | T77: NO_EXITOSO | U77: CB NO ENTREGA EQUIPO | V77: 22/08/2025 EN COMUNICACIÓN CON EL SR LUIS GENALDO DAZA RINCONAL NÚMERO 3105588702 NOS CONFIRMA LA SOLICITUD, NOS INDICA QUE LA DIRECCIÓN PARA LA RECOLECCIÓN DE LOS EQUIPOS ES CARRERA 97 C # 49 C 15 SUR BOSA DROGUERIA SERVICOP. SE ESCALA PARA VISITA, POR FAVOR LLAMAR ANTES DE DESPLAZARSE | 23/08/2025 SE LLEGA ALA DIRECCIÓN INDICADA Y COMERCIO INDICA QUE NO SE ENCUENTRA PERSONA ENCARGADA DE LA ENTREGA , SE LLAMA AL NÚMERO 3105588702 SR LUIS GENALDO DAZA RINCON INDICA QUE EL DÍA DE HOY NO PUEDE ATENDER NI ENTREGAR EQUIPOS QUE DE LUNES A VIERNES. | W77: VISITA_TÉCNICA | X77: 0 | Y77: TIPO I | Z77: =VLOOKUP(D77,TIPOLOGIAS!A:F,5,0) -> TERRESTRE | AA77: GARCIA PASTRANA KEVIN FERNANDO | AB77: 1 | AC77: =IF(AND(W77="SOPORTE_TELEFÓNICO",OR(U77="SIN CONTACTO CON EL CB",U77="NÚMEROS DE CONTACTO ERRADOS")),0,IF(W77="SOPORTE_TELEFÓNICO",'BASE DE LIQUIDACION 2025'!$B$9,IF(Y77="TIPO I",'BASE DE LIQUIDACION 2025'!$C$3,IF(Y77="TIPO II",'BASE DE LIQUIDACION 2025'!$C$4,IF(Y77="TIPO III",'BASE DE LIQUIDACION 2025'!$C$5,'BASE DE LIQUIDACION 2025'!$C$6))))) -> 44559.564 | AD77: =IF(W77="SOPORTE_TELEFÓNICO",AC77,CIERRES!AB77*CIERRES!AC77) -> 44559.564
A78: BOGOTA | B78: =VLOOKUP(A78,'CENTRO DE COSTOS'!A:D,4,FALSE) -> WILLIAM ASDRUBAL ROZO ROZO | C78: =VLOOKUP(A78,'CENTRO DE COSTOS'!A:C,2,FALSE) -> 0004-0004 | D78: 11001 | E78: LC-CS-25-000105 | F78: 72530 | G78: ORDEN DE CAMBIO | H78: CUNDINAMARCA | I78: BOGOTA | J78: LA CASTELLANA BOGOTA 3 | K78: REDEBAN | L78: FO-25-1406236 | M78: 45891.333 | N78: 45892.576 | P78: CIERRE | Q78: RECUPERACION DE EQUIPOS | R78: CB UNO A UNO | S78: CB UNO A UNO | T78: ILOCALIZADO | U78: CB CERRADO - DESOCUPADO | V78: 22/08/2025 EN COMUNICACIÓN CON LA SRA MARCELA DE ANTONIO AL NÚMERO 3116207484 NOS CONFIRMA LA SOLICITUD, DATOS CORRECTOS. SE ESCALA PARA VISITA, POR FAVOR LLAMAR ANTES DE DESPLAZARSE | 23/08/2025 SE VISITA DIRECCIÓN INDICADA EN LA ORDEN SE EVIDENCIA QUE EL COMERCIO SE ENCUENTRA CERRADO SE LLAMA EL TELÉFONO DE CONTACTO VARIAS VECES NO SE LOGRA COMUNICACIÓN CON EL CLIENTE SE TOMAN EVIDENCIAS FOTOGRÁFICAS DE LA VISITA Y NOS RETIRAMOS | W78: VISITA_TÉCNICA | X78: NONE | Y78: TIPO I | Z78: =VLOOKUP(D78,TIPOLOGIAS!A:F,5,0) -> TERRESTRE | AA78: VEGA MANRIQUE JONATAN MAURICIO | AB78: 1 | AC78: =IF(AND(W78="SOPORTE_TELEFÓNICO",OR(U78="SIN CONTACTO CON EL CB",U78="NÚMEROS DE CONTACTO ERRADOS")),0,IF(W78="SOPORTE_TELEFÓNICO",'BASE DE LIQUIDACION 2025'!$B$9,IF(Y78="TIPO I",'BASE DE LIQUIDACION 2025'!$C$3,IF(Y78="TIPO II",'BASE DE LIQUIDACION 2025'!$C$4,IF(Y78="TIPO III",'BASE DE LIQUIDACION 2025'!$C$5,'BASE DE LIQUIDACION 2025'!$C$6))))) -> 44559.564 | AD78: =IF(W78="SOPORTE_TELEFÓNICO",AC78,CIERRES!AB78*CIERRES!AC78) -> 44559.564
A79: APARTADO | B79: =VLOOKUP(A79,'CENTRO DE COSTOS'!A:D,4,FALSE) -> JUAN SEBASTIÁN RÍOS CASTRILLÓN | C79: =VLOOKUP(A79,'CENTRO DE COSTOS'!A:C,2,FALSE) -> 0004-0005 | D79: 5172 | E79: LC-CS-25-000023 | F79: 59671 | G79: ORDEN DE CAMBIO | H79: ANTIOQUIA | I79: CHIGORODO | J79: BARRIO CHIGORODO CHIGORODO 2 | K79: REDEBAN | L79: FO-25-1380901 | M79: 45884.528 | N79: 45892.656 | P79: CIERRE | Q79: CIERRE | R79: CB UNO A UNO | S79: CB UNO A UNO | T79: ILOCALIZADO | U79: CB CERRADO - DESOCUPADO | V79: 15/08/2025 SE INTENTA COMUNICACIÓN AL NÚMERO 3147932162 SUENA PERO NO HAY CONTACTO. SE INTENTARÁ NUEVAMENTE | 19/08/2025 SE INTENTA COMUNICACIÓN AL NÚMERO 3147932162 SUENA PERO NO HAY CONTACTO. SE INTENTARÁ NUEVAMENTE | 19/08/2025 SE INTENTA COMUNICACIÓN AL NÚMERO 3147932162 SUENA PERO NO HAY CONTACTO. | 23/08/2025 SE REALIZA VISITA AL ESTABLECIMIENTO COMERCIAL CON EL OBJETIVO DE GESTIONAR EL CIERRE DEL CORRESPONSAL BANCOLOMBIA. AL LLEGAR, SE CONSTATA QUE EL COMERCIO SE ENCUENTRA CERRADO. SE INTENTA ESTABLECER COMUNICACIÓN CON EL USUARIO RESPONSABLE MEDIANTE LOS CANALES HABITUALES, PERO NO SE OBTIENE RESPUESTA. | W79: VISITA_TÉCNICA | X79: LA009528 | Y79: TIPO II | Z79: =VLOOKUP(D79,TIPOLOGIAS!A:F,5,0) -> TERRESTRE | AA79: MARTINEZ TOVAR OSCAR DAVID | AB79: 1 | AC79: =IF(AND(W79="SOPORTE_TELEFÓNICO",OR(U79="SIN CONTACTO CON EL CB",U79="NÚMEROS DE CONTACTO ERRADOS")),0,IF(W79="SOPORTE_TELEFÓNICO",'BASE DE LIQUIDACION 2025'!$B$9,IF(Y79="TIPO I",'BASE DE LIQUIDACION 2025'!$C$3,IF(Y79="TIPO II",'BASE DE LIQUIDACION 2025'!$C$4,IF(Y79="TIPO III",'BASE DE LIQUIDACION 2025'!$C$5,'BASE DE LIQUIDACION 2025'!$C$6))))) -> 134410.88 | AD79: =IF(W79="SOPORTE_TELEFÓNICO",AC79,CIERRES!AB79*CIERRES!AC79) -> 134410.88
A80: CUCUTA | B80: =VLOOKUP(A80,'CENTRO DE COSTOS'!A:D,4,FALSE) -> MIGUEL JULIÁN HERNÁNDEZ GUARÍN | C80: =VLOOKUP(A80,'CENTRO DE COSTOS'!A:C,2,FALSE) -> 0004-0008 | D80: 54405 | E80: LC-CS-25-000121 | F80: 77857 | G80: ORDEN DE CAMBIO | H80: NORTE DE SANTANDER | I80: LOS PATIOS | J80: PTM PUNTOSERVIS LOS PATIOS 1 L | K80: REDEBAN | L80: FO-25-1410406 | FO-25-1416809 | M80: 45891.562 | N80: 45893.58 | P80: CIERRE | Q80: RECUPERACION DE EQUIPOS | R80: AGREGADOR | S80: COMCARD - PTM | T80: ILOCALIZADO | U80: CB CERRADO - DESOCUPADO | V80: 28/08/2025 EN COMUNICACIÓN CON LA SRA DIANA ORTIZ AL NÚMERO 3028161475 NOS CONFIRMA LA SOLICITUD, DATOS CORRECTOS. SE ESCALA PARA VISITA, POR FAVOR LLAMAR A LOS NÚMEROS 3028161475 O 3203894073 ANTES DE DESPLAZARSE. | 23/08/2025 SE REALIZA VISITA, COMERCIO SE ENCUENTRA CERRADO, SE INTENTA CONTACTAR TELEFÓNICAMENTE AL CLIENTE, PERO NO RESPONDE EL NÚMERO DE CONTACTO. 3028161475 | W80: VISITA_TÉCNICA | X80: NONE | Y80: TIPO I | Z80: =VLOOKUP(D80,TIPOLOGIAS!A:F,5,0) -> TERRESTRE | AA80: PACHECO BUITRAGO JAVIER ALONSO | AB80: 2 | AC80: =IF(AND(W80="SOPORTE_TELEFÓNICO",OR(U80="SIN CONTACTO CON EL CB",U80="NÚMEROS DE CONTACTO ERRADOS")),0,IF(W80="SOPORTE_TELEFÓNICO",'BASE DE LIQUIDACION 2025'!$B$9,IF(Y80="TIPO I",'BASE DE LIQUIDACION 2025'!$C$3,IF(Y80="TIPO II",'BASE DE LIQUIDACION 2025'!$C$4,IF(Y80="TIPO III",'BASE DE LIQUIDACION 2025'!$C$5,'BASE DE LIQUIDACION 2025'!$C$6))))) -> 44559.564 | AD80: =IF(W80="SOPORTE_TELEFÓNICO",AC80,CIERRES!AB80*CIERRES!AC80) -> 89119.128
A81: CALI | B81: =VLOOKUP(A81,'CENTRO DE COSTOS'!A:D,4,FALSE) -> DIEGO FERNANDO HENAO CARDONA | C81: =VLOOKUP(A81,'CENTRO DE COSTOS'!A:C,2,FALSE) -> 0004-0003 | D81: 76001 | E81: LC-CS-25-000125 | F81: 47249 | G81: ORDEN DE CAMBIO | H81: VALLE DEL CAUCA | I81: CALI | J81: PTM CALI ISA BOUTIQUE | K81: REDEBAN | L81: FO-25-1410468 | M81: 45891.562 | N81: 45893.582 | P81: CIERRE | Q81: RECUPERACION DE EQUIPOS | R81: AGREGADOR | S81: COMCARD - PTM | T81: ILOCALIZADO | U81: CB CERRADO - DESOCUPADO | V81: 31/08/2025 SE INTENTA COMUNICACIÓN AL NÚMERO 3148149892 SE ENCUENTRA APAGADO. SE INTENTARÁ NUEVAMENTE | 23/08/2025 SE INTENTA COMUNICACIÓN AL NÚMERO 3148149892 SE ENCUENTRA APAGADO. SE INTENTARÁ NUEVAMENTE | 23/08/2025 SE INTENTA COMUNICACIÓN VIA WHATSAPP Y LLAMADA AL NÚMERO 3148149892 SE ENCUENTRA APAGADO, NO HAY CONTACTO | 22/08/2025 SE LLEGA AL COMERCIO PERO EL COMERCIO SE ENCUENTRA CERRADO SE LLAMA EL CLIENTE Y NO CONTESTA ENTONCES NO SE PUEDE HACER RETIRO DE PUBLICIDAD NI EQUIPOS SE PREGUNTA LOS ALREDEDORES Y DICE QUE EL COMERCIO LLEVA TIEMPO ASÍ CERRADO | W81: VISITA_TÉCNICA | X81: TR00D556 | Y81: TIPO I | Z81: =VLOOKUP(D81,TIPOLOGIAS!A:F,5,0) -> TERRESTRE | AA81: CUERO RUIZ JHONNY | AB81: 1 | AC81: =IF(AND(W81="SOPORTE_TELEFÓNICO",OR(U81="SIN CONTACTO CON EL CB",U81="NÚMEROS DE CONTACTO ERRADOS")),0,IF(W81="SOPORTE_TELEFÓNICO",'BASE DE LIQUIDACION 2025'!$B$9,IF(Y81="TIPO I",'BASE DE LIQUIDACION 2025'!$C$3,IF(Y81="TIPO II",'BASE DE LIQUIDACION 2025'!$C$4,IF(Y81="TIPO III",'BASE DE LIQUIDACION 2025'!$C$5,'BASE DE LIQUIDACION 2025'!$C$6))))) -> 44559.564 | AD81: =IF(W81="SOPORTE_TELEFÓNICO",AC81,CIERRES!AB81*CIERRES!AC81) -> 44559.564
A82: MEDELLIN | B82: =VLOOKUP(A82,'CENTRO DE COSTOS'!A:D,4,FALSE) -> JUAN SEBASTIÁN RÍOS CASTRILLÓN | C82: =VLOOKUP(A82,'CENTRO DE COSTOS'!A:C,2,FALSE) -> 0004-0005 | D82: 5001 | E82: LC-CS-25-000079 | F82: 25583 | G82: ORDEN DE CAMBIO | H82: ANTIOQUIA | I82: MEDELLIN | J82: COMCARD FERRE-JORDANÑ1 | K82: REDEBAN | L82: FO-25-1397938 | M82: 45889.582 | N82: 45893.586 | P82: CIERRE | Q82: CIERRE | R82: AGREGADOR | S82: COMCARD - PTM | T82: NO_EXITOSO | U82: CB NO ENTREGA EQUIPO | V82: 20/08/2025 SE INTENTA COMUNICACIÓN AL NÚMERO 3003102770 SUENA PERO NO HAY CONTACTO. SE INTENTARÁ NUEVAMENTE | 21/08/2025 SE INTENTA COMUNICACIÓN AL NÚMERO 3003102770 SUENA PERO NO HAY CONTACTO. SE INTENTARÁ NUEVAMENTE | 22/08/2025 SE INTENTA COMUNICACIÓN AL NÚMERO 3003102770 SUENA PERO NO HAY CONTACTO. | 23/08/2025 SE CONTACTA A CLIENTE VÍA CHAT Y TELEFÓNICA NO SE RECIBEN RESPUESTAS. EN EL PUNTO EMPLEADO INFORMA EL SR NO ESTÁ Y LOS EQUIPOS NO SE ENCUENTRAN EN EL LUGAR POR LO TANTO NO SE PUEDE REALIZAR EL CIERRE DEL CB | W82: VISITA_TÉCNICA | X82: NONE | Y82: TIPO I | Z82: =VLOOKUP(D82,TIPOLOGIAS!A:F,5,0) -> TERRESTRE | AA82: HERNANDEZ CHAVARRIA JUAN CAMILO | AB82: 1 | AC82: =IF(AND(W82="SOPORTE_TELEFÓNICO",OR(U82="SIN CONTACTO CON EL CB",U82="NÚMEROS DE CONTACTO ERRADOS")),0,IF(W82="SOPORTE_TELEFÓNICO",'BASE DE LIQUIDACION 2025'!$B$9,IF(Y82="TIPO I",'BASE DE LIQUIDACION 2025'!$C$3,IF(Y82="TIPO II",'BASE DE LIQUIDACION 2025'!$C$4,IF(Y82="TIPO III",'BASE DE LIQUIDACION 2025'!$C$5,'BASE DE LIQUIDACION 2025'!$C$6))))) -> 44559.564 | AD82: =IF(W82="SOPORTE_TELEFÓNICO",AC82,CIERRES!AB82*CIERRES!AC82) -> 44559.564
A83: BOGOTA | B83: =VLOOKUP(A83,'CENTRO DE COSTOS'!A:D,4,FALSE) -> WILLIAM ASDRUBAL ROZO ROZO | C83: =VLOOKUP(A83,'CENTRO DE COSTOS'!A:C,2,FALSE) -> 0004-0004 | D83: 11001 | E83: LC-CS-25-000069 | F83: 45415 | G83: ORDEN DE CAMBIO | H83: CUNDINAMARCA | I83: BOGOTA | J83: BARRIO RESTREPO BOGOTA 7 | K83: REDEBAN | L83: FO-25-1393695 | M83: 45888.651 | N83: 45893.587 | P83: CIERRE | Q83: CIERRE | R83: CB UNO A UNO | S83: CB UNO A UNO | T83: ILOCALIZADO | U83: CB CERRADO - DESOCUPADO | V83: 19/08/2025 EN COMUNICACIÓN CON EL SR CARLOS ARLEY MORENO BEJARANO AL NÚMERO 3146259714 NOS CONFIRMA LA SOLICITUD, DATOS CORRECTOS. SE ESCALA PARA VISITA, POR FAVOR LLAMAR ANTES DE DESPLAZARSE | 23/08/2025 SE VISITA COMERCIO LA DIRECCIÓN SUMISNISTADA EN LA ORDEN PERO EN EL SITIO NO HAY CONTACTO CON EL CLIENTE Y NO HAY NÚMEROS DE CONTACTO, SE TOMA EVIDENCIA FOTOGRAFICA DE LA VISITA Y NOS RETIRAMOS | W83: VISITA_TÉCNICA | X83: 0 | Y83: TIPO I | Z83: =VLOOKUP(D83,TIPOLOGIAS!A:F,5,0) -> TERRESTRE | AA83: VEGA MANRIQUE JONATAN MAURICIO | AB83: 1 | AC83: =IF(AND(W83="SOPORTE_TELEFÓNICO",OR(U83="SIN CONTACTO CON EL CB",U83="NÚMEROS DE CONTACTO ERRADOS")),0,IF(W83="SOPORTE_TELEFÓNICO",'BASE DE LIQUIDACION 2025'!$B$9,IF(Y83="TIPO I",'BASE DE LIQUIDACION 2025'!$C$3,IF(Y83="TIPO II",'BASE DE LIQUIDACION 2025'!$C$4,IF(Y83="TIPO III",'BASE DE LIQUIDACION 2025'!$C$5,'BASE DE LIQUIDACION 2025'!$C$6))))) -> 44559.564 | AD83: =IF(W83="SOPORTE_TELEFÓNICO",AC83,CIERRES!AB83*CIERRES!AC83) -> 44559.564
A84: CUCUTA | B84: =VLOOKUP(A84,'CENTRO DE COSTOS'!A:D,4,FALSE) -> MIGUEL JULIÁN HERNÁNDEZ GUARÍN | C84: =VLOOKUP(A84,'CENTRO DE COSTOS'!A:C,2,FALSE) -> 0004-0008 | D84: 54498 | E84: LC-CS-25-000063 | F84: 45252 | G84: ORDEN DE CAMBIO | H84: NORTE DE SANTANDER | I84: OCAÑA | J84: DISTRICOL DROGUERIA LA COLINA | K84: REDEBAN | L84: FO-25-1409474 | FO-25-1392606 | M84: 45888.595 | N84: 45893.59 | P84: CIERRE | Q84: CIERRE | R84: AGREGADOR | S84: DISTRICOL | T84: EJECUTADO_EXITOSO | U84: CIERRE EXITOSO | V84: 19/08/2025 SE INTENTA COMUNICACIÓN AL NÚMERO 3157158244 SUENA PERO NO HAY CONTACTO. SE INTENTARÁ NUEVAMENTE | 20/08/2025 SE INTENTA COMUNICACIÓN AL NÚMERO 3157158244 SUENA PERO NO HAY CONTACTO. SE INTENTARÁ NUEVAMENTE | 22/08/2025 SE REALIZÓ VISITA AL COMERCIO Y CLIENTE MANIFIESTA QUE LA PERSONA ENCARGADA O REPRESENTANTE SE ENCUENTRA A LAS 3PM, SE REPROGRAMAR VISITA PARA LAS HORAS PM 22/08/2025 SE REALIZA VISITA AL COMERCIO Y SE REALIZA RETIRO DE DATAFONO LECTORA CABLEADO PUBLICIDAD FUE DESTRUIDA POR EL CLIENTE POR SU MAL ESTADO | W84: VISITA_TÉCNICA | X84: NONE GA0LZ547 | Y84: TIPO IV | Z84: =VLOOKUP(D84,TIPOLOGIAS!A:F,5,0) -> TERRESTRE | AA84: MORA VEGA JEAMPIER | AB84: 1 | AC84: =IF(AND(W84="SOPORTE_TELEFÓNICO",OR(U84="SIN CONTACTO CON EL CB",U84="NÚMEROS DE CONTACTO ERRADOS")),0,IF(W84="SOPORTE_TELEFÓNICO",'BASE DE LIQUIDACION 2025'!$B$9,IF(Y84="TIPO I",'BASE DE LIQUIDACION 2025'!$C$3,IF(Y84="TIPO II",'BASE DE LIQUIDACION 2025'!$C$4,IF(Y84="TIPO III",'BASE DE LIQUIDACION 2025'!$C$5,'BASE DE LIQUIDACION 2025'!$C$6))))) -> 464809.37 | AD84: =IF(W84="SOPORTE_TELEFÓNICO",AC84,CIERRES!AB84*CIERRES!AC84) -> 464809.37
A85: BOGOTA | B85: =VLOOKUP(A85,'CENTRO DE COSTOS'!A:D,4,FALSE) -> WILLIAM ASDRUBAL ROZO ROZO | C85: =VLOOKUP(A85,'CENTRO DE COSTOS'!A:C,2,FALSE) -> 0004-0004 | D85: 11001 | E85: LC-CS-25-000065 | F85: 68439 | G85: ORDEN DE CAMBIO | H85: CUNDINAMARCA | I85: BOGOTA | J85: PTM BOGOTA REYES MULTISERVICI | K85: REDEBAN | L85: FO-25-1392550 | M85: 45888.595 | N85: 45894.599 | P85: CIERRE | Q85: CIERRE | R85: AGREGADOR | S85: COMCARD - PTM | T85: ILOCALIZADO | U85: CB CERRADO - DESOCUPADO | V85: 19/08/2025 SE INTENTA COMUNICACIÓN AL NÚMERO 6050962 NO HAY CONTACTO. SE INTENTARÁ NUEVAMENTE | 20/08/2025 SE INTENTA COMUNICACIÓN AL NÚMERO 6050962 NO HAY CONTACTO. SE INTENTARÁ NUEVAMENTE | 20/08/2025 SE INTENTA COMUNICACIÓN AL NÚMERO 6050962 NO HAY CONTACTO. | 25/08/2025 SE VISITA COMERCIO, SE EVIDENCIA QUE ESTÁ CERRADO, SE LLAMA A TELÉFONOS DE CONTACTO 3206578031 Y NO HAY RESPUESTA, SE TOMA EVIDENCIA DE LA VISITA Y NOS RETIRAMOS. | W85: VISITA_TÉCNICA | X85: NONE | Y85: TIPO I | Z85: =VLOOKUP(D85,TIPOLOGIAS!A:F,5,0) -> TERRESTRE | AA85: VEGA MANRIQUE JONATAN MAURICIO | AB85: 1 | AC85: =IF(AND(W85="SOPORTE_TELEFÓNICO",OR(U85="SIN CONTACTO CON EL CB",U85="NÚMEROS DE CONTACTO ERRADOS")),0,IF(W85="SOPORTE_TELEFÓNICO",'BASE DE LIQUIDACION 2025'!$B$9,IF(Y85="TIPO I",'BASE DE LIQUIDACION 2025'!$C$3,IF(Y85="TIPO II",'BASE DE LIQUIDACION 2025'!$C$4,IF(Y85="TIPO III",'BASE DE LIQUIDACION 2025'!$C$5,'BASE DE LIQUIDACION 2025'!$C$6))))) -> 44559.564 | AD85: =IF(W85="SOPORTE_TELEFÓNICO",AC85,CIERRES!AB85*CIERRES!AC85) -> 44559.564
A86: BARRANQUILLA | B86: =VLOOKUP(A86,'CENTRO DE COSTOS'!A:D,4,FALSE) -> JOSE MAURICIO HERNANDEZ ROJAS | C86: =VLOOKUP(A86,'CENTRO DE COSTOS'!A:C,2,FALSE) -> 0004-0001 | D86: 8436 | E86: LC-CS-25-000115 | F86: 54295 | G86: ORDEN DE CAMBIO | H86: ATLANTICO | I86: MANATI | J86: PTM MANATI PAPELERIA JC & NA | K86: REDEBAN | L86: FO-25-1410403 | M86: 45891.562 | N86: 45894.635 | P86: CIERRE | Q86: RECUPERACION DE EQUIPOS | R86: AGREGADOR | S86: COMCARD - PTM | T86: NO_EXITOSO | U86: CB NO ENTREGA EQUIPO | V86: 23/08/2025 EN COMUNICACIÓN CON LA SRA ADRIANA BADILLO AL NÚMERO 3215116269 NOS CONFIRMA LA SOLICITUD, NOS INDICA QUE LA DIRECCIÓN PARA LA RECOLECCIÓN DE LOS EQUIPOS ES CALLE 5A 39 194 OFICINA 702 MEDELLIN BARRIO POBLADO | 25/08/2025 SE REALIZA VISITA TÉCNICA, NO SE CONSIGUE LOS EQUIPOS EN SITIO, CLIENTE INDICA QUE LOS ENVÍO A PTM A LA CIUDAD DE MEDELLÍN. | W86: VISITA_TÉCNICA | X86: NO SE TIENE EL DATO | Y86: TIPO II | Z86: =VLOOKUP(D86,TIPOLOGIAS!A:F,5,0) -> TERRESTRE | AA86: DE AGUAS MUÑOZ DAVID JOSE | AB86: 1 | AC86: =IF(AND(W86="SOPORTE_TELEFÓNICO",OR(U86="SIN CONTACTO CON EL CB",U86="NÚMEROS DE CONTACTO ERRADOS")),0,IF(W86="SOPORTE_TELEFÓNICO",'BASE DE LIQUIDACION 2025'!$B$9,IF(Y86="TIPO I",'BASE DE LIQUIDACION 2025'!$C$3,IF(Y86="TIPO II",'BASE DE LIQUIDACION 2025'!$C$4,IF(Y86="TIPO III",'BASE DE LIQUIDACION 2025'!$C$5,'BASE DE LIQUIDACION 2025'!$C$6))))) -> 134410.88 | AD86: =IF(W86="SOPORTE_TELEFÓNICO",AC86,CIERRES!AB86*CIERRES!AC86) -> 134410.88
A87: BOGOTA | B87: =VLOOKUP(A87,'CENTRO DE COSTOS'!A:D,4,FALSE) -> WILLIAM ASDRUBAL ROZO ROZO | C87: =VLOOKUP(A87,'CENTRO DE COSTOS'!A:C,2,FALSE) -> 0004-0004 | D87: 11001 | E87: LC-CS-25-000092 | F87: 69346 | G87: ORDEN DE CAMBIO | H87: CUNDINAMARCA | I87: BOGOTA | J87: BARRIO VIRREY BOGOTA 5 | K87: REDEBAN | L87: FO-25-1397915 | M87: 45889.583 | N87: 45894.69 | P87: CIERRE | Q87: RECUPERACION DE EQUIPOS | R87: CB UNO A UNO | S87: CB UNO A UNO | T87: ILOCALIZADO | U87: CB CERRADO - DESOCUPADO | V87: 21/08/2025 NO CONTACTADO | 25/08/2025 SE LLEGA A DIRECCIÓN PARA RETIRO DE EQUIPOS ESTÁ CERRADO SE INTENTA CONTACTO AL NÚMERO 3204130173 NADIE CONTESTA SE DEJA REGISTRO FOTOGRÁFICO | W87: VISITA_TÉCNICA | X87: 0 | Y87: TIPO I | Z87: =VLOOKUP(D87,TIPOLOGIAS!A:F,5,0) -> TERRESTRE | AA87: BUSTOS MORA DIEGO MANUEL | AB87: 1 | AC87: =IF(AND(W87="SOPORTE_TELEFÓNICO",OR(U87="SIN CONTACTO CON EL CB",U87="NÚMEROS DE CONTACTO ERRADOS")),0,IF(W87="SOPORTE_TELEFÓNICO",'BASE DE LIQUIDACION 2025'!$B$9,IF(Y87="TIPO I",'BASE DE LIQUIDACION 2025'!$C$3,IF(Y87="TIPO II",'BASE DE LIQUIDACION 2025'!$C$4,IF(Y87="TIPO III",'BASE DE LIQUIDACION 2025'!$C$5,'BASE DE LIQUIDACION 2025'!$C$6))))) -> 44559.564 | AD87: =IF(W87="SOPORTE_TELEFÓNICO",AC87,CIERRES!AB87*CIERRES!AC87) -> 44559.564
A88: MEDELLIN | B88: =VLOOKUP(A88,'CENTRO DE COSTOS'!A:D,4,FALSE) -> JUAN SEBASTIÁN RÍOS CASTRILLÓN | C88: =VLOOKUP(A88,'CENTRO DE COSTOS'!A:C,2,FALSE) -> 0004-0005 | D88: 5660 | E88: LC-CS-25-000055 | F88: 78762 | G88: ORDEN DE CAMBIO | H88: ANTIOQUIA | I88: SAN LUIS | J88: DISTRICOL TECNOMARCAS | K88: REDEBAN | L88: FO-25-1392593 | M88: 45888.595 | N88: 45895.429 | P88: CIERRE | Q88: CIERRE | R88: AGREGADOR | S88: DISTRICOL | T88: ILOCALIZADO | U88: CB CERRADO - DESOCUPADO | V88: 19/08/2025 SE INENTA COMUICACIÓN AL NÚMERO 3507753783, NO HAY CONTACTO. SE INTENTARÁ NUEVAMENTE | 20/08/2025 SE INENTA COMUICACIÓN AL NÚMERO 3507753783, NO HAY CONTACTO. SE INTENTARÁ NUEVAMENTE | 20/08/2025 SE INTENTA COMUNICACIÓN AL NÚMERO 3507753783, NO HAY CONTACTO, NÚMERO SUSPENDIDO | 22/08/2025 SE PRESENTA NOVEDAD EN LA VÍA POR DERRUMBES Y UN CAMIÓN VOLCADO, NO HAY PASO EN LA AUTOPISTA MEDELLIN-BOGOTA. VISITA SE POSPONE PARA LA PROXIMA SEMANA QUE SE NORMALICE LA SITUACIÓN. | 25/08/2025 SE LLEGA AL SITIO SE ENCUENTRA CERRADO SE INTENTA COMUNICACIÓN CON EL CLIENTE Y NI FUE POSIBLE. SE REGRESA EN LA NOCHE Y SIGUE CERRADO EL COMERCIO | W88: VISITA_TÉCNICA | X88: SXRZZ986 | Y88: TIPO III | Z88: =VLOOKUP(D88,TIPOLOGIAS!A:F,5,0) -> TERRESTRE | AA88: ZAPATA LOPEZ EDWARD ASDRUBAL | AB88: 1 | AC88: =IF(AND(W88="SOPORTE_TELEFÓNICO",OR(U88="SIN CONTACTO CON EL CB",U88="NÚMEROS DE CONTACTO ERRADOS")),0,IF(W88="SOPORTE_TELEFÓNICO",'BASE DE LIQUIDACION 2025'!$B$9,IF(Y88="TIPO I",'BASE DE LIQUIDACION 2025'!$C$3,IF(Y88="TIPO II",'BASE DE LIQUIDACION 2025'!$C$4,IF(Y88="TIPO III",'BASE DE LIQUIDACION 2025'!$C$5,'BASE DE LIQUIDACION 2025'!$C$6))))) -> 222904.07 | AD88: =IF(W88="SOPORTE_TELEFÓNICO",AC88,CIERRES!AB88*CIERRES!AC88) -> 222904.07
A89: SANTA MARTA | B89: =VLOOKUP(A89,'CENTRO DE COSTOS'!A:D,4,FALSE) -> JOSE MAURICIO HERNANDEZ ROJAS | C89: =VLOOKUP(A89,'CENTRO DE COSTOS'!A:C,2,FALSE) -> 0004-0001 | D89: 44430 | E89: LC-CS-25-000007 | F89: 68485 | G89: ORDEN DE CAMBIO | H89: LA GUAJIRA | I89: MAICAO | J89: DISTRICOL TIENDA Y&A | K89: REDEBAN | L89: FO-25-1380449 | M89: 45884.483 | N89: 45895.434 | P89: CIERRE | Q89: CIERRE | R89: AGREGADOR | S89: DISTRICOL | T89: NO_EXITOSO | U89: CB NO ENTREGA EQUIPO | V89: 15/08/2025 EN COMUNICACIÓN CON EL SEÑOR JUAN FERNANDO YEPES ALZATE AL NÚMERO 3207960856 NOS CONFRIMA SOLICITUD, DATOS CORRECTOS. SE ESCALA PARA VISITA | 25/08/2025 COLABORADOR EN DESPLAZAMIENTO A MAICAO, SE PRESENTA RETRASO POR BLOQUEOS PARCIALES EN LA VIA DESDE SANTA MARTA | 26/08/2025 SE REALIZA LA VISITA, EL USUARIO INRMA QUE YA ENVÍO LOS EQUIPOS A MEDELLÍN A LA DIRECCIÓN CRA 30 # 8B -25, EDIFICIO SAN ESTEBAN POBLADO MEDELLIN EL CLIENTE INFORMA QUE SE COMUNICÓ CON SILVANA MARULANDA TEL:3028618037 CORREO:SILVANA1017DISTRIVOL@GMAIL.COM EL CLIENTE ENVIÓ EL DATÁFONO Y LA LECTORA LA SEMANA PASADA | W89: VISITA_TÉCNICA | X89: 0 | Y89: TIPO IV | Z89: =VLOOKUP(D89,TIPOLOGIAS!A:F,5,0) -> TERRESTRE | AA89: THOMAS CAMPO SIGIFREDO SEGUNDO | AB89: 1 | AC89: =IF(AND(W89="SOPORTE_TELEFÓNICO",OR(U89="SIN CONTACTO CON EL CB",U89="NÚMEROS DE CONTACTO ERRADOS")),0,IF(W89="SOPORTE_TELEFÓNICO",'BASE DE LIQUIDACION 2025'!$B$9,IF(Y89="TIPO I",'BASE DE LIQUIDACION 2025'!$C$3,IF(Y89="TIPO II",'BASE DE LIQUIDACION 2025'!$C$4,IF(Y89="TIPO III",'BASE DE LIQUIDACION 2025'!$C$5,'BASE DE LIQUIDACION 2025'!$C$6))))) -> 464809.37 | AD89: =IF(W89="SOPORTE_TELEFÓNICO",AC89,CIERRES!AB89*CIERRES!AC89) -> 464809.37
A90: MEDELLIN | B90: =VLOOKUP(A90,'CENTRO DE COSTOS'!A:D,4,FALSE) -> JUAN SEBASTIÁN RÍOS CASTRILLÓN | C90: =VLOOKUP(A90,'CENTRO DE COSTOS'!A:C,2,FALSE) -> 0004-0005 | D90: 5266 | E90: LC-CS-25-000145 | F90: 64680 | G90: ORDEN DE CAMBIO | H90: ANTIOQUIA | I90: ENVIGADO | J90: DISTRICOL DROGUERIA AMERICANA | K90: REDEBAN | L90: FO-25-1424061 | M90: 45895.333 | N90: 45895.511 | P90: CIERRE | Q90: CIERRE | R90: AGREGADOR | S90: DISTRICOL | T90: NO_EXITOSO | U90: CB NO ENTREGA EQUIPO | V90: 26/08/2025 EN COMUNICACIÓN CON LA SRA DAIELA ESTEFANY OSPINA USME AL NÚMERO 3128939185 NOS CONFIRMA LA SOLICITUD, DATOS CORRECTOS. SE ESCALA PARA VISITA | 26/08/2025 SE LLEGA A DIRECCIÓN NOS INDICAN QUE EL DÍA DE HOY NO PUEDEN ENTREGAR EL DATÁFONO YA QUE EL DUEÑO NO SE ENCUENTRA EL EMPLEADO NOS INDICA QUE NO PUEDE FIRMAR NI ENTREGAR INFORMACIÓN ADICIONAL | W90: VISITA_TÉCNICA | X90: 3A003057 | Y90: TIPO I | Z90: =VLOOKUP(D90,TIPOLOGIAS!A:F,5,0) -> TERRESTRE | AA90: CASTAÑEDA PALACIO CARLOS FELIPE | AB90: 1 | AC90: =IF(AND(W90="SOPORTE_TELEFÓNICO",OR(U90="SIN CONTACTO CON EL CB",U90="NÚMEROS DE CONTACTO ERRADOS")),0,IF(W90="SOPORTE_TELEFÓNICO",'BASE DE LIQUIDACION 2025'!$B$9,IF(Y90="TIPO I",'BASE DE LIQUIDACION 2025'!$C$3,IF(Y90="TIPO II",'BASE DE LIQUIDACION 2025'!$C$4,IF(Y90="TIPO III",'BASE DE LIQUIDACION 2025'!$C$5,'BASE DE LIQUIDACION 2025'!$C$6))))) -> 44559.564 | AD90: =IF(W90="SOPORTE_TELEFÓNICO",AC90,CIERRES!AB90*CIERRES!AC90) -> 44559.564
A91: BARRANQUILLA | B91: =VLOOKUP(A91,'CENTRO DE COSTOS'!A:D,4,FALSE) -> JOSE MAURICIO HERNANDEZ ROJAS | C91: =VLOOKUP(A91,'CENTRO DE COSTOS'!A:C,2,FALSE) -> 0004-0001 | D91: 8758 | E91: LC-CS-25-000054 | F91: 47346 | G91: ORDEN DE CAMBIO | H91: ATLANTICO | I91: SOLEDAD | J91: PTM DROGUERIA LOS ALMENDROS TR | K91: REDEBAN | L91: FO-25-1392562 | M91: 45888.595 | N91: 45895.569 | P91: CIERRE | Q91: CIERRE | R91: AGREGADOR | S91: COMCARD - PTM | T91: NO_EXITOSO | U91: CB NO ENTREGA EQUIPO | V91: 19/08/2025 SE INTENTA COMUNICACIÓN CON EL NÚMERO 3008154381 SUENA PERO NO HAY CONTACTO. SE INTENTARÁ NUEVAMENTE | 20/08/2025 SE REALIZA GESTIÓN TELEFÓNICA Y CLIENTE INDICA QUE EL SE COMUNICA CON LA LINEA DE ATENCIÓN A EL CLIENTE PARA PROGRAMAR LA ENTREGA DE LOS EQUIPOS. | 26/08/2025 SE REALIZA GESTIÓN TELEFÓNICA Y CLIENTE INDICA QUE EL SE COMUNICA CON LA LINEA DE ATENCIÓN A EL CLIENTE PARA PROGRAMAR LA ENTREGA DE LOS EQUIPOS. | W91: SOPORTE_TELEFÓNICO | X91: 0 | Y91: TIPO I | Z91: =VLOOKUP(D91,TIPOLOGIAS!A:F,5,0) -> TERRESTRE | AA91: DE AGUAS MUÑOZ DAVID JOSE | AB91: 0 | AC91: =IF(AND(W91="SOPORTE_TELEFÓNICO",OR(U91="SIN CONTACTO CON EL CB",U91="NÚMEROS DE CONTACTO ERRADOS")),0,IF(W91="SOPORTE_TELEFÓNICO",'BASE DE LIQUIDACION 2025'!$B$9,IF(Y91="TIPO I",'BASE DE LIQUIDACION 2025'!$C$3,IF(Y91="TIPO II",'BASE DE LIQUIDACION 2025'!$C$4,IF(Y91="TIPO III",'BASE DE LIQUIDACION 2025'!$C$5,'BASE DE LIQUIDACION 2025'!$C$6))))) -> 37904.612 | AD91: =IF(W91="SOPORTE_TELEFÓNICO",AC91,CIERRES!AB91*CIERRES!AC91) -> 37904.612
A92: CALI | B92: =VLOOKUP(A92,'CENTRO DE COSTOS'!A:D,4,FALSE) -> DIEGO FERNANDO HENAO CARDONA | C92: =VLOOKUP(A92,'CENTRO DE COSTOS'!A:C,2,FALSE) -> 0004-0003 | D92: 76109 | E92: LC-CS-25-000106 | F92: 76884 | G92: ORDEN DE CAMBIO | H92: VALLE DEL CAUCA | I92: BUENAVENTURA | J92: BARRIO BAHIA MALAGA | K92: REDEBAN | L92: FO-25-1406218 | M92: 45891.333 | N92: 45895.574 | P92: CIERRE | Q92: RECUPERACION DE EQUIPOS | R92: CB UNO A UNO | S92: CB UNO A UNO | T92: NO_EXITOSO | U92: PARCIAL EXITOSO PTE. DATAFONO | V92: 22/08/2025 EN COMUNICACIÓN CON LA SRA LIZZETH MIREYA ARRECHEA AL NÚMERO 3163776668 NOS CONFIRMA LA SOLICITUD, NOS INDICA QUE LA DIRECCIÓN PARA LA RECOLECCIÓN DE LOS EQUIPOS ES CL 7 # 44 51 BARRIO MIRAFLORES. SE ESCALA PARA VISITA, POR FAVOR LLAMAR ANTES DE DESPLAZARSE | 26/08/2025 SE LLAMA AL CLIENTE Y SE VÁLIDA LA RECUPERACIÓN DE SOLO LA LECTORA EN LA DIRECCIÓN INDICADA EN BUENAVENTURA, SE VISITA EL COMERCIO, RETIRO SOLO LECTORA SYMBOL EN BUEN ESTADO YA EL CLIENTE HABÍA ENTREGADO LOS OTROS EQUIPOS Y PUBLICIDAD | W92: VISITA_TÉCNICA | X92: A16ZZ183 | Y92: TIPO III | Z92: =VLOOKUP(D92,TIPOLOGIAS!A:F,5,0) -> TERRESTRE | AA92: HERRERA MONAR GEOVANNY | AB92: 1 | AC92: =IF(AND(W92="SOPORTE_TELEFÓNICO",OR(U92="SIN CONTACTO CON EL CB",U92="NÚMEROS DE CONTACTO ERRADOS")),0,IF(W92="SOPORTE_TELEFÓNICO",'BASE DE LIQUIDACION 2025'!$B$9,IF(Y92="TIPO I",'BASE DE LIQUIDACION 2025'!$C$3,IF(Y92="TIPO II",'BASE DE LIQUIDACION 2025'!$C$4,IF(Y92="TIPO III",'BASE DE LIQUIDACION 2025'!$C$5,'BASE DE LIQUIDACION 2025'!$C$6))))) -> 222904.07 | AD92: =IF(W92="SOPORTE_TELEFÓNICO",AC92,CIERRES!AB92*CIERRES!AC92) -> 222904.07
A93: BOGOTA | B93: =VLOOKUP(A93,'CENTRO DE COSTOS'!A:D,4,FALSE) -> WILLIAM ASDRUBAL ROZO ROZO | C93: =VLOOKUP(A93,'CENTRO DE COSTOS'!A:C,2,FALSE) -> 0004-0004 | D93: 11001 | E93: LC-CS-25-000149 | F93: 64871 | G93: ORDEN DE CAMBIO | H93: CUNDINAMARCA | I93: BOGOTA | J93: PTM BOGOTA DISTRIBUIDORA DE VI | K93: REDEBAN | L93: FO-25-1424028 | M93: 45895.333 | N93: 45896.381 | P93: CIERRE | Q93: CIERRE | R93: AGREGADOR | S93: COMCARD - PTM | T93: ILOCALIZADO | U93: CB CERRADO - DESOCUPADO | V93: 26/08/2025 EN COMUNICACIÓN CON EL SR WILMER MANUEL CELEITA CLAVIJO AL NÚMERO 3213719899 NOS CONFIRMA LA SOLICITUD, DATOS CORRECTOS. SE ESCALA PARA VISITA, POR FAVOR LLAMAR ANTES DE DESPLAZARSE | 26/08/2025 SE LLEGA A DIRECCIÓN PARA RETIRO DE EQUIPOS LA NO HAY NÚMERO DE TORRE O APARTAMENTO Y NO ES EN LA TIENDA DE INTENTA CONTACTO AL NÚMERO 3213719899 NO CONTESTAN SE DEJA REGISTRO FOTOGRÁFICO | W93: VISITA_TÉCNICA | X93: 0 | Y93: TIPO I | Z93: =VLOOKUP(D93,TIPOLOGIAS!A:F,5,0) -> TERRESTRE | AA93: BUSTOS MORA DIEGO MANUEL | AB93: 1 | AC93: =IF(AND(W93="SOPORTE_TELEFÓNICO",OR(U93="SIN CONTACTO CON EL CB",U93="NÚMEROS DE CONTACTO ERRADOS")),0,IF(W93="SOPORTE_TELEFÓNICO",'BASE DE LIQUIDACION 2025'!$B$9,IF(Y93="TIPO I",'BASE DE LIQUIDACION 2025'!$C$3,IF(Y93="TIPO II",'BASE DE LIQUIDACION 2025'!$C$4,IF(Y93="TIPO III",'BASE DE LIQUIDACION 2025'!$C$5,'BASE DE LIQUIDACION 2025'!$C$6))))) -> 44559.564 | AD93: =IF(W93="SOPORTE_TELEFÓNICO",AC93,CIERRES!AB93*CIERRES!AC93) -> 44559.564
A94: MEDELLIN | B94: =VLOOKUP(A94,'CENTRO DE COSTOS'!A:D,4,FALSE) -> JUAN SEBASTIÁN RÍOS CASTRILLÓN | C94: =VLOOKUP(A94,'CENTRO DE COSTOS'!A:C,2,FALSE) -> 0004-0005 | D94: 5001 | E94: LC-CS-25-000086 | F94: 75311 | G94: ORDEN DE CAMBIO | H94: ANTIOQUIA | I94: MEDELLIN | J94: BARRIO CENTRO MEDELLIN 103 | K94: REDEBAN | L94: FO-25-1419905 | FO-25-1397920 | M94: 45889.583 | N94: 45896.398 | P94: CIERRE | Q94: CIERRE | R94: CB UNO A UNO | S94: CB UNO A UNO | T94: ILOCALIZADO | U94: CB CERRADO - DESOCUPADO | V94: 20/08/2025 EN COMUNICACIÓN CON LA SRA YENIFER VANESA GOMEZ AL NÚMERO 3128807653 NOS CONFIRMA LA SOLICITUD, NOS INDICA QUE LA DIRECCIÓN PARA LA RECOLECCIÓN DE LOS EQUIPOS ES CL 56 41 170 APTO 503. SE ESCALA PARA VISITA | 25/08/2025 YENNIFER GÓMEZ MANIFIESTA QUE PARA MAÑANA SE PODRÍA PASAR POR LOS EQUIPOS, RECLAMARLOS EN PORTERÍA. 27/08/2025 USUARIO NO SE ENCUENTRA, NADIE QUE PUEDA ENTREGAR, SE CONSULTA CON EL CELADOR DE LA PORTERÍA EL CUAL INFORMA NO TENER INFORMACIÓN SOBRE LOS EQUIPOS | W94: VISITA_TÉCNICA | X94: 0 | Y94: TIPO I | Z94: =VLOOKUP(D94,TIPOLOGIAS!A:F,5,0) -> TERRESTRE | AA94: HERNANDEZ CHAVARRIA JUAN CAMILO | AB94: 2 | AC94: =IF(AND(W94="SOPORTE_TELEFÓNICO",OR(U94="SIN CONTACTO CON EL CB",U94="NÚMEROS DE CONTACTO ERRADOS")),0,IF(W94="SOPORTE_TELEFÓNICO",'BASE DE LIQUIDACION 2025'!$B$9,IF(Y94="TIPO I",'BASE DE LIQUIDACION 2025'!$C$3,IF(Y94="TIPO II",'BASE DE LIQUIDACION 2025'!$C$4,IF(Y94="TIPO III",'BASE DE LIQUIDACION 2025'!$C$5,'BASE DE LIQUIDACION 2025'!$C$6))))) -> 44559.564 | AD94: =IF(W94="SOPORTE_TELEFÓNICO",AC94,CIERRES!AB94*CIERRES!AC94) -> 89119.128
A95: BOGOTA | B95: =VLOOKUP(A95,'CENTRO DE COSTOS'!A:D,4,FALSE) -> WILLIAM ASDRUBAL ROZO ROZO | C95: =VLOOKUP(A95,'CENTRO DE COSTOS'!A:C,2,FALSE) -> 0004-0004 | D95: 11001 | E95: LC-CS-25-000090 | F95: 57327 | G95: ORDEN DE CAMBIO | H95: CUNDINAMARCA | I95: BOGOTA | J95: BARRIO PINAR BOGOTA | K95: REDEBAN | L95: FO-25-1420056 | FO-25-1397900 | M95: 45889.583 | N95: 45896.646 | P95: CIERRE | Q95: RECUPERACION DE EQUIPOS | R95: CB UNO A UNO | S95: CB UNO A UNO | T95: NO_EXITOSO | U95: CB NO ENTREGA EQUIPO | V95: 27/08/2025 SE INTENTA COMUNICACIÓN A LOS NÚMEROS 3102951644-3203334439 PERO NO HAY CONTACTO. SE INTENTARÁ NUEVAMENTE | 21/08/2025 EN COMUNICACIÓN CON EL SR DAVID MORENO AL NÚMERO 3102951644 NOS CONFIRMA LA SOLICITUD, DATOS CORRECTOS. SE ESCALA PARA VISITA | 25/08/2025 SE REALIZA VISITA A COMERCIO ATENDIER LA SRA. MARIANA ROJAS QUIEN INDICA QUE LA PERSONA ENCARGADA DE LOS EQUIPOS LOS TIENE BAJO LLAVE, SOLICITA REALIZAR VISITA EL DÍA MIÉRCOLES 27-08-2025. 27/08/2025 SE REALIZA CONTACTO VÍA WHATSAPP CON EL SR. DAVID MORENO QUIEN INFORMA QUE NO ESTÁ EL DÍA DE HOY EN EL COMERCIO, SOLICITA PASAR EL DÍA VIERNES A RECOGER LOS EQUIPOS, SE LE ENVÍA LISTADO DE PLACAS A ENTREGAR. | W95: VISITA_TÉCNICA | X95: TRSZZ894 | Y95: TIPO I | Z95: =VLOOKUP(D95,TIPOLOGIAS!A:F,5,0) -> TERRESTRE | AA95: MURCIA HERNANDEZ HARVEY IGNACIO | AB95: 1 | AC95: =IF(AND(W95="SOPORTE_TELEFÓNICO",OR(U95="SIN CONTACTO CON EL CB",U95="NÚMEROS DE CONTACTO ERRADOS")),0,IF(W95="SOPORTE_TELEFÓNICO",'BASE DE LIQUIDACION 2025'!$B$9,IF(Y95="TIPO I",'BASE DE LIQUIDACION 2025'!$C$3,IF(Y95="TIPO II",'BASE DE LIQUIDACION 2025'!$C$4,IF(Y95="TIPO III",'BASE DE LIQUIDACION 2025'!$C$5,'BASE DE LIQUIDACION 2025'!$C$6))))) -> 44559.564 | AD95: =IF(W95="SOPORTE_TELEFÓNICO",AC95,CIERRES!AB95*CIERRES!AC95) -> 44559.564
A96: BOGOTA | B96: =VLOOKUP(A96,'CENTRO DE COSTOS'!A:D,4,FALSE) -> WILLIAM ASDRUBAL ROZO ROZO | C96: =VLOOKUP(A96,'CENTRO DE COSTOS'!A:C,2,FALSE) -> 0004-0004 | D96: 11001 | E96: TA-25-1034478 | F96: 36751 | G96: ORDEN DE CAMBIO | H96: CUNDINAMARCA | I96: BOGOTA | J96: REVAL ENGATIVA | K96: REDEBAN | L96: FO-25-1433937 | M96: 45896.516 | N96: 45897.319 | P96: CIERRE | Q96: RETIRO VOLUNTARIO | R96: ROBUSTO | S96: REVAL | T96: NO_EXITOSO | U96: PARCIAL EXITOSO PTE. DATAFONO | V96: 27/08/2025 SE REALIZA RETIRO DE DATAFONO,LECTOR DE BARRAS Y PINPAD, NO ENTREGA HUB, LOS EQUIPOS SON BACKUP DEL CB ROBUSTO. | W96: VISITA_TÉCNICA | X96: AB00G058 | Y96: TIPO I | Z96: =VLOOKUP(D96,TIPOLOGIAS!A:F,5,0) -> TERRESTRE | AA96: MURCIA HERNANDEZ HARVEY IGNACIO | AB96: 1 | AC96: =IF(AND(W96="SOPORTE_TELEFÓNICO",OR(U96="SIN CONTACTO CON EL CB",U96="NÚMEROS DE CONTACTO ERRADOS")),0,IF(W96="SOPORTE_TELEFÓNICO",'BASE DE LIQUIDACION 2025'!$B$9,IF(Y96="TIPO I",'BASE DE LIQUIDACION 2025'!$C$3,IF(Y96="TIPO II",'BASE DE LIQUIDACION 2025'!$C$4,IF(Y96="TIPO III",'BASE DE LIQUIDACION 2025'!$C$5,'BASE DE LIQUIDACION 2025'!$C$6))))) -> 44559.564 | AD96: =IF(W96="SOPORTE_TELEFÓNICO",AC96,CIERRES!AB96*CIERRES!AC96) -> 44559.564
A97: BOGOTA | B97: =VLOOKUP(A97,'CENTRO DE COSTOS'!A:D,4,FALSE) -> WILLIAM ASDRUBAL ROZO ROZO | C97: =VLOOKUP(A97,'CENTRO DE COSTOS'!A:C,2,FALSE) -> 0004-0004 | D97: 25398 | E97: LC-CS-25-000116 | F97: 61075 | G97: ORDEN DE CAMBIO | H97: CUNDINAMARCA | I97: LA PEÑA | J97: PTM LA PEÑA PUNTO MODA J.G CR | K97: REDEBAN | L97: FO-25-1410419 | M97: 45891.562 | N97: 45897.641 | P97: CIERRE | Q97: RECUPERACION DE EQUIPOS | R97: AGREGADOR | S97: COMCARD - PTM | T97: ILOCALIZADO | U97: CB CERRADO - DESOCUPADO | V97: 22/08/2025 EN COMUNICACIÓN CON LA SRA ADRIANA BADILLO AL NÚMERO 3215116269 NOS CONFIRMA LA SOLICITUD, NOS INDICA QUE LA DIRECCIÓN PARA LA RECOLECCIÓN DE LOS EQUIPOS ES CALLE 5A 39 194 OFICINA 702 MEDELLIN BARRIO POBLADO | 28/08/2025 SE VISITA MUNICIO LA PEÑA CUNDINAMARCA PARA CIERRE DE PUNTO AL LLEGAR A LA DIRECCIÓN CALLE 5A#39-194 ESTÁ NO EXISTE EN EL MUNICIPIO PUESTO QUE SOLO CUENTA CON DOS CARRERAS SE VÁLIDA CON COMERCIANTES DEL PUEBLO QUIENES DESCONOCEN AL TITULAR DE LA ORDEN SE INTENTA COMUNICACIÓN TELEFÓNICA A LA LÍNEA 3215116269 DONDE CLIENTE CONFIRMA QUE LA DIRECCIÓN ESTÁ BIEN PERO PERTENECE A MEDELLÍN Y LOS EQUIPOS LOS POSEE PTM , SE PROCEDE A DILIGENCIA FORMATO ILOCALIZABLE Y SE FINALIZA ACTIVIDAD POR DIRECCIÓN NO EXISTENTE | W97: VISITA_TÉCNICA | X97: 0 | Y97: TIPO III | Z97: =VLOOKUP(D97,TIPOLOGIAS!A:F,5,0) -> TERRESTRE | AA97: ROMERO ROJAS BREIDY JHOHAN | AB97: 1 | AC97: =IF(AND(W97="SOPORTE_TELEFÓNICO",OR(U97="SIN CONTACTO CON EL CB",U97="NÚMEROS DE CONTACTO ERRADOS")),0,IF(W97="SOPORTE_TELEFÓNICO",'BASE DE LIQUIDACION 2025'!$B$9,IF(Y97="TIPO I",'BASE DE LIQUIDACION 2025'!$C$3,IF(Y97="TIPO II",'BASE DE LIQUIDACION 2025'!$C$4,IF(Y97="TIPO III",'BASE DE LIQUIDACION 2025'!$C$5,'BASE DE LIQUIDACION 2025'!$C$6))))) -> 222904.07 | AD97: =IF(W97="SOPORTE_TELEFÓNICO",AC97,CIERRES!AB97*CIERRES!AC97) -> 222904.07
A98: APARTADO | B98: =VLOOKUP(A98,'CENTRO DE COSTOS'!A:D,4,FALSE) -> JUAN SEBASTIÁN RÍOS CASTRILLÓN | C98: =VLOOKUP(A98,'CENTRO DE COSTOS'!A:C,2,FALSE) -> 0004-0005 | D98: 5045 | E98: LC-CS-25-000139 | F98: 41725 | G98: ORDEN DE CAMBIO | H98: ANTIOQUIA | I98: APARTADO | J98: BARRIO LAURELES APARTADO | K98: REDEBAN | L98: FO-25-1435254 | FO-25-1424276 | M98: 45894.333 | N98: 45897.659 | P98: CIERRE | Q98: CIERRE | R98: CB UNO A UNO | S98: CB UNO A UNO | T98: NO_EXITOSO | U98: CB NO ENTREGA EQUIPO | V98: 26/08/2025 EN COMUNICACIÓN CON EL SR ELOY CÁRDENAS ARTEAGA AL NÚMERO 3135279633 NOS CONFIRMA LA SOLICITUD, DATOS CORRECTOS. SE ESCALA PARA VISITA 28/08/2025 CLIENTE INDICA QUE YA ENTREGO DATAFONO CON SUS PERIFECOS | W98: VISITA_TÉCNICA | X98: AA0UZ924 | Y98: TIPO I | Z98: =VLOOKUP(D98,TIPOLOGIAS!A:F,5,0) -> TERRESTRE | AA98: CASTRO HENAO DANIEL ESTEBAN | AB98: 1 | AC98: =IF(AND(W98="SOPORTE_TELEFÓNICO",OR(U98="SIN CONTACTO CON EL CB",U98="NÚMEROS DE CONTACTO ERRADOS")),0,IF(W98="SOPORTE_TELEFÓNICO",'BASE DE LIQUIDACION 2025'!$B$9,IF(Y98="TIPO I",'BASE DE LIQUIDACION 2025'!$C$3,IF(Y98="TIPO II",'BASE DE LIQUIDACION 2025'!$C$4,IF(Y98="TIPO III",'BASE DE LIQUIDACION 2025'!$C$5,'BASE DE LIQUIDACION 2025'!$C$6))))) -> 44559.564 | AD98: =IF(W98="SOPORTE_TELEFÓNICO",AC98,CIERRES!AB98*CIERRES!AC98) -> 44559.564
A99: PEREIRA | B99: =VLOOKUP(A99,'CENTRO DE COSTOS'!A:D,4,FALSE) -> DIEGO FERNANDO HENAO CARDONA | C99: =VLOOKUP(A99,'CENTRO DE COSTOS'!A:C,2,FALSE) -> 0004-0002 | D99: 63594 | E99: LC-CS-25-000151 | F99: 67248 | G99: ORDEN DE CAMBIO | H99: QUINDIO | I99: QUIMBAYA | J99: DISTRICOL RC RODRIGUEZ LACTEOS | K99: REDEBAN | L99: FO-25-1424075 | M99: 45895.333 | N99: 45898.456 | P99: CIERRE | Q99: CIERRE | R99: AGREGADOR | S99: DISTRICOL | T99: NO_EXITOSO | U99: CB NO ENTREGA EQUIPO | V99: 26/08/2025 SE INTENTA COMUICACIÓN AL NÚMERO 3124522720 SE ENCUENTRA APAGADO. SE INTENTARÁ NUEVAMENTE | 26/08/2025 SE INTENTA COMUICACIÓN AL NÚMERO 3124522720 SE ENCUENTRA APAGADO. SE INTENTARÁ NUEVAMENTE | 26/08/2025 SE INTENTA COMUICACIÓN AL NÚMERO 3124522720 SE ENCUENTRA APAGADO | 29/08/2025 SE VISITA DIRECCIÓN SE VÁLIDA CON PROPIETARIO NUEVO HE INDICA QUE EL ANTIGUO DUEÑO YA HABÍA ENTREGADO LOS EQUIPOS, SE LLAMA AL CONTACTO Y EL CLIENTE COMENTA QUE YA LOS EQUIPOS LOS HABÍA ENTREGADO AL ENCARGADO DE DISTRICOL. | W99: VISITA_TÉCNICA | X99: AAJ05702 | Y99: TIPO II | Z99: =VLOOKUP(D99,TIPOLOGIAS!A:F,5,0) -> TERRESTRE | AA99: SANCHEZ SOLORZANO JUAN SEBASTIAN | AB99: 1 | AC99: =IF(AND(W99="SOPORTE_TELEFÓNICO",OR(U99="SIN CONTACTO CON EL CB",U99="NÚMEROS DE CONTACTO ERRADOS")),0,IF(W99="SOPORTE_TELEFÓNICO",'BASE DE LIQUIDACION 2025'!$B$9,IF(Y99="TIPO I",'BASE DE LIQUIDACION 2025'!$C$3,IF(Y99="TIPO II",'BASE DE LIQUIDACION 2025'!$C$4,IF(Y99="TIPO III",'BASE DE LIQUIDACION 2025'!$C$5,'BASE DE LIQUIDACION 2025'!$C$6))))) -> 134410.88 | AD99: =IF(W99="SOPORTE_TELEFÓNICO",AC99,CIERRES!AB99*CIERRES!AC99) -> 134410.88
A100: BOGOTA | B100: =VLOOKUP(A100,'CENTRO DE COSTOS'!A:D,4,FALSE) -> WILLIAM ASDRUBAL ROZO ROZO | C100: =VLOOKUP(A100,'CENTRO DE COSTOS'!A:C,2,FALSE) -> 0004-0004 | D100: 11001 | E100: LC-CS-25-000157 | F100: 36751 | G100: ORDEN DE CAMBIO | H100: CUNDINAMARCA | I100: BOGOTA | J100: REVAL ENGATIVA | K100: REDEBAN | L100: FO-25-1430297 | M100: 45895.333 | N100: 45898.528 | P100: CIERRE | Q100: RECUPERACION DE EQUIPOS | R100: ROBUSTO | S100: REVAL | T100: SOLICITUD_CANCELADA | U100: NO TIENE INVENTARIO ACTIVO | V100: 27/08/2025 EN COMUNICACIÓN CON LA SRA YUDY ORTIZ AL NÚMERO 3208956660 NOS CONFIRMA LA SOLICITUD, DATOS CORRECTOS. SE ESCALA PARA VISITA, POR FAVOR LLAMAR ANTES DE DESPLAZARSE | 28/08/2025 SE VISITA COMERCIO CB BANCOLOMBIA ROBUSTO PERO LA SRA YUDI INDICA QUE EL DÍA ANTERIOR (27 DE AGOSTO 2025) EL TÉCNICO HARVEY MURCIA REALIZO LA ACTUALIZACIÓN DE LOS EQUIPOS POR LO QUE ÉL YA RETIRO TODOS LOS EQUIPOS QUE TENÍAN PARA DEVOLVER DE ESE PUNTO, SE TOMAN EVIDENCIAS DE LA VISITA Y NOS RETIRAMOS DEL PUNTO, NO SE MANIPULAN EQUIPOS. | W100: VISITA_TÉCNICA | X100: NONE | Y100: TIPO I | Z100: =VLOOKUP(D100,TIPOLOGIAS!A:F,5,0) -> TERRESTRE | AA100: VEGA MANRIQUE JONATAN MAURICIO | AB100: 1 | AC100: =IF(AND(W100="SOPORTE_TELEFÓNICO",OR(U100="SIN CONTACTO CON EL CB",U100="NÚMEROS DE CONTACTO ERRADOS")),0,IF(W100="SOPORTE_TELEFÓNICO",'BASE DE LIQUIDACION 2025'!$B$9,IF(Y100="TIPO I",'BASE DE LIQUIDACION 2025'!$C$3,IF(Y100="TIPO II",'BASE DE LIQUIDACION 2025'!$C$4,IF(Y100="TIPO III",'BASE DE LIQUIDACION 2025'!$C$5,'BASE DE LIQUIDACION 2025'!$C$6))))) -> 44559.564 | AD100: =IF(W100="SOPORTE_TELEFÓNICO",AC100,CIERRES!AB100*CIERRES!AC100) -> 44559.564
...

Sheet TIPOLOGIAS
A1: COD. CIUDAD | B1: CIUDAD | C1: DEPARTAMENTO | D1: DESDE DONDE SE ATIENDE | E1: TIPO DE TRAYECTO NUEVO | F1: TIPOLOGIA NUEVA
A2: 91430 | B2: LA VICTORIA | C2: AMAZONAS | D2: BOGOTA | E2: AEREO | F2: TIPO IV ESPECIAL
A3: 91669 | B3: PUERTO SANTANDER | C3: AMAZONAS | D3: BOGOTA | E3: AEREO | F3: TIPO IV ESPECIAL
A4: 91263 | B4: EL ENCANTO | C4: AMAZONAS | D4: BOGOTA | E4: AEREO | F4: TIPO IV ESPECIAL
A5: 91405 | B5: LA CHORRERA | C5: AMAZONAS | D5: BOGOTA | E5: AEREO | F5: TIPO IV ESPECIAL
A6: 91407 | B6: LA PEDRERA | C6: AMAZONAS | D6: BOGOTA | E6: AEREO | F6: TIPO IV ESPECIAL
A7: 91001 | B7: LETICIA | C7: AMAZONAS | D7: BOGOTA | E7: AEREO | F7: TIPO IV ESPECIAL
A8: 91460 | B8: MIRITI - PARANA | C8: AMAZONAS | D8: BOGOTA | E8: AEREO | F8: TIPO IV ESPECIAL
A9: 91530 | B9: PUERTO ALEGRIA | C9: AMAZONAS | D9: BOGOTA | E9: AEREO | F9: TIPO IV ESPECIAL
A10: 91536 | B10: PUERTO ARICA | C10: AMAZONAS | D10: BOGOTA | E10: AEREO | F10: TIPO IV ESPECIAL
A11: 91540 | B11: PUERTO NARIÑO | C11: AMAZONAS | D11: BOGOTA | E11: AEREO | F11: TIPO IV ESPECIAL
A12: 91798 | B12: TARAPACA | C12: AMAZONAS | D12: BOGOTA | E12: AEREO | F12: TIPO IV ESPECIAL
A13: 5055 | B13: ARGELIA | C13: ANTIOQUIA | D13: MEDELLIN | E13: TERRESTRE | F13: TIPO IV
... A1124: 23682 | B1124: SAN JOSE DE URE | C1124: CORDOBA | D1124: MONTERIA | E1124: TERRESTRE | F1124: TIPO III

Sheet CENTRO DE COSTOS
A1: CIUDAD | B1: CENTRO_COSTO | C1: DESCRIPCION | D1: COORDINADOR
A2: APARTADO | B2: 0004-0005 | C2: Redeban Noroccidente (Medellín) | D2: JUAN SEBASTIÁN RÍOS CASTRILLÓN
A3: BARRANQUILLA | B3: 0004-0001 | C3: Redeban Costa (Barranqullla) | D3: JOSE MAURICIO HERNANDEZ ROJAS
A4: BOGOTA | B4: 0004-0004 | C4: Redeban Centro ( Bogotá) | D4: WILLIAM ASDRUBAL ROZO ROZO
A5: BUCARAMANGA | B5: 0004-0008 | C5: Redeban Santander | D5: MIGUEL JULIÁN HERNÁNDEZ GUARÍN
A6: CALI | B6: 0004-0003 | C6: Redeban Suroccidente (Cali) | D6: DIEGO FERNANDO HENAO CARDONA
A7: CARTAGENA | B7: 0004-0001 | C7: Redeban Costa (Barranqullla) | D7: JOSE MAURICIO HERNANDEZ ROJAS
A8: CUCUTA | B8: 0004-0008 | C8: Redeban Santander | D8: MIGUEL JULIÁN HERNÁNDEZ GUARÍN
A9: FLORENCIA | B9: 0004-0007 | C9: Redeban Oriente (Otros) | D9: KEVIN ALEXIS CORZO BUSTOS
A10: IBAGUE | B10: 0004-0007 | C10: Redeban Oriente (Otros) | D10: KEVIN ALEXIS CORZO BUSTOS
A11: MANIZALES | B11: 0004-0002 | C11: Redeban Eje Cafetero (Pereira) | D11: DIEGO FERNANDO HENAO CARDONA
A12: MEDELLIN | B12: 0004-0005 | C12: Redeban Noroccidente (Medellín) | D12: JUAN SEBASTIÁN RÍOS CASTRILLÓN
... A23: YOPAL | B23: 0004-0007 | C23: Redeban Oriente (Otros) | D23: KEVIN ALEXIS CORZO BUSTOS
