Workbook

Sheet RESUMEN
A1: FACTURACIÓN ACTIVIDADES CORRESPONSAL BANCARIO WOMPI | E1: FACTURACIÓN SERVICIOS ADICIONALES
A2: 1 AL 30 DE NOVIEMBRE 2025 | E2: 1 AL 30 DE NOVIEMBRE 2025
A4: CONCEPTOS | B4: CANTIDAD | C4: TOTAL | E4: CONCEPTOS | F4: CANTIDAD | G4: VALOR UNITARIO | H4: TOTAL
A5: Aperturas | B5: =COUNTA(APERTURAS!A:A)-1 -> 133 | C5: =APERTURAS!Z135 -> 63463121
A6: Incidentes | B6: =COUNTA(INCIDENTES!A:A)-1 -> 655 | C6: =INCIDENTES!AA657 -> 44909577
A7: OC Papelería | B7: =COUNTA('OC PAPALERÍA'!A:A)-1 -> 2292 | C7: ='OC PAPALERÍA'!AA2294 -> 77876087
A8: OC Cierres | B8: =COUNTA('OC CIERRES'!A:A)-1 -> 58 | C8: ='OC CIERRES'!AA60 -> 13482704
A9: OC Publicidad | B9: =COUNTA('OC PUBLICIDAD'!A:A)-1 -> 58 | C9: ='OC PUBLICIDAD'!AA60 -> 10061454
A10: OC Traslados | B10: =COUNTA('OC TRASLADOS'!A:A)-1 -> 11 | C10: ='OC TRASLADOS'!AA13 -> 899975 | H10: =SUM(H5:H9) -> 0
A11: Servicios Adicionales | C11: =H10 -> 0
A12: SUBTOTAL | C12: =SUM(C5:C11) -> 210692918
A13: Iva | C13: =C12*0.19 -> 40031654
A14: TOTAL | C14: =SUM(C12:C13) -> 2.5072457e+08

Sheet TD
A1: ACTIVIDAD | B1: APERTURA
A3: DESCRIPCION CENTRO DE COSTOS | B3: Suma de VALOR TOTAL | C3: CENTRO DE COSTOS | D3: VALOR
A4: Wompi Centro | B4: 14539661 | C4: =A4 -> Wompi Centro | D4: =B4 -> 14539661 | H4: CENTRO DE COSTOS | I4: Suma de VALOR
A5: Wompi Costa | B5: 9031931 | C5: =A5 -> Wompi Costa | D5: =B5 -> 9031931 | H5: Wompi Centro | I5: 36483158
A6: Wompi Eje Cafetero | B6: 7686309 | C6: =A6 -> Wompi Eje Cafetero | D6: =B6 -> 7686309 | H6: Wompi Costa | I6: 26943227
A7: Wompi Noroccidente | B7: 5835873 | C7: =A7 -> Wompi Noroccidente | D7: =B7 -> 5835873 | H7: Wompi Eje Cafetero | I7: 15752402
A8: Wompi Oriente | B8: 8678589 | C8: =A8 -> Wompi Oriente | D8: =B8 -> 8678589 | H8: Wompi Noroccidente | I8: 32205102
A9: Wompi Santander | B9: 14025509 | C9: =A9 -> Wompi Santander | D9: =B9 -> 14025509 | H9: Wompi Oriente | I9: 26764391
A10: Wompi Suroccidente | B10: 15031132 | C10: =A10 -> Wompi Suroccidente | D10: =B10 -> 15031132 | H10: Wompi Santander | I10: 34579886
A11: Total general | B11: 74829004 | H11: Wompi Suroccidente | I11: 38215689
H12: Total general | I12: 210943855
A15: ACTIVIDAD | B15: INCIDENTE
A17: DESCRIPCION CENTRO DE COSTOS | B17: Suma de VALOR TOTAL
A18: Wompi Centro | B18: 7149102 | C18: =A18 -> Wompi Centro | D18: =B18 -> 7149102
A19: Wompi Costa | B19: 6553224 | C19: =A19 -> Wompi Costa | D19: =B19 -> 6553224
A20: Wompi Eje Cafetero | B20: 2103611 | C20: =A20 -> Wompi Eje Cafetero | D20: =B20 -> 2103611
A21: Wompi Noroccidente | B21: 5966201 | C21: =A21 -> Wompi Noroccidente | D21: =B21 -> 5966201
A22: Wompi Oriente | B22: 5627328 | C22: =A22 -> Wompi Oriente | D22: =B22 -> 5627328
A23: Wompi Santander | B23: 5997673 | C23: =A23 -> Wompi Santander | D23: =B23 -> 5997673
A24: Wompi Suroccidente | B24: 8193714 | C24: =A24 -> Wompi Suroccidente | D24: =B24 -> 8193714
A25: Total general | B25: 41590853
A29: ACTIVIDAD | B29: ORDEN DE CAMBIO
A30: SOLICITUD | B30: ROLLOS
A32: DESCRIPCION CENTRO DE COSTOS | B32: Suma de VALOR TOTAL
A33: Wompi Centro | B33: 12738595 | C33: =A33 -> Wompi Centro | D33: =B33 -> 12738595
A34: Wompi Costa | B34: 10005932 | C34: =A34 -> Wompi Costa | D34: =B34 -> 10005932
A35: Wompi Eje Cafetero | B35: 5184656 | C35: =A35 -> Wompi Eje Cafetero | D35: =B35 -> 5184656
A36: Wompi Noroccidente | B36: 16237033 | C36: =A36 -> Wompi Noroccidente | D36: =B36 -> 16237033
A37: Wompi Oriente | B37: 9499872 | C37: =A37 -> Wompi Oriente | D37: =B37 -> 9499872
A38: Wompi Santander | B38: 12610038 | C38: =A38 -> Wompi Santander | D38: =B38 -> 12610038
A39: Wompi Suroccidente | B39: 11965127 | C39: =A39 -> Wompi Suroccidente | D39: =B39 -> 11965127
A40: Total general | B40: 78241253
A44: ACTIVIDAD | B44: ORDEN DE CAMBIO
A45: SOLICITUD | B45: CIERRE
A47: DESCRIPCION CENTRO DE COSTOS | B47: Suma de VALOR TOTAL
A48: Wompi Centro | B48: 1362264 | C48: =A48 -> Wompi Centro | D48: =B48 -> 1362264
A49: Wompi Costa | B49: 203532 | C49: =A49 -> Wompi Costa | D49: =B49 -> 203532
A50: Wompi Noroccidente | B50: 2914958 | C50: =A50 -> Wompi Noroccidente | D50: =B50 -> 2914958
A51: Wompi Oriente | B51: 2228348 | C51: =A51 -> Wompi Oriente | D51: =B51 -> 2228348
A52: Wompi Santander | B52: 1636106 | C52: =A52 -> Wompi Santander | D52: =B52 -> 1636106
A53: Wompi Suroccidente | B53: 521932 | C53: =A53 -> Wompi Suroccidente | D53: =B53 -> 521932
A54: Wompi Eje Cafetero | B54: 203532 | C54: =A54 -> Wompi Eje Cafetero | D54: =B54 -> 203532
A55: Total general | B55: 9070672
A58: ACTIVIDAD | B58: ORDEN DE CAMBIO
A59: SOLICITUD | B59: PUBLICIDAD
A61: DESCRIPCION CENTRO DE COSTOS | B61: Suma de VALOR TOTAL
A62: Wompi Centro | B62: 574634 | C62: =A62 -> Wompi Centro | D62: =B62 -> 574634
A63: Wompi Costa | B63: 1148608 | C63: =A63 -> Wompi Costa | D63: =B63 -> 1148608
A64: Wompi Noroccidente | B64: 670123 | C64: =A64 -> Wompi Noroccidente | D64: =B64 -> 670123
A65: Wompi Oriente | B65: 670803 | C65: =A65 -> Wompi Oriente | D65: =B65 -> 670803
A66: Wompi Santander | B66: 191658 | C66: =A66 -> Wompi Santander | D66: =B66 -> 191658
A67: Wompi Eje Cafetero | B67: 574294 | C67: =A67 -> Wompi Eje Cafetero | D67: =B67 -> 574294
A68: Wompi Suroccidente | B68: 935290 | C68: =A68 -> Wompi Suroccidente | D68: =B68 -> 935290
A69: Total general | B69: 4765410
A73: ACTIVIDAD | B73: ORDEN DE CAMBIO
A74: SOLICITUD | B74: TRASLADO
A76: DESCRIPCION CENTRO DE COSTOS | B76: Suma de VALOR TOTAL
A77: Wompi Centro | B77: 118902 | C77: =A77 -> Wompi Centro | D77: =B77 -> 118902
A78: Wompi Noroccidente | B78: 580914 | C78: =A78 -> Wompi Noroccidente | D78: =B78 -> 580914
A79: Wompi Oriente | B79: 59451 | C79: =A79 -> Wompi Oriente | D79: =B79 -> 59451
A80: Wompi Santander | B80: 118902 | C80: =A80 -> Wompi Santander | D80: =B80 -> 118902
A81: Wompi Suroccidente | B81: 1568494 | C81: =A81 -> Wompi Suroccidente | D81: =B81 -> 1568494
A82: Total general | B82: 2446663

Sheet TARIFAS 2025
A1: TIPO ACTIVIDAD | B1: PRINCIPAL | C1: INTERMEDIA | D1: LEJANA
A2: ENVIO DATAFONO | B2: 39706 | C2: 49474 | D2: 51412
A3: ENVIO VISITA DATAFONO | B3: 59451 | C3: 182458 | D3: 462012
A4: INSTALACIÓN DATAFONO | B4: 130010 | C4: 222882 | D4: 474719
A5: INSTALACIÓN DATAFONO Y MATERIAL POP | B5: 367716 | C5: 488953 | D5: 598334
A6: LOGISTICA INVERSA DATAFONO | B6: 49274 | C6: 188826 | D6: 454487
A7: LOGISTICA INVERSA MATERIAL POP | B7: 95829 | C7: 287147 | D7: 551974
A8: SOPORTE TÉCNICO | B8: 51282 | C8: 172989 | D8: 452148
A9: ORDENES DE CAMBIO_CIERRES DESTRUCCIÓN DE POP EN SITIO | B9: 71290 | C9: 206527 | D9: 602411
A10: ORDENES DE CAMBIO_CIERRES RETORNO DE POP A BODEGA | B10: 101766 | C10: 318400 | D10: 707110
A11: ORDENES DE CAMBIO_PAPELERÍA | B11: 31419 | C11: 36351 | D11: 40250
A12: ORDENES DE CAMBIO_PUBLICIDAD | B12: 95829 | C12: 287147 | D12: 551974
A13: ORDENES DE CAMBIO_OTRAS | B13: 59451 | C13: 182458 | D13: 462012
A14: SOPORTE TELEFÓNICO | B14: 22000 | C14: 22000 | D14: 22000
A16: SERVICIOS ADICIONALES EN SITIO | B16: Estos valores aplican en las actividades que se requieran, previa autorización de Wompi.
A17: Acometida eléctrica 3N12 Cu THHN (ml) | B17: 21000 | C17: 21000 | D17: 21000
A18: Acometida de datos (ML) | B18: 16235 | C18: 16235 | D18: 16235
A19: Switch | B19: 257392 | C19: 257392 | D19: 257392
A20: Router | B20: 306552 | C20: 306552 | D20: 306552

Sheet CENTROS DE COSTOS
A1: CIUDAD | B1: CENTRO_COSTO | C1: DESCRIPCION CENTRO DE COSTOS | D1: COORDINADOR DE ZONA
A2: APARTADO | B2: 0036-0005 | C2: Wompi Noroccidente | D2: JUAN SEBASTIÁN RÍOS CASTRILLÓN
A3: BARRANQUILLA | B3: 0036-0001 | C3: Wompi Costa | D3: JOSE MAURICIO HERNANDEZ ROJAS
A4: BOGOTA | B4: 0036-0004 | C4: Wompi Centro | D4: WILLIAM ASDRUBAL ROZO ROZO
A5: BUCARAMANGA | B5: 0036-0007 | C5: Wompi Santander | D5: MIGUEL JULIÁN HERNÁNDEZ GUARÍN
A6: CALI | B6: 0036-0003 | C6: Wompi Suroccidente | D6: DIEGO FERNANDO HENAO CARDONA
A7: CARTAGENA | B7: 0036-0001 | C7: Wompi Costa | D7: JOSE MAURICIO HERNANDEZ ROJAS
A8: CUCUTA | B8: 0036-0007 | C8: Wompi Santander | D8: MIGUEL JULIÁN HERNÁNDEZ GUARÍN
A9: FLORENCIA | B9: 0036-0006 | C9: Wompi Oriente | D9: KEVIN ALEXIS CORZO BUSTOS
A10: IBAGUE | B10: 0036-0006 | C10: Wompi Oriente | D10: KEVIN ALEXIS CORZO BUSTOS
A11: MANIZALES | B11: 0036-0002 | C11: Wompi Eje Cafetero | D11: DIEGO FERNANDO HENAO CARDONA
A12: MEDELLIN | B12: 0036-0005 | C12: Wompi Noroccidente | D12: JUAN SEBASTIÁN RÍOS CASTRILLÓN
... A23: YOPAL | B23: 0036-0006 | C23: Wompi Oriente | D23: KEVIN ALEXIS CORZO BUSTOS

Sheet TIPOLOGIA
A1: COD. CIUDAD | B1: CIUDAD | C1: DEPARTAMENTO | D1: DESDE DONDE SE ATIENDE | E1: TIPOLOGIA WOMPI | F1: TIPO DE TRAYECTO | G1: BODEGA WOMPI
A2: 91430 | B2: LA VICTORIA | C2: AMAZONAS | D2: BOGOTA | E2: LEJANA | F2: AEREO | G2: BOGOTA
A3: 91669 | B3: PUERTO SANTANDER | C3: AMAZONAS | D3: BOGOTA | E3: LEJANA | F3: AEREO | G3: BOGOTA
A4: 91263 | B4: EL ENCANTO | C4: AMAZONAS | D4: BOGOTA | E4: LEJANA | F4: AEREO | G4: BOGOTA
A5: 91405 | B5: LA CHORRERA | C5: AMAZONAS | D5: BOGOTA | E5: LEJANA | F5: AEREO | G5: BOGOTA
A6: 91407 | B6: LA PEDRERA | C6: AMAZONAS | D6: BOGOTA | E6: LEJANA | F6: AEREO | G6: BOGOTA
A7: 91001 | B7: LETICIA | C7: AMAZONAS | D7: BOGOTA | E7: LEJANA | F7: AEREO | G7: BOGOTA
A8: 91460 | B8: MIRITI - PARANA | C8: AMAZONAS | D8: BOGOTA | E8: LEJANA | F8: AEREO | G8: BOGOTA
A9: 91530 | B9: PUERTO ALEGRIA | C9: AMAZONAS | D9: BOGOTA | E9: LEJANA | F9: AEREO | G9: BOGOTA
A10: 91536 | B10: PUERTO ARICA | C10: AMAZONAS | D10: BOGOTA | E10: LEJANA | F10: AEREO | G10: BOGOTA
A11: 91540 | B11: PUERTO NARIÑO | C11: AMAZONAS | D11: BOGOTA | E11: LEJANA | F11: AEREO | G11: BOGOTA
A12: 91798 | B12: TARAPACA | C12: AMAZONAS | D12: BOGOTA | E12: LEJANA | F12: AEREO | G12: BOGOTA
A13: 5055 | B13: ARGELIA | C13: ANTIOQUIA | D13: MEDELLIN | E13: LEJANA | F13: TERRESTRE | G13: MEDELLIN
... A1124: 23682 | B1124: SAN JOSE DE URE | C1124: CORDOBA | D1124: MONTERIA | E1124: LEJANA | F1124: TERRESTRE | G1124: MONTERIA

Sheet APERTURAS
A1: CIUDAD SEDE | B1: CENTRO_COSTO | C1: DESCRIPCION CENTRO DE COSTOS | D1: CÓDIGO DANE | E1: TA/CODIGO ACTIVIDAD | F1: CODIGO CB | G1: ACTIVIDAD | H1: TIPO DE APERTURA | I1: DEPARTAMENTO | J1: CIUDAD | K1: NOMBRE DEL CB | L1: RED | M1: FO | N1: FECHA LISTA | O1: FECHA ULTIMA ACTUALIZACION | P1: ESTADO | Q1: OBSERVACIONES CLIENTE | R1: FORMA DE ATENCIÓN | S1: TERMINALES | T1: TIPOLOGIA | U1: TIPO DE TRAYECTO | V1: NOMBRE DEL TECNICO | W1: DIAS DE VISITA | X1: VALOR DIAS ACTIVIDAD | Y1: % FACTURACIÓN | Z1: VALOR TOTAL
A2: MONTERIA | B2: =VLOOKUP(A2,'CENTROS DE COSTOS'!A:D,2,0) -> 0036-0001 | C2: =VLOOKUP(A2,'CENTROS DE COSTOS'!A:D,3,0) -> Wompi Costa | D2: 23001 | E2: TA-25-1046209 | F2: 81286 | G2: APERTURA | H2: CB CRECIMIENTO - NUEVO | I2: CORDOBA | J2: MONTERIA | K2: BARRIO MONTERIA MODERNO MONTERIA 2 | L2: WOMPI | M2: FO-25-1654602 | N2: 45901 | O2: 45973 | P2: EJECUTADO | Q2: 12-09 SE REALIZA LLAMADA AL CLIENTE, SE HABLA CON BLAS ALFONSO VILLADIEGO DOMINGUEZ EL CUAL INDICA QUE EL CORREO CON LAS CREDENCIALES POR PARTE DE WOMPI AUN NO HA LLEGADO 22-09 SE REALIZA LLAMADA AL CLIENTE, SE HABLA CON EL SR BLAS ALFONSO VILLADIEGO DOMINGUEZ EL CUAL IDNICA QUE EL CORREO ESTA ERRADO, EL CORREO CORRECTO ES ENERGIAINTEGRALDELASABANA@GMAIL.COM 08-10 SE REALIZA LLAMADA AL CLIENTE, SE HABLA CON LA SRA SERY RAMOS. SE VALIDA DIRECCIÓN OK, CANAL OK, DISPONIBILIDAD TOTAL, LLAMAR EL DÍA LA INSTALACIÓN PARA CONFIRMAR VISITA, AVISO EXTERIOR ALTURA APROX 2 METROS; CREDENCIALES: SI 9/10/2025 SE ENVIO ESTE CASO DE APERTURA WOMPI, DONDE EL NOMBRE DE COMERCIO NO ES EL MISMO DEL AVISO PUBLICITARIO, SIN EMBARGO SI ES EL MISMO OBJETIVO COMERCIAL, LA DIRECCION COINCIDE Y LA CÁMARA DE COMERCIO TAMBIEN TIENE EL MISMO NOMBRE DE LISTA DE CHEQUEO. NOMBRE ESTABLECIMIENTO CÁMARA DE COMERCIO: ELECTROREDES DEL SINU NOMBRE AVISO PUBLICITARIO: ENERGIA INTEGRAL DE LA SABANA |RESPUESTA DE WOMPI: LO IMPORTANTE ES GARANTIZAR QUE LA DIRECCIÓN COINCIDA, SI ESTA COINCIDE PODEMOS INSTALAR RECOMENDANDO AL PUNTO QUE REALICE LA ACTUALIZACIÓN EN CÁMARA DE COMERCIO O EN EL AVISO 9/10/2025 SE VISITA COMERCIO, CB INDICA QUE EL CORREO DE REGISTRO SE ENCUENTRA ERRÓNEO POR LO CUAL NO HAN PODIDO CREAR CREDENCIALES DE ACCESO, SE ESCALA A COORDINADOR Y SE LE INDICA AL COMERCIO QUE DEBE HACER ACTUALIZACIÓN EN LÍNEA 018000. | SE ESTABLECE COMUNICACIÓN DE NUEVO CON EL USUARIO EL CUAL INDICA QUE AUN NO TIENE CORREO POR PARTE DE WOMPI - COMUNICACIÓN POR WPP | 11-11 SE REALIZA LLAMADA AL CLIENTE, SE HABLA CON EL SR BLAS ALFONSO VILLADIEGO DOMINGUEZ SE VALIDA DIRECCIÓN OK, CANAL OK, DISPONIBILIDAD TOTAL, USUARIO Y CONTRASEÑA WOMPI OK, LLAMAR EL DÍA LA INSTALACIÓN PARA CONFIRMAR VISITA, AVISO EXTERIOR ALTURA - 2 METROS (COMUNICACION POR WPP) | 12-11 SE REALIZA INSTALACIÓN DE CORRESPONSAL, SE INSTALA EQUIPO CON PRUEBAS EXITOSAS, SE CAPACITA Y SE EVALÚA AL CLIENTE, SE INSTALA PUBLICIDAD COMPLETA, CB QUEDA OPERATIVO. USUARIO SOMOS BANCOLOMBIA ACTIVO | R2: VISITA_TÉCNICA | S2: 254UMD4X8473 | T2: PRINCIPAL | U2: TERRESTRE | V2: CASSIANI PEREZ RAUL RAMIRO | W2: 2 | X2: =IF(T2="PRINCIPAL",'TARIFAS 2025'!$B$5,IF(T2="INTERMEDIA",'TARIFAS 2025'!$C$5,IF(T2="LEJANA",'TARIFAS 2025'!$D$5))) -> 367716 | Y2: 1 | Z2: =X2*W2*Y2 -> 735432
A3: BUCARAMANGA | B3: =VLOOKUP(A3,'CENTROS DE COSTOS'!A:D,2,0) -> 0036-0007 | C3: =VLOOKUP(A3,'CENTROS DE COSTOS'!A:D,3,0) -> Wompi Santander | D3: 81065 | E3: TA-25-1246641 | F3: 81750 | G3: APERTURA | H3: CB CRECIMIENTO - NUEVO | I3: ARAUCA | J3: ARAUQUITA | K3: BARRIO SEIS DE ENERO ARAUQUITA | L3: WOMPI | M3: FO-25-1748405 | N3: 45932 | O3: 45967 | P3: EJECUTADO | Q3: 10-10 SE REALIZA LLAMADA AL CLIENTE, SE HABLA CON LA SRA ALBA ALFONSO NIÑO LA CUAL INDICA QUE AUN NO TIENE EL CORREO POR PARTE DE WOMPI | 28/10/2025 EN NUEVA COMUNICACION CON LA USUARIA INDICA QUE YA TIENE EL CORREO POR PARTE DE WOMPÍ, ALTURA DEL AVISO 1 MT | 06-11 SE REALIZA INSTALACIÓN DE CORRESPONSAL, SE INSTALA EQUIPO CON PRUEBAS EXITOSAS, SE CAPACITA Y SE EVALÚA AL CLIENTE, SE INSTALA PUBLICIDAD COMPLETA, CB QUEDA OPERATIVO. USUARIO SOMOS BANCOLOMBIA ACTIVO | R3: VISITA_TÉCNICA | S3: 254UMD4X8479 | T3: LEJANA | U3: AEREO | V3: SANTOS GONZALEZ JOHAN FABIAN | W3: 1 | X3: =IF(T3="PRINCIPAL",'TARIFAS 2025'!$B$5,IF(T3="INTERMEDIA",'TARIFAS 2025'!$C$5,IF(T3="LEJANA",'TARIFAS 2025'!$D$5))) -> 598334 | Y3: 1 | Z3: =X3*W3*Y3 -> 598334
A4: NEIVA | B4: =VLOOKUP(A4,'CENTROS DE COSTOS'!A:D,2,0) -> 0036-0006 | C4: =VLOOKUP(A4,'CENTROS DE COSTOS'!A:D,3,0) -> Wompi Oriente | D4: 18247 | E4: TA-25-1246642 | F4: 81763 | G4: APERTURA | H4: CB CRECIMIENTO - NUEVO | I4: CAQUETA | J4: EL DONCELLO | K4: BARRIO CENTRO EL DONCELLO 2 | L4: WOMPI | M4: FO-25-1748407 | N4: 45932 | O4: 45968 | P4: EJECUTADO | Q4: 11-10 SE REALIZA LLAMADA AL CLIENTE, SE HABLA CON LA SRA MARIA LUZ ORTIZ BARRAGAN, EL CUAL INDICA QUE AUN NO TIENE EL CORREO POR PARTE DE WOMPI. CORREO CORRECTO | 28/10/2025 SE REALIZA COMUNICACIÓN POR WPP CON EL USUARIO E INDICA QUE YA TIENE EL CORREO, NO INDICA ALTURA DEL AVISO | 07-11 SE REALIZA INSTALACIÓN DE CORRESPONSAL, SE INSTALA EQUIPO CON PRUEBAS EXITOSAS, SE CAPACITA Y SE EVALÚA AL CLIENTE, SE INSTALA PUBLICIDAD COMPLETA, CB QUEDA OPERATIVO. USUARIO SOMOS BANCOLOMBIA ACTIVO | R4: VISITA_TÉCNICA | S4: 254MMD4X0414 | T4: LEJANA | U4: TERRESTRE | V4: BERMUDEZ SANCHEZ JOSE NEYBER | W4: 1 | X4: =IF(T4="PRINCIPAL",'TARIFAS 2025'!$B$5,IF(T4="INTERMEDIA",'TARIFAS 2025'!$C$5,IF(T4="LEJANA",'TARIFAS 2025'!$D$5))) -> 598334 | Y4: 1 | Z4: =X4*W4*Y4 -> 598334
A5: MANIZALES | B5: =VLOOKUP(A5,'CENTROS DE COSTOS'!A:D,2,0) -> 0036-0002 | C5: =VLOOKUP(A5,'CENTROS DE COSTOS'!A:D,3,0) -> Wompi Eje Cafetero | D5: 17777 | E5: TA-25-1246646 | F5: 81788 | G5: APERTURA | H5: CB CRECIMIENTO - NUEVO | I5: CALDAS | J5: SUPIA | K5: BARRIO CODEMAS SUPÍA | L5: WOMPI | M5: FO-25-1748414 | N5: 45932 | O5: 45966 | P5: EJECUTADO | Q5: 10-10 SE REALIZA LLAMADA AL CLIENTE, SE HABLA CON LA SRA SHIRLEY PATRICIA CANTELLON LOPEZ, EL CUAL INDICA QUE AUN NO TIENE EL CORREO POR PARTE DE WOMPI | 28/10/2025 EN NUEVA COMUNICACIÓN CON LA USUARIA INDICA QUE YA TIENE EL CORREO POR PARTE DE WOMPI, 2.5 MT 31-10 DEBIDO A PROBLEMAS DE MOVILIDAD EN LA VIA QUE COMUNICA AL MUNICIPIO DE SUPIA, NO SE PUEDE DESPLAZAR, SE REALIZARA DESPLAZAMIENTO LA PROXIMA SEMANA | 05-11 SE REALIZA INSTALACIÓN DE CORRESPONSAL, SE INSTALA EQUIPO CON PRUEBAS EXITOSAS, SE CAPACITA Y SE EVALÚA AL CLIENTE, SE INSTALA PUBLICIDAD COMPLETA, CB QUEDA OPERATIVO. USUARIO SOMOS BANCOLOMBIA ACTIVO | R5: VISITA_TÉCNICA | S5: 254UMD4X8954 | T5: INTERMEDIA | U5: TERRESTRE | V5: ARROYAVE CANO MANUEL GUILLERMO | W5: 1 | X5: =IF(T5="PRINCIPAL",'TARIFAS 2025'!$B$5,IF(T5="INTERMEDIA",'TARIFAS 2025'!$C$5,IF(T5="LEJANA",'TARIFAS 2025'!$D$5))) -> 488953 | Y5: 1 | Z5: =X5*W5*Y5 -> 488953
A6: MEDELLIN | B6: =VLOOKUP(A6,'CENTROS DE COSTOS'!A:D,2,0) -> 0036-0005 | C6: =VLOOKUP(A6,'CENTROS DE COSTOS'!A:D,3,0) -> Wompi Noroccidente | D6: 5237 | E6: TA-25-1253400 | F6: 81760 | G6: APERTURA | H6: CB CRECIMIENTO - NUEVO | I6: ANTIOQUIA | J6: DON MATIAS | K6: BARRIO PARQUE DON MATIAS DON MATIAS | L6: WOMPI | M6: FO-25-1763460 | N6: 45932 | O6: 45965 | P6: EJECUTADO | Q6: 10-10 SE REALIZA LLAMADA AL CLIENTE, SE HABLA CON LA SRA YESICA PAOLA JIMENEZ CARDENAS, INDICA NO TENER LAS CREDENCIALES DE ACCESO WOMPI. CORREO CORRECTO | 28/10/2025 EN NUEVA COMUNICACIÓN CON LA USUARIA INDICA QUE AUN NO TIENE CORREO POR PARTE DE WOMPI | 31/10/2025 30-10 SE REALIZA LLAMADA AL CLIENTE, SE HABLA CON LA SRA YESICA PAOLA JIMENEZ CARDENAS SE VALIDA DIRECCIÓN OK, CANAL OK, DISPONIBILIDAD TOTAL, USUARIO Y CONTRASEÑA WOMPI OK, LLAMAR EL DÍA LA INSTALACIÓN PARA CONFIRMAR VISITA, AVISO EXTERIOR ALTURA: NO INDICA ALTURA | 04-11 SE REALIZA INSTALACIÓN DE CORRESPONSAL, SE INSTALA EQUIPO CON PRUEBAS EXITOSAS, SE CAPACITA Y SE EVALÚA AL CLIENTE, SE INSTALA PUBLICIDAD COMPLETA, CB QUEDA OPERATIVO. USUARIO SOMOS BANCOLOMBIA ACTIVO | R6: VISITA_TÉCNICA | S6: 254MMD4W7548 | T6: INTERMEDIA | U6: TERRESTRE | V6: ZAPATA LOPEZ EDWARD ASDRUBAL | W6: 1 | X6: =IF(T6="PRINCIPAL",'TARIFAS 2025'!$B$5,IF(T6="INTERMEDIA",'TARIFAS 2025'!$C$5,IF(T6="LEJANA",'TARIFAS 2025'!$D$5))) -> 488953 | Y6: 1 | Z6: =X6*W6*Y6 -> 488953
A7: TUNJA | B7: =VLOOKUP(A7,'CENTROS DE COSTOS'!A:D,2,0) -> 0036-0007 | C7: =VLOOKUP(A7,'CENTROS DE COSTOS'!A:D,3,0) -> Wompi Santander | D7: 15001 | E7: TA-25-1253402 | F7: 81789 | G7: APERTURA | H7: CB CRECIMIENTO - NUEVO | I7: BOYACA | J7: TUNJA | K7: BARRIO LAS QUINTAS TUNJA 5 | L7: WOMPI | M7: FO-25-1763467 | N7: 45932 | O7: 45972 | P7: EJECUTADO | Q7: 10-10 SE REALIZA LLAMADA AL CLIENTE, SE HABLA CON LA SRA YILLIAN YINDEE CARDONA CASTEBLANCO, INDICA NO TENER LAS CREDENCIALES DE ACCESO WOMPI. CORREO CORRECTO // 28-10-2025 SE REALIZA LLAMADA SE HABLA CON LA SEÑORA YILLIAN AL REALIZAR LA BUSQUEDA EN SU CORREO DEL MENSAJE DE WOMPI NO LO ENCUENTRA, SE ESCRIBE EN EL BUSCADOR SIN EXITO, LA SEÑORA CONFIRMA NO HABERLE LLEGADO Y QUEDA ATENDA AL CORREO PARA CONTINUAR CON EL PROCESO | 31/10/2025 SE REALIZA LLAMADA AL CLIENTE, SE HABLA CON LA SRA YILLIAN YINDEE CARDONA CASTEBLANCO SE VALIDA DIRECCIÓN OK, CANAL OK, DISPONIBILIDAD TOTAL, USUARIO Y CONTRASEÑA WOMPI OK, LLAMAR EL DÍA LA INSTALACIÓN PARA CONFIRMAR VISITA, AVISO EXTERIOR ALTURA APROX 4 METROS - SE PROGRAMA PARA ESTA FECHA YA QUE LA SRA INDICA QUE VA A ESTAR POR FUERA DEL PAIS | 11-11 SE REALIZA INSTALACIÓN DE CORRESPONSAL, SE INSTALA EQUIPO CON PRUEBAS EXITOSAS, SE CAPACITA Y SE EVALÚA AL CLIENTE, SE INSTALA PUBLICIDAD COMPLETA, CB QUEDA OPERATIVO. USUARIO SOMOS BANCOLOMBIA ACTIVO | R7: VISITA_TÉCNICA | S7: 254KMD4W6142 | T7: PRINCIPAL | U7: TERRESTRE | V7: GONZALEZ GONZALEZ MARIO ALBERTO | W7: 1 | X7: =IF(T7="PRINCIPAL",'TARIFAS 2025'!$B$5,IF(T7="INTERMEDIA",'TARIFAS 2025'!$C$5,IF(T7="LEJANA",'TARIFAS 2025'!$D$5))) -> 367716 | Y7: 1 | Z7: =X7*W7*Y7 -> 367716
A8: CALI | B8: =VLOOKUP(A8,'CENTROS DE COSTOS'!A:D,2,0) -> 0036-0003 | C8: =VLOOKUP(A8,'CENTROS DE COSTOS'!A:D,3,0) -> Wompi Suroccidente | D8: 19532 | E8: TA-25-1246657 | F8: 81921 | G8: APERTURA | H8: CB CRECIMIENTO - NUEVO | I8: CAUCA | J8: PATIA | K8: BARRIO CENTRO PATIA 4 | L8: WOMPI | M8: FO-25-1748434 | N8: 45950 | O8: 45982 | P8: EJECUTADO | Q8: 21-10 SE REALIZA LLAMADA AL CLIENTE, SE HABLA CON LA SRA YENIFER CAMAYO ANDRADE, EL CUAL INDICA QUE EL CORREO ESTA CORRECTO PERO NO LE HA LLEGADO NADA DE WOMPI -COMUNICACIÓN POR WPP | 28-10 EN NUEVA COMUNICACIÓN CON EL USUARIO INDICA QUE YA TIENE EL CORREO POR PARTE DE WOMPI, SE PROCEDE CON LA PROGRAMACIÓN | 07-11 DADO PROBLEMAS PARA DESPLAZARSE HACIA EL SITIO POR ZONA ROJA, SE ESTARÁ TRATANDO DE VIAJAR LA PRÓXIMA SEMANA | 18-11 DADO PROBLEMAS PARA DESPLAZAR HACIA EL SITIO POR ZONA ROJA, SE ESTARÁ TRATANDO DE VIAJAR LA PRÓXIMA SEMANA. SE REALIZA LLAMADA CON LA SEÑORA YENIFER, SE LE INFORMA QUE DEBIDO A LOS ENFRENTAMIENTOS DE GRUPOS ARMADOS EN LA VÍA SE REPROGRAMA VISITA TÉCNICA | 21-11 SE REALIZA INSTALACIÓN DE CORRESPONSAL, SE INSTALA EQUIPO CON PRUEBAS EXITOSAS, SE CAPACITA Y SE EVALÚA AL CLIENTE, SE INSTALA PUBLICIDAD COMPLETA, CB QUEDA OPERATIVO. USUARIO SOMOS BANCOLOMBIA ACTIVO | R8: VISITA_TÉCNICA | S8: 254MMD4W7882 | T8: LEJANA | U8: TERRESTRE | V8: GIMBUEL LASSO LUIS GERMAN | W8: 1 | X8: =IF(T8="PRINCIPAL",'TARIFAS 2025'!$B$5,IF(T8="INTERMEDIA",'TARIFAS 2025'!$C$5,IF(T8="LEJANA",'TARIFAS 2025'!$D$5))) -> 598334 | Y8: 1 | Z8: =X8*W8*Y8 -> 598334
A9: PEREIRA | B9: =VLOOKUP(A9,'CENTROS DE COSTOS'!A:D,2,0) -> 0036-0002 | C9: =VLOOKUP(A9,'CENTROS DE COSTOS'!A:D,3,0) -> Wompi Eje Cafetero | D9: 76622 | E9: TA-25-1246658 | F9: 81927 | G9: APERTURA | H9: CB CRECIMIENTO - NUEVO | I9: VALLE DEL CAUCA | J9: ROLDANILLO | K9: BARRIO LA ASUNCION ROLDANILLO 2 | L9: WOMPI | M9: FO-25-1748436 | N9: 45950 | O9: 45971 | P9: EJECUTADO | Q9: 21-10 SE REALIZA LLAMADA AL CLIENTE, SE HABLA CON LA SR GERMAN ALONSO MARTINEZ BERMUDEZ EL CUAL INDICA QUE EL CORREO ESTA ERRADO, EL CORREO CORRECTO ES germanalonso0410@gmail.com | 28/10/2025 SE ESTABLECE COMUNICACIÓN CON EL SR GERMAN EL CUAL INDICA QUE YA TIENE EL CORREO POR PARTE DE WOMPI , ALTURA DEL AVISO 2 MT 07-11 DADO PROBLEMAS DE CIERRE EN LA VIA QUE COMUNICA A PEREURA CON CARTAGO NO SE PUDO REALIZAR DESPLAZAMIENTO EL DIA 7 DE NOVIEMBRE | 10-11 SE REALIZA INSTALACIÓN DE CORRESPONSAL, SE INSTALA EQUIPO CON PRUEBAS EXITOSAS, SE CAPACITA Y SE EVALÚA AL CLIENTE, SE INSTALA PUBLICIDAD COMPLETA, CB QUEDA OPERATIVO. USUARIO SOMOS BANCOLOMBIA ACTIVO | R9: VISITA_TÉCNICA | S9: 254MMD4X0180 | T9: LEJANA | U9: TERRESTRE | V9: LOAIZA LOPEZ JHON FREDDY | W9: 1 | X9: =IF(T9="PRINCIPAL",'TARIFAS 2025'!$B$5,IF(T9="INTERMEDIA",'TARIFAS 2025'!$C$5,IF(T9="LEJANA",'TARIFAS 2025'!$D$5))) -> 598334 | Y9: 1 | Z9: =X9*W9*Y9 -> 598334
A10: BOGOTA | B10: =VLOOKUP(A10,'CENTROS DE COSTOS'!A:D,2,0) -> 0036-0004 | C10: =VLOOKUP(A10,'CENTROS DE COSTOS'!A:D,3,0) -> Wompi Centro | D10: 25718 | E10: TA-25-1253410 | F10: 81925 | G10: APERTURA | H10: CB CRECIMIENTO - NUEVO | I10: CUNDINAMARCA | J10: SASAIMA | K10: BARRIO EL CARMEN SASAIMA | L10: WOMPI | M10: FO-25-1763475 | N10: 45950 | O10: 45966 | P10: EJECUTADO | Q10: 21-10 SE REALIZA LLAMADA AL CLIENTE, SE HABLA CON LA SR EDUARDO CRUZ MURCIA EL CUAL INDICA QUE EL CORREO ESTA ERRADO, EL CORREO CORRECTO ES rujacara1@hotmail.com // 28-10-2025 SE REALIZA LLAMADA AL NUMERO DE LA LISTA SE HABLA CON EL CLIENTE QUIEN AL BUSCAR EN SU CORREO NO ENCUENTRA EL MENSAJE DE WOMPI, ME VUELVE A CONFIRMAR SU CORREO: rujacara1@hotmail.com | 31/10/2025 30-10 SE REALIZA LLAMADA AL CLIENTE, SE HABLA CON LA SR EDUARDO CRUZ MURCIA SE VALIDA DIRECCIÓN OK, CANAL OK, DISPONIBILIDAD TOTAL, USUARIO Y CONTRASEÑA WOMPI OK, LLAMAR EL DÍA LA INSTALACIÓN PARA CONFIRMAR VISITA, AVISO EXTERIOR ALTURA APROX 2.50 METROS - COMUNICACIÓN POR WPP | 05-11 SE REALIZA INSTALACIÓN DE CORRESPONSAL, SE INSTALA EQUIPO CON PRUEBAS EXITOSAS, SE CAPACITA Y SE EVALÚA AL CLIENTE, SE INSTALA PUBLICIDAD COMPLETA, CB QUEDA OPERATIVO. USUARIO SOMOS BANCOLOMBIA ACTIVO | R10: VISITA_TÉCNICA | S10: 254MMD4X2531 | T10: INTERMEDIA | U10: TERRESTRE | V10: LOZADA ROJAS CHRISTIAN ANDRES | W10: 1 | X10: =IF(T10="PRINCIPAL",'TARIFAS 2025'!$B$5,IF(T10="INTERMEDIA",'TARIFAS 2025'!$C$5,IF(T10="LEJANA",'TARIFAS 2025'!$D$5))) -> 488953 | Y10: 1 | Z10: =X10*W10*Y10 -> 488953
A11: PASTO | B11: =VLOOKUP(A11,'CENTROS DE COSTOS'!A:D,2,0) -> 0036-0003 | C11: =VLOOKUP(A11,'CENTROS DE COSTOS'!A:D,3,0) -> Wompi Suroccidente | D11: 52427 | E11: TA-25-1246659 | F11: 81913 | G11: APERTURA | H11: CB CRECIMIENTO - NUEVO | I11: NARIÑO | J11: MAGUI | K11: BARRIO PIEDRA VERDE MAGUI | L11: WOMPI | M11: FO-25-1748439 | N11: 45950 | O11: 45973 | P11: EJECUTADO | Q11: 22-10 SE REALIZA LLAMADA AL CLIENTE, SE HABLA CON LA SRA DANIA MADONA BENALCAZAR CASTILLO, INDICA QUE NO TIENE LAS CREDENCIALES DE ACCESO (CORREO CORRECTO) // 28-10-2025 SE REALIZA LLAMADA AL NUMERO DE LA LISTA SE HABLA CON LA MAMA SE LA SEÑORA DANIA, AL CONFIRMAR POR EL CORREO DE WOMPI ME INDICA QUE NO LE HA LLEGADO AUN, QUE ESTA EN ESPERA DE ESE CORREO PERO AUN NO LO TIENE 28-10 EN COMUNICACIÓN CON LA USUARIA INDICA QUE YA TIENE EL CORREO POR PARTE DE WOMPI | 07-10 SE REALIZARA DESPLAZAMIENTO EL DIA 10 DE NOVIEMBRE YA QUE DADO PROBLEMAS EN LA VIA HACIA TUMACO NO SE PUEDE DESPLAZAR ANTES | 12-11 12-11 SE REALIZA INSTALACIÓN DE CORRESPONSAL, SE INSTALA EQUIPO CON PRUEBAS EXITOSAS, SE CAPACITA Y SE EVALÚA AL CLIENTE, SE INSTALA PUBLICIDAD COMPLETA, CB QUEDA OPERATIVO. USUARIO SOMOS BANCOLOMBIA ACTIVO. COMERCIO SIN AVISO PUBLICITARIO. SIN EMBARGO, SI ES EL MISMO OBJETIVO COMERCIAL, LA DIRECCIÓN COINCIDE Y LA CÁMARA DE COMERCIO TAMBIÓN TIENE EL MISMO NOMBRE DE LISTA DE CHEQUEO | R11: VISITA_TÉCNICA | S11: 254MMD4X2338 | T11: LEJANA | U11: FLUVIAL | V11: PAZ MARTINEZ RICHARD HUMBERTO | W11: 1 | X11: =IF(T11="PRINCIPAL",'TARIFAS 2025'!$B$5,IF(T11="INTERMEDIA",'TARIFAS 2025'!$C$5,IF(T11="LEJANA",'TARIFAS 2025'!$D$5))) -> 598334 | Y11: 1 | Z11: =X11*W11*Y11 -> 598334
A12: MANIZALES | B12: =VLOOKUP(A12,'CENTROS DE COSTOS'!A:D,2,0) -> 0036-0002 | C12: =VLOOKUP(A12,'CENTROS DE COSTOS'!A:D,3,0) -> Wompi Eje Cafetero | D12: 17042 | E12: TA-25-1253412 | F12: 81889 | G12: APERTURA | H12: CB CRECIMIENTO - NUEVO | I12: CALDAS | J12: ANSERMA | K12: BARRIO VEREDA EL PARAISO ANSERMA | L12: WOMPI | M12: FO-25-1763478 | N12: 45950 | O12: 45967 | P12: EJECUTADO | Q12: 22-10-2025 SE REALIZA LLAMADA AL NUMERO DE LA LISTA, SE HABLA CON EL SEÑOR HENRRY AL VALIDAR EL CORREO ME INDICA QUE NO LE HA LLEGADO, EL CORREO SE VALIDA LETRA POR LETRA SIN EMBARGO DESPUES DE UNA BUSQUEDA ME INDICA QUE QUE EFECTIVAMENTE NO LO TIENE // 29-10-2025 SE REALIZA CONTACTO POR WHATSAPP CON EL SEÑOR HENRRY ME INDICA QUE NO LE HA LLEGADO EL CORREO Y ME LO RECTIFICA NUEVAMENTE YA QUE ESTA ESPERANDO EL PROCESO DE INSTALACION; CORREO CONFIRMADO POR EL CLIENTE: portillo_serrano@hotmail.com | 6/11/2025 SE REALIZA INSTALACIÓN DE CORRESPONSAL, SE INSTALAN EQUIPOS CON PRUEBAS EXITOSAS, SE CAPACITA Y SE EVALÚA AL CLIENTE, SE INSTALA PUBLICIDAD COMPLETA, CB QUEDA OPERATIVO. USUARIO SOMOS BANCOLOMBIA ACTIVO | R12: VISITA_TÉCNICA | S12: 254UMD4X8655 | T12: INTERMEDIA | U12: TERRESTRE | V12: FRANCO CAÑAVERAL YAMID RAUL | W12: 1 | X12: =IF(T12="PRINCIPAL",'TARIFAS 2025'!$B$5,IF(T12="INTERMEDIA",'TARIFAS 2025'!$C$5,IF(T12="LEJANA",'TARIFAS 2025'!$D$5))) -> 488953 | Y12: 1 | Z12: =X12*W12*Y12 -> 488953
A13: CALI | B13: =VLOOKUP(A13,'CENTROS DE COSTOS'!A:D,2,0) -> 0036-0003 | C13: =VLOOKUP(A13,'CENTROS DE COSTOS'!A:D,3,0) -> Wompi Suroccidente | D13: 19001 | E13: TA-25-1233729 | F13: 81956 | G13: APERTURA | H13: CB CRECIMIENTO - NUEVO | I13: CAUCA | J13: POPAYAN | K13: BARRIO VILLA DEL NORTE EN POPAYAN | L13: WOMPI | M13: FO-25-1724170 | N13: 45952 | O13: 45965 | P13: EJECUTADO | Q13: 23-10 SE REALIZA LLAMADA AL CLIENTE, SE HABLA CON LA SRA EDILMA INES ARANDA MUELAS SE VALIDA DIRECCIÓN OK, CANAL OK, DISPONIBILIDAD TOTAL, USUARIO Y CONTRASEÑA WOMPI OK, LLAMAR EL DÍA LA INSTALACIÓN PARA CONFIRMAR VISITA, AVISO EXTERIOR ALTURA: NO INDICA - COMUICACIÓN POR WPP | 04-11 DADO A INCONVENIENTES CON EL TRANSPORTE EL DIA FESTIVO, LA VISITA SE ESTA ATENDIENDO EL DIA MARTES 4 DE NOVIEMBRE | SE REALIZA INSTALACIÓN DE CORRESPONSAL, SE INSTALA EQUIPO CON PRUEBAS EXITOSAS, SE CAPACITA Y SE EVALÚA AL CLIENTE, SE INSTALA PUBLICIDAD COMPLETA, CB QUEDA OPERATIVO. USUARIO SOMOS BANCOLOMBIA ACTIVO | R13: VISITA_TÉCNICA | S13: 254MMD4W8511 | T13: LEJANA | U13: TERRESTRE | V13: GIMBUEL LASSO LUIS GERMAN | W13: 1 | X13: =IF(T13="PRINCIPAL",'TARIFAS 2025'!$B$5,IF(T13="INTERMEDIA",'TARIFAS 2025'!$C$5,IF(T13="LEJANA",'TARIFAS 2025'!$D$5))) -> 598334 | Y13: 1 | Z13: =X13*W13*Y13 -> 598334
... A134: MEDELLIN | B134: =VLOOKUP(A134,'CENTROS DE COSTOS'!A:D,2,0) -> 0036-0005 | C134: =VLOOKUP(A134,'CENTROS DE COSTOS'!A:D,3,0) -> Wompi Noroccidente | D134: 5001 | E134: TA-25-1334007 | F134: 82402 | G134: APERTURA | H134: CB CRECIMIENTO - NUEVO | I134: ANTIOQUIA | J134: MEDELLIN | K134: BARRIO EL CENTRO LA CANDELARIA MEDELLIN | L134: WOMPI | M134: FO-25-1895899 | N134: 45987 | O134: 45988 | P134: EJECUTADO | Q134: 27-11 SE REALIZA LLAMADA AL CLIENTE, SE HABLA CON LA SR ANGELO EUGENIO PUERTA CORREA SE VALIDA DIRECCIÓN OK, CANAL OK, DISPONIBILIDAD TOTAL, USUARIO Y CONTRASEÑA WOMPI OK, LLAMAR EL DÍA LA INSTALACIÓN PARA CONFIRMAR VISITA, AVISO EXTERIOR ALTURA: 2 METROS (COMUNICACION POR WPP) | 27-11 SE REALIZA INSTALACIÓN DE CORRESPONSAL, SE INSTALA EQUIPO CON PRUEBAS EXITOSAS, SE CAPACITA Y SE EVALÚA AL CLIENTE, SE INSTALA PUBLICIDAD COMPLETA, CB QUEDA OPERATIVO. USUARIO SOMOS BANCOLOMBIA ACTIVO | R134: VISITA_TÉCNICA | S134: 254MMD4W7770 | T134: PRINCIPAL | U134: TERRESTRE | V134: MARTINEZ TOVAR OSCAR DAVID | W134: 1 | X134: =IF(T134="PRINCIPAL",'TARIFAS 2025'!$B$5,IF(T134="INTERMEDIA",'TARIFAS 2025'!$C$5,IF(T134="LEJANA",'TARIFAS 2025'!$D$5))) -> 367716 | Y134: 1 | Z134: =X134*W134*Y134 -> 367716
Z135: =SUM(Z2:Z134) -> 63463121

Sheet INCIDENTES
A1: CIUDAD SEDE | B1: CENTRO_COSTO | C1: DESCRIPCION CENTRO DE COSTOS | D1: CÓDIGO DANE | E1: TA/CODIGO ACTIVIDAD | F1: CODIGO CB | G1: ACTIVIDAD | H1: DEPARTAMENTO | I1: CIUDAD | J1: NOMBRE DEL CB | K1: RED | L1: FO | M1: FECHA ASIGNACION A LINEA COMUNICACIONES | N1: FECHA DEL CIERRE DEL TICKET (DD/MM/AAAA) | O1: SOLICITUD | P1: GRUPO_FALLA | Q1: CATEGORÍA | R1: FALLA | S1: OBSERVACION | T1: FORMA DE ATENCIÓN | U1: INVENTARIO ACTUAL DE ROLLOS | V1: TIPOLOGIA | W1: TIPO DE TRAYECTO | X1: NOMBRE DEL TECNICO | Y1: DIAS DE ACTIVIDAD | Z1: VALOR DIAS ACTIVIDAD | AA1: VALOR TOTAL
A2: MEDELLIN | B2: =VLOOKUP(A2,'CENTROS DE COSTOS'!A:D,2,0) -> 0036-0005 | C2: =VLOOKUP(A2,'CENTROS DE COSTOS'!A:D,3,0) -> Wompi Noroccidente | D2: 5001 | E2: 2960293 | F2: 68652 | G2: INCIDENTE | H2: ANTIOQUIA | I2: MEDELLIN | J2: BARRIO ROBLEDO MIRADOR DEL VALLE MEDELLIN | K2: WOMPI | L2: FO-25-1761835 | M2: 45960.671 | N2: 45962.378 | O2: INCIDENTE | P2: CREDENCIALES DE ACCESO (USUARIO/CONTRASEÑA) | Q2: NO FUNCIONA EL USUARIO O CONTRASEÑA | R2: ERROR INICIO DE SESIÓN | S2: 01/11/2025 SE LLEGA AL PUNTO, CLIENTE NOS INDICA QUE NO PUEDE INICIAR SECCIÓN, SE ELIMINA CACHÉ Y DATOS DE LA APLICACIÓN, SE ACTUALIZA EQUIPO Y SE REINICIA, QUEDA OPERATIVO, TAMBIÉN SE HACEN PRUEBAS DE RED Y SE ENCUENTRAN INTERMITENCIAS, SE LE DICE A CLIENTE, PRUEBAS OK | T2: VISITA_TÉCNICA | U2: 32 | V2: PRINCIPAL | W2: TERRESTRE | X2: CARDONA MOLINA BROLIN STIVEN | Y2: 1 | Z2: =IF(T2="SOPORTE_TELEFÓNICO",'TARIFAS 2025'!$B$14,IF(V2="PRINCIPAL",'TARIFAS 2025'!$B$8,IF(V2="INTERMEDIA",'TARIFAS 2025'!$C$8,IF(V2="LEJANA",'TARIFAS 2025'!$D$8)))) -> 51282 | AA2: =Z2*Y2 -> 51282
A3: CUCUTA | B3: =VLOOKUP(A3,'CENTROS DE COSTOS'!A:D,2,0) -> 0036-0007 | C3: =VLOOKUP(A3,'CENTROS DE COSTOS'!A:D,3,0) -> Wompi Santander | D3: 54001 | E3: 2957899 | F3: 80784 | G3: INCIDENTE | H3: NORTE DE SANTANDER | I3: CUCUTA | J3: BARRIO CALLEJON CUCUTA 22 | K3: WOMPI | L3: FO-25-1766789 | FO-25-1756840 | M3: 45960.444 | N3: 45962.415 | O3: INCIDENTE | P3: EQUIPO | Q3: INTENTO DE MANIPULACION | R3: MALA MANIPULACIÓN DEL DATAFONO | S3: 31/10/2025 SE REALIZA VISITA SE ENCONTRÓ COMERCIO CERRADO NO SE LOGRÓ COMUNICACIÓN CON EL CLIENTE NI POR LLAMADA O WHATSAPP PARA SABER SI IBA A LABORAR EN LAS HORAS DE LA TARDE,SE PROGRAMA VISITA PARA EL DÍA DE MAÑANA 01-11-25 A LA ESPERA DE RESPUESTA POR PARTE DE CLIENTE PARA REALIZAR EL CAMBIO DEL DATAFONO 01/11/2025 SE REALIZA VISITA SE ENCONTRÓ DATAFONO BLOQUEADO NO PERMITE INGRESAR A LA APLICACIÓN WOMPI ARROJA ERROR EN EL SERVIDOR - AUTO INICIALIZACIÓN ,SE PROCEDE A CAMBIAR DATAFONO SE INTERESAN CREDENCIALES PRUEBAS OK | T3: VISITA_TÉCNICA | U3: 0 | V3: PRINCIPAL | W3: TERRESTRE | X3: DURAN ACOSTA FRANK YONNY | Y3: 2 | Z3: =IF(T3="SOPORTE_TELEFÓNICO",'TARIFAS 2025'!$B$14,IF(V3="PRINCIPAL",'TARIFAS 2025'!$B$8,IF(V3="INTERMEDIA",'TARIFAS 2025'!$C$8,IF(V3="LEJANA",'TARIFAS 2025'!$D$8)))) -> 51282 | AA3: =Z3*Y3 -> 102564
A4: TUNJA | B4: =VLOOKUP(A4,'CENTROS DE COSTOS'!A:D,2,0) -> 0036-0007 | C4: =VLOOKUP(A4,'CENTROS DE COSTOS'!A:D,3,0) -> Wompi Santander | D4: 15238 | E4: 2922589 | F4: 18727 | G4: INCIDENTE | H4: BOYACA | I4: DUITAMA | J4: BARRIO EL CARMEN II DUITAMA | K4: WOMPI | L4: FO-25-1721580 | M4: 45953.333 | N4: 45962.476 | O4: INCIDENTE | P4: NAVEGACION LENTA | Q4: USUARIO NO PUEDE NAVEGAR ENTRE PANTALLAS O LA APP NO ABRE SE QUEDA CARGANDO | R4: CACHE | S4: 01/11/2025 SE LOGRA COMUNICACION CON EL SEÑOR CARLOS MESA QUIEN NOS CONFIRMA QUE LOS DATAFONO SE ENCUENTRAN TRABAJANDO CON NORMALIDAD AUNQUE PRESENTA UN DESCUADRE DE GRAN VALOR, CLIENTE MANIFIESTA QUE NO VA A USAR LOS EQUIPOS HASTA QUE SE LE SOLICIONES ESTE INCONVENIENTE, SE LE INDICA AL CLIENTE QUE DICHA SOLICITUD DEBE ESCALARLA CON LA ENTIDAD BANCARIA PARA SU SOLUCION, SE CIERRA LA ORDEN YA QUE EL DATAFONO SE ENCUENTRA TRABAJANDO DE FORMA NORMAL, CLIENTE SE NIEGA A ENVIAR PRUEBAS DE TRANSACCIONES EXITOSAS. | T4: SOPORTE_TELEFÓNICO | U4: 64 | V4: INTERMEDIA | W4: TERRESTRE | X4: SOLER HOYOS CRISTIAN LEONARDO | Y4: 1 | Z4: =IF(T4="SOPORTE_TELEFÓNICO",'TARIFAS 2025'!$B$14,IF(V4="PRINCIPAL",'TARIFAS 2025'!$B$8,IF(V4="INTERMEDIA",'TARIFAS 2025'!$C$8,IF(V4="LEJANA",'TARIFAS 2025'!$D$8)))) -> 22000 | AA4: =Z4*Y4 -> 22000
A5: BOGOTA | B5: =VLOOKUP(A5,'CENTROS DE COSTOS'!A:D,2,0) -> 0036-0004 | C5: =VLOOKUP(A5,'CENTROS DE COSTOS'!A:D,3,0) -> Wompi Centro | D5: 11001 | E5: 2965082 | F5: 31244 | G5: INCIDENTE | H5: CUNDINAMARCA | I5: BOGOTA | J5: BARRIO LA PEPITA 2 | K5: WOMPI | L5: FO-25-1766917 | M5: 45961.662 | N5: 45962.534 | O5: INCIDENTE | P5: CONEXIÓN | Q5: CONEXIÓN DEFICIENTE WIFI | R5: FALLAS EN CANAL DE COMUNICACIÓN DEL CLIENTE (INTERNET) | S5: 01/11/2025 SE REALIZA LLAMADA, LA SEÑORA ADRIANA INDICA QUE ES EL INTERNET ( CLARO HOGAR ) QUE LE ESTA FALLANDO SOLAMENTE AL DATAFONO, YA QUE EN OTROS DISPOSITIVOS FUNCIONA NORMAL. LA SEÑORA ADRIANA LE COMPARTE DATOS DESDE EL CELULAR AL DATAFONO Y FUNCIONA NORMAL, A CONFORMIDAD DEL CLIENTE. | T5: SOPORTE_TELEFÓNICO | U5: 32 | V5: PRINCIPAL | W5: TERRESTRE | X5: ARIAS QUILINDO JULIAN | Y5: 1 | Z5: =IF(T5="SOPORTE_TELEFÓNICO",'TARIFAS 2025'!$B$14,IF(V5="PRINCIPAL",'TARIFAS 2025'!$B$8,IF(V5="INTERMEDIA",'TARIFAS 2025'!$C$8,IF(V5="LEJANA",'TARIFAS 2025'!$D$8)))) -> 22000 | AA5: =Z5*Y5 -> 22000
A6: MEDELLIN | B6: =VLOOKUP(A6,'CENTROS DE COSTOS'!A:D,2,0) -> 0036-0005 | C6: =VLOOKUP(A6,'CENTROS DE COSTOS'!A:D,3,0) -> Wompi Noroccidente | D6: 5607 | E6: 2965759 | F6: 31280 | G6: INCIDENTE | H6: ANTIOQUIA | I6: RETIRO | J6: BARRIO EL PINO | K6: WOMPI | L6: FO-25-1767194 | M6: 45962.375 | N6: 45962.537 | O6: INCIDENTE | P6: CREDENCIALES DE ACCESO (USUARIO/CONTRASEÑA) | Q6: INGRESO DE CREDENCIALES ERRADAS | R6: ERROR INICIO DE SESIÓN | S6: 01/11/2025 SE LLEGA AL PUNTO, SE VERIFICA QUE NO PUEDE INGRESAR EL USUARIO, SE ACTUALIZA, SE BORRA CACHÉ Y SE ENCUENTRA INTERMITENCIA EN LA RED, PRUEBAS OK | T6: VISITA_TÉCNICA | U6: 64 | V6: INTERMEDIA | W6: TERRESTRE | X6: CARDONA MOLINA BROLIN STIVEN | Y6: 1 | Z6: =IF(T6="SOPORTE_TELEFÓNICO",'TARIFAS 2025'!$B$14,IF(V6="PRINCIPAL",'TARIFAS 2025'!$B$8,IF(V6="INTERMEDIA",'TARIFAS 2025'!$C$8,IF(V6="LEJANA",'TARIFAS 2025'!$D$8)))) -> 172989 | AA6: =Z6*Y6 -> 172989
A7: VILLAVICENCIO | B7: =VLOOKUP(A7,'CENTROS DE COSTOS'!A:D,2,0) -> 0036-0006 | C7: =VLOOKUP(A7,'CENTROS DE COSTOS'!A:D,3,0) -> Wompi Oriente | D7: 50001 | E7: 2965265 | F7: 42229 | G7: INCIDENTE | H7: META | I7: VILLAVICENCIO | J7: BARRIO DANUBIO VILLAVICENCIO 1 | K7: WOMPI | L7: FO-25-1767029 | M7: 45961.683 | N7: 45962.54 | O7: INCIDENTE | P7: EQUIPO | Q7: PUERTO USB MALO | R7: FUENTE DE PODER | S7: 01/11/2025 SE REALIZA REVISIÓN FÍSICA DEL DATAFONO, NO SE ENCUENTRA FALLA, EN EL CARGADOR EL CONECTOR QUE LLEGA AL COSTADO DEL DATAFONO PRESENTA JUEGO NO ENCAJA COM AJUSTE, SE REALIZA PRUEBA CON OTRO CABLE TIPO DEL COMERCIO, LA CARGA ES CONSTANTE, SE INDICA A LA SRTA. YEIRA MEZA QUE SE DEBE USAR ESTE CABLE MIENTRAS SE SUMINISTRA CABLE DE CAMBIO PARA EL CARGADOR DEL DATAFONO. | T7: VISITA_TÉCNICA | U7: 64 | V7: PRINCIPAL | W7: TERRESTRE | X7: MURCIA HERNANDEZ HARVEY IGNACIO | Y7: 1 | Z7: =IF(T7="SOPORTE_TELEFÓNICO",'TARIFAS 2025'!$B$14,IF(V7="PRINCIPAL",'TARIFAS 2025'!$B$8,IF(V7="INTERMEDIA",'TARIFAS 2025'!$C$8,IF(V7="LEJANA",'TARIFAS 2025'!$D$8)))) -> 51282 | AA7: =Z7*Y7 -> 51282
A8: MEDELLIN | B8: =VLOOKUP(A8,'CENTROS DE COSTOS'!A:D,2,0) -> 0036-0005 | C8: =VLOOKUP(A8,'CENTROS DE COSTOS'!A:D,3,0) -> Wompi Noroccidente | D8: 5001 | E8: 2964523 | F8: 29381 | G8: INCIDENTE | H8: ANTIOQUIA | I8: MEDELLÍN | J8: COPYRED INSUMOS Y PAPELERIA | K8: WOMPI | L8: FO-25-1766282 | M8: 45961.6 | N8: 45962.578 | O8: INCIDENTE | P8: LECTURA | Q8: ERROR LECTURA CODIGO DE BARRAS | R8: NO LEE CODIGOS DE BARRAS LARGOS | S8: 01/11/2025 SE COMUNICA CON CLIENTE AL 3007795647 SE LE INDICA REALIZAR BORRADO DE CACHE, ACTUALIZACIÓN DEL TEM CALL Y REINICIO DE EQUIPO, TAMBIÉN SE LE DA INDICACIONES PARA LEER CORRECTAMENTE CÓDIGOS DE BARRAS, SE PRUEBA CON FACTURA DE EPM Y TIGO Y LEE CORRECTAMENTE, SE CIERRA | T8: SOPORTE_TELEFÓNICO | U8: 48 | V8: PRINCIPAL | W8: TERRESTRE | X8: QUINTERO SANCHEZ JUAN SEBASTIAN | Y8: 1 | Z8: =IF(T8="SOPORTE_TELEFÓNICO",'TARIFAS 2025'!$B$14,IF(V8="PRINCIPAL",'TARIFAS 2025'!$B$8,IF(V8="INTERMEDIA",'TARIFAS 2025'!$C$8,IF(V8="LEJANA",'TARIFAS 2025'!$D$8)))) -> 22000 | AA8: =Z8*Y8 -> 22000
A9: PASTO | B9: =VLOOKUP(A9,'CENTROS DE COSTOS'!A:D,2,0) -> 0036-0003 | C9: =VLOOKUP(A9,'CENTROS DE COSTOS'!A:D,3,0) -> Wompi Suroccidente | D9: 52683 | E9: 2960758 | F9: 37746 | G9: INCIDENTE | H9: NARIÑO | I9: SANDONA | J9: BARRIO SAN CARLOS SANDONA 1 | K9: WOMPI | L9: FO-25-1761983 | M9: 45960.698 | N9: 45962.582 | O9: INCIDENTE | P9: LECTURA | Q9: ERROR LECTURA CODIGO DE BARRAS | R9: NO LEE CODIGOS DE BARRAS CORTOS | S9: 01/11/2025 SE VALIDA CON EL CLIENTE QUIEN INDICA QUE EL DATAFONO NO LEE ESPECIFICAMENTE LA FACTURA DE CEDENAR, EL RESTO SI LAS LEE PERO LA DE CEDENAR NO, SE LE EXPLICA AL CLIENTE QUE CON ESTA FACTURA HAY UNA NOVEDAD QUE YA HABIA SIDO ESCALADA Y ESTA EN PROCESO DE CORRECCION PERO QUE LA FACTURA PUEDE SER PAGA CON CODIGO DE CONVENIO MANUALMENTE, LA USUARIO INDICA QUE SI PUEDE HACERLO ASI SOLO QUE PENSO QUE ERA LA UNICA QUE NO PODIA REALIZARLO, SE LE INDICA QUE ASI LO PUEDE SEGUIR REALIZANDO. | T9: SOPORTE_TELEFÓNICO | U9: 0 | V9: INTERMEDIA | W9: TERRESTRE | X9: HENAO CARDONA DIEGO FERNANDO | Y9: 1 | Z9: =IF(T9="SOPORTE_TELEFÓNICO",'TARIFAS 2025'!$B$14,IF(V9="PRINCIPAL",'TARIFAS 2025'!$B$8,IF(V9="INTERMEDIA",'TARIFAS 2025'!$C$8,IF(V9="LEJANA",'TARIFAS 2025'!$D$8)))) -> 22000 | AA9: =Z9*Y9 -> 22000
A10: MEDELLIN | B10: =VLOOKUP(A10,'CENTROS DE COSTOS'!A:D,2,0) -> 0036-0005 | C10: =VLOOKUP(A10,'CENTROS DE COSTOS'!A:D,3,0) -> Wompi Noroccidente | D10: 5088 | E10: 2966575 | F10: 71700 | G10: INCIDENTE | H10: ANTIOQUIA | I10: BELLO | J10: BELLO CABAÑAS | K10: WOMPI | L10: FO-25-1768865 | M10: 45962.451 | N10: 45962.585 | O10: INCIDENTE | P10: EQUIPO | Q10: DATAFONO NO ENCIENDE | R10: FUENTE DE PODER | S10: 01/11/2025 SE ESTABLECE COMUNICACIÓN TELEFÓNICA CON EL USUARIO PARA CONFIRMAR EL INCIDENTE PREVIAMENTE REPORTADO RELACIONADO CON EL DATÁFONO WOMPI DEL CORRESPONSAL BANCOLOMBIA. DURANTE LA LLAMADA, EL USUARIO INDICA QUE EL DISPOSITIVO PRESENTA FALLAS DE CARGA Y NO ENCIENDE CORRECTAMENTE. ADEMÁS, ACLARA QUE EN EL MOMENTO NO SE ENCUENTRA EN EL ESTABLECIMIENTO COMERCIAL, YA QUE ESTÁ ATENDIENDO DILIGENCIAS PERSONALES FUERA DEL LUGAR. INFORMA QUE REGRESARÁ AL COMERCIO EL DÍA MARTES | T10: SOPORTE_TELEFÓNICO | U10: 40 | V10: PRINCIPAL | W10: TERRESTRE | X10: MARTINEZ TOVAR OSCAR DAVID | Y10: 1 | Z10: =IF(T10="SOPORTE_TELEFÓNICO",'TARIFAS 2025'!$B$14,IF(V10="PRINCIPAL",'TARIFAS 2025'!$B$8,IF(V10="INTERMEDIA",'TARIFAS 2025'!$C$8,IF(V10="LEJANA",'TARIFAS 2025'!$D$8)))) -> 22000 | AA10: =Z10*Y10 -> 22000
A11: BARRANQUILLA | B11: =VLOOKUP(A11,'CENTROS DE COSTOS'!A:D,2,0) -> 0036-0001 | C11: =VLOOKUP(A11,'CENTROS DE COSTOS'!A:D,3,0) -> Wompi Costa | D11: 8606 | E11: 2965883 | F11: 75354 | G11: INCIDENTE | H11: ATLANTICO | I11: REPELON | J11: BARRIO MARCOS LOPERA REPELON | K11: WOMPI | L11: FO-25-1767944 | M11: 45962.375 | N11: 45963.392 | O11: INCIDENTE | P11: NAVEGACION LENTA | Q11: USUARIO NO PUEDE NAVEGAR ENTRE PANTALLAS O LA APP NO ABRE SE QUEDA CARGANDO | R11: CACHE | S11: 01/11/2025 EN COMUNICACIÓN CON HERLINDA RODRÍGUEZ AL NÚMERO 3007986858 ME MANIFIESTA QUE EL DATÁFONO ESTÁ LENTO LE COMUNICO QUE EL DATÁFONO HAY QUE BORRAR CACHÉ Y BUSCAR LA ÚLTIMA ACTUALIZACIÓN QUE ES 26.0.3 HACES EL PROCEDIMIENTO DE BORRAR CACHÉ Y ACTUALIZARLA LO CUAL QUEDA EN LA ÚLTIMA QUE ES 26.0.3 LE MANIFIESTO QUE REALIZA PRUEBAS LO CUAL ME DICE QUE EL DATÁFONO YA ESTÁ TRABAJANDO BIEN Y EL PROBLEMA DE LENTITUD CAMBIO LO CUAL REALIZA VARIAS PRUEBAS EXITOSAS | T11: SOPORTE_TELEFÓNICO | U11: 0 | V11: INTERMEDIA | W11: TERRESTRE | X11: PEÑALOZA GUTIERREZ RAFAEL GUSTAVO | Y11: 1 | Z11: =IF(T11="SOPORTE_TELEFÓNICO",'TARIFAS 2025'!$B$14,IF(V11="PRINCIPAL",'TARIFAS 2025'!$B$8,IF(V11="INTERMEDIA",'TARIFAS 2025'!$C$8,IF(V11="LEJANA",'TARIFAS 2025'!$D$8)))) -> 22000 | AA11: =Z11*Y11 -> 22000
A12: MEDELLIN | B12: =VLOOKUP(A12,'CENTROS DE COSTOS'!A:D,2,0) -> 0036-0005 | C12: =VLOOKUP(A12,'CENTROS DE COSTOS'!A:D,3,0) -> Wompi Noroccidente | D12: 5001 | E12: 2967212 | F12: 70713 | G12: INCIDENTE | H12: ANTIOQUIA | I12: MEDELLÍN | J12: TIENDA LAS ESCALAS DE AYALA | K12: WOMPI | L12: FO-25-1770556 | M12: 45963.375 | N12: 45963.54 | O12: INCIDENTE | P12: CAPACITACIÓN | Q12: MALA MANIPULACIÓN POS | R12: FALTA CAPACITACIÓN USUARIO CB | S12: 02/11/2025 SE REALIZA GESTIÓN TELEFÓNICA AL NÚMERO 3006488701 Y EN COMUNICACIÓN CON EL SEÑOR JOSÉ AYALA INDICA QUE NO LE DA INGRESO A LA APLICACIÓN DE WOMPI, POR MEDIO DE VIDEO LLAMADA SE BRINDA PRIMEROS AUXILIOS Y SE IDENTIFICA QUE EL USUARIO NO ESTABA METIENDO BIEN LA CLAVE, NO PONÍAN MAYÚSCULAS, SE DA SOLUCIÓN, SERVICIOS OK | T12: SOPORTE_TELEFÓNICO | U12: 32 | V12: PRINCIPAL | W12: TERRESTRE | X12: BARRIENTOS HERNANDEZ CRISTIAN HORACIO | Y12: 1 | Z12: =IF(T12="SOPORTE_TELEFÓNICO",'TARIFAS 2025'!$B$14,IF(V12="PRINCIPAL",'TARIFAS 2025'!$B$8,IF(V12="INTERMEDIA",'TARIFAS 2025'!$C$8,IF(V12="LEJANA",'TARIFAS 2025'!$D$8)))) -> 22000 | AA12: =Z12*Y12 -> 22000
A13: CALI | B13: =VLOOKUP(A13,'CENTROS DE COSTOS'!A:D,2,0) -> 0036-0003 | C13: =VLOOKUP(A13,'CENTROS DE COSTOS'!A:D,3,0) -> Wompi Suroccidente | D13: 19001 | E13: 2957028 | F13: 80291 | G13: INCIDENTE | H13: CAUCA | I13: POPAYAN | J13: BARRIO SAN EDUARDO POPAYAN 6 | K13: WOMPI | L13: FO-25-1755940 | M13: 45960.376 | N13: 45964.365 | O13: INCIDENTE | P13: CREDENCIALES DE ACCESO (USUARIO/CONTRASEÑA) | Q13: NO FUNCIONA EL USUARIO O CONTRASEÑA | R13: ERROR INICIO DE SESIÓN | S13: 03/11/2025 SE HABLA CON EL CLIENTE Y SE LE SOLICITA CREAR UNA NUEVA CONTRASEÑA, EL CLIENTE REALIZA LA CREACIÓN DE UNA NUEVA CONTRASEÑA Y YA PUEDE INGRESAR SIN NOVEDAD | T13: SOPORTE_TELEFÓNICO | U13: 8 | V13: LEJANA | W13: TERRESTRE | X13: HENAO CARDONA DIEGO FERNANDO | Y13: 1 | Z13: =IF(T13="SOPORTE_TELEFÓNICO",'TARIFAS 2025'!$B$14,IF(V13="PRINCIPAL",'TARIFAS 2025'!$B$8,IF(V13="INTERMEDIA",'TARIFAS 2025'!$C$8,IF(V13="LEJANA",'TARIFAS 2025'!$D$8)))) -> 22000 | AA13: =Z13*Y13 -> 22000
... A135: CALI | B135: =VLOOKUP(A135,'CENTROS DE COSTOS'!A:D,2,0) -> 0036-0003 | C135: =VLOOKUP(A135,'CENTROS DE COSTOS'!A:D,3,0) -> Wompi Suroccidente | D135: 76306 | E135: 2986516 | F135: 54283 | G135: INCIDENTE | H135: VALLE DEL CAUCA | I135: GINEBRA | J135: BARRIO SAN JOSE GINEBRA | K135: WOMPI | L135: FO-25-1792949 | M135: 45967.683 | N135: 45968.483 | O135: INCIDENTE | P135: NAVEGACION LENTA | Q135: USUARIO NO PUEDE NAVEGAR ENTRE PANTALLAS O LA APP NO ABRE SE QUEDA CARGANDO | R135: CACHE | S135: 07/11/2025 SE REALIZA ACTUALIZACIÓN DE APLICACION WOMPI Y BORRADO DE CACHÉ DONDE EL DISPOSITIVO EMPIEZA A REALIZAR TRANSACCIONES | T135: VISITA_TÉCNICA | U135: 24 | V135: INTERMEDIA | W135: TERRESTRE | X135: ESCOBAR LENIS JUAN SEBASTIAN | Y135: 1 | Z135: =IF(T135="SOPORTE_TELEFÓNICO",'TARIFAS 2025'!$B$14,IF(V135="PRINCIPAL",'TARIFAS 2025'!$B$8,IF(V135="INTERMEDIA",'TARIFAS 2025'!$C$8,IF(V135="LEJANA",'TARIFAS 2025'!$D$8)))) -> 172989 | AA135: =Z135*Y135 -> 172989
A136: YOPAL | B136: =VLOOKUP(A136,'CENTROS DE COSTOS'!A:D,2,0) -> 0036-0006 | C136: =VLOOKUP(A136,'CENTROS DE COSTOS'!A:D,3,0) -> Wompi Oriente | D136: 85001 | E136: 2988398 | F136: 52651 | G136: INCIDENTE | H136: CASANARE | I136: YOPAL | J136: TECNOMOVILC TECNOLOGÍA MÓVIL CELULAR | K136: WOMPI | L136: FO-25-1794745 | M136: 45968.384 | N136: 45968.487 | O136: INCIDENTE | P136: IMPRESIÓN | Q136: TAPA DE IMPRESORA DESAJUSTADA | R136: MALA MANIPULACIÓN DEL DATAFONO | S136: 07/11/2025 EN COMUNICACIÓN CON LA SEÑORA OLGA DELGADO AL NUMERO 3143371167, INDICA NO REQUIERE LA VISITA, EL SERVICIO SE ENCUENTRA OPERATIVO. | T136: SOPORTE_TELEFÓNICO | U136: 16 | V136: PRINCIPAL | W136: TERRESTRE | X136: BERNAL ELAICA EDGAR ALEXIS | Y136: 1 | Z136: =IF(T136="SOPORTE_TELEFÓNICO",'TARIFAS 2025'!$B$14,IF(V136="PRINCIPAL",'TARIFAS 2025'!$B$8,IF(V136="INTERMEDIA",'TARIFAS 2025'!$C$8,IF(V136="LEJANA",'TARIFAS 2025'!$D$8)))) -> 22000 | AA136: =Z136*Y136 -> 22000
A137: MEDELLIN | B137: =VLOOKUP(A137,'CENTROS DE COSTOS'!A:D,2,0) -> 0036-0005 | C137: =VLOOKUP(A137,'CENTROS DE COSTOS'!A:D,3,0) -> Wompi Noroccidente | D137: 5001 | E137: 2984953 | F137: 38038 | G137: INCIDENTE | H137: ANTIOQUIA | I137: MEDELLIN | J137: BARRIO PICACHO MEDELLIN 1 | K137: WOMPI | L137: FO-25-1791571 | M137: 45967.581 | N137: 45968.512 | O137: INCIDENTE | P137: NAVEGACION LENTA | Q137: USUARIO NO PUEDE NAVEGAR ENTRE PANTALLAS O LA APP NO ABRE SE QUEDA CARGANDO | R137: CACHE | S137: 07/11/2025 SE LLAMA AL CLIENTE Y SE LE INDICA AL CLIENTE COMO LIMPIAR CACHÉ Y SE LE DAN RECOMENDACIONES DE USO DEL EQUIPO COMO USARLO CON LA BATERÍA SUPERIOR AL 40%, ELIMINAR CACHÉ UNA VEZ POR MA MAÑANA Y OTRA POR LA TARDE, NO TENER EL EQUIPO LEJOS DE LA RED WIFI, EQUIPO QUEDA OPERATIVO | T137: SOPORTE_TELEFÓNICO | U137: 56 | V137: PRINCIPAL | W137: TERRESTRE | X137: CARDONA MOLINA BROLIN STIVEN | Y137: 1 | Z137: =IF(T137="SOPORTE_TELEFÓNICO",'TARIFAS 2025'!$B$14,IF(V137="PRINCIPAL",'TARIFAS 2025'!$B$8,IF(V137="INTERMEDIA",'TARIFAS 2025'!$C$8,IF(V137="LEJANA",'TARIFAS 2025'!$D$8)))) -> 22000 | AA137: =Z137*Y137 -> 22000
A138: TUNJA | B138: =VLOOKUP(A138,'CENTROS DE COSTOS'!A:D,2,0) -> 0036-0007 | C138: =VLOOKUP(A138,'CENTROS DE COSTOS'!A:D,3,0) -> Wompi Santander | D138: 15176 | E138: 2986738 | F138: 69859 | G138: INCIDENTE | H138: BOYACA | I138: CHIQUINQUIRA | J138: BARRIO LA ESPERANZA CHIQUINQUIRA 1 | K138: WOMPI | L138: FO-25-1792948 | M138: 45967.692 | N138: 45968.515 | O138: INCIDENTE | P138: NAVEGACION LENTA | Q138: USUARIO NO PUEDE NAVEGAR ENTRE PANTALLAS O LA APP NO ABRE SE QUEDA CARGANDO | R138: CACHE | S138: 07/11/2025 "SE ESTABLECE COMUNICACIÓN CON LA SEÑORA LEIDY PORRAS AL NÚMERO 3107615880 PARA VALIDAR LA FALLA DEL CORRESPONSAL. SE REALIZA GESTIÓN TELEFÓNICA EN VIDEOLLAMADA, DURANTE LA CUAL SE LLEVAN A CABO LAS SIGUIENTES VALIDACIONES CON EL EQUIPO: BORRADO DE CACHÉ, ACTUALIZACIÓN DE LA VERSIÓN 26.2.5 , Y VALIDACIÓN DEL FUNCIONAMIENTO DEL EQUIPO MEDIANTE PRUEBAS EXITOSAS. ESTO DEMUESTRA QUE EL EQUIPO TRABAJA CON UNA COMUNICACIÓN MÁS ESTABLE. SE INFORMA AL CLIENTE QUE LAS FALLAS DE NAVEGACIÓN LENTA PUEDEN DEBERSE A PROBLEMAS DE CONFIGURACIÓN DEL WI-FI O CAÍDAS DE RED. CON LAS VALIDACIONES REALIZADAS, SE OBTIENEN PRUEBA EXITOSA Y EL CLIENTE COMPARTE EL VOUCHERS CORRESPONDIENTE , CONFIRMANDO QUE LA COMUNICACIÓN ES MÁS ESTABLE. DE ESTA MANERA, EL CLIENTE QUEDA CONFORME Y SE PROCEDE A CERRAR LA ACTIVIDAD." | T138: SOPORTE_TELEFÓNICO | U138: 32 | V138: LEJANA | W138: TERRESTRE | X138: ALVARADO MORENO CRISTHIAN | Y138: 1 | Z138: =IF(T138="SOPORTE_TELEFÓNICO",'TARIFAS 2025'!$B$14,IF(V138="PRINCIPAL",'TARIFAS 2025'!$B$8,IF(V138="INTERMEDIA",'TARIFAS 2025'!$C$8,IF(V138="LEJANA",'TARIFAS 2025'!$D$8)))) -> 22000 | AA138: =Z138*Y138 -> 22000
A139: MONTERIA | B139: =VLOOKUP(A139,'CENTROS DE COSTOS'!A:D,2,0) -> 0036-0001 | C139: =VLOOKUP(A139,'CENTROS DE COSTOS'!A:D,3,0) -> Wompi Costa | D139: 23417 | E139: 2981462 | F139: 59132 | G139: INCIDENTE | H139: CORDOBA | I139: LORICA | J139: BARRIO LOS ANDES VIA A COVEÑAS LORICA | K139: WOMPI | L139: FO-25-1786686 | M139: 45967.337 | N139: 45968.52 | O139: INCIDENTE | P139: EQUIPO | Q139: BLOQUEO POR PIN | R139: DAÑO EN LA FUENTE DE PODER | S139: 07/11/2025 NOS COMUNICAMOS CON EL CB, NOS INDICA FALLA EN EL CARGADOR, INFORMANDO QUE NO COJE CARGA EL EQUIPO, SE LE INDICA REALIZAR PRUEBAS CON OTRO CARGADOR INDICANDO QUE EL EQUIPO YA CON OTRO CARGADOR TOMA CARGA Y LO GRAN ESTABILIDAD, POR LO TANTO NO SE VISITA Y SE LE INDICA QUE PUEDE UTILIZAR ESTE CARGADOR HASTA QUE NOS INFORMEN EL CAMBIO DE ESTE ACCESORIO. NOTA: PARA ESTE PROCESÓ NOS COMUNICAMOS CON LA SRA CRISTINA SUÁREZ CON CC 1063180156, EN NO DE CONTACTO 3136096758. | T139: SOPORTE_TELEFÓNICO | U139: 0 | V139: INTERMEDIA | W139: TERRESTRE | X139: CASSIANI PEREZ RAUL RAMIRO | Y139: 1 | Z139: =IF(T139="SOPORTE_TELEFÓNICO",'TARIFAS 2025'!$B$14,IF(V139="PRINCIPAL",'TARIFAS 2025'!$B$8,IF(V139="INTERMEDIA",'TARIFAS 2025'!$C$8,IF(V139="LEJANA",'TARIFAS 2025'!$D$8)))) -> 22000 | AA139: =Z139*Y139 -> 22000
A140: PEREIRA | B140: =VLOOKUP(A140,'CENTROS DE COSTOS'!A:D,2,0) -> 0036-0002 | C140: =VLOOKUP(A140,'CENTROS DE COSTOS'!A:D,3,0) -> Wompi Eje Cafetero | D140: 66001 | E140: 2980856 | F140: 63031 | G140: INCIDENTE | H140: RISARALDA | I140: PEREIRA | J140: TWINS URBAN SHOP | K140: WOMPI | L140: FO-25-1785473 | M140: 45967.333 | N140: 45968.525 | O140: INCIDENTE | P140: SOFTWARE | Q140: APP ELIMINADA | R140: APP ELIMINADA POR EL CB | S140: 07/11/2025 EN COMUNICACIÓN CON EL CLIENTE SE EVIDENCIA QUE LA APP LA ELIMINO, SE LOGRA REALIZAR ACTUALIZACIÓN DE LA VERSIÓN POR TELL CAM Y SE ESCALA CON WOMPI PARA QUE SE REALICE TELECARGA DE LA APP, SE LLAMA NUEVAMENTE AL CLIENTE E INDICA QUE YA ESTÁ FUNCIONANDO CORRECTAMENTE. | T140: SOPORTE_TELEFÓNICO | U140: 32 | V140: PRINCIPAL | W140: TERRESTRE | X140: FRANCO CAÑAVERAL YAMID RAUL | Y140: 1 | Z140: =IF(T140="SOPORTE_TELEFÓNICO",'TARIFAS 2025'!$B$14,IF(V140="PRINCIPAL",'TARIFAS 2025'!$B$8,IF(V140="INTERMEDIA",'TARIFAS 2025'!$C$8,IF(V140="LEJANA",'TARIFAS 2025'!$D$8)))) -> 22000 | AA140: =Z140*Y140 -> 22000
A141: TUNJA | B141: =VLOOKUP(A141,'CENTROS DE COSTOS'!A:D,2,0) -> 0036-0007 | C141: =VLOOKUP(A141,'CENTROS DE COSTOS'!A:D,3,0) -> Wompi Santander | D141: 15176 | E141: 2978928 | F141: 57782 | G141: INCIDENTE | H141: BOYACA | I141: CHIQUINQUIRA | J141: BARRIO LOS SAUCES CHIQUINQUIRA | K141: WOMPI | L141: FO-25-1783644 | M141: 45966.569 | N141: 45968.537 | O141: INCIDENTE | P141: EQUIPO | Q141: DATAFONO NO ENCIENDE | R141: FUENTE DE PODER | S141: 07/11/2025 SE ESTABLECE COMUNICACIÓN CON LA SEÑORA NANCY PACHON AL NÚMERO DE CONTACTO 3202475108, CON EL FIN DE VALIDAR LA FALLA REPORTADA. LA CLIENTE INFORMA QUE EL DATÁFONO SE ENCUENTRA EN PERFECTO FUNCIONAMIENTO, INDICANDO QUE PREVIAMENTE HABÍA PRESENTADO INCONVENIENTES DE CARGA, LOS CUALES FUERON SOLUCIONADOS TRAS REALIZAR UN REINICIO DEL EQUIPO.LA SEÑORA NANCY MANIFIESTA HABER CONTACTADO A LA LÍNEA DE SOPORTE PARA SOLICITAR LA CANCELACIÓN DE LA VISITA TÉCNICA, Y ADJUNTA UN VOUCHER QUE CONFIRMA LA CORRECTA OPERATIVIDAD DEL DISPOSITIVO SE LE INFORMA QUE SE PROCEDERÁ CON EL CIERRE DE LA ORDEN, A LO CUAL LA CLIENTE MANIFIESTA CONFORMIDAD | T141: SOPORTE_TELEFÓNICO | U141: 32 | V141: LEJANA | W141: TERRESTRE | X141: ALVARADO MORENO CRISTHIAN | Y141: 1 | Z141: =IF(T141="SOPORTE_TELEFÓNICO",'TARIFAS 2025'!$B$14,IF(V141="PRINCIPAL",'TARIFAS 2025'!$B$8,IF(V141="INTERMEDIA",'TARIFAS 2025'!$C$8,IF(V141="LEJANA",'TARIFAS 2025'!$D$8)))) -> 22000 | AA141: =Z141*Y141 -> 22000
A142: TUNJA | B142: =VLOOKUP(A142,'CENTROS DE COSTOS'!A:D,2,0) -> 0036-0007 | C142: =VLOOKUP(A142,'CENTROS DE COSTOS'!A:D,3,0) -> Wompi Santander | D142: 15646 | E142: 2978689 | F142: 52924 | G142: INCIDENTE | H142: BOYACA | I142: SAMACA | J142: BARRIO CENTRO SAMACA 3 | K142: WOMPI | L142: FO-25-1783230 | M142: 45966.556 | N142: 45968.54 | O142: INCIDENTE | P142: PANTALLA | Q142: TÁCTIL | R142: NO RESPONDE LA PANTALLA TÁCTIL | S142: 07/11/2025 SE REALIZA VISITA TÉCNICA AL PUNTO PARA ENTREGA DE ROLLOS.CLIENTE CON ORDEN DE INCIDENTE GENERADA SE EVIDENCIA QUE EL EQUIPO PRESENTA BLOQUEO EN LA PANTALLA TÁCTIL. SE PROCEDE A RETIRAR LA BATERÍA Y ENCENDER NUEVAMENTE EL DISPOSITIVO. POSTERIORMENTE, SE REALIZA LIMPIEZA DE CACHÉ Y ACTUALIZACIÓN DEL SISTEMA, LUEGO DE LO CUAL SE REINICIA EL EQUIPO. SE EJECUTAN PRUEBAS DE FUNCIONAMIENTO CON RESULTADOS EXITOSOS. CLIENTE QUEDA CONFORME CON LA GESTIÓN REALIZADA. | T142: VISITA_TÉCNICA | U142: 64 | V142: INTERMEDIA | W142: TERRESTRE | X142: RODRIGUEZ MURCIA YERSON IVAN | Y142: 1 | Z142: =IF(T142="SOPORTE_TELEFÓNICO",'TARIFAS 2025'!$B$14,IF(V142="PRINCIPAL",'TARIFAS 2025'!$B$8,IF(V142="INTERMEDIA",'TARIFAS 2025'!$C$8,IF(V142="LEJANA",'TARIFAS 2025'!$D$8)))) -> 172989 | AA142: =Z142*Y142 -> 172989
A143: MEDELLIN | B143: =VLOOKUP(A143,'CENTROS DE COSTOS'!A:D,2,0) -> 0036-0005 | C143: =VLOOKUP(A143,'CENTROS DE COSTOS'!A:D,3,0) -> Wompi Noroccidente | D143: 5079 | E143: 2863040 | F143: 13055 | G143: INCIDENTE | H143: ANTIOQUIA | I143: BARBOSA | J143: BARBOSA III ANTIOQUIA | K143: WOMPI | L143: FO-25-1700538 | FO-25-1654904 | M143: 45939.468 | N143: 45968.557 | O143: INCIDENTE | P143: CONEXIÓN | Q143: CONEXIÓN DEFICIENTE WIFI | R143: FALLAS EN CANAL DE COMUNICACIÓN DEL CLIENTE (INTERNET) | S143: 17/10/2025 SE REALIZA GESTIÓN TELEFÓNICA Y PERSONA QUE ATIENDE EN EL NÚMERO 3023564578 INDICA QUE ANTES DE LA LLAMADA YA HABÍA BORRADO CACHÉ Y QUE LA FALLA PERSISTE QUE POR FAVOR LE AYUDEN CON ESO 07/11/2025 SE VERIFICA EL CANAL DEL MODEM QUE TIENEN EL CLIENTE Y EST ATRASMITIENDO SOLO POR RED 5G POR LO QUE SE LE EXPLICA AL CLIENTE QUE POR ESO EL DATAFONO NO DETECTA EL MODEM Y DEBE COMUNICARSE CON SU PROVEEDOR PARA QUE LE CAMBIE LA RED POR LA QUE TRASMITE EL NUEVO MODEM | T143: VISITA_TÉCNICA | U143: 64 | V143: INTERMEDIA | W143: TERRESTRE | X143: ALVAREZ ARENAS VICTOR HUGO | Y143: 2 | Z143: =IF(T143="SOPORTE_TELEFÓNICO",'TARIFAS 2025'!$B$14,IF(V143="PRINCIPAL",'TARIFAS 2025'!$B$8,IF(V143="INTERMEDIA",'TARIFAS 2025'!$C$8,IF(V143="LEJANA",'TARIFAS 2025'!$D$8)))) -> 172989 | AA143: =Z143*Y143 -> 345978
A144: VILLAVICENCIO | B144: =VLOOKUP(A144,'CENTROS DE COSTOS'!A:D,2,0) -> 0036-0006 | C144: =VLOOKUP(A144,'CENTROS DE COSTOS'!A:D,3,0) -> Wompi Oriente | D144: 50001 | E144: 2987462 | F144: 81456 | G144: INCIDENTE | H144: META | I144: VILLAVICENCIO | J144: DROGUERÍA FARMACÉUTICA EXPRESS | K144: WOMPI | L144: FO-25-1793851 | M144: 45968.333 | N144: 45968.59 | O144: INCIDENTE | P144: CONEXIÓN | Q144: APARECEN ERRORES EN PANTALLA: HUBO UNA DESCONEXION DE LA RED | R144: WIFI | S144: 07/11/2025 SE REALIZA ACTUALIZACIÓN DE APLICACIONE DE EQUIPO VERSION 26.2.5, SE REALIZAN PRUEBAS Y CB QUEDA OPERANDO OK | T144: VISITA_TÉCNICA | U144: 0 | V144: PRINCIPAL | W144: TERRESTRE | X144: PEDREROS CONTRERAS MICHAEL STEVENS | Y144: 1 | Z144: =IF(T144="SOPORTE_TELEFÓNICO",'TARIFAS 2025'!$B$14,IF(V144="PRINCIPAL",'TARIFAS 2025'!$B$8,IF(V144="INTERMEDIA",'TARIFAS 2025'!$C$8,IF(V144="LEJANA",'TARIFAS 2025'!$D$8)))) -> 51282 | AA144: =Z144*Y144 -> 51282
A145: BOGOTA | B145: =VLOOKUP(A145,'CENTROS DE COSTOS'!A:D,2,0) -> 0036-0004 | C145: =VLOOKUP(A145,'CENTROS DE COSTOS'!A:D,3,0) -> Wompi Centro | D145: 11001 | E145: 2987464 | F145: 45991 | G145: INCIDENTE | H145: CUNDINAMARCA | I145: BOGOTA | J145: BARRIO ENGATIVA CENTRO BOGOTA 3 | K145: WOMPI | L145: FO-25-1793844 | M145: 45968.333 | N145: 45968.595 | O145: INCIDENTE | P145: CONEXIÓN | Q145: CONEXIÓN DEFICIENTE WIFI | R145: WIFI | S145: 07/11/2025 SE REALIZA CONFIRMACIÓN DE WIFI, CB REALIZA PRUEBAS DE FUNCIONAMIENTO OK | T145: VISITA_TÉCNICA | U145: 56 | V145: PRINCIPAL | W145: TERRESTRE | X145: MICHELI LOPEZ MIGUEL ANGEL | Y145: 1 | Z145: =IF(T145="SOPORTE_TELEFÓNICO",'TARIFAS 2025'!$B$14,IF(V145="PRINCIPAL",'TARIFAS 2025'!$B$8,IF(V145="INTERMEDIA",'TARIFAS 2025'!$C$8,IF(V145="LEJANA",'TARIFAS 2025'!$D$8)))) -> 51282 | AA145: =Z145*Y145 -> 51282
A146: MANIZALES | B146: =VLOOKUP(A146,'CENTROS DE COSTOS'!A:D,2,0) -> 0036-0002 | C146: =VLOOKUP(A146,'CENTROS DE COSTOS'!A:D,3,0) -> Wompi Eje Cafetero | D146: 17001 | E146: 2982412 | F146: 68804 | G146: INCIDENTE | H146: CALDAS | I146: MANIZALES | J146: CARNICERIA LAS PALMAS | K146: WOMPI | L146: FO-25-1786642 | M146: 45967.385 | N146: 45968.599 | O146: INCIDENTE | P146: CREDENCIALES DE ACCESO (USUARIO/CONTRASEÑA) | Q146: NO FUNCIONA EL USUARIO O CONTRASEÑA | R146: ERROR INICIO DE SESIÓN | S146: 07/11/2025 SE VALIDA CON EL CLIENTE NO LE PERMITE EL INGRESO ASI CAMBIE CONTRASEÑA, SE ESCALA CON WOMPI Y SE VALIDA BORRADO Y RESINATALACION DE APLICACION Y DESPUES DE ESTO EL CLIENTE YA PUEDDE INGRESAR AL DATAFONO | T146: SOPORTE_TELEFÓNICO | U146: 40 | V146: PRINCIPAL | W146: TERRESTRE | X146: HENAO CARDONA DIEGO FERNANDO | Y146: 1 | Z146: =IF(T146="SOPORTE_TELEFÓNICO",'TARIFAS 2025'!$B$14,IF(V146="PRINCIPAL",'TARIFAS 2025'!$B$8,IF(V146="INTERMEDIA",'TARIFAS 2025'!$C$8,IF(V146="LEJANA",'TARIFAS 2025'!$D$8)))) -> 22000 | AA146: =Z146*Y146 -> 22000
A147: PASTO | B147: =VLOOKUP(A147,'CENTROS DE COSTOS'!A:D,2,0) -> 0036-0003 | C147: =VLOOKUP(A147,'CENTROS DE COSTOS'!A:D,3,0) -> Wompi Suroccidente | D147: 52001 | E147: 2988369 | F147: 79822 | G147: INCIDENTE | H147: NARIÑO | I147: PASTO | J147: A Y E DROGUERIA | K147: WOMPI | L147: FO-25-1794748 | M147: 45968.381 | N147: 45968.616 | O147: INCIDENTE | P147: SOFTWARE | Q147: VERSIÓN DESACTUALIZADA | R147: VERSIÓN NO ACTUALIZADA | S147: 07/11/2025 SE VISITA CB. SE ENCUENTRA DATAFONO CON VERSIÓN DESACTUALIZADA. SE REALIZA ACTUALIZACIÓN DE VERSIÓN Y BORRADO DE CACHE. SE REALIZAN PRUEBAS TX Y DE CÓDIGO DE BARRAS EXITOSAS. QUEDA OPERATIVO | T147: VISITA_TÉCNICA | U147: 16 | V147: PRINCIPAL | W147: TERRESTRE | X147: CASTILLO HERRERA ALEX RICARDO | Y147: 1 | Z147: =IF(T147="SOPORTE_TELEFÓNICO",'TARIFAS 2025'!$B$14,IF(V147="PRINCIPAL",'TARIFAS 2025'!$B$8,IF(V147="INTERMEDIA",'TARIFAS 2025'!$C$8,IF(V147="LEJANA",'TARIFAS 2025'!$D$8)))) -> 51282 | AA147: =Z147*Y147 -> 51282
A148: BUCARAMANGA | B148: =VLOOKUP(A148,'CENTROS DE COSTOS'!A:D,2,0) -> 0036-0007 | C148: =VLOOKUP(A148,'CENTROS DE COSTOS'!A:D,3,0) -> Wompi Santander | D148: 68001 | E148: 2985755 | F148: 71344 | G148: INCIDENTE | H148: SANTANDER | I148: BUCARAMANGA | J148: BARRIO CONCORDIA BUCARAMANGA 3 | K148: WOMPI | L148: FO-25-1791561 | M148: 45967.631 | N148: 45968.626 | O148: INCIDENTE | P148: LECTURA | Q148: NO LEE NINGUNA FACTURA | R148: NO LEE CODIGOS DE BARRAS LARGOS | S148: 07/11/2025 SE ESTABLECE CONTACTO TELEFÓNICO CON LA SEÑORA MARTA AL NÚMERO +57 320 9776185 SE PROCEDE REALIZANDO BORRADO DE CACHÉ ACTUALIZACIÓN DE APLICACIÓN REINICIO DEL EQUIPO SE LE INDICAA LA USUARIA DE CÓMO REALIZAR CORRECTAMENTE EL PAGO DE LAS FACTURAS SE REALIZA PRUEBA CON UNA FACTURA POR UN PESO INDICANDO QUE LA TRANSACCIÓN FUE EXITOSA SE LE INDICA A LA CLIENTE QUE EN CASO QUE SE LE PRESENTE ALGÚN INCONVENIENTE SE VUELVA A COMUNICAR NUEVAMENTE LA LÍNEA DE ATENCIÓN 01 8000 95 3344 SE PROCEDE CON EL CIERRE DE LA ACTIVIDAD | T148: SOPORTE_TELEFÓNICO | U148: 24 | V148: PRINCIPAL | W148: TERRESTRE | X148: REYES RAMIREZ DIEGO ALEXANDER | Y148: 1 | Z148: =IF(T148="SOPORTE_TELEFÓNICO",'TARIFAS 2025'!$B$14,IF(V148="PRINCIPAL",'TARIFAS 2025'!$B$8,IF(V148="INTERMEDIA",'TARIFAS 2025'!$C$8,IF(V148="LEJANA",'TARIFAS 2025'!$D$8)))) -> 22000 | AA148: =Z148*Y148 -> 22000
A149: BOGOTA | B149: =VLOOKUP(A149,'CENTROS DE COSTOS'!A:D,2,0) -> 0036-0004 | C149: =VLOOKUP(A149,'CENTROS DE COSTOS'!A:D,3,0) -> Wompi Centro | D149: 11001 | E149: 2989537 | F149: 14690 | G149: INCIDENTE | H149: CUNDINAMARCA | I149: BOGOTÁ | J149: TELECOMUNICACIONES LA CRECIENTE | K149: WOMPI | L149: FO-25-1795537 | M149: 45968.442 | N149: 45968.655 | O149: INCIDENTE | P149: SOFTWARE | Q149: APP ELIMINADA | R149: APP ELIMINADA POR EL CB | S149: 07/11/2025 SE REALIZA COMUNICACIÓN CON LA SEÑORA KAREN MENESES PARA VALIDAR FALLA CLIENTE INDICA QUE BORRÓ POR EQUIVOCACION LA APP DE WOMPI ,SE REALIZA INSTALACIÓN DE FORMA REMOTA ,SE REALIZAN PRUEBAS OK CLIENTE INDICA DATAFONO YA SE ENCUENTRA OPERATIVO | T149: SOPORTE_TELEFÓNICO | U149: 16 | V149: PRINCIPAL | W149: TERRESTRE | X149: GALINDO ROJAS LUIS FELIPE | Y149: 1 | Z149: =IF(T149="SOPORTE_TELEFÓNICO",'TARIFAS 2025'!$B$14,IF(V149="PRINCIPAL",'TARIFAS 2025'!$B$8,IF(V149="INTERMEDIA",'TARIFAS 2025'!$C$8,IF(V149="LEJANA",'TARIFAS 2025'!$D$8)))) -> 22000 | AA149: =Z149*Y149 -> 22000
A150: CALI | B150: =VLOOKUP(A150,'CENTROS DE COSTOS'!A:D,2,0) -> 0036-0003 | C150: =VLOOKUP(A150,'CENTROS DE COSTOS'!A:D,3,0) -> Wompi Suroccidente | D150: 76001 | E150: 2989518 | F150: 76950 | G150: INCIDENTE | H150: VALLE DEL CAUCA | I150: CALI | J150: MONIK COSMETICS | K150: WOMPI | L150: FO-25-1795471 | M150: 45968.439 | N150: 45968.657 | O150: INCIDENTE | P150: SOFTWARE | Q150: APP ELIMINADA | R150: APP ELIMINADA POR EL CB | S150: 07/11/2025 SE VALIDA Y CLIENTE BORRO LA APP POR ERROR, SE ESCALA A WOMPI PARA REINSTALAR APP, SE REINSTALA EXITOSAMENTE | T150: SOPORTE_TELEFÓNICO | U150: 8 | V150: PRINCIPAL | W150: TERRESTRE | X150: HENAO CARDONA DIEGO FERNANDO | Y150: 1 | Z150: =IF(T150="SOPORTE_TELEFÓNICO",'TARIFAS 2025'!$B$14,IF(V150="PRINCIPAL",'TARIFAS 2025'!$B$8,IF(V150="INTERMEDIA",'TARIFAS 2025'!$C$8,IF(V150="LEJANA",'TARIFAS 2025'!$D$8)))) -> 22000 | AA150: =Z150*Y150 -> 22000
A151: BARRANQUILLA | B151: =VLOOKUP(A151,'CENTROS DE COSTOS'!A:D,2,0) -> 0036-0001 | C151: =VLOOKUP(A151,'CENTROS DE COSTOS'!A:D,3,0) -> Wompi Costa | D151: 8141 | E151: 2988139 | F151: 63746 | G151: INCIDENTE | H151: ATLANTICO | I151: CANDELARIA | J151: BARRIO ESPERANZA CANDELARIA | K151: WOMPI | L151: FO-25-1794761 | M151: 45968.359 | N151: 45968.66 | O151: INCIDENTE | P151: CONEXIÓN | Q151: APARECEN ERRORES EN PANTALLA: HUBO UNA DESCONEXION DE LA RED | R151: FALLAS EN CANAL DE COMUNICACIÓN DEL CLIENTE (INTERNET) | S151: 07/11/2025 EN COMUNICACIÓN CON EL SEÑOR YEIFER AL NÚMERO 3004388948, ME INFORMA QUE YA ESTA TRABAJANDO BIEN, QUE EL PROBLEMA ERA EL CANAL DE SU INTERNET, DICE QUE NO ES NECESARIA LA VISITA | T151: SOPORTE_TELEFÓNICO | U151: 40 | V151: INTERMEDIA | W151: TERRESTRE | X151: DE AVILA SIADES ALBERTO ENRIQUE | Y151: 1 | Z151: =IF(T151="SOPORTE_TELEFÓNICO",'TARIFAS 2025'!$B$14,IF(V151="PRINCIPAL",'TARIFAS 2025'!$B$8,IF(V151="INTERMEDIA",'TARIFAS 2025'!$C$8,IF(V151="LEJANA",'TARIFAS 2025'!$D$8)))) -> 22000 | AA151: =Z151*Y151 -> 22000
A152: IBAGUE | B152: =VLOOKUP(A152,'CENTROS DE COSTOS'!A:D,2,0) -> 0036-0006 | C152: =VLOOKUP(A152,'CENTROS DE COSTOS'!A:D,3,0) -> Wompi Oriente | D152: 73001 | E152: 2987272 | F152: 25829 | G152: INCIDENTE | H152: TOLIMA | I152: IBAGUE | J152: BARRIO CENTRO 2 IBAGUE | K152: WOMPI | L152: FO-25-1793846 | M152: 45968.333 | N152: 45968.688 | O152: INCIDENTE | P152: SOFTWARE | Q152: CONFIGURACIÓN GENERAL | R152: VERSIÓN NO ACTUALIZADA | S152: 07/11/2025 SE REALIZA CAMBIO DE DATÁFONO POR DAÑO, SE REALIZA PRUEBAS DE FUNCIONAMIENTO EXITOSAS. ERROR AUTO - INICIALIZACIÓN | T152: VISITA_TÉCNICA | U152: 64 | V152: PRINCIPAL | W152: TERRESTRE | X152: BARRAGAN TAFUR EDWIN ESTEBAN | Y152: 1 | Z152: =IF(T152="SOPORTE_TELEFÓNICO",'TARIFAS 2025'!$B$14,IF(V152="PRINCIPAL",'TARIFAS 2025'!$B$8,IF(V152="INTERMEDIA",'TARIFAS 2025'!$C$8,IF(V152="LEJANA",'TARIFAS 2025'!$D$8)))) -> 51282 | AA152: =Z152*Y152 -> 51282
A153: BOGOTA | B153: =VLOOKUP(A153,'CENTROS DE COSTOS'!A:D,2,0) -> 0036-0004 | C153: =VLOOKUP(A153,'CENTROS DE COSTOS'!A:D,3,0) -> Wompi Centro | D153: 11001 | E153: 2987071 | F153: 47172 | G153: INCIDENTE | H153: CUNDINAMARCA | I153: BOGOTA | J153: BARRIO LA CAPUCHINA BOGOTA 1 | K153: WOMPI | L153: FO-25-1793266 | M153: 45968.333 | N153: 45968.691 | O153: INCIDENTE | P153: CONEXIÓN | Q153: CONEXIÓN DEFICIENTE WIFI | R153: FALLAS EN CANAL DE COMUNICACIÓN DEL CLIENTE (INTERNET) | S153: 07/11/2025 SE LLAMA A LA SEÑORA ANA RUTH 3219087948 Y NOS INDICA QUE YA SOLUCIONO CONECTANDO SE AL INTERNET | T153: SOPORTE_TELEFÓNICO | U153: 64 | V153: PRINCIPAL | W153: TERRESTRE | X153: SOTO LONDOÑO FREDY ALEXANDER | Y153: 1 | Z153: =IF(T153="SOPORTE_TELEFÓNICO",'TARIFAS 2025'!$B$14,IF(V153="PRINCIPAL",'TARIFAS 2025'!$B$8,IF(V153="INTERMEDIA",'TARIFAS 2025'!$C$8,IF(V153="LEJANA",'TARIFAS 2025'!$D$8)))) -> 22000 | AA153: =Z153*Y153 -> 22000
A154: MEDELLIN | B154: =VLOOKUP(A154,'CENTROS DE COSTOS'!A:D,2,0) -> 0036-0005 | C154: =VLOOKUP(A154,'CENTROS DE COSTOS'!A:D,3,0) -> Wompi Noroccidente | D154: 5088 | E154: 2990535 | F154: 71700 | G154: INCIDENTE | H154: ANTIOQUIA | I154: BELLO | J154: BELLO CABAÑAS | K154: WOMPI | L154: FO-25-1796003 | M154: 45968.505 | N154: 45968.696 | O154: INCIDENTE | P154: TRANSACCION ERROR | Q154: UNA MISMA TRX ESTA PRESENTANDO FALLAS | R154: AFECTACIÓN GENERALIZADA DE LOS SERVICIOS | S154: 07/11/2025 SE REALIZA VISITA TÉCNICA EN ATENCIÓN AL INCIDENTE REPORTADO CON EL DATÁFONO WOMPI. EL USUARIO CONFIRMA SU IDENTIFICACIÓN Y MANIFIESTA QUE, EN ALGUNAS TRANSACCIONES, SE PRESENTA UN ERROR AL MOMENTO DE GENERAR EL PIN. DURANTE LA VALIDACIÓN, SE IDENTIFICA QUE EL INCONVENIENTE ESTÁ RELACIONADO CON MÚLTIPLES TOQUES EN LA PANTALLA DURANTE EL INGRESO DEL PIN. SE BRINDA ORIENTACIÓN AL USUARIO SOBRE EL PROCEDIMIENTO CORRECTO PARA DIGITAR EL PIN, INDICANDO QUE DEBE HACERLO CON UN SOLO TOQUE POR NÚMERO, EVITANDO PRESIONAR REPETIDAMENTE LA PANTALLA, YA QUE ESTA ACCIÓN GENERA EL ERROR OBSERVADO. | T154: VISITA_TÉCNICA | U154: 40 | V154: PRINCIPAL | W154: TERRESTRE | X154: MARTINEZ TOVAR OSCAR DAVID | Y154: 1 | Z154: =IF(T154="SOPORTE_TELEFÓNICO",'TARIFAS 2025'!$B$14,IF(V154="PRINCIPAL",'TARIFAS 2025'!$B$8,IF(V154="INTERMEDIA",'TARIFAS 2025'!$C$8,IF(V154="LEJANA",'TARIFAS 2025'!$D$8)))) -> 51282 | AA154: =Z154*Y154 -> 51282
A155: CALI | B155: =VLOOKUP(A155,'CENTROS DE COSTOS'!A:D,2,0) -> 0036-0003 | C155: =VLOOKUP(A155,'CENTROS DE COSTOS'!A:D,3,0) -> Wompi Suroccidente | D155: 19001 | E155: 2986478 | F155: 79829 | G155: INCIDENTE | H155: CAUCA | I155: POPAYAN | J155: BARRIO JIMENA POPAYAN | K155: WOMPI | L155: FO-25-1792952 | M155: 45967.679 | N155: 45968.703 | O155: INCIDENTE | P155: SOFTWARE | Q155: APP ELIMINADA | R155: APP ELIMINADA POR EL CB | S155: 07/11/2025 POR EROR EL CLIENTE BORRO LA APP , SE ESCALA A WOMPI, Y SE ENVIA REISNTALACION DE APLICACION SE CONFIRMA REINSTALACION | T155: SOPORTE_TELEFÓNICO | U155: 16 | V155: LEJANA | W155: TERRESTRE | X155: HENAO CARDONA DIEGO FERNANDO | Y155: 1 | Z155: =IF(T155="SOPORTE_TELEFÓNICO",'TARIFAS 2025'!$B$14,IF(V155="PRINCIPAL",'TARIFAS 2025'!$B$8,IF(V155="INTERMEDIA",'TARIFAS 2025'!$C$8,IF(V155="LEJANA",'TARIFAS 2025'!$D$8)))) -> 22000 | AA155: =Z155*Y155 -> 22000
A156: PEREIRA | B156: =VLOOKUP(A156,'CENTROS DE COSTOS'!A:D,2,0) -> 0036-0002 | C156: =VLOOKUP(A156,'CENTROS DE COSTOS'!A:D,3,0) -> Wompi Eje Cafetero | D156: 63001 | E156: 2984711 | F156: 52799 | G156: INCIDENTE | H156: QUINDIO | I156: ARMENIA | J156: TIENDA LOS DOS TIOS | K156: WOMPI | L156: FO-25-1790111 | M156: 45967.523 | N156: 45968.707 | O156: INCIDENTE | P156: IMPRESIÓN | Q156: ROLLO MAL PUESTO | R156: MALA MANIPULACIÓN DEL DATAFONO | S156: 07/11/2025 SE LLEGA A COMERCIO SE EVIDENCIA QUE ESTÁ CERRADO SE LLAMA A CONTACTO HE INDICA EL CLIENTE QUE TIENE CERRADO POR QUE SALIÓ A UNA CITA MÉDICA PERO INFORMA QUE YA EL DATAFONO LE ESTÁ TRABAJANDO NORMALMENTE QUE CAMBIÓ DE ROLLO Y ME IMPRIMIO CON NORMALIDAD. QUE NO REQUIERE LA VISITA TÉCNICA | T156: VISITA_TÉCNICA | U156: 24 | V156: INTERMEDIA | W156: TERRESTRE | X156: SANCHEZ SOLORZANO JUAN SEBASTIAN | Y156: 1 | Z156: =IF(T156="SOPORTE_TELEFÓNICO",'TARIFAS 2025'!$B$14,IF(V156="PRINCIPAL",'TARIFAS 2025'!$B$8,IF(V156="INTERMEDIA",'TARIFAS 2025'!$C$8,IF(V156="LEJANA",'TARIFAS 2025'!$D$8)))) -> 172989 | AA156: =Z156*Y156 -> 172989
A157: BUCARAMANGA | B157: =VLOOKUP(A157,'CENTROS DE COSTOS'!A:D,2,0) -> 0036-0007 | C157: =VLOOKUP(A157,'CENTROS DE COSTOS'!A:D,3,0) -> Wompi Santander | D157: 68001 | E157: 2987278 | F157: 74163 | G157: INCIDENTE | H157: SANTANDER | I157: BUCARAMANGA | J157: BARRIO COLORADOS BUCARAMANGA | K157: WOMPI | L157: FO-25-1793841 | M157: 45968.333 | N157: 45969.399 | O157: INCIDENTE | P157: CONEXIÓN | Q157: CONEXIÓN DEFICIENTE WIFI | R157: WIFI | S157: 08/11/2025 SE ESTABLECE CONTACTO VIA WHATSAPP CON LA TITULAR LA SEÑORA ANGELA AL NÚMERO +57 310 2879977 QUIEN SE COMUNICA VIA WHATSAPP LUEGO DE QUE LAS ENCARGADAS DEL PUNTO LE DIERAN EL EL NÚMERO DE CONTACTO NOS INDICA QUE SE COMUNICA POR QUE TENIA PROBLEMAS PARA NAVEGAR CON EL INTERNET QUE TENIA DE 2.4 EL CUAL ES MUY LENTO AL COMUNICARSE AL CAC UN ASESOR LE DICE QUE LA FALLA ES POR QUE EL INTERNET QUE TENIA ES BANDA 2.4 Y QUE DEBERÍA ESTAR CONECTADO A LA BANDA 5G A LO CUAL LA CLIENTA SOLICITA QUE AL OPERADOR QUE LE HABILITEN ESTE CANAL Y AL INTENTAR CONECTAR EL EQUIPO NO LE APARECE LA RED SE LE INDICA A LA USUARIA QUE ESTOS EQUIPOS NO FUNCIONAN CON LA BANDA 5G Y QUE DEBE VOLVER A CONECTARSE A LA BANDA 2.4 PARA PODER OPERAR A LO CUAL LA LA CLIENTA INDICA QUE A ESA RED SI ES POSIBLE CONECTARSE PERO FUNCIONA MUY LENTO NOS INDICA QUE SE ENCUENTRA MUY MOLESTA POR EL PESIMO SERVICIO QUE ESTA OFRECIENDO Y LOS INCONVENIENTES QUE ESTA PRESENTADO EL EQUIPO A LO CUAL INDICA QUE SE COMUNICARA NUEVAMENTE AL CAC Y | T157: SOPORTE_TELEFÓNICO | U157: 32 | V157: PRINCIPAL | W157: TERRESTRE | X157: REYES RAMIREZ DIEGO ALEXANDER | Y157: 1 | Z157: =IF(T157="SOPORTE_TELEFÓNICO",'TARIFAS 2025'!$B$14,IF(V157="PRINCIPAL",'TARIFAS 2025'!$B$8,IF(V157="INTERMEDIA",'TARIFAS 2025'!$C$8,IF(V157="LEJANA",'TARIFAS 2025'!$D$8)))) -> 22000 | AA157: =Z157*Y157 -> 22000
A158: BOGOTA | B158: =VLOOKUP(A158,'CENTROS DE COSTOS'!A:D,2,0) -> 0036-0004 | C158: =VLOOKUP(A158,'CENTROS DE COSTOS'!A:D,3,0) -> Wompi Centro | D158: 25805 | E158: 2986826 | F158: 10451 | G158: INCIDENTE | H158: CUNDINAMARCA | I158: TIBACUY | J158: TIBACUY - CUNDINAMARCA | K158: WOMPI | L158: FO-25-1793154 | M158: 45968.333 | N158: 45969.41 | O158: INCIDENTE | P158: LECTOR DE TARJETAS | Q158: NO LEE TARJETAS | R158: OBSTRUCCION DEL LECTOR | S158: 07/11/2025 SE REALIZA LLAMADA A LA SRA LEIDY SERRANO AL CELULAR 3124041530 EN EL QUE CONTESTA Y NOS INFORMA QUE EL DAÑO QUE PRESENTA ES EN EL LECTOR DE BANDA MAGNETICA AL PASAR LA TARJETA EMPRESARIALES LE SALE " ERROR AL LEER TARJETA" SE LE INFOMA QUE REALICE ACTUALIZACIÓN DE APP, BORRE CACHA Y LIMPIE LA TARJETA Y SE EXPLICA LA FORMA CORRECTA PARA EJECUTAR LA TX AL REALIZAR NUEVAS VALIDACIONES ENCONTRAMOS QUE EL DAÑO FUE SOLUCIONADO Y SE PROCEDE A REALIZAR CIERRE DE LA VISITA | T158: SOPORTE_TELEFÓNICO | U158: 24 | V158: INTERMEDIA | W158: TERRESTRE | X158: GALEANO SORIANO JUAN DAVID | Y158: 1 | Z158: =IF(T158="SOPORTE_TELEFÓNICO",'TARIFAS 2025'!$B$14,IF(V158="PRINCIPAL",'TARIFAS 2025'!$B$8,IF(V158="INTERMEDIA",'TARIFAS 2025'!$C$8,IF(V158="LEJANA",'TARIFAS 2025'!$D$8)))) -> 22000 | AA158: =Z158*Y158 -> 22000
A159: BUCARAMANGA | B159: =VLOOKUP(A159,'CENTROS DE COSTOS'!A:D,2,0) -> 0036-0007 | C159: =VLOOKUP(A159,'CENTROS DE COSTOS'!A:D,3,0) -> Wompi Santander | D159: 54385 | E159: 2988323 | F159: 52018 | G159: INCIDENTE | H159: NORTE DE SANTANDER | I159: LA ESPERANZA | J159: BARRIO SAN ROQUE LA ESPERANZA | K159: WOMPI | L159: FO-25-1794755 | M159: 45968.371 | N159: 45969.415 | O159: INCIDENTE | P159: NAVEGACION LENTA | Q159: USUARIO NO PUEDE NAVEGAR ENTRE PANTALLAS O LA APP NO ABRE SE QUEDA CARGANDO | R159: CACHE | S159: 08/11/2025 EN COMUNICACIÓN TELEFÓNICA CON EL SEÑOR MARTÍN VILLAMIZAR SE LE INDICA COMO HACER EL BORRADO DE CACHÉ Y ACTUALIZACION A LA ÚLTIMA VERSIÓN SE REALIZAN PRUEBAS OK | T159: SOPORTE_TELEFÓNICO | U159: 32 | V159: LEJANA | W159: TERRESTRE | X159: MARIÑO PABON JORGE ENRIQUE | Y159: 1 | Z159: =IF(T159="SOPORTE_TELEFÓNICO",'TARIFAS 2025'!$B$14,IF(V159="PRINCIPAL",'TARIFAS 2025'!$B$8,IF(V159="INTERMEDIA",'TARIFAS 2025'!$C$8,IF(V159="LEJANA",'TARIFAS 2025'!$D$8)))) -> 22000 | AA159: =Z159*Y159 -> 22000
A160: PASTO | B160: =VLOOKUP(A160,'CENTROS DE COSTOS'!A:D,2,0) -> 0036-0003 | C160: =VLOOKUP(A160,'CENTROS DE COSTOS'!A:D,3,0) -> Wompi Suroccidente | D160: 52399 | E160: 2989593 | F160: 74008 | G160: INCIDENTE | H160: NARIÑO | I160: LA UNION | J160: BARRIO NIÑO DIOS LA UNION 3 | K160: WOMPI | L160: FO-25-1795464 | M160: 45968.453 | N160: 45969.419 | O160: INCIDENTE | P160: IMPRESIÓN | Q160: ROLLO MAL PUESTO | R160: MALA MANIPULACIÓN DEL DATAFONO | S160: 08/11/2025 SE VALIDA CON EL CLIENTE QUIEN INDICA QUE EL DATAFONO NO LE HABILITA LA OPCION DE IMPRESION, SE LE INDICA REALIZA DE NUEVO LA PUESTA DEL ROLLO Y PERCATARSE QUE QUEDE BIEN PUESTO Y LA TAPA BIEN CERRADA, EL CLIENTE REALIZA LA LABOR Y YA LE PERMITE LA IMPRESION, SE CIERRA EL CASO | T160: SOPORTE_TELEFÓNICO | U160: 24 | V160: LEJANA | W160: TERRESTRE | X160: HENAO CARDONA DIEGO FERNANDO | Y160: 1 | Z160: =IF(T160="SOPORTE_TELEFÓNICO",'TARIFAS 2025'!$B$14,IF(V160="PRINCIPAL",'TARIFAS 2025'!$B$8,IF(V160="INTERMEDIA",'TARIFAS 2025'!$C$8,IF(V160="LEJANA",'TARIFAS 2025'!$D$8)))) -> 22000 | AA160: =Z160*Y160 -> 22000
A161: MEDELLIN | B161: =VLOOKUP(A161,'CENTROS DE COSTOS'!A:D,2,0) -> 0036-0005 | C161: =VLOOKUP(A161,'CENTROS DE COSTOS'!A:D,3,0) -> Wompi Noroccidente | D161: 5789 | E161: 2927879 | F161: 58299 | G161: INCIDENTE | H161: ANTIOQUIA | I161: TAMESIS | J161: BARRIO PARQUE TAMESIS TAMESIS | K161: WOMPI | L161: FO-25-1726292 | M161: 45953.669 | N161: 45969.428 | O161: INCIDENTE | P161: NAVEGACION LENTA | Q161: USUARIO NO PUEDE NAVEGAR ENTRE PANTALLAS O LA APP NO ABRE SE QUEDA CARGANDO | R161: CACHE | S161: 08/11/2025 SE REALIZÓ GESTIÓN TELEFÓNICA SE HABLO CON LA SEÑORA MARTA LILIANA CASTRO SE REALIZA BORRADO DE CACHE Y ACTUALIZA VERSIÓN SE LE HACE SEGUIMIENTO DURANTE 30 MINUTOS NOS INDICA QUE EL DATAFONO MEJORÓ CON EL TEMA DE LA LENTITUD PERO SIN EMBARGO ES ALGO LENTO EN CIERTAS TRANSACCIONES INDICA QUE ESTARÁ ATENTA A LAS ACTUALIZACIONES Y CONTINUARA HACIENDO EL BORRADO DE CACHE SE PROCEDE A CERRAR CASO | T161: SOPORTE_TELEFÓNICO | U161: 64 | V161: LEJANA | W161: TERRESTRE | X161: CASTAÑEDA PALACIO CARLOS FELIPE | Y161: 1 | Z161: =IF(T161="SOPORTE_TELEFÓNICO",'TARIFAS 2025'!$B$14,IF(V161="PRINCIPAL",'TARIFAS 2025'!$B$8,IF(V161="INTERMEDIA",'TARIFAS 2025'!$C$8,IF(V161="LEJANA",'TARIFAS 2025'!$D$8)))) -> 22000 | AA161: =Z161*Y161 -> 22000
A162: BOGOTA | B162: =VLOOKUP(A162,'CENTROS DE COSTOS'!A:D,2,0) -> 0036-0004 | C162: =VLOOKUP(A162,'CENTROS DE COSTOS'!A:D,3,0) -> Wompi Centro | D162: 11001 | E162: 2977589 | F162: 79981 | G162: INCIDENTE | H162: CUNDINAMARCA | I162: BOGOTÁ | J162: CIBER KRONOS | K162: WOMPI | L162: FO-25-1787006 | FO-25-1782080 | M162: 45966.46 | N162: 45969.447 | O162: INCIDENTE | P162: CONEXIÓN | Q162: APARECEN ERRORES EN PANTALLA: HUBO UNA DESCONEXION DE LA RED | R162: FALLAS EN CANAL DE COMUNICACIÓN DEL CLIENTE (INTERNET) | S162: 06/11/2025 SE REALIZA VISITA TÉCNICA A CLIENTE SE VALIDA FALLAS EN NAVEGACIÓN CONECTA WIFI NO NAVEGA CON EL OPERADOR CLARO SE REALIZAN VALIDACIONES EN PC DEL CLIENTE Y CELULAR DEL TÉCNICO Y FUNCIONAN CORRECTAMENTE LA NAVEGACIÓN EN TODO MENOS EN EL DATAFONO SE ESTABLECE COMUNICACIÓN CON EL OPERADOR CLARO PERO NO SÉ PUEDE TENER ACCESO AL MÓDEM SE RECINFIGORA APLICATIVOS WOMPI NO FUNCIONA SE VALIDA CON DATOS DE CELULAR Y EN ESE CASO SI FUNCIONA SE ESCALA CASO A JONATAN SALASAR CON TODAS LAS EVIDENCIAS. 08/11/2025 SE REALIZA VISITA PARA VALIDAR FALLA EQUIPO WOMPI SE CONECTA A LA RED CLARO PERO NO NAVEGA, SE HACE VISITA EN CONJUNTO CON EL TECNICO DEL OPERADOR CLARO DURANTE LA VISITA SE EVIDENCIA QUE EFECTIVAMENTE CON DATOS NAVEGA BIEN Y REALIZA TRANSACCIONES PERO CON LA RED CLIENTE NO SE CONECTA A PESAR DE QUE LOS DEMAS DISPOSITIVOS NAVEGAN BIEN, SE HACE PRUEBA CON COMERCIO VECINO QUE TAMBIEN MANEJA OPERADOR CLARO Y EL EQUIPO NAVEGA Y SE CONECTA ESTABLE SE REALIZAN MULTIPLES PRUEBAS CAMBIANDO RED Y CLAVE P | T162: VISITA_TÉCNICA | U162: 0 | V162: PRINCIPAL | W162: TERRESTRE | X162: ROZO ROZO WILLIAM ASDRUBAL | Y162: 2 | Z162: =IF(T162="SOPORTE_TELEFÓNICO",'TARIFAS 2025'!$B$14,IF(V162="PRINCIPAL",'TARIFAS 2025'!$B$8,IF(V162="INTERMEDIA",'TARIFAS 2025'!$C$8,IF(V162="LEJANA",'TARIFAS 2025'!$D$8)))) -> 51282 | AA162: =Z162*Y162 -> 102564
A163: BUCARAMANGA | B163: =VLOOKUP(A163,'CENTROS DE COSTOS'!A:D,2,0) -> 0036-0007 | C163: =VLOOKUP(A163,'CENTROS DE COSTOS'!A:D,3,0) -> Wompi Santander | D163: 68276 | E163: 2981902 | F163: 81168 | G163: INCIDENTE | H163: SANTANDER | I163: FLORIDABLANCA | J163: BARRIO BELLAVISTA FLORIDABLANCA FLORIDABLACA | K163: WOMPI | L163: FO-25-1786775 | M163: 45967.356 | N163: 45969.459 | O163: INCIDENTE | P163: CREDENCIALES DE ACCESO (USUARIO/CONTRASEÑA) | Q163: NO FUNCIONA EL USUARIO O CONTRASEÑA | R163: ERROR INICIO DE SESIÓN | S163: 07/11/2025 SE ESTABLECE CONTACTO VÍA WHATSAPP CON LA CLIENTA CAMILA ZAFRA QUIEN NOS CONFIRMA QUE PRESENTÓ UNA FALLA AL INTENTAR INGRESAR EL EQUIPO CON LAS CREDENCIALES LE ARROJABA EL ERROR UPS ALGO SALIÓ MAL LUEGO NOS CONFIRMAN HORAS DE LA NOCHE DE QUE EL EQUIPO YA SE ENCUENTRA OPERATIVO Y LE PERMITE INGRESAR NORMALMENTE SE PROCEDE CON EL CIERRE DE LA ACTIVIDAD ACORDE A LAS ACORDE A LAS INDICACIONES DADAS | T163: SOPORTE_TELEFÓNICO | U163: 0 | V163: PRINCIPAL | W163: TERRESTRE | X163: REYES RAMIREZ DIEGO ALEXANDER | Y163: 1 | Z163: =IF(T163="SOPORTE_TELEFÓNICO",'TARIFAS 2025'!$B$14,IF(V163="PRINCIPAL",'TARIFAS 2025'!$B$8,IF(V163="INTERMEDIA",'TARIFAS 2025'!$C$8,IF(V163="LEJANA",'TARIFAS 2025'!$D$8)))) -> 22000 | AA163: =Z163*Y163 -> 22000
A164: MEDELLIN | B164: =VLOOKUP(A164,'CENTROS DE COSTOS'!A:D,2,0) -> 0036-0005 | C164: =VLOOKUP(A164,'CENTROS DE COSTOS'!A:D,3,0) -> Wompi Noroccidente | D164: 5001 | E164: 2993506 | F164: 35402 | G164: INCIDENTE | H164: ANTIOQUIA | I164: MEDELLIN | J164: BARRIO CENTRO BOMBONA MEDELLIN | K164: WOMPI | L164: FO-25-1799188 | M164: 45969.375 | N164: 45969.469 | O164: INCIDENTE | P164: CONEXIÓN | Q164: CONEXIÓN DEFICIENTE WIFI | R164: FALLAS EN CANAL DE COMUNICACIÓN DEL CLIENTE (INTERNET) | S164: 08/11/2025 CLIENTE DEBE CONECTAR RED AL WIFI DEL COLEGIO PORQUE NO TIENEN PERMITIDO TENER OTRA RED, POR LO CUAL, LE GESTIONARON UNA RED A PARTE PARA EL POS YA QUE LA OTRA SE CONGESTIONA CON LOS ESTUDIANTES. QUEDA FUNCIONANDO CORRECTAMENTE Y CON LA ÚLTIMA VERSIÓN. | T164: SOPORTE_TELEFÓNICO | U164: 56 | V164: PRINCIPAL | W164: TERRESTRE | X164: MARIN PIEDRAHITA JIMMY ALEXIS | Y164: 1 | Z164: =IF(T164="SOPORTE_TELEFÓNICO",'TARIFAS 2025'!$B$14,IF(V164="PRINCIPAL",'TARIFAS 2025'!$B$8,IF(V164="INTERMEDIA",'TARIFAS 2025'!$C$8,IF(V164="LEJANA",'TARIFAS 2025'!$D$8)))) -> 22000 | AA164: =Z164*Y164 -> 22000
A165: BUCARAMANGA | B165: =VLOOKUP(A165,'CENTROS DE COSTOS'!A:D,2,0) -> 0036-0007 | C165: =VLOOKUP(A165,'CENTROS DE COSTOS'!A:D,3,0) -> Wompi Santander | D165: 68001 | E165: 2992926 | F165: 81056 | G165: INCIDENTE | H165: SANTANDER | I165: BUCARAMANGA | J165: BARRIO EL PRADO BUCARAMANGA 5 | K165: WOMPI | L165: FO-25-1798121 | M165: 45969.375 | N165: 45969.472 | O165: INCIDENTE | P165: CONEXIÓN | Q165: CONEXIÓN DEFICIENTE WIFI | R165: WIFI | S165: 08/11/2025 SE LLAMA AL CLIENTE PARA ATENDER INCIDENTE, PERO LA SEÑORA CAMILA INDICA QUE ELLA LLAMÓ PERO AL FIN SE PUDO CONECTAR A LA RED Y SEGUIR TRABAJANDO POR LO ANTERIOR NO NECESITA YA EL SOPORTE TÉCNICO Y CANCELA LA VISITA | T165: SOPORTE_TELEFÓNICO | U165: 0 | V165: PRINCIPAL | W165: TERRESTRE | X165: PEÑA DIAZ IVAN YESID | Y165: 1 | Z165: =IF(T165="SOPORTE_TELEFÓNICO",'TARIFAS 2025'!$B$14,IF(V165="PRINCIPAL",'TARIFAS 2025'!$B$8,IF(V165="INTERMEDIA",'TARIFAS 2025'!$C$8,IF(V165="LEJANA",'TARIFAS 2025'!$D$8)))) -> 22000 | AA165: =Z165*Y165 -> 22000
A166: MEDELLIN | B166: =VLOOKUP(A166,'CENTROS DE COSTOS'!A:D,2,0) -> 0036-0005 | C166: =VLOOKUP(A166,'CENTROS DE COSTOS'!A:D,3,0) -> Wompi Noroccidente | D166: 5001 | E166: 2992648 | F166: 53402 | G166: INCIDENTE | H166: ANTIOQUIA | I166: MEDELLIN | J166: BARRIO BELEN SAN BERNARDO MEDELLIN 4 | K166: WOMPI | L166: FO-25-1798070 | M166: 45969.375 | N166: 45969.478 | O166: INCIDENTE | P166: IMPRESIÓN | Q166: ROLLO MAL PUESTO | R166: MALA MANIPULACIÓN DEL DATAFONO | S166: 08/11/2025 SE REALIZA LLAMADA A CLIENTE DEBIDO A FALLA EN IMPRESIÓN, SE LE INDICA REALIZA BORRADO DE CACHE Y ACTUALIZAR A TRAVÉS DEL TEM CALL Y REINICIAR, TAMBIÉN SE LE INDICA VERIFICAR QUE EL ROLLOS ESTÉ COLOCADO CORRECTAMENTE Y QUE LA TAPA ESTÉ CORRECTAMENTE CERRADA, INDICA QUE YA FUNCIONA CORRECTAMENTE SE CIERRA | T166: SOPORTE_TELEFÓNICO | U166: 16 | V166: PRINCIPAL | W166: TERRESTRE | X166: QUINTERO SANCHEZ JUAN SEBASTIAN | Y166: 1 | Z166: =IF(T166="SOPORTE_TELEFÓNICO",'TARIFAS 2025'!$B$14,IF(V166="PRINCIPAL",'TARIFAS 2025'!$B$8,IF(V166="INTERMEDIA",'TARIFAS 2025'!$C$8,IF(V166="LEJANA",'TARIFAS 2025'!$D$8)))) -> 22000 | AA166: =Z166*Y166 -> 22000
A167: PASTO | B167: =VLOOKUP(A167,'CENTROS DE COSTOS'!A:D,2,0) -> 0036-0003 | C167: =VLOOKUP(A167,'CENTROS DE COSTOS'!A:D,3,0) -> Wompi Suroccidente | D167: 52227 | E167: 2992551 | F167: 12257 | G167: INCIDENTE | H167: NARIÑO | I167: CUMBAL | J167: CUMBAL II - NARIÑO | K167: WOMPI | L167: FO-25-1798074 | M167: 45968.705 | N167: 45969.483 | O167: INCIDENTE | P167: CONEXIÓN | Q167: APARECEN ERRORES EN PANTALLA: HUBO UNA DESCONEXION DE LA RED | R167: FALLAS EN CANAL DE COMUNICACIÓN DEL CLIENTE (INTERNET) | S167: 08/11/2025 SE VALIDA CON EL CLIENTE LOS DATAFONO NO LE CONECTAN AL WIFI, SE VALIDA Y SE ENCONTRO PROBLEMAS EN LA RED DEL CLIENTE, SE VALIDA Y EL PROVEEDOR SOLUCIONA EL PROBLEMA Y YA EL CLIENTE PUEDE TRANSAR SIN NOVEDAD | T167: SOPORTE_TELEFÓNICO | U167: 56 | V167: LEJANA | W167: TERRESTRE | X167: HENAO CARDONA DIEGO FERNANDO | Y167: 1 | Z167: =IF(T167="SOPORTE_TELEFÓNICO",'TARIFAS 2025'!$B$14,IF(V167="PRINCIPAL",'TARIFAS 2025'!$B$8,IF(V167="INTERMEDIA",'TARIFAS 2025'!$C$8,IF(V167="LEJANA",'TARIFAS 2025'!$D$8)))) -> 22000 | AA167: =Z167*Y167 -> 22000
A168: BOGOTA | B168: =VLOOKUP(A168,'CENTROS DE COSTOS'!A:D,2,0) -> 0036-0004 | C168: =VLOOKUP(A168,'CENTROS DE COSTOS'!A:D,3,0) -> Wompi Centro | D168: 25793 | E168: 2993325 | F168: 76917 | G168: INCIDENTE | H168: CUNDINAMARCA | I168: TAUSA | J168: BARRIO CENTRO TAUSA | K168: WOMPI | L168: FO-25-1799548 | M168: 45969.394 | N168: 45969.485 | O168: INCIDENTE | P168: CONEXIÓN | Q168: CONEXIÓN DEFICIENTE WIFI | R168: WIFI | S168: 08/11/2025 SE REALIZA COMUNICACIÓN CON LA SEÑORA XIMENA TORRES PARA VALIDAR FALLA CLIENTE INDICA QUE TIENE PROBLEMAS CON EL WIFI ,PERO CUANDO CONECTA EL DATAFONO CON LOS DATOS DEL CELULAR FUNCIONA DE MANERA CORRECTA ,SE LE INDICA REALIZAR VALIDACIONES CON EL OPERADOR DEL INTERNET Y INDICA QUE VA TRABAJAR CON LA CONEXIÓN DE LOS DATOS DEL CELULAR | T168: SOPORTE_TELEFÓNICO | U168: 16 | V168: INTERMEDIA | W168: TERRESTRE | X168: GALINDO ROJAS LUIS FELIPE | Y168: 1 | Z168: =IF(T168="SOPORTE_TELEFÓNICO",'TARIFAS 2025'!$B$14,IF(V168="PRINCIPAL",'TARIFAS 2025'!$B$8,IF(V168="INTERMEDIA",'TARIFAS 2025'!$C$8,IF(V168="LEJANA",'TARIFAS 2025'!$D$8)))) -> 22000 | AA168: =Z168*Y168 -> 22000
A169: MEDELLIN | B169: =VLOOKUP(A169,'CENTROS DE COSTOS'!A:D,2,0) -> 0036-0005 | C169: =VLOOKUP(A169,'CENTROS DE COSTOS'!A:D,3,0) -> Wompi Noroccidente | D169: 5088 | E169: 2992048 | F169: 46990 | G169: INCIDENTE | H169: ANTIOQUIA | I169: BELLO | J169: BARRIO BELLO BELLO 1 | K169: WOMPI | L169: FO-25-1797574 | M169: 45968.667 | N169: 45969.489 | O169: INCIDENTE | P169: SOFTWARE | Q169: VERSIÓN DESACTUALIZADA | R169: VERSIÓN NO ACTUALIZADA | S169: 08/11/2025 SE COMUNICA CON EL USUARIO HE INDICA QUE EL DÍA DE AYER SE ACTUALIZO EL EQUIPO Y ESTÁ TRABAJANDO DESDE LA ACTUALIZACIÓN CON NORMALIDAD. | T169: SOPORTE_TELEFÓNICO | U169: 56 | V169: PRINCIPAL | W169: TERRESTRE | X169: ZAPATA LOPEZ EDWARD ASDRUBAL | Y169: 1 | Z169: =IF(T169="SOPORTE_TELEFÓNICO",'TARIFAS 2025'!$B$14,IF(V169="PRINCIPAL",'TARIFAS 2025'!$B$8,IF(V169="INTERMEDIA",'TARIFAS 2025'!$C$8,IF(V169="LEJANA",'TARIFAS 2025'!$D$8)))) -> 22000 | AA169: =Z169*Y169 -> 22000
A170: MEDELLIN | B170: =VLOOKUP(A170,'CENTROS DE COSTOS'!A:D,2,0) -> 0036-0005 | C170: =VLOOKUP(A170,'CENTROS DE COSTOS'!A:D,3,0) -> Wompi Noroccidente | D170: 5686 | E170: 2993535 | F170: 56741 | G170: INCIDENTE | H170: ANTIOQUIA | I170: SANTA ROSA DE OSOS | J170: BARRIO LA 33 SANTA ROSA DE OSOS | K170: WOMPI | L170: FO-25-1799542 | M170: 45969.404 | N170: 45969.499 | O170: INCIDENTE | P170: NAVEGACION LENTA | Q170: USUARIO NO PUEDE NAVEGAR ENTRE PANTALLAS O LA APP NO ABRE SE QUEDA CARGANDO | R170: CACHE | S170: 08/11/2025 SE REALIZÓ GESTIÓN TELEFÓNICA SE HABLÓ CON LA SEÑORA JESSICA NOS INFORMA QUE EL DATÁFONO SE ENCUENTRA MUY LENTO Y NO LEÍA FACTURAS CON CÓDIGO DE BARRAS SE PROCEDE A HACER ACTUALIZACIÓN Y BORRADO DE MEMORIA CACHÉ SE REALIZARON PRUEBAS EXITOSAS CLIENTE NOS MANIFIESTA QUE EL DATÁFONO ESTÁ LEYENDO FACTURAS Y ES MÁS RÁPIDO EN LAS TRANSACCIONES SE MONITOREÓ DURANTE 30 MINUTOS SE PROCEDE A CERRAR CASO | T170: SOPORTE_TELEFÓNICO | U170: 64 | V170: INTERMEDIA | W170: TERRESTRE | X170: CASTAÑEDA PALACIO CARLOS FELIPE | Y170: 1 | Z170: =IF(T170="SOPORTE_TELEFÓNICO",'TARIFAS 2025'!$B$14,IF(V170="PRINCIPAL",'TARIFAS 2025'!$B$8,IF(V170="INTERMEDIA",'TARIFAS 2025'!$C$8,IF(V170="LEJANA",'TARIFAS 2025'!$D$8)))) -> 22000 | AA170: =Z170*Y170 -> 22000
A171: VALLEDUPAR | B171: =VLOOKUP(A171,'CENTROS DE COSTOS'!A:D,2,0) -> 0036-0001 | C171: =VLOOKUP(A171,'CENTROS DE COSTOS'!A:D,3,0) -> Wompi Costa | D171: 20001 | E171: 2989487 | F171: 80974 | G171: INCIDENTE | H171: CESAR | I171: VALLEDUPAR | J171: BARRIO CENTRO VALLEDUPAR 32 | K171: WOMPI | L171: FO-25-1795460 | M171: 45968.455 | N171: 45969.51 | O171: INCIDENTE | P171: LECTURA | Q171: NO LEE NINGUNA FACTURA | R171: NO LEE CODIGOS DE BARRAS LARGOS | S171: 08/11/2025 SE LLEGA A SITIÓ POR SOLICITUD DE CLIENTE LA CUAL MANIFESTABA QUE EL EQUIPO NO LEE LAS FACTIRAS ,SE LLEGA A SITIO SE LE REALIZA CAPACITACIÓN SOBRE EL MANEJI DE LA CAMARA PARA LEER FACTURAS,SE REALIZAN PRUEBAS QUEDANDO EQUIPO OPERATIVO SE VALIDAN CON VARIAS FACTURAS LA CUAL LAS TOMA SIN DIFICULTAD | T171: VISITA_TÉCNICA | U171: 0 | V171: PRINCIPAL | W171: TERRESTRE | X171: MAESTRE MENGUAL EDGAR ENRIQUE | Y171: 1 | Z171: =IF(T171="SOPORTE_TELEFÓNICO",'TARIFAS 2025'!$B$14,IF(V171="PRINCIPAL",'TARIFAS 2025'!$B$8,IF(V171="INTERMEDIA",'TARIFAS 2025'!$C$8,IF(V171="LEJANA",'TARIFAS 2025'!$D$8)))) -> 51282 | AA171: =Z171*Y171 -> 51282
A172: MEDELLIN | B172: =VLOOKUP(A172,'CENTROS DE COSTOS'!A:D,2,0) -> 0036-0005 | C172: =VLOOKUP(A172,'CENTROS DE COSTOS'!A:D,3,0) -> Wompi Noroccidente | D172: 5001 | E172: 2992516 | F172: 13666 | G172: INCIDENTE | H172: ANTIOQUIA | I172: MEDELLIN | J172: BARRIO CENTRO VI MEDELLIN | K172: WOMPI | L172: FO-25-1797896 | M172: 45968.694 | N172: 45969.515 | O172: INCIDENTE | P172: NAVEGACION LENTA | Q172: USUARIO NO PUEDE NAVEGAR ENTRE PANTALLAS O LA APP NO ABRE SE QUEDA CARGANDO | R172: CACHE | S172: 08/11/2025 SE VISITA POR LENTITUD SE ENCUENTRA ACTUALIZADO SE BORRA CACHE SE REINICIA PRUEBAS OK | T172: VISITA_TÉCNICA | U172: 40 | V172: PRINCIPAL | W172: TERRESTRE | X172: PAREJA ECHAVARRIA JHON DAVID | Y172: 1 | Z172: =IF(T172="SOPORTE_TELEFÓNICO",'TARIFAS 2025'!$B$14,IF(V172="PRINCIPAL",'TARIFAS 2025'!$B$8,IF(V172="INTERMEDIA",'TARIFAS 2025'!$C$8,IF(V172="LEJANA",'TARIFAS 2025'!$D$8)))) -> 51282 | AA172: =Z172*Y172 -> 51282
A173: SINCELEJO | B173: =VLOOKUP(A173,'CENTROS DE COSTOS'!A:D,2,0) -> 0036-0001 | C173: =VLOOKUP(A173,'CENTROS DE COSTOS'!A:D,3,0) -> Wompi Costa | D173: 70823 | E173: 2976453 | F173: 70774 | G173: INCIDENTE | H173: SUCRE | I173: TOLU VIEJO | J173: CENTRO TOU VIEJO SUCRE | K173: WOMPI | L173: FO-25-1781370 | M173: 45966.389 | N173: 45969.515 | O173: INCIDENTE | P173: IMPRESIÓN | Q173: TAPA DE IMPRESORA DESAJUSTADA | R173: MALA MANIPULACIÓN DEL DATAFONO | S173: 08/11/2025 SE VISITA SITIO SE VERIFICA INFORMACIÓN SE REALIZA PRIMEROS AUXILIOS, SE OBSERVA TAPA CON LA BISAGRA DESAJUSTADA, SE REACOMODA EN SU POSICIÓN PARA QUE HAGA PRESIÓN SOBRE EL PAPEL, SE REALIZA PRUEBA TRX EXITOSA. | T173: VISITA_TÉCNICA | U173: 24 | V173: INTERMEDIA | W173: TERRESTRE | X173: SANTOS GUZMAN CHRISTIAN FELIPE | Y173: 1 | Z173: =IF(T173="SOPORTE_TELEFÓNICO",'TARIFAS 2025'!$B$14,IF(V173="PRINCIPAL",'TARIFAS 2025'!$B$8,IF(V173="INTERMEDIA",'TARIFAS 2025'!$C$8,IF(V173="LEJANA",'TARIFAS 2025'!$D$8)))) -> 172989 | AA173: =Z173*Y173 -> 172989
A174: NEIVA | B174: =VLOOKUP(A174,'CENTROS DE COSTOS'!A:D,2,0) -> 0036-0006 | C174: =VLOOKUP(A174,'CENTROS DE COSTOS'!A:D,3,0) -> Wompi Oriente | D174: 41298 | E174: 2987234 | F174: 38241 | G174: INCIDENTE | H174: HUILA | I174: GARZON | J174: BARRIO CENTRO GARZON 4 | K174: WOMPI | L174: FO-25-1793870 | M174: 45968.333 | N174: 45969.517 | O174: INCIDENTE | P174: TRANSACCION ERROR | Q174: VARIAS TRXS ESTAN PRESENTANDO FALLAS | R174: AFECTACIÓN GENERALIZADA DE LOS SERVICIOS | S174: 08/11/2025 SE LLEGA AL PUNTO O SE EVIDENCIA ERROR EN TODAS LAS TRANSACCIONES , SE ACTUALIZA DATAFONO , SE BORRA CACHE , SE BORRA ALMACEMAMIENTO, SE REINICIA , CLIENTE INGRESA CREDENCIALES , SE REALIZA PRUEBAS OK | T174: VISITA_TÉCNICA | U174: 0 | V174: LEJANA | W174: TERRESTRE | X174: ANDRADE HERNANDEZ JUAN CARLOS | Y174: 1 | Z174: =IF(T174="SOPORTE_TELEFÓNICO",'TARIFAS 2025'!$B$14,IF(V174="PRINCIPAL",'TARIFAS 2025'!$B$8,IF(V174="INTERMEDIA",'TARIFAS 2025'!$C$8,IF(V174="LEJANA",'TARIFAS 2025'!$D$8)))) -> 452148 | AA174: =Z174*Y174 -> 452148
A175: BOGOTA | B175: =VLOOKUP(A175,'CENTROS DE COSTOS'!A:D,2,0) -> 0036-0004 | C175: =VLOOKUP(A175,'CENTROS DE COSTOS'!A:D,3,0) -> Wompi Centro | D175: 11001 | E175: 2992930 | F175: 50539 | G175: INCIDENTE | H175: CUNDINAMARCA | I175: BOGOTA | J175: BARRIO RESTREPO BOGOTA 10 | K175: WOMPI | L175: FO-25-1798118 | M175: 45969.375 | N175: 45969.519 | O175: INCIDENTE | P175: CONEXIÓN | Q175: CONEXIÓN DEFICIENTE WIFI | R175: WIFI | S175: 08/11/2025 SE REALIZA COMUNICACIÓN CON EL SEÑOR JESÚS GÓMEZ ZULUAGA PARA VALIDAR FALLA ,CLIENTE INDICA QUE TIENE PROBLEMAS CON LA NAVEGACIÓN DEL INTERNET EN EL DATAFONO ,SE LE INDICA CONECTAR COMPARTIENDO DESDE EL CELULAR Y LE MEJORA LA NAVEGACIÓN,SE LE SUGIERE REALIZAR VALIDACIÓNES CON EL OPERADOR DE INTERNET | T175: SOPORTE_TELEFÓNICO | U175: 16 | V175: PRINCIPAL | W175: TERRESTRE | X175: GALINDO ROJAS LUIS FELIPE | Y175: 1 | Z175: =IF(T175="SOPORTE_TELEFÓNICO",'TARIFAS 2025'!$B$14,IF(V175="PRINCIPAL",'TARIFAS 2025'!$B$8,IF(V175="INTERMEDIA",'TARIFAS 2025'!$C$8,IF(V175="LEJANA",'TARIFAS 2025'!$D$8)))) -> 22000 | AA175: =Z175*Y175 -> 22000
A176: MEDELLIN | B176: =VLOOKUP(A176,'CENTROS DE COSTOS'!A:D,2,0) -> 0036-0005 | C176: =VLOOKUP(A176,'CENTROS DE COSTOS'!A:D,3,0) -> Wompi Noroccidente | D176: 5001 | E176: 2991891 | F176: 49924 | G176: INCIDENTE | H176: ANTIOQUIA | I176: MEDELLIN | J176: BARRIO SANTA CRUZ MEDELLIN 8 | K176: WOMPI | L176: FO-25-1797576 | M176: 45968.66 | N176: 45969.523 | O176: INCIDENTE | P176: CAPACITACIÓN | Q176: MALA MANIPULACIÓN POS | R176: FALTA CAPACITACIÓN USUARIO CB | S176: 08/11/2025 EN COMUNICACIÓN CON EL SEÑOR JULIANA SE LE INDICA EL USO ADECUADO DEL DATAFONO Y EN QUE MOMENTO DE DEBEN COLOCAR LOS PIN DE SEGURIDAD NO HACER MUCHOS INTENTOS YA QUE VAN A PROVOCAR RECHAZOS EN EL DATAFONO. EL CLIENTE LOGRA HACER PRUEBAS EXITOSAS | T176: SOPORTE_TELEFÓNICO | U176: 64 | V176: PRINCIPAL | W176: TERRESTRE | X176: DIAZ ZABALA FRANCIS DUBAN | Y176: 1 | Z176: =IF(T176="SOPORTE_TELEFÓNICO",'TARIFAS 2025'!$B$14,IF(V176="PRINCIPAL",'TARIFAS 2025'!$B$8,IF(V176="INTERMEDIA",'TARIFAS 2025'!$C$8,IF(V176="LEJANA",'TARIFAS 2025'!$D$8)))) -> 22000 | AA176: =Z176*Y176 -> 22000
A177: BOGOTA | B177: =VLOOKUP(A177,'CENTROS DE COSTOS'!A:D,2,0) -> 0036-0004 | C177: =VLOOKUP(A177,'CENTROS DE COSTOS'!A:D,3,0) -> Wompi Centro | D177: 11001 | E177: 2992947 | F177: 72659 | G177: INCIDENTE | H177: CUNDINAMARCA | I177: BOGOTA | J177: VILLA NUEVA BOGOTA 2 | K177: WOMPI | L177: FO-25-1798153 | M177: 45969.375 | N177: 45969.529 | O177: INCIDENTE | P177: RECHAZO GENERAL | Q177: RECHAZO GENERAL | R177: ERROR EN LA APLICACION | S177: 08/11/2025 SE REALIZA ACTUALIZACIÓN AL EQUIPO SE VERIFICA CONEXIÓN A LA RED Y SE PROCEDE A QUITAR LAS PERSONALIZACIONES DEL DATÁFONO QUEDA OPERATIVO | T177: VISITA_TÉCNICA | U177: 16 | V177: PRINCIPAL | W177: TERRESTRE | X177: ALARCON AREVALO JOHAN STIVEN | Y177: 1 | Z177: =IF(T177="SOPORTE_TELEFÓNICO",'TARIFAS 2025'!$B$14,IF(V177="PRINCIPAL",'TARIFAS 2025'!$B$8,IF(V177="INTERMEDIA",'TARIFAS 2025'!$C$8,IF(V177="LEJANA",'TARIFAS 2025'!$D$8)))) -> 51282 | AA177: =Z177*Y177 -> 51282
A178: MEDELLIN | B178: =VLOOKUP(A178,'CENTROS DE COSTOS'!A:D,2,0) -> 0036-0005 | C178: =VLOOKUP(A178,'CENTROS DE COSTOS'!A:D,3,0) -> Wompi Noroccidente | D178: 5001 | E178: 2980769 | F178: 60786 | G178: INCIDENTE | H178: ANTIOQUIA | I178: MEDELLIN | J178: BARRIO SANTA CRUZ MEDELLIN 14 | K178: WOMPI | L178: FO-25-1784879 | M178: 45967.333 | N178: 45969.532 | O178: INCIDENTE | P178: LECTURA | Q178: ERROR LECTURA CODIGO DE BARRAS | R178: NO LEE CODIGOS DE BARRAS LARGOS | S178: 08/11/2025 PROBLEMA CON LECTURA DE CÓDIGOS DE BARRAS EN LOS CUALES SE LE BRINDA RECOMENDACIONES DE MANIPULACIÓN, ILUMINACIÓN Y ORIENTACIÓN EN USO DE POS. SE BRINDAN TODAS LAS INDICACIONES DESPUÉS DE BRINDAR LOS PASOS DE ACTUALIZACIÓN. CLIENTE FINALIZA LLAMADA PARA HACER PRUEBAS CON LA VERSIÓN Y CON LAS INDICACIONES. AUNQUE FUNCIONA YA LA LECTURA, SE REQUIERE UNA MEJORA YA QUE MUCHAS VECES HAY PROBLEMAS EN VARIOS PUNTOS CON LECTURAS DE EPM, ENTRE OTRAS. SE REPITE COMUNICACIÓN CON EL CLIENTE DÓNDE SÍ LE FUNCIONA LA LECTURA DE CÓDIGO DE BARRAS PERO SE VISITA EL SITIO PARA PODER TOMAR PRUEBAS DE QUE AYER LE FUNCIONARON LAS LECTURAS. . | T178: VISITA_TÉCNICA | U178: 32 | V178: PRINCIPAL | W178: TERRESTRE | X178: MARIN PIEDRAHITA JIMMY ALEXIS | Y178: 1 | Z178: =IF(T178="SOPORTE_TELEFÓNICO",'TARIFAS 2025'!$B$14,IF(V178="PRINCIPAL",'TARIFAS 2025'!$B$8,IF(V178="INTERMEDIA",'TARIFAS 2025'!$C$8,IF(V178="LEJANA",'TARIFAS 2025'!$D$8)))) -> 51282 | AA178: =Z178*Y178 -> 51282
A179: MEDELLIN | B179: =VLOOKUP(A179,'CENTROS DE COSTOS'!A:D,2,0) -> 0036-0005 | C179: =VLOOKUP(A179,'CENTROS DE COSTOS'!A:D,3,0) -> Wompi Noroccidente | D179: 5001 | E179: 2993350 | F179: 68504 | G179: INCIDENTE | H179: ANTIOQUIA | I179: MEDELLÍN | J179: EL MANDADO EXPRESS II | K179: WOMPI | L179: FO-25-1799650 | M179: 45969.428 | N179: 45969.534 | O179: INCIDENTE | P179: CONEXIÓN | Q179: APARECEN ERRORES EN PANTALLA: HUBO UNA DESCONEXION DE LA RED | R179: FALLAS EN CANAL DE COMUNICACIÓN DEL CLIENTE (INTERNET) | S179: 08/11/2025 SE COMUNICA CON CLIENTE E INFORMA SOBRE UNOS PERROS EN PANTALLA CUANDO ESTA CONECTADO Y TIENE BUENA SEÑAL DE LA RED, SE LE INDICA BORRAR EL CACHE DE LA APP, ACTUALIZAR A TRAVÉS DEL TEMCAL Y REINICIAR, CLIENTE INFORMA QUE YA LE FUNCIÓN SE CIERRA VISITA | T179: SOPORTE_TELEFÓNICO | U179: 8 | V179: PRINCIPAL | W179: TERRESTRE | X179: QUINTERO SANCHEZ JUAN SEBASTIAN | Y179: 1 | Z179: =IF(T179="SOPORTE_TELEFÓNICO",'TARIFAS 2025'!$B$14,IF(V179="PRINCIPAL",'TARIFAS 2025'!$B$8,IF(V179="INTERMEDIA",'TARIFAS 2025'!$C$8,IF(V179="LEJANA",'TARIFAS 2025'!$D$8)))) -> 22000 | AA179: =Z179*Y179 -> 22000
A180: BUCARAMANGA | B180: =VLOOKUP(A180,'CENTROS DE COSTOS'!A:D,2,0) -> 0036-0007 | C180: =VLOOKUP(A180,'CENTROS DE COSTOS'!A:D,3,0) -> Wompi Santander | D180: 68001 | E180: 2990403 | F180: 74162 | G180: INCIDENTE | H180: SANTANDER | I180: BUCARAMANGA | J180: BARRIO BALCONES DEL SUR BUCARAMANGA | K180: WOMPI | L180: FO-25-1795888 | M180: 45968.494 | N180: 45969.536 | O180: INCIDENTE | P180: TRANSACCION ERROR | Q180: VARIAS TRXS ESTAN PRESENTANDO FALLAS | R180: AFECTACIÓN GENERALIZADA DE LOS SERVICIOS | S180: 08/11/2025 EN COMUNICACIÓN CON CLIENTE SE LE BRINDA LOS PRIMEROS AUXILIOS, BORRADO DE CACHE Y ACTUALIZACIÓN TEM CALL Y LA FALLA PERSISTE, SE VISITA CORRESPONSAL, SE REALIZA CONECTAR ECR POR ERROR CON LA CONEXIÓN, SE ACTUALIZA TEM CALL Y SE HACEN PRUEBAS EXITOSA, CORRESPONSAL QUEDA OPERATIVO. | T180: VISITA_TÉCNICA | U180: 24 | V180: PRINCIPAL | W180: TERRESTRE | X180: MARTINEZ FLOREZ DONIS ALBERTO | Y180: 1 | Z180: =IF(T180="SOPORTE_TELEFÓNICO",'TARIFAS 2025'!$B$14,IF(V180="PRINCIPAL",'TARIFAS 2025'!$B$8,IF(V180="INTERMEDIA",'TARIFAS 2025'!$C$8,IF(V180="LEJANA",'TARIFAS 2025'!$D$8)))) -> 51282 | AA180: =Z180*Y180 -> 51282
A181: CUCUTA | B181: =VLOOKUP(A181,'CENTROS DE COSTOS'!A:D,2,0) -> 0036-0007 | C181: =VLOOKUP(A181,'CENTROS DE COSTOS'!A:D,3,0) -> Wompi Santander | D181: 54001 | E181: 2992345 | F181: 77608 | G181: INCIDENTE | H181: NORTE DE SANTANDER | I181: CUCUTA | J181: BARRIOS PRADOS CLUB CUCUTA | K181: WOMPI | L181: FO-25-1797902 | M181: 45968.685 | N181: 45969.617 | O181: INCIDENTE | P181: NAVEGACION LENTA | Q181: USUARIO NO PUEDE NAVEGAR ENTRE PANTALLAS O LA APP NO ABRE SE QUEDA CARGANDO | R181: CANAL DE COMUNICACIÓN | S181: 08/11/2025 SE LLAMA AL 3042459085 Y SE HABLA CON LA SEÑORA LEIDY MORA LA CUAL NOS INDICA QUE RECIENTEMENTE CAMBIO SU PROVEEDOR DE SERVICIOS DE INTERNET Y ADQUIERO STARLINK LA CUAL MANEJA UNA FRECUENCIA DE WIFI DE 5GHZ, SE LE EXPLICA AL CLIENTE QUE EL DATAFONO NO CUENTA CON ESA FRECUENCIA PARA PODER TRABAJAR Y POR ESO NO LE APARECE LA RED WIFI DE STARLINK, SE LE INDICA CONECTARSE POR EL HOSPOT DEL CELULAR Y REALIZAR PRUEBAS LA CUALES SALEN ÉXITOSAS, LE DEJA OBSERVACIÓN LLAMAR AL PROVEEDOR Y LE CAMBIÉ LA FRECUENCIA AL ROUTER A 2.4 GHZ PARA QUE EL DATAFONO PUEDA TRABAJAR CON EL INTERNET DEL COMERCIO. | T181: SOPORTE_TELEFÓNICO | U181: 32 | V181: PRINCIPAL | W181: TERRESTRE | X181: TORRES MANTILLA JOSE DANIEL | Y181: 1 | Z181: =IF(T181="SOPORTE_TELEFÓNICO",'TARIFAS 2025'!$B$14,IF(V181="PRINCIPAL",'TARIFAS 2025'!$B$8,IF(V181="INTERMEDIA",'TARIFAS 2025'!$C$8,IF(V181="LEJANA",'TARIFAS 2025'!$D$8)))) -> 22000 | AA181: =Z181*Y181 -> 22000
A182: MEDELLIN | B182: =VLOOKUP(A182,'CENTROS DE COSTOS'!A:D,2,0) -> 0036-0005 | C182: =VLOOKUP(A182,'CENTROS DE COSTOS'!A:D,3,0) -> Wompi Noroccidente | D182: 5001 | E182: 2990859 | F182: 49189 | G182: INCIDENTE | H182: ANTIOQUIA | I182: MEDELLIN | J182: BARRIO BELEN LAS VIOLETAS MEDELLIN 1 | K182: WOMPI | L182: FO-25-1796358 | M182: 45968.556 | N182: 45969.622 | O182: INCIDENTE | P182: CONEXIÓN | Q182: CONEXIÓN DEFICIENTE WIFI | R182: FALLAS EN CANAL DE COMUNICACIÓN DEL CLIENTE (INTERNET) | S182: 08/11/2025 SE LLAMA VARIAS VECES AL USUARIO EN LA MAÑANA AL NÚMERO DE LA TA NO CONTESTA, LUEGO SE VUELVE A LLAMAR Y CONTESTA UN USUARIO INDICANDO QUE NO CONOCE A LA TITULAR , SE SOLICITA MÁS NUMERO AL COORDINADOR Y A LOS QUE ME SUMINISTRAN NO CONTESTAN SE HACEN MÁS DE 7 LLAMADAS SIN ÉXITO | T182: SOPORTE_TELEFÓNICO | U182: 56 | V182: PRINCIPAL | W182: TERRESTRE | X182: MONTOYA VELEZ ANDRES FELIPE | Y182: 1 | Z182: =IF(T182="SOPORTE_TELEFÓNICO",'TARIFAS 2025'!$B$14,IF(V182="PRINCIPAL",'TARIFAS 2025'!$B$8,IF(V182="INTERMEDIA",'TARIFAS 2025'!$C$8,IF(V182="LEJANA",'TARIFAS 2025'!$D$8)))) -> 22000 | AA182: =Z182*Y182 -> 22000
A183: CUCUTA | B183: =VLOOKUP(A183,'CENTROS DE COSTOS'!A:D,2,0) -> 0036-0007 | C183: =VLOOKUP(A183,'CENTROS DE COSTOS'!A:D,3,0) -> Wompi Santander | D183: 54313 | E183: 2987344 | F183: 73221 | G183: INCIDENTE | H183: NORTE DE SANTANDER | I183: GRAMALOTE | J183: BARRIO LOS SANTOS GRAMOLETE | K183: WOMPI | L183: FO-25-1793858 | M183: 45968.333 | N183: 45969.625 | O183: INCIDENTE | P183: NAVEGACION LENTA | Q183: USUARIO NO PUEDE NAVEGAR ENTRE PANTALLAS O LA APP NO ABRE SE QUEDA CARGANDO | R183: CANAL DE COMUNICACIÓN | S183: 08/11/2025 SE COMUNICA CON LA SEÑORA ERIKA AL 3133510973 Y SE LE INDICA COMO REALIZAR EL APAGADO DE LA RED 5G DE SU ROUTER, LA CLIENTE REALIZA DIFERENTES PRUEBAS, EL DATAFONO QUEDA OPERATIVO. | T183: SOPORTE_TELEFÓNICO | U183: 0 | V183: INTERMEDIA | W183: TERRESTRE | X183: TORRES MANTILLA JOSE DANIEL | Y183: 1 | Z183: =IF(T183="SOPORTE_TELEFÓNICO",'TARIFAS 2025'!$B$14,IF(V183="PRINCIPAL",'TARIFAS 2025'!$B$8,IF(V183="INTERMEDIA",'TARIFAS 2025'!$C$8,IF(V183="LEJANA",'TARIFAS 2025'!$D$8)))) -> 22000 | AA183: =Z183*Y183 -> 22000
A184: CUCUTA | B184: =VLOOKUP(A184,'CENTROS DE COSTOS'!A:D,2,0) -> 0036-0007 | C184: =VLOOKUP(A184,'CENTROS DE COSTOS'!A:D,3,0) -> Wompi Santander | D184: 54001 | E184: 2989708 | F184: 79511 | G184: INCIDENTE | H184: NORTE DE SANTANDER | I184: CUCUTA | J184: J.C CASTRO S.A.S | K184: WOMPI | L184: FO-25-1795458 | M184: 45968.456 | N184: 45969.649 | O184: INCIDENTE | P184: CONEXIÓN | Q184: CONEXIÓN DEFICIENTE WIFI | R184: WIFI | S184: 08/11/2025 SE COMUNICA CON EL CLIENTE JONATHAN GALVAN AL # 3152344898, SE LE REALIZA EN PROCESO DE ACTUALIZACIÓN Y BORRADO DE CACHE POR MEDIO DE SOPORTE TELEFONICO, CLIENTE INFORMA QUE EL DATAFONO YA FUNCIONA BIEN SIN NOVEDAD. | T184: SOPORTE_TELEFÓNICO | U184: 8 | V184: PRINCIPAL | W184: TERRESTRE | X184: NARANJO AFANADOR RUBEN JESUS | Y184: 1 | Z184: =IF(T184="SOPORTE_TELEFÓNICO",'TARIFAS 2025'!$B$14,IF(V184="PRINCIPAL",'TARIFAS 2025'!$B$8,IF(V184="INTERMEDIA",'TARIFAS 2025'!$C$8,IF(V184="LEJANA",'TARIFAS 2025'!$D$8)))) -> 22000 | AA184: =Z184*Y184 -> 22000
A185: TUNJA | B185: =VLOOKUP(A185,'CENTROS DE COSTOS'!A:D,2,0) -> 0036-0007 | C185: =VLOOKUP(A185,'CENTROS DE COSTOS'!A:D,3,0) -> Wompi Santander | D185: 15403 | E185: 2992748 | F185: 47741 | G185: INCIDENTE | H185: BOYACA | I185: LA UVITA | J185: BARRIO CENTRO LA UVITA | K185: WOMPI | L185: FO-25-1798079 | M185: 45969.375 | N185: 45970.412 | O185: INCIDENTE | P185: CONVENIOS | Q185: LLAME A SU EMISOR | R185: ERROR DE CONFIGURACIÓN | S185: 08/11/2025 SE ESTABLECE COMUNICACION CON LE CLIENTE AL NÚMERO CELULAR 3232932248 OMAIRA NIÑO GALVIS , PARA VALIDAR FALLA , EL CUAL LA CLIENTE INDICA QUE EL CORRESPONSAL SE ENCUENTRA OPERATIVO QUE ERA PROBLEMAS INTERNOS DE LOS CONVENIOS , INDICA QUE CUALQUIER NOVEDAD SE COMUNICARA NUEVAMENTE CON LA ENTIDAD, CLIENTE COMPARTE BAUCHER DEMOSTRANDO QUE EL CB SE ENCUENTRA TRABAJANDO CORRECTAMENTE | T185: SOPORTE_TELEFÓNICO | U185: 0 | V185: LEJANA | W185: TERRESTRE | X185: ALVARADO MORENO CRISTHIAN | Y185: 1 | Z185: =IF(T185="SOPORTE_TELEFÓNICO",'TARIFAS 2025'!$B$14,IF(V185="PRINCIPAL",'TARIFAS 2025'!$B$8,IF(V185="INTERMEDIA",'TARIFAS 2025'!$C$8,IF(V185="LEJANA",'TARIFAS 2025'!$D$8)))) -> 22000 | AA185: =Z185*Y185 -> 22000
A186: MEDELLIN | B186: =VLOOKUP(A186,'CENTROS DE COSTOS'!A:D,2,0) -> 0036-0005 | C186: =VLOOKUP(A186,'CENTROS DE COSTOS'!A:D,3,0) -> Wompi Noroccidente | D186: 5088 | E186: 2993353 | F186: 50310 | G186: INCIDENTE | H186: ANTIOQUIA | I186: BELLO | J186: BARRIO MADERA BELLO 2 | K186: WOMPI | L186: FO-25-1799894 | M186: 45969.432 | N186: 45970.481 | O186: INCIDENTE | P186: LECTURA | Q186: NO LEE NINGUNA FACTURA | R186: SUCIEDAD EN LA CAMARA | S186: 09/11/2025 SE LLAMA MÚLTIPLES VECES AL CLIENTE Y NO CONTESTA, SE VISTA PUNTO EL CUAL SE ENCUENTRA EN UNA UNIDAD CERRADA, SE HABLA A PORTERÍA Y NOS COMETAN QUE NO NOS PUEDEN DEJAR PASAR SIN AUTORIZACIÓN Y QUE EL NEGOCIO AL CUAL VAMOS A IR SE ENCUENTRA CERRADO | T186: VISITA_TÉCNICA | U186: 16 | V186: PRINCIPAL | W186: TERRESTRE | X186: CARDONA MOLINA BROLIN STIVEN | Y186: 1 | Z186: =IF(T186="SOPORTE_TELEFÓNICO",'TARIFAS 2025'!$B$14,IF(V186="PRINCIPAL",'TARIFAS 2025'!$B$8,IF(V186="INTERMEDIA",'TARIFAS 2025'!$C$8,IF(V186="LEJANA",'TARIFAS 2025'!$D$8)))) -> 51282 | AA186: =Z186*Y186 -> 51282
A187: MEDELLIN | B187: =VLOOKUP(A187,'CENTROS DE COSTOS'!A:D,2,0) -> 0036-0005 | C187: =VLOOKUP(A187,'CENTROS DE COSTOS'!A:D,3,0) -> Wompi Noroccidente | D187: 5001 | E187: 2993598 | F187: 34517 | G187: INCIDENTE | H187: ANTIOQUIA | I187: MEDELLIN | J187: BARRIO ROBLEDO MEDELLIN 3 | K187: WOMPI | L187: FO-25-1801875 | M187: 45970.375 | N187: 45970.487 | O187: INCIDENTE | P187: NAVEGACION LENTA | Q187: USUARIO NO PUEDE NAVEGAR ENTRE PANTALLAS O LA APP NO ABRE SE QUEDA CARGANDO | R187: CACHE | S187: 09/11/2025 SE INTENTA CONTACTAR EN MÚLTIPLES OCASIONES SIN ÉXITO, SE VISITA PUNTO Y SE ENCUENTRA CERRADO | T187: VISITA_TÉCNICA | U187: 64 | V187: PRINCIPAL | W187: TERRESTRE | X187: CARDONA MOLINA BROLIN STIVEN | Y187: 1 | Z187: =IF(T187="SOPORTE_TELEFÓNICO",'TARIFAS 2025'!$B$14,IF(V187="PRINCIPAL",'TARIFAS 2025'!$B$8,IF(V187="INTERMEDIA",'TARIFAS 2025'!$C$8,IF(V187="LEJANA",'TARIFAS 2025'!$D$8)))) -> 51282 | AA187: =Z187*Y187 -> 51282
A188: MEDELLIN | B188: =VLOOKUP(A188,'CENTROS DE COSTOS'!A:D,2,0) -> 0036-0005 | C188: =VLOOKUP(A188,'CENTROS DE COSTOS'!A:D,3,0) -> Wompi Noroccidente | D188: 5001 | E188: 2993776 | F188: 12110 | G188: INCIDENTE | H188: ANTIOQUIA | I188: MEDELLIN | J188: BARRIO MANRIQUE ORIENTAL II | K188: WOMPI | L188: FO-25-1801872 | M188: 45970.375 | N188: 45971.396 | O188: INCIDENTE | P188: CREDENCIALES DE ACCESO (USUARIO/CONTRASEÑA) | Q188: NO FUNCIONA EL USUARIO O CONTRASEÑA | R188: ERROR INICIO DE SESIÓN | S188: 10/11/2025 SE VALIDA SOPORTE TELEFÓNICO Y QUIÉN ATIENDE DICE QUE NO PUEDE VALIDAR USUARIO O CAMBIO DE CONTRASEÑA PORQUE QUIEN TIENE EL CORREO ES EL HERMANO Y VA A ESTAR EL DÍA DE MAÑANA, POR LO CUAL ES NECESARIO VOLVER A COMUNICARSE MAÑANA. SE ACUERDA CON LA SEÑORA PARA QUE LLAME NUEVAMENTE YA QUE NO SE PUEDE GESTIONAR DATOS SIN EL CORREO REGISTRADO. | T188: SOPORTE_TELEFÓNICO | U188: 48 | V188: PRINCIPAL | W188: TERRESTRE | X188: MARIN PIEDRAHITA JIMMY ALEXIS | Y188: 1 | Z188: =IF(T188="SOPORTE_TELEFÓNICO",'TARIFAS 2025'!$B$14,IF(V188="PRINCIPAL",'TARIFAS 2025'!$B$8,IF(V188="INTERMEDIA",'TARIFAS 2025'!$C$8,IF(V188="LEJANA",'TARIFAS 2025'!$D$8)))) -> 22000 | AA188: =Z188*Y188 -> 22000
A189: MEDELLIN | B189: =VLOOKUP(A189,'CENTROS DE COSTOS'!A:D,2,0) -> 0036-0005 | C189: =VLOOKUP(A189,'CENTROS DE COSTOS'!A:D,3,0) -> Wompi Noroccidente | D189: 5360 | E189: 2993725 | F189: 33796 | G189: INCIDENTE | H189: ANTIOQUIA | I189: ITAGÜÍ | J189: JUGUETES BUFFALO E INNOVACIÓN | K189: WOMPI | L189: FO-25-1802457 | FO-25-1801353 | M189: 45970.375 | N189: 45971.481 | O189: INCIDENTE | P189: TRANSACCION ERROR | Q189: UNA MISMA TRX ESTA PRESENTANDO FALLAS | R189: AFECTACIÓN GENERALIZADA DE LOS SERVICIOS | S189: 09/11/2025 SE INTENTA BORRAR CACHÉ, ACTUALIZAR EL EQUIPO, CAMBIAR DE RED Y SIGUE ARROJANDO ERROR EN LAS TRANSACCIONES. SE REALIZARA NUEVAMENTE VALIDACIONES MAÑANA QUE SE TENGA SOPORTE DE WOMPI PARA VERIFICACION. 10/11/2025 SE REALIZA ACTUALIZACIÓN DE EQUIPO YA QUE TENÍA ACTUALIZACIONES REPRESADAS, SE INDICA A CLIENTE FORMA CORRECTA DE ACTUALIZAR EL EQUIPO | T189: VISITA_TÉCNICA | U189: 24 | V189: PRINCIPAL | W189: TERRESTRE | X189: HERNANDEZ CHAVARRIA JUAN CAMILO | Y189: 2 | Z189: =IF(T189="SOPORTE_TELEFÓNICO",'TARIFAS 2025'!$B$14,IF(V189="PRINCIPAL",'TARIFAS 2025'!$B$8,IF(V189="INTERMEDIA",'TARIFAS 2025'!$C$8,IF(V189="LEJANA",'TARIFAS 2025'!$D$8)))) -> 51282 | AA189: =Z189*Y189 -> 102564
A190: SINCELEJO | B190: =VLOOKUP(A190,'CENTROS DE COSTOS'!A:D,2,0) -> 0036-0001 | C190: =VLOOKUP(A190,'CENTROS DE COSTOS'!A:D,3,0) -> Wompi Costa | D190: 70717 | E190: 2993526 | F190: 31917 | G190: INCIDENTE | H190: SUCRE | I190: SAN PEDRO | J190: BARRIO AV PRINCIPAL SAN PEDRO | K190: WOMPI | L190: FO-25-1799554 | M190: 45969.39 | N190: 45971.494 | O190: INCIDENTE | P190: CONEXIÓN | Q190: APARECEN ERRORES EN PANTALLA: HUBO UNA DESCONEXION DE LA RED | R190: WIFI | S190: 10/11/2025 EN COMUNICACIÓN CON EL SEÑOR JOSÉ HERNÁNDEZ AL NÚMERO DE CONTACTO 3042931231, ME INFORMA QUE PRESENTA PROBLEMAS CON EL EQUIPO YA QUE LE SALE SIN CONEXIÓN, SE PROCEDE A REALIZAR PRUEBAS, SE DESCARGÓ LA APP Y SE REALIZÓ LA ACTUALIZACIÓN CORRESPONDIENTE ( TEAM CALL ), SE BORRÓ LA CACHE DE LA APLICACIÓN. SE REINICIO EL DISPOSITIVO, SE VERIFICO LA CONEXIÓN WIFI CON EL MÓDEM. RESULTADO: SE CONFIRMO CON EL CLIENTE QUE LA FALLA YA SE LOGRÓ SOLUCIONAR Y EL SERVICIO SE ENCUENTRA FUNCIONANDO CORRECTAMENTE, EL CLIENTE REALIZÓ UNA PRUEBA EXITOSA ( TX DE SALDO ). | T190: SOPORTE_TELEFÓNICO | U190: 0 | V190: INTERMEDIA | W190: TERRESTRE | X190: CACERES HERNANDEZ ANDRES | Y190: 1 | Z190: =IF(T190="SOPORTE_TELEFÓNICO",'TARIFAS 2025'!$B$14,IF(V190="PRINCIPAL",'TARIFAS 2025'!$B$8,IF(V190="INTERMEDIA",'TARIFAS 2025'!$C$8,IF(V190="LEJANA",'TARIFAS 2025'!$D$8)))) -> 22000 | AA190: =Z190*Y190 -> 22000
A191: MONTERIA | B191: =VLOOKUP(A191,'CENTROS DE COSTOS'!A:D,2,0) -> 0036-0001 | C191: =VLOOKUP(A191,'CENTROS DE COSTOS'!A:D,3,0) -> Wompi Costa | D191: 23001 | E191: 2993468 | F191: 56400 | G191: INCIDENTE | H191: CORDOBA | I191: MONTERIA | J191: BARRIO SUCRE MONTERIA 1 | K191: WOMPI | L191: FO-25-1799897 | M191: 45969.431 | N191: 45971.497 | O191: INCIDENTE | P191: CONEXIÓN | Q191: CONEXIÓN DEFICIENTE WIFI | R191: WIFI | S191: 10/11/2025 SE REALIZA VISITA TÉCNICA Y SE REALIZA CONEXIÓN A WIFI YA QUE EL EQUIPO SE ENCUENTRA SIN CONEXIÓN, SE REALIZA PRUEBA Y SE DEJA NUEVAMENTE EL SERVICIO FUNCIONANDO CORRECTAMENTE. SE EXPLICA AL CLIENTE LA CORRECTA CONECTIVIDAD DE WIFI. | T191: VISITA_TÉCNICA | U191: 32 | V191: PRINCIPAL | W191: TERRESTRE | X191: CASSIANI PEREZ RAUL RAMIRO | Y191: 1 | Z191: =IF(T191="SOPORTE_TELEFÓNICO",'TARIFAS 2025'!$B$14,IF(V191="PRINCIPAL",'TARIFAS 2025'!$B$8,IF(V191="INTERMEDIA",'TARIFAS 2025'!$C$8,IF(V191="LEJANA",'TARIFAS 2025'!$D$8)))) -> 51282 | AA191: =Z191*Y191 -> 51282
A192: CUCUTA | B192: =VLOOKUP(A192,'CENTROS DE COSTOS'!A:D,2,0) -> 0036-0007 | C192: =VLOOKUP(A192,'CENTROS DE COSTOS'!A:D,3,0) -> Wompi Santander | D192: 54498 | E192: 2987312 | F192: 79112 | G192: INCIDENTE | H192: NORTE DE SANTANDER | I192: OCAÑA | J192: BARRIO EL CENTRO OCAÑA 7 | K192: WOMPI | L192: FO-25-1793879 | M192: 45968.333 | N192: 45971.531 | O192: INCIDENTE | P192: CONEXIÓN | Q192: APARECEN ERRORES EN PANTALLA: HUBO UNA DESCONEXION DE LA RED | R192: WIFI | S192: 10/11/2025 SE REALIZÓ LLAMADA TELEFÓNICA AL NÚMERO 3227238515 SE HABLÓ CON EL SR CRISTIAN MANIFIESTA QUE FUE PROBLEMAS DEL WIFI, INDICA QUE YA ESTÁ FUNCIONANDO NORMALMENTE EL DATAFONO, SE ADJUNTA PRUEBAS DE VOUCHER WOMPI | T192: SOPORTE_TELEFÓNICO | U192: 0 | V192: LEJANA | W192: TERRESTRE | X192: MORA VEGA JEAMPIER | Y192: 1 | Z192: =IF(T192="SOPORTE_TELEFÓNICO",'TARIFAS 2025'!$B$14,IF(V192="PRINCIPAL",'TARIFAS 2025'!$B$8,IF(V192="INTERMEDIA",'TARIFAS 2025'!$C$8,IF(V192="LEJANA",'TARIFAS 2025'!$D$8)))) -> 22000 | AA192: =Z192*Y192 -> 22000
A193: MEDELLIN | B193: =VLOOKUP(A193,'CENTROS DE COSTOS'!A:D,2,0) -> 0036-0005 | C193: =VLOOKUP(A193,'CENTROS DE COSTOS'!A:D,3,0) -> Wompi Noroccidente | D193: 5197 | E193: 2989687 | F193: 10192 | G193: INCIDENTE | H193: ANTIOQUIA | I193: COCORNA | J193: COCORNA - ANTIOQUIA | K193: WOMPI | L193: FO-25-1800501 | FO-25-1795456 | M193: 45968.457 | N193: 45971.537 | O193: INCIDENTE | P193: SOFTWARE | Q193: VERSIÓN DESACTUALIZADA | R193: VERSIÓN NO ACTUALIZADA | S193: 08/11/2025 EN COMUNICACIÓN CON EL USUARIO NOS MANIFIESTA QUE PRESENTA FALLA AL MOMENTO DE HACER TRXS SE HACE SOPORTE SIN ÉXITO SE INTENTA CONECTADO EL EQUIPO A UN RED WIFI DIFERENTE Y A DATOS MÓVILES SIN ÉXITO. LA FALLA PERSISTE SE REPROGRAMA PARA VISITA TECNICA 10/11/2025 SE HACE VISITA OK SE ACTUALIZA VERSIÓN SE ME HACE UNA PEQUEÑA CAPACITACIÓN AL USUARIO DE COMO ES EL MANEJO DEL EQUIPO. SE RESPONDEN PREGUNTAS Y SE CON LA AUTUALIZACION DE LA APP SE PUEDEN HACER MOVIMIENTOS OK | T193: VISITA_TÉCNICA | U193: 0 | V193: INTERMEDIA | W193: TERRESTRE | X193: DIAZ ZABALA FRANCIS DUBAN | Y193: 1 | Z193: =IF(T193="SOPORTE_TELEFÓNICO",'TARIFAS 2025'!$B$14,IF(V193="PRINCIPAL",'TARIFAS 2025'!$B$8,IF(V193="INTERMEDIA",'TARIFAS 2025'!$C$8,IF(V193="LEJANA",'TARIFAS 2025'!$D$8)))) -> 172989 | AA193: =Z193*Y193 -> 172989
A194: BOGOTA | B194: =VLOOKUP(A194,'CENTROS DE COSTOS'!A:D,2,0) -> 0036-0004 | C194: =VLOOKUP(A194,'CENTROS DE COSTOS'!A:D,3,0) -> Wompi Centro | D194: 11001 | E194: 2859361 | F194: 75743 | G194: INCIDENTE | H194: CUNDINAMARCA | I194: BOGOTA | J194: BARRIO NUEVO CORINTO BOGOTA | K194: WOMPI | L194: FO-25-1699864 | FO-25-1648441 | M194: 45938.662 | N194: 45971.562 | O194: INCIDENTE | P194: NAVEGACION LENTA | Q194: USUARIO NO PUEDE NAVEGAR ENTRE PANTALLAS O LA APP NO ABRE SE QUEDA CARGANDO | R194: CACHE | S194: 17/10/2025 SE EFECTÚA GESTIÓN TELEFÓNICA A LA LÍNEA 3134192895 ATIENDE SRA ANA QUIÉN CONFIRMA EL DATAFONO LLEVA DOS DÍAS PRESENTANDO LENTITUD AL NAVEGAR EN LA APP DE WOMPI,SE VÁLIDA VERSION26.0.2-NEXT.0 SE REALIZA BORRADO DE CACHÉ Y SE BORRA RED WIFI , SE CONECTA DE NUEVO A RED WIFI ,SE REINICIA EQUIPO Y AL CARGAR ESTE SIGUE PRESENTANDO LA MISMA NOVEDAD AL NAVEGAR SE ESCALA CASO CON WOMPI , SE EFECTUA GESTION TELEFONICA CON CLIENTE A LA LINEA 3134192895 QUIEN CONFIRMA AUN SE PRESENTA LA NOVEDAD CON LAS TRANSACCIONES , LA SEMANA PASADA LE ESCALARON UN CASO Y AUN NO RECIBE RESPUESTA , SE INDICA A CLIENTE NOVEDAD DE FALLA MASIVA CON EL SISTEMA LA CUAL ESTA EN PROCESO DE SOLUCION POR PARTE DEL AREA TECNICA INDICA QUE LA UNICA SOLUCION QUE LE DAN ES BORRAR CACHE Y ESTE PROCESO SE VOLVIO MUY REPETITIVO Y NECESITA UNA SOLUCION PRONTA YA QUE NO ESTA MUY AGUSTO CON EL NUEVO EQUIPO INSTALADO Y FINALIZA LLAMADA 10/11/2025 SE REALIZA BORRADO DE CACHÉ REINICIO AL EQUIPO EQUIPO QUEDA FUNCIONANDO CORRECTAMENTE | T194: VISITA_TÉCNICA | U194: 64 | V194: PRINCIPAL | W194: TERRESTRE | X194: GONZALEZ FANDIÑO SANTIAGO ERNESTO | Y194: 2 | Z194: =IF(T194="SOPORTE_TELEFÓNICO",'TARIFAS 2025'!$B$14,IF(V194="PRINCIPAL",'TARIFAS 2025'!$B$8,IF(V194="INTERMEDIA",'TARIFAS 2025'!$C$8,IF(V194="LEJANA",'TARIFAS 2025'!$D$8)))) -> 51282 | AA194: =Z194*Y194 -> 102564
A195: TUNJA | B195: =VLOOKUP(A195,'CENTROS DE COSTOS'!A:D,2,0) -> 0036-0007 | C195: =VLOOKUP(A195,'CENTROS DE COSTOS'!A:D,3,0) -> Wompi Santander | D195: 15759 | E195: 2988662 | F195: 81442 | G195: INCIDENTE | H195: BOYACA | I195: SOGAMOSO | J195: Farma Express Sogamoso | K195: WOMPI | L195: FO-25-1794743 | M195: 45968.39 | N195: 45971.602 | O195: INCIDENTE | P195: CONEXIÓN | Q195: CONEXIÓN DEFICIENTE WIFI | R195: FALLAS EN CANAL DE COMUNICACIÓN DEL CLIENTE (INTERNET) | S195: 10/11/2025 SE VISITA CB MANTENIMIENTO DE EQUIPO....BORRADO CACHE Y TELL CAM.. PRUEBAS OK | T195: VISITA_TÉCNICA | U195: 0 | V195: INTERMEDIA | W195: TERRESTRE | X195: GONZALEZ GONZALEZ MARIO ALBERTO | Y195: 1 | Z195: =IF(T195="SOPORTE_TELEFÓNICO",'TARIFAS 2025'!$B$14,IF(V195="PRINCIPAL",'TARIFAS 2025'!$B$8,IF(V195="INTERMEDIA",'TARIFAS 2025'!$C$8,IF(V195="LEJANA",'TARIFAS 2025'!$D$8)))) -> 172989 | AA195: =Z195*Y195 -> 172989
A196: BOGOTA | B196: =VLOOKUP(A196,'CENTROS DE COSTOS'!A:D,2,0) -> 0036-0004 | C196: =VLOOKUP(A196,'CENTROS DE COSTOS'!A:D,3,0) -> Wompi Centro | D196: 11001 | E196: 2991888 | F196: 68743 | G196: INCIDENTE | H196: CUNDINAMARCA | I196: BOGOTA | J196: TESORO BOGOTA5 | K196: WOMPI | L196: FO-25-1797578 | M196: 45968.66 | N196: 45971.608 | O196: INCIDENTE | P196: NAVEGACION LENTA | Q196: USUARIO NO PUEDE NAVEGAR ENTRE PANTALLAS O LA APP NO ABRE SE QUEDA CARGANDO | R196: CACHE | S196: 10/11/2025 SE REALIZA VISITA A COMERCIO, SE VALIDA EQUIPO OPERANDO CON LENTITUD, SE PROCEDE A REALIZAR ACTUALIZACIÓN Y BORRADO DE CACHE, SE CORRIGE TECLADO (ENGLISH), SE REALIZA PRUEBAS CON CLIENTES OPERANDO CON NORMALIDAD A CONFORMIDAD DEL USUARIO. | T196: VISITA_TÉCNICA | U196: 24 | V196: PRINCIPAL | W196: TERRESTRE | X196: ARIAS QUILINDO JULIAN | Y196: 1 | Z196: =IF(T196="SOPORTE_TELEFÓNICO",'TARIFAS 2025'!$B$14,IF(V196="PRINCIPAL",'TARIFAS 2025'!$B$8,IF(V196="INTERMEDIA",'TARIFAS 2025'!$C$8,IF(V196="LEJANA",'TARIFAS 2025'!$D$8)))) -> 51282 | AA196: =Z196*Y196 -> 51282
A197: MEDELLIN | B197: =VLOOKUP(A197,'CENTROS DE COSTOS'!A:D,2,0) -> 0036-0005 | C197: =VLOOKUP(A197,'CENTROS DE COSTOS'!A:D,3,0) -> Wompi Noroccidente | D197: 5001 | E197: 2995819 | F197: 77268 | G197: INCIDENTE | H197: ANTIOQUIA | I197: MEDELLIN | J197: BARRIO ACEVEDO MEDELLIN | K197: WOMPI | L197: FO-25-1805103 | M197: 45971.43 | N197: 45971.612 | O197: INCIDENTE | P197: IMPRESIÓN | Q197: SUCIEDAD EN IMPRESORA | R197: MALA MANIPULACIÓN DEL DATAFONO | S197: 10/11/2025 SE LLAMA AL CLIENTE AL 3217630067 Y SE HABLA CON LA SEÑORA MÓNICA LA CUAL SE LE EXPLICA CÓMO LIMPIAR SENSOR DE IMPRESIÓN A LO CUAL INFORMA QUE YA DEJÓ IMPRIMIR POR LO QUE SE CIERRA ACTIVIDAD | T197: SOPORTE_TELEFÓNICO | U197: 64 | V197: PRINCIPAL | W197: TERRESTRE | X197: ALVAREZ ARENAS VICTOR HUGO | Y197: 1 | Z197: =IF(T197="SOPORTE_TELEFÓNICO",'TARIFAS 2025'!$B$14,IF(V197="PRINCIPAL",'TARIFAS 2025'!$B$8,IF(V197="INTERMEDIA",'TARIFAS 2025'!$C$8,IF(V197="LEJANA",'TARIFAS 2025'!$D$8)))) -> 22000 | AA197: =Z197*Y197 -> 22000
A198: CALI | B198: =VLOOKUP(A198,'CENTROS DE COSTOS'!A:D,2,0) -> 0036-0003 | C198: =VLOOKUP(A198,'CENTROS DE COSTOS'!A:D,3,0) -> Wompi Suroccidente | D198: 76001 | E198: 2995712 | F198: 79364 | G198: INCIDENTE | H198: VALLE DEL CAUCA | I198: CALI | J198: BARRIO CIUDAD JARDIN CALI 3 | K198: WOMPI | L198: FO-25-1805107 | M198: 45971.424 | N198: 45971.624 | O198: INCIDENTE | P198: CONEXIÓN | Q198: CONEXIÓN DEFICIENTE WIFI | R198: FALLAS EN CANAL DE COMUNICACIÓN DEL CLIENTE (INTERNET) | S198: 10/11/2025 SE LLEGA AL COMERCIO CLIENTE NO PUEDE INGRESAR A CONFIGURACIÓN SE LE DA LA CLAVE Y QUEDA FUNCIONANDO CORRECTAMENTE | T198: VISITA_TÉCNICA | U198: 8 | V198: PRINCIPAL | W198: TERRESTRE | X198: CUERO RUIZ JHONNY | Y198: 1 | Z198: =IF(T198="SOPORTE_TELEFÓNICO",'TARIFAS 2025'!$B$14,IF(V198="PRINCIPAL",'TARIFAS 2025'!$B$8,IF(V198="INTERMEDIA",'TARIFAS 2025'!$C$8,IF(V198="LEJANA",'TARIFAS 2025'!$D$8)))) -> 51282 | AA198: =Z198*Y198 -> 51282
A199: BOGOTA | B199: =VLOOKUP(A199,'CENTROS DE COSTOS'!A:D,2,0) -> 0036-0004 | C199: =VLOOKUP(A199,'CENTROS DE COSTOS'!A:D,3,0) -> Wompi Centro | D199: 11001 | E199: 2996454 | F199: 68467 | G199: INCIDENTE | H199: CUNDINAMARCA | I199: BOGOTA | J199: BARRIO EDUARDO SANTOS BOGOTA 7 | K199: WOMPI | L199: FO-25-1805567 | M199: 45971.484 | N199: 45971.672 | O199: INCIDENTE | P199: CREDENCIALES DE ACCESO (USUARIO/CONTRASEÑA) | Q199: USUARIO NO PUEDE NAVEGAR ENTRE PANTALLAS O LA APP NO ABRE SE QUEDA CARGANDO | R199: MEMORIA LLENA | S199: 11/11/2025 SERVICIO OK SE REALIZA VISITA, DONDE EL CB INDICA QUE YA PUDIERON RESTABLECER LA CLAVE DEL DATÁFONO, EL DATÁFONO SE ENCUENTRA FUNCIONANDO BIEN EL CB REALIZA PRUEBAS OK | T199: VISITA_TÉCNICA | U199: 24 | V199: PRINCIPAL | W199: TERRESTRE | X199: MICHELI LOPEZ MIGUEL ANGEL | Y199: 1 | Z199: =IF(T199="SOPORTE_TELEFÓNICO",'TARIFAS 2025'!$B$14,IF(V199="PRINCIPAL",'TARIFAS 2025'!$B$8,IF(V199="INTERMEDIA",'TARIFAS 2025'!$C$8,IF(V199="LEJANA",'TARIFAS 2025'!$D$8)))) -> 51282 | AA199: =Z199*Y199 -> 51282
A200: BOGOTA | B200: =VLOOKUP(A200,'CENTROS DE COSTOS'!A:D,2,0) -> 0036-0004 | C200: =VLOOKUP(A200,'CENTROS DE COSTOS'!A:D,3,0) -> Wompi Centro | D200: 25754 | E200: 2994100 | F200: 53460 | G200: INCIDENTE | H200: CUNDINAMARCA | I200: SOACHA | J200: BARRIO OLIVOS SEGUNDO SECTOR SOACHA | K200: WOMPI | L200: FO-25-1802537 | M200: 45971.333 | N200: 45971.676 | O200: INCIDENTE | P200: NAVEGACION LENTA | Q200: USUARIO NO PUEDE NAVEGAR ENTRE PANTALLAS O LA APP NO ABRE SE QUEDA CARGANDO | R200: CACHE | S200: 10/11/2025 14:20 SE REALIZA PRIMER LLAMADA PARA SOPORTE AL NÚMERO 3123165930 NO CONTESTAN 15:00 SE REALIZA SEGUNDO CONTACTO CON CLIENTE PARA REALIZAR BORRADO DE CACHE Y ACTUALIZACIÓN DE LA APP AL MISMO NÚMERO CONTACTANDO AL SEÑOR VICTOR ROMERO SE REALIZA PROCESO TEAM CALL PARA ACTUALIZAR QUEDANDO ACTUALIZADO EXITOSA SE INDICA A CLIENTE QUE PUEDE USARLO SIN PROBLEMAS Y LA RECOMENDACIÓN DE BORRADO DE CACHE CLIENTE ENTIENDE Y AGRADECE INDICA QUE QUEDA OPERATIVO | T200: SOPORTE_TELEFÓNICO | U200: 0 | V200: PRINCIPAL | W200: TERRESTRE | X200: BUSTOS MORA DIEGO MANUEL | Y200: 1 | Z200: =IF(T200="SOPORTE_TELEFÓNICO",'TARIFAS 2025'!$B$14,IF(V200="PRINCIPAL",'TARIFAS 2025'!$B$8,IF(V200="INTERMEDIA",'TARIFAS 2025'!$C$8,IF(V200="LEJANA",'TARIFAS 2025'!$D$8)))) -> 22000 | AA200: =Z200*Y200 -> 22000
A201: MEDELLIN | B201: =VLOOKUP(A201,'CENTROS DE COSTOS'!A:D,2,0) -> 0036-0005 | C201: =VLOOKUP(A201,'CENTROS DE COSTOS'!A:D,3,0) -> Wompi Noroccidente | D201: 5789 | E201: 2993561 | F201: 60299 | G201: INCIDENTE | H201: ANTIOQUIA | I201: TAMESIS | J201: BARRIO TAMESIS TAMESIS 1 | K201: WOMPI | L201: FO-25-1800287 | M201: 45969.478 | N201: 45971.678 | O201: INCIDENTE | P201: CONEXIÓN | Q201: CONEXIÓN DEFICIENTE WIFI | R201: WIFI | S201: 10/11/2025 SE CONTACTA A USUARIO JUAN DIEGO PALACIO - 3234008903 EL CUAL INFORMA TRABAJAR SIN PROBLEMAS, SE CIERRA ACTIVIDAD, CB ESTA OPERATIVO | T201: SOPORTE_TELEFÓNICO | U201: 16 | V201: LEJANA | W201: TERRESTRE | X201: HERNANDEZ CHAVARRIA JUAN CAMILO | Y201: 1 | Z201: =IF(T201="SOPORTE_TELEFÓNICO",'TARIFAS 2025'!$B$14,IF(V201="PRINCIPAL",'TARIFAS 2025'!$B$8,IF(V201="INTERMEDIA",'TARIFAS 2025'!$C$8,IF(V201="LEJANA",'TARIFAS 2025'!$D$8)))) -> 22000 | AA201: =Z201*Y201 -> 22000
A202: BOGOTA | B202: =VLOOKUP(A202,'CENTROS DE COSTOS'!A:D,2,0) -> 0036-0004 | C202: =VLOOKUP(A202,'CENTROS DE COSTOS'!A:D,3,0) -> Wompi Centro | D202: 25290 | E202: 2993393 | F202: 80147 | G202: INCIDENTE | H202: CUNDINAMARCA | I202: FUSAGASUGA | J202: BARRIO URBANIZACION PARQUE LOS CAMBULOS FUSAGASUGA | K202: WOMPI | L202: FO-25-1800591 | M202: 45969.53 | N202: 45971.687 | O202: INCIDENTE | P202: IMPRESIÓN | Q202: USUARIO NO PUEDE NAVEGAR ENTRE PANTALLAS O LA APP NO ABRE SE QUEDA CARGANDO | R202: MALA MANIPULACIÓN DEL DATAFONO | S202: 10/11/2025 PRIMER INTENTO COMUNICACION #3128830193 9:59 AM FALLIDO SEGUNDO INTENTO COMUNICACION #3128830193 10:20 AM FALLIDO TERCER INTENTO COMUNICACION #3128830193 10:49 AM FALLIDO SE ATIENDE EVITA HOY LUNES POR QUÉ EL SÁBADO NO CONTAMOS CON SOPORTE DE WOMPI SE REALIZA CONTACTÓ TELÉFONICO CON LA SEÑORA EMILCE TORRES LA CUAL NOS INDICA QUE EL SERVICIO DEL CB SE ENCUENTRA OPERATIVO DESDE QUE LE PRESTARON LOS PRIMEROS AUXILIOS EN LA LLAMA AL CAC MANIFIESTA QUE NO ES NECESARIA LA VISITA SE LE INFORMA LO SUCEDIDO AL COORDINADOR WILLIAM ROZO QUIEN AUTORIZA | T202: SOPORTE_TELEFÓNICO | U202: 0 | V202: INTERMEDIA | W202: TERRESTRE | X202: HERNANDEZ NARANJO OSCAR EDUARDO | Y202: 1 | Z202: =IF(T202="SOPORTE_TELEFÓNICO",'TARIFAS 2025'!$B$14,IF(V202="PRINCIPAL",'TARIFAS 2025'!$B$8,IF(V202="INTERMEDIA",'TARIFAS 2025'!$C$8,IF(V202="LEJANA",'TARIFAS 2025'!$D$8)))) -> 22000 | AA202: =Z202*Y202 -> 22000
A203: PASTO | B203: =VLOOKUP(A203,'CENTROS DE COSTOS'!A:D,2,0) -> 0036-0003 | C203: =VLOOKUP(A203,'CENTROS DE COSTOS'!A:D,3,0) -> Wompi Suroccidente | D203: 52079 | E203: 2993546 | F203: 56774 | G203: INCIDENTE | H203: NARIÑO | I203: BARBACOAS | J203: BARRIO SAN ANTONIO BARBACOAS | K203: WOMPI | L203: FO-25-1799900 | M203: 45969.431 | N203: 45971.7 | O203: INCIDENTE | P203: NAVEGACION LENTA | Q203: USUARIO NO PUEDE NAVEGAR ENTRE PANTALLAS O LA APP NO ABRE SE QUEDA CARGANDO | R203: CACHE | S203: 10/11/2025 SE REALIZA VALIDACION CON EL CLIENTE, SE VALIDA CON WOMPI Y DADO LA ULTIMA ACTUALIZACION LOS MOVIMIENTOS SOLO SE VISUALIZARAN EN EL DATAFONO , DE LAS ULTIMAS 6 HORAS, YA NO APARECERÁN DE VARIOS DÍAS. | T203: SOPORTE_TELEFÓNICO | U203: 0 | V203: LEJANA | W203: TERRESTRE | X203: HENAO CARDONA DIEGO FERNANDO | Y203: 1 | Z203: =IF(T203="SOPORTE_TELEFÓNICO",'TARIFAS 2025'!$B$14,IF(V203="PRINCIPAL",'TARIFAS 2025'!$B$8,IF(V203="INTERMEDIA",'TARIFAS 2025'!$C$8,IF(V203="LEJANA",'TARIFAS 2025'!$D$8)))) -> 22000 | AA203: =Z203*Y203 -> 22000
A204: PEREIRA | B204: =VLOOKUP(A204,'CENTROS DE COSTOS'!A:D,2,0) -> 0036-0002 | C204: =VLOOKUP(A204,'CENTROS DE COSTOS'!A:D,3,0) -> Wompi Eje Cafetero | D204: 66001 | E204: 2994841 | F204: 80907 | G204: INCIDENTE | H204: RISARALDA | I204: PEREIRA | J204: BARRIO CENTRO PEREIRA 52 | K204: WOMPI | L204: FO-25-1804861 | M204: 45971.373 | N204: 45971.708 | O204: INCIDENTE | P204: EQUIPO | Q204: DATAFONO NO ENCIENDE | R204: FUENTE DE PODER | S204: 10/11/2025 SE VALIDA CON EL CLIENTE QUIEN INDICA QUE EL CARGADOR SE DAÑO, YA SE LE HABIA DICHO QUE PODIA UTILIZAR EL CARGADOR DEL CELULAR, ELLA LO UTILIZA PERO INDICA QUE EL CONECTOR DEL CARGADOR SE RECALIENTE MUCHO, SE LE INDICA QUE SI LO ESTA USANDO CON EL CABLE DE CARGA QUE TRAE EL DATAFONO DICE QUE NO SE LE INDICA UTLIZAR CON ESTE, LA USUARIA LO UTILIZA CON EL CABLE DEL DATAFONO Y EL CONECTOR DEL CELULAR, EL CLIENTE CONFIRMA QUE YA NO SE RECALIENTA Y ESTA CARGANDO MEJOR. | T204: SOPORTE_TELEFÓNICO | U204: 0 | V204: PRINCIPAL | W204: TERRESTRE | X204: HENAO CARDONA DIEGO FERNANDO | Y204: 1 | Z204: =IF(T204="SOPORTE_TELEFÓNICO",'TARIFAS 2025'!$B$14,IF(V204="PRINCIPAL",'TARIFAS 2025'!$B$8,IF(V204="INTERMEDIA",'TARIFAS 2025'!$C$8,IF(V204="LEJANA",'TARIFAS 2025'!$D$8)))) -> 22000 | AA204: =Z204*Y204 -> 22000
A205: MEDELLIN | B205: =VLOOKUP(A205,'CENTROS DE COSTOS'!A:D,2,0) -> 0036-0005 | C205: =VLOOKUP(A205,'CENTROS DE COSTOS'!A:D,3,0) -> Wompi Noroccidente | D205: 5001 | E205: 2992796 | F205: 67519 | G205: INCIDENTE | H205: ANTIOQUIA | I205: MEDELLIN | J205: BARRIO CASTILLA MEDELLIN 8 | K205: WOMPI | L205: FO-25-1800088 | FO-25-1799203 | M205: 45969.375 | N205: 45971.711 | O205: INCIDENTE | P205: SOFTWARE | Q205: APP ELIMINADA | R205: APP ELIMINADA POR EL CB | S205: 08/11/2025 TICKET N° (478033) CASO LINEACOM INCIDENTE 67519 SE INTENTA HACER DESCARGA DE ACTUALIZACIÓN CON EL FIN DE VOLVER A HACER LA INSTALACIÓN DE LA APP DE WOMPY YA QUE EL CORRESPONSAL INDICA QUE SE DESINSTALO, DESPUÉS DE LA DESCARGA NO SE INSTALA LA APP SE ESCALA PARA QUE HABILITEN DESCARGA Y INSTALAR AL APP DE WOMPY SERIAL: 254MMD4W8121 10/11/2025 SE REALIZÓ GESTIÓN TELEFÓNICA SE HABLÓ CON LA SEÑORA DIANA SE LOGRA VALIDAR QUE YA ESTÁ INSTALADA LA APLICACIÓN Y NOS INFORMAN QUE ESTÁ FUNCIONANDO NORMALMENTE SE PROCEDE A CERRAR CASO | T205: SOPORTE_TELEFÓNICO | U205: 56 | V205: PRINCIPAL | W205: TERRESTRE | X205: CASTAÑEDA PALACIO CARLOS FELIPE | Y205: 2 | Z205: =IF(T205="SOPORTE_TELEFÓNICO",'TARIFAS 2025'!$B$14,IF(V205="PRINCIPAL",'TARIFAS 2025'!$B$8,IF(V205="INTERMEDIA",'TARIFAS 2025'!$C$8,IF(V205="LEJANA",'TARIFAS 2025'!$D$8)))) -> 22000 | AA205: =Z205*Y205 -> 44000
A206: BOGOTA | B206: =VLOOKUP(A206,'CENTROS DE COSTOS'!A:D,2,0) -> 0036-0004 | C206: =VLOOKUP(A206,'CENTROS DE COSTOS'!A:D,3,0) -> Wompi Centro | D206: 25269 | E206: 2992182 | F206: 69758 | G206: INCIDENTE | H206: CUNDINAMARCA | I206: FACATATIVA | J206: BARRIO LA ARBOLEDA FACATATIVA 4 | K206: WOMPI | L206: FO-25-1800236 | FO-25-1797908 | M206: 45968.673 | N206: 45971.714 | O206: INCIDENTE | P206: SOFTWARE | Q206: APP ELIMINADA | R206: APP ELIMINADA POR EL CB | S206: 08/11/2025 SE REALIZA COMUNICACIÓN CON LA SEÑORA ALEJANDRA MARTÍNEZ PARA VALIDAR FALLA ,CLIENTE INDICA QUE BORRÓ POR EQUIVOCACION LA APP WOMPI ,SE GENERA CASO POR WOMPI CON EL TICKET -478045 A LA ESPERA DE RESPUESTA 10/11/2025 SE REALIZA COMUNICACIÓN CON LA SEÑORA ALEJANDRA MARTÍNEZ PARA CONFIRMAR RESPUESTA POR PARTE DE WOMPI ,CLIENTE CONFIRMA QUE HA LE APARECE LA APP WOMPI ,YA SE ENCUENTRA OPERATIVO | T206: SOPORTE_TELEFÓNICO | U206: 48 | V206: INTERMEDIA | W206: TERRESTRE | X206: GALINDO ROJAS LUIS FELIPE | Y206: 2 | Z206: =IF(T206="SOPORTE_TELEFÓNICO",'TARIFAS 2025'!$B$14,IF(V206="PRINCIPAL",'TARIFAS 2025'!$B$8,IF(V206="INTERMEDIA",'TARIFAS 2025'!$C$8,IF(V206="LEJANA",'TARIFAS 2025'!$D$8)))) -> 22000 | AA206: =Z206*Y206 -> 44000
A207: BUCARAMANGA | B207: =VLOOKUP(A207,'CENTROS DE COSTOS'!A:D,2,0) -> 0036-0007 | C207: =VLOOKUP(A207,'CENTROS DE COSTOS'!A:D,3,0) -> Wompi Santander | D207: 68001 | E207: 2991884 | F207: 38073 | G207: INCIDENTE | H207: SANTANDER | I207: BUCARAMANGA | J207: BARRIO GIRARDOT BUCARMANGA | K207: WOMPI | L207: FO-25-1805675 | FO-25-1797581 | M207: 45968.658 | N207: 45971.717 | O207: INCIDENTE | P207: SOFTWARE | Q207: APP ELIMINADA | R207: APP ELIMINADA POR EL CB | S207: 10/11/2025 NO SE LOGRA COMUNICACIÓN CON LA LÍNEA MÓVIL 3163425308, SE TRATA DE REALIZA CONTACTO VÍA CHAT O MEDIANTE LLAMADA PERO NO HAY RESPUESTA, SE REALIZA VISITA A COMERCIO Y SE ENCUENTRA CERRADO, SE REPORTA NOVEDAD A COORDINADOR, SE REPROGRAMA VISITA ARA CUANDO EL CLIENTE RESPONDA Y PODER VALIDAR LOS DATOS Y DISPONIBILIDAD DE ATENCIÓN. 10/11/2025 EN COMUNICACIÓN CON LA SEÑORA JESICA AL MOVIL 3163425308, SE VALIDA QUE YA CUENTA CON LA APP EN EL DATAFONO, SE VALIDA QUE ESTA OPERANDO EXITOSAMENTE, SE LE INFORMA QUE SE PROCEDERÁ A REALIZAR EL CIERRE DE LA ORDEN, CLIENTE CONFORME | T207: SOPORTE_TELEFÓNICO | U207: 32 | V207: PRINCIPAL | W207: TERRESTRE | X207: HERNANDEZ GUARIN MIGUEL JULIAN | Y207: 2 | Z207: =IF(T207="SOPORTE_TELEFÓNICO",'TARIFAS 2025'!$B$14,IF(V207="PRINCIPAL",'TARIFAS 2025'!$B$8,IF(V207="INTERMEDIA",'TARIFAS 2025'!$C$8,IF(V207="LEJANA",'TARIFAS 2025'!$D$8)))) -> 22000 | AA207: =Z207*Y207 -> 44000
A208: NEIVA | B208: =VLOOKUP(A208,'CENTROS DE COSTOS'!A:D,2,0) -> 0036-0006 | C208: =VLOOKUP(A208,'CENTROS DE COSTOS'!A:D,3,0) -> Wompi Oriente | D208: 41020 | E208: 2990598 | F208: 72585 | G208: INCIDENTE | H208: HUILA | I208: ALGECIRAS | J208: CENTRO ALGECIRAS HUILA | K208: WOMPI | L208: FO-25-1801230 | FO-25-1796191 | M208: 45968.524 | N208: 45971.723 | O208: INCIDENTE | P208: LECTOR DE TARJETAS | Q208: NO LEE TARJETAS | R208: DAÑO DEL LECTOR DE TARJETAS | S208: 08/11/2025 SE LLEGA A SITIO, SE VERIFICA APP ACTUALIZADA, SE BORRA CACHE, SE REALIZA INTENTO CON DIFERENTES TARJETAS Y CON TODAS SALE ERROR AL LEER LA TARJETA, SE ESCALA CON COORDINADOR PARA CAMBIO DE EQUIPO PERO POR SER DÍA SÁBADO NO SE LOGRA SOPORTE CON WOMPI. 10/11/2025 SE REALIZA CAMBIO DE EQUIPO POR FALLA, NO LEE TARJETAS, SE HACEN PRUEBAS EXITOSAS EN NUEVO DATAFONO | T208: VISITA_TÉCNICA | U208: 0 | V208: INTERMEDIA | W208: TERRESTRE | X208: CORZO BUSTO KEVIN ALEXIS | Y208: 2 | Z208: =IF(T208="SOPORTE_TELEFÓNICO",'TARIFAS 2025'!$B$14,IF(V208="PRINCIPAL",'TARIFAS 2025'!$B$8,IF(V208="INTERMEDIA",'TARIFAS 2025'!$C$8,IF(V208="LEJANA",'TARIFAS 2025'!$D$8)))) -> 172989 | AA208: =Z208*Y208 -> 345978
A209: BOGOTA | B209: =VLOOKUP(A209,'CENTROS DE COSTOS'!A:D,2,0) -> 0036-0004 | C209: =VLOOKUP(A209,'CENTROS DE COSTOS'!A:D,3,0) -> Wompi Centro | D209: 25290 | E209: 2994022 | F209: 70311 | G209: INCIDENTE | H209: CUNDINAMARCA | I209: FUSAGASUGA | J209: BARRIO BOSQUE FUSAGUSAGA | K209: WOMPI | L209: FO-25-1802404 | M209: 45971.333 | N209: 45971.738 | O209: INCIDENTE | P209: IMPRESIÓN | Q209: ROLLO MAL PUESTO | R209: MALA MANIPULACIÓN DEL DATAFONO | S209: 10/11/2025 ACTUALIZACIÓN DE APP BORRADO DE. CACHE INSTALACIÓN DE ROLLOS DE FORMA CORRECTA SE ENTREGA SERVICIO OPERATIVO PRUEBAS OK | T209: VISITA_TÉCNICA | U209: 56 | V209: INTERMEDIA | W209: TERRESTRE | X209: HERNANDEZ NARANJO OSCAR EDUARDO | Y209: 1 | Z209: =IF(T209="SOPORTE_TELEFÓNICO",'TARIFAS 2025'!$B$14,IF(V209="PRINCIPAL",'TARIFAS 2025'!$B$8,IF(V209="INTERMEDIA",'TARIFAS 2025'!$C$8,IF(V209="LEJANA",'TARIFAS 2025'!$D$8)))) -> 172989 | AA209: =Z209*Y209 -> 172989
A210: BOGOTA | B210: =VLOOKUP(A210,'CENTROS DE COSTOS'!A:D,2,0) -> 0036-0004 | C210: =VLOOKUP(A210,'CENTROS DE COSTOS'!A:D,3,0) -> Wompi Centro | D210: 25875 | E210: 2994075 | F210: 75267 | G210: INCIDENTE | H210: CUNDINAMARCA | I210: VILLETA | J210: BARRIO CENTRO VILLETA 10 | K210: WOMPI | L210: FO-25-1803371 | M210: 45971.333 | N210: 45971.741 | O210: INCIDENTE | P210: SOFTWARE | Q210: APP ELIMINADA | R210: APP ELIMINADA POR EL CB | S210: 10/11/2025 SE LLEGA A LA DIRECCIÓN INDICADA Y SE ENCUENTRA APP WOMPI DESISTALADA SE PROCEDE A REALIZAR ESCALAMIENTO PARA INSTALACIÓN DE APP REMOTA. SE INSTALA APP, CREDENCIALES OK , PRUEBAS ÉXITOSAS | T210: VISITA_TÉCNICA | U210: 48 | V210: INTERMEDIA | W210: TERRESTRE | X210: GARCIA PASTRANA KEVIN FERNANDO | Y210: 1 | Z210: =IF(T210="SOPORTE_TELEFÓNICO",'TARIFAS 2025'!$B$14,IF(V210="PRINCIPAL",'TARIFAS 2025'!$B$8,IF(V210="INTERMEDIA",'TARIFAS 2025'!$C$8,IF(V210="LEJANA",'TARIFAS 2025'!$D$8)))) -> 172989 | AA210: =Z210*Y210 -> 172989
A211: BUCARAMANGA | B211: =VLOOKUP(A211,'CENTROS DE COSTOS'!A:D,2,0) -> 0036-0007 | C211: =VLOOKUP(A211,'CENTROS DE COSTOS'!A:D,3,0) -> Wompi Santander | D211: 68001 | E211: 2993562 | F211: 30809 | G211: INCIDENTE | H211: SANTANDER | I211: BUCARAMANGA | J211: BARRIO GIRARDOT 3 | K211: WOMPI | L211: FO-25-1805464 | FO-25-1800284 | M211: 45969.479 | N211: 45971.746 | O211: INCIDENTE | P211: CREDENCIALES DE ACCESO (USUARIO/CONTRASEÑA) | Q211: NO FUNCIONA EL USUARIO O CONTRASEÑA | R211: ERROR INICIO DE SESIÓN | S211: 10/11/2025 INCIDENTE CU: 30809 RESUMEN DEL CASO: DURANTE LA VALIDACIÓN EN SITIO, SE VERIFICA QUE LAS CREDENCIALES DE ACCESO NO PERMITEN EL INGRESO AL SISTEMA. POSTERIOR A LA TELECARGA, LA NUEVA VERSIÓN DE LA APLICACIÓN NO SE DESCARGA CORRECTAMENTE. ACCIONES REALIZADAS: SE VALIDAN LOS DATOS DE LOS USUARIOS Y CREDENCIALES. SE REALIZA BORRADO DE CACHÉ DEL DISPOSITIVO. SE INTENTA REALIZAR NUEVAMENTE LA DESCARGA DE LA APLICACIÓN, PERO NO ESTABLECE CONEXIÓN CON LOS DATOS MÓVILES. SE VERIFICA EL FUNCIONAMIENTO DEL ECR SIN ÉXITO EN LA DESCARGA. SE REALIZA CAMBIO DE CONTRASEÑA DE MANERA EXITOSA; SIN EMBARGO, EL SISTEMA CONTINÚA SIN PERMITIR EL INGRESO DE LOS USUARIOS. RESULTADO: NO FUE POSIBLE DESCARGAR LA NUEVA VERSIÓN NI ACCEDER CON LOS USUARIOS, AUN DESPUÉS DE APLICAR LAS ACCIONES CORRECTIVAS MENCIONADAS. USUARIO: CBLINAUDJ202 SERIAL: 254MMD4W7091 QUEREMOS CONTARLE QUE CREAMOS EL TICKET N° (478201), PARA DAR SEGUIMIENTO A LA ATENCIÓN DE SU COMERCIO. 10/11/2025 SE REALIZA VISITA A COMERCIO DES | T211: VISITA_TÉCNICA | U211: 16 | V211: PRINCIPAL | W211: TERRESTRE | X211: HERNANDEZ GUARIN MIGUEL JULIAN | Y211: 2 | Z211: =IF(T211="SOPORTE_TELEFÓNICO",'TARIFAS 2025'!$B$14,IF(V211="PRINCIPAL",'TARIFAS 2025'!$B$8,IF(V211="INTERMEDIA",'TARIFAS 2025'!$C$8,IF(V211="LEJANA",'TARIFAS 2025'!$D$8)))) -> 51282 | AA211: =Z211*Y211 -> 102564
A212: CUCUTA | B212: =VLOOKUP(A212,'CENTROS DE COSTOS'!A:D,2,0) -> 0036-0007 | C212: =VLOOKUP(A212,'CENTROS DE COSTOS'!A:D,3,0) -> Wompi Santander | D212: 54498 | E212: 2988775 | F212: 79815 | G212: INCIDENTE | H212: NORTE DE SANTANDER | I212: OCAÑA | J212: BARRIO EDIFICIO MIRADORES DE LA COLINA OCAÑA | K212: WOMPI | L212: FO-25-1794740 | M212: 45968.397 | N212: 45971.759 | O212: INCIDENTE | P212: SOFTWARE | Q212: VERSIÓN DESACTUALIZADA | R212: VERSIÓN NO ACTUALIZADA | S212: 10/11/2025 SE REALIZA LLAMADA TELEFÓNICA AL NÚMERO 3172305177 SE HABLÓ CON EL SR JUAN MANIFIESTA QUE EL EQUIPO NO LE DEJA REALIZAR TRANSACCIONES, SE LE DA INDICACIONES SOBRE LA ACTUALIZACIÓN DE LA ÚLTIMA Y SE ENCUENTRA DESACTUALIZADO EQUIPO WOMPII, SE REALIZA DESCARGA DE LA ÚLTIMA VERSIÓN SE REINICIA EQUIPO, SE PRUEBA CONEXIONES WIFI OK, PRUEBAS EXITOSAS | T212: SOPORTE_TELEFÓNICO | U212: 0 | V212: LEJANA | W212: TERRESTRE | X212: MORA VEGA JEAMPIER | Y212: 1 | Z212: =IF(T212="SOPORTE_TELEFÓNICO",'TARIFAS 2025'!$B$14,IF(V212="PRINCIPAL",'TARIFAS 2025'!$B$8,IF(V212="INTERMEDIA",'TARIFAS 2025'!$C$8,IF(V212="LEJANA",'TARIFAS 2025'!$D$8)))) -> 22000 | AA212: =Z212*Y212 -> 22000
A213: BOGOTA | B213: =VLOOKUP(A213,'CENTROS DE COSTOS'!A:D,2,0) -> 0036-0004 | C213: =VLOOKUP(A213,'CENTROS DE COSTOS'!A:D,3,0) -> Wompi Centro | D213: 25743 | E213: 2988040 | F213: 69314 | G213: INCIDENTE | H213: CUNDINAMARCA | I213: SILVANIA | J213: BARRIO KENNEDY SILVANIA | K213: WOMPI | L213: FO-25-1800482 | FO-25-1794771 | M213: 45968.351 | N213: 45971.764 | O213: INCIDENTE | P213: SOFTWARE | Q213: APP ELIMINADA | R213: APP ELIMINADA POR EL CB | S213: 08/11/2025 SE VISITA COMERCIO, SE VALIDA EQUIPO EVIDENCIANDO QUE NO CUENTA CON LA APP WOMPI, SE ESCALA CON EL COORDINADOR TICKET 478012 Y SE PROCEDE A ACTUALIZAR DATAFONO Y NO ES POSIBLE LA INSTALACIÓN DE LA APP, SE REPROGRAMA. 10/11/2025 SE REALIZA COMUNICACIÓN CON LA SEÑORA CAROLINA VARGAS PARA CONFIRMAR RESPUESTA POR PARTE DE WOMPI ,CLIENTE CONFIRMA QUE HA LE APARECE LA APP WOMPI ,YA SE ENCUENTRA OPERATIVO | T213: VISITA_TÉCNICA | U213: 40 | V213: INTERMEDIA | W213: TERRESTRE | X213: GALINDO ROJAS LUIS FELIPE | Y213: 2 | Z213: =IF(T213="SOPORTE_TELEFÓNICO",'TARIFAS 2025'!$B$14,IF(V213="PRINCIPAL",'TARIFAS 2025'!$B$8,IF(V213="INTERMEDIA",'TARIFAS 2025'!$C$8,IF(V213="LEJANA",'TARIFAS 2025'!$D$8)))) -> 172989 | AA213: =Z213*Y213 -> 345978
A214: BOGOTA | B214: =VLOOKUP(A214,'CENTROS DE COSTOS'!A:D,2,0) -> 0036-0004 | C214: =VLOOKUP(A214,'CENTROS DE COSTOS'!A:D,3,0) -> Wompi Centro | D214: 11001 | E214: TA-25-1282106 | F214: 50849 | G214: INCIDENTE | H214: CUNDINAMARCA | I214: BOGOTA | J214: BARRIO OIKOS BOGOTA | K214: WOMPI | L214: FO-25-1809238 | M214: 45972.34 | N214: 45972.361 | O214: INCIDENTE | P214: CONEXIÓN | Q214: APARECEN ERRORES EN PANTALLA: HUBO UNA DESCONEXION DE LA RED | R214: FALLAS EN CANAL DE COMUNICACIÓN DEL CLIENTE (INTERNET) | S214: 11/11/2025 SE REALIZA VISITA TECNICA PARA VALIDACION DE FALLA EQUIPO WOMPI NO INICIA SESION CONECTADO A LA RED WIFI DEL CLIENTE PERO SI CON DATOS MOVILES OPERADOR ETB Y CLARO DESDE LA VISITA DE MIGRACION, EN SITIO SE VALIDA QUE SE CONECTA A LA RED PERO AL INICIAR SESION SE QUEDA CARGANDO Y NO INICIA SE REALIZA PRIMERO SOPORTE TECNICO CON OPERADOR ETB VALIDANDO QUE LOS DEMAS DISPOSITIVOS OPERAN BIEN PERO EL DATAFONO FUNCIONA ETB REALIZA UN ESCALAMIENTO A SEGUNDO NIVEL DONDE ME INDICAN QUE REALIZARAN UN REFRESH DE DNS AL MODEM, PASADOS 10 MINUTOS DE ESTE PROCESO EL DATAFONO YA INICIA SESION Y PUEDE REALIZAR TRANSACCIONES, SE HACE EL MISMO PROCESO CON CLARO QUIEN HACE PASO A PASO DE SOPORTE PERO INDICA QUE ES FALLA DEL DATAFONO YA QUE LOS DEMAS DISPOSITIVOS OPERAN BIEN SE LES INDICA QUE NO NAVEGA CON LA RED DE ELLOS PERO SI CON DATOS Y LA OTRA RED A LO QUE CLARO REALIZA UN RESET DE FABRICA AL MODEM SE CONFIGURA UNA NUEVA RED WIFI Y YA EL DATAFONO QUEDA OPERANDO TAMBIEN CON EL OPERADOR CLARO. SERVICIO QUEDA OPERA | T214: VISITA_TÉCNICA | U214: 16 | V214: PRINCIPAL | W214: TERRESTRE | X214: SALAZAR AGUDELO JHONATAN STIVEN | Y214: 1 | Z214: =IF(T214="SOPORTE_TELEFÓNICO",'TARIFAS 2025'!$B$14,IF(V214="PRINCIPAL",'TARIFAS 2025'!$B$8,IF(V214="INTERMEDIA",'TARIFAS 2025'!$C$8,IF(V214="LEJANA",'TARIFAS 2025'!$D$8)))) -> 51282 | AA214: =Z214*Y214 -> 51282
A215: NEIVA | B215: =VLOOKUP(A215,'CENTROS DE COSTOS'!A:D,2,0) -> 0036-0006 | C215: =VLOOKUP(A215,'CENTROS DE COSTOS'!A:D,3,0) -> Wompi Oriente | D215: 18001 | E215: 2999309 | F215: 65542 | G215: INCIDENTE | H215: CAQUETA | I215: FLORENCIA | J215: BARRIO PRADOS DEL NORTE FLORENCIA | K215: WOMPI | L215: FO-25-1808309 | M215: 45972.333 | N215: 45972.448 | O215: INCIDENTE | P215: PANTALLA | Q215: TÁCTIL | R215: NO RESPONDE LA PANTALLA TÁCTIL | S215: 11/11/2025 SE LLEGA AL CB Y SE REALIZA CAMBIO DE IDIOMA DE ESPAÑOL A INGLÉS SE REALIZO PRUEBAS DE CB Y TÁCTIL FUNCIONA BIEN SE PUEDE ESCRIBIR CON NORMALIDAD LOS NÚMEROS EN LA PANTALLA SIN NINGÚN BLOQUEO, ADICIONAL SE REALIZA BORRADO DE CACHE Y SE VALIDA QUE ESTE EN LA VERSIÓN ACTUALIZADA. | T215: VISITA_TÉCNICA | U215: 16 | V215: LEJANA | W215: TERRESTRE | X215: BERMUDEZ SANCHEZ JOSE NEYBER | Y215: 1 | Z215: =IF(T215="SOPORTE_TELEFÓNICO",'TARIFAS 2025'!$B$14,IF(V215="PRINCIPAL",'TARIFAS 2025'!$B$8,IF(V215="INTERMEDIA",'TARIFAS 2025'!$C$8,IF(V215="LEJANA",'TARIFAS 2025'!$D$8)))) -> 452148 | AA215: =Z215*Y215 -> 452148
A216: CUCUTA | B216: =VLOOKUP(A216,'CENTROS DE COSTOS'!A:D,2,0) -> 0036-0007 | C216: =VLOOKUP(A216,'CENTROS DE COSTOS'!A:D,3,0) -> Wompi Santander | D216: 54001 | E216: 2995427 | F216: 80596 | G216: INCIDENTE | H216: NORTE DE SANTANDER | I216: CUCUTA | J216: BARRIO NUEVO ESCOBAL CUCUTA 4 | K216: WOMPI | L216: FO-25-1804467 | M216: 45971.405 | N216: 45972.453 | O216: INCIDENTE | P216: TRANSACCION ERROR | Q216: VARIAS TRXS ESTAN PRESENTANDO FALLAS | R216: AFECTACIÓN GENERALIZADA DE LOS SERVICIOS | S216: 11/11/2025 SE CONTACTA TELEFÓNICAMENTE AL COMERCIO, LA SEÑORA ERIKA LAGOS INFORMA QUE EL SERVICIO SE ENCUENTRA OPERATIVO Y YA LE APARECEN LOS MOVIMIENTOS REALIZADOS EN EL DATAFONO. 3213715265 | T216: SOPORTE_TELEFÓNICO | U216: 0 | V216: PRINCIPAL | W216: TERRESTRE | X216: PACHECO BUITRAGO JAVIER ALONSO | Y216: 1 | Z216: =IF(T216="SOPORTE_TELEFÓNICO",'TARIFAS 2025'!$B$14,IF(V216="PRINCIPAL",'TARIFAS 2025'!$B$8,IF(V216="INTERMEDIA",'TARIFAS 2025'!$C$8,IF(V216="LEJANA",'TARIFAS 2025'!$D$8)))) -> 22000 | AA216: =Z216*Y216 -> 22000
A217: IBAGUE | B217: =VLOOKUP(A217,'CENTROS DE COSTOS'!A:D,2,0) -> 0036-0006 | C217: =VLOOKUP(A217,'CENTROS DE COSTOS'!A:D,3,0) -> Wompi Oriente | D217: 73001 | E217: 2999394 | F217: 80373 | G217: INCIDENTE | H217: TOLIMA | I217: IBAGUE | J217: BARRIO LA MACARENA IBAGUE 1 | K217: WOMPI | L217: FO-25-1809414 | M217: 45972.333 | N217: 45972.469 | O217: INCIDENTE | P217: CREDENCIALES DE ACCESO (USUARIO/CONTRASEÑA) | Q217: NO FUNCIONA EL USUARIO O CONTRASEÑA | R217: EL USUARIO NO RECUERDA LA CONTRASEÑA O EL USUARIO | S217: 11/11/2025 SE REALIZA VALIDACIÓN DE CREDENCIALES, SE PROCEDE A REALIZAR CAMBIO DE CONTRASEÑA. EQUIPO OPERATIVO | T217: VISITA_TÉCNICA | U217: 0 | V217: PRINCIPAL | W217: TERRESTRE | X217: BARRAGAN TAFUR EDWIN ESTEBAN | Y217: 1 | Z217: =IF(T217="SOPORTE_TELEFÓNICO",'TARIFAS 2025'!$B$14,IF(V217="PRINCIPAL",'TARIFAS 2025'!$B$8,IF(V217="INTERMEDIA",'TARIFAS 2025'!$C$8,IF(V217="LEJANA",'TARIFAS 2025'!$D$8)))) -> 51282 | AA217: =Z217*Y217 -> 51282
A218: BOGOTA | B218: =VLOOKUP(A218,'CENTROS DE COSTOS'!A:D,2,0) -> 0036-0004 | C218: =VLOOKUP(A218,'CENTROS DE COSTOS'!A:D,3,0) -> Wompi Centro | D218: 11001 | E218: 2996758 | F218: 78598 | G218: INCIDENTE | H218: CUNDINAMARCA | I218: BOGOTA | J218: BARRIO FONTIBON RECODO BOGOTA 2 | K218: WOMPI | L218: FO-25-1805851 | M218: 45971.508 | N218: 45972.492 | O218: INCIDENTE | P218: NAVEGACION LENTA | Q218: USUARIO NO PUEDE NAVEGAR ENTRE PANTALLAS O LA APP NO ABRE SE QUEDA CARGANDO | R218: CACHE | S218: 11/11/2025 INCIDENTE WOMPI COMERCIO INDICA QUE EL EQUIPO SE ENCUENTRA DEMACIADO LENTO SE REALIZA BORRADO DE CACHÉ LIMPIEZA DE MEMORIA Y ACTUALIZACIÓN DE LA APLICACIÓN WOMPI VERSIÓN 26.2.5, SE REINICIA EL EQUIPO Y QUEDA FUNCIONAL SE LE RECOMIENDA AL CLIENTE QUE SE COMUNIQUE CON EL OPERADOR QUE MANEJAN QUE HAGA VALIDACIONES DE LOS EQUIPOS O CABLEADO YA QUE POR DATOS DE CELULAR EL EQUIPO TRABAJA EN PERFECTAS CONDICIONES PERSONA QUE ATIENDE ANDREA GALINDO | T218: VISITA_TÉCNICA | U218: 24 | V218: PRINCIPAL | W218: TERRESTRE | X218: GONZALEZ FANDIÑO SANTIAGO ERNESTO | Y218: 1 | Z218: =IF(T218="SOPORTE_TELEFÓNICO",'TARIFAS 2025'!$B$14,IF(V218="PRINCIPAL",'TARIFAS 2025'!$B$8,IF(V218="INTERMEDIA",'TARIFAS 2025'!$C$8,IF(V218="LEJANA",'TARIFAS 2025'!$D$8)))) -> 51282 | AA218: =Z218*Y218 -> 51282
A219: BOGOTA | B219: =VLOOKUP(A219,'CENTROS DE COSTOS'!A:D,2,0) -> 0036-0004 | C219: =VLOOKUP(A219,'CENTROS DE COSTOS'!A:D,3,0) -> Wompi Centro | D219: 25290 | E219: 2999462 | F219: 58513 | G219: INCIDENTE | H219: CUNDINAMARCA | I219: FUSAGASUGA | J219: BARRIO LOS GIRASOLES FUSAGASUGA | K219: WOMPI | L219: FO-25-1809409 | M219: 45972.333 | N219: 45972.529 | O219: INCIDENTE | P219: NAVEGACION LENTA | Q219: USUARIO NO PUEDE NAVEGAR ENTRE PANTALLAS O LA APP NO ABRE SE QUEDA CARGANDO | R219: MEMORIA LLENA | S219: 11/11/2025 SE REALIZA LLAMADA A LA SEÑORA MARIA TORRES, SE PROCEDE A REALIZAR ACTUALIZACION Y BORRADO DE CACHE Y ME INFORMA QUE FUNCIONA CON NORMALIDAD. | T219: SOPORTE_TELEFÓNICO | U219: 40 | V219: INTERMEDIA | W219: TERRESTRE | X219: ARIAS QUILINDO JULIAN | Y219: 1 | Z219: =IF(T219="SOPORTE_TELEFÓNICO",'TARIFAS 2025'!$B$14,IF(V219="PRINCIPAL",'TARIFAS 2025'!$B$8,IF(V219="INTERMEDIA",'TARIFAS 2025'!$C$8,IF(V219="LEJANA",'TARIFAS 2025'!$D$8)))) -> 22000 | AA219: =Z219*Y219 -> 22000
A220: PASTO | B220: =VLOOKUP(A220,'CENTROS DE COSTOS'!A:D,2,0) -> 0036-0003 | C220: =VLOOKUP(A220,'CENTROS DE COSTOS'!A:D,3,0) -> Wompi Suroccidente | D220: 52001 | E220: 2997647 | F220: 16907 | G220: INCIDENTE | H220: NARIÑO | I220: PASTO | J220: BARRIO VILLA DEL RIO PASTO | K220: WOMPI | L220: FO-25-1807012 | M220: 45971.615 | N220: 45972.539 | O220: INCIDENTE | P220: SOFTWARE | Q220: CONFIGURACIÓN GENERAL | R220: IDIOMA | S220: 11/11/2025 SE VERIFICÓ FALLA DE TECLADO NO APARECE O AL REALIZAR TX SE SALE AUTOMÁTICAMENTE Y NO PERMITE REALIZARLA, TAMBIÉN ES LENTO AL EJECUTAR LA TX, A SU VEZ REPORTA FALLA DE CALENTAMIENTO DEL EQUIPO EN LA PARTE INFERIOR, SE ENCONTRÓ FALLA DE IDIOMA LA ACTUALIZACIÓN CAMBIO EL IDIOMA A ESPAÑOL, SE CAMBIA A IDIOMA ORIGINAL INGLÉS, SE LE EXPLICO COMO REALIZAR DE FORMA CORRECTA BORRADO DE CACHE AL ESTAR LENTO EN LAS OPERACIONES, SE LE INDICO QUE LA CONEXIÓN PARA CARGAR EL DATAFONO LO DEBE REALIZAR A UNA TOMA CORRIENTE EN BUEN ESTADO O AUN ESTABILIZADOR YA QUE PUEDE GENERAR ESE TIPO DE CALENTAMIENTO DEL EQUIPO, SIN EMBARGO SE LE INDICO QUE LA PRÓXIMA CARGA LA REALICE EN OTRA TOMA CORRIENTE O EN UN ESTABILIZADOR Y SI LA FALLA PERSISTE TOMAR VIDEO REPORTAR NUEVAMENTE FALLA POR RECALENTAMIENTO, ES DE ACLARAR QUE ESA NOVEDAD NO SE PUEDE VERIFICAR POR QUE AL CONECTAR NO SE NOTA NI SE RÉPLICA LA FALLA DE CALENTAMIENTO DEL EQUIPO, SE EJECUTAN PRUEBAS TX EXITOSAS QUEDA OPERATIVO. | T220: VISITA_TÉCNICA | U220: 56 | V220: PRINCIPAL | W220: TERRESTRE | X220: REMICIO AMADO JOHN HEBER | Y220: 1 | Z220: =IF(T220="SOPORTE_TELEFÓNICO",'TARIFAS 2025'!$B$14,IF(V220="PRINCIPAL",'TARIFAS 2025'!$B$8,IF(V220="INTERMEDIA",'TARIFAS 2025'!$C$8,IF(V220="LEJANA",'TARIFAS 2025'!$D$8)))) -> 51282 | AA220: =Z220*Y220 -> 51282
A221: PASTO | B221: =VLOOKUP(A221,'CENTROS DE COSTOS'!A:D,2,0) -> 0036-0003 | C221: =VLOOKUP(A221,'CENTROS DE COSTOS'!A:D,3,0) -> Wompi Suroccidente | D221: 52001 | E221: 2997290 | F221: 17196 | G221: INCIDENTE | H221: NARIÑO | I221: PASTO | J221: BARRIO PROGRESO PASTO | K221: WOMPI | L221: FO-25-1806869 | M221: 45971.604 | N221: 45972.541 | O221: INCIDENTE | P221: IMPRESIÓN | Q221: RODILLO ATASCADO | R221: MALA MANIPULACIÓN DEL DATAFONO | S221: 11/11/2025 SE LLEGO A SITIO PARA VERIFICAR FALLA DE IMPRESIÓN, PERO CLIENTE INFORMA QUE APENAS HOY A PRIMERA HORA EL SISTEMA FUNCIONÓ, PERMITIO IMPRIMIR, SE REVISO ACTUALIZACIÓN Y VERSIÓN DEL SISTEMA SE ENCONTRÓ CAMBIO DE IDIOMA ESPAÑOL (ESPAÑA) SE CAMBIÓ A IDIOMA ORIGINAL INGLÉS, SE REALIZO BORRADO DE CACHE Y ALMACENAMIENTO, SE EJECUTAN PRUEBAS TX EXITOSAS QUEDA OPERATIVO. | T221: VISITA_TÉCNICA | U221: 64 | V221: PRINCIPAL | W221: TERRESTRE | X221: REMICIO AMADO JOHN HEBER | Y221: 1 | Z221: =IF(T221="SOPORTE_TELEFÓNICO",'TARIFAS 2025'!$B$14,IF(V221="PRINCIPAL",'TARIFAS 2025'!$B$8,IF(V221="INTERMEDIA",'TARIFAS 2025'!$C$8,IF(V221="LEJANA",'TARIFAS 2025'!$D$8)))) -> 51282 | AA221: =Z221*Y221 -> 51282
...

Sheet OC PAPALERÍA
A1: CIUDAD SEDE | B1: CENTRO_COSTO | C1: DESCRIPCION CENTRO DE COSTOS | D1: CÓDIGO DANE | E1: TA/CODIGO ACTIVIDAD | F1: CODIGO CB | G1: ACTIVIDAD | H1: DEPARTAMENTO | I1: CIUDAD | J1: NOMBRE DEL CB | K1: RED | L1: FO | M1: FECHA ASIGNACION A LINEA COMUNICACIONES | N1: FECHA DEL CIERRE DEL TICKET (DD/MM/AAAA) | O1: SOLICITUD | P1: DESCRIPCIÓN | Q1: ESTADO | R1: CAUSAL ESTADO | S1: OBSERVACION | T1: FORMA DE ATENCIÓN | U1: CANTIDAD DE ROLLOS | V1: TIPOLOGIA | W1: TIPO DE TRAYECTO | X1: NOMBRE DEL TECNICO | Y1: DIAS DE ACTIVIDAD | Z1: VALOR DIAS ACTIVIDAD | AA1: VALOR TOTAL
A2: CUCUTA | B2: =VLOOKUP(A2,'CENTROS DE COSTOS'!A:D,2,0) -> 0036-0007 | C2: =VLOOKUP(A2,'CENTROS DE COSTOS'!A:D,3,0) -> Wompi Santander | D2: 54001 | E2: 2938691 | F2: 71610 | G2: ORDEN DE CAMBIO | H2: NORTE DE SANTANDER | I2: CUCUTA | J2: BARRIO CARLOS RAMIRES PARIS CUCUTA | K2: WOMPI | L2: FO-25-1739112 | M2: 45957.438 | N2: 45962.363 | O2: ROLLOS | P2: ROLLOS | Q2: EJECUTADO_EXITOSO | R2: EJECUTADO EXITOSO | S2: 27/10/2025 SE ESCALA AL COORDINADOR DE ZONA PARA ENTREGA DE ROLLOS EN SITIO | 31/10/2025 SE ENTREGAN 32 ROLLOS EXITOSO | T2: VISITA_TÉCNICA | U2: 32 | V2: =VLOOKUP(D2,TIPOLOGIA!A:F,5,0) -> PRINCIPAL | W2: =VLOOKUP(D2,TIPOLOGIA!A:F,6,0) -> TERRESTRE | X2: NARANJO AFANADOR RUBEN JESUS | Y2: 1 | Z2: =IF(T2="SOPORTE_TELEFÓNICO",'TARIFAS 2025'!$B$14,IF(V2="PRINCIPAL",'TARIFAS 2025'!$B$11,IF(V2="INTERMEDIA",'TARIFAS 2025'!$C$11,IF(V2="LEJANA",'TARIFAS 2025'!$D$11)))) -> 31419 | AA2: =Z2*Y2 -> 31419
A3: CUCUTA | B3: =VLOOKUP(A3,'CENTROS DE COSTOS'!A:D,2,0) -> 0036-0007 | C3: =VLOOKUP(A3,'CENTROS DE COSTOS'!A:D,3,0) -> Wompi Santander | D3: 54001 | E3: 2962048 | F3: 80138 | G3: ORDEN DE CAMBIO | H3: NORTE DE SANTANDER | I3: CUCUTA | J3: PERFUMERÍA Y VARIEDADES ALTAGRACIA | K3: WOMPI | L3: FO-25-1764036 | M3: 45961.384 | N3: 45962.364 | O3: ROLLOS | P3: ROLLOS | Q3: EJECUTADO_EXITOSO | R3: EJECUTADO EXITOSO | S3: 31/10/2025 SE ESCALA AL COORDINADOR DE ZONA PARA ENTREGA DE ROLLOS EN SITIO | 31/10/2025 SE REALIZA ENTREGA DE 16 ROLLOS WOMPI OK | T3: VISITA_TÉCNICA | U3: 16 | V3: =VLOOKUP(D3,TIPOLOGIA!A:F,5,0) -> PRINCIPAL | W3: =VLOOKUP(D3,TIPOLOGIA!A:F,6,0) -> TERRESTRE | X3: DURAN ACOSTA FRANK YONNY | Y3: 1 | Z3: =IF(T3="SOPORTE_TELEFÓNICO",'TARIFAS 2025'!$B$14,IF(V3="PRINCIPAL",'TARIFAS 2025'!$B$11,IF(V3="INTERMEDIA",'TARIFAS 2025'!$C$11,IF(V3="LEJANA",'TARIFAS 2025'!$D$11)))) -> 31419 | AA3: =Z3*Y3 -> 31419
A4: PEREIRA | B4: =VLOOKUP(A4,'CENTROS DE COSTOS'!A:D,2,0) -> 0036-0002 | C4: =VLOOKUP(A4,'CENTROS DE COSTOS'!A:D,3,0) -> Wompi Eje Cafetero | D4: 63001 | E4: 2959439 | F4: 48546 | G4: ORDEN DE CAMBIO | H4: QUINDIO | I4: ARMENIA | J4: DROGUERIA GUARIN LA MEJOR | K4: WOMPI | L4: FO-25-1761799 | M4: 45960.591 | N4: 45962.381 | O4: ROLLOS | P4: ROLLOS | Q4: EJECUTADO_EXITOSO | R4: EJECUTADO EXITOSO | S4: 30/10/2025 SE ESCALA AL COORDINADOR DE ZONA PARA ENTREGA DE ROLLOS EN SITIO | 01/11/2025 SE VISITA COMERCIO SE REALIZÓ ENTREGA DE 64 ROLLOS | T4: VISITA_TÉCNICA | U4: 64 | V4: =VLOOKUP(D4,TIPOLOGIA!A:F,5,0) -> INTERMEDIA | W4: =VLOOKUP(D4,TIPOLOGIA!A:F,6,0) -> TERRESTRE | X4: SANCHEZ SOLORZANO JUAN SEBASTIAN | Y4: 1 | Z4: =IF(T4="SOPORTE_TELEFÓNICO",'TARIFAS 2025'!$B$14,IF(V4="PRINCIPAL",'TARIFAS 2025'!$B$11,IF(V4="INTERMEDIA",'TARIFAS 2025'!$C$11,IF(V4="LEJANA",'TARIFAS 2025'!$D$11)))) -> 36351 | AA4: =Z4*Y4 -> 36351
A5: TUNJA | B5: =VLOOKUP(A5,'CENTROS DE COSTOS'!A:D,2,0) -> 0036-0007 | C5: =VLOOKUP(A5,'CENTROS DE COSTOS'!A:D,3,0) -> Wompi Santander | D5: 15516 | E5: 2960637 | F5: 46402 | G5: ORDEN DE CAMBIO | H5: BOYACA | I5: PAIPA | J5: BARRIO ESTACION DE ALEJANDRIA PAIPA | K5: WOMPI | L5: FO-25-1768411 | M5: 45960.431 | N5: 45962.431 | O5: ROLLOS | P5: ROLLOS | Q5: GESTIÓN_TELEFONICA | R5: CANCELADO POR EL USUARIO | S5: 01/11/2025 SE CIERRA ACTIVIDAD YA QUE SE INTENTA EN REPETIDAS OCACIONES CONTACTO CON USUARIO PARA CONFIRMAR DATOS DEL ENVIO SIN RESPUESTA | 01/11/2025 SE CIERRA ACTIVIDAD YA QUE SE INTENTA EN REPETIDAS OCACIONES CONTACTO CON USUARIO PARA CONFIRMAR DATOS DEL ENVIO SIN RESPUESTA | T5: SOPORTE_TELEFÓNICO | U5: 0 | V5: =VLOOKUP(D5,TIPOLOGIA!A:F,5,0) -> INTERMEDIA | W5: =VLOOKUP(D5,TIPOLOGIA!A:F,6,0) -> TERRESTRE | X5: HERNANDEZ GUARIN MIGUEL JULIAN | Y5: 1 | Z5: =IF(T5="SOPORTE_TELEFÓNICO",'TARIFAS 2025'!$B$14,IF(V5="PRINCIPAL",'TARIFAS 2025'!$B$11,IF(V5="INTERMEDIA",'TARIFAS 2025'!$C$11,IF(V5="LEJANA",'TARIFAS 2025'!$D$11)))) -> 22000 | AA5: =Z5*Y5 -> 22000
A6: PASTO | B6: =VLOOKUP(A6,'CENTROS DE COSTOS'!A:D,2,0) -> 0036-0003 | C6: =VLOOKUP(A6,'CENTROS DE COSTOS'!A:D,3,0) -> Wompi Suroccidente | D6: 52683 | E6: 2960728 | F6: 37746 | G6: ORDEN DE CAMBIO | H6: NARIÑO | I6: SANDONA | J6: BARRIO SAN CARLOS SANDONA 1 | K6: WOMPI | L6: FO-25-1768412 | M6: 45960.433 | N6: 45962.432 | O6: ROLLOS | P6: ROLLOS | Q6: GESTIÓN_TELEFONICA | R6: CANCELADO POR EL USUARIO | S6: 01/11/2025 SE CIERRA ACTIVIDAD YA QUE SE INTENTA EN REPETIDAS OCACIONES CONTACTO CON USUARIO PARA CONFIRMAR DATOS DEL ENVIO SIN RESPUESTA | 01/11/2025 SE CIERRA ACTIVIDAD YA QUE SE INTENTA EN REPETIDAS OCACIONES CONTACTO CON USUARIO PARA CONFIRMAR DATOS DEL ENVIO SIN RESPUESTA | T6: SOPORTE_TELEFÓNICO | U6: 0 | V6: =VLOOKUP(D6,TIPOLOGIA!A:F,5,0) -> INTERMEDIA | W6: =VLOOKUP(D6,TIPOLOGIA!A:F,6,0) -> TERRESTRE | X6: HENAO CARDONA DIEGO FERNANDO | Y6: 1 | Z6: =IF(T6="SOPORTE_TELEFÓNICO",'TARIFAS 2025'!$B$14,IF(V6="PRINCIPAL",'TARIFAS 2025'!$B$11,IF(V6="INTERMEDIA",'TARIFAS 2025'!$C$11,IF(V6="LEJANA",'TARIFAS 2025'!$D$11)))) -> 22000 | AA6: =Z6*Y6 -> 22000
A7: PASTO | B7: =VLOOKUP(A7,'CENTROS DE COSTOS'!A:D,2,0) -> 0036-0003 | C7: =VLOOKUP(A7,'CENTROS DE COSTOS'!A:D,3,0) -> Wompi Suroccidente | D7: 52001 | E7: 2952164 | F7: 52572 | G7: ORDEN DE CAMBIO | H7: NARIÑO | I7: PASTO | J7: FULL MOTOS LA 15 | K7: WOMPI | L7: FO-25-1751559 | M7: 45959.436 | N7: 45962.437 | O7: ROLLOS | P7: ROLLOS | Q7: EJECUTADO_EXITOSO | R7: EJECUTADO EXITOSO | S7: 29/10/2025 SE ESCALA AL COORDINADOR DE ZONA PARA ENTREGA DE ROLLOS EN SITIO | 01/11/2025 SE VISITA EL CB PARA ENTREGAR 24 ROLLOS, ENTREGA OK | T7: VISITA_TÉCNICA | U7: 24 | V7: =VLOOKUP(D7,TIPOLOGIA!A:F,5,0) -> PRINCIPAL | W7: =VLOOKUP(D7,TIPOLOGIA!A:F,6,0) -> TERRESTRE | X7: GUERRERO RAMIREZ OSCAR DARIO | Y7: 1 | Z7: =IF(T7="SOPORTE_TELEFÓNICO",'TARIFAS 2025'!$B$14,IF(V7="PRINCIPAL",'TARIFAS 2025'!$B$11,IF(V7="INTERMEDIA",'TARIFAS 2025'!$C$11,IF(V7="LEJANA",'TARIFAS 2025'!$D$11)))) -> 31419 | AA7: =Z7*Y7 -> 31419
A8: NEIVA | B8: =VLOOKUP(A8,'CENTROS DE COSTOS'!A:D,2,0) -> 0036-0006 | C8: =VLOOKUP(A8,'CENTROS DE COSTOS'!A:D,3,0) -> Wompi Oriente | D8: 18001 | E8: 2955921 | F8: 79385 | G8: ORDEN DE CAMBIO | H8: CAQUETA | I8: FLORENCIA | J8: BARRIO CENTRO FLORENCIA 37 | K8: WOMPI | L8: FO-25-1756120 | M8: 45960.333 | N8: 45962.438 | O8: ROLLOS | P8: ROLLOS | Q8: EJECUTADO_EXITOSO | R8: EJECUTADO EXITOSO | S8: 30/10/2025 SE REALIZA ENVIO DE ROLLOS CON OPERADOR LOGISTICO | 01/11/2025 SE REALIZA ENTREGA DE 16 ROLLOS WOMPI EN SITIO ENTREGA EXITOSA | T8: VISITA_TÉCNICA | U8: 16 | V8: =VLOOKUP(D8,TIPOLOGIA!A:F,5,0) -> LEJANA | W8: =VLOOKUP(D8,TIPOLOGIA!A:F,6,0) -> TERRESTRE | X8: BERMUDEZ SANCHEZ JOSE NEYBER | Y8: 1 | Z8: =IF(T8="SOPORTE_TELEFÓNICO",'TARIFAS 2025'!$B$14,IF(V8="PRINCIPAL",'TARIFAS 2025'!$B$11,IF(V8="INTERMEDIA",'TARIFAS 2025'!$C$11,IF(V8="LEJANA",'TARIFAS 2025'!$D$11)))) -> 40250 | AA8: =Z8*Y8 -> 40250
A9: BARRANQUILLA | B9: =VLOOKUP(A9,'CENTROS DE COSTOS'!A:D,2,0) -> 0036-0001 | C9: =VLOOKUP(A9,'CENTROS DE COSTOS'!A:D,3,0) -> Wompi Costa | D9: 8001 | E9: 2959112 | F9: 74045 | G9: ORDEN DE CAMBIO | H9: ATLANTICO | I9: BARRANQUILLA | J9: BARRIO CARRIZAL BARRANQUILLA 8 | K9: WOMPI | L9: FO-25-1759383 | M9: 45960.519 | N9: 45962.438 | O9: ROLLOS | P9: ROLLOS | Q9: EJECUTADO_EXITOSO | R9: EJECUTADO EXITOSO | S9: 30/10/2025 SE ESCALA AL COORDINADOR DE ZONA PARA ENTREGA DE ROLLOS EN SITIO | 01/11/2025 SE REALIZA VISITA SE ENTREGA 32 ROLLOS | T9: VISITA_TÉCNICA | U9: 32 | V9: =VLOOKUP(D9,TIPOLOGIA!A:F,5,0) -> PRINCIPAL | W9: =VLOOKUP(D9,TIPOLOGIA!A:F,6,0) -> TERRESTRE | X9: VILLACOB VILLACOB ELKIN EDUARDO | Y9: 1 | Z9: =IF(T9="SOPORTE_TELEFÓNICO",'TARIFAS 2025'!$B$14,IF(V9="PRINCIPAL",'TARIFAS 2025'!$B$11,IF(V9="INTERMEDIA",'TARIFAS 2025'!$C$11,IF(V9="LEJANA",'TARIFAS 2025'!$D$11)))) -> 31419 | AA9: =Z9*Y9 -> 31419
A10: CALI | B10: =VLOOKUP(A10,'CENTROS DE COSTOS'!A:D,2,0) -> 0036-0003 | C10: =VLOOKUP(A10,'CENTROS DE COSTOS'!A:D,3,0) -> Wompi Suroccidente | D10: 76001 | E10: 2963897 | F10: 71411 | G10: ORDEN DE CAMBIO | H10: VALLE DEL CAUCA | I10: CALI | J10: BARRIO SAN VICENTE CALI 9 | K10: WOMPI | L10: FO-25-1766512 | M10: 45961.528 | N10: 45962.439 | O10: ROLLOS | P10: ROLLOS | Q10: EJECUTADO_EXITOSO | R10: EJECUTADO EXITOSO | S10: 31/10/2025 SE ESCALA AL COORDINADOR DE ZONA PARA ENTREGA DE ROLLOS EN SITIO | 01/11/2025 SE ENTREGAN 40 ROLLOS DE WOMPI A LA SEÑORITA RUBÍ MEDINA | T10: VISITA_TÉCNICA | U10: 40 | V10: =VLOOKUP(D10,TIPOLOGIA!A:F,5,0) -> PRINCIPAL | W10: =VLOOKUP(D10,TIPOLOGIA!A:F,6,0) -> TERRESTRE | X10: VALENCIA GONZALEZ JOSE DANIEL | Y10: 1 | Z10: =IF(T10="SOPORTE_TELEFÓNICO",'TARIFAS 2025'!$B$14,IF(V10="PRINCIPAL",'TARIFAS 2025'!$B$11,IF(V10="INTERMEDIA",'TARIFAS 2025'!$C$11,IF(V10="LEJANA",'TARIFAS 2025'!$D$11)))) -> 31419 | AA10: =Z10*Y10 -> 31419
A11: PEREIRA | B11: =VLOOKUP(A11,'CENTROS DE COSTOS'!A:D,2,0) -> 0036-0002 | C11: =VLOOKUP(A11,'CENTROS DE COSTOS'!A:D,3,0) -> Wompi Eje Cafetero | D11: 63001 | E11: 2955159 | F11: 35759 | G11: ORDEN DE CAMBIO | H11: QUINDIO | I11: ARMENIA | J11: TIENDA LA BOMBA JES | K11: WOMPI | L11: FO-25-1756130 | M11: 45959.672 | N11: 45962.44 | O11: ROLLOS | P11: ROLLOS | Q11: EJECUTADO_EXITOSO | R11: EJECUTADO EXITOSO | S11: 30/10/2025 SE REALIZA ENVIO DE ROLLOS CON OPERADOR LOGISTICO | 01/11/2025 SE VISITA COMERCIO DE REALIZÓ ENTREGA DE 32 ROLLOS | T11: VISITA_TÉCNICA | U11: 32 | V11: =VLOOKUP(D11,TIPOLOGIA!A:F,5,0) -> INTERMEDIA | W11: =VLOOKUP(D11,TIPOLOGIA!A:F,6,0) -> TERRESTRE | X11: SANCHEZ SOLORZANO JUAN SEBASTIAN | Y11: 1 | Z11: =IF(T11="SOPORTE_TELEFÓNICO",'TARIFAS 2025'!$B$14,IF(V11="PRINCIPAL",'TARIFAS 2025'!$B$11,IF(V11="INTERMEDIA",'TARIFAS 2025'!$C$11,IF(V11="LEJANA",'TARIFAS 2025'!$D$11)))) -> 36351 | AA11: =Z11*Y11 -> 36351
A12: CARTAGENA | B12: =VLOOKUP(A12,'CENTROS DE COSTOS'!A:D,2,0) -> 0036-0001 | C12: =VLOOKUP(A12,'CENTROS DE COSTOS'!A:D,3,0) -> Wompi Costa | D12: 13001 | E12: 2948487 | F12: 50317 | G12: ORDEN DE CAMBIO | H12: BOLIVAR | I12: CARTAGENA | J12: BARRIO ZARAGOCILLA CARTAGENA DE INDIAS 4 | K12: WOMPI | L12: FO-25-1747720 | M12: 45958.657 | N12: 45962.445 | O12: ROLLOS | P12: ROLLOS | Q12: EJECUTADO_EXITOSO | R12: EJECUTADO EXITOSO | S12: 28/10/2025 SE ESCALA AL COORDINADOR DE ZONA PARA ENTREGA DE ROLLOS EN SITIO | 01/11/2025 SE ENTREGAN 64 ROLLOS | T12: VISITA_TÉCNICA | U12: 64 | V12: =VLOOKUP(D12,TIPOLOGIA!A:F,5,0) -> PRINCIPAL | W12: =VLOOKUP(D12,TIPOLOGIA!A:F,6,0) -> TERRESTRE | X12: CANEDO HERRERA ALEXANDER | Y12: 1 | Z12: =IF(T12="SOPORTE_TELEFÓNICO",'TARIFAS 2025'!$B$14,IF(V12="PRINCIPAL",'TARIFAS 2025'!$B$11,IF(V12="INTERMEDIA",'TARIFAS 2025'!$C$11,IF(V12="LEJANA",'TARIFAS 2025'!$D$11)))) -> 31419 | AA12: =Z12*Y12 -> 31419
A13: BARRANQUILLA | B13: =VLOOKUP(A13,'CENTROS DE COSTOS'!A:D,2,0) -> 0036-0001 | C13: =VLOOKUP(A13,'CENTROS DE COSTOS'!A:D,3,0) -> Wompi Costa | D13: 8001 | E13: 2960332 | F13: 68455 | G13: ORDEN DE CAMBIO | H13: ATLANTICO | I13: BARRANQUILLA | J13: BARRIO CARRIZAL BARRANQUILLA 7 | K13: WOMPI | L13: FO-25-1761591 | M13: 45960.659 | N13: 45962.465 | O13: ROLLOS | P13: ROLLOS | Q13: EJECUTADO_EXITOSO | R13: EJECUTADO EXITOSO | S13: 30/10/2025 SE ESCALA AL COORDINADOR DE ZONA PARA ENTREGA DE ROLLOS EN SITIO | 01/11/2025 SE REALIZA VISITA SE ENTREGA 32 ROLLOS | T13: VISITA_TÉCNICA | U13: 32 | V13: =VLOOKUP(D13,TIPOLOGIA!A:F,5,0) -> PRINCIPAL | W13: =VLOOKUP(D13,TIPOLOGIA!A:F,6,0) -> TERRESTRE | X13: VILLACOB VILLACOB ELKIN EDUARDO | Y13: 1 | Z13: =IF(T13="SOPORTE_TELEFÓNICO",'TARIFAS 2025'!$B$14,IF(V13="PRINCIPAL",'TARIFAS 2025'!$B$11,IF(V13="INTERMEDIA",'TARIFAS 2025'!$C$11,IF(V13="LEJANA",'TARIFAS 2025'!$D$11)))) -> 31419 | AA13: =Z13*Y13 -> 31419
A14: NEIVA | B14: =VLOOKUP(A14,'CENTROS DE COSTOS'!A:D,2,0) -> 0036-0006 | C14: =VLOOKUP(A14,'CENTROS DE COSTOS'!A:D,3,0) -> Wompi Oriente | D14: 18001 | E14: 2934250 | F14: 50349 | G14: ORDEN DE CAMBIO | H14: CAQUETA | I14: FLORENCIA | J14: BARRIO SIETE DE AGOSTO FLORENCIA 1 | K14: WOMPI | L14: FO-25-1732628 | M14: 45957.333 | N14: 45962.467 | O14: ROLLOS | P14: ROLLOS | Q14: EJECUTADO_EXITOSO | R14: EJECUTADO EXITOSO | S14: 01/11/2025 SE REALIZA ENTREGA DE 64 ROLLOS WOMPI EN SITIO ENTREGA EXITOSA | T14: VISITA_TÉCNICA | U14: 64 | V14: =VLOOKUP(D14,TIPOLOGIA!A:F,5,0) -> LEJANA | W14: =VLOOKUP(D14,TIPOLOGIA!A:F,6,0) -> TERRESTRE | X14: BERMUDEZ SANCHEZ JOSE NEYBER | Y14: 1 | Z14: =IF(T14="SOPORTE_TELEFÓNICO",'TARIFAS 2025'!$B$14,IF(V14="PRINCIPAL",'TARIFAS 2025'!$B$11,IF(V14="INTERMEDIA",'TARIFAS 2025'!$C$11,IF(V14="LEJANA",'TARIFAS 2025'!$D$11)))) -> 40250 | AA14: =Z14*Y14 -> 40250
A15: BOGOTA | B15: =VLOOKUP(A15,'CENTROS DE COSTOS'!A:D,2,0) -> 0036-0004 | C15: =VLOOKUP(A15,'CENTROS DE COSTOS'!A:D,3,0) -> Wompi Centro | D15: 11001 | E15: 2952496 | F15: 80116 | G15: ORDEN DE CAMBIO | H15: CUNDINAMARCA | I15: BOGOTA | J15: BARRIO PATIO BONITO BOGOTA 29 | K15: WOMPI | L15: FO-25-1751539 | M15: 45959.458 | N15: 45962.468 | O15: ROLLOS | P15: ROLLOS | Q15: EJECUTADO_CANCELADO | R15: CB CERRADO - DESOCUPADO | S15: 29/10/2025 SE ESCALA AL COORDINADOR DE ZONA PARA ENTREGA DE ROLLOS EN SITIO | 01/11/2025 SE REALIZA VISITA DE CAMPO ENCONTRADO QUE COMERCIO ESTA CERRADO, SE INTENTA COMUNICACIÓN A LA LÍNEA 3203460921 NO HAY RESPUESTA, SE INFORMA A SUPERVISOR QUIEN AUTORIZA CIERRE DE VISITA | T15: VISITA_TÉCNICA | V15: =VLOOKUP(D15,TIPOLOGIA!A:F,5,0) -> PRINCIPAL | W15: =VLOOKUP(D15,TIPOLOGIA!A:F,6,0) -> TERRESTRE | X15: LOZADA ROJAS CHRISTIAN ANDRES | Y15: 1 | Z15: =IF(T15="SOPORTE_TELEFÓNICO",'TARIFAS 2025'!$B$14,IF(V15="PRINCIPAL",'TARIFAS 2025'!$B$11,IF(V15="INTERMEDIA",'TARIFAS 2025'!$C$11,IF(V15="LEJANA",'TARIFAS 2025'!$D$11)))) -> 31419 | AA15: =Z15*Y15 -> 31419
A16: MEDELLIN | B16: =VLOOKUP(A16,'CENTROS DE COSTOS'!A:D,2,0) -> 0036-0005 | C16: =VLOOKUP(A16,'CENTROS DE COSTOS'!A:D,3,0) -> Wompi Noroccidente | D16: 5212 | E16: 2939403 | F16: 79369 | G16: ORDEN DE CAMBIO | H16: ANTIOQUIA | I16: COPACABANA | J16: BARRIO PIEDRAS BLANCAS COPACABANA 1 | K16: WOMPI | L16: FO-25-1739093 | M16: 45957.47 | N16: 45962.469 | O16: ROLLOS | P16: ROLLOS | Q16: EJECUTADO_EXITOSO | R16: EJECUTADO EXITOSO | S16: 27/10/2025 SE ESCALA AL COORDINADOR DE ZONA PARA ENTREGA DE ROLLOS EN SITIO | 01/11/2025 SE ENTREGAN 16 ROLLOS WOMPI | T16: VISITA_TÉCNICA | U16: 16 | V16: =VLOOKUP(D16,TIPOLOGIA!A:F,5,0) -> PRINCIPAL | W16: =VLOOKUP(D16,TIPOLOGIA!A:F,6,0) -> TERRESTRE | X16: BARRIENTOS HERNANDEZ CRISTIAN HORACIO | Y16: 1 | Z16: =IF(T16="SOPORTE_TELEFÓNICO",'TARIFAS 2025'!$B$14,IF(V16="PRINCIPAL",'TARIFAS 2025'!$B$11,IF(V16="INTERMEDIA",'TARIFAS 2025'!$C$11,IF(V16="LEJANA",'TARIFAS 2025'!$D$11)))) -> 31419 | AA16: =Z16*Y16 -> 31419
A17: BOGOTA | B17: =VLOOKUP(A17,'CENTROS DE COSTOS'!A:D,2,0) -> 0036-0004 | C17: =VLOOKUP(A17,'CENTROS DE COSTOS'!A:D,3,0) -> Wompi Centro | D17: 11001 | E17: 2953614 | F17: 74002 | G17: ORDEN DE CAMBIO | H17: CUNDINAMARCA | I17: BOGOTA | J17: BARRIO DANUBIO AZUL BOGOTA 7 | K17: WOMPI | L17: FO-25-1756086 | M17: 45959.544 | N17: 45962.47 | O17: ROLLOS | P17: ROLLOS | Q17: EJECUTADO_EXITOSO | R17: EJECUTADO EXITOSO | S17: 30/10/2025 SE ESCALA AL COORDINADOR DE ZONA PARA ENTREGA DE ROLLOS EN SITIO | 01/11/2025 SE REALIZA ENTREGA DE 24 ROLLOS | T17: VISITA_TÉCNICA | U17: 24 | V17: =VLOOKUP(D17,TIPOLOGIA!A:F,5,0) -> PRINCIPAL | W17: =VLOOKUP(D17,TIPOLOGIA!A:F,6,0) -> TERRESTRE | X17: MICHELI LOPEZ MIGUEL ANGEL | Y17: 1 | Z17: =IF(T17="SOPORTE_TELEFÓNICO",'TARIFAS 2025'!$B$14,IF(V17="PRINCIPAL",'TARIFAS 2025'!$B$11,IF(V17="INTERMEDIA",'TARIFAS 2025'!$C$11,IF(V17="LEJANA",'TARIFAS 2025'!$D$11)))) -> 31419 | AA17: =Z17*Y17 -> 31419
A18: CARTAGENA | B18: =VLOOKUP(A18,'CENTROS DE COSTOS'!A:D,2,0) -> 0036-0001 | C18: =VLOOKUP(A18,'CENTROS DE COSTOS'!A:D,3,0) -> Wompi Costa | D18: 13001 | E18: 2948388 | F18: 78072 | G18: ORDEN DE CAMBIO | H18: BOLIVAR | I18: CARTAGENA | J18: BARRIO OLAYA CARTAGENA DE INDIAS 2 | K18: WOMPI | L18: FO-25-1747508 | M18: 45958.656 | N18: 45962.472 | O18: ROLLOS | P18: ROLLOS | Q18: EJECUTADO_EXITOSO | R18: EJECUTADO EXITOSO | S18: 28/10/2025 SE ESCALA AL COORDINADOR DE ZONA PARA ENTREGA DE ROLLOS EN SITIO | 01/11/2025 SE REALIZA ENTREGA DE 16 ROLLOS PARA EL CORRESPONSAL | T18: VISITA_TÉCNICA | U18: 16 | V18: =VLOOKUP(D18,TIPOLOGIA!A:F,5,0) -> PRINCIPAL | W18: =VLOOKUP(D18,TIPOLOGIA!A:F,6,0) -> TERRESTRE | X18: MARTINEZ SALGUEDO ANDRES AUGUSTO | Y18: 1 | Z18: =IF(T18="SOPORTE_TELEFÓNICO",'TARIFAS 2025'!$B$14,IF(V18="PRINCIPAL",'TARIFAS 2025'!$B$11,IF(V18="INTERMEDIA",'TARIFAS 2025'!$C$11,IF(V18="LEJANA",'TARIFAS 2025'!$D$11)))) -> 31419 | AA18: =Z18*Y18 -> 31419
A19: BOGOTA | B19: =VLOOKUP(A19,'CENTROS DE COSTOS'!A:D,2,0) -> 0036-0004 | C19: =VLOOKUP(A19,'CENTROS DE COSTOS'!A:D,3,0) -> Wompi Centro | D19: 11001 | E19: 2964096 | F19: 79525 | G19: ORDEN DE CAMBIO | H19: CUNDINAMARCA | I19: BOGOTA | J19: BARRIO PALERMO BOGOTA 3 | K19: WOMPI | L19: FO-25-1766509 | M19: 45961.562 | N19: 45962.472 | O19: ROLLOS | P19: ROLLOS | Q19: EJECUTADO_EXITOSO | R19: EJECUTADO EXITOSO | S19: 31/10/2025 SE ESCALA AL COORDINADOR DE ZONA PARA ENTREGA DE ROLLOS EN SITIO | 01/11/2025 SE ENTREGAN 24 ROLLOS WOMPI | T19: VISITA_TÉCNICA | U19: 24 | V19: =VLOOKUP(D19,TIPOLOGIA!A:F,5,0) -> PRINCIPAL | W19: =VLOOKUP(D19,TIPOLOGIA!A:F,6,0) -> TERRESTRE | X19: INFANTE SIERRA MANUEL FERNANDO | Y19: 1 | Z19: =IF(T19="SOPORTE_TELEFÓNICO",'TARIFAS 2025'!$B$14,IF(V19="PRINCIPAL",'TARIFAS 2025'!$B$11,IF(V19="INTERMEDIA",'TARIFAS 2025'!$C$11,IF(V19="LEJANA",'TARIFAS 2025'!$D$11)))) -> 31419 | AA19: =Z19*Y19 -> 31419
A20: BOGOTA | B20: =VLOOKUP(A20,'CENTROS DE COSTOS'!A:D,2,0) -> 0036-0004 | C20: =VLOOKUP(A20,'CENTROS DE COSTOS'!A:D,3,0) -> Wompi Centro | D20: 25754 | E20: 2956146 | F20: 56761 | G20: ORDEN DE CAMBIO | H20: CUNDINAMARCA | I20: SOACHA | J20: BARRIO SAN NICOLAS SOACHA 1 | K20: WOMPI | L20: FO-25-1755028 | M20: 45960.333 | N20: 45962.474 | O20: ROLLOS | P20: ROLLOS | Q20: EJECUTADO_EXITOSO | R20: EJECUTADO EXITOSO | S20: 30/10/2025 SE ESCALA AL COORDINADOR DE ZONA PARA ENTREGA DE ROLLOS EN SITIO | 01/11/2025 ENTREGA DE 24 ROLLOS WOMPI NO SE MANIPULA TERMINAL | T20: VISITA_TÉCNICA | U20: 24 | V20: =VLOOKUP(D20,TIPOLOGIA!A:F,5,0) -> PRINCIPAL | W20: =VLOOKUP(D20,TIPOLOGIA!A:F,6,0) -> TERRESTRE | X20: BUSTOS MORA DIEGO MANUEL | Y20: 1 | Z20: =IF(T20="SOPORTE_TELEFÓNICO",'TARIFAS 2025'!$B$14,IF(V20="PRINCIPAL",'TARIFAS 2025'!$B$11,IF(V20="INTERMEDIA",'TARIFAS 2025'!$C$11,IF(V20="LEJANA",'TARIFAS 2025'!$D$11)))) -> 31419 | AA20: =Z20*Y20 -> 31419
A21: SANTA MARTA | B21: =VLOOKUP(A21,'CENTROS DE COSTOS'!A:D,2,0) -> 0036-0001 | C21: =VLOOKUP(A21,'CENTROS DE COSTOS'!A:D,3,0) -> Wompi Costa | D21: 47001 | E21: 2934661 | F21: 76207 | G21: ORDEN DE CAMBIO | H21: MAGDALENA | I21: SANTA MARTA | J21: LOCAL COMERCIAL LA 3L | K21: WOMPI | L21: FO-25-1733359 | M21: 45957.333 | N21: 45962.476 | O21: ROLLOS | P21: ROLLOS | Q21: EJECUTADO_EXITOSO | R21: EJECUTADO EXITOSO | S21: 25/10/2025 SE REALIZA ENVIO DE ROLLOS CON OPERADOR LOGISTICO | 01/11/2025 SE REALIZA ENTREGA DE 8 ROLLOS PARA DATÁFONO A SATISFACCIÓN DEL CLIENTE | T21: VISITA_TÉCNICA | U21: 8 | V21: =VLOOKUP(D21,TIPOLOGIA!A:F,5,0) -> PRINCIPAL | W21: =VLOOKUP(D21,TIPOLOGIA!A:F,6,0) -> TERRESTRE | X21: THOMAS CAMPO SIGIFREDO SEGUNDO | Y21: 1 | Z21: =IF(T21="SOPORTE_TELEFÓNICO",'TARIFAS 2025'!$B$14,IF(V21="PRINCIPAL",'TARIFAS 2025'!$B$11,IF(V21="INTERMEDIA",'TARIFAS 2025'!$C$11,IF(V21="LEJANA",'TARIFAS 2025'!$D$11)))) -> 31419 | AA21: =Z21*Y21 -> 31419
A22: MEDELLIN | B22: =VLOOKUP(A22,'CENTROS DE COSTOS'!A:D,2,0) -> 0036-0005 | C22: =VLOOKUP(A22,'CENTROS DE COSTOS'!A:D,3,0) -> Wompi Noroccidente | D22: 5212 | E22: 2943281 | F22: 79291 | G22: ORDEN DE CAMBIO | H22: ANTIOQUIA | I22: COPACABANA | J22: ASESORIAS Y SERVICIOS DE TRANSITO 2 | K22: WOMPI | L22: FO-25-1743047 | M22: 45958.333 | N22: 45962.477 | O22: ROLLOS | P22: ROLLOS | Q22: EJECUTADO_EXITOSO | R22: EJECUTADO EXITOSO | S22: 28/10/2025 SE ESCALA AL COORDINADOR DE ZONA PARA ENTREGA DE ROLLOS EN SITIO | 01/11/2025 SE ENTREGAN 16 ROLLOS WOMPI | T22: VISITA_TÉCNICA | U22: 16 | V22: =VLOOKUP(D22,TIPOLOGIA!A:F,5,0) -> PRINCIPAL | W22: =VLOOKUP(D22,TIPOLOGIA!A:F,6,0) -> TERRESTRE | X22: BARRIENTOS HERNANDEZ CRISTIAN HORACIO | Y22: 1 | Z22: =IF(T22="SOPORTE_TELEFÓNICO",'TARIFAS 2025'!$B$14,IF(V22="PRINCIPAL",'TARIFAS 2025'!$B$11,IF(V22="INTERMEDIA",'TARIFAS 2025'!$C$11,IF(V22="LEJANA",'TARIFAS 2025'!$D$11)))) -> 31419 | AA22: =Z22*Y22 -> 31419
A23: BOGOTA | B23: =VLOOKUP(A23,'CENTROS DE COSTOS'!A:D,2,0) -> 0036-0004 | C23: =VLOOKUP(A23,'CENTROS DE COSTOS'!A:D,3,0) -> Wompi Centro | D23: 11001 | E23: 2954391 | F23: 35051 | G23: ORDEN DE CAMBIO | H23: CUNDINAMARCA | I23: BOGOTA | J23: BARRIO CUNDINAMARCA BOGOTA | K23: WOMPI | L23: FO-25-1753546 | M23: 45959.625 | N23: 45962.478 | O23: ROLLOS | P23: ROLLOS | Q23: EJECUTADO_CANCELADO | R23: EJECUTADO EXITOSO | S23: 01/11/2025 SE LLEGA AL COMERCIO PARA LA ENTREGA LA PAPELERÍA EL CUAL SE ENCUENTRA CERRADO SE MARCAN MÚLTIPLES OCASIONES AL NÚMERO DE CONTACTO 3124896423 NADIE RESPONDE SE LLEGA EVIDENCIA FOTOGRÁFICA DEL PUNTO CERRADO | T23: VISITA_TÉCNICA | V23: =VLOOKUP(D23,TIPOLOGIA!A:F,5,0) -> PRINCIPAL | W23: =VLOOKUP(D23,TIPOLOGIA!A:F,6,0) -> TERRESTRE | X23: GOMEZ VEGA DAVID SNEYDER | Y23: 1 | Z23: =IF(T23="SOPORTE_TELEFÓNICO",'TARIFAS 2025'!$B$14,IF(V23="PRINCIPAL",'TARIFAS 2025'!$B$11,IF(V23="INTERMEDIA",'TARIFAS 2025'!$C$11,IF(V23="LEJANA",'TARIFAS 2025'!$D$11)))) -> 31419 | AA23: =Z23*Y23 -> 31419
A24: BOGOTA | B24: =VLOOKUP(A24,'CENTROS DE COSTOS'!A:D,2,0) -> 0036-0004 | C24: =VLOOKUP(A24,'CENTROS DE COSTOS'!A:D,3,0) -> Wompi Centro | D24: 25754 | E24: 2949599 | F24: 52975 | G24: ORDEN DE CAMBIO | H24: CUNDINAMARCA | I24: SOACHA | J24: BARRIO CIUDAD LATINA SOACHA 1 | K24: WOMPI | L24: FO-25-1749071 | M24: 45959.333 | N24: 45962.481 | O24: ROLLOS | P24: ROLLOS | Q24: EJECUTADO_EXITOSO | R24: EJECUTADO EXITOSO | S24: 29/10/2025 SE ESCALA AL COORDINADOR DE ZONA PARA ENTREGA DE ROLLOS EN SITIO | 01/11/2025 ENTREGA DE 40 ROLLOS WOMPI PARA DATAFONO NO SE MANIPULA TERMINAL | T24: VISITA_TÉCNICA | U24: 40 | V24: =VLOOKUP(D24,TIPOLOGIA!A:F,5,0) -> PRINCIPAL | W24: =VLOOKUP(D24,TIPOLOGIA!A:F,6,0) -> TERRESTRE | X24: BUSTOS MORA DIEGO MANUEL | Y24: 1 | Z24: =IF(T24="SOPORTE_TELEFÓNICO",'TARIFAS 2025'!$B$14,IF(V24="PRINCIPAL",'TARIFAS 2025'!$B$11,IF(V24="INTERMEDIA",'TARIFAS 2025'!$C$11,IF(V24="LEJANA",'TARIFAS 2025'!$D$11)))) -> 31419 | AA24: =Z24*Y24 -> 31419
A25: MONTERIA | B25: =VLOOKUP(A25,'CENTROS DE COSTOS'!A:D,2,0) -> 0036-0001 | C25: =VLOOKUP(A25,'CENTROS DE COSTOS'!A:D,3,0) -> Wompi Costa | D25: 23001 | E25: 2960087 | F25: 72854 | G25: ORDEN DE CAMBIO | H25: CORDOBA | I25: MONTERIA | J25: BARRIO CORREGIMIENTO EL SABANAL MONTERIA | K25: WOMPI | L25: FO-25-1761450 | M25: 45960.647 | N25: 45962.483 | O25: ROLLOS | P25: ROLLOS | Q25: EJECUTADO_EXITOSO | R25: EJECUTADO EXITOSO | S25: 30/10/2025 SE ESCALA AL COORDINADOR DE ZONA PARA ENTREGA DE ROLLOS EN SITIO | 01/11/2025 SE REALIZA ENVÍO DE ROLLOS WOMPI, POR MEDIO DE MOTO TAXI AL CORREGIMOS EL SABANAL COMO INDICAN LAS OBSERVACIONES DE LA TA NOS COMUNICAMOS CON EL CLIENTE PARA QUE ESTÉ ATENTO Y RECIBA EL ENVÍO, AL NO 3002686862. | T25: ENVÍO | U25: 24 | V25: =VLOOKUP(D25,TIPOLOGIA!A:F,5,0) -> PRINCIPAL | W25: =VLOOKUP(D25,TIPOLOGIA!A:F,6,0) -> TERRESTRE | X25: CASSIANI PEREZ RAUL RAMIRO | Y25: 1 | Z25: =IF(T25="SOPORTE_TELEFÓNICO",'TARIFAS 2025'!$B$14,IF(V25="PRINCIPAL",'TARIFAS 2025'!$B$11,IF(V25="INTERMEDIA",'TARIFAS 2025'!$C$11,IF(V25="LEJANA",'TARIFAS 2025'!$D$11)))) -> 31419 | AA25: =Z25*Y25 -> 31419
A26: BOGOTA | B26: =VLOOKUP(A26,'CENTROS DE COSTOS'!A:D,2,0) -> 0036-0004 | C26: =VLOOKUP(A26,'CENTROS DE COSTOS'!A:D,3,0) -> Wompi Centro | D26: 11001 | E26: 2961168 | F26: 71988 | G26: ORDEN DE CAMBIO | H26: CUNDINAMARCA | I26: BOGOTA | J26: BOGOTA LOS PERODISTAS | K26: WOMPI | L26: FO-25-1763090 | M26: 45961.333 | N26: 45962.483 | O26: ROLLOS | P26: ROLLOS | Q26: EJECUTADO_EXITOSO | R26: EJECUTADO EXITOSO | S26: 01/11/2025 SE REALIZA ENTREGA DE 32 ROLLOS WOMPI | T26: VISITA_TÉCNICA | U26: 32 | V26: =VLOOKUP(D26,TIPOLOGIA!A:F,5,0) -> PRINCIPAL | W26: =VLOOKUP(D26,TIPOLOGIA!A:F,6,0) -> TERRESTRE | X26: ALARCON AREVALO JOHAN STIVEN | Y26: 1 | Z26: =IF(T26="SOPORTE_TELEFÓNICO",'TARIFAS 2025'!$B$14,IF(V26="PRINCIPAL",'TARIFAS 2025'!$B$11,IF(V26="INTERMEDIA",'TARIFAS 2025'!$C$11,IF(V26="LEJANA",'TARIFAS 2025'!$D$11)))) -> 31419 | AA26: =Z26*Y26 -> 31419
A27: CALI | B27: =VLOOKUP(A27,'CENTROS DE COSTOS'!A:D,2,0) -> 0036-0003 | C27: =VLOOKUP(A27,'CENTROS DE COSTOS'!A:D,3,0) -> Wompi Suroccidente | D27: 76001 | E27: 2962480 | F27: 80443 | G27: ORDEN DE CAMBIO | H27: VALLE DEL CAUCA | I27: CALI | J27: BARRIO MARROQUIN II CALI 1 | K27: WOMPI | L27: FO-25-1764361 | M27: 45961.417 | N27: 45962.485 | O27: ROLLOS | P27: ROLLOS | Q27: EJECUTADO_EXITOSO | R27: EJECUTADO EXITOSO | S27: 31/10/2025 SE ESCALA AL COORDINADOR DE ZONA PARA ENTREGA DE ROLLOS EN SITIO | 01/11/2025 Ñ SE ENTREGAN 16 ROLLOS EN BUEN ESTADO | T27: VISITA_TÉCNICA | U27: 16 | V27: =VLOOKUP(D27,TIPOLOGIA!A:F,5,0) -> PRINCIPAL | W27: =VLOOKUP(D27,TIPOLOGIA!A:F,6,0) -> TERRESTRE | X27: ESCOBAR LENIS JUAN SEBASTIAN | Y27: 1 | Z27: =IF(T27="SOPORTE_TELEFÓNICO",'TARIFAS 2025'!$B$14,IF(V27="PRINCIPAL",'TARIFAS 2025'!$B$11,IF(V27="INTERMEDIA",'TARIFAS 2025'!$C$11,IF(V27="LEJANA",'TARIFAS 2025'!$D$11)))) -> 31419 | AA27: =Z27*Y27 -> 31419
A28: CALI | B28: =VLOOKUP(A28,'CENTROS DE COSTOS'!A:D,2,0) -> 0036-0003 | C28: =VLOOKUP(A28,'CENTROS DE COSTOS'!A:D,3,0) -> Wompi Suroccidente | D28: 76001 | E28: 2964952 | F28: 78450 | G28: ORDEN DE CAMBIO | H28: VALLE DEL CAUCA | I28: CALI | J28: BARRIO MUNICIPAL CALI 2 | K28: WOMPI | L28: FO-25-1766678 | M28: 45961.651 | N28: 45962.485 | O28: ROLLOS | P28: ROLLOS | Q28: EJECUTADO_EXITOSO | R28: EJECUTADO EXITOSO | S28: 31/10/2025 SE ESCALA AL COORDINADOR DE ZONA PARA ENTREGA DE ROLLOS EN SITIO | 01/11/2025 SE ENTREGAN 16 ROLLOS DE WOMPI ALA SEÑORA ZULEIMA CANIZALEZ CRUZ | T28: VISITA_TÉCNICA | U28: 16 | V28: =VLOOKUP(D28,TIPOLOGIA!A:F,5,0) -> PRINCIPAL | W28: =VLOOKUP(D28,TIPOLOGIA!A:F,6,0) -> TERRESTRE | X28: VALENCIA GONZALEZ JOSE DANIEL | Y28: 1 | Z28: =IF(T28="SOPORTE_TELEFÓNICO",'TARIFAS 2025'!$B$14,IF(V28="PRINCIPAL",'TARIFAS 2025'!$B$11,IF(V28="INTERMEDIA",'TARIFAS 2025'!$C$11,IF(V28="LEJANA",'TARIFAS 2025'!$D$11)))) -> 31419 | AA28: =Z28*Y28 -> 31419
A29: SANTA MARTA | B29: =VLOOKUP(A29,'CENTROS DE COSTOS'!A:D,2,0) -> 0036-0001 | C29: =VLOOKUP(A29,'CENTROS DE COSTOS'!A:D,3,0) -> Wompi Costa | D29: 47001 | E29: 2938778 | F29: 51605 | G29: ORDEN DE CAMBIO | H29: MAGDALENA | I29: SANTA MARTA | J29: BARRIO VILLA DE RIO SANTA MARTA | K29: WOMPI | L29: FO-25-1739104 | M29: 45957.446 | N29: 45962.487 | O29: ROLLOS | P29: ROLLOS | Q29: EJECUTADO_EXITOSO | R29: EJECUTADO EXITOSO | S29: 27/10/2025 SE ESCALA AL COORDINADOR DE ZONA PARA ENTREGA DE ROLLOS EN SITIO | 01/11/2025 SE REALIZA ENTREGA DE 16 ROLLOS PARA DATÁFONO SATISFACCIÓN DEL CLIENTE | T29: VISITA_TÉCNICA | U29: 16 | V29: =VLOOKUP(D29,TIPOLOGIA!A:F,5,0) -> PRINCIPAL | W29: =VLOOKUP(D29,TIPOLOGIA!A:F,6,0) -> TERRESTRE | X29: THOMAS CAMPO SIGIFREDO SEGUNDO | Y29: 1 | Z29: =IF(T29="SOPORTE_TELEFÓNICO",'TARIFAS 2025'!$B$14,IF(V29="PRINCIPAL",'TARIFAS 2025'!$B$11,IF(V29="INTERMEDIA",'TARIFAS 2025'!$C$11,IF(V29="LEJANA",'TARIFAS 2025'!$D$11)))) -> 31419 | AA29: =Z29*Y29 -> 31419
A30: CALI | B30: =VLOOKUP(A30,'CENTROS DE COSTOS'!A:D,2,0) -> 0036-0003 | C30: =VLOOKUP(A30,'CENTROS DE COSTOS'!A:D,3,0) -> Wompi Suroccidente | D30: 76001 | E30: 2962703 | F30: 80724 | G30: ORDEN DE CAMBIO | H30: VALLE DEL CAUCA | I30: CALI | J30: BARRIO CIUDADELA DEL RIO CALI 2 | K30: WOMPI | L30: FO-25-1764357 | M30: 45961.422 | N30: 45962.488 | O30: ROLLOS | P30: ROLLOS | Q30: EJECUTADO_EXITOSO | R30: EJECUTADO EXITOSO | S30: 31/10/2025 SE ESCALA AL COORDINADOR DE ZONA PARA ENTREGA DE ROLLOS EN SITIO | 01/11/2025 SE ENTREGAN 16 ROLLOS A FRANCISCO | T30: VISITA_TÉCNICA | U30: 16 | V30: =VLOOKUP(D30,TIPOLOGIA!A:F,5,0) -> PRINCIPAL | W30: =VLOOKUP(D30,TIPOLOGIA!A:F,6,0) -> TERRESTRE | X30: CUERO RUIZ JHONNY | Y30: 1 | Z30: =IF(T30="SOPORTE_TELEFÓNICO",'TARIFAS 2025'!$B$14,IF(V30="PRINCIPAL",'TARIFAS 2025'!$B$11,IF(V30="INTERMEDIA",'TARIFAS 2025'!$C$11,IF(V30="LEJANA",'TARIFAS 2025'!$D$11)))) -> 31419 | AA30: =Z30*Y30 -> 31419
A31: SANTA MARTA | B31: =VLOOKUP(A31,'CENTROS DE COSTOS'!A:D,2,0) -> 0036-0001 | C31: =VLOOKUP(A31,'CENTROS DE COSTOS'!A:D,3,0) -> Wompi Costa | D31: 47001 | E31: 2939357 | F31: 75187 | G31: ORDEN DE CAMBIO | H31: MAGDALENA | I31: SANTA MARTA | J31: BARRIO ALCAZARES SANTA MARTA 3 | K31: WOMPI | L31: FO-25-1740238 | M31: 45957.476 | N31: 45962.49 | O31: ROLLOS | P31: ROLLOS | Q31: EJECUTADO_EXITOSO | R31: EJECUTADO EXITOSO | S31: 27/10/2025 SE ESCALA AL COORDINADOR DE ZONA PARA ENTREGA DE ROLLOS EN SITIO | 01/11/2025 SE REALIZA ENTREGA DE 24 ROLLOS PARA DATÁFONO A SATISFACCIÓN DEL CLIENTE | T31: VISITA_TÉCNICA | U31: 24 | V31: =VLOOKUP(D31,TIPOLOGIA!A:F,5,0) -> PRINCIPAL | W31: =VLOOKUP(D31,TIPOLOGIA!A:F,6,0) -> TERRESTRE | X31: THOMAS CAMPO SIGIFREDO SEGUNDO | Y31: 1 | Z31: =IF(T31="SOPORTE_TELEFÓNICO",'TARIFAS 2025'!$B$14,IF(V31="PRINCIPAL",'TARIFAS 2025'!$B$11,IF(V31="INTERMEDIA",'TARIFAS 2025'!$C$11,IF(V31="LEJANA",'TARIFAS 2025'!$D$11)))) -> 31419 | AA31: =Z31*Y31 -> 31419
A32: BOGOTA | B32: =VLOOKUP(A32,'CENTROS DE COSTOS'!A:D,2,0) -> 0036-0004 | C32: =VLOOKUP(A32,'CENTROS DE COSTOS'!A:D,3,0) -> Wompi Centro | D32: 11001 | E32: 2947099 | F32: 31444 | G32: ORDEN DE CAMBIO | H32: CUNDINAMARCA | I32: BOGOTA | J32: BARRIO LA GLORIA 3 | K32: WOMPI | L32: FO-25-1746793 | M32: 45958.56 | N32: 45962.491 | O32: ROLLOS | P32: ROLLOS | Q32: EJECUTADO_CANCELADO | R32: CB CERRADO - DESOCUPADO | S32: 28/10/2025 SE ESCALA AL COORDINADOR DE ZONA PARA ENTREGA DE ROLLOS EN SITIO | 01/11/2025 COMERCIO CERRADO, SE LLAMA AL NÚMERO DE CONTACTO 3192150170 SE VA A BUZÓN DE VOZ, SE LE INFORMA A SUPERVISOR QUIEN AUTORIZA CIERRE DE SOLICITUD | T32: VISITA_TÉCNICA | V32: =VLOOKUP(D32,TIPOLOGIA!A:F,5,0) -> PRINCIPAL | W32: =VLOOKUP(D32,TIPOLOGIA!A:F,6,0) -> TERRESTRE | X32: MICHELI LOPEZ MIGUEL ANGEL | Y32: 1 | Z32: =IF(T32="SOPORTE_TELEFÓNICO",'TARIFAS 2025'!$B$14,IF(V32="PRINCIPAL",'TARIFAS 2025'!$B$11,IF(V32="INTERMEDIA",'TARIFAS 2025'!$C$11,IF(V32="LEJANA",'TARIFAS 2025'!$D$11)))) -> 31419 | AA32: =Z32*Y32 -> 31419
A33: CUCUTA | B33: =VLOOKUP(A33,'CENTROS DE COSTOS'!A:D,2,0) -> 0036-0007 | C33: =VLOOKUP(A33,'CENTROS DE COSTOS'!A:D,3,0) -> Wompi Santander | D33: 54001 | E33: 2965413 | F33: 71222 | G33: ORDEN DE CAMBIO | H33: NORTE DE SANTANDER | I33: CUCUTA | J33: FERRECOMUNEROS | K33: WOMPI | L33: FO-25-1767066 | M33: 45961.674 | N33: 45962.492 | O33: ROLLOS | P33: ROLLOS | Q33: EJECUTADO_EXITOSO | R33: EJECUTADO EXITOSO | S33: 31/10/2025 SE ESCALA AL COORDINADOR DE ZONA PARA ENTREGA DE ROLLOS EN SITIO | 01/11/2025 SE REALIZÓ VISITA AL COMERCIO Y SE HIZO ENTREGA DE 16 ROLLOS WOMPI TODO OK | T33: VISITA_TÉCNICA | U33: 16 | V33: =VLOOKUP(D33,TIPOLOGIA!A:F,5,0) -> PRINCIPAL | W33: =VLOOKUP(D33,TIPOLOGIA!A:F,6,0) -> TERRESTRE | X33: MORA VEGA JEAMPIER | Y33: 1 | Z33: =IF(T33="SOPORTE_TELEFÓNICO",'TARIFAS 2025'!$B$14,IF(V33="PRINCIPAL",'TARIFAS 2025'!$B$11,IF(V33="INTERMEDIA",'TARIFAS 2025'!$C$11,IF(V33="LEJANA",'TARIFAS 2025'!$D$11)))) -> 31419 | AA33: =Z33*Y33 -> 31419
A34: MONTERIA | B34: =VLOOKUP(A34,'CENTROS DE COSTOS'!A:D,2,0) -> 0036-0001 | C34: =VLOOKUP(A34,'CENTROS DE COSTOS'!A:D,3,0) -> Wompi Costa | D34: 23001 | E34: 2960739 | F34: 74154 | G34: ORDEN DE CAMBIO | H34: CORDOBA | I34: MONTERIA | J34: TIENDA MARIA JOSE 03 | K34: WOMPI | L34: FO-25-1761938 | M34: 45960.694 | N34: 45962.492 | O34: ROLLOS | P34: ROLLOS | Q34: EJECUTADO_EXITOSO | R34: EJECUTADO EXITOSO | S34: 30/10/2025 SE ESCALA AL COORDINADOR DE ZONA PARA ENTREGA DE ROLLOS EN SITIO | 01/11/2025 SE REALIZA ENTREGA DE 56 ROLLOS A CORRESPONSAL WOMPI | T34: VISITA_TÉCNICA | U34: 56 | V34: =VLOOKUP(D34,TIPOLOGIA!A:F,5,0) -> PRINCIPAL | W34: =VLOOKUP(D34,TIPOLOGIA!A:F,6,0) -> TERRESTRE | X34: MARQUEZ HOYOS JEYSON DANIEL | Y34: 1 | Z34: =IF(T34="SOPORTE_TELEFÓNICO",'TARIFAS 2025'!$B$14,IF(V34="PRINCIPAL",'TARIFAS 2025'!$B$11,IF(V34="INTERMEDIA",'TARIFAS 2025'!$C$11,IF(V34="LEJANA",'TARIFAS 2025'!$D$11)))) -> 31419 | AA34: =Z34*Y34 -> 31419
A35: BOGOTA | B35: =VLOOKUP(A35,'CENTROS DE COSTOS'!A:D,2,0) -> 0036-0004 | C35: =VLOOKUP(A35,'CENTROS DE COSTOS'!A:D,3,0) -> Wompi Centro | D35: 11001 | E35: 2953468 | F35: 81375 | G35: ORDEN DE CAMBIO | H35: CUNDINAMARCA | I35: BOGOTA | J35: SOLUCIONES EL TROPEZON | K35: WOMPI | L35: FO-25-1752617 | M35: 45959.531 | N35: 45962.497 | O35: ROLLOS | P35: ROLLOS | Q35: EJECUTADO_EXITOSO | R35: EJECUTADO EXITOSO | S35: 01/11/2025 ENTREGA DE 8 ROLLOS NO SE MANIPULAN EQUIPOS | T35: VISITA_TÉCNICA | U35: 8 | V35: =VLOOKUP(D35,TIPOLOGIA!A:F,5,0) -> PRINCIPAL | W35: =VLOOKUP(D35,TIPOLOGIA!A:F,6,0) -> TERRESTRE | X35: HERNANDEZ NARANJO OSCAR EDUARDO | Y35: 1 | Z35: =IF(T35="SOPORTE_TELEFÓNICO",'TARIFAS 2025'!$B$14,IF(V35="PRINCIPAL",'TARIFAS 2025'!$B$11,IF(V35="INTERMEDIA",'TARIFAS 2025'!$C$11,IF(V35="LEJANA",'TARIFAS 2025'!$D$11)))) -> 31419 | AA35: =Z35*Y35 -> 31419
A36: BOGOTA | B36: =VLOOKUP(A36,'CENTROS DE COSTOS'!A:D,2,0) -> 0036-0004 | C36: =VLOOKUP(A36,'CENTROS DE COSTOS'!A:D,3,0) -> Wompi Centro | D36: 11001 | E36: 2940318 | F36: 74003 | G36: ORDEN DE CAMBIO | H36: CUNDINAMARCA | I36: BOGOTA | J36: BARRIO GRANADA NORTE BOGOTA 3 | K36: WOMPI | L36: FO-25-1741278 | M36: 45957.538 | N36: 45962.497 | O36: ROLLOS | P36: ROLLOS | Q36: EJECUTADO_EXITOSO | R36: EJECUTADO EXITOSO | S36: 27/10/2025 SE ESCALA AL COORDINADOR DE ZONA PARA ENTREGA DE ROLLOS EN SITIO | 01/11/2025 SE LLEGA A LA DIRECCIÓN INDICADA Y SE ENTREGAN 24 ROLLOS WOMPI | T36: VISITA_TÉCNICA | U36: 24 | V36: =VLOOKUP(D36,TIPOLOGIA!A:F,5,0) -> PRINCIPAL | W36: =VLOOKUP(D36,TIPOLOGIA!A:F,6,0) -> TERRESTRE | X36: GARCIA PASTRANA KEVIN FERNANDO | Y36: 1 | Z36: =IF(T36="SOPORTE_TELEFÓNICO",'TARIFAS 2025'!$B$14,IF(V36="PRINCIPAL",'TARIFAS 2025'!$B$11,IF(V36="INTERMEDIA",'TARIFAS 2025'!$C$11,IF(V36="LEJANA",'TARIFAS 2025'!$D$11)))) -> 31419 | AA36: =Z36*Y36 -> 31419
A37: MEDELLIN | B37: =VLOOKUP(A37,'CENTROS DE COSTOS'!A:D,2,0) -> 0036-0005 | C37: =VLOOKUP(A37,'CENTROS DE COSTOS'!A:D,3,0) -> Wompi Noroccidente | D37: 5079 | E37: 2864926 | F37: 29130 | G37: ORDEN DE CAMBIO | H37: ANTIOQUIA | I37: BARBOSA | J37: BARRIO VEREDA POPALITO BARBOSA | K37: WOMPI | L37: FO-25-1674625 | M37: 45939.64 | N37: 45962.5 | O37: ROLLOS | P37: ROLLOS | Q37: EJECUTADO_EXITOSO | R37: EJECUTADO EXITOSO | S37: 11/10/2025 SE ESCALA AL COORDINADOR DE ZONA PARA ENTREGA DE ROLLOS EN SITIO | 01/11/2025 SE LLAMA A LA USUARIA PARA CONFIRMAR VISITA, ME INDICA QUE EL COMERCIO ESTÁ CERRADO PORQUE ESTA HACIENDO UNAS VUELTAS | 01/11/2025 SE ENTREGAN 16 ROLLOS WOMPI | T37: VISITA_TÉCNICA | U37: 16 | V37: =VLOOKUP(D37,TIPOLOGIA!A:F,5,0) -> INTERMEDIA | W37: =VLOOKUP(D37,TIPOLOGIA!A:F,6,0) -> TERRESTRE | X37: BARRIENTOS HERNANDEZ CRISTIAN HORACIO | Y37: 1 | Z37: =IF(T37="SOPORTE_TELEFÓNICO",'TARIFAS 2025'!$B$14,IF(V37="PRINCIPAL",'TARIFAS 2025'!$B$11,IF(V37="INTERMEDIA",'TARIFAS 2025'!$C$11,IF(V37="LEJANA",'TARIFAS 2025'!$D$11)))) -> 36351 | AA37: =Z37*Y37 -> 36351
A38: BOGOTA | B38: =VLOOKUP(A38,'CENTROS DE COSTOS'!A:D,2,0) -> 0036-0004 | C38: =VLOOKUP(A38,'CENTROS DE COSTOS'!A:D,3,0) -> Wompi Centro | D38: 11001 | E38: 2960020 | F38: 79541 | G38: ORDEN DE CAMBIO | H38: CUNDINAMARCA | I38: BOGOTA | J38: BARRIO BOSA SAN PEDRO BOGOTA 2 | K38: WOMPI | L38: FO-25-1761454 | M38: 45960.635 | N38: 45962.504 | O38: ROLLOS | P38: ROLLOS | Q38: EJECUTADO_EXITOSO | R38: EJECUTADO EXITOSO | S38: 30/10/2025 SE ESCALA AL COORDINADOR DE ZONA PARA ENTREGA DE ROLLOS EN SITIO | 01/11/2025 ENTREGA DE 32 ROLLOS DE WOMPI NO SE MANIPULAN EQUIPOS | T38: VISITA_TÉCNICA | U38: 32 | V38: =VLOOKUP(D38,TIPOLOGIA!A:F,5,0) -> PRINCIPAL | W38: =VLOOKUP(D38,TIPOLOGIA!A:F,6,0) -> TERRESTRE | X38: HERNANDEZ NARANJO OSCAR EDUARDO | Y38: 1 | Z38: =IF(T38="SOPORTE_TELEFÓNICO",'TARIFAS 2025'!$B$14,IF(V38="PRINCIPAL",'TARIFAS 2025'!$B$11,IF(V38="INTERMEDIA",'TARIFAS 2025'!$C$11,IF(V38="LEJANA",'TARIFAS 2025'!$D$11)))) -> 31419 | AA38: =Z38*Y38 -> 31419
A39: BOGOTA | B39: =VLOOKUP(A39,'CENTROS DE COSTOS'!A:D,2,0) -> 0036-0004 | C39: =VLOOKUP(A39,'CENTROS DE COSTOS'!A:D,3,0) -> Wompi Centro | D39: 11001 | E39: 2951030 | F39: 74517 | G39: ORDEN DE CAMBIO | H39: CUNDINAMARCA | I39: BOGOTA | J39: BARRIO EL OLIVO BOGOTA 1 | K39: WOMPI | L39: FO-25-1749497 | M39: 45959.38 | N39: 45962.506 | O39: ROLLOS | P39: ROLLOS | Q39: EJECUTADO_EXITOSO | R39: EJECUTADO EXITOSO | S39: 29/10/2025 SE ESCALA AL COORDINADOR DE ZONA PARA ENTREGA DE ROLLOS EN SITIO | 01/11/2025 SE ENTREGAN 16 ROLLOS WOMPI | T39: VISITA_TÉCNICA | U39: 16 | V39: =VLOOKUP(D39,TIPOLOGIA!A:F,5,0) -> PRINCIPAL | W39: =VLOOKUP(D39,TIPOLOGIA!A:F,6,0) -> TERRESTRE | X39: ALARCON AREVALO JOHAN STIVEN | Y39: 1 | Z39: =IF(T39="SOPORTE_TELEFÓNICO",'TARIFAS 2025'!$B$14,IF(V39="PRINCIPAL",'TARIFAS 2025'!$B$11,IF(V39="INTERMEDIA",'TARIFAS 2025'!$C$11,IF(V39="LEJANA",'TARIFAS 2025'!$D$11)))) -> 31419 | AA39: =Z39*Y39 -> 31419
A40: BOGOTA | B40: =VLOOKUP(A40,'CENTROS DE COSTOS'!A:D,2,0) -> 0036-0004 | C40: =VLOOKUP(A40,'CENTROS DE COSTOS'!A:D,3,0) -> Wompi Centro | D40: 11001 | E40: 2959376 | F40: 62853 | G40: ORDEN DE CAMBIO | H40: CUNDINAMARCA | I40: BOGOTA | J40: BARRIO BOSA SAN BERNANDINO BOGOTA | K40: WOMPI | L40: FO-25-1760944 | M40: 45960.592 | N40: 45962.511 | O40: ROLLOS | P40: ROLLOS | Q40: EJECUTADO_EXITOSO | R40: EJECUTADO EXITOSO | S40: 30/10/2025 SE ESCALA AL COORDINADOR DE ZONA PARA ENTREGA DE ROLLOS EN SITIO | 01/11/2025 ENTREGA DE 56 ROLLOS DE WOMPI NO SE MANIPULAN EQUIPOS | T40: VISITA_TÉCNICA | U40: 56 | V40: =VLOOKUP(D40,TIPOLOGIA!A:F,5,0) -> PRINCIPAL | W40: =VLOOKUP(D40,TIPOLOGIA!A:F,6,0) -> TERRESTRE | X40: HERNANDEZ NARANJO OSCAR EDUARDO | Y40: 1 | Z40: =IF(T40="SOPORTE_TELEFÓNICO",'TARIFAS 2025'!$B$14,IF(V40="PRINCIPAL",'TARIFAS 2025'!$B$11,IF(V40="INTERMEDIA",'TARIFAS 2025'!$C$11,IF(V40="LEJANA",'TARIFAS 2025'!$D$11)))) -> 31419 | AA40: =Z40*Y40 -> 31419
A41: NEIVA | B41: =VLOOKUP(A41,'CENTROS DE COSTOS'!A:D,2,0) -> 0036-0006 | C41: =VLOOKUP(A41,'CENTROS DE COSTOS'!A:D,3,0) -> Wompi Oriente | D41: 41001 | E41: 2960976 | F41: 36995 | G41: ORDEN DE CAMBIO | H41: HUILA | I41: NEIVA | J41: BARRIO CENTRO NEIVA 14 | K41: WOMPI | L41: FO-25-1763093 | M41: 45961.333 | N41: 45962.515 | O41: ROLLOS | P41: ROLLOS | Q41: EJECUTADO_EXITOSO | R41: EJECUTADO EXITOSO | S41: 01/11/2025 SE ENTREGA 24 ROLLOS WOMPI SIN NOVEDAD | T41: VISITA_TÉCNICA | U41: 24 | V41: =VLOOKUP(D41,TIPOLOGIA!A:F,5,0) -> PRINCIPAL | W41: =VLOOKUP(D41,TIPOLOGIA!A:F,6,0) -> TERRESTRE | X41: ANDRADE HERNANDEZ JUAN CARLOS | Y41: 1 | Z41: =IF(T41="SOPORTE_TELEFÓNICO",'TARIFAS 2025'!$B$14,IF(V41="PRINCIPAL",'TARIFAS 2025'!$B$11,IF(V41="INTERMEDIA",'TARIFAS 2025'!$C$11,IF(V41="LEJANA",'TARIFAS 2025'!$D$11)))) -> 31419 | AA41: =Z41*Y41 -> 31419
A42: CUCUTA | B42: =VLOOKUP(A42,'CENTROS DE COSTOS'!A:D,2,0) -> 0036-0007 | C42: =VLOOKUP(A42,'CENTROS DE COSTOS'!A:D,3,0) -> Wompi Santander | D42: 54001 | E42: 2948478 | F42: 66489 | G42: ORDEN DE CAMBIO | H42: NORTE DE SANTANDER | I42: CUCUTA | J42: DROGUERIA ZOE PLUSS | K42: WOMPI | L42: FO-25-1747510 | M42: 45958.656 | N42: 45962.52 | O42: ROLLOS | P42: ROLLOS | Q42: EJECUTADO_EXITOSO | R42: EJECUTADO EXITOSO | S42: 28/10/2025 SE ESCALA AL COORDINADOR DE ZONA PARA ENTREGA DE ROLLOS EN SITIO | 01/11/2025 SE ENTREGAN 24 ROLLOS WOMPI | T42: VISITA_TÉCNICA | U42: 24 | V42: =VLOOKUP(D42,TIPOLOGIA!A:F,5,0) -> PRINCIPAL | W42: =VLOOKUP(D42,TIPOLOGIA!A:F,6,0) -> TERRESTRE | X42: NARANJO AFANADOR RUBEN JESUS | Y42: 1 | Z42: =IF(T42="SOPORTE_TELEFÓNICO",'TARIFAS 2025'!$B$14,IF(V42="PRINCIPAL",'TARIFAS 2025'!$B$11,IF(V42="INTERMEDIA",'TARIFAS 2025'!$C$11,IF(V42="LEJANA",'TARIFAS 2025'!$D$11)))) -> 31419 | AA42: =Z42*Y42 -> 31419
A43: BOGOTA | B43: =VLOOKUP(A43,'CENTROS DE COSTOS'!A:D,2,0) -> 0036-0004 | C43: =VLOOKUP(A43,'CENTROS DE COSTOS'!A:D,3,0) -> Wompi Centro | D43: 11001 | E43: 2950432 | F43: 40464 | G43: ORDEN DE CAMBIO | H43: CUNDINAMARCA | I43: BOGOTA | J43: BARRIO BOSA CIUD EL RECREO | K43: WOMPI | L43: FO-25-1749026 | M43: 45959.333 | N43: 45962.526 | O43: ROLLOS | P43: ROLLOS | Q43: EJECUTADO_EXITOSO | R43: EJECUTADO EXITOSO | S43: 29/10/2025 SE ESCALA AL COORDINADOR DE ZONA PARA ENTREGA DE ROLLOS EN SITIO | 01/11/2025 ENTREGA DE 32 ROLLOS DE WOMPI NO SE MANIPULAN EQUIPOS | T43: VISITA_TÉCNICA | U43: 32 | V43: =VLOOKUP(D43,TIPOLOGIA!A:F,5,0) -> PRINCIPAL | W43: =VLOOKUP(D43,TIPOLOGIA!A:F,6,0) -> TERRESTRE | X43: HERNANDEZ NARANJO OSCAR EDUARDO | Y43: 1 | Z43: =IF(T43="SOPORTE_TELEFÓNICO",'TARIFAS 2025'!$B$14,IF(V43="PRINCIPAL",'TARIFAS 2025'!$B$11,IF(V43="INTERMEDIA",'TARIFAS 2025'!$C$11,IF(V43="LEJANA",'TARIFAS 2025'!$D$11)))) -> 31419 | AA43: =Z43*Y43 -> 31419
A44: NEIVA | B44: =VLOOKUP(A44,'CENTROS DE COSTOS'!A:D,2,0) -> 0036-0006 | C44: =VLOOKUP(A44,'CENTROS DE COSTOS'!A:D,3,0) -> Wompi Oriente | D44: 41001 | E44: 2962489 | F44: 74764 | G44: ORDEN DE CAMBIO | H44: HUILA | I44: NEIVA | J44: BARRIO EDUARDO SANTO NEIVA | K44: WOMPI | L44: FO-25-1764360 | M44: 45961.419 | N44: 45962.527 | O44: ROLLOS | P44: ROLLOS | Q44: EJECUTADO_EXITOSO | R44: EJECUTADO EXITOSO | S44: 31/10/2025 SE ESCALA AL COORDINADOR DE ZONA PARA ENTREGA DE ROLLOS EN SITIO | 01/11/2025 SE ENTREGA 24 ROLLOS SIN NOVEDAD | T44: VISITA_TÉCNICA | U44: 24 | V44: =VLOOKUP(D44,TIPOLOGIA!A:F,5,0) -> PRINCIPAL | W44: =VLOOKUP(D44,TIPOLOGIA!A:F,6,0) -> TERRESTRE | X44: ANDRADE HERNANDEZ JUAN CARLOS | Y44: 1 | Z44: =IF(T44="SOPORTE_TELEFÓNICO",'TARIFAS 2025'!$B$14,IF(V44="PRINCIPAL",'TARIFAS 2025'!$B$11,IF(V44="INTERMEDIA",'TARIFAS 2025'!$C$11,IF(V44="LEJANA",'TARIFAS 2025'!$D$11)))) -> 31419 | AA44: =Z44*Y44 -> 31419
... A408: MEDELLIN | B408: =VLOOKUP(A408,'CENTROS DE COSTOS'!A:D,2,0) -> 0036-0005 | C408: =VLOOKUP(A408,'CENTROS DE COSTOS'!A:D,3,0) -> Wompi Noroccidente | D408: 5642 | E408: 2910293 | F408: 57360 | G408: ORDEN DE CAMBIO | H408: ANTIOQUIA | I408: SALGAR | J408: BARRIO CALLE PRINCIPAL SALGAR | K408: WOMPI | L408: FO-25-1776759 | M408: 45951.333 | N408: 45968.428 | O408: ROLLOS | P408: ROLLOS | Q408: EJECUTADO_EXITOSO | R408: EJECUTADO EXITOSO | S408: 06/11/2025 DESDE BODEGA SE REALIZA EL ENVIO MAL DIRECCIONADO, SE CREA NUEVAMENTE LA TA PARA ENVIAR POR FLOTA | 07/11/2025 SE REALIZA ENVIO DE 16 ROLLOS DE WOMPI OK, SE CONFIRMA CON EL USUARIO QUE LOS RECIBIÓ OK | T408: ENVÍO | U408: 16 | V408: =VLOOKUP(D408,TIPOLOGIA!A:F,5,0) -> INTERMEDIA | W408: =VLOOKUP(D408,TIPOLOGIA!A:F,6,0) -> TERRESTRE | X408: MONTOYA VELEZ ANDRES FELIPE | Y408: 1 | Z408: =IF(T408="SOPORTE_TELEFÓNICO",'TARIFAS 2025'!$B$14,IF(V408="PRINCIPAL",'TARIFAS 2025'!$B$11,IF(V408="INTERMEDIA",'TARIFAS 2025'!$C$11,IF(V408="LEJANA",'TARIFAS 2025'!$D$11)))) -> 36351 | AA408: =Z408*Y408 -> 36351
A409: MEDELLIN | B409: =VLOOKUP(A409,'CENTROS DE COSTOS'!A:D,2,0) -> 0036-0005 | C409: =VLOOKUP(A409,'CENTROS DE COSTOS'!A:D,3,0) -> Wompi Noroccidente | D409: 5642 | E409: 2910293-1 | F409: 57360 | G409: ORDEN DE CAMBIO | H409: ANTIOQUIA | I409: SALGAR | J409: BARRIO CALLE PRINCIPAL SALGAR | K409: WOMPI | L409: FO-25-1726661 | M409: 45951.333 | N409: 45968.429 | O409: ROLLOS | P409: ROLLOS | Q409: EJECUTADO_CANCELADO | R409: USUARIO NO RECIBE PEDIDO | S409: 23/10/2025 SE REALIZA ENVIO DE ROLLOS CON OPERADOR LOGISTICO | 07/11/2025 ENVIO PRESENTO NOVEDAD DURANTE ENTREGA SE GENERA DEVOLUCION POR PARTE DE LA TRANSPORTADORA | T409: ENVÍO | U409: 16 | V409: =VLOOKUP(D409,TIPOLOGIA!A:F,5,0) -> INTERMEDIA | W409: =VLOOKUP(D409,TIPOLOGIA!A:F,6,0) -> TERRESTRE | X409: BETANCUR AGUIRRE EDGAR AUGUSTO | Y409: 1 | Z409: =IF(T409="SOPORTE_TELEFÓNICO",'TARIFAS 2025'!$B$14,IF(V409="PRINCIPAL",'TARIFAS 2025'!$B$11,IF(V409="INTERMEDIA",'TARIFAS 2025'!$C$11,IF(V409="LEJANA",'TARIFAS 2025'!$D$11)))) -> 36351 | AA409: =Z409*Y409 -> 36351
A410: CALI | B410: =VLOOKUP(A410,'CENTROS DE COSTOS'!A:D,2,0) -> 0036-0003 | C410: =VLOOKUP(A410,'CENTROS DE COSTOS'!A:D,3,0) -> Wompi Suroccidente | D410: 19001 | E410: 2980728 | F410: 36075 | G410: ORDEN DE CAMBIO | H410: CAUCA | I410: POPAYAN | J410: BARRIO CAJETE POPAYAN | K410: WOMPI | L410: FO-25-1788866 | M410: 45967.333 | N410: 45968.431 | O410: ROLLOS | P410: ROLLOS | Q410: EJECUTADO_EXITOSO | R410: EJECUTADO EXITOSO | S410: 06/11/2025 SE ESCALA AL COORDINADOR DE ZONA PARA ENTREGA DE ROLLOS EN SITIO | 07/11/2025 ENTREGA DE ROLLOS WOMPI | T410: VISITA_TÉCNICA | U410: 40 | V410: =VLOOKUP(D410,TIPOLOGIA!A:F,5,0) -> LEJANA | W410: =VLOOKUP(D410,TIPOLOGIA!A:F,6,0) -> TERRESTRE | X410: LOPEZ CALDONO CESAR FERNANDO | Y410: 1 | Z410: =IF(T410="SOPORTE_TELEFÓNICO",'TARIFAS 2025'!$B$14,IF(V410="PRINCIPAL",'TARIFAS 2025'!$B$11,IF(V410="INTERMEDIA",'TARIFAS 2025'!$C$11,IF(V410="LEJANA",'TARIFAS 2025'!$D$11)))) -> 40250 | AA410: =Z410*Y410 -> 40250
A411: BARRANQUILLA | B411: =VLOOKUP(A411,'CENTROS DE COSTOS'!A:D,2,0) -> 0036-0001 | C411: =VLOOKUP(A411,'CENTROS DE COSTOS'!A:D,3,0) -> Wompi Costa | D411: 8001 | E411: 2972573 | F411: 60460 | G411: ORDEN DE CAMBIO | H411: ATLANTICO | I411: BARRANQUILLA | J411: BARRIO CEVILLAR BARRANQUILLA 4 | K411: WOMPI | L411: FO-25-1778245 | M411: 45965.574 | N411: 45968.438 | O411: ROLLOS | P411: ROLLOS | Q411: EJECUTADO_EXITOSO | R411: EJECUTADO EXITOSO | S411: 04/11/2025 SE ESCALA AL COORDINADOR DE ZONA PARA ENTREGA DE ROLLOS EN SITIO | 07/11/2025 SE HACE ENTREGA DE 56 ROLLOS WOMPI DE MANERA EXITOSA | T411: VISITA_TÉCNICA | U411: 56 | V411: =VLOOKUP(D411,TIPOLOGIA!A:F,5,0) -> PRINCIPAL | W411: =VLOOKUP(D411,TIPOLOGIA!A:F,6,0) -> TERRESTRE | X411: ORTEGA TORRES JUAN SEBASTIAN | Y411: 1 | Z411: =IF(T411="SOPORTE_TELEFÓNICO",'TARIFAS 2025'!$B$14,IF(V411="PRINCIPAL",'TARIFAS 2025'!$B$11,IF(V411="INTERMEDIA",'TARIFAS 2025'!$C$11,IF(V411="LEJANA",'TARIFAS 2025'!$D$11)))) -> 31419 | AA411: =Z411*Y411 -> 31419
A412: NEIVA | B412: =VLOOKUP(A412,'CENTROS DE COSTOS'!A:D,2,0) -> 0036-0006 | C412: =VLOOKUP(A412,'CENTROS DE COSTOS'!A:D,3,0) -> Wompi Oriente | D412: 41001 | E412: 2984210 | F412: 75569 | G412: ORDEN DE CAMBIO | H412: HUILA | I412: NEIVA | J412: BARRIO LOSS MARTIRES NEIVA | K412: WOMPI | L412: FO-25-1788944 | M412: 45967.481 | N412: 45968.449 | O412: ROLLOS | P412: ROLLOS | Q412: EJECUTADO_EXITOSO | R412: EJECUTADO EXITOSO | S412: 06/11/2025 SE ESCALA AL COORDINADOR DE ZONA PARA ENTREGA DE ROLLOS EN SITIO | 07/11/2025 SE REALIZA VISITA AL PUNTO SE ENTREGAN 16 ROLLOS PAPEL WOMPI CLIENTE RECIBE A SATISFACCIÓN | T412: VISITA_TÉCNICA | U412: 16 | V412: =VLOOKUP(D412,TIPOLOGIA!A:F,5,0) -> PRINCIPAL | W412: =VLOOKUP(D412,TIPOLOGIA!A:F,6,0) -> TERRESTRE | X412: DEVIA REINOSO JUAN CARLOS | Y412: 1 | Z412: =IF(T412="SOPORTE_TELEFÓNICO",'TARIFAS 2025'!$B$14,IF(V412="PRINCIPAL",'TARIFAS 2025'!$B$11,IF(V412="INTERMEDIA",'TARIFAS 2025'!$C$11,IF(V412="LEJANA",'TARIFAS 2025'!$D$11)))) -> 31419 | AA412: =Z412*Y412 -> 31419
A413: PASTO | B413: =VLOOKUP(A413,'CENTROS DE COSTOS'!A:D,2,0) -> 0036-0003 | C413: =VLOOKUP(A413,'CENTROS DE COSTOS'!A:D,3,0) -> Wompi Suroccidente | D413: 52001 | E413: 2982453 | F413: 52533 | G413: ORDEN DE CAMBIO | H413: NARIÑO | I413: PASTO | J413: FRIDASTORE | K413: WOMPI | L413: FO-25-1787616 | M413: 45967.392 | N413: 45968.451 | O413: ROLLOS | P413: ROLLOS | Q413: EJECUTADO_EXITOSO | R413: EJECUTADO EXITOSO | S413: 06/11/2025 SE ESCALA AL COORDINADOR DE ZONA PARA ENTREGA DE ROLLOS EN SITIO | 07/11/2025 SE VISITA CB. SE REALIZA ENTREGA DE 32 ROLLOS. CLIENTE INFORMA QUE EL DATAFONO FUNCIONA CORRECTAMENTE. NO SÉ MANIPULA | T413: VISITA_TÉCNICA | U413: 32 | V413: =VLOOKUP(D413,TIPOLOGIA!A:F,5,0) -> PRINCIPAL | W413: =VLOOKUP(D413,TIPOLOGIA!A:F,6,0) -> TERRESTRE | X413: CASTILLO HERRERA ALEX RICARDO | Y413: 1 | Z413: =IF(T413="SOPORTE_TELEFÓNICO",'TARIFAS 2025'!$B$14,IF(V413="PRINCIPAL",'TARIFAS 2025'!$B$11,IF(V413="INTERMEDIA",'TARIFAS 2025'!$C$11,IF(V413="LEJANA",'TARIFAS 2025'!$D$11)))) -> 31419 | AA413: =Z413*Y413 -> 31419
A414: BUCARAMANGA | B414: =VLOOKUP(A414,'CENTROS DE COSTOS'!A:D,2,0) -> 0036-0007 | C414: =VLOOKUP(A414,'CENTROS DE COSTOS'!A:D,3,0) -> Wompi Santander | D414: 68001 | E414: 2984768 | F414: 22946 | G414: ORDEN DE CAMBIO | H414: SANTANDER | I414: BUCARAMANGA | J414: BARRIO CANDILES - BUCARAMANGA | K414: WOMPI | L414: FO-25-1792747 | M414: 45967.544 | N414: 45968.452 | O414: ROLLOS | P414: ROLLOS | Q414: EJECUTADO_EXITOSO | R414: EJECUTADO EXITOSO | S414: 06/11/2025 SE ESCALA AL COORDINADOR DE ZONA PARA ENTREGA DE ROLLOS EN SITIO | 07/11/2025 SE REALIZA ENTREGA DE 64 ROLLOS CON VISITA NO SE MANIPULA TERMINAL | T414: VISITA_TÉCNICA | U414: 64 | V414: =VLOOKUP(D414,TIPOLOGIA!A:F,5,0) -> PRINCIPAL | W414: =VLOOKUP(D414,TIPOLOGIA!A:F,6,0) -> TERRESTRE | X414: REYES RAMIREZ DIEGO ALEXANDER | Y414: 1 | Z414: =IF(T414="SOPORTE_TELEFÓNICO",'TARIFAS 2025'!$B$14,IF(V414="PRINCIPAL",'TARIFAS 2025'!$B$11,IF(V414="INTERMEDIA",'TARIFAS 2025'!$C$11,IF(V414="LEJANA",'TARIFAS 2025'!$D$11)))) -> 31419 | AA414: =Z414*Y414 -> 31419
A415: BOGOTA | B415: =VLOOKUP(A415,'CENTROS DE COSTOS'!A:D,2,0) -> 0036-0004 | C415: =VLOOKUP(A415,'CENTROS DE COSTOS'!A:D,3,0) -> Wompi Centro | D415: 25430 | E415: 2971053 | F415: 63009 | G415: ORDEN DE CAMBIO | H415: CUNDINAMARCA | I415: MADRID | J415: BARRIO SOCIEGO MADRID 6 | K415: WOMPI | L415: FO-25-1776387 | M415: 45965.45 | N415: 45968.457 | O415: ROLLOS | P415: ROLLOS | Q415: EJECUTADO_EXITOSO | R415: EJECUTADO EXITOSO | S415: 04/11/2025 SE ESCALA AL COORDINADOR DE ZONA PARA ENTREGA DE ROLLOS EN SITIO | 06/11/2025 SE REALIZA ENVIO DE 32 ROLLOS WOMPI POR INTERAPIDISIMO GUÍA 700174074319 | T415: ENVÍO | U415: 32 | V415: =VLOOKUP(D415,TIPOLOGIA!A:F,5,0) -> INTERMEDIA | W415: =VLOOKUP(D415,TIPOLOGIA!A:F,6,0) -> TERRESTRE | X415: BUSTOS MORA DIEGO MANUEL | Y415: 1 | Z415: =IF(T415="SOPORTE_TELEFÓNICO",'TARIFAS 2025'!$B$14,IF(V415="PRINCIPAL",'TARIFAS 2025'!$B$11,IF(V415="INTERMEDIA",'TARIFAS 2025'!$C$11,IF(V415="LEJANA",'TARIFAS 2025'!$D$11)))) -> 36351 | AA415: =Z415*Y415 -> 36351
A416: PEREIRA | B416: =VLOOKUP(A416,'CENTROS DE COSTOS'!A:D,2,0) -> 0036-0002 | C416: =VLOOKUP(A416,'CENTROS DE COSTOS'!A:D,3,0) -> Wompi Eje Cafetero | D416: 76736 | E416: 2984872 | F416: 49228 | G416: ORDEN DE CAMBIO | H416: VALLE DEL CAUCA | I416: SEVILLA | J416: BARRIO CENTRO SEVILLA 5 | K416: WOMPI | L416: FO-25-1793062 | M416: 45967.585 | N416: 45968.469 | O416: ROLLOS | P416: ROLLOS | Q416: EJECUTADO_EXITOSO | R416: EJECUTADO EXITOSO | S416: 06/11/2025 SE CONFIRMAN DATOS, SE REALIZA ENVIO POR OPERADOR LOGISTICO | 07/11/2025 SE VISITA COMERCIO SE REALIZÓ ENTREGA DE 24 ROLLOS WOMPI | T416: VISITA_TÉCNICA | U416: 24 | V416: =VLOOKUP(D416,TIPOLOGIA!A:F,5,0) -> INTERMEDIA | W416: =VLOOKUP(D416,TIPOLOGIA!A:F,6,0) -> TERRESTRE | X416: SANCHEZ SOLORZANO JUAN SEBASTIAN | Y416: 1 | Z416: =IF(T416="SOPORTE_TELEFÓNICO",'TARIFAS 2025'!$B$14,IF(V416="PRINCIPAL",'TARIFAS 2025'!$B$11,IF(V416="INTERMEDIA",'TARIFAS 2025'!$C$11,IF(V416="LEJANA",'TARIFAS 2025'!$D$11)))) -> 36351 | AA416: =Z416*Y416 -> 36351
A417: VALLEDUPAR | B417: =VLOOKUP(A417,'CENTROS DE COSTOS'!A:D,2,0) -> 0036-0001 | C417: =VLOOKUP(A417,'CENTROS DE COSTOS'!A:D,3,0) -> Wompi Costa | D417: 20001 | E417: 2983366 | F417: 72032 | G417: ORDEN DE CAMBIO | H417: CESAR | I417: VALLEDUPAR | J417: VALELDUPAR MARIA CAMILA | K417: WOMPI | L417: FO-25-1787576 | M417: 45967.437 | N417: 45968.477 | O417: ROLLOS | P417: ROLLOS | Q417: EJECUTADO_EXITOSO | R417: EJECUTADO EXITOSO | S417: 06/11/2025 SE ESCALA AL COORDINADOR DE ZONA PARA ENTREGA DE ROLLOS EN SITIO | 07/11/2025 SE REALIZA ENTREGA DE 24 ROLLO EN SITIO | T417: VISITA_TÉCNICA | U417: 24 | V417: =VLOOKUP(D417,TIPOLOGIA!A:F,5,0) -> PRINCIPAL | W417: =VLOOKUP(D417,TIPOLOGIA!A:F,6,0) -> TERRESTRE | X417: MONTES DIAZ JOHN FRED | Y417: 1 | Z417: =IF(T417="SOPORTE_TELEFÓNICO",'TARIFAS 2025'!$B$14,IF(V417="PRINCIPAL",'TARIFAS 2025'!$B$11,IF(V417="INTERMEDIA",'TARIFAS 2025'!$C$11,IF(V417="LEJANA",'TARIFAS 2025'!$D$11)))) -> 31419 | AA417: =Z417*Y417 -> 31419
A418: SINCELEJO | B418: =VLOOKUP(A418,'CENTROS DE COSTOS'!A:D,2,0) -> 0036-0001 | C418: =VLOOKUP(A418,'CENTROS DE COSTOS'!A:D,3,0) -> Wompi Costa | D418: 70508 | E418: 2927476 | F418: 11079 | G418: ORDEN DE CAMBIO | H418: SUCRE | I418: OVEJAS | J418: OVEJAS - SUCRE | K418: WOMPI | L418: FO-25-1738942 | M418: 45953.649 | N418: 45968.483 | O418: ROLLOS | P418: ROLLOS | Q418: EJECUTADO_EXITOSO | R418: EJECUTADO EXITOSO | S418: 27/10/2025 SE REALIZA ENVIO DE ROLLOS CON OPERADOR LOGISTICO | 04/11/2025 SE INTENTA COMUNICACION CON EL USUARIO FALLIDA PARA VALIDAR LA RECEPCION DE LOS ROLLOS | 07/11/2025 SE REALIZA ENVIO DE 64 ROLLOS, CON LA GUIA 2265100437 SERVIENTREGA. SE CONFIRMA ENTREGA EXITOSA POR PARTE DE LA TRANSPORTADORA | T418: ENVÍO | U418: 64 | V418: =VLOOKUP(D418,TIPOLOGIA!A:F,5,0) -> INTERMEDIA | W418: =VLOOKUP(D418,TIPOLOGIA!A:F,6,0) -> TERRESTRE | X418: ALVAREZ LOPEZ MARIANA | Y418: 1 | Z418: =IF(T418="SOPORTE_TELEFÓNICO",'TARIFAS 2025'!$B$14,IF(V418="PRINCIPAL",'TARIFAS 2025'!$B$11,IF(V418="INTERMEDIA",'TARIFAS 2025'!$C$11,IF(V418="LEJANA",'TARIFAS 2025'!$D$11)))) -> 36351 | AA418: =Z418*Y418 -> 36351
