Workbook

Sheet RESUMEN
A1: FACTURACIÓN ENTREGA DE ROLLOS A GESTORES
A2: 1 AL 3O DE NOVIEMBRE 2025
A3: WOMPI
A4: CONCEPTOS | B4: CANTIDAD | C4: TOTAL
A5: ='ENTREGA DE ROLLOS EN BODEGAS'!V1 -> ENTREGA DE ROLLOS EN BODEGAS | B5: =COUNTA('ENTREGA DE ROLLOS EN BODEGAS'!A:A)-1 -> 2410 | C5: ='ENTREGA DE ROLLOS EN BODEGAS'!V2412 -> 50314387
A6: SUBTOTAL | C6: =SUM(C5:C5) -> 50314387
A7: Iva | C7: =C6*0.19 -> 9559733.5
A8: TOTAL | C8: =SUM(C6:C7) -> 59874120

Sheet BASE TARIFA 2025
A1: PROPONENTE | B1: TIPO ACTIVIDAD | C1: BODEGA | D1: CENTRO DE COSTOS | E1: ENTREGA DE DATAFONOS EN BODEGAS | F1: ENTREGA DE ROLLOS EN BODEGAS
A2: WOMPI (SOLICITUD ADICIONAL) | B2: ENTREGA DE DATAFONOS EN BODEGAS UBICADAS EN CIUDADES PRINCIPALES | C2: MEDELLIN | D2: WOMPI NOROCCIDENTE | E2: 37313 | F2: 15709.5
A3: WOMPI (SOLICITUD ADICIONAL) | B3: ENTREGA DE DATAFONOS EN BODEGAS UBICADAS EN CIUDADES PRINCIPALES | C3: BOGOTA | D3: WOMPI CENTRO | E3: 37313 | F3: 15709.5
A4: WOMPI (SOLICITUD ADICIONAL) | B4: ENTREGA DE DATAFONOS EN BODEGAS UBICADAS EN CIUDADES PRINCIPALES | C4: CALI | D4: WOMPI SUROCCIDENTE | E4: 37313 | F4: 15709.5
A5: WOMPI (SOLICITUD ADICIONAL) | B5: ENTREGA DE DATAFONOS EN BODEGAS UBICADAS EN CIUDADES PRINCIPALES | C5: PEREIRA | D5: WOMPI EJE CAFETERO | E5: 37313 | F5: 15709.5
A6: WOMPI (SOLICITUD ADICIONAL) | B6: ENTREGA DE DATAFONOS EN BODEGAS UBICADAS EN CIUDADES PRINCIPALES | C6: BARRANQUILLA | D6: WOMPI COSTA | E6: 37313 | F6: 15709.5
A7: WOMPI (SOLICITUD ADICIONAL) | B7: ENTREGA DE DATAFONOS EN BODEGAS UBICADAS EN CIUDADES PRINCIPALES | C7: BUCARAMANGA | D7: WOMPI SANTANDERES | E7: 37313 | F7: 15709.5
A8: WOMPI (SOLICITUD ADICIONAL) | B8: ENTREGA DE DATAFONOS EN BODEGAS UBICADAS EN CIUDADES PRINCIPALES | C8: MONTERIA | D8: WOMPI COSTA | E8: 37313 | F8: 15709.5
A9: WOMPI (SOLICITUD ADICIONAL) | B9: ENTREGA DE DATAFONOS EN BODEGAS UBICADAS EN CIUDADES REMOTAS CERTIFICADAS | C9: CUCUTA | D9: WOMPI SANTANDERES | E9: 49671.7 | F9: 28277.1
A10: WOMPI (SOLICITUD ADICIONAL) | B10: ENTREGA DE DATAFONOS EN BODEGAS UBICADAS EN CIUDADES REMOTAS CERTIFICADAS | C10: NEIVA | D10: WOMPI ORIENTE | E10: 49671.7 | F10: 28277.1
A11: WOMPI (SOLICITUD ADICIONAL) | B11: ENTREGA DE DATAFONOS EN BODEGAS UBICADAS EN CIUDADES REMOTAS CERTIFICADAS | C11: SANTA MARTA | D11: WOMPI COSTA | E11: 49671.7 | F11: 28277.1
A12: WOMPI (SOLICITUD ADICIONAL) | B12: ENTREGA DE DATAFONOS EN BODEGAS UBICADAS EN CIUDADES REMOTAS CERTIFICADAS | C12: TUNJA | D12: WOMPI SANTANDERES | E12: 49671.7 | F12: 28277.1
A13: WOMPI (SOLICITUD ADICIONAL) | B13: ENTREGA DE DATAFONOS EN BODEGAS UBICADAS EN CIUDADES REMOTAS CERTIFICADAS | C13: VILLAVICENCIO | D13: WOMPI ORIENTE | E13: 49671.7 | F13: 28277.1
... A23: WOMPI (SOLICITUD ADICIONAL) | B23: ENTREGA DE DATAFONOS EN BODEGAS UBICADAS EN CIUDADES REMOTAS NO CERTIFICADAS | C23: YOPAL | D23: WOMPI ORIENTE | E23: 49671.7 | F23: 28277.1

Sheet TD
A1: Centro_de_Costos | B1: Suma de ENTREGA DE ROLLOS EN BODEGAS
A2: WOMPI CENTRO | B2: 11499354
A3: WOMPI COSTA | B3: 10374554
A4: WOMPI EJE CAFETERO | B4: 5674271.4
A5: WOMPI NOROCCIDENTE | B5: 5067884.7
A6: WOMPI ORIENTE | B6: 13516454
A7: WOMPI SANTANDERES | B7: 15920007
A8: WOMPI SUROCCIDENTE | B8: 10399689
A9: Total general | B9: 72452214

Sheet Hoja1
A1: CODIGO PUNTO DE SERVICIO | B1: ROLLOS
A2: 10007 | B2: 16
A3: 10015 | B3: 16
A4: 10016 | B4: 8
A5: 10018 | B5: 16
A6: 10023 | B6: 8
A7: 10024 | B7: 16
A8: 10028 | B8: 8
A9: 10029 | B9: 16
A10: 10030 | B10: 16
A11: 10032 | B11: 16
A12: 10033 | B12: 8
A13: 10035 | B13: 16
... A17890: 81253 | B17890: 8

Sheet Hoja2
A3: Etiquetas de fila | B3: Suma de ENTREGA DE ROLLOS EN BODEGAS
A4: WOMPI CENTRO | B4: 8671644
A5: WOMPI COSTA | B5: 5850217.8
A6: WOMPI EJE CAFETERO | B6: 3415245.3
A7: WOMPI NOROCCIDENTE | B7: 3716867.7
A8: WOMPI ORIENTE | B8: 10688744
A9: WOMPI SANTANDERES | B9: 12536181
A10: WOMPI SUROCCIDENTE | B10: 5435487
A11: Total general | B11: 50314387

Sheet ENTREGA DE ROLLOS EN BODEGAS
A1: Codigo_Punto | B1: Nombre_Punto | C1: Nit_CC_Persona | D1: TelefonoCB | E1: Celular_Contacto1 | F1: Celular_dueno | G1: Dirección_Establecimiento | H1: Latitud | I1: Longitud | J1: Departamento | K1: Municipio | L1: Corregimiento | M1: Codigo_Dane | N1: Fecha_Migracion | O1: Formulario | P1: Forma de atención | Q1: Descripción de la Solución | R1: Estado | S1: Cantidad de Rollos por CB | T1: Bodega | U1: Centro_de_Costos | V1: ENTREGA DE ROLLOS EN BODEGAS
A2: 78455 | B2: BARRIO PARQUE PRINCIPAL GRANADA GRANADA | C2: 900815151 | D2: 3108256807 | E2: 3135853734 | F2: 3135853734 | G2: CR 23 20 36,PARQUE PRINCIPAL GRANADA | H2: 6.1431387 | I2: -75.1851605 | J2: ANTIOQUIA | K2: GRANADA | L2: GRANADA | M2: 5313 | N2: 2025-11-10 | S2: =VLOOKUP(A2,Hoja1!A:B,2,0) -> 8 | T2: =VLOOKUP(M2,[1]TIPOLOGIAS!$A:$F,4,0) -> MEDELLIN | U2: =VLOOKUP(T2,'BASE TARIFA 2025'!C:D,2,0) -> WOMPI NOROCCIDENTE | V2: =VLOOKUP(T2,'BASE TARIFA 2025'!C:F,4,0) -> 15709.5
A3: 76347 | B3: BARRIO JUNIN GRANADA GRANADA | C3: 43645420 | D3: 3235263995 | E3: 3128575628 | F3: 3128575628 | G3: CR 23 22 17,JUNIN GRANADA | H3: 6.1444621 | I3: -75.1860924 | J3: ANTIOQUIA | K3: GRANADA | L3: GRANADA | M3: 5313 | N3: 2025-11-10 | S3: =VLOOKUP(A3,Hoja1!A:B,2,0) -> 8 | T3: =VLOOKUP(M3,[1]TIPOLOGIAS!$A:$F,4,0) -> MEDELLIN | U3: =VLOOKUP(T3,'BASE TARIFA 2025'!C:D,2,0) -> WOMPI NOROCCIDENTE | V3: =VLOOKUP(T3,'BASE TARIFA 2025'!C:F,4,0) -> 15709.5
A4: 42888 | B4: BARRIO CENTRO GRANADA 1 | C4: 1041202120 | D4: 8320396 | E4: 3217742193 | F4: 3217742193 | G4: CR 24 A 21 10,CENTRO | H4: 6.142882 | I4: -75.1851 | J4: ANTIOQUIA | K4: GRANADA | L4: GRANADA | M4: 5313 | N4: 2025-11-10 | S4: =VLOOKUP(A4,Hoja1!A:B,2,0) -> 8 | T4: =VLOOKUP(M4,[1]TIPOLOGIAS!$A:$F,4,0) -> MEDELLIN | U4: =VLOOKUP(T4,'BASE TARIFA 2025'!C:D,2,0) -> WOMPI NOROCCIDENTE | V4: =VLOOKUP(T4,'BASE TARIFA 2025'!C:F,4,0) -> 15709.5
A5: 37971 | B5: BARRIO CENTRO GRANADA | C5: 1041203634 | E5: 3127054455 | F5: 3215029004 | G5: CR 23 21 34 LC 109 CENTRO | H5: 6.14341944 | I5: -75.1856152 | J5: ANTIOQUIA | K5: GRANADA | L5: GRANADA | M5: 5313 | N5: 2025-11-10 | S5: =VLOOKUP(A5,Hoja1!A:B,2,0) -> 8 | T5: =VLOOKUP(M5,[1]TIPOLOGIAS!$A:$F,4,0) -> MEDELLIN | U5: =VLOOKUP(T5,'BASE TARIFA 2025'!C:D,2,0) -> WOMPI NOROCCIDENTE | V5: =VLOOKUP(T5,'BASE TARIFA 2025'!C:F,4,0) -> 15709.5
A6: 13134 | B6: BARRIO UNICO - GRANDA ANTIOQUIA | C6: 70830261 | D6: 2643794 | E6: 3117207058 | F6: 3133559106 | G6: CL 21 21-25 | H6: 6.1439934 | I6: -75.1848529 | J6: ANTIOQUIA | K6: GRANADA | L6: GRANADA | M6: 5313 | N6: 2025-11-10 | S6: =VLOOKUP(A6,Hoja1!A:B,2,0) -> 16 | T6: =VLOOKUP(M6,[1]TIPOLOGIAS!$A:$F,4,0) -> MEDELLIN | U6: =VLOOKUP(T6,'BASE TARIFA 2025'!C:D,2,0) -> WOMPI NOROCCIDENTE | V6: =VLOOKUP(T6,'BASE TARIFA 2025'!C:F,4,0) -> 15709.5
A7: 10254 | B7: HISPANIA - ANTIOQUIA | C7: 21555569 | D7: 8432224 | E7: 3147215403 | F7: 3147215403 | G7: CR 51 FLORENCIA PAR PRINCIPAL DE HISPANIA | H7: 5.7991142 | I7: -75.9077696 | J7: ANTIOQUIA | K7: HISPANIA | L7: HISPANIA | M7: 5353 | N7: 2025-11-12 | S7: =VLOOKUP(A7,Hoja1!A:B,2,0) -> 8 | T7: =VLOOKUP(M7,[1]TIPOLOGIAS!$A:$F,4,0) -> MEDELLIN | U7: =VLOOKUP(T7,'BASE TARIFA 2025'!C:D,2,0) -> WOMPI NOROCCIDENTE | V7: =VLOOKUP(T7,'BASE TARIFA 2025'!C:F,4,0) -> 15709.5
A8: 40400 | B8: BARRIO PARQUE HISPANIA | C8: 1027884461 | D8: 8432045 | E8: 3146379251 | F8: 3146379251 | G8: CL 50 50 12 TOLEDO PORQUE PRINCIPAL,PARQUE | H8: 5.7999259 | I8: -75.9072391 | J8: ANTIOQUIA | K8: HISPANIA | L8: HISPANIA | M8: 5353 | N8: 2025-11-12 | S8: =VLOOKUP(A8,Hoja1!A:B,2,0) -> 16 | T8: =VLOOKUP(M8,[1]TIPOLOGIAS!$A:$F,4,0) -> MEDELLIN | U8: =VLOOKUP(T8,'BASE TARIFA 2025'!C:D,2,0) -> WOMPI NOROCCIDENTE | V8: =VLOOKUP(T8,'BASE TARIFA 2025'!C:F,4,0) -> 15709.5
A9: 73886 | B9: BARRIO CALLE TOLEDO HISPANIA | C9: 1001144624 | D9: 3113503670 | E9: 3113503670 | F9: 3113503670 | G9: CALLE 50 TOLEDO 49 33,CALLE TOLEDO | H9: 5.7998727 | I9: -75.9067541 | J9: ANTIOQUIA | K9: HISPANIA | L9: HISPANIA | M9: 5353 | N9: 2025-11-12 | S9: =VLOOKUP(A9,Hoja1!A:B,2,0) -> 8 | T9: =VLOOKUP(M9,[1]TIPOLOGIAS!$A:$F,4,0) -> MEDELLIN | U9: =VLOOKUP(T9,'BASE TARIFA 2025'!C:D,2,0) -> WOMPI NOROCCIDENTE | V9: =VLOOKUP(T9,'BASE TARIFA 2025'!C:F,4,0) -> 15709.5
A10: 77395 | B10: BARRIO VILLA REPUBLICANA CHIQUINQUIRA | C10: 46680285 | D10: 3133329935 | E10: 3133329935 | F10: 3133329935 | G10: CL 19 17 A 02,VILLA REPUBLICANA | H10: 5.62386426 | I10: -73.81922155 | J10: BOYACÁ | K10: CHIQUINQUIRÁ | L10: CHIQUINQUIRÁ | M10: 15176 | N10: 2025-11-13 | S10: =VLOOKUP(A10,Hoja1!A:B,2,0) -> 8 | T10: =VLOOKUP(M10,[1]TIPOLOGIAS!$A:$F,4,0) -> TUNJA | U10: =VLOOKUP(T10,'BASE TARIFA 2025'!C:D,2,0) -> WOMPI SANTANDERES | V10: =VLOOKUP(T10,'BASE TARIFA 2025'!C:F,4,0) -> 28277.1
A11: 78515 | B11: BARRIO SAN CARLOS CHIQUINQUIRA 1 | C11: 1002522047 | D11: 3142740848 | E11: 3142740848 | F11: 3142740848 | G11: DG 28 7 02 ,SAN CARLOS | H11: 5.6239891 | I11: -73.8077324 | J11: BOYACÁ | K11: CHIQUINQUIRÁ | L11: CHIQUINQUIRÁ | M11: 15176 | N11: 2025-11-14 | S11: =VLOOKUP(A11,Hoja1!A:B,2,0) -> 8 | T11: =VLOOKUP(M11,[1]TIPOLOGIAS!$A:$F,4,0) -> TUNJA | U11: =VLOOKUP(T11,'BASE TARIFA 2025'!C:D,2,0) -> WOMPI SANTANDERES | V11: =VLOOKUP(T11,'BASE TARIFA 2025'!C:F,4,0) -> 28277.1
A12: 76795 | B12: BARRIO VEDERA SUCRE OCCIDENTAL CHIQUINQUIRA | C12: 7316213 | D12: 3152292734 | E12: 3152292734 | F12: 3152292734 | G12: VRD SUCRE OCCIDENTAL,KM 1 SUR VIA BOGOTÁ,VEDERA SUCRE OCCIDENTAL | H12: 5.59722349 | I12: -73.83546531 | J12: BOYACÁ | K12: CHIQUINQUIRÁ | L12: CHIQUINQUIRÁ | M12: 15176 | N12: 2025-11-14 | S12: =VLOOKUP(A12,Hoja1!A:B,2,0) -> 8 | T12: =VLOOKUP(M12,[1]TIPOLOGIAS!$A:$F,4,0) -> TUNJA | U12: =VLOOKUP(T12,'BASE TARIFA 2025'!C:D,2,0) -> WOMPI SANTANDERES | V12: =VLOOKUP(T12,'BASE TARIFA 2025'!C:F,4,0) -> 28277.1
A13: 77224 | B13: BARRIO CENTRO CHIQUINQUIRÁ | C13: 1053327379 | D13: 3142696302 | E13: 3142696302 | F13: 3142696302 | G13: CR 12 16 13 BALCONES DE SAN JOSE ,PISO 2, OFICINA 202,CENTRO | H13: 5.61791145 | I13: -73.81791619 | J13: BOYACÁ | K13: CHIQUINQUIRÁ | L13: CHIQUINQUIRÁ | M13: 15176 | N13: 2025-11-13 | S13: =VLOOKUP(A13,Hoja1!A:B,2,0) -> 8 | T13: =VLOOKUP(M13,[1]TIPOLOGIAS!$A:$F,4,0) -> TUNJA | U13: =VLOOKUP(T13,'BASE TARIFA 2025'!C:D,2,0) -> WOMPI SANTANDERES | V13: =VLOOKUP(T13,'BASE TARIFA 2025'!C:F,4,0) -> 28277.1
A14: 70922 | B14: BARRIO VEREDA SASA CHIQUINQUIRA | C14: 1053343081 | D14: 3108094994 | E14: 3108094994 | F14: 3108094994 | G14: VRD SASA, KILOMETRO 8 VIA TUNJA,VEREDA SASA | H14: 5.6118117 | I14: -73.7395567 | J14: BOYACÁ | K14: CHIQUINQUIRÁ | L14: CHIQUINQUIRÁ | M14: 15176 | N14: 2025-11-14 | S14: =VLOOKUP(A14,Hoja1!A:B,2,0) -> 8 | T14: =VLOOKUP(M14,[1]TIPOLOGIAS!$A:$F,4,0) -> TUNJA | U14: =VLOOKUP(T14,'BASE TARIFA 2025'!C:D,2,0) -> WOMPI SANTANDERES | V14: =VLOOKUP(T14,'BASE TARIFA 2025'!C:F,4,0) -> 28277.1
A15: 67789 | B15: PARQUE PRINCIPAL LA CEJA | C15: 1040049827 | D15: 3217235081 | E15: 3217235081 | F15: 3217235081 | G15: CL 13 AE 7 29 | H15: 6.0221272 | I15: -75.4225021 | J15: ANTIOQUIA | K15: LA CEJA | L15: LA CEJA | M15: 5376 | N15: 2025-11-19 | S15: =VLOOKUP(A15,Hoja1!A:B,2,0) -> 8 | T15: =VLOOKUP(M15,[1]TIPOLOGIAS!$A:$F,4,0) -> MEDELLIN | U15: =VLOOKUP(T15,'BASE TARIFA 2025'!C:D,2,0) -> WOMPI NOROCCIDENTE | V15: =VLOOKUP(T15,'BASE TARIFA 2025'!C:F,4,0) -> 15709.5
A16: 77118 | B16: BARRIO LA CEJA LA CEJA 9 | C16: 901314321 | D16: 3205880628 | E16: 3205880628 | F16: 3137013499 | G16: CL 20 17 A 08,LA CEJA | H16: 6.0305830 | I16: -75.4291404 | J16: ANTIOQUIA | K16: LA CEJA | L16: LA CEJA | M16: 5376 | N16: 2025-11-19 | S16: =VLOOKUP(A16,Hoja1!A:B,2,0) -> 8 | T16: =VLOOKUP(M16,[1]TIPOLOGIAS!$A:$F,4,0) -> MEDELLIN | U16: =VLOOKUP(T16,'BASE TARIFA 2025'!C:D,2,0) -> WOMPI NOROCCIDENTE | V16: =VLOOKUP(T16,'BASE TARIFA 2025'!C:F,4,0) -> 15709.5
A17: 76330 | B17: BARRIO CUIDAD JARDIN LA CEJA LA CEJA | C17: 71527195 | D17: 3024372762 | E17: 3024372762 | F17: 3122417335 | G17: CL 19 10 160 LC 29 | H17: 6.028166 | I17: -75.424026 | J17: ANTIOQUIA | K17: LA CEJA | L17: LA CEJA | M17: 5376 | N17: 2025-11-19 | S17: =VLOOKUP(A17,Hoja1!A:B,2,0) -> 8 | T17: =VLOOKUP(M17,[1]TIPOLOGIAS!$A:$F,4,0) -> MEDELLIN | U17: =VLOOKUP(T17,'BASE TARIFA 2025'!C:D,2,0) -> WOMPI NOROCCIDENTE | V17: =VLOOKUP(T17,'BASE TARIFA 2025'!C:F,4,0) -> 15709.5
... A20: 76146 | B20: BARRIO CALLE DEL COMERCIO NECHI | C20: 21646911 | D20: 3245668267 | E20: 3245668267 | F20: 3245668267 | G20: CALLE DEL COMERCIO BRR CALLE DEL COMERCIO,CALLE DEL COMERCIO | H20: 8.09571846 | I20: -74.7738059 | J20: ANTIOQUIA | K20: NECHÍ | L20: NECHÍ | M20: 5495 | N20: 2025-11-05 | S20: =VLOOKUP(A20,Hoja1!A:B,2,0) -> 8 | T20: =VLOOKUP(M20,[1]TIPOLOGIAS!$A:$F,4,0) -> MONTERIA | U20: =VLOOKUP(T20,'BASE TARIFA 2025'!C:D,2,0) -> WOMPI COSTA | V20: =VLOOKUP(T20,'BASE TARIFA 2025'!C:F,4,0) -> 15709.5
A21: 79812 | B21: BARRIO CENTRO NECHI 2 | C21: 1038484267 | D21: 3127995453 | E21: 3127995453 | G21: CR 28 31 37 ,CENTRO | H21: 8.0964269 | I21: -74.7738804 | J21: ANTIOQUIA | K21: NECHÍ | L21: NECHÍ | M21: 5495 | N21: 2025-11-05 | S21: =VLOOKUP(A21,Hoja1!A:B,2,0) -> 8 | T21: =VLOOKUP(M21,[1]TIPOLOGIAS!$A:$F,4,0) -> MONTERIA | U21: =VLOOKUP(T21,'BASE TARIFA 2025'!C:D,2,0) -> WOMPI COSTA | V21: =VLOOKUP(T21,'BASE TARIFA 2025'!C:F,4,0) -> 15709.5
A22: 36854 | B22: BARRIO PUERTO BERRIO ANTIOQUIA 1 | C22: 1039681777 | E22: 3015821687 | F22: 3015821687 | G22: COLEMMA ALTOS DE LA MALENA BG 1 BRR MALENA | H22: 6.4905367 | I22: -74.4179400 | J22: ANTIOQUIA | K22: PUERTO BERRÍO | L22: PUERTO BERRÍO | M22: 5579 | N22: 2025-11-06 | S22: =VLOOKUP(A22,Hoja1!A:B,2,0) -> 8 | T22: =VLOOKUP(M22,[1]TIPOLOGIAS!$A:$F,4,0) -> MEDELLIN | U22: =VLOOKUP(T22,'BASE TARIFA 2025'!C:D,2,0) -> WOMPI NOROCCIDENTE | V22: =VLOOKUP(T22,'BASE TARIFA 2025'!C:F,4,0) -> 15709.5
A23: 38484 | B23: BARRIO PLAZA DE MERCADO PUERTO BERRIO | C23: 22188241 | E23: 3017808975 | F23: 3147776504 | G23: CR 3 n 12 25 PLAZA DE MERCADO | H23: 6.4915707 | I23: -74.3997843 | J23: ANTIOQUIA | K23: PUERTO BERRÍO | L23: PUERTO BERRÍO | M23: 5579 | N23: 2025-11-06 | S23: =VLOOKUP(A23,Hoja1!A:B,2,0) -> 8 | T23: =VLOOKUP(M23,[1]TIPOLOGIAS!$A:$F,4,0) -> MEDELLIN | U23: =VLOOKUP(T23,'BASE TARIFA 2025'!C:D,2,0) -> WOMPI NOROCCIDENTE | V23: =VLOOKUP(T23,'BASE TARIFA 2025'!C:F,4,0) -> 15709.5
A24: 19841 | B24: BARRIO CENTRO ITAGUI | C24: 900356199 | D24: 3713515 | E24: 3104962846 | F24: 3104962846 | G24: CR 49 52 18 | H24: 6.1718655 | I24: -75.6075296 | J24: ANTIOQUIA | K24: ITAGÜÍ | L24: ITAGÜÍ | M24: 5360 | N24: 2025-11-20 | S24: =VLOOKUP(A24,Hoja1!A:B,2,0) -> 8 | T24: =VLOOKUP(M24,[1]TIPOLOGIAS!$A:$F,4,0) -> MEDELLIN | U24: =VLOOKUP(T24,'BASE TARIFA 2025'!C:D,2,0) -> WOMPI NOROCCIDENTE | V24: =VLOOKUP(T24,'BASE TARIFA 2025'!C:F,4,0) -> 15709.5
A25: 21690 | B25: BARRIO VILLA PAULA - ITAGUÍ | C25: 900393402 | D25: 2779804 | E25: 3218568106 | F25: 3218568106 | G25: CR 51 55 21 | H25: 6.174481 | I25: -75.606261 | J25: ANTIOQUIA | K25: ITAGÜÍ | L25: ITAGÜÍ | M25: 5360 | N25: 2025-11-05 | S25: =VLOOKUP(A25,Hoja1!A:B,2,0) -> 8 | T25: =VLOOKUP(M25,[1]TIPOLOGIAS!$A:$F,4,0) -> MEDELLIN | U25: =VLOOKUP(T25,'BASE TARIFA 2025'!C:D,2,0) -> WOMPI NOROCCIDENTE | V25: =VLOOKUP(T25,'BASE TARIFA 2025'!C:F,4,0) -> 15709.5
A26: 12172 | B26: BARRIO SANTA MARIA - ITAGUI | C26: 8162439 | D26: 3715196 | E26: 3113494477 | F26: 3113494477 | G26: CR 52 80-95 | H26: 6.1892231 | I26: -75.5934104 | J26: ANTIOQUIA | K26: ITAGÜÍ | L26: ITAGÜÍ | M26: 5360 | N26: 2025-11-20 | S26: =VLOOKUP(A26,Hoja1!A:B,2,0) -> 16 | T26: =VLOOKUP(M26,[1]TIPOLOGIAS!$A:$F,4,0) -> MEDELLIN | U26: =VLOOKUP(T26,'BASE TARIFA 2025'!C:D,2,0) -> WOMPI NOROCCIDENTE | V26: =VLOOKUP(T26,'BASE TARIFA 2025'!C:F,4,0) -> 15709.5
A27: 28499 | B27: BARRIO PARQUE PRINCIPAL 3 LA UNIÓN | C27: 900280884 | D27: 5688198 | E27: 3137052134 | F27: 3137052134 | G27: CR 09 9 73 | H27: 5.973093 | I27: -75.360755 | J27: ANTIOQUIA | K27: LA UNIÓN | L27: LA UNIÓN | M27: 5400 | N27: 2025-11-07 | S27: =VLOOKUP(A27,Hoja1!A:B,2,0) -> 16 | T27: =VLOOKUP(M27,[1]TIPOLOGIAS!$A:$F,4,0) -> MEDELLIN | U27: =VLOOKUP(T27,'BASE TARIFA 2025'!C:D,2,0) -> WOMPI NOROCCIDENTE | V27: =VLOOKUP(T27,'BASE TARIFA 2025'!C:F,4,0) -> 15709.5
A28: 40901 | B28: BARRIO CENTRO LA UNION 1 | C28: 1036779870 | E28: 3207609743 | F28: 3148595683 | G28: CR 11 NÚMERO 10-65,CENTRO | H28: 5.9734720 | I28: -75.3625684 | J28: ANTIOQUIA | K28: LA UNIÓN | L28: LA UNIÓN | M28: 5400 | N28: 2025-11-07 | S28: =VLOOKUP(A28,Hoja1!A:B,2,0) -> 8 | T28: =VLOOKUP(M28,[1]TIPOLOGIAS!$A:$F,4,0) -> MEDELLIN | U28: =VLOOKUP(T28,'BASE TARIFA 2025'!C:D,2,0) -> WOMPI NOROCCIDENTE | V28: =VLOOKUP(T28,'BASE TARIFA 2025'!C:F,4,0) -> 15709.5
A29: 79629 | B29: BARRIO EL EDEN LA UNION | C29: 1017155887 | D29: 3104455714 | E29: 3104455714 | F29: 3104455714 | G29: CR 8 9 31,EL EDEN | H29: 5.9731588 | I29: -75.3598665 | J29: ANTIOQUIA | K29: LA UNIÓN | L29: LA UNIÓN | M29: 5400 | N29: 2025-11-13 | S29: =VLOOKUP(A29,Hoja1!A:B,2,0) -> 8 | T29: =VLOOKUP(M29,[1]TIPOLOGIAS!$A:$F,4,0) -> MEDELLIN | U29: =VLOOKUP(T29,'BASE TARIFA 2025'!C:D,2,0) -> WOMPI NOROCCIDENTE | V29: =VLOOKUP(T29,'BASE TARIFA 2025'!C:F,4,0) -> 15709.5
A30: 69294 | B30: PARQUE PRINCIPAL LA UNION ANTIOQUIA | C30: 1040036655 | D30: 3148797221 | E30: 3148797221 | F30: 3148797221 | G30: CALLE 12 07 57,PARQUE PRINCIPAL | H30: 5.9753174 | I30: -75.3601249 | J30: ANTIOQUIA | K30: LA UNIÓN | L30: LA UNIÓN | M30: 5400 | N30: 2025-11-13 | S30: =VLOOKUP(A30,Hoja1!A:B,2,0) -> 8 | T30: =VLOOKUP(M30,[1]TIPOLOGIAS!$A:$F,4,0) -> MEDELLIN | U30: =VLOOKUP(T30,'BASE TARIFA 2025'!C:D,2,0) -> WOMPI NOROCCIDENTE | V30: =VLOOKUP(T30,'BASE TARIFA 2025'!C:F,4,0) -> 15709.5
A31: 72019 | B31: LA UNION HOSPITAL | C31: 1036782025 | D31: 3216642199 | E31: 3216642199 | F31: 3216642199 | G31: CL 12 NRO 11 09,HOSPITAL | H31: 5.9744872 | I31: -75.3629122 | J31: ANTIOQUIA | K31: LA UNIÓN | L31: LA UNIÓN | M31: 5400 | N31: 2025-11-07 | S31: =VLOOKUP(A31,Hoja1!A:B,2,0) -> 8 | T31: =VLOOKUP(M31,[1]TIPOLOGIAS!$A:$F,4,0) -> MEDELLIN | U31: =VLOOKUP(T31,'BASE TARIFA 2025'!C:D,2,0) -> WOMPI NOROCCIDENTE | V31: =VLOOKUP(T31,'BASE TARIFA 2025'!C:F,4,0) -> 15709.5
A32: 74952 | B32: BARRIO LA UNION LA UNION 4 | C32: 43473505 | D32: 3114204205 | E32: 3215534638 | F32: 3127102087 | G32: CR 10 11 64,LA UNION | H32: 5.9745060 | I32: -75.3619963 | J32: ANTIOQUIA | K32: LA UNIÓN | L32: LA UNIÓN | M32: 5400 | N32: 2025-11-07 | S32: =VLOOKUP(A32,Hoja1!A:B,2,0) -> 8 | T32: =VLOOKUP(M32,[1]TIPOLOGIAS!$A:$F,4,0) -> MEDELLIN | U32: =VLOOKUP(T32,'BASE TARIFA 2025'!C:D,2,0) -> WOMPI NOROCCIDENTE | V32: =VLOOKUP(T32,'BASE TARIFA 2025'!C:F,4,0) -> 15709.5
A33: 75932 | B33: BARRIO LA UNION LA UNION 5 | C33: 901711520 | D33: 0 | E33: 3104326808 | F33: 3007216779 | G33: CL 10 # 08 30 | H33: 5.9736987 | I33: -75.3602504 | J33: ANTIOQUIA | K33: LA UNIÓN | L33: LA UNIÓN | M33: 5400 | N33: 2025-11-13 | S33: =VLOOKUP(A33,Hoja1!A:B,2,0) -> 8 | T33: =VLOOKUP(M33,[1]TIPOLOGIAS!$A:$F,4,0) -> MEDELLIN | U33: =VLOOKUP(T33,'BASE TARIFA 2025'!C:D,2,0) -> WOMPI NOROCCIDENTE | V33: =VLOOKUP(T33,'BASE TARIFA 2025'!C:F,4,0) -> 15709.5
A34: 46089 | B34: BARRIO CENTRO LA UNION 2 | C34: 15355049 | E34: 3217672293 | F34: 3127587149 | G34: CL 7 10 - 02,CENTRO | H34: 5.9709510 | I34: -75.3607482 | J34: ANTIOQUIA | K34: LA UNIÓN | L34: LA UNIÓN | M34: 5400 | N34: 2025-11-13 | S34: =VLOOKUP(A34,Hoja1!A:B,2,0) -> 8 | T34: =VLOOKUP(M34,[1]TIPOLOGIAS!$A:$F,4,0) -> MEDELLIN | U34: =VLOOKUP(T34,'BASE TARIFA 2025'!C:D,2,0) -> WOMPI NOROCCIDENTE | V34: =VLOOKUP(T34,'BASE TARIFA 2025'!C:F,4,0) -> 15709.5
A35: 49305 | B35: BARRIO CENTRO LA UNION 3 | C35: 43862122 | D35: 0 | E35: 3185582078 | F35: 3185582078 | G35: CR 8 11 04 | H35: 5.974612 | I35: -75.360146 | J35: ANTIOQUIA | K35: LA UNIÓN | L35: LA UNIÓN | M35: 5400 | N35: 2025-11-13 | S35: =VLOOKUP(A35,Hoja1!A:B,2,0) -> 8 | T35: =VLOOKUP(M35,[1]TIPOLOGIAS!$A:$F,4,0) -> MEDELLIN | U35: =VLOOKUP(T35,'BASE TARIFA 2025'!C:D,2,0) -> WOMPI NOROCCIDENTE | V35: =VLOOKUP(T35,'BASE TARIFA 2025'!C:F,4,0) -> 15709.5
A36: 69014 | B36: BARRIO LATIN FLOWERS FARMS | C36: 900111576 | D36: 3136607428 | E36: 0 | F36: 3136607428 | G36: CL 12 12 68,SECTOR EL HOSPITAL | H36: 5.9741124 | I36: -75.3642466 | J36: ANTIOQUIA | K36: LA UNIÓN | L36: LA UNIÓN | M36: 5400 | N36: 2025-11-07 | S36: =VLOOKUP(A36,Hoja1!A:B,2,0) -> 8 | T36: =VLOOKUP(M36,[1]TIPOLOGIAS!$A:$F,4,0) -> MEDELLIN | U36: =VLOOKUP(T36,'BASE TARIFA 2025'!C:D,2,0) -> WOMPI NOROCCIDENTE | V36: =VLOOKUP(T36,'BASE TARIFA 2025'!C:F,4,0) -> 15709.5
A37: 78803 | B37: BARRIO VEREDA QUIRBAQUIRA ARCABUCO 1 | C37: 1095822577 | D37: 3163088919 | E37: 3163088919 | G37: VRD QUIRBAQUIRA, SECTOR CASA BLANCA,VEREDA QUIRBAQUIRA | H37: 5.6912697 | I37: -73.3675628 | J37: BOYACÁ | K37: ARCABUCO | L37: ARCABUCO | M37: 15051 | N37: 2025-11-05 | S37: =VLOOKUP(A37,Hoja1!A:B,2,0) -> 8 | T37: =VLOOKUP(M37,[1]TIPOLOGIAS!$A:$F,4,0) -> TUNJA | U37: =VLOOKUP(T37,'BASE TARIFA 2025'!C:D,2,0) -> WOMPI SANTANDERES | V37: =VLOOKUP(T37,'BASE TARIFA 2025'!C:F,4,0) -> 28277.1
A38: 47103 | B38: BARRIO CENTRO BOYACA 1 | C38: 7179742 | D38: 3165362959 | E38: 3165362959 | F38: 3165362959 | G38: Carrera 5 # 3 - 31 Centro | H38: 5.454 | I38: -73.362 | J38: BOYACÁ | K38: BOYACÁ | L38: BOYACÁ | M38: 15104 | N38: 2025-11-13 | S38: =VLOOKUP(A38,Hoja1!A:B,2,0) -> 8 | T38: =VLOOKUP(M38,[1]TIPOLOGIAS!$A:$F,4,0) -> TUNJA | U38: =VLOOKUP(T38,'BASE TARIFA 2025'!C:D,2,0) -> WOMPI SANTANDERES | V38: =VLOOKUP(T38,'BASE TARIFA 2025'!C:F,4,0) -> 28277.1
A39: 65463 | B39: BARRIO CENTRO BOYACA 4 | C39: 1050170897 | D39: 3144233419 | E39: 3144233419 | F39: 3144233419 | G39: CR 4 A 3 85,CENTRO | H39: 5.4538173 | I39: -73.3630605 | J39: BOYACÁ | K39: BOYACÁ | L39: BOYACÁ | M39: 15104 | N39: 2025-11-13 | S39: =VLOOKUP(A39,Hoja1!A:B,2,0) -> 8 | T39: =VLOOKUP(M39,[1]TIPOLOGIAS!$A:$F,4,0) -> TUNJA | U39: =VLOOKUP(T39,'BASE TARIFA 2025'!C:D,2,0) -> WOMPI SANTANDERES | V39: =VLOOKUP(T39,'BASE TARIFA 2025'!C:F,4,0) -> 28277.1
A40: 70551 | B40: BARRIO BOYACA BAJO CHIQUINQUIRA 3 | C40: 1053344552 | D40: 3225201619 | E40: 3225201619 | F40: 3225201619 | G40: CR 9 A 3 9,BOYACA BAJO | H40: 5.61052869 | I40: -73.82480853 | J40: BOYACÁ | K40: CHIQUINQUIRÁ | L40: CHIQUINQUIRÁ | M40: 15176 | N40: 2025-11-14 | S40: =VLOOKUP(A40,Hoja1!A:B,2,0) -> 8 | T40: =VLOOKUP(M40,[1]TIPOLOGIAS!$A:$F,4,0) -> TUNJA | U40: =VLOOKUP(T40,'BASE TARIFA 2025'!C:D,2,0) -> WOMPI SANTANDERES | V40: =VLOOKUP(T40,'BASE TARIFA 2025'!C:F,4,0) -> 28277.1
A41: 49763 | B41: BARRIO PUERTO BERRIO PUERTO BERRIO | C41: 901175583 | D41: 0 | E41: 3103830426 | F41: 3103830426 | G41: CL 42 A NR0. 8 -6 BRR LLERAS | H41: 6.4860518 | I41: -74.4055606 | J41: ANTIOQUIA | K41: PUERTO BERRÍO | L41: PUERTO BERRÍO | M41: 5579 | N41: 2025-11-06 | S41: =VLOOKUP(A41,Hoja1!A:B,2,0) -> 16 | T41: =VLOOKUP(M41,[1]TIPOLOGIAS!$A:$F,4,0) -> MEDELLIN | U41: =VLOOKUP(T41,'BASE TARIFA 2025'!C:D,2,0) -> WOMPI NOROCCIDENTE | V41: =VLOOKUP(T41,'BASE TARIFA 2025'!C:F,4,0) -> 15709.5
A42: 45977 | B42: BARRIO LA MARGARITA PUERTO BERRIO 1 | C42: 42960789 | D42: 8330068 | E42: 3016209379 | F42: 3016209379 | G42: VRD LA MARGARITA,LA MARGARITA | H42: 6.495189 | I42: -74.474370 | J42: ANTIOQUIA | K42: PUERTO BERRÍO | L42: PUERTO BERRÍO | M42: 5579 | N42: 2025-11-06 | S42: =VLOOKUP(A42,Hoja1!A:B,2,0) -> 8 | T42: =VLOOKUP(M42,[1]TIPOLOGIAS!$A:$F,4,0) -> MEDELLIN | U42: =VLOOKUP(T42,'BASE TARIFA 2025'!C:D,2,0) -> WOMPI NOROCCIDENTE | V42: =VLOOKUP(T42,'BASE TARIFA 2025'!C:F,4,0) -> 15709.5
A43: 60457 | B43: BARRIO CENTRO PUERTO BERRIO 4 | C43: 98505429 | D43: 0 | E43: 3137979779 | F43: 3137979779 | G43: CR 3 57 97 | H43: 6.4928787 | I43: -74.399246 | J43: ANTIOQUIA | K43: PUERTO BERRÍO | L43: PUERTO BERRÍO | M43: 5579 | N43: 2025-11-07 | S43: =VLOOKUP(A43,Hoja1!A:B,2,0) -> 8 | T43: =VLOOKUP(M43,[1]TIPOLOGIAS!$A:$F,4,0) -> MEDELLIN | U43: =VLOOKUP(T43,'BASE TARIFA 2025'!C:D,2,0) -> WOMPI NOROCCIDENTE | V43: =VLOOKUP(T43,'BASE TARIFA 2025'!C:F,4,0) -> 15709.5
A44: 69297 | B44: BARRIO CENTRO PUERTO BERRIO 6 | C44: 43652146 | D44: 3136557113 | E44: 3136557113 | F44: 3136557113 | G44: CALLE 50 7 20 BRR CENTRO,CENTRO | H44: 6.4896454 | I44: -74.4034766 | J44: ANTIOQUIA | K44: PUERTO BERRÍO | L44: PUERTO BERRÍO | M44: 5579 | N44: 2025-11-07 | S44: =VLOOKUP(A44,Hoja1!A:B,2,0) -> 8 | T44: =VLOOKUP(M44,[1]TIPOLOGIAS!$A:$F,4,0) -> MEDELLIN | U44: =VLOOKUP(T44,'BASE TARIFA 2025'!C:D,2,0) -> WOMPI NOROCCIDENTE | V44: =VLOOKUP(T44,'BASE TARIFA 2025'!C:F,4,0) -> 15709.5
A45: 67654 | B45: BARRIO VRA MINAS DEL VAPOR PUERTO BERRIO | C45: 39215386 | D45: 0 | E45: 3229306882 | F45: 3229306882 | G45: VRA MINAS DEL VAPOR - VDA MINAS DEL VAPOR ,VRA MINAS DEL VAPOR | H45: 6.4564882 | I45: -74.6306562 | J45: ANTIOQUIA | K45: PUERTO BERRÍO | L45: PUERTO BERRÍO | M45: 5579 | N45: 2025-11-10 | S45: =VLOOKUP(A45,Hoja1!A:B,2,0) -> 8 | T45: =VLOOKUP(M45,[1]TIPOLOGIAS!$A:$F,4,0) -> MEDELLIN | U45: =VLOOKUP(T45,'BASE TARIFA 2025'!C:D,2,0) -> WOMPI NOROCCIDENTE | V45: =VLOOKUP(T45,'BASE TARIFA 2025'!C:F,4,0) -> 15709.5
A46: 15218 | B46: BARRIO LA GRANJA II TUNJA | C46: 74374334 | D46: 8821750 | E46: 3103292709 | F46: 3103292709 | G46: CL 54 7-13 LA GRANJA | H46: 5.56117952 | I46: -73.34892293 | J46: BOYACÁ | K46: TUNJA | L46: TUNJA | M46: 15001 | N46: 2025-11-20 | S46: =VLOOKUP(A46,Hoja1!A:B,2,0) -> 16 | T46: =VLOOKUP(M46,[1]TIPOLOGIAS!$A:$F,4,0) -> TUNJA | U46: =VLOOKUP(T46,'BASE TARIFA 2025'!C:D,2,0) -> WOMPI SANTANDERES | V46: =VLOOKUP(T46,'BASE TARIFA 2025'!C:F,4,0) -> 28277.1
A47: 80194 | B47: BARRIO SANTA RITA TUNJA 4 | C47: 24037163 | D47: 3108181835 | E47: 3143145414 | F47: 3143145414 | G47: CR 8 B 58 05,SANTA RITA | H47: 5.5653133 | I47: -73.3478377 | J47: BOYACÁ | K47: TUNJA | L47: TUNJA | M47: 15001 | N47: 2025-11-05 | S47: =VLOOKUP(A47,Hoja1!A:B,2,0) -> 8 | T47: =VLOOKUP(M47,[1]TIPOLOGIAS!$A:$F,4,0) -> TUNJA | U47: =VLOOKUP(T47,'BASE TARIFA 2025'!C:D,2,0) -> WOMPI SANTANDERES | V47: =VLOOKUP(T47,'BASE TARIFA 2025'!C:F,4,0) -> 28277.1
A48: 77296 | B48: BARRIO CENTRO TUNJA 29 | C48: 1013681722 | D48: 3228080370 | E48: 3228080370 | F48: 3228080370 | G48: CR 9 20 09,CENTRO | H48: 5.53291885 | I48: -73.36089901 | J48: BOYACÁ | K48: TUNJA | L48: TUNJA | M48: 15001 | N48: 2025-11-20 | S48: =VLOOKUP(A48,Hoja1!A:B,2,0) -> 8 | T48: =VLOOKUP(M48,[1]TIPOLOGIAS!$A:$F,4,0) -> TUNJA | U48: =VLOOKUP(T48,'BASE TARIFA 2025'!C:D,2,0) -> WOMPI SANTANDERES | V48: =VLOOKUP(T48,'BASE TARIFA 2025'!C:F,4,0) -> 28277.1
A49: 77601 | B49: BARRIO LA FUENTE TUNJA 3 | C49: 33367554 | D49: 3102533408 | E49: 3102533400 | F49: 3102533400 | G49: CL 34 B 16 B 16,LA FUENTE | H49: 5.54800902 | I49: -73.36447181 | J49: BOYACÁ | K49: TUNJA | L49: TUNJA | M49: 15001 | N49: 2025-11-20 | S49: =VLOOKUP(A49,Hoja1!A:B,2,0) -> 8 | T49: =VLOOKUP(M49,[1]TIPOLOGIAS!$A:$F,4,0) -> TUNJA | U49: =VLOOKUP(T49,'BASE TARIFA 2025'!C:D,2,0) -> WOMPI SANTANDERES | V49: =VLOOKUP(T49,'BASE TARIFA 2025'!C:F,4,0) -> 28277.1
... A53: 10364 | B53: BARRIO EL CARMELO | C53: 43840383 | D53: 2815772 | E53: 3004564538 | F53: 3229709071 | G53: CL 76 45 A 23 | H53: 6.1831241 | I53: -75.5921676 | J53: ANTIOQUIA | K53: ITAGÜÍ | L53: ITAGÜÍ | M53: 5360 | N53: 2025-11-20 | S53: =VLOOKUP(A53,Hoja1!A:B,2,0) -> 16 | T53: =VLOOKUP(M53,[1]TIPOLOGIAS!$A:$F,4,0) -> MEDELLIN | U53: =VLOOKUP(T53,'BASE TARIFA 2025'!C:D,2,0) -> WOMPI NOROCCIDENTE | V53: =VLOOKUP(T53,'BASE TARIFA 2025'!C:F,4,0) -> 15709.5
A54: 34342 | B54: BARRIO CENTRO MILAN 1 | C54: 65783765 | E54: 3115984971 | F54: 3115984971 | G54: CL PRINCIPAL DE SAN ANTONIO DE GETUCHA | H54: 1.0999342 | I54: -75.4022001 | J54: CAQUETÁ | K54: MILÁN | L54: MILÁN | M54: 18460 | N54: 2025-11-21 | S54: =VLOOKUP(A54,Hoja1!A:B,2,0) -> 8 | T54: =VLOOKUP(M54,[1]TIPOLOGIAS!$A:$F,4,0) -> NEIVA | U54: =VLOOKUP(T54,'BASE TARIFA 2025'!C:D,2,0) -> WOMPI ORIENTE | V54: =VLOOKUP(T54,'BASE TARIFA 2025'!C:F,4,0) -> 28277.1
A55: 37791 | B55: BARRIO SAN ANTONIO GETUCHA MILAN | C55: 7725296 | E55: 3124344457 | F55: 3124344457 | G55: CL PRINCIPAL IPM SAN ANTONIO DE GETUCHA SAN ANTONIO GETUCHA | H55: 1.098474166 | I55: -75.40140972 | J55: CAQUETÁ | K55: MILÁN | L55: MILÁN | M55: 18460 | N55: 2025-11-21 | S55: =VLOOKUP(A55,Hoja1!A:B,2,0) -> 8 | T55: =VLOOKUP(M55,[1]TIPOLOGIAS!$A:$F,4,0) -> NEIVA | U55: =VLOOKUP(T55,'BASE TARIFA 2025'!C:D,2,0) -> WOMPI ORIENTE | V55: =VLOOKUP(T55,'BASE TARIFA 2025'!C:F,4,0) -> 28277.1
A56: 68669 | B56: BARRIO CENTRO MILAN 2 | C56: 1106768220 | D56: 3212068788 | E56: 3212068788 | F56: 3212068788 | G56: CL PRINCIPAL MANZANA 9,CENTRO | H56: 1.0999974 | I56: -75.4022003 | J56: CAQUETÁ | K56: MILÁN | L56: MILÁN | M56: 18460 | N56: 2025-11-21 | S56: =VLOOKUP(A56,Hoja1!A:B,2,0) -> 8 | T56: =VLOOKUP(M56,[1]TIPOLOGIAS!$A:$F,4,0) -> NEIVA | U56: =VLOOKUP(T56,'BASE TARIFA 2025'!C:D,2,0) -> WOMPI ORIENTE | V56: =VLOOKUP(T56,'BASE TARIFA 2025'!C:F,4,0) -> 28277.1
A57: 64433 | B57: BARRIO EL PROGRESO PUERTO ESCONDIDO 1 | C57: 901523817 | D57: 3234014949 | E57: 3106240241 | F57: 3106240241 | G57: PLAZA PRINCIPAL DEL PROGRESO 17 35 ,brrEL PROGRESO | H57: 9.019334 | I57: -76.261506 | J57: CÓRDOBA | K57: PUERTO ESCONDIDO | L57: PUERTO ESCONDIDO | M57: 23574 | N57: 2025-11-28 | S57: =VLOOKUP(A57,Hoja1!A:B,2,0) -> 8 | T57: =VLOOKUP(M57,[1]TIPOLOGIAS!$A:$F,4,0) -> MONTERIA | U57: =VLOOKUP(T57,'BASE TARIFA 2025'!C:D,2,0) -> WOMPI COSTA | V57: =VLOOKUP(T57,'BASE TARIFA 2025'!C:F,4,0) -> 15709.5
A58: 28519 | B58: BARRIO TUCHIN 2 CÓRDOBA | C58: 78380842 | D58: 3186385 | E58: 3116827824 | F58: 3116827824 | G58: CL 1 1 119 | H58: 9.1838259 | I58: -75.5481295 | J58: CÓRDOBA | K58: TUCHÍN | L58: TUCHÍN | M58: 23815 | N58: 2025-11-10 | S58: =VLOOKUP(A58,Hoja1!A:B,2,0) -> 16 | T58: =VLOOKUP(M58,[1]TIPOLOGIAS!$A:$F,4,0) -> MONTERIA | U58: =VLOOKUP(T58,'BASE TARIFA 2025'!C:D,2,0) -> WOMPI COSTA | V58: =VLOOKUP(T58,'BASE TARIFA 2025'!C:F,4,0) -> 15709.5
A59: 28877 | B59: BARRIO CENTRO TUCHIN | C59: 92500783 | D59: 7856529 | E59: 3004483217 | F59: 3004483217 | G59: CL 13 CR 13 A 85 BARRIO CENTRAL | H59: 9.1868027 | I59: -75.5545002 | J59: CÓRDOBA | K59: TUCHÍN | L59: TUCHÍN | M59: 23815 | N59: 2025-11-10 | S59: =VLOOKUP(A59,Hoja1!A:B,2,0) -> 16 | T59: =VLOOKUP(M59,[1]TIPOLOGIAS!$A:$F,4,0) -> MONTERIA | U59: =VLOOKUP(T59,'BASE TARIFA 2025'!C:D,2,0) -> WOMPI COSTA | V59: =VLOOKUP(T59,'BASE TARIFA 2025'!C:F,4,0) -> 15709.5
A60: 64838 | B60: BARRIO EL CENTRO TUCHIN | C60: 11062493 | D60: 3017479723 | E60: 3145144465 | F60: 3145144465 | G60: CL 15 12-34 FRENTE AL PARQUE,EL CENTRO | H60: 9.18719 | I60: -75.55416 | J60: CÓRDOBA | K60: TUCHÍN | L60: TUCHÍN | M60: 23815 | N60: 2025-11-10 | S60: =VLOOKUP(A60,Hoja1!A:B,2,0) -> 16 | T60: =VLOOKUP(M60,[1]TIPOLOGIAS!$A:$F,4,0) -> MONTERIA | U60: =VLOOKUP(T60,'BASE TARIFA 2025'!C:D,2,0) -> WOMPI COSTA | V60: =VLOOKUP(T60,'BASE TARIFA 2025'!C:F,4,0) -> 15709.5
A61: 75067 | B61: BARRIO SAN PEDRO TUCHIN | C61: 1128047535 | D61: 3004573086 | E61: 3004573086 | F61: 3004573086 | G61: CL 14 15 C 33,SAN PEDRO | H61: 9.1872295 | I61: -75.5560865 | J61: CÓRDOBA | K61: TUCHÍN | L61: TUCHÍN | M61: 23815 | N61: 2025-11-10 | S61: =VLOOKUP(A61,Hoja1!A:B,2,0) -> 8 | T61: =VLOOKUP(M61,[1]TIPOLOGIAS!$A:$F,4,0) -> MONTERIA | U61: =VLOOKUP(T61,'BASE TARIFA 2025'!C:D,2,0) -> WOMPI COSTA | V61: =VLOOKUP(T61,'BASE TARIFA 2025'!C:F,4,0) -> 15709.5
A62: 76704 | B62: BARRIO TUCHIN TUCHIN | C62: 1078247211 | D62: 3138796610 | E62: 3138796610 | F62: 3138796610 | G62: CL 13 13 4,TUCHIN | H62: 9.187192 | I62: -75.553131 | J62: CÓRDOBA | K62: TUCHÍN | L62: TUCHÍN | M62: 23815 | N62: 2025-11-13 | S62: =VLOOKUP(A62,Hoja1!A:B,2,0) -> 8 | T62: =VLOOKUP(M62,[1]TIPOLOGIAS!$A:$F,4,0) -> MONTERIA | U62: =VLOOKUP(T62,'BASE TARIFA 2025'!C:D,2,0) -> WOMPI COSTA | V62: =VLOOKUP(T62,'BASE TARIFA 2025'!C:F,4,0) -> 15709.5
A63: 77154 | B63: BARRIO OTRO TUCHIN | C63: 1003071911 | D63: 3005145872 | E63: 3005145872 | F63: 3005145872 | G63: CL 12 16 D 153,OTRO | H63: 9.185053 | I63: -75.558262 | J63: CÓRDOBA | K63: TUCHÍN | L63: TUCHÍN | M63: 23815 | N63: 2025-11-13 | S63: =VLOOKUP(A63,Hoja1!A:B,2,0) -> 8 | T63: =VLOOKUP(M63,[1]TIPOLOGIAS!$A:$F,4,0) -> MONTERIA | U63: =VLOOKUP(T63,'BASE TARIFA 2025'!C:D,2,0) -> WOMPI COSTA | V63: =VLOOKUP(T63,'BASE TARIFA 2025'!C:F,4,0) -> 15709.5
A64: 44595 | B64: BARRIO SANTA HELENA BOJACA | C64: 20404575 | E64: 3133684189 | F64: 3133684189 | G64: TV 8 12 35,SANTA HELENA | H64: 4.7366952 | I64: -74.3446350 | J64: CUNDINAMARCA | K64: BOJACÁ | L64: BOJACÁ | M64: 25099 | N64: 2025-11-10 | S64: =VLOOKUP(A64,Hoja1!A:B,2,0) -> 8 | T64: =VLOOKUP(M64,[1]TIPOLOGIAS!$A:$F,4,0) -> BOGOTA | U64: =VLOOKUP(T64,'BASE TARIFA 2025'!C:D,2,0) -> WOMPI CENTRO | V64: =VLOOKUP(T64,'BASE TARIFA 2025'!C:F,4,0) -> 15709.5
A65: 79354 | B65: BARRIO SANTA ELENA BOJACA BOJACA | C65: 1070967938 | D65: 3168652745 | E65: 3168652745 | G65: CR 10 D 9 79 ,SANTA ELENA BOJACA | H65: 4.7372958 | I65: -74.3442711 | J65: CUNDINAMARCA | K65: BOJACÁ | L65: BOJACÁ | M65: 25099 | N65: 2025-11-14 | S65: =VLOOKUP(A65,Hoja1!A:B,2,0) -> 8 | T65: =VLOOKUP(M65,[1]TIPOLOGIAS!$A:$F,4,0) -> BOGOTA | U65: =VLOOKUP(T65,'BASE TARIFA 2025'!C:D,2,0) -> WOMPI CENTRO | V65: =VLOOKUP(T65,'BASE TARIFA 2025'!C:F,4,0) -> 15709.5
A66: 60469 | B66: BARRIO CENTRO BOJACA 2 | C66: 1069259583 | D66: 0 | E66: 3228490249 | F66: 3228490249 | G66: CL 7 5 58 | H66: 4.7328166 | I66: -74.3412807 | J66: CUNDINAMARCA | K66: BOJACÁ | L66: BOJACÁ | M66: 25099 | N66: 2025-11-13 | S66: =VLOOKUP(A66,Hoja1!A:B,2,0) -> 16 | T66: =VLOOKUP(M66,[1]TIPOLOGIAS!$A:$F,4,0) -> BOGOTA | U66: =VLOOKUP(T66,'BASE TARIFA 2025'!C:D,2,0) -> WOMPI CENTRO | V66: =VLOOKUP(T66,'BASE TARIFA 2025'!C:F,4,0) -> 15709.5
A67: 65875 | B67: BARRIO CENTRO BOJACA 3 | C67: 20404918 | D67: 0 | E67: 3143402603 | F67: 3143402603 | G67: CL 17 14 58,CENTRO | H67: 4.740918 | I67: -74.344396 | J67: CUNDINAMARCA | K67: BOJACÁ | L67: BOJACÁ | M67: 25099 | N67: 2025-11-10 | S67: =VLOOKUP(A67,Hoja1!A:B,2,0) -> 8 | T67: =VLOOKUP(M67,[1]TIPOLOGIAS!$A:$F,4,0) -> BOGOTA | U67: =VLOOKUP(T67,'BASE TARIFA 2025'!C:D,2,0) -> WOMPI CENTRO | V67: =VLOOKUP(T67,'BASE TARIFA 2025'!C:F,4,0) -> 15709.5
A68: 60326 | B68: BARRIO LA CARO CHIA 1 | C68: 901049038 | D68: 8840153 | E68: 3102002969 | F68: 3102002969 | G68: AUT NORTE KM 23 VDA YERBABUENA ESTACIÓN DE SERVICIO ESSO | H68: 4.869898 | I68: -74.022365 | J68: CUNDINAMARCA | K68: CHÍA | L68: CHÍA | M68: 25175 | N68: 2025-11-11 | S68: =VLOOKUP(A68,Hoja1!A:B,2,0) -> 8 | T68: =VLOOKUP(M68,[1]TIPOLOGIAS!$A:$F,4,0) -> BOGOTA | U68: =VLOOKUP(T68,'BASE TARIFA 2025'!C:D,2,0) -> WOMPI CENTRO | V68: =VLOOKUP(T68,'BASE TARIFA 2025'!C:F,4,0) -> 15709.5
A69: 79551 | B69: BARRIO LA PRIMAVERA CHIA | C69: 79850029 | D69: 3114483703 | E69: 3114483703 | F69: 3114483703 | G69: CR 13 17 103,LA PRIMAVERA | H69: 4.8675661 | I69: -74.0595819 | J69: CUNDINAMARCA | K69: CHÍA | L69: CHÍA | M69: 25175 | N69: 2025-11-04 | S69: =VLOOKUP(A69,Hoja1!A:B,2,0) -> 8 | T69: =VLOOKUP(M69,[1]TIPOLOGIAS!$A:$F,4,0) -> BOGOTA | U69: =VLOOKUP(T69,'BASE TARIFA 2025'!C:D,2,0) -> WOMPI CENTRO | V69: =VLOOKUP(T69,'BASE TARIFA 2025'!C:F,4,0) -> 15709.5
A70: 81067 | B70: BARRIO NUEVO MILENIO CHIA 1 | C70: 11521144 | D70: 3227018594 | E70: 3227018594 | G70: CR 3 31 36 CA 42,NUEVO MILENIO | H70: 4.8782894 | I70: -74.0452671 | J70: CUNDINAMARCA | K70: CHÍA | L70: CHÍA | M70: 25175 | N70: 2025-11-04 | S70: =VLOOKUP(A70,Hoja1!A:B,2,0) -> 8 | T70: =VLOOKUP(M70,[1]TIPOLOGIAS!$A:$F,4,0) -> BOGOTA | U70: =VLOOKUP(T70,'BASE TARIFA 2025'!C:D,2,0) -> WOMPI CENTRO | V70: =VLOOKUP(T70,'BASE TARIFA 2025'!C:F,4,0) -> 15709.5
A71: 81127 | B71: BARRIO CHILAGOS CHIA 1 | C71: 1000459942 | D71: 3203536252 | E71: 3203536252 | F71: 3203536252 | G71: AV CHILACOS CR 9 21 - 56,CHILACOS | H71: 4.8683050 | I71: -74.0539150 | J71: CUNDINAMARCA | K71: CHÍA | L71: CHÍA | M71: 25175 | N71: 2025-11-04 | S71: =VLOOKUP(A71,Hoja1!A:B,2,0) -> 8 | T71: =VLOOKUP(M71,[1]TIPOLOGIAS!$A:$F,4,0) -> BOGOTA | U71: =VLOOKUP(T71,'BASE TARIFA 2025'!C:D,2,0) -> WOMPI CENTRO | V71: =VLOOKUP(T71,'BASE TARIFA 2025'!C:F,4,0) -> 15709.5
A72: 70277 | B72: BARRIO MARGARITAS CHIA | C72: 28904277 | D72: 3107760065 | E72: 3107760065 | F72: 3107760065 | G72: KM 24 VIA CHIA -CAJICA.MARGARITAS EDS TEXACO | H72: 4.8831373 | I72: -74.0376439 | J72: CUNDINAMARCA | K72: CHÍA | L72: CHÍA | M72: 25175 | N72: 2025-11-13 | S72: =VLOOKUP(A72,Hoja1!A:B,2,0) -> 8 | T72: =VLOOKUP(M72,[1]TIPOLOGIAS!$A:$F,4,0) -> BOGOTA | U72: =VLOOKUP(T72,'BASE TARIFA 2025'!C:D,2,0) -> WOMPI CENTRO | V72: =VLOOKUP(T72,'BASE TARIFA 2025'!C:F,4,0) -> 15709.5
A73: 13339 | B73: BARRIO CAMPO HERMOSO | C73: 17658240 | D73: 5139474 | E73: 3146302114 | F73: 3146302114 | G73: CL 7 CR 1 ESQ | H73: 1.9226472 | I73: -74.6913869 | J73: CAQUETÁ | K73: SAN VICENTE DEL CAGUÁN | L73: SAN VICENTE DEL CAGUÁN | M73: 18753 | N73: 2025-11-24 | S73: =VLOOKUP(A73,Hoja1!A:B,2,0) -> 8 | T73: =VLOOKUP(M73,[1]TIPOLOGIAS!$A:$F,4,0) -> NEIVA | U73: =VLOOKUP(T73,'BASE TARIFA 2025'!C:D,2,0) -> WOMPI ORIENTE | V73: =VLOOKUP(T73,'BASE TARIFA 2025'!C:F,4,0) -> 28277.1
A74: 24121 | B74: CENTRO SAN VICENTE DEL CAGUAN I - CAQUETA | C74: 17328491 | D74: 3203069 | E74: 3203069606 | F74: 3203069606 | G74: VRD CRISTALINA DEL LOZADA | H74: 2.1132197 | I74: -74.7692183 | J74: CAQUETÁ | K74: SAN VICENTE DEL CAGUÁN | L74: SAN VICENTE DEL CAGUÁN | M74: 18753 | N74: 2025-11-06 | S74: =VLOOKUP(A74,Hoja1!A:B,2,0) -> 8 | T74: =VLOOKUP(M74,[1]TIPOLOGIAS!$A:$F,4,0) -> NEIVA | U74: =VLOOKUP(T74,'BASE TARIFA 2025'!C:D,2,0) -> WOMPI ORIENTE | V74: =VLOOKUP(T74,'BASE TARIFA 2025'!C:F,4,0) -> 28277.1
A75: 42669 | B75: BARRIO CASERIO LA NOVIA SAN VICENTE DEL CAGUAN | C75: 40081296 | E75: 3133287624 | F75: 3133287624 | G75: CASERIO LA NOVIA,CASERIO LA NOVIA | H75: 2.1037246 | I75: -74.7691966 | J75: CAQUETÁ | K75: SAN VICENTE DEL CAGUÁN | L75: SAN VICENTE DEL CAGUÁN | M75: 18753 | N75: 2025-11-25 | S75: =VLOOKUP(A75,Hoja1!A:B,2,0) -> 8 | T75: =VLOOKUP(M75,[1]TIPOLOGIAS!$A:$F,4,0) -> NEIVA | U75: =VLOOKUP(T75,'BASE TARIFA 2025'!C:D,2,0) -> WOMPI ORIENTE | V75: =VLOOKUP(T75,'BASE TARIFA 2025'!C:F,4,0) -> 28277.1
A76: 78967 | B76: BARRIO EL RIUNFO SAN VICENTE DEL CAGUAN | C76: 40731941 | D76: 3213717225 | E76: 3213717225 | F76: 3219968637 | G76: MZ N LT2,EL TRIUNFO | H76: 2.1209107 | I76: -74.7563908 | J76: CAQUETÁ | K76: SAN VICENTE DEL CAGUÁN | L76: SAN VICENTE DEL CAGUÁN | M76: 18753 | N76: 2025-11-06 | S76: =VLOOKUP(A76,Hoja1!A:B,2,0) -> 8 | T76: =VLOOKUP(M76,[1]TIPOLOGIAS!$A:$F,4,0) -> NEIVA | U76: =VLOOKUP(T76,'BASE TARIFA 2025'!C:D,2,0) -> WOMPI ORIENTE | V76: =VLOOKUP(T76,'BASE TARIFA 2025'!C:F,4,0) -> 28277.1
A77: 78969 | B77: BARRIO GALERIA MUNICIPAL SAN VICENTE DEL CAGUAN | C77: 43102314 | D77: 3236853994 | E77: 3226853994 | F77: 3226853994 | G77: CR 7 5 74 LOCAL 27 INTERNO ,GALERIA MUNICIPAL | H77: 2.1128627 | I77: -74.7719252 | J77: CAQUETÁ | K77: SAN VICENTE DEL CAGUÁN | L77: SAN VICENTE DEL CAGUÁN | M77: 18753 | N77: 2025-11-13 | S77: =VLOOKUP(A77,Hoja1!A:B,2,0) -> 8 | T77: =VLOOKUP(M77,[1]TIPOLOGIAS!$A:$F,4,0) -> NEIVA | U77: =VLOOKUP(T77,'BASE TARIFA 2025'!C:D,2,0) -> WOMPI ORIENTE | V77: =VLOOKUP(T77,'BASE TARIFA 2025'!C:F,4,0) -> 28277.1
A78: 79131 | B78: BARRIO LOS POZOS SAN VICENTE DEL CAGUAN | C78: 1006504932 | D78: 3209387427 | E78: 3209387427 | G78: INSPECCION LOS POZOS | H78: 2.1231124 | I78: -74.5564811 | J78: CAQUETÁ | K78: SAN VICENTE DEL CAGUÁN | L78: SAN VICENTE DEL CAGUÁN | M78: 18753 | N78: 2025-11-06 | S78: =VLOOKUP(A78,Hoja1!A:B,2,0) -> 8 | T78: =VLOOKUP(M78,[1]TIPOLOGIAS!$A:$F,4,0) -> NEIVA | U78: =VLOOKUP(T78,'BASE TARIFA 2025'!C:D,2,0) -> WOMPI ORIENTE | V78: =VLOOKUP(T78,'BASE TARIFA 2025'!C:F,4,0) -> 28277.1
A79: 79133 | B79: BARRIO HERNANDEZ SAN VICENTE DEL CAGUAN 2 | C79: 1033488366 | D79: 3005153568 | E79: 3005153568 | G79: CL 1 6 24,HERNANDEZ | H79: 2.1107534 | I79: -74.7690186 | J79: CAQUETÁ | K79: SAN VICENTE DEL CAGUÁN | L79: SAN VICENTE DEL CAGUÁN | M79: 18753 | N79: 2025-11-13 | S79: =VLOOKUP(A79,Hoja1!A:B,2,0) -> 8 | T79: =VLOOKUP(M79,[1]TIPOLOGIAS!$A:$F,4,0) -> NEIVA | U79: =VLOOKUP(T79,'BASE TARIFA 2025'!C:D,2,0) -> WOMPI ORIENTE | V79: =VLOOKUP(T79,'BASE TARIFA 2025'!C:F,4,0) -> 28277.1
A80: 77630 | B80: BARRIO JARDIN SAN VICENTE DEL CAGUAN | C80: 1121850144 | D80: 3229147898 | E80: 3202020891 | F80: 3202020891 | G80: CR 9 13 SUR,JARDIN | H80: 2.107108 | I80: -74.769386 | J80: CAQUETÁ | K80: SAN VICENTE DEL CAGUÁN | L80: SAN VICENTE DEL CAGUÁN | M80: 18753 | N80: 2025-11-06 | S80: =VLOOKUP(A80,Hoja1!A:B,2,0) -> 8 | T80: =VLOOKUP(M80,[1]TIPOLOGIAS!$A:$F,4,0) -> NEIVA | U80: =VLOOKUP(T80,'BASE TARIFA 2025'!C:D,2,0) -> WOMPI ORIENTE | V80: =VLOOKUP(T80,'BASE TARIFA 2025'!C:F,4,0) -> 28277.1
A81: 79520 | B81: BARRIO CONSOLATA SAN VICENTE DEL CAGUAN | C81: 1072466719 | D81: 3015583086 | E81: 3015583086 | F81: 3015583086 | G81: CL 6 2 BIS 03 - LA CONSOLATA | H81: 2.1165792 | I81: -74.7694033 | J81: CAQUETÁ | K81: SAN VICENTE DEL CAGUÁN | L81: SAN VICENTE DEL CAGUÁN | M81: 18753 | N81: 2025-11-12 | S81: =VLOOKUP(A81,Hoja1!A:B,2,0) -> 8 | T81: =VLOOKUP(M81,[1]TIPOLOGIAS!$A:$F,4,0) -> NEIVA | U81: =VLOOKUP(T81,'BASE TARIFA 2025'!C:D,2,0) -> WOMPI ORIENTE | V81: =VLOOKUP(T81,'BASE TARIFA 2025'!C:F,4,0) -> 28277.1
A82: 80402 | B82: BARRIO CENTRO SAN VICENTE DEL CAGUAN 6 | C82: 1117820127 | D82: 3103212591 | E82: 3103212591 | F82: 3103212591 | G82: CL 5 N 4 ESQ,CENTRO | H82: 2.1142235 | I82: -74.7691074 | J82: CAQUETÁ | K82: SAN VICENTE DEL CAGUÁN | L82: SAN VICENTE DEL CAGUÁN | M82: 18753 | N82: 2025-11-12 | S82: =VLOOKUP(A82,Hoja1!A:B,2,0) -> 8 | T82: =VLOOKUP(M82,[1]TIPOLOGIAS!$A:$F,4,0) -> NEIVA | U82: =VLOOKUP(T82,'BASE TARIFA 2025'!C:D,2,0) -> WOMPI ORIENTE | V82: =VLOOKUP(T82,'BASE TARIFA 2025'!C:F,4,0) -> 28277.1
A83: 80403 | B83: BARRIO CL PRINCIPAL SAN VICENTE DEL CAGUAN | C83: 30520050 | D83: 3202977658 | E83: 3202977658 | F83: 3202977658 | G83: INSP CAMPO HERMOSO,CL PRINCIPAL | H83: 1.9201377 | I83: -74.6890496 | J83: CAQUETÁ | K83: SAN VICENTE DEL CAGUÁN | L83: SAN VICENTE DEL CAGUÁN | M83: 18753 | N83: 2025-11-13 | S83: =VLOOKUP(A83,Hoja1!A:B,2,0) -> 8 | T83: =VLOOKUP(M83,[1]TIPOLOGIAS!$A:$F,4,0) -> NEIVA | U83: =VLOOKUP(T83,'BASE TARIFA 2025'!C:D,2,0) -> WOMPI ORIENTE | V83: =VLOOKUP(T83,'BASE TARIFA 2025'!C:F,4,0) -> 28277.1
A84: 80404 | B84: BARRIO PUERTO REDONDO SAN VICENTE DEL CAGUAN 2 | C84: 94193733 | D84: 3114405136 | E84: 3114405136 | G84: CR 7 2 31 33,PUERTO REDONDO | H84: 2.1105243 | I84: -74.7699071 | J84: CAQUETÁ | K84: SAN VICENTE DEL CAGUÁN | L84: SAN VICENTE DEL CAGUÁN | M84: 18753 | N84: 2025-11-06 | S84: =VLOOKUP(A84,Hoja1!A:B,2,0) -> 8 | T84: =VLOOKUP(M84,[1]TIPOLOGIAS!$A:$F,4,0) -> NEIVA | U84: =VLOOKUP(T84,'BASE TARIFA 2025'!C:D,2,0) -> WOMPI ORIENTE | V84: =VLOOKUP(T84,'BASE TARIFA 2025'!C:F,4,0) -> 28277.1
A85: 67108 | B85: BARRIO GUAYABAL SAN VICENTE DEL CAGUAN | C85: 1075275760 | D85: 3202403945 | E85: 3202403945 | F85: 3202403945 | G85: INSP GUAYABAL,GUAYABAL | H85: 2.699445 | I85: -74.882292 | J85: CAQUETÁ | K85: SAN VICENTE DEL CAGUÁN | L85: SAN VICENTE DEL CAGUÁN | M85: 18753 | N85: 2025-11-07 | S85: =VLOOKUP(A85,Hoja1!A:B,2,0) -> 8 | T85: =VLOOKUP(M85,[1]TIPOLOGIAS!$A:$F,4,0) -> NEIVA | U85: =VLOOKUP(T85,'BASE TARIFA 2025'!C:D,2,0) -> WOMPI ORIENTE | V85: =VLOOKUP(T85,'BASE TARIFA 2025'!C:F,4,0) -> 28277.1
A86: 75439 | B86: BARRIO SANTA ISABEL SAN VICENTE DE CAGUAN | C86: 1075271177 | D86: 0 | E86: 3106395383 | F86: 3106395383 | G86: CR 6 6 A 04,SANTA ISABEL | H86: 2.114671 | I86: -74.772639 | J86: CAQUETÁ | K86: SAN VICENTE DEL CAGUÁN | L86: SAN VICENTE DEL CAGUÁN | M86: 18753 | N86: 2025-11-05 | S86: =VLOOKUP(A86,Hoja1!A:B,2,0) -> 8 | T86: =VLOOKUP(M86,[1]TIPOLOGIAS!$A:$F,4,0) -> NEIVA | U86: =VLOOKUP(T86,'BASE TARIFA 2025'!C:D,2,0) -> WOMPI ORIENTE | V86: =VLOOKUP(T86,'BASE TARIFA 2025'!C:F,4,0) -> 28277.1
A87: 72259 | B87: CAQUETA SAN VICEN DEL CAGUAN | C87: 30508451 | D87: 3125121138 | E87: 3125121138 | F87: 3125121138 | G87: MZ R LT24,URBANIZACIÓN PRIMAVERA | H87: 2.1287219 | I87: -74.7593143 | J87: CAQUETÁ | K87: SAN VICENTE DEL CAGUÁN | L87: SAN VICENTE DEL CAGUÁN | M87: 18753 | N87: 2025-11-07 | S87: =VLOOKUP(A87,Hoja1!A:B,2,0) -> 8 | T87: =VLOOKUP(M87,[1]TIPOLOGIAS!$A:$F,4,0) -> NEIVA | U87: =VLOOKUP(T87,'BASE TARIFA 2025'!C:D,2,0) -> WOMPI ORIENTE | V87: =VLOOKUP(T87,'BASE TARIFA 2025'!C:F,4,0) -> 28277.1
A88: 77569 | B88: BARRIO VRD SAN VICENTE DEL CAGUAN | C88: 1117824669 | D88: 0 | E88: 3132955039 | F88: 3132955039 | G88: VRD SAN JUAN DEL LOZADA ,VRD | H88: 2.242813 | I88: -74.451859 | J88: CAQUETÁ | K88: SAN VICENTE DEL CAGUÁN | L88: SAN VICENTE DEL CAGUÁN | M88: 18753 | N88: 2025-11-28 | S88: =VLOOKUP(A88,Hoja1!A:B,2,0) -> 8 | T88: =VLOOKUP(M88,[1]TIPOLOGIAS!$A:$F,4,0) -> NEIVA | U88: =VLOOKUP(T88,'BASE TARIFA 2025'!C:D,2,0) -> WOMPI ORIENTE | V88: =VLOOKUP(T88,'BASE TARIFA 2025'!C:F,4,0) -> 28277.1
A89: 47203 | B89: BARRIO CASERIO VILLA LOBOS SAN VICENTE DEL CAGUAN | C89: 17691232 | D89: 0 | E89: 3232268146 | F89: 3214670774 | G89: CAS VILLA LOBOS | H89: 1.633825 | I89: -74.561671 | J89: CAQUETÁ | K89: SAN VICENTE DEL CAGUÁN | L89: SAN VICENTE DEL CAGUÁN | M89: 18753 | N89: 2025-11-25 | S89: =VLOOKUP(A89,Hoja1!A:B,2,0) -> 8 | T89: =VLOOKUP(M89,[1]TIPOLOGIAS!$A:$F,4,0) -> NEIVA | U89: =VLOOKUP(T89,'BASE TARIFA 2025'!C:D,2,0) -> WOMPI ORIENTE | V89: =VLOOKUP(T89,'BASE TARIFA 2025'!C:F,4,0) -> 28277.1
A90: 51889 | B90: BARRIO INSP CAMPO HERMOSO SAN VICENTE DEL CAGUAN | C90: 1117836836 | D90: 3143705547 | E90: 3104158944 | F90: 3143705547 | G90: INSP CAMPO HERMOSO | H90: 1.55150 | I90: -74.41270 | J90: CAQUETÁ | K90: SAN VICENTE DEL CAGUÁN | L90: SAN VICENTE DEL CAGUÁN | M90: 18753 | N90: 2025-11-24 | S90: =VLOOKUP(A90,Hoja1!A:B,2,0) -> 8 | T90: =VLOOKUP(M90,[1]TIPOLOGIAS!$A:$F,4,0) -> NEIVA | U90: =VLOOKUP(T90,'BASE TARIFA 2025'!C:D,2,0) -> WOMPI ORIENTE | V90: =VLOOKUP(T90,'BASE TARIFA 2025'!C:F,4,0) -> 28277.1
A91: 66513 | B91: BARRIO LOS MUISCAS TUNJA 5 | C91: 1049613566 | D91: 3134637535 | E91: 3134637535 | F91: 3134637535 | G91: TV 1 67 03 MZ 19 ,LOS MUISCAS | H91: 5.5702437 | I91: -73.3395212 | J91: BOYACÁ | K91: TUNJA | L91: TUNJA | M91: 15001 | N91: 2025-11-20 | S91: =VLOOKUP(A91,Hoja1!A:B,2,0) -> 16 | T91: =VLOOKUP(M91,[1]TIPOLOGIAS!$A:$F,4,0) -> TUNJA | U91: =VLOOKUP(T91,'BASE TARIFA 2025'!C:D,2,0) -> WOMPI SANTANDERES | V91: =VLOOKUP(T91,'BASE TARIFA 2025'!C:F,4,0) -> 28277.1
A92: 59682 | B92: BARRIO PRADOS DE ALCALA TUNJA | C92: 50897407 | D92: 3164071085 | E92: 3208356593 | F92: 3208356593 | G92: CR 1 A 18 20 MZ 2 CASA 2,PISO 1 | H92: 5.529 | I92: -73.350 | J92: BOYACÁ | K92: TUNJA | L92: TUNJA | M92: 15001 | N92: 2025-11-24 | S92: =VLOOKUP(A92,Hoja1!A:B,2,0) -> 8 | T92: =VLOOKUP(M92,[1]TIPOLOGIAS!$A:$F,4,0) -> TUNJA | U92: =VLOOKUP(T92,'BASE TARIFA 2025'!C:D,2,0) -> WOMPI SANTANDERES | V92: =VLOOKUP(T92,'BASE TARIFA 2025'!C:F,4,0) -> 28277.1
A93: 57213 | B93: BARRIO CENTRO TUNJA 18 | C93: 40043268 | D93: 3015123142 | E93: 3015123142 | F93: 3015123142 | G93: CR 10 17 97 | H93: 5.5310387 | I93: -73.3625633 | J93: BOYACÁ | K93: TUNJA | L93: TUNJA | M93: 15001 | N93: 2025-11-24 | S93: =VLOOKUP(A93,Hoja1!A:B,2,0) -> 8 | T93: =VLOOKUP(M93,[1]TIPOLOGIAS!$A:$F,4,0) -> TUNJA | U93: =VLOOKUP(T93,'BASE TARIFA 2025'!C:D,2,0) -> WOMPI SANTANDERES | V93: =VLOOKUP(T93,'BASE TARIFA 2025'!C:F,4,0) -> 28277.1
A94: 53404 | B94: BARRIO BOCHICA TUNJA 1 | C94: 50897407 | D94: 3164071085 | E94: 3164071085 | F94: 3164071085 | G94: CR 4 8 05 | H94: 5.520 | I94: -73.359 | J94: BOYACÁ | K94: TUNJA | L94: TUNJA | M94: 15001 | N94: 2025-11-24 | S94: =VLOOKUP(A94,Hoja1!A:B,2,0) -> 8 | T94: =VLOOKUP(M94,[1]TIPOLOGIAS!$A:$F,4,0) -> TUNJA | U94: =VLOOKUP(T94,'BASE TARIFA 2025'!C:D,2,0) -> WOMPI SANTANDERES | V94: =VLOOKUP(T94,'BASE TARIFA 2025'!C:F,4,0) -> 28277.1
A95: 41589 | B95: BARRIO SANTA LUCIA TUNJA 3 | C95: 74374334 | D95: 7456261 | E95: 3103292709 | F95: 3103292709 | G95: cr 14 N 26-124 | H95: 5.540 | I95: -73.362 | J95: BOYACÁ | K95: TUNJA | L95: TUNJA | M95: 15001 | N95: 2025-11-24 | S95: =VLOOKUP(A95,Hoja1!A:B,2,0) -> 16 | T95: =VLOOKUP(M95,[1]TIPOLOGIAS!$A:$F,4,0) -> TUNJA | U95: =VLOOKUP(T95,'BASE TARIFA 2025'!C:D,2,0) -> WOMPI SANTANDERES | V95: =VLOOKUP(T95,'BASE TARIFA 2025'!C:F,4,0) -> 28277.1
A96: 36449 | B96: BARRIO EL DORADO TUNJA 1 | C96: 33379495 | D96: 7474112 | E96: 3005188531 | F96: 3005188531 | G96: CR 2 ESTE 22 140 | H96: 5.53512828 | I96: -73.35123733 | J96: BOYACÁ | K96: TUNJA | L96: TUNJA | M96: 15001 | N96: 2025-11-20 | S96: =VLOOKUP(A96,Hoja1!A:B,2,0) -> 8 | T96: =VLOOKUP(M96,[1]TIPOLOGIAS!$A:$F,4,0) -> TUNJA | U96: =VLOOKUP(T96,'BASE TARIFA 2025'!C:D,2,0) -> WOMPI SANTANDERES | V96: =VLOOKUP(T96,'BASE TARIFA 2025'!C:F,4,0) -> 28277.1
... A98: 32317 | B98: BARRIO CENTRO BOAVITA | C98: 23351488 | D98: 3734111 | E98: 3222739405 | F98: 3222739405 | G98: CR 7 5 31 | H98: 6.3264781 | I98: -72.5761156 | J98: BOYACÁ | K98: BOAVITA | L98: BOAVITA | M98: 15097 | N98: 2025-11-07 | S98: =VLOOKUP(A98,Hoja1!A:B,2,0) -> 8 | T98: =VLOOKUP(M98,[1]TIPOLOGIAS!$A:$F,4,0) -> TUNJA | U98: =VLOOKUP(T98,'BASE TARIFA 2025'!C:D,2,0) -> WOMPI SANTANDERES | V98: =VLOOKUP(T98,'BASE TARIFA 2025'!C:F,4,0) -> 28277.1
A99: 37485 | B99: BARRIO CENTRO BOAVITA 1 | C99: 51852790 | E99: 3125364630 | F99: 3125364630 | G99: CR 7 5 -78 | H99: 6.3307733 | I99: -72.5861296 | J99: BOYACÁ | K99: BOAVITA | L99: BOAVITA | M99: 15097 | N99: 2025-11-07 | S99: =VLOOKUP(A99,Hoja1!A:B,2,0) -> 8 | T99: =VLOOKUP(M99,[1]TIPOLOGIAS!$A:$F,4,0) -> TUNJA | U99: =VLOOKUP(T99,'BASE TARIFA 2025'!C:D,2,0) -> WOMPI SANTANDERES | V99: =VLOOKUP(T99,'BASE TARIFA 2025'!C:F,4,0) -> 28277.1
A100: 81050 | B100: BARRIO CENTRO BOAVITA 6 | C100: 1052498236 | D100: 3213348499 | E100: 3112111435 | F100: 3112111435 | G100: CL 4 NO.7-52,CENTRO | H100: 6.3292475 | I100: -72.5850955 | J100: BOYACÁ | K100: BOAVITA | L100: BOAVITA | M100: 15097 | N100: 2025-11-07 | S100: =VLOOKUP(A100,Hoja1!A:B,2,0) -> 8 | T100: =VLOOKUP(M100,[1]TIPOLOGIAS!$A:$F,4,0) -> TUNJA | U100: =VLOOKUP(T100,'BASE TARIFA 2025'!C:D,2,0) -> WOMPI SANTANDERES | V100: =VLOOKUP(T100,'BASE TARIFA 2025'!C:F,4,0) -> 28277.1
A101: 57781 | B101: BARRIO CENTRO BOAVITA 3 | C101: 1100502384 | D101: 3224813573 | E101: 3224813573 | F101: 3224813573 | G101: CL 5 7-16 BARRIO CENTRO | H101: 6.3301919 | I101: -72.5854562 | J101: BOYACÁ | K101: BOAVITA | L101: BOAVITA | M101: 15097 | N101: 2025-11-07 | S101: =VLOOKUP(A101,Hoja1!A:B,2,0) -> 8 | T101: =VLOOKUP(M101,[1]TIPOLOGIAS!$A:$F,4,0) -> TUNJA | U101: =VLOOKUP(T101,'BASE TARIFA 2025'!C:D,2,0) -> WOMPI SANTANDERES | V101: =VLOOKUP(T101,'BASE TARIFA 2025'!C:F,4,0) -> 28277.1
A102: 64746 | B102: BARRIO CENTRO BOAVITA 5 | C102: 1049372922 | D102: 3205974172 | E102: 3205974172 | F102: 3203029086 | G102: CR 7 NO.3-19,CENTRO | H102: 6.3291962 | I102: -72.5843093 | J102: BOYACÁ | K102: BOAVITA | L102: BOAVITA | M102: 15097 | N102: 2025-11-07 | S102: =VLOOKUP(A102,Hoja1!A:B,2,0) -> 8 | T102: =VLOOKUP(M102,[1]TIPOLOGIAS!$A:$F,4,0) -> TUNJA | U102: =VLOOKUP(T102,'BASE TARIFA 2025'!C:D,2,0) -> WOMPI SANTANDERES | V102: =VLOOKUP(T102,'BASE TARIFA 2025'!C:F,4,0) -> 28277.1
A103: 71664 | B103: BARRIO GAMBOTICO EL CARMEN | C103: 45646291 | D103: 3002031425 | E103: 3002031425 | F103: 3002031425 | G103: CR 63 22 15,GAMBOTICO | H103: 9.71024411 | I103: -75.11204086 | J103: BOLÍVAR | K103: EL CARMEN DE BOLÍVAR | L103: EL CARMEN DE BOLÍVAR | M103: 13244 | N103: 2025-11-05 | S103: =VLOOKUP(A103,Hoja1!A:B,2,0) -> 8 | T103: =VLOOKUP(M103,[1]TIPOLOGIAS!$A:$F,4,0) -> CARTAGENA | U103: =VLOOKUP(T103,'BASE TARIFA 2025'!C:D,2,0) -> WOMPI COSTA | V103: =VLOOKUP(T103,'BASE TARIFA 2025'!C:F,4,0) -> 28277.1
A104: 61349 | B104: BARRIO TALAIGUA NUEVO TALAIGUA NUEVO | C104: 1052700486 | D104: 3107455213 | E104: 3003566584 | F104: 3003566584 | G104: CL 14 CRA 6 5 58 | H104: 9.303362500000 | I104: -74.568268333 | J104: BOLÍVAR | K104: TALAIGUA NUEVO | L104: TALAIGUA NUEVO | M104: 13780 | N104: 2025-11-06 | S104: =VLOOKUP(A104,Hoja1!A:B,2,0) -> 8 | T104: =VLOOKUP(M104,[1]TIPOLOGIAS!$A:$F,4,0) -> CARTAGENA | U104: =VLOOKUP(T104,'BASE TARIFA 2025'!C:D,2,0) -> WOMPI COSTA | V104: =VLOOKUP(T104,'BASE TARIFA 2025'!C:F,4,0) -> 28277.1
A105: 62675 | B105: BARRIO CORREGIMIENTO TALAIGUA NU | C105: 22668792 | D105: 3215222471 | E105: 3205557908 | F105: 3215222471 | G105: CL 4 9 - 20 CORREGIMIENTO TALAIGUA VIEJO , | H105: 9.3120083 | I105: -74.5856652 | J105: BOLÍVAR | K105: TALAIGUA NUEVO | L105: TALAIGUA NUEVO | M105: 13780 | N105: 2025-11-06 | S105: =VLOOKUP(A105,Hoja1!A:B,2,0) -> 8 | T105: =VLOOKUP(M105,[1]TIPOLOGIAS!$A:$F,4,0) -> CARTAGENA | U105: =VLOOKUP(T105,'BASE TARIFA 2025'!C:D,2,0) -> WOMPI COSTA | V105: =VLOOKUP(T105,'BASE TARIFA 2025'!C:F,4,0) -> 28277.1
A106: 79421 | B106: BARRIO 10 DE ABRIL TALAIGUA NUEVO 1 | C106: 8738671 | D106: 3002842027 | E106: 3002842027 | F106: 3002842027 | G106: CR 8B 13A 29 BODEGA,10 DE ABRIL | H106: 9.3029488 | I106: -74.5680969 | J106: BOLÍVAR | K106: TALAIGUA NUEVO | L106: TALAIGUA NUEVO | M106: 13780 | N106: 2025-11-06 | S106: =VLOOKUP(A106,Hoja1!A:B,2,0) -> 8 | T106: =VLOOKUP(M106,[1]TIPOLOGIAS!$A:$F,4,0) -> CARTAGENA | U106: =VLOOKUP(T106,'BASE TARIFA 2025'!C:D,2,0) -> WOMPI COSTA | V106: =VLOOKUP(T106,'BASE TARIFA 2025'!C:F,4,0) -> 28277.1
...
