Workbook
Name A: #REF!
Name ACTIVIDAD: [1]Hoja2!$P$2:$P$30
Name Actividad: [2]Formulas!$H$2:$H$5000
Name arearesponsable: '[3]Listas desplegables'!$BB$2:$BB$100
Name Clientes: [4]Clientes!$A$2:$A$100
Name Clientes: [2]Clientes!$A$2:$A$100
Name COORDINADOR: [1]Hoja2!$D$2:$D$30
Name Coordinadores: [5]Coordinadores!$A$2:$A$1000
Name Coordinadores: [2]Coordinadores!$A$2:$A$1000
Name DOCUMENTADOR: [1]Hoja2!$A$2:$A$30
Name ES: [1]Hoja2!$K$2:$K$30
Name ESS: [1]Hoja2!$K$2:$K$30
Name Estado: [4]Formulas!$K$2:$K$5000
Name Estado: [2]Formulas!$K$2:$K$5000
Name ESTADOACTIVIDAD: [1]Hoja2!$M$2:$M$30
Name ESTADOS: '[6]Listas desplegables'!$B$1:$D$1
Name ESTADOSCIERRES: '[7]lista desplegable'!$CX$1:$DA$1
Name Facturacion: '[8]Listas desplegables'!$AO$1:$AR$1
Name FACTURACIÓN: '[6]Listas desplegables'!$Y$1:$AB$1
Name falla: #REF!
Name Fallas: '[9]Listas desplegables'!$F$2:$L$2
Name Grupo_Falla: '[10]Listas Desplegables'!$CH$2:$CH$5
Name inconservmanager: '[11]Listas desplegables'!$BC$2:$BC$100
Name INCUMPLIMIENTO: '[3]Listas desplegables'!$AK$1:$AN$1
Name LISTA: [12]Dptos!$A$1139:$A$1171
Name LISTA2: #REF!
Name LOLO: [13]Coordinadores!$A$2:$A$1000
Name solicitudes: '[8]Listas desplegables'!$U$1:$AF$1
Name solicitudes: '[14]Listas desplegables'!$AF$1:$AQ$1
Name Tecnicos: [4]Tecnicos!$A$2:$A$1000
Name Tecnicos: [2]Tecnicos!$A$2:$A$1000
Name Version: [2]Formulas!$I$2:$I$3

Sheet RESUMEN
A1: LÍNEA COMUNICACIONES S.A.S | F1: FACTURACIÓN CORRESPONSALES BANCARIOS TIQUIETES AEREOS
A2: FACTURACIÓN PROYECTO CB BANCOLOMBIA | F2: =A3 -> 45930
A3: 45930
F4: CONCEPTOS | G4: TRAYECTOS | H4: TOTAL | I4: % Administración | J4: TOTAL
A5: CONCEPTOS | B5: CANTIDAD | C5: VALOR UNITARIO | D5: VALOR TOTAL | I5: =H5*0.12 -> 0 | J5: =H5+I5 -> 0
A6: Adecuaciones CB | B6: =COUNTA(ADECUACIONES!A:A)-1 -> 10 | C6: 0 | D6: =ADECUACIONES!AE12 -> 1511089.2 | I6: =H6*0.12 -> 0 | J6: =H6+I6 -> 0
A7: Incidentes | B7: =COUNTA(INCIDENTES!A:A)-1 -> 210 | C7: 0 | D7: =INCIDENTES!AG212 -> 20457074 | I7: =H7*0.12 -> 0 | J7: =H7+I7 -> 0
A8: Ordenes de Cambio | B8: =COUNTA(OC!A:A)-1 -> 12 | C8: 0 | D8: =OC!AG14 -> 1484720.1 | I8: =H8*0.12 -> 0 | J8: =H8+I8 -> 0
A9: Tiquetes | B9: 0 | C9: 0 | D9: =J12 -> 0 | I9: =H9*0.12 -> 0 | J9: =H9+I9 -> 0
A10: SUBTOTAL | D10: =SUM(D6:D9) -> 23452883 | I10: =H10*0.12 -> 0 | J10: =H10+I10 -> 0
A11: Iva | D11: =D10*0.19 -> 4456047.8 | I11: =H11*0.12 -> 0 | J11: =H11+I11 -> 0
A12: TOTAL | D12: =D10+D11 -> 27908931 | F12: TOTAL | H12: =SUM(H5:H11) -> 0 | I12: =SUM(I5:I11) -> 0 | J12: =SUM(J5:J11) -> 0

Sheet Tablas dinámicas
A2: ADECUACIONES | J2: NOMBRE CC | K2: Suma de VALOR | L2: Suma de VALOR2
A3: COORDINADOR | B3: CENTRO DE COSTOS LÍNEACOM | C3: % | D3: $ | E3: NOMBRE CC | F3: VALOR | J3: Redeban Centro ( Bogotá) | K3: 1736974.8 | L3: 0.074062314
A4: DIEGO FERNANDO HENAO CARDONA | B4: 0004-0003 | C4: 0.17789869 | D4: 268820.78 | E4: =VLOOKUP(B4,'CENTRO DE COSTOS'!B:C,2,0) -> Redeban Suroccidente (Cali) | F4: =D4 -> 268820.78 | J4: Redeban Costa (Barranqullla) | K4: 2900584.4 | L4: 0.12367709
A5: JUAN SEBASTIÁN RÍOS CASTRILLÓN | B5: 0004-0005 | C5: 0.39654802 | D5: 599219.42 | E5: =VLOOKUP(B5,'CENTRO DE COSTOS'!B:C,2,0) -> Redeban Noroccidente (Medellín) | F5: =D5 -> 599219.42 | J5: Redeban Eje Cafetero (Pereira) | K5: 817097.79 | L5: 0.034839972
A6: KEVIN ALEXIS CORZO BUSTOS | B6: 0004-0007 | C6: 0.33708733 | D6: 509369.02 | E6: =VLOOKUP(B6,'CENTRO DE COSTOS'!B:C,2,0) -> Redeban Oriente (Otros) | F6: =D6 -> 509369.02 | J6: Redeban Noroccidente (Medellín) | K6: 5435677.2 | L6: 0.2317701
A7: MIGUEL JULIÁN HERNÁNDEZ GUARÍN | B7: 0004-0008 | C7: 0.058977307 | D7: 89119.97 | E7: =VLOOKUP(B7,'CENTRO DE COSTOS'!B:C,2,0) -> Redeban Santander | F7: =D7 -> 89119.97 | J7: Redeban Oriente (Otros) | K7: 4631207.7 | L7: 0.19746859
A8: WILLIAM ASDRUBAL ROZO ROZO | B8: 0004-0004 | C8: 0.029488653 | D8: 44559.985 | E8: =VLOOKUP(B8,'CENTRO DE COSTOS'!B:C,2,0) -> Redeban Centro ( Bogotá) | F8: =D8 -> 44559.985 | J8: Redeban Santander | K8: 5165648.9 | L8: 0.22025646
A9: Total general | C9: 1 | D9: 1511089.2 | F9: =D9 -> 1511089.2 | J9: Redeban Suroccidente (Cali) | K9: 2765692.4 | L9: 0.11792548
E10: =VLOOKUP(B10,'CENTRO DE COSTOS'!B:C,2,0) -> #N/A | F10: =D10 -> 0 | J10: Total general | K10: 23452883 | L10: 1
A15: INCIDENTES
A16: COORDINADOR | B16: CENTRO DE COSTOS LÍNEACOM | C16: % | D16: $ | E16: NOMBRE CC
A17: DIEGO FERNANDO HENAO CARDONA | B17: 0004-0002 | C17: 0.039942066 | D17: 817097.79 | E17: =VLOOKUP(B17,'CENTRO DE COSTOS'!B:C,2,0) -> Redeban Eje Cafetero (Pereira) | F17: =D17 -> 817097.79
B18: 0004-0003 | C18: 0.11882986 | D18: 2430911.1 | E18: =VLOOKUP(B18,'CENTRO DE COSTOS'!B:C,2,0) -> Redeban Suroccidente (Cali) | F18: =D18 -> 2430911.1
A19: JOSE MAURICIO HERNANDEZ ROJAS | B19: 0004-0001 | C19: 0.13856449 | D19: 2834623.9 | E19: =VLOOKUP(B19,'CENTRO DE COSTOS'!B:C,2,0) -> Redeban Costa (Barranqullla) | F19: =D19 -> 2834623.9
A20: JUAN SEBASTIÁN RÍOS CASTRILLÓN | B20: 0004-0005 | C20: 0.22196348 | D20: 4540723.2 | E20: =VLOOKUP(B20,'CENTRO DE COSTOS'!B:C,2,0) -> Redeban Noroccidente (Medellín) | F20: =D20 -> 4540723.2
A21: KEVIN ALEXIS CORZO BUSTOS | B21: 0004-0007 | C21: 0.17970726 | D21: 3676284.7 | E21: =VLOOKUP(B21,'CENTRO DE COSTOS'!B:C,2,0) -> Redeban Oriente (Otros) | F21: =D21 -> 3676284.7
A22: MIGUEL JULIÁN HERNÁNDEZ GUARÍN | B22: 0004-0008 | C22: 0.22471147 | D22: 4596939.2 | E22: =VLOOKUP(B22,'CENTRO DE COSTOS'!B:C,2,0) -> Redeban Santander | F22: =D22 -> 4596939.2
A23: WILLIAM ASDRUBAL ROZO ROZO | B23: 0004-0004 | C23: 0.076281382 | D23: 1560493.9 | E23: =VLOOKUP(B23,'CENTRO DE COSTOS'!B:C,2,0) -> Redeban Centro ( Bogotá) | F23: =D23 -> 1560493.9
A24: Total general | C24: 1 | D24: 20457074
A29: OC
A30: COORDINADOR | B30: CENTRO DE COSTOS LÍNEACOM | C30: % | D30: $ | E30: NOMBRE CC
A31: DIEGO FERNANDO HENAO CARDONA | B31: 0004-0003 | C31: 0.044426201 | D31: 65960.474 | E31: =VLOOKUP(B31,'CENTRO DE COSTOS'!B:C,2,0) -> Redeban Suroccidente (Cali) | F31: =D31 -> 65960.474
A32: JOSE MAURICIO HERNANDEZ ROJAS | B32: 0004-0001 | C32: 0.044426201 | D32: 65960.474 | E32: =VLOOKUP(B32,'CENTRO DE COSTOS'!B:C,2,0) -> Redeban Costa (Barranqullla) | F32: =D32 -> 65960.474
A33: JUAN SEBASTIÁN RÍOS CASTRILLÓN | B33: 0004-0005 | C33: 0.19918536 | D33: 295734.51 | E33: =VLOOKUP(B33,'CENTRO DE COSTOS'!B:C,2,0) -> Redeban Noroccidente (Medellín) | F33: =D33 -> 295734.51
A34: KEVIN ALEXIS CORZO BUSTOS | B34: 0004-0007 | C34: 0.30009291 | D34: 445553.98 | E34: =VLOOKUP(B34,'CENTRO DE COSTOS'!B:C,2,0) -> Redeban Oriente (Otros) | F34: =D34 -> 445553.98
A35: MIGUEL JULIÁN HERNÁNDEZ GUARÍN | B35: 0004-0008 | C35: 0.32301693 | D35: 479589.74 | E35: =VLOOKUP(B35,'CENTRO DE COSTOS'!B:C,2,0) -> Redeban Santander | F35: =D35 -> 479589.74
A36: WILLIAM ASDRUBAL ROZO ROZO | B36: 0004-0004 | C36: 0.088852401 | D36: 131920.95 | E36: =VLOOKUP(B36,'CENTRO DE COSTOS'!B:C,2,0) -> Redeban Centro ( Bogotá) | F36: =D36 -> 131920.95
A37: Total general | C37: 1 | D37: 1484720.1

Sheet BASE LIQUIDACION
A1: TARIFAS 2025 | E1: Incremento 2025
A2: Tipificación | B2: Descripción | C2: Dia actividad Exitosa | D2: Dia actividad Fallida | E2: 0.052
A3: Tipo I | B3: Metropolitano | C3: =62700.07*(1+$E$2) -> 65960.474 | D3: =42357.4*(1+$E$2) -> 44559.985
A4: Tipo II | B4: Hasta 3 horas | C4: =155716.31*(1+$E$2) -> 163813.56 | D4: =127766.53*(1+$E$2) -> 134410.39
A5: Tipo III | B5: De 3 a 5 horas | C5: =262099.22*(1+$E$2) -> 275728.38 | D5: =211886.19*(1+$E$2) -> 222904.27
A6: Tipo IV | B6: Más de 5 horas | C6: =455883.78*(1+$E$2) -> 479589.74 | D6: =441833.68*(1+$E$2) -> 464809.03
A7: Destino aereo | B7: No incluye valor del Tiquete | C7: =455883.78*(1+$E$2) -> 479589.74 | D7: =441833.68*(1+$E$2) -> 464809.03
A8: *Donde se requiera transporte aéreo o fluvial se factura adicional a tarifa TIPO IV el valor del tiquete + el 12% de admon.
A10: Gestión Telefónica | B10: =36031.04*(1+$E$2) -> 37904.654
A11: Mts Acometida electrica | B11: =30182.1*(1+$E$2) -> 31751.569
A12: Mts Acometida datos | B12: =15432.22*(1+$E$2) -> 16234.695
A13: switche | B13: =244669.03*(1+$E$2) -> 257391.82
A14: Router | B14: =291399.51*(1+$E$2) -> 306552.28
A15: Envio operador Logistico | B15: =53547.34*(1+$E$2) -> 56331.802

Sheet ADECUACIONES
A1: CIUDAD SEDE | B1: COORDINADOR | C1: CENTRO DE COSTOS LÍNEACOM | D1: CÓDIGO DANE | E1: TA/CODIGO ACTIVIDAD | F1: CODIGO CB | G1: ACTIVIDAD | H1: TIPO DE APERTURA | I1: DEPARTAMENTO | J1: CIUDAD | K1: NOMBRE DEL CB | L1: RED | M1: FO | N1: FECHA LISTA | O1: FECHA ULTIMA ACTUALIZACION | P1: FORMATO | Q1: CADENA | R1: ESTADO | S1: OBSERVACIONES CLIENTE | T1: FORMA DE ATENCIÓN | U1: TERMINALES | V1: TIPIFICACION | W1: TIPO DE TRAYECTO | X1: NOMBRE DEL TECNICO | Y1: ACOMETIDA DATOS | Z1: ACOMETIDA ELECTRICA | AA1: SWITCH | AB1: ROUTER | AC1: VALOR DIAS ACTIVIDAD FACTURABLES | AD1: DIAS ACTIVIDAD FACTURABLES | AE1: VALOR TOTAL INSTALACION DE PUBLICIDAD
A2: CIUDAD SEDE | B2: COORDINADOR | C2: CENTRO DE COSTOS LINEACOM | D2: CODIGO DANE | E2: TA/CODIGO ACTIVIDAD | F2: CODIGO CB | G2: ACTIVIDAD | H2: TIPO DE APERTURA | I2: DEPARTAMENTO | J2: CIUDAD | K2: NOMBRE DEL CB | L2: RED | M2: FO | P2: FORMATO | Q2: CADENA | R2: ESTADO | S2: OBSERVACIONES CLIENTE | T2: FORMA DE ATENCION | V2: TIPIFICACION | W2: TIPO DE TRAYECTO | X2: NOMBRE DEL TECNICO | Y2: ACOMETIDA DATOS | Z2: ACOMETIDA ELECTRICA | AA2: SWITCH | AB2: ROUTER | AC2: VALOR DIAS ACTIVIDAD FACTURABLES | AD2: DIAS ACTIVIDAD FACTURABLES | AE2: VALOR TOTAL INSTALACION DE PUBLICIDAD
A3: PASTO | B3: =VLOOKUP(A3,'CENTRO DE COSTOS'!A:D,4,FALSE) -> DIEGO FERNANDO HENAO CARDONA | C3: =VLOOKUP(A3,'CENTRO DE COSTOS'!A:C,2,FALSE) -> 0004-0003 | D3: 52687 | E3: TA-25-1034011 | F3: 81249 | G3: APERTURA | H3: CB CRECIMIENTO - NUEVO | I3: NARIÑO | J3: SAN LORENZO | K3: BARRIO EL CENTRO SAN LORENZO | L3: REDEBAN | M3: FO-25-1433131 | N3: 45896 | O3: 45903 | P3: UNO A UNO | Q3: UNO A UNO | R3: EJECUTADO/CANCELADO | S3: 27-08-2025 SE REALIZA LLAMADA AL CLIENTE, SE HABLA CON EL SR HECTOR ROSENDO ESPAÑA RODRIGUEZ SE VALIDA DIRECCIÓN OK, CANAL OK, DISPONIBILIDAD TOTAL, LLAMAR EL DÍA LA INSTALACIÓN PARA CONFIRMAR VISITA, AVISO EXTERIOR ALTURA APROX 3 METROS; TOMACORRIENTE CERCANO: SI; TIENE CABINA DE SEGURIDAD: NO 28-09 SE REALIZÓ COMUNICACIÓN TELEFÓNICA CON USUARIO E INFORMA QUE DEBIDO A CELEBRACIÓN DE FIESTAS EN EL MUNICIPIO ES COMPLICADO EL TRANSPORTE Y LA ATENCIÓN DE LA VISITA. SOLICITA QUE ESTA SEA REALIZADA EN LA SIGUIENTE SEMANA CUANDO YA SE HAYA NORMALIZADO TODO. 3/09/2025 SE VISITA EL COMERCIO PARA REALIZAR APERTURA PERO NO ES POSIBLE YA QUE EN EL COMERCIO FUNCIONA CORRESPONSAL DE BANCO AGRARIO POR LO QUE NO SE APERTURA YA QUE SE ESTARÍA VIOLANDO PRINCIPIO DE EXCLUSIVIDAD DE BANCOLOMBIA. | T3: VISITA _TECNICA | U3: FKZZZ662 | V3: TIPO II | W3: TERRESTRE | X3: GUERRERO RAMIREZ OSCAR DARIO | Y3: 0 | Z3: 0 | AA3: 0 | AB3: 0 | AC3: 1 | AD3: =IF(V3="TIPO I",'BASE LIQUIDACION'!$D$3,IF(V3="TIPO II",'BASE LIQUIDACION'!$D$4,IF(V3="TIPO III",'BASE LIQUIDACION'!$D$5,'BASE LIQUIDACION'!$D$7))) -> 134410.39 | AE3: =Y3*'BASE LIQUIDACION'!$B$12+Z3*'BASE LIQUIDACION'!$B$11+AA3*'BASE LIQUIDACION'!$B$13+AB3*'BASE LIQUIDACION'!$B$14+AC3*AD3 -> 134410.39
A4: NEIVA | B4: =VLOOKUP(A4,'CENTRO DE COSTOS'!A:D,4,FALSE) -> KEVIN ALEXIS CORZO BUSTOS | C4: =VLOOKUP(A4,'CENTRO DE COSTOS'!A:C,2,FALSE) -> 0004-0007 | D4: 18753 | E4: TA-25-1034461 | F4: 81230 | G4: APERTURA | H4: CB CRECIMIENTO ALIANZA - NUEVO | I4: CAQUETA | J4: SAN VICENTE DEL CAGUAN | K4: DISTRICOL SURTICELL EMILY | L4: REDEBAN | M4: FO-25-1433896 | N4: 45896 | O4: 45905 | P4: AGREGADOR | Q4: DISTRICOL | R4: EJECUTADO/CANCELADO | S4: 27-08 PROGRAMACIÓN REALIZADA POR LA ALIANZA 5/09/2025 SE REALIZA VISITA PARA IMPLEMENTACIÓN CB DISTRICOL 81230, PERO SE EVIDENCIA QUE APROXIMADAMENTE A 40MTS HAY UN CB AGREGADOR PTM SAN VICENTE DEL CAGUAN 50792, POR FAVOR NOS INDICA COMO PROCEDER. / ENTIDAD SOLICITA CANCELAR ACTIVIDAD | T4: VISITA _TECNICA | U4: FKZZZ688 | V4: TIPO IV ESPECIAL | W4: TERRESTRE / AEREO | X4: BERMUDEZ SANCHEZ JOSE NEYBER | Y4: 0 | Z4: 0 | AA4: 0 | AB4: 0 | AC4: 1 | AD4: =IF(V4="TIPO I",'BASE LIQUIDACION'!$D$3,IF(V4="TIPO II",'BASE LIQUIDACION'!$D$4,IF(V4="TIPO III",'BASE LIQUIDACION'!$D$5,'BASE LIQUIDACION'!$D$7))) -> 464809.03 | AE4: =Y4*'BASE LIQUIDACION'!$B$12+Z4*'BASE LIQUIDACION'!$B$11+AA4*'BASE LIQUIDACION'!$B$13+AB4*'BASE LIQUIDACION'!$B$14+AC4*AD4 -> 464809.03
A5: TUNJA | B5: =VLOOKUP(A5,'CENTRO DE COSTOS'!A:D,4,FALSE) -> MIGUEL JULIÁN HERNÁNDEZ GUARÍN | C5: =VLOOKUP(A5,'CENTRO DE COSTOS'!A:C,2,FALSE) -> 0004-0008 | D5: 15001 | E5: TA-25-1040108 | F5: 81267 | G5: APERTURA | H5: CB CRECIMIENTO ALIANZA - NUEVO | I5: BOYACA | J5: TUNJA | K5: DISTRICOL TIENDA KEVINS | L5: REDEBAN | M5: FO-25-1444565 | N5: 45898 | O5: 45901 | P5: AGREGADOR | Q5: DISTRICOL | R5: EJECUTADO/CANCELADO | S5: 29-08 PROGRAMACIÓN REALIZADA POR LA ALIANZA 1/09/2025 SE ESCALA NOVEDAD DE IMPLEMENTACIÓN. SE IDENTIFICA EL PUNTO DE CORRESPONSAL CON AVAL 90117612. SE PROCEDE A CANCELAR EL PUNTO DE INSTALACIÓN. | T5: VISITA _TECNICA | U5: SKZZZ569 | V5: TIPO I | W5: TERRESTRE | X5: SOLER HOYOS CRISTIAN LEONARDO | Y5: 0 | Z5: 0 | AA5: 0 | AB5: 0 | AC5: 1 | AD5: =IF(V5="TIPO I",'BASE LIQUIDACION'!$D$3,IF(V5="TIPO II",'BASE LIQUIDACION'!$D$4,IF(V5="TIPO III",'BASE LIQUIDACION'!$D$5,'BASE LIQUIDACION'!$D$7))) -> 44559.985 | AE5: =Y5*'BASE LIQUIDACION'!$B$12+Z5*'BASE LIQUIDACION'!$B$11+AA5*'BASE LIQUIDACION'!$B$13+AB5*'BASE LIQUIDACION'!$B$14+AC5*AD5 -> 44559.985
A6: BUCARAMANGA | B6: =VLOOKUP(A6,'CENTRO DE COSTOS'!A:D,4,FALSE) -> MIGUEL JULIÁN HERNÁNDEZ GUARÍN | C6: =VLOOKUP(A6,'CENTRO DE COSTOS'!A:C,2,FALSE) -> 0004-0008 | D6: 68307 | E6: TA-25-1054855 | F6: 81327 | G6: APERTURA | H6: CB CRECIMIENTO ALIANZA - NUEVO | I6: SANTANDER | J6: GIRON | K6: PTM GIRON MULTISERVICIOS LOS C | L6: REDEBAN | M6: FO-25-1467930 | N6: 45903 | O6: 45904 | P6: AGREGADOR | Q6: COMCARD - PTM | R6: EJECUTADO/CANCELADO | S6: 03-09 PROGRAMACIÓN REALIZADA POR LA ALIANZA4/09/2025 NOS PERMITIMOS INFORMARLE QUE, TRAS REALIZAR LA RESPECTIVA VERIFICACIÓN EN CAMPO, IDENTIFICAMOS QUE EL PUNTO A INSTALAR EN LA DIRECCIÓN CRA 19A NO 25-11 LC 1, BARRIO VILLA CAMPESTRE 1 (CÓDIGO 81327), SE ENCUENTRA A UNA DISTANCIA APROXIMADA DE 50 METROS DEL PUNTO YA INSTALADO EN LA DIRECCIÓN CAR 21 #22-124, VILLA CAMPESTRE 3ª ETAPA (CÓDIGO 77310). TENIENDO EN CUENTA LA CERCANÍA ENTRE AMBOS PUNTOS, SOLICITAMOS SU AUTORIZACIÓN PARA PROCEDER CON LA IMPLEMENTACIÓN EN LA DIRECCIÓN MENCIONADA, GARANTIZANDO QUE SE PARÁMETROS TÉCNICOS Y OPERATIVOS ESTABLECIDOS. / ENTIDAD SOLICITAN CANCELAR INSTALACIÓN | T6: VISITA _TECNICA | U6: SMZZZ288 | V6: TIPO I | W6: TERRESTRE | X6: SANTOS GONZALEZ JOHAN FABIAN | Y6: 0 | Z6: 0 | AA6: 0 | AB6: 0 | AC6: 1 | AD6: =IF(V6="TIPO I",'BASE LIQUIDACION'!$D$3,IF(V6="TIPO II",'BASE LIQUIDACION'!$D$4,IF(V6="TIPO III",'BASE LIQUIDACION'!$D$5,'BASE LIQUIDACION'!$D$7))) -> 44559.985 | AE6: =Y6*'BASE LIQUIDACION'!$B$12+Z6*'BASE LIQUIDACION'!$B$11+AA6*'BASE LIQUIDACION'!$B$13+AB6*'BASE LIQUIDACION'!$B$14+AC6*AD6 -> 44559.985
A7: APARTADO | B7: =VLOOKUP(A7,'CENTRO DE COSTOS'!A:D,4,FALSE) -> JUAN SEBASTIÁN RÍOS CASTRILLÓN | C7: =VLOOKUP(A7,'CENTRO DE COSTOS'!A:C,2,FALSE) -> 0004-0005 | D7: 5837 | E7: TA-25-1117897 | F7: 81501 | G7: APERTURA | H7: CB CRECIMIENTO ALIANZA - NUEVO | I7: ANTIOQUIA | J7: TURBO | K7: DISTRICOL TIENDA GINES ROPA Y ACCESORIOS | L7: REDEBAN | M7: FO-25-1543491 | N7: 45917 | O7: 45919 | P7: AGREGADOR | Q7: DISTRICOL | R7: EJECUTADO/CANCELADO | S7: 17-09 PROGRAMACIÓN REALIZADA POR LA ALIANZA 19/09/2025 VISITAMOS DIRECCIÓN RELACIONADA EN CUADRO ENCONTRANDO QUE NO HAY COMERCIO EN ESTA. SEGÚN VALIDACIONES DE PERSONAL TÉCNICO EL COMERCIO ESTÁ UBICADO REALMENTE EN DIRECCIÓN CARRERA 30 # 22-30 COMO MUESTRA UN RECIBO DE SERVICIOS PÚBLICOS. | T7: VISITA _TECNICA | U7: FSZZZ877 | V7: TIPO II | W7: TERRESTRE | X7: CASTRO HENAO DANIEL ESTEBAN | Y7: 0 | Z7: 0 | AA7: 0 | AB7: 0 | AC7: 1 | AD7: =IF(V7="TIPO I",'BASE LIQUIDACION'!$D$3,IF(V7="TIPO II",'BASE LIQUIDACION'!$D$4,IF(V7="TIPO III",'BASE LIQUIDACION'!$D$5,'BASE LIQUIDACION'!$D$7))) -> 134410.39 | AE7: =Y7*'BASE LIQUIDACION'!$B$12+Z7*'BASE LIQUIDACION'!$B$11+AA7*'BASE LIQUIDACION'!$B$13+AB7*'BASE LIQUIDACION'!$B$14+AC7*AD7 -> 134410.39
A8: PASTO | B8: =VLOOKUP(A8,'CENTRO DE COSTOS'!A:D,4,FALSE) -> DIEGO FERNANDO HENAO CARDONA | C8: =VLOOKUP(A8,'CENTRO DE COSTOS'!A:C,2,FALSE) -> 0004-0003 | D8: 52356 | E8: TA-25-1118001 | F8: 81502 | G8: APERTURA | H8: CB CRECIMIENTO ALIANZA - NUEVO | I8: NARIÑO | J8: IPIALES | K8: DISTRICOL VAR SEBASTIAN JM | L8: REDEBAN | M8: FO-25-1543540 | N8: 45917 | O8: 45918 | P8: AGREGADOR | Q8: DISTRICOL | R8: EJECUTADO/CANCELADO | S8: 17-09 PROGRAMACIÓN REALIZADA POR LA ALIANZA 18/09/2025 SE REALIZÓ VISITA AL COMERCIO PARA LA APERTURA DEL CB PERO NO ES POSIBLE YA QUE EL COMERCIO NO CUENTA CON CONEXIÓN A INTERNET, QUEDA PENDIENTE QUE EL USUARIO ADQUIERA EL SERVICIO PARA PODER INSTALAR EL CB | T8: VISITA _TECNICA | U8: FSZZZ885 | V8: TIPO II | W8: TERRESTRE | X8: GUERRERO RAMIREZ OSCAR DARIO | Y8: 0 | Z8: 0 | AA8: 0 | AB8: 0 | AC8: 1 | AD8: =IF(V8="TIPO I",'BASE LIQUIDACION'!$D$3,IF(V8="TIPO II",'BASE LIQUIDACION'!$D$4,IF(V8="TIPO III",'BASE LIQUIDACION'!$D$5,'BASE LIQUIDACION'!$D$7))) -> 134410.39 | AE8: =Y8*'BASE LIQUIDACION'!$B$12+Z8*'BASE LIQUIDACION'!$B$11+AA8*'BASE LIQUIDACION'!$B$13+AB8*'BASE LIQUIDACION'!$B$14+AC8*AD8 -> 134410.39
A9: MEDELLIN | B9: =VLOOKUP(A9,'CENTRO DE COSTOS'!A:D,4,FALSE) -> JUAN SEBASTIÁN RÍOS CASTRILLÓN | C9: =VLOOKUP(A9,'CENTRO DE COSTOS'!A:C,2,FALSE) -> 0004-0005 | D9: 5604 | E9: TA-25-1145368 | F9: 81673 | G9: APERTURA | H9: CB CRECIMIENTO ALIANZA - NUEVO | I9: ANTIOQUIA | J9: REMEDIOS | K9: DISTRICOL MUNDO PELUQUERO R | L9: REDEBAN | M9: FO-25-1585234 | N9: 45924 | O9: 45925 | P9: AGREGADOR | Q9: DISTRICOL | R9: EJECUTADO/CANCELADO | S9: 24-09 PROGRAMACIÓN REALIZADA POR LA ALIANZA 25/09/2025 VISITAMOS PUNTO ENCONTRANDO QUE COMERCIO ESTÁ EN DIRECCIÓN DISTINTA A LA RELACIONADA EN LISTA DE CHEQUEO. LA DIRECCIÓN REAL EN LA QUE ESTÁ EL COMERCIO ES CALLE 11 # 13 – 86. ESCALAMOS POR NOVEDAD DE DIRECCIÓN. 25/09/2025 POR FAVOR PROCEDER CON LA CANCELACIÓN DE LA IMPLEMENTACIÓN, YA QUE EL CB NO SE ENCUENTRA EN LA DIRECCIÓN REGISTRADA EN LA LISTA DE CHEQUEO. | T9: VISITA _TECNICA | U9: FWZZZ437 | V9: TIPO IV | W9: TERRESTRE | X9: DIAZ ZABALA FRANCIS DUBAN | Y9: 0 | Z9: 0 | AA9: 0 | AB9: 0 | AC9: 1 | AD9: =IF(V9="TIPO I",'BASE LIQUIDACION'!$D$3,IF(V9="TIPO II",'BASE LIQUIDACION'!$D$4,IF(V9="TIPO III",'BASE LIQUIDACION'!$D$5,'BASE LIQUIDACION'!$D$7))) -> 464809.03 | AE9: =Y9*'BASE LIQUIDACION'!$B$12+Z9*'BASE LIQUIDACION'!$B$11+AA9*'BASE LIQUIDACION'!$B$13+AB9*'BASE LIQUIDACION'!$B$14+AC9*AD9 -> 464809.03
A10: VILLAVICENCIO | B10: =VLOOKUP(A10,'CENTRO DE COSTOS'!A:D,4,FALSE) -> KEVIN ALEXIS CORZO BUSTOS | C10: =VLOOKUP(A10,'CENTRO DE COSTOS'!A:C,2,FALSE) -> 0004-0007 | D10: 50001 | E10: TA-25-1145459 | F10: 81695 | G10: APERTURA | H10: CB CRECIMIENTO ALIANZA - NUEVO | I10: META | J10: VILLAVICENCIO | K10: PTM VILLAVICENCIO DROGAS VILL | L10: REDEBAN | M10: FO-25-1577404 | N10: 45924 | O10: 45926 | P10: AGREGADOR | Q10: COMCARD - PTM | R10: EJECUTADO/CANCELADO | S10: 24-09 PROGRAMACIÓN REALIZADA POR LA ALIANZA 26/09/2025 SE ESCALA CASO DE APERTURA CB 3007081695 - PTM VILLAVICENCIO DROGAS VILLAVICENCIO CB A INSTALAR PTM 81695 - CALLE 10 NO 12 C - 111 ESTERO CB INSTALADO WOMPI 77610 - CALLE 10 NO 12 C – 112 BARRIO ESTERO / ENTIDAD SOLICITA CANCELAR INSTALACIÓN | T10: VISITA _TECNICA | U10: FWZZZ460 | V10: TIPO I | W10: TERRESTRE | X10: CASTRILLON URREA LONDIER LEANDRO | Y10: 0 | Z10: 0 | AA10: 0 | AB10: 0 | AC10: 1 | AD10: =IF(V10="TIPO I",'BASE LIQUIDACION'!$D$3,IF(V10="TIPO II",'BASE LIQUIDACION'!$D$4,IF(V10="TIPO III",'BASE LIQUIDACION'!$D$5,'BASE LIQUIDACION'!$D$7))) -> 44559.985 | AE10: =Y10*'BASE LIQUIDACION'!$B$12+Z10*'BASE LIQUIDACION'!$B$11+AA10*'BASE LIQUIDACION'!$B$13+AB10*'BASE LIQUIDACION'!$B$14+AC10*AD10 -> 44559.985
A11: BOGOTA | B11: =VLOOKUP(A11,'CENTRO DE COSTOS'!A:D,4,FALSE) -> WILLIAM ASDRUBAL ROZO ROZO | C11: =VLOOKUP(A11,'CENTRO DE COSTOS'!A:C,2,FALSE) -> 0004-0004 | D11: 11001 | E11: TA-25-1145952 | F11: 81630 | G11: APERTURA | H11: CB CRECIMIENTO ALIANZA - NUEVO | I11: CUNDINAMARCA | J11: BOGOTA | K11: PTM BOGOTA TIENDA SANTI LA SEP | L11: REDEBAN | M11: FO-25-1589721 | N11: 45924 | O11: 45929 | P11: AGREGADOR | Q11: COMCARD - PTM | R11: EJECUTADO | S11: 24-09 PROGRAMACIÓN REALIZADA POR LA ALIANZA 26/09/2025 SE LLEGA A SITIO, SE VERIFICA Y NO AHI PUNTO CABLEADO, NI PUERTO DISPONIBLE PARA LA CONEXIÓN DEL DATAFONO, CLIENTE SE NIEGA A DESCONECTAR DISPOSITIVOS PARA REALIZAR LA INSTALACIÓN. SE REPROGRAMA YA QUE INDICA QUE SE VA A CONSEGUIR UN SWITCH O REPETIDOR. SE ESCALA CON COORDINADOR QUIEN INDICA SE REALIZARA REPROGRAMACION PARA VISITAR NUEVAMENTE EL PUNTO. 29/09/2025 SE REALIZA INSTALACIÓN DE CORRESPONSAL, SE INSTALAN EQUIPOS CON PRUEBAS EXITOSAS, SE CAPACITA Y SE EVALÚA AL CLIENTE, SE INSTALA PUBLICIDAD COMPLETA, CB QUEDA OPERATIVO. USUARIO SOMOS BANCOLOMBIA ACTIVO | T11: VISITA _TECNICA | U11: FWZZZ506 | V11: TIPO I | W11: TERRESTRE | X11: ARIAS QUILINDO JULIAN | Y11: 0 | Z11: 0 | AA11: 0 | AB11: 0 | AC11: 1 | AD11: =IF(V11="TIPO I",'BASE LIQUIDACION'!$D$3,IF(V11="TIPO II",'BASE LIQUIDACION'!$D$4,IF(V11="TIPO III",'BASE LIQUIDACION'!$D$5,'BASE LIQUIDACION'!$D$7))) -> 44559.985 | AE11: =Y11*'BASE LIQUIDACION'!$B$12+Z11*'BASE LIQUIDACION'!$B$11+AA11*'BASE LIQUIDACION'!$B$13+AB11*'BASE LIQUIDACION'!$B$14+AC11*AD11 -> 44559.985
AE12: =SUM(AE3:AE11) -> 1511089.2
Z21: facturacion_swicth
Z22: facturacion_switch

Sheet TIPOLOGIAS
A1: COD. CIUDAD | B1: CIUDAD | C1: DEPARTAMENTO | D1: DESDE DONDE SE ATIENDE | E1: TIPO DE TRAYECTO NUEVO | F1: TIPOLOGIA NUEVA
A2: 91430 | B2: LA VICTORIA | C2: AMAZONAS | D2: BOGOTA | E2: AEREO | F2: TIPO IV ESPECIAL
A3: 91669 | B3: PUERTO SANTANDER | C3: AMAZONAS | D3: BOGOTA | E3: AEREO | F3: TIPO IV ESPECIAL
A4: 91263 | B4: EL ENCANTO | C4: AMAZONAS | D4: BOGOTA | E4: AEREO | F4: TIPO IV ESPECIAL
A5: 91405 | B5: LA CHORRERA | C5: AMAZONAS | D5: BOGOTA | E5: AEREO | F5: TIPO IV ESPECIAL
A6: 91407 | B6: LA PEDRERA | C6: AMAZONAS | D6: BOGOTA | E6: AEREO | F6: TIPO IV ESPECIAL
A7: 91001 | B7: LETICIA | C7: AMAZONAS | D7: BOGOTA | E7: AEREO | F7: TIPO IV ESPECIAL
A8: 91460 | B8: MIRITI - PARANA | C8: AMAZONAS | D8: BOGOTA | E8: AEREO | F8: TIPO IV ESPECIAL
A9: 91530 | B9: PUERTO ALEGRIA | C9: AMAZONAS | D9: BOGOTA | E9: AEREO | F9: TIPO IV ESPECIAL
A10: 91536 | B10: PUERTO ARICA | C10: AMAZONAS | D10: BOGOTA | E10: AEREO | F10: TIPO IV ESPECIAL
A11: 91540 | B11: PUERTO NARIÑO | C11: AMAZONAS | D11: BOGOTA | E11: AEREO | F11: TIPO IV ESPECIAL
A12: 91798 | B12: TARAPACA | C12: AMAZONAS | D12: BOGOTA | E12: AEREO | F12: TIPO IV ESPECIAL
A13: 5055 | B13: ARGELIA | C13: ANTIOQUIA | D13: MEDELLIN | E13: TERRESTRE | F13: TIPO IV
... A1124: 23682 | B1124: SAN JOSE DE URE | C1124: CORDOBA | D1124: MONTERIA | E1124: TERRESTRE | F1124: TIPO III

Sheet INCIDENTES
A1: CIUDAD SEDE | B1: COORDINADOR | C1: CENTRO DE COSTOS LÍNEACOM | D1: CÓDIGO DANE | E1: TA/CODIGO ACTIVIDAD | F1: CODIGO CB | G1: ACTIVIDAD | H1: DEPARTAMENTO | I1: CIUDAD | J1: NOMBRE DEL CB | K1: RED | L1: FO | M1: FECHA ASIGNACIÓN A LÍNEA COMUNICACIONES (DD/MM/AAAA HH:MM) | N1: FECHA CIERRE DEL TICKET (DD/MM/AAAA HH:MM) | O1: ACOMETIDA | P1: GRUPO_FALLA | Q1: CATEGORÍA | R1: FALLA | S1: FORMATO | T1: CADENA | U1: ESTADO | V1: OBSERVACION | W1: FORMA DE ATENCIÓN | X1: TERMINAL | Y1: TIPIFICACION | Z1: TIPO DE TRAYECTO | AA1: NOMBRE DEL TECNICO | AB1: DIAS DE VISITA | AC1: ACOMETIDA DATOS | AD1: ACOMETIDA ELÉCTRICA | AE1: SWITCH | AF1: VALOR DIAS ACTIVIDAD FACTURABLES | AG1: VALOR DIAS ACOMPAÑAMIENTO FACTURABLES
A2: CALI | B2: =VLOOKUP(A2,'CENTRO DE COSTOS'!A:D,4,FALSE) -> DIEGO FERNANDO HENAO CARDONA | C2: =VLOOKUP(A2,'CENTRO DE COSTOS'!A:D,2,FALSE) -> 0004-0003 | D2: 76001 | E2: 2811808 | F2: 65776 | G2: INCIDENTE | H2: VALLE DEL CAUCA | I2: CALI | J2: REDY CASA DEL TENDERO | K2: REDEBAN | L2: FO-25-1601530 | M2: 45930.333 | N2: 45930.426 | O2: NO | P2: USUARIO | Q2: USUARIOS | R2: USUARIOS BLOQUEADOS | U2: CERRADO | V2: 30/09/2025 SE ESCALA PARA VISITA. LLAMAR ANTES DE VISITAR, CONFIRMAR FALLA Y DATOS | 30/09/2025 SE HABLA CON EL CLIENTE QUIEN ME INCIDA QUE DESPUES DEL CAMBIO DE EQUIPO, FUERON A SACAR UN DUPLICADO Y LA CLAVE 1526 NO LE FUNCIONO , PERO QUE EN LA NOCHE CUANDO FUERON A SACAR EL CIERRE, YA PUDIERON OPERARLO NORMAL , EL DATAFONO ESTA FUNCIONAL | W2: SOPORTE_TELEFÓNICO | X2: 0 | Y2: TIPO I | Z2: TERRESTRE | AA2: HENAO CARDONA DIEGO FERNANDO | AB2: 0 | AC2: 0 | AD2: 0 | AE2: 0 | AF2: =IF(W2="SOPORTE_TELEFÓNICO",'BASE LIQUIDACION'!$B$10,IF(Y2="TIPO I",'BASE LIQUIDACION'!$C$3,IF(Y2="TIPO II",'BASE LIQUIDACION'!$C$4,IF(Y2="TIPO III",'BASE LIQUIDACION'!$C$5,'BASE LIQUIDACION'!$C$7)))) -> 37904.654 | AG2: =IF(W2="SOPORTE_TELEFÓNICO",'BASE LIQUIDACION'!$B$10,(AB2*AF2+AC2*'BASE LIQUIDACION'!$B$12+AD2*'BASE LIQUIDACION'!$B$11+INCIDENTES!AE2*'BASE LIQUIDACION'!$B$13)) -> 37904.654
A3: TUNJA | B3: =VLOOKUP(A3,'CENTRO DE COSTOS'!A:D,4,FALSE) -> MIGUEL JULIÁN HERNÁNDEZ GUARÍN | C3: =VLOOKUP(A3,'CENTRO DE COSTOS'!A:D,2,FALSE) -> 0004-0008 | D3: 15238 | E3: 2811639 | F3: 65128 | G3: INCIDENTE | H3: BOYACA | I3: DUITAMA | J3: BARRIO VATICANO DUITAMA 1 | K3: REDEBAN | L3: FO-25-1601034 | M3: 45929.745 | N3: 45930.598 | O3: NO | P3: USUARIO | Q3: CIERRE | R3: COMERCIO NO REALIZA CIERRE | U3: CERRADO | V3: 29/09/2025 SE ESCALA PARA VISITA. LLAMAR ANTES DE VISITAR, CONFIRMAR FALLA Y DATOS | 30/09/2025 SE REALIZAN VALIDACIONES DE COMUNICACION CORRESPONSAL OPERATIVO SE EVIDENCIA QUE EL EQUIPO SE ENCUENTRA CON LA MEMORIA ACOMULADA CLIENTE AUTORIZA RELIZAR BORRADO AL EQUIPO SE LE INDICA LA FORMA CORRECTA DE REALIZAR LOS CIERRES DIARIOS PRUEBAS OK CLIENTE CONFORME | W3: VISITA_TÉCNICA | X3: 1A007838 | Y3: TIPO II | Z3: TERRESTRE | AA3: RODRIGUEZ MURCIA YERSON IVAN | AB3: 1 | AC3: 0 | AD3: 0 | AE3: 0 | AF3: =IF(W3="SOPORTE_TELEFÓNICO",'BASE LIQUIDACION'!$B$10,IF(Y3="TIPO I",'BASE LIQUIDACION'!$C$3,IF(Y3="TIPO II",'BASE LIQUIDACION'!$C$4,IF(Y3="TIPO III",'BASE LIQUIDACION'!$C$5,'BASE LIQUIDACION'!$C$7)))) -> 163813.56 | AG3: =IF(W3="SOPORTE_TELEFÓNICO",'BASE LIQUIDACION'!$B$10,(AB3*AF3+AC3*'BASE LIQUIDACION'!$B$12+AD3*'BASE LIQUIDACION'!$B$11+INCIDENTES!AE3*'BASE LIQUIDACION'!$B$13)) -> 163813.56
A4: APARTADO | B4: =VLOOKUP(A4,'CENTRO DE COSTOS'!A:D,4,FALSE) -> JUAN SEBASTIÁN RÍOS CASTRILLÓN | C4: =VLOOKUP(A4,'CENTRO DE COSTOS'!A:D,2,FALSE) -> 0004-0005 | D4: 5045 | E4: 2810861 | F4: 32309 | G4: INCIDENTE | H4: ANTIOQUIA | I4: APARTADO | J4: CHINITA APARTADO ANTIOQUIA | K4: REDEBAN | L4: FO-25-1600699 | M4: 45929.683 | N4: 45930.467 | O4: NO | P4: USUARIO | Q4: COMUNICACION | R4: CANAL DEL COMERCIO | U4: CERRADO | V4: 29/09/2025 SE ESCALA PARA VISITA. LLAMAR ANTES DE VISITAR, CONFIRMAR FALLA Y DATOS | 30/09/2025 SE REALIZA BORRADO DE MEMORIA, CLIENTE INDICA REINICIOS, SE VERIFICA CABLEADO Y SE ENCUENTRA DATAFONO EN BUENAS CONDICIONES | W4: VISITA_TÉCNICA | X4: NN00M741 | Y4: TIPO I | Z4: TERRESTRE | AA4: CASTRO HENAO DANIEL ESTEBAN | AB4: 1 | AC4: 0 | AD4: 0 | AE4: 0 | AF4: =IF(W4="SOPORTE_TELEFÓNICO",'BASE LIQUIDACION'!$B$10,IF(Y4="TIPO I",'BASE LIQUIDACION'!$C$3,IF(Y4="TIPO II",'BASE LIQUIDACION'!$C$4,IF(Y4="TIPO III",'BASE LIQUIDACION'!$C$5,'BASE LIQUIDACION'!$C$7)))) -> 65960.474 | AG4: =IF(W4="SOPORTE_TELEFÓNICO",'BASE LIQUIDACION'!$B$10,(AB4*AF4+AC4*'BASE LIQUIDACION'!$B$12+AD4*'BASE LIQUIDACION'!$B$11+INCIDENTES!AE4*'BASE LIQUIDACION'!$B$13)) -> 65960.474
A5: CALI | B5: =VLOOKUP(A5,'CENTRO DE COSTOS'!A:D,4,FALSE) -> DIEGO FERNANDO HENAO CARDONA | C5: =VLOOKUP(A5,'CENTRO DE COSTOS'!A:D,2,FALSE) -> 0004-0003 | D5: 76109 | E5: 2808683 | F5: 63162 | G5: INCIDENTE | H5: VALLE DEL CAUCA | I5: BUENAVENTURA | J5: BARRIO CENTRO BUENAVENTURA 9 | K5: REDEBAN | L5: FO-25-1598975 | M5: 45929.541 | N5: 45930.594 | O5: NO | P5: USUARIO | Q5: COMUNICACION | R5: CONEXIONES DE COMERCIO | U5: CERRADO | V5: 29/09/2025 SE ESCALA PARA VISITA. LLAMAR ANTES DE VISITAR, CONFIRMAR FALLA Y DATOS | 30/09/2025 DATAFONO SIN INTERNET SE REVISA CABLEADO SE REINICIA ROUTER Y QUEDA FUNCIONANDO CORRECTAMENTE | W5: VISITA_TÉCNICA | X5: JA00T600 | Y5: TIPO III | Z5: TERRESTRE | AA5: CUERO RUIZ JHONNY | AB5: 1 | AC5: 0 | AD5: 0 | AE5: 0 | AF5: =IF(W5="SOPORTE_TELEFÓNICO",'BASE LIQUIDACION'!$B$10,IF(Y5="TIPO I",'BASE LIQUIDACION'!$C$3,IF(Y5="TIPO II",'BASE LIQUIDACION'!$C$4,IF(Y5="TIPO III",'BASE LIQUIDACION'!$C$5,'BASE LIQUIDACION'!$C$7)))) -> 275728.38 | AG5: =IF(W5="SOPORTE_TELEFÓNICO",'BASE LIQUIDACION'!$B$10,(AB5*AF5+AC5*'BASE LIQUIDACION'!$B$12+AD5*'BASE LIQUIDACION'!$B$11+INCIDENTES!AE5*'BASE LIQUIDACION'!$B$13)) -> 275728.38
A6: TUNJA | B6: =VLOOKUP(A6,'CENTRO DE COSTOS'!A:D,4,FALSE) -> MIGUEL JULIÁN HERNÁNDEZ GUARÍN | C6: =VLOOKUP(A6,'CENTRO DE COSTOS'!A:D,2,FALSE) -> 0004-0008 | D6: 15755 | E6: 2808716 | F6: 50614 | G6: INCIDENTE | H6: BOYACA | I6: SOCOTA | J6: BARRIO SAN CAYETANO SOCOTA | K6: REDEBAN | L6: FO-25-1598991 | M6: 45929.534 | N6: 45930.749 | O6: NO | P6: USUARIO | Q6: COMUNICACION | R6: CANAL DEL COMERCIO | U6: CERRADO | V6: 29/09/2025 SE ESCALA PARA VISITA. LLAMAR ANTES DE VISITAR, CONFIRMAR FALLA Y DATOS | 30/09/2025 SE ESTABLECE COMUNICACIÓN CON LA SEÑORA SANDRA OJEDA BELLO PARA VALIDACIÓN DE LA FALLA AL NÚMERO DE CONTACTO 3143427809 CLIENTE INDICA QUE LA FALLA REPORTADA SE DEBIÓ A UNA FALLA DEL INTERNET DEL COMERCIO EL CUAL YA FUE SOLUCIONADO ADICIONAL INDICA QUE SE COMUNICO EL DÍA DE AYER A LA LÍNEA 018000953344 PARA CANCELAR LA VISITA TECNICA YA QUE EL CORRESPONSAL ESTA FUNCIONANDO CORRECTAMENTE CLIENTE COMPARTE EVIDENCIA EVIDENCIANDO QUE EL CORRESPONSAL BANCARIO SE ENCUENTRA OPERATIVO SE LE INDICA QUE SE PROCEDERÁ CON EL CIERRE DE LA ORDEN DE TRABAJO CLIENTE CONFORME | W6: SOPORTE_TELEFÓNICO | X6: 0 | Y6: TIPO III | Z6: TERRESTRE | AA6: RODRIGUEZ MURCIA YERSON IVAN | AB6: 0 | AC6: 0 | AD6: 0 | AE6: 0 | AF6: =IF(W6="SOPORTE_TELEFÓNICO",'BASE LIQUIDACION'!$B$10,IF(Y6="TIPO I",'BASE LIQUIDACION'!$C$3,IF(Y6="TIPO II",'BASE LIQUIDACION'!$C$4,IF(Y6="TIPO III",'BASE LIQUIDACION'!$C$5,'BASE LIQUIDACION'!$C$7)))) -> 37904.654 | AG6: =IF(W6="SOPORTE_TELEFÓNICO",'BASE LIQUIDACION'!$B$10,(AB6*AF6+AC6*'BASE LIQUIDACION'!$B$12+AD6*'BASE LIQUIDACION'!$B$11+INCIDENTES!AE6*'BASE LIQUIDACION'!$B$13)) -> 37904.654
A7: VILLAVICENCIO | B7: =VLOOKUP(A7,'CENTRO DE COSTOS'!A:D,4,FALSE) -> KEVIN ALEXIS CORZO BUSTOS | C7: =VLOOKUP(A7,'CENTRO DE COSTOS'!A:D,2,FALSE) -> 0004-0007 | D7: 85440 | E7: 2808162 | F7: 79156 | G7: INCIDENTE | H7: CASANARE | I7: VILLANUEVA | J7: BARRIO CENTRO VILLANUEVA 10 | K7: REDEBAN | L7: FO-25-1598679 | M7: 45929.494 | N7: 45930.474 | O7: NO | P7: USUARIO | Q7: LECTOR DE BARRAS | R7: ERROR PAGOS PARCIALES DE FACTURAS | U7: CERRADO | V7: 29/09/2025 SE ESCALA PARA VISITA. LLAMAR ANTES DE VISITAR, CONFIRMAR FALLA Y DATOS SE COMUNICA CON EL SR JUAN 3132227029 PARA REPORTAR PROBLEMA CON DATÁFONO, MANIFIESTA: NO LEE LOS CÓDIGOS DE BARRA, ALUMBRA Y SUENA COMO SI LEYERA, PERO NO FUNCIONA, SE QUEDA AHÍ LEYÉNDOLO HASTA QUE UNO LE DÉ CANCELAR | 30/09/2025 SE REALIZA VISTA AL CB POR SOLICITUD DE LECTORA NO LEE LOS CÓDIGOS, REINICIAMOS EL DISPOSITIVO Y REALIZAMOS LA PRUEBA Y FUNCIONÓ LA LECTORA LEYÓ LOS CÓDIGOS, REALIZÓ PRUEBA DE CONSULTA DE SALDO PARA VERIFICAR EL FUNCIONAMIENTO Y FUE EXITOSA | W7: VISITA_TÉCNICA | X7: SASZZ731 | Y7: TIPO III | Z7: TERRESTRE | AA7: MOLINA CASTRO JAVIER ALBERTO | AB7: 1 | AC7: 0 | AD7: 0 | AE7: 0 | AF7: =IF(W7="SOPORTE_TELEFÓNICO",'BASE LIQUIDACION'!$B$10,IF(Y7="TIPO I",'BASE LIQUIDACION'!$C$3,IF(Y7="TIPO II",'BASE LIQUIDACION'!$C$4,IF(Y7="TIPO III",'BASE LIQUIDACION'!$C$5,'BASE LIQUIDACION'!$C$7)))) -> 275728.38 | AG7: =IF(W7="SOPORTE_TELEFÓNICO",'BASE LIQUIDACION'!$B$10,(AB7*AF7+AC7*'BASE LIQUIDACION'!$B$12+AD7*'BASE LIQUIDACION'!$B$11+INCIDENTES!AE7*'BASE LIQUIDACION'!$B$13)) -> 275728.38
A8: VILLAVICENCIO | B8: =VLOOKUP(A8,'CENTRO DE COSTOS'!A:D,4,FALSE) -> KEVIN ALEXIS CORZO BUSTOS | C8: =VLOOKUP(A8,'CENTRO DE COSTOS'!A:D,2,FALSE) -> 0004-0007 | D8: 50001 | E8: 2806560 | F8: 76214 | G8: INCIDENTE | H8: META | I8: VILLAVICENCIO | J8: BARRIO SERRAMONTE 2 VILLAVICEN | K8: REDEBAN | L8: FO-25-1597610 | M8: 45929.417 | N8: 45930.359 | O8: NO | P8: USUARIO | Q8: COMUNICACION | R8: CANAL DEL COMERCIO | U8: CERRADO | V8: 29/09/2025 SE ESCALA PARA VISITA. LLAMAR ANTES DE VISITAR, CONFIRMAR FALLA Y DATOS | 30/09/2025 SE LLEGA AL COMERCIO SE VÁLIDAD CONEXIONES SE ENTREGA OPERATIVO SIN NOVEDA | W8: VISITA_TÉCNICA | X8: FA0GZ506 | Y8: TIPO I | Z8: TERRESTRE | AA8: ROZO JIMENEZ EDGAR ARMANDO | AB8: 1 | AC8: 0 | AD8: 0 | AE8: 0 | AF8: =IF(W8="SOPORTE_TELEFÓNICO",'BASE LIQUIDACION'!$B$10,IF(Y8="TIPO I",'BASE LIQUIDACION'!$C$3,IF(Y8="TIPO II",'BASE LIQUIDACION'!$C$4,IF(Y8="TIPO III",'BASE LIQUIDACION'!$C$5,'BASE LIQUIDACION'!$C$7)))) -> 65960.474 | AG8: =IF(W8="SOPORTE_TELEFÓNICO",'BASE LIQUIDACION'!$B$10,(AB8*AF8+AC8*'BASE LIQUIDACION'!$B$12+AD8*'BASE LIQUIDACION'!$B$11+INCIDENTES!AE8*'BASE LIQUIDACION'!$B$13)) -> 65960.474
A9: TUNJA | B9: =VLOOKUP(A9,'CENTRO DE COSTOS'!A:D,4,FALSE) -> MIGUEL JULIÁN HERNÁNDEZ GUARÍN | C9: =VLOOKUP(A9,'CENTRO DE COSTOS'!A:D,2,FALSE) -> 0004-0008 | D9: 15806 | E9: 2803981 | F9: 29530 | G9: INCIDENTE | H9: BOYACA | I9: TIBASOSA | J9: BARRIO VDA PATROCINIO TIBASOSA | K9: REDEBAN | L9: FO-25-1594943 | M9: 45928.458 | N9: 45930.588 | O9: NO | P9: USUARIO | Q9: COMUNICACION | R9: CANAL DEL COMERCIO | U9: CERRADO | V9: 28/09/2025 SE ESCALA PARA VISITA. LLAMAR ANTES DE VISITAR, CONFIRMAR FALLA Y DATOS | 29/09/2025 SE ESTABLECE COMUNICACIÓN CON EL CLIENTE AL NÚMERO CELULAR 3118205832 SE CONTACTA A LA SEÑORA SANDRA BONILA , LA SEÑORA SANDRA COMPARTE NÚMERO TELEFONICO DE LA PARSONA ENCARGADA DEL COMERCIO AL NÚMERO 3144341413 SEÑORA YURI PARA CONFIRMAR SI PUEDE ATENDER Y NO HA CERRADO EL COMERCIO EL CUAL LA LLAMADA ES FALLIDA BUZON DE VOZ , SE SEGUIRA HACIENDO GESTIÓN PARA CONFIRMAR VISITA. | 30/09/2025 POR TEMAS DE DESPLAZAMIENTO YA ME ENCUENTRO EN SITIO , ESTOY EN LA ESPERA DE AUTORIZACIÓN DE INGRESO AL PUNTO CLIENTE SE ENCUENTRA VALIDANDO IDENTIDAD DEL TÉCNICO Y SALDO PARA EL INGRESO Y VALIDAR FALLA Y PODER CERRA ORDEN , CLIENTE CONFORME | 30/09/2025 AL REALIZAR GESTION TELÉFONICA NO HUBO COMUNICACIÓN CON EL CLIENTE , SE REALIZA VISITA EN FRIO , SE VALIDA QUE EL CORRESPONSAL ESTA OPERATIVO SE VÁLIDA CONEXIONES SE CAMBIA CABLE PACTH CORD 3 METROS POR MANTENIMIENTO PREVENTIVO DEJANDO PRUEBAS OK SIN TELECARGA | W9: VISITA_TÉCNICA | X9: 9A003382 | Y9: TIPO II | Z9: TERRESTRE | AA9: ALVARADO MORENO CRISTHIAN | AB9: 1 | AC9: 0 | AD9: 0 | AE9: 0 | AF9: =IF(W9="SOPORTE_TELEFÓNICO",'BASE LIQUIDACION'!$B$10,IF(Y9="TIPO I",'BASE LIQUIDACION'!$C$3,IF(Y9="TIPO II",'BASE LIQUIDACION'!$C$4,IF(Y9="TIPO III",'BASE LIQUIDACION'!$C$5,'BASE LIQUIDACION'!$C$7)))) -> 163813.56 | AG9: =IF(W9="SOPORTE_TELEFÓNICO",'BASE LIQUIDACION'!$B$10,(AB9*AF9+AC9*'BASE LIQUIDACION'!$B$12+AD9*'BASE LIQUIDACION'!$B$11+INCIDENTES!AE9*'BASE LIQUIDACION'!$B$13)) -> 163813.56
A10: BUCARAMANGA | B10: =VLOOKUP(A10,'CENTRO DE COSTOS'!A:D,4,FALSE) -> MIGUEL JULIÁN HERNÁNDEZ GUARÍN | C10: =VLOOKUP(A10,'CENTRO DE COSTOS'!A:D,2,FALSE) -> 0004-0008 | D10: 68755 | E10: 2803348 | F10: 64390 | G10: INCIDENTE | H10: SANTANDER | I10: SOCORRO | J10: DISTRICOL CASETA SAN VICTORINO | K10: REDEBAN | L10: FO-25-1594655 | M10: 45927.717 | N10: 45929.48 | O10: NO | P10: USUARIO | Q10: CIERRE | R10: COMERCIO NO REALIZA CIERRE | U10: CERRADO | V10: 28/09/2025 SE ESCALA PARA VISITA. LLAMAR ANTES DE VISITAR, CONFIRMAR FALLA Y DATOS | 29/09/2025 SE ESTABLECE CONTACTO TELEFÓNICOAL NÚMERO 3173031803 CON LA USUARIA LILY SAAVEDRA HOLGUIN IDENTIFICADA CON CÉDULA 37941988 QUIEN NOS INDICA QUE SE COMUNICO AL CAC YA QUE NO PODIA REALIZAR EL CIERRE A LO CUAL NOS INDICA QUE MEDIANTE LA GESTIÓN TELEFÓNICA QUE LE HICIERON YA PUEDE REALIZAR LOS CIERRES Y LOS DUPLICADOS SIN NINGÚN INCONVENIENTE NOS ENVIA COMPROBANTE DE QU ESTA OPERANDO NORMAL A LO CUAL NO REQUIERE EL SERVICIO TÉCNICO AGRADECE POR LA ATENCIÓN PRESTADA | W10: SOPORTE_TELEFÓNICO | X10: 0 | Y10: TIPO III | Z10: TERRESTRE | AA10: REYES RAMIREZ DIEGO ALEXANDER | AB10: 0 | AC10: 0 | AD10: 0 | AE10: 0 | AF10: =IF(W10="SOPORTE_TELEFÓNICO",'BASE LIQUIDACION'!$B$10,IF(Y10="TIPO I",'BASE LIQUIDACION'!$C$3,IF(Y10="TIPO II",'BASE LIQUIDACION'!$C$4,IF(Y10="TIPO III",'BASE LIQUIDACION'!$C$5,'BASE LIQUIDACION'!$C$7)))) -> 37904.654 | AG10: =IF(W10="SOPORTE_TELEFÓNICO",'BASE LIQUIDACION'!$B$10,(AB10*AF10+AC10*'BASE LIQUIDACION'!$B$12+AD10*'BASE LIQUIDACION'!$B$11+INCIDENTES!AE10*'BASE LIQUIDACION'!$B$13)) -> 37904.654
A11: CARTAGENA | B11: =VLOOKUP(A11,'CENTRO DE COSTOS'!A:D,4,FALSE) -> JOSE MAURICIO HERNANDEZ ROJAS | C11: =VLOOKUP(A11,'CENTRO DE COSTOS'!A:D,2,FALSE) -> 0004-0001 | D11: 13052 | E11: 2803201 | F11: 55393 | G11: INCIDENTE | H11: BOLIVAR | I11: ARJONA | J11: PTM ARJONA EL PUNTO DEL COLOR | K11: REDEBAN | L11: FO-25-1593456 | M11: 45927.548 | N11: 45929.531 | O11: NO | P11: USUARIO | Q11: USUARIOS | R11: USUARIOS BLOQUEADOS | U11: CERRADO | V11: 27/09/2025 SE ESCALA PARA VISITA. LLAMAR ANTES DE VISITAR, CONFIRMAR FALLA Y DATOS | 29/09/2025 SE RESTAURA USUARIO SUPERVISOR POR BLOQUEO , SE REALIZAN PRUEBAS Y TODO QUEDA OK | W11: VISITA_TÉCNICA | X11: TRFZZ018 | Y11: TIPO II | Z11: TERRESTRE | AA11: MARTINEZ SALGUEDO ANDRES AUGUSTO | AB11: 1 | AC11: 0 | AD11: 0 | AE11: 0 | AF11: =IF(W11="SOPORTE_TELEFÓNICO",'BASE LIQUIDACION'!$B$10,IF(Y11="TIPO I",'BASE LIQUIDACION'!$C$3,IF(Y11="TIPO II",'BASE LIQUIDACION'!$C$4,IF(Y11="TIPO III",'BASE LIQUIDACION'!$C$5,'BASE LIQUIDACION'!$C$7)))) -> 163813.56 | AG11: =IF(W11="SOPORTE_TELEFÓNICO",'BASE LIQUIDACION'!$B$10,(AB11*AF11+AC11*'BASE LIQUIDACION'!$B$12+AD11*'BASE LIQUIDACION'!$B$11+INCIDENTES!AE11*'BASE LIQUIDACION'!$B$13)) -> 163813.56
A12: MEDELLIN | B12: =VLOOKUP(A12,'CENTRO DE COSTOS'!A:D,4,FALSE) -> JUAN SEBASTIÁN RÍOS CASTRILLÓN | C12: =VLOOKUP(A12,'CENTRO DE COSTOS'!A:D,2,FALSE) -> 0004-0005 | D12: 5615 | E12: 2803120 | F12: 20701 | G12: INCIDENTE | H12: ANTIOQUIA | I12: RIONEGRO | J12: COMCARD SAN ANTONIO TELESAN | K12: REDEBAN | L12: FO-25-1593172 | M12: 45927.492 | N12: 45929.487 | O12: NO | P12: USUARIO | Q12: MANTENIMIENTO | R12: MANTENIMIENTO GENERAL | U12: CERRADO | V12: 27/09/2025 SE ESCALA PARA VISITA. LLAMAR ANTES DE VISITAR, CONFIRMAR FALLA Y DATOS | 28/09/2025 SE COMUNICA CON CLIENTE AL 3233282900 E INFORMA QUE EL DÍA DE HOY NO ABRE, SE APLAZA VISITA | 29/09/2025 SE LLAMA AL CLIENTE Y NOS INDICA QUE EL DATÁFONO YA FUNCIKNA CORRECTAMENTE | W12: SOPORTE_TELEFÓNICO | X12: 0 | Y12: TIPO II | Z12: TERRESTRE | AA12: CARDONA MOLINA BROLIN STIVEN | AB12: 0 | AC12: 0 | AD12: 0 | AE12: 0 | AF12: =IF(W12="SOPORTE_TELEFÓNICO",'BASE LIQUIDACION'!$B$10,IF(Y12="TIPO I",'BASE LIQUIDACION'!$C$3,IF(Y12="TIPO II",'BASE LIQUIDACION'!$C$4,IF(Y12="TIPO III",'BASE LIQUIDACION'!$C$5,'BASE LIQUIDACION'!$C$7)))) -> 37904.654 | AG12: =IF(W12="SOPORTE_TELEFÓNICO",'BASE LIQUIDACION'!$B$10,(AB12*AF12+AC12*'BASE LIQUIDACION'!$B$12+AD12*'BASE LIQUIDACION'!$B$11+INCIDENTES!AE12*'BASE LIQUIDACION'!$B$13)) -> 37904.654
A13: MONTERIA | B13: =VLOOKUP(A13,'CENTRO DE COSTOS'!A:D,4,FALSE) -> JOSE MAURICIO HERNANDEZ ROJAS | C13: =VLOOKUP(A13,'CENTRO DE COSTOS'!A:D,2,FALSE) -> 0004-0001 | D13: 23660 | E13: 2802689 | F13: 81679 | G13: INCIDENTE | H13: CORDOBA | I13: SAHAGUN | J13: DISTRICOL EL ROSARIO | K13: REDEBAN | L13: FO-25-1592359 | M13: 45927.401 | N13: 45929.387 | O13: NO | P13: USUARIO | Q13: COMUNICACION | R13: CANAL DEL COMERCIO | U13: CERRADO | V13: 27/09/2025 SE ESCALA PARA VISITA. LLAMAR ANTES DE VISITAR, CONFIRMAR FALLA Y DATOS | 29/09/2025 SE COMUNICA CON EL NÚMERO 3215382774 LUISA SUAREZ, INDICA QUE EL CB SE ENCUENTRA FUNCIONANDO CORRECTAMENTE. | W13: SOPORTE_TELEFÓNICO | X13: 0 | Y13: TIPO II | Z13: TERRESTRE | AA13: SANTOS GUZMAN CHRISTIAN FELIPE | AB13: 0 | AC13: 0 | AD13: 0 | AE13: 0 | AF13: =IF(W13="SOPORTE_TELEFÓNICO",'BASE LIQUIDACION'!$B$10,IF(Y13="TIPO I",'BASE LIQUIDACION'!$C$3,IF(Y13="TIPO II",'BASE LIQUIDACION'!$C$4,IF(Y13="TIPO III",'BASE LIQUIDACION'!$C$5,'BASE LIQUIDACION'!$C$7)))) -> 37904.654 | AG13: =IF(W13="SOPORTE_TELEFÓNICO",'BASE LIQUIDACION'!$B$10,(AB13*AF13+AC13*'BASE LIQUIDACION'!$B$12+AD13*'BASE LIQUIDACION'!$B$11+INCIDENTES!AE13*'BASE LIQUIDACION'!$B$13)) -> 37904.654
A14: BARRANQUILLA | B14: =VLOOKUP(A14,'CENTRO DE COSTOS'!A:D,4,FALSE) -> JOSE MAURICIO HERNANDEZ ROJAS | C14: =VLOOKUP(A14,'CENTRO DE COSTOS'!A:D,2,FALSE) -> 0004-0001 | D14: 8137 | E14: 2802873 | F14: 50862 | G14: INCIDENTE | H14: ATLANTICO | I14: CAMPO DE LA CRUZ | J14: PTM CAMPO DE LA CRUZ GRANERO E | K14: REDEBAN | L14: FO-25-1592365 | M14: 45927.398 | N14: 45929.385 | O14: NO | P14: USUARIO | Q14: COMUNICACION | R14: CANAL DEL COMERCIO | U14: CERRADO | V14: 27/09/2025 SE ESCALA PARA VISITA. LLAMAR ANTES DE VISITAR, CONFIRMAR FALLA Y DATOS | 29/09/2025 COMERCIO NO ATENDÍA DOMINGO Y HOY LUNES SE DESPLAZA COLABORADOR A SITIO, PERO DEBIDO A LA BAJA FRECUENCIA DE SALIDA DE BUSES A MUNICIPIO, SE ATENDERÁ A LAS 11:00M AM APROX | 29/09/2025 SE REALIZA LLAMADA AL CLIENTE EL CUAL NOS DICE QUE YA TIENE INTERNET, QUE DESDE EL SÁBADO EN LA TARDE ESTA LABORANDO NORMALMENTE, POSIBLEMENTE FALLAS DE CONEXIÓN POR SU OPERADOR DE DATOS ,CB OPERATIVO. | W14: SOPORTE_TELEFÓNICO | X14: 0 | Y14: TIPO II | Z14: TERRESTRE | AA14: PORRAS CASTRO DARLON NASCK | AB14: 0 | AC14: 0 | AD14: 0 | AE14: 0 | AF14: =IF(W14="SOPORTE_TELEFÓNICO",'BASE LIQUIDACION'!$B$10,IF(Y14="TIPO I",'BASE LIQUIDACION'!$C$3,IF(Y14="TIPO II",'BASE LIQUIDACION'!$C$4,IF(Y14="TIPO III",'BASE LIQUIDACION'!$C$5,'BASE LIQUIDACION'!$C$7)))) -> 37904.654 | AG14: =IF(W14="SOPORTE_TELEFÓNICO",'BASE LIQUIDACION'!$B$10,(AB14*AF14+AC14*'BASE LIQUIDACION'!$B$12+AD14*'BASE LIQUIDACION'!$B$11+INCIDENTES!AE14*'BASE LIQUIDACION'!$B$13)) -> 37904.654
A15: PASTO | B15: =VLOOKUP(A15,'CENTRO DE COSTOS'!A:D,4,FALSE) -> DIEGO FERNANDO HENAO CARDONA | C15: =VLOOKUP(A15,'CENTRO DE COSTOS'!A:D,2,FALSE) -> 0004-0003 | D15: 52490 | E15: 2802099 | F15: 41691 | G15: INCIDENTE | H15: NARIÑO | I15: OLAYA HERRERA | J15: BARRIO CENTRO OLAYA HERRERA 2 | K15: REDEBAN | L15: FO-25-1591693 | M15: 45927.333 | N15: 45930.573 | O15: NO | P15: USUARIO | Q15: CIERRE | R15: COMERCIO NO REALIZA CIERRE | U15: CERRADO | V15: 27/09/2025 EN COMUNICACIÓN CON LA SRA : VICENTA SEGURA PERLAZA AL NÚMERO 3214751285 NOS INFORMA QUE LA FALLA QUE TIENE CON EL DATAFONO ES CON LOS CIERRES, CONFIRMA DATOS E INDICA QUE LA RED ES REDEBAN, SE ESCALA PARA VISITA | 30/09/2025 SE REALIZA VALIDACION CON EL CLIENTE Y SE ENCUENTRA QUE USUARIO NO REALIZABA EL CIERRE GENERAL, SE LE EXPLICA AL CLIENTE LA FORMA CORRECTA DE GENERAR LOS CIERRES, CLIENTE REALIZA EL CIERRE Y SE LE EEXPLICA QUE DESPUES DE REALIZAR EL CIERRE GENERAL DEBE DARLE LA TECLA VERDE PARA QUE EL DATAFONO BORRE LO QUE TENGA EN MEMORIA. | W15: SOPORTE_TELEFÓNICO | X15: 0 | Y15: TIPO IV ESPECIAL | Z15: FLUVIAL | AA15: HENAO CARDONA DIEGO FERNANDO | AB15: 0 | AC15: 0 | AD15: 0 | AE15: 0 | AF15: =IF(W15="SOPORTE_TELEFÓNICO",'BASE LIQUIDACION'!$B$10,IF(Y15="TIPO I",'BASE LIQUIDACION'!$C$3,IF(Y15="TIPO II",'BASE LIQUIDACION'!$C$4,IF(Y15="TIPO III",'BASE LIQUIDACION'!$C$5,'BASE LIQUIDACION'!$C$7)))) -> 37904.654 | AG15: =IF(W15="SOPORTE_TELEFÓNICO",'BASE LIQUIDACION'!$B$10,(AB15*AF15+AC15*'BASE LIQUIDACION'!$B$12+AD15*'BASE LIQUIDACION'!$B$11+INCIDENTES!AE15*'BASE LIQUIDACION'!$B$13)) -> 37904.654
A16: PEREIRA | B16: =VLOOKUP(A16,'CENTRO DE COSTOS'!A:D,4,FALSE) -> DIEGO FERNANDO HENAO CARDONA | C16: =VLOOKUP(A16,'CENTRO DE COSTOS'!A:D,2,FALSE) -> 0004-0002 | D16: 76895 | E16: 2802027 | F16: 77269 | G16: INCIDENTE | H16: VALLE DEL CAUCA | I16: ZARZAL | J16: BARRIO LOS LAGOS SEGUNDA ETAPA | K16: REDEBAN | L16: FO-25-1591709 | M16: 45927.333 | N16: 45929.471 | O16: NO | P16: USUARIO | Q16: COMUNICACION | R16: CANAL DEL COMERCIO | U16: CERRADO | V16: 27/09/2025 SE INTENTA COMUNICACIÓN CON LA SRA FLOR MAYERLY CAICEDO SOLÍS A LOS NÚMEROS 3225098691-3147598029 PARA CONFIRMAR DATOS Y FALLA PERO NO HAY CONTAQCTO, SE ESCALA L COORDINADOR DE ZONA PARA VALIDAR EN SITIO | 29/09/2025 EN COMUNICACIÓN CON LA SEÑORA MAYERLY CAICEDO AL NÚMERO 3147598029 CONFIRMA QUE DATÁFONO SE ENCUENTRA TRABAJANDO SIN NOVEDAD | W16: SOPORTE_TELEFÓNICO | X16: 0 | Y16: TIPO III | Z16: TERRESTRE | AA16: LOAIZA LOPEZ JHON FREDDY | AB16: 0 | AC16: 0 | AD16: 0 | AE16: 0 | AF16: =IF(W16="SOPORTE_TELEFÓNICO",'BASE LIQUIDACION'!$B$10,IF(Y16="TIPO I",'BASE LIQUIDACION'!$C$3,IF(Y16="TIPO II",'BASE LIQUIDACION'!$C$4,IF(Y16="TIPO III",'BASE LIQUIDACION'!$C$5,'BASE LIQUIDACION'!$C$7)))) -> 37904.654 | AG16: =IF(W16="SOPORTE_TELEFÓNICO",'BASE LIQUIDACION'!$B$10,(AB16*AF16+AC16*'BASE LIQUIDACION'!$B$12+AD16*'BASE LIQUIDACION'!$B$11+INCIDENTES!AE16*'BASE LIQUIDACION'!$B$13)) -> 37904.654
A17: BARRANQUILLA | B17: =VLOOKUP(A17,'CENTRO DE COSTOS'!A:D,4,FALSE) -> JOSE MAURICIO HERNANDEZ ROJAS | C17: =VLOOKUP(A17,'CENTRO DE COSTOS'!A:D,2,FALSE) -> 0004-0001 | D17: 8078 | E17: 2801742 | F17: 62375 | G17: INCIDENTE | H17: ATLANTICO | I17: BARANOA | J17: BARRIO BARANOA BARANOA 3 | K17: REDEBAN | L17: FO-25-1590888 | M17: 45926.702 | N17: 45927.719 | O17: NO | P17: USUARIO | Q17: MANTENIMIENTO | R17: MANTENIMIENTO GENERAL | U17: CERRADO | V17: 26/09/2025 SE ESCALA PARA VISITA. LLAMAR ANTES DE VISITAR, CONFIRMAR FALLA Y DATOS | 27/09/2025 SE REALIZA VISITA SE PROCEDE A VALIDAR DATAFONO Y ESTÁ OK, SE LE INDICA AL CLIENTE EL PROCESO DE LA CARGA DE LA BATERÍA PARA QUE TENGA EN CUENTA CUANDO ESTÉ BAJA, SE REALIZA ACOMPAÑAMIENTO QUE LA BATERÍA AGARRE CARGA, SE HACEN PRUEBAS Y TODO OK | W17: VISITA_TÉCNICA | X17: HA00M871 | Y17: TIPO II | Z17: TERRESTRE | AA17: PORRAS CASTRO DARLON NASCK | AB17: 1 | AC17: 0 | AD17: 0 | AE17: 0 | AF17: =IF(W17="SOPORTE_TELEFÓNICO",'BASE LIQUIDACION'!$B$10,IF(Y17="TIPO I",'BASE LIQUIDACION'!$C$3,IF(Y17="TIPO II",'BASE LIQUIDACION'!$C$4,IF(Y17="TIPO III",'BASE LIQUIDACION'!$C$5,'BASE LIQUIDACION'!$C$7)))) -> 163813.56 | AG17: =IF(W17="SOPORTE_TELEFÓNICO",'BASE LIQUIDACION'!$B$10,(AB17*AF17+AC17*'BASE LIQUIDACION'!$B$12+AD17*'BASE LIQUIDACION'!$B$11+INCIDENTES!AE17*'BASE LIQUIDACION'!$B$13)) -> 163813.56
A18: MEDELLIN | B18: =VLOOKUP(A18,'CENTRO DE COSTOS'!A:D,4,FALSE) -> JUAN SEBASTIÁN RÍOS CASTRILLÓN | C18: =VLOOKUP(A18,'CENTRO DE COSTOS'!A:D,2,FALSE) -> 0004-0005 | D18: 5001 | E18: 2801003 | F18: 70017 | G18: INCIDENTE | H18: ANTIOQUIA | I18: MEDELLIN | J18: PTM MEDELLIN SALSAMENTARIA DO | K18: REDEBAN | L18: FO-25-1589979 | M18: 45926.62 | N18: 45927.524 | O18: NO | P18: USUARIO | Q18: MANTENIMIENTO | R18: MANTENIMIENTO GENERAL | U18: CERRADO | V18: 26/09/2025 SE ESCALA PARA VISITA. LLAMAR ANTES DE VISITAR, CONFIRMAR FALLA Y DATOS | 27/09/2025 SE INICIALIZA DE NUEVO EL CB YA QUE MOSTRABA EL NOMBRE ANTERIOR, SE ACTUALIZA A VERSIÓN 9.90, SE REALIZAN PRUEBAS Y QUEDA CON EL NUEVO NOMBRE, PRUEBAS OK | W18: VISITA_TÉCNICA | X18: UV001523 | Y18: TIPO I | Z18: TERRESTRE | AA18: CARDONA MOLINA BROLIN STIVEN | AB18: 1 | AC18: 0 | AD18: 0 | AE18: 0 | AF18: =IF(W18="SOPORTE_TELEFÓNICO",'BASE LIQUIDACION'!$B$10,IF(Y18="TIPO I",'BASE LIQUIDACION'!$C$3,IF(Y18="TIPO II",'BASE LIQUIDACION'!$C$4,IF(Y18="TIPO III",'BASE LIQUIDACION'!$C$5,'BASE LIQUIDACION'!$C$7)))) -> 65960.474 | AG18: =IF(W18="SOPORTE_TELEFÓNICO",'BASE LIQUIDACION'!$B$10,(AB18*AF18+AC18*'BASE LIQUIDACION'!$B$12+AD18*'BASE LIQUIDACION'!$B$11+INCIDENTES!AE18*'BASE LIQUIDACION'!$B$13)) -> 65960.474
A19: NEIVA | B19: =VLOOKUP(A19,'CENTRO DE COSTOS'!A:D,4,FALSE) -> KEVIN ALEXIS CORZO BUSTOS | C19: =VLOOKUP(A19,'CENTRO DE COSTOS'!A:D,2,FALSE) -> 0004-0007 | D19: 41551 | E19: 2800088 | F19: 80538 | G19: INCIDENTE | H19: HUILA | I19: PITALITO | J19: BARRIO AGUA BLANCA PITALITO 4 | K19: REDEBAN | L19: FO-25-1589312 | M19: 45926.54 | N19: 45929.507 | O19: NO | P19: ENTIDAD | Q19: ERROR DE TRANSACCIONES | R19: TRANSACCION NO PERMITIDA | U19: CERRADO | V19: 26/09/2025 SE INTENTA COMUNICACIÓN CON LA SRA YESICA TRUJILLO PERDOMO AL NÚMERO 3144434059 PARA CONFRIMAR DATOS Y FALLA PERO NO HAY CONTACTO, SE ESCALA AL COORDINADOR DE ZONA PARA VALIDAR EN SITIO | 29/09/2025 EN COMUNICACIÓN CON EL CLIENTE VIA TELÉFONICA ,LA SEÑORA YESICA TRUJILLO, AL NÚMERO +57 314 4434059, NOS INDICA QUE EL EQUIPO SE ENCUENTRA FUNCIONANDO CORRECTAMENTE YA QUE EL PROBLEMA DE TRANSACCIONES SE DEBIO A UNA CAÍDA DE LA PLATAFORMA DE BANCOLOMBIA LA CUAL YA SE RESTABLECIÓ Y FUNCIONA DE FORMA CORRECTA , CB OPERATIVO M. | W19: SOPORTE_TELEFÓNICO | X19: 0 | Y19: TIPO III | Z19: TERRESTRE | AA19: DEVIA REINOSO JUAN CARLOS | AB19: 0 | AC19: 0 | AD19: 0 | AE19: 0 | AF19: =IF(W19="SOPORTE_TELEFÓNICO",'BASE LIQUIDACION'!$B$10,IF(Y19="TIPO I",'BASE LIQUIDACION'!$C$3,IF(Y19="TIPO II",'BASE LIQUIDACION'!$C$4,IF(Y19="TIPO III",'BASE LIQUIDACION'!$C$5,'BASE LIQUIDACION'!$C$7)))) -> 37904.654 | AG19: =IF(W19="SOPORTE_TELEFÓNICO",'BASE LIQUIDACION'!$B$10,(AB19*AF19+AC19*'BASE LIQUIDACION'!$B$12+AD19*'BASE LIQUIDACION'!$B$11+INCIDENTES!AE19*'BASE LIQUIDACION'!$B$13)) -> 37904.654
A20: VILLAVICENCIO | B20: =VLOOKUP(A20,'CENTRO DE COSTOS'!A:D,4,FALSE) -> KEVIN ALEXIS CORZO BUSTOS | C20: =VLOOKUP(A20,'CENTRO DE COSTOS'!A:D,2,FALSE) -> 0004-0007 | D20: 50001 | E20: 2800046 | F20: 80632 | G20: INCIDENTE | H20: META | I20: VILLAVICENCIO | J20: BARRIO PINILLA VILLAVICENCIO 2 | K20: REDEBAN | L20: FO-25-1589002 | M20: 45926.518 | N20: 45926.737 | O20: NO | P20: USUARIO | Q20: NO ENCIENDE | R20: CONEXIONES DE COMERCIO | U20: CERRADO | V20: 26/09/2025 SE ESCALA PARA VISITA. LLAMAR ANTES DE VISITAR, CONFIRMAR FALLA Y DATOS | 26/09/2025 SE LLEGA AL COMERCIO E INDICA QUE SE ENCUENTRA FUNCIONANDO SE HABÍA QUEDO BLOQUEADO | W20: VISITA_TÉCNICA | X20: V6ZZZ816 | Y20: TIPO I | Z20: TERRESTRE | AA20: ROZO JIMENEZ EDGAR ARMANDO | AB20: 1 | AC20: 0 | AD20: 0 | AE20: 0 | AF20: =IF(W20="SOPORTE_TELEFÓNICO",'BASE LIQUIDACION'!$B$10,IF(Y20="TIPO I",'BASE LIQUIDACION'!$C$3,IF(Y20="TIPO II",'BASE LIQUIDACION'!$C$4,IF(Y20="TIPO III",'BASE LIQUIDACION'!$C$5,'BASE LIQUIDACION'!$C$7)))) -> 65960.474 | AG20: =IF(W20="SOPORTE_TELEFÓNICO",'BASE LIQUIDACION'!$B$10,(AB20*AF20+AC20*'BASE LIQUIDACION'!$B$12+AD20*'BASE LIQUIDACION'!$B$11+INCIDENTES!AE20*'BASE LIQUIDACION'!$B$13)) -> 65960.474
A21: CUCUTA | B21: =VLOOKUP(A21,'CENTRO DE COSTOS'!A:D,4,FALSE) -> MIGUEL JULIÁN HERNÁNDEZ GUARÍN | C21: =VLOOKUP(A21,'CENTRO DE COSTOS'!A:D,2,FALSE) -> 0004-0008 | D21: 54001 | E21: 2799185 | F21: 81650 | G21: INCIDENTE | H21: NORTE DE SANTANDER | I21: CUCUTA | J21: DISTRICOL MARCELAS CHIP STORE | K21: REDEBAN | L21: FO-25-1588261 | M21: 45926.463 | N21: 45926.724 | O21: NO | P21: USUARIO | Q21: COMUNICACION | R21: CONEXIONES DE COMERCIO | U21: CERRADO | V21: 26/09/2025 SE ESCALA PARA VISITA. LLAMAR ANTES DE VISITAR, CONFIRMAR FALLA Y DATOS | 26/09/2025 SE COMUNICA CON LA CLIENTE MARCELA SANTOS AL #3222295656, NOS INFORMA QUE EL PROBLEMA YA SE SOLUCIONO YA QUE ERA UNA FALLA INTERNO DEL INTERNET | W21: SOPORTE_TELEFÓNICO | X21: 0 | Y21: TIPO I | Z21: TERRESTRE | AA21: NARANJO AFANADOR RUBEN JESUS | AB21: 0 | AC21: 0 | AD21: 0 | AE21: 0 | AF21: =IF(W21="SOPORTE_TELEFÓNICO",'BASE LIQUIDACION'!$B$10,IF(Y21="TIPO I",'BASE LIQUIDACION'!$C$3,IF(Y21="TIPO II",'BASE LIQUIDACION'!$C$4,IF(Y21="TIPO III",'BASE LIQUIDACION'!$C$5,'BASE LIQUIDACION'!$C$7)))) -> 37904.654 | AG21: =IF(W21="SOPORTE_TELEFÓNICO",'BASE LIQUIDACION'!$B$10,(AB21*AF21+AC21*'BASE LIQUIDACION'!$B$12+AD21*'BASE LIQUIDACION'!$B$11+INCIDENTES!AE21*'BASE LIQUIDACION'!$B$13)) -> 37904.654
A22: MONTERIA | B22: =VLOOKUP(A22,'CENTRO DE COSTOS'!A:D,4,FALSE) -> JOSE MAURICIO HERNANDEZ ROJAS | C22: =VLOOKUP(A22,'CENTRO DE COSTOS'!A:D,2,FALSE) -> 0004-0001 | D22: 23079 | E22: 2797827 | F22: 27499 | G22: INCIDENTE | H22: CORDOBA | I22: BUENAVISTA | J22: DISTRICOL PANADERIA Y HELADERI | K22: REDEBAN | L22: FO-25-1587162 | M22: 45926.382 | N22: 45927.558 | O22: NO | P22: USUARIO | Q22: LECTOR DE TARJETAS | R22: OBSTRUCCION DEL LECTOR | U22: CERRADO | V22: 26/09/2025 SE ESCALA PARA VISITA. LLAMAR ANTES DE VISITAR, CONFIRMAR FALLA Y DATOS | 27/09/2025 SE VISITA SITIO, SE REALIZA LIMPIEZA DE LECTOR DE TARJETAS EN PINPAD YA QUE SE ENCONTRABA OBSTRUIDO. SE REALIZAN PRUEBAS EXITOSAS | W22: VISITA_TÉCNICA | X22: 99DZZ458 | Y22: TIPO II | Z22: TERRESTRE | AA22: COGOLLO VERTEL EDER LUIS | AB22: 1 | AC22: 0 | AD22: 0 | AE22: 0 | AF22: =IF(W22="SOPORTE_TELEFÓNICO",'BASE LIQUIDACION'!$B$10,IF(Y22="TIPO I",'BASE LIQUIDACION'!$C$3,IF(Y22="TIPO II",'BASE LIQUIDACION'!$C$4,IF(Y22="TIPO III",'BASE LIQUIDACION'!$C$5,'BASE LIQUIDACION'!$C$7)))) -> 163813.56 | AG22: =IF(W22="SOPORTE_TELEFÓNICO",'BASE LIQUIDACION'!$B$10,(AB22*AF22+AC22*'BASE LIQUIDACION'!$B$12+AD22*'BASE LIQUIDACION'!$B$11+INCIDENTES!AE22*'BASE LIQUIDACION'!$B$13)) -> 163813.56
A23: MEDELLIN | B23: =VLOOKUP(A23,'CENTRO DE COSTOS'!A:D,4,FALSE) -> JUAN SEBASTIÁN RÍOS CASTRILLÓN | C23: =VLOOKUP(A23,'CENTRO DE COSTOS'!A:D,2,FALSE) -> 0004-0005 | D23: 5001 | E23: 2797495 | F23: 26225 | G23: INCIDENTE | H23: ANTIOQUIA | I23: MEDELLIN | J23: COMCARD MED MINUCENTER | K23: REDEBAN | L23: FO-25-1586779 | M23: 45926.358 | N23: 45926.548 | O23: NO | P23: USUARIO | Q23: MANTENIMIENTO | R23: MANTENIMIENTO GENERAL | U23: CERRADO | V23: 26/09/2025 SE ESCALA PARA VISITA. LLAMAR ANTES DE VISITAR, CONFIRMAR FALLA Y DATOS | 26/09/2025 SE REALIZA LIMPIEZA DEL TECLADO DEL DATÁFONO Y QUEDA FUNCIONANDO, SE REINICIA Y SE REALIZAN PRUEBAS, TODO OK | W23: VISITA_TÉCNICA | X23: 99991001 | Y23: TIPO I | Z23: TERRESTRE | AA23: CARDONA MOLINA BROLIN STIVEN | AB23: 1 | AC23: 0 | AD23: 0 | AE23: 0 | AF23: =IF(W23="SOPORTE_TELEFÓNICO",'BASE LIQUIDACION'!$B$10,IF(Y23="TIPO I",'BASE LIQUIDACION'!$C$3,IF(Y23="TIPO II",'BASE LIQUIDACION'!$C$4,IF(Y23="TIPO III",'BASE LIQUIDACION'!$C$5,'BASE LIQUIDACION'!$C$7)))) -> 65960.474 | AG23: =IF(W23="SOPORTE_TELEFÓNICO",'BASE LIQUIDACION'!$B$10,(AB23*AF23+AC23*'BASE LIQUIDACION'!$B$12+AD23*'BASE LIQUIDACION'!$B$11+INCIDENTES!AE23*'BASE LIQUIDACION'!$B$13)) -> 65960.474
A24: BOGOTA | B24: =VLOOKUP(A24,'CENTRO DE COSTOS'!A:D,4,FALSE) -> WILLIAM ASDRUBAL ROZO ROZO | C24: =VLOOKUP(A24,'CENTRO DE COSTOS'!A:D,2,FALSE) -> 0004-0004 | D24: 11001 | E24: 2797427 | F24: 64118 | G24: INCIDENTE | H24: CUNDINAMARCA | I24: BOGOTA | J24: BARRIO BOSA LAURELES BOGOTA 2 | K24: REDEBAN | L24: FO-25-1586787 | M24: 45926.343 | N24: 45926.687 | O24: NO | P24: USUARIO | Q24: USUARIOS | R24: CREACION DE USUARIOS | U24: CERRADO | V24: 26/09/2025 SE ESCALA PARA VISITA. LLAMAR ANTES DE VISITAR, CONFIRMAR FALLA Y DATOS | 26/09/2025 SE REALIZA CAMBIO DE CLAVE SUPERVISOR ( CIERRES Y DUPLICADO) PRUEBA OK | W24: VISITA_TÉCNICA | X24: OA00O731 | Y24: TIPO I | Z24: TERRESTRE | AA24: ORTIZ MARTINEZ STIVEN | AB24: 1 | AC24: 0 | AD24: 0 | AE24: 0 | AF24: =IF(W24="SOPORTE_TELEFÓNICO",'BASE LIQUIDACION'!$B$10,IF(Y24="TIPO I",'BASE LIQUIDACION'!$C$3,IF(Y24="TIPO II",'BASE LIQUIDACION'!$C$4,IF(Y24="TIPO III",'BASE LIQUIDACION'!$C$5,'BASE LIQUIDACION'!$C$7)))) -> 65960.474 | AG24: =IF(W24="SOPORTE_TELEFÓNICO",'BASE LIQUIDACION'!$B$10,(AB24*AF24+AC24*'BASE LIQUIDACION'!$B$12+AD24*'BASE LIQUIDACION'!$B$11+INCIDENTES!AE24*'BASE LIQUIDACION'!$B$13)) -> 65960.474
A25: MEDELLIN | B25: =VLOOKUP(A25,'CENTRO DE COSTOS'!A:D,4,FALSE) -> JUAN SEBASTIÁN RÍOS CASTRILLÓN | C25: =VLOOKUP(A25,'CENTRO DE COSTOS'!A:D,2,FALSE) -> 0004-0005 | D25: 5001 | E25: 2795568 | F25: 80717 | G25: INCIDENTE | H25: ANTIOQUIA | I25: MEDELLIN | J25: DISTRICOL VARIEDADES Y DETALLE | K25: REDEBAN | L25: FO-25-1585334 | M25: 45925.671 | N25: 45926.527 | O25: NO | P25: USUARIO | Q25: MANTENIMIENTO | R25: MANTENIMIENTO GENERAL | U25: CERRADO | V25: 25/09/2025 SE ESCALA PARA VISITA. LLAMAR ANTES DE VISITAR, CONFIRMAR FALLA Y DATOS | 26/09/2025 SE LLAMA AL USUARIO PARA CONFIRMAR VISITA Y NOS COMENTA QUE RETIRÓ EL ROLLO Y REALIZÓ UNA LIMPIEZA Y LA IMPRESORA DEL DATÁFONO VOLVIO A FUNCIONAR CORRECTAMENTE | W25: SOPORTE_TELEFÓNICO | X25: 0 | Y25: TIPO I | Z25: TERRESTRE | AA25: CARDONA MOLINA BROLIN STIVEN | AB25: 0 | AC25: 0 | AD25: 0 | AE25: 0 | AF25: =IF(W25="SOPORTE_TELEFÓNICO",'BASE LIQUIDACION'!$B$10,IF(Y25="TIPO I",'BASE LIQUIDACION'!$C$3,IF(Y25="TIPO II",'BASE LIQUIDACION'!$C$4,IF(Y25="TIPO III",'BASE LIQUIDACION'!$C$5,'BASE LIQUIDACION'!$C$7)))) -> 37904.654 | AG25: =IF(W25="SOPORTE_TELEFÓNICO",'BASE LIQUIDACION'!$B$10,(AB25*AF25+AC25*'BASE LIQUIDACION'!$B$12+AD25*'BASE LIQUIDACION'!$B$11+INCIDENTES!AE25*'BASE LIQUIDACION'!$B$13)) -> 37904.654
A26: IBAGUE | B26: =VLOOKUP(A26,'CENTRO DE COSTOS'!A:D,4,FALSE) -> KEVIN ALEXIS CORZO BUSTOS | C26: =VLOOKUP(A26,'CENTRO DE COSTOS'!A:D,2,FALSE) -> 0004-0007 | D26: 73001 | E26: 2795532 | F26: 80945 | G26: INCIDENTE | H26: TOLIMA | I26: IBAGUE | J26: BARRIO LA POLA IBAGUE 7 | K26: REDEBAN | L26: FO-25-1585139 | M26: 45925.665 | N26: 45926.409 | O26: NO | P26: USUARIO | Q26: MANTENIMIENTO | R26: MANTENIMIENTO GENERAL | U26: CERRADO | V26: 25/09/2025 SE ESCALA PARA VISITA. LLAMAR ANTES DE VISITAR, CONFIRMAR FALLA Y DATOS | 26/09/2025 SE LE EXPLICA AL SEÑOR JHONY QUIMBAYO, DE CÓMO APAGAR CORRECTAMENTE EL EQUIPO PARA QUE NO TENGA PROBLEMAS CON LA IMPRESORA DE RECIBOS. SE HACEN PRUEBAS DE TRANSACCIONES TODO OK Y SE VERIFICA LA IMPRESORA. | W26: VISITA_TÉCNICA | X26: FIZZZ331 | Y26: TIPO I | Z26: TERRESTRE | AA26: VARGAS HERRERA JHON JAIRO | AB26: 1 | AC26: 0 | AD26: 0 | AE26: 0 | AF26: =IF(W26="SOPORTE_TELEFÓNICO",'BASE LIQUIDACION'!$B$10,IF(Y26="TIPO I",'BASE LIQUIDACION'!$C$3,IF(Y26="TIPO II",'BASE LIQUIDACION'!$C$4,IF(Y26="TIPO III",'BASE LIQUIDACION'!$C$5,'BASE LIQUIDACION'!$C$7)))) -> 65960.474 | AG26: =IF(W26="SOPORTE_TELEFÓNICO",'BASE LIQUIDACION'!$B$10,(AB26*AF26+AC26*'BASE LIQUIDACION'!$B$12+AD26*'BASE LIQUIDACION'!$B$11+INCIDENTES!AE26*'BASE LIQUIDACION'!$B$13)) -> 65960.474
A27: BOGOTA | B27: =VLOOKUP(A27,'CENTRO DE COSTOS'!A:D,4,FALSE) -> WILLIAM ASDRUBAL ROZO ROZO | C27: =VLOOKUP(A27,'CENTRO DE COSTOS'!A:D,2,FALSE) -> 0004-0004 | D27: 25754 | E27: 2793909 | F27: 80698 | G27: INCIDENTE | H27: CUNDINAMARCA | I27: SOACHA | J27: BARRIO SAN HUMBERTO SOACHA 3 | K27: REDEBAN | L27: FO-25-1583521 | M27: 45925.507 | N27: 45925.69 | O27: NO | P27: USUARIO | Q27: CIERRE | R27: COMERCIO NO REALIZA CIERRE | U27: CERRADO | V27: 25/09/2025 SE ESCALA PARA VISITA. LLAMAR ANTES DE VISITAR, CONFIRMAR FALLA Y DATOS | 25/09/2025 DURANTE LA VISITA TECNICA ENCONTRAMOS QUE EL DATÁFONO NO LE PERMITE REALIZAR EL CIERRE POR ACUMULACIÓN DE TRANSACCIONES SE REALIZA BORRADO DE TRANSACCIONES ADICIONAL SE REALIZAN TRANSACCIONES DE PRUEBA Y SE BRINDA INFORMACIÓN DEL CORRECTO CIERRE QUEDANDO OKAY LA FUNCIONALIDAD DE CIERRE SIN NOVEDAD EN EL INCIDENTE A CONFORMIDAD CORRESPONSAL BANCARIO | W27: VISITA_TÉCNICA | X27: V8ZZZ365 | Y27: TIPO I | Z27: TERRESTRE | AA27: GALEANO SORIANO JUAN DAVID | AB27: 1 | AC27: 0 | AD27: 0 | AE27: 0 | AF27: =IF(W27="SOPORTE_TELEFÓNICO",'BASE LIQUIDACION'!$B$10,IF(Y27="TIPO I",'BASE LIQUIDACION'!$C$3,IF(Y27="TIPO II",'BASE LIQUIDACION'!$C$4,IF(Y27="TIPO III",'BASE LIQUIDACION'!$C$5,'BASE LIQUIDACION'!$C$7)))) -> 65960.474 | AG27: =IF(W27="SOPORTE_TELEFÓNICO",'BASE LIQUIDACION'!$B$10,(AB27*AF27+AC27*'BASE LIQUIDACION'!$B$12+AD27*'BASE LIQUIDACION'!$B$11+INCIDENTES!AE27*'BASE LIQUIDACION'!$B$13)) -> 65960.474
A28: BUCARAMANGA | B28: =VLOOKUP(A28,'CENTRO DE COSTOS'!A:D,4,FALSE) -> MIGUEL JULIÁN HERNÁNDEZ GUARÍN | C28: =VLOOKUP(A28,'CENTRO DE COSTOS'!A:D,2,FALSE) -> 0004-0008 | D28: 81220 | E28: 2793725 | F28: 25792 | G28: INCIDENTE | H28: ARAUCA | I28: CRAVO NORTE | J28: SECTOR CRAVO NORTE ARAUCA | K28: REDEBAN | L28: FO-25-1583343 | M28: 45925.492 | N28: 45927.44 | O28: NO | P28: USUARIO | Q28: COMUNICACION | R28: CANAL DEL COMERCIO | U28: CERRADO | V28: 25/09/2025 SE ESCALA PARA VISITA. LLAMAR ANTES DE VISITAR, CONFIRMAR FALLA Y DATOS | 26/09/2025 SE COMUNICA CON EL CLIENTE AL NÚMERO DE TELÉFONO 315 4384521 , SE VALIDA CON EL SEÑOR LUIS DONDE INDICA QUE LA FALLA ES EL INTERNET, QUE DEBIDO A ESTA INTERMITENTE POR FALLAS DE LA ENTIDAD PRESTADORA DE SERVICIO , NOS SOLICITA CANCELAR VISITA TÉCNICA , SE LE INDICA QUE LA ORDEN SE CIERRA, Y DE NECESITAR DEBE COMUNICARSE A LA LÍNEA 018000 | W28: SOPORTE_TELEFÓNICO | X28: 0 | Y28: TIPO IV ESPECIAL | Z28: AEREO | AA28: HERRERA LUQUE SAUL JAVIER | AB28: 0 | AC28: 0 | AD28: 0 | AE28: 0 | AF28: =IF(W28="SOPORTE_TELEFÓNICO",'BASE LIQUIDACION'!$B$10,IF(Y28="TIPO I",'BASE LIQUIDACION'!$C$3,IF(Y28="TIPO II",'BASE LIQUIDACION'!$C$4,IF(Y28="TIPO III",'BASE LIQUIDACION'!$C$5,'BASE LIQUIDACION'!$C$7)))) -> 37904.654 | AG28: =IF(W28="SOPORTE_TELEFÓNICO",'BASE LIQUIDACION'!$B$10,(AB28*AF28+AC28*'BASE LIQUIDACION'!$B$12+AD28*'BASE LIQUIDACION'!$B$11+INCIDENTES!AE28*'BASE LIQUIDACION'!$B$13)) -> 37904.654
A29: CALI | B29: =VLOOKUP(A29,'CENTRO DE COSTOS'!A:D,4,FALSE) -> DIEGO FERNANDO HENAO CARDONA | C29: =VLOOKUP(A29,'CENTRO DE COSTOS'!A:D,2,FALSE) -> 0004-0003 | D29: 76111 | E29: 2793720 | F29: 79848 | G29: INCIDENTE | H29: VALLE DEL CAUCA | I29: GUADALAJARA DE BUGA | J29: BARRIO CENTRO GUADALAJARA DE BUGA GUADALAJARA DE BUGA | K29: REDEBAN | L29: FO-25-1583348 | M29: 45925.491 | N29: 45926.558 | O29: NO | P29: USUARIO | Q29: MANTENIMIENTO | R29: MANTENIMIENTO GENERAL | U29: CERRADO | V29: 25/09/2025 SE ESCALA PARA VISITA. LLAMAR ANTES DE VISITAR, CONFIRMAR FALLA Y DATOS | 26/09/2025 EN LA VISITA TÉCNICA SE REALIZÓ EL PROCESO DE REINICIAR EL DATÁFONO, CONFIGURAR NUEVAMENTE LOS PARÁMETROS Y SE REALIZÓ LA INICIALIZACIÓN OK,SE REALIZARON LAS PRUEBAS DEJANDO EL SERVICIO OPERANDO SIN FALLAS Y SIN NOVEDAD | W29: VISITA_TÉCNICA | X29: FAUZZ213 | Y29: TIPO II | Z29: TERRESTRE | AA29: SANCHEZ URREGO ROBINSON DAVID | AB29: 1 | AC29: 0 | AD29: 0 | AE29: 0 | AF29: =IF(W29="SOPORTE_TELEFÓNICO",'BASE LIQUIDACION'!$B$10,IF(Y29="TIPO I",'BASE LIQUIDACION'!$C$3,IF(Y29="TIPO II",'BASE LIQUIDACION'!$C$4,IF(Y29="TIPO III",'BASE LIQUIDACION'!$C$5,'BASE LIQUIDACION'!$C$7)))) -> 163813.56 | AG29: =IF(W29="SOPORTE_TELEFÓNICO",'BASE LIQUIDACION'!$B$10,(AB29*AF29+AC29*'BASE LIQUIDACION'!$B$12+AD29*'BASE LIQUIDACION'!$B$11+INCIDENTES!AE29*'BASE LIQUIDACION'!$B$13)) -> 163813.56
A30: MEDELLIN | B30: =VLOOKUP(A30,'CENTRO DE COSTOS'!A:D,4,FALSE) -> JUAN SEBASTIÁN RÍOS CASTRILLÓN | C30: =VLOOKUP(A30,'CENTRO DE COSTOS'!A:D,2,FALSE) -> 0004-0005 | D30: 5088 | E30: 2793492 | F30: 17101 | G30: INCIDENTE | H30: ANTIOQUIA | I30: BELLO | J30: BARRIO ZAMORA II BELLO | K30: REDEBAN | L30: FO-25-1583367 | M30: 45925.484 | N30: 45925.722 | O30: NO | P30: USUARIO | Q30: USUARIOS | R30: MALA MANIPULACION POS | U30: CERRADO | V30: 25/09/2025 SE ESCALA PARA VISITA. LLAMAR ANTES DE VISITAR, CONFIRMAR FALLA Y DATOS | 25/09/2025 SE IDENTIFICA QUE USUARIO BORRO PARÁMETROS DE COMUNICACIÓN, SE CONFIGURA Y SE DEJAN SERVICIOS FUNCIONANDO CORRECTAMENTE | W30: VISITA_TÉCNICA | X30: A00JZ244 | Y30: TIPO I | Z30: TERRESTRE | AA30: BARRIENTOS HERNANDEZ CRISTIAN HORACIO | AB30: 1 | AC30: 0 | AD30: 0 | AE30: 0 | AF30: =IF(W30="SOPORTE_TELEFÓNICO",'BASE LIQUIDACION'!$B$10,IF(Y30="TIPO I",'BASE LIQUIDACION'!$C$3,IF(Y30="TIPO II",'BASE LIQUIDACION'!$C$4,IF(Y30="TIPO III",'BASE LIQUIDACION'!$C$5,'BASE LIQUIDACION'!$C$7)))) -> 65960.474 | AG30: =IF(W30="SOPORTE_TELEFÓNICO",'BASE LIQUIDACION'!$B$10,(AB30*AF30+AC30*'BASE LIQUIDACION'!$B$12+AD30*'BASE LIQUIDACION'!$B$11+INCIDENTES!AE30*'BASE LIQUIDACION'!$B$13)) -> 65960.474
A31: MONTERIA | B31: =VLOOKUP(A31,'CENTRO DE COSTOS'!A:D,4,FALSE) -> JOSE MAURICIO HERNANDEZ ROJAS | C31: =VLOOKUP(A31,'CENTRO DE COSTOS'!A:D,2,FALSE) -> 0004-0001 | D31: 5154 | E31: 2793264 | F31: 75821 | G31: INCIDENTE | H31: ANTIOQUIA | I31: CAUCASIA | J31: PTM CAUCASIA PAPELERIA G J | K31: REDEBAN | L31: FO-25-1593008 | M31: 45925.46 | N31: 45927.512 | O31: NO | P31: USUARIO | Q31: MANTENIMIENTO | R31: MANTENIMIENTO GENERAL | U31: CERRADO | V31: 27/09/2025 EN COMUNICACIÓN CON LA SRA GERALDINE BURGOS AL NÚMERO 3147313658 NOS INFORMA QUE NO PUSO EL DENUNCIO COMO CORRESPONDE, SE LE INFORMA QUE CUANDO TENGA EL NUEVO DENUNCIO LO REPORTE. SE PROCEDE A CERRAR | 27/09/2025 EN COMUNICACIÓN CON LA SRA GERALDINE BURGOS AL NÚMERO 3147313658 NOS INFORMA QUE NO PUSO EL DENUNCIO COMO CORRESPONDE, SE LE INFORMA QUE CUANDO TENGA EL NUEVO DENUNCIO LO REPORTE. SE PROCEDE A CERRAR | W31: SOPORTE_TELEFÓNICO | X31: 0 | Y31: TIPO II | Z31: TERRESTRE | AA31: CONTRERAS ROSSI LITZY YULIETH | AB31: 0 | AC31: 0 | AD31: 0 | AE31: 0 | AF31: =IF(W31="SOPORTE_TELEFÓNICO",'BASE LIQUIDACION'!$B$10,IF(Y31="TIPO I",'BASE LIQUIDACION'!$C$3,IF(Y31="TIPO II",'BASE LIQUIDACION'!$C$4,IF(Y31="TIPO III",'BASE LIQUIDACION'!$C$5,'BASE LIQUIDACION'!$C$7)))) -> 37904.654 | AG31: =IF(W31="SOPORTE_TELEFÓNICO",'BASE LIQUIDACION'!$B$10,(AB31*AF31+AC31*'BASE LIQUIDACION'!$B$12+AD31*'BASE LIQUIDACION'!$B$11+INCIDENTES!AE31*'BASE LIQUIDACION'!$B$13)) -> 37904.654
A32: PASTO | B32: =VLOOKUP(A32,'CENTRO DE COSTOS'!A:D,4,FALSE) -> DIEGO FERNANDO HENAO CARDONA | C32: =VLOOKUP(A32,'CENTRO DE COSTOS'!A:D,2,FALSE) -> 0004-0003 | D32: 52001 | E32: 2792068 | F32: 56707 | G32: INCIDENTE | H32: NARIÑO | I32: PASTO | J32: PTM DULCE FANTASIA 10 | K32: REDEBAN | L32: FO-25-1581991 | M32: 45925.392 | N32: 45925.71 | O32: NO | P32: USUARIO | Q32: MANTENIMIENTO | R32: MANTENIMIENTO GENERAL | U32: CERRADO | V32: 25/09/2025 SE ESCALA PARA VISITA. LLAMAR ANTES DE VISITAR, CONFIRMAR FALLA Y DATOS | 25/09/2025 SE LLEGÓ A SITIO PERO LOCAL SE ENCUENTRA CERRADO, ES DE ACLARAR QUE SE LLAMÓ AL CLIENTE EN HORAS DE LA MAÑANA PERO ESTE NO RESPONDIÓ A LO CUAL SE LLAMÓ NUEVAMENTE Y HASTA LA HORA CONTESTA INFORMANDO QUE NO ESTÁ DISPONIBLE YA QUE SE ENCUENTRA REALIZANDO ACTIVIDADES PERSONA, INFORMA QUE EL EQUIPO YA SE ENCUENTRA FUNCIONANDO DESDE HORAS DE LA MAÑANA AL REALIZAR UN CAMBIO DE ROLLO E INDICA QUE ESTÁ IMPRIMIENDO LOS VOUCHERS SIN INCONVENIENTES Y QUE EL CB SE ENCUENTRA TOTALMENTE OPERATIVO. | W32: VISITA_TÉCNICA | X32: COMERCIO CERRADO, SOLUCIÓN TELEFÓNICA EN SITIO | Y32: TIPO I | Z32: TERRESTRE | AA32: REMICIO AMADO JOHN HEBER | AB32: 1 | AC32: 0 | AD32: 0 | AE32: 0 | AF32: =IF(W32="SOPORTE_TELEFÓNICO",'BASE LIQUIDACION'!$B$10,IF(Y32="TIPO I",'BASE LIQUIDACION'!$C$3,IF(Y32="TIPO II",'BASE LIQUIDACION'!$C$4,IF(Y32="TIPO III",'BASE LIQUIDACION'!$C$5,'BASE LIQUIDACION'!$C$7)))) -> 65960.474 | AG32: =IF(W32="SOPORTE_TELEFÓNICO",'BASE LIQUIDACION'!$B$10,(AB32*AF32+AC32*'BASE LIQUIDACION'!$B$12+AD32*'BASE LIQUIDACION'!$B$11+INCIDENTES!AE32*'BASE LIQUIDACION'!$B$13)) -> 65960.474
A33: BOGOTA | B33: =VLOOKUP(A33,'CENTRO DE COSTOS'!A:D,4,FALSE) -> WILLIAM ASDRUBAL ROZO ROZO | C33: =VLOOKUP(A33,'CENTRO DE COSTOS'!A:D,2,FALSE) -> 0004-0004 | D33: 25817 | E33: 2791732 | F33: 53108 | G33: INCIDENTE | H33: CUNDINAMARCA | I33: TOCANCIPA | J33: BARRIO TOCANCIPA TOCANCIPA 3 | K33: REDEBAN | L33: FO-25-1581534 | M33: 45925.36 | N33: 45926.647 | O33: NO | P33: USUARIO | Q33: COMUNICACION | R33: CANAL DEL COMERCIO | U33: CERRADO | V33: 25/09/2025 SE ESCALA PARA VISITA. LLAMAR ANTES DE VISITAR, CONFIRMAR FALLA Y DATOS | 26/09/2025 DURANTE LA VISITA TECNICA PARA ATENDER INCIDENTE REPORTADO POR CORRESPONSAL BANCARIO, CORRESPONSAL NOS INDICA QUE EL DAÑO YA FUE SOLUCIONADO, SE HACEN PRUEBAS CONFIRMANDO QUE SERVICIO SE ENCUENTRA FUNCIONAL Y OPERATIVO A CONFORMIDAD DEL CB SIN NOVEDAD EN EL INCIDENTE SALDO OK | W33: VISITA_TÉCNICA | X33: 9C0NZ318 | Y33: TIPO II | Z33: TERRESTRE | AA33: GALEANO SORIANO JUAN DAVID | AB33: 1 | AC33: 0 | AD33: 0 | AE33: 0 | AF33: =IF(W33="SOPORTE_TELEFÓNICO",'BASE LIQUIDACION'!$B$10,IF(Y33="TIPO I",'BASE LIQUIDACION'!$C$3,IF(Y33="TIPO II",'BASE LIQUIDACION'!$C$4,IF(Y33="TIPO III",'BASE LIQUIDACION'!$C$5,'BASE LIQUIDACION'!$C$7)))) -> 163813.56 | AG33: =IF(W33="SOPORTE_TELEFÓNICO",'BASE LIQUIDACION'!$B$10,(AB33*AF33+AC33*'BASE LIQUIDACION'!$B$12+AD33*'BASE LIQUIDACION'!$B$11+INCIDENTES!AE33*'BASE LIQUIDACION'!$B$13)) -> 163813.56
A34: PASTO | B34: =VLOOKUP(A34,'CENTRO DE COSTOS'!A:D,4,FALSE) -> DIEGO FERNANDO HENAO CARDONA | C34: =VLOOKUP(A34,'CENTRO DE COSTOS'!A:D,2,FALSE) -> 0004-0003 | D34: 52399 | E34: 2791721 | F34: 66057 | G34: INCIDENTE | H34: NARIÑO | I34: LA UNION | J34: DISTRICOL MERCAHOGAR | K34: REDEBAN | L34: FO-25-1581549 | M34: 45925.359 | N34: 45926.645 | O34: NO | P34: USUARIO | Q34: MANTENIMIENTO | R34: MANTENIMIENTO GENERAL | U34: CERRADO | V34: 25/09/2025 EN COMUNICACIÓN CON EL SR EDGAR MESA AL NÚMERO 3122434896 NOS INFORMA QUE LA FALLA QUE PRESENTA ES CON LA IMPRESION. CONFIRMA DATOS E INDICA QUE LA RED ES REDEBAN, SE ESCALA PARA VISITA | 26/09/2025 SE VISITA CB. SE ENCUENTRA DATAFONO CON FALLA EN LA IMPRESORA, NO IMPRIME ALGUNOS CARACTERES Y PRESENTA UN RUIDO EXTRAÑO. SE REALIZA MANTENIMIENTO, LIMPIEZA Y AJUSTE DE LAS PIEZAS Y LA IMPRESIÓN Y EL RUIDO MEJORAN. SE REALIZA. PRUEBAS TX EXITOSAS. QUEDA OPERATIVO | W34: VISITA_TÉCNICA | X34: 7A00K519 | Y34: TIPO III | Z34: TERRESTRE | AA34: CASTILLO HERRERA ALEX RICARDO | AB34: 1 | AC34: 0 | AD34: 0 | AE34: 0 | AF34: =IF(W34="SOPORTE_TELEFÓNICO",'BASE LIQUIDACION'!$B$10,IF(Y34="TIPO I",'BASE LIQUIDACION'!$C$3,IF(Y34="TIPO II",'BASE LIQUIDACION'!$C$4,IF(Y34="TIPO III",'BASE LIQUIDACION'!$C$5,'BASE LIQUIDACION'!$C$7)))) -> 275728.38 | AG34: =IF(W34="SOPORTE_TELEFÓNICO",'BASE LIQUIDACION'!$B$10,(AB34*AF34+AC34*'BASE LIQUIDACION'!$B$12+AD34*'BASE LIQUIDACION'!$B$11+INCIDENTES!AE34*'BASE LIQUIDACION'!$B$13)) -> 275728.38
A35: APARTADO | B35: =VLOOKUP(A35,'CENTRO DE COSTOS'!A:D,4,FALSE) -> JUAN SEBASTIÁN RÍOS CASTRILLÓN | C35: =VLOOKUP(A35,'CENTRO DE COSTOS'!A:D,2,FALSE) -> 0004-0005 | D35: 5147 | E35: 2791710 | F35: 79886 | G35: INCIDENTE | H35: ANTIOQUIA | I35: CAREPA | J35: DISTRICOL COOTRANSCAR | K35: REDEBAN | L35: FO-25-1581556 | M35: 45925.357 | N35: 45929.747 | O35: NO | P35: USUARIO | Q35: COMUNICACION | R35: CANAL DEL COMERCIO | U35: CERRADO | V35: 25/09/2025 SE ESCALA PARA VISITA. LLAMAR ANTES DE VISITAR, CONFIRMAR FALLA Y DATOS | 29/09/2025 CLIENTE INDICA QUE INTERNET ESTABA MALO, AL VOLVER SE RECUPERO LA RED DEL DATAFONO. DATAFONO OPERATIVO | W35: VISITA_TÉCNICA | X35: SAUZZ945 | Y35: TIPO I | Z35: TERRESTRE | AA35: CASTRO HENAO DANIEL ESTEBAN | AB35: 1 | AC35: 0 | AD35: 0 | AE35: 0 | AF35: =IF(W35="SOPORTE_TELEFÓNICO",'BASE LIQUIDACION'!$B$10,IF(Y35="TIPO I",'BASE LIQUIDACION'!$C$3,IF(Y35="TIPO II",'BASE LIQUIDACION'!$C$4,IF(Y35="TIPO III",'BASE LIQUIDACION'!$C$5,'BASE LIQUIDACION'!$C$7)))) -> 65960.474 | AG35: =IF(W35="SOPORTE_TELEFÓNICO",'BASE LIQUIDACION'!$B$10,(AB35*AF35+AC35*'BASE LIQUIDACION'!$B$12+AD35*'BASE LIQUIDACION'!$B$11+INCIDENTES!AE35*'BASE LIQUIDACION'!$B$13)) -> 65960.474
A36: MEDELLIN | B36: =VLOOKUP(A36,'CENTRO DE COSTOS'!A:D,4,FALSE) -> JUAN SEBASTIÁN RÍOS CASTRILLÓN | C36: =VLOOKUP(A36,'CENTRO DE COSTOS'!A:D,2,FALSE) -> 0004-0005 | D36: 5088 | E36: 2790710 | F36: 33412 | G36: INCIDENTE | H36: ANTIOQUIA | I36: BELLO | J36: BARRIO NIQUIA EL BURRO BELLO | K36: REDEBAN | L36: FO-25-1581264 | M36: 45925.333 | N36: 45925.699 | O36: NO | P36: USUARIO | Q36: COMUNICACION | R36: CONEXIONES DE COMERCIO | U36: CERRADO | V36: 25/09/2025 SE ESCALA PARA VISITA. LLAMAR ANTES DE VISITAR, CONFIRMAR FALLA Y DATOS | 25/09/2025 SE COMUNICA CON EL USUARIO PARA CONFIRMAR LA VISITA, EL USUARIO INFORMA QUE EL DÍA DE HOY HA ESTADO TRABAJANDO PERFECTAMENTE SIN NINGÚN INCONVENIENTE. | W36: SOPORTE_TELEFÓNICO | X36: 0 | Y36: TIPO I | Z36: TERRESTRE | AA36: ZAPATA LOPEZ EDWARD ASDRUBAL | AB36: 0 | AC36: 0 | AD36: 0 | AE36: 0 | AF36: =IF(W36="SOPORTE_TELEFÓNICO",'BASE LIQUIDACION'!$B$10,IF(Y36="TIPO I",'BASE LIQUIDACION'!$C$3,IF(Y36="TIPO II",'BASE LIQUIDACION'!$C$4,IF(Y36="TIPO III",'BASE LIQUIDACION'!$C$5,'BASE LIQUIDACION'!$C$7)))) -> 37904.654 | AG36: =IF(W36="SOPORTE_TELEFÓNICO",'BASE LIQUIDACION'!$B$10,(AB36*AF36+AC36*'BASE LIQUIDACION'!$B$12+AD36*'BASE LIQUIDACION'!$B$11+INCIDENTES!AE36*'BASE LIQUIDACION'!$B$13)) -> 37904.654
A37: BUCARAMANGA | B37: =VLOOKUP(A37,'CENTRO DE COSTOS'!A:D,4,FALSE) -> MIGUEL JULIÁN HERNÁNDEZ GUARÍN | C37: =VLOOKUP(A37,'CENTRO DE COSTOS'!A:D,2,FALSE) -> 0004-0008 | D37: 68755 | E37: 2790521 | F37: 78892 | G37: INCIDENTE | H37: SANTANDER | I37: SOCORRO | J37: BARRIO CENTRO SOCORRO SOCORRO | K37: REDEBAN | L37: FO-25-1580252 | M37: 45924.73 | N37: 45925.563 | O37: NO | P37: USUARIO | Q37: COMUNICACION | R37: CONEXIONES DE COMERCIO | U37: CERRADO | V37: 24/09/2025 SE ESCALA PARA VISITA. LLAMAR ANTES DE VISITAR, CONFIRMAR FALLA Y DATOS | 25/09/2025 EN COMUNICACIÓN CON LA SEÑORA ESPERANZAAL.NUMERO 3164365720MANIFIESTA , FUE UNA FALLA DEL INTERNET EL DIA DE AYER , INFORMA Q EL DATAFONL YA SE ENCUENTRA OPERATIVO EL DIA DE HOY Y NO NECESITA LA VISITA TECNICA, SE CIERRA ORDEN | W37: SOPORTE_TELEFÓNICO | X37: 0 | Y37: TIPO III | Z37: TERRESTRE | AA37: GELVEZ MOGOLLON JOSE ELISEO | AB37: 0 | AC37: 0 | AD37: 0 | AE37: 0 | AF37: =IF(W37="SOPORTE_TELEFÓNICO",'BASE LIQUIDACION'!$B$10,IF(Y37="TIPO I",'BASE LIQUIDACION'!$C$3,IF(Y37="TIPO II",'BASE LIQUIDACION'!$C$4,IF(Y37="TIPO III",'BASE LIQUIDACION'!$C$5,'BASE LIQUIDACION'!$C$7)))) -> 37904.654 | AG37: =IF(W37="SOPORTE_TELEFÓNICO",'BASE LIQUIDACION'!$B$10,(AB37*AF37+AC37*'BASE LIQUIDACION'!$B$12+AD37*'BASE LIQUIDACION'!$B$11+INCIDENTES!AE37*'BASE LIQUIDACION'!$B$13)) -> 37904.654
A38: NEIVA | B38: =VLOOKUP(A38,'CENTRO DE COSTOS'!A:D,4,FALSE) -> KEVIN ALEXIS CORZO BUSTOS | C38: =VLOOKUP(A38,'CENTRO DE COSTOS'!A:D,2,FALSE) -> 0004-0007 | D38: 18001 | E38: 2789860 | F38: 37490 | G38: INCIDENTE | H38: CAQUETA | I38: FLORENCIA | J38: BARRIO CENTRO FLORENCIA 1 | K38: REDEBAN | L38: FO-25-1579602 | M38: 45924.676 | N38: 45925.684 | O38: NO | P38: USUARIO | Q38: COMUNICACION | R38: CONEXIONES DE COMERCIO | U38: CERRADO | V38: 24/09/2025 SE INTENTA COMUNICACIÓN CON EL SR DIEGO CARVAJAL AL NÚMERO 3208358585 PARA CONFIRMAR DATOS Y FALLA PERO NO HAY CONTACTO, SE ESCALA A COORDINADOR DE ZONA PARA VALIDAR EN SITIO | 25/09/2025 SE REALIZA VISITA AL CB Y SE EVIDENCIA QUE LAS CONEXIONES DEL INTERNET ESTÁN MAL ORGANIZADAS, SE ORGANIZA EL CABLE QUE DA INTERNET AL DATAFONO Y QUEDA OPERATIVO, PRUEBAS CB OK. | W38: VISITA_TÉCNICA | X38: AB00O906 | Y38: TIPO IV | Z38: TERRESTRE | AA38: BERMUDEZ SANCHEZ JOSE NEYBER | AB38: 1 | AC38: 0 | AD38: 0 | AE38: 0 | AF38: =IF(W38="SOPORTE_TELEFÓNICO",'BASE LIQUIDACION'!$B$10,IF(Y38="TIPO I",'BASE LIQUIDACION'!$C$3,IF(Y38="TIPO II",'BASE LIQUIDACION'!$C$4,IF(Y38="TIPO III",'BASE LIQUIDACION'!$C$5,'BASE LIQUIDACION'!$C$7)))) -> 479589.74 | AG38: =IF(W38="SOPORTE_TELEFÓNICO",'BASE LIQUIDACION'!$B$10,(AB38*AF38+AC38*'BASE LIQUIDACION'!$B$12+AD38*'BASE LIQUIDACION'!$B$11+INCIDENTES!AE38*'BASE LIQUIDACION'!$B$13)) -> 479589.74
A39: CUCUTA | B39: =VLOOKUP(A39,'CENTRO DE COSTOS'!A:D,4,FALSE) -> MIGUEL JULIÁN HERNÁNDEZ GUARÍN | C39: =VLOOKUP(A39,'CENTRO DE COSTOS'!A:D,2,FALSE) -> 0004-0008 | D39: 54001 | E39: 2789429 | F39: 80565 | G39: INCIDENTE | H39: NORTE DE SANTANDER | I39: CUCUTA | J39: DISTRICOL SANTIAGO PHARMA PLUS | K39: REDEBAN | L39: FO-25-1579220 | M39: 45924.646 | N39: 45925.519 | O39: NO | P39: USUARIO | Q39: NO ENCIENDE | R39: CONEXIONES DE COMERCIO | U39: CERRADO | V39: 24/09/2025 SE ESCALA PARA VISITA. LLAMAR ANTES DE VISITAR, CONFIRMAR FALLA Y DATOS | 25/09/2025 SE COMUNICA CON LA CLIENTE ISABEL SOFIA FUENTES AL # 3156406539, SE DA SOPORTE TELEFONICO REINICIANDO EL DATAFONO, CLIENTE INFORMA QUE YA ENCIENDE CORRECTAMENTE Y OPERA CON NORMALIDAD, SE ANEXA PRUEBA SOPORTADA POR EL CLIENTE EXITOSA, CB OPERATIVO. | W39: SOPORTE_TELEFÓNICO | X39: 0 | Y39: TIPO I | Z39: TERRESTRE | AA39: NARANJO AFANADOR RUBEN JESUS | AB39: 0 | AC39: 0 | AD39: 0 | AE39: 0 | AF39: =IF(W39="SOPORTE_TELEFÓNICO",'BASE LIQUIDACION'!$B$10,IF(Y39="TIPO I",'BASE LIQUIDACION'!$C$3,IF(Y39="TIPO II",'BASE LIQUIDACION'!$C$4,IF(Y39="TIPO III",'BASE LIQUIDACION'!$C$5,'BASE LIQUIDACION'!$C$7)))) -> 37904.654 | AG39: =IF(W39="SOPORTE_TELEFÓNICO",'BASE LIQUIDACION'!$B$10,(AB39*AF39+AC39*'BASE LIQUIDACION'!$B$12+AD39*'BASE LIQUIDACION'!$B$11+INCIDENTES!AE39*'BASE LIQUIDACION'!$B$13)) -> 37904.654
A40: TUNJA | B40: =VLOOKUP(A40,'CENTRO DE COSTOS'!A:D,4,FALSE) -> MIGUEL JULIÁN HERNÁNDEZ GUARÍN | C40: =VLOOKUP(A40,'CENTRO DE COSTOS'!A:D,2,FALSE) -> 0004-0008 | D40: 15367 | E40: 2789231 | F40: 80894 | G40: INCIDENTE | H40: BOYACA | I40: JENESANO | J40: BARRIO CENTRO JENESANO 7 | K40: REDEBAN | L40: FO-25-1579049 | M40: 45924.631 | N40: 45925.675 | O40: NO | P40: ENTIDAD | Q40: ERROR DE TRANSACCIONES | R40: TRANSACCION NO PERMITIDA | U40: CERRADO | V40: 24/09/2025 SE ESCALA PARA VISITA. LLAMAR ANTES DE VISITAR, CONFIRMAR FALLA Y DATOS | 25/09/2025 SE REALIZA VISITA AL COMERCIO, SE BORRA Y ACTUALIZA EQUIPO A VERSION 10.3N, SE CONFIGURA EQUIPO COMO MIXTO, SE HACEN PRUEBAS OK | W40: VISITA_TÉCNICA | X40: FGZZZ912 | Y40: TIPO II | Z40: TERRESTRE | AA40: SOLER HOYOS CRISTIAN LEONARDO | AB40: 1 | AC40: 0 | AD40: 0 | AE40: 0 | AF40: =IF(W40="SOPORTE_TELEFÓNICO",'BASE LIQUIDACION'!$B$10,IF(Y40="TIPO I",'BASE LIQUIDACION'!$C$3,IF(Y40="TIPO II",'BASE LIQUIDACION'!$C$4,IF(Y40="TIPO III",'BASE LIQUIDACION'!$C$5,'BASE LIQUIDACION'!$C$7)))) -> 163813.56 | AG40: =IF(W40="SOPORTE_TELEFÓNICO",'BASE LIQUIDACION'!$B$10,(AB40*AF40+AC40*'BASE LIQUIDACION'!$B$12+AD40*'BASE LIQUIDACION'!$B$11+INCIDENTES!AE40*'BASE LIQUIDACION'!$B$13)) -> 163813.56
A41: CUCUTA | B41: =VLOOKUP(A41,'CENTRO DE COSTOS'!A:D,4,FALSE) -> MIGUEL JULIÁN HERNÁNDEZ GUARÍN | C41: =VLOOKUP(A41,'CENTRO DE COSTOS'!A:D,2,FALSE) -> 0004-0008 | D41: 54001 | E41: 2788155 | F41: 79861 | G41: INCIDENTE | H41: NORTE DE SANTANDER | I41: CUCUTA | J41: BARRIO EL CENTRO CUCUTA 83 | K41: REDEBAN | L41: FO-25-1578144 | M41: 45924.555 | N41: 45925.506 | O41: NO | P41: USUARIO | Q41: MANTENIMIENTO | R41: MANTENIMIENTO GENERAL | U41: CERRADO | V41: 24/09/2025 SE ESCALA PARA VISITA. LLAMAR ANTES DE VISITAR, CONFIRMAR FALLA Y DATOS | 25/09/2025 SE REALIZA VISITA, SE REALIZA MANTENIMIENTO, SE REALIZAN PRUEBAS Y CIERRES OK | W41: VISITA_TÉCNICA | X41: FAWZZ653 | Y41: TIPO I | Z41: TERRESTRE | AA41: PACHECO BUITRAGO JAVIER ALONSO | AB41: 1 | AC41: 0 | AD41: 0 | AE41: 0 | AF41: =IF(W41="SOPORTE_TELEFÓNICO",'BASE LIQUIDACION'!$B$10,IF(Y41="TIPO I",'BASE LIQUIDACION'!$C$3,IF(Y41="TIPO II",'BASE LIQUIDACION'!$C$4,IF(Y41="TIPO III",'BASE LIQUIDACION'!$C$5,'BASE LIQUIDACION'!$C$7)))) -> 65960.474 | AG41: =IF(W41="SOPORTE_TELEFÓNICO",'BASE LIQUIDACION'!$B$10,(AB41*AF41+AC41*'BASE LIQUIDACION'!$B$12+AD41*'BASE LIQUIDACION'!$B$11+INCIDENTES!AE41*'BASE LIQUIDACION'!$B$13)) -> 65960.474
A42: VALLEDUPAR | B42: =VLOOKUP(A42,'CENTRO DE COSTOS'!A:D,4,FALSE) -> JOSE MAURICIO HERNANDEZ ROJAS | C42: =VLOOKUP(A42,'CENTRO DE COSTOS'!A:D,2,FALSE) -> 0004-0001 | D42: 20570 | E42: 2787385 | F42: 70157 | G42: INCIDENTE | H42: CESAR | I42: PUEBLO BELLO | J42: BARRIO CENTRO PUEBLO 14 BELLO | K42: REDEBAN | L42: FO-25-1576710 | M42: 45924.472 | N42: 45925.433 | O42: NO | P42: USUARIO | Q42: COMUNICACION | R42: CONEXIONES DE COMERCIO | U42: CERRADO | V42: 24/09/2025 SE INTENTA COMUNICACIÓN CON LA SRA ANYI DIAZ AL NÚMERO 3164164844 PARA CONFIRMAR DATOS Y FALLA PERO NO HAY CONTACTO, SE ESCALA A COORDINADOR DE ZONA PARA VALIDAR EN SITIO | 25/09/2025 SE REALIZA GESTIÓN TELEFÓNICA ATIENDE LA SRA ANGIE DIAS CON CC: 1094832277, INDICANDONOS QUE EL DIA DE AYER PRESENTABA PROBLEMAS CON EL CABLE DE RED, LA CUAL EL DIA DE AYER LO CAMBIO Y LE QUEDO OPERATIVO | W42: SOPORTE_TELEFÓNICO | X42: 0 | Y42: TIPO III | Z42: TERRESTRE | AA42: MAESTRE MENGUAL EDGAR ENRIQUE | AB42: 0 | AC42: 0 | AD42: 0 | AE42: 0 | AF42: =IF(W42="SOPORTE_TELEFÓNICO",'BASE LIQUIDACION'!$B$10,IF(Y42="TIPO I",'BASE LIQUIDACION'!$C$3,IF(Y42="TIPO II",'BASE LIQUIDACION'!$C$4,IF(Y42="TIPO III",'BASE LIQUIDACION'!$C$5,'BASE LIQUIDACION'!$C$7)))) -> 37904.654 | AG42: =IF(W42="SOPORTE_TELEFÓNICO",'BASE LIQUIDACION'!$B$10,(AB42*AF42+AC42*'BASE LIQUIDACION'!$B$12+AD42*'BASE LIQUIDACION'!$B$11+INCIDENTES!AE42*'BASE LIQUIDACION'!$B$13)) -> 37904.654
A43: VILLAVICENCIO | B43: =VLOOKUP(A43,'CENTRO DE COSTOS'!A:D,4,FALSE) -> KEVIN ALEXIS CORZO BUSTOS | C43: =VLOOKUP(A43,'CENTRO DE COSTOS'!A:D,2,FALSE) -> 0004-0007 | D43: 50226 | E43: 2787115 | F43: 54150 | G43: INCIDENTE | H43: META | I43: CUMARAL | J43: BARRIO VILLA CLAUDIA CUMARAL | K43: REDEBAN | L43: FO-25-1576333 | M43: 45924.447 | N43: 45927.394 | O43: NO | P43: USUARIO | Q43: COMUNICACION | R43: CONEXIONES DE COMERCIO | U43: CERRADO | V43: 24/09/2025 SE ESCALA PARA VISITA. LLAMAR ANTES DE VISITAR, CONFIRMAR FALLA Y DATOS | 26/09/2025 SE REALIZA VISITA AL CB Y EL USUARIO INFORMA QUE YA EL DATÁFONO ESTÁ FUNCIONANDO, ERA POR SEÑAL DEL INTERNET Y YA TODO OK SE REALIZA UNA PRUEBA Y TODO OK | W43: VISITA_TÉCNICA | X43: XP3ZZ042 | Y43: TIPO II | Z43: TERRESTRE | AA43: MOLINA CASTRO JAVIER ALBERTO | AB43: 1 | AC43: 0 | AD43: 0 | AE43: 0 | AF43: =IF(W43="SOPORTE_TELEFÓNICO",'BASE LIQUIDACION'!$B$10,IF(Y43="TIPO I",'BASE LIQUIDACION'!$C$3,IF(Y43="TIPO II",'BASE LIQUIDACION'!$C$4,IF(Y43="TIPO III",'BASE LIQUIDACION'!$C$5,'BASE LIQUIDACION'!$C$7)))) -> 163813.56 | AG43: =IF(W43="SOPORTE_TELEFÓNICO",'BASE LIQUIDACION'!$B$10,(AB43*AF43+AC43*'BASE LIQUIDACION'!$B$12+AD43*'BASE LIQUIDACION'!$B$11+INCIDENTES!AE43*'BASE LIQUIDACION'!$B$13)) -> 163813.56
A44: MEDELLIN | B44: =VLOOKUP(A44,'CENTRO DE COSTOS'!A:D,4,FALSE) -> JUAN SEBASTIÁN RÍOS CASTRILLÓN | C44: =VLOOKUP(A44,'CENTRO DE COSTOS'!A:D,2,FALSE) -> 0004-0005 | D44: 5001 | E44: 2786290 | F44: 25163 | G44: INCIDENTE | H44: ANTIOQUIA | I44: MEDELLIN | J44: REDY BELEN LA 33 | K44: REDEBAN | L44: FO-25-1575826 | M44: 45924.412 | N44: 45924.66 | O44: NO | P44: USUARIO | Q44: MANTENIMIENTO | R44: MANTENIMIENTO GENERAL | U44: CERRADO | V44: 24/09/2025 SE ESCALA PARA VISITA. LLAMAR ANTES DE VISITAR, CONFIRMAR FALLA Y DATOS | 24/09/2025 SE LLEGA COMERCIO Y KA SEÑORA VICKY INDICA QUE YA EL DATÁFONO FUNCIONA CORRECTAMENTE, FUENTE DE PODER MAL CONECTADA | W44: VISITA_TÉCNICA | X44: 999VZ081 | Y44: TIPO I | Z44: TERRESTRE | AA44: BADEL ACUÑA LUIS ALBERTO | AB44: 1 | AC44: 0 | AD44: 0 | AE44: 0 | AF44: =IF(W44="SOPORTE_TELEFÓNICO",'BASE LIQUIDACION'!$B$10,IF(Y44="TIPO I",'BASE LIQUIDACION'!$C$3,IF(Y44="TIPO II",'BASE LIQUIDACION'!$C$4,IF(Y44="TIPO III",'BASE LIQUIDACION'!$C$5,'BASE LIQUIDACION'!$C$7)))) -> 65960.474 | AG44: =IF(W44="SOPORTE_TELEFÓNICO",'BASE LIQUIDACION'!$B$10,(AB44*AF44+AC44*'BASE LIQUIDACION'!$B$12+AD44*'BASE LIQUIDACION'!$B$11+INCIDENTES!AE44*'BASE LIQUIDACION'!$B$13)) -> 65960.474
A45: VALLEDUPAR | B45: =VLOOKUP(A45,'CENTRO DE COSTOS'!A:D,4,FALSE) -> JOSE MAURICIO HERNANDEZ ROJAS | C45: =VLOOKUP(A45,'CENTRO DE COSTOS'!A:D,2,FALSE) -> 0004-0001 | D45: 20011 | E45: 2786424 | F45: 39373 | G45: INCIDENTE | H45: CESAR | I45: AGUACHICA | J45: DISTRICOL TODO MATERIALES JM | K45: REDEBAN | L45: FO-25-1575835 | M45: 45924.404 | N45: 45927.553 | O45: NO | P45: USUARIO | Q45: COMUNICACION | R45: CONEXIONES DE COMERCIO | U45: CERRADO | V45: 24/09/2025 SE INTENTA COMUNICACIÓN CON LA SRA YANETH ÁLVAREZ AL NÚMERO 3115143763 PARA CONFIRMAR DATOS Y FALLA PERO NO HAY CONTACTO, SE ESCALA AQ COORDINADOR DE ZONA PARA VALIDAR EN SITIO | 27/09/2025 SE LLEGA A SITIO, Y SE VALIDA QUE LAS CONEXIONES DEL CABLE UTB DEL MODEM AL DATAFONO ESTABAN UN POCO FLOJOS, SE PROCEDE A AJUSTAR EL CABLEADO, SE REALIZAN PRUEBAS DEJANDO SERVICIO FUNCIONAL AL 100 % | W45: VISITA_TÉCNICA | X45: AA08Z505 | Y45: TIPO IV | Z45: TERRESTRE | AA45: MONTES DIAZ JOHN FRED | AB45: 1 | AC45: 0 | AD45: 0 | AE45: 0 | AF45: =IF(W45="SOPORTE_TELEFÓNICO",'BASE LIQUIDACION'!$B$10,IF(Y45="TIPO I",'BASE LIQUIDACION'!$C$3,IF(Y45="TIPO II",'BASE LIQUIDACION'!$C$4,IF(Y45="TIPO III",'BASE LIQUIDACION'!$C$5,'BASE LIQUIDACION'!$C$7)))) -> 479589.74 | AG45: =IF(W45="SOPORTE_TELEFÓNICO",'BASE LIQUIDACION'!$B$10,(AB45*AF45+AC45*'BASE LIQUIDACION'!$B$12+AD45*'BASE LIQUIDACION'!$B$11+INCIDENTES!AE45*'BASE LIQUIDACION'!$B$13)) -> 479589.74
A46: PASTO | B46: =VLOOKUP(A46,'CENTRO DE COSTOS'!A:D,4,FALSE) -> DIEGO FERNANDO HENAO CARDONA | C46: =VLOOKUP(A46,'CENTRO DE COSTOS'!A:D,2,FALSE) -> 0004-0003 | D46: 52001 | E46: 2786212 | F46: 76204 | G46: INCIDENTE | H46: NARIÑO | I46: PASTO | J46: DISTRICOL DROGUERIA KAFAR | K46: REDEBAN | L46: FO-25-1575716 | M46: 45924.401 | N46: 45924.663 | O46: NO | P46: USUARIO | Q46: COMUNICACION | R46: CANAL DEL COMERCIO | U46: CERRADO | V46: 24/09/2025 SE ESCALA PARA VISITA. LLAMAR ANTES DE VISITAR, CONFIRMAR FALLA Y DATOS | 24/09/2025 SE VERIFICÓ FALLA DE COMUNICACIÓN, FALLA DE PARÁMETROS DE COMUNICACIÓN, SE ENCONTRÓ FALLA DEL CANAL DEL COMERCIO EL CUAL NO CONECTA CORRECTAMENTE EL DATÁFONO EL CLIENTE YA REPORTO A SU OPERADOR DE INTERNET, A SU VEZ SE ENCONTRÓ FALLA DE LECTORA SE CAMBIA LECTOR SE EJECUTAN PRUEBAS TX EXITOSAS QUEDA OPERATIVO. | W46: VISITA_TÉCNICA | X46: FA0GZ496 | Y46: TIPO I | Z46: TERRESTRE | AA46: REMICIO AMADO JOHN HEBER | AB46: 1 | AC46: 0 | AD46: 0 | AE46: 0 | AF46: =IF(W46="SOPORTE_TELEFÓNICO",'BASE LIQUIDACION'!$B$10,IF(Y46="TIPO I",'BASE LIQUIDACION'!$C$3,IF(Y46="TIPO II",'BASE LIQUIDACION'!$C$4,IF(Y46="TIPO III",'BASE LIQUIDACION'!$C$5,'BASE LIQUIDACION'!$C$7)))) -> 65960.474 | AG46: =IF(W46="SOPORTE_TELEFÓNICO",'BASE LIQUIDACION'!$B$10,(AB46*AF46+AC46*'BASE LIQUIDACION'!$B$12+AD46*'BASE LIQUIDACION'!$B$11+INCIDENTES!AE46*'BASE LIQUIDACION'!$B$13)) -> 65960.474
A47: VILLAVICENCIO | B47: =VLOOKUP(A47,'CENTRO DE COSTOS'!A:D,4,FALSE) -> KEVIN ALEXIS CORZO BUSTOS | C47: =VLOOKUP(A47,'CENTRO DE COSTOS'!A:D,2,FALSE) -> 0004-0007 | D47: 25335 | E47: 2786081 | F47: 75234 | G47: INCIDENTE | H47: CUNDINAMARCA | I47: GUAYABETAL | J47: PTM GUAYABETAL D.VELEZ COMUNIC | K47: REDEBAN | L47: FO-25-1575647 | M47: 45924.397 | N47: 45925.665 | O47: NO | P47: USUARIO | Q47: NO ENCIENDE | R47: CONEXIONES DE COMERCIO | U47: CERRADO | V47: 24/09/2025 SE ESCALA PARA VISITA. LLAMAR ANTES DE VISITAR, CONFIRMAR FALLA Y DATOS | 25/09/2025 SE REALIZA CONTACTO CON LA SEÑORA DOLLY LA CUAL INDICA QUE EL DATAFONO SE ENXUENTRA OK, UE EL DAÑO ERA EN EL TOMA CORRIENTE DE COMERCIO | W47: SOPORTE_TELEFÓNICO | X47: 0 | Y47: TIPO II | Z47: TERRESTRE | AA47: PEDREROS CONTRERAS MICHAEL STEVENS | AB47: 0 | AC47: 0 | AD47: 0 | AE47: 0 | AF47: =IF(W47="SOPORTE_TELEFÓNICO",'BASE LIQUIDACION'!$B$10,IF(Y47="TIPO I",'BASE LIQUIDACION'!$C$3,IF(Y47="TIPO II",'BASE LIQUIDACION'!$C$4,IF(Y47="TIPO III",'BASE LIQUIDACION'!$C$5,'BASE LIQUIDACION'!$C$7)))) -> 37904.654 | AG47: =IF(W47="SOPORTE_TELEFÓNICO",'BASE LIQUIDACION'!$B$10,(AB47*AF47+AC47*'BASE LIQUIDACION'!$B$12+AD47*'BASE LIQUIDACION'!$B$11+INCIDENTES!AE47*'BASE LIQUIDACION'!$B$13)) -> 37904.654
A48: MEDELLIN | B48: =VLOOKUP(A48,'CENTRO DE COSTOS'!A:D,4,FALSE) -> JUAN SEBASTIÁN RÍOS CASTRILLÓN | C48: =VLOOKUP(A48,'CENTRO DE COSTOS'!A:D,2,FALSE) -> 0004-0005 | D48: 5501 | E48: 2783837 | F48: 44521 | G48: INCIDENTE | H48: ANTIOQUIA | I48: OLAYA | J48: DISTRICOL SUPERMERCADO LUBISKY | K48: REDEBAN | L48: FO-25-1573964 | M48: 45923.694 | N48: 45925.658 | O48: NO | P48: USUARIO | Q48: COMUNICACION | R48: CANAL DEL COMERCIO | U48: CERRADO | V48: 23/09/2025 SE ESCALA PARA VISITA. LLAMAR ANTES DE VISITAR, CONFIRMAR FALLA Y DATOS | 25/09/2025 SE VÁLIDA POR LLAMADA XON EL USUARIO E INDICA QUE YA ESTA OPERATIVO EL CB SE HACEN PRUEBAS OK SE HABLA CON EL SEÑOR LUBIN JARAMILLO | W48: SOPORTE_TELEFÓNICO | X48: 0 | Y48: TIPO II | Z48: TERRESTRE | AA48: MONTOYA VELEZ ANDRES FELIPE | AB48: 0 | AC48: 0 | AD48: 0 | AE48: 0 | AF48: =IF(W48="SOPORTE_TELEFÓNICO",'BASE LIQUIDACION'!$B$10,IF(Y48="TIPO I",'BASE LIQUIDACION'!$C$3,IF(Y48="TIPO II",'BASE LIQUIDACION'!$C$4,IF(Y48="TIPO III",'BASE LIQUIDACION'!$C$5,'BASE LIQUIDACION'!$C$7)))) -> 37904.654 | AG48: =IF(W48="SOPORTE_TELEFÓNICO",'BASE LIQUIDACION'!$B$10,(AB48*AF48+AC48*'BASE LIQUIDACION'!$B$12+AD48*'BASE LIQUIDACION'!$B$11+INCIDENTES!AE48*'BASE LIQUIDACION'!$B$13)) -> 37904.654
A49: APARTADO | B49: =VLOOKUP(A49,'CENTRO DE COSTOS'!A:D,4,FALSE) -> JUAN SEBASTIÁN RÍOS CASTRILLÓN | C49: =VLOOKUP(A49,'CENTRO DE COSTOS'!A:D,2,FALSE) -> 0004-0005 | D49: 5837 | E49: 2782755 | F49: 81350 | G49: INCIDENTE | H49: ANTIOQUIA | I49: TURBO | J49: DISTRICOL ELECTRODOMESTICOS | K49: REDEBAN | L49: FO-25-1579528 | FO-25-1573391 | M49: 45923.636 | N49: 45925.635 | O49: NO | P49: USUARIO | Q49: MANTENIMIENTO | R49: MANTENIMIENTO GENERAL | U49: CERRADO | V49: 23/09/2025 SE ESCALA PARA VISITA. LLAMAR ANTES DE VISITAR, CONFIRMAR FALLA Y DATOS | 24/09/2025 SE REALIZA CAMBIO DE DATÁFONO POR ALERTA IRRUPTION. CLIENTE TIENE PORTAL CAUTIVO Y DEBE ANEXAR LA DIRECCIÓN MAC DEL DATSFONO AL ROUTER DEL CLIENTE PARA TENER ACCESO A INTERNET. CLIENTE INDICA QUE YA LE INFORMO AL PROVEEDOR DE INTERNET PARA ACEPTAR LA MAC DEL DATAFINO EN SU RED. CLIENTE INDICARA A LINEA BANCOLOMBIA CUANDO PROVEEDOR DE INTERNET LE SOLUCIONE. 25/09/2025 OPERADOR DE INTERNET ARREGLO SU CANAL DEJANDO OPERATIVO EL DATAFONO. CLIENTE INDICA TRANSACCIONES OK | W49: VISITA_TÉCNICA | X49: 0 | Y49: TIPO II | Z49: TERRESTRE | AA49: CASTRO HENAO DANIEL ESTEBAN | AB49: 1 | AC49: 0 | AD49: 0 | AE49: 0 | AF49: =IF(W49="SOPORTE_TELEFÓNICO",'BASE LIQUIDACION'!$B$10,IF(Y49="TIPO I",'BASE LIQUIDACION'!$C$3,IF(Y49="TIPO II",'BASE LIQUIDACION'!$C$4,IF(Y49="TIPO III",'BASE LIQUIDACION'!$C$5,'BASE LIQUIDACION'!$C$7)))) -> 163813.56 | AG49: =IF(W49="SOPORTE_TELEFÓNICO",'BASE LIQUIDACION'!$B$10,(AB49*AF49+AC49*'BASE LIQUIDACION'!$B$12+AD49*'BASE LIQUIDACION'!$B$11+INCIDENTES!AE49*'BASE LIQUIDACION'!$B$13)) -> 163813.56
A50: PASTO | B50: =VLOOKUP(A50,'CENTRO DE COSTOS'!A:D,4,FALSE) -> DIEGO FERNANDO HENAO CARDONA | C50: =VLOOKUP(A50,'CENTRO DE COSTOS'!A:D,2,FALSE) -> 0004-0003 | D50: 52001 | E50: 2781894 | F50: 56861 | G50: INCIDENTE | H50: NARIÑO | I50: PASTO | J50: BARRIO TOROBAJO PASTO 1 | K50: REDEBAN | L50: FO-25-1572570 | M50: 45923.578 | N50: 45924.511 | O50: NO | P50: USUARIO | Q50: COMUNICACION | R50: CONEXIONES DE COMERCIO | U50: CERRADO | V50: 23/09/2025 SE ESCALA PARA VISITA. LLAMAR ANTES DE VISITAR, CONFIRMAR FALLA Y DATOS | 24/09/2025 SE ENCUENTRA DATAFONO SIN CONEXIÓN SE REALIZA MANTENIMIENTO Y REVISIÓN DE CABLES Y SE LOGRA CONEXIÓN EXITOSA CONFIGURACIÓN OK PARÁMETROS OK Y SE REALIZAN PRUEBAS ÉXITOSAS DE TRANSACCIONES | W50: VISITA_TÉCNICA | X50: IIOZZ209 | Y50: TIPO I | Z50: TERRESTRE | AA50: PAZ MARTINEZ RICHARD HUMBERTO | AB50: 1 | AC50: 0 | AD50: 0 | AE50: 0 | AF50: =IF(W50="SOPORTE_TELEFÓNICO",'BASE LIQUIDACION'!$B$10,IF(Y50="TIPO I",'BASE LIQUIDACION'!$C$3,IF(Y50="TIPO II",'BASE LIQUIDACION'!$C$4,IF(Y50="TIPO III",'BASE LIQUIDACION'!$C$5,'BASE LIQUIDACION'!$C$7)))) -> 65960.474 | AG50: =IF(W50="SOPORTE_TELEFÓNICO",'BASE LIQUIDACION'!$B$10,(AB50*AF50+AC50*'BASE LIQUIDACION'!$B$12+AD50*'BASE LIQUIDACION'!$B$11+INCIDENTES!AE50*'BASE LIQUIDACION'!$B$13)) -> 65960.474
A51: MEDELLIN | B51: =VLOOKUP(A51,'CENTRO DE COSTOS'!A:D,4,FALSE) -> JUAN SEBASTIÁN RÍOS CASTRILLÓN | C51: =VLOOKUP(A51,'CENTRO DE COSTOS'!A:D,2,FALSE) -> 0004-0005 | D51: 5001 | E51: 2781349 | F51: 38424 | G51: INCIDENTE | H51: ANTIOQUIA | I51: MEDELLIN | J51: BARRIO SANTA CRUZ MEDELLIN 4 | K51: REDEBAN | L51: FO-25-1571329 | M51: 45923.491 | N51: 45923.635 | O51: NO | P51: USUARIO | Q51: MANTENIMIENTO | R51: MANTENIMIENTO GENERAL | U51: CERRADO | V51: 23/09/2025 SE ESCALA PARA VISITA. LLAMAR ANTES DE VISITAR, CONFIRMAR FALLA Y DATOS | 23/09/2025 SE HACE VISITA OK EQUIPOS OPERANDO CON NORMALIDAD. SE HACE MANTENIMIENTO OK DE DATÁFONO | W51: VISITA_TÉCNICA | X51: AA00X490 | Y51: TIPO I | Z51: TERRESTRE | AA51: DIAZ ZABALA FRANCIS DUBAN | AB51: 1 | AC51: 0 | AD51: 0 | AE51: 0 | AF51: =IF(W51="SOPORTE_TELEFÓNICO",'BASE LIQUIDACION'!$B$10,IF(Y51="TIPO I",'BASE LIQUIDACION'!$C$3,IF(Y51="TIPO II",'BASE LIQUIDACION'!$C$4,IF(Y51="TIPO III",'BASE LIQUIDACION'!$C$5,'BASE LIQUIDACION'!$C$7)))) -> 65960.474 | AG51: =IF(W51="SOPORTE_TELEFÓNICO",'BASE LIQUIDACION'!$B$10,(AB51*AF51+AC51*'BASE LIQUIDACION'!$B$12+AD51*'BASE LIQUIDACION'!$B$11+INCIDENTES!AE51*'BASE LIQUIDACION'!$B$13)) -> 65960.474
A52: BOGOTA | B52: =VLOOKUP(A52,'CENTRO DE COSTOS'!A:D,4,FALSE) -> WILLIAM ASDRUBAL ROZO ROZO | C52: =VLOOKUP(A52,'CENTRO DE COSTOS'!A:D,2,FALSE) -> 0004-0004 | D52: 11001 | E52: 2780601 | F52: 80771 | G52: INCIDENTE | H52: CUNDINAMARCA | I52: BOGOTA | J52: BARRIO LA IGUALDAD BOGOTA 3 | K52: REDEBAN | L52: FO-25-1571099 | M52: 45923.456 | N52: 45924.41 | O52: NO | P52: ENTIDAD | Q52: ERROR DE TRANSACCIONES | R52: TRANSACCION NO PERMITIDA | U52: CERRADO | V52: 23/09/2025 SE ESCALA PARA VISITA. LLAMAR ANTES DE VISITAR, CONFIRMAR FALLA Y DATOS | 24/09/2025 SE REALIZA VISITA A CB PARA ATENDER INCIDENTE CLIENTE INDICA QUE YA ESTÁ FUNCIONANDO SIN NOVEDAD | W52: VISITA_TÉCNICA | X52: F8ZZZ025 | Y52: TIPO I | Z52: TERRESTRE | AA52: GALINDO ROJAS LUIS FELIPE | AB52: 1 | AC52: 0 | AD52: 0 | AE52: 0 | AF52: =IF(W52="SOPORTE_TELEFÓNICO",'BASE LIQUIDACION'!$B$10,IF(Y52="TIPO I",'BASE LIQUIDACION'!$C$3,IF(Y52="TIPO II",'BASE LIQUIDACION'!$C$4,IF(Y52="TIPO III",'BASE LIQUIDACION'!$C$5,'BASE LIQUIDACION'!$C$7)))) -> 65960.474 | AG52: =IF(W52="SOPORTE_TELEFÓNICO",'BASE LIQUIDACION'!$B$10,(AB52*AF52+AC52*'BASE LIQUIDACION'!$B$12+AD52*'BASE LIQUIDACION'!$B$11+INCIDENTES!AE52*'BASE LIQUIDACION'!$B$13)) -> 65960.474
A53: BUCARAMANGA | B53: =VLOOKUP(A53,'CENTRO DE COSTOS'!A:D,4,FALSE) -> MIGUEL JULIÁN HERNÁNDEZ GUARÍN | C53: =VLOOKUP(A53,'CENTRO DE COSTOS'!A:D,2,FALSE) -> 0004-0008 | D53: 68895 | E53: 2780328 | F53: 80820 | G53: INCIDENTE | H53: SANTANDER | I53: ZAPATOCA | J53: BARRIO SANTA BARBARA ZAPATOCA 2 | K53: REDEBAN | L53: FO-25-1571145 | M53: 45923.44 | N53: 45924.728 | O53: NO | P53: USUARIO | Q53: COMUNICACION | R53: CONEXIONES DE COMERCIO | U53: CERRADO | V53: 23/09/2025 EN COMUNICACIÓN CON LA SRA YOSARY MILENA MANJARRES RODRIGUEZ AL NÚMERO 3008873436 NOS INFORMA QUE LA FALLA ES CABLE DE RED DESCONECTADO, CONFIRMA DATOS E INDICA QUE LA RED ES REDEBAN, SE ESCALA PARA VISITA | 24/09/2025 EN COMUNICACIÓN CON SEÑORA MILENA MANJARREZ NOS INFORMA QUE AYER EN LA TARDE Y EL DÍA DE HOY YA ESTÁ TRABAJANDO NORMALMENTE AL PARECER ERA FALA DEL INTERNET, POR LO ANTERIOR INDICA QUE NO ES NECESARIO YA QUE ESTÁ OPERANDO CORRECTAMENTE | W53: SOPORTE_TELEFÓNICO | X53: 0 | Y53: TIPO III | Z53: TERRESTRE | AA53: PEÑA DIAZ IVAN YESID | AB53: 0 | AC53: 0 | AD53: 0 | AE53: 0 | AF53: =IF(W53="SOPORTE_TELEFÓNICO",'BASE LIQUIDACION'!$B$10,IF(Y53="TIPO I",'BASE LIQUIDACION'!$C$3,IF(Y53="TIPO II",'BASE LIQUIDACION'!$C$4,IF(Y53="TIPO III",'BASE LIQUIDACION'!$C$5,'BASE LIQUIDACION'!$C$7)))) -> 37904.654 | AG53: =IF(W53="SOPORTE_TELEFÓNICO",'BASE LIQUIDACION'!$B$10,(AB53*AF53+AC53*'BASE LIQUIDACION'!$B$12+AD53*'BASE LIQUIDACION'!$B$11+INCIDENTES!AE53*'BASE LIQUIDACION'!$B$13)) -> 37904.654
A54: MEDELLIN | B54: =VLOOKUP(A54,'CENTRO DE COSTOS'!A:D,4,FALSE) -> JUAN SEBASTIÁN RÍOS CASTRILLÓN | C54: =VLOOKUP(A54,'CENTRO DE COSTOS'!A:D,2,FALSE) -> 0004-0005 | D54: 5001 | E54: 2777679 | F54: 31129 | G54: INCIDENTE | H54: ANTIOQUIA | I54: MEDELLIN | J54: BARRIO MORAVIA 2 | K54: REDEBAN | L54: FO-25-1568225 | M54: 45923.333 | N54: 45923.539 | O54: NO | P54: USUARIO | Q54: NO ENCIENDE | R54: CONEXIONES DE COMERCIO | U54: CERRADO | V54: 23/09/2025 SE ESCALA PARA VISITA. LLAMAR ANTES DE VISITAR, CONFIRMAR FALLA Y DATOS | 23/09/2025 SE HACE MANTENIMIENTO OK SE VALIDA CABLEDO DEL COMERCIO Y SE ORGÁNICA CABLEADOS | W54: VISITA_TÉCNICA | X54: BL01B278 | Y54: TIPO I | Z54: TERRESTRE | AA54: DIAZ ZABALA FRANCIS DUBAN | AB54: 1 | AC54: 0 | AD54: 0 | AE54: 0 | AF54: =IF(W54="SOPORTE_TELEFÓNICO",'BASE LIQUIDACION'!$B$10,IF(Y54="TIPO I",'BASE LIQUIDACION'!$C$3,IF(Y54="TIPO II",'BASE LIQUIDACION'!$C$4,IF(Y54="TIPO III",'BASE LIQUIDACION'!$C$5,'BASE LIQUIDACION'!$C$7)))) -> 65960.474 | AG54: =IF(W54="SOPORTE_TELEFÓNICO",'BASE LIQUIDACION'!$B$10,(AB54*AF54+AC54*'BASE LIQUIDACION'!$B$12+AD54*'BASE LIQUIDACION'!$B$11+INCIDENTES!AE54*'BASE LIQUIDACION'!$B$13)) -> 65960.474
A55: PASTO | B55: =VLOOKUP(A55,'CENTRO DE COSTOS'!A:D,4,FALSE) -> DIEGO FERNANDO HENAO CARDONA | C55: =VLOOKUP(A55,'CENTRO DE COSTOS'!A:D,2,FALSE) -> 0004-0003 | D55: 52001 | E55: 2777112 | F55: 81018 | G55: INCIDENTE | H55: NARIÑO | I55: PASTO | J55: DISTRICOL DROG FARMAMEDIC | K55: REDEBAN | L55: FO-25-1566513 | M55: 45922.68 | N55: 45923.48 | O55: NO | P55: USUARIO | Q55: LECTOR DE BARRAS | R55: CAPACITACION MANIPULACION DE COMERCIO | U55: CERRADO | V55: 22/09/2025 SE ESCALA PARA VISITA. LLAMAR ANTES DE VISITAR, CONFIRMAR FALLA Y DATOS | 23/09/2025 SE VERIFICÓ FALLA DE LECTOR DE CÓDIGO DE BARRAS NO PERMITE LEER CÓDIGOS DE CEDENAR SE LE DIO EL CÓDIGO DE CONVENIO SE EJECUTAN PRUEBAS TX EXITOSAS, A SU VEZ INDICA FALLA DE IMPRESIÓN SALE ENTRECORTADO LA INFORMACIÓN ESO ES PORQUE NO CIERRA BIEN LA TAPA DEL ROLLOS, SE REALIZÓ PRUEBAS TX EXITOSAS QUEDA OPERATIVO. | W55: VISITA_TÉCNICA | X55: FJZZZ920 | Y55: TIPO I | Z55: TERRESTRE | AA55: REMICIO AMADO JOHN HEBER | AB55: 1 | AC55: 0 | AD55: 0 | AE55: 0 | AF55: =IF(W55="SOPORTE_TELEFÓNICO",'BASE LIQUIDACION'!$B$10,IF(Y55="TIPO I",'BASE LIQUIDACION'!$C$3,IF(Y55="TIPO II",'BASE LIQUIDACION'!$C$4,IF(Y55="TIPO III",'BASE LIQUIDACION'!$C$5,'BASE LIQUIDACION'!$C$7)))) -> 65960.474 | AG55: =IF(W55="SOPORTE_TELEFÓNICO",'BASE LIQUIDACION'!$B$10,(AB55*AF55+AC55*'BASE LIQUIDACION'!$B$12+AD55*'BASE LIQUIDACION'!$B$11+INCIDENTES!AE55*'BASE LIQUIDACION'!$B$13)) -> 65960.474
A56: NEIVA | B56: =VLOOKUP(A56,'CENTRO DE COSTOS'!A:D,4,FALSE) -> KEVIN ALEXIS CORZO BUSTOS | C56: =VLOOKUP(A56,'CENTRO DE COSTOS'!A:D,2,FALSE) -> 0004-0007 | D56: 41551 | E56: 2774399 | F56: 80538 | G56: INCIDENTE | H56: HUILA | I56: PITALITO | J56: BARRIO AGUA BLANCA PITALITO 4 | K56: REDEBAN | L56: FO-25-1564206 | M56: 45922.487 | N56: 45924.389 | O56: NO | P56: USUARIO | Q56: COMUNICACION | R56: CONEXIONES DE COMERCIO | U56: CERRADO | V56: 22/09/2025 SE INTENTA COMUNICACIÓN DESDE EL N. CORPORATIVO A LA SRA YESICA TRUJILLO PERDOMO AL NÚMERO 3144434059 PARA CONFIRMAR DATOS Y FALLAS PERO NO HAY CONTACTO, SE ESCALA A COORDINADOR DE ZONA PARA VALIDAR EN SITIO | 24/09/2025 SE REALIZA VISITA AL PUNTO, SE EVIDENCIA UNA MALA CONEXION DE INTERNET POR PARTE DEL COMERCIO LA CUAL SE CORRIGE , PPRUEBAS OK, CB OPERATIVO. | W56: VISITA_TÉCNICA | X56: SEZZZ144 | Y56: TIPO III | Z56: TERRESTRE | AA56: DEVIA REINOSO JUAN CARLOS | AB56: 1 | AC56: 0 | AD56: 0 | AE56: 0 | AF56: =IF(W56="SOPORTE_TELEFÓNICO",'BASE LIQUIDACION'!$B$10,IF(Y56="TIPO I",'BASE LIQUIDACION'!$C$3,IF(Y56="TIPO II",'BASE LIQUIDACION'!$C$4,IF(Y56="TIPO III",'BASE LIQUIDACION'!$C$5,'BASE LIQUIDACION'!$C$7)))) -> 275728.38 | AG56: =IF(W56="SOPORTE_TELEFÓNICO",'BASE LIQUIDACION'!$B$10,(AB56*AF56+AC56*'BASE LIQUIDACION'!$B$12+AD56*'BASE LIQUIDACION'!$B$11+INCIDENTES!AE56*'BASE LIQUIDACION'!$B$13)) -> 275728.38
A57: TUNJA | B57: =VLOOKUP(A57,'CENTRO DE COSTOS'!A:D,4,FALSE) -> MIGUEL JULIÁN HERNÁNDEZ GUARÍN | C57: =VLOOKUP(A57,'CENTRO DE COSTOS'!A:D,2,FALSE) -> 0004-0008 | D57: 15176 | E57: 2772904 | F57: 81495 | G57: INCIDENTE | H57: BOYACA | I57: CHIQUINQUIRA | J57: DISTRICOL TECHNOWORLD CHIQUINQ | K57: REDEBAN | L57: FO-25-1563147 | M57: 45922.399 | N57: 45922.628 | O57: NO | P57: USUARIO | Q57: MANTENIMIENTO | R57: MANTENIMIENTO GENERAL | U57: CERRADO | V57: 22/09/2025 EN COMUNICACIÓN CON LA SRA KAREN ALEXANDRA BENAVIDEZ AL NÚMERO 3223543827 NOS INFORMA QUE LA FALLA ES DATAFONO NO IMPRIME VOUCHERS, SE ESCALA A COORDINADOR DE ZONA PARA CONFIRMAR FALLA EN SITIO | 22/09/2025 SE VISITA COMERCIO , SE VALIDA EQUIPO TRABAJANDO CORRECTAMENTE EN LA IMPRESIÓN , SE REALIZA BORRADO DE EQUIPO CARGANDO NUEVAMENTE S.O Y VERSIÓN 10.3 N DEJANDO PRUEBAS OK SIN TELECARGA NO AUTORIZADA | W57: VISITA_TÉCNICA | X57: FSZZZ882 | Y57: TIPO III | Z57: TERRESTRE | AA57: ALVARADO MORENO CRISTHIAN | AB57: 1 | AC57: 0 | AD57: 0 | AE57: 0 | AF57: =IF(W57="SOPORTE_TELEFÓNICO",'BASE LIQUIDACION'!$B$10,IF(Y57="TIPO I",'BASE LIQUIDACION'!$C$3,IF(Y57="TIPO II",'BASE LIQUIDACION'!$C$4,IF(Y57="TIPO III",'BASE LIQUIDACION'!$C$5,'BASE LIQUIDACION'!$C$7)))) -> 275728.38 | AG57: =IF(W57="SOPORTE_TELEFÓNICO",'BASE LIQUIDACION'!$B$10,(AB57*AF57+AC57*'BASE LIQUIDACION'!$B$12+AD57*'BASE LIQUIDACION'!$B$11+INCIDENTES!AE57*'BASE LIQUIDACION'!$B$13)) -> 275728.38
A58: BOGOTA | B58: =VLOOKUP(A58,'CENTRO DE COSTOS'!A:D,4,FALSE) -> WILLIAM ASDRUBAL ROZO ROZO | C58: =VLOOKUP(A58,'CENTRO DE COSTOS'!A:D,2,FALSE) -> 0004-0004 | D58: 99001 | E58: 2772350 | F58: 37352 | G58: INCIDENTE | H58: VICHADA | I58: PUERTO CARREÑO | J58: BARRIO LA PLAZUELA PUERTO CARR | K58: REDEBAN | L58: FO-25-1565018 | M58: 45922.383 | N58: 45922.552 | O58: NO | P58: USUARIO | Q58: COMUNICACION | R58: CANAL DEL COMERCIO | U58: CERRADO | V58: 0 | W58: SOPORTE_TELEFÓNICO | X58: 0 | Y58: TIPO IV ESPECIAL | Z58: AEREO | AA58: GOMEZ FERRARO JOHANA | AB58: 0 | AC58: 0 | AD58: 0 | AE58: 0 | AF58: =IF(W58="SOPORTE_TELEFÓNICO",'BASE LIQUIDACION'!$B$10,IF(Y58="TIPO I",'BASE LIQUIDACION'!$C$3,IF(Y58="TIPO II",'BASE LIQUIDACION'!$C$4,IF(Y58="TIPO III",'BASE LIQUIDACION'!$C$5,'BASE LIQUIDACION'!$C$7)))) -> 37904.654 | AG58: =IF(W58="SOPORTE_TELEFÓNICO",'BASE LIQUIDACION'!$B$10,(AB58*AF58+AC58*'BASE LIQUIDACION'!$B$12+AD58*'BASE LIQUIDACION'!$B$11+INCIDENTES!AE58*'BASE LIQUIDACION'!$B$13)) -> 37904.654
A59: VILLAVICENCIO | B59: =VLOOKUP(A59,'CENTRO DE COSTOS'!A:D,4,FALSE) -> KEVIN ALEXIS CORZO BUSTOS | C59: =VLOOKUP(A59,'CENTRO DE COSTOS'!A:D,2,FALSE) -> 0004-0007 | D59: 50573 | E59: 2772221 | F59: 80563 | G59: INCIDENTE | H59: META | I59: PUERTO LOPEZ | J59: BARRIO LA SABANA PUERTO LOPEZ | K59: REDEBAN | L59: FO-25-1563188 | M59: 45922.376 | N59: 45923.424 | O59: NO | P59: USUARIO | Q59: CIERRE | R59: COMERCIO NO REALIZA CIERRE | U59: CERRADO | V59: 22/09/2025 SE ESCALA PARA VISITA. LLAMAR ANTES DE VISITAR, CONFIRMAR FALLA Y DATOS | 23/09/2025 SE REALIZA CONTACTO TELEFÓNICO 320974056 CON LA SEÑORA MILVIA SE REALIZA BORRADO DE TRANSACCIÓN SE LE BRINDA ASESORÍA SOBRE EL BUEN USO DEL DATÁFONO Y CIERRE DIARIO OK SIN NOVEDAD | W59: SOPORTE_TELEFÓNICO | X59: 0 | Y59: TIPO II | Z59: TERRESTRE | AA59: CASTRILLON URREA LONDIER LEANDRO | AB59: 0 | AC59: 0 | AD59: 0 | AE59: 0 | AF59: =IF(W59="SOPORTE_TELEFÓNICO",'BASE LIQUIDACION'!$B$10,IF(Y59="TIPO I",'BASE LIQUIDACION'!$C$3,IF(Y59="TIPO II",'BASE LIQUIDACION'!$C$4,IF(Y59="TIPO III",'BASE LIQUIDACION'!$C$5,'BASE LIQUIDACION'!$C$7)))) -> 37904.654 | AG59: =IF(W59="SOPORTE_TELEFÓNICO",'BASE LIQUIDACION'!$B$10,(AB59*AF59+AC59*'BASE LIQUIDACION'!$B$12+AD59*'BASE LIQUIDACION'!$B$11+INCIDENTES!AE59*'BASE LIQUIDACION'!$B$13)) -> 37904.654
A60: CALI | B60: =VLOOKUP(A60,'CENTRO DE COSTOS'!A:D,4,FALSE) -> DIEGO FERNANDO HENAO CARDONA | C60: =VLOOKUP(A60,'CENTRO DE COSTOS'!A:D,2,FALSE) -> 0004-0003 | D60: 76001 | E60: 2772022 | F60: 20915 | G60: INCIDENTE | H60: VALLE DEL CAUCA | I60: CALI | J60: 2AGAFACIL PLAZA CAYCEDO | K60: REDEBAN | L60: FO-25-1562562 | M60: 45922.371 | N60: 45923.331 | O60: NO | P60: USUARIO | Q60: LECTOR DE BARRAS | R60: ERROR PAGOS PARCIALES DE FACTURAS | U60: CERRADO | V60: 22/09/2025 SE ESCALA PARA VISITA. LLAMAR ANTES DE VISITAR, CONFIRMAR FALLA Y DATOS | 22/09/2025 SE HABLA CON LA SEÑORA DIANA QUIEN INDICA QUE TIENE UN EQUIPO SIN LECTOR DE BARRAS QUE ELLLA LEGO HACE POCO AL PUNTO Y EL EQUIPO LO ENCONTRO SIN NADA Y REQUIERE LA INSTALACION DE UN NUEVO LECTOR, SE VALIDA INVENTARIO CON REDEBAN PERO EN EL PUNTO HAY 3 DATAFONOS Y FIGURAN 3 LECTORAS DE CODIGO DE BARRAS , SE HABLA CON PAOLA DE REDEBAN QUIEN INDICA QUE NO SE PUEDE INSTALAR EL LECTOR QUE EL CLIENTE DEBE PRIMERO COLOCAR UN DENUNCIO POR PERDIDA PARA REALIZAR EL REMPLAZO DEL MISMO TODA VEZ QUE EL INVENTARIO ESTA COMPLETO, SE LE INFORMA AL CLIENTE | W60: SOPORTE_TELEFÓNICO | X60: 0 | Y60: TIPO I | Z60: TERRESTRE | AA60: HENAO CARDONA DIEGO FERNANDO | AB60: 0 | AC60: 0 | AD60: 0 | AE60: 0 | AF60: =IF(W60="SOPORTE_TELEFÓNICO",'BASE LIQUIDACION'!$B$10,IF(Y60="TIPO I",'BASE LIQUIDACION'!$C$3,IF(Y60="TIPO II",'BASE LIQUIDACION'!$C$4,IF(Y60="TIPO III",'BASE LIQUIDACION'!$C$5,'BASE LIQUIDACION'!$C$7)))) -> 37904.654 | AG60: =IF(W60="SOPORTE_TELEFÓNICO",'BASE LIQUIDACION'!$B$10,(AB60*AF60+AC60*'BASE LIQUIDACION'!$B$12+AD60*'BASE LIQUIDACION'!$B$11+INCIDENTES!AE60*'BASE LIQUIDACION'!$B$13)) -> 37904.654
A61: VILLAVICENCIO | B61: =VLOOKUP(A61,'CENTRO DE COSTOS'!A:D,4,FALSE) -> KEVIN ALEXIS CORZO BUSTOS | C61: =VLOOKUP(A61,'CENTRO DE COSTOS'!A:D,2,FALSE) -> 0004-0007 | D61: 50223 | E61: 2771842 | F61: 80364 | G61: INCIDENTE | H61: META | I61: CUBARRAL | J61: BARRIO EL JARDIN CUBARRAL | K61: REDEBAN | L61: FO-25-1562409 | M61: 45922.36 | N61: 45923.567 | O61: NO | P61: USUARIO | Q61: USUARIOS | R61: TAPA MAL ASEGURADA | U61: CERRADO | V61: 22/09/2025 SE ESCALA PARA VISITA. LLAMAR ANTES DE VISITAR, CONFIRMAR FALLA Y DATOS | 23/09/2025 SE REALIZA VISITA A COMERCIO CLIENTE MANIFIESTA SERVICIO OPERATIVO EL DÍA DE HOY SE ENCUENTRA SIN NOVEDADES OK SE LE BRINDA ASESORÍA PARA EL CORRECTO FUNCIONAMIENTO | W61: VISITA_TÉCNICA | X61: LBZZZ622 | Y61: TIPO II | Z61: TERRESTRE | AA61: CASTRILLON URREA LONDIER LEANDRO | AB61: 1 | AC61: 0 | AD61: 0 | AE61: 0 | AF61: =IF(W61="SOPORTE_TELEFÓNICO",'BASE LIQUIDACION'!$B$10,IF(Y61="TIPO I",'BASE LIQUIDACION'!$C$3,IF(Y61="TIPO II",'BASE LIQUIDACION'!$C$4,IF(Y61="TIPO III",'BASE LIQUIDACION'!$C$5,'BASE LIQUIDACION'!$C$7)))) -> 163813.56 | AG61: =IF(W61="SOPORTE_TELEFÓNICO",'BASE LIQUIDACION'!$B$10,(AB61*AF61+AC61*'BASE LIQUIDACION'!$B$12+AD61*'BASE LIQUIDACION'!$B$11+INCIDENTES!AE61*'BASE LIQUIDACION'!$B$13)) -> 163813.56
A62: NEIVA | B62: =VLOOKUP(A62,'CENTRO DE COSTOS'!A:D,4,FALSE) -> KEVIN ALEXIS CORZO BUSTOS | C62: =VLOOKUP(A62,'CENTRO DE COSTOS'!A:D,2,FALSE) -> 0004-0007 | D62: 41001 | E62: 2771670 | F62: 80614 | G62: INCIDENTE | H62: HUILA | I62: NEIVA | J62: BARRIO CALIXTO LEIVA NEIVA 1 | K62: REDEBAN | L62: FO-25-1562465 | M62: 45922.359 | N62: 45922.644 | O62: NO | P62: USUARIO | Q62: LECTOR DE BARRAS | R62: ERROR PAGOS PARCIALES DE FACTURAS | U62: CERRADO | V62: 22/09/2025 SE ESCALA PARA VISITA. LLAMAR ANTES DE VISITAR, CONFIRMAR FALLA Y DATOS | 22/09/2025 SE REALIZA VISITA AL PUNTO, CLIENTE ÍNDICA QUE EL LECTOR NO LEE LOS CÓDIGOS DE BARRAS RURALES, SE LE INDICA AL CLIENTE QUE ESA CLASE DE CÓDIGO DE BARRAS NO LAS LEE EL LECTOR POR EL TAMAÑO. DE REALIZAN PRUEBAS CON OTROS CÓDIGOS Y FUNCIONAN OK, CB OPERATIVO | W62: VISITA_TÉCNICA | X62: V6ZZZ780 | Y62: TIPO I | Z62: TERRESTRE | AA62: DEVIA REINOSO JUAN CARLOS | AB62: 1 | AC62: 0 | AD62: 0 | AE62: 0 | AF62: =IF(W62="SOPORTE_TELEFÓNICO",'BASE LIQUIDACION'!$B$10,IF(Y62="TIPO I",'BASE LIQUIDACION'!$C$3,IF(Y62="TIPO II",'BASE LIQUIDACION'!$C$4,IF(Y62="TIPO III",'BASE LIQUIDACION'!$C$5,'BASE LIQUIDACION'!$C$7)))) -> 65960.474 | AG62: =IF(W62="SOPORTE_TELEFÓNICO",'BASE LIQUIDACION'!$B$10,(AB62*AF62+AC62*'BASE LIQUIDACION'!$B$12+AD62*'BASE LIQUIDACION'!$B$11+INCIDENTES!AE62*'BASE LIQUIDACION'!$B$13)) -> 65960.474
A63: MEDELLIN | B63: =VLOOKUP(A63,'CENTRO DE COSTOS'!A:D,4,FALSE) -> JUAN SEBASTIÁN RÍOS CASTRILLÓN | C63: =VLOOKUP(A63,'CENTRO DE COSTOS'!A:D,2,FALSE) -> 0004-0005 | D63: 5679 | E63: 2771714 | F63: 37908 | G63: INCIDENTE | H63: ANTIOQUIA | I63: SANTA BARBARA | J63: BARRIO GALERIA SANTA BARBARA | K63: REDEBAN | L63: FO-25-1562097 | M63: 45922.344 | N63: 45923.424 | O63: NO | P63: USUARIO | Q63: USUARIOS | R63: MALA MANIPULACION POS | U63: CERRADO | V63: 22/09/2025 SE ESCALA PARA VISITA. LLAMAR ANTES DE VISITAR, CONFIRMAR FALLA Y DATOS | 22/09/2025 SE EVIDENCIA QUE EL USUARIO USO LA PRIMERA PARTE DEL ROLLO QUE ESTÁBA NUEVO Y POR ESO NO IMPRIMIÓ BIEN SE HACEN PRUEBAS OK | W63: SOPORTE_TELEFÓNICO | X63: 0 | Y63: TIPO II | Z63: TERRESTRE | AA63: MONTOYA VELEZ ANDRES FELIPE | AB63: 0 | AC63: 0 | AD63: 0 | AE63: 0 | AF63: =IF(W63="SOPORTE_TELEFÓNICO",'BASE LIQUIDACION'!$B$10,IF(Y63="TIPO I",'BASE LIQUIDACION'!$C$3,IF(Y63="TIPO II",'BASE LIQUIDACION'!$C$4,IF(Y63="TIPO III",'BASE LIQUIDACION'!$C$5,'BASE LIQUIDACION'!$C$7)))) -> 37904.654 | AG63: =IF(W63="SOPORTE_TELEFÓNICO",'BASE LIQUIDACION'!$B$10,(AB63*AF63+AC63*'BASE LIQUIDACION'!$B$12+AD63*'BASE LIQUIDACION'!$B$11+INCIDENTES!AE63*'BASE LIQUIDACION'!$B$13)) -> 37904.654
A64: BOGOTA | B64: =VLOOKUP(A64,'CENTRO DE COSTOS'!A:D,4,FALSE) -> WILLIAM ASDRUBAL ROZO ROZO | C64: =VLOOKUP(A64,'CENTRO DE COSTOS'!A:D,2,FALSE) -> 0004-0004 | D64: 25286 | E64: 2770696 | F64: 79847 | G64: INCIDENTE | H64: CUNDINAMARCA | I64: FUNZA | J64: BARRIO CENTRO FUNZA FUNZA | K64: REDEBAN | L64: FO-25-1561042 | M64: 45921.572 | N64: 45922.65 | O64: NO | P64: USUARIO | Q64: CIERRE | R64: COMERCIO NO REALIZA CIERRE | U64: CERRADO | V64: 21/09/2025 SE ESCALA PARA VISITA. LLAMAR ANTES DE VISITAR, CONFIRMAR FALLA Y DATOS | 22/09/2025 SE LLAMA AL CLIENTE PARA VALIDAR LA FALLA, SE HABLÁ CON LA SRA DIANA HUERTAS QUIEN INDICA QUE SE LE ACUMULA LA INFORMACIÓN DE TRANSACCIONES DE LOS DÍAS Y AL HACER EL CIERRE NO BORRA LA INFO, SE LE INDAGA COMO REALIZA EL CIERRE Y SE DETECTA QUE LO ESTÁ HACIENDO ERRADAMENTE, POR LO QUE SE LE BRINDAN LOS PASOS PARA HACERLO DE LA MANERA CORRECTA, EL CLIENTE QUEDA SATISFECHO Y SE CIERRA LA ACTIVIDAD EXITOSA | W64: SOPORTE_TELEFÓNICO | X64: 0 | Y64: TIPO II | Z64: TERRESTRE | AA64: VEGA MANRIQUE JONATAN MAURICIO | AB64: 0 | AC64: 0 | AD64: 0 | AE64: 0 | AF64: =IF(W64="SOPORTE_TELEFÓNICO",'BASE LIQUIDACION'!$B$10,IF(Y64="TIPO I",'BASE LIQUIDACION'!$C$3,IF(Y64="TIPO II",'BASE LIQUIDACION'!$C$4,IF(Y64="TIPO III",'BASE LIQUIDACION'!$C$5,'BASE LIQUIDACION'!$C$7)))) -> 37904.654 | AG64: =IF(W64="SOPORTE_TELEFÓNICO",'BASE LIQUIDACION'!$B$10,(AB64*AF64+AC64*'BASE LIQUIDACION'!$B$12+AD64*'BASE LIQUIDACION'!$B$11+INCIDENTES!AE64*'BASE LIQUIDACION'!$B$13)) -> 37904.654
A65: MEDELLIN | B65: =VLOOKUP(A65,'CENTRO DE COSTOS'!A:D,4,FALSE) -> JUAN SEBASTIÁN RÍOS CASTRILLÓN | C65: =VLOOKUP(A65,'CENTRO DE COSTOS'!A:D,2,FALSE) -> 0004-0005 | D65: 5001 | E65: 2770660 | F65: 74979 | G65: INCIDENTE | H65: ANTIOQUIA | I65: MEDELLIN | J65: PTM MEDELLIN MERCADOS EL TIGRE | K65: REDEBAN | L65: FO-25-1560803 | M65: 45921.461 | N65: 45922.39 | O65: NO | P65: USUARIO | Q65: COMUNICACION | R65: CONEXIONES DE COMERCIO | U65: CERRADO | V65: 21/09/2025 SE ESCALA PARA VISITA. LLAMAR ANTES DE VISITAR, CONFIRMAR FALLA Y DATOS | 22/09/2025 SE LLAMA AL CLIENTE Y NOS INDICA QUE HABÍA UNA MALA CONEXIÓN CON CLARO, EL PROBLEMA QUEDÓ RESUELTO | W65: SOPORTE_TELEFÓNICO | X65: 0 | Y65: TIPO I | Z65: TERRESTRE | AA65: CARDONA MOLINA BROLIN STIVEN | AB65: 0 | AC65: 0 | AD65: 0 | AE65: 0 | AF65: =IF(W65="SOPORTE_TELEFÓNICO",'BASE LIQUIDACION'!$B$10,IF(Y65="TIPO I",'BASE LIQUIDACION'!$C$3,IF(Y65="TIPO II",'BASE LIQUIDACION'!$C$4,IF(Y65="TIPO III",'BASE LIQUIDACION'!$C$5,'BASE LIQUIDACION'!$C$7)))) -> 37904.654 | AG65: =IF(W65="SOPORTE_TELEFÓNICO",'BASE LIQUIDACION'!$B$10,(AB65*AF65+AC65*'BASE LIQUIDACION'!$B$12+AD65*'BASE LIQUIDACION'!$B$11+INCIDENTES!AE65*'BASE LIQUIDACION'!$B$13)) -> 37904.654
A66: BARRANQUILLA | B66: =VLOOKUP(A66,'CENTRO DE COSTOS'!A:D,4,FALSE) -> JOSE MAURICIO HERNANDEZ ROJAS | C66: =VLOOKUP(A66,'CENTRO DE COSTOS'!A:D,2,FALSE) -> 0004-0001 | D66: 8001 | E66: 2769611 | F66: 45896 | G66: INCIDENTE | H66: ATLANTICO | I66: BARRANQUILLA | J66: BARRIO ALTO PRADO BARRANQUILLA | K66: REDEBAN | L66: FO-25-1558507 | M66: 45920.415 | N66: 45920.59 | O66: NO | P66: USUARIO | Q66: COMUNICACION | R66: CONEXIONES DE COMERCIO | U66: CERRADO | V66: 20/09/2025 SE ESCALA PARA VISITA. LLAMAR ANTES DE VISITAR, CONFIRMAR FALLA Y DATOS | 20/09/2025 OKA | 20/09/2025 EN COMUNICACIÓN VÍA WASHAP AL NÚMERO 3004192612, LA SEÑORA LINA RAMÍREZ ME INFORMA QUE ERA UN PROBLEMA CON LA CONEXIÓN INTERNA, PERO QUE YA SOLUCIONARON Y QUE NO ES NECESARIA LA VISITA | W66: SOPORTE_TELEFÓNICO | X66: 0 | Y66: TIPO I | Z66: TERRESTRE | AA66: DE AVILA SIADES ALBERTO ENRIQUE | AB66: 0 | AC66: 0 | AD66: 0 | AE66: 0 | AF66: =IF(W66="SOPORTE_TELEFÓNICO",'BASE LIQUIDACION'!$B$10,IF(Y66="TIPO I",'BASE LIQUIDACION'!$C$3,IF(Y66="TIPO II",'BASE LIQUIDACION'!$C$4,IF(Y66="TIPO III",'BASE LIQUIDACION'!$C$5,'BASE LIQUIDACION'!$C$7)))) -> 37904.654 | AG66: =IF(W66="SOPORTE_TELEFÓNICO",'BASE LIQUIDACION'!$B$10,(AB66*AF66+AC66*'BASE LIQUIDACION'!$B$12+AD66*'BASE LIQUIDACION'!$B$11+INCIDENTES!AE66*'BASE LIQUIDACION'!$B$13)) -> 37904.654
A67: BARRANQUILLA | B67: =VLOOKUP(A67,'CENTRO DE COSTOS'!A:D,4,FALSE) -> JOSE MAURICIO HERNANDEZ ROJAS | C67: =VLOOKUP(A67,'CENTRO DE COSTOS'!A:D,2,FALSE) -> 0004-0001 | D67: 8296 | E67: 2768866 | F67: 49496 | G67: INCIDENTE | H67: ATLANTICO | I67: GALAPA | J67: DISTRICOL VARIEDADES KAROLAY | K67: REDEBAN | L67: FO-25-1557594 | M67: 45920.333 | N67: 45920.575 | O67: NO | P67: USUARIO | Q67: COMUNICACION | R67: CONEXIONES DE COMERCIO | U67: CERRADO | V67: 20/09/2025 SE ESCALA PARA VISITA. LLAMAR ANTES DE VISITAR, CONFIRMAR FALLA Y DATOS | 20/09/2025 SE REALIZA VISITA SE PROCEDE A VALIDAR DATAFONO Y TODOS OK ,INTERNET OK , SE VALIDA EL CONECTOR DEL CABLE DE RED DEL CLIENTE POSIBLE FRACTURA, SE CAMBIA CONECTOR SE HACEN PRUEBAS Y TODO OK | W67: VISITA_TÉCNICA | X67: AD00Q073 | Y67: TIPO I | Z67: TERRESTRE | AA67: PORRAS CASTRO DARLON NASCK | AB67: 1 | AC67: 0 | AD67: 0 | AE67: 0 | AF67: =IF(W67="SOPORTE_TELEFÓNICO",'BASE LIQUIDACION'!$B$10,IF(Y67="TIPO I",'BASE LIQUIDACION'!$C$3,IF(Y67="TIPO II",'BASE LIQUIDACION'!$C$4,IF(Y67="TIPO III",'BASE LIQUIDACION'!$C$5,'BASE LIQUIDACION'!$C$7)))) -> 65960.474 | AG67: =IF(W67="SOPORTE_TELEFÓNICO",'BASE LIQUIDACION'!$B$10,(AB67*AF67+AC67*'BASE LIQUIDACION'!$B$12+AD67*'BASE LIQUIDACION'!$B$11+INCIDENTES!AE67*'BASE LIQUIDACION'!$B$13)) -> 65960.474
A68: MEDELLIN | B68: =VLOOKUP(A68,'CENTRO DE COSTOS'!A:D,4,FALSE) -> JUAN SEBASTIÁN RÍOS CASTRILLÓN | C68: =VLOOKUP(A68,'CENTRO DE COSTOS'!A:D,2,FALSE) -> 0004-0005 | D68: 5001 | E68: 2768860 | F68: 21681 | G68: INCIDENTE | H68: ANTIOQUIA | I68: MEDELLIN | J68: BARRIO BLANQUIZAL MEDELLIN | K68: REDEBAN | L68: FO-25-1557598 | M68: 45920.333 | N68: 45920.578 | O68: NO | P68: USUARIO | Q68: MANTENIMIENTO | R68: MANTENIMIENTO GENERAL | U68: CERRADO | V68: 20/09/2025 SE ESCALA PARA VISITA. LLAMAR ANTES DE VISITAR, CONFIRMAR FALLA Y DATOS | 20/09/2025 SE REALIZA MANTENIMIENTO Y SE EXPLICA AL USUARIO CONO HACER CORRECTAMENTE LOS CIERRES, PRUEBAS OK | W68: VISITA_TÉCNICA | X68: AAVZZ111 | Y68: TIPO I | Z68: TERRESTRE | AA68: CARDONA MOLINA BROLIN STIVEN | AB68: 1 | AC68: 0 | AD68: 0 | AE68: 0 | AF68: =IF(W68="SOPORTE_TELEFÓNICO",'BASE LIQUIDACION'!$B$10,IF(Y68="TIPO I",'BASE LIQUIDACION'!$C$3,IF(Y68="TIPO II",'BASE LIQUIDACION'!$C$4,IF(Y68="TIPO III",'BASE LIQUIDACION'!$C$5,'BASE LIQUIDACION'!$C$7)))) -> 65960.474 | AG68: =IF(W68="SOPORTE_TELEFÓNICO",'BASE LIQUIDACION'!$B$10,(AB68*AF68+AC68*'BASE LIQUIDACION'!$B$12+AD68*'BASE LIQUIDACION'!$B$11+INCIDENTES!AE68*'BASE LIQUIDACION'!$B$13)) -> 65960.474
A69: MEDELLIN | B69: =VLOOKUP(A69,'CENTRO DE COSTOS'!A:D,4,FALSE) -> JUAN SEBASTIÁN RÍOS CASTRILLÓN | C69: =VLOOKUP(A69,'CENTRO DE COSTOS'!A:D,2,FALSE) -> 0004-0005 | D69: 5631 | E69: 2766731 | F69: 35686 | G69: INCIDENTE | H69: ANTIOQUIA | I69: SABANETA | J69: DISTRICOL TIENDA MARIGU | K69: REDEBAN | L69: FO-25-1554971 | M69: 45919.503 | N69: 45920.553 | O69: NO | P69: USUARIO | Q69: LECTOR DE TARJETAS | R69: OBSTRUCCION DEL LECTOR | U69: CERRADO | V69: 19/09/2025 SE ESCALA PARA VISITA. LLAMAR ANTES DE VISITAR, CONFIRMAR FALLA Y DATOS | 20/09/2025 SE REALIZÓ GESTIÓN TELEFÓNICA SE HABLÓ CON L SEÑORA MARÍA VÉLEZ NOS INDICA QUE SE ENCUENTRA HACIENDO COMPENSACIÓN EN EL PARQUE DE SABANETA Y NOS PODRÁ ATENDER DESPUÉS DE LAS 12:30 | 20/09/2025 SE REALIZÓ CAMBIO DE EQUIPO POR LECTOR DE CHIP AVERIADO | W69: VISITA_TÉCNICA | X69: 9A005422 | Y69: TIPO I | Z69: TERRESTRE | AA69: CASTAÑEDA PALACIO CARLOS FELIPE | AB69: 1 | AC69: 0 | AD69: 0 | AE69: 0 | AF69: =IF(W69="SOPORTE_TELEFÓNICO",'BASE LIQUIDACION'!$B$10,IF(Y69="TIPO I",'BASE LIQUIDACION'!$C$3,IF(Y69="TIPO II",'BASE LIQUIDACION'!$C$4,IF(Y69="TIPO III",'BASE LIQUIDACION'!$C$5,'BASE LIQUIDACION'!$C$7)))) -> 65960.474 | AG69: =IF(W69="SOPORTE_TELEFÓNICO",'BASE LIQUIDACION'!$B$10,(AB69*AF69+AC69*'BASE LIQUIDACION'!$B$12+AD69*'BASE LIQUIDACION'!$B$11+INCIDENTES!AE69*'BASE LIQUIDACION'!$B$13)) -> 65960.474
A70: TUNJA | B70: =VLOOKUP(A70,'CENTRO DE COSTOS'!A:D,4,FALSE) -> MIGUEL JULIÁN HERNÁNDEZ GUARÍN | C70: =VLOOKUP(A70,'CENTRO DE COSTOS'!A:D,2,FALSE) -> 0004-0008 | D70: 15001 | E70: 2765780 | F70: 66513 | G70: INCIDENTE | H70: BOYACA | I70: TUNJA | J70: BARRIO LOS MUISCAS TUNJA 5 | K70: REDEBAN | L70: FO-25-1555044 | M70: 45919.453 | N70: 45919.747 | O70: NO | P70: USUARIO | Q70: COMUNICACION | R70: CONEXIONES DE COMERCIO | U70: CERRADO | V70: 19/09/2025 SE ESCALA PARA VISITA. LLAMAR ANTES DE VISITAR, CONFIRMAR FALLA Y DATOS | 19/09/2025 SE VISITA CB MANTENIMIENTO CONFIGURACIÓN EQUIPO A INTERNET DE CLIENTE PRUEBAS EXITOSAS | W70: VISITA_TÉCNICA | X70: 4A00W933 | Y70: TIPO I | Z70: TERRESTRE | AA70: GONZALEZ GONZALEZ MARIO ALBERTO | AB70: 1 | AC70: 0 | AD70: 0 | AE70: 0 | AF70: =IF(W70="SOPORTE_TELEFÓNICO",'BASE LIQUIDACION'!$B$10,IF(Y70="TIPO I",'BASE LIQUIDACION'!$C$3,IF(Y70="TIPO II",'BASE LIQUIDACION'!$C$4,IF(Y70="TIPO III",'BASE LIQUIDACION'!$C$5,'BASE LIQUIDACION'!$C$7)))) -> 65960.474 | AG70: =IF(W70="SOPORTE_TELEFÓNICO",'BASE LIQUIDACION'!$B$10,(AB70*AF70+AC70*'BASE LIQUIDACION'!$B$12+AD70*'BASE LIQUIDACION'!$B$11+INCIDENTES!AE70*'BASE LIQUIDACION'!$B$13)) -> 65960.474
A71: TUNJA | B71: =VLOOKUP(A71,'CENTRO DE COSTOS'!A:D,4,FALSE) -> MIGUEL JULIÁN HERNÁNDEZ GUARÍN | C71: =VLOOKUP(A71,'CENTRO DE COSTOS'!A:D,2,FALSE) -> 0004-0008 | D71: 15761 | E71: 2765924 | F71: 78180 | G71: INCIDENTE | H71: BOYACA | I71: SOMONDOCO | J71: BARRIO CENTRO SOMONDOCO 3 | K71: REDEBAN | L71: FO-25-1555081 | M71: 45919.45 | N71: 45922.735 | O71: NO | P71: USUARIO | Q71: COMUNICACION | R71: CANAL DEL COMERCIO | U71: CERRADO | V71: 19/09/2025 SE ESCALA PARA VISITA. LLAMAR ANTES DE VISITAR, CONFIRMAR FALLA Y DATOS | 20/09/2025 EN COMUNICACIÓN CON LAS LÍNEAS 3167378110 Y 3132447685 NO SE LOGRA ESTABLECER CONTACTO CON EL CLIENTE, SE REALIZAN VARIOS INTENTOS PERO NO SE LOGRA ESTABLECER CONTACTO, SE INTENTARÁ REALIZAR CONTACTO EL DÍA LUNES 20/09 PARA ESTABLECER VISITA | 22/09/2025 EN COMUNICACIÓN CON LA LÍNEA 3167378110 RESPONDE LA SEÑORA DIANA CHIVATA SE LE INFORMA QUE DEBIDO AL TRASPORTE INTERMUNICIPAL SE ESTARÁ LLEGANDO AL MUNICIPIO SOBRE EL MEDIO DÍA 12PM DE HOY 22/09 POS DISPOSICIÓN DE TRASPORTE. CLIENTE ENTIENDE Y CONFIRMA DISPOSICIÓN. SE ATENDERÁ VISITA HOY 22/09 A LAS 12 PM. | 22/09/2025 SE REALIZA INSPECCIÓN DE RED, SE ENCUENTRA ROUTER REPETIDOR DESCONFIGURADO SE PROCEDE A REALIZAR LA CONFIGURACIÓN, PRUEBAS EXITOSAS. | W71: VISITA_TÉCNICA | X71: SXLZZ562 | Y71: TIPO III | Z71: TERRESTRE | AA71: HERRERA GARZON JEYSON STEVENT | AB71: 1 | AC71: 0 | AD71: 0 | AE71: 0 | AF71: =IF(W71="SOPORTE_TELEFÓNICO",'BASE LIQUIDACION'!$B$10,IF(Y71="TIPO I",'BASE LIQUIDACION'!$C$3,IF(Y71="TIPO II",'BASE LIQUIDACION'!$C$4,IF(Y71="TIPO III",'BASE LIQUIDACION'!$C$5,'BASE LIQUIDACION'!$C$7)))) -> 275728.38 | AG71: =IF(W71="SOPORTE_TELEFÓNICO",'BASE LIQUIDACION'!$B$10,(AB71*AF71+AC71*'BASE LIQUIDACION'!$B$12+AD71*'BASE LIQUIDACION'!$B$11+INCIDENTES!AE71*'BASE LIQUIDACION'!$B$13)) -> 275728.38
A72: BOGOTA | B72: =VLOOKUP(A72,'CENTRO DE COSTOS'!A:D,4,FALSE) -> WILLIAM ASDRUBAL ROZO ROZO | C72: =VLOOKUP(A72,'CENTRO DE COSTOS'!A:D,2,FALSE) -> 0004-0004 | D72: 25754 | E72: 2765005 | F72: 34350 | G72: INCIDENTE | H72: CUNDINAMARCA | I72: SOACHA | J72: COMCARD SOACHA LA 38 | K72: REDEBAN | L72: FO-25-1552895 | M72: 45919.378 | N72: 45919.726 | O72: NO | P72: USUARIO | Q72: CIERRE | R72: COMERCIO NO REALIZA CIERRE | U72: CERRADO | V72: 19/09/2025 SE ESCALA PARA VISITA. LLAMAR ANTES DE VISITAR, CONFIRMAR FALLA Y DATOS | 19/09/2025 SE LLEGA A DIRECCIÓN PARA ATENDER INCIDENTE LA SEÑORITA ELI LINARES INDICA QUE CANCELO LA VISITA ERA EL ROLLO QUE ESTABA DAÑADO INDICA SERVICIO OPERATIVO NO SE MANIPULA TERMINAL NO FIRMAN CONTROLES | W72: VISITA_TÉCNICA | X72: 0 | Y72: TIPO I | Z72: TERRESTRE | AA72: BUSTOS MORA DIEGO MANUEL | AB72: 1 | AC72: 0 | AD72: 0 | AE72: 0 | AF72: =IF(W72="SOPORTE_TELEFÓNICO",'BASE LIQUIDACION'!$B$10,IF(Y72="TIPO I",'BASE LIQUIDACION'!$C$3,IF(Y72="TIPO II",'BASE LIQUIDACION'!$C$4,IF(Y72="TIPO III",'BASE LIQUIDACION'!$C$5,'BASE LIQUIDACION'!$C$7)))) -> 65960.474 | AG72: =IF(W72="SOPORTE_TELEFÓNICO",'BASE LIQUIDACION'!$B$10,(AB72*AF72+AC72*'BASE LIQUIDACION'!$B$12+AD72*'BASE LIQUIDACION'!$B$11+INCIDENTES!AE72*'BASE LIQUIDACION'!$B$13)) -> 65960.474
A73: MEDELLIN | B73: =VLOOKUP(A73,'CENTRO DE COSTOS'!A:D,4,FALSE) -> JUAN SEBASTIÁN RÍOS CASTRILLÓN | C73: =VLOOKUP(A73,'CENTRO DE COSTOS'!A:D,2,FALSE) -> 0004-0005 | D73: 5001 | E73: 2764675 | F73: 69720 | G73: INCIDENTE | H73: ANTIOQUIA | I73: MEDELLIN | J73: DISTRICOL MERCADOS LA ROSA 2 | K73: REDEBAN | L73: FO-25-1552011 | M73: 45919.37 | N73: 45919.716 | O73: NO | P73: USUARIO | Q73: MANTENIMIENTO | R73: MANTENIMIENTO GENERAL | U73: CERRADO | V73: 19/09/2025 SE ESCALA PARA VISITA. LLAMAR ANTES DE VISITAR, CONFIRMAR FALLA Y DATOS | 19/09/2025 SE ENCENTRA EL EQUIPO CONGELADO CON EL MENSAJE WARNIN KEY, SE REINICIA EL EQUIPO Y SE ACOMODA MAGIC BOX, EQUIPO QUEDA FUNCIONANDO CORRECTAMENTE | W73: VISITA_TÉCNICA | X73: MN002486 | Y73: TIPO I | Z73: TERRESTRE | AA73: CARDONA MOLINA BROLIN STIVEN | AB73: 1 | AC73: 0 | AD73: 0 | AE73: 0 | AF73: =IF(W73="SOPORTE_TELEFÓNICO",'BASE LIQUIDACION'!$B$10,IF(Y73="TIPO I",'BASE LIQUIDACION'!$C$3,IF(Y73="TIPO II",'BASE LIQUIDACION'!$C$4,IF(Y73="TIPO III",'BASE LIQUIDACION'!$C$5,'BASE LIQUIDACION'!$C$7)))) -> 65960.474 | AG73: =IF(W73="SOPORTE_TELEFÓNICO",'BASE LIQUIDACION'!$B$10,(AB73*AF73+AC73*'BASE LIQUIDACION'!$B$12+AD73*'BASE LIQUIDACION'!$B$11+INCIDENTES!AE73*'BASE LIQUIDACION'!$B$13)) -> 65960.474
A74: CUCUTA | B74: =VLOOKUP(A74,'CENTRO DE COSTOS'!A:D,4,FALSE) -> MIGUEL JULIÁN HERNÁNDEZ GUARÍN | C74: =VLOOKUP(A74,'CENTRO DE COSTOS'!A:D,2,FALSE) -> 0004-0008 | D74: 54001 | E74: 2764373 | F74: 75391 | G74: INCIDENTE | H74: NORTE DE SANTANDER | I74: CUCUTA | J74: BARRIO ALFONSO LOPEZ CUCUTA 8 | K74: REDEBAN | L74: FO-25-1551745 | M74: 45919.351 | N74: 45919.714 | O74: NO | P74: USUARIO | Q74: COMUNICACION | R74: CANAL DEL COMERCIO | U74: CERRADO | V74: 19/09/2025 SE VISITA COMERCIO Y SE REALIZAN PRUEBAS SE ENCUENTRAN FUNCIONANDO EL EQUIPO, SE VERIFICAN PARÁMETROS TODO OK. | W74: VISITA_TÉCNICA | X74: V1009447 | Y74: TIPO I | Z74: TERRESTRE | AA74: TORRES MANTILLA JOSE DANIEL | AB74: 1 | AC74: 0 | AD74: 0 | AE74: 0 | AF74: =IF(W74="SOPORTE_TELEFÓNICO",'BASE LIQUIDACION'!$B$10,IF(Y74="TIPO I",'BASE LIQUIDACION'!$C$3,IF(Y74="TIPO II",'BASE LIQUIDACION'!$C$4,IF(Y74="TIPO III",'BASE LIQUIDACION'!$C$5,'BASE LIQUIDACION'!$C$7)))) -> 65960.474 | AG74: =IF(W74="SOPORTE_TELEFÓNICO",'BASE LIQUIDACION'!$B$10,(AB74*AF74+AC74*'BASE LIQUIDACION'!$B$12+AD74*'BASE LIQUIDACION'!$B$11+INCIDENTES!AE74*'BASE LIQUIDACION'!$B$13)) -> 65960.474
A75: PASTO | B75: =VLOOKUP(A75,'CENTRO DE COSTOS'!A:D,4,FALSE) -> DIEGO FERNANDO HENAO CARDONA | C75: =VLOOKUP(A75,'CENTRO DE COSTOS'!A:D,2,FALSE) -> 0004-0003 | D75: 52001 | E75: 2764356 | F75: 71539 | G75: INCIDENTE | H75: NARIÑO | I75: PASTO | J75: DISTRICOL EL CACHORRO REBAJA | K75: REDEBAN | L75: FO-25-1551567 | M75: 45919.346 | N75: 45919.708 | O75: NO | P75: ENTIDAD | Q75: ERROR DE TRANSACCIONES | R75: TRANSACCION NO PERMITIDA | U75: CERRADO | V75: 19/09/2025 SE ESCALA PARA VISITA. LLAMAR ANTES DE VISITAR, CONFIRMAR FALLA Y DATOS | 19/09/2025 SE REALIZA VALIDACIÓN CON EL CLIENTE LA SEÑORA PAOLA, QUIEN ME INDICA QUE NO LE SIRVEN LAS CONSIGNACIONES A CUENTAS CORRIENTES, SE REALIZA UNA PRUEBA DE UNA CONSIGNACIÓN A UNA CUENTA CORRIENTE Y LA TRANSACCIÓN SALE SIN PROBLEMA , LA CLIENTE DICE QUE ES QUE CON LA DE UN CLIENTE EN ESPECIFICO NO FUNCIONA, SE LE INDICA QUE NO ES PROBLEMA DEL DATAFONO, SE LE INDICA QUE DEBE REALIZAR LA CONSIGNACIÓN POR CUENTA CONVENIO PERO DEBE TENER LA REFERENCIA PARA PODER REALIZARLA. | W75: SOPORTE_TELEFÓNICO | X75: 0 | Y75: TIPO I | Z75: TERRESTRE | AA75: HENAO CARDONA DIEGO FERNANDO | AB75: 0 | AC75: 0 | AD75: 0 | AE75: 0 | AF75: =IF(W75="SOPORTE_TELEFÓNICO",'BASE LIQUIDACION'!$B$10,IF(Y75="TIPO I",'BASE LIQUIDACION'!$C$3,IF(Y75="TIPO II",'BASE LIQUIDACION'!$C$4,IF(Y75="TIPO III",'BASE LIQUIDACION'!$C$5,'BASE LIQUIDACION'!$C$7)))) -> 37904.654 | AG75: =IF(W75="SOPORTE_TELEFÓNICO",'BASE LIQUIDACION'!$B$10,(AB75*AF75+AC75*'BASE LIQUIDACION'!$B$12+AD75*'BASE LIQUIDACION'!$B$11+INCIDENTES!AE75*'BASE LIQUIDACION'!$B$13)) -> 37904.654
A76: PEREIRA | B76: =VLOOKUP(A76,'CENTRO DE COSTOS'!A:D,4,FALSE) -> DIEGO FERNANDO HENAO CARDONA | C76: =VLOOKUP(A76,'CENTRO DE COSTOS'!A:D,2,FALSE) -> 0004-0002 | D76: 76147 | E76: 2764178 | F76: 59182 | G76: INCIDENTE | H76: VALLE DEL CAUCA | I76: CARTAGO | J76: BARRIO GUAYACANES CARTAGO | K76: REDEBAN | L76: FO-25-1551401 | M76: 45919.333 | N76: 45919.704 | O76: NO | P76: USUARIO | Q76: MANTENIMIENTO | R76: MANTENIMIENTO GENERAL | U76: CERRADO | V76: 19/09/2025 SE ESCALA PARA VISITA. LLAMAR ANTES DE VISITAR, CONFIRMAR FALLA Y DATOS | 19/09/2025 SE ENCUENTRA DATÁFONO EN FUNCIONAMIENTO SIN PROBLEMAS SE LE INDICA AL CLIENTE NO DESCONECTAR DATÁFONO | W76: VISITA_TÉCNICA | X76: FAZZZ560 | Y76: TIPO I | Z76: TERRESTRE | AA76: LOAIZA LOPEZ JHON FREDDY | AB76: 1 | AC76: 0 | AD76: 0 | AE76: 0 | AF76: =IF(W76="SOPORTE_TELEFÓNICO",'BASE LIQUIDACION'!$B$10,IF(Y76="TIPO I",'BASE LIQUIDACION'!$C$3,IF(Y76="TIPO II",'BASE LIQUIDACION'!$C$4,IF(Y76="TIPO III",'BASE LIQUIDACION'!$C$5,'BASE LIQUIDACION'!$C$7)))) -> 65960.474 | AG76: =IF(W76="SOPORTE_TELEFÓNICO",'BASE LIQUIDACION'!$B$10,(AB76*AF76+AC76*'BASE LIQUIDACION'!$B$12+AD76*'BASE LIQUIDACION'!$B$11+INCIDENTES!AE76*'BASE LIQUIDACION'!$B$13)) -> 65960.474
A77: MEDELLIN | B77: =VLOOKUP(A77,'CENTRO DE COSTOS'!A:D,4,FALSE) -> JUAN SEBASTIÁN RÍOS CASTRILLÓN | C77: =VLOOKUP(A77,'CENTRO DE COSTOS'!A:D,2,FALSE) -> 0004-0005 | D77: 5001 | E77: 2763823 | F77: 34519 | G77: INCIDENTE | H77: ANTIOQUIA | I77: MEDELLIN | J77: BARRIO ENCISO MEDELLIN 3 | K77: REDEBAN | L77: FO-25-1551411 | M77: 45919.333 | N77: 45920.331 | O77: NO | P77: USUARIO | Q77: USUARIOS | R77: CREACION DE USUARIOS | U77: CERRADO | V77: 19/09/2025 SE ESCALA PARA VISITA. LLAMAR ANTES DE VISITAR, CONFIRMAR FALLA Y DATOS | 19/09/2025 SE REALIZA CAMBIO DE USUARIOS POR SEGURIDAD A SOLICITUD CLIENTE PRUEBAS OK NO TELECARGA | W77: VISITA_TÉCNICA | X77: BL01B406 | Y77: TIPO I | Z77: TERRESTRE | AA77: PAREJA ECHAVARRIA JHON DAVID | AB77: 1 | AC77: 0 | AD77: 0 | AE77: 0 | AF77: =IF(W77="SOPORTE_TELEFÓNICO",'BASE LIQUIDACION'!$B$10,IF(Y77="TIPO I",'BASE LIQUIDACION'!$C$3,IF(Y77="TIPO II",'BASE LIQUIDACION'!$C$4,IF(Y77="TIPO III",'BASE LIQUIDACION'!$C$5,'BASE LIQUIDACION'!$C$7)))) -> 65960.474 | AG77: =IF(W77="SOPORTE_TELEFÓNICO",'BASE LIQUIDACION'!$B$10,(AB77*AF77+AC77*'BASE LIQUIDACION'!$B$12+AD77*'BASE LIQUIDACION'!$B$11+INCIDENTES!AE77*'BASE LIQUIDACION'!$B$13)) -> 65960.474
A78: CUCUTA | B78: =VLOOKUP(A78,'CENTRO DE COSTOS'!A:D,4,FALSE) -> MIGUEL JULIÁN HERNÁNDEZ GUARÍN | C78: =VLOOKUP(A78,'CENTRO DE COSTOS'!A:D,2,FALSE) -> 0004-0008 | D78: 54498 | E78: 2763489 | F78: 79112 | G78: INCIDENTE | H78: NORTE DE SANTANDER | I78: OCAÑA | J78: BARRIO EL CENTRO OCAÑA 7 | K78: REDEBAN | L78: FO-25-1551437 | M78: 45919.333 | N78: 45922.754 | O78: NO | P78: USUARIO | Q78: NO ENCIENDE | R78: CONEXIONES DE COMERCIO | U78: CERRADO | V78: 19/09/2025 SE ESCALA PARA VISITA. LLAMAR ANTES DE VISITAR, CONFIRMAR FALLA Y DATOS | 22/09/2025 SE VISITA COMERCIO Y SE REALIZA MANTENIMIENTO PREVENTIVO EL EQUIPO SE ENCUENTRA TRABAJANDO OK, EL CLIENTE MANIFIESTA QUE ES DESPUÉS DE LAS 6:30 PM QUE LE FALLA EL EQUIPO SE LE RECOMIENDA CONECTAR EL EQUIPO A UN ESTABILIZADOR DE VOLTAJE POR POSIBLES CONEXIONES DE CORRIENTE DEFECTUOSAS, SE REALIZAN CIERRES Y PRUEBAS EXITOSOS. | W78: VISITA_TÉCNICA | X78: SASZZ687 | Y78: TIPO IV | Z78: TERRESTRE | AA78: TORRES MANTILLA JOSE DANIEL | AB78: 1 | AC78: 0 | AD78: 0 | AE78: 0 | AF78: =IF(W78="SOPORTE_TELEFÓNICO",'BASE LIQUIDACION'!$B$10,IF(Y78="TIPO I",'BASE LIQUIDACION'!$C$3,IF(Y78="TIPO II",'BASE LIQUIDACION'!$C$4,IF(Y78="TIPO III",'BASE LIQUIDACION'!$C$5,'BASE LIQUIDACION'!$C$7)))) -> 479589.74 | AG78: =IF(W78="SOPORTE_TELEFÓNICO",'BASE LIQUIDACION'!$B$10,(AB78*AF78+AC78*'BASE LIQUIDACION'!$B$12+AD78*'BASE LIQUIDACION'!$B$11+INCIDENTES!AE78*'BASE LIQUIDACION'!$B$13)) -> 479589.74
A79: VALLEDUPAR | B79: =VLOOKUP(A79,'CENTRO DE COSTOS'!A:D,4,FALSE) -> JOSE MAURICIO HERNANDEZ ROJAS | C79: =VLOOKUP(A79,'CENTRO DE COSTOS'!A:D,2,FALSE) -> 0004-0001 | D79: 20250 | E79: 2763128 | F79: 64864 | G79: INCIDENTE | H79: CESAR | I79: EL PASO | J79: PTM EL PASO PAPELERIA MI ANGEL | K79: REDEBAN | L79: FO-25-1550889 | M79: 45918.704 | N79: 45922.74 | O79: NO | P79: USUARIO | Q79: MANTENIMIENTO | R79: MANTENIMIENTO GENERAL | U79: CERRADO | V79: 18/09/2025 SE ESCALA PARA VISITA. LLAMAR ANTES DE VISITAR, CONFIRMAR FALLA Y DATOS | 20/09/2025 LA ORDEN REQUIERE CAMBIO DE DATAFONO, Y DEBIDO A QUE NO SE CUENTA CON SOPORTE ACTIVOS DE RBM, SE REAGENDA PARA EL LUNES 22 SEPTIEMBRE | 22/09/2025 SE LLEGA A SITIO PERO NO SE ENCUENTRA EL DATAFONO EN EL LUGAR, YA QUE EL CLIENTE LE DIO A CARGO EL CB Y EL NEGOCIO A UN FAMILIAR Y ESTE MISMO TRASLADÓ TODO PARA EL MUNICIPIO DE SABANALARGA ATLANTICO, POR ENDE NO HAGO INTERVENCION EN NINGUN EQUIPO | W79: VISITA_TÉCNICA | X79: 5A002486 | Y79: TIPO III | Z79: TERRESTRE | AA79: MONTES DIAZ JOHN FRED | AB79: 1 | AC79: 0 | AD79: 0 | AE79: 0 | AF79: =IF(W79="SOPORTE_TELEFÓNICO",'BASE LIQUIDACION'!$B$10,IF(Y79="TIPO I",'BASE LIQUIDACION'!$C$3,IF(Y79="TIPO II",'BASE LIQUIDACION'!$C$4,IF(Y79="TIPO III",'BASE LIQUIDACION'!$C$5,'BASE LIQUIDACION'!$C$7)))) -> 275728.38 | AG79: =IF(W79="SOPORTE_TELEFÓNICO",'BASE LIQUIDACION'!$B$10,(AB79*AF79+AC79*'BASE LIQUIDACION'!$B$12+AD79*'BASE LIQUIDACION'!$B$11+INCIDENTES!AE79*'BASE LIQUIDACION'!$B$13)) -> 275728.38
A80: CUCUTA | B80: =VLOOKUP(A80,'CENTRO DE COSTOS'!A:D,4,FALSE) -> MIGUEL JULIÁN HERNÁNDEZ GUARÍN | C80: =VLOOKUP(A80,'CENTRO DE COSTOS'!A:D,2,FALSE) -> 0004-0008 | D80: 54518 | E80: 2763028 | F80: 77625 | G80: INCIDENTE | H80: NORTE DE SANTANDER | I80: PAMPLONA | J80: BARRIO SIMON BOLIVAR PARTE ALTA PAMPLONA | K80: REDEBAN | L80: FO-25-1550892 | M80: 45918.701 | N80: 45919.69 | O80: NO | P80: USUARIO | Q80: COMUNICACION | R80: CONEXIONES DE COMERCIO | U80: CERRADO | V80: 18/09/2025 SE ESCALA PARA VISITA. LLAMAR ANTES DE VISITAR, CONFIRMAR FALLA Y DATOS | 19/09/2025 SE REALIZÓ VISITA AL COMERCIO Y SE ENCUENTRA CONEXIONES DEL COMERCIO FALLANDO, SE VERIFICAN CONEXIONES, PRUEBAS EXITOSAS | W80: VISITA_TÉCNICA | X80: F1JZZ374 | Y80: TIPO III | Z80: TERRESTRE | AA80: MORA VEGA JEAMPIER | AB80: 1 | AC80: 0 | AD80: 0 | AE80: 0 | AF80: =IF(W80="SOPORTE_TELEFÓNICO",'BASE LIQUIDACION'!$B$10,IF(Y80="TIPO I",'BASE LIQUIDACION'!$C$3,IF(Y80="TIPO II",'BASE LIQUIDACION'!$C$4,IF(Y80="TIPO III",'BASE LIQUIDACION'!$C$5,'BASE LIQUIDACION'!$C$7)))) -> 275728.38 | AG80: =IF(W80="SOPORTE_TELEFÓNICO",'BASE LIQUIDACION'!$B$10,(AB80*AF80+AC80*'BASE LIQUIDACION'!$B$12+AD80*'BASE LIQUIDACION'!$B$11+INCIDENTES!AE80*'BASE LIQUIDACION'!$B$13)) -> 275728.38
A81: MEDELLIN | B81: =VLOOKUP(A81,'CENTRO DE COSTOS'!A:D,4,FALSE) -> JUAN SEBASTIÁN RÍOS CASTRILLÓN | C81: =VLOOKUP(A81,'CENTRO DE COSTOS'!A:D,2,FALSE) -> 0004-0005 | D81: 5001 | E81: 2761655 | F81: 31529 | G81: INCIDENTE | H81: ANTIOQUIA | I81: MEDELLIN | J81: COMCARD MED LUZMAK | K81: REDEBAN | L81: FO-25-1549590 | M81: 45918.603 | N81: 45919.567 | O81: NO | P81: USUARIO | Q81: MANTENIMIENTO | R81: MANTENIMIENTO GENERAL | U81: CERRADO | V81: 18/09/2025 SE ESCALA PARA VISITA. LLAMAR ANTES DE VISITAR, CONFIRMAR FALLA Y DATOS | 19/09/2025 SE LLEGA AL PUNTO, CLIENTE INDICA QUE TENÍA LA PANTALLA CONGELADA, NOS DICE QUE REINICIÓ EL DATÁFONO Y QUEDÓ OPERSTIVO, PRUEBAS OK | W81: VISITA_TÉCNICA | X81: 1111G612 | Y81: TIPO I | Z81: TERRESTRE | AA81: CARDONA MOLINA BROLIN STIVEN | AB81: 1 | AC81: 0 | AD81: 0 | AE81: 0 | AF81: =IF(W81="SOPORTE_TELEFÓNICO",'BASE LIQUIDACION'!$B$10,IF(Y81="TIPO I",'BASE LIQUIDACION'!$C$3,IF(Y81="TIPO II",'BASE LIQUIDACION'!$C$4,IF(Y81="TIPO III",'BASE LIQUIDACION'!$C$5,'BASE LIQUIDACION'!$C$7)))) -> 65960.474 | AG81: =IF(W81="SOPORTE_TELEFÓNICO",'BASE LIQUIDACION'!$B$10,(AB81*AF81+AC81*'BASE LIQUIDACION'!$B$12+AD81*'BASE LIQUIDACION'!$B$11+INCIDENTES!AE81*'BASE LIQUIDACION'!$B$13)) -> 65960.474
A82: CALI | B82: =VLOOKUP(A82,'CENTRO DE COSTOS'!A:D,4,FALSE) -> DIEGO FERNANDO HENAO CARDONA | C82: =VLOOKUP(A82,'CENTRO DE COSTOS'!A:D,2,FALSE) -> 0004-0003 | D82: 76001 | E82: 2761524 | F82: 80586 | G82: INCIDENTE | H82: VALLE DEL CAUCA | I82: CALI | J82: BARRIO POTRERO GRANDE CALI 2 | K82: REDEBAN | L82: FO-25-1549243 | M82: 45918.564 | N82: 45919.467 | O82: NO | P82: USUARIO | Q82: NO ENCIENDE | R82: CONEXIONES DE COMERCIO | U82: CERRADO | V82: 18/09/2025 SE ESCALA PARA VISITA. LLAMAR ANTES DE VISITAR, CONFIRMAR FALLA Y DATOS | 19/09/2025 SE REALIZA GESTIÓN TELEFÓNICA ANTES DE REALIZAR LA VISITA, EL CLIENTE INFORMA QUE EL DATAFONO NO PRENDÍA DESPUÉS DE QUE HUBO UN APAGON EN LA ZONA PERO EN EL MOMENTO YA ESTÁ FUNCIONANDO, CLIENTE REALIZA TRX Y CONFIRMA QUE SALEN OK.. | W82: SOPORTE_TELEFÓNICO | X82: 0 | Y82: TIPO I | Z82: TERRESTRE | AA82: MONTERO MUESES GIAN CARLO | AB82: 0 | AC82: 0 | AD82: 0 | AE82: 0 | AF82: =IF(W82="SOPORTE_TELEFÓNICO",'BASE LIQUIDACION'!$B$10,IF(Y82="TIPO I",'BASE LIQUIDACION'!$C$3,IF(Y82="TIPO II",'BASE LIQUIDACION'!$C$4,IF(Y82="TIPO III",'BASE LIQUIDACION'!$C$5,'BASE LIQUIDACION'!$C$7)))) -> 37904.654 | AG82: =IF(W82="SOPORTE_TELEFÓNICO",'BASE LIQUIDACION'!$B$10,(AB82*AF82+AC82*'BASE LIQUIDACION'!$B$12+AD82*'BASE LIQUIDACION'!$B$11+INCIDENTES!AE82*'BASE LIQUIDACION'!$B$13)) -> 37904.654
A83: MEDELLIN | B83: =VLOOKUP(A83,'CENTRO DE COSTOS'!A:D,4,FALSE) -> JUAN SEBASTIÁN RÍOS CASTRILLÓN | C83: =VLOOKUP(A83,'CENTRO DE COSTOS'!A:D,2,FALSE) -> 0004-0005 | D83: 5809 | E83: 2760041 | F83: 57362 | G83: INCIDENTE | H83: ANTIOQUIA | I83: TITIRIBI | J83: BARRIO VEREDA OTRAMINA TITIRIB | K83: REDEBAN | L83: FO-25-1548241 | M83: 45918.445 | N83: 45919.463 | O83: NO | P83: USUARIO | Q83: COMUNICACION | R83: CANAL DEL COMERCIO | U83: CERRADO | V83: 18/09/2025 SE ESCALA PARA VISITA. LLAMAR ANTES DE VISITAR, CONFIRMAR FALLA Y DATOS | 19/09/2025 SE REALIZA EL CAMBIO DE CABLE ENSORTIJADO Y CABLE DE RED SE HACEN PRUEBAS OK | W83: VISITA_TÉCNICA | X83: IIRZZ834 | Y83: TIPO II | Z83: TERRESTRE | AA83: MONTOYA VELEZ ANDRES FELIPE | AB83: 1 | AC83: 0 | AD83: 0 | AE83: 0 | AF83: =IF(W83="SOPORTE_TELEFÓNICO",'BASE LIQUIDACION'!$B$10,IF(Y83="TIPO I",'BASE LIQUIDACION'!$C$3,IF(Y83="TIPO II",'BASE LIQUIDACION'!$C$4,IF(Y83="TIPO III",'BASE LIQUIDACION'!$C$5,'BASE LIQUIDACION'!$C$7)))) -> 163813.56 | AG83: =IF(W83="SOPORTE_TELEFÓNICO",'BASE LIQUIDACION'!$B$10,(AB83*AF83+AC83*'BASE LIQUIDACION'!$B$12+AD83*'BASE LIQUIDACION'!$B$11+INCIDENTES!AE83*'BASE LIQUIDACION'!$B$13)) -> 163813.56
A84: MEDELLIN | B84: =VLOOKUP(A84,'CENTRO DE COSTOS'!A:D,4,FALSE) -> JUAN SEBASTIÁN RÍOS CASTRILLÓN | C84: =VLOOKUP(A84,'CENTRO DE COSTOS'!A:D,2,FALSE) -> 0004-0005 | D84: 5088 | E84: 2759288 | F84: 30086 | G84: INCIDENTE | H84: ANTIOQUIA | I84: BELLO | J84: COMCARD BELLO MERCADOS LA CRUZ | K84: REDEBAN | L84: FO-25-1547602 | M84: 45918.401 | N84: 45918.664 | O84: NO | P84: USUARIO | Q84: NO ENCIENDE | R84: CONEXIONES DE COMERCIO | U84: CERRADO | V84: 03/10/2025 SE ESCALA PARA VISITA. LLAMAR ANTES DE VISITAR, CONFIRMAR FALLA Y DATOS | 18/09/2025 SE REALIZA CONTACTO TELEFÓNICO CON EL USUARIO PARA VALIDAR EL INCIDENTE PREVIAMENTE REPORTADO RELACIONADO CON EL DATÁFONO DEL CORRESPONSAL BANCOLOMBIA. EL USUARIO INFORMA QUE EL DISPOSITIVO PRESENTÓ UNA PANTALLA AZUL, LO QUE MOTIVÓ SU LLAMADA INMEDIATA A LA LÍNEA DE SOPORTE. SIN EMBARGO, AL REVISAR EL EQUIPO, IDENTIFICÓ QUE EL DATÁFONO NO ESTABA CORRECTAMENTE CONECTADO, LO QUE HABRÍA OCASIONADO LA FALLA VISUAL. TRAS CORREGIR LA CONEXIÓN, EL DATÁFONO VOLVIÓ A FUNCIONAR CON NORMALIDAD. EL USUARIO CONFIRMA QUE EL DISPOSITIVO SE ENCUENTRA OPERATIVO Y DESCARTA LA NECESIDAD DE UNA VISITA TÉCNICA. | W84: SOPORTE_TELEFÓNICO | X84: 0 | Y84: TIPO I | Z84: TERRESTRE | AA84: MARTINEZ TOVAR OSCAR DAVID | AB84: 0 | AC84: 0 | AD84: 0 | AE84: 0 | AF84: =IF(W84="SOPORTE_TELEFÓNICO",'BASE LIQUIDACION'!$B$10,IF(Y84="TIPO I",'BASE LIQUIDACION'!$C$3,IF(Y84="TIPO II",'BASE LIQUIDACION'!$C$4,IF(Y84="TIPO III",'BASE LIQUIDACION'!$C$5,'BASE LIQUIDACION'!$C$7)))) -> 37904.654 | AG84: =IF(W84="SOPORTE_TELEFÓNICO",'BASE LIQUIDACION'!$B$10,(AB84*AF84+AC84*'BASE LIQUIDACION'!$B$12+AD84*'BASE LIQUIDACION'!$B$11+INCIDENTES!AE84*'BASE LIQUIDACION'!$B$13)) -> 37904.654
A85: IBAGUE | B85: =VLOOKUP(A85,'CENTRO DE COSTOS'!A:D,4,FALSE) -> KEVIN ALEXIS CORZO BUSTOS | C85: =VLOOKUP(A85,'CENTRO DE COSTOS'!A:D,2,FALSE) -> 0004-0007 | D85: 73268 | E85: 2758985 | F85: 19851 | G85: INCIDENTE | H85: TOLIMA | I85: ESPINAL | J85: REVAL 411 ESPINAL | K85: REDEBAN | L85: FO-25-1547315 | M85: 45918.383 | N85: 45919.381 | O85: NO | P85: USUARIO | Q85: COMUNICACION | R85: CONEXIONES DE COMERCIO | U85: CERRADO | V85: 25/09/2025 SE ESCALA PARA VISITA. LLAMAR ANTES DE VISITAR, CONFIRMAR FALLA Y DATOS | 19/09/2025 SE LLEGA AL PUNTO DE ATENCIÓN DEL CB A LA ESPERA DE AUTORIZACIÓN DE INGRESO AL PUNTO POR TEMA DE SEGURIDAD | 19/09/2025 SE REALIZA REVISIÓN DE CONEXIONES,SE CONFIGURAN PARÁMETROS DE COMUNICACIÓN TRANSACCIONES DE PRUEBA O.K | W85: VISITA_TÉCNICA | X85: 1111F657 | Y85: TIPO II | Z85: TERRESTRE | AA85: GUTIERREZ CAMILO ANDRES | AB85: 1 | AC85: 0 | AD85: 0 | AE85: 0 | AF85: =IF(W85="SOPORTE_TELEFÓNICO",'BASE LIQUIDACION'!$B$10,IF(Y85="TIPO I",'BASE LIQUIDACION'!$C$3,IF(Y85="TIPO II",'BASE LIQUIDACION'!$C$4,IF(Y85="TIPO III",'BASE LIQUIDACION'!$C$5,'BASE LIQUIDACION'!$C$7)))) -> 163813.56 | AG85: =IF(W85="SOPORTE_TELEFÓNICO",'BASE LIQUIDACION'!$B$10,(AB85*AF85+AC85*'BASE LIQUIDACION'!$B$12+AD85*'BASE LIQUIDACION'!$B$11+INCIDENTES!AE85*'BASE LIQUIDACION'!$B$13)) -> 163813.56
A86: MEDELLIN | B86: =VLOOKUP(A86,'CENTRO DE COSTOS'!A:D,4,FALSE) -> JUAN SEBASTIÁN RÍOS CASTRILLÓN | C86: =VLOOKUP(A86,'CENTRO DE COSTOS'!A:D,2,FALSE) -> 0004-0005 | D86: 5001 | E86: 2757070 | F86: 52519 | G86: INCIDENTE | H86: ANTIOQUIA | I86: MEDELLIN | J86: BARRIO BUENOS AIRES MEDELLIN 1 | K86: REDEBAN | L86: FO-25-1545396 | M86: 45917.699 | N86: 45918.638 | O86: NO | P86: ENTIDAD | Q86: ERROR DE TRANSACCIONES | R86: TRANSACCION NO PERMITIDA | U86: CERRADO | V86: 17/09/2025 SE ESCALA PARA VISITA. LLAMAR ANTES DE VISITAR, CONFIRMAR FALLA Y DATOS | 18/09/2025 SE ENCUENTRA REVERSO PENDIENTE SE CONFIGURAN PARAMETROS OK PRUEBAS OK | W86: VISITA_TÉCNICA | X86: SXMZZ318 | Y86: TIPO I | Z86: TERRESTRE | AA86: PAREJA ECHAVARRIA JHON DAVID | AB86: 1 | AC86: 0 | AD86: 0 | AE86: 0 | AF86: =IF(W86="SOPORTE_TELEFÓNICO",'BASE LIQUIDACION'!$B$10,IF(Y86="TIPO I",'BASE LIQUIDACION'!$C$3,IF(Y86="TIPO II",'BASE LIQUIDACION'!$C$4,IF(Y86="TIPO III",'BASE LIQUIDACION'!$C$5,'BASE LIQUIDACION'!$C$7)))) -> 65960.474 | AG86: =IF(W86="SOPORTE_TELEFÓNICO",'BASE LIQUIDACION'!$B$10,(AB86*AF86+AC86*'BASE LIQUIDACION'!$B$12+AD86*'BASE LIQUIDACION'!$B$11+INCIDENTES!AE86*'BASE LIQUIDACION'!$B$13)) -> 65960.474
A87: PASTO | B87: =VLOOKUP(A87,'CENTRO DE COSTOS'!A:D,4,FALSE) -> DIEGO FERNANDO HENAO CARDONA | C87: =VLOOKUP(A87,'CENTRO DE COSTOS'!A:D,2,FALSE) -> 0004-0003 | D87: 52356 | E87: TA-25-1119422 | F87: 25904 | G87: INCIDENTE | H87: NARIÑO | I87: IPIALES | J87: ALKOSTO 20 DE JULIO | K87: REDEBAN | L87: FO-25-1544465 | M87: 45917.635 | N87: 45917.74 | O87: NO | P87: USUARIO | Q87: COMUNICACION | R87: CANAL DEL COMERCIO | U87: CERRADO | V87: 17/09/2025 SE ESCALA POR SOLICITUD DE LA RED | 17/09/2025 EL COMERCIO FUE VISITADO EL DIA DE HOY , YA QUE EL DIA DE AYER NO SE PUDO VISITAR PUES PARA INGRESAR AL PUNTO SE REQUIERE PRIMERO UN PERMISO EL CUAL SE TRAMITO EL DIA DE AYER PARA EL INGRESO EL DIA DE HOY, SE VISITA COMERCIO , SE VALIDA CONECTIVIDAD DE LOS EQUIPOS DE REDEBAN - BANCOLOMBIA Y ESTOS ESTA ACTIVOS EN RED, SE REALIZAN PRUEBAS FUNCIONALES EN CADA UNO, MOSTRANTO OPERATIVIDAD, SE REALIZA BORRADO DE TRANSACCIONES YA QUE EL CLIENTE INDICABA QUE LOS CIERRES LES ESTABAN ARROJANDO TRANSACCIONES DE DIAS ANTERIORES, CLIENTE QUEDA CONFORME CON LOS EQUIPOS. SE ATIENDE BAJO LA TA 2745128 | W87: SOPORTE_TELEFÓNICO | X87: 0 | Y87: TIPO II | Z87: TERRESTRE | AA87: HENAO CARDONA DIEGO FERNANDO | AB87: 0 | AC87: 0 | AD87: 0 | AE87: 0 | AF87: =IF(W87="SOPORTE_TELEFÓNICO",'BASE LIQUIDACION'!$B$10,IF(Y87="TIPO I",'BASE LIQUIDACION'!$C$3,IF(Y87="TIPO II",'BASE LIQUIDACION'!$C$4,IF(Y87="TIPO III",'BASE LIQUIDACION'!$C$5,'BASE LIQUIDACION'!$C$7)))) -> 37904.654 | AG87: =IF(W87="SOPORTE_TELEFÓNICO",'BASE LIQUIDACION'!$B$10,(AB87*AF87+AC87*'BASE LIQUIDACION'!$B$12+AD87*'BASE LIQUIDACION'!$B$11+INCIDENTES!AE87*'BASE LIQUIDACION'!$B$13)) -> 37904.654
A88: MANIZALES | B88: =VLOOKUP(A88,'CENTRO DE COSTOS'!A:D,4,FALSE) -> DIEGO FERNANDO HENAO CARDONA | C88: =VLOOKUP(A88,'CENTRO DE COSTOS'!A:D,2,FALSE) -> 0004-0002 | D88: 17001 | E88: 2755850 | F88: 81145 | G88: INCIDENTE | H88: CALDAS | I88: MANIZALES | J88: BARRIO LOS CAMBULOS MANEIZALES | K88: REDEBAN | L88: FO-25-1544863 | M88: 45917.624 | N88: 45918.608 | O88: NO | P88: USUARIO | Q88: COMUNICACION | R88: CONEXIONES DE COMERCIO | U88: CERRADO | V88: 17/09/2025 SE ESCALA PARA VISITA. LLAMAR ANTES DE VISITAR, CONFIRMAR FALLA Y DATOS | 18/09/2025 SE REALIZA LLAMADA CON USUARIO EL CUAL INDICA QUE EL DIA DE AYER NO PUDO HACER TRANSACCIONES PERO YA EL DIA DE HOY SE ENCUENTRA FUNCIONANDO CON NORMALIDAD INDICA QUE EL SERVICIO ESTA OK | W88: SOPORTE_TELEFÓNICO | X88: 0 | Y88: TIPO I | Z88: TERRESTRE | AA88: AGUIRRE HENAO RAUL EDUARDO | AB88: 0 | AC88: 0 | AD88: 0 | AE88: 0 | AF88: =IF(W88="SOPORTE_TELEFÓNICO",'BASE LIQUIDACION'!$B$10,IF(Y88="TIPO I",'BASE LIQUIDACION'!$C$3,IF(Y88="TIPO II",'BASE LIQUIDACION'!$C$4,IF(Y88="TIPO III",'BASE LIQUIDACION'!$C$5,'BASE LIQUIDACION'!$C$7)))) -> 37904.654 | AG88: =IF(W88="SOPORTE_TELEFÓNICO",'BASE LIQUIDACION'!$B$10,(AB88*AF88+AC88*'BASE LIQUIDACION'!$B$12+AD88*'BASE LIQUIDACION'!$B$11+INCIDENTES!AE88*'BASE LIQUIDACION'!$B$13)) -> 37904.654
A89: BUCARAMANGA | B89: =VLOOKUP(A89,'CENTRO DE COSTOS'!A:D,4,FALSE) -> MIGUEL JULIÁN HERNÁNDEZ GUARÍN | C89: =VLOOKUP(A89,'CENTRO DE COSTOS'!A:D,2,FALSE) -> 0004-0008 | D89: 68001 | E89: 2755205 | F89: 47890 | G89: INCIDENTE | H89: SANTANDER | I89: BUCARAMANGA | J89: DISTRICOL MENSAJERIA ZUUUM | K89: REDEBAN | L89: FO-25-1543687 | M89: 45917.561 | N89: 45918.517 | O89: NO | P89: USUARIO | Q89: COMUNICACION | R89: CONEXIONES DE COMERCIO | U89: CERRADO | V89: 17/09/2025 SE ESCALA AL COORDINADOR DE ZONA PARA ENTREGA DE ROLLOS EN SITIO | 18/09/2025 SE HACE PRESENCIA EN COMERCIO CLIENTE INFORMA QUE EL DAÑO ESTABA EN EL SWITH PROPIO DE ELLOS, REALIZARON EL CAMBIO DE DICHO SWITH Y YA EL EQUIPO ESTA OPERANDO SIN PROBLEMA SE REALIZA PRUEBA OK Y SE PROCEDE A CERRAR LA ORDEN | W89: VISITA_TÉCNICA | X89: SIZZZ940 | Y89: TIPO I | Z89: TERRESTRE | AA89: BARRERA ORTEGA MARLON STWAR | AB89: 1 | AC89: 0 | AD89: 0 | AE89: 0 | AF89: =IF(W89="SOPORTE_TELEFÓNICO",'BASE LIQUIDACION'!$B$10,IF(Y89="TIPO I",'BASE LIQUIDACION'!$C$3,IF(Y89="TIPO II",'BASE LIQUIDACION'!$C$4,IF(Y89="TIPO III",'BASE LIQUIDACION'!$C$5,'BASE LIQUIDACION'!$C$7)))) -> 65960.474 | AG89: =IF(W89="SOPORTE_TELEFÓNICO",'BASE LIQUIDACION'!$B$10,(AB89*AF89+AC89*'BASE LIQUIDACION'!$B$12+AD89*'BASE LIQUIDACION'!$B$11+INCIDENTES!AE89*'BASE LIQUIDACION'!$B$13)) -> 65960.474
A90: MEDELLIN | B90: =VLOOKUP(A90,'CENTRO DE COSTOS'!A:D,4,FALSE) -> JUAN SEBASTIÁN RÍOS CASTRILLÓN | C90: =VLOOKUP(A90,'CENTRO DE COSTOS'!A:D,2,FALSE) -> 0004-0005 | D90: 5088 | E90: 2755121 | F90: 80316 | G90: INCIDENTE | H90: ANTIOQUIA | I90: BELLO | J90: BARRIO ARAUCARIAS BELLO | K90: REDEBAN | L90: FO-25-1543355 | M90: 45917.527 | N90: 45918.51 | O90: NO | P90: USUARIO | Q90: CIERRE | R90: COMERCIO NO REALIZA CIERRE | U90: CERRADO | V90: 17/09/2025 SE ESCALA PARA VISITA. LLAMAR ANTES DE VISITAR, CONFIRMAR FALLA Y DATOS | 18/09/2025 SE REALIZA REVISIÓN DEL DATÁFONO CONFIGURACIÓN Y COMUNICACIÓN Y TODO ESTÁ FUNCIONANDO CORRECTAMENTE, USUARIO MANIFIESTA QUE NO IMPRIME, PERO SE REALIZA EN PRUEBAS Y FUNCIONA CORRECTAMENTE | W90: VISITA_TÉCNICA | X90: FAZZZ519 | Y90: TIPO I | Z90: TERRESTRE | AA90: RAMIREZ TABARES JUAN DIEGO | AB90: 1 | AC90: 0 | AD90: 0 | AE90: 0 | AF90: =IF(W90="SOPORTE_TELEFÓNICO",'BASE LIQUIDACION'!$B$10,IF(Y90="TIPO I",'BASE LIQUIDACION'!$C$3,IF(Y90="TIPO II",'BASE LIQUIDACION'!$C$4,IF(Y90="TIPO III",'BASE LIQUIDACION'!$C$5,'BASE LIQUIDACION'!$C$7)))) -> 65960.474 | AG90: =IF(W90="SOPORTE_TELEFÓNICO",'BASE LIQUIDACION'!$B$10,(AB90*AF90+AC90*'BASE LIQUIDACION'!$B$12+AD90*'BASE LIQUIDACION'!$B$11+INCIDENTES!AE90*'BASE LIQUIDACION'!$B$13)) -> 65960.474
A91: MEDELLIN | B91: =VLOOKUP(A91,'CENTRO DE COSTOS'!A:D,4,FALSE) -> JUAN SEBASTIÁN RÍOS CASTRILLÓN | C91: =VLOOKUP(A91,'CENTRO DE COSTOS'!A:D,2,FALSE) -> 0004-0005 | D91: 5607 | E91: 2754158 | F91: 36661 | G91: INCIDENTE | H91: ANTIOQUIA | I91: RETIRO | J91: BARRIO EL RETIRO RETIRO | K91: REDEBAN | L91: FO-25-1542488 | M91: 45917.459 | N91: 45918.75 | O91: NO | P91: USUARIO | Q91: COMUNICACION | R91: CONEXIONES DE COMERCIO | U91: CERRADO | V91: 25/09/2025 SE ESCALA PARA VISITA. LLAMAR ANTES DE VISITAR, CONFIRMAR FALLA Y DATOS | 18/09/2025 SE HACE MANTENIMIENTO SE OK SE HACEN VALIDACIONES DE CABLEADOS OK Y PARÁMETROS DE DATÁFONO. | W91: VISITA_TÉCNICA | X91: AALUZ178 | Y91: TIPO II | Z91: TERRESTRE | AA91: DIAZ ZABALA FRANCIS DUBAN | AB91: 1 | AC91: 0 | AD91: 0 | AE91: 0 | AF91: =IF(W91="SOPORTE_TELEFÓNICO",'BASE LIQUIDACION'!$B$10,IF(Y91="TIPO I",'BASE LIQUIDACION'!$C$3,IF(Y91="TIPO II",'BASE LIQUIDACION'!$C$4,IF(Y91="TIPO III",'BASE LIQUIDACION'!$C$5,'BASE LIQUIDACION'!$C$7)))) -> 163813.56 | AG91: =IF(W91="SOPORTE_TELEFÓNICO",'BASE LIQUIDACION'!$B$10,(AB91*AF91+AC91*'BASE LIQUIDACION'!$B$12+AD91*'BASE LIQUIDACION'!$B$11+INCIDENTES!AE91*'BASE LIQUIDACION'!$B$13)) -> 163813.56
A92: VILLAVICENCIO | B92: =VLOOKUP(A92,'CENTRO DE COSTOS'!A:D,4,FALSE) -> KEVIN ALEXIS CORZO BUSTOS | C92: =VLOOKUP(A92,'CENTRO DE COSTOS'!A:D,2,FALSE) -> 0004-0007 | D92: 50318 | E92: 2753925 | F92: 78805 | G92: INCIDENTE | H92: META | I92: GUAMAL | J92: BARRIO LAS FERIAS GUAMAL 2 | K92: REDEBAN | L92: FO-25-1542194 | M92: 45917.444 | N92: 45918.562 | O92: NO | P92: USUARIO | Q92: COMUNICACION | R92: CONEXIONES DE COMERCIO | U92: CERRADO | V92: 21/09/2025 SE ESCALA PARA VISITA. LLAMAR ANTES DE VISITAR, CONFIRMAR FALLA Y DATOS | 18/09/2025 SE REALIZA VISITA Y SE CONFIGURA MEDIO DE COMUNICACIÓN, PRUEBAS OK | W92: VISITA_TÉCNICA | X92: V1SZZ187 | Y92: TIPO II | Z92: TERRESTRE | AA92: PEDREROS CONTRERAS MICHAEL STEVENS | AB92: 1 | AC92: 0 | AD92: 0 | AE92: 0 | AF92: =IF(W92="SOPORTE_TELEFÓNICO",'BASE LIQUIDACION'!$B$10,IF(Y92="TIPO I",'BASE LIQUIDACION'!$C$3,IF(Y92="TIPO II",'BASE LIQUIDACION'!$C$4,IF(Y92="TIPO III",'BASE LIQUIDACION'!$C$5,'BASE LIQUIDACION'!$C$7)))) -> 163813.56 | AG92: =IF(W92="SOPORTE_TELEFÓNICO",'BASE LIQUIDACION'!$B$10,(AB92*AF92+AC92*'BASE LIQUIDACION'!$B$12+AD92*'BASE LIQUIDACION'!$B$11+INCIDENTES!AE92*'BASE LIQUIDACION'!$B$13)) -> 163813.56
A93: VILLAVICENCIO | B93: =VLOOKUP(A93,'CENTRO DE COSTOS'!A:D,4,FALSE) -> KEVIN ALEXIS CORZO BUSTOS | C93: =VLOOKUP(A93,'CENTRO DE COSTOS'!A:D,2,FALSE) -> 0004-0007 | D93: 50313 | E93: 2753054 | F93: 80529 | G93: INCIDENTE | H93: META | I93: GRANADA | J93: BARRIO EL PARAISO GRANDA | K93: REDEBAN | L93: FO-25-1541682 | M93: 45917.399 | N93: 45918.551 | O93: NO | P93: USUARIO | Q93: NO ENCIENDE | R93: CONEXIONES DE COMERCIO | U93: CERRADO | V93: 19/09/2025 SE ESCALA PARA VISITA. LLAMAR ANTES DE VISITAR, CONFIRMAR FALLA Y DATOS | 18/09/2025 SE REALIZA VISITA AL PUNTO Y COMERCIO YA SE ENCUENTRA OPERANDO OK, EL DAÑO ERA EN LA TOMA CORRIENTE DE COMERCIO | W93: VISITA_TÉCNICA | X93: SEZZZ158 | Y93: TIPO II | Z93: TERRESTRE | AA93: PEDREROS CONTRERAS MICHAEL STEVENS | AB93: 1 | AC93: 0 | AD93: 0 | AE93: 0 | AF93: =IF(W93="SOPORTE_TELEFÓNICO",'BASE LIQUIDACION'!$B$10,IF(Y93="TIPO I",'BASE LIQUIDACION'!$C$3,IF(Y93="TIPO II",'BASE LIQUIDACION'!$C$4,IF(Y93="TIPO III",'BASE LIQUIDACION'!$C$5,'BASE LIQUIDACION'!$C$7)))) -> 163813.56 | AG93: =IF(W93="SOPORTE_TELEFÓNICO",'BASE LIQUIDACION'!$B$10,(AB93*AF93+AC93*'BASE LIQUIDACION'!$B$12+AD93*'BASE LIQUIDACION'!$B$11+INCIDENTES!AE93*'BASE LIQUIDACION'!$B$13)) -> 163813.56
A94: CUCUTA | B94: =VLOOKUP(A94,'CENTRO DE COSTOS'!A:D,4,FALSE) -> MIGUEL JULIÁN HERNÁNDEZ GUARÍN | C94: =VLOOKUP(A94,'CENTRO DE COSTOS'!A:D,2,FALSE) -> 0004-0008 | D94: 54874 | E94: 2752889 | F94: 60354 | G94: INCIDENTE | H94: NORTE DE SANTANDER | I94: VILLA DEL ROSARIO | J94: BARRIO VEINTE DE JULIO VILLA D | K94: REDEBAN | L94: FO-25-1541688 | M94: 45917.398 | N94: 45917.71 | O94: NO | P94: USUARIO | Q94: COMUNICACION | R94: CANAL DEL COMERCIO | U94: CERRADO | V94: 20/09/2025 SE ESCALA PARA VISITA. LLAMAR ANTES DE VISITAR, CONFIRMAR FALLA Y DATOS | 17/09/2025 SE REALIZA VISITA, COMERCIO INDICA QUE EL SERVICIO SE ENCUENTRA OPERATIVO Y NO REQUIERE LA VISITA TÉCNICA. NO SÉ INGRESA AL COMERCIO | W94: VISITA_TÉCNICA | X94: NONE | Y94: TIPO I | Z94: TERRESTRE | AA94: PACHECO BUITRAGO JAVIER ALONSO | AB94: 1 | AC94: 0 | AD94: 0 | AE94: 0 | AF94: =IF(W94="SOPORTE_TELEFÓNICO",'BASE LIQUIDACION'!$B$10,IF(Y94="TIPO I",'BASE LIQUIDACION'!$C$3,IF(Y94="TIPO II",'BASE LIQUIDACION'!$C$4,IF(Y94="TIPO III",'BASE LIQUIDACION'!$C$5,'BASE LIQUIDACION'!$C$7)))) -> 65960.474 | AG94: =IF(W94="SOPORTE_TELEFÓNICO",'BASE LIQUIDACION'!$B$10,(AB94*AF94+AC94*'BASE LIQUIDACION'!$B$12+AD94*'BASE LIQUIDACION'!$B$11+INCIDENTES!AE94*'BASE LIQUIDACION'!$B$13)) -> 65960.474
A95: NEIVA | B95: =VLOOKUP(A95,'CENTRO DE COSTOS'!A:D,4,FALSE) -> KEVIN ALEXIS CORZO BUSTOS | C95: =VLOOKUP(A95,'CENTRO DE COSTOS'!A:D,2,FALSE) -> 0004-0007 | D95: 41001 | E95: 2752973 | F95: 74529 | G95: INCIDENTE | H95: HUILA | I95: NEIVA | J95: BARRIO CONDOMINIO RESIDENCIAL | K95: REDEBAN | L95: FO-25-1541697 | M95: 45917.397 | N95: 45917.692 | O95: NO | P95: USUARIO | Q95: COMUNICACION | R95: CONEXIONES DE COMERCIO | U95: CERRADO | V95: 21/09/2025 SE ESCALA PARA VISITA. LLAMAR ANTES DE VISITAR, CONFIRMAR FALLA Y DATOS | 17/09/2025 SE REALIZA VISITA AL PUNTO, SE ENVÍDENCIA EQUIPI SE ENCUENTRA OPERATIVO. EL DAÑO SE DEBIO A CONEXIONES DEL COMERCIO, PPRUEBAS OK, CB OPERATIVO | W95: VISITA_TÉCNICA | X95: EFGZZ742 | Y95: TIPO I | Z95: TERRESTRE | AA95: DEVIA REINOSO JUAN CARLOS | AB95: 1 | AC95: 0 | AD95: 0 | AE95: 0 | AF95: =IF(W95="SOPORTE_TELEFÓNICO",'BASE LIQUIDACION'!$B$10,IF(Y95="TIPO I",'BASE LIQUIDACION'!$C$3,IF(Y95="TIPO II",'BASE LIQUIDACION'!$C$4,IF(Y95="TIPO III",'BASE LIQUIDACION'!$C$5,'BASE LIQUIDACION'!$C$7)))) -> 65960.474 | AG95: =IF(W95="SOPORTE_TELEFÓNICO",'BASE LIQUIDACION'!$B$10,(AB95*AF95+AC95*'BASE LIQUIDACION'!$B$12+AD95*'BASE LIQUIDACION'!$B$11+INCIDENTES!AE95*'BASE LIQUIDACION'!$B$13)) -> 65960.474
A96: MEDELLIN | B96: =VLOOKUP(A96,'CENTRO DE COSTOS'!A:D,4,FALSE) -> JUAN SEBASTIÁN RÍOS CASTRILLÓN | C96: =VLOOKUP(A96,'CENTRO DE COSTOS'!A:D,2,FALSE) -> 0004-0005 | D96: 5088 | E96: 2751447 | F96: 59783 | G96: INCIDENTE | H96: ANTIOQUIA | I96: BELLO | J96: DISTRICOL TIENDA MIX J | K96: REDEBAN | L96: FO-25-1540333 | M96: 45917.333 | N96: 45917.414 | O96: NO | P96: USUARIO | Q96: USUARIOS | R96: USUARIOS BLOQUEADOS | U96: CERRADO | V96: 17/09/2025 SE ESCALA PARA VISITA. LLAMAR ANTES DE VISITAR, CONFIRMAR FALLA Y DATOS | 17/09/2025 SE HABLA CON USUARIO Y COMENTA QUE ESE PROCESO YA LO PUDO REALIZAR, SACÓ UN DUPLICADO Y FUNCIONÓ CORRECTAMENTE LA CLAVE ADMINISTRADOR. SE CIERRA INCIDENTE. | W96: SOPORTE_TELEFÓNICO | X96: 0 | Y96: TIPO I | Z96: TERRESTRE | AA96: QUINTERO SANCHEZ JUAN SEBASTIAN | AB96: 0 | AC96: 0 | AD96: 0 | AE96: 0 | AF96: =IF(W96="SOPORTE_TELEFÓNICO",'BASE LIQUIDACION'!$B$10,IF(Y96="TIPO I",'BASE LIQUIDACION'!$C$3,IF(Y96="TIPO II",'BASE LIQUIDACION'!$C$4,IF(Y96="TIPO III",'BASE LIQUIDACION'!$C$5,'BASE LIQUIDACION'!$C$7)))) -> 37904.654 | AG96: =IF(W96="SOPORTE_TELEFÓNICO",'BASE LIQUIDACION'!$B$10,(AB96*AF96+AC96*'BASE LIQUIDACION'!$B$12+AD96*'BASE LIQUIDACION'!$B$11+INCIDENTES!AE96*'BASE LIQUIDACION'!$B$13)) -> 37904.654
A97: TUNJA | B97: =VLOOKUP(A97,'CENTRO DE COSTOS'!A:D,4,FALSE) -> MIGUEL JULIÁN HERNÁNDEZ GUARÍN | C97: =VLOOKUP(A97,'CENTRO DE COSTOS'!A:D,2,FALSE) -> 0004-0008 | D97: 15759 | E97: 2751618 | F97: 76327 | G97: INCIDENTE | H97: BOYACA | I97: SOGAMOSO | J97: BARRIO LA PRADERA SOGAMOSO 1 | K97: REDEBAN | L97: FO-25-1540742 | M97: 45917.333 | N97: 45917.667 | O97: NO | P97: USUARIO | Q97: CIERRE | R97: COMERCIO NO REALIZA CIERRE | U97: CERRADO | V97: 17/09/2025 EQUIPO CON MEMORIA ACOMULADA NO ARROJA CIERRES CLIENTE AUTORIZA RELIZAR BORRADO SE LE INDICA LA FORMA CORRECTA DE REALIZAR LOS CIERRES DIARIOS PRUEBAS OK CLIENTE CONFORME | W97: VISITA_TÉCNICA | X97: V10OZ404 | Y97: TIPO II | Z97: TERRESTRE | AA97: RODRIGUEZ MURCIA YERSON IVAN | AB97: 1 | AC97: 0 | AD97: 0 | AE97: 0 | AF97: =IF(W97="SOPORTE_TELEFÓNICO",'BASE LIQUIDACION'!$B$10,IF(Y97="TIPO I",'BASE LIQUIDACION'!$C$3,IF(Y97="TIPO II",'BASE LIQUIDACION'!$C$4,IF(Y97="TIPO III",'BASE LIQUIDACION'!$C$5,'BASE LIQUIDACION'!$C$7)))) -> 163813.56 | AG97: =IF(W97="SOPORTE_TELEFÓNICO",'BASE LIQUIDACION'!$B$10,(AB97*AF97+AC97*'BASE LIQUIDACION'!$B$12+AD97*'BASE LIQUIDACION'!$B$11+INCIDENTES!AE97*'BASE LIQUIDACION'!$B$13)) -> 163813.56
A98: PEREIRA | B98: =VLOOKUP(A98,'CENTRO DE COSTOS'!A:D,4,FALSE) -> DIEGO FERNANDO HENAO CARDONA | C98: =VLOOKUP(A98,'CENTRO DE COSTOS'!A:D,2,FALSE) -> 0004-0002 | D98: 66170 | E98: 2751369 | F98: 79238 | G98: INCIDENTE | H98: RISARALDA | I98: DOSQUEBRADAS | J98: DISTRICOL VARIEDADES MIFER | K98: REDEBAN | L98: FO-25-1540345 | M98: 45917.333 | N98: 45917.646 | O98: NO | P98: USUARIO | Q98: LECTOR DE BARRAS | R98: CAPACITACION MANIPULACION DE COMERCIO | U98: CERRADO | V98: 17/09/2025 SE ESCALA PARA VISITA. LLAMAR ANTES DE VISITAR, CONFIRMAR FALLA Y DATOS | 17/09/2025 VISITAMOS COMERCIO EL LECTOR DE BARRAS EL DÍA DE AYER NO PRENDIA LO DESCONECTO Y CONECTO EN REPETIDAS OCASIONES PERO NO FUNCIONABA PERO EL DÍA DE HOY YA ESTA FUNCIONANDO SIN NOVEDAD SE REALIZAN PRUEBAS OK. | W98: VISITA_TÉCNICA | X98: A4WZZ115 | Y98: TIPO I | Z98: TERRESTRE | AA98: ARROYAVE CANO MANUEL GUILLERMO | AB98: 1 | AC98: 0 | AD98: 0 | AE98: 0 | AF98: =IF(W98="SOPORTE_TELEFÓNICO",'BASE LIQUIDACION'!$B$10,IF(Y98="TIPO I",'BASE LIQUIDACION'!$C$3,IF(Y98="TIPO II",'BASE LIQUIDACION'!$C$4,IF(Y98="TIPO III",'BASE LIQUIDACION'!$C$5,'BASE LIQUIDACION'!$C$7)))) -> 65960.474 | AG98: =IF(W98="SOPORTE_TELEFÓNICO",'BASE LIQUIDACION'!$B$10,(AB98*AF98+AC98*'BASE LIQUIDACION'!$B$12+AD98*'BASE LIQUIDACION'!$B$11+INCIDENTES!AE98*'BASE LIQUIDACION'!$B$13)) -> 65960.474
A99: TUNJA | B99: =VLOOKUP(A99,'CENTRO DE COSTOS'!A:D,4,FALSE) -> MIGUEL JULIÁN HERNÁNDEZ GUARÍN | C99: =VLOOKUP(A99,'CENTRO DE COSTOS'!A:D,2,FALSE) -> 0004-0008 | D99: 15001 | E99: 2751367 | F99: 59681 | G99: INCIDENTE | H99: BOYACA | I99: TUNJA | J99: BARRIO ALTAMIRA TUNJA | K99: REDEBAN | L99: FO-25-1540348 | M99: 45917.333 | N99: 45917.66 | O99: NO | P99: USUARIO | Q99: COMUNICACION | R99: CONEXIONES DE COMERCIO | U99: CERRADO | V99: 17/09/2025 SE ESCALA PARA VISITA. LLAMAR ANTES DE VISITAR, CONFIRMAR FALLA Y DATOS | 17/09/2025 SE REALIZA INSPECCIÓN DE RED, SE DETECTA MAL CONEXIÓN EN EL MÓDEM DEL USUARIO, SE CONECTA A PUERTO ADECUADO, PRUEBAS OK | W99: VISITA_TÉCNICA | X99: LA009538 | Y99: TIPO I | Z99: TERRESTRE | AA99: HERRERA GARZON JEYSON STEVENT | AB99: 1 | AC99: 0 | AD99: 0 | AE99: 0 | AF99: =IF(W99="SOPORTE_TELEFÓNICO",'BASE LIQUIDACION'!$B$10,IF(Y99="TIPO I",'BASE LIQUIDACION'!$C$3,IF(Y99="TIPO II",'BASE LIQUIDACION'!$C$4,IF(Y99="TIPO III",'BASE LIQUIDACION'!$C$5,'BASE LIQUIDACION'!$C$7)))) -> 65960.474 | AG99: =IF(W99="SOPORTE_TELEFÓNICO",'BASE LIQUIDACION'!$B$10,(AB99*AF99+AC99*'BASE LIQUIDACION'!$B$12+AD99*'BASE LIQUIDACION'!$B$11+INCIDENTES!AE99*'BASE LIQUIDACION'!$B$13)) -> 65960.474
A100: MEDELLIN | B100: =VLOOKUP(A100,'CENTRO DE COSTOS'!A:D,4,FALSE) -> JUAN SEBASTIÁN RÍOS CASTRILLÓN | C100: =VLOOKUP(A100,'CENTRO DE COSTOS'!A:D,2,FALSE) -> 0004-0005 | D100: 5306 | E100: 2751101 | F100: 32938 | G100: INCIDENTE | H100: ANTIOQUIA | I100: GIRALDO | J100: BARRIO CALLE PRINCIPAL VIA AL | K100: REDEBAN | L100: FO-25-1539436 | M100: 45916.721 | N100: 45918.531 | O100: NO | P100: USUARIO | Q100: COMUNICACION | R100: CONEXIONES DE COMERCIO | U100: CERRADO | V100: 05/10/2025 SE INTENTA COMUNICACION CON EL CB AL NUMERO 321113669 *, SE ESCALA PARA VISITA, LLAMAR A CONFIRMAR DATOS | 18/09/2025 SE REALIZA BORRADO Y RECARGA DE VERSION POR LENTITUD, SE CONFIRMA FALLA EN CONEXIÓNES DE PARTE DE COMERCIO, EQUIPO YA FUNCIONA OK | W100: VISITA_TÉCNICA | X100: 11XZZ536 | Y100: TIPO III | Z100: TERRESTRE | AA100: QUINTERO SANCHEZ JUAN SEBASTIAN | AB100: 1 | AC100: 0 | AD100: 0 | AE100: 0 | AF100: =IF(W100="SOPORTE_TELEFÓNICO",'BASE LIQUIDACION'!$B$10,IF(Y100="TIPO I",'BASE LIQUIDACION'!$C$3,IF(Y100="TIPO II",'BASE LIQUIDACION'!$C$4,IF(Y100="TIPO III",'BASE LIQUIDACION'!$C$5,'BASE LIQUIDACION'!$C$7)))) -> 275728.38 | AG100: =IF(W100="SOPORTE_TELEFÓNICO",'BASE LIQUIDACION'!$B$10,(AB100*AF100+AC100*'BASE LIQUIDACION'!$B$12+AD100*'BASE LIQUIDACION'!$B$11+INCIDENTES!AE100*'BASE LIQUIDACION'!$B$13)) -> 275728.38
...

Sheet OC
A1: CIUDAD SEDE | B1: COORDINADOR | C1: CENTRO DE COSTOS LÍNEACOM | D1: CÓDIGO DANE | E1: TA/CODIGO ACTIVIDAD | F1: CODIGO CB | G1: ACTIVIDAD | H1: DEPARTAMENTO | I1: CIUDAD | J1: NOMBRE DEL CB | K1: RED | L1: FO | M1: FECHA ASIGNACION A LINEA COMUNICACIONES | N1: FECHA DEL CIERRE DEL TICKET (DD/MM/AAAA) | O1: ACOMETIDA | P1: SOLICITUD | Q1: DESCRIPCIÓN | R1: FORMATO | S1: CADENA | T1: ESTADO | U1: CAUSAL ESTADO | V1: OBSERVACION | W1: FORMA DE ATENCIÓN | X1: TERMINAL | Y1: TIPIFICACION | Z1: TIPO DE TRAYECTO | AA1: NOMBRE DEL TECNICO | AB1: DIAS DE VISITA | AC1: SWITCH | AD1: ACOMETIDA DATOS | AE1: ACOMETIDA ELECTRICA | AF1: VALOR ACTIVIDAD | AG1: VALOR TOTAL
A2: YOPAL | B2: =VLOOKUP(A2,'CENTRO DE COSTOS'!A:D,4,FALSE) -> KEVIN ALEXIS CORZO BUSTOS | C2: =VLOOKUP(A2,'CENTRO DE COSTOS'!A:D,2,FALSE) -> 0004-0007 | D2: 85001 | E2: 14097142 | F2: 62204 | G2: ORDEN DE CAMBIO | H2: CASANARE | I2: YOPAL | J2: BARRIO 20 DE JULIO YOPAL 1 | K2: REDEBAN | L2: FO-25-1572244 | M2: 45923.333 | N2: 45929.722 | P2: TRASLADO | Q2: TRASLADO EXTERNO | R2: CB UNO A UNO | S2: CB UNO A UNO | T2: EJECUTADO_CANCELADO | U2: DIRECCION ERRADA | V2: 29/09/2025 SE LLEGA AL COMERCIO SE PREGUNTA NO CONOCEN AL CLIENTE SE LLAMA E INDICA DONDE ESTA EL COMERCIO SE VALIDA QUE LA DIRECCIÓN SE ENCUENTRA ERRADA DIRECCIÓN CORRECTA ES CLL 6 # 19 70 | W2: VISITA_TÉCNICA | X2: 0 | Y2: =VLOOKUP(D2,TIPOLOGIAS!A:F,6,0) -> TIPO I | Z2: =VLOOKUP(D2,TIPOLOGIAS!A:F,5,0) -> TERRESTRE | AA2: ROZO JIMENEZ EDGAR ARMANDO | AB2: 1 | AC2: 0 | AD2: 0 | AE2: 0 | AF2: =IF(W2="SOPORTE_TELEFÓNICO",'BASE LIQUIDACION'!$B$10,IF(Y2="TIPO I",'BASE LIQUIDACION'!$C$3,IF(Y2="TIPO II",'BASE LIQUIDACION'!$C$4,IF(Y2="TIPO III",'BASE LIQUIDACION'!$C$5,'BASE LIQUIDACION'!$C$7)))) -> 65960.474 | AG2: =IF(W2="SOPORTE_TELEFÓNICO",'BASE LIQUIDACION'!$B$10,(AB2*AF2+AC2*'BASE LIQUIDACION'!$B$13+AD2*'BASE LIQUIDACION'!$B$12+AE2*'BASE LIQUIDACION'!$B$11)) -> 65960.474
A3: APARTADO | B3: =VLOOKUP(A3,'CENTRO DE COSTOS'!A:D,4,FALSE) -> JUAN SEBASTIÁN RÍOS CASTRILLÓN | C3: =VLOOKUP(A3,'CENTRO DE COSTOS'!A:D,2,FALSE) -> 0004-0005 | D3: 5837 | E3: 14066377 | F3: 39220 | G3: ORDEN DE CAMBIO | H3: ANTIOQUIA | I3: TURBO | J3: BARRIO TURBO TURBO | K3: REDEBAN | L3: FO-25-1572233 | M3: 45923.333 | N3: 45929.559 | P3: TRASLADO | Q3: TRASLADO EXTERNO | R3: CB UNO A UNO | S3: CB UNO A UNO | T3: EJECUTADO_CANCELADO | U3: PETICIÓN USUARIO | V3: 29/09/2025 CLIENTE NO SE ENCUENTRA EN DIRECCION, EN LLAMADA TELEFÓNICA INDICA QUE ESTARIA NUEVAMENTE EN DIRECCION EL VIERNES YA QUE SE ENCUENTRA EN MEDELLÍN | W3: VISITA_TÉCNICA | X3: 0 | Y3: =VLOOKUP(D3,TIPOLOGIAS!A:F,6,0) -> TIPO II | Z3: =VLOOKUP(D3,TIPOLOGIAS!A:F,5,0) -> TERRESTRE | AA3: CASTRO HENAO DANIEL ESTEBAN | AB3: 1 | AC3: 0 | AD3: 0 | AE3: 0 | AF3: =IF(W3="SOPORTE_TELEFÓNICO",'BASE LIQUIDACION'!$B$10,IF(Y3="TIPO I",'BASE LIQUIDACION'!$C$3,IF(Y3="TIPO II",'BASE LIQUIDACION'!$C$4,IF(Y3="TIPO III",'BASE LIQUIDACION'!$C$5,'BASE LIQUIDACION'!$C$7)))) -> 163813.56 | AG3: =IF(W3="SOPORTE_TELEFÓNICO",'BASE LIQUIDACION'!$B$10,(AB3*AF3+AC3*'BASE LIQUIDACION'!$B$13+AD3*'BASE LIQUIDACION'!$B$12+AE3*'BASE LIQUIDACION'!$B$11)) -> 163813.56
A4: NEIVA | B4: =VLOOKUP(A4,'CENTRO DE COSTOS'!A:D,4,FALSE) -> KEVIN ALEXIS CORZO BUSTOS | C4: =VLOOKUP(A4,'CENTRO DE COSTOS'!A:D,2,FALSE) -> 0004-0007 | D4: 41001 | E4: 14028037 | F4: 80793 | G4: ORDEN DE CAMBIO | H4: HUILA | I4: NEIVA | J4: BARRIO CARACOLI NEIVA | K4: REDEBAN | L4: FO-25-1546052 | M4: 45917.719 | N4: 45918.645 | P4: TRASLADO | Q4: TRASLADO EXTERNO | R4: UNO A UNO | S4: UNO A UNO | T4: EJECUTADO_CANCELADO | U4: CB CON EFECTY | V4: 18/09/2025 SE REALIZA VISITA A LA DIRECCIÓN A TRASLADAR SE EVIDENCIA EN PUNTO A TRASLADAR FUNCIONA UN EFECTY , POR POLÍTICAS DE BANCOLOMBIA NO SE REALIZA TRALSADO. | W4: VISITA_TÉCNICA | X4: 0 | Y4: =VLOOKUP(D4,TIPOLOGIAS!A:F,6,0) -> TIPO I | Z4: =VLOOKUP(D4,TIPOLOGIAS!A:F,5,0) -> TERRESTRE | AA4: DEVIA REINOSO JUAN CARLOS | AB4: 1 | AC4: 0 | AD4: 0 | AE4: 0 | AF4: =IF(W4="SOPORTE_TELEFÓNICO",'BASE LIQUIDACION'!$B$10,IF(Y4="TIPO I",'BASE LIQUIDACION'!$C$3,IF(Y4="TIPO II",'BASE LIQUIDACION'!$C$4,IF(Y4="TIPO III",'BASE LIQUIDACION'!$C$5,'BASE LIQUIDACION'!$C$7)))) -> 65960.474 | AG4: =IF(W4="SOPORTE_TELEFÓNICO",'BASE LIQUIDACION'!$B$10,(AB4*AF4+AC4*'BASE LIQUIDACION'!$B$13+AD4*'BASE LIQUIDACION'!$B$12+AE4*'BASE LIQUIDACION'!$B$11)) -> 65960.474
A5: NEIVA | B5: =VLOOKUP(A5,'CENTRO DE COSTOS'!A:D,4,FALSE) -> KEVIN ALEXIS CORZO BUSTOS | C5: =VLOOKUP(A5,'CENTRO DE COSTOS'!A:D,2,FALSE) -> 0004-0007 | D5: 41396 | E5: 14055543 | F5: 68222 | G5: ORDEN DE CAMBIO | H5: HUILA | I5: LA PLATA | J5: DISTRICOL PAGO SERVIS LA POLA | K5: REDEBAN | L5: FO-25-1542401 | M5: 45915.516 | N5: 45918.56 | P5: TRASLADO | Q5: TRASLADO EXTERNO | R5: AGREGADOR | S5: DISTRICOL | T5: EJECUTADO_CANCELADO | U5: PETICIÓN RED | V5: 18/09/2025 SE LLEGA A LA DIRECCIÓN REPORTADA EN LA ORDEN , NO HAY NADIES EN EL COMERCIO, SE CANCELA ACTIVIDAD UNA VEZ CLIENTE CONFIRMA DIRECCIÓN DEBIDO QUE SE EVIDENCIA MARCA COMPARTIDA . | W5: VISITA_TÉCNICA | X5: 0 | Y5: =VLOOKUP(D5,TIPOLOGIAS!A:F,6,0) -> TIPO III | Z5: =VLOOKUP(D5,TIPOLOGIAS!A:F,5,0) -> TERRESTRE | AA5: ANDRADE HERNANDEZ JUAN CARLOS | AB5: 1 | AC5: 0 | AD5: 0 | AE5: 0 | AF5: =IF(W5="SOPORTE_TELEFÓNICO",'BASE LIQUIDACION'!$B$10,IF(Y5="TIPO I",'BASE LIQUIDACION'!$C$3,IF(Y5="TIPO II",'BASE LIQUIDACION'!$C$4,IF(Y5="TIPO III",'BASE LIQUIDACION'!$C$5,'BASE LIQUIDACION'!$C$7)))) -> 275728.38 | AG5: =IF(W5="SOPORTE_TELEFÓNICO",'BASE LIQUIDACION'!$B$10,(AB5*AF5+AC5*'BASE LIQUIDACION'!$B$13+AD5*'BASE LIQUIDACION'!$B$12+AE5*'BASE LIQUIDACION'!$B$11)) -> 275728.38
A6: SINCELEJO | B6: =VLOOKUP(A6,'CENTRO DE COSTOS'!A:D,4,FALSE) -> JOSE MAURICIO HERNANDEZ ROJAS | C6: =VLOOKUP(A6,'CENTRO DE COSTOS'!A:D,2,FALSE) -> 0004-0001 | D6: 70001 | E6: 13981662 | F6: 77578 | G6: ORDEN DE CAMBIO | H6: SUCRE | I6: SINCELEJO | J6: BARRIO CENTRO SINCELEJO 24 | K6: REDEBAN | L6: FO-25-1514035 | M6: 45910.717 | N6: 45917.685 | P6: TRASLADO | Q6: TRASLADO EXTERNO | R6: CB UNO A UNO | S6: CB UNO A UNO | T6: EJECUTADO_CANCELADO | U6: DIRECCION ERRADA | V6: 17/09/2025 SE REALIZA VISITA PARA TRASLADO DEL CB 77578, PERO SE EVIDENCIA EN SITIO QUE EL COMERCIO TIENE FACHADA CON NOMBRE DE OTRO COMERCIO, ADICIONAL LA DIRECCIÓN QUE VIENE EN LA ORDEN Y CÁMARA DE COMERCIO NO COINCIDE CR 21 # 36 - 7 BL 3 TO 1 LC B11 CON LA DE LA CALLE EN LA QUE ESTÁ, PUES SE VALIDA DIRECCIÓN DEL CB 25634 Y ES CL 38 M A B 18 32. SE ESCALÓ CASO A LA RED Y LA RESPUESTA ES CANCELAR EL TRASLADO. | W6: VISITA_TÉCNICA | X6: 0 | Y6: =VLOOKUP(D6,TIPOLOGIAS!A:F,6,0) -> TIPO I | Z6: =VLOOKUP(D6,TIPOLOGIAS!A:F,5,0) -> TERRESTRE | AA6: SANTOS GUZMAN CHRISTIAN FELIPE | AB6: 1 | AC6: 0 | AD6: 0 | AE6: 0 | AF6: =IF(W6="SOPORTE_TELEFÓNICO",'BASE LIQUIDACION'!$B$10,IF(Y6="TIPO I",'BASE LIQUIDACION'!$C$3,IF(Y6="TIPO II",'BASE LIQUIDACION'!$C$4,IF(Y6="TIPO III",'BASE LIQUIDACION'!$C$5,'BASE LIQUIDACION'!$C$7)))) -> 65960.474 | AG6: =IF(W6="SOPORTE_TELEFÓNICO",'BASE LIQUIDACION'!$B$10,(AB6*AF6+AC6*'BASE LIQUIDACION'!$B$13+AD6*'BASE LIQUIDACION'!$B$12+AE6*'BASE LIQUIDACION'!$B$11)) -> 65960.474
A7: BOGOTA | B7: =VLOOKUP(A7,'CENTRO DE COSTOS'!A:D,4,FALSE) -> WILLIAM ASDRUBAL ROZO ROZO | C7: =VLOOKUP(A7,'CENTRO DE COSTOS'!A:D,2,FALSE) -> 0004-0004 | D7: 11001 | E7: 13984507 | F7: 32053 | G7: ORDEN DE CAMBIO | H7: CUNDINAMARCA | I7: BOGOTA | J7: BARRIO RESTREPO 13 BOGOTA | K7: REDEBAN | L7: FO-25-1514047 | M7: 45910.717 | N7: 45913.518 | P7: TRASLADO | Q7: TRASLADO EXTERNO | R7: CB UNO A UNO | S7: CB UNO A UNO | T7: EJECUTADO_CANCELADO | U7: PETICIÓN BANCOLOMBIA | V7: 17/09/2025 DURANTE LA VISITA TÉCNICA PARA REALIZAR TRASLADO DE CORRESPONSAL AL LLEGAR SE EVIDENCIA QUE CORRESPONSAL BANCARIO SE ENCUENTRA CERRADO SE PROCEDE A LLAMAR AL CLIENTE EL CUAL NOS INDICA QUE ESTÁ POR LLEGAR, SE REALIZA DE IGUAL MANERA LA VALIDACIÓN DE CERCANÍA CON OTROS CORRESPONSALES, ENCONTRANDO QUE TENEMOS PROXIMIDAD CON UN CORRESPONSAL DE ALIANZA PTM DE NÚMERO 62060 A MENOS 20 METROS, SE REALIZA ESCALAMIENTO A RBM EN DONDE NOS INDICAN CANCELAR LA ACTIVIDAD A PETICIÓN DE LA ENTIDAD BANCARIA, SE BRINDA INFORMACIÓN A COMERCIO. SE PROCEDE A REALIZAR CIERRE DE LA ACTIVIDAD | W7: VISITA_TÉCNICA | X7: 0 | Y7: =VLOOKUP(D7,TIPOLOGIAS!A:F,6,0) -> TIPO I | Z7: =VLOOKUP(D7,TIPOLOGIAS!A:F,5,0) -> TERRESTRE | AA7: GALEANO SORIANO JUAN DAVID | AB7: 1 | AC7: 0 | AD7: 0 | AE7: 0 | AF7: =IF(W7="SOPORTE_TELEFÓNICO",'BASE LIQUIDACION'!$B$10,IF(Y7="TIPO I",'BASE LIQUIDACION'!$C$3,IF(Y7="TIPO II",'BASE LIQUIDACION'!$C$4,IF(Y7="TIPO III",'BASE LIQUIDACION'!$C$5,'BASE LIQUIDACION'!$C$7)))) -> 65960.474 | AG7: =IF(W7="SOPORTE_TELEFÓNICO",'BASE LIQUIDACION'!$B$10,(AB7*AF7+AC7*'BASE LIQUIDACION'!$B$13+AD7*'BASE LIQUIDACION'!$B$12+AE7*'BASE LIQUIDACION'!$B$11)) -> 65960.474
A8: MEDELLIN | B8: =VLOOKUP(A8,'CENTRO DE COSTOS'!A:D,4,FALSE) -> JUAN SEBASTIÁN RÍOS CASTRILLÓN | C8: =VLOOKUP(A8,'CENTRO DE COSTOS'!A:D,2,FALSE) -> 0004-0005 | D8: 5001 | E8: 14011980 | F8: 76177 | G8: ORDEN DE CAMBIO | H8: ANTIOQUIA | I8: MEDELLIN | J8: PTM MEDELLIN MYCELL MEDELLIN | K8: REDEBAN | L8: FO-25-1503416 | M8: 45909.391 | N8: 45910.596 | P8: TRASLADO | Q8: TRASLADO EXTERNO | R8: AGREGADOR | S8: COMCARD - PTM | T8: EJECUTADO_CANCELADO | U8: PETICIÓN USUARIO | V8: 10/09/2025 SE LLEGA PUNTO Y CLIENTE INDICA QUE SE SOLICITÓ EL TRASLADO PERO EL CC AUN NO LE A ENTREGADO EL LOCAL, EL TEMA YA ESTA ESCALADO CON PTM Y SE ESTA A LA ESPERA | W8: VISITA_TÉCNICA | X8: 0 | Y8: =VLOOKUP(D8,TIPOLOGIAS!A:F,6,0) -> TIPO I | Z8: =VLOOKUP(D8,TIPOLOGIAS!A:F,5,0) -> TERRESTRE | AA8: BADEL ACUÑA LUIS ALBERTO | AB8: 1 | AC8: 0 | AD8: 0 | AE8: 0 | AF8: =IF(W8="SOPORTE_TELEFÓNICO",'BASE LIQUIDACION'!$B$10,IF(Y8="TIPO I",'BASE LIQUIDACION'!$C$3,IF(Y8="TIPO II",'BASE LIQUIDACION'!$C$4,IF(Y8="TIPO III",'BASE LIQUIDACION'!$C$5,'BASE LIQUIDACION'!$C$7)))) -> 65960.474 | AG8: =IF(W8="SOPORTE_TELEFÓNICO",'BASE LIQUIDACION'!$B$10,(AB8*AF8+AC8*'BASE LIQUIDACION'!$B$13+AD8*'BASE LIQUIDACION'!$B$12+AE8*'BASE LIQUIDACION'!$B$11)) -> 65960.474
A9: BUCARAMANGA | B9: =VLOOKUP(A9,'CENTRO DE COSTOS'!A:D,4,FALSE) -> MIGUEL JULIÁN HERNÁNDEZ GUARÍN | C9: =VLOOKUP(A9,'CENTRO DE COSTOS'!A:D,2,FALSE) -> 0004-0008 | D9: 13688 | E9: 14012829 | F9: 73893 | G9: ORDEN DE CAMBIO | H9: BOLIVAR | I9: SANTA ROSA DEL SUR | J9: DISTRICOL PENAS BISTRO | K9: REDEBAN | L9: FO-25-1503431 | M9: 45909.391 | N9: 45912.521 | P9: TRASLADO | Q9: TRASLADO EXTERNO | R9: AGREGADOR | S9: DISTRICOL | T9: EJECUTADO_CANCELADO | U9: DIRECCION ERRADA | V9: 12/09/2025 SE LLEGA AL SITIO POR INDICACIO DE RBM DIRECCION:CR 12 #11 80 PERO NO CONCUERDA NO EXISTE , EN COMUNICACIÓN CON LA USUARIA INDICA QUE ES POR LA CALLE 12# 11 ; SE LLEGA AL PUNTO DONDE SE LE INDICA AL CLIENTE QUE ESA DIRECCIÓN NO CONCUERDA CON LA ORDEN , CLIENTE INDICA QUE ESTÁ MAL LA INFORMACIÓN QUE ELLOS SE VAN A COMUNICAR CON LA ALIANZA DISTRICOL PARA QUE ACTUALICEN LA INFORMACIÓN DE LA CAMARA DE COMERCIO, CLIENTE INDICA QUE POR EL MOMENTO CONTINÚA EN LA DIRECCIÓN ANTIGUA Y QUE APENAS TENGA LA AUTORIZACIÓN DE DISTRICOL SE COMUNICA NUEVAMENTE , CASI FUE ESCALADO CON COORDINADOR DE ZONA DONDE INDICA CANCELAR TRASLADO | W9: VISITA_TÉCNICA | X9: 0 | Y9: =VLOOKUP(D9,TIPOLOGIAS!A:F,6,0) -> TIPO IV ESPECIAL | Z9: =VLOOKUP(D9,TIPOLOGIAS!A:F,5,0) -> TERRESTRE/FLUVIAL | AA9: HERRERA LUQUE SAUL JAVIER | AB9: 1 | AC9: 0 | AD9: 0 | AE9: 0 | AF9: =IF(W9="SOPORTE_TELEFÓNICO",'BASE LIQUIDACION'!$B$10,IF(Y9="TIPO I",'BASE LIQUIDACION'!$C$3,IF(Y9="TIPO II",'BASE LIQUIDACION'!$C$4,IF(Y9="TIPO III",'BASE LIQUIDACION'!$C$5,'BASE LIQUIDACION'!$C$7)))) -> 479589.74 | AG9: =IF(W9="SOPORTE_TELEFÓNICO",'BASE LIQUIDACION'!$B$10,(AB9*AF9+AC9*'BASE LIQUIDACION'!$B$13+AD9*'BASE LIQUIDACION'!$B$12+AE9*'BASE LIQUIDACION'!$B$11)) -> 479589.74
A10: YOPAL | B10: =VLOOKUP(A10,'CENTRO DE COSTOS'!A:D,4,FALSE) -> KEVIN ALEXIS CORZO BUSTOS | C10: =VLOOKUP(A10,'CENTRO DE COSTOS'!A:D,2,FALSE) -> 0004-0007 | D10: 85001 | E10: 14012940 | F10: 73661 | G10: ORDEN DE CAMBIO | H10: CASANARE | I10: YOPAL | J10: DISTRICOL GRUPO GARYED SAS | K10: REDEBAN | L10: FO-25-1503436 | M10: 45909.391 | N10: 45909.678 | P10: TRASLADO | Q10: TRASLADO EXTERNO | R10: AGREGADOR | S10: DISTRICOL | T10: GESTIÓN_TELEFONICA | U10: CANCELADO POR EL USUARIO | V10: 09/09/2025 SE INTENTA COMUNICACIÓN AL NÚMERO 3103396539 PERO NO HAY RESPUESTA Y TAMPOCO POR WHATSAPP, SE ESCALA PARA VISITA POR FAVOR LLAMAR ANTES DE DESPLAZARSE | W10: SOPORTE_TELEFÓNICO | X10: 0 | Y10: =VLOOKUP(D10,TIPOLOGIAS!A:F,6,0) -> TIPO I | Z10: =VLOOKUP(D10,TIPOLOGIAS!A:F,5,0) -> TERRESTRE | AA10: BERNAL ELAICA EDGAR ALEXIS | AB10: 0 | AC10: 0 | AD10: 0 | AE10: 0 | AF10: =IF(W10="SOPORTE_TELEFÓNICO",'BASE LIQUIDACION'!$B$10,IF(Y10="TIPO I",'BASE LIQUIDACION'!$C$3,IF(Y10="TIPO II",'BASE LIQUIDACION'!$C$4,IF(Y10="TIPO III",'BASE LIQUIDACION'!$C$5,'BASE LIQUIDACION'!$C$7)))) -> 37904.654 | AG10: =IF(W10="SOPORTE_TELEFÓNICO",'BASE LIQUIDACION'!$B$10,(AB10*AF10+AC10*'BASE LIQUIDACION'!$B$13+AD10*'BASE LIQUIDACION'!$B$12+AE10*'BASE LIQUIDACION'!$B$11)) -> 37904.654
A11: MEDELLIN | B11: =VLOOKUP(A11,'CENTRO DE COSTOS'!A:D,4,FALSE) -> JUAN SEBASTIÁN RÍOS CASTRILLÓN | C11: =VLOOKUP(A11,'CENTRO DE COSTOS'!A:D,2,FALSE) -> 0004-0005 | D11: 5001 | E11: 13963693 | F11: 51338 | G11: ORDEN DE CAMBIO | H11: ANTIOQUIA | I11: MEDELLIN | J11: PTM MEDELLIN MERCADOS SUAREZ | K11: REDEBAN | L11: FO-25-1456174 | M11: 45901.455 | N11: 45903.498 | P11: TRASLADO | Q11: TRASLADO EXTERNO | R11: AGREGADOR | S11: COMCARD - PTM | T11: EJECUTADO_CANCELADO | U11: OC REPETIDA | V11: 03/09/2025 SE LLEGA AL PUNTO Y SE VERIFICA QUE EL TRASLADO YA FUE REALIZADO ANTERIORMENTE | W11: VISITA_TÉCNICA | X11: 0 | Y11: =VLOOKUP(D11,TIPOLOGIAS!A:F,6,0) -> TIPO I | Z11: =VLOOKUP(D11,TIPOLOGIAS!A:F,5,0) -> TERRESTRE | AA11: BADEL ACUÑA LUIS ALBERTO | AB11: 1 | AC11: 0 | AD11: 0 | AE11: 0 | AF11: =IF(W11="SOPORTE_TELEFÓNICO",'BASE LIQUIDACION'!$B$10,IF(Y11="TIPO I",'BASE LIQUIDACION'!$C$3,IF(Y11="TIPO II",'BASE LIQUIDACION'!$C$4,IF(Y11="TIPO III",'BASE LIQUIDACION'!$C$5,'BASE LIQUIDACION'!$C$7)))) -> 65960.474 | AG11: =IF(W11="SOPORTE_TELEFÓNICO",'BASE LIQUIDACION'!$B$10,(AB11*AF11+AC11*'BASE LIQUIDACION'!$B$13+AD11*'BASE LIQUIDACION'!$B$12+AE11*'BASE LIQUIDACION'!$B$11)) -> 65960.474
A12: BOGOTA | B12: =VLOOKUP(A12,'CENTRO DE COSTOS'!A:D,4,FALSE) -> WILLIAM ASDRUBAL ROZO ROZO | C12: =VLOOKUP(A12,'CENTRO DE COSTOS'!A:D,2,FALSE) -> 0004-0004 | D12: 11001 | E12: 13963793 | F12: 78672 | G12: ORDEN DE CAMBIO | H12: CUNDINAMARCA | I12: BOGOTA | J12: PTM BOGOTA COMERCIALIZADORA Y | K12: REDEBAN | L12: FO-25-1456154 | M12: 45901.455 | N12: 45902.66 | P12: TRASLADO | Q12: TRASLADO EXTERNO | R12: AGREGADOR | S12: COMCARD - PTM | T12: EJECUTADO_CANCELADO | U12: DIRECCION ERRADA | V12: 02/09/2025 SE VISITA CB POR TRASLADO DE PUNTO AL LLEGAR A LA DIRECCIÓN DE LA ORDEN CR 11 S#40-03 SUR ESTÁ NO EXISTE , SE PROCEDE A CONTACTAR A CLIENTE QUIÉN CONFIRMA DIRECCIÓN REAL COMO CR 11F#40-03 SUR SE INDICA A CLIENTE QUE ES NECESARIO ACTUALIZAR LA INFORMACIÓN Y SOLICITAR NUEVAMENTE EL TRASLADO SE VISITA A CLIENTE EN DIRECCIÓN REAL DONDE DEBE REALIZARSE EL TRASLADO Y SE FINALIZA ACTIVIDAD SMAS NOVEDAD | W12: VISITA_TÉCNICA | X12: 0 | Y12: =VLOOKUP(D12,TIPOLOGIAS!A:F,6,0) -> TIPO I | Z12: =VLOOKUP(D12,TIPOLOGIAS!A:F,5,0) -> TERRESTRE | AA12: ROMERO ROJAS BREIDY JHOHAN | AB12: 1 | AC12: 0 | AD12: 0 | AE12: 0 | AF12: =IF(W12="SOPORTE_TELEFÓNICO",'BASE LIQUIDACION'!$B$10,IF(Y12="TIPO I",'BASE LIQUIDACION'!$C$3,IF(Y12="TIPO II",'BASE LIQUIDACION'!$C$4,IF(Y12="TIPO III",'BASE LIQUIDACION'!$C$5,'BASE LIQUIDACION'!$C$7)))) -> 65960.474 | AG12: =IF(W12="SOPORTE_TELEFÓNICO",'BASE LIQUIDACION'!$B$10,(AB12*AF12+AC12*'BASE LIQUIDACION'!$B$13+AD12*'BASE LIQUIDACION'!$B$12+AE12*'BASE LIQUIDACION'!$B$11)) -> 65960.474
A13: CALI | B13: =VLOOKUP(A13,'CENTRO DE COSTOS'!A:D,4,FALSE) -> DIEGO FERNANDO HENAO CARDONA | C13: =VLOOKUP(A13,'CENTRO DE COSTOS'!A:D,2,FALSE) -> 0004-0003 | D13: 76001 | E13: 13967173 | F13: 44824 | G13: ORDEN DE CAMBIO | H13: VALLE DEL CAUCA | I13: CALI | J13: DISTRICOL D Y M INTERCOMUNICAC | K13: REDEBAN | L13: FO-25-1456172 | M13: 45901.455 | N13: 45902.551 | P13: TRASLADO | Q13: TRASLADO EXTERNO | R13: AGREGADOR | S13: DISTRICOL | T13: EJECUTADO_CANCELADO | U13: PETICIÓN BANCOLOMBIA | V13: 02/09/2025 SE REALIZA VISITA AL COMERCIO PARA REALIZAR EL TRASLADO, PERO SE ENCUENTRA QUE EN EL MISMO COMERCIO SE ENCUENTRA PUBLICIDAD O CB DEL GRUPO AVAL. ‎POR LO QUE NO SE REALIZA EL TRASLADO Y SE LE INFORMA A EL CLIENTE. | W13: VISITA_TÉCNICA | X13: 0 | Y13: =VLOOKUP(D13,TIPOLOGIAS!A:F,6,0) -> TIPO I | Z13: =VLOOKUP(D13,TIPOLOGIAS!A:F,5,0) -> TERRESTRE | AA13: TORRES GARCIA JENDRY JOSE | AB13: 1 | AC13: 0 | AD13: 0 | AE13: 0 | AF13: =IF(W13="SOPORTE_TELEFÓNICO",'BASE LIQUIDACION'!$B$10,IF(Y13="TIPO I",'BASE LIQUIDACION'!$C$3,IF(Y13="TIPO II",'BASE LIQUIDACION'!$C$4,IF(Y13="TIPO III",'BASE LIQUIDACION'!$C$5,'BASE LIQUIDACION'!$C$7)))) -> 65960.474 | AG13: =IF(W13="SOPORTE_TELEFÓNICO",'BASE LIQUIDACION'!$B$10,(AB13*AF13+AC13*'BASE LIQUIDACION'!$B$13+AD13*'BASE LIQUIDACION'!$B$12+AE13*'BASE LIQUIDACION'!$B$11)) -> 65960.474
AG14: =SUM(AG2:AG13) -> 1484720.1

Sheet CENTRO DE COSTOS
A1: CIUDAD | B1: CENTRO_COSTO | C1: DESCRIPCION | D1: COORDINADOR
A2: APARTADO | B2: 0004-0005 | C2: Redeban Noroccidente (Medellín) | D2: JUAN SEBASTIÁN RÍOS CASTRILLÓN
A3: BARRANQUILLA | B3: 0004-0001 | C3: Redeban Costa (Barranqullla) | D3: JOSE MAURICIO HERNANDEZ ROJAS
A4: BOGOTA | B4: 0004-0004 | C4: Redeban Centro ( Bogotá) | D4: WILLIAM ASDRUBAL ROZO ROZO
A5: BUCARAMANGA | B5: 0004-0008 | C5: Redeban Santander | D5: MIGUEL JULIÁN HERNÁNDEZ GUARÍN
A6: CALI | B6: 0004-0003 | C6: Redeban Suroccidente (Cali) | D6: DIEGO FERNANDO HENAO CARDONA
A7: CARTAGENA | B7: 0004-0001 | C7: Redeban Costa (Barranqullla) | D7: JOSE MAURICIO HERNANDEZ ROJAS
A8: CUCUTA | B8: 0004-0008 | C8: Redeban Santander | D8: MIGUEL JULIÁN HERNÁNDEZ GUARÍN
A9: FLORENCIA | B9: 0004-0007 | C9: Redeban Oriente (Otros) | D9: KEVIN ALEXIS CORZO BUSTOS
A10: IBAGUE | B10: 0004-0007 | C10: Redeban Oriente (Otros) | D10: KEVIN ALEXIS CORZO BUSTOS
A11: MANIZALES | B11: 0004-0002 | C11: Redeban Eje Cafetero (Pereira) | D11: DIEGO FERNANDO HENAO CARDONA
A12: MEDELLIN | B12: 0004-0005 | C12: Redeban Noroccidente (Medellín) | D12: JUAN SEBASTIÁN RÍOS CASTRILLÓN
... A23: YOPAL | B23: 0004-0007 | C23: Redeban Oriente (Otros) | D23: KEVIN ALEXIS CORZO BUSTOS
