Workbook
Name A: #REF!
Name A: #REF!
Name ACTIVIDAD: [1]Hoja2!$P$2:$P$30
Name Actividad: [2]Formulas!$H$2:$H$5000
Name Analistas: '[3]Listas Desplegables'!$T$2:$T$7
Name arearesponsable: '[4]Listas desplegables'!$BB$2:$BB$100
Name CCO: [5]Tecnicos!$A$2:$A$1000
Name Clientes: [6]Clientes!$A$2:$A$100
Name Clientes: [2]Clientes!$A$2:$A$100
Name COORDINADOR: [1]Hoja2!$D$2:$D$30
Name Coordinadores: [7]Coordinadores!$A$2:$A$1000
Name Coordinadores: [2]Coordinadores!$A$2:$A$1000
Name DOCUMENTADOR: [1]Hoja2!$A$2:$A$30
Name ES: [1]Hoja2!$K$2:$K$30
Name ESS: [1]Hoja2!$K$2:$K$30
Name Estado: [6]Formulas!$K$2:$K$5000
Name Estado: [2]Formulas!$K$2:$K$5000
Name ESTADOACTIVIDAD: [1]Hoja2!$M$2:$M$30
Name ESTADOS: '[8]Listas desplegables'!$B$1:$D$1
Name ESTADOS: '[9]Listas desplegables'!$B$1:$D$1
Name ESTADOSCIERRES: '[10]lista desplegable'!$CX$1:$DA$1
Name Facturacion: '[11]Listas desplegables'!$AO$1:$AR$1
Name FACTURACIÓN: '[8]Listas desplegables'!$Y$1:$AB$1
Name FACTURACIÓN: '[9]Listas desplegables'!$Y$1:$AB$1
Name falla: #REF!
Name Fallas: '[12]Listas desplegables'!$F$2:$L$2
Name Fallas: '[13]Listas desplegables'!$F$2:$L$2
Name Grupo_Falla: '[14]Listas Desplegables'!$CH$2:$CH$5
Name Grupo_Falla: '[15]Listas Desplegables'!$CH$2:$CH$5
Name inconservmanager: '[16]Listas desplegables'!$BC$2:$BC$100
Name inconservmanager: '[4]Listas desplegables'!$BC$2:$BC$100
Name INCUMPLIMIENTO: '[4]Listas desplegables'!$AK$1:$AN$1
Name INCUMPLIMIENTO: '[17]Listas desplegables'!$AT$1:$AX$1
Name LISTA: [18]Dptos!$A$1139:$A$1171
Name LISTA: [19]Dptos!$A$1139:$A$1171
Name LISTA2: #REF!
Name LISTA2: #REF!
Name LOLO: [20]Coordinadores!$A$2:$A$1000
Name solicitudes: '[11]Listas desplegables'!$U$1:$AF$1
Name solicitudes: '[21]Listas desplegables'!$AF$1:$AQ$1
Name Tecnicos: [6]Tecnicos!$A$2:$A$1000
Name Tecnicos: [2]Tecnicos!$A$2:$A$1000
Name Version: [22]Formulas!$I$2:$I$3
Name Version: [2]Formulas!$I$2:$I$3

Sheet Detalle REDEBAN
A1: FACTURACIÓN ACTIVIDADES REDEBAN CB BANCOLOMBIA Y AVAL
A2: 1 AL 30 DE SEPTIEMBRE 2025
A4: CONCEPTOS | B4: CANTIDAD | C4: TOTAL
A5: Aperturas Bancolombia | B5: =COUNTA('APERTURAS BANCOLOMBIA'!$A:$A)-1 -> 219 | C5: ='APERTURAS BANCOLOMBIA'!AC221 -> 42735836
A6: Incidentes Bancolombia | B6: =COUNTA('INCIDENTES BANCOLOMBIA'!A:A)-1 -> 1194 | C6: ='INCIDENTES BANCOLOMBIA'!AF1196 -> 1.9131574e+08
A7: Gestión de Campo Bancolombia | B7: =COUNTA('OC BANCOLOMBIA'!A:A)-1 -> 447 | C7: ='OC BANCOLOMBIA'!AF449 -> 70068670
A8: Soporte Papelería Bancolombia | B8: =COUNTA(PAPELERIA!A:A)-1 -> 1946 | C8: =PAPELERIA!AE1948 -> 82774117
A9: Aperturas Aval | B9: =COUNTA('APERTURAS AVAL'!A:A)-1 -> 188 | C9: ='APERTURAS AVAL'!AB190 -> 39272916
A10: Incidentes Aval | B10: =COUNTA('INCIDENTES AVAL'!A:A)-1 -> 283 | C10: ='INCIDENTES AVAL'!AD285 -> 164964.32
A11: Gestión de Campo Aval | B11: =COUNTA('OC AVAL'!A:A)-1 -> 63 | C11: ='OC AVAL'!AF65 -> 7805089.8
A12: Aperturas BBVA | B12: =COUNTA('APERTURAS BBVA'!A:A)-1 -> 0 | C12: ='APERTURAS BBVA'!AH3 -> 0
A13: Gestión de Campo BBVA | B13: =COUNTA('OC BBVA'!A:A)-1 -> 0 | C13: ='OC BBVA'!AF4 -> 0
A14: Incidentes BBVA | B14: =COUNTA('INCIDENTES BBVA'!A:A)-1 -> 0 | C14: ='INCIDENTES BBVA'!AD5 -> 0
A15: SUBTOTAL | C15: =SUM(C5:C14) -> 4.3413733e+08
A16: Iva | C16: =C15*0.19 -> 82486092
A17: TOTAL | B17: TOTAL | C17: =C15+C16 -> 5.1662342e+08

Sheet BASE LIQUIDACION REDEBAN 2025
A1: Tipificación | B1: Implementaciones | C1: Incidentes – Ordenes de Cambio | D1: Fallida | G1: Tipificación | H1: Actividad sin cambio de datafono | J1: Actividad + adicional cambio de datafono | L1: Visita Fallida | N1: Incremento 2025
A2: TIPO I | B2: =71384.4052*(1+$N$2) -> 75096.394 | C2: =62699.6885*(1+$N$2) -> 65960.072 | D2: =35693.4343*(1+$N$2) -> 37549.493 | H2: Instalación Pinpad + HUB | I2: Segunda actividad en mismo comercio, misma visita | J2: Instalación Pinpad + HUB | K2: Segunda actividad en mismo comercio, misma visita | N2: 0.052
A3: TIPO II | B3: =155716.4408*(1+$N$2) -> 163813.7 | C3: =137802.16*(1+$N$2) -> 144967.87 | D3: =117879.8485*(1+$N$2) -> 124009.6 | G3: Tipo I | H3: =31819.23994686*(1+$N$2) -> 33473.84 | I3: =26222.67548178*(1+$N$2) -> 27586.255 | J3: =51196.46628516*(1+$N$2) -> 53858.683 | K3: =42157.66342524*(1+$N$2) -> 44349.862 | L3: =28948.10610808*(1+$N$2) -> 30453.408
A4: TIPO III | B4: =262099.6015*(1+$N$2) -> 275728.78 | C4: =262099.6015*(1+$N$2) -> 275728.78 | D4: =262099.6015*(1+$N$2) -> 275728.78 | G4: Tipo II | H4: =98014.03066668*(1+$N$2) -> 103110.76 | I4: =26222.67548178*(1+$N$2) -> 27586.255 | J4: =119562.49505524*(1+$N$2) -> 125779.74 | K4: =42157.66342524*(1+$N$2) -> 44349.862 | L4: =94765.6295813*(1+$N$2) -> 99693.442
A5: TIPO IV | B5: =479878.9419*(1+$N$2) -> 504832.65 | C5: =455882.9625*(1+$N$2) -> 479588.88 | D5: =370911.6746*(1+$N$2) -> 390199.08 | G5: Tipo III | H5: =189140.9827006*(1+$N$2) -> 198976.31 | I5: =26222.67548178*(1+$N$2) -> 27586.255 | J5: =200461.60194168*(1+$N$2) -> 210885.61 | K5: =42157.66342524*(1+$N$2) -> 44349.862 | L5: =171492.68108896*(1+$N$2) -> 180410.3
A6: Destino Aéreo | B6: =939603.5767*(1+$N$2) -> 988462.96 | C6: a partir del 5to servicio | G6: Tipo IV | H6: =461621.60109668*(1+$N$2) -> 485625.92 | I6: =26222.67548178*(1+$N$2) -> 27586.255 | J6: =461621.60109668*(1+$N$2) -> 485625.92 | K6: =42157.66342524*(1+$N$2) -> 44349.862 | L6: =461621.60109668*(1+$N$2) -> 485625.92
G7: * Tipo IV Especial Donde se requiera desplazamiento aéreo o fluvial será facturado el valor de la actividad y adicional el valor de $988.463 por cada 5 actividades de esta tipología
A8: Tarifas para día adicional de actividades:
A9: Tipificación | B9: Día adicional- menos de dos horas | C9: Medio día adicional | D9: Día adicional- más de 4 horas
A10: Tipo I | B10: =71384.4052*(1+$N$2) -> 75096.394 | C10: =133455.9267*(1+$N$2) -> 140395.63 | D10: =191225.1201*(1+$N$2) -> 201168.83 | G10: Actividad | H10: Unidad | I10: Valor Unitario
A11: Tipo II | B11: =133455.9267*(1+$N$2) -> 140395.63 | C11: =191225.1201*(1+$N$2) -> 201168.83 | D11: =257740.6152*(1+$N$2) -> 271143.13 | G11: Gestión telefónica y cierre de incidente de bloqueo | H11: Unidad | I11: =17639.19516086*(1+$N$2) -> 18556.433
A12: Tipo III | B12: =186821.7926*(1+$N$2) -> 196536.53 | C12: =248892.0824*(1+$N$2) -> 261834.47 | D12: =306662.5075*(1+$N$2) -> 322608.96 | G12: Servicio de cierre de incidente de bloqueo | H12: Unidad | I12: =4810.80785492*(1+$N$2) -> 5060.9699
A13: Tipo IV | B13: =186821.7926*(1+$N$2) -> 196536.53 | C13: =248892.0824*(1+$N$2) -> 261834.47 | D13: =306662.5075*(1+$N$2) -> 322608.96
A16: Servicio | B16: Tarifa actividad | D16: VALOR DE LA TERMINAL ADICIONAL | E16: VALOR DE INSTALACIÓN DE BASE EN "Y"
A17: Papelería – Tarifa única | B17: =34010.9321*(1+$N$2) -> 35779.501 | D17: =20537.3658*(1+$N$2) -> 21605.309 | E17: =10737.9606*(1+$N$2) -> 11296.335
A18: Papelería Tipo II - Visita técnica | B18: =64310*(1+$N$2) -> 67654.12
A19: Solución telefónica | B19: =39202.5476*(1+$N$2) -> 41241.08
A22: Traifas 2024
A23: Tipificación | B23: Implementaciones | C23: Incidentes – Ordenes de Cambio | D23: Fallida | G23: Tipificación | H23: Actividad sin cambio de datafono | J23: Actividad + adicional cambio de datafono | L23: Visita Fallida
A24: TIPO I | B24: 71384.405 | C24: 62699.689 | D24: 35693.434 | H24: Instalación Pinpad + HUB | I24: Segunda actividad en mismo comercio, misma visita | J24: Instalación Pinpad + HUB | K24: Segunda actividad en mismo comercio, misma visita
A25: TIPO II | B25: 155716.44 | C25: 137802.16 | D25: 117879.85 | G25: Tipo I | H25: 31819.24 | I25: 26222.675 | J25: 51196.466 | K25: 42157.663 | L25: 28948.106
A26: TIPO III | B26: 262099.6 | C26: 262099.6 | D26: 262099.6 | G26: Tipo II | H26: 98014.031 | I26: 26222.675 | J26: 119562.5 | K26: 42157.663 | L26: 94765.63
A27: TIPO IV | B27: 479878.94 | C27: 455882.96 | D27: 370911.67 | G27: Tipo III | H27: 189140.98 | I27: 26222.675 | J27: 200461.6 | K27: 42157.663 | L27: 171492.68
A28: Destino Aéreo | B28: 939603.58 | C28: a partir del 5to servicio | G28: Tipo IV | H28: 461621.6 | I28: 26222.675 | J28: 461621.6 | K28: 42157.663 | L28: 461621.6
G29: * Tipo IV Especial Donde se requiera desplazamiento aéreo o fluvial será facturado el valor de la actividad y adicional el valor de $939,604 por cada 5 actividades de esta tipología
A30: Tarifas para día adicional de actividades:
A31: Tipificación | B31: Día adicional- menos de dos horas | C31: Medio día adicional | D31: Día adicional- más de 4 horas
A32: Tipo I | B32: 71384.405 | C32: 133455.93 | D32: 191225.12 | G32: Actividad | H32: Unidad | I32: Valor Unitario
A33: Tipo II | B33: 133455.93 | C33: 191225.12 | D33: 257740.62 | G33: Gestión telefónica y cierre de incidente de bloqueo | H33: Unidad | I33: 17639.195
A34: Tipo III | B34: 186821.79 | C34: 248892.08 | D34: 306662.51 | G34: Servicio de cierre de incidente de bloqueo | H34: Unidad | I34: 4810.8079
A35: Tipo IV | B35: 186821.79 | C35: 248892.08 | D35: 306662.51
A38: Servicio | B38: Tarifa actividad | D38: VALOR DE LA TERMINAL ADICIONAL | E38: VALOR DE INSTALACIÓN DE BASE EN "Y"
A39: Papelería – Tarifa única | B39: 34010.932 | D39: 20537.366 | E39: 10737.961
A40: Papelería Tipo II - Visita técnica | B40: 64310
A41: Solución telefónica | B41: 39202.548

Sheet CENTRO DE COSTOS
A1: CIUDAD | B1: CENTRO_COSTO | C1: DESCRIPCION | D1: COORDINADOR
A2: APARTADO | B2: 0004-0005 | C2: Redeban Noroccidente (Medellín) | D2: JUAN SEBASTIÁN RÍOS CASTRILLÓN
A3: BARRANQUILLA | B3: 0004-0001 | C3: Redeban Costa (Barranqullla) | D3: JOSE MAURICIO HERNANDEZ ROJAS
A4: BOGOTA | B4: 0004-0004 | C4: Redeban Centro ( Bogotá) | D4: WILLIAM ASDRUBAL ROZO ROZO
A5: BUCARAMANGA | B5: 0004-0008 | C5: Redeban Santander | D5: MIGUEL JULIÁN HERNÁNDEZ GUARÍN
A6: CALI | B6: 0004-0003 | C6: Redeban Suroccidente (Cali) | D6: DIEGO FERNANDO HENAO CARDONA
A7: CARTAGENA | B7: 0004-0001 | C7: Redeban Costa (Barranqullla) | D7: JOSE MAURICIO HERNANDEZ ROJAS
A8: CUCUTA | B8: 0004-0008 | C8: Redeban Santander | D8: MIGUEL JULIÁN HERNÁNDEZ GUARÍN
A9: FLORENCIA | B9: 0004-0007 | C9: Redeban Oriente (Otros) | D9: KEVIN ALEXIS CORZO BUSTOS
A10: IBAGUE | B10: 0004-0007 | C10: Redeban Oriente (Otros) | D10: KEVIN ALEXIS CORZO BUSTOS
A11: MANIZALES | B11: 0004-0002 | C11: Redeban Eje Cafetero (Pereira) | D11: DIEGO FERNANDO HENAO CARDONA
A12: MEDELLIN | B12: 0004-0005 | C12: Redeban Noroccidente (Medellín) | D12: JUAN SEBASTIÁN RÍOS CASTRILLÓN
... A23: YOPAL | B23: 0004-0007 | C23: Redeban Oriente (Otros) | D23: KEVIN ALEXIS CORZO BUSTOS

Sheet Tablas dinámicas
A1: APERTURAS BANCOLOMBIA | G1: NOMBRE DE CC | H1: Suma de VALOR CC | I1: Suma de VALOR CC2
A2: COORDINADOR | B2: CENTRO DE COSTOS LÍNEACOM | C2: Suma de VALOR FACTURABLE A LA RED | D2: NOMBRE DE CC | E2: VALOR CC | G2: Redeban Centro ( Bogotá) | H2: 48969421 | I2: 0.10471527
A3: DIEGO FERNANDO HENAO CARDONA | B3: 0004-0002 | C3: 1231369.1 | D3: =VLOOKUP(B3,'CENTRO DE COSTOS'!B:C,2,0) -> Redeban Eje Cafetero (Pereira) | E3: =C3 -> 1231369.1 | G3: Redeban Costa (Barranqullla) | H3: 75691830 | I3: 0.16185796
B4: 0004-0003 | C4: 10239672 | D4: =VLOOKUP(B4,'CENTRO DE COSTOS'!B:C,2,0) -> Redeban Suroccidente (Cali) | E4: =C4 -> 10239672 | G4: Redeban Eje Cafetero (Pereira) | H4: 17132270 | I4: 0.036635318
A5: JOSE MAURICIO HERNANDEZ ROJAS | B5: 0004-0001 | C5: 5024949.9 | D5: =VLOOKUP(B5,'CENTRO DE COSTOS'!B:C,2,0) -> Redeban Costa (Barranqullla) | E5: =C5 -> 5024949.9 | G5: Redeban Noroccidente (Medellín) | H5: 1.0878126e+08 | I5: 0.23261575
A6: JUAN SEBASTIÁN RÍOS CASTRILLÓN | B6: 0004-0005 | C6: 8253502.7 | D6: =VLOOKUP(B6,'CENTRO DE COSTOS'!B:C,2,0) -> Redeban Noroccidente (Medellín) | E6: =C6 -> 8253502.7 | G6: Redeban Oriente (Otros) | H6: 64858437 | I6: 0.13869204
A7: KEVIN ALEXIS CORZO BUSTOS | B7: 0004-0007 | C7: 4179634.7 | D7: =VLOOKUP(B7,'CENTRO DE COSTOS'!B:C,2,0) -> Redeban Oriente (Otros) | E7: =C7 -> 4179634.7 | G7: Redeban Santander | H7: 79260436 | I7: 0.169489
A8: MIGUEL JULIÁN HERNÁNDEZ GUARÍN | B8: 0004-0008 | C8: 11574428 | D8: =VLOOKUP(B8,'CENTRO DE COSTOS'!B:C,2,0) -> Redeban Santander | E8: =C8 -> 11574428 | G8: Redeban Suroccidente (Cali) | H8: 72949894 | I8: 0.15599466
A9: WILLIAM ASDRUBAL ROZO ROZO | B9: 0004-0004 | C9: 2232279.1 | D9: =VLOOKUP(B9,'CENTRO DE COSTOS'!B:C,2,0) -> Redeban Centro ( Bogotá) | E9: =C9 -> 2232279.1 | G9: Total general | H9: 4.6764355e+08 | I9: 1
A10: Total general | C10: 42735836
A15: INCIDENTES BANCOLOMBIA
A16: COORDINADOR | B16: CENTRO DE COSTOS LÍNEACOM | C16: Suma de VALOR FACTURABLE A LA RED | D16: NOMBRE DE CC | E16: VALOR CC
A17: DIEGO FERNANDO HENAO CARDONA | B17: 0004-0002 | C17: 7477346.2 | D17: =VLOOKUP(B17,'CENTRO DE COSTOS'!B:C,2,0) -> Redeban Eje Cafetero (Pereira) | E17: =C17 -> 7477346.2
B18: 0004-0003 | C18: 24817715 | D18: =VLOOKUP(B18,'CENTRO DE COSTOS'!B:C,2,0) -> Redeban Suroccidente (Cali) | E18: =C18 -> 24817715
A19: JOSE MAURICIO HERNANDEZ ROJAS | B19: 0004-0001 | C19: 38450028 | D19: =VLOOKUP(B19,'CENTRO DE COSTOS'!B:C,2,0) -> Redeban Costa (Barranqullla) | E19: =C19 -> 38450028
A20: JUAN SEBASTIÁN RÍOS CASTRILLÓN | B20: 0004-0005 | C20: 56740009 | D20: =VLOOKUP(B20,'CENTRO DE COSTOS'!B:C,2,0) -> Redeban Noroccidente (Medellín) | E20: =C20 -> 56740009
A21: KEVIN ALEXIS CORZO BUSTOS | B21: 0004-0007 | C21: 22067473 | D21: =VLOOKUP(B21,'CENTRO DE COSTOS'!B:C,2,0) -> Redeban Oriente (Otros) | E21: =C21 -> 22067473
A22: MIGUEL JULIÁN HERNÁNDEZ GUARÍN | B22: 0004-0008 | C22: 26307565 | D22: =VLOOKUP(B22,'CENTRO DE COSTOS'!B:C,2,0) -> Redeban Santander | E22: =C22 -> 26307565
A23: WILLIAM ASDRUBAL ROZO ROZO | B23: 0004-0004 | C23: 15455600 | D23: =VLOOKUP(B23,'CENTRO DE COSTOS'!B:C,2,0) -> Redeban Centro ( Bogotá) | E23: =C23 -> 15455600
A24: Total general | C24: 1.9131574e+08
A30: ORDENES DE CAMBIO BANCOLOMBIA
A31: COORDINADOR | B31: CENTRO DE COSTOS LÍNEACOM | C31: Suma de VALOR TOTAL | D31: NOMBRE DE CC | E31: VALOR CC
A32: DIEGO FERNANDO HENAO CARDONA | B32: 0004-0002 | C32: 3069545.2 | D32: =VLOOKUP(B32,'CENTRO DE COSTOS'!B:C,2,0) -> Redeban Eje Cafetero (Pereira) | E32: =C32 -> 3069545.2
B33: 0004-0003 | C33: 11145765 | D33: =VLOOKUP(B33,'CENTRO DE COSTOS'!B:C,2,0) -> Redeban Suroccidente (Cali) | E33: =C33 -> 11145765
A34: JOSE MAURICIO HERNANDEZ ROJAS | B34: 0004-0001 | C34: 9237693.7 | D34: =VLOOKUP(B34,'CENTRO DE COSTOS'!B:C,2,0) -> Redeban Costa (Barranqullla) | E34: =C34 -> 9237693.7
A35: JUAN SEBASTIÁN RÍOS CASTRILLÓN | B35: 0004-0005 | C35: 8943557.5 | D35: =VLOOKUP(B35,'CENTRO DE COSTOS'!B:C,2,0) -> Redeban Noroccidente (Medellín) | E35: =C35 -> 8943557.5
A36: KEVIN ALEXIS CORZO BUSTOS | B36: 0004-0007 | C36: 14079576 | D36: =VLOOKUP(B36,'CENTRO DE COSTOS'!B:C,2,0) -> Redeban Oriente (Otros) | E36: =C36 -> 14079576
A37: MIGUEL JULIÁN HERNÁNDEZ GUARÍN | B37: 0004-0008 | C37: 15148756 | D37: =VLOOKUP(B37,'CENTRO DE COSTOS'!B:C,2,0) -> Redeban Santander | E37: =C37 -> 15148756
A38: WILLIAM ASDRUBAL ROZO ROZO | B38: 0004-0004 | C38: 8443777.4 | D38: =VLOOKUP(B38,'CENTRO DE COSTOS'!B:C,2,0) -> Redeban Centro ( Bogotá) | E38: =C38 -> 8443777.4
A39: Total general | C39: 70068670
A45: PAPELERIA BANCOLOMBIA
A46: COORDINADOR | B46: CENTRO DE COSTOS LÍNEACOM | C46: Suma de VALOR TOTAL | D46: NOMBRE DE CC | E46: VALOR CC
A47: DIEGO FERNANDO HENAO CARDONA | B47: 0004-0002 | C47: 4112644.4 | D47: =VLOOKUP(B47,'CENTRO DE COSTOS'!B:C,2,0) -> Redeban Eje Cafetero (Pereira) | E47: =C47 -> 4112644.4
B48: 0004-0003 | C48: 12574586 | D48: =VLOOKUP(B48,'CENTRO DE COSTOS'!B:C,2,0) -> Redeban Suroccidente (Cali) | E48: =C48 -> 12574586
A49: JOSE MAURICIO HERNANDEZ ROJAS | B49: 0004-0001 | C49: 15701154 | D49: =VLOOKUP(B49,'CENTRO DE COSTOS'!B:C,2,0) -> Redeban Costa (Barranqullla) | E49: =C49 -> 15701154
A50: JUAN SEBASTIÁN RÍOS CASTRILLÓN | B50: 0004-0005 | C50: 18757071 | D50: =VLOOKUP(B50,'CENTRO DE COSTOS'!B:C,2,0) -> Redeban Noroccidente (Medellín) | E50: =C50 -> 18757071
A51: KEVIN ALEXIS CORZO BUSTOS | B51: 0004-0007 | C51: 8237418.6 | D51: =VLOOKUP(B51,'CENTRO DE COSTOS'!B:C,2,0) -> Redeban Oriente (Otros) | E51: =C51 -> 8237418.6
A52: MIGUEL JULIÁN HERNÁNDEZ GUARÍN | B52: 0004-0008 | C52: 11693967 | D52: =VLOOKUP(B52,'CENTRO DE COSTOS'!B:C,2,0) -> Redeban Santander | E52: =C52 -> 11693967
A53: WILLIAM ASDRUBAL ROZO ROZO | B53: 0004-0004 | C53: 11697275 | D53: =VLOOKUP(B53,'CENTRO DE COSTOS'!B:C,2,0) -> Redeban Centro ( Bogotá) | E53: =C53 -> 11697275
A54: Total general | C54: 82774117
A60: APERTURAS BBVA
A61: COORDINADOR | B61: CENTRO DE COSTOS | C61: Suma de VALOR FACTURABLE A LA RED | D61: NOMBRE DE CC | E61: VALOR CC
A62: Total general | D62: =VLOOKUP(B62,'CENTRO DE COSTOS'!B:C,2,0) -> #N/A | E62: =C62 -> 0
A67: OC BBVA
A68: COORDINADOR | B68: CENTRO DE COSTOS | C68: Suma de VALOR FACTURABLE A LA RED | D68: NOMBRE DE CC | E68: VALOR CC
A69: Total general | D69: =VLOOKUP(B69,'CENTRO DE COSTOS'!B:C,2,0) -> #N/A | E69: =C69 -> 0
A75: INCIDENTE BBVA
A76: COORDINADOR | B76: CENTRO DE COSTOS LÍNEACOM | C76: Suma de VALOR FACTURABLE A LA RED | D76: NOMBRE DE CC | E76: VALOR CC
A77: Total general | D77: =VLOOKUP(B77,'CENTRO DE COSTOS'!B:C,2,0) -> #N/A | E77: =C77 -> 0
A83: APERTURAS AVAL
A84: COORDINADOR | B84: CENTRO DE COSTOS LÍNEACOM | C84: Suma de VALOR FACTURABLE A LA RED | D84: NOMBRE DE CC | E84: VALOR CC
A85: DIEGO FERNANDO HENAO CARDONA | B85: 0004-0002 | C85: 753548.96 | D85: =VLOOKUP(B85,'CENTRO DE COSTOS'!B:C,2,0) -> Redeban Eje Cafetero (Pereira) | E85: =C85 -> 753548.96
B86: 0004-0003 | C86: 5554898 | D86: =VLOOKUP(B86,'CENTRO DE COSTOS'!B:C,2,0) -> Redeban Suroccidente (Cali) | E86: =C86 -> 5554898
A87: JOSE MAURICIO HERNANDEZ ROJAS | B87: 0004-0001 | C87: 2489521.4 | D87: =VLOOKUP(B87,'CENTRO DE COSTOS'!B:C,2,0) -> Redeban Costa (Barranqullla) | E87: =C87 -> 2489521.4
A88: JUAN SEBASTIÁN RÍOS CASTRILLÓN | B88: 0004-0005 | C88: 11382103 | D88: =VLOOKUP(B88,'CENTRO DE COSTOS'!B:C,2,0) -> Redeban Noroccidente (Medellín) | E88: =C88 -> 11382103
A89: KEVIN ALEXIS CORZO BUSTOS | B89: 0004-0007 | C89: 6764991 | D89: =VLOOKUP(B89,'CENTRO DE COSTOS'!B:C,2,0) -> Redeban Oriente (Otros) | E89: =C89 -> 6764991
A90: MIGUEL JULIÁN HERNÁNDEZ GUARÍN | B90: 0004-0008 | C90: 7083964 | D90: =VLOOKUP(B90,'CENTRO DE COSTOS'!B:C,2,0) -> Redeban Santander | E90: =C90 -> 7083964
A91: WILLIAM ASDRUBAL ROZO ROZO | B91: 0004-0004 | C91: 5243889.9 | D91: =VLOOKUP(B91,'CENTRO DE COSTOS'!B:C,2,0) -> Redeban Centro ( Bogotá) | E91: =C91 -> 5243889.9
A92: Total general | C92: 39272916
A97: INCIDENTES AVAL
A98: COORDINADOR | B98: CENTRO DE COSTOS LÍNEACOM | C98: Suma de VALOR FACTURABLE A LA RED | D98: NOMBRE DE CC | E98: VALOR CC
A99: DIEGO FERNANDO HENAO CARDONA | B99: 0004-0002 | C99: 276888.02 | D99: =VLOOKUP(B99,'CENTRO DE COSTOS'!B:C,2,0) -> Redeban Eje Cafetero (Pereira) | E99: =C99 -> 276888.02
B100: 0004-0003 | C100: 6779108 | D100: =VLOOKUP(B100,'CENTRO DE COSTOS'!B:C,2,0) -> Redeban Suroccidente (Cali) | E100: =C100 -> 6779108
A101: JOSE MAURICIO HERNANDEZ ROJAS | B101: 0004-0001 | C101: 4366627.9 | D101: =VLOOKUP(B101,'CENTRO DE COSTOS'!B:C,2,0) -> Redeban Costa (Barranqullla) | E101: =C101 -> 4366627.9
A102: JUAN SEBASTIÁN RÍOS CASTRILLÓN | B102: 0004-0005 | C102: 3961582.6 | D102: =VLOOKUP(B102,'CENTRO DE COSTOS'!B:C,2,0) -> Redeban Noroccidente (Medellín) | E102: =C102 -> 3961582.6
A103: KEVIN ALEXIS CORZO BUSTOS | B103: 0004-0007 | C103: 7719386.5 | D103: =VLOOKUP(B103,'CENTRO DE COSTOS'!B:C,2,0) -> Redeban Oriente (Otros) | E103: =C103 -> 7719386.5
A104: MIGUEL JULIÁN HERNÁNDEZ GUARÍN | B104: 0004-0008 | C104: 5896253.1 | D104: =VLOOKUP(B104,'CENTRO DE COSTOS'!B:C,2,0) -> Redeban Santander | E104: =C104 -> 5896253.1
A105: WILLIAM ASDRUBAL ROZO ROZO | B105: 0004-0004 | C105: 4671335.2 | D105: =VLOOKUP(B105,'CENTRO DE COSTOS'!B:C,2,0) -> Redeban Centro ( Bogotá) | E105: =C105 -> 4671335.2
A106: Total general | C106: 33671181
A111: OC AVAL
A112: COORDINADOR | B112: CENTRO DE COSTOS LÍNEACOM | C112: Suma de VALOR FACTURABLE A LA RED | D112: NOMBRE DE CC | E112: VALOR CC
A113: DIEGO FERNANDO HENAO CARDONA | B113: 0004-0002 | C113: 210927.94 | D113: =VLOOKUP(B113,'CENTRO DE COSTOS'!B:C,2,0) -> Redeban Eje Cafetero (Pereira) | E113: =C113 -> 210927.94
B114: 0004-0003 | C114: 1838150.7 | D114: =VLOOKUP(B114,'CENTRO DE COSTOS'!B:C,2,0) -> Redeban Suroccidente (Cali) | E114: =C114 -> 1838150.7
A115: JOSE MAURICIO HERNANDEZ ROJAS | B115: 0004-0001 | C115: 421855.89 | D115: =VLOOKUP(B115,'CENTRO DE COSTOS'!B:C,2,0) -> Redeban Costa (Barranqullla) | E115: =C115 -> 421855.89
A116: JUAN SEBASTIÁN RÍOS CASTRILLÓN | B116: 0004-0005 | C116: 743429.17 | D116: =VLOOKUP(B116,'CENTRO DE COSTOS'!B:C,2,0) -> Redeban Noroccidente (Medellín) | E116: =C116 -> 743429.17
A117: KEVIN ALEXIS CORZO BUSTOS | B117: 0004-0007 | C117: 1809957.4 | D117: =VLOOKUP(B117,'CENTRO DE COSTOS'!B:C,2,0) -> Redeban Oriente (Otros) | E117: =C117 -> 1809957.4
A118: MIGUEL JULIÁN HERNÁNDEZ GUARÍN | B118: 0004-0008 | C118: 1555503.4 | D118: =VLOOKUP(B118,'CENTRO DE COSTOS'!B:C,2,0) -> Redeban Santander | E118: =C118 -> 1555503.4
A119: WILLIAM ASDRUBAL ROZO ROZO | B119: 0004-0004 | C119: 1225265.2 | D119: =VLOOKUP(B119,'CENTRO DE COSTOS'!B:C,2,0) -> Redeban Centro ( Bogotá) | E119: =C119 -> 1225265.2
A120: Total general | C120: 7805089.8

Sheet APERTURAS BANCOLOMBIA
A1: CIUDAD SEDE | B1: COORDINADOR | C1: CENTRO DE COSTOS LÍNEACOM | D1: CÓDIGO DANE | E1: TA/CODIGO ACTIVIDAD | F1: CODIGO CB | G1: ACTIVIDAD | H1: TIPO DE APERTURA | I1: DEPARTAMENTO | J1: CIUDAD | K1: NOMBRE DEL CB | L1: RED | M1: FO | N1: FECHA LISTA | O1: FECHA ULTIMA ACTUALIZACION | P1: FORMATO | Q1: CADENA | R1: ESTADO | S1: OBSERVACIONES CLIENTE | T1: FORMA DE ATENCIÓN | U1: TERMINALES | V1: TIPO DE ATENCION | W1: TIPO DE TRAYECTO | X1: NOMBRE DEL TECNICO | Y1: DIAS DE VISITA | Z1: DIA ADICIONAL | AA1: VALOR DIAS ACTIVIDAD FACTURABLES A LA RED | AB1: VALOR DIAS ACOMPAÑAMIENTO FACTURABLES | AC1: VALOR FACTURABLE A LA RED | AD1: CU CB | AE1: COBRO ENTIDAD | AF1: ESTADO | AG1: TIPO | AH1: VAL TIPO | AI1: VAL COSTO | AJ1: OBSERVACIONES | AK1: OBSERVACIONES LINEA
A2: PASTO | B2: =VLOOKUP(A2,'CENTRO DE COSTOS'!A:D,4,FALSE) -> DIEGO FERNANDO HENAO CARDONA | C2: =VLOOKUP(A2,'CENTRO DE COSTOS'!A:D,2,FALSE) -> 0004-0003 | D2: 52621 | E2: TA-25-992136 | F2: 81154 | G2: APERTURA | H2: CB CRECIMIENTO - NUEVO | I2: NARIÑO | J2: ROBERTO PAYAN | K2: BARRIO EL VILLA HORIZONTE ROBERTO PAYAN | L2: REDEBAN | M2: FO-25-1402263 | N2: 45890 | O2: 45902 | P2: UNO A UNO | Q2: UNO A UNO | R2: EJECUTADO | S2: 21-08 SE REALIZA CONTACTO CON EL CLIENTE VIA WHATSAPP, SE HABLA CON LA SRA MARIA ELVIRA PARRA ARTUNDUAGA AL NÚMERO 3236143368 SE VALIDA DIRECCIÓN OK, CANAL OK, DISPONIBILIDAD TOTAL, LLAMAR EL DIA DE LA INSTALACIÓN PARA CONFIRMAR VISITA, AVISO EXTERIOR ALTURA APROX 8 METROS; TOMACORRIENTE CERCANO: SI; TIENE CABINA DE SEGURIDAD; SI 01-09 SE INICIO DESPLAZAMIENTO PERO SOLO HOY SE LLEGO HASTA BARBACOAS, SE VALIDA Y SE DEBE TOMAR LANCHA EL DIA DE MAÑANA 2/09/2025 SE REALIZA INSTALACIÓN DE CORRESPONSAL, SE INSTALAN EQUIPOS CON PRUEBAS EXITOSAS, SE CAPACITA Y SE EVALÚA AL CLIENTE, SE INSTALA PUBLICIDAD COMPLETA, CB QUEDA OPERATIVO. USUARIO SOMOS BANCOLOMBIA ACTIVO | T2: VISITA_TÉCNICA | U2: SIZZZ900 | V2: TIPO IV ESPECIAL | W2: FLUVIAL | X2: PAZ MARTINEZ RICHARD HUMBERTO | Y2: 1 | Z2: 0 | AA2: =IF(V2="TIPO I",'BASE LIQUIDACION REDEBAN 2025'!$B$2,IF(V2="TIPO II",'BASE LIQUIDACION REDEBAN 2025'!$B$3,IF(V2="TIPO III",'BASE LIQUIDACION REDEBAN 2025'!$B$4,IF(V2="TIPO IV",'BASE LIQUIDACION REDEBAN 2025'!$B$5,IF(W2="AEREO",'BASE LIQUIDACION REDEBAN 2025'!$B$6,'BASE LIQUIDACION REDEBAN 2025'!$B$5))))) -> 504832.65 | AB2: =IF(V2="TIPO I",'BASE LIQUIDACION REDEBAN 2025'!$B$10,IF(V2="TIPO II",'BASE LIQUIDACION REDEBAN 2025'!$B$11,IF(V2="TIPO III",'BASE LIQUIDACION REDEBAN 2025'!$B$12,'BASE LIQUIDACION REDEBAN 2025'!$B$13))) -> 196536.53 | AC2: =Y2*AA2+Z2*AB2 -> 504832.65
A3: CALI | B3: =VLOOKUP(A3,'CENTRO DE COSTOS'!A:D,4,FALSE) -> DIEGO FERNANDO HENAO CARDONA | C3: =VLOOKUP(A3,'CENTRO DE COSTOS'!A:D,2,FALSE) -> 0004-0003 | D3: 19256 | E3: TA-25-992167 | F3: 81133 | G3: APERTURA | H3: CB CRECIMIENTO - NUEVO | I3: CAUCA | J3: EL TAMBO | K3: BARRIO PLAYA RICA EL TAMBO 1 | L3: REDEBAN | M3: FO-25-1402365 | N3: 45890 | O3: 45902 | P3: UNO A UNO | Q3: UNO A UNO | R3: EJECUTADO | S3: 21-08 SE REALIZA LLAMADA AL CLIENTE, SE HABLA CON LA SRA YUDY MILENA CALVACHE HERNANDEZ SE VALIDA DIRECCIÓN OK, CANAL OK, DISPONIBILIDAD TOTAL, LLAMAR EL DÍA LA INSTALACIÓN PARA CONFIRMAR VISITA, AVISO EXTERIOR ALTURA: NO INDICA ALTURA ; TOMACORRIENTE CERCANO: SI; TIENE CABINA DE SEGURIDAD: NO 25-08 DADO PROBLEMAS DE TRANSPORTE HACIA EL CORREGIMIENTO NO ES POSIBLE EL DESPLAZAMIENTO EL DIA DE HOY , SE VALIDARA EL DIA DE MAÑANA. 26-08 SE REALIZA LLAMADA CON EL CLIENTE, QUIEN INFORMA QUE PARA PODER REALIZAR EL INGRESO A LA ZONA ES NECESARIO DILIGENCIAR UNOS PERMISOS ESPECIALES, YA QUE SE TRATA DE UNA ZONA CON PRESENCIA GUERRILLERA. DEBIDO A ESTA SITUACIÓN, SE ACUERDA REPROGRAMAR LA APERTURA. 02-09 SE REALIZA INSTALACIÓN DE CORRESPONSAL, SE INSTALAN EQUIPOS CON PRUEBAS EXITOSAS, SE CAPACITA Y SE EVALÚA AL CLIENTE, SE INSTALA PUBLICIDAD COMPLETA, CB QUEDA OPERATIVO. USUARIO SOMOS BANCOLOMBIA ACTIVO | T3: VISITA_TÉCNICA | U3: SIZZZ915 | V3: TIPO III | W3: TERRESTRE | X3: GIMBUEL LASSO LUIS GERMAN | Y3: 1 | Z3: 0 | AA3: =IF(V3="TIPO I",'BASE LIQUIDACION REDEBAN 2025'!$B$2,IF(V3="TIPO II",'BASE LIQUIDACION REDEBAN 2025'!$B$3,IF(V3="TIPO III",'BASE LIQUIDACION REDEBAN 2025'!$B$4,IF(V3="TIPO IV",'BASE LIQUIDACION REDEBAN 2025'!$B$5,IF(W3="AEREO",'BASE LIQUIDACION REDEBAN 2025'!$B$6,'BASE LIQUIDACION REDEBAN 2025'!$B$5))))) -> 275728.78 | AB3: =IF(V3="TIPO I",'BASE LIQUIDACION REDEBAN 2025'!$B$10,IF(V3="TIPO II",'BASE LIQUIDACION REDEBAN 2025'!$B$11,IF(V3="TIPO III",'BASE LIQUIDACION REDEBAN 2025'!$B$12,'BASE LIQUIDACION REDEBAN 2025'!$B$13))) -> 196536.53 | AC3: =Y3*AA3+Z3*AB3 -> 275728.78
A4: PASTO | B4: =VLOOKUP(A4,'CENTRO DE COSTOS'!A:D,4,FALSE) -> DIEGO FERNANDO HENAO CARDONA | C4: =VLOOKUP(A4,'CENTRO DE COSTOS'!A:D,2,FALSE) -> 0004-0003 | D4: 52079 | E4: TA-25-1033974 | F4: 81185 | G4: APERTURA | H4: CB CRECIMIENTO - NUEVO | I4: NARIÑO | J4: BARBACOAS | K4: BARRIO GUAYACAL BARBACOAS | L4: REDEBAN | M4: FO-25-1432981 | N4: 45896 | O4: 45902 | P4: UNO A UNO | Q4: UNO A UNO | R4: EJECUTADO | S4: 27-08 SE REALIZA LLAMADA AL CLIENTE, SE HABLA CON LA SRA YULIS FIORELA PORTILLA CABEZAS SE VALIDA DIRECCIÓN OK, CANAL OK, DISPONIBILIDAD TOTAL, LLAMAR EL DÍA LA INSTALACIÓN PARA CONFIRMAR VISITA, AVISO EXTERIOR ALTURA APROX 2 METROS; TOMACORRIENTE CERCANO: SI; TIENE CABINA DE SEGURIDAD: NO - COMUNICACIÓN POR WPP / EL MODEM ESTA A 4 MT 29/08/2025 POR DISPONIBILIDAD DE TRASNPORTE NO ES POSIBLE REALIZAR LA ACTIVIDAD EL DIA DE HOY, SE VIAJARA EL DIA LUNES 01-09 SE LLEGO A BARBACOAS, SE ESTA REALIZANDO LA IMPLEMENTACIÓN EL DIA DE MAÑANA 02-09 SE REALIZA INSTALACIÓN DE CORRESPONSAL, SE INSTALAN EQUIPOS CON PRUEBAS EXITOSAS, SE CAPACITA Y SE EVALÚA AL CLIENTE, SE INSTALA PUBLICIDAD COMPLETA, CB QUEDA OPERATIVO. USUARIO SOMOS BANCOLOMBIA ACTIVO | T4: VISITA_TÉCNICA | U4: FKZZZ635 | V4: TIPO IV | W4: TERRESTRE | X4: PAZ MARTINEZ RICHARD HUMBERTO | Y4: 1 | Z4: 0 | AA4: =IF(V4="TIPO I",'BASE LIQUIDACION REDEBAN 2025'!$B$2,IF(V4="TIPO II",'BASE LIQUIDACION REDEBAN 2025'!$B$3,IF(V4="TIPO III",'BASE LIQUIDACION REDEBAN 2025'!$B$4,IF(V4="TIPO IV",'BASE LIQUIDACION REDEBAN 2025'!$B$5,IF(W4="AEREO",'BASE LIQUIDACION REDEBAN 2025'!$B$6,'BASE LIQUIDACION REDEBAN 2025'!$B$5))))) -> 504832.65 | AB4: =IF(V4="TIPO I",'BASE LIQUIDACION REDEBAN 2025'!$B$10,IF(V4="TIPO II",'BASE LIQUIDACION REDEBAN 2025'!$B$11,IF(V4="TIPO III",'BASE LIQUIDACION REDEBAN 2025'!$B$12,'BASE LIQUIDACION REDEBAN 2025'!$B$13))) -> 196536.53 | AC4: =Y4*AA4+Z4*AB4 -> 504832.65
A5: PEREIRA | B5: =VLOOKUP(A5,'CENTRO DE COSTOS'!A:D,4,FALSE) -> DIEGO FERNANDO HENAO CARDONA | C5: =VLOOKUP(A5,'CENTRO DE COSTOS'!A:D,2,FALSE) -> 0004-0002 | D5: 66001 | E5: TA-25-1033985 | F5: 81241 | G5: APERTURA | H5: CB CRECIMIENTO - NUEVO | I5: RISARALDA | J5: PEREIRA | K5: BARRIO CENTRO PEREIRA 55 | L5: REDEBAN | M5: FO-25-1433027 | N5: 45896 | O5: 45901 | P5: UNO A UNO | Q5: UNO A UNO | R5: EJECUTADO | S5: 27-08-2025 SE REALIZA LLAMADA AL CLIENTE, SE HABLA CON LA SRA JULIANA ECHEVERRY GALVEZ SE VALIDA DIRECCIÓN OK, CANAL OK, DISPONIBILIDAD TOTAL, LLAMAR EL DÍA LA INSTALACIÓN PARA CONFIRMAR VISITA, AVISO EXTERIOR ALTURA APROX 2 METROS; TOMACORRIENTE CERCANO: SI; TIENE CABINA DE SEGURIDAD: NO // CONTACTO REALIZADO POR LA APP 29-08 REALIZAMOS LLAMADA A LA SRA JULIANA LA CUAL NOS INDICA QUE EL DÍA DE HOY NO ES POSIBLE ATENDERNOS YA QUE TIENE UN COMPROMISO QUE POR FAVOR REPROGRAMAR LA VISITA PARA LA OTRA SEMANA. 1/09/2025 SE REALIZA INSTALACIÓN DE CORRESPONSAL, SE INSTALAN EQUIPOS, SE CAPACITA Y SE EVALÚA AL CLIENTE, SE INSTALA PUBLICIDAD COMPLETA, CB QUEDA OPERATIVO. USUARIO SOMOS BANCOLOMBIA ACTIVO. NOTA: SOLO SE REALIZAN PRUEBA DE CONSULTA DE SALDO YA QUE EL CLIENTE NO TIENE TARJETA PARA HACER LAS PRUEBAS DE DEPOSITO, RETIRO, RECAUDO Y TRANSFERENCIA | T5: VISITA_TÉCNICA | U5: FKZZZ643 | V5: TIPO I | W5: TERRESTRE | X5: ARROYAVE CANO MANUEL GUILLERMO | Y5: 1 | Z5: 0 | AA5: =IF(V5="TIPO I",'BASE LIQUIDACION REDEBAN 2025'!$B$2,IF(V5="TIPO II",'BASE LIQUIDACION REDEBAN 2025'!$B$3,IF(V5="TIPO III",'BASE LIQUIDACION REDEBAN 2025'!$B$4,IF(V5="TIPO IV",'BASE LIQUIDACION REDEBAN 2025'!$B$5,IF(W5="AEREO",'BASE LIQUIDACION REDEBAN 2025'!$B$6,'BASE LIQUIDACION REDEBAN 2025'!$B$5))))) -> 75096.394 | AB5: =IF(V5="TIPO I",'BASE LIQUIDACION REDEBAN 2025'!$B$10,IF(V5="TIPO II",'BASE LIQUIDACION REDEBAN 2025'!$B$11,IF(V5="TIPO III",'BASE LIQUIDACION REDEBAN 2025'!$B$12,'BASE LIQUIDACION REDEBAN 2025'!$B$13))) -> 75096.394 | AC5: =Y5*AA5+Z5*AB5 -> 75096.394
A6: MONTERIA | B6: =VLOOKUP(A6,'CENTRO DE COSTOS'!A:D,4,FALSE) -> JOSE MAURICIO HERNANDEZ ROJAS | C6: =VLOOKUP(A6,'CENTRO DE COSTOS'!A:D,2,FALSE) -> 0004-0001 | D6: 23001 | E6: TA-25-1033987 | F6: 81212 | G6: APERTURA | H6: CB CRECIMIENTO - NUEVO | I6: CORDOBA | J6: MONTERIA | K6: BARRIO POLICARPA MONTERIA 3 | L6: REDEBAN | M6: FO-25-1433037 | N6: 45896 | O6: 45901 | P6: UNO A UNO | Q6: UNO A UNO | R6: EJECUTADO | S6: 26-08 SE REALIZA LLAMADA AL CLIENTE, SE HABLA CON LA SRA SIDNEY PATRICIA VILLEGAS VILORIA SE VALIDA DIRECCIÓN OK, CANAL OK, DISPONIBILIDAD TOTAL, LLAMAR EL DÍA DE LA INSTALACIÓN PARA CONFIRMAR VISITA, AVISO EXTERIOR NO INDICA ALTURA; TOMACORRIENTE CERCANO: SI; TIENE CABINA DE SEGURIDAD: SI 28-08 SE REALIZÓ LLAMADA DE VALIDACIÓN Y LA SEÑORA SIDNEY PATRICIA VILLEGAS VILORIA, INFORMA QUE POR LAS FUERTE LLUVIA Y BRISA DE ANOCHE SE CAYERON VARIOS ÁRBOLES Y ESTÁ SIN FLUIDO ELÉCTRICO Y DAÑOS EN EL INTERNET. PIDE POR FAVOR ESPERAR A QUE LE SOLUCIONEN PARA RECIBIR LA INSTALACIÓN. 29-08 SE REALIZÓ LLAMADA DE VALIDACIÓN Y EL CLIENTE INFORMA QUE TODAVÍA TIENE PROBLEMAS CON EL CANAL DE COMUNICACIÓN, QUE NO HAN REALIZADO LOS ARREGLOS EN LA ZONA. 30-08 LA ACTIVIDAD SE REAGENDA PARA EL DÍA LUNES 01-09-25. 1/09/2025 SE ESCALA CASO, DONDE SE LLEVA A COMERCIO DE LA PAPELERÍA, PERO EL LOCAL NO CUENTA CON EL NOMBRE DE COMERCIO EN FACHADA, CABE ACLARAR QUE LA MERCANCÍA SI TIENE RELACIÓN CON PAPELERIA, // POR FAVOR, PROCEDAMOS CON LA IMPLANTACIÓN CORRESPONDIENTE Y DEJEMOS COMO EVIDENCIA LA CÁMARA DE COMERCIO, ASÍ COMO LA DOCUMENTACIÓN DE LA NOVEDAD PRESENTADA. 01-09 SE REALIZA INSTALACIÓN DE CORRESPONSAL, SE INSTALAN EQUIPOS CON PRUEBAS EXITOSAS, SE CAPACITA Y SE EVALÚA AL CLIENTE, SE INSTALA PUBLICIDAD COMPLETA, CB QUEDA OPERATIVO. USUARIO SOMOS BANCOLOMBIA ACTIVO. NO SÉ REALIZÓ PRUEBAS DE RECAUDO PORQUE EL CLIENTE NO IBA A PAGAR FACTURA EN EL MOMENTO Y LA DE TRANSFERENCIA EL CLIENTE NO TIENE MÁS CUENTA | T6: VISITA_TÉCNICA | U6: FKZZZ646 | V6: TIPO I | W6: TERRESTRE | X6: CALDERA SALCEDO CARLOS JULIO | Y6: 1 | Z6: 0 | AA6: =IF(V6="TIPO I",'BASE LIQUIDACION REDEBAN 2025'!$B$2,IF(V6="TIPO II",'BASE LIQUIDACION REDEBAN 2025'!$B$3,IF(V6="TIPO III",'BASE LIQUIDACION REDEBAN 2025'!$B$4,IF(V6="TIPO IV",'BASE LIQUIDACION REDEBAN 2025'!$B$5,IF(W6="AEREO",'BASE LIQUIDACION REDEBAN 2025'!$B$6,'BASE LIQUIDACION REDEBAN 2025'!$B$5))))) -> 75096.394 | AB6: =IF(V6="TIPO I",'BASE LIQUIDACION REDEBAN 2025'!$B$10,IF(V6="TIPO II",'BASE LIQUIDACION REDEBAN 2025'!$B$11,IF(V6="TIPO III",'BASE LIQUIDACION REDEBAN 2025'!$B$12,'BASE LIQUIDACION REDEBAN 2025'!$B$13))) -> 75096.394 | AC6: =Y6*AA6+Z6*AB6 -> 75096.394
A7: CALI | B7: =VLOOKUP(A7,'CENTRO DE COSTOS'!A:D,4,FALSE) -> DIEGO FERNANDO HENAO CARDONA | C7: =VLOOKUP(A7,'CENTRO DE COSTOS'!A:D,2,FALSE) -> 0004-0003 | D7: 19809 | E7: TA-25-1033991 | F7: 81252 | G7: APERTURA | H7: CB CRECIMIENTO - NUEVO | I7: CAUCA | J7: TIMBIQUI | K7: BARRIO UNION DE VIVIENDAS TIMBIQUI | L7: REDEBAN | M7: FO-25-1433056 | N7: 45896 | O7: 45904 | P7: UNO A UNO | Q7: UNO A UNO | R7: EJECUTADO | S7: 27-08-2025 SE REALIZA LLAMADA AL CLIENTE, SE HABLA CON LA SRA IRLANDA VENTE CONGOLINO SE VALIDA DIRECCIÓN OK, CANAL OK, DISPONIBILIDAD TOTAL, LLAMAR EL DÍA LA INSTALACIÓN PARA CONFIRMAR VISITA, AVISO EXTERIOR ALTURA APROX 3 METROS; TOMACORRIENTE CERCANO: SI; TIENE CABINA DE SEGURIDAD: SI 04-09 SE REALIZA INSTALACIÓN DE CORRESPONSAL, SE INSTALAN EQUIPOS CON PRUEBAS EXITOSAS, SE CAPACITA Y SE EVALÚA AL CLIENTE, SE INSTALA PUBLICIDAD COMPLETA, CB QUEDA OPERATIVO. USUARIO SOMOS BANCOLOMBIA ACTIVO | T7: VISITA_TÉCNICA | U7: FKZZZ649 | V7: TIPO IV ESPECIAL | W7: AEREO | X7: PAREDES CASTILLO DIEGO | Y7: 1 | Z7: 0 | AA7: =IF(V7="TIPO I",'BASE LIQUIDACION REDEBAN 2025'!$B$2,IF(V7="TIPO II",'BASE LIQUIDACION REDEBAN 2025'!$B$3,IF(V7="TIPO III",'BASE LIQUIDACION REDEBAN 2025'!$B$4,IF(V7="TIPO IV",'BASE LIQUIDACION REDEBAN 2025'!$B$5,IF(W7="AEREO",'BASE LIQUIDACION REDEBAN 2025'!$B$6,'BASE LIQUIDACION REDEBAN 2025'!$B$5))))) -> 988462.96 | AB7: =IF(V7="TIPO I",'BASE LIQUIDACION REDEBAN 2025'!$B$10,IF(V7="TIPO II",'BASE LIQUIDACION REDEBAN 2025'!$B$11,IF(V7="TIPO III",'BASE LIQUIDACION REDEBAN 2025'!$B$12,'BASE LIQUIDACION REDEBAN 2025'!$B$13))) -> 196536.53 | AC7: =Y7*AA7+Z7*AB7 -> 988462.96
A8: NEIVA | B8: =VLOOKUP(A8,'CENTRO DE COSTOS'!A:D,4,FALSE) -> KEVIN ALEXIS CORZO BUSTOS | C8: =VLOOKUP(A8,'CENTRO DE COSTOS'!A:D,2,FALSE) -> 0004-0007 | D8: 18785 | E8: TA-25-1034017 | F8: 81251 | G8: APERTURA | H8: CB CRECIMIENTO - NUEVO | I8: CAQUETA | J8: SOLITA | K8: BARRIO JORDAN SOLITA | L8: REDEBAN | M8: FO-25-1433151 | N8: 45896 | O8: 45902 | P8: UNO A UNO | Q8: UNO A UNO | R8: EJECUTADO | S8: 27-08 SE REALIZA LLAMADA AL CLIENTE, SE HABLA CON LA SRA IDARYI CANO PINZON SE VALIDA DIRECCIÓN OK, CANAL OK, DISPONIBILIDAD TOTAL, LLAMAR EL DÍA LA INSTALACIÓN PARA CONFIRMAR VISITA, AVISO EXTERIOR ALTURA APROX 2 METROS; TOMACORRIENTE CERCANO: SI; TIENE CABINA DE SEGURIDAD: NO - EL MODEM ESTA 5 MT 01-09 EN COMUNICACIÓN CON LA CLIENTA PARA CONFIRMAR LA INSTALACIÓN EL DÍA DE HOY, CLIENTE MANIFIESTO QUE NO ES POSIBLE ATENDER LA VISITA YA QUE POR MOTIVOS PERSONALES ESTÁ EN FLORENCIA REALIZANDO UNAS DILIGENCIAS, MANIFESTÓ ATENDER LA VISITA EL DÍA DE MAÑANA 02 DE SEPTIEMBRE EN EL TRANSCURSO DEL DÍA. 2/09/2025 SE REALIZA INSTALACIÓN DE CORRESPONSAL, SE INSTALAN EQUIPOS CON PRUEBAS EXITOSAS, SE CAPACITA Y SE EVALÚA AL CLIENTE, SE INSTALA PUBLICIDAD COMPLETA, CB QUEDA OPERATIVO. USUARIO SOMOS BANCOLOMBIA ACTIVO | T8: VISITA_TÉCNICA | U8: FKZZZ665 | V8: TIPO IV | W8: TERRESTRE | X8: BERMUDEZ SANCHEZ JOSE NEYBER | Y8: 1 | Z8: 0 | AA8: =IF(V8="TIPO I",'BASE LIQUIDACION REDEBAN 2025'!$B$2,IF(V8="TIPO II",'BASE LIQUIDACION REDEBAN 2025'!$B$3,IF(V8="TIPO III",'BASE LIQUIDACION REDEBAN 2025'!$B$4,IF(V8="TIPO IV",'BASE LIQUIDACION REDEBAN 2025'!$B$5,IF(W8="AEREO",'BASE LIQUIDACION REDEBAN 2025'!$B$6,'BASE LIQUIDACION REDEBAN 2025'!$B$5))))) -> 504832.65 | AB8: =IF(V8="TIPO I",'BASE LIQUIDACION REDEBAN 2025'!$B$10,IF(V8="TIPO II",'BASE LIQUIDACION REDEBAN 2025'!$B$11,IF(V8="TIPO III",'BASE LIQUIDACION REDEBAN 2025'!$B$12,'BASE LIQUIDACION REDEBAN 2025'!$B$13))) -> 196536.53 | AC8: =Y8*AA8+Z8*AB8 -> 504832.65
A9: VILLAVICENCIO | B9: =VLOOKUP(A9,'CENTRO DE COSTOS'!A:D,4,FALSE) -> KEVIN ALEXIS CORZO BUSTOS | C9: =VLOOKUP(A9,'CENTRO DE COSTOS'!A:D,2,FALSE) -> 0004-0007 | D9: 50350 | E9: TA-25-1034022 | F9: 81208 | G9: APERTURA | H9: CB CRECIMIENTO - NUEVO | I9: META | J9: LA MACARENA | K9: BARRIO CENTRO LA MACARENA 9 | L9: REDEBAN | M9: FO-25-1433176 | N9: 45896 | O9: 45903 | P9: UNO A UNO | Q9: UNO A UNO | R9: EJECUTADO | S9: 27-08 SE REALIZA LLAMADA AL CLIENTE, SE HABLA CON LA SR RICARDO FLOREZ ARENAS SE VALIDA DIRECCIÓN OK, CANAL OK, DISPONIBILIDAD TOTAL, LLAMAR EL DÍA LA INSTALACIÓN PARA CONFIRMAR VISITA, AVISO EXTERIOR ALTURA APROX 2 METROS; TOMACORRIENTE CERCANO: SI; TIENE CABINA DE SEGURIDAD: NO - COMUNICACIÓN POR WPP / EL MODEM ESTA A 5 MT Y NO TIENE PUERTO DISPONIBLES ( LLEVAR SWITCH) 03-09 SE REALIZA INSTALACIÓN DE CORRESPONSAL, SE INSTALAN EQUIPOS CON PRUEBAS EXITOSAS, SE CAPACITA Y SE EVALÚA AL CLIENTE, SE INSTALA PUBLICIDAD COMPLETA, CB QUEDA OPERATIVO. USUARIO SOMOS BANCOLOMBIA ACTIVO | T9: VISITA_TÉCNICA | U9: FKZZZ669 | V9: TIPO IV ESPECIAL | W9: AEREO | X9: ROZO JIMENEZ EDGAR ARMANDO | Y9: 1 | Z9: 0 | AA9: =IF(V9="TIPO I",'BASE LIQUIDACION REDEBAN 2025'!$B$2,IF(V9="TIPO II",'BASE LIQUIDACION REDEBAN 2025'!$B$3,IF(V9="TIPO III",'BASE LIQUIDACION REDEBAN 2025'!$B$4,IF(V9="TIPO IV",'BASE LIQUIDACION REDEBAN 2025'!$B$5,IF(W9="AEREO",'BASE LIQUIDACION REDEBAN 2025'!$B$6,'BASE LIQUIDACION REDEBAN 2025'!$B$5))))) -> 988462.96 | AB9: =IF(V9="TIPO I",'BASE LIQUIDACION REDEBAN 2025'!$B$10,IF(V9="TIPO II",'BASE LIQUIDACION REDEBAN 2025'!$B$11,IF(V9="TIPO III",'BASE LIQUIDACION REDEBAN 2025'!$B$12,'BASE LIQUIDACION REDEBAN 2025'!$B$13))) -> 196536.53 | AC9: =Y9*AA9+Z9*AB9 -> 988462.96
A10: BUCARAMANGA | B10: =VLOOKUP(A10,'CENTRO DE COSTOS'!A:D,4,FALSE) -> MIGUEL JULIÁN HERNÁNDEZ GUARÍN | C10: =VLOOKUP(A10,'CENTRO DE COSTOS'!A:D,2,FALSE) -> 0004-0008 | D10: 68679 | E10: TA-25-1034026 | F10: 81247 | G10: APERTURA | H10: CB CRECIMIENTO - NUEVO | I10: SANTANDER | J10: SAN GIL | K10: BARRIO CIUDAD FUTURO ETAPA 3 SAN GIL | L10: REDEBAN | M10: FO-25-1433206 | N10: 45896 | O10: 45901 | P10: UNO A UNO | Q10: UNO A UNO | R10: EJECUTADO | S10: 27-08 SE REALIZA LLAMADA AL CLIENTE, SE HABLA CON LA SRA OLGA PATRICIA SARMIENTO OTERO SE VALIDA DIRECCIÓN OK, CANAL OK, DISPONIBILIDAD TOTAL, LLAMAR EL DÍA LA INSTALACIÓN PARA CONFIRMAR VISITA, AVISO EXTERIOR ALTURA APROX 2 METROS; TOMACORRIENTE CERCANO: SI; TIENE CABINA DE SEGURIDAD: NO - SE PROGRAMA PARA DICHA FECHA POR SOLITUD DEL USUARIO 01-09 SE REALIZA INSTALACIÓN DE CORRESPONSAL, SE INSTALAN EQUIPOS CON PRUEBAS EXITOSAS, SE CAPACITA Y SE EVALÚA AL CLIENTE, SE INSTALA PUBLICIDAD COMPLETA, CB QUEDA OPERATIVO. USUARIO SOMOS BANCOLOMBIA ACTIVO | T10: VISITA_TÉCNICA | U10: FKZZZ672 | V10: TIPO II | W10: TERRESTRE | X10: GELVEZ MOGOLLON JOSE ELISEO | Y10: 1 | Z10: 0 | AA10: =IF(V10="TIPO I",'BASE LIQUIDACION REDEBAN 2025'!$B$2,IF(V10="TIPO II",'BASE LIQUIDACION REDEBAN 2025'!$B$3,IF(V10="TIPO III",'BASE LIQUIDACION REDEBAN 2025'!$B$4,IF(V10="TIPO IV",'BASE LIQUIDACION REDEBAN 2025'!$B$5,IF(W10="AEREO",'BASE LIQUIDACION REDEBAN 2025'!$B$6,'BASE LIQUIDACION REDEBAN 2025'!$B$5))))) -> 163813.7 | AB10: =IF(V10="TIPO I",'BASE LIQUIDACION REDEBAN 2025'!$B$10,IF(V10="TIPO II",'BASE LIQUIDACION REDEBAN 2025'!$B$11,IF(V10="TIPO III",'BASE LIQUIDACION REDEBAN 2025'!$B$12,'BASE LIQUIDACION REDEBAN 2025'!$B$13))) -> 140395.63 | AC10: =Y10*AA10+Z10*AB10 -> 163813.7
A11: CALI | B11: =VLOOKUP(A11,'CENTRO DE COSTOS'!A:D,4,FALSE) -> DIEGO FERNANDO HENAO CARDONA | C11: =VLOOKUP(A11,'CENTRO DE COSTOS'!A:D,2,FALSE) -> 0004-0003 | D11: 76001 | E11: TA-25-1034027 | F11: 81195 | G11: APERTURA | H11: CB CRECIMIENTO - NUEVO | I11: VALLE DEL CAUCA | J11: CALI | K11: BARRIO BENAJAMIN HERRERA CALI | L11: REDEBAN | M11: FO-25-1433211 | N11: 45896 | O11: 45902 | P11: UNO A UNO | Q11: UNO A UNO | R11: EJECUTADO | S11: 27-08 SE REALIZA LLAMADA AL CLIENTE, SE HABLA CON LA SRA MALLERLY RUBIANO LOPEZ SE VALIDA DIRECCIÓN OK, CANAL OK, DISPONIBILIDAD TOTAL, LLAMAR EL DÍA LA INSTALACIÓN PARA CONFIRMAR VISITA, AVISO EXTERIOR ALTURA: NO INDICA ALTURA; TOMACORRIENTE CERCANO: SI; TIENE CABINA DE SEGURIDAD: NO 29/08/2025 SE LLAMA AL CLIENTE AL NÚMERO 3104237740 HABLO CON LA SEÑORA MALLERLY INFORMA QUE EL DÍA DE HOY NO PUEDE ATENDER LA INSTALACIÓN TODO EL PERSONAL DE LA DROGUERÍA ESTÁ EN INVENTARIO NO ALGUIEN MÁS QUE NOS ATIENDA LA ACTIVIDAD NO SE PUEDE REPROGRAMAR VENCE EL HOY, SE LE INDICA AL CLIENTE QUE SE CANCELA LA INSTALACIÓN 01-09 SE LLAMO EL CLIENTE PERO NO CONTESTO, SE REALIZARA LLAMADA EL DIA DE MAÑANA PARA VALIDAR DISPONIBILIDAD 02-09 SE REALIZA INSTALACIÓN DE CORRESPONSAL, SE INSTALAN EQUIPOS CON PRUEBAS EXITOSAS, SE CAPACITA Y SE EVALÚA AL CLIENTE, SE INSTALA PUBLICIDAD COMPLETA, CB QUEDA OPERATIVO. USUARIO SOMOS BANCOLOMBIA ACTIVO | T11: VISITA_TÉCNICA | U11: FKZZZ673 | V11: TIPO I | W11: TERRESTRE | X11: PAREDES CASTILLO DIEGO | Y11: 1 | Z11: 0 | AA11: =IF(V11="TIPO I",'BASE LIQUIDACION REDEBAN 2025'!$B$2,IF(V11="TIPO II",'BASE LIQUIDACION REDEBAN 2025'!$B$3,IF(V11="TIPO III",'BASE LIQUIDACION REDEBAN 2025'!$B$4,IF(V11="TIPO IV",'BASE LIQUIDACION REDEBAN 2025'!$B$5,IF(W11="AEREO",'BASE LIQUIDACION REDEBAN 2025'!$B$6,'BASE LIQUIDACION REDEBAN 2025'!$B$5))))) -> 75096.394 | AB11: =IF(V11="TIPO I",'BASE LIQUIDACION REDEBAN 2025'!$B$10,IF(V11="TIPO II",'BASE LIQUIDACION REDEBAN 2025'!$B$11,IF(V11="TIPO III",'BASE LIQUIDACION REDEBAN 2025'!$B$12,'BASE LIQUIDACION REDEBAN 2025'!$B$13))) -> 75096.394 | AC11: =Y11*AA11+Z11*AB11 -> 75096.394
A12: PASTO | B12: =VLOOKUP(A12,'CENTRO DE COSTOS'!A:D,4,FALSE) -> DIEGO FERNANDO HENAO CARDONA | C12: =VLOOKUP(A12,'CENTRO DE COSTOS'!A:D,2,FALSE) -> 0004-0003 | D12: 86568 | E12: TA-25-1034476 | F12: 81229 | G12: APERTURA | H12: CB CRECIMIENTO ALIANZA - NUEVO | I12: PUTUMAYO | J12: PUERTO ASIS | K12: DISTRICOL LADY PERFUMERIA | L12: REDEBAN | M12: FO-25-1433932 | N12: 45896 | O12: 45902 | P12: AGREGADOR | Q12: DISTRICOL | R12: EJECUTADO | S12: 27-08 PROGRAMACIÓN REALIZADA POR LA ALIANZA 29/08/2025 POR DISPONIBILIDAD DE TRASNPORTE NO ES POSIBLE REALIZAR LA ACTIVIDAD EL DIA DE HOY, SE VIAJARA EL DIA LUNES 01-09 POR RETRASOS DEBIDO A ARREGLOS EN LA VÍA AL PUTUMAYO NO SE ALCANZA A REALIZAR VISITA EL DÍA DE HOY. SE INFORMA A CLIENTE QUE SE VISITARÁ MAÑANA DESPUÉS DE MEDIO DÍA. SEÑORA RUBIELA PIDE SE LA VISITE A LAS 3 PM 2/09/2025 SE REALIZA INSTALACIÓN DE CORRESPONSAL, SE INSTALAN EQUIPOS CON PRUEBAS EXITOSAS, SE CAPACITA Y SE EVALÚA AL CLIENTE, SE INSTALA PUBLICIDAD COMPLETA, CB QUEDA OPERATIVO. USUARIO SOMOS BANCOLOMBIA ACTIVO | T12: VISITA_TÉCNICA | U12: FKZZZ695 | V12: TIPO IV | W12: TERRESTRE | X12: CASTILLO HERRERA ALEX RICARDO | Y12: 1 | Z12: 0 | AA12: =IF(V12="TIPO I",'BASE LIQUIDACION REDEBAN 2025'!$B$2,IF(V12="TIPO II",'BASE LIQUIDACION REDEBAN 2025'!$B$3,IF(V12="TIPO III",'BASE LIQUIDACION REDEBAN 2025'!$B$4,IF(V12="TIPO IV",'BASE LIQUIDACION REDEBAN 2025'!$B$5,IF(W12="AEREO",'BASE LIQUIDACION REDEBAN 2025'!$B$6,'BASE LIQUIDACION REDEBAN 2025'!$B$5))))) -> 504832.65 | AB12: =IF(V12="TIPO I",'BASE LIQUIDACION REDEBAN 2025'!$B$10,IF(V12="TIPO II",'BASE LIQUIDACION REDEBAN 2025'!$B$11,IF(V12="TIPO III",'BASE LIQUIDACION REDEBAN 2025'!$B$12,'BASE LIQUIDACION REDEBAN 2025'!$B$13))) -> 196536.53 | AC12: =Y12*AA12+Z12*AB12 -> 504832.65
A13: MONTERIA | B13: =VLOOKUP(A13,'CENTRO DE COSTOS'!A:D,4,FALSE) -> JOSE MAURICIO HERNANDEZ ROJAS | C13: =VLOOKUP(A13,'CENTRO DE COSTOS'!A:D,2,FALSE) -> 0004-0001 | D13: 5250 | E13: TA-25-1040105 | F13: 81260 | G13: APERTURA | H13: CB CRECIMIENTO ALIANZA - NUEVO | I13: ANTIOQUIA | J13: EL BAGRE | K13: DISTRICOL DROGUERIA G&P | L13: REDEBAN | M13: FO-25-1444555 | N13: 45898 | O13: 45902 | P13: AGREGADOR | Q13: DISTRICOL | R13: EJECUTADO | S13: 29-08 PROGRAMACIÓN REALIZADA POR LA ALIANZA 2/09/2025 SE REALIZA INSTALACIÓN DE CORRESPONSAL, SE INSTALAN EQUIPOS CON PRUEBAS EXITOSAS, SE CAPACITA Y SE EVALÚA AL CLIENTE, SE INSTALA PUBLICIDAD COMPLETA, CB QUEDA OPERATIVO. USUARIO SOMOS BANCOLOMBIA ACTIVO. LAS PRUEBAS DE RECAUDO Y TRANSFERENCIA NO SE REALIZARON PORQUE EL CLIENTE NO TIENE OTRA CUENTA Y NO HAY FACTURAS PARA HACER RECAUDOS | T13: VISITA_TÉCNICA | U13: SKZZZ566 | V13: TIPO IV | W13: TERRESTRE | X13: CALDERA SALCEDO CARLOS JULIO | Y13: 1 | Z13: 0 | AA13: =IF(V13="TIPO I",'BASE LIQUIDACION REDEBAN 2025'!$B$2,IF(V13="TIPO II",'BASE LIQUIDACION REDEBAN 2025'!$B$3,IF(V13="TIPO III",'BASE LIQUIDACION REDEBAN 2025'!$B$4,IF(V13="TIPO IV",'BASE LIQUIDACION REDEBAN 2025'!$B$5,IF(W13="AEREO",'BASE LIQUIDACION REDEBAN 2025'!$B$6,'BASE LIQUIDACION REDEBAN 2025'!$B$5))))) -> 504832.65 | AB13: =IF(V13="TIPO I",'BASE LIQUIDACION REDEBAN 2025'!$B$10,IF(V13="TIPO II",'BASE LIQUIDACION REDEBAN 2025'!$B$11,IF(V13="TIPO III",'BASE LIQUIDACION REDEBAN 2025'!$B$12,'BASE LIQUIDACION REDEBAN 2025'!$B$13))) -> 196536.53 | AC13: =Y13*AA13+Z13*AB13 -> 504832.65
... A220: BUCARAMANGA | B220: =VLOOKUP(A220,'CENTRO DE COSTOS'!A:D,4,FALSE) -> MIGUEL JULIÁN HERNÁNDEZ GUARÍN | C220: =VLOOKUP(A220,'CENTRO DE COSTOS'!A:D,2,FALSE) -> 0004-0008 | D220: 68001 | E220: TA-25-1157235 | F220: 81703 | G220: APERTURA | H220: CB CRECIMIENTO ALIANZA - NUEVO | I220: SANTANDER | J220: BUCARAMANGA | K220: DISTRICOL OPULENCE SHOES | L220: REDEBAN | M220: FO-25-1598678 | N220: 45929 | O220: 45930 | P220: AGREGADOR | Q220: DISTRICOL | R220: EJECUTADO | S220: 29-09 PROGRAMACIÓN REALIZADA POR LA ALIANZA 30/09/2025 SE REALIZA INSTALACIÓN DE CORRESPONSAL, SE INSTALAN EQUIPOS CON PRUEBAS EXITOSAS, SE CAPACITA Y SE EVALÚA AL CLIENTE, SE INSTALA PUBLICIDAD COMPLETA, CB QUEDA OPERATIVO. USUARIO SOMOS BANCOLOMBIA ACTIVO | T220: REYES RAMIREZ DIEGO ALEXANDER | U220: FYZZZ196 | V220: TIPO I | W220: TERRESTRE | X220: REYES RAMIREZ DIEGO ALEXANDER | Y220: 1 | Z220: 0 | AA220: =IF(V220="TIPO I",'BASE LIQUIDACION REDEBAN 2025'!$B$2,IF(V220="TIPO II",'BASE LIQUIDACION REDEBAN 2025'!$B$3,IF(V220="TIPO III",'BASE LIQUIDACION REDEBAN 2025'!$B$4,IF(V220="TIPO IV",'BASE LIQUIDACION REDEBAN 2025'!$B$5,IF(W220="AEREO",'BASE LIQUIDACION REDEBAN 2025'!$B$6,'BASE LIQUIDACION REDEBAN 2025'!$B$5))))) -> 75096.394 | AB220: =IF(V220="TIPO I",'BASE LIQUIDACION REDEBAN 2025'!$B$10,IF(V220="TIPO II",'BASE LIQUIDACION REDEBAN 2025'!$B$11,IF(V220="TIPO III",'BASE LIQUIDACION REDEBAN 2025'!$B$12,'BASE LIQUIDACION REDEBAN 2025'!$B$13))) -> 75096.394 | AC220: =Y220*AA220+Z220*AB220 -> 75096.394
AC221: =SUM(AC2:AC220) -> 42735836

Sheet INCIDENTES BANCOLOMBIA
A1: CIUDAD SEDE | B1: COORDINADOR | C1: CENTRO DE COSTOS LÍNEACOM | D1: CÓDIGO DANE | E1: TA/CODIGO ACTIVIDAD | F1: CODIGO CB | G1: ACTIVIDAD | H1: DEPARTAMENTO | I1: CIUDAD | J1: NOMBRE DEL CB | K1: RED | L1: FO | M1: FECHA ASIGNACIÓN A LÍNEA COMUNICACIONES (DD/MM/AAAA HH:MM) | N1: FECHA CIERRE DEL TICKET (DD/MM/AAAA HH:MM) | O1: ACOMETIDA | P1: GRUPO_FALLA | Q1: CATEGORÍA | R1: FALLA | S1: FORMATO | T1: CADENA | U1: ESTADO | V1: OBSERVACION | W1: FORMA DE ATENCIÓN | X1: TERMINAL | Y1: TIPIFICACION | Z1: TIPO DE TRAYECTO | AA1: NOMBRE DEL TECNICO | AB1: DIAS DE VISITA | AC1: DIA ADICIONAL | AD1: VALOR DIAS ACTIVIDAD FACTURABLES A LA RED | AE1: VALOR DIAS ACOMPAÑAMIENTO FACTURABLES A RED | AF1: VALOR FACTURABLE A LA RED | AG1: CU CB | AH1: COBRO ENTIDAD | AI1: ESTADO | AJ1: TIPO | AK1: VAL TIPO | AL1: VAL COSTO | AM1: OBSERVACIONES | AN1: Observaciones LINEA
A2: BOGOTA | B2: =VLOOKUP(A2,'CENTRO DE COSTOS'!A:D,4,FALSE) -> WILLIAM ASDRUBAL ROZO ROZO | C2: =VLOOKUP(A2,'CENTRO DE COSTOS'!A:D,2,FALSE) -> 0004-0004 | D2: 25754 | E2: 2815944 | F2: 66235 | G2: INCIDENTE | H2: CUNDINAMARCA | I2: SOACHA | J2: BARRIO NEMESIS SOACHA | K2: REDEBAN | L2: FO-25-1605128 | M2: 45930.555 | N2: 45930.697 | O2: NO | P2: SOFTWARE | Q2: LECTOR DE BARRAS | R2: LECTOR DESCONFIGURADO | U2: CERRADO | V2: 30/09/2025 SE RELAIZA VISITA DE CAMPO ENCONTRANDO QUE LECTOR DE CODIGO DE BARRAS PERDIO CONFIGURACIÓN ARROJA FORMATO INVALIDO SE REALIZA CONFIGURACIÓN DE LECTOR CON PRUEBAS OK PARÁMETROS OK NO SE INICIALIZA EQUIPO TODO A CONFORMIDAD DE CB | W2: VISITA_TÉCNICA | X2: 2A00L313 | Y2: TIPO I | Z2: TERRESTRE | AA2: GALEANO SORIANO JUAN DAVID | AB2: 1 | AC2: 0 | AD2: =IF(W2="SOPORTE_TELEFÓNICO",'BASE LIQUIDACION REDEBAN 2025'!$B$19,IF(W2="ENVÍO",'BASE LIQUIDACION REDEBAN 2025'!$C$2,IF(Y2="TIPO I",'BASE LIQUIDACION REDEBAN 2025'!$C$2,IF(Y2="TIPO II",'BASE LIQUIDACION REDEBAN 2025'!$C$3,IF(Y2="TIPO III",'BASE LIQUIDACION REDEBAN 2025'!$C$4,IF(Y2="TIPO IV",'BASE LIQUIDACION REDEBAN 2025'!$C$5,IF(Z2="AEREO",'BASE LIQUIDACION REDEBAN 2025'!$B$6,'BASE LIQUIDACION REDEBAN 2025'!$C$5))))))) -> 65960.072 | AE2: =IF(OR(W2="SOPORTE_TELEFÓNICO",W2="ENVÍO"),0,IF(Y2="TIPO I",'BASE LIQUIDACION REDEBAN 2025'!$B$10,IF(Y2="TIPO II",'BASE LIQUIDACION REDEBAN 2025'!$B$11,IF(Y2="TIPO III",'BASE LIQUIDACION REDEBAN 2025'!$B$12,'BASE LIQUIDACION REDEBAN 2025'!$B$13)))) -> 75096.394 | AF2: =IF(OR(W2="SOPORTE_TELEFÓNICO",W2="ENVÍO"),AD2,(AD2*AB2+AE2*AC2)) -> 65960.072
A3: BUCARAMANGA | B3: =VLOOKUP(A3,'CENTRO DE COSTOS'!A:D,4,FALSE) -> MIGUEL JULIÁN HERNÁNDEZ GUARÍN | C3: =VLOOKUP(A3,'CENTRO DE COSTOS'!A:D,2,FALSE) -> 0004-0008 | D3: 68001 | E3: 2815477 | F3: 59523 | G3: INCIDENTE | H3: SANTANDER | I3: BUCARAMANGA | J3: BARRIO BETANIA BUCARAMANGA | K3: REDEBAN | L3: FO-25-1604645 | M3: 45930.501 | N3: 45930.692 | O3: NO | P3: HARDWARE | Q3: PINPAD | R3: ALERTADO | U3: CERRADO | V3: 30/09/2025 CB CON PINPAD ALERTADO, CAMBIO DE DATAFONO PINPAD, CAMBIO DE FUENTE Y CABLE MAGIC O POR TECNOLOGIA, BORRADO E INYECCION DE SO +VER 10.3N,CONFIGURACION CB OK, CUBRE CLAVE OK, PRUEBAS OK. CLIENTE NO PERMITE CIERRE POR FLUJO DE CLIENTES INDICA QUE SE DEMORA MÁS DE UN DÍA EN IMPRIMIRLO | W3: VISITA_TÉCNICA | X3: JA007449 | Y3: TIPO I | Z3: TERRESTRE | AA3: SANTOS GONZALEZ JOHAN FABIAN | AB3: 1 | AC3: 0 | AD3: =IF(W3="SOPORTE_TELEFÓNICO",'BASE LIQUIDACION REDEBAN 2025'!$B$19,IF(W3="ENVÍO",'BASE LIQUIDACION REDEBAN 2025'!$C$2,IF(Y3="TIPO I",'BASE LIQUIDACION REDEBAN 2025'!$C$2,IF(Y3="TIPO II",'BASE LIQUIDACION REDEBAN 2025'!$C$3,IF(Y3="TIPO III",'BASE LIQUIDACION REDEBAN 2025'!$C$4,IF(Y3="TIPO IV",'BASE LIQUIDACION REDEBAN 2025'!$C$5,IF(Z3="AEREO",'BASE LIQUIDACION REDEBAN 2025'!$B$6,'BASE LIQUIDACION REDEBAN 2025'!$C$5))))))) -> 65960.072 | AE3: =IF(OR(W3="SOPORTE_TELEFÓNICO",W3="ENVÍO"),0,IF(Y3="TIPO I",'BASE LIQUIDACION REDEBAN 2025'!$B$10,IF(Y3="TIPO II",'BASE LIQUIDACION REDEBAN 2025'!$B$11,IF(Y3="TIPO III",'BASE LIQUIDACION REDEBAN 2025'!$B$12,'BASE LIQUIDACION REDEBAN 2025'!$B$13)))) -> 75096.394 | AF3: =IF(OR(W3="SOPORTE_TELEFÓNICO",W3="ENVÍO"),AD3,(AD3*AB3+AE3*AC3)) -> 65960.072
A4: CALI | B4: =VLOOKUP(A4,'CENTRO DE COSTOS'!A:D,4,FALSE) -> DIEGO FERNANDO HENAO CARDONA | C4: =VLOOKUP(A4,'CENTRO DE COSTOS'!A:D,2,FALSE) -> 0004-0003 | D4: 76001 | E4: 2814912 | F4: 74231 | G4: INCIDENTE | H4: VALLE DEL CAUCA | I4: CALI | J4: PTM CALI LR EL LIDO | K4: REDEBAN | L4: FO-25-1604036 | M4: 45930.463 | N4: 45930.688 | O4: NO | P4: HARDWARE | Q4: SE REINICIA | R4: DAÑO POS | U4: CERRADO | V4: 30/09/2025 SE VISITA EL COMERCIO, SE REVISA LOS EQUIPOS SE ENCUENTRAN EL DATAFONO SE REINICIA CUANDO IMPRIME EL VOUCHER, ESTA FLOJO LA BATERÍA SE AJUSTA RESOLVIENDO EL PROBLEMA, PRUEBAS OK, TELECARGA TRNA | W4: VISITA_TÉCNICA | X4: EG3ZZ029 - EF02Z996 | Y4: TIPO I | Z4: TERRESTRE | AA4: HERRERA MONAR GEOVANNY | AB4: 1 | AC4: 0 | AD4: =IF(W4="SOPORTE_TELEFÓNICO",'BASE LIQUIDACION REDEBAN 2025'!$B$19,IF(W4="ENVÍO",'BASE LIQUIDACION REDEBAN 2025'!$C$2,IF(Y4="TIPO I",'BASE LIQUIDACION REDEBAN 2025'!$C$2,IF(Y4="TIPO II",'BASE LIQUIDACION REDEBAN 2025'!$C$3,IF(Y4="TIPO III",'BASE LIQUIDACION REDEBAN 2025'!$C$4,IF(Y4="TIPO IV",'BASE LIQUIDACION REDEBAN 2025'!$C$5,IF(Z4="AEREO",'BASE LIQUIDACION REDEBAN 2025'!$B$6,'BASE LIQUIDACION REDEBAN 2025'!$C$5))))))) -> 65960.072 | AE4: =IF(OR(W4="SOPORTE_TELEFÓNICO",W4="ENVÍO"),0,IF(Y4="TIPO I",'BASE LIQUIDACION REDEBAN 2025'!$B$10,IF(Y4="TIPO II",'BASE LIQUIDACION REDEBAN 2025'!$B$11,IF(Y4="TIPO III",'BASE LIQUIDACION REDEBAN 2025'!$B$12,'BASE LIQUIDACION REDEBAN 2025'!$B$13)))) -> 75096.394 | AF4: =IF(OR(W4="SOPORTE_TELEFÓNICO",W4="ENVÍO"),AD4,(AD4*AB4+AE4*AC4)) -> 65960.072
A5: CALI | B5: =VLOOKUP(A5,'CENTRO DE COSTOS'!A:D,4,FALSE) -> DIEGO FERNANDO HENAO CARDONA | C5: =VLOOKUP(A5,'CENTRO DE COSTOS'!A:D,2,FALSE) -> 0004-0003 | D5: 76001 | E5: 2814756 | F5: 73907 | G5: INCIDENTE | H5: VALLE DEL CAUCA | I5: CALI | J5: REVAL JARDÍN PLAZA II | K5: REDEBAN | L5: FO-25-1604054 | M5: 45930.458 | N5: 45930.683 | O5: NO | P5: HARDWARE | Q5: LECTOR DE BARRAS | R5: DAÑO POS | U5: CERRADO | V5: 30/09/2025 SE REALIZA CAMBIO DE LECTOR DE BARRAS YA QUE NO FUNCIONABA SE CAMBIÓ POR UN SYMBOL SE REALIZA PRUEBAS OK | W5: VISITA_TÉCNICA | X5: ON0IZ819 | Y5: TIPO I | Z5: TERRESTRE | AA5: ESCOBAR LENIS JUAN SEBASTIAN | AB5: 1 | AC5: 0 | AD5: =IF(W5="SOPORTE_TELEFÓNICO",'BASE LIQUIDACION REDEBAN 2025'!$B$19,IF(W5="ENVÍO",'BASE LIQUIDACION REDEBAN 2025'!$C$2,IF(Y5="TIPO I",'BASE LIQUIDACION REDEBAN 2025'!$C$2,IF(Y5="TIPO II",'BASE LIQUIDACION REDEBAN 2025'!$C$3,IF(Y5="TIPO III",'BASE LIQUIDACION REDEBAN 2025'!$C$4,IF(Y5="TIPO IV",'BASE LIQUIDACION REDEBAN 2025'!$C$5,IF(Z5="AEREO",'BASE LIQUIDACION REDEBAN 2025'!$B$6,'BASE LIQUIDACION REDEBAN 2025'!$C$5))))))) -> 65960.072 | AE5: =IF(OR(W5="SOPORTE_TELEFÓNICO",W5="ENVÍO"),0,IF(Y5="TIPO I",'BASE LIQUIDACION REDEBAN 2025'!$B$10,IF(Y5="TIPO II",'BASE LIQUIDACION REDEBAN 2025'!$B$11,IF(Y5="TIPO III",'BASE LIQUIDACION REDEBAN 2025'!$B$12,'BASE LIQUIDACION REDEBAN 2025'!$B$13)))) -> 75096.394 | AF5: =IF(OR(W5="SOPORTE_TELEFÓNICO",W5="ENVÍO"),AD5,(AD5*AB5+AE5*AC5)) -> 65960.072
A6: CALI | B6: =VLOOKUP(A6,'CENTRO DE COSTOS'!A:D,4,FALSE) -> DIEGO FERNANDO HENAO CARDONA | C6: =VLOOKUP(A6,'CENTRO DE COSTOS'!A:D,2,FALSE) -> 0004-0003 | D6: 76364 | E6: 2814200 | F6: 17613 | G6: INCIDENTE | H6: VALLE DEL CAUCA | I6: JAMUNDI | J6: BARRIO TERRANOVA III JAMUNDI | K6: REDEBAN | L6: FO-25-1603460 | M6: 45930.421 | N6: 45930.717 | O6: NO | P6: HARDWARE | Q6: COMUNICACION | R6: MENSAJE CABLE DE RED DESCONECTADO | U6: CERRADO | V6: 30/09/2025 SE REALIZA CAMBIO DE EQUIPO E6 PUERTO IP MALO, CB BANCOLOMBIA PURO, PRUEBAS OK | W6: VISITA_TÉCNICA | X6: II00S911 | Y6: TIPO II | Z6: TERRESTRE | AA6: PAREDES CASTILLO DIEGO | AB6: 1 | AC6: 0 | AD6: =IF(W6="SOPORTE_TELEFÓNICO",'BASE LIQUIDACION REDEBAN 2025'!$B$19,IF(W6="ENVÍO",'BASE LIQUIDACION REDEBAN 2025'!$C$2,IF(Y6="TIPO I",'BASE LIQUIDACION REDEBAN 2025'!$C$2,IF(Y6="TIPO II",'BASE LIQUIDACION REDEBAN 2025'!$C$3,IF(Y6="TIPO III",'BASE LIQUIDACION REDEBAN 2025'!$C$4,IF(Y6="TIPO IV",'BASE LIQUIDACION REDEBAN 2025'!$C$5,IF(Z6="AEREO",'BASE LIQUIDACION REDEBAN 2025'!$B$6,'BASE LIQUIDACION REDEBAN 2025'!$C$5))))))) -> 144967.87 | AE6: =IF(OR(W6="SOPORTE_TELEFÓNICO",W6="ENVÍO"),0,IF(Y6="TIPO I",'BASE LIQUIDACION REDEBAN 2025'!$B$10,IF(Y6="TIPO II",'BASE LIQUIDACION REDEBAN 2025'!$B$11,IF(Y6="TIPO III",'BASE LIQUIDACION REDEBAN 2025'!$B$12,'BASE LIQUIDACION REDEBAN 2025'!$B$13)))) -> 140395.63 | AF6: =IF(OR(W6="SOPORTE_TELEFÓNICO",W6="ENVÍO"),AD6,(AD6*AB6+AE6*AC6)) -> 144967.87
A7: MEDELLIN | B7: =VLOOKUP(A7,'CENTRO DE COSTOS'!A:D,4,FALSE) -> JUAN SEBASTIÁN RÍOS CASTRILLÓN | C7: =VLOOKUP(A7,'CENTRO DE COSTOS'!A:D,2,FALSE) -> 0004-0005 | D7: 5579 | E7: 2812568 | F7: 51485 | G7: INCIDENTE | H7: ANTIOQUIA | I7: PUERTO BERRIO | J7: PTM PUERTO BERRIO SERVICENTRO | K7: REDEBAN | L7: FO-25-1601968 | M7: 45930.333 | N7: 45930.621 | O7: NO | P7: HARDWARE | Q7: COMUNICACION | R7: MENSAJE CABLE DE RED DESCONECTADO | U7: CERRADO | V7: 30/09/2025 SE HACE MANTENIMIENTO OK SE ORGANIZAN CABLEADOS DE DATÁFONO SE COMFIGURA PARÁMETROS DE DE DATÁFONO OK PRUEBAS EXITOSAS | W7: VISITA_TÉCNICA | X7: 9BRZZ690 | Y7: TIPO III | Z7: TERRESTRE | AA7: DIAZ ZABALA FRANCIS DUBAN | AB7: 1 | AC7: 0 | AD7: =IF(W7="SOPORTE_TELEFÓNICO",'BASE LIQUIDACION REDEBAN 2025'!$B$19,IF(W7="ENVÍO",'BASE LIQUIDACION REDEBAN 2025'!$C$2,IF(Y7="TIPO I",'BASE LIQUIDACION REDEBAN 2025'!$C$2,IF(Y7="TIPO II",'BASE LIQUIDACION REDEBAN 2025'!$C$3,IF(Y7="TIPO III",'BASE LIQUIDACION REDEBAN 2025'!$C$4,IF(Y7="TIPO IV",'BASE LIQUIDACION REDEBAN 2025'!$C$5,IF(Z7="AEREO",'BASE LIQUIDACION REDEBAN 2025'!$B$6,'BASE LIQUIDACION REDEBAN 2025'!$C$5))))))) -> 275728.78 | AE7: =IF(OR(W7="SOPORTE_TELEFÓNICO",W7="ENVÍO"),0,IF(Y7="TIPO I",'BASE LIQUIDACION REDEBAN 2025'!$B$10,IF(Y7="TIPO II",'BASE LIQUIDACION REDEBAN 2025'!$B$11,IF(Y7="TIPO III",'BASE LIQUIDACION REDEBAN 2025'!$B$12,'BASE LIQUIDACION REDEBAN 2025'!$B$13)))) -> 196536.53 | AF7: =IF(OR(W7="SOPORTE_TELEFÓNICO",W7="ENVÍO"),AD7,(AD7*AB7+AE7*AC7)) -> 275728.78
A8: MEDELLIN | B8: =VLOOKUP(A8,'CENTRO DE COSTOS'!A:D,4,FALSE) -> JUAN SEBASTIÁN RÍOS CASTRILLÓN | C8: =VLOOKUP(A8,'CENTRO DE COSTOS'!A:D,2,FALSE) -> 0004-0005 | D8: 5001 | E8: 2811767 | F8: 37382 | G8: INCIDENTE | H8: ANTIOQUIA | I8: MEDELLIN | J8: BARRIO MANRIQUE MEDELLIN 5 | K8: REDEBAN | L8: FO-25-1601523 | M8: 45930.333 | N8: 45930.601 | O8: NO | P8: HARDWARE | Q8: HUB | R8: DETERIORO CABLE | U8: CERRADO | V8: 30/09/2025 SE REALIZA LIMPIEZA DEL LECTOR CHIP DE PINPAD, SE CAMBIA HUB CON EL CABLE PELADO, SE DEJAN SERVICIOS FUNCIONANDO CORRECTAMENTE | W8: VISITA_TÉCNICA | X8: AB00N148 | Y8: TIPO I | Z8: TERRESTRE | AA8: BARRIENTOS HERNANDEZ CRISTIAN HORACIO | AB8: 1 | AC8: 0 | AD8: =IF(W8="SOPORTE_TELEFÓNICO",'BASE LIQUIDACION REDEBAN 2025'!$B$19,IF(W8="ENVÍO",'BASE LIQUIDACION REDEBAN 2025'!$C$2,IF(Y8="TIPO I",'BASE LIQUIDACION REDEBAN 2025'!$C$2,IF(Y8="TIPO II",'BASE LIQUIDACION REDEBAN 2025'!$C$3,IF(Y8="TIPO III",'BASE LIQUIDACION REDEBAN 2025'!$C$4,IF(Y8="TIPO IV",'BASE LIQUIDACION REDEBAN 2025'!$C$5,IF(Z8="AEREO",'BASE LIQUIDACION REDEBAN 2025'!$B$6,'BASE LIQUIDACION REDEBAN 2025'!$C$5))))))) -> 65960.072 | AE8: =IF(OR(W8="SOPORTE_TELEFÓNICO",W8="ENVÍO"),0,IF(Y8="TIPO I",'BASE LIQUIDACION REDEBAN 2025'!$B$10,IF(Y8="TIPO II",'BASE LIQUIDACION REDEBAN 2025'!$B$11,IF(Y8="TIPO III",'BASE LIQUIDACION REDEBAN 2025'!$B$12,'BASE LIQUIDACION REDEBAN 2025'!$B$13)))) -> 75096.394 | AF8: =IF(OR(W8="SOPORTE_TELEFÓNICO",W8="ENVÍO"),AD8,(AD8*AB8+AE8*AC8)) -> 65960.072
A9: CALI | B9: =VLOOKUP(A9,'CENTRO DE COSTOS'!A:D,4,FALSE) -> DIEGO FERNANDO HENAO CARDONA | C9: =VLOOKUP(A9,'CENTRO DE COSTOS'!A:D,2,FALSE) -> 0004-0003 | D9: 76001 | E9: 2811812 | F9: 78740 | G9: INCIDENTE | H9: VALLE DEL CAUCA | I9: CALI | J9: PTM CALI MISCELANEA Y PAPELERI | K9: REDEBAN | L9: FO-25-1601527 | M9: 45930.333 | N9: 45930.488 | O9: NO | P9: HARDWARE | Q9: LECTOR DE TARJETAS | R9: MENSAJE RETIRE TARJETA | U9: CERRADO | V9: 30/09/2025 SE REALIZA MANTENIMIENTO PREVENTIVO Y SE EXTRAE PLÁSTICO DE SU INTERIOR. SE REALIZA PRUEBAS OPERATIVAS SIN NOVEDAD. CB QUEDA OKEY. | W9: VISITA_TÉCNICA | X9: LMQZZ730 | Y9: TIPO I | Z9: TERRESTRE | AA9: TORRES GARCIA JENDRY JOSE | AB9: 1 | AC9: 0 | AD9: =IF(W9="SOPORTE_TELEFÓNICO",'BASE LIQUIDACION REDEBAN 2025'!$B$19,IF(W9="ENVÍO",'BASE LIQUIDACION REDEBAN 2025'!$C$2,IF(Y9="TIPO I",'BASE LIQUIDACION REDEBAN 2025'!$C$2,IF(Y9="TIPO II",'BASE LIQUIDACION REDEBAN 2025'!$C$3,IF(Y9="TIPO III",'BASE LIQUIDACION REDEBAN 2025'!$C$4,IF(Y9="TIPO IV",'BASE LIQUIDACION REDEBAN 2025'!$C$5,IF(Z9="AEREO",'BASE LIQUIDACION REDEBAN 2025'!$B$6,'BASE LIQUIDACION REDEBAN 2025'!$C$5))))))) -> 65960.072 | AE9: =IF(OR(W9="SOPORTE_TELEFÓNICO",W9="ENVÍO"),0,IF(Y9="TIPO I",'BASE LIQUIDACION REDEBAN 2025'!$B$10,IF(Y9="TIPO II",'BASE LIQUIDACION REDEBAN 2025'!$B$11,IF(Y9="TIPO III",'BASE LIQUIDACION REDEBAN 2025'!$B$12,'BASE LIQUIDACION REDEBAN 2025'!$B$13)))) -> 75096.394 | AF9: =IF(OR(W9="SOPORTE_TELEFÓNICO",W9="ENVÍO"),AD9,(AD9*AB9+AE9*AC9)) -> 65960.072
A10: MEDELLIN | B10: =VLOOKUP(A10,'CENTRO DE COSTOS'!A:D,4,FALSE) -> JUAN SEBASTIÁN RÍOS CASTRILLÓN | C10: =VLOOKUP(A10,'CENTRO DE COSTOS'!A:D,2,FALSE) -> 0004-0005 | D10: 5190 | E10: 2811562 | F10: 27117 | G10: INCIDENTE | H10: ANTIOQUIA | I10: CISNEROS | J10: BARRIO PARQUE PRINCIPAL CISNER | K10: REDEBAN | L10: FO-25-1601037 | M10: 45929.734 | N10: 45930.6 | O10: NO | P10: HARDWARE | Q10: IMPRESION | R10: NO IMPRIME UNO O VARIOS CARACTERES | U10: CERRADO | V10: 30/09/2025 SE HACE MANTENIMIENTO SE OK SE CAMBIA DATÁFONO POR EN IMPRESIÓN | W10: VISITA_TÉCNICA | X10: 1FZZZ568 | Y10: TIPO II | Z10: TERRESTRE | AA10: DIAZ ZABALA FRANCIS DUBAN | AB10: 1 | AC10: 0 | AD10: =IF(W10="SOPORTE_TELEFÓNICO",'BASE LIQUIDACION REDEBAN 2025'!$B$19,IF(W10="ENVÍO",'BASE LIQUIDACION REDEBAN 2025'!$C$2,IF(Y10="TIPO I",'BASE LIQUIDACION REDEBAN 2025'!$C$2,IF(Y10="TIPO II",'BASE LIQUIDACION REDEBAN 2025'!$C$3,IF(Y10="TIPO III",'BASE LIQUIDACION REDEBAN 2025'!$C$4,IF(Y10="TIPO IV",'BASE LIQUIDACION REDEBAN 2025'!$C$5,IF(Z10="AEREO",'BASE LIQUIDACION REDEBAN 2025'!$B$6,'BASE LIQUIDACION REDEBAN 2025'!$C$5))))))) -> 144967.87 | AE10: =IF(OR(W10="SOPORTE_TELEFÓNICO",W10="ENVÍO"),0,IF(Y10="TIPO I",'BASE LIQUIDACION REDEBAN 2025'!$B$10,IF(Y10="TIPO II",'BASE LIQUIDACION REDEBAN 2025'!$B$11,IF(Y10="TIPO III",'BASE LIQUIDACION REDEBAN 2025'!$B$12,'BASE LIQUIDACION REDEBAN 2025'!$B$13)))) -> 140395.63 | AF10: =IF(OR(W10="SOPORTE_TELEFÓNICO",W10="ENVÍO"),AD10,(AD10*AB10+AE10*AC10)) -> 144967.87
A11: MEDELLIN | B11: =VLOOKUP(A11,'CENTRO DE COSTOS'!A:D,4,FALSE) -> JUAN SEBASTIÁN RÍOS CASTRILLÓN | C11: =VLOOKUP(A11,'CENTRO DE COSTOS'!A:D,2,FALSE) -> 0004-0005 | D11: 5001 | E11: 2811319 | F11: 47980 | G11: INCIDENTE | H11: ANTIOQUIA | I11: MEDELLIN | J11: DISTRICOL DROGUERIA TAYRONA | K11: REDEBAN | L11: FO-25-1600920 | M11: 45929.703 | N11: 45930.56 | O11: NO | P11: HARDWARE | Q11: LECTOR DE BARRAS | R11: FORMATO INVALIDO LECTOR DAÑADO | U11: CERRADO | V11: 30/09/2025 SE REALIZA CAMBIO DE LECTORA YA QUE LA ANTERIOR EN OCASIONES NO LEÍA. | W11: VISITA_TÉCNICA | X11: 9C00I718 | Y11: TIPO I | Z11: TERRESTRE | AA11: RAMIREZ TABARES JUAN DIEGO | AB11: 1 | AC11: 0 | AD11: =IF(W11="SOPORTE_TELEFÓNICO",'BASE LIQUIDACION REDEBAN 2025'!$B$19,IF(W11="ENVÍO",'BASE LIQUIDACION REDEBAN 2025'!$C$2,IF(Y11="TIPO I",'BASE LIQUIDACION REDEBAN 2025'!$C$2,IF(Y11="TIPO II",'BASE LIQUIDACION REDEBAN 2025'!$C$3,IF(Y11="TIPO III",'BASE LIQUIDACION REDEBAN 2025'!$C$4,IF(Y11="TIPO IV",'BASE LIQUIDACION REDEBAN 2025'!$C$5,IF(Z11="AEREO",'BASE LIQUIDACION REDEBAN 2025'!$B$6,'BASE LIQUIDACION REDEBAN 2025'!$C$5))))))) -> 65960.072 | AE11: =IF(OR(W11="SOPORTE_TELEFÓNICO",W11="ENVÍO"),0,IF(Y11="TIPO I",'BASE LIQUIDACION REDEBAN 2025'!$B$10,IF(Y11="TIPO II",'BASE LIQUIDACION REDEBAN 2025'!$B$11,IF(Y11="TIPO III",'BASE LIQUIDACION REDEBAN 2025'!$B$12,'BASE LIQUIDACION REDEBAN 2025'!$B$13)))) -> 75096.394 | AF11: =IF(OR(W11="SOPORTE_TELEFÓNICO",W11="ENVÍO"),AD11,(AD11*AB11+AE11*AC11)) -> 65960.072
A12: BOGOTA | B12: =VLOOKUP(A12,'CENTRO DE COSTOS'!A:D,4,FALSE) -> WILLIAM ASDRUBAL ROZO ROZO | C12: =VLOOKUP(A12,'CENTRO DE COSTOS'!A:D,2,FALSE) -> 0004-0004 | D12: 11001 | E12: 2810996 | F12: 75740 | G12: INCIDENTE | H12: CUNDINAMARCA | I12: BOGOTA | J12: BARRIO BOSA PRIMAVERA BOGOTA 1 | K12: REDEBAN | L12: FO-25-1600929 | M12: 45929.691 | N12: 45930.54 | O12: NO | P12: SOFTWARE | Q12: ERROR DE TRANSACCIONES | R12: RECHAZO GENERAL | U12: CERRADO | V12: 30/09/2025 SE REALIZA BORRADO DE DATAFONO SE DEJA VERSIÓN 9.90 POR FALLA EN PARÁMETROS DE COMUNICACIÓN POR REVERSO PENDIENTE PRUEBA OK | W12: VISITA_TÉCNICA | X12: V100R766 | Y12: TIPO I | Z12: TERRESTRE | AA12: ORTIZ MARTINEZ STIVEN | AB12: 1 | AC12: 0 | AD12: =IF(W12="SOPORTE_TELEFÓNICO",'BASE LIQUIDACION REDEBAN 2025'!$B$19,IF(W12="ENVÍO",'BASE LIQUIDACION REDEBAN 2025'!$C$2,IF(Y12="TIPO I",'BASE LIQUIDACION REDEBAN 2025'!$C$2,IF(Y12="TIPO II",'BASE LIQUIDACION REDEBAN 2025'!$C$3,IF(Y12="TIPO III",'BASE LIQUIDACION REDEBAN 2025'!$C$4,IF(Y12="TIPO IV",'BASE LIQUIDACION REDEBAN 2025'!$C$5,IF(Z12="AEREO",'BASE LIQUIDACION REDEBAN 2025'!$B$6,'BASE LIQUIDACION REDEBAN 2025'!$C$5))))))) -> 65960.072 | AE12: =IF(OR(W12="SOPORTE_TELEFÓNICO",W12="ENVÍO"),0,IF(Y12="TIPO I",'BASE LIQUIDACION REDEBAN 2025'!$B$10,IF(Y12="TIPO II",'BASE LIQUIDACION REDEBAN 2025'!$B$11,IF(Y12="TIPO III",'BASE LIQUIDACION REDEBAN 2025'!$B$12,'BASE LIQUIDACION REDEBAN 2025'!$B$13)))) -> 75096.394 | AF12: =IF(OR(W12="SOPORTE_TELEFÓNICO",W12="ENVÍO"),AD12,(AD12*AB12+AE12*AC12)) -> 65960.072
A13: MEDELLIN | B13: =VLOOKUP(A13,'CENTRO DE COSTOS'!A:D,4,FALSE) -> JUAN SEBASTIÁN RÍOS CASTRILLÓN | C13: =VLOOKUP(A13,'CENTRO DE COSTOS'!A:D,2,FALSE) -> 0004-0005 | D13: 5001 | E13: 2810944 | F13: 26429 | G13: INCIDENTE | H13: ANTIOQUIA | I13: MEDELLIN | J13: COMCARD MED PAPER WORLD | K13: REDEBAN | L13: FO-25-1600695 | M13: 45929.684 | N13: 45930.533 | O13: NO | P13: HARDWARE | Q13: IMPRESION | R13: TAPA IMPRESORA | U13: CERRADO | V13: 30/09/2025 SE REALIZA CAMBIO DE TAPA IMPRESION POR QUÉ LA QUE TENÍA ESTA REVENTADA, ADICIONAL SE CAMBIÓ FUENTE DE PODER. | W13: VISITA_TÉCNICA | X13: 9999F062 | Y13: TIPO I | Z13: TERRESTRE | AA13: RAMIREZ TABARES JUAN DIEGO | AB13: 1 | AC13: 0 | AD13: =IF(W13="SOPORTE_TELEFÓNICO",'BASE LIQUIDACION REDEBAN 2025'!$B$19,IF(W13="ENVÍO",'BASE LIQUIDACION REDEBAN 2025'!$C$2,IF(Y13="TIPO I",'BASE LIQUIDACION REDEBAN 2025'!$C$2,IF(Y13="TIPO II",'BASE LIQUIDACION REDEBAN 2025'!$C$3,IF(Y13="TIPO III",'BASE LIQUIDACION REDEBAN 2025'!$C$4,IF(Y13="TIPO IV",'BASE LIQUIDACION REDEBAN 2025'!$C$5,IF(Z13="AEREO",'BASE LIQUIDACION REDEBAN 2025'!$B$6,'BASE LIQUIDACION REDEBAN 2025'!$C$5))))))) -> 65960.072 | AE13: =IF(OR(W13="SOPORTE_TELEFÓNICO",W13="ENVÍO"),0,IF(Y13="TIPO I",'BASE LIQUIDACION REDEBAN 2025'!$B$10,IF(Y13="TIPO II",'BASE LIQUIDACION REDEBAN 2025'!$B$11,IF(Y13="TIPO III",'BASE LIQUIDACION REDEBAN 2025'!$B$12,'BASE LIQUIDACION REDEBAN 2025'!$B$13)))) -> 75096.394 | AF13: =IF(OR(W13="SOPORTE_TELEFÓNICO",W13="ENVÍO"),AD13,(AD13*AB13+AE13*AC13)) -> 65960.072
... A274: MONTERIA | B274: =VLOOKUP(A274,'CENTRO DE COSTOS'!A:D,4,FALSE) -> JOSE MAURICIO HERNANDEZ ROJAS | C274: =VLOOKUP(A274,'CENTRO DE COSTOS'!A:D,2,FALSE) -> 0004-0001 | D274: 23466 | E274: 2775317 | F274: 44450 | G274: INCIDENTE | H274: CORDOBA | I274: MONTELIBANO | J274: DISTRICOL PAPELERIA Y VARIEDAD | K274: REDEBAN | L274: FO-25-1565214 | M274: 45922.56 | N274: 45924.583 | O274: NO | P274: HARDWARE | Q274: LECTOR DE BARRAS | R274: FORMATO INVALIDO LECTOR DAÑADO | U274: CERRADO | V274: 24/09/2025 SE REALIZÓ CAMBIO DE LECTOR DE CÓDIGO DE BARRAS OK, PRUEBAS OK, TELECARGA DRNA. | W274: VISITA_TÉCNICA | X274: GA07Z866 | Y274: TIPO IV | Z274: TERRESTRE | AA274: CALDERA SALCEDO CARLOS JULIO | AB274: 1 | AC274: 0 | AD274: =IF(W274="SOPORTE_TELEFÓNICO",'BASE LIQUIDACION REDEBAN 2025'!$B$19,IF(W274="ENVÍO",'BASE LIQUIDACION REDEBAN 2025'!$C$2,IF(Y274="TIPO I",'BASE LIQUIDACION REDEBAN 2025'!$C$2,IF(Y274="TIPO II",'BASE LIQUIDACION REDEBAN 2025'!$C$3,IF(Y274="TIPO III",'BASE LIQUIDACION REDEBAN 2025'!$C$4,IF(Y274="TIPO IV",'BASE LIQUIDACION REDEBAN 2025'!$C$5,IF(Z274="AEREO",'BASE LIQUIDACION REDEBAN 2025'!$B$6,'BASE LIQUIDACION REDEBAN 2025'!$C$5))))))) -> 479588.88 | AE274: =IF(OR(W274="SOPORTE_TELEFÓNICO",W274="ENVÍO"),0,IF(Y274="TIPO I",'BASE LIQUIDACION REDEBAN 2025'!$B$10,IF(Y274="TIPO II",'BASE LIQUIDACION REDEBAN 2025'!$B$11,IF(Y274="TIPO III",'BASE LIQUIDACION REDEBAN 2025'!$B$12,'BASE LIQUIDACION REDEBAN 2025'!$B$13)))) -> 196536.53 | AF274: =IF(OR(W274="SOPORTE_TELEFÓNICO",W274="ENVÍO"),AD274,(AD274*AB274+AE274*AC274)) -> 479588.88
A275: MEDELLIN | B275: =VLOOKUP(A275,'CENTRO DE COSTOS'!A:D,4,FALSE) -> JUAN SEBASTIÁN RÍOS CASTRILLÓN | C275: =VLOOKUP(A275,'CENTRO DE COSTOS'!A:D,2,FALSE) -> 0004-0005 | D275: 5579 | E275: TA-25-1136322 | F275: 51485 | G275: INCIDENTE | H275: ANTIOQUIA | I275: PUERTO BERRIO | J275: PTM PUERTO BERRIO SERVICENTRO | K275: REDEBAN | L275: FO-25-1565077 | M275: 45922.55 | N275: 45924.47 | O275: NO | P275: SOFTWARE | Q275: COMUNICACION | R275: PARAMETROS DE CONFIGURACION EN POS | U275: CERRADO | V275: 24/09/2025 VISITA SE REALIZÓ CON OTRA TA SE HIZO CAMBIO DE EQUIPO OK | W275: SOPORTE_TELEFÓNICO | X275: 0 | Y275: TIPO III | Z275: TERRESTRE | AA275: MONTOYA VELEZ ANDRES FELIPE | AB275: 0 | AC275: 0 | AD275: =IF(W275="SOPORTE_TELEFÓNICO",'BASE LIQUIDACION REDEBAN 2025'!$B$19,IF(W275="ENVÍO",'BASE LIQUIDACION REDEBAN 2025'!$C$2,IF(Y275="TIPO I",'BASE LIQUIDACION REDEBAN 2025'!$C$2,IF(Y275="TIPO II",'BASE LIQUIDACION REDEBAN 2025'!$C$3,IF(Y275="TIPO III",'BASE LIQUIDACION REDEBAN 2025'!$C$4,IF(Y275="TIPO IV",'BASE LIQUIDACION REDEBAN 2025'!$C$5,IF(Z275="AEREO",'BASE LIQUIDACION REDEBAN 2025'!$B$6,'BASE LIQUIDACION REDEBAN 2025'!$C$5))))))) -> 41241.08 | AE275: =IF(OR(W275="SOPORTE_TELEFÓNICO",W275="ENVÍO"),0,IF(Y275="TIPO I",'BASE LIQUIDACION REDEBAN 2025'!$B$10,IF(Y275="TIPO II",'BASE LIQUIDACION REDEBAN 2025'!$B$11,IF(Y275="TIPO III",'BASE LIQUIDACION REDEBAN 2025'!$B$12,'BASE LIQUIDACION REDEBAN 2025'!$B$13)))) -> 0 | AF275: =IF(OR(W275="SOPORTE_TELEFÓNICO",W275="ENVÍO"),AD275,(AD275*AB275+AE275*AC275)) -> 41241.08
A276: BARRANQUILLA | B276: =VLOOKUP(A276,'CENTRO DE COSTOS'!A:D,4,FALSE) -> JOSE MAURICIO HERNANDEZ ROJAS | C276: =VLOOKUP(A276,'CENTRO DE COSTOS'!A:D,2,FALSE) -> 0004-0001 | D276: 8638 | E276: 2775023 | F276: 61179 | G276: INCIDENTE | H276: ATLANTICO | I276: SABANALARGA | J276: BARRIO CRUZ DE MAYO SABANALARG | K276: REDEBAN | L276: FO-25-1565014 | M276: 45922.522 | N276: 45923.681 | O276: NO | P276: HARDWARE | Q276: ALERT IRRUPTION | R276: ALERT IRRUPTION | U276: CERRADO | V276: 23/09/2025 SE REALIZA VISITA SE PROCEDE A CAMBIAR DATAFONO ,YA QUE EL QUE ESTABA ESTABA EN ALERTH INTERRUPTION ,SE PROCEDE AL CAMBIO DE HACEN PRUEBAS Y TODO OK, PRUEBAS CB Y COMERCIO ,DATAFONO MIXTO,CB OPERATIVO | W276: VISITA_TÉCNICA | X276: 9TZZZ138 | Y276: TIPO II | Z276: TERRESTRE | AA276: PORRAS CASTRO DARLON NASCK | AB276: 1 | AC276: 0 | AD276: =IF(W276="SOPORTE_TELEFÓNICO",'BASE LIQUIDACION REDEBAN 2025'!$B$19,IF(W276="ENVÍO",'BASE LIQUIDACION REDEBAN 2025'!$C$2,IF(Y276="TIPO I",'BASE LIQUIDACION REDEBAN 2025'!$C$2,IF(Y276="TIPO II",'BASE LIQUIDACION REDEBAN 2025'!$C$3,IF(Y276="TIPO III",'BASE LIQUIDACION REDEBAN 2025'!$C$4,IF(Y276="TIPO IV",'BASE LIQUIDACION REDEBAN 2025'!$C$5,IF(Z276="AEREO",'BASE LIQUIDACION REDEBAN 2025'!$B$6,'BASE LIQUIDACION REDEBAN 2025'!$C$5))))))) -> 144967.87 | AE276: =IF(OR(W276="SOPORTE_TELEFÓNICO",W276="ENVÍO"),0,IF(Y276="TIPO I",'BASE LIQUIDACION REDEBAN 2025'!$B$10,IF(Y276="TIPO II",'BASE LIQUIDACION REDEBAN 2025'!$B$11,IF(Y276="TIPO III",'BASE LIQUIDACION REDEBAN 2025'!$B$12,'BASE LIQUIDACION REDEBAN 2025'!$B$13)))) -> 140395.63 | AF276: =IF(OR(W276="SOPORTE_TELEFÓNICO",W276="ENVÍO"),AD276,(AD276*AB276+AE276*AC276)) -> 144967.87
A277: MEDELLIN | B277: =VLOOKUP(A277,'CENTRO DE COSTOS'!A:D,4,FALSE) -> JUAN SEBASTIÁN RÍOS CASTRILLÓN | C277: =VLOOKUP(A277,'CENTRO DE COSTOS'!A:D,2,FALSE) -> 0004-0005 | D277: 5030 | E277: 2774895 | F277: 77223 | G277: INCIDENTE | H277: ANTIOQUIA | I277: AMAGA | J277: "BARRIO VEREDA PIE DE CUESTA AMAGA" | K277: REDEBAN | L277: FO-25-1564414 | M277: 45922.521 | N277: 45923.668 | O277: NO | P277: HARDWARE | Q277: LECTOR DE BARRAS | R277: DAÑO POS | U277: CERRADO | V277: 23/09/2025 SE CAMBIA EQUIPO POR DAÑO EN PUERTO USB TODO OK EQUIPO Q SE INSTALO INICIALMENTE SALIÓ MALO POR RG SE CAMBIA DE NUEVO | W277: VISITA_TÉCNICA | X277: SX9ZZ511 | Y277: TIPO II | Z277: TERRESTRE | AA277: ALVAREZ ARENAS VICTOR HUGO | AB277: 1 | AC277: 0 | AD277: =IF(W277="SOPORTE_TELEFÓNICO",'BASE LIQUIDACION REDEBAN 2025'!$B$19,IF(W277="ENVÍO",'BASE LIQUIDACION REDEBAN 2025'!$C$2,IF(Y277="TIPO I",'BASE LIQUIDACION REDEBAN 2025'!$C$2,IF(Y277="TIPO II",'BASE LIQUIDACION REDEBAN 2025'!$C$3,IF(Y277="TIPO III",'BASE LIQUIDACION REDEBAN 2025'!$C$4,IF(Y277="TIPO IV",'BASE LIQUIDACION REDEBAN 2025'!$C$5,IF(Z277="AEREO",'BASE LIQUIDACION REDEBAN 2025'!$B$6,'BASE LIQUIDACION REDEBAN 2025'!$C$5))))))) -> 144967.87 | AE277: =IF(OR(W277="SOPORTE_TELEFÓNICO",W277="ENVÍO"),0,IF(Y277="TIPO I",'BASE LIQUIDACION REDEBAN 2025'!$B$10,IF(Y277="TIPO II",'BASE LIQUIDACION REDEBAN 2025'!$B$11,IF(Y277="TIPO III",'BASE LIQUIDACION REDEBAN 2025'!$B$12,'BASE LIQUIDACION REDEBAN 2025'!$B$13)))) -> 140395.63 | AF277: =IF(OR(W277="SOPORTE_TELEFÓNICO",W277="ENVÍO"),AD277,(AD277*AB277+AE277*AC277)) -> 144967.87
A278: CALI | B278: =VLOOKUP(A278,'CENTRO DE COSTOS'!A:D,4,FALSE) -> DIEGO FERNANDO HENAO CARDONA | C278: =VLOOKUP(A278,'CENTRO DE COSTOS'!A:D,2,FALSE) -> 0004-0003 | D278: 76377 | E278: 2774679 | F278: 74926 | G278: INCIDENTE | H278: VALLE DEL CAUCA | I278: LA CUMBRE | J278: BARRIO PAVAS LA CUMBRE 1 | K278: REDEBAN | L278: FO-25-1564193 | M278: 45922.501 | N278: 45923.663 | O278: NO | P278: HARDWARE | Q278: IMPRESION | R278: NO IMPRIME UNO O VARIOS CARACTERES | U278: CERRADO | V278: 23/09/2025 SE REALIZA CAMBIO WE DATÁFONO, POR MOTIVO QUE LA IMPRESIONES LA HACEN FALTA ALGUNOS CARÁCTERES. ‎SE REALIZAN PRUEBAS OPERATIVAS SIN NOVEDAD. ‎CB QUEDA OKEY. | W278: VISITA_TÉCNICA | X278: SVUZZ269 | Y278: TIPO II | Z278: TERRESTRE | AA278: TORRES GARCIA JENDRY JOSE | AB278: 1 | AC278: 0 | AD278: =IF(W278="SOPORTE_TELEFÓNICO",'BASE LIQUIDACION REDEBAN 2025'!$B$19,IF(W278="ENVÍO",'BASE LIQUIDACION REDEBAN 2025'!$C$2,IF(Y278="TIPO I",'BASE LIQUIDACION REDEBAN 2025'!$C$2,IF(Y278="TIPO II",'BASE LIQUIDACION REDEBAN 2025'!$C$3,IF(Y278="TIPO III",'BASE LIQUIDACION REDEBAN 2025'!$C$4,IF(Y278="TIPO IV",'BASE LIQUIDACION REDEBAN 2025'!$C$5,IF(Z278="AEREO",'BASE LIQUIDACION REDEBAN 2025'!$B$6,'BASE LIQUIDACION REDEBAN 2025'!$C$5))))))) -> 144967.87 | AE278: =IF(OR(W278="SOPORTE_TELEFÓNICO",W278="ENVÍO"),0,IF(Y278="TIPO I",'BASE LIQUIDACION REDEBAN 2025'!$B$10,IF(Y278="TIPO II",'BASE LIQUIDACION REDEBAN 2025'!$B$11,IF(Y278="TIPO III",'BASE LIQUIDACION REDEBAN 2025'!$B$12,'BASE LIQUIDACION REDEBAN 2025'!$B$13)))) -> 140395.63 | AF278: =IF(OR(W278="SOPORTE_TELEFÓNICO",W278="ENVÍO"),AD278,(AD278*AB278+AE278*AC278)) -> 144967.87
A279: MEDELLIN | B279: =VLOOKUP(A279,'CENTRO DE COSTOS'!A:D,4,FALSE) -> JUAN SEBASTIÁN RÍOS CASTRILLÓN | C279: =VLOOKUP(A279,'CENTRO DE COSTOS'!A:D,2,FALSE) -> 0004-0005 | D279: 5088 | E279: 2774645 | F279: 81032 | G279: INCIDENTE | H279: ANTIOQUIA | I279: BELLO | J279: PTM BELLO MISCELANEA SOLUCION | K279: REDEBAN | L279: FO-25-1564197 | M279: 45922.496 | N279: 45923.381 | O279: NO | P279: HARDWARE | Q279: DETERIORO | R279: DATAFONO | U279: CERRADO | V279: 22/09/2025 SE REALIZA VISITA TÉCNICA EN RESPUESTA AL INCIDENTE REPORTADO CON EL DATÁFONO DEL CORRESPONSAL BANCOLOMBIA. EL USUARIO CONFIRMA LA IDENTIDAD DEL TÉCNICO ASIGNADO Y PROCEDE A INFORMAR QUE EL LECTOR DE CÓDIGO DE BARRAS NO ENCIENDE. DURANTE LA VALIDACIÓN, SE DETECTA QUE EL PUERTO USB DEL DATÁFONO —DONDE SE CONECTA EL LECTOR— PRESENTA DAÑOS FÍSICOS QUE IMPIDEN EL FUNCIONAMIENTO DEL PERIFÉRICO. SE REALIZA EL REEMPLAZO DEL EQUIPO POR UNO NUEVO, QUEDANDO EL DATÁFONO OPERATIVO Y EL LECTOR DE BARRAS FUNCIONAL. | W279: VISITA_TÉCNICA | X279: FJZZZ895 | Y279: TIPO I | Z279: TERRESTRE | AA279: MARTINEZ TOVAR OSCAR DAVID | AB279: 1 | AC279: 0 | AD279: =IF(W279="SOPORTE_TELEFÓNICO",'BASE LIQUIDACION REDEBAN 2025'!$B$19,IF(W279="ENVÍO",'BASE LIQUIDACION REDEBAN 2025'!$C$2,IF(Y279="TIPO I",'BASE LIQUIDACION REDEBAN 2025'!$C$2,IF(Y279="TIPO II",'BASE LIQUIDACION REDEBAN 2025'!$C$3,IF(Y279="TIPO III",'BASE LIQUIDACION REDEBAN 2025'!$C$4,IF(Y279="TIPO IV",'BASE LIQUIDACION REDEBAN 2025'!$C$5,IF(Z279="AEREO",'BASE LIQUIDACION REDEBAN 2025'!$B$6,'BASE LIQUIDACION REDEBAN 2025'!$C$5))))))) -> 65960.072 | AE279: =IF(OR(W279="SOPORTE_TELEFÓNICO",W279="ENVÍO"),0,IF(Y279="TIPO I",'BASE LIQUIDACION REDEBAN 2025'!$B$10,IF(Y279="TIPO II",'BASE LIQUIDACION REDEBAN 2025'!$B$11,IF(Y279="TIPO III",'BASE LIQUIDACION REDEBAN 2025'!$B$12,'BASE LIQUIDACION REDEBAN 2025'!$B$13)))) -> 75096.394 | AF279: =IF(OR(W279="SOPORTE_TELEFÓNICO",W279="ENVÍO"),AD279,(AD279*AB279+AE279*AC279)) -> 65960.072
A280: BOGOTA | B280: =VLOOKUP(A280,'CENTRO DE COSTOS'!A:D,4,FALSE) -> WILLIAM ASDRUBAL ROZO ROZO | C280: =VLOOKUP(A280,'CENTRO DE COSTOS'!A:D,2,FALSE) -> 0004-0004 | D280: 11001 | E280: 2774384 | F280: 21499 | G280: INCIDENTE | H280: CUNDINAMARCA | I280: BOGOTA | J280: MULTIPAGAS CARRERA OCTAVA | K280: REDEBAN | L280: FO-25-1563940 | M280: 45922.484 | N280: 45923.428 | O280: NO | P280: HARDWARE | Q280: DETERIORO | R280: DATAFONO | U280: CERRADO | V280: 23/09/2025 SE REALIZA VISITA DE CAMPO ENCONTRADO QUE EQUIPO SE REINICIA Y EL TECLADO ESTÁ NO FUNCIONA BIEN, POR LO ANTERIOR SE CAMBIA EQUIPO PINPAD Y HUB, SE REALIZAN PRUEBAS OK, CUPO OK Y USUARIO OK. | W280: VISITA_TÉCNICA | X280: GB0DZ159 | Y280: TIPO I | Z280: TERRESTRE | AA280: LOZADA ROJAS CHRISTIAN ANDRES | AB280: 1 | AC280: 0 | AD280: =IF(W280="SOPORTE_TELEFÓNICO",'BASE LIQUIDACION REDEBAN 2025'!$B$19,IF(W280="ENVÍO",'BASE LIQUIDACION REDEBAN 2025'!$C$2,IF(Y280="TIPO I",'BASE LIQUIDACION REDEBAN 2025'!$C$2,IF(Y280="TIPO II",'BASE LIQUIDACION REDEBAN 2025'!$C$3,IF(Y280="TIPO III",'BASE LIQUIDACION REDEBAN 2025'!$C$4,IF(Y280="TIPO IV",'BASE LIQUIDACION REDEBAN 2025'!$C$5,IF(Z280="AEREO",'BASE LIQUIDACION REDEBAN 2025'!$B$6,'BASE LIQUIDACION REDEBAN 2025'!$C$5))))))) -> 65960.072 | AE280: =IF(OR(W280="SOPORTE_TELEFÓNICO",W280="ENVÍO"),0,IF(Y280="TIPO I",'BASE LIQUIDACION REDEBAN 2025'!$B$10,IF(Y280="TIPO II",'BASE LIQUIDACION REDEBAN 2025'!$B$11,IF(Y280="TIPO III",'BASE LIQUIDACION REDEBAN 2025'!$B$12,'BASE LIQUIDACION REDEBAN 2025'!$B$13)))) -> 75096.394 | AF280: =IF(OR(W280="SOPORTE_TELEFÓNICO",W280="ENVÍO"),AD280,(AD280*AB280+AE280*AC280)) -> 65960.072
A281: CALI | B281: =VLOOKUP(A281,'CENTRO DE COSTOS'!A:D,4,FALSE) -> DIEGO FERNANDO HENAO CARDONA | C281: =VLOOKUP(A281,'CENTRO DE COSTOS'!A:D,2,FALSE) -> 0004-0003 | D281: 76001 | E281: 2774270 | F281: 59062 | G281: INCIDENTE | H281: VALLE DEL CAUCA | I281: CALI | J281: BARRIO SAN LUIS I CALI 2 | K281: REDEBAN | L281: FO-25-1563944 | M281: 45922.472 | N281: 45923.388 | O281: NO | P281: HARDWARE | Q281: IMPRESION | R281: TAPA IMPRESORA | U281: CERRADO | V281: 23/09/2025 SE LE HACE MANTENIMIENTO AL PORTARROLLOS Y QUEDA FUNCIONANDO CORRECTAMENTE | W281: VISITA_TÉCNICA | X281: MA002221 | Y281: TIPO I | Z281: TERRESTRE | AA281: CUERO RUIZ JHONNY | AB281: 1 | AC281: 0 | AD281: =IF(W281="SOPORTE_TELEFÓNICO",'BASE LIQUIDACION REDEBAN 2025'!$B$19,IF(W281="ENVÍO",'BASE LIQUIDACION REDEBAN 2025'!$C$2,IF(Y281="TIPO I",'BASE LIQUIDACION REDEBAN 2025'!$C$2,IF(Y281="TIPO II",'BASE LIQUIDACION REDEBAN 2025'!$C$3,IF(Y281="TIPO III",'BASE LIQUIDACION REDEBAN 2025'!$C$4,IF(Y281="TIPO IV",'BASE LIQUIDACION REDEBAN 2025'!$C$5,IF(Z281="AEREO",'BASE LIQUIDACION REDEBAN 2025'!$B$6,'BASE LIQUIDACION REDEBAN 2025'!$C$5))))))) -> 65960.072 | AE281: =IF(OR(W281="SOPORTE_TELEFÓNICO",W281="ENVÍO"),0,IF(Y281="TIPO I",'BASE LIQUIDACION REDEBAN 2025'!$B$10,IF(Y281="TIPO II",'BASE LIQUIDACION REDEBAN 2025'!$B$11,IF(Y281="TIPO III",'BASE LIQUIDACION REDEBAN 2025'!$B$12,'BASE LIQUIDACION REDEBAN 2025'!$B$13)))) -> 75096.394 | AF281: =IF(OR(W281="SOPORTE_TELEFÓNICO",W281="ENVÍO"),AD281,(AD281*AB281+AE281*AC281)) -> 65960.072
A282: APARTADO | B282: =VLOOKUP(A282,'CENTRO DE COSTOS'!A:D,4,FALSE) -> JUAN SEBASTIÁN RÍOS CASTRILLÓN | C282: =VLOOKUP(A282,'CENTRO DE COSTOS'!A:D,2,FALSE) -> 0004-0005 | D282: 5045 | E282: 2774264 | F282: 52863 | G282: INCIDENTE | H282: ANTIOQUIA | I282: APARTADO | J282: DISTRICOL ANGELES DEC Y REG JB | K282: REDEBAN | L282: FO-25-1563949 | M282: 45922.472 | N282: 45923.385 | O282: NO | P282: SOFTWARE | Q282: LLT | R282: LLT | U282: CERRADO | V282: 22/09/2025 COMERCIO NO SE ENCUENTRA. SE TRATA DE LLAMAR AL NÚMERO DE CONTACTO Y DICEN QUE ESTOY EQUIVOCADO QUE NO CONOCEN NINGUNA CORRESPONSAL. SE BUSCA EN GOOGLE MAPS LA DIRECCIÓN Y ESO NOS LLEVA A UN LUGAR DONDE NO HAY CORRESPONSALES Y SE LE PREGUNTA A PERSONAS ALEDAÑAR Y DICEN NO CONOCEN ALGÚN CORRESPONSAL O LOCAL CON ESE NOMBRE. SE SUSPENDERÁ ATENCIÓN HASTA QUE EL USUARIO ENTREGUE INFORMACIÓN Y NÚMERO DE CONTACTO PROPIO PARA UNA COMUNICACIÓN EXITOSA. | W282: VISITA_TÉCNICA | X282: NONE | Y282: TIPO I | Z282: TERRESTRE | AA282: SALDARRIAGA MIRANDA SANTIAGO | AB282: 1 | AC282: 0 | AD282: =IF(W282="SOPORTE_TELEFÓNICO",'BASE LIQUIDACION REDEBAN 2025'!$B$19,IF(W282="ENVÍO",'BASE LIQUIDACION REDEBAN 2025'!$C$2,IF(Y282="TIPO I",'BASE LIQUIDACION REDEBAN 2025'!$C$2,IF(Y282="TIPO II",'BASE LIQUIDACION REDEBAN 2025'!$C$3,IF(Y282="TIPO III",'BASE LIQUIDACION REDEBAN 2025'!$C$4,IF(Y282="TIPO IV",'BASE LIQUIDACION REDEBAN 2025'!$C$5,IF(Z282="AEREO",'BASE LIQUIDACION REDEBAN 2025'!$B$6,'BASE LIQUIDACION REDEBAN 2025'!$C$5))))))) -> 65960.072 | AE282: =IF(OR(W282="SOPORTE_TELEFÓNICO",W282="ENVÍO"),0,IF(Y282="TIPO I",'BASE LIQUIDACION REDEBAN 2025'!$B$10,IF(Y282="TIPO II",'BASE LIQUIDACION REDEBAN 2025'!$B$11,IF(Y282="TIPO III",'BASE LIQUIDACION REDEBAN 2025'!$B$12,'BASE LIQUIDACION REDEBAN 2025'!$B$13)))) -> 75096.394 | AF282: =IF(OR(W282="SOPORTE_TELEFÓNICO",W282="ENVÍO"),AD282,(AD282*AB282+AE282*AC282)) -> 65960.072
A283: BOGOTA | B283: =VLOOKUP(A283,'CENTRO DE COSTOS'!A:D,4,FALSE) -> WILLIAM ASDRUBAL ROZO ROZO | C283: =VLOOKUP(A283,'CENTRO DE COSTOS'!A:D,2,FALSE) -> 0004-0004 | D283: 25200 | E283: 2774175 | F283: 68808 | G283: INCIDENTE | H283: CUNDINAMARCA | I283: COGUA | J283: BARRIO CENTRO COGUA 6 | K283: REDEBAN | L283: FO-25-1563953 | M283: 45922.471 | N283: 45923.574 | O283: NO | P283: HARDWARE | Q283: SE REINICIA | R283: DAÑO POS | U283: CERRADO | V283: 23/09/2025 SE REALIZA CAMBIO DE EQUIPO POR CONSTANTE REINICIO DE INSTALA DESK 2600 SERVICIO OPERATIVO PRUEBAS OK TRNA RBM | W283: VISITA_TÉCNICA | X283: AALUZ234 | Y283: TIPO II | Z283: TERRESTRE | AA283: BUSTOS MORA DIEGO MANUEL | AB283: 1 | AC283: 0 | AD283: =IF(W283="SOPORTE_TELEFÓNICO",'BASE LIQUIDACION REDEBAN 2025'!$B$19,IF(W283="ENVÍO",'BASE LIQUIDACION REDEBAN 2025'!$C$2,IF(Y283="TIPO I",'BASE LIQUIDACION REDEBAN 2025'!$C$2,IF(Y283="TIPO II",'BASE LIQUIDACION REDEBAN 2025'!$C$3,IF(Y283="TIPO III",'BASE LIQUIDACION REDEBAN 2025'!$C$4,IF(Y283="TIPO IV",'BASE LIQUIDACION REDEBAN 2025'!$C$5,IF(Z283="AEREO",'BASE LIQUIDACION REDEBAN 2025'!$B$6,'BASE LIQUIDACION REDEBAN 2025'!$C$5))))))) -> 144967.87 | AE283: =IF(OR(W283="SOPORTE_TELEFÓNICO",W283="ENVÍO"),0,IF(Y283="TIPO I",'BASE LIQUIDACION REDEBAN 2025'!$B$10,IF(Y283="TIPO II",'BASE LIQUIDACION REDEBAN 2025'!$B$11,IF(Y283="TIPO III",'BASE LIQUIDACION REDEBAN 2025'!$B$12,'BASE LIQUIDACION REDEBAN 2025'!$B$13)))) -> 140395.63 | AF283: =IF(OR(W283="SOPORTE_TELEFÓNICO",W283="ENVÍO"),AD283,(AD283*AB283+AE283*AC283)) -> 144967.87
A284: APARTADO | B284: =VLOOKUP(A284,'CENTRO DE COSTOS'!A:D,4,FALSE) -> JUAN SEBASTIÁN RÍOS CASTRILLÓN | C284: =VLOOKUP(A284,'CENTRO DE COSTOS'!A:D,2,FALSE) -> 0004-0005 | D284: 5045 | E284: 2774009 | F284: 81348 | G284: INCIDENTE | H284: ANTIOQUIA | I284: APARTADO | J284: DISTRICOL APARTABURGUER | K284: REDEBAN | L284: FO-25-1563594 | M284: 45922.456 | N284: 45922.619 | O284: NO | P284: SOFTWARE | Q284: COMUNICACION | R284: VERIFIQUE PARAMETROS | U284: CERRADO | V284: 22/09/2025 DATÁFONO CON MENSAJE CABLE ETHERNET DESCONECTADO, DE PROCEDE A VALIDAR CONEXIONES Y CONFIGURACIÓN, SE HACE REINICIO DEL EQUIPO Y SE PRUEBA CON UNA CONSULTA DE SALDO Y IMPRIME VERSIÓN SOF, DEJANDO TODO FUNCIONANDO CORRECTAMENTE | W284: VISITA_TÉCNICA | X284: VGZZZ815 | Y284: TIPO I | Z284: TERRESTRE | AA284: SALDARRIAGA MIRANDA SANTIAGO | AB284: 1 | AC284: 0 | AD284: =IF(W284="SOPORTE_TELEFÓNICO",'BASE LIQUIDACION REDEBAN 2025'!$B$19,IF(W284="ENVÍO",'BASE LIQUIDACION REDEBAN 2025'!$C$2,IF(Y284="TIPO I",'BASE LIQUIDACION REDEBAN 2025'!$C$2,IF(Y284="TIPO II",'BASE LIQUIDACION REDEBAN 2025'!$C$3,IF(Y284="TIPO III",'BASE LIQUIDACION REDEBAN 2025'!$C$4,IF(Y284="TIPO IV",'BASE LIQUIDACION REDEBAN 2025'!$C$5,IF(Z284="AEREO",'BASE LIQUIDACION REDEBAN 2025'!$B$6,'BASE LIQUIDACION REDEBAN 2025'!$C$5))))))) -> 65960.072 | AE284: =IF(OR(W284="SOPORTE_TELEFÓNICO",W284="ENVÍO"),0,IF(Y284="TIPO I",'BASE LIQUIDACION REDEBAN 2025'!$B$10,IF(Y284="TIPO II",'BASE LIQUIDACION REDEBAN 2025'!$B$11,IF(Y284="TIPO III",'BASE LIQUIDACION REDEBAN 2025'!$B$12,'BASE LIQUIDACION REDEBAN 2025'!$B$13)))) -> 75096.394 | AF284: =IF(OR(W284="SOPORTE_TELEFÓNICO",W284="ENVÍO"),AD284,(AD284*AB284+AE284*AC284)) -> 65960.072
A285: CALI | B285: =VLOOKUP(A285,'CENTRO DE COSTOS'!A:D,4,FALSE) -> DIEGO FERNANDO HENAO CARDONA | C285: =VLOOKUP(A285,'CENTRO DE COSTOS'!A:D,2,FALSE) -> 0004-0003 | D285: 19548 | E285: 2773941 | F285: 10639 | G285: INCIDENTE | H285: CAUCA | I285: PIENDAMO | J285: PIENDAMO II - CAUCA | K285: REDEBAN | L285: FO-25-1563959 | M285: 45922.454 | N285: 45924.638 | O285: NO | P285: HARDWARE | Q285: IMPRESION | R285: TAPA IMPRESORA | U285: CERRADO | V285: 24/09/2025 SE INGRESA EQUIPO CON TAPA IMPRESORA MALA SE PROCEDE A CAMBIAR SE HACEN PRUEBAS OK TELECARGA DRNA | W285: VISITA_TÉCNICA | X285: 11119861 | Y285: TIPO III | Z285: TERRESTRE | AA285: GIMBUEL LASSO LUIS GERMAN | AB285: 1 | AC285: 0 | AD285: =IF(W285="SOPORTE_TELEFÓNICO",'BASE LIQUIDACION REDEBAN 2025'!$B$19,IF(W285="ENVÍO",'BASE LIQUIDACION REDEBAN 2025'!$C$2,IF(Y285="TIPO I",'BASE LIQUIDACION REDEBAN 2025'!$C$2,IF(Y285="TIPO II",'BASE LIQUIDACION REDEBAN 2025'!$C$3,IF(Y285="TIPO III",'BASE LIQUIDACION REDEBAN 2025'!$C$4,IF(Y285="TIPO IV",'BASE LIQUIDACION REDEBAN 2025'!$C$5,IF(Z285="AEREO",'BASE LIQUIDACION REDEBAN 2025'!$B$6,'BASE LIQUIDACION REDEBAN 2025'!$C$5))))))) -> 275728.78 | AE285: =IF(OR(W285="SOPORTE_TELEFÓNICO",W285="ENVÍO"),0,IF(Y285="TIPO I",'BASE LIQUIDACION REDEBAN 2025'!$B$10,IF(Y285="TIPO II",'BASE LIQUIDACION REDEBAN 2025'!$B$11,IF(Y285="TIPO III",'BASE LIQUIDACION REDEBAN 2025'!$B$12,'BASE LIQUIDACION REDEBAN 2025'!$B$13)))) -> 196536.53 | AF285: =IF(OR(W285="SOPORTE_TELEFÓNICO",W285="ENVÍO"),AD285,(AD285*AB285+AE285*AC285)) -> 275728.78
A286: BUCARAMANGA | B286: =VLOOKUP(A286,'CENTRO DE COSTOS'!A:D,4,FALSE) -> MIGUEL JULIÁN HERNÁNDEZ GUARÍN | C286: =VLOOKUP(A286,'CENTRO DE COSTOS'!A:D,2,FALSE) -> 0004-0008 | D286: 81001 | E286: 2773915 | F286: 51621 | G286: INCIDENTE | H286: ARAUCA | I286: ARAUCA | J286: BARRIO FUNDADORES ARAUCA | K286: REDEBAN | L286: FO-25-1563966 | M286: 45922.449 | N286: 45924.571 | O286: NO | P286: HARDWARE | Q286: TECLADO | R286: DAÑO POS | U286: CERRADO | V286: 24/09/2025 SE CAMBIA EQUIPO DEBIDO TECLADO BORROSO, SE CAMBIA LECTOR DE BARRAS DEBIDO CABLE DE DATOS DETERIORADO , SE REALIZA INYECCIÓN DE SISTEMA Y VERSIÓN INICIALIZADA OK PRUEBAS OK CUBRE CLAVE OK | W286: VISITA_TÉCNICA | X286: TR08Z510 | Y286: TIPO IV ESPECIAL | Z286: AEREO | AA286: HERRERA LUQUE SAUL JAVIER | AB286: 1 | AC286: 0 | AD286: =IF(W286="SOPORTE_TELEFÓNICO",'BASE LIQUIDACION REDEBAN 2025'!$B$19,IF(W286="ENVÍO",'BASE LIQUIDACION REDEBAN 2025'!$C$2,IF(Y286="TIPO I",'BASE LIQUIDACION REDEBAN 2025'!$C$2,IF(Y286="TIPO II",'BASE LIQUIDACION REDEBAN 2025'!$C$3,IF(Y286="TIPO III",'BASE LIQUIDACION REDEBAN 2025'!$C$4,IF(Y286="TIPO IV",'BASE LIQUIDACION REDEBAN 2025'!$C$5,IF(Z286="AEREO",'BASE LIQUIDACION REDEBAN 2025'!$B$6,'BASE LIQUIDACION REDEBAN 2025'!$C$5))))))) -> 988462.96 | AE286: =IF(OR(W286="SOPORTE_TELEFÓNICO",W286="ENVÍO"),0,IF(Y286="TIPO I",'BASE LIQUIDACION REDEBAN 2025'!$B$10,IF(Y286="TIPO II",'BASE LIQUIDACION REDEBAN 2025'!$B$11,IF(Y286="TIPO III",'BASE LIQUIDACION REDEBAN 2025'!$B$12,'BASE LIQUIDACION REDEBAN 2025'!$B$13)))) -> 196536.53 | AF286: =IF(OR(W286="SOPORTE_TELEFÓNICO",W286="ENVÍO"),AD286,(AD286*AB286+AE286*AC286)) -> 988462.96
A287: BOGOTA | B287: =VLOOKUP(A287,'CENTRO DE COSTOS'!A:D,4,FALSE) -> WILLIAM ASDRUBAL ROZO ROZO | C287: =VLOOKUP(A287,'CENTRO DE COSTOS'!A:D,2,FALSE) -> 0004-0004 | D287: 97001 | E287: 2773574 | F287: 22566 | G287: INCIDENTE | H287: VAUPES | I287: MITU | J287: CENTRO MITU II VAUPES | K287: REDEBAN | L287: FO-25-1563972 | M287: 45922.438 | N287: 45922.501 | O287: NO | P287: HARDWARE | Q287: IMPRESION | R287: DAÑO POS | U287: CERRADO | V287: 22/09/2025 EN COMUNICACION CON LA SEÑORA CARMEN SANDOVAL AL NUMERO 3132610860 INDICA QUE EL DATAFONO TENIA INCONVENIENTES AL IMPRIMIR PERO YA EL CB ESTA FUNCIONANDO BIEN Y NO REQUIERE VISITA TECNICA, SE PROCEDE A CERRAR ESTE CASO | W287: SOPORTE_TELEFÓNICO | X287: 0 | Y287: TIPO IV ESPECIAL | Z287: AEREO | AA287: CONTRERAS ROSSI LITZY YULIETH | AB287: 0 | AC287: 0 | AD287: =IF(W287="SOPORTE_TELEFÓNICO",'BASE LIQUIDACION REDEBAN 2025'!$B$19,IF(W287="ENVÍO",'BASE LIQUIDACION REDEBAN 2025'!$C$2,IF(Y287="TIPO I",'BASE LIQUIDACION REDEBAN 2025'!$C$2,IF(Y287="TIPO II",'BASE LIQUIDACION REDEBAN 2025'!$C$3,IF(Y287="TIPO III",'BASE LIQUIDACION REDEBAN 2025'!$C$4,IF(Y287="TIPO IV",'BASE LIQUIDACION REDEBAN 2025'!$C$5,IF(Z287="AEREO",'BASE LIQUIDACION REDEBAN 2025'!$B$6,'BASE LIQUIDACION REDEBAN 2025'!$C$5))))))) -> 41241.08 | AE287: =IF(OR(W287="SOPORTE_TELEFÓNICO",W287="ENVÍO"),0,IF(Y287="TIPO I",'BASE LIQUIDACION REDEBAN 2025'!$B$10,IF(Y287="TIPO II",'BASE LIQUIDACION REDEBAN 2025'!$B$11,IF(Y287="TIPO III",'BASE LIQUIDACION REDEBAN 2025'!$B$12,'BASE LIQUIDACION REDEBAN 2025'!$B$13)))) -> 0 | AF287: =IF(OR(W287="SOPORTE_TELEFÓNICO",W287="ENVÍO"),AD287,(AD287*AB287+AE287*AC287)) -> 41241.08
... A342: CUCUTA | B342: =VLOOKUP(A342,'CENTRO DE COSTOS'!A:D,4,FALSE) -> MIGUEL JULIÁN HERNÁNDEZ GUARÍN | C342: =VLOOKUP(A342,'CENTRO DE COSTOS'!A:D,2,FALSE) -> 0004-0008 | D342: 54250 | E342: 2769292 | F342: 30937 | G342: INCIDENTE | H342: NORTE DE SANTANDER | I342: EL TARRA | J342: COMCARD TARRA KEINER | K342: REDEBAN | L342: FO-25-1558143 | M342: 45920.39 | N342: 45924.695 | O342: NO | P342: HARDWARE | Q342: ALERT IRRUPTION | R342: ALERT IRRUPTION | U342: CERRADO | V342: 24/09/2025 SE REALIZA CAMBIO DE DATAFONO POR DAÑO ALERT RUTION, SE HACEN PRUEBAS EXITOSA, CB OPERATIVO. | W342: VISITA_TÉCNICA | X342: BVZZZ217 | Y342: TIPO IV | Z342: TERRESTRE | AA342: NARANJO AFANADOR RUBEN JESUS | AB342: 1 | AC342: 0 | AD342: =IF(W342="SOPORTE_TELEFÓNICO",'BASE LIQUIDACION REDEBAN 2025'!$B$19,IF(W342="ENVÍO",'BASE LIQUIDACION REDEBAN 2025'!$C$2,IF(Y342="TIPO I",'BASE LIQUIDACION REDEBAN 2025'!$C$2,IF(Y342="TIPO II",'BASE LIQUIDACION REDEBAN 2025'!$C$3,IF(Y342="TIPO III",'BASE LIQUIDACION REDEBAN 2025'!$C$4,IF(Y342="TIPO IV",'BASE LIQUIDACION REDEBAN 2025'!$C$5,IF(Z342="AEREO",'BASE LIQUIDACION REDEBAN 2025'!$B$6,'BASE LIQUIDACION REDEBAN 2025'!$C$5))))))) -> 479588.88 | AE342: =IF(OR(W342="SOPORTE_TELEFÓNICO",W342="ENVÍO"),0,IF(Y342="TIPO I",'BASE LIQUIDACION REDEBAN 2025'!$B$10,IF(Y342="TIPO II",'BASE LIQUIDACION REDEBAN 2025'!$B$11,IF(Y342="TIPO III",'BASE LIQUIDACION REDEBAN 2025'!$B$12,'BASE LIQUIDACION REDEBAN 2025'!$B$13)))) -> 196536.53 | AF342: =IF(OR(W342="SOPORTE_TELEFÓNICO",W342="ENVÍO"),AD342,(AD342*AB342+AE342*AC342)) -> 479588.88
A343: BOGOTA | B343: =VLOOKUP(A343,'CENTRO DE COSTOS'!A:D,4,FALSE) -> WILLIAM ASDRUBAL ROZO ROZO | C343: =VLOOKUP(A343,'CENTRO DE COSTOS'!A:D,2,FALSE) -> 0004-0004 | D343: 11001 | E343: TA-25-1128962 | F343: 81493 | G343: INCIDENTE | H343: CUNDINAMARCA | I343: BOGOTA | J343: DISTRICOL TODO EN UNO | K343: REDEBAN | L343: FO-25-1557858 | M343: 45920.363 | N343: 45920.581 | O343: NO | P343: HARDWARE | Q343: HUB | R343: DAÑO HUB | U343: CERRADO | V343: 20/09/2025 SE REALIZA CAMBIO DE HUB, SE REALIZA PRUEBAS CON PINPAD BACKUP, CABLE DE PINPAD BACKUP, SE EVIDENCIA FALLA DE HUB, PRUEBAS OK, CB OPERATIVO. | W343: VISITA_TÉCNICA | X343: FSZZZ900 | Y343: TIPO I | Z343: TERRESTRE | AA343: MURCIA HERNANDEZ HARVEY IGNACIO | AB343: 1 | AC343: 0 | AD343: =IF(W343="SOPORTE_TELEFÓNICO",'BASE LIQUIDACION REDEBAN 2025'!$B$19,IF(W343="ENVÍO",'BASE LIQUIDACION REDEBAN 2025'!$C$2,IF(Y343="TIPO I",'BASE LIQUIDACION REDEBAN 2025'!$C$2,IF(Y343="TIPO II",'BASE LIQUIDACION REDEBAN 2025'!$C$3,IF(Y343="TIPO III",'BASE LIQUIDACION REDEBAN 2025'!$C$4,IF(Y343="TIPO IV",'BASE LIQUIDACION REDEBAN 2025'!$C$5,IF(Z343="AEREO",'BASE LIQUIDACION REDEBAN 2025'!$B$6,'BASE LIQUIDACION REDEBAN 2025'!$C$5))))))) -> 65960.072 | AE343: =IF(OR(W343="SOPORTE_TELEFÓNICO",W343="ENVÍO"),0,IF(Y343="TIPO I",'BASE LIQUIDACION REDEBAN 2025'!$B$10,IF(Y343="TIPO II",'BASE LIQUIDACION REDEBAN 2025'!$B$11,IF(Y343="TIPO III",'BASE LIQUIDACION REDEBAN 2025'!$B$12,'BASE LIQUIDACION REDEBAN 2025'!$B$13)))) -> 75096.394 | AF343: =IF(OR(W343="SOPORTE_TELEFÓNICO",W343="ENVÍO"),AD343,(AD343*AB343+AE343*AC343)) -> 65960.072
A344: BARRANQUILLA | B344: =VLOOKUP(A344,'CENTRO DE COSTOS'!A:D,4,FALSE) -> JOSE MAURICIO HERNANDEZ ROJAS | C344: =VLOOKUP(A344,'CENTRO DE COSTOS'!A:D,2,FALSE) -> 0004-0001 | D344: 8001 | E344: 2769441 | F344: 21410 | G344: INCIDENTE | H344: ATLANTICO | I344: BARRANQUILLA | J344: PAGAFACIL PASEO BOLIVAR | K344: REDEBAN | L344: FO-25-1557939 | M344: 45920.37 | N344: 45922.48 | O344: NO | P344: HARDWARE | Q344: HUB | R344: SE REINICIA | U344: CERRADO | V344: 22/09/2025 SE REALIZA VISITA TÉCNICA, SE CAMBIA EL HUB, SE REALIZAN PRUEBAS EXITOSAS, EQUIPO FUNCIONA CORRECTAMENTE, CB QUEDA OPERATIVO. | W344: VISITA_TÉCNICA | X344: AALZZ255 | Y344: TIPO I | Z344: TERRESTRE | AA344: DE AGUAS MUÑOZ DAVID JOSE | AB344: 1 | AC344: 0 | AD344: =IF(W344="SOPORTE_TELEFÓNICO",'BASE LIQUIDACION REDEBAN 2025'!$B$19,IF(W344="ENVÍO",'BASE LIQUIDACION REDEBAN 2025'!$C$2,IF(Y344="TIPO I",'BASE LIQUIDACION REDEBAN 2025'!$C$2,IF(Y344="TIPO II",'BASE LIQUIDACION REDEBAN 2025'!$C$3,IF(Y344="TIPO III",'BASE LIQUIDACION REDEBAN 2025'!$C$4,IF(Y344="TIPO IV",'BASE LIQUIDACION REDEBAN 2025'!$C$5,IF(Z344="AEREO",'BASE LIQUIDACION REDEBAN 2025'!$B$6,'BASE LIQUIDACION REDEBAN 2025'!$C$5))))))) -> 65960.072 | AE344: =IF(OR(W344="SOPORTE_TELEFÓNICO",W344="ENVÍO"),0,IF(Y344="TIPO I",'BASE LIQUIDACION REDEBAN 2025'!$B$10,IF(Y344="TIPO II",'BASE LIQUIDACION REDEBAN 2025'!$B$11,IF(Y344="TIPO III",'BASE LIQUIDACION REDEBAN 2025'!$B$12,'BASE LIQUIDACION REDEBAN 2025'!$B$13)))) -> 75096.394 | AF344: =IF(OR(W344="SOPORTE_TELEFÓNICO",W344="ENVÍO"),AD344,(AD344*AB344+AE344*AC344)) -> 65960.072
A345: VILLAVICENCIO | B345: =VLOOKUP(A345,'CENTRO DE COSTOS'!A:D,4,FALSE) -> KEVIN ALEXIS CORZO BUSTOS | C345: =VLOOKUP(A345,'CENTRO DE COSTOS'!A:D,2,FALSE) -> 0004-0007 | D345: 50001 | E345: 2769360 | F345: 20513 | G345: INCIDENTE | H345: META | I345: VILLAVICENCIO | J345: EXXON BARRIO CAMOA II VILLAVIC | K345: REDEBAN | L345: FO-25-1557942 | M345: 45920.369 | N345: 45920.583 | O345: NO | P345: HARDWARE | Q345: COMUNICACION | R345: MENSAJE CABLE DE RED DESCONECTADO | U345: CERRADO | V345: 20/09/2025 SE CAMBIA CABLE MAGIC BOX | W345: VISITA_TÉCNICA | X345: AAAAS010 | Y345: TIPO I | Z345: TERRESTRE | AA345: PEDREROS CONTRERAS MICHAEL STEVENS | AB345: 1 | AC345: 0 | AD345: =IF(W345="SOPORTE_TELEFÓNICO",'BASE LIQUIDACION REDEBAN 2025'!$B$19,IF(W345="ENVÍO",'BASE LIQUIDACION REDEBAN 2025'!$C$2,IF(Y345="TIPO I",'BASE LIQUIDACION REDEBAN 2025'!$C$2,IF(Y345="TIPO II",'BASE LIQUIDACION REDEBAN 2025'!$C$3,IF(Y345="TIPO III",'BASE LIQUIDACION REDEBAN 2025'!$C$4,IF(Y345="TIPO IV",'BASE LIQUIDACION REDEBAN 2025'!$C$5,IF(Z345="AEREO",'BASE LIQUIDACION REDEBAN 2025'!$B$6,'BASE LIQUIDACION REDEBAN 2025'!$C$5))))))) -> 65960.072 | AE345: =IF(OR(W345="SOPORTE_TELEFÓNICO",W345="ENVÍO"),0,IF(Y345="TIPO I",'BASE LIQUIDACION REDEBAN 2025'!$B$10,IF(Y345="TIPO II",'BASE LIQUIDACION REDEBAN 2025'!$B$11,IF(Y345="TIPO III",'BASE LIQUIDACION REDEBAN 2025'!$B$12,'BASE LIQUIDACION REDEBAN 2025'!$B$13)))) -> 75096.394 | AF345: =IF(OR(W345="SOPORTE_TELEFÓNICO",W345="ENVÍO"),AD345,(AD345*AB345+AE345*AC345)) -> 65960.072
A346: CUCUTA | B346: =VLOOKUP(A346,'CENTRO DE COSTOS'!A:D,4,FALSE) -> MIGUEL JULIÁN HERNÁNDEZ GUARÍN | C346: =VLOOKUP(A346,'CENTRO DE COSTOS'!A:D,2,FALSE) -> 0004-0008 | D346: 54001 | E346: 2769437 | F346: 79069 | G346: INCIDENTE | H346: NORTE DE SANTANDER | I346: CUCUTA | J346: BARRIO GUAIMARAL CUCUTA 12 | K346: REDEBAN | L346: FO-25-1557948 | M346: 45920.367 | N346: 45920.585 | O346: NO | P346: SOFTWARE | Q346: ACTUALIZACION | R346: VERSION CARGA SO VR | U346: CERRADO | V346: 20/09/2025 SE REALIZA MANTENIMIENTO, PRUEBAS Y CIERRES OK | W346: VISITA_TÉCNICA | X346: SASZZ644 | Y346: TIPO I | Z346: TERRESTRE | AA346: DURAN ACOSTA FRANK YONNY | AB346: 1 | AC346: 0 | AD346: =IF(W346="SOPORTE_TELEFÓNICO",'BASE LIQUIDACION REDEBAN 2025'!$B$19,IF(W346="ENVÍO",'BASE LIQUIDACION REDEBAN 2025'!$C$2,IF(Y346="TIPO I",'BASE LIQUIDACION REDEBAN 2025'!$C$2,IF(Y346="TIPO II",'BASE LIQUIDACION REDEBAN 2025'!$C$3,IF(Y346="TIPO III",'BASE LIQUIDACION REDEBAN 2025'!$C$4,IF(Y346="TIPO IV",'BASE LIQUIDACION REDEBAN 2025'!$C$5,IF(Z346="AEREO",'BASE LIQUIDACION REDEBAN 2025'!$B$6,'BASE LIQUIDACION REDEBAN 2025'!$C$5))))))) -> 65960.072 | AE346: =IF(OR(W346="SOPORTE_TELEFÓNICO",W346="ENVÍO"),0,IF(Y346="TIPO I",'BASE LIQUIDACION REDEBAN 2025'!$B$10,IF(Y346="TIPO II",'BASE LIQUIDACION REDEBAN 2025'!$B$11,IF(Y346="TIPO III",'BASE LIQUIDACION REDEBAN 2025'!$B$12,'BASE LIQUIDACION REDEBAN 2025'!$B$13)))) -> 75096.394 | AF346: =IF(OR(W346="SOPORTE_TELEFÓNICO",W346="ENVÍO"),AD346,(AD346*AB346+AE346*AC346)) -> 65960.072
A347: MEDELLIN | B347: =VLOOKUP(A347,'CENTRO DE COSTOS'!A:D,4,FALSE) -> JUAN SEBASTIÁN RÍOS CASTRILLÓN | C347: =VLOOKUP(A347,'CENTRO DE COSTOS'!A:D,2,FALSE) -> 0004-0005 | D347: 5282 | E347: 2768780 | F347: 35480 | G347: INCIDENTE | H347: ANTIOQUIA | I347: FREDONIA | J347: DISTRICOL CARNES Y CHORIZOS EL | K347: REDEBAN | L347: FO-25-1557610 | M347: 45920.333 | N347: 45922.488 | O347: NO | P347: HARDWARE | Q347: IMPRESION | R347: DAÑO POS | U347: CERRADO | V347: 22/09/2025 SE REALIZA CAMBIO DE EQUIPO YA QUE PRESENTA DEMASIADA LENTITUD EN LA IMPRESIÓN Y FALTA INFORMACIÓN EN TIRILLAS | W347: VISITA_TÉCNICA | X347: GZ000717 | Y347: TIPO II | Z347: TERRESTRE | AA347: HERNANDEZ CHAVARRIA JUAN CAMILO | AB347: 1 | AC347: 0 | AD347: =IF(W347="SOPORTE_TELEFÓNICO",'BASE LIQUIDACION REDEBAN 2025'!$B$19,IF(W347="ENVÍO",'BASE LIQUIDACION REDEBAN 2025'!$C$2,IF(Y347="TIPO I",'BASE LIQUIDACION REDEBAN 2025'!$C$2,IF(Y347="TIPO II",'BASE LIQUIDACION REDEBAN 2025'!$C$3,IF(Y347="TIPO III",'BASE LIQUIDACION REDEBAN 2025'!$C$4,IF(Y347="TIPO IV",'BASE LIQUIDACION REDEBAN 2025'!$C$5,IF(Z347="AEREO",'BASE LIQUIDACION REDEBAN 2025'!$B$6,'BASE LIQUIDACION REDEBAN 2025'!$C$5))))))) -> 144967.87 | AE347: =IF(OR(W347="SOPORTE_TELEFÓNICO",W347="ENVÍO"),0,IF(Y347="TIPO I",'BASE LIQUIDACION REDEBAN 2025'!$B$10,IF(Y347="TIPO II",'BASE LIQUIDACION REDEBAN 2025'!$B$11,IF(Y347="TIPO III",'BASE LIQUIDACION REDEBAN 2025'!$B$12,'BASE LIQUIDACION REDEBAN 2025'!$B$13)))) -> 140395.63 | AF347: =IF(OR(W347="SOPORTE_TELEFÓNICO",W347="ENVÍO"),AD347,(AD347*AB347+AE347*AC347)) -> 144967.87
A348: BUCARAMANGA | B348: =VLOOKUP(A348,'CENTRO DE COSTOS'!A:D,4,FALSE) -> MIGUEL JULIÁN HERNÁNDEZ GUARÍN | C348: =VLOOKUP(A348,'CENTRO DE COSTOS'!A:D,2,FALSE) -> 0004-0008 | D348: 68276 | E348: 2768756 | F348: 46777 | G348: INCIDENTE | H348: SANTANDER | I348: FLORIDABLANCA | J348: DISTRICOL MULTISERVICIOS R B | K348: REDEBAN | L348: FO-25-1557613 | M348: 45920.333 | N348: 45920.58 | O348: NO | P348: SOFTWARE | Q348: CIERRE | R348: CIERRE NO HABILITADO | U348: CERRADO | V348: 20/09/2025 SE REALIZA CONFIGURACIÓN DE CLAVE SUPERVISOR, SE REALIZA CIERRES Y DUPLICADO ÉXITO, DATÁFONO OPERATIVO. | W348: VISITA_TÉCNICA | X348: 9C00B083 | Y348: TIPO I | Z348: TERRESTRE | AA348: MARTINEZ FLOREZ DONIS ALBERTO | AB348: 1 | AC348: 0 | AD348: =IF(W348="SOPORTE_TELEFÓNICO",'BASE LIQUIDACION REDEBAN 2025'!$B$19,IF(W348="ENVÍO",'BASE LIQUIDACION REDEBAN 2025'!$C$2,IF(Y348="TIPO I",'BASE LIQUIDACION REDEBAN 2025'!$C$2,IF(Y348="TIPO II",'BASE LIQUIDACION REDEBAN 2025'!$C$3,IF(Y348="TIPO III",'BASE LIQUIDACION REDEBAN 2025'!$C$4,IF(Y348="TIPO IV",'BASE LIQUIDACION REDEBAN 2025'!$C$5,IF(Z348="AEREO",'BASE LIQUIDACION REDEBAN 2025'!$B$6,'BASE LIQUIDACION REDEBAN 2025'!$C$5))))))) -> 65960.072 | AE348: =IF(OR(W348="SOPORTE_TELEFÓNICO",W348="ENVÍO"),0,IF(Y348="TIPO I",'BASE LIQUIDACION REDEBAN 2025'!$B$10,IF(Y348="TIPO II",'BASE LIQUIDACION REDEBAN 2025'!$B$11,IF(Y348="TIPO III",'BASE LIQUIDACION REDEBAN 2025'!$B$12,'BASE LIQUIDACION REDEBAN 2025'!$B$13)))) -> 75096.394 | AF348: =IF(OR(W348="SOPORTE_TELEFÓNICO",W348="ENVÍO"),AD348,(AD348*AB348+AE348*AC348)) -> 65960.072
A349: IBAGUE | B349: =VLOOKUP(A349,'CENTRO DE COSTOS'!A:D,4,FALSE) -> KEVIN ALEXIS CORZO BUSTOS | C349: =VLOOKUP(A349,'CENTRO DE COSTOS'!A:D,2,FALSE) -> 0004-0007 | D349: 73001 | E349: 2768641 | F349: 81328 | G349: INCIDENTE | H349: TOLIMA | I349: IBAGUE | J349: PTM IBAGUE VARIEDADES Y ACCESO | K349: REDEBAN | L349: FO-25-1557323 | M349: 45920.333 | N349: 45920.567 | O349: NO | P349: HARDWARE | Q349: IMPRESION | R349: NO IMPRIME UNO O VARIOS CARACTERES | U349: CERRADO | V349: 20/09/2025 SE REALIZA CAMBIO DE EQUIPO " NO IMPRIME SOLO LA MITAD DEL BAUCHER" TRANSACCIONES DE PRUEBA O.K | W349: VISITA_TÉCNICA | X349: SMZZZ293 | Y349: TIPO I | Z349: TERRESTRE | AA349: GUTIERREZ CAMILO ANDRES | AB349: 1 | AC349: 0 | AD349: =IF(W349="SOPORTE_TELEFÓNICO",'BASE LIQUIDACION REDEBAN 2025'!$B$19,IF(W349="ENVÍO",'BASE LIQUIDACION REDEBAN 2025'!$C$2,IF(Y349="TIPO I",'BASE LIQUIDACION REDEBAN 2025'!$C$2,IF(Y349="TIPO II",'BASE LIQUIDACION REDEBAN 2025'!$C$3,IF(Y349="TIPO III",'BASE LIQUIDACION REDEBAN 2025'!$C$4,IF(Y349="TIPO IV",'BASE LIQUIDACION REDEBAN 2025'!$C$5,IF(Z349="AEREO",'BASE LIQUIDACION REDEBAN 2025'!$B$6,'BASE LIQUIDACION REDEBAN 2025'!$C$5))))))) -> 65960.072 | AE349: =IF(OR(W349="SOPORTE_TELEFÓNICO",W349="ENVÍO"),0,IF(Y349="TIPO I",'BASE LIQUIDACION REDEBAN 2025'!$B$10,IF(Y349="TIPO II",'BASE LIQUIDACION REDEBAN 2025'!$B$11,IF(Y349="TIPO III",'BASE LIQUIDACION REDEBAN 2025'!$B$12,'BASE LIQUIDACION REDEBAN 2025'!$B$13)))) -> 75096.394 | AF349: =IF(OR(W349="SOPORTE_TELEFÓNICO",W349="ENVÍO"),AD349,(AD349*AB349+AE349*AC349)) -> 65960.072
A350: MEDELLIN | B350: =VLOOKUP(A350,'CENTRO DE COSTOS'!A:D,4,FALSE) -> JUAN SEBASTIÁN RÍOS CASTRILLÓN | C350: =VLOOKUP(A350,'CENTRO DE COSTOS'!A:D,2,FALSE) -> 0004-0005 | D350: 5001 | E350: 2768737 | F350: 78141 | G350: INCIDENTE | H350: ANTIOQUIA | I350: MEDELLIN | J350: PTM MEDELLIN CENTRO DE COPIADO | K350: REDEBAN | L350: FO-25-1557339 | M350: 45920.333 | N350: 45920.573 | O350: NO | P350: SOFTWARE | Q350: ACTUALIZACION | R350: VERSION CARGA SO VR | U350: CERRADO | V350: 20/09/2025 SE REALIZA FORMATEO DE SO Y VR POR CIERRE SATURADO PRUEBAS OK NO TELECARGA | W350: VISITA_TÉCNICA | X350: LMOZZ292 | Y350: TIPO I | Z350: TERRESTRE | AA350: PAREJA ECHAVARRIA JHON DAVID | AB350: 1 | AC350: 0 | AD350: =IF(W350="SOPORTE_TELEFÓNICO",'BASE LIQUIDACION REDEBAN 2025'!$B$19,IF(W350="ENVÍO",'BASE LIQUIDACION REDEBAN 2025'!$C$2,IF(Y350="TIPO I",'BASE LIQUIDACION REDEBAN 2025'!$C$2,IF(Y350="TIPO II",'BASE LIQUIDACION REDEBAN 2025'!$C$3,IF(Y350="TIPO III",'BASE LIQUIDACION REDEBAN 2025'!$C$4,IF(Y350="TIPO IV",'BASE LIQUIDACION REDEBAN 2025'!$C$5,IF(Z350="AEREO",'BASE LIQUIDACION REDEBAN 2025'!$B$6,'BASE LIQUIDACION REDEBAN 2025'!$C$5))))))) -> 65960.072 | AE350: =IF(OR(W350="SOPORTE_TELEFÓNICO",W350="ENVÍO"),0,IF(Y350="TIPO I",'BASE LIQUIDACION REDEBAN 2025'!$B$10,IF(Y350="TIPO II",'BASE LIQUIDACION REDEBAN 2025'!$B$11,IF(Y350="TIPO III",'BASE LIQUIDACION REDEBAN 2025'!$B$12,'BASE LIQUIDACION REDEBAN 2025'!$B$13)))) -> 75096.394 | AF350: =IF(OR(W350="SOPORTE_TELEFÓNICO",W350="ENVÍO"),AD350,(AD350*AB350+AE350*AC350)) -> 65960.072
A351: VALLEDUPAR | B351: =VLOOKUP(A351,'CENTRO DE COSTOS'!A:D,4,FALSE) -> JOSE MAURICIO HERNANDEZ ROJAS | C351: =VLOOKUP(A351,'CENTRO DE COSTOS'!A:D,2,FALSE) -> 0004-0001 | D351: 20550 | E351: 2768639 | F351: 70051 | G351: INCIDENTE | H351: CESAR | I351: PELAYA | J351: BARRIO LAS FLORES PELAYA | K351: REDEBAN | L351: FO-25-1557342 | M351: 45920.333 | N351: 45922.415 | O351: NO | P351: HARDWARE | Q351: IMPRESION | R351: NO AVANZA PAPEL | U351: CERRADO | V351: 22/09/2025 BUENOS DÍAS SE EVIDENCIA QUE EL DATAFONO IMPRIME FORZADO Y A VECES NO AVANZA EL PAPEL, SE HACE CAMBIO DE EQUIPO Y SE HACEN PRUEBAS DE TRANSACCIONES. TODO OK | W351: VISITA_TÉCNICA | X351: A30CZ921 | Y351: TIPO IV | Z351: TERRESTRE | AA351: BENITEZ CARVAJAL ALVARO JAVIER | AB351: 1 | AC351: 0 | AD351: =IF(W351="SOPORTE_TELEFÓNICO",'BASE LIQUIDACION REDEBAN 2025'!$B$19,IF(W351="ENVÍO",'BASE LIQUIDACION REDEBAN 2025'!$C$2,IF(Y351="TIPO I",'BASE LIQUIDACION REDEBAN 2025'!$C$2,IF(Y351="TIPO II",'BASE LIQUIDACION REDEBAN 2025'!$C$3,IF(Y351="TIPO III",'BASE LIQUIDACION REDEBAN 2025'!$C$4,IF(Y351="TIPO IV",'BASE LIQUIDACION REDEBAN 2025'!$C$5,IF(Z351="AEREO",'BASE LIQUIDACION REDEBAN 2025'!$B$6,'BASE LIQUIDACION REDEBAN 2025'!$C$5))))))) -> 479588.88 | AE351: =IF(OR(W351="SOPORTE_TELEFÓNICO",W351="ENVÍO"),0,IF(Y351="TIPO I",'BASE LIQUIDACION REDEBAN 2025'!$B$10,IF(Y351="TIPO II",'BASE LIQUIDACION REDEBAN 2025'!$B$11,IF(Y351="TIPO III",'BASE LIQUIDACION REDEBAN 2025'!$B$12,'BASE LIQUIDACION REDEBAN 2025'!$B$13)))) -> 196536.53 | AF351: =IF(OR(W351="SOPORTE_TELEFÓNICO",W351="ENVÍO"),AD351,(AD351*AB351+AE351*AC351)) -> 479588.88
A352: MEDELLIN | B352: =VLOOKUP(A352,'CENTRO DE COSTOS'!A:D,4,FALSE) -> JUAN SEBASTIÁN RÍOS CASTRILLÓN | C352: =VLOOKUP(A352,'CENTRO DE COSTOS'!A:D,2,FALSE) -> 0004-0005 | D352: 5411 | E352: 2768587 | F352: 41280 | G352: INCIDENTE | H352: ANTIOQUIA | I352: LIBORINA | J352: BARRIO PARQUE PRINCIPAL LOBORI | K352: REDEBAN | L352: FO-25-1557299 | M352: 45920.333 | N352: 45922.761 | O352: NO | P352: HARDWARE | Q352: IMPRESION | R352: NO IMPRIME UNO O VARIOS CARACTERES | U352: CERRADO | V352: 22/09/2025 SE CAMBIA DATÁFONO POR DAÑO EN IMPRESORA | W352: VISITA_TÉCNICA | X352: AB0PZ994 | Y352: TIPO III | Z352: TERRESTRE | AA352: CASTAÑEDA PALACIO CARLOS FELIPE | AB352: 1 | AC352: 0 | AD352: =IF(W352="SOPORTE_TELEFÓNICO",'BASE LIQUIDACION REDEBAN 2025'!$B$19,IF(W352="ENVÍO",'BASE LIQUIDACION REDEBAN 2025'!$C$2,IF(Y352="TIPO I",'BASE LIQUIDACION REDEBAN 2025'!$C$2,IF(Y352="TIPO II",'BASE LIQUIDACION REDEBAN 2025'!$C$3,IF(Y352="TIPO III",'BASE LIQUIDACION REDEBAN 2025'!$C$4,IF(Y352="TIPO IV",'BASE LIQUIDACION REDEBAN 2025'!$C$5,IF(Z352="AEREO",'BASE LIQUIDACION REDEBAN 2025'!$B$6,'BASE LIQUIDACION REDEBAN 2025'!$C$5))))))) -> 275728.78 | AE352: =IF(OR(W352="SOPORTE_TELEFÓNICO",W352="ENVÍO"),0,IF(Y352="TIPO I",'BASE LIQUIDACION REDEBAN 2025'!$B$10,IF(Y352="TIPO II",'BASE LIQUIDACION REDEBAN 2025'!$B$11,IF(Y352="TIPO III",'BASE LIQUIDACION REDEBAN 2025'!$B$12,'BASE LIQUIDACION REDEBAN 2025'!$B$13)))) -> 196536.53 | AF352: =IF(OR(W352="SOPORTE_TELEFÓNICO",W352="ENVÍO"),AD352,(AD352*AB352+AE352*AC352)) -> 275728.78
A353: MEDELLIN | B353: =VLOOKUP(A353,'CENTRO DE COSTOS'!A:D,4,FALSE) -> JUAN SEBASTIÁN RÍOS CASTRILLÓN | C353: =VLOOKUP(A353,'CENTRO DE COSTOS'!A:D,2,FALSE) -> 0004-0005 | D353: 5631 | E353: 2768726 | F353: 47090 | G353: INCIDENTE | H353: ANTIOQUIA | I353: SABANETA | J353: BARRIO PARCELAS DOS SABANETA | K353: REDEBAN | L353: FO-25-1557304 | M353: 45920.333 | N353: 45920.551 | O353: NO | P353: HARDWARE | Q353: SE REINICIA | R353: DAÑO POS | U353: CERRADO | V353: 20/09/2025 SE CAMBIA DATAFONO POR DAÑO EN PUERTO USB | W353: VISITA_TÉCNICA | X353: 9C00D605 | Y353: TIPO I | Z353: TERRESTRE | AA353: CASTAÑEDA PALACIO CARLOS FELIPE | AB353: 1 | AC353: 0 | AD353: =IF(W353="SOPORTE_TELEFÓNICO",'BASE LIQUIDACION REDEBAN 2025'!$B$19,IF(W353="ENVÍO",'BASE LIQUIDACION REDEBAN 2025'!$C$2,IF(Y353="TIPO I",'BASE LIQUIDACION REDEBAN 2025'!$C$2,IF(Y353="TIPO II",'BASE LIQUIDACION REDEBAN 2025'!$C$3,IF(Y353="TIPO III",'BASE LIQUIDACION REDEBAN 2025'!$C$4,IF(Y353="TIPO IV",'BASE LIQUIDACION REDEBAN 2025'!$C$5,IF(Z353="AEREO",'BASE LIQUIDACION REDEBAN 2025'!$B$6,'BASE LIQUIDACION REDEBAN 2025'!$C$5))))))) -> 65960.072 | AE353: =IF(OR(W353="SOPORTE_TELEFÓNICO",W353="ENVÍO"),0,IF(Y353="TIPO I",'BASE LIQUIDACION REDEBAN 2025'!$B$10,IF(Y353="TIPO II",'BASE LIQUIDACION REDEBAN 2025'!$B$11,IF(Y353="TIPO III",'BASE LIQUIDACION REDEBAN 2025'!$B$12,'BASE LIQUIDACION REDEBAN 2025'!$B$13)))) -> 75096.394 | AF353: =IF(OR(W353="SOPORTE_TELEFÓNICO",W353="ENVÍO"),AD353,(AD353*AB353+AE353*AC353)) -> 65960.072
A354: CALI | B354: =VLOOKUP(A354,'CENTRO DE COSTOS'!A:D,4,FALSE) -> DIEGO FERNANDO HENAO CARDONA | C354: =VLOOKUP(A354,'CENTRO DE COSTOS'!A:D,2,FALSE) -> 0004-0003 | D354: 76248 | E354: 2768494 | F354: 28458 | G354: INCIDENTE | H354: VALLE DEL CAUCA | I354: EL CERRITO | J354: BARRIO CERRITO 1 VALLE DEL CAU | K354: REDEBAN | L354: FO-25-1557309 | M354: 45919.73 | N354: 45920.557 | O354: NO | P354: HARDWARE | Q354: IMPRESION | R354: TAPA IMPRESORA | U354: CERRADO | V354: 20/09/2025 EN LA VISITA TÉCNICA SE REALIZÓ EL CAMBIO DE DATÁFONO YA QUE SE ENCONTRÓ CON LA TAPA SUPERIOR DE LA IMPRESORA PARTIDA,SE CAMBIÓ SU RESPECTIVO MAGIC BOX TETRA Y FUENTE DE PODER,SE INSTALA EL SISTEMA OPERATIVO Y VERSIÓN 9.90,SE REALIZÓ LA CONFIGURACIÓN E INICIALIZACIÓN OK, SE CREARON LOS USUARIOS Y SE REALIZARON LAS PRUEBAS DEJANDO EL SERVICIO OPERANDO SIN FALLAS Y SIN NOVEDAD. | W354: VISITA_TÉCNICA | X354: BL01Y601 | Y354: TIPO II | Z354: TERRESTRE | AA354: SANCHEZ URREGO ROBINSON DAVID | AB354: 1 | AC354: 0 | AD354: =IF(W354="SOPORTE_TELEFÓNICO",'BASE LIQUIDACION REDEBAN 2025'!$B$19,IF(W354="ENVÍO",'BASE LIQUIDACION REDEBAN 2025'!$C$2,IF(Y354="TIPO I",'BASE LIQUIDACION REDEBAN 2025'!$C$2,IF(Y354="TIPO II",'BASE LIQUIDACION REDEBAN 2025'!$C$3,IF(Y354="TIPO III",'BASE LIQUIDACION REDEBAN 2025'!$C$4,IF(Y354="TIPO IV",'BASE LIQUIDACION REDEBAN 2025'!$C$5,IF(Z354="AEREO",'BASE LIQUIDACION REDEBAN 2025'!$B$6,'BASE LIQUIDACION REDEBAN 2025'!$C$5))))))) -> 144967.87 | AE354: =IF(OR(W354="SOPORTE_TELEFÓNICO",W354="ENVÍO"),0,IF(Y354="TIPO I",'BASE LIQUIDACION REDEBAN 2025'!$B$10,IF(Y354="TIPO II",'BASE LIQUIDACION REDEBAN 2025'!$B$11,IF(Y354="TIPO III",'BASE LIQUIDACION REDEBAN 2025'!$B$12,'BASE LIQUIDACION REDEBAN 2025'!$B$13)))) -> 140395.63 | AF354: =IF(OR(W354="SOPORTE_TELEFÓNICO",W354="ENVÍO"),AD354,(AD354*AB354+AE354*AC354)) -> 144967.87
A355: TUNJA | B355: =VLOOKUP(A355,'CENTRO DE COSTOS'!A:D,4,FALSE) -> MIGUEL JULIÁN HERNÁNDEZ GUARÍN | C355: =VLOOKUP(A355,'CENTRO DE COSTOS'!A:D,2,FALSE) -> 0004-0008 | D355: 15759 | E355: 2768555 | F355: 47017 | G355: INCIDENTE | H355: BOYACA | I355: SOGAMOSO | J355: BARRIO VEINTE DE JULIO SOGAMOS | K355: REDEBAN | L355: FO-25-1557312 | M355: 45919.729 | N355: 45920.562 | O355: NO | P355: SOFTWARE | Q355: ACTUALIZACION | R355: VERSION CARGA SO VR | U355: CERRADO | V355: 20/09/2025 SE REALIZA VISITA AL COMERCIO, SE BORRA Y ACTUALIZA EQUIPO A VERSION 9.9, PRUEBAS OK. | W355: VISITA_TÉCNICA | X355: TR00B954 | Y355: TIPO II | Z355: TERRESTRE | AA355: SOLER HOYOS CRISTIAN LEONARDO | AB355: 1 | AC355: 0 | AD355: =IF(W355="SOPORTE_TELEFÓNICO",'BASE LIQUIDACION REDEBAN 2025'!$B$19,IF(W355="ENVÍO",'BASE LIQUIDACION REDEBAN 2025'!$C$2,IF(Y355="TIPO I",'BASE LIQUIDACION REDEBAN 2025'!$C$2,IF(Y355="TIPO II",'BASE LIQUIDACION REDEBAN 2025'!$C$3,IF(Y355="TIPO III",'BASE LIQUIDACION REDEBAN 2025'!$C$4,IF(Y355="TIPO IV",'BASE LIQUIDACION REDEBAN 2025'!$C$5,IF(Z355="AEREO",'BASE LIQUIDACION REDEBAN 2025'!$B$6,'BASE LIQUIDACION REDEBAN 2025'!$C$5))))))) -> 144967.87 | AE355: =IF(OR(W355="SOPORTE_TELEFÓNICO",W355="ENVÍO"),0,IF(Y355="TIPO I",'BASE LIQUIDACION REDEBAN 2025'!$B$10,IF(Y355="TIPO II",'BASE LIQUIDACION REDEBAN 2025'!$B$11,IF(Y355="TIPO III",'BASE LIQUIDACION REDEBAN 2025'!$B$12,'BASE LIQUIDACION REDEBAN 2025'!$B$13)))) -> 140395.63 | AF355: =IF(OR(W355="SOPORTE_TELEFÓNICO",W355="ENVÍO"),AD355,(AD355*AB355+AE355*AC355)) -> 144967.87
... A686: MEDELLIN | B686: =VLOOKUP(A686,'CENTRO DE COSTOS'!A:D,4,FALSE) -> JUAN SEBASTIÁN RÍOS CASTRILLÓN | C686: =VLOOKUP(A686,'CENTRO DE COSTOS'!A:D,2,FALSE) -> 0004-0005 | D686: 5360 | E686: 2727768 | F686: 47440 | G686: INCIDENTE | H686: ANTIOQUIA | I686: ITAGUI | J686: OPRAP SUPERCENTRO DE LA MODA | K686: REDEBAN | L686: FO-25-1514681 | M686: 45911.497 | N686: 45912.399 | O686: NO | P686: HARDWARE | Q686: IMPRESION | R686: TAPA IMPRESORA | U686: CERRADO | V686: 12/09/2025 SE REALIZA CAMBIO DE TAPA DE IMPRESIÓN POR DAÑO | W686: VISITA_TÉCNICA | X686: AD00F490 | Y686: TIPO I | Z686: TERRESTRE | AA686: HERNANDEZ CHAVARRIA JUAN CAMILO | AB686: 1 | AC686: 0 | AD686: =IF(W686="SOPORTE_TELEFÓNICO",'BASE LIQUIDACION REDEBAN 2025'!$B$19,IF(W686="ENVÍO",'BASE LIQUIDACION REDEBAN 2025'!$C$2,IF(Y686="TIPO I",'BASE LIQUIDACION REDEBAN 2025'!$C$2,IF(Y686="TIPO II",'BASE LIQUIDACION REDEBAN 2025'!$C$3,IF(Y686="TIPO III",'BASE LIQUIDACION REDEBAN 2025'!$C$4,IF(Y686="TIPO IV",'BASE LIQUIDACION REDEBAN 2025'!$C$5,IF(Z686="AEREO",'BASE LIQUIDACION REDEBAN 2025'!$B$6,'BASE LIQUIDACION REDEBAN 2025'!$C$5))))))) -> 65960.072 | AE686: =IF(OR(W686="SOPORTE_TELEFÓNICO",W686="ENVÍO"),0,IF(Y686="TIPO I",'BASE LIQUIDACION REDEBAN 2025'!$B$10,IF(Y686="TIPO II",'BASE LIQUIDACION REDEBAN 2025'!$B$11,IF(Y686="TIPO III",'BASE LIQUIDACION REDEBAN 2025'!$B$12,'BASE LIQUIDACION REDEBAN 2025'!$B$13)))) -> 75096.394 | AF686: =IF(OR(W686="SOPORTE_TELEFÓNICO",W686="ENVÍO"),AD686,(AD686*AB686+AE686*AC686)) -> 65960.072
A687: MEDELLIN | B687: =VLOOKUP(A687,'CENTRO DE COSTOS'!A:D,4,FALSE) -> JUAN SEBASTIÁN RÍOS CASTRILLÓN | C687: =VLOOKUP(A687,'CENTRO DE COSTOS'!A:D,2,FALSE) -> 0004-0005 | D687: 5001 | E687: TA-25-1096342 | F687: 29374 | G687: INCIDENTE | H687: ANTIOQUIA | I687: MEDELLIN | J687: BARRIO PRADO 4 MEDELLIN | K687: REDEBAN | L687: FO-25-1513919 | M687: 45911.478 | N687: 45912.472 | O687: NO | P687: SOFTWARE | Q687: ACTUALIZACION | R687: TECNOLOGIA | U687: CERRADO | V687: 12/09/2025 SE REALIZA CAMBIO DE EQUIPO POR TECNOLOGÍA , SE CAMBIA LECTOR DE BARRAS POR CABLE EN MAL ESTADO SE REINICIA | W687: VISITA_TÉCNICA | X687: 9A003208 | Y687: TIPO I | Z687: TERRESTRE | AA687: MONTOYA VELEZ ANDRES FELIPE | AB687: 1 | AC687: 0 | AD687: =IF(W687="SOPORTE_TELEFÓNICO",'BASE LIQUIDACION REDEBAN 2025'!$B$19,IF(W687="ENVÍO",'BASE LIQUIDACION REDEBAN 2025'!$C$2,IF(Y687="TIPO I",'BASE LIQUIDACION REDEBAN 2025'!$C$2,IF(Y687="TIPO II",'BASE LIQUIDACION REDEBAN 2025'!$C$3,IF(Y687="TIPO III",'BASE LIQUIDACION REDEBAN 2025'!$C$4,IF(Y687="TIPO IV",'BASE LIQUIDACION REDEBAN 2025'!$C$5,IF(Z687="AEREO",'BASE LIQUIDACION REDEBAN 2025'!$B$6,'BASE LIQUIDACION REDEBAN 2025'!$C$5))))))) -> 65960.072 | AE687: =IF(OR(W687="SOPORTE_TELEFÓNICO",W687="ENVÍO"),0,IF(Y687="TIPO I",'BASE LIQUIDACION REDEBAN 2025'!$B$10,IF(Y687="TIPO II",'BASE LIQUIDACION REDEBAN 2025'!$B$11,IF(Y687="TIPO III",'BASE LIQUIDACION REDEBAN 2025'!$B$12,'BASE LIQUIDACION REDEBAN 2025'!$B$13)))) -> 75096.394 | AF687: =IF(OR(W687="SOPORTE_TELEFÓNICO",W687="ENVÍO"),AD687,(AD687*AB687+AE687*AC687)) -> 65960.072
A688: BOGOTA | B688: =VLOOKUP(A688,'CENTRO DE COSTOS'!A:D,4,FALSE) -> WILLIAM ASDRUBAL ROZO ROZO | C688: =VLOOKUP(A688,'CENTRO DE COSTOS'!A:D,2,FALSE) -> 0004-0004 | D688: 25754 | E688: 2727598 | F688: 37321 | G688: INCIDENTE | H688: CUNDINAMARCA | I688: SOACHA | J688: BARRIO VILLA ITALIA SOACHA | K688: REDEBAN | L688: FO-25-1514685 | M688: 45911.481 | N688: 45912.544 | O688: NO | P688: HARDWARE | Q688: PINPAD | R688: SE REINICIA | U688: CERRADO | V688: 12/09/2025 SE REALIZA CAMBIO DE EQUIPO POR COMPATIBILIDAD TECNOLÓGICA POR DAÑO EN PINPAD SERVICIO OPERATIVO PRUEBAS OK TRNA RBM SE REALIZA PRUEBA DE CONSULTA DE SALDO NO HAY NÚMERO DE CUENTA PARA CONSIGNAR NI TARJETA PARA RETIRO | W688: VISITA_TÉCNICA | X688: GZ00L853 | Y688: TIPO I | Z688: TERRESTRE | AA688: BUSTOS MORA DIEGO MANUEL | AB688: 1 | AC688: 0 | AD688: =IF(W688="SOPORTE_TELEFÓNICO",'BASE LIQUIDACION REDEBAN 2025'!$B$19,IF(W688="ENVÍO",'BASE LIQUIDACION REDEBAN 2025'!$C$2,IF(Y688="TIPO I",'BASE LIQUIDACION REDEBAN 2025'!$C$2,IF(Y688="TIPO II",'BASE LIQUIDACION REDEBAN 2025'!$C$3,IF(Y688="TIPO III",'BASE LIQUIDACION REDEBAN 2025'!$C$4,IF(Y688="TIPO IV",'BASE LIQUIDACION REDEBAN 2025'!$C$5,IF(Z688="AEREO",'BASE LIQUIDACION REDEBAN 2025'!$B$6,'BASE LIQUIDACION REDEBAN 2025'!$C$5))))))) -> 65960.072 | AE688: =IF(OR(W688="SOPORTE_TELEFÓNICO",W688="ENVÍO"),0,IF(Y688="TIPO I",'BASE LIQUIDACION REDEBAN 2025'!$B$10,IF(Y688="TIPO II",'BASE LIQUIDACION REDEBAN 2025'!$B$11,IF(Y688="TIPO III",'BASE LIQUIDACION REDEBAN 2025'!$B$12,'BASE LIQUIDACION REDEBAN 2025'!$B$13)))) -> 75096.394 | AF688: =IF(OR(W688="SOPORTE_TELEFÓNICO",W688="ENVÍO"),AD688,(AD688*AB688+AE688*AC688)) -> 65960.072
A689: BARRANQUILLA | B689: =VLOOKUP(A689,'CENTRO DE COSTOS'!A:D,4,FALSE) -> JOSE MAURICIO HERNANDEZ ROJAS | C689: =VLOOKUP(A689,'CENTRO DE COSTOS'!A:D,2,FALSE) -> 0004-0001 | D689: 8001 | E689: 2727594 | F689: 63319 | G689: INCIDENTE | H689: ATLANTICO | I689: BARRANQUILLA | J689: PTM BARRANQUILLA VARIEDADES LA | K689: REDEBAN | L689: FO-25-1514691 | M689: 45911.481 | N689: 45912.475 | O689: NO | P689: HARDWARE | Q689: COMUNICACION | R689: MENSAJE CABLE DE RED DESCONECTADO | U689: CERRADO | V689: 12/09/2025 SE REMPLAZA DATAFONO, TENÍA PUERTO DE RED QUEMADO | W689: VISITA_TÉCNICA | X689: LA00V251 | Y689: TIPO I | Z689: TERRESTRE | AA689: DE AVILA SIADES ALBERTO ENRIQUE | AB689: 1 | AC689: 0 | AD689: =IF(W689="SOPORTE_TELEFÓNICO",'BASE LIQUIDACION REDEBAN 2025'!$B$19,IF(W689="ENVÍO",'BASE LIQUIDACION REDEBAN 2025'!$C$2,IF(Y689="TIPO I",'BASE LIQUIDACION REDEBAN 2025'!$C$2,IF(Y689="TIPO II",'BASE LIQUIDACION REDEBAN 2025'!$C$3,IF(Y689="TIPO III",'BASE LIQUIDACION REDEBAN 2025'!$C$4,IF(Y689="TIPO IV",'BASE LIQUIDACION REDEBAN 2025'!$C$5,IF(Z689="AEREO",'BASE LIQUIDACION REDEBAN 2025'!$B$6,'BASE LIQUIDACION REDEBAN 2025'!$C$5))))))) -> 65960.072 | AE689: =IF(OR(W689="SOPORTE_TELEFÓNICO",W689="ENVÍO"),0,IF(Y689="TIPO I",'BASE LIQUIDACION REDEBAN 2025'!$B$10,IF(Y689="TIPO II",'BASE LIQUIDACION REDEBAN 2025'!$B$11,IF(Y689="TIPO III",'BASE LIQUIDACION REDEBAN 2025'!$B$12,'BASE LIQUIDACION REDEBAN 2025'!$B$13)))) -> 75096.394 | AF689: =IF(OR(W689="SOPORTE_TELEFÓNICO",W689="ENVÍO"),AD689,(AD689*AB689+AE689*AC689)) -> 65960.072
A690: BUCARAMANGA | B690: =VLOOKUP(A690,'CENTRO DE COSTOS'!A:D,4,FALSE) -> MIGUEL JULIÁN HERNÁNDEZ GUARÍN | C690: =VLOOKUP(A690,'CENTRO DE COSTOS'!A:D,2,FALSE) -> 0004-0008 | D690: 68001 | E690: 2727284 | F690: 77273 | G690: INCIDENTE | H690: SANTANDER | I690: BUCARAMANGA | J690: MULTIPAGAS UNICO BUCARAMANGA | K690: REDEBAN | L690: FO-25-1513823 | M690: 45911.462 | N690: 45911.712 | O690: NO | P690: SOFTWARE | Q690: ACTUALIZACION | R690: VERSION CARGA SO VR | U690: CERRADO | V690: 11/09/2025 SE REALIZA BORRADO DE S.O Y VERSIÓN 9.90 CREACIÓN DE USUARIOS PRUEBAS OK SERVICIO OPERATIVO SE EJECUTAN PRUEBAS CON CUENTA Y TARJETA DEL USUARIO | W690: VISITA_TÉCNICA | X690: FACZZ583 | Y690: TIPO I | Z690: TERRESTRE | AA690: REYES RAMIREZ DIEGO ALEXANDER | AB690: 1 | AC690: 0 | AD690: =IF(W690="SOPORTE_TELEFÓNICO",'BASE LIQUIDACION REDEBAN 2025'!$B$19,IF(W690="ENVÍO",'BASE LIQUIDACION REDEBAN 2025'!$C$2,IF(Y690="TIPO I",'BASE LIQUIDACION REDEBAN 2025'!$C$2,IF(Y690="TIPO II",'BASE LIQUIDACION REDEBAN 2025'!$C$3,IF(Y690="TIPO III",'BASE LIQUIDACION REDEBAN 2025'!$C$4,IF(Y690="TIPO IV",'BASE LIQUIDACION REDEBAN 2025'!$C$5,IF(Z690="AEREO",'BASE LIQUIDACION REDEBAN 2025'!$B$6,'BASE LIQUIDACION REDEBAN 2025'!$C$5))))))) -> 65960.072 | AE690: =IF(OR(W690="SOPORTE_TELEFÓNICO",W690="ENVÍO"),0,IF(Y690="TIPO I",'BASE LIQUIDACION REDEBAN 2025'!$B$10,IF(Y690="TIPO II",'BASE LIQUIDACION REDEBAN 2025'!$B$11,IF(Y690="TIPO III",'BASE LIQUIDACION REDEBAN 2025'!$B$12,'BASE LIQUIDACION REDEBAN 2025'!$B$13)))) -> 75096.394 | AF690: =IF(OR(W690="SOPORTE_TELEFÓNICO",W690="ENVÍO"),AD690,(AD690*AB690+AE690*AC690)) -> 65960.072
A691: MONTERIA | B691: =VLOOKUP(A691,'CENTRO DE COSTOS'!A:D,4,FALSE) -> JOSE MAURICIO HERNANDEZ ROJAS | C691: =VLOOKUP(A691,'CENTRO DE COSTOS'!A:D,2,FALSE) -> 0004-0001 | D691: 23660 | E691: 2727282 | F691: 63138 | G691: INCIDENTE | H691: CORDOBA | I691: SAHAGUN | J691: BARRIO CENTENARIO SAHAGUN 4 | K691: REDEBAN | L691: FO-25-1513829 | M691: 45911.461 | N691: 45912.532 | O691: NO | P691: HARDWARE | Q691: IMPRESION | R691: DAÑO POS | U691: CERRADO | V691: 12/09/2025 SE VISITA SITIO, SE CAMBIA EQUIPO POR DAÑO EN IMPRESORA Y TECLADO OK. SE INSTALA EQUIPO DESK2600 Y SE REALIZAN PRUEBAS EXITOSAS | W691: VISITA_TÉCNICA | X691: JA00T576 | Y691: TIPO II | Z691: TERRESTRE | AA691: COGOLLO VERTEL EDER LUIS | AB691: 1 | AC691: 0 | AD691: =IF(W691="SOPORTE_TELEFÓNICO",'BASE LIQUIDACION REDEBAN 2025'!$B$19,IF(W691="ENVÍO",'BASE LIQUIDACION REDEBAN 2025'!$C$2,IF(Y691="TIPO I",'BASE LIQUIDACION REDEBAN 2025'!$C$2,IF(Y691="TIPO II",'BASE LIQUIDACION REDEBAN 2025'!$C$3,IF(Y691="TIPO III",'BASE LIQUIDACION REDEBAN 2025'!$C$4,IF(Y691="TIPO IV",'BASE LIQUIDACION REDEBAN 2025'!$C$5,IF(Z691="AEREO",'BASE LIQUIDACION REDEBAN 2025'!$B$6,'BASE LIQUIDACION REDEBAN 2025'!$C$5))))))) -> 144967.87 | AE691: =IF(OR(W691="SOPORTE_TELEFÓNICO",W691="ENVÍO"),0,IF(Y691="TIPO I",'BASE LIQUIDACION REDEBAN 2025'!$B$10,IF(Y691="TIPO II",'BASE LIQUIDACION REDEBAN 2025'!$B$11,IF(Y691="TIPO III",'BASE LIQUIDACION REDEBAN 2025'!$B$12,'BASE LIQUIDACION REDEBAN 2025'!$B$13)))) -> 140395.63 | AF691: =IF(OR(W691="SOPORTE_TELEFÓNICO",W691="ENVÍO"),AD691,(AD691*AB691+AE691*AC691)) -> 144967.87
A692: SANTA MARTA | B692: =VLOOKUP(A692,'CENTRO DE COSTOS'!A:D,4,FALSE) -> JOSE MAURICIO HERNANDEZ ROJAS | C692: =VLOOKUP(A692,'CENTRO DE COSTOS'!A:D,2,FALSE) -> 0004-0001 | D692: 47001 | E692: 2727271 | F692: 71534 | G692: INCIDENTE | H692: MAGDALENA | I692: SANTA MARTA | J692: PTM CORREGIMIENTO BURITICA ADD | K692: REDEBAN | L692: FO-25-1513833 | M692: 45911.458 | N692: 45912.588 | O692: NO | P692: HARDWARE | Q692: LECTOR DE TARJETAS | R692: DAÑO POS | U692: CERRADO | V692: 12/09/2025 SE REALIZA LA VISITA SE ENCUENTRA EL DATÁFONO CON PROBLEMAS DE LECTURA DE TARJETA YA QUE EN OCASIONES NO LAS LEE Y TOCA APRETAR O AGARRAR LA TARJETA ARA QUE LEA, SE PROCEDE A CAMBIAR EL EQUIPO, SE REALIZAN PRUEBAS Y TODO OK | W692: VISITA_TÉCNICA | X692: A30KZ101 | Y692: TIPO I | Z692: TERRESTRE | AA692: THOMAS CAMPO SIGIFREDO SEGUNDO | AB692: 1 | AC692: 0 | AD692: =IF(W692="SOPORTE_TELEFÓNICO",'BASE LIQUIDACION REDEBAN 2025'!$B$19,IF(W692="ENVÍO",'BASE LIQUIDACION REDEBAN 2025'!$C$2,IF(Y692="TIPO I",'BASE LIQUIDACION REDEBAN 2025'!$C$2,IF(Y692="TIPO II",'BASE LIQUIDACION REDEBAN 2025'!$C$3,IF(Y692="TIPO III",'BASE LIQUIDACION REDEBAN 2025'!$C$4,IF(Y692="TIPO IV",'BASE LIQUIDACION REDEBAN 2025'!$C$5,IF(Z692="AEREO",'BASE LIQUIDACION REDEBAN 2025'!$B$6,'BASE LIQUIDACION REDEBAN 2025'!$C$5))))))) -> 65960.072 | AE692: =IF(OR(W692="SOPORTE_TELEFÓNICO",W692="ENVÍO"),0,IF(Y692="TIPO I",'BASE LIQUIDACION REDEBAN 2025'!$B$10,IF(Y692="TIPO II",'BASE LIQUIDACION REDEBAN 2025'!$B$11,IF(Y692="TIPO III",'BASE LIQUIDACION REDEBAN 2025'!$B$12,'BASE LIQUIDACION REDEBAN 2025'!$B$13)))) -> 75096.394 | AF692: =IF(OR(W692="SOPORTE_TELEFÓNICO",W692="ENVÍO"),AD692,(AD692*AB692+AE692*AC692)) -> 65960.072
A693: BOGOTA | B693: =VLOOKUP(A693,'CENTRO DE COSTOS'!A:D,4,FALSE) -> WILLIAM ASDRUBAL ROZO ROZO | C693: =VLOOKUP(A693,'CENTRO DE COSTOS'!A:D,2,FALSE) -> 0004-0004 | D693: 25151 | E693: 2727411 | F693: 73373 | G693: INCIDENTE | H693: CUNDINAMARCA | I693: CAQUEZA | J693: BARRIO CENTRO CAQUEZA 4 | K693: REDEBAN | L693: FO-25-1513839 | M693: 45911.457 | N693: 45912.564 | O693: NO | P693: SOFTWARE | Q693: LLT | R693: LLT | U693: CERRADO | V693: 12/09/2025 SE REALIZA CONTRATO TELÉFONICO CON CLIENTE SONIA ALEXANDRA HERRERA VARELAA NÚMERO REGISTRADO 3142773044 AL CUAL SE LE INFORMA QUE NO SE PUEDE ATENDER YA QUE LA VIA SE ENCUENTRA CERRADA POR DERRUMBES . BOGOTÁ. VILLAVICENCIO. SE LE INDICA A CLIENTE QUE APENAS DEL EL PASO LLAMAR A ENTIDAD PARA AGENDAR NUEVA VISITA | W693: SOPORTE_TELEFÓNICO | X693: 0 | Y693: TIPO II | Z693: TERRESTRE | AA693: ORTIZ MARTINEZ STIVEN | AB693: 0 | AC693: 0 | AD693: =IF(W693="SOPORTE_TELEFÓNICO",'BASE LIQUIDACION REDEBAN 2025'!$B$19,IF(W693="ENVÍO",'BASE LIQUIDACION REDEBAN 2025'!$C$2,IF(Y693="TIPO I",'BASE LIQUIDACION REDEBAN 2025'!$C$2,IF(Y693="TIPO II",'BASE LIQUIDACION REDEBAN 2025'!$C$3,IF(Y693="TIPO III",'BASE LIQUIDACION REDEBAN 2025'!$C$4,IF(Y693="TIPO IV",'BASE LIQUIDACION REDEBAN 2025'!$C$5,IF(Z693="AEREO",'BASE LIQUIDACION REDEBAN 2025'!$B$6,'BASE LIQUIDACION REDEBAN 2025'!$C$5))))))) -> 41241.08 | AE693: =IF(OR(W693="SOPORTE_TELEFÓNICO",W693="ENVÍO"),0,IF(Y693="TIPO I",'BASE LIQUIDACION REDEBAN 2025'!$B$10,IF(Y693="TIPO II",'BASE LIQUIDACION REDEBAN 2025'!$B$11,IF(Y693="TIPO III",'BASE LIQUIDACION REDEBAN 2025'!$B$12,'BASE LIQUIDACION REDEBAN 2025'!$B$13)))) -> 0 | AF693: =IF(OR(W693="SOPORTE_TELEFÓNICO",W693="ENVÍO"),AD693,(AD693*AB693+AE693*AC693)) -> 41241.08
A694: BOGOTA | B694: =VLOOKUP(A694,'CENTRO DE COSTOS'!A:D,4,FALSE) -> WILLIAM ASDRUBAL ROZO ROZO | C694: =VLOOKUP(A694,'CENTRO DE COSTOS'!A:D,2,FALSE) -> 0004-0004 | D694: 91001 | E694: 2727208 | F694: 72927 | G694: INCIDENTE | H694: AMAZONAS | I694: LETICIA | J694: BARRIO CENTRO LETICIA 9 | K694: REDEBAN | L694: FO-25-1513860 | M694: 45911.444 | N694: 45919.592 | O694: NO | P694: HARDWARE | Q694: ALERT IRRUPTION | R694: ALERT IRRUPTION | U694: CERRADO | V694: 19/09/2025 SE REALIZA CAMBIO DE DATAFONO QUEMADO PRUEBAS OK | W694: VISITA_TÉCNICA | X694: EF00S467 | Y694: TIPO IV ESPECIAL | Z694: AEREO | AA694: GOMEZ VEGA DAVID SNEYDER | AB694: 1 | AC694: 0 | AD694: =IF(W694="SOPORTE_TELEFÓNICO",'BASE LIQUIDACION REDEBAN 2025'!$B$19,IF(W694="ENVÍO",'BASE LIQUIDACION REDEBAN 2025'!$C$2,IF(Y694="TIPO I",'BASE LIQUIDACION REDEBAN 2025'!$C$2,IF(Y694="TIPO II",'BASE LIQUIDACION REDEBAN 2025'!$C$3,IF(Y694="TIPO III",'BASE LIQUIDACION REDEBAN 2025'!$C$4,IF(Y694="TIPO IV",'BASE LIQUIDACION REDEBAN 2025'!$C$5,IF(Z694="AEREO",'BASE LIQUIDACION REDEBAN 2025'!$B$6,'BASE LIQUIDACION REDEBAN 2025'!$C$5))))))) -> 988462.96 | AE694: =IF(OR(W694="SOPORTE_TELEFÓNICO",W694="ENVÍO"),0,IF(Y694="TIPO I",'BASE LIQUIDACION REDEBAN 2025'!$B$10,IF(Y694="TIPO II",'BASE LIQUIDACION REDEBAN 2025'!$B$11,IF(Y694="TIPO III",'BASE LIQUIDACION REDEBAN 2025'!$B$12,'BASE LIQUIDACION REDEBAN 2025'!$B$13)))) -> 196536.53 | AF694: =IF(OR(W694="SOPORTE_TELEFÓNICO",W694="ENVÍO"),AD694,(AD694*AB694+AE694*AC694)) -> 988462.96
A695: CALI | B695: =VLOOKUP(A695,'CENTRO DE COSTOS'!A:D,4,FALSE) -> DIEGO FERNANDO HENAO CARDONA | C695: =VLOOKUP(A695,'CENTRO DE COSTOS'!A:D,2,FALSE) -> 0004-0003 | D695: 19001 | E695: 2727200 | F695: 70730 | G695: INCIDENTE | H695: CAUCA | I695: POPAYAN | J695: DISTRICOL DROGUERIA SAMUSALUD | K695: REDEBAN | L695: FO-25-1513866 | M695: 45911.442 | N695: 45912.638 | O695: NO | P695: HARDWARE | Q695: SE REINICIA | R695: DAÑO POS | U695: CERRADO | V695: 12/09/2025 SE INGRESA SE CAMBIA FUENTE DE ENERGÍA SE HACEN PRUEBAS OK TELECARGA DRNA | W695: VISITA_TÉCNICA | X695: A30IZ465 | Y695: TIPO III | Z695: TERRESTRE | AA695: GIMBUEL LASSO LUIS GERMAN | AB695: 1 | AC695: 0 | AD695: =IF(W695="SOPORTE_TELEFÓNICO",'BASE LIQUIDACION REDEBAN 2025'!$B$19,IF(W695="ENVÍO",'BASE LIQUIDACION REDEBAN 2025'!$C$2,IF(Y695="TIPO I",'BASE LIQUIDACION REDEBAN 2025'!$C$2,IF(Y695="TIPO II",'BASE LIQUIDACION REDEBAN 2025'!$C$3,IF(Y695="TIPO III",'BASE LIQUIDACION REDEBAN 2025'!$C$4,IF(Y695="TIPO IV",'BASE LIQUIDACION REDEBAN 2025'!$C$5,IF(Z695="AEREO",'BASE LIQUIDACION REDEBAN 2025'!$B$6,'BASE LIQUIDACION REDEBAN 2025'!$C$5))))))) -> 275728.78 | AE695: =IF(OR(W695="SOPORTE_TELEFÓNICO",W695="ENVÍO"),0,IF(Y695="TIPO I",'BASE LIQUIDACION REDEBAN 2025'!$B$10,IF(Y695="TIPO II",'BASE LIQUIDACION REDEBAN 2025'!$B$11,IF(Y695="TIPO III",'BASE LIQUIDACION REDEBAN 2025'!$B$12,'BASE LIQUIDACION REDEBAN 2025'!$B$13)))) -> 196536.53 | AF695: =IF(OR(W695="SOPORTE_TELEFÓNICO",W695="ENVÍO"),AD695,(AD695*AB695+AE695*AC695)) -> 275728.78
A696: MEDELLIN | B696: =VLOOKUP(A696,'CENTRO DE COSTOS'!A:D,4,FALSE) -> JUAN SEBASTIÁN RÍOS CASTRILLÓN | C696: =VLOOKUP(A696,'CENTRO DE COSTOS'!A:D,2,FALSE) -> 0004-0005 | D696: 15572 | E696: 2726965 | F696: 72996 | G696: INCIDENTE | H696: BOYACA | I696: PUERTO BOYACA | J696: DISTRICOL CORRESPONSAL LA 5TA | K696: REDEBAN | L696: FO-25-1513883 | M696: 45911.434 | N696: 45912.641 | O696: NO | P696: HARDWARE | Q696: SE REINICIA | R696: LECTOR BARRAS | U696: CERRADO | V696: 12/09/2025 SE REVISA LECTORA YA QUE REINICIA EL EQUIPO SE REALIZAN PRUEBAS EXITOSAS SERVICIO OPERATIVO OK | W696: VISITA_TÉCNICA | X696: LN00S307 | Y696: TIPO IV | Z696: TERRESTRE | AA696: ZAPATA LOPEZ EDWARD ASDRUBAL | AB696: 1 | AC696: 0 | AD696: =IF(W696="SOPORTE_TELEFÓNICO",'BASE LIQUIDACION REDEBAN 2025'!$B$19,IF(W696="ENVÍO",'BASE LIQUIDACION REDEBAN 2025'!$C$2,IF(Y696="TIPO I",'BASE LIQUIDACION REDEBAN 2025'!$C$2,IF(Y696="TIPO II",'BASE LIQUIDACION REDEBAN 2025'!$C$3,IF(Y696="TIPO III",'BASE LIQUIDACION REDEBAN 2025'!$C$4,IF(Y696="TIPO IV",'BASE LIQUIDACION REDEBAN 2025'!$C$5,IF(Z696="AEREO",'BASE LIQUIDACION REDEBAN 2025'!$B$6,'BASE LIQUIDACION REDEBAN 2025'!$C$5))))))) -> 479588.88 | AE696: =IF(OR(W696="SOPORTE_TELEFÓNICO",W696="ENVÍO"),0,IF(Y696="TIPO I",'BASE LIQUIDACION REDEBAN 2025'!$B$10,IF(Y696="TIPO II",'BASE LIQUIDACION REDEBAN 2025'!$B$11,IF(Y696="TIPO III",'BASE LIQUIDACION REDEBAN 2025'!$B$12,'BASE LIQUIDACION REDEBAN 2025'!$B$13)))) -> 196536.53 | AF696: =IF(OR(W696="SOPORTE_TELEFÓNICO",W696="ENVÍO"),AD696,(AD696*AB696+AE696*AC696)) -> 479588.88
A697: BOGOTA | B697: =VLOOKUP(A697,'CENTRO DE COSTOS'!A:D,4,FALSE) -> WILLIAM ASDRUBAL ROZO ROZO | C697: =VLOOKUP(A697,'CENTRO DE COSTOS'!A:D,2,FALSE) -> 0004-0004 | D697: 25486 | E697: 2726856 | F697: 63776 | G697: INCIDENTE | H697: CUNDINAMARCA | I697: NEMOCON | J697: BARRIO DIVINO NINO NEMOCON | K697: REDEBAN | L697: FO-25-1513373 | M697: 45911.422 | N697: 45912.527 | O697: NO | P697: HARDWARE | Q697: LECTOR DE BARRAS | R697: CABLE LECTORA AVERIADO | U697: CERRADO | V697: 12/09/2025 SE VISITA COMERCIO CB BANCOLOMBIA, SE REALIZA CAMBIO DE LECTOR DE BARRAS PUES ESTÁ DETERIORADO Y GENERA INTERMITENCIA AL LEER CÓDIGOS DE BARRAS, SE DEJA EL NUEVO CON PRUEBAS OK, NO UPS, NO SE ALTERAN USUARIOS. | W697: VISITA_TÉCNICA | X697: JA00X284 | Y697: TIPO II | Z697: TERRESTRE | AA697: VEGA MANRIQUE JONATAN MAURICIO | AB697: 1 | AC697: 0 | AD697: =IF(W697="SOPORTE_TELEFÓNICO",'BASE LIQUIDACION REDEBAN 2025'!$B$19,IF(W697="ENVÍO",'BASE LIQUIDACION REDEBAN 2025'!$C$2,IF(Y697="TIPO I",'BASE LIQUIDACION REDEBAN 2025'!$C$2,IF(Y697="TIPO II",'BASE LIQUIDACION REDEBAN 2025'!$C$3,IF(Y697="TIPO III",'BASE LIQUIDACION REDEBAN 2025'!$C$4,IF(Y697="TIPO IV",'BASE LIQUIDACION REDEBAN 2025'!$C$5,IF(Z697="AEREO",'BASE LIQUIDACION REDEBAN 2025'!$B$6,'BASE LIQUIDACION REDEBAN 2025'!$C$5))))))) -> 144967.87 | AE697: =IF(OR(W697="SOPORTE_TELEFÓNICO",W697="ENVÍO"),0,IF(Y697="TIPO I",'BASE LIQUIDACION REDEBAN 2025'!$B$10,IF(Y697="TIPO II",'BASE LIQUIDACION REDEBAN 2025'!$B$11,IF(Y697="TIPO III",'BASE LIQUIDACION REDEBAN 2025'!$B$12,'BASE LIQUIDACION REDEBAN 2025'!$B$13)))) -> 140395.63 | AF697: =IF(OR(W697="SOPORTE_TELEFÓNICO",W697="ENVÍO"),AD697,(AD697*AB697+AE697*AC697)) -> 144967.87
A698: BUCARAMANGA | B698: =VLOOKUP(A698,'CENTRO DE COSTOS'!A:D,4,FALSE) -> MIGUEL JULIÁN HERNÁNDEZ GUARÍN | C698: =VLOOKUP(A698,'CENTRO DE COSTOS'!A:D,2,FALSE) -> 0004-0008 | D698: 68001 | E698: 2726677 | F698: 26983 | G698: INCIDENTE | H698: SANTANDER | I698: BUCARAMANGA | J698: BARRIO ALARCON 2 BUCARAMANGA | K698: REDEBAN | L698: FO-25-1513379 | M698: 45911.421 | N698: 45911.731 | O698: NO | P698: HARDWARE | Q698: COMUNICACION | R698: MENSAJE DE ERROR SOCKET | U698: CERRADO | V698: 11/09/2025 SE REALIZA VISITA AL COMERCIO SE HACE CAMBIO DE DATAFONO SE REALIZAN PRUEBAS OK | W698: VISITA_TÉCNICA | X698: 6Z00Y273 | Y698: TIPO I | Z698: TERRESTRE | AA698: MARIÑO PABON JORGE ENRIQUE | AB698: 1 | AC698: 0 | AD698: =IF(W698="SOPORTE_TELEFÓNICO",'BASE LIQUIDACION REDEBAN 2025'!$B$19,IF(W698="ENVÍO",'BASE LIQUIDACION REDEBAN 2025'!$C$2,IF(Y698="TIPO I",'BASE LIQUIDACION REDEBAN 2025'!$C$2,IF(Y698="TIPO II",'BASE LIQUIDACION REDEBAN 2025'!$C$3,IF(Y698="TIPO III",'BASE LIQUIDACION REDEBAN 2025'!$C$4,IF(Y698="TIPO IV",'BASE LIQUIDACION REDEBAN 2025'!$C$5,IF(Z698="AEREO",'BASE LIQUIDACION REDEBAN 2025'!$B$6,'BASE LIQUIDACION REDEBAN 2025'!$C$5))))))) -> 65960.072 | AE698: =IF(OR(W698="SOPORTE_TELEFÓNICO",W698="ENVÍO"),0,IF(Y698="TIPO I",'BASE LIQUIDACION REDEBAN 2025'!$B$10,IF(Y698="TIPO II",'BASE LIQUIDACION REDEBAN 2025'!$B$11,IF(Y698="TIPO III",'BASE LIQUIDACION REDEBAN 2025'!$B$12,'BASE LIQUIDACION REDEBAN 2025'!$B$13)))) -> 75096.394 | AF698: =IF(OR(W698="SOPORTE_TELEFÓNICO",W698="ENVÍO"),AD698,(AD698*AB698+AE698*AC698)) -> 65960.072
A699: MONTERIA | B699: =VLOOKUP(A699,'CENTRO DE COSTOS'!A:D,4,FALSE) -> JOSE MAURICIO HERNANDEZ ROJAS | C699: =VLOOKUP(A699,'CENTRO DE COSTOS'!A:D,2,FALSE) -> 0004-0001 | D699: 23001 | E699: 2726840 | F699: 68357 | G699: INCIDENTE | H699: CORDOBA | I699: MONTERIA | J699: BARRIO JUAN XXIII MONTERIA 6 | K699: REDEBAN | L699: FO-25-1513386 | M699: 45911.418 | N699: 45911.685 | O699: NO | P699: HARDWARE | Q699: NO ENCIENDE SE REINICIA | R699: FUENTE PODER AVERIADA | U699: CERRADO | V699: 11/09/2025 SE VISITA SITIO, SE CAMBIA FUENTE DE PODER OK. SE REALIZA PRUEBAS EXITOSAS | W699: VISITA_TÉCNICA | X699: EG0OZ468 | Y699: TIPO I | Z699: TERRESTRE | AA699: COGOLLO VERTEL EDER LUIS | AB699: 1 | AC699: 0 | AD699: =IF(W699="SOPORTE_TELEFÓNICO",'BASE LIQUIDACION REDEBAN 2025'!$B$19,IF(W699="ENVÍO",'BASE LIQUIDACION REDEBAN 2025'!$C$2,IF(Y699="TIPO I",'BASE LIQUIDACION REDEBAN 2025'!$C$2,IF(Y699="TIPO II",'BASE LIQUIDACION REDEBAN 2025'!$C$3,IF(Y699="TIPO III",'BASE LIQUIDACION REDEBAN 2025'!$C$4,IF(Y699="TIPO IV",'BASE LIQUIDACION REDEBAN 2025'!$C$5,IF(Z699="AEREO",'BASE LIQUIDACION REDEBAN 2025'!$B$6,'BASE LIQUIDACION REDEBAN 2025'!$C$5))))))) -> 65960.072 | AE699: =IF(OR(W699="SOPORTE_TELEFÓNICO",W699="ENVÍO"),0,IF(Y699="TIPO I",'BASE LIQUIDACION REDEBAN 2025'!$B$10,IF(Y699="TIPO II",'BASE LIQUIDACION REDEBAN 2025'!$B$11,IF(Y699="TIPO III",'BASE LIQUIDACION REDEBAN 2025'!$B$12,'BASE LIQUIDACION REDEBAN 2025'!$B$13)))) -> 75096.394 | AF699: =IF(OR(W699="SOPORTE_TELEFÓNICO",W699="ENVÍO"),AD699,(AD699*AB699+AE699*AC699)) -> 65960.072
... A918: PEREIRA | B918: =VLOOKUP(A918,'CENTRO DE COSTOS'!A:D,4,FALSE) -> DIEGO FERNANDO HENAO CARDONA | C918: =VLOOKUP(A918,'CENTRO DE COSTOS'!A:D,2,FALSE) -> 0004-0002 | D918: 66594 | E918: 2702871 | F918: 22193 | G918: INCIDENTE | H918: RISARALDA | I918: QUINCHIA | J918: CENTRO QUINCHIA RISARALDA | K918: REDEBAN | L918: FO-25-1487248 | M918: 45905.703 | N918: 45909.358 | O918: NO | P918: SOFTWARE | Q918: ERROR DE TRANSACCIONES | R918: RECHAZO GENERAL | U918: CERRADO | V918: 09/09/2025 SE HABLA CON EL CLIENTE, INDICA QUE EL DATAFONO OPERA PERO CON UNA TARJETA EN ESPECIFICO AL MOMENTO DE QUERER RETIRAR O CONSULTAR SALDO , MUESTRA PIN INVALIDO, SE ESCALA CON PAOLA GARZON DE REDEBAN, SE VALIDA Y REDEBAN AUTORIZA REALIZAR INICIALIZACION REMOTA DE TERMINAL, SE REALIZA VALIDACION E INICIALIZACION, EL CLIENTE EMPIEZA A OPERAR EL DATAFONO E INDICA QUE YA LA TARJETA QUE LE PRESETABA EL PROBLEMA YA LE PERMITIO CONSULTAR SALDO Y RETIRAR, SE DEJA EN SEGUIMIENTO POR UN TIEMPO Y EL CB ESTA TRANSANDO SIN NOVEDAD, SE CIERRA CASO | W918: SOPORTE_TELEFÓNICO | X918: 0 | Y918: TIPO II | Z918: TERRESTRE | AA918: HENAO CARDONA DIEGO FERNANDO | AB918: 0 | AC918: 0 | AD918: =IF(W918="SOPORTE_TELEFÓNICO",'BASE LIQUIDACION REDEBAN 2025'!$B$19,IF(W918="ENVÍO",'BASE LIQUIDACION REDEBAN 2025'!$C$2,IF(Y918="TIPO I",'BASE LIQUIDACION REDEBAN 2025'!$C$2,IF(Y918="TIPO II",'BASE LIQUIDACION REDEBAN 2025'!$C$3,IF(Y918="TIPO III",'BASE LIQUIDACION REDEBAN 2025'!$C$4,IF(Y918="TIPO IV",'BASE LIQUIDACION REDEBAN 2025'!$C$5,IF(Z918="AEREO",'BASE LIQUIDACION REDEBAN 2025'!$B$6,'BASE LIQUIDACION REDEBAN 2025'!$C$5))))))) -> 41241.08 | AE918: =IF(OR(W918="SOPORTE_TELEFÓNICO",W918="ENVÍO"),0,IF(Y918="TIPO I",'BASE LIQUIDACION REDEBAN 2025'!$B$10,IF(Y918="TIPO II",'BASE LIQUIDACION REDEBAN 2025'!$B$11,IF(Y918="TIPO III",'BASE LIQUIDACION REDEBAN 2025'!$B$12,'BASE LIQUIDACION REDEBAN 2025'!$B$13)))) -> 0 | AF918: =IF(OR(W918="SOPORTE_TELEFÓNICO",W918="ENVÍO"),AD918,(AD918*AB918+AE918*AC918)) -> 41241.08
A919: VILLAVICENCIO | B919: =VLOOKUP(A919,'CENTRO DE COSTOS'!A:D,4,FALSE) -> KEVIN ALEXIS CORZO BUSTOS | C919: =VLOOKUP(A919,'CENTRO DE COSTOS'!A:D,2,FALSE) -> 0004-0007 | D919: 50001 | E919: TA-25-1071111 | F919: 79202 | G919: INCIDENTE | H919: META | I919: VILLAVICENCIO | J919: BARRIO OLIMPICO VILLAVICENCIO 4 | K919: REDEBAN | L919: FO-25-1487166 | M919: 45905.701 | N919: 45905.739 | O919: NO | P919: SOFTWARE | Q919: DATOS DESACTUALIZADOS | R919: FECHA DIRECCION DESACTUALZADA | U919: CERRADO | V919: 05/09/2025 SE REALIZA CAMBIO DE EQUIPO POR SOLICITUD DE REDEBAN SE EVIDENCIA DIRECCIÓN EN EL VOUCHER SIGUE SIN ACTUALIZAR SE REALIZA ESCALAMIENTO CON REDEBAN | W919: VISITA_TÉCNICA | X919: A4UZZ556 | Y919: TIPO I | Z919: TERRESTRE | AA919: CASTRILLON URREA LONDIER LEANDRO | AB919: 1 | AC919: 0 | AD919: =IF(W919="SOPORTE_TELEFÓNICO",'BASE LIQUIDACION REDEBAN 2025'!$B$19,IF(W919="ENVÍO",'BASE LIQUIDACION REDEBAN 2025'!$C$2,IF(Y919="TIPO I",'BASE LIQUIDACION REDEBAN 2025'!$C$2,IF(Y919="TIPO II",'BASE LIQUIDACION REDEBAN 2025'!$C$3,IF(Y919="TIPO III",'BASE LIQUIDACION REDEBAN 2025'!$C$4,IF(Y919="TIPO IV",'BASE LIQUIDACION REDEBAN 2025'!$C$5,IF(Z919="AEREO",'BASE LIQUIDACION REDEBAN 2025'!$B$6,'BASE LIQUIDACION REDEBAN 2025'!$C$5))))))) -> 65960.072 | AE919: =IF(OR(W919="SOPORTE_TELEFÓNICO",W919="ENVÍO"),0,IF(Y919="TIPO I",'BASE LIQUIDACION REDEBAN 2025'!$B$10,IF(Y919="TIPO II",'BASE LIQUIDACION REDEBAN 2025'!$B$11,IF(Y919="TIPO III",'BASE LIQUIDACION REDEBAN 2025'!$B$12,'BASE LIQUIDACION REDEBAN 2025'!$B$13)))) -> 75096.394 | AF919: =IF(OR(W919="SOPORTE_TELEFÓNICO",W919="ENVÍO"),AD919,(AD919*AB919+AE919*AC919)) -> 65960.072
A920: PEREIRA | B920: =VLOOKUP(A920,'CENTRO DE COSTOS'!A:D,4,FALSE) -> DIEGO FERNANDO HENAO CARDONA | C920: =VLOOKUP(A920,'CENTRO DE COSTOS'!A:D,2,FALSE) -> 0004-0002 | D920: 63130 | E920: 2702243 | F920: 80585 | G920: INCIDENTE | H920: QUINDIO | I920: CALARCA | J920: BARRIO LA HUERTA CALARCA | K920: REDEBAN | L920: FO-25-1487030 | M920: 45905.645 | N920: 45906.663 | O920: NO | P920: SOFTWARE | Q920: LECTOR DE BARRAS | R920: FORMATO INVALIDO | U920: CERRADO | V920: 06/09/2025 SE VISITA COMERCIO SE REALIZÓ CAMBIO DE LECTOR POR DAÑO FORMATO INVÁLIDO SE TE CONFIGURA PERO NO FUNCIONA SE REALIZÓ EL CAMBIO. | W920: VISITA_TÉCNICA | X920: V6ZZZ825 | Y920: TIPO II | Z920: TERRESTRE | AA920: SANCHEZ SOLORZANO JUAN SEBASTIAN | AB920: 1 | AC920: 0 | AD920: =IF(W920="SOPORTE_TELEFÓNICO",'BASE LIQUIDACION REDEBAN 2025'!$B$19,IF(W920="ENVÍO",'BASE LIQUIDACION REDEBAN 2025'!$C$2,IF(Y920="TIPO I",'BASE LIQUIDACION REDEBAN 2025'!$C$2,IF(Y920="TIPO II",'BASE LIQUIDACION REDEBAN 2025'!$C$3,IF(Y920="TIPO III",'BASE LIQUIDACION REDEBAN 2025'!$C$4,IF(Y920="TIPO IV",'BASE LIQUIDACION REDEBAN 2025'!$C$5,IF(Z920="AEREO",'BASE LIQUIDACION REDEBAN 2025'!$B$6,'BASE LIQUIDACION REDEBAN 2025'!$C$5))))))) -> 144967.87 | AE920: =IF(OR(W920="SOPORTE_TELEFÓNICO",W920="ENVÍO"),0,IF(Y920="TIPO I",'BASE LIQUIDACION REDEBAN 2025'!$B$10,IF(Y920="TIPO II",'BASE LIQUIDACION REDEBAN 2025'!$B$11,IF(Y920="TIPO III",'BASE LIQUIDACION REDEBAN 2025'!$B$12,'BASE LIQUIDACION REDEBAN 2025'!$B$13)))) -> 140395.63 | AF920: =IF(OR(W920="SOPORTE_TELEFÓNICO",W920="ENVÍO"),AD920,(AD920*AB920+AE920*AC920)) -> 144967.87
A921: YOPAL | B921: =VLOOKUP(A921,'CENTRO DE COSTOS'!A:D,4,FALSE) -> KEVIN ALEXIS CORZO BUSTOS | C921: =VLOOKUP(A921,'CENTRO DE COSTOS'!A:D,2,FALSE) -> 0004-0007 | D921: 85410 | E921: 2702569 | F921: 69510 | G921: INCIDENTE | H921: CASANARE | I921: TAURAMENA | J921: PTM TAURAMENA,CASANARE CREDIHO | K921: REDEBAN | L921: FO-25-1487024 | M921: 45905.676 | N921: 45908.58 | O921: NO | P921: HARDWARE | Q921: COMUNICACION | R921: DAÑO POS | U921: CERRADO | V921: 08/09/2025 SE VISITA COMERCIO, SE REALIZA CAMBIO DE DATAFONO. SE CAMBIA PINPAD POR TECNOLOGIA. PRUEBAS OK. OPERATIVO EL SERVICIO | W921: VISITA_TÉCNICA | X921: EG001879 | Y921: TIPO II | Z921: TERRESTRE | AA921: BERNAL ELAICA EDGAR ALEXIS | AB921: 1 | AC921: 0 | AD921: =IF(W921="SOPORTE_TELEFÓNICO",'BASE LIQUIDACION REDEBAN 2025'!$B$19,IF(W921="ENVÍO",'BASE LIQUIDACION REDEBAN 2025'!$C$2,IF(Y921="TIPO I",'BASE LIQUIDACION REDEBAN 2025'!$C$2,IF(Y921="TIPO II",'BASE LIQUIDACION REDEBAN 2025'!$C$3,IF(Y921="TIPO III",'BASE LIQUIDACION REDEBAN 2025'!$C$4,IF(Y921="TIPO IV",'BASE LIQUIDACION REDEBAN 2025'!$C$5,IF(Z921="AEREO",'BASE LIQUIDACION REDEBAN 2025'!$B$6,'BASE LIQUIDACION REDEBAN 2025'!$C$5))))))) -> 144967.87 | AE921: =IF(OR(W921="SOPORTE_TELEFÓNICO",W921="ENVÍO"),0,IF(Y921="TIPO I",'BASE LIQUIDACION REDEBAN 2025'!$B$10,IF(Y921="TIPO II",'BASE LIQUIDACION REDEBAN 2025'!$B$11,IF(Y921="TIPO III",'BASE LIQUIDACION REDEBAN 2025'!$B$12,'BASE LIQUIDACION REDEBAN 2025'!$B$13)))) -> 140395.63 | AF921: =IF(OR(W921="SOPORTE_TELEFÓNICO",W921="ENVÍO"),AD921,(AD921*AB921+AE921*AC921)) -> 144967.87
A922: PEREIRA | B922: =VLOOKUP(A922,'CENTRO DE COSTOS'!A:D,4,FALSE) -> DIEGO FERNANDO HENAO CARDONA | C922: =VLOOKUP(A922,'CENTRO DE COSTOS'!A:D,2,FALSE) -> 0004-0002 | D922: 66001 | E922: 2701431 | F922: 76555 | G922: INCIDENTE | H922: RISARALDA | I922: PEREIRA | J922: PTM PEREIRA PAPELERIA CAVERNA | K922: REDEBAN | L922: FO-25-1486355 | M922: 45905.574 | N922: 45906.483 | O922: NO | P922: SOFTWARE | Q922: COMUNICACION | R922: VERIFIQUE PARAMETROS | U922: CERRADO | V922: 06/09/2025 SE FORMATEA, CONFIGURA E INICIALIZA EQUIPO, SE REALIZAN PRUEBAS OK. | W922: VISITA_TÉCNICA | X922: 103ZZ235 | Y922: TIPO I | Z922: TERRESTRE | AA922: FRANCO CAÑAVERAL YAMID RAUL | AB922: 1 | AC922: 0 | AD922: =IF(W922="SOPORTE_TELEFÓNICO",'BASE LIQUIDACION REDEBAN 2025'!$B$19,IF(W922="ENVÍO",'BASE LIQUIDACION REDEBAN 2025'!$C$2,IF(Y922="TIPO I",'BASE LIQUIDACION REDEBAN 2025'!$C$2,IF(Y922="TIPO II",'BASE LIQUIDACION REDEBAN 2025'!$C$3,IF(Y922="TIPO III",'BASE LIQUIDACION REDEBAN 2025'!$C$4,IF(Y922="TIPO IV",'BASE LIQUIDACION REDEBAN 2025'!$C$5,IF(Z922="AEREO",'BASE LIQUIDACION REDEBAN 2025'!$B$6,'BASE LIQUIDACION REDEBAN 2025'!$C$5))))))) -> 65960.072 | AE922: =IF(OR(W922="SOPORTE_TELEFÓNICO",W922="ENVÍO"),0,IF(Y922="TIPO I",'BASE LIQUIDACION REDEBAN 2025'!$B$10,IF(Y922="TIPO II",'BASE LIQUIDACION REDEBAN 2025'!$B$11,IF(Y922="TIPO III",'BASE LIQUIDACION REDEBAN 2025'!$B$12,'BASE LIQUIDACION REDEBAN 2025'!$B$13)))) -> 75096.394 | AF922: =IF(OR(W922="SOPORTE_TELEFÓNICO",W922="ENVÍO"),AD922,(AD922*AB922+AE922*AC922)) -> 65960.072
A923: MEDELLIN | B923: =VLOOKUP(A923,'CENTRO DE COSTOS'!A:D,4,FALSE) -> JUAN SEBASTIÁN RÍOS CASTRILLÓN | C923: =VLOOKUP(A923,'CENTRO DE COSTOS'!A:D,2,FALSE) -> 0004-0005 | D923: 5266 | E923: 2701369 | F923: 33059 | G923: INCIDENTE | H923: ANTIOQUIA | I923: ENVIGADO | J923: OPRAP CC VIVA ENVIGADO NORTE | K923: REDEBAN | L923: FO-25-1486351 | M923: 45905.576 | N923: 45906.492 | O923: NO | P923: HARDWARE | Q923: IMPRESION | R923: NO IMPRIME UNO O VARIOS CARACTERES | U923: CERRADO | V923: 06/09/2025 SE REALIZÓ CONTACTO TELEFÓNICO SE HABLÓ CON LA SEÑORA JULIETH NOS INDICA QUE LIMPIÓ LA IMPRESORA DEL DATÁFONO Y YA SE ENCUENTRA FUNCIONANDO NORMALMENTE SE PROCEDE A CERRAR CASO | W923: SOPORTE_TELEFÓNICO | X923: 0 | Y923: TIPO I | Z923: TERRESTRE | AA923: CASTAÑEDA PALACIO CARLOS FELIPE | AB923: 0 | AC923: 0 | AD923: =IF(W923="SOPORTE_TELEFÓNICO",'BASE LIQUIDACION REDEBAN 2025'!$B$19,IF(W923="ENVÍO",'BASE LIQUIDACION REDEBAN 2025'!$C$2,IF(Y923="TIPO I",'BASE LIQUIDACION REDEBAN 2025'!$C$2,IF(Y923="TIPO II",'BASE LIQUIDACION REDEBAN 2025'!$C$3,IF(Y923="TIPO III",'BASE LIQUIDACION REDEBAN 2025'!$C$4,IF(Y923="TIPO IV",'BASE LIQUIDACION REDEBAN 2025'!$C$5,IF(Z923="AEREO",'BASE LIQUIDACION REDEBAN 2025'!$B$6,'BASE LIQUIDACION REDEBAN 2025'!$C$5))))))) -> 41241.08 | AE923: =IF(OR(W923="SOPORTE_TELEFÓNICO",W923="ENVÍO"),0,IF(Y923="TIPO I",'BASE LIQUIDACION REDEBAN 2025'!$B$10,IF(Y923="TIPO II",'BASE LIQUIDACION REDEBAN 2025'!$B$11,IF(Y923="TIPO III",'BASE LIQUIDACION REDEBAN 2025'!$B$12,'BASE LIQUIDACION REDEBAN 2025'!$B$13)))) -> 0 | AF923: =IF(OR(W923="SOPORTE_TELEFÓNICO",W923="ENVÍO"),AD923,(AD923*AB923+AE923*AC923)) -> 41241.08
A924: MONTERIA | B924: =VLOOKUP(A924,'CENTRO DE COSTOS'!A:D,4,FALSE) -> JOSE MAURICIO HERNANDEZ ROJAS | C924: =VLOOKUP(A924,'CENTRO DE COSTOS'!A:D,2,FALSE) -> 0004-0001 | D924: 23001 | E924: 2701399 | F924: 69993 | G924: INCIDENTE | H924: CORDOBA | I924: MONTERIA | J924: BARRIO CENTRO MONTERIA 50 | K924: REDEBAN | L924: FO-25-1486344 | M924: 45905.587 | N924: 45906.494 | O924: NO | P924: HARDWARE | Q924: LECTOR DE BARRAS | R924: DAÑO POS | U924: CERRADO | V924: 06/09/2025 SE VISITA SITIO, SE CAMBIA LECTOR POR DAÑO, NO ENCIENDE OK SE REALIZAN PRUEBAS EXITOSAS | W924: VISITA_TÉCNICA | X924: UV001499 | Y924: TIPO I | Z924: TERRESTRE | AA924: COGOLLO VERTEL EDER LUIS | AB924: 1 | AC924: 0 | AD924: =IF(W924="SOPORTE_TELEFÓNICO",'BASE LIQUIDACION REDEBAN 2025'!$B$19,IF(W924="ENVÍO",'BASE LIQUIDACION REDEBAN 2025'!$C$2,IF(Y924="TIPO I",'BASE LIQUIDACION REDEBAN 2025'!$C$2,IF(Y924="TIPO II",'BASE LIQUIDACION REDEBAN 2025'!$C$3,IF(Y924="TIPO III",'BASE LIQUIDACION REDEBAN 2025'!$C$4,IF(Y924="TIPO IV",'BASE LIQUIDACION REDEBAN 2025'!$C$5,IF(Z924="AEREO",'BASE LIQUIDACION REDEBAN 2025'!$B$6,'BASE LIQUIDACION REDEBAN 2025'!$C$5))))))) -> 65960.072 | AE924: =IF(OR(W924="SOPORTE_TELEFÓNICO",W924="ENVÍO"),0,IF(Y924="TIPO I",'BASE LIQUIDACION REDEBAN 2025'!$B$10,IF(Y924="TIPO II",'BASE LIQUIDACION REDEBAN 2025'!$B$11,IF(Y924="TIPO III",'BASE LIQUIDACION REDEBAN 2025'!$B$12,'BASE LIQUIDACION REDEBAN 2025'!$B$13)))) -> 75096.394 | AF924: =IF(OR(W924="SOPORTE_TELEFÓNICO",W924="ENVÍO"),AD924,(AD924*AB924+AE924*AC924)) -> 65960.072
A925: BOGOTA | B925: =VLOOKUP(A925,'CENTRO DE COSTOS'!A:D,4,FALSE) -> WILLIAM ASDRUBAL ROZO ROZO | C925: =VLOOKUP(A925,'CENTRO DE COSTOS'!A:D,2,FALSE) -> 0004-0004 | D925: 11001 | E925: 2701278 | F925: 79611 | G925: INCIDENTE | H925: CUNDINAMARCA | I925: BOGOTA | J925: BARRIO SAN FRANCISCO BOGOTA 13 | K925: REDEBAN | L925: FO-25-1485772 | M925: 45905.545 | N925: 45906.475 | O925: NO | P925: SOFTWARE | Q925: LECTOR DE BARRAS | R925: LECTOR DESCONFIGURADO | U925: CERRADO | V925: 06/09/2025 SE REALIZA CONFIGURACIÓN DE LECTOR DE BARRA PRUEBAS OK | W925: VISITA_TÉCNICA | X925: SXUZZ137 | Y925: TIPO I | Z925: TERRESTRE | AA925: ORTIZ MARTINEZ STIVEN | AB925: 1 | AC925: 0 | AD925: =IF(W925="SOPORTE_TELEFÓNICO",'BASE LIQUIDACION REDEBAN 2025'!$B$19,IF(W925="ENVÍO",'BASE LIQUIDACION REDEBAN 2025'!$C$2,IF(Y925="TIPO I",'BASE LIQUIDACION REDEBAN 2025'!$C$2,IF(Y925="TIPO II",'BASE LIQUIDACION REDEBAN 2025'!$C$3,IF(Y925="TIPO III",'BASE LIQUIDACION REDEBAN 2025'!$C$4,IF(Y925="TIPO IV",'BASE LIQUIDACION REDEBAN 2025'!$C$5,IF(Z925="AEREO",'BASE LIQUIDACION REDEBAN 2025'!$B$6,'BASE LIQUIDACION REDEBAN 2025'!$C$5))))))) -> 65960.072 | AE925: =IF(OR(W925="SOPORTE_TELEFÓNICO",W925="ENVÍO"),0,IF(Y925="TIPO I",'BASE LIQUIDACION REDEBAN 2025'!$B$10,IF(Y925="TIPO II",'BASE LIQUIDACION REDEBAN 2025'!$B$11,IF(Y925="TIPO III",'BASE LIQUIDACION REDEBAN 2025'!$B$12,'BASE LIQUIDACION REDEBAN 2025'!$B$13)))) -> 75096.394 | AF925: =IF(OR(W925="SOPORTE_TELEFÓNICO",W925="ENVÍO"),AD925,(AD925*AB925+AE925*AC925)) -> 65960.072
A926: BOGOTA | B926: =VLOOKUP(A926,'CENTRO DE COSTOS'!A:D,4,FALSE) -> WILLIAM ASDRUBAL ROZO ROZO | C926: =VLOOKUP(A926,'CENTRO DE COSTOS'!A:D,2,FALSE) -> 0004-0004 | D926: 11001 | E926: 2701318 | F926: 22814 | G926: INCIDENTE | H926: CUNDINAMARCA | I926: BOGOTA | J926: MULTIPAGAS CHAPINERO | K926: REDEBAN | L926: FO-25-1485418 | M926: 45905.53 | N926: 45906.469 | O926: NO | P926: SOFTWARE | Q926: COMUNICACION | R926: PARAMETROS DE CONFIGURACION EN POS | U926: CERRADO | V926: 06/09/2025 SE VISITA COMERCIO CB BANCOLOMBIA ROBUSTO, SE DA UNA ESPERA DE 40 MIN PARA QUE PERMITAN EL ACCESO Y NO HAY RESPUESTA POR PARTE DE MONITOREO DEL PUNTO AUTORIZANDO EL INGRESO, SE TOMA EVIDENCIA DE LA VISITA Y SE LE INDICA A LA SRA CONSTANSA GUTIÉRREZ QUIÉN ATIENDE QUE DEBEN VOLVER A LLAMAR PARA SOLICITAR EL MANTENIMIENTO. | W926: VISITA_TÉCNICA | X926: NONE | Y926: TIPO I | Z926: TERRESTRE | AA926: VEGA MANRIQUE JONATAN MAURICIO | AB926: 1 | AC926: 0 | AD926: =IF(W926="SOPORTE_TELEFÓNICO",'BASE LIQUIDACION REDEBAN 2025'!$B$19,IF(W926="ENVÍO",'BASE LIQUIDACION REDEBAN 2025'!$C$2,IF(Y926="TIPO I",'BASE LIQUIDACION REDEBAN 2025'!$C$2,IF(Y926="TIPO II",'BASE LIQUIDACION REDEBAN 2025'!$C$3,IF(Y926="TIPO III",'BASE LIQUIDACION REDEBAN 2025'!$C$4,IF(Y926="TIPO IV",'BASE LIQUIDACION REDEBAN 2025'!$C$5,IF(Z926="AEREO",'BASE LIQUIDACION REDEBAN 2025'!$B$6,'BASE LIQUIDACION REDEBAN 2025'!$C$5))))))) -> 65960.072 | AE926: =IF(OR(W926="SOPORTE_TELEFÓNICO",W926="ENVÍO"),0,IF(Y926="TIPO I",'BASE LIQUIDACION REDEBAN 2025'!$B$10,IF(Y926="TIPO II",'BASE LIQUIDACION REDEBAN 2025'!$B$11,IF(Y926="TIPO III",'BASE LIQUIDACION REDEBAN 2025'!$B$12,'BASE LIQUIDACION REDEBAN 2025'!$B$13)))) -> 75096.394 | AF926: =IF(OR(W926="SOPORTE_TELEFÓNICO",W926="ENVÍO"),AD926,(AD926*AB926+AE926*AC926)) -> 65960.072
A927: PASTO | B927: =VLOOKUP(A927,'CENTRO DE COSTOS'!A:D,4,FALSE) -> DIEGO FERNANDO HENAO CARDONA | C927: =VLOOKUP(A927,'CENTRO DE COSTOS'!A:D,2,FALSE) -> 0004-0003 | D927: 52356 | E927: 2701085 | F927: 79560 | G927: INCIDENTE | H927: NARIÑO | I927: IPIALES | J927: BARRIO CHAMPAGNAT IPIALES 1 | K927: REDEBAN | L927: FO-25-1485403 | M927: 45905.52 | N927: 45906.666 | O927: NO | P927: HARDWARE | Q927: LECTOR DE BARRAS | R927: CABLE LECTORA AVERIADO | U927: CERRADO | V927: 06/09/2025 SE HABLA CON LA SEÑORA LUCY QUIEN INDICA QUE EL LECTOR ESTA TRABAJANDO SIN PROBLEMA, PERO QUE VIO QUE UN CABLE QUE ESTA POR DETRAS SE VE DESGASTADO, PERO NO LE HA GENERADO PROBLEMA , SOLO LLAMO YA QUE POR PREVENIR QUE MAS ADELANTE NO SE VAYA A DAÑAR, SE LE INDICA AL CLIENTE QUE SI DESEA SE PUEDDE REALIZAR CAMBIO DE LECTOR, PERO INDICA QUE CON LOS OTROS LECTORES NO LE FUNCIONA EL PAGO DE LA FACTURA CEDENAR Y QUE CON ESE QUE TIENE ALLI SI, SE LE INFORMA QUE SI EL LECTOR NO PRESENTA PROBLEMA NI SE APAGA PUEDE OPERARLO SIN PROBLEMA, LA USUARIA INDICA QUE EFECTIVAMENTE NO LE GENERA PROBLEMA Y LE TRABAJA NORMAL. SE CIERRA CASO, | W927: SOPORTE_TELEFÓNICO | X927: 0 | Y927: TIPO II | Z927: TERRESTRE | AA927: HENAO CARDONA DIEGO FERNANDO | AB927: 0 | AC927: 0 | AD927: =IF(W927="SOPORTE_TELEFÓNICO",'BASE LIQUIDACION REDEBAN 2025'!$B$19,IF(W927="ENVÍO",'BASE LIQUIDACION REDEBAN 2025'!$C$2,IF(Y927="TIPO I",'BASE LIQUIDACION REDEBAN 2025'!$C$2,IF(Y927="TIPO II",'BASE LIQUIDACION REDEBAN 2025'!$C$3,IF(Y927="TIPO III",'BASE LIQUIDACION REDEBAN 2025'!$C$4,IF(Y927="TIPO IV",'BASE LIQUIDACION REDEBAN 2025'!$C$5,IF(Z927="AEREO",'BASE LIQUIDACION REDEBAN 2025'!$B$6,'BASE LIQUIDACION REDEBAN 2025'!$C$5))))))) -> 41241.08 | AE927: =IF(OR(W927="SOPORTE_TELEFÓNICO",W927="ENVÍO"),0,IF(Y927="TIPO I",'BASE LIQUIDACION REDEBAN 2025'!$B$10,IF(Y927="TIPO II",'BASE LIQUIDACION REDEBAN 2025'!$B$11,IF(Y927="TIPO III",'BASE LIQUIDACION REDEBAN 2025'!$B$12,'BASE LIQUIDACION REDEBAN 2025'!$B$13)))) -> 0 | AF927: =IF(OR(W927="SOPORTE_TELEFÓNICO",W927="ENVÍO"),AD927,(AD927*AB927+AE927*AC927)) -> 41241.08
A928: SANTA MARTA | B928: =VLOOKUP(A928,'CENTRO DE COSTOS'!A:D,4,FALSE) -> JOSE MAURICIO HERNANDEZ ROJAS | C928: =VLOOKUP(A928,'CENTRO DE COSTOS'!A:D,2,FALSE) -> 0004-0001 | D928: 47555 | E928: 2701098 | F928: 21476 | G928: INCIDENTE | H928: MAGDALENA | I928: PLATO | J928: GUAYACANES PLATO MAGDALENA | K928: REDEBAN | L928: FO-25-1485399 | M928: 45905.523 | N928: 45909.497 | O928: NO | P928: SOFTWARE | Q928: COMUNICACION | R928: PARAMETROS DE CONFIGURACION EN POS | U928: CERRADO | V928: 09/09/2025 SE VISITA SITIO SE VERIFICA INFORMACIÓN SE REALIZA PRIMEROS AUXILIOS, SE RECONFIGURA LOS PARAMETROS DE COMUNICACION, SE REPISA TERMINAL, TECLADO OK, LECTOR DE CHIP OK, IMPRESIÓN OK, LECTORA OK, PRUEBA TRX EXITOSAS. | W928: VISITA_TÉCNICA | X928: FA0GZ599 | Y928: TIPO IV | Z928: TERRESTRE | AA928: SANTOS GUZMAN CHRISTIAN FELIPE | AB928: 1 | AC928: 0 | AD928: =IF(W928="SOPORTE_TELEFÓNICO",'BASE LIQUIDACION REDEBAN 2025'!$B$19,IF(W928="ENVÍO",'BASE LIQUIDACION REDEBAN 2025'!$C$2,IF(Y928="TIPO I",'BASE LIQUIDACION REDEBAN 2025'!$C$2,IF(Y928="TIPO II",'BASE LIQUIDACION REDEBAN 2025'!$C$3,IF(Y928="TIPO III",'BASE LIQUIDACION REDEBAN 2025'!$C$4,IF(Y928="TIPO IV",'BASE LIQUIDACION REDEBAN 2025'!$C$5,IF(Z928="AEREO",'BASE LIQUIDACION REDEBAN 2025'!$B$6,'BASE LIQUIDACION REDEBAN 2025'!$C$5))))))) -> 479588.88 | AE928: =IF(OR(W928="SOPORTE_TELEFÓNICO",W928="ENVÍO"),0,IF(Y928="TIPO I",'BASE LIQUIDACION REDEBAN 2025'!$B$10,IF(Y928="TIPO II",'BASE LIQUIDACION REDEBAN 2025'!$B$11,IF(Y928="TIPO III",'BASE LIQUIDACION REDEBAN 2025'!$B$12,'BASE LIQUIDACION REDEBAN 2025'!$B$13)))) -> 196536.53 | AF928: =IF(OR(W928="SOPORTE_TELEFÓNICO",W928="ENVÍO"),AD928,(AD928*AB928+AE928*AC928)) -> 479588.88
A929: PEREIRA | B929: =VLOOKUP(A929,'CENTRO DE COSTOS'!A:D,4,FALSE) -> DIEGO FERNANDO HENAO CARDONA | C929: =VLOOKUP(A929,'CENTRO DE COSTOS'!A:D,2,FALSE) -> 0004-0002 | D929: 66001 | E929: 2700398 | F929: 59520 | G929: INCIDENTE | H929: RISARALDA | I929: PEREIRA | J929: BARRIO ALTAGRACIA PEREIRA | K929: REDEBAN | L929: FO-25-1485324 | M929: 45905.468 | N929: 45906.456 | O929: NO | P929: SOFTWARE | Q929: LECTOR DE BARRAS | R929: LECTOR DESCONFIGURADO | U929: CERRADO | V929: 06/09/2025 SE REALIZA CONFIGURACIÓN DEL LECTOR Y SE REALIZAN PRUEBAS OK. | W929: VISITA_TÉCNICA | X929: JA007446 | Y929: TIPO I | Z929: TERRESTRE | AA929: FRANCO CAÑAVERAL YAMID RAUL | AB929: 1 | AC929: 0 | AD929: =IF(W929="SOPORTE_TELEFÓNICO",'BASE LIQUIDACION REDEBAN 2025'!$B$19,IF(W929="ENVÍO",'BASE LIQUIDACION REDEBAN 2025'!$C$2,IF(Y929="TIPO I",'BASE LIQUIDACION REDEBAN 2025'!$C$2,IF(Y929="TIPO II",'BASE LIQUIDACION REDEBAN 2025'!$C$3,IF(Y929="TIPO III",'BASE LIQUIDACION REDEBAN 2025'!$C$4,IF(Y929="TIPO IV",'BASE LIQUIDACION REDEBAN 2025'!$C$5,IF(Z929="AEREO",'BASE LIQUIDACION REDEBAN 2025'!$B$6,'BASE LIQUIDACION REDEBAN 2025'!$C$5))))))) -> 65960.072 | AE929: =IF(OR(W929="SOPORTE_TELEFÓNICO",W929="ENVÍO"),0,IF(Y929="TIPO I",'BASE LIQUIDACION REDEBAN 2025'!$B$10,IF(Y929="TIPO II",'BASE LIQUIDACION REDEBAN 2025'!$B$11,IF(Y929="TIPO III",'BASE LIQUIDACION REDEBAN 2025'!$B$12,'BASE LIQUIDACION REDEBAN 2025'!$B$13)))) -> 75096.394 | AF929: =IF(OR(W929="SOPORTE_TELEFÓNICO",W929="ENVÍO"),AD929,(AD929*AB929+AE929*AC929)) -> 65960.072
A930: VALLEDUPAR | B930: =VLOOKUP(A930,'CENTRO DE COSTOS'!A:D,4,FALSE) -> JOSE MAURICIO HERNANDEZ ROJAS | C930: =VLOOKUP(A930,'CENTRO DE COSTOS'!A:D,2,FALSE) -> 0004-0001 | D930: 20178 | E930: 2700622 | F930: 66228 | G930: INCIDENTE | H930: CESAR | I930: CHIRIGUANA | J930: BARRIO CENTRO CHIRIGUANA 4 | K930: REDEBAN | L930: FO-25-1485318 | M930: 45905.478 | N930: 45908.424 | O930: NO | P930: HARDWARE | Q930: COMUNICACION | R930: CAMBIO DE IP | U930: CERRADO | V930: 08/09/2025 BUENOS DÍAS SE VISITA CB Y SE ENCUENTRA CON ERROR DE COMUNICACIÓN, SE BORRA APLICATIVO Y SE LE ASIGNAN LOS PARÁMETROS NUEVAMENTE . SE HACEN PRUEBAS DE TRANSACCIONES Y SE DEJA TODO OK | W930: VISITA_TÉCNICA | X930: 2A00L3069.9 | Y930: TIPO III | Z930: TERRESTRE | AA930: BENITEZ CARVAJAL ALVARO JAVIER | AB930: 1 | AC930: 0 | AD930: =IF(W930="SOPORTE_TELEFÓNICO",'BASE LIQUIDACION REDEBAN 2025'!$B$19,IF(W930="ENVÍO",'BASE LIQUIDACION REDEBAN 2025'!$C$2,IF(Y930="TIPO I",'BASE LIQUIDACION REDEBAN 2025'!$C$2,IF(Y930="TIPO II",'BASE LIQUIDACION REDEBAN 2025'!$C$3,IF(Y930="TIPO III",'BASE LIQUIDACION REDEBAN 2025'!$C$4,IF(Y930="TIPO IV",'BASE LIQUIDACION REDEBAN 2025'!$C$5,IF(Z930="AEREO",'BASE LIQUIDACION REDEBAN 2025'!$B$6,'BASE LIQUIDACION REDEBAN 2025'!$C$5))))))) -> 275728.78 | AE930: =IF(OR(W930="SOPORTE_TELEFÓNICO",W930="ENVÍO"),0,IF(Y930="TIPO I",'BASE LIQUIDACION REDEBAN 2025'!$B$10,IF(Y930="TIPO II",'BASE LIQUIDACION REDEBAN 2025'!$B$11,IF(Y930="TIPO III",'BASE LIQUIDACION REDEBAN 2025'!$B$12,'BASE LIQUIDACION REDEBAN 2025'!$B$13)))) -> 196536.53 | AF930: =IF(OR(W930="SOPORTE_TELEFÓNICO",W930="ENVÍO"),AD930,(AD930*AB930+AE930*AC930)) -> 275728.78
A931: BOGOTA | B931: =VLOOKUP(A931,'CENTRO DE COSTOS'!A:D,4,FALSE) -> WILLIAM ASDRUBAL ROZO ROZO | C931: =VLOOKUP(A931,'CENTRO DE COSTOS'!A:D,2,FALSE) -> 0004-0004 | D931: 25754 | E931: 2700938 | F931: 72701 | G931: INCIDENTE | H931: CUNDINAMARCA | I931: SOACHA | J931: PRADO VEGAS SOACHA 2 | K931: REDEBAN | L931: FO-25-1485313 | M931: 45905.498 | N931: 45906.465 | O931: NO | P931: HARDWARE | Q931: PINPAD | R931: ALERTADO | U931: CERRADO | V931: 06/09/2025 SE REALIZA VISITA DE CAMPO ENCONTRANDO QUE DATÁFONO SE REINICIA AL REALIZAR TX SE REALIZA CAMBIO DE EQUIPO CON PINPAD Y HUB POR COMPATIBILIDAD CON EL DATAFONO PRUEBA OK PARÁMETROS OKAY CIERRE OKAY | W931: VISITA_TÉCNICA | X931: EF00R078 | Y931: TIPO I | Z931: TERRESTRE | AA931: GALEANO SORIANO JUAN DAVID | AB931: 1 | AC931: 0 | AD931: =IF(W931="SOPORTE_TELEFÓNICO",'BASE LIQUIDACION REDEBAN 2025'!$B$19,IF(W931="ENVÍO",'BASE LIQUIDACION REDEBAN 2025'!$C$2,IF(Y931="TIPO I",'BASE LIQUIDACION REDEBAN 2025'!$C$2,IF(Y931="TIPO II",'BASE LIQUIDACION REDEBAN 2025'!$C$3,IF(Y931="TIPO III",'BASE LIQUIDACION REDEBAN 2025'!$C$4,IF(Y931="TIPO IV",'BASE LIQUIDACION REDEBAN 2025'!$C$5,IF(Z931="AEREO",'BASE LIQUIDACION REDEBAN 2025'!$B$6,'BASE LIQUIDACION REDEBAN 2025'!$C$5))))))) -> 65960.072 | AE931: =IF(OR(W931="SOPORTE_TELEFÓNICO",W931="ENVÍO"),0,IF(Y931="TIPO I",'BASE LIQUIDACION REDEBAN 2025'!$B$10,IF(Y931="TIPO II",'BASE LIQUIDACION REDEBAN 2025'!$B$11,IF(Y931="TIPO III",'BASE LIQUIDACION REDEBAN 2025'!$B$12,'BASE LIQUIDACION REDEBAN 2025'!$B$13)))) -> 75096.394 | AF931: =IF(OR(W931="SOPORTE_TELEFÓNICO",W931="ENVÍO"),AD931,(AD931*AB931+AE931*AC931)) -> 65960.072
... A1037: NEIVA | B1037: =VLOOKUP(A1037,'CENTRO DE COSTOS'!A:D,4,FALSE) -> KEVIN ALEXIS CORZO BUSTOS | C1037: =VLOOKUP(A1037,'CENTRO DE COSTOS'!A:D,2,FALSE) -> 0004-0007 | D1037: 18753 | E1037: 2687441 | F1037: 60174 | G1037: INCIDENTE | H1037: CAQUETA | I1037: SAN VICENTE DEL CAGUAN | J1037: BARRIO PALMERAS BAJAS SAN VICE | K1037: REDEBAN | L1037: FO-25-1467601 | M1037: 45903.447 | N1037: 45905.515 | O1037: NO | P1037: HARDWARE | Q1037: NO ENCIENDE | R1037: DAÑO POS | U1037: CERRADO | V1037: 05/09/2025 SE REALIZA CAMBIO DE DATÁFONO YA QUE EN TODAS LAS OPERACIONES SE REINICIA Y SE APAGA, ALGUNAS VECES NO PRENDE, PRUEBAS CB OK SE DEJA OPERATIVO | W1037: VISITA_TÉCNICA | X1037: 10000024 | Y1037: TIPO IV ESPECIAL | Z1037: TERRESTRE / AEREO | AA1037: BERMUDEZ SANCHEZ JOSE NEYBER | AB1037: 1 | AC1037: 0 | AD1037: =IF(W1037="SOPORTE_TELEFÓNICO",'BASE LIQUIDACION REDEBAN 2025'!$B$19,IF(W1037="ENVÍO",'BASE LIQUIDACION REDEBAN 2025'!$C$2,IF(Y1037="TIPO I",'BASE LIQUIDACION REDEBAN 2025'!$C$2,IF(Y1037="TIPO II",'BASE LIQUIDACION REDEBAN 2025'!$C$3,IF(Y1037="TIPO III",'BASE LIQUIDACION REDEBAN 2025'!$C$4,IF(Y1037="TIPO IV",'BASE LIQUIDACION REDEBAN 2025'!$C$5,IF(Z1037="AEREO",'BASE LIQUIDACION REDEBAN 2025'!$B$6,'BASE LIQUIDACION REDEBAN 2025'!$C$5))))))) -> 479588.88 | AE1037: =IF(OR(W1037="SOPORTE_TELEFÓNICO",W1037="ENVÍO"),0,IF(Y1037="TIPO I",'BASE LIQUIDACION REDEBAN 2025'!$B$10,IF(Y1037="TIPO II",'BASE LIQUIDACION REDEBAN 2025'!$B$11,IF(Y1037="TIPO III",'BASE LIQUIDACION REDEBAN 2025'!$B$12,'BASE LIQUIDACION REDEBAN 2025'!$B$13)))) -> 196536.53 | AF1037: =IF(OR(W1037="SOPORTE_TELEFÓNICO",W1037="ENVÍO"),AD1037,(AD1037*AB1037+AE1037*AC1037)) -> 479588.88
A1038: BOGOTA | B1038: =VLOOKUP(A1038,'CENTRO DE COSTOS'!A:D,4,FALSE) -> WILLIAM ASDRUBAL ROZO ROZO | C1038: =VLOOKUP(A1038,'CENTRO DE COSTOS'!A:D,2,FALSE) -> 0004-0004 | D1038: 11001 | E1038: 2687457 | F1038: 34383 | G1038: INCIDENTE | H1038: CUNDINAMARCA | I1038: BOGOTA | J1038: REVAL GRANSAN | K1038: REDEBAN | L1038: FO-25-1467593 | M1038: 45903.449 | N1038: 45903.73 | O1038: NO | P1038: HARDWARE | Q1038: IMPRESION | R1038: NO AVANZA PAPEL | U1038: CERRADO | V1038: 03/09/2025 CAMBIO DE EQUIPO Y TECNOLOGÍA DE 3500 A 2600 PRUEBAS OK | W1038: VISITA_TÉCNICA | Y1038: TIPO I | Z1038: TERRESTRE | AA1038: ROZO ROZO WILLIAM ASDRUBAL | AB1038: 1 | AC1038: 0 | AD1038: =IF(W1038="SOPORTE_TELEFÓNICO",'BASE LIQUIDACION REDEBAN 2025'!$B$19,IF(W1038="ENVÍO",'BASE LIQUIDACION REDEBAN 2025'!$C$2,IF(Y1038="TIPO I",'BASE LIQUIDACION REDEBAN 2025'!$C$2,IF(Y1038="TIPO II",'BASE LIQUIDACION REDEBAN 2025'!$C$3,IF(Y1038="TIPO III",'BASE LIQUIDACION REDEBAN 2025'!$C$4,IF(Y1038="TIPO IV",'BASE LIQUIDACION REDEBAN 2025'!$C$5,IF(Z1038="AEREO",'BASE LIQUIDACION REDEBAN 2025'!$B$6,'BASE LIQUIDACION REDEBAN 2025'!$C$5))))))) -> 65960.072 | AE1038: =IF(OR(W1038="SOPORTE_TELEFÓNICO",W1038="ENVÍO"),0,IF(Y1038="TIPO I",'BASE LIQUIDACION REDEBAN 2025'!$B$10,IF(Y1038="TIPO II",'BASE LIQUIDACION REDEBAN 2025'!$B$11,IF(Y1038="TIPO III",'BASE LIQUIDACION REDEBAN 2025'!$B$12,'BASE LIQUIDACION REDEBAN 2025'!$B$13)))) -> 75096.394 | AF1038: =IF(OR(W1038="SOPORTE_TELEFÓNICO",W1038="ENVÍO"),AD1038,(AD1038*AB1038+AE1038*AC1038)) -> 65960.072
A1039: MEDELLIN | B1039: =VLOOKUP(A1039,'CENTRO DE COSTOS'!A:D,4,FALSE) -> JUAN SEBASTIÁN RÍOS CASTRILLÓN | C1039: =VLOOKUP(A1039,'CENTRO DE COSTOS'!A:D,2,FALSE) -> 0004-0005 | D1039: 5856 | E1039: 2687387 | F1039: 37717 | G1039: INCIDENTE | H1039: ANTIOQUIA | I1039: VALPARAISO | J1039: BARRIO PARQUE VALPARAISO | K1039: REDEBAN | L1039: FO-25-1467585 | M1039: 45903.45 | N1039: 45904.647 | O1039: NO | P1039: HARDWARE | Q1039: COMUNICACION | R1039: DAÑO POS | U1039: CERRADO | V1039: 04/09/2025 SE REALIZA VISITA TÉCNICA EN RESPUESTA AL INCIDENTE PREVIAMENTE REPORTADO. AL LLEGAR AL PUNTO, EL USUARIO INFORMA QUE EL DATÁFONO NO LOGRA CONECTARSE A INTERNET. ADICIONALMENTE, MENCIONA QUE RECIENTEMENTE OCURRIÓ UN HURACÁN EN LA ZONA, LO CUAL PROVOCÓ UN CORTOCIRCUITO. SE PROCEDE A VALIDAR EL ESTADO DEL EQUIPO Y SE CONSTATA QUE EL DATÁFONO PRESENTA DAÑOS ELÉCTRICOS VISIBLES, COMPATIBLES CON SOBRECARGA POR EVENTO CLIMÁTICO. EL EQUIPO SE ENCUENTRA QUEMADO, LO QUE IMPIDE SU FUNCIONAMIENTO Y CONEXIÓN A LA RED. DEBIDO A LA MAGNITUD DEL DAÑO, SE DETERMINA QUE EL EQUIPO NO ES RECUPERABLE Y REQUIERE REEMPLAZO. SE REALIZA EL CAMBIO POR UN DATÁFONO NUEVO, EL CUAL QUEDA INSTALADO Y OPERATIVO, CON CONEXIÓN ESTABLE A INTERNET Y FUNCIONAMIENTO NORMAL. | W1039: VISITA_TÉCNICA | X1039: AA00P624 | Y1039: TIPO III | Z1039: TERRESTRE | AA1039: MARTINEZ TOVAR OSCAR DAVID | AB1039: 1 | AC1039: 0 | AD1039: =IF(W1039="SOPORTE_TELEFÓNICO",'BASE LIQUIDACION REDEBAN 2025'!$B$19,IF(W1039="ENVÍO",'BASE LIQUIDACION REDEBAN 2025'!$C$2,IF(Y1039="TIPO I",'BASE LIQUIDACION REDEBAN 2025'!$C$2,IF(Y1039="TIPO II",'BASE LIQUIDACION REDEBAN 2025'!$C$3,IF(Y1039="TIPO III",'BASE LIQUIDACION REDEBAN 2025'!$C$4,IF(Y1039="TIPO IV",'BASE LIQUIDACION REDEBAN 2025'!$C$5,IF(Z1039="AEREO",'BASE LIQUIDACION REDEBAN 2025'!$B$6,'BASE LIQUIDACION REDEBAN 2025'!$C$5))))))) -> 275728.78 | AE1039: =IF(OR(W1039="SOPORTE_TELEFÓNICO",W1039="ENVÍO"),0,IF(Y1039="TIPO I",'BASE LIQUIDACION REDEBAN 2025'!$B$10,IF(Y1039="TIPO II",'BASE LIQUIDACION REDEBAN 2025'!$B$11,IF(Y1039="TIPO III",'BASE LIQUIDACION REDEBAN 2025'!$B$12,'BASE LIQUIDACION REDEBAN 2025'!$B$13)))) -> 196536.53 | AF1039: =IF(OR(W1039="SOPORTE_TELEFÓNICO",W1039="ENVÍO"),AD1039,(AD1039*AB1039+AE1039*AC1039)) -> 275728.78
A1040: BOGOTA | B1040: =VLOOKUP(A1040,'CENTRO DE COSTOS'!A:D,4,FALSE) -> WILLIAM ASDRUBAL ROZO ROZO | C1040: =VLOOKUP(A1040,'CENTRO DE COSTOS'!A:D,2,FALSE) -> 0004-0004 | D1040: 11001 | E1040: 2687606 | F1040: 61769 | G1040: INCIDENTE | H1040: CUNDINAMARCA | I1040: BOGOTA | J1040: PTM BOGOTA SURICAT3 | K1040: REDEBAN | L1040: FO-25-1467580 | M1040: 45903.451 | N1040: 45903.694 | O1040: NO | P1040: HARDWARE | Q1040: ALERT IRRUPTION | R1040: ALERT IRRUPTION | U1040: CERRADO | V1040: 03/09/2025 CAMBIO DE EQUIPO POR DAÑO SE REALIZA PRUEBAS OK SE ENTREGA SERVICIO OPERATIVO | W1040: VISITA_TÉCNICA | X1040: HA00L016 | Y1040: TIPO I | Z1040: TERRESTRE | AA1040: HERNANDEZ NARANJO OSCAR EDUARDO | AB1040: 1 | AC1040: 0 | AD1040: =IF(W1040="SOPORTE_TELEFÓNICO",'BASE LIQUIDACION REDEBAN 2025'!$B$19,IF(W1040="ENVÍO",'BASE LIQUIDACION REDEBAN 2025'!$C$2,IF(Y1040="TIPO I",'BASE LIQUIDACION REDEBAN 2025'!$C$2,IF(Y1040="TIPO II",'BASE LIQUIDACION REDEBAN 2025'!$C$3,IF(Y1040="TIPO III",'BASE LIQUIDACION REDEBAN 2025'!$C$4,IF(Y1040="TIPO IV",'BASE LIQUIDACION REDEBAN 2025'!$C$5,IF(Z1040="AEREO",'BASE LIQUIDACION REDEBAN 2025'!$B$6,'BASE LIQUIDACION REDEBAN 2025'!$C$5))))))) -> 65960.072 | AE1040: =IF(OR(W1040="SOPORTE_TELEFÓNICO",W1040="ENVÍO"),0,IF(Y1040="TIPO I",'BASE LIQUIDACION REDEBAN 2025'!$B$10,IF(Y1040="TIPO II",'BASE LIQUIDACION REDEBAN 2025'!$B$11,IF(Y1040="TIPO III",'BASE LIQUIDACION REDEBAN 2025'!$B$12,'BASE LIQUIDACION REDEBAN 2025'!$B$13)))) -> 75096.394 | AF1040: =IF(OR(W1040="SOPORTE_TELEFÓNICO",W1040="ENVÍO"),AD1040,(AD1040*AB1040+AE1040*AC1040)) -> 65960.072
A1041: MEDELLIN | B1041: =VLOOKUP(A1041,'CENTRO DE COSTOS'!A:D,4,FALSE) -> JUAN SEBASTIÁN RÍOS CASTRILLÓN | C1041: =VLOOKUP(A1041,'CENTRO DE COSTOS'!A:D,2,FALSE) -> 0004-0005 | D1041: 15572 | E1041: 2687721 | F1041: 44951 | G1041: INCIDENTE | H1041: BOYACA | I1041: PUERTO BOYACA | J1041: DISTRICOL TIENDA JUANICA | K1041: REDEBAN | L1041: FO-25-1467572 | M1041: 45903.458 | N1041: 45904.699 | O1041: NO | P1041: HARDWARE | Q1041: IMPRESION | R1041: NO AVANZA PAPEL | U1041: CERRADO | V1041: 04/09/2025 CAMBIO DE FUENTE DE PODER OK PRUEBAS OK | W1041: VISITA_TÉCNICA | X1041: AB1HZ999 | Y1041: TIPO IV | Z1041: TERRESTRE | AA1041: PAREJA ECHAVARRIA JHON DAVID | AB1041: 1 | AC1041: 0 | AD1041: =IF(W1041="SOPORTE_TELEFÓNICO",'BASE LIQUIDACION REDEBAN 2025'!$B$19,IF(W1041="ENVÍO",'BASE LIQUIDACION REDEBAN 2025'!$C$2,IF(Y1041="TIPO I",'BASE LIQUIDACION REDEBAN 2025'!$C$2,IF(Y1041="TIPO II",'BASE LIQUIDACION REDEBAN 2025'!$C$3,IF(Y1041="TIPO III",'BASE LIQUIDACION REDEBAN 2025'!$C$4,IF(Y1041="TIPO IV",'BASE LIQUIDACION REDEBAN 2025'!$C$5,IF(Z1041="AEREO",'BASE LIQUIDACION REDEBAN 2025'!$B$6,'BASE LIQUIDACION REDEBAN 2025'!$C$5))))))) -> 479588.88 | AE1041: =IF(OR(W1041="SOPORTE_TELEFÓNICO",W1041="ENVÍO"),0,IF(Y1041="TIPO I",'BASE LIQUIDACION REDEBAN 2025'!$B$10,IF(Y1041="TIPO II",'BASE LIQUIDACION REDEBAN 2025'!$B$11,IF(Y1041="TIPO III",'BASE LIQUIDACION REDEBAN 2025'!$B$12,'BASE LIQUIDACION REDEBAN 2025'!$B$13)))) -> 196536.53 | AF1041: =IF(OR(W1041="SOPORTE_TELEFÓNICO",W1041="ENVÍO"),AD1041,(AD1041*AB1041+AE1041*AC1041)) -> 479588.88
A1042: CARTAGENA | B1042: =VLOOKUP(A1042,'CENTRO DE COSTOS'!A:D,4,FALSE) -> JOSE MAURICIO HERNANDEZ ROJAS | C1042: =VLOOKUP(A1042,'CENTRO DE COSTOS'!A:D,2,FALSE) -> 0004-0001 | D1042: 13001 | E1042: 2687932 | F1042: 77917 | G1042: INCIDENTE | H1042: BOLIVAR | I1042: CARTAGENA | J1042: "BARRIO SAN JOSE DE LOS CAMPANOS CARTAGENA DE INDIAS" | K1042: REDEBAN | L1042: FO-25-1467566 | M1042: 45903.472 | N1042: 45904.407 | O1042: NO | P1042: SOFTWARE | Q1042: COMUNICACION | R1042: PARAMETROS DE CONFIGURACION EN POS | U1042: CERRADO | V1042: 04/09/2025 BUEN DIA SE RECONFIGURAN PARÁMETROS DE COMUNICACIÓN SE REALIZA PRUEBA Y TODO QUEDA OK | W1042: VISITA_TÉCNICA | X1042: A1NZZ359 | Y1042: TIPO I | Z1042: TERRESTRE | AA1042: MARTINEZ SALGUEDO ANDRES AUGUSTO | AB1042: 1 | AC1042: 0 | AD1042: =IF(W1042="SOPORTE_TELEFÓNICO",'BASE LIQUIDACION REDEBAN 2025'!$B$19,IF(W1042="ENVÍO",'BASE LIQUIDACION REDEBAN 2025'!$C$2,IF(Y1042="TIPO I",'BASE LIQUIDACION REDEBAN 2025'!$C$2,IF(Y1042="TIPO II",'BASE LIQUIDACION REDEBAN 2025'!$C$3,IF(Y1042="TIPO III",'BASE LIQUIDACION REDEBAN 2025'!$C$4,IF(Y1042="TIPO IV",'BASE LIQUIDACION REDEBAN 2025'!$C$5,IF(Z1042="AEREO",'BASE LIQUIDACION REDEBAN 2025'!$B$6,'BASE LIQUIDACION REDEBAN 2025'!$C$5))))))) -> 65960.072 | AE1042: =IF(OR(W1042="SOPORTE_TELEFÓNICO",W1042="ENVÍO"),0,IF(Y1042="TIPO I",'BASE LIQUIDACION REDEBAN 2025'!$B$10,IF(Y1042="TIPO II",'BASE LIQUIDACION REDEBAN 2025'!$B$11,IF(Y1042="TIPO III",'BASE LIQUIDACION REDEBAN 2025'!$B$12,'BASE LIQUIDACION REDEBAN 2025'!$B$13)))) -> 75096.394 | AF1042: =IF(OR(W1042="SOPORTE_TELEFÓNICO",W1042="ENVÍO"),AD1042,(AD1042*AB1042+AE1042*AC1042)) -> 65960.072
A1043: BUCARAMANGA | B1043: =VLOOKUP(A1043,'CENTRO DE COSTOS'!A:D,4,FALSE) -> MIGUEL JULIÁN HERNÁNDEZ GUARÍN | C1043: =VLOOKUP(A1043,'CENTRO DE COSTOS'!A:D,2,FALSE) -> 0004-0008 | D1043: 68276 | E1043: 2688582 | F1043: 58447 | G1043: INCIDENTE | H1043: SANTANDER | I1043: FLORIDABLANCA | J1043: PTM FLORIDABLANCA TIENDA MARIA | K1043: REDEBAN | L1043: FO-25-1467562 | M1043: 45903.508 | N1043: 45903.722 | O1043: NO | P1043: HARDWARE | Q1043: LECTOR DE BARRAS | R1043: CABLE LECTORA AVERIADO | U1043: CERRADO | V1043: 03/09/2025 SE REALIZA CAMBIO DE LECTOR DE BARRAS POR DAÑO SE REINICIA, PRUEBAS Y LIMPIEZA DE EQUIPOS OK. CB MIXTO TERMINAL TUZZZ922 | W1043: VISITA_TÉCNICA | X1043: XYZZZ954 | Y1043: TIPO I | Z1043: TERRESTRE | AA1043: MARTINEZ FLOREZ DONIS ALBERTO | AB1043: 1 | AC1043: 0 | AD1043: =IF(W1043="SOPORTE_TELEFÓNICO",'BASE LIQUIDACION REDEBAN 2025'!$B$19,IF(W1043="ENVÍO",'BASE LIQUIDACION REDEBAN 2025'!$C$2,IF(Y1043="TIPO I",'BASE LIQUIDACION REDEBAN 2025'!$C$2,IF(Y1043="TIPO II",'BASE LIQUIDACION REDEBAN 2025'!$C$3,IF(Y1043="TIPO III",'BASE LIQUIDACION REDEBAN 2025'!$C$4,IF(Y1043="TIPO IV",'BASE LIQUIDACION REDEBAN 2025'!$C$5,IF(Z1043="AEREO",'BASE LIQUIDACION REDEBAN 2025'!$B$6,'BASE LIQUIDACION REDEBAN 2025'!$C$5))))))) -> 65960.072 | AE1043: =IF(OR(W1043="SOPORTE_TELEFÓNICO",W1043="ENVÍO"),0,IF(Y1043="TIPO I",'BASE LIQUIDACION REDEBAN 2025'!$B$10,IF(Y1043="TIPO II",'BASE LIQUIDACION REDEBAN 2025'!$B$11,IF(Y1043="TIPO III",'BASE LIQUIDACION REDEBAN 2025'!$B$12,'BASE LIQUIDACION REDEBAN 2025'!$B$13)))) -> 75096.394 | AF1043: =IF(OR(W1043="SOPORTE_TELEFÓNICO",W1043="ENVÍO"),AD1043,(AD1043*AB1043+AE1043*AC1043)) -> 65960.072
A1044: TUNJA | B1044: =VLOOKUP(A1044,'CENTRO DE COSTOS'!A:D,4,FALSE) -> MIGUEL JULIÁN HERNÁNDEZ GUARÍN | C1044: =VLOOKUP(A1044,'CENTRO DE COSTOS'!A:D,2,FALSE) -> 0004-0008 | D1044: 15897 | E1044: 2688585 | F1044: 75885 | G1044: INCIDENTE | H1044: BOYACA | I1044: ZETAQUIRA | J1044: BARRIO LA PAZ ZETAQUIRA | K1044: REDEBAN | L1044: FO-25-1467557 | M1044: 45903.51 | N1044: 45903.675 | O1044: NO | P1044: SOFTWARE | Q1044: LECTOR DE TARJETAS | R1044: CTL CONFIGURACION LECTOR INTERNAL | U1044: CERRADO | V1044: 03/09/2025 SE ESTABLECE COMUNICACIÓN CON LA SEÑORA MARCELA ROMERO AL NÚMERO DE CONTACTO 3144256609 CLIENTE INDICA QUE LA ORDEN FUE GENERADA DEBIDO A QUE EN HORAS DE LA MAÑANA LE PRESENTO EL ERROR PIN INVÁLIDO EN UN RETIRO CON TARJETA CLIENTE REALIZA TRX CON LA TARJETA PERSONAL DE ELLA EVIDENCIANDO QUE EL EQUIPO SE ENCUENTRA FUNCIONANDO CORRECTAMENTE CORRESPONSAL OPERATIVO NO REQUIERE DE LA VISITA TÉCNICA COMPARTE EVIDENCIA VERIFICANDO QUE EL CORRESPONSAL SE ENCUENTRA OPERATIVO SE LE INDICA QUE SE PROCEDERÁ CON EL CIERRE DE LA ORDEN DE TRABAJO GENERADA ADICIONAL SE LE SUGIERE QUE EN CASO DE VOLVER A PRESENTAR ESA FALLA CON ALGUNA TARJETA SUGERIRLE AL CLIENTE UN CAMBIO DE CLAVE CLIENTE CONFORME | W1044: SOPORTE_TELEFÓNICO | X1044: 0 | Y1044: TIPO III | Z1044: TERRESTRE | AA1044: RODRIGUEZ MURCIA YERSON IVAN | AB1044: 0 | AC1044: 0 | AD1044: =IF(W1044="SOPORTE_TELEFÓNICO",'BASE LIQUIDACION REDEBAN 2025'!$B$19,IF(W1044="ENVÍO",'BASE LIQUIDACION REDEBAN 2025'!$C$2,IF(Y1044="TIPO I",'BASE LIQUIDACION REDEBAN 2025'!$C$2,IF(Y1044="TIPO II",'BASE LIQUIDACION REDEBAN 2025'!$C$3,IF(Y1044="TIPO III",'BASE LIQUIDACION REDEBAN 2025'!$C$4,IF(Y1044="TIPO IV",'BASE LIQUIDACION REDEBAN 2025'!$C$5,IF(Z1044="AEREO",'BASE LIQUIDACION REDEBAN 2025'!$B$6,'BASE LIQUIDACION REDEBAN 2025'!$C$5))))))) -> 41241.08 | AE1044: =IF(OR(W1044="SOPORTE_TELEFÓNICO",W1044="ENVÍO"),0,IF(Y1044="TIPO I",'BASE LIQUIDACION REDEBAN 2025'!$B$10,IF(Y1044="TIPO II",'BASE LIQUIDACION REDEBAN 2025'!$B$11,IF(Y1044="TIPO III",'BASE LIQUIDACION REDEBAN 2025'!$B$12,'BASE LIQUIDACION REDEBAN 2025'!$B$13)))) -> 0 | AF1044: =IF(OR(W1044="SOPORTE_TELEFÓNICO",W1044="ENVÍO"),AD1044,(AD1044*AB1044+AE1044*AC1044)) -> 41241.08
A1045: IBAGUE | B1045: =VLOOKUP(A1045,'CENTRO DE COSTOS'!A:D,4,FALSE) -> KEVIN ALEXIS CORZO BUSTOS | C1045: =VLOOKUP(A1045,'CENTRO DE COSTOS'!A:D,2,FALSE) -> 0004-0007 | D1045: 73319 | E1045: 2685791 | F1045: 35171 | G1045: INCIDENTE | H1045: TOLIMA | I1045: GUAMO | J1045: COMCARD GUAMO PANALES | K1045: REDEBAN | L1045: FO-25-1467126 | M1045: 45903.375 | N1045: 45904.601 | O1045: NO | P1045: HARDWARE | Q1045: NO ENCIENDE SE REINICIA | R1045: FUENTE PODER AVERIADA | U1045: CERRADO | V1045: 04/09/2025 SE CAMBIA FUENTE DE PODER POR DETERIORO. SE HACEN HACEN PRUEBAS DE TRANSACCIONES TODO OK ESE ⅘ | W1045: VISITA_TÉCNICA | X1045: BL0CZ353 - MA00B657 | Y1045: TIPO II | Z1045: TERRESTRE | AA1045: VARGAS HERRERA JHON JAIRO | AB1045: 1 | AC1045: 0 | AD1045: =IF(W1045="SOPORTE_TELEFÓNICO",'BASE LIQUIDACION REDEBAN 2025'!$B$19,IF(W1045="ENVÍO",'BASE LIQUIDACION REDEBAN 2025'!$C$2,IF(Y1045="TIPO I",'BASE LIQUIDACION REDEBAN 2025'!$C$2,IF(Y1045="TIPO II",'BASE LIQUIDACION REDEBAN 2025'!$C$3,IF(Y1045="TIPO III",'BASE LIQUIDACION REDEBAN 2025'!$C$4,IF(Y1045="TIPO IV",'BASE LIQUIDACION REDEBAN 2025'!$C$5,IF(Z1045="AEREO",'BASE LIQUIDACION REDEBAN 2025'!$B$6,'BASE LIQUIDACION REDEBAN 2025'!$C$5))))))) -> 144967.87 | AE1045: =IF(OR(W1045="SOPORTE_TELEFÓNICO",W1045="ENVÍO"),0,IF(Y1045="TIPO I",'BASE LIQUIDACION REDEBAN 2025'!$B$10,IF(Y1045="TIPO II",'BASE LIQUIDACION REDEBAN 2025'!$B$11,IF(Y1045="TIPO III",'BASE LIQUIDACION REDEBAN 2025'!$B$12,'BASE LIQUIDACION REDEBAN 2025'!$B$13)))) -> 140395.63 | AF1045: =IF(OR(W1045="SOPORTE_TELEFÓNICO",W1045="ENVÍO"),AD1045,(AD1045*AB1045+AE1045*AC1045)) -> 144967.87
A1046: CALI | B1046: =VLOOKUP(A1046,'CENTRO DE COSTOS'!A:D,4,FALSE) -> DIEGO FERNANDO HENAO CARDONA | C1046: =VLOOKUP(A1046,'CENTRO DE COSTOS'!A:D,2,FALSE) -> 0004-0003 | D1046: 76364 | E1046: 2686006 | F1046: 80158 | G1046: INCIDENTE | H1046: VALLE DEL CAUCA | I1046: JAMUNDI | J1046: BARRIO POPULAR JAMUNDI 2 | K1046: REDEBAN | L1046: FO-25-1467123 | M1046: 45903.378 | N1046: 45903.671 | O1046: NO | P1046: HARDWARE | Q1046: CABLEADO | R1046: CABLE MAGICBOX AVERIADO | U1046: CERRADO | V1046: 03/09/2025 SE VISITA CORRESPONSAL Y SE REEMPLAZA CABLE DE PIN PAD POR DAÑO. TRANSACCIONES DE PRUEBA EXITOSAS. | W1046: VISITA_TÉCNICA | X1046: F1ZZZ704 | Y1046: TIPO II | Z1046: TERRESTRE | AA1046: BOLAÑOS TABORDA JORGE ENRIQUE | AB1046: 1 | AC1046: 0 | AD1046: =IF(W1046="SOPORTE_TELEFÓNICO",'BASE LIQUIDACION REDEBAN 2025'!$B$19,IF(W1046="ENVÍO",'BASE LIQUIDACION REDEBAN 2025'!$C$2,IF(Y1046="TIPO I",'BASE LIQUIDACION REDEBAN 2025'!$C$2,IF(Y1046="TIPO II",'BASE LIQUIDACION REDEBAN 2025'!$C$3,IF(Y1046="TIPO III",'BASE LIQUIDACION REDEBAN 2025'!$C$4,IF(Y1046="TIPO IV",'BASE LIQUIDACION REDEBAN 2025'!$C$5,IF(Z1046="AEREO",'BASE LIQUIDACION REDEBAN 2025'!$B$6,'BASE LIQUIDACION REDEBAN 2025'!$C$5))))))) -> 144967.87 | AE1046: =IF(OR(W1046="SOPORTE_TELEFÓNICO",W1046="ENVÍO"),0,IF(Y1046="TIPO I",'BASE LIQUIDACION REDEBAN 2025'!$B$10,IF(Y1046="TIPO II",'BASE LIQUIDACION REDEBAN 2025'!$B$11,IF(Y1046="TIPO III",'BASE LIQUIDACION REDEBAN 2025'!$B$12,'BASE LIQUIDACION REDEBAN 2025'!$B$13)))) -> 140395.63 | AF1046: =IF(OR(W1046="SOPORTE_TELEFÓNICO",W1046="ENVÍO"),AD1046,(AD1046*AB1046+AE1046*AC1046)) -> 144967.87
A1047: CALI | B1047: =VLOOKUP(A1047,'CENTRO DE COSTOS'!A:D,4,FALSE) -> DIEGO FERNANDO HENAO CARDONA | C1047: =VLOOKUP(A1047,'CENTRO DE COSTOS'!A:D,2,FALSE) -> 0004-0003 | D1047: 76520 | E1047: 2686030 | F1047: 37650 | G1047: INCIDENTE | H1047: VALLE DEL CAUCA | I1047: PALMIRA | J1047: DISTRICOL VARIEDADES JM | K1047: REDEBAN | L1047: FO-25-1467118 | M1047: 45903.385 | N1047: 45903.626 | O1047: NO | P1047: HARDWARE | Q1047: SE REINICIA | R1047: DAÑO POS | U1047: CERRADO | V1047: 03/09/2025 SE LLEGA AL COMERCIO SE REVISAN PARÁMETROS TODO ESTÁ BIEN SE HACEN TRANSACCIONES DE PRUEBA Y FUNCIONA CORRECTAMENTE | W1047: VISITA_TÉCNICA | X1047: 9B00K263 | Y1047: TIPO I | Z1047: TERRESTRE | AA1047: CUERO RUIZ JHONNY | AB1047: 1 | AC1047: 0 | AD1047: =IF(W1047="SOPORTE_TELEFÓNICO",'BASE LIQUIDACION REDEBAN 2025'!$B$19,IF(W1047="ENVÍO",'BASE LIQUIDACION REDEBAN 2025'!$C$2,IF(Y1047="TIPO I",'BASE LIQUIDACION REDEBAN 2025'!$C$2,IF(Y1047="TIPO II",'BASE LIQUIDACION REDEBAN 2025'!$C$3,IF(Y1047="TIPO III",'BASE LIQUIDACION REDEBAN 2025'!$C$4,IF(Y1047="TIPO IV",'BASE LIQUIDACION REDEBAN 2025'!$C$5,IF(Z1047="AEREO",'BASE LIQUIDACION REDEBAN 2025'!$B$6,'BASE LIQUIDACION REDEBAN 2025'!$C$5))))))) -> 65960.072 | AE1047: =IF(OR(W1047="SOPORTE_TELEFÓNICO",W1047="ENVÍO"),0,IF(Y1047="TIPO I",'BASE LIQUIDACION REDEBAN 2025'!$B$10,IF(Y1047="TIPO II",'BASE LIQUIDACION REDEBAN 2025'!$B$11,IF(Y1047="TIPO III",'BASE LIQUIDACION REDEBAN 2025'!$B$12,'BASE LIQUIDACION REDEBAN 2025'!$B$13)))) -> 75096.394 | AF1047: =IF(OR(W1047="SOPORTE_TELEFÓNICO",W1047="ENVÍO"),AD1047,(AD1047*AB1047+AE1047*AC1047)) -> 65960.072
A1048: PEREIRA | B1048: =VLOOKUP(A1048,'CENTRO DE COSTOS'!A:D,4,FALSE) -> DIEGO FERNANDO HENAO CARDONA | C1048: =VLOOKUP(A1048,'CENTRO DE COSTOS'!A:D,2,FALSE) -> 0004-0002 | D1048: 76250 | E1048: 2686653 | F1048: 37515 | G1048: INCIDENTE | H1048: VALLE DEL CAUCA | I1048: EL DOVIO | J1048: BARRIO CENTRO EL DOVIO 1 | K1048: REDEBAN | L1048: FO-25-1467114 | M1048: 45903.412 | N1048: 45904.512 | O1048: NO | P1048: HARDWARE | Q1048: DETERIORO | R1048: DATAFONO | U1048: CERRADO | V1048: 04/09/2025 VISITAMOS COMERCIO EL DATÁFONO TIENE DETERIORADO EL PUERTO DE ENERGÍA, REALIZAMOS CAMBIO LO CONFIGURAMOS Y REALIZAMOS PRUEBAS CON EL NUEVO DATÁFONO OK. | W1048: VISITA_TÉCNICA | X1048: LN00F199 | Y1048: TIPO II | Z1048: TERRESTRE | AA1048: ARROYAVE CANO MANUEL GUILLERMO | AB1048: 1 | AC1048: 0 | AD1048: =IF(W1048="SOPORTE_TELEFÓNICO",'BASE LIQUIDACION REDEBAN 2025'!$B$19,IF(W1048="ENVÍO",'BASE LIQUIDACION REDEBAN 2025'!$C$2,IF(Y1048="TIPO I",'BASE LIQUIDACION REDEBAN 2025'!$C$2,IF(Y1048="TIPO II",'BASE LIQUIDACION REDEBAN 2025'!$C$3,IF(Y1048="TIPO III",'BASE LIQUIDACION REDEBAN 2025'!$C$4,IF(Y1048="TIPO IV",'BASE LIQUIDACION REDEBAN 2025'!$C$5,IF(Z1048="AEREO",'BASE LIQUIDACION REDEBAN 2025'!$B$6,'BASE LIQUIDACION REDEBAN 2025'!$C$5))))))) -> 144967.87 | AE1048: =IF(OR(W1048="SOPORTE_TELEFÓNICO",W1048="ENVÍO"),0,IF(Y1048="TIPO I",'BASE LIQUIDACION REDEBAN 2025'!$B$10,IF(Y1048="TIPO II",'BASE LIQUIDACION REDEBAN 2025'!$B$11,IF(Y1048="TIPO III",'BASE LIQUIDACION REDEBAN 2025'!$B$12,'BASE LIQUIDACION REDEBAN 2025'!$B$13)))) -> 140395.63 | AF1048: =IF(OR(W1048="SOPORTE_TELEFÓNICO",W1048="ENVÍO"),AD1048,(AD1048*AB1048+AE1048*AC1048)) -> 144967.87
A1049: CALI | B1049: =VLOOKUP(A1049,'CENTRO DE COSTOS'!A:D,4,FALSE) -> DIEGO FERNANDO HENAO CARDONA | C1049: =VLOOKUP(A1049,'CENTRO DE COSTOS'!A:D,2,FALSE) -> 0004-0003 | D1049: 76520 | E1049: 2686673 | F1049: 11063 | G1049: INCIDENTE | H1049: VALLE DEL CAUCA | I1049: PALMIRA | J1049: MULTIPAGAS EL SEMBRADOR | K1049: REDEBAN | L1049: FO-25-1467109 | M1049: 45903.415 | N1049: 45903.68 | O1049: NO | P1049: HARDWARE | Q1049: TECLADO | R1049: DAÑO POS | U1049: CERRADO | V1049: 03/09/2025 SE CAMBIA DATAFONO YA QUE EL DEL CLIENTE TENIA LAS TECLAS BORROSAS Y DURAS | W1049: VISITA_TÉCNICA | X1049: JAATZ147 | Y1049: TIPO I | Z1049: TERRESTRE | AA1049: CUERO RUIZ JHONNY | AB1049: 1 | AC1049: 0 | AD1049: =IF(W1049="SOPORTE_TELEFÓNICO",'BASE LIQUIDACION REDEBAN 2025'!$B$19,IF(W1049="ENVÍO",'BASE LIQUIDACION REDEBAN 2025'!$C$2,IF(Y1049="TIPO I",'BASE LIQUIDACION REDEBAN 2025'!$C$2,IF(Y1049="TIPO II",'BASE LIQUIDACION REDEBAN 2025'!$C$3,IF(Y1049="TIPO III",'BASE LIQUIDACION REDEBAN 2025'!$C$4,IF(Y1049="TIPO IV",'BASE LIQUIDACION REDEBAN 2025'!$C$5,IF(Z1049="AEREO",'BASE LIQUIDACION REDEBAN 2025'!$B$6,'BASE LIQUIDACION REDEBAN 2025'!$C$5))))))) -> 65960.072 | AE1049: =IF(OR(W1049="SOPORTE_TELEFÓNICO",W1049="ENVÍO"),0,IF(Y1049="TIPO I",'BASE LIQUIDACION REDEBAN 2025'!$B$10,IF(Y1049="TIPO II",'BASE LIQUIDACION REDEBAN 2025'!$B$11,IF(Y1049="TIPO III",'BASE LIQUIDACION REDEBAN 2025'!$B$12,'BASE LIQUIDACION REDEBAN 2025'!$B$13)))) -> 75096.394 | AF1049: =IF(OR(W1049="SOPORTE_TELEFÓNICO",W1049="ENVÍO"),AD1049,(AD1049*AB1049+AE1049*AC1049)) -> 65960.072
A1050: IBAGUE | B1050: =VLOOKUP(A1050,'CENTRO DE COSTOS'!A:D,4,FALSE) -> KEVIN ALEXIS CORZO BUSTOS | C1050: =VLOOKUP(A1050,'CENTRO DE COSTOS'!A:D,2,FALSE) -> 0004-0007 | D1050: 73585 | E1050: 2687025 | F1050: 32656 | G1050: INCIDENTE | H1050: TOLIMA | I1050: PURIFICACION | J1050: BARRIO LOS CAMBULOS PURIFICACI | K1050: REDEBAN | L1050: FO-25-1467100 | M1050: 45903.431 | N1050: 45904.659 | O1050: NO | P1050: HARDWARE | Q1050: IMPRESION | R1050: TAPA IMPRESORA | U1050: CERRADO | V1050: 04/09/2025 SE CAMBIA TAPA DE LA IMPRESORA DEL DATÁFONO POR DAÑO. SE HACEN PRUEBAS DE TRANSACCIONES TODO OK | W1050: VISITA_TÉCNICA | X1050: BL01X782 | Y1050: TIPO II | Z1050: TERRESTRE | AA1050: VARGAS HERRERA JHON JAIRO | AB1050: 1 | AC1050: 0 | AD1050: =IF(W1050="SOPORTE_TELEFÓNICO",'BASE LIQUIDACION REDEBAN 2025'!$B$19,IF(W1050="ENVÍO",'BASE LIQUIDACION REDEBAN 2025'!$C$2,IF(Y1050="TIPO I",'BASE LIQUIDACION REDEBAN 2025'!$C$2,IF(Y1050="TIPO II",'BASE LIQUIDACION REDEBAN 2025'!$C$3,IF(Y1050="TIPO III",'BASE LIQUIDACION REDEBAN 2025'!$C$4,IF(Y1050="TIPO IV",'BASE LIQUIDACION REDEBAN 2025'!$C$5,IF(Z1050="AEREO",'BASE LIQUIDACION REDEBAN 2025'!$B$6,'BASE LIQUIDACION REDEBAN 2025'!$C$5))))))) -> 144967.87 | AE1050: =IF(OR(W1050="SOPORTE_TELEFÓNICO",W1050="ENVÍO"),0,IF(Y1050="TIPO I",'BASE LIQUIDACION REDEBAN 2025'!$B$10,IF(Y1050="TIPO II",'BASE LIQUIDACION REDEBAN 2025'!$B$11,IF(Y1050="TIPO III",'BASE LIQUIDACION REDEBAN 2025'!$B$12,'BASE LIQUIDACION REDEBAN 2025'!$B$13)))) -> 140395.63 | AF1050: =IF(OR(W1050="SOPORTE_TELEFÓNICO",W1050="ENVÍO"),AD1050,(AD1050*AB1050+AE1050*AC1050)) -> 144967.87
... A1106: CALI | B1106: =VLOOKUP(A1106,'CENTRO DE COSTOS'!A:D,4,FALSE) -> DIEGO FERNANDO HENAO CARDONA | C1106: =VLOOKUP(A1106,'CENTRO DE COSTOS'!A:D,2,FALSE) -> 0004-0003 | D1106: 19001 | E1106: 2679301 | F1106: 60462 | G1106: INCIDENTE | H1106: CAUCA | I1106: POPAYAN | J1106: BARRIO PRADOS DEL NORTE POPAYA | K1106: REDEBAN | L1106: FO-25-1459838 | M1106: 45902.401 | N1106: 45904.654 | O1106: NO | P1106: HARDWARE | Q1106: COMUNICACION | R1106: MENSAJE CABLE DE RED DESCONECTADO | U1106: CERRADO | V1106: 04/09/2025 SE INGRESA EQUIPO CON TECLADO OK SE LE INFORMA AL CLIENTE QUE EL TECLADO DEL MODELO ESTA OK SE HACEN PRUEBAS OK TELECARGA DRNA | W1106: VISITA_TÉCNICA | X1106: KA00C843 | Y1106: TIPO III | Z1106: TERRESTRE | AA1106: GIMBUEL LASSO LUIS GERMAN | AB1106: 1 | AC1106: 0 | AD1106: =IF(W1106="SOPORTE_TELEFÓNICO",'BASE LIQUIDACION REDEBAN 2025'!$B$19,IF(W1106="ENVÍO",'BASE LIQUIDACION REDEBAN 2025'!$C$2,IF(Y1106="TIPO I",'BASE LIQUIDACION REDEBAN 2025'!$C$2,IF(Y1106="TIPO II",'BASE LIQUIDACION REDEBAN 2025'!$C$3,IF(Y1106="TIPO III",'BASE LIQUIDACION REDEBAN 2025'!$C$4,IF(Y1106="TIPO IV",'BASE LIQUIDACION REDEBAN 2025'!$C$5,IF(Z1106="AEREO",'BASE LIQUIDACION REDEBAN 2025'!$B$6,'BASE LIQUIDACION REDEBAN 2025'!$C$5))))))) -> 275728.78 | AE1106: =IF(OR(W1106="SOPORTE_TELEFÓNICO",W1106="ENVÍO"),0,IF(Y1106="TIPO I",'BASE LIQUIDACION REDEBAN 2025'!$B$10,IF(Y1106="TIPO II",'BASE LIQUIDACION REDEBAN 2025'!$B$11,IF(Y1106="TIPO III",'BASE LIQUIDACION REDEBAN 2025'!$B$12,'BASE LIQUIDACION REDEBAN 2025'!$B$13)))) -> 196536.53 | AF1106: =IF(OR(W1106="SOPORTE_TELEFÓNICO",W1106="ENVÍO"),AD1106,(AD1106*AB1106+AE1106*AC1106)) -> 275728.78
A1107: BUCARAMANGA | B1107: =VLOOKUP(A1107,'CENTRO DE COSTOS'!A:D,4,FALSE) -> MIGUEL JULIÁN HERNÁNDEZ GUARÍN | C1107: =VLOOKUP(A1107,'CENTRO DE COSTOS'!A:D,2,FALSE) -> 0004-0008 | D1107: 68001 | E1107: TA-25-1048275 | F1107: 30389 | G1107: INCIDENTE | H1107: SANTANDER | I1107: BUCARAMANGA | J1107: COMCARD BMANGA MAYITA | K1107: REDEBAN | L1107: FO-25-1459800 | M1107: 45902.416 | N1107: 45902.526 | O1107: NO | P1107: HARDWARE | Q1107: ACTUALIZACION | R1107: VERSION CAMBIO POS | U1107: CERRADO | V1107: 02/09/2025 SE REALIZA VISITA AL COMERCIO SE EVIDENCIA QUE LA TIRILLA NO ESTÁ SALIENDO CON LA INFORMACIÓN COMPLETA SE REALIZA BORRADO DE SISTEMA E INYECCION DE VERSIÓN 9.90 SE REALIZAN PRUEBAS OK | W1107: VISITA_TÉCNICA | X1107: BHZZZ421 | Y1107: TIPO I | Z1107: TERRESTRE | AA1107: MARIÑO PABON JORGE ENRIQUE | AB1107: 1 | AC1107: 0 | AD1107: =IF(W1107="SOPORTE_TELEFÓNICO",'BASE LIQUIDACION REDEBAN 2025'!$B$19,IF(W1107="ENVÍO",'BASE LIQUIDACION REDEBAN 2025'!$C$2,IF(Y1107="TIPO I",'BASE LIQUIDACION REDEBAN 2025'!$C$2,IF(Y1107="TIPO II",'BASE LIQUIDACION REDEBAN 2025'!$C$3,IF(Y1107="TIPO III",'BASE LIQUIDACION REDEBAN 2025'!$C$4,IF(Y1107="TIPO IV",'BASE LIQUIDACION REDEBAN 2025'!$C$5,IF(Z1107="AEREO",'BASE LIQUIDACION REDEBAN 2025'!$B$6,'BASE LIQUIDACION REDEBAN 2025'!$C$5))))))) -> 65960.072 | AE1107: =IF(OR(W1107="SOPORTE_TELEFÓNICO",W1107="ENVÍO"),0,IF(Y1107="TIPO I",'BASE LIQUIDACION REDEBAN 2025'!$B$10,IF(Y1107="TIPO II",'BASE LIQUIDACION REDEBAN 2025'!$B$11,IF(Y1107="TIPO III",'BASE LIQUIDACION REDEBAN 2025'!$B$12,'BASE LIQUIDACION REDEBAN 2025'!$B$13)))) -> 75096.394 | AF1107: =IF(OR(W1107="SOPORTE_TELEFÓNICO",W1107="ENVÍO"),AD1107,(AD1107*AB1107+AE1107*AC1107)) -> 65960.072
A1108: VILLAVICENCIO | B1108: =VLOOKUP(A1108,'CENTRO DE COSTOS'!A:D,4,FALSE) -> KEVIN ALEXIS CORZO BUSTOS | C1108: =VLOOKUP(A1108,'CENTRO DE COSTOS'!A:D,2,FALSE) -> 0004-0007 | D1108: 50001 | E1108: 2679128 | F1108: 79160 | G1108: INCIDENTE | H1108: META | I1108: VILLAVICENCIO | J1108: BARRIO BOCHICA VILLAVICENCIO 1 | K1108: REDEBAN | L1108: FO-25-1459505 | M1108: 45902.393 | N1108: 45902.541 | O1108: NO | P1108: SOFTWARE | Q1108: COMUNICACION | R1108: VERIFIQUE PARAMETROS | U1108: CERRADO | V1108: 02/09/2025 SE REALIZA CONFIGURACIÓN DE PARÁMETRO E INICIALIZACIÓN POR FALLAS DE ERROR EN PARÁMETROS | W1108: VISITA_TÉCNICA | X1108: SASZZ735 | Y1108: TIPO I | Z1108: TERRESTRE | AA1108: ROZO JIMENEZ EDGAR ARMANDO | AB1108: 1 | AC1108: 0 | AD1108: =IF(W1108="SOPORTE_TELEFÓNICO",'BASE LIQUIDACION REDEBAN 2025'!$B$19,IF(W1108="ENVÍO",'BASE LIQUIDACION REDEBAN 2025'!$C$2,IF(Y1108="TIPO I",'BASE LIQUIDACION REDEBAN 2025'!$C$2,IF(Y1108="TIPO II",'BASE LIQUIDACION REDEBAN 2025'!$C$3,IF(Y1108="TIPO III",'BASE LIQUIDACION REDEBAN 2025'!$C$4,IF(Y1108="TIPO IV",'BASE LIQUIDACION REDEBAN 2025'!$C$5,IF(Z1108="AEREO",'BASE LIQUIDACION REDEBAN 2025'!$B$6,'BASE LIQUIDACION REDEBAN 2025'!$C$5))))))) -> 65960.072 | AE1108: =IF(OR(W1108="SOPORTE_TELEFÓNICO",W1108="ENVÍO"),0,IF(Y1108="TIPO I",'BASE LIQUIDACION REDEBAN 2025'!$B$10,IF(Y1108="TIPO II",'BASE LIQUIDACION REDEBAN 2025'!$B$11,IF(Y1108="TIPO III",'BASE LIQUIDACION REDEBAN 2025'!$B$12,'BASE LIQUIDACION REDEBAN 2025'!$B$13)))) -> 75096.394 | AF1108: =IF(OR(W1108="SOPORTE_TELEFÓNICO",W1108="ENVÍO"),AD1108,(AD1108*AB1108+AE1108*AC1108)) -> 65960.072
A1109: MEDELLIN | B1109: =VLOOKUP(A1109,'CENTRO DE COSTOS'!A:D,4,FALSE) -> JUAN SEBASTIÁN RÍOS CASTRILLÓN | C1109: =VLOOKUP(A1109,'CENTRO DE COSTOS'!A:D,2,FALSE) -> 0004-0005 | D1109: 5615 | E1109: 2678813 | F1109: 64669 | G1109: INCIDENTE | H1109: ANTIOQUIA | I1109: RIONEGRO | J1109: PTM RIONEGRO PAPELERIA EL YEN | K1109: REDEBAN | L1109: FO-25-1459482 | M1109: 45902.378 | N1109: 45903.491 | O1109: NO | P1109: HARDWARE | Q1109: IMPRESION | R1109: NO IMPRIME UNO O VARIOS CARACTERES | U1109: CERRADO | V1109: 03/09/2025 SE HACE MANTENIMIENTO OK SE LIMPIA IMPRESORA OK PRUEBAS | W1109: VISITA_TÉCNICA | X1109: 3A003046 | Y1109: TIPO II | Z1109: TERRESTRE | AA1109: DIAZ ZABALA FRANCIS DUBAN | AB1109: 1 | AC1109: 0 | AD1109: =IF(W1109="SOPORTE_TELEFÓNICO",'BASE LIQUIDACION REDEBAN 2025'!$B$19,IF(W1109="ENVÍO",'BASE LIQUIDACION REDEBAN 2025'!$C$2,IF(Y1109="TIPO I",'BASE LIQUIDACION REDEBAN 2025'!$C$2,IF(Y1109="TIPO II",'BASE LIQUIDACION REDEBAN 2025'!$C$3,IF(Y1109="TIPO III",'BASE LIQUIDACION REDEBAN 2025'!$C$4,IF(Y1109="TIPO IV",'BASE LIQUIDACION REDEBAN 2025'!$C$5,IF(Z1109="AEREO",'BASE LIQUIDACION REDEBAN 2025'!$B$6,'BASE LIQUIDACION REDEBAN 2025'!$C$5))))))) -> 144967.87 | AE1109: =IF(OR(W1109="SOPORTE_TELEFÓNICO",W1109="ENVÍO"),0,IF(Y1109="TIPO I",'BASE LIQUIDACION REDEBAN 2025'!$B$10,IF(Y1109="TIPO II",'BASE LIQUIDACION REDEBAN 2025'!$B$11,IF(Y1109="TIPO III",'BASE LIQUIDACION REDEBAN 2025'!$B$12,'BASE LIQUIDACION REDEBAN 2025'!$B$13)))) -> 140395.63 | AF1109: =IF(OR(W1109="SOPORTE_TELEFÓNICO",W1109="ENVÍO"),AD1109,(AD1109*AB1109+AE1109*AC1109)) -> 144967.87
A1110: MEDELLIN | B1110: =VLOOKUP(A1110,'CENTRO DE COSTOS'!A:D,4,FALSE) -> JUAN SEBASTIÁN RÍOS CASTRILLÓN | C1110: =VLOOKUP(A1110,'CENTRO DE COSTOS'!A:D,2,FALSE) -> 0004-0005 | D1110: 5001 | E1110: 2678921 | F1110: 73553 | G1110: INCIDENTE | H1110: ANTIOQUIA | I1110: MEDELLIN | J1110: BARRIO BELEN MEDELLIN | K1110: REDEBAN | L1110: FO-25-1459476 | M1110: 45902.381 | N1110: 45902.509 | O1110: NO | P1110: SOFTWARE | Q1110: COMUNICACION | R1110: PARAMETROS DE CONFIGURACION EN POS | U1110: CERRADO | V1110: 02/09/2025 SE REVISA EQUIPO, SE CARGA VERSIÓN Y SE CONFIGURA COMUNICACIÓN, TODO OK | W1110: VISITA_TÉCNICA | X1110: SV00W478 | Y1110: TIPO I | Z1110: TERRESTRE | AA1110: QUINTERO SANCHEZ JUAN SEBASTIAN | AB1110: 1 | AC1110: 0 | AD1110: =IF(W1110="SOPORTE_TELEFÓNICO",'BASE LIQUIDACION REDEBAN 2025'!$B$19,IF(W1110="ENVÍO",'BASE LIQUIDACION REDEBAN 2025'!$C$2,IF(Y1110="TIPO I",'BASE LIQUIDACION REDEBAN 2025'!$C$2,IF(Y1110="TIPO II",'BASE LIQUIDACION REDEBAN 2025'!$C$3,IF(Y1110="TIPO III",'BASE LIQUIDACION REDEBAN 2025'!$C$4,IF(Y1110="TIPO IV",'BASE LIQUIDACION REDEBAN 2025'!$C$5,IF(Z1110="AEREO",'BASE LIQUIDACION REDEBAN 2025'!$B$6,'BASE LIQUIDACION REDEBAN 2025'!$C$5))))))) -> 65960.072 | AE1110: =IF(OR(W1110="SOPORTE_TELEFÓNICO",W1110="ENVÍO"),0,IF(Y1110="TIPO I",'BASE LIQUIDACION REDEBAN 2025'!$B$10,IF(Y1110="TIPO II",'BASE LIQUIDACION REDEBAN 2025'!$B$11,IF(Y1110="TIPO III",'BASE LIQUIDACION REDEBAN 2025'!$B$12,'BASE LIQUIDACION REDEBAN 2025'!$B$13)))) -> 75096.394 | AF1110: =IF(OR(W1110="SOPORTE_TELEFÓNICO",W1110="ENVÍO"),AD1110,(AD1110*AB1110+AE1110*AC1110)) -> 65960.072
A1111: PEREIRA | B1111: =VLOOKUP(A1111,'CENTRO DE COSTOS'!A:D,4,FALSE) -> DIEGO FERNANDO HENAO CARDONA | C1111: =VLOOKUP(A1111,'CENTRO DE COSTOS'!A:D,2,FALSE) -> 0004-0002 | D1111: 66170 | E1111: 2678990 | F1111: 47144 | G1111: INCIDENTE | H1111: RISARALDA | I1111: DOSQUEBRADAS | J1111: BARRIO JUPITER DOSQUEBRADAS | K1111: REDEBAN | L1111: FO-25-1459468 | M1111: 45902.39 | N1111: 45902.636 | O1111: NO | P1111: HARDWARE | Q1111: LECTOR DE BARRAS | R1111: CABLE LECTORA AVERIADO | U1111: CERRADO | V1111: 02/09/2025 VISITAMOS COMERCIO EL CABLE DEL LECTOR DE BARRAS ESTA AVERIADO, CAMBIAMOS LECTOR DE BARRAS REALIZAMOS PRUEBAS CON EL NUEVO LECTOR OK. | W1111: VISITA_TÉCNICA | X1111: 9C00D659 | Y1111: TIPO I | Z1111: TERRESTRE | AA1111: ARROYAVE CANO MANUEL GUILLERMO | AB1111: 1 | AC1111: 0 | AD1111: =IF(W1111="SOPORTE_TELEFÓNICO",'BASE LIQUIDACION REDEBAN 2025'!$B$19,IF(W1111="ENVÍO",'BASE LIQUIDACION REDEBAN 2025'!$C$2,IF(Y1111="TIPO I",'BASE LIQUIDACION REDEBAN 2025'!$C$2,IF(Y1111="TIPO II",'BASE LIQUIDACION REDEBAN 2025'!$C$3,IF(Y1111="TIPO III",'BASE LIQUIDACION REDEBAN 2025'!$C$4,IF(Y1111="TIPO IV",'BASE LIQUIDACION REDEBAN 2025'!$C$5,IF(Z1111="AEREO",'BASE LIQUIDACION REDEBAN 2025'!$B$6,'BASE LIQUIDACION REDEBAN 2025'!$C$5))))))) -> 65960.072 | AE1111: =IF(OR(W1111="SOPORTE_TELEFÓNICO",W1111="ENVÍO"),0,IF(Y1111="TIPO I",'BASE LIQUIDACION REDEBAN 2025'!$B$10,IF(Y1111="TIPO II",'BASE LIQUIDACION REDEBAN 2025'!$B$11,IF(Y1111="TIPO III",'BASE LIQUIDACION REDEBAN 2025'!$B$12,'BASE LIQUIDACION REDEBAN 2025'!$B$13)))) -> 75096.394 | AF1111: =IF(OR(W1111="SOPORTE_TELEFÓNICO",W1111="ENVÍO"),AD1111,(AD1111*AB1111+AE1111*AC1111)) -> 65960.072
A1112: BOGOTA | B1112: =VLOOKUP(A1112,'CENTRO DE COSTOS'!A:D,4,FALSE) -> WILLIAM ASDRUBAL ROZO ROZO | C1112: =VLOOKUP(A1112,'CENTRO DE COSTOS'!A:D,2,FALSE) -> 0004-0004 | D1112: 25491 | E1112: 2679008 | F1112: 32981 | G1112: INCIDENTE | H1112: CUNDINAMARCA | I1112: NOCAIMA | J1112: BARRIO TOBIA CHICA CENTRO TOBI | K1112: REDEBAN | L1112: FO-25-1459424 | M1112: 45902.391 | N1112: 45903.495 | O1112: NO | P1112: SOFTWARE | Q1112: LLT | R1112: LLT | U1112: CERRADO | V1112: 03/09/2025 SE LLEGA A COMERCIO EN EL CUAL SE ENCUENTRA SIN ENERGÍA ELÉCTRICA. DURANTE TODO EL DÍA SE ESCALA Y SE CIERRA | W1112: VISITA_TÉCNICA | X1112: 11VZZ981 | Y1112: TIPO III | Z1112: TERRESTRE | AA1112: ORTIZ MARTINEZ STIVEN | AB1112: 1 | AC1112: 0 | AD1112: =IF(W1112="SOPORTE_TELEFÓNICO",'BASE LIQUIDACION REDEBAN 2025'!$B$19,IF(W1112="ENVÍO",'BASE LIQUIDACION REDEBAN 2025'!$C$2,IF(Y1112="TIPO I",'BASE LIQUIDACION REDEBAN 2025'!$C$2,IF(Y1112="TIPO II",'BASE LIQUIDACION REDEBAN 2025'!$C$3,IF(Y1112="TIPO III",'BASE LIQUIDACION REDEBAN 2025'!$C$4,IF(Y1112="TIPO IV",'BASE LIQUIDACION REDEBAN 2025'!$C$5,IF(Z1112="AEREO",'BASE LIQUIDACION REDEBAN 2025'!$B$6,'BASE LIQUIDACION REDEBAN 2025'!$C$5))))))) -> 275728.78 | AE1112: =IF(OR(W1112="SOPORTE_TELEFÓNICO",W1112="ENVÍO"),0,IF(Y1112="TIPO I",'BASE LIQUIDACION REDEBAN 2025'!$B$10,IF(Y1112="TIPO II",'BASE LIQUIDACION REDEBAN 2025'!$B$11,IF(Y1112="TIPO III",'BASE LIQUIDACION REDEBAN 2025'!$B$12,'BASE LIQUIDACION REDEBAN 2025'!$B$13)))) -> 196536.53 | AF1112: =IF(OR(W1112="SOPORTE_TELEFÓNICO",W1112="ENVÍO"),AD1112,(AD1112*AB1112+AE1112*AC1112)) -> 275728.78
A1113: VILLAVICENCIO | B1113: =VLOOKUP(A1113,'CENTRO DE COSTOS'!A:D,4,FALSE) -> KEVIN ALEXIS CORZO BUSTOS | C1113: =VLOOKUP(A1113,'CENTRO DE COSTOS'!A:D,2,FALSE) -> 0004-0007 | D1113: 50568 | E1113: 2678566 | F1113: 64582 | G1113: INCIDENTE | H1113: META | I1113: PUERTO GAITAN | J1113: BARRIO VEREDA PUERTO TRIUNFO P | K1113: REDEBAN | L1113: FO-25-1459182 | M1113: 45902.372 | N1113: 45904.349 | O1113: NO | P1113: HARDWARE | Q1113: LECTOR DE BARRAS | R1113: FORMATO INVALIDO LECTOR DAÑADO | U1113: CERRADO | V1113: 03/09/2025 SE CAMBIA LECTOR DE BARRAS POR DAÑO, NO RECONOCE RECIBOS | W1113: VISITA_TÉCNICA | X1113: 1A003538 | Y1113: TIPO III | Z1113: TERRESTRE | AA1113: PEDREROS CONTRERAS MICHAEL STEVENS | AB1113: 1 | AC1113: 0 | AD1113: =IF(W1113="SOPORTE_TELEFÓNICO",'BASE LIQUIDACION REDEBAN 2025'!$B$19,IF(W1113="ENVÍO",'BASE LIQUIDACION REDEBAN 2025'!$C$2,IF(Y1113="TIPO I",'BASE LIQUIDACION REDEBAN 2025'!$C$2,IF(Y1113="TIPO II",'BASE LIQUIDACION REDEBAN 2025'!$C$3,IF(Y1113="TIPO III",'BASE LIQUIDACION REDEBAN 2025'!$C$4,IF(Y1113="TIPO IV",'BASE LIQUIDACION REDEBAN 2025'!$C$5,IF(Z1113="AEREO",'BASE LIQUIDACION REDEBAN 2025'!$B$6,'BASE LIQUIDACION REDEBAN 2025'!$C$5))))))) -> 275728.78 | AE1113: =IF(OR(W1113="SOPORTE_TELEFÓNICO",W1113="ENVÍO"),0,IF(Y1113="TIPO I",'BASE LIQUIDACION REDEBAN 2025'!$B$10,IF(Y1113="TIPO II",'BASE LIQUIDACION REDEBAN 2025'!$B$11,IF(Y1113="TIPO III",'BASE LIQUIDACION REDEBAN 2025'!$B$12,'BASE LIQUIDACION REDEBAN 2025'!$B$13)))) -> 196536.53 | AF1113: =IF(OR(W1113="SOPORTE_TELEFÓNICO",W1113="ENVÍO"),AD1113,(AD1113*AB1113+AE1113*AC1113)) -> 275728.78
A1114: VALLEDUPAR | B1114: =VLOOKUP(A1114,'CENTRO DE COSTOS'!A:D,4,FALSE) -> JOSE MAURICIO HERNANDEZ ROJAS | C1114: =VLOOKUP(A1114,'CENTRO DE COSTOS'!A:D,2,FALSE) -> 0004-0001 | D1114: 20621 | E1114: 2678045 | F1114: 28875 | G1114: INCIDENTE | H1114: CESAR | I1114: LA PAZ | J1114: BARRIO JORGE ELIECER GAITAN LA | K1114: REDEBAN | L1114: FO-25-1458853 | M1114: 45902.347 | N1114: 45902.499 | O1114: NO | P1114: HARDWARE | Q1114: PINPAD | R1114: SE REINICIA | U1114: CERRADO | V1114: 02/09/2025 SE REALIZA CAMBIO DE PINPAD, YA QUE AL MOMENTO DE INSERTAR LA TRJETA SE REINICIABA Y APAGABA EL DATAFONO, SE CAMBIA DE IGUAL FORMA EL DATAFONO POR COMPATIBILIDAD, SE REALIZAN PRUEBAS DEJANDO SERVICIO FUNCIONAL AL 100 % | W1114: VISITA_TÉCNICA | X1114: BL01Y556 | Y1114: TIPO II | Z1114: TERRESTRE | AA1114: MONTES DIAZ JOHN FRED | AB1114: 1 | AC1114: 0 | AD1114: =IF(W1114="SOPORTE_TELEFÓNICO",'BASE LIQUIDACION REDEBAN 2025'!$B$19,IF(W1114="ENVÍO",'BASE LIQUIDACION REDEBAN 2025'!$C$2,IF(Y1114="TIPO I",'BASE LIQUIDACION REDEBAN 2025'!$C$2,IF(Y1114="TIPO II",'BASE LIQUIDACION REDEBAN 2025'!$C$3,IF(Y1114="TIPO III",'BASE LIQUIDACION REDEBAN 2025'!$C$4,IF(Y1114="TIPO IV",'BASE LIQUIDACION REDEBAN 2025'!$C$5,IF(Z1114="AEREO",'BASE LIQUIDACION REDEBAN 2025'!$B$6,'BASE LIQUIDACION REDEBAN 2025'!$C$5))))))) -> 144967.87 | AE1114: =IF(OR(W1114="SOPORTE_TELEFÓNICO",W1114="ENVÍO"),0,IF(Y1114="TIPO I",'BASE LIQUIDACION REDEBAN 2025'!$B$10,IF(Y1114="TIPO II",'BASE LIQUIDACION REDEBAN 2025'!$B$11,IF(Y1114="TIPO III",'BASE LIQUIDACION REDEBAN 2025'!$B$12,'BASE LIQUIDACION REDEBAN 2025'!$B$13)))) -> 140395.63 | AF1114: =IF(OR(W1114="SOPORTE_TELEFÓNICO",W1114="ENVÍO"),AD1114,(AD1114*AB1114+AE1114*AC1114)) -> 144967.87
A1115: PASTO | B1115: =VLOOKUP(A1115,'CENTRO DE COSTOS'!A:D,4,FALSE) -> DIEGO FERNANDO HENAO CARDONA | C1115: =VLOOKUP(A1115,'CENTRO DE COSTOS'!A:D,2,FALSE) -> 0004-0003 | D1115: 52411 | E1115: 2677027 | F1115: 32012 | G1115: INCIDENTE | H1115: NARIÑO | I1115: LINARES | J1115: BARRIO CRISTO REY DE LINARES L | K1115: REDEBAN | L1115: FO-25-1458793 | M1115: 45902.333 | N1115: 45904.589 | O1115: NO | P1115: SOFTWARE | Q1115: ERROR DE TRANSACCIONES | R1115: RECHAZO GENERAL | U1115: CERRADO | V1115: 04/09/2025 SE REALIZA CAMBIO DE EQUIPO POR FALLA RECHAZO GENERAL Y INCOMPATIBILIDAD SE REALIZA CAMBIO DE EQUIPO SE INSTALA VERSIÓN SE CONFIGURA PARÁMETROS SE INICIALIZA SE REALIZA PRUE | W1115: VISITA_TÉCNICA | X1115: AB000088 | Y1115: TIPO III | Z1115: TERRESTRE | AA1115: BRAVO MADROÑERO OSCAR ESTEBAN | AB1115: 1 | AC1115: 0 | AD1115: =IF(W1115="SOPORTE_TELEFÓNICO",'BASE LIQUIDACION REDEBAN 2025'!$B$19,IF(W1115="ENVÍO",'BASE LIQUIDACION REDEBAN 2025'!$C$2,IF(Y1115="TIPO I",'BASE LIQUIDACION REDEBAN 2025'!$C$2,IF(Y1115="TIPO II",'BASE LIQUIDACION REDEBAN 2025'!$C$3,IF(Y1115="TIPO III",'BASE LIQUIDACION REDEBAN 2025'!$C$4,IF(Y1115="TIPO IV",'BASE LIQUIDACION REDEBAN 2025'!$C$5,IF(Z1115="AEREO",'BASE LIQUIDACION REDEBAN 2025'!$B$6,'BASE LIQUIDACION REDEBAN 2025'!$C$5))))))) -> 275728.78 | AE1115: =IF(OR(W1115="SOPORTE_TELEFÓNICO",W1115="ENVÍO"),0,IF(Y1115="TIPO I",'BASE LIQUIDACION REDEBAN 2025'!$B$10,IF(Y1115="TIPO II",'BASE LIQUIDACION REDEBAN 2025'!$B$11,IF(Y1115="TIPO III",'BASE LIQUIDACION REDEBAN 2025'!$B$12,'BASE LIQUIDACION REDEBAN 2025'!$B$13)))) -> 196536.53 | AF1115: =IF(OR(W1115="SOPORTE_TELEFÓNICO",W1115="ENVÍO"),AD1115,(AD1115*AB1115+AE1115*AC1115)) -> 275728.78
A1116: MEDELLIN | B1116: =VLOOKUP(A1116,'CENTRO DE COSTOS'!A:D,4,FALSE) -> JUAN SEBASTIÁN RÍOS CASTRILLÓN | C1116: =VLOOKUP(A1116,'CENTRO DE COSTOS'!A:D,2,FALSE) -> 0004-0005 | D1116: 5001 | E1116: 2677165 | F1116: 16831 | G1116: INCIDENTE | H1116: ANTIOQUIA | I1116: MEDELLIN | J1116: PAGAFACIL CALLE NUEVA | K1116: REDEBAN | L1116: FO-25-1458787 | M1116: 45902.333 | N1116: 45902.562 | O1116: NO | P1116: SOFTWARE | Q1116: CIERRE | R1116: CIERRE NO HABILITADO | U1116: CERRADO | V1116: 02/09/2025 SE BRINDA SOPORTE TELEFÓNICO PARA RECUPERAR CLAVE CIERRE PRUEBAS OK | W1116: SOPORTE_TELEFÓNICO | X1116: 0 | Y1116: TIPO I | Z1116: TERRESTRE | AA1116: PAREJA ECHAVARRIA JHON DAVID | AB1116: 0 | AC1116: 0 | AD1116: =IF(W1116="SOPORTE_TELEFÓNICO",'BASE LIQUIDACION REDEBAN 2025'!$B$19,IF(W1116="ENVÍO",'BASE LIQUIDACION REDEBAN 2025'!$C$2,IF(Y1116="TIPO I",'BASE LIQUIDACION REDEBAN 2025'!$C$2,IF(Y1116="TIPO II",'BASE LIQUIDACION REDEBAN 2025'!$C$3,IF(Y1116="TIPO III",'BASE LIQUIDACION REDEBAN 2025'!$C$4,IF(Y1116="TIPO IV",'BASE LIQUIDACION REDEBAN 2025'!$C$5,IF(Z1116="AEREO",'BASE LIQUIDACION REDEBAN 2025'!$B$6,'BASE LIQUIDACION REDEBAN 2025'!$C$5))))))) -> 41241.08 | AE1116: =IF(OR(W1116="SOPORTE_TELEFÓNICO",W1116="ENVÍO"),0,IF(Y1116="TIPO I",'BASE LIQUIDACION REDEBAN 2025'!$B$10,IF(Y1116="TIPO II",'BASE LIQUIDACION REDEBAN 2025'!$B$11,IF(Y1116="TIPO III",'BASE LIQUIDACION REDEBAN 2025'!$B$12,'BASE LIQUIDACION REDEBAN 2025'!$B$13)))) -> 0 | AF1116: =IF(OR(W1116="SOPORTE_TELEFÓNICO",W1116="ENVÍO"),AD1116,(AD1116*AB1116+AE1116*AC1116)) -> 41241.08
A1117: SANTA MARTA | B1117: =VLOOKUP(A1117,'CENTRO DE COSTOS'!A:D,4,FALSE) -> JOSE MAURICIO HERNANDEZ ROJAS | C1117: =VLOOKUP(A1117,'CENTRO DE COSTOS'!A:D,2,FALSE) -> 0004-0001 | D1117: 47001 | E1117: 2677087 | F1117: 26642 | G1117: INCIDENTE | H1117: MAGDALENA | I1117: SANTA MARTA | J1117: BARRIO MARIA EUGENIA 2 SANTA M | K1117: REDEBAN | L1117: FO-25-1458768 | M1117: 45902.333 | N1117: 45902.683 | O1117: NO | P1117: HARDWARE | Q1117: IMPRESION | R1117: NO AVANZA PAPEL | U1117: CERRADO | V1117: 02/09/2025 SE REALIZA LA VISITA SE ENCUENTRA EL DATÁFONO CON PROBLEMAS DE IMPRESIÓN YA QUE NO AVANZA PAPEL SE PROCEDE A CAMBIAR EL EQUIPO SE REALIZAN PRUEBAS Y TODO OK | W1117: VISITA_TÉCNICA | X1117: 9999O600 | Y1117: TIPO I | Z1117: TERRESTRE | AA1117: THOMAS CAMPO SIGIFREDO SEGUNDO | AB1117: 1 | AC1117: 0 | AD1117: =IF(W1117="SOPORTE_TELEFÓNICO",'BASE LIQUIDACION REDEBAN 2025'!$B$19,IF(W1117="ENVÍO",'BASE LIQUIDACION REDEBAN 2025'!$C$2,IF(Y1117="TIPO I",'BASE LIQUIDACION REDEBAN 2025'!$C$2,IF(Y1117="TIPO II",'BASE LIQUIDACION REDEBAN 2025'!$C$3,IF(Y1117="TIPO III",'BASE LIQUIDACION REDEBAN 2025'!$C$4,IF(Y1117="TIPO IV",'BASE LIQUIDACION REDEBAN 2025'!$C$5,IF(Z1117="AEREO",'BASE LIQUIDACION REDEBAN 2025'!$B$6,'BASE LIQUIDACION REDEBAN 2025'!$C$5))))))) -> 65960.072 | AE1117: =IF(OR(W1117="SOPORTE_TELEFÓNICO",W1117="ENVÍO"),0,IF(Y1117="TIPO I",'BASE LIQUIDACION REDEBAN 2025'!$B$10,IF(Y1117="TIPO II",'BASE LIQUIDACION REDEBAN 2025'!$B$11,IF(Y1117="TIPO III",'BASE LIQUIDACION REDEBAN 2025'!$B$12,'BASE LIQUIDACION REDEBAN 2025'!$B$13)))) -> 75096.394 | AF1117: =IF(OR(W1117="SOPORTE_TELEFÓNICO",W1117="ENVÍO"),AD1117,(AD1117*AB1117+AE1117*AC1117)) -> 65960.072
