Workbook
Name A: #REF!
Name A: #REF!
Name ACTIVIDAD: [1]Hoja2!$P$2:$P$30
Name Actividad: [2]Formulas!$H$2:$H$5000
Name Analistas: '[3]Listas Desplegables'!$T$2:$T$7
Name arearesponsable: '[4]Listas desplegables'!$BB$2:$BB$100
Name CCO: [5]Tecnicos!$A$2:$A$1000
Name CCO: [6]Tecnicos!$A$2:$A$1000
Name Clientes: [7]Clientes!$A$2:$A$100
Name Clientes: [2]Clientes!$A$2:$A$100
Name COORDINADOR: [1]Hoja2!$D$2:$D$30
Name Coordinadores: [8]Coordinadores!$A$2:$A$1000
Name Coordinadores: [2]Coordinadores!$A$2:$A$1000
Name DOCUMENTADOR: [1]Hoja2!$A$2:$A$30
Name ES: [1]Hoja2!$K$2:$K$30
Name ESS: [1]Hoja2!$K$2:$K$30
Name Estado: [7]Formulas!$K$2:$K$5000
Name Estado: [2]Formulas!$K$2:$K$5000
Name ESTADOACTIVIDAD: [1]Hoja2!$M$2:$M$30
Name ESTADOS: '[9]Listas desplegables'!$B$1:$D$1
Name ESTADOS: '[10]Listas desplegables'!$B$1:$D$1
Name ESTADOSCIERRES: '[11]lista desplegable'!$CX$1:$DA$1
Name Facturacion: '[12]Listas desplegables'!$AO$1:$AR$1
Name FACTURACIÓN: '[9]Listas desplegables'!$Y$1:$AB$1
Name FACTURACIÓN: '[10]Listas desplegables'!$Y$1:$AB$1
Name falla: #REF!
Name Fallas: '[13]Listas desplegables'!$F$2:$L$2
Name Fallas: '[14]Listas desplegables'!$F$2:$L$2
Name Grupo_Falla: '[15]Listas Desplegables'!$CH$2:$CH$5
Name Grupo_Falla: '[16]Listas Desplegables'!$CH$2:$CH$5
Name inconservmanager: '[17]Listas desplegables'!$BC$2:$BC$100
Name inconservmanager: '[4]Listas desplegables'!$BC$2:$BC$100
Name INCUMPLIMIENTO: '[4]Listas desplegables'!$AK$1:$AN$1
Name INCUMPLIMIENTO: '[18]Listas desplegables'!$AT$1:$AX$1
Name LISTA: [19]Dptos!$A$1139:$A$1171
Name LISTA: [19]Dptos!$A$1139:$A$1171
Name LISTA2: #REF!
Name LISTA2: [20]Hoja3!$A$1:$A$26
Name LOLO: [21]Coordinadores!$A$2:$A$1000
Name solicitudes: '[12]Listas desplegables'!$U$1:$AF$1
Name solicitudes: '[22]Listas desplegables'!$U$1:$AF$1
Name Tecnicos: [7]Tecnicos!$A$2:$A$1000
Name Tecnicos: [2]Tecnicos!$A$2:$A$1000
Name Version: [23]Formulas!$I$2:$I$3
Name Version: [2]Formulas!$I$2:$I$3

Sheet CAPACITACIONES 
A1: MES | B1: NIT Proveedor | C1: Nombre Proveedor (el proveedor ya debe estar creado para el Grupo Bancolombia) | D1: Concepto Facturación | E1: Público que se capacitó | F1: No. personas impactadas | G1: Valor Servicio Unitario | H1: Valor a Facturar sin IVA | I1: Valor a Facturar con IVA
A2: SEPTIEMBREDE 2025 | B2: 811013990-5 | C2: LINEA COMUNICACIONES | D2: CAPACITACION CORRESPONSALES BANCARIOS APERTURAS | E2: CAPACITACION CORRESPONSALES BANCARIOS | F2: =COUNTA('CAPACITACIONES APERTURAS'!A:A)-1 -> 212 | G2: ='BASE FACTURACION 2025'!C3 -> 122645.45 | H2: ='CAPACITACIONES APERTURAS'!AC214 -> 26000836 | I2: =H2*1.19 -> 30940995
A3: =A2 -> SEPTIEMBREDE 2025 | B3: 811013990-5 | C3: LINEA COMUNICACIONES | D3: CAPACITACION CORRESPONSALES BANCARIOS OC | E3: CAPACITACION CORRESPONSALES BANCARIOS | F3: =COUNTA('CAPACITACION OC '!A:A)-1 -> 0 | G3: 0 | H3: ='CAPACITACION OC '!AW3 -> 0 | I3: =H3*1.19 -> 0
A4: TOTAL | E4: TOTAL | F4: =SUM(F2:F3) -> 212 | H4: =SUM(H2:H3) -> 26000836 | I4: =SUM(I2:I3) -> 30940995

Sheet BASE FACTURACION 2025
A1: Incidentes, Aperturas y Gestion de campo 2025 | H1: Incremento 2025
A2: Tipificación | B2: Descripción | C2: Capacitacion - Apertura | D2: Capacitacion OC | E2: Gestión Telefónica | F2: Capacitación especifica Cambio de red | H2: 0.052
A3: Tipo I | B3: Metropolitano | C3: =116583.13*(1+$H$2) -> 122645.45 | D3: =186397.63*(1+$H$2) -> 196090.31 | E3: =36031.04*(1+$H$2) -> 37904.654 | F3: =61943.61*(1+$H$2) -> 65164.678
A4: Tipo II | B4: Hasta 3 horas | C4: =116583.13*(1+$H$2) -> 122645.45 | D4: =239830.52*(1+$H$2) -> 252301.71 | E4: =36031.04*(1+$H$2) -> 37904.654 | F4: =61943.61*(1+$H$2) -> 65164.678
A5: Tipo III | B5: De 3 a 5 horas | C5: =116583.13*(1+$H$2) -> 122645.45 | D5: =385797.87*(1+$H$2) -> 405859.36 | E5: =36031.04*(1+$H$2) -> 37904.654 | F5: =61943.61*(1+$H$2) -> 65164.678
A6: Tipo IV | B6: Más de 5 horas | C6: =116583.13*(1+$H$2) -> 122645.45 | D6: =579581.34*(1+$H$2) -> 609719.57 | E6: =36031.04*(1+$H$2) -> 37904.654 | F6: =61943.61*(1+$H$2) -> 65164.678
A7: Destino Aereo* | B7: Viajes en Avión | C7: =116583.13*(1+$H$2) -> 122645.45 | D7: =579581.34*(1+$H$2) -> 609719.57 | E7: =36031.04*(1+$H$2) -> 37904.654 | F7: =61943.61*(1+$H$2) -> 65164.678
A8: * Tener presente que se cobrara el valor del tiquete de avion mas un porcentaje
A9: **Para la capacitacion de datafono adicional se cobrara la mitad de una actividad normal, para este caso $70.053
A11: TARIFAS 2025
A12: Tipificación | B12: Descripción | C12: Dia actividad Exitosa | D12: Dia actividad Fallida
A13: Tipo I | B13: Metropolitano | C13: =62700.07*(1+$H$2) -> 65960.474 | D13: =42357.4*(1+$H$2) -> 44559.985
A14: Tipo II | B14: Hasta 3 horas | C14: =155716.31*(1+$H$2) -> 163813.56 | D14: =127766.53*(1+$H$2) -> 134410.39
A15: Tipo III | B15: De 3 a 5 horas | C15: =262099.22*(1+$H$2) -> 275728.38 | D15: =211886.19*(1+$H$2) -> 222904.27
A16: Tipo IV | B16: Más de 5 horas | C16: =455883.78*(1+$H$2) -> 479589.74 | D16: =441833.68*(1+$H$2) -> 464809.03
A17: Destino aereo | B17: No incluye valor del Tiquete | C17: =455883.78*(1+$H$2) -> 479589.74 | D17: =441833.68*(1+$H$2) -> 464809.03
A18: *Donde se requiera transporte aéreo o fluvial se factura adicional a tarifa TIPO IV el valor del tiquete + el 12% de admon.

Sheet Tabla dinámica
A3: COORDINADOR | B3: CENTRO DE COSTOS LÍNEACOM | C3: Suma de VALOR TOTAL | D3: Suma de VALOR TOTAL 2 | E3: NOMBRE CC
A4: DIEGO FERNANDO HENAO CARDONA | B4: 0004-0002 | C4: 0.04245283 | D4: 1103809.1 | E4: =VLOOKUP(B4,'CENTRO DE COSTOS'!B:C,2,0) -> Redeban Eje Cafetero (Pereira)
B5: 0004-0003 | C5: 0.20754717 | D5: 5396399.9 | E5: =VLOOKUP(B5,'CENTRO DE COSTOS'!B:C,2,0) -> Redeban Suroccidente (Cali)
A6: JOSE MAURICIO HERNANDEZ ROJAS | B6: 0004-0001 | C6: 0.094339623 | D6: 2452909.1 | E6: =VLOOKUP(B6,'CENTRO DE COSTOS'!B:C,2,0) -> Redeban Costa (Barranqullla)
A7: JUAN SEBASTIÁN RÍOS CASTRILLÓN | B7: 0004-0005 | C7: 0.24528302 | D7: 6377563.5 | E7: =VLOOKUP(B7,'CENTRO DE COSTOS'!B:C,2,0) -> Redeban Noroccidente (Medellín)
A8: KEVIN ALEXIS CORZO BUSTOS | B8: 0004-0007 | C8: 0.089622642 | D8: 2330263.6 | E8: =VLOOKUP(B8,'CENTRO DE COSTOS'!B:C,2,0) -> Redeban Oriente (Otros)
A9: MIGUEL JULIÁN HERNÁNDEZ GUARÍN | B9: 0004-0008 | C9: 0.21226415 | D9: 5519045.4 | E9: =VLOOKUP(B9,'CENTRO DE COSTOS'!B:C,2,0) -> Redeban Santander
A10: WILLIAM ASDRUBAL ROZO ROZO | B10: 0004-0004 | C10: 0.10849057 | D10: 2820845.4 | E10: =VLOOKUP(B10,'CENTRO DE COSTOS'!B:C,2,0) -> Redeban Centro ( Bogotá)
A11: Total general | C11: 1 | D11: 26000836

Sheet CAPACITACIONES APERTURAS
A1: CIUDAD SEDE | B1: COORDINADOR | C1: CENTRO DE COSTOS LÍNEACOM | D1: CÓDIGO DANE | E1: TA/CODIGO ACTIVIDAD | F1: CODIGO CB | G1: ACTIVIDAD | H1: TIPO DE APERTURA | I1: DEPARTAMENTO | J1: CIUDAD | K1: NOMBRE DEL CB | L1: RED | M1: FO | N1: FECHA LISTA | O1: FECHA ULTIMA ACTUALIZACION | P1: FORMATO | Q1: CADENA | R1: ESTADO | S1: OBSERVACIONES CLIENTE | T1: FORMA DE ATENCIÓN | U1: TERMINALES | V1: TIPIFICACION | W1: TIPO DE TRAYECTO | X1: NOMBRE DEL TECNICO | Y1: CAPACITACIÓN COMPLETA | Z1: CAPACITACIÓN ESPECÍFICA | AA1: VALOR CAPACITACIÓN COMPLETA | AB1: VALOR CAPACITACIÓN ESPECÍFICA | AC1: VALOR TOTAL
A2: PASTO | B2: =VLOOKUP(A2,'CENTRO DE COSTOS'!A:D,4,FALSE) -> DIEGO FERNANDO HENAO CARDONA | C2: =VLOOKUP(A2,'CENTRO DE COSTOS'!A:D,2,FALSE) -> 0004-0003 | D2: 52621 | E2: TA-25-992136 | F2: 81154 | G2: APERTURA | H2: CB CRECIMIENTO - NUEVO | I2: NARIÑO | J2: ROBERTO PAYAN | K2: BARRIO EL VILLA HORIZONTE ROBERTO PAYAN | L2: REDEBAN | M2: FO-25-1402263 | N2: 45890 | O2: 45902 | P2: UNO A UNO | Q2: UNO A UNO | R2: EJECUTADO | S2: 21-08 SE REALIZA CONTACTO CON EL CLIENTE VIA WHATSAPP, SE HABLA CON LA SRA MARIA ELVIRA PARRA ARTUNDUAGA AL NÚMERO 3236143368 SE VALIDA DIRECCIÓN OK, CANAL OK, DISPONIBILIDAD TOTAL, LLAMAR EL DIA DE LA INSTALACIÓN PARA CONFIRMAR VISITA, AVISO EXTERIOR ALTURA APROX 8 METROS; TOMACORRIENTE CERCANO: SI; TIENE CABINA DE SEGURIDAD; SI 01-09 SE INICIO DESPLAZAMIENTO PERO SOLO HOY SE LLEGO HASTA BARBACOAS, SE VALIDA Y SE DEBE TOMAR LANCHA EL DIA DE MAÑANA 2/09/2025 SE REALIZA INSTALACIÓN DE CORRESPONSAL, SE INSTALAN EQUIPOS CON PRUEBAS EXITOSAS, SE CAPACITA Y SE EVALÚA AL CLIENTE, SE INSTALA PUBLICIDAD COMPLETA, CB QUEDA OPERATIVO. USUARIO SOMOS BANCOLOMBIA ACTIVO | T2: VISITA_TÉCNICA | U2: SIZZZ900 | V2: TIPO IV ESPECIAL | W2: FLUVIAL | X2: PAZ MARTINEZ RICHARD HUMBERTO | Y2: 1 | Z2: 0 | AA2: ='BASE FACTURACION 2025'!$C$3 -> 122645.45 | AB2: ='BASE FACTURACION 2025'!$F$3 -> 65164.678 | AC2: =AA2*Y2+AB2*Z2 -> 122645.45
A3: CALI | B3: =VLOOKUP(A3,'CENTRO DE COSTOS'!A:D,4,FALSE) -> DIEGO FERNANDO HENAO CARDONA | C3: =VLOOKUP(A3,'CENTRO DE COSTOS'!A:D,2,FALSE) -> 0004-0003 | D3: 19256 | E3: TA-25-992167 | F3: 81133 | G3: APERTURA | H3: CB CRECIMIENTO - NUEVO | I3: CAUCA | J3: EL TAMBO | K3: BARRIO PLAYA RICA EL TAMBO 1 | L3: REDEBAN | M3: FO-25-1402365 | N3: 45890 | O3: 45902 | P3: UNO A UNO | Q3: UNO A UNO | R3: EJECUTADO | S3: 21-08 SE REALIZA LLAMADA AL CLIENTE, SE HABLA CON LA SRA YUDY MILENA CALVACHE HERNANDEZ SE VALIDA DIRECCIÓN OK, CANAL OK, DISPONIBILIDAD TOTAL, LLAMAR EL DÍA LA INSTALACIÓN PARA CONFIRMAR VISITA, AVISO EXTERIOR ALTURA: NO INDICA ALTURA ; TOMACORRIENTE CERCANO: SI; TIENE CABINA DE SEGURIDAD: NO 25-08 DADO PROBLEMAS DE TRANSPORTE HACIA EL CORREGIMIENTO NO ES POSIBLE EL DESPLAZAMIENTO EL DIA DE HOY , SE VALIDARA EL DIA DE MAÑANA. 26-08 SE REALIZA LLAMADA CON EL CLIENTE, QUIEN INFORMA QUE PARA PODER REALIZAR EL INGRESO A LA ZONA ES NECESARIO DILIGENCIAR UNOS PERMISOS ESPECIALES, YA QUE SE TRATA DE UNA ZONA CON PRESENCIA GUERRILLERA. DEBIDO A ESTA SITUACIÓN, SE ACUERDA REPROGRAMAR LA APERTURA. 02-09 SE REALIZA INSTALACIÓN DE CORRESPONSAL, SE INSTALAN EQUIPOS CON PRUEBAS EXITOSAS, SE CAPACITA Y SE EVALÚA AL CLIENTE, SE INSTALA PUBLICIDAD COMPLETA, CB QUEDA OPERATIVO. USUARIO SOMOS BANCOLOMBIA ACTIVO | T3: VISITA_TÉCNICA | U3: SIZZZ915 | V3: TIPO III | W3: TERRESTRE | X3: GIMBUEL LASSO LUIS GERMAN | Y3: 1 | Z3: 0 | AA3: ='BASE FACTURACION 2025'!$C$3 -> 122645.45 | AB3: ='BASE FACTURACION 2025'!$F$3 -> 65164.678 | AC3: =AA3*Y3+AB3*Z3 -> 122645.45
A4: PASTO | B4: =VLOOKUP(A4,'CENTRO DE COSTOS'!A:D,4,FALSE) -> DIEGO FERNANDO HENAO CARDONA | C4: =VLOOKUP(A4,'CENTRO DE COSTOS'!A:D,2,FALSE) -> 0004-0003 | D4: 52079 | E4: TA-25-1033974 | F4: 81185 | G4: APERTURA | H4: CB CRECIMIENTO - NUEVO | I4: NARIÑO | J4: BARBACOAS | K4: BARRIO GUAYACAL BARBACOAS | L4: REDEBAN | M4: FO-25-1432981 | N4: 45896 | O4: 45902 | P4: UNO A UNO | Q4: UNO A UNO | R4: EJECUTADO | S4: 27-08 SE REALIZA LLAMADA AL CLIENTE, SE HABLA CON LA SRA YULIS FIORELA PORTILLA CABEZAS SE VALIDA DIRECCIÓN OK, CANAL OK, DISPONIBILIDAD TOTAL, LLAMAR EL DÍA LA INSTALACIÓN PARA CONFIRMAR VISITA, AVISO EXTERIOR ALTURA APROX 2 METROS; TOMACORRIENTE CERCANO: SI; TIENE CABINA DE SEGURIDAD: NO - COMUNICACIÓN POR WPP / EL MODEM ESTA A 4 MT 29/08/2025 POR DISPONIBILIDAD DE TRASNPORTE NO ES POSIBLE REALIZAR LA ACTIVIDAD EL DIA DE HOY, SE VIAJARA EL DIA LUNES 01-09 SE LLEGO A BARBACOAS, SE ESTA REALIZANDO LA IMPLEMENTACIÓN EL DIA DE MAÑANA 02-09 SE REALIZA INSTALACIÓN DE CORRESPONSAL, SE INSTALAN EQUIPOS CON PRUEBAS EXITOSAS, SE CAPACITA Y SE EVALÚA AL CLIENTE, SE INSTALA PUBLICIDAD COMPLETA, CB QUEDA OPERATIVO. USUARIO SOMOS BANCOLOMBIA ACTIVO | T4: VISITA_TÉCNICA | U4: FKZZZ635 | V4: TIPO IV | W4: TERRESTRE | X4: PAZ MARTINEZ RICHARD HUMBERTO | Y4: 1 | Z4: 0 | AA4: ='BASE FACTURACION 2025'!$C$3 -> 122645.45 | AB4: ='BASE FACTURACION 2025'!$F$3 -> 65164.678 | AC4: =AA4*Y4+AB4*Z4 -> 122645.45
A5: PEREIRA | B5: =VLOOKUP(A5,'CENTRO DE COSTOS'!A:D,4,FALSE) -> DIEGO FERNANDO HENAO CARDONA | C5: =VLOOKUP(A5,'CENTRO DE COSTOS'!A:D,2,FALSE) -> 0004-0002 | D5: 66001 | E5: TA-25-1033985 | F5: 81241 | G5: APERTURA | H5: CB CRECIMIENTO - NUEVO | I5: RISARALDA | J5: PEREIRA | K5: BARRIO CENTRO PEREIRA 55 | L5: REDEBAN | M5: FO-25-1433027 | N5: 45896 | O5: 45901 | P5: UNO A UNO | Q5: UNO A UNO | R5: EJECUTADO | S5: 27-08-2025 SE REALIZA LLAMADA AL CLIENTE, SE HABLA CON LA SRA JULIANA ECHEVERRY GALVEZ SE VALIDA DIRECCIÓN OK, CANAL OK, DISPONIBILIDAD TOTAL, LLAMAR EL DÍA LA INSTALACIÓN PARA CONFIRMAR VISITA, AVISO EXTERIOR ALTURA APROX 2 METROS; TOMACORRIENTE CERCANO: SI; TIENE CABINA DE SEGURIDAD: NO // CONTACTO REALIZADO POR LA APP 29-08 REALIZAMOS LLAMADA A LA SRA JULIANA LA CUAL NOS INDICA QUE EL DÍA DE HOY NO ES POSIBLE ATENDERNOS YA QUE TIENE UN COMPROMISO QUE POR FAVOR REPROGRAMAR LA VISITA PARA LA OTRA SEMANA. 1/09/2025 SE REALIZA INSTALACIÓN DE CORRESPONSAL, SE INSTALAN EQUIPOS, SE CAPACITA Y SE EVALÚA AL CLIENTE, SE INSTALA PUBLICIDAD COMPLETA, CB QUEDA OPERATIVO. USUARIO SOMOS BANCOLOMBIA ACTIVO. NOTA: SOLO SE REALIZAN PRUEBA DE CONSULTA DE SALDO YA QUE EL CLIENTE NO TIENE TARJETA PARA HACER LAS PRUEBAS DE DEPOSITO, RETIRO, RECAUDO Y TRANSFERENCIA | T5: VISITA_TÉCNICA | U5: FKZZZ643 | V5: TIPO I | W5: TERRESTRE | X5: ARROYAVE CANO MANUEL GUILLERMO | Y5: 1 | Z5: 0 | AA5: ='BASE FACTURACION 2025'!$C$3 -> 122645.45 | AB5: ='BASE FACTURACION 2025'!$F$3 -> 65164.678 | AC5: =AA5*Y5+AB5*Z5 -> 122645.45
A6: MONTERIA | B6: =VLOOKUP(A6,'CENTRO DE COSTOS'!A:D,4,FALSE) -> JOSE MAURICIO HERNANDEZ ROJAS | C6: =VLOOKUP(A6,'CENTRO DE COSTOS'!A:D,2,FALSE) -> 0004-0001 | D6: 23001 | E6: TA-25-1033987 | F6: 81212 | G6: APERTURA | H6: CB CRECIMIENTO - NUEVO | I6: CORDOBA | J6: MONTERIA | K6: BARRIO POLICARPA MONTERIA 3 | L6: REDEBAN | M6: FO-25-1433037 | N6: 45896 | O6: 45901 | P6: UNO A UNO | Q6: UNO A UNO | R6: EJECUTADO | S6: 26-08 SE REALIZA LLAMADA AL CLIENTE, SE HABLA CON LA SRA SIDNEY PATRICIA VILLEGAS VILORIA SE VALIDA DIRECCIÓN OK, CANAL OK, DISPONIBILIDAD TOTAL, LLAMAR EL DÍA DE LA INSTALACIÓN PARA CONFIRMAR VISITA, AVISO EXTERIOR NO INDICA ALTURA; TOMACORRIENTE CERCANO: SI; TIENE CABINA DE SEGURIDAD: SI 28-08 SE REALIZÓ LLAMADA DE VALIDACIÓN Y LA SEÑORA SIDNEY PATRICIA VILLEGAS VILORIA, INFORMA QUE POR LAS FUERTE LLUVIA Y BRISA DE ANOCHE SE CAYERON VARIOS ÁRBOLES Y ESTÁ SIN FLUIDO ELÉCTRICO Y DAÑOS EN EL INTERNET. PIDE POR FAVOR ESPERAR A QUE LE SOLUCIONEN PARA RECIBIR LA INSTALACIÓN. 29-08 SE REALIZÓ LLAMADA DE VALIDACIÓN Y EL CLIENTE INFORMA QUE TODAVÍA TIENE PROBLEMAS CON EL CANAL DE COMUNICACIÓN, QUE NO HAN REALIZADO LOS ARREGLOS EN LA ZONA. 30-08 LA ACTIVIDAD SE REAGENDA PARA EL DÍA LUNES 01-09-25. 1/09/2025 SE ESCALA CASO, DONDE SE LLEVA A COMERCIO DE LA PAPELERÍA, PERO EL LOCAL NO CUENTA CON EL NOMBRE DE COMERCIO EN FACHADA, CABE ACLARAR QUE LA MERCANCÍA SI TIENE RELACIÓN CON PAPELERIA, // POR FAVOR, PROCEDAMOS CON LA IMPLANTACIÓN CORRESPONDIENTE Y DEJEMOS COMO EVIDENCIA LA CÁMARA DE COMERCIO, ASÍ COMO LA DOCUMENTACIÓN DE LA NOVEDAD PRESENTADA. 01-09 SE REALIZA INSTALACIÓN DE CORRESPONSAL, SE INSTALAN EQUIPOS CON PRUEBAS EXITOSAS, SE CAPACITA Y SE EVALÚA AL CLIENTE, SE INSTALA PUBLICIDAD COMPLETA, CB QUEDA OPERATIVO. USUARIO SOMOS BANCOLOMBIA ACTIVO. NO SÉ REALIZÓ PRUEBAS DE RECAUDO PORQUE EL CLIENTE NO IBA A PAGAR FACTURA EN EL MOMENTO Y LA DE TRANSFERENCIA EL CLIENTE NO TIENE MÁS CUENTA | T6: VISITA_TÉCNICA | U6: FKZZZ646 | V6: TIPO I | W6: TERRESTRE | X6: CALDERA SALCEDO CARLOS JULIO | Y6: 1 | Z6: 0 | AA6: ='BASE FACTURACION 2025'!$C$3 -> 122645.45 | AB6: ='BASE FACTURACION 2025'!$F$3 -> 65164.678 | AC6: =AA6*Y6+AB6*Z6 -> 122645.45
A7: CALI | B7: =VLOOKUP(A7,'CENTRO DE COSTOS'!A:D,4,FALSE) -> DIEGO FERNANDO HENAO CARDONA | C7: =VLOOKUP(A7,'CENTRO DE COSTOS'!A:D,2,FALSE) -> 0004-0003 | D7: 19809 | E7: TA-25-1033991 | F7: 81252 | G7: APERTURA | H7: CB CRECIMIENTO - NUEVO | I7: CAUCA | J7: TIMBIQUI | K7: BARRIO UNION DE VIVIENDAS TIMBIQUI | L7: REDEBAN | M7: FO-25-1433056 | N7: 45896 | O7: 45904 | P7: UNO A UNO | Q7: UNO A UNO | R7: EJECUTADO | S7: 27-08-2025 SE REALIZA LLAMADA AL CLIENTE, SE HABLA CON LA SRA IRLANDA VENTE CONGOLINO SE VALIDA DIRECCIÓN OK, CANAL OK, DISPONIBILIDAD TOTAL, LLAMAR EL DÍA LA INSTALACIÓN PARA CONFIRMAR VISITA, AVISO EXTERIOR ALTURA APROX 3 METROS; TOMACORRIENTE CERCANO: SI; TIENE CABINA DE SEGURIDAD: SI 04-09 SE REALIZA INSTALACIÓN DE CORRESPONSAL, SE INSTALAN EQUIPOS CON PRUEBAS EXITOSAS, SE CAPACITA Y SE EVALÚA AL CLIENTE, SE INSTALA PUBLICIDAD COMPLETA, CB QUEDA OPERATIVO. USUARIO SOMOS BANCOLOMBIA ACTIVO | T7: VISITA_TÉCNICA | U7: FKZZZ649 | V7: TIPO IV ESPECIAL | W7: AEREO | X7: PAREDES CASTILLO DIEGO | Y7: 1 | Z7: 0 | AA7: ='BASE FACTURACION 2025'!$C$3 -> 122645.45 | AB7: ='BASE FACTURACION 2025'!$F$3 -> 65164.678 | AC7: =AA7*Y7+AB7*Z7 -> 122645.45
A8: NEIVA | B8: =VLOOKUP(A8,'CENTRO DE COSTOS'!A:D,4,FALSE) -> KEVIN ALEXIS CORZO BUSTOS | C8: =VLOOKUP(A8,'CENTRO DE COSTOS'!A:D,2,FALSE) -> 0004-0007 | D8: 18785 | E8: TA-25-1034017 | F8: 81251 | G8: APERTURA | H8: CB CRECIMIENTO - NUEVO | I8: CAQUETA | J8: SOLITA | K8: BARRIO JORDAN SOLITA | L8: REDEBAN | M8: FO-25-1433151 | N8: 45896 | O8: 45902 | P8: UNO A UNO | Q8: UNO A UNO | R8: EJECUTADO | S8: 27-08 SE REALIZA LLAMADA AL CLIENTE, SE HABLA CON LA SRA IDARYI CANO PINZON SE VALIDA DIRECCIÓN OK, CANAL OK, DISPONIBILIDAD TOTAL, LLAMAR EL DÍA LA INSTALACIÓN PARA CONFIRMAR VISITA, AVISO EXTERIOR ALTURA APROX 2 METROS; TOMACORRIENTE CERCANO: SI; TIENE CABINA DE SEGURIDAD: NO - EL MODEM ESTA 5 MT 01-09 EN COMUNICACIÓN CON LA CLIENTA PARA CONFIRMAR LA INSTALACIÓN EL DÍA DE HOY, CLIENTE MANIFIESTO QUE NO ES POSIBLE ATENDER LA VISITA YA QUE POR MOTIVOS PERSONALES ESTÁ EN FLORENCIA REALIZANDO UNAS DILIGENCIAS, MANIFESTÓ ATENDER LA VISITA EL DÍA DE MAÑANA 02 DE SEPTIEMBRE EN EL TRANSCURSO DEL DÍA. 2/09/2025 SE REALIZA INSTALACIÓN DE CORRESPONSAL, SE INSTALAN EQUIPOS CON PRUEBAS EXITOSAS, SE CAPACITA Y SE EVALÚA AL CLIENTE, SE INSTALA PUBLICIDAD COMPLETA, CB QUEDA OPERATIVO. USUARIO SOMOS BANCOLOMBIA ACTIVO | T8: VISITA_TÉCNICA | U8: FKZZZ665 | V8: TIPO IV | W8: TERRESTRE | X8: BERMUDEZ SANCHEZ JOSE NEYBER | Y8: 1 | Z8: 0 | AA8: ='BASE FACTURACION 2025'!$C$3 -> 122645.45 | AB8: ='BASE FACTURACION 2025'!$F$3 -> 65164.678 | AC8: =AA8*Y8+AB8*Z8 -> 122645.45
A9: VILLAVICENCIO | B9: =VLOOKUP(A9,'CENTRO DE COSTOS'!A:D,4,FALSE) -> KEVIN ALEXIS CORZO BUSTOS | C9: =VLOOKUP(A9,'CENTRO DE COSTOS'!A:D,2,FALSE) -> 0004-0007 | D9: 50350 | E9: TA-25-1034022 | F9: 81208 | G9: APERTURA | H9: CB CRECIMIENTO - NUEVO | I9: META | J9: LA MACARENA | K9: BARRIO CENTRO LA MACARENA 9 | L9: REDEBAN | M9: FO-25-1433176 | N9: 45896 | O9: 45903 | P9: UNO A UNO | Q9: UNO A UNO | R9: EJECUTADO | S9: 27-08 SE REALIZA LLAMADA AL CLIENTE, SE HABLA CON LA SR RICARDO FLOREZ ARENAS SE VALIDA DIRECCIÓN OK, CANAL OK, DISPONIBILIDAD TOTAL, LLAMAR EL DÍA LA INSTALACIÓN PARA CONFIRMAR VISITA, AVISO EXTERIOR ALTURA APROX 2 METROS; TOMACORRIENTE CERCANO: SI; TIENE CABINA DE SEGURIDAD: NO - COMUNICACIÓN POR WPP / EL MODEM ESTA A 5 MT Y NO TIENE PUERTO DISPONIBLES ( LLEVAR SWITCH) 03-09 SE REALIZA INSTALACIÓN DE CORRESPONSAL, SE INSTALAN EQUIPOS CON PRUEBAS EXITOSAS, SE CAPACITA Y SE EVALÚA AL CLIENTE, SE INSTALA PUBLICIDAD COMPLETA, CB QUEDA OPERATIVO. USUARIO SOMOS BANCOLOMBIA ACTIVO | T9: VISITA_TÉCNICA | U9: FKZZZ669 | V9: TIPO IV ESPECIAL | W9: AEREO | X9: ROZO JIMENEZ EDGAR ARMANDO | Y9: 1 | Z9: 0 | AA9: ='BASE FACTURACION 2025'!$C$3 -> 122645.45 | AB9: ='BASE FACTURACION 2025'!$F$3 -> 65164.678 | AC9: =AA9*Y9+AB9*Z9 -> 122645.45
A10: BUCARAMANGA | B10: =VLOOKUP(A10,'CENTRO DE COSTOS'!A:D,4,FALSE) -> MIGUEL JULIÁN HERNÁNDEZ GUARÍN | C10: =VLOOKUP(A10,'CENTRO DE COSTOS'!A:D,2,FALSE) -> 0004-0008 | D10: 68679 | E10: TA-25-1034026 | F10: 81247 | G10: APERTURA | H10: CB CRECIMIENTO - NUEVO | I10: SANTANDER | J10: SAN GIL | K10: BARRIO CIUDAD FUTURO ETAPA 3 SAN GIL | L10: REDEBAN | M10: FO-25-1433206 | N10: 45896 | O10: 45901 | P10: UNO A UNO | Q10: UNO A UNO | R10: EJECUTADO | S10: 27-08 SE REALIZA LLAMADA AL CLIENTE, SE HABLA CON LA SRA OLGA PATRICIA SARMIENTO OTERO SE VALIDA DIRECCIÓN OK, CANAL OK, DISPONIBILIDAD TOTAL, LLAMAR EL DÍA LA INSTALACIÓN PARA CONFIRMAR VISITA, AVISO EXTERIOR ALTURA APROX 2 METROS; TOMACORRIENTE CERCANO: SI; TIENE CABINA DE SEGURIDAD: NO - SE PROGRAMA PARA DICHA FECHA POR SOLITUD DEL USUARIO 01-09 SE REALIZA INSTALACIÓN DE CORRESPONSAL, SE INSTALAN EQUIPOS CON PRUEBAS EXITOSAS, SE CAPACITA Y SE EVALÚA AL CLIENTE, SE INSTALA PUBLICIDAD COMPLETA, CB QUEDA OPERATIVO. USUARIO SOMOS BANCOLOMBIA ACTIVO | T10: VISITA_TÉCNICA | U10: FKZZZ672 | V10: TIPO II | W10: TERRESTRE | X10: GELVEZ MOGOLLON JOSE ELISEO | Y10: 1 | Z10: 0 | AA10: ='BASE FACTURACION 2025'!$C$3 -> 122645.45 | AB10: ='BASE FACTURACION 2025'!$F$3 -> 65164.678 | AC10: =AA10*Y10+AB10*Z10 -> 122645.45
A11: CALI | B11: =VLOOKUP(A11,'CENTRO DE COSTOS'!A:D,4,FALSE) -> DIEGO FERNANDO HENAO CARDONA | C11: =VLOOKUP(A11,'CENTRO DE COSTOS'!A:D,2,FALSE) -> 0004-0003 | D11: 76001 | E11: TA-25-1034027 | F11: 81195 | G11: APERTURA | H11: CB CRECIMIENTO - NUEVO | I11: VALLE DEL CAUCA | J11: CALI | K11: BARRIO BENAJAMIN HERRERA CALI | L11: REDEBAN | M11: FO-25-1433211 | N11: 45896 | O11: 45902 | P11: UNO A UNO | Q11: UNO A UNO | R11: EJECUTADO | S11: 27-08 SE REALIZA LLAMADA AL CLIENTE, SE HABLA CON LA SRA MALLERLY RUBIANO LOPEZ SE VALIDA DIRECCIÓN OK, CANAL OK, DISPONIBILIDAD TOTAL, LLAMAR EL DÍA LA INSTALACIÓN PARA CONFIRMAR VISITA, AVISO EXTERIOR ALTURA: NO INDICA ALTURA; TOMACORRIENTE CERCANO: SI; TIENE CABINA DE SEGURIDAD: NO 29/08/2025 SE LLAMA AL CLIENTE AL NÚMERO 3104237740 HABLO CON LA SEÑORA MALLERLY INFORMA QUE EL DÍA DE HOY NO PUEDE ATENDER LA INSTALACIÓN TODO EL PERSONAL DE LA DROGUERÍA ESTÁ EN INVENTARIO NO ALGUIEN MÁS QUE NOS ATIENDA LA ACTIVIDAD NO SE PUEDE REPROGRAMAR VENCE EL HOY, SE LE INDICA AL CLIENTE QUE SE CANCELA LA INSTALACIÓN 01-09 SE LLAMO EL CLIENTE PERO NO CONTESTO, SE REALIZARA LLAMADA EL DIA DE MAÑANA PARA VALIDAR DISPONIBILIDAD 02-09 SE REALIZA INSTALACIÓN DE CORRESPONSAL, SE INSTALAN EQUIPOS CON PRUEBAS EXITOSAS, SE CAPACITA Y SE EVALÚA AL CLIENTE, SE INSTALA PUBLICIDAD COMPLETA, CB QUEDA OPERATIVO. USUARIO SOMOS BANCOLOMBIA ACTIVO | T11: VISITA_TÉCNICA | U11: FKZZZ673 | V11: TIPO I | W11: TERRESTRE | X11: PAREDES CASTILLO DIEGO | Y11: 1 | Z11: 0 | AA11: ='BASE FACTURACION 2025'!$C$3 -> 122645.45 | AB11: ='BASE FACTURACION 2025'!$F$3 -> 65164.678 | AC11: =AA11*Y11+AB11*Z11 -> 122645.45
A12: PASTO | B12: =VLOOKUP(A12,'CENTRO DE COSTOS'!A:D,4,FALSE) -> DIEGO FERNANDO HENAO CARDONA | C12: =VLOOKUP(A12,'CENTRO DE COSTOS'!A:D,2,FALSE) -> 0004-0003 | D12: 86568 | E12: TA-25-1034476 | F12: 81229 | G12: APERTURA | H12: CB CRECIMIENTO ALIANZA - NUEVO | I12: PUTUMAYO | J12: PUERTO ASIS | K12: DISTRICOL LADY PERFUMERIA | L12: REDEBAN | M12: FO-25-1433932 | N12: 45896 | O12: 45902 | P12: AGREGADOR | Q12: DISTRICOL | R12: EJECUTADO | S12: 27-08 PROGRAMACIÓN REALIZADA POR LA ALIANZA 29/08/2025 POR DISPONIBILIDAD DE TRASNPORTE NO ES POSIBLE REALIZAR LA ACTIVIDAD EL DIA DE HOY, SE VIAJARA EL DIA LUNES 01-09 POR RETRASOS DEBIDO A ARREGLOS EN LA VÍA AL PUTUMAYO NO SE ALCANZA A REALIZAR VISITA EL DÍA DE HOY. SE INFORMA A CLIENTE QUE SE VISITARÁ MAÑANA DESPUÉS DE MEDIO DÍA. SEÑORA RUBIELA PIDE SE LA VISITE A LAS 3 PM 2/09/2025 SE REALIZA INSTALACIÓN DE CORRESPONSAL, SE INSTALAN EQUIPOS CON PRUEBAS EXITOSAS, SE CAPACITA Y SE EVALÚA AL CLIENTE, SE INSTALA PUBLICIDAD COMPLETA, CB QUEDA OPERATIVO. USUARIO SOMOS BANCOLOMBIA ACTIVO | T12: VISITA_TÉCNICA | U12: FKZZZ695 | V12: TIPO IV | W12: TERRESTRE | X12: CASTILLO HERRERA ALEX RICARDO | Y12: 1 | Z12: 0 | AA12: ='BASE FACTURACION 2025'!$C$3 -> 122645.45 | AB12: ='BASE FACTURACION 2025'!$F$3 -> 65164.678 | AC12: =AA12*Y12+AB12*Z12 -> 122645.45
A13: MONTERIA | B13: =VLOOKUP(A13,'CENTRO DE COSTOS'!A:D,4,FALSE) -> JOSE MAURICIO HERNANDEZ ROJAS | C13: =VLOOKUP(A13,'CENTRO DE COSTOS'!A:D,2,FALSE) -> 0004-0001 | D13: 5250 | E13: TA-25-1040105 | F13: 81260 | G13: APERTURA | H13: CB CRECIMIENTO ALIANZA - NUEVO | I13: ANTIOQUIA | J13: EL BAGRE | K13: DISTRICOL DROGUERIA G&P | L13: REDEBAN | M13: FO-25-1444555 | N13: 45898 | O13: 45902 | P13: AGREGADOR | Q13: DISTRICOL | R13: EJECUTADO | S13: 29-08 PROGRAMACIÓN REALIZADA POR LA ALIANZA 2/09/2025 SE REALIZA INSTALACIÓN DE CORRESPONSAL, SE INSTALAN EQUIPOS CON PRUEBAS EXITOSAS, SE CAPACITA Y SE EVALÚA AL CLIENTE, SE INSTALA PUBLICIDAD COMPLETA, CB QUEDA OPERATIVO. USUARIO SOMOS BANCOLOMBIA ACTIVO. LAS PRUEBAS DE RECAUDO Y TRANSFERENCIA NO SE REALIZARON PORQUE EL CLIENTE NO TIENE OTRA CUENTA Y NO HAY FACTURAS PARA HACER RECAUDOS | T13: VISITA_TÉCNICA | U13: SKZZZ566 | V13: TIPO IV | W13: TERRESTRE | X13: CALDERA SALCEDO CARLOS JULIO | Y13: 1 | Z13: 0 | AA13: ='BASE FACTURACION 2025'!$C$3 -> 122645.45 | AB13: ='BASE FACTURACION 2025'!$F$3 -> 65164.678 | AC13: =AA13*Y13+AB13*Z13 -> 122645.45
... A213: BUCARAMANGA | B213: =VLOOKUP(A213,'CENTRO DE COSTOS'!A:D,4,FALSE) -> MIGUEL JULIÁN HERNÁNDEZ GUARÍN | C213: =VLOOKUP(A213,'CENTRO DE COSTOS'!A:D,2,FALSE) -> 0004-0008 | D213: 68001 | E213: TA-25-1157235 | F213: 81703 | G213: APERTURA | H213: CB CRECIMIENTO ALIANZA - NUEVO | I213: SANTANDER | J213: BUCARAMANGA | K213: DISTRICOL OPULENCE SHOES | L213: REDEBAN | M213: FO-25-1598678 | N213: 45929 | O213: 45930 | P213: AGREGADOR | Q213: DISTRICOL | R213: EJECUTADO | S213: 29-09 PROGRAMACIÓN REALIZADA POR LA ALIANZA 30/09/2025 SE REALIZA INSTALACIÓN DE CORRESPONSAL, SE INSTALAN EQUIPOS CON PRUEBAS EXITOSAS, SE CAPACITA Y SE EVALÚA AL CLIENTE, SE INSTALA PUBLICIDAD COMPLETA, CB QUEDA OPERATIVO. USUARIO SOMOS BANCOLOMBIA ACTIVO | T213: VISITA_TÉCNICA | U213: FYZZZ196 | V213: TIPO I | W213: TERRESTRE | X213: REYES RAMIREZ DIEGO ALEXANDER | Y213: 1 | Z213: 0 | AA213: ='BASE FACTURACION 2025'!$C$3 -> 122645.45 | AB213: ='BASE FACTURACION 2025'!$F$3 -> 65164.678 | AC213: =AA213*Y213+AB213*Z213 -> 122645.45
AC214: =SUM(AC2:AC213) -> 26000836

Sheet CAPACITACION OC 
A1: Ciudad Sede | B1: COORDINADOR | C1: CENTRO DE COSTOS LÍNEACOM | D1: Código DANE | E1: OC | F1: Cb | G1: Departamento | H1: Ciudad | I1: Nmbre del cb | J1: Red | K1: TA | L1: FO | M1: Fecha apertura del incidente (DD/MM/AAAA) | N1: Fecha Asignación a Línea Comunicaciones (DD/MM/AAAA) | O1: Fecha real de solución (DD/MM/AAAA) | P1: Fecha del cierre del ticket (DD/MM/AAAA) | Q1: FECHA DE PROGRAMACIÓN (DD/MM/AAAA) | R1: Fecha vencimiento del incidente | S1: TIEMPO DE SOLUCIÓN (DIAS) | T1: DENTRO DE LOS SLA | U1: ESTADO | V1: CAUSAL | W1: TIPO DE ACTIVIDAD | X1: SOLICITUD | Y1: DESCRIPCIÓN | Z1: Forma de Atención | AA1: Clase de envío | AB1: DESCRIPCIÓN USD | AC1: Llamada 1 | AD1: Llamada 2 | AE1: Llamada 3 | AF1: Documentación Analistas | AG1: OBSERVACIÓN | AH1: CANTIDAD DE ROLLOS | AI1: RETROALIMENTACIÓN O.T. | AJ1: SERIAL / PLACA- GUIA | AK1: LECTOR | AL1: TERMINAL | AM1: Técnico | AN1: RESPONSABLE INCUMPLIMIENTO | AO1: PORQUE | AP1: Tipo | AQ1: Tipo de Trayecto | AR1: Dias de visita | AS1: SWITCH | AT1: ACOMETIDA DATOS | AU1: ACOMETIDA ELECTRICA | AV1: VALOR ACTIVIDAD | AW1: VALOR TOTAL
B2: =VLOOKUP(A2,'CENTRO DE COSTOS'!A:D,4,FALSE) -> #N/A | C2: =VLOOKUP(A2,'CENTRO DE COSTOS'!A:D,2,FALSE) -> #N/A | AV2: =IF(Z2="SOPORTE_TELEFÓNICO",'BASE FACTURACION 2025'!$E$3,IF(AP2="TIPO I",'BASE FACTURACION 2025'!$D$3,IF(AP2="TIPO II",'BASE FACTURACION 2025'!$D$4,IF(AP2="TIPO III",'BASE FACTURACION 2025'!$D$5,'BASE FACTURACION 2025'!$D$6)))) -> 609719.57 | AW2: =IF(Z2="SOPORTE_TELEFÓNICO",'BASE FACTURACION 2025'!$E$3,AR2*AV2) -> 0
AW3: =SUM(AW2:AW2) -> 0

Sheet CENTRO DE COSTOS
A1: CIUDAD | B1: CENTRO_COSTO | C1: DESCRIPCION | D1: COORDINADOR
A2: APARTADO | B2: 0004-0005 | C2: Redeban Noroccidente (Medellín) | D2: JUAN SEBASTIÁN RÍOS CASTRILLÓN
A3: BARRANQUILLA | B3: 0004-0001 | C3: Redeban Costa (Barranqullla) | D3: JOSE MAURICIO HERNANDEZ ROJAS
A4: BOGOTA | B4: 0004-0004 | C4: Redeban Centro ( Bogotá) | D4: WILLIAM ASDRUBAL ROZO ROZO
A5: BUCARAMANGA | B5: 0004-0008 | C5: Redeban Santander | D5: MIGUEL JULIÁN HERNÁNDEZ GUARÍN
A6: CALI | B6: 0004-0003 | C6: Redeban Suroccidente (Cali) | D6: DIEGO FERNANDO HENAO CARDONA
A7: CARTAGENA | B7: 0004-0001 | C7: Redeban Costa (Barranqullla) | D7: JOSE MAURICIO HERNANDEZ ROJAS
A8: CUCUTA | B8: 0004-0008 | C8: Redeban Santander | D8: MIGUEL JULIÁN HERNÁNDEZ GUARÍN
A9: FLORENCIA | B9: 0004-0007 | C9: Redeban Oriente (Otros) | D9: KEVIN ALEXIS CORZO BUSTOS
A10: IBAGUE | B10: 0004-0007 | C10: Redeban Oriente (Otros) | D10: KEVIN ALEXIS CORZO BUSTOS
A11: MANIZALES | B11: 0004-0002 | C11: Redeban Eje Cafetero (Pereira) | D11: DIEGO FERNANDO HENAO CARDONA
A12: MEDELLIN | B12: 0004-0005 | C12: Redeban Noroccidente (Medellín) | D12: JUAN SEBASTIÁN RÍOS CASTRILLÓN
... A23: YOPAL | B23: 0004-0007 | C23: Redeban Oriente (Otros) | D23: KEVIN ALEXIS CORZO BUSTOS
