Workbook
Name A: #REF!
Name A: #REF!
Name ACTIVIDAD: [1]Hoja2!$P$2:$P$30
Name Actividad: [2]Formulas!$H$2:$H$5000
Name Analistas: '[3]Listas Desplegables'!$T$2:$T$7
Name arearesponsable: '[4]Listas desplegables'!$BB$2:$BB$100
Name CCO: [5]Tecnicos!$A$2:$A$1000
Name Clientes: [6]Clientes!$A$2:$A$100
Name Clientes: [2]Clientes!$A$2:$A$100
Name COORDINADOR: [1]Hoja2!$D$2:$D$30
Name Coordinadores: [7]Coordinadores!$A$2:$A$1000
Name Coordinadores: [2]Coordinadores!$A$2:$A$1000
Name DOCUMENTADOR: [1]Hoja2!$A$2:$A$30
Name ES: [1]Hoja2!$K$2:$K$30
Name ESS: [1]Hoja2!$K$2:$K$30
Name Estado: [6]Formulas!$K$2:$K$5000
Name Estado: [2]Formulas!$K$2:$K$5000
Name ESTADOACTIVIDAD: [1]Hoja2!$M$2:$M$30
Name ESTADOS: '[8]Listas desplegables'!$B$1:$D$1
Name ESTADOS: '[9]Listas desplegables'!$B$1:$D$1
Name ESTADOSCIERRES: '[10]lista desplegable'!$CX$1:$DA$1
Name Facturacion: '[11]Listas desplegables'!$AO$1:$AR$1
Name FACTURACIÓN: '[8]Listas desplegables'!$Y$1:$AB$1
Name FACTURACIÓN: '[9]Listas desplegables'!$Y$1:$AB$1
Name falla: #REF!
Name Fallas: '[12]Listas desplegables'!$F$2:$L$2
Name Fallas: '[13]Listas desplegables'!$F$2:$L$2
Name Grupo_Falla: '[14]Listas Desplegables'!$CH$2:$CH$5
Name Grupo_Falla: '[15]Listas Desplegables'!$CH$2:$CH$5
Name inconservmanager: '[16]Listas desplegables'!$BC$2:$BC$100
Name inconservmanager: '[4]Listas desplegables'!$BC$2:$BC$100
Name INCUMPLIMIENTO: '[4]Listas desplegables'!$AK$1:$AN$1
Name INCUMPLIMIENTO: '[17]Listas desplegables'!$AT$1:$AX$1
Name LISTA: [18]Dptos!$A$1139:$A$1171
Name LISTA: [19]Dptos!$A$1139:$A$1171
Name LISTA2: #REF!
Name LISTA2: [20]Hoja3!$A$1:$A$26
Name LOLO: [21]Coordinadores!$A$2:$A$1000
Name solicitudes: '[11]Listas desplegables'!$U$1:$AF$1
Name solicitudes: '[11]Listas desplegables'!$U$1:$AF$1
Name Tecnicos: [6]Tecnicos!$A$2:$A$1000
Name Tecnicos: [2]Tecnicos!$A$2:$A$1000
Name Version: [22]Formulas!$I$2:$I$3
Name Version: [2]Formulas!$I$2:$I$3

Sheet RESUMEN
A1: =CONCATENATE("TOTAL GENERAL MES ",A3) -> TOTAL GENERAL MES JUNIO DE 2025 | J1: FACTURACIÓN CORRESPONSALES BANCARIOS TIQUIETES AEREOS
A2: MES | B2: NIT Proveedor | C2: Nombre Proveedor (el proveedor ya debe estar creado para el Grupo Bancolombia) | D2: Concepto Facturación | E2: Público al que le instalo la publicidad | F2: No. personas impactadas | G2: Valor a Facturar sin IVA | H2: Valor a Facturar con IVA | J2: CONCEPTOS | K2: TRAYECTOS | L2: TOTAL | M2: % Administración | N2: TOTAL
A3: JUNIO DE 2025 | B3: 811013990-5 | C3: LINEA COMUNICACIONES S.A.S | D3: INSTALACION PUBLICIDAD APERTURAS CORRESPONSALES BANCARIOS | E3: OPERADOR DEL CORRESPONSAL BANCARIO | F3: =COUNTA('PUBLICIDAD APERTURAS'!A:A)-1 -> 490 | G3: ='PUBLICIDAD APERTURAS'!AO492 -> 1.0808399e+08 | H3: =G3*1.19 -> 1.2861994e+08 | J3: APERTURA 79313 | K3: PASTO - OLAYA HERRERA - PASTO | L3: 300000 | M3: =L3*0.12 -> 36000 | N3: =L3+M3 -> 336000
A4: =A3 -> JUNIO DE 2025 | B4: 811013990-5 | C4: LINEA COMUNICACIONES S.A.S | D4: ORDENES DE CAMBIO POR DEMANDA | E4: OPERADOR DEL CORRESPONSAL BANCARIO | F4: =COUNTA('PUBLICIDAD OC'!A:A)-1 -> 118 | G4: ='PUBLICIDAD OC'!AE120 -> 29749553 | H4: =G4*1.19 -> 35401968 | J4: APERTURA 79563 - 79643 | K4: MEDELLIN - ISTMINA - MEDELLIN | L4: 850800 | M4: =L4*0.12 -> 102096 | N4: =L4+M4 -> 952896
A5: =A4 -> JUNIO DE 2025 | B5: 811013990-5 | C5: LINEA COMUNICACIONES S.A.S | D5: TRAYECTOS ESPECIALES OC | E5: OPERADOR DEL CORRESPONSAL BANCARIO | F5: 8 | G5: =N11 -> 4454788.8 | H5: =G5*1.19 -> 5301198.7 | J5: APERTURA 79657 | K5: CALI - TIMBIQUI - CALI | L5: 620900 | M5: =L5*0.12 -> 74508 | N5: =L5+M5 -> 695408
A6: TOTAL A FACTURAR | F6: =SUM(F3:F5) -> 616 | G6: =SUM(G3:G5) -> 1.4228833e+08 | H6: =SUM(H3:H5) -> 1.6932311e+08 | J6: APERTURA 79779 | K6: MEDELLIN - ISTMINA - MEDELLIN | L6: 654800 | M6: =L6*0.12 -> 78576 | N6: =L6+M6 -> 733376
J7: APERTURA 79818 | K7: MEDELLIN - NUQUI - MEDELLIN | L7: 506100 | M7: =L7*0.12 -> 60732 | N7: =L7+M7 -> 566832
J8: APERTURA 79909 - 79910 | K8: BUCARAMANGA - SANTA ROSA DEL SUR - BUCARAMANGA | L8: 300000 | M8: =L8*0.12 -> 36000 | N8: =L8+M8 -> 336000
J9: APERTURA 80036 | K9: MEDELLIN - NUQUI - MEDELLIN | L9: 345740 | M9: =L9*0.12 -> 41488.8 | N9: =L9+M9 -> 387228.8
J10: OC PUBLICIDAD 77228 | K10: MEDELLIN - QUIBDO - MEDELLIN | L10: 399150 | M10: =L10*0.12 -> 47898 | N10: =L10+M10 -> 447048
J11: TOTAL | L11: =SUM(L3:L10) -> 3977490 | M11: =SUM(M3:M10) -> 477298.8 | N11: =SUM(N3:N10) -> 4454788.8

Sheet BASE DE LIQUIDACION 2025
A1: TARIFAS AÑO 2025 | G1: TARIFAS AÑO 2025 | N1: Incremento 2025
A2: TIPOLOGÍA | B2: Instalación de avisos internos | C2: Instalación de avisos EXTERNOS | D2: Transporte de señalización y aviso de 1,50m x 50 cm. | E2: Total Valor Actividad | G2: ORDENES DE CAMBIO | N2: 0.052
A3: TIPO I | B3: =10695.08*(1+$N$2) -> 11251.224 | C3: =120073.31*(1+$N$2) -> 126317.12 | D3: =54574.12*(1+$N$2) -> 57411.974 | E3: =185342.51*(1+$N$2) -> 194980.32 | G3: Tipificación | H3: Descripción | I3: Dia actividad | J3: Transporte | K3: Envio operador Logistico | L3: Gestión telefónica
A4: TIPO II - TIPO III - TIPO IV | B4: =10695.08*(1+$N$2) -> 11251.224 | C4: =120073.31*(1+$N$2) -> 126317.12 | D4: =105331.06*(1+$N$2) -> 110808.28 | E4: =236099.45*(1+$N$2) -> 248376.62 | G4: Tipo I | H4: Metropolitano | I4: =91255.89*(1+$N$2) -> 96001.196 | J4: =54574.12*(1+$N$2) -> 57411.974 | K4: =53547.34*(1+$N$2) -> 56331.802 | L4: =36031.04*(1+$N$2) -> 37904.654
G5: Tipo II | H5: Hasta 3 horas | I5: =221348.48*(1+$N$2) -> 232858.6 | J5: =105331.06*(1+$N$2) -> 110808.28 | K5: =53547.34*(1+$N$2) -> 56331.802 | L5: =36031.04*(1+$N$2) -> 37904.654
G6: Tipo III | H6: De 3 a 5 horas | I6: =327732.48*(1+$N$2) -> 344774.57 | J6: =105331.06*(1+$N$2) -> 110808.28 | K6: =53547.34*(1+$N$2) -> 56331.802 | L6: =36031.04*(1+$N$2) -> 37904.654
G7: Tipo IV | H7: Más de 5 horas | I7: =521514.86*(1+$N$2) -> 548633.63 | J7: =105331.06*(1+$N$2) -> 110808.28 | K7: =53547.34*(1+$N$2) -> 56331.802 | L7: =36031.04*(1+$N$2) -> 37904.654
G8: Destino Aereo* | H8: Viaje en Avión | I8: =521514.86*(1+$N$2) -> 548633.63 | J8: =105331.06*(1+$N$2) -> 110808.28 | K8: =53547.34*(1+$N$2) -> 56331.802 | L8: =36031.04*(1+$N$2) -> 37904.654
G9: * donde se requiera transporte aéreo o fluvial se factura adicional a tarifa TIPO IV el valor del tiquete + el 12% de admon

Sheet Tabla dinámica
A2: PUBLICIDAD APERTURAS | J2: NOMBRE CC | K2: Suma de VALOR | L2: Suma de VALOR2
A3: COORDINADOR | B3: CENTRO DE COSTOS LÍNEACOM | C3: % | D3: $ | E3: NOMBRE CC | F3: VALOR | J3: Redeban Centro ( Bogotá) | K3: 21894105 | L3: 0.15884454
A4: DIEGO FERNANDO HENAO CARDONA | B4: 0004-0002 | C4: 0.059059374 | D4: 6383372.6 | E4: =VLOOKUP(B4,'CENTRO DE COSTOS'!B:C,2,0) -> Redeban Eje Cafetero (Pereira) | F4: =D4 -> 6383372.6 | J4: Redeban Costa (Barranqullla) | K4: 19197961 | L4: 0.13928367
B5: 0004-0003 | C5: 0.1796278 | D5: 19414889 | E5: =VLOOKUP(B5,'CENTRO DE COSTOS'!B:C,2,0) -> Redeban Suroccidente (Cali) | F5: =D5 -> 19414889 | J5: Redeban Eje Cafetero (Pereira) | K5: 7414373.3 | L5: 0.053792228
A6: JOSE MAURICIO HERNANDEZ ROJAS | B6: 0004-0001 | C6: 0.14537167 | D6: 15712349 | E6: =VLOOKUP(B6,'CENTRO DE COSTOS'!B:C,2,0) -> Redeban Costa (Barranqullla) | F6: =D6 -> 15712349 | J6: Redeban Noroccidente (Medellín) | K6: 27023029 | L6: 0.19605554
A7: JUAN SEBASTIÁN RÍOS CASTRILLÓN | B7: 0004-0005 | C7: 0.19874469 | D7: 21481119 | E7: =VLOOKUP(B7,'CENTRO DE COSTOS'!B:C,2,0) -> Redeban Noroccidente (Medellín) | F7: =D7 -> 21481119 | J7: Redeban Oriente (Otros) | K7: 17023112 | L7: 0.12350486
A8: KEVIN ALEXIS CORZO BUSTOS | B8: 0004-0007 | C8: 0.12701007 | D8: 13727755 | E8: =VLOOKUP(B8,'CENTRO DE COSTOS'!B:C,2,0) -> Redeban Oriente (Otros) | F8: =D8 -> 13727755 | J8: Redeban Santander | K8: 22008202 | L8: 0.15967232
A9: MIGUEL JULIÁN HERNÁNDEZ GUARÍN | B9: 0004-0008 | C9: 0.14295883 | D9: 15451560 | E9: =VLOOKUP(B9,'CENTRO DE COSTOS'!B:C,2,0) -> Redeban Santander | F9: =D9 -> 15451560 | J9: Redeban Suroccidente (Cali) | K9: 23272758 | L9: 0.16884684
A10: WILLIAM ASDRUBAL ROZO ROZO | B10: 0004-0004 | C10: 0.14722757 | D10: 15912943 | E10: =VLOOKUP(B10,'CENTRO DE COSTOS'!B:C,2,0) -> Redeban Centro ( Bogotá) | F10: =D10 -> 15912943 | J10: Total general | K10: 1.3783354e+08 | L10: 1
A11: Total general | C11: 1 | D11: 1.0808399e+08
A15: COORDINADOR | B15: CENTRO DE COSTOS LÍNEACOM | C15: % | D15: $ | E15: NOMBRE CC | F15: VALOR
A16: DIEGO FERNANDO HENAO CARDONA | B16: 0004-0002 | C16: 0.034656004 | D16: 1031000.6 | E16: =VLOOKUP(B16,'CENTRO DE COSTOS'!B:C,2,0) -> Redeban Eje Cafetero (Pereira) | F16: =D16 -> 1031000.6
B17: 0004-0003 | C17: 0.12967824 | D17: 3857869.6 | E17: =VLOOKUP(B17,'CENTRO DE COSTOS'!B:C,2,0) -> Redeban Suroccidente (Cali) | F17: =D17 -> 3857869.6
A18: JOSE MAURICIO HERNANDEZ ROJAS | B18: 0004-0001 | C18: 0.11716517 | D18: 3485611.4 | E18: =VLOOKUP(B18,'CENTRO DE COSTOS'!B:C,2,0) -> Redeban Costa (Barranqullla) | F18: =D18 -> 3485611.4
A19: JUAN SEBASTIÁN RÍOS CASTRILLÓN | B19: 0004-0005 | C19: 0.18628549 | D19: 5541910.2 | E19: =VLOOKUP(B19,'CENTRO DE COSTOS'!B:C,2,0) -> Redeban Noroccidente (Medellín) | F19: =D19 -> 5541910.2
A20: KEVIN ALEXIS CORZO BUSTOS | B20: 0004-0007 | C20: 0.11076999 | D20: 3295357.7 | E20: =VLOOKUP(B20,'CENTRO DE COSTOS'!B:C,2,0) -> Redeban Oriente (Otros) | F20: =D20 -> 3295357.7
A21: MIGUEL JULIÁN HERNÁNDEZ GUARÍN | B21: 0004-0008 | C21: 0.22039463 | D21: 6556641.7 | E21: =VLOOKUP(B21,'CENTRO DE COSTOS'!B:C,2,0) -> Redeban Santander | F21: =D21 -> 6556641.7
A22: WILLIAM ASDRUBAL ROZO ROZO | B22: 0004-0004 | C22: 0.20105048 | D22: 5981162 | E22: =VLOOKUP(B22,'CENTRO DE COSTOS'!B:C,2,0) -> Redeban Centro ( Bogotá) | F22: =D22 -> 5981162
A23: Total general | C23: 1 | D23: 29749553

Sheet PUBLICIDAD APERTURAS
A1: CIUDAD | B1: COORDINADOR | C1: CENTRO DE COSTOS LÍNEACOM | D1: CODIGO DANE | E1: TA | F1: FO | G1: FECHA LISTA | H1: FECHA LIMITE | I1: FECHA SOLICITUD DE LA ACTIVIDAD | J1: FECHA INICIO DE LA ACTIVIDAD | K1: FECHA ULTIMA ACTUALIZACION | L1: DEPARTAMENTO | M1: CIUDAD | N1: NOMBRE PUNTO | O1: CÓDIGO PUNTO | P1: TIPO DE APERTURA | Q1: ACTIVIDAD | R1: RED | S1: FORMATO | T1: CADENA | U1: ESTADO | V1: OBSERVACIONES CLIENTE | W1: NOMBRE DEL TECNICO | X1: TERMINALES | Y1: PLACA DATAFONOS INSTALADOS | Z1: PLACA DATAFONOS RETIRADOS | AA1: PLACA LECTOR INSTALADO | AB1: PLACA LECTOR RETIRADO | AC1: OBSERVACION ESTANDAR | AD1: PRIMER CAUSAL DE INCUMPLIMIENTO | AE1: CANTIDAD ROLLOS ENTREGADOS | AF1: TIPIFICACION | AG1: TIPO DE TRAYECTO | AH1: FORMA DE ATENCIÓN | AI1: Flanger, Display Legal, Display Carta o Tabloide | AJ1: Instalación de avisos EXTERNOS | AK1: TRANSPORTE DE AVISO POR INSTALACION O POR NO INSTALACION (IDA-REGRESO) | AL1: VALOR Flanger, Separador, Sticker, Display | AM1: VALOR Instalación de avisos EXTERNOS | AN1: VALOR TRANSPORTE DE AVISO | AO1: VALOR TOTAL INSTALACION DE PUBLICIDAD
A2: PASTO | B2: =VLOOKUP(A2,'CENTRO DE COSTOS'!A:D,4,FALSE) -> DIEGO FERNANDO HENAO CARDONA | C2: =VLOOKUP(A2,'CENTRO DE COSTOS'!A:D,2,FALSE) -> 0004-0003 | D2: 52490 | E2: TA-25-634237 | F2: FO-25-955291 | G2: 45796 | H2: 45805 | I2: 45796 | J2: 45813 | K2: 45813 | L2: NARIÑO | M2: OLAYA HERRERA | N2: BARRIO SAN MARTIN 2 CORREGIMIENTO DE BOAS DE SATINGA OLAYA HERRERA | O2: 79313 | P2: CB CRECIMIENTO - NUEVO | Q2: APERTURA | R2: REDEBAN | S2: UNO A UNO | T2: UNO A UNO | U2: EJECUTADO | V2: 19-05-2025 SE REALIZA LLAMADA AL CLIENTE, SE HABLA CON LA SRA ALEIDA RIASCOS PERLAZA, SE VALIDA DIRECCIÓN OK, CANAL OK, DISPONIBILIDAD TOTAL, LLAMAR EL DÍA LA INSTALACIÓN PARA CONFIRMAR VISITA, AVISO EXTERIOR ALTURA APROX NO TIENE CONOCIMIENTO DE MEDIDAS; TOMACORRIENTE CERCANO: SI; TIENE CABINA DE SEGURIDAD:NO // CONTACTO REALIZADO POR WHATSAPP 28-05 SE REPROGRAMA VISITA PARA LA PRÓXIMA SEMANA SEBIDO A QUE NO SE LOGRO CONSEGUIR TRANSPORTE INTERMUNICIPAL DE CALI A BUENAVENTURA POR CIERRE DE LA VIA 05-06 SE REALIZA INSTALACIÓN DE CORRESPONSAL, SE INSTALAN EQUIPOS CON PRUEBAS EXITOSAS, SE CAPACITA Y SE EVALÚA AL CLIENTE, SE INSTALA PUBLICIDAD COMPLETA, CB QUEDA OPERATIVO. USUARIO SOMOS BANCOLOMBIA ACTIVO | W2: PAREDES CASTILLO DIEGO | X2: A4WZZ840 | Y2: 1169751 | Z2: N/A | AA2: 860310 | AB2: N/A | AC2: FACTOR/EXTERNO | AD2: TRANSPORTE | AE2: 40 ROLLOS | AF2: TIPO IV ESPECIAL | AG2: FLUVIAL | AH2: VISITA_TÉCNICA | AI2: 1 | AJ2: 1 | AK2: 1 | AL2: =IF(AF2="TIPO I",'BASE DE LIQUIDACION 2025'!$B$3,'BASE DE LIQUIDACION 2025'!$B$4) -> 11251.224 | AM2: =IF(AF2="TIPO I",'BASE DE LIQUIDACION 2025'!$C$3,'BASE DE LIQUIDACION 2025'!$C$4) -> 126317.12 | AN2: =IF(AF2="TIPO I",'BASE DE LIQUIDACION 2025'!$D$3,'BASE DE LIQUIDACION 2025'!$D$4) -> 110808.28 | AO2: =AL2*AI2+AJ2*AM2+AK2*AN2 -> 248376.62
A3: BUCARAMANGA | B3: =VLOOKUP(A3,'CENTRO DE COSTOS'!A:D,4,FALSE) -> MIGUEL JULIÁN HERNÁNDEZ GUARÍN | C3: =VLOOKUP(A3,'CENTRO DE COSTOS'!A:D,2,FALSE) -> 0004-0008 | D3: 68276 | E3: TA-25-669597 | F3: FO-25-979659 | G3: 45800 | H3: 45804 | I3: 45800 | J3: 45811 | K3: 45811 | L3: SANTANDER | M3: FLORIDABLANCA | N3: BARRIO CASCO ANTIGUO FLORIDABLANCA FLORIDABLANCA | O3: 79387 | P3: CAMBIO DE RAZON SOCIAL | Q3: APERTURA | R3: REDEBAN | S3: UNO A UNO | T3: UNO A UNO | U3: EJECUTADO | V3: 23-05 SE REALIZA LLAMADA AL CLIENTE, SE HABLA CON LA SRA CARLOS ANDRES MORALES OTERO SE VALIDA DIRECCIÓN OK, CANAL OK, DISPONIBILIDAD TOTAL, LLAMAR EL DÍA LA INSTALACIÓN PARA CONFIRMAR VISITA - CAMBIO DE RAZON SOCIAL - USUARIO SOLICITA FECHA PARA EL MIERCOLES 28-05 SE ESTABLECE COMUNICACIÓN CON EL SEÑOR CARLOS AL NÚMERO 3183832689 QUIEN SOLICITA QUE SE REPROGRAME ACTIVIDAD PARA EL DIA 2 DE JUNIO DEL AÑO EN CURSO DEBIDO A QUE SE ENCUENTRA REALIZAN UNOS EXÁMENES Y NO NOS PUEDE ATENDER 31-05 SE ESTABLECE COMUNICACIÓN CON EL SEÑOR CARLOS AL NÚMERO 3183832689 QUIEN SOLICITA QUE SE REPROGRAME ACTIVIDAD PARA EL DIA 3 DE JUNIO DEL AÑO EN CURSO DEBIDO A QUE SE ENCUENTRA REALIZAN UNOS EXÁMENES Y NO NOS PUEDE ATENDER 3/6/2025 SE REALIZA INSTALACIÓN DE CORRESPONSAL, SE INSTALAN EQUIPOS CON PRUEBAS EXITOSAS, SE CAPACITA Y SE EVALÚA AL CLIENTE, SE INSTALA PUBLICIDAD COMPLETA, CB QUEDA OPERATIVO. USUARIO SOMOS BANCOLOMBIA ACTIVO | W3: BARRERA ORTEGA MARLON STWAR | X3: 10XZZ925-SXXZZ344 | Y3: 989054-1016076 | Z3: 793883 | AA3: 1103341-893140 | AB3: N/A | AC3: USUARIO | AD3: SIN DISPONIBILIDAD | AE3: 40 ROLLOS | AF3: TIPO I | AG3: TERRESTRE | AH3: VISITA_TÉCNICA | AI3: 1 | AJ3: 1 | AK3: 1 | AL3: =IF(AF3="TIPO I",'BASE DE LIQUIDACION 2025'!$B$3,'BASE DE LIQUIDACION 2025'!$B$4) -> 11251.224 | AM3: =IF(AF3="TIPO I",'BASE DE LIQUIDACION 2025'!$C$3,'BASE DE LIQUIDACION 2025'!$C$4) -> 126317.12 | AN3: =IF(AF3="TIPO I",'BASE DE LIQUIDACION 2025'!$D$3,'BASE DE LIQUIDACION 2025'!$D$4) -> 57411.974 | AO3: =AL3*AI3+AJ3*AM3+AK3*AN3 -> 194980.32
A4: VILLAVICENCIO | B4: =VLOOKUP(A4,'CENTRO DE COSTOS'!A:D,4,FALSE) -> KEVIN ALEXIS CORZO BUSTOS | C4: =VLOOKUP(A4,'CENTRO DE COSTOS'!A:D,2,FALSE) -> 0004-0007 | D4: 50124 | E4: TA-25-669663 | F4: FO-25-979669 | G4: 45800 | H4: 45804 | I4: 45800 | J4: 45812 | K4: 45812 | L4: META | M4: CABUYARO | N4: BARRIO CENTRO CABUYARO 5 | O4: 79356 | P4: CB CRECIMIENTO - NUEVO | Q4: APERTURA | R4: REDEBAN | S4: UNO A UNO | T4: UNO A UNO | U4: EJECUTADO | V4: 23-05 SE REALIZA LLAMADA AL CLIENTE, SE HABLA CON LA SR JULIETTE DANIELA QUIJANO ORTIZ SE VALIDA DIRECCIÓN OK, CANAL OK, DISPONIBILIDAD TOTAL, LLAMAR EL DÍA LA INSTALACIÓN PARA CONFIRMAR VISITA, AVISO EXTERIOR ALTURA APROX 2.50 METROS; TOMACORRIENTE CERCANO: SI; TIENE CABINA DE SEGURIDAD: NO 27-05 DE REALIZA CONTACTO TELEFÓNICO 3208738350 CON LA SEÑORA JULIETTE QUIEN MANIFIESTA EL DÍA DE HOY 27 MAYO NO NOS PUEDE ATENDER. SOLICITA VISITA PARA EL DÍA MARTES 3 DE JUNIO 03-06 SE PROGR 4/6/2025 SE REALIZA INSTALACIÓN DE CORRESPONSAL, SE INSTALAN EQUIPOS CON PRUEBAS EXITOSAS, SE CAPACITA Y SE EVALÚA AL CLIENTE, SE INSTALA PUBLICIDAD COMPLETA, CB QUEDA OPERATIVO. USUARIO SOMOS BANCOLOMBIA ACTIVO | W4: CASTRILLON URREA LONDIER LEANDRO | X4: 10XZZ894 | Y4: 859272 | Z4: N/A | AA4: 915631 | AB4: N/A | AC4: USUARIO | AD4: SIN DISPONIBILIDAD | AE4: 40 ROLLOS | AF4: TIPO III | AG4: TERRESTRE | AH4: VISITA_TÉCNICA | AI4: 1 | AJ4: 1 | AK4: 1 | AL4: =IF(AF4="TIPO I",'BASE DE LIQUIDACION 2025'!$B$3,'BASE DE LIQUIDACION 2025'!$B$4) -> 11251.224 | AM4: =IF(AF4="TIPO I",'BASE DE LIQUIDACION 2025'!$C$3,'BASE DE LIQUIDACION 2025'!$C$4) -> 126317.12 | AN4: =IF(AF4="TIPO I",'BASE DE LIQUIDACION 2025'!$D$3,'BASE DE LIQUIDACION 2025'!$D$4) -> 110808.28 | AO4: =AL4*AI4+AJ4*AM4+AK4*AN4 -> 248376.62
A5: CALI | B5: =VLOOKUP(A5,'CENTRO DE COSTOS'!A:D,4,FALSE) -> DIEGO FERNANDO HENAO CARDONA | C5: =VLOOKUP(A5,'CENTRO DE COSTOS'!A:D,2,FALSE) -> 0004-0003 | D5: 19397 | E5: TA-25-680398 | F5: FO-25-1006223 | G5: 45805 | H5: 45807 | I5: 45805 | J5: 45811 | K5: 45811 | L5: CAUCA | M5: LA VEGA | N5: BARRIO SANTA MARIA LA VEGA | O5: 79561 | P5: CB CRECIMIENTO - NUEVO | Q5: APERTURA | R5: REDEBAN | S5: UNO A UNO | T5: UNO A UNO | U5: EJECUTADO | V5: 28-05-2025 SE REALIZA LLAMADA AL CLIENTE, SE HABLA CON EL SR LEINER ALEJANDRO GARCIA MAMIAN SE VALIDA DIRECCIÓN OK, CANAL OK, DISPONIBILIDAD TOTAL, LLAMAR EL DÍA LA INSTALACIÓN PARA CONFIRMAR VISITA, AVISO EXTERIOR ALTURA APROX 1,60 METROS; TOMACORRIENTE CERCANO: SI; TIENE CABINA DE SEGURIDAD: NO // CONTACTO REALIZADO POR LA APP 30-05 SE REALIZA LLAMADA CELULAR AL SEÑOR LEINER Y SE LE INFORMA QUE POR TEMAS DE EL PARO ARMADO NO SE CUENTA CON TRANSPORTE A LA ZONA SE REPROGRAMA VISITA CON EL CB PARA EL DÍA MARTES 3/6/2025 SE REALIZA INSTALACIÓN DE CORRESPONSAL, SE INSTALAN EQUIPOS CON PRUEBAS EXITOSAS, SE CAPACITA Y SE EVALÚA AL CLIENTE, SE INSTALA PUBLICIDAD COMPLETA, CB QUEDA OPERATIVO. USUARIO SOMOS BANCOLOMBIA ACTIVO | W5: GIMBUEL LASSO LUIS GERMAN | X5: LMUZZ995 | Y5: 761185 | Z5: N/A | AA5: 933206 | AB5: N/A | AC5: FACTOR/EXTERNO | AD5: PARO | AE5: 40 ROLLOS | AF5: TIPO IV | AG5: TERRESTRE | AH5: VISITA_TÉCNICA | AI5: 1 | AJ5: 1 | AK5: 1 | AL5: =IF(AF5="TIPO I",'BASE DE LIQUIDACION 2025'!$B$3,'BASE DE LIQUIDACION 2025'!$B$4) -> 11251.224 | AM5: =IF(AF5="TIPO I",'BASE DE LIQUIDACION 2025'!$C$3,'BASE DE LIQUIDACION 2025'!$C$4) -> 126317.12 | AN5: =IF(AF5="TIPO I",'BASE DE LIQUIDACION 2025'!$D$3,'BASE DE LIQUIDACION 2025'!$D$4) -> 110808.28 | AO5: =AL5*AI5+AJ5*AM5+AK5*AN5 -> 248376.62
A6: APARTADO | B6: =VLOOKUP(A6,'CENTRO DE COSTOS'!A:D,4,FALSE) -> JUAN SEBASTIÁN RÍOS CASTRILLÓN | C6: =VLOOKUP(A6,'CENTRO DE COSTOS'!A:D,2,FALSE) -> 0004-0005 | D6: 27135 | E6: TA-25-680419 | F6: FO-25-1006269 | G6: 45805 | H6: 45807 | I6: 45805 | J6: 45814 | K6: 45814 | L6: CHOCO | M6: EL CANTON DEL SAN PABLO | N6: BARRIO AVENIDA 20 DE JULIO CARTON DEL SAN PABLO CHOCO EL CANTON DEL SAN PABLO | O6: 79580 | P6: CB CRECIMIENTO - NUEVO | Q6: APERTURA | R6: REDEBAN | S6: UNO A UNO | T6: UNO A UNO | U6: EJECUTADO | V6: 28-05-2025 SE REALIZA LLAMADA AL CLIENTE, SE HABLA CON LA SRA DORIS MARIA PALACIOS CORDOBA SE VALIDA DIRECCIÓN OK, CANAL OK, DISPONIBILIDAD TOTAL, LLAMAR EL DÍA LA INSTALACIÓN PARA CONFIRMAR VISITA, AVISO EXTERIOR ALTURA APROX 3 - 4 METROS; TOMACORRIENTE CERCANO: SI; TIENE CABINA DE SEGURIDAD: NO // CONTACTO REALIZADO POR LA APP 06-06 SE REALIZA INSTALACIÓN DE CORRESPONSAL, SE INSTALAN EQUIPOS CON PRUEBAS EXITOSAS, SE CAPACITA Y SE EVALÚA AL CLIENTE, SE INSTALA PUBLICIDAD COMPLETA, CB QUEDA OPERATIVO. USUARIO SOMOS BANCOLOMBIA ACTIVO | W6: ROBLEDO DIAZ ANDRES FELIPE | X6: LMVZZ014 | Y6: 792636 | Z6: N/A | AA6: 905838 | AB6: N/A | AC6: FACTOR/EXTERNO | AD6: TRANSPORTE | AE6: 40 ROLLOS | AF6: TIPO IV | AG6: TERRESTRE | AH6: VISITA_TÉCNICA | AI6: 1 | AJ6: 1 | AK6: 1 | AL6: =IF(AF6="TIPO I",'BASE DE LIQUIDACION 2025'!$B$3,'BASE DE LIQUIDACION 2025'!$B$4) -> 11251.224 | AM6: =IF(AF6="TIPO I",'BASE DE LIQUIDACION 2025'!$C$3,'BASE DE LIQUIDACION 2025'!$C$4) -> 126317.12 | AN6: =IF(AF6="TIPO I",'BASE DE LIQUIDACION 2025'!$D$3,'BASE DE LIQUIDACION 2025'!$D$4) -> 110808.28 | AO6: =AL6*AI6+AJ6*AM6+AK6*AN6 -> 248376.62
A7: PASTO | B7: =VLOOKUP(A7,'CENTRO DE COSTOS'!A:D,4,FALSE) -> DIEGO FERNANDO HENAO CARDONA | C7: =VLOOKUP(A7,'CENTRO DE COSTOS'!A:D,2,FALSE) -> 0004-0003 | D7: 52320 | E7: TA-25-680438 | F7: FO-25-1006318 | G7: 45805 | H7: 45807 | I7: 45805 | J7: 45811 | K7: 45811 | L7: NARIÑO | M7: GUAITARILLA | N7: BARRIO CENTRO GUAITARILLA | O7: 79558 | P7: CB CRECIMIENTO - NUEVO | Q7: APERTURA | R7: REDEBAN | S7: UNO A UNO | T7: UNO A UNO | U7: EJECUTADO | V7: 28-05 SE REALIZA LLAMADA AL CLIENTE, SE HABLA CON EL SR JOSE ARMANDO ROSERO MARTINEZ, SE VALIDA DIRECCIÓN OK, CANAL OK, DISPONIBILIDAD TOTAL, LLAMAR EL DÍA LA INSTALACIÓN PARA CONFIRMAR VISITA, AVISO EXTERIOR ALTURA APROX 2 METROS; TOMACORRIENTE CERCANO: SI; TIENE CABINA DE SEGURIDAD:SI //MODEN SE ENCUENTRA A 5 MEGTROS DE DISTANCIA DE DONDE VA SER INSTALADO EL DATAFONO 30-05 NO SE PUEDE NO SE LOGRA TRANSPORTE PARA EL MUNICIPIO DE GUAITARILLA DEBIDO A QUE ZONA NO HAY TRANSPORTE DISPONIBLE. SE VISITARÁ EL DÍA MARTES 03/06/2025 3/6/2025 SE REALIZA INSTALACIÓN DE CORRESPONSAL, SE INSTALAN EQUIPOS CON PRUEBAS EXITOSAS, SE CAPACITA Y SE EVALÚA AL CLIENTE, SE INSTALA PUBLICIDAD COMPLETA, CB QUEDA OPERATIVO. USUARIO SOMOS BANCOLOMBIA ACTIVO | W7: BOLAÑOS TABORDA JORGE ENRIQUE | X7: LMUZZ992 | Y7: 1115746 | Z7: N/A | AA7: 892665 | AB7: N/A | AC7: FACTOR/EXTERNO | AD7: TRANSPORTE | AE7: 40 ROLLOS | AF7: TIPO II | AG7: TERRESTRE | AH7: VISITA_TÉCNICA | AI7: 1 | AJ7: 1 | AK7: 1 | AL7: =IF(AF7="TIPO I",'BASE DE LIQUIDACION 2025'!$B$3,'BASE DE LIQUIDACION 2025'!$B$4) -> 11251.224 | AM7: =IF(AF7="TIPO I",'BASE DE LIQUIDACION 2025'!$C$3,'BASE DE LIQUIDACION 2025'!$C$4) -> 126317.12 | AN7: =IF(AF7="TIPO I",'BASE DE LIQUIDACION 2025'!$D$3,'BASE DE LIQUIDACION 2025'!$D$4) -> 110808.28 | AO7: =AL7*AI7+AJ7*AM7+AK7*AN7 -> 248376.62
A8: MEDELLIN | B8: =VLOOKUP(A8,'CENTRO DE COSTOS'!A:D,4,FALSE) -> JUAN SEBASTIÁN RÍOS CASTRILLÓN | C8: =VLOOKUP(A8,'CENTRO DE COSTOS'!A:D,2,FALSE) -> 0004-0005 | D8: 27361 | E8: TA-25-680473 | F8: FO-25-1006417 | G8: 45805 | H8: 45817 | I8: 45805 | J8: 45812 | K8: 45812 | L8: CHOCO | M8: ISTMINA | N8: BARRIO CUBIS SEC MESETA ALTA ISTMINA CHOCO ISTMINA | O8: 79563 | P8: CB CRECIMIENTO - NUEVO | Q8: APERTURA | R8: REDEBAN | S8: UNO A UNO | T8: UNO A UNO | U8: EJECUTADO | V8: 28-05 SE REALIZA LLAMADA AL CLIENTE, SE HABLA CON LA SRA JOAN AVENDAÑO DAZA SE VALIDA DIRECCIÓN OK, CANAL OK, DISPONIBILIDAD TOTAL, LLAMAR EL DÍA LA INSTALACIÓN PARA CONFIRMAR VISITA, AVISO EXTERIOR ALTURA APROX 2 METROS; TOMACORRIENTE CERCANO: SI; TIENE CABINA DE SEGURIDAD: SI 04-06 SE REALIZA INSTALACIÓN DE CORRESPONSAL, SE INSTALAN EQUIPOS CON PRUEBAS EXITOSAS, SE CAPACITA Y SE EVALÚA AL CLIENTE, SE INSTALA PUBLICIDAD COMPLETA, CB QUEDA OPERATIVO. USUARIO SOMOS BANCOLOMBIA ACTIVO. SE INSTALAN 10 MT DE CABLE UTP | W8: ROBLEDO DIAZ ANDRES FELIPE | X8: LMUZZ997 | Y8: 771855 | Z8: N/A | AA8: 1146028 | AB8: N/A | AC8: N/A | AD8: N/A | AE8: 40 ROLLOS | AF8: TIPO IV ESPECIAL | AG8: AEREO | AH8: VISITA_TÉCNICA | AI8: 1 | AJ8: 1 | AK8: 1 | AL8: =IF(AF8="TIPO I",'BASE DE LIQUIDACION 2025'!$B$3,'BASE DE LIQUIDACION 2025'!$B$4) -> 11251.224 | AM8: =IF(AF8="TIPO I",'BASE DE LIQUIDACION 2025'!$C$3,'BASE DE LIQUIDACION 2025'!$C$4) -> 126317.12 | AN8: =IF(AF8="TIPO I",'BASE DE LIQUIDACION 2025'!$D$3,'BASE DE LIQUIDACION 2025'!$D$4) -> 110808.28 | AO8: =AL8*AI8+AJ8*AM8+AK8*AN8 -> 248376.62
A9: CALI | B9: =VLOOKUP(A9,'CENTRO DE COSTOS'!A:D,4,FALSE) -> DIEGO FERNANDO HENAO CARDONA | C9: =VLOOKUP(A9,'CENTRO DE COSTOS'!A:D,2,FALSE) -> 0004-0003 | D9: 76109 | E9: TA-25-680495 | F9: FO-25-1006485 | G9: 45805 | H9: 45807 | I9: 45805 | J9: 45812 | K9: 45812 | L9: VALLE DEL CAUCA | M9: BUENAVENTURA | N9: BARRIO PUNTA DEL ESTE BUENAVENTURA | O9: 79355 | P9: CB CRECIMIENTO - OTRAS LISTAS | Q9: APERTURA | R9: REDEBAN | S9: UNO A UNO | T9: UNO A UNO | U9: EJECUTADO | V9: 28-05 SE REALIZA LLAMADA AL CLIENTE, SE HABLA CON LA SR JESSICA PAOLA VALENCIA BECERRA SE VALIDA DIRECCIÓN OK, CANAL OK, DISPONIBILIDAD TOTAL, LLAMAR EL DÍA LA INSTALACIÓN PARA CONFIRMAR VISITA, AVISO EXTERIOR ALTURA: NO INDICA ALTURA; TOMACORRIENTE CERCANO: SI; TIENE CABINA DE SEGURIDAD: NO 30-05 DEBIDO A PROBLEMAS EN LA VIA CALI - BUENAVENTURA POR CIERRES Y PROTESTAS NO SE CONSIGUE TRANSPORTE PARA EL PUERTO NO ESTAN SALIENDO LOS BUSES DESDE LA TERMINAL, SE DEBE REALIZAR DESPLAZAMIENTO EL PROXIMO MARTES VALIDANDO ESTADO DEL TRANSPORTE. 4/6/2025 SE REALIZA INSTALACIÓN DE CORRESPONSAL, SE INSTALAN EQUIPOS CON PRUEBAS EXITOSAS, SE CAPACITA Y SE EVALÚA AL CLIENTE, SE INSTALA PUBLICIDAD COMPLETA, CB QUEDA OPERATIVO. USUARIO SOMOS BANCOLOMBIA ACTIVO | W9: PAREDES CASTILLO DIEGO | X9: 10XZZ893 | Y9: 1072780 | Z9: N/A | AA9: 528290 | AB9: N/A | AC9: FACTOR/EXTERNO | AD9: TRANSPORTE | AE9: 40 ROLLOS | AF9: TIPO III | AG9: TERRESTRE | AH9: VISITA_TÉCNICA | AI9: 1 | AJ9: 1 | AK9: 1 | AL9: =IF(AF9="TIPO I",'BASE DE LIQUIDACION 2025'!$B$3,'BASE DE LIQUIDACION 2025'!$B$4) -> 11251.224 | AM9: =IF(AF9="TIPO I",'BASE DE LIQUIDACION 2025'!$C$3,'BASE DE LIQUIDACION 2025'!$C$4) -> 126317.12 | AN9: =IF(AF9="TIPO I",'BASE DE LIQUIDACION 2025'!$D$3,'BASE DE LIQUIDACION 2025'!$D$4) -> 110808.28 | AO9: =AL9*AI9+AJ9*AM9+AK9*AN9 -> 248376.62
A10: CALI | B10: =VLOOKUP(A10,'CENTRO DE COSTOS'!A:D,4,FALSE) -> DIEGO FERNANDO HENAO CARDONA | C10: =VLOOKUP(A10,'CENTRO DE COSTOS'!A:D,2,FALSE) -> 0004-0003 | D10: 76001 | E10: TA-25-680500 | F10: FO-25-1027231 | G10: 45805 | H10: 45807 | I10: 45805 | J10: 45811 | K10: 45811 | L10: VALLE DEL CAUCA | M10: CALI | N10: BARRIO VILLA DEL LAGO CALI 2 | O10: 79361 | P10: CB CRECIMIENTO - OTRAS LISTAS | Q10: APERTURA | R10: REDEBAN | S10: UNO A UNO | T10: UNO A UNO | U10: EJECUTADO | V10: 28-05 SE REALIZA LLAMADA AL CLIENTE, SE HABLA CON LA SRA DEISY (HIJA) SE VALIDA DIRECCIÓN OK, CANAL OK, DISPONIBILIDAD TOTAL, LLAMAR EL DÍA LA INSTALACIÓN PARA CONFIRMAR VISITA, AVISO EXTERIOR ALTURA: NO INDICA ALTURA; TOMACORRIENTE CERCANO: SI; TIENE CABINA DE SEGURIDAD: NO - COMUNICACIÓN POR WPP 30/5/2025 SE LLEGA AL PUNTO DESPUES DE LAS 4 PM YA QUE SE TUVO INCONVENIENTE CON VARIOS CAMBIOS DE EQUIPOS EN LA PRIMERA APERTURA, SE CONFIGURAN EQUIPOS PERO AL MOMENTO DE INICIALIZAR SE ENCUENTRA QUE LA TERMINAL NO ESTA EN BASE 24 , YA NO SE CUENTA CON SOPORTE DE REDEBAN, POR LO CUAL NO SE PUEDE LLEVAR A CABO LA APERTURA 3/6/2025 SE REALIZA INSTALACIÓN DE CORRESPONSAL, SE INSTALAN EQUIPOS CON PRUEBAS EXITOSAS, SE CAPACITA Y SE EVALÚA AL CLIENTE, SE INSTALA PUBLICIDAD COMPLETA, CB QUEDA OPERATIVO. USUARIO SOMOS BANCOLOMBIA ACTIVO | W10: HERRERA MONAR GEOVANNY | X10: 10XZZ899 | Y10: 1219158 | Z10: 1006564 | AA10: 789713 | AB10: N/A | AC10: RED | AD10: SIN SOPORTE RBM | AE10: 40 ROLLOS | AF10: TIPO I | AG10: TERRESTRE | AH10: VISITA_TÉCNICA | AI10: 1 | AJ10: 1 | AK10: 3 | AL10: =IF(AF10="TIPO I",'BASE DE LIQUIDACION 2025'!$B$3,'BASE DE LIQUIDACION 2025'!$B$4) -> 11251.224 | AM10: =IF(AF10="TIPO I",'BASE DE LIQUIDACION 2025'!$C$3,'BASE DE LIQUIDACION 2025'!$C$4) -> 126317.12 | AN10: =IF(AF10="TIPO I",'BASE DE LIQUIDACION 2025'!$D$3,'BASE DE LIQUIDACION 2025'!$D$4) -> 57411.974 | AO10: =AL10*AI10+AJ10*AM10+AK10*AN10 -> 309804.27
A11: VILLAVICENCIO | B11: =VLOOKUP(A11,'CENTRO DE COSTOS'!A:D,4,FALSE) -> KEVIN ALEXIS CORZO BUSTOS | C11: =VLOOKUP(A11,'CENTRO DE COSTOS'!A:D,2,FALSE) -> 0004-0007 | D11: 50001 | E11: TA-25-684715 | F11: FO-25-1016284 | G11: 45807 | H11: 45812 | I11: 45807 | J11: 45812 | K11: 45812 | L11: META | M11: VILLAVICENCIO | N11: BARRIOI CATUMARE VILLAVICENCIO | O11: 79665 | P11: CB CRECIMIENTO - NUEVO | Q11: APERTURA | R11: REDEBAN | S11: UNO A UNO | T11: UNO A UNO | U11: EJECUTADO | V11: 30-05-2025 SE REALIZA LLAMADA AL CLIENTE, SE HABLA CON LA SRA ERIKA FERNANDA MARRERO INFANTE SE VALIDA DIRECCIÓN OK, CANAL OK, DISPONIBILIDAD TOTAL, LLAMAR EL DÍA LA INSTALACIÓN PARA CONFIRMAR VISITA, AVISO EXTERIOR ALTURA: CLIENTE NO TIENE CONOCIMIENTO DE MEDIDAS; TOMACORRIENTE CERCANO: SI; TIENE CABINA DE SEGURIDAD: NO // CONTACTO REALIZADO POR LA APP 4/6/2025 SE REALIZA INSTALACIÓN DE CORRESPONSAL, SE INSTALAN EQUIPOS CON PRUEBAS EXITOSAS, SE CAPACITA Y SE EVALÚA AL CLIENTE, SE INSTALA PUBLICIDAD COMPLETA, CB QUEDA OPERATIVO. USUARIO SOMOS BANCOLOMBIA ACTIVO | W11: PEDREROS CONTRERAS MICHAEL STEVENS | X11: SXUZZ191 | Y11: 1040805 | Z11: 1138829 | AA11: 523819 | AB11: N/A | AC11: N/A | AD11: N/A | AE11: 40 ROLLOS | AF11: TIPO I | AG11: TERRESTRE | AH11: VISITA_TÉCNICA | AI11: 1 | AJ11: 1 | AK11: 1 | AL11: =IF(AF11="TIPO I",'BASE DE LIQUIDACION 2025'!$B$3,'BASE DE LIQUIDACION 2025'!$B$4) -> 11251.224 | AM11: =IF(AF11="TIPO I",'BASE DE LIQUIDACION 2025'!$C$3,'BASE DE LIQUIDACION 2025'!$C$4) -> 126317.12 | AN11: =IF(AF11="TIPO I",'BASE DE LIQUIDACION 2025'!$D$3,'BASE DE LIQUIDACION 2025'!$D$4) -> 57411.974 | AO11: =AL11*AI11+AJ11*AM11+AK11*AN11 -> 194980.32
A12: VILLAVICENCIO | B12: =VLOOKUP(A12,'CENTRO DE COSTOS'!A:D,4,FALSE) -> KEVIN ALEXIS CORZO BUSTOS | C12: =VLOOKUP(A12,'CENTRO DE COSTOS'!A:D,2,FALSE) -> 0004-0007 | D12: 50313 | E12: TA-25-684717 | F12: FO-25-1016288 | G12: 45807 | H12: 45812 | I12: 45807 | J12: 45811 | K12: 45811 | L12: META | M12: GRANADA | N12: BARRIO RICAUTE GRANADA 2 | O12: 79637 | P12: CB CRECIMIENTO - NUEVO | Q12: APERTURA | R12: REDEBAN | S12: UNO A UNO | T12: UNO A UNO | U12: EJECUTADO | V12: 30-05-2025 SE REALIZA LLAMADA AL CLIENTE, SE HABLA CON LA SRA LEIDY VIVIANA PENAGOS ALARCON SE VALIDA DIRECCIÓN OK, CANAL OK, DISPONIBILIDAD TOTAL, LLAMAR EL DÍA LA INSTALACIÓN PARA CONFIRMAR VISITA, AVISO EXTERIOR ALTURA: CLIENTE NO TIENE CONOCIMIENTO DE MEDIDAS; TOMACORRIENTE CERCANO: SI; TIENE CABINA DE SEGURIDAD: NO // CONTACTO REALIZADO POR LA APP 3/6/2025 SE REALIZA VISITA PARA IMPLEMENTACIÓN, PERO SE EVIDENCIA QUE EL BARRIO NO COINCIDE CON EL RELACIONADO EN LISTA DE CHEQUEO, LA DIRECCIÓN CL 19 NRO 12 - 41 ESTÁ BIEN, PERO EL BARRIO ES CENTRO Y NO RICAUTE. POR FAVOR NOS INDICA COMO PROCEDER. 3/6/2025 SE REALIZA INSTALACIÓN DE CORRESPONSAL, SE INSTALAN EQUIPOS CON PRUEBAS EXITOSAS, SE CAPACITA Y SE EVALÚA AL CLIENTE, SE INSTALA PUBLICIDAD COMPLETA, CB QUEDA OPERATIVO. USUARIO SOMOS BANCOLOMBIA ACTIVO | W12: PEDREROS CONTRERAS MICHAEL STEVENS | X12: SXUZZ163 | Y12: 981893 | Z12: N/A | AA12: 514973 | AB12: N/A | AC12: N/A | AD12: N/A | AE12: 40 ROLLOS | AF12: TIPO II | AG12: TERRESTRE | AH12: VISITA_TÉCNICA | AI12: 1 | AJ12: 1 | AK12: 1 | AL12: =IF(AF12="TIPO I",'BASE DE LIQUIDACION 2025'!$B$3,'BASE DE LIQUIDACION 2025'!$B$4) -> 11251.224 | AM12: =IF(AF12="TIPO I",'BASE DE LIQUIDACION 2025'!$C$3,'BASE DE LIQUIDACION 2025'!$C$4) -> 126317.12 | AN12: =IF(AF12="TIPO I",'BASE DE LIQUIDACION 2025'!$D$3,'BASE DE LIQUIDACION 2025'!$D$4) -> 110808.28 | AO12: =AL12*AI12+AJ12*AM12+AK12*AN12 -> 248376.62
A13: NEIVA | B13: =VLOOKUP(A13,'CENTRO DE COSTOS'!A:D,4,FALSE) -> KEVIN ALEXIS CORZO BUSTOS | C13: =VLOOKUP(A13,'CENTRO DE COSTOS'!A:D,2,FALSE) -> 0004-0007 | D13: 41001 | E13: TA-25-684720 | F13: FO-25-1016294 | G13: 45807 | H13: 45812 | I13: 45807 | J13: 45811 | K13: 45811 | L13: HUILA | M13: NEIVA | N13: BARRIO PRADOS DEL SAUCE NEIVA 1 | O13: 79645 | P13: CB CRECIMIENTO - NUEVO | Q13: APERTURA | R13: REDEBAN | S13: UNO A UNO | T13: UNO A UNO | U13: EJECUTADO | V13: 30-05-2025 SE REALIZA LLAMADA AL CLIENTE, SE HABLA CON EL SR JOSE ANDRES PERDOMO PERDOMO SE VALIDA DIRECCIÓN OK, CANAL OK, DISPONIBILIDAD TOTAL, LLAMAR EL DÍA LA INSTALACIÓN PARA CONFIRMAR VISITA, AVISO EXTERIOR ALTURA APROX 1,70 A 2 METROS; TOMACORRIENTE CERCANO: SI; TIENE CABINA DE SEGURIDAD: SI // CONTACTO REALIZADO POR LA APP 03-06 SE REALIZA INSTALACIÓN DE CORRESPONSAL, SE INSTALAN EQUIPOS CON PRUEBAS EXITOSAS, SE CAPACITA Y SE EVALÚA AL CLIENTE, SE INSTALA PUBLICIDAD COMPLETA, CB QUEDA OPERATIVO. USUARIO SOMOS BANCOLOMBIA ACTIVO | W13: DIAZ VARGAS JONATHAN MIGUEL | X13: SXUZZ171 | Y13: 792659 | Z13: N/A | AA13: 892883 | AB13: N/A | AC13: N/A | AD13: N/A | AE13: 40 ROLLOS | AF13: TIPO I | AG13: TERRESTRE | AH13: VISITA_TÉCNICA | AI13: 1 | AJ13: 1 | AK13: 1 | AL13: =IF(AF13="TIPO I",'BASE DE LIQUIDACION 2025'!$B$3,'BASE DE LIQUIDACION 2025'!$B$4) -> 11251.224 | AM13: =IF(AF13="TIPO I",'BASE DE LIQUIDACION 2025'!$C$3,'BASE DE LIQUIDACION 2025'!$C$4) -> 126317.12 | AN13: =IF(AF13="TIPO I",'BASE DE LIQUIDACION 2025'!$D$3,'BASE DE LIQUIDACION 2025'!$D$4) -> 57411.974 | AO13: =AL13*AI13+AJ13*AM13+AK13*AN13 -> 194980.32
A14: VILLAVICENCIO | B14: =VLOOKUP(A14,'CENTRO DE COSTOS'!A:D,4,FALSE) -> KEVIN ALEXIS CORZO BUSTOS | C14: =VLOOKUP(A14,'CENTRO DE COSTOS'!A:D,2,FALSE) -> 0004-0007 | D14: 50001 | E14: TA-25-684721 | F14: FO-25-1016299 | G14: 45807 | H14: 45812 | I14: 45807 | J14: 45812 | K14: 45812 | L14: META | M14: VILLAVICENCIO | N14: BARRIO LA MADRID ETAPA 4 VILLAVICENCIO | O14: 79666 | P14: CB CRECIMIENTO - NUEVO | Q14: APERTURA | R14: REDEBAN | S14: UNO A UNO | T14: UNO A UNO | U14: EJECUTADO | V14: 30-05-2025 SE REALIZA LLAMADA AL CLIENTE, SE HABLA CON LA SRA CAROL JULIETH ARIZA FONTECHA SE VALIDA DIRECCIÓN OK, CANAL OK, DISPONIBILIDAD TOTAL, LLAMAR EL DÍA LA INSTALACIÓN PARA CONFIRMAR VISITA, AVISO EXTERIOR ALTURA: CLIENTE NO TIENE CONOCIMIENTO DE MEDIDAS; TOMACORRIENTE CERCANO: SI; TIENE CABINA DE SEGURIDAD: NO // CONTACTO REALIZADO POR LA APP 4/6/2025 SE REALIZA INSTALACIÓN DE CORRESPONSAL, SE INSTALAN EQUIPOS CON PRUEBAS EXITOSAS, SE CAPACITA Y SE EVALÚA AL CLIENTE, SE INSTALA PUBLICIDAD COMPLETA, CB QUEDA OPERATIVO. USUARIO SOMOS BANCOLOMBIA ACTIVO | W14: ROZO JIMENEZ EDGAR ARMANDO | X14: SXUZZ192 | Y14: 1169258 | Z14: N/A | AA14: 903879 | AB14: N/A | AC14: N/A | AD14: N/A | AE14: 40 ROLLOS | AF14: TIPO I | AG14: TERRESTRE | AH14: VISITA_TÉCNICA | AI14: 1 | AJ14: 1 | AK14: 1 | AL14: =IF(AF14="TIPO I",'BASE DE LIQUIDACION 2025'!$B$3,'BASE DE LIQUIDACION 2025'!$B$4) -> 11251.224 | AM14: =IF(AF14="TIPO I",'BASE DE LIQUIDACION 2025'!$C$3,'BASE DE LIQUIDACION 2025'!$C$4) -> 126317.12 | AN14: =IF(AF14="TIPO I",'BASE DE LIQUIDACION 2025'!$D$3,'BASE DE LIQUIDACION 2025'!$D$4) -> 57411.974 | AO14: =AL14*AI14+AJ14*AM14+AK14*AN14 -> 194980.32
A15: VALLEDUPAR | B15: =VLOOKUP(A15,'CENTRO DE COSTOS'!A:D,4,FALSE) -> JOSE MAURICIO HERNANDEZ ROJAS | C15: =VLOOKUP(A15,'CENTRO DE COSTOS'!A:D,2,FALSE) -> 0004-0001 | D15: 20238 | E15: TA-25-684723 | F15: FO-25-1016304 | G15: 45807 | H15: 45812 | I15: 45807 | J15: 45814 | K15: 45814 | L15: CESAR | M15: EL COPEY | N15: BARRIO EL BOSQUE EL COPEY 1 | O15: 79633 | P15: CB CRECIMIENTO - NUEVO | Q15: APERTURA | R15: REDEBAN | S15: UNO A UNO | T15: UNO A UNO | U15: EJECUTADO | V15: 30-05-2025 SE REALIZA LLAMADA AL CLIENTE, SE HABLA CON LA SRA EDWIN CHINCHILLA MANOSALVA SE VALIDA DIRECCIÓN OK, CANAL OK, DISPONIBILIDAD TOTAL, LLAMAR EL DÍA LA INSTALACIÓN PARA CONFIRMAR VISITA, AVISO EXTERIOR ALTURA: 2,50 METROS; TOMACORRIENTE CERCANO: A 4 METROS ; TIENE CABINA DE SEGURIDAD: NO // CONTACTO REALIZADO POR WHATSAPP 03-06 NO SE PUEDE ACCEDER A LA APERTURA E INSTALACIÓN DE EQUIPOS EN COPEY YA QUE HAY PROTESTA Y PARO EN LA VIA SANTA MARTA Y BOSCONIA POR PARTE DE COMUNIDADES DE LA SIERRA DESDE EL DÍA DE AYER, INFORMAN FUENTES QUE EL PARO VA A SEGUIR HASTA EL RESTO DEL DÍA DE HOY 5/6/2025 SE REALIZA VALIDACIÓN NUEVAMENTE Y LA NOVEDAD CONTINUA6/6/2025 SE REALIZA INSTALACIÓN DE CORRESPONSAL, SE INSTALAN EQUIPOS CON PRUEBAS EXITOSAS, SE CAPACITA Y SE EVALÚA AL CLIENTE, SE INSTALA PUBLICIDAD COMPLETA, CB QUEDA OPERATIVO. USUARIO SOMOS BANCOLOMBIA ACTIVO | W15: MAESTRE MENGUAL EDGAR ENRIQUE | X15: SXUZZ159 | Y15: 929689 | Z15: N/A | AA15: 531715 | AB15: N/A | AC15: FACTOR/EXTERNO | AD15: PARO | AE15: 40 ROLLOS | AF15: TIPO II | AG15: TERRESTRE | AH15: VISITA_TÉCNICA | AI15: 1 | AJ15: 1 | AK15: 1 | AL15: =IF(AF15="TIPO I",'BASE DE LIQUIDACION 2025'!$B$3,'BASE DE LIQUIDACION 2025'!$B$4) -> 11251.224 | AM15: =IF(AF15="TIPO I",'BASE DE LIQUIDACION 2025'!$C$3,'BASE DE LIQUIDACION 2025'!$C$4) -> 126317.12 | AN15: =IF(AF15="TIPO I",'BASE DE LIQUIDACION 2025'!$D$3,'BASE DE LIQUIDACION 2025'!$D$4) -> 110808.28 | AO15: =AL15*AI15+AJ15*AM15+AK15*AN15 -> 248376.62
A16: BARRANQUILLA | B16: =VLOOKUP(A16,'CENTRO DE COSTOS'!A:D,4,FALSE) -> JOSE MAURICIO HERNANDEZ ROJAS | C16: =VLOOKUP(A16,'CENTRO DE COSTOS'!A:D,2,FALSE) -> 0004-0001 | D16: 8001 | E16: TA-25-684728 | F16: FO-25-1016309 | G16: 45807 | H16: 45812 | I16: 45807 | J16: 45811 | K16: 45811 | L16: ATLANTICO | M16: BARRANQUILLA | N16: BARRIO LA MAGDALENA BARRANQUILLA 4 | O16: 79598 | P16: CB CRECIMIENTO - NUEVO | Q16: APERTURA | R16: REDEBAN | S16: UNO A UNO | T16: UNO A UNO | U16: EJECUTADO | V16: 30-05-2025 SE REALIZA LLAMADA AL CLIENTE, SE HABLA CON LA SRA LIGIA MUÑOS SILVA SE VALIDA DIRECCIÓN OK, CANAL OK, DISPONIBILIDAD TOTAL, LLAMAR EL DÍA LA INSTALACIÓN PARA CONFIRMAR VISITA, AVISO EXTERIOR ALTURA: 2,10 METROS; TOMACORRIENTE CERCANO: SI; TIENE CABINA DE SEGURIDAD: SI // CONTACTO REALIZADO POR LA APP 3/6/2025 SE REALIZA INSTALACIÓN DE CORRESPONSAL, SE INSTALAN EQUIPOS CON PRUEBAS EXITOSAS, SE CAPACITA Y SE EVALÚA AL CLIENTE, SE INSTALA PUBLICIDAD COMPLETA, CB QUEDA OPERATIVO. USUARIO SOMOS BANCOLOMBIA ACTIVO | W16: DE AVILA SIADES ALBERTO ENRIQUE | X16: SXUZZ124 | Y16: 1115570 | Z16: N/A | AA16: 905668 | AB16: N/A | AC16: N/A | AD16: N/A | AE16: 40 ROLLOS | AF16: TIPO I | AG16: TERRESTRE | AH16: VISITA_TÉCNICA | AI16: 1 | AJ16: 1 | AK16: 1 | AL16: =IF(AF16="TIPO I",'BASE DE LIQUIDACION 2025'!$B$3,'BASE DE LIQUIDACION 2025'!$B$4) -> 11251.224 | AM16: =IF(AF16="TIPO I",'BASE DE LIQUIDACION 2025'!$C$3,'BASE DE LIQUIDACION 2025'!$C$4) -> 126317.12 | AN16: =IF(AF16="TIPO I",'BASE DE LIQUIDACION 2025'!$D$3,'BASE DE LIQUIDACION 2025'!$D$4) -> 57411.974 | AO16: =AL16*AI16+AJ16*AM16+AK16*AN16 -> 194980.32
A17: CALI | B17: =VLOOKUP(A17,'CENTRO DE COSTOS'!A:D,4,FALSE) -> DIEGO FERNANDO HENAO CARDONA | C17: =VLOOKUP(A17,'CENTRO DE COSTOS'!A:D,2,FALSE) -> 0004-0003 | D17: 76126 | E17: TA-25-684731 | F17: FO-25-1016315 | G17: 45807 | H17: 45812 | I17: 45807 | J17: 45812 | K17: 45812 | L17: VALLE DEL CAUCA | M17: CALIMA | N17: BARRIO OBRERO CALIMA | O17: 79619 | P17: CB CRECIMIENTO - NUEVO | Q17: APERTURA | R17: REDEBAN | S17: UNO A UNO | T17: UNO A UNO | U17: EJECUTADO | V17: 30-05-2025 SE REALIZA LLAMADA AL CLIENTE, SE HABLA CON LA SRA SHARIN LOPEZ ARANA SE VALIDA DIRECCIÓN OK, CANAL OK, DISPONIBILIDAD TOTAL, LLAMAR EL DÍA LA INSTALACIÓN PARA CONFIRMAR VISITA, AVISO EXTERIOR ALTURA: 2 - 2,50 METROS; TOMACORRIENTE CERCANO: SI; TIENE CABINA DE SEGURIDAD: NO // CONTACTO REALIZADO POR LA APP 4/6/2025 SE REALIZA INSTALACIÓN DE CORRESPONSAL, SE INSTALAN EQUIPOS CON PRUEBAS EXITOSAS, SE CAPACITA Y SE EVALÚA AL CLIENTE, SE INSTALA PUBLICIDAD COMPLETA, CB QUEDA OPERATIVO. USUARIO SOMOS BANCOLOMBIA ACTIVO | W17: HERRERA MONAR GEOVANNY | X17: SXUZZ145 | Y17: 793073 | Z17: N/A | AA17: 750456 | AB17: N/A | AC17: N/A | AD17: N/A | AE17: 40 ROLLOS | AF17: TIPO II | AG17: TERRESTRE | AH17: VISITA_TÉCNICA | AI17: 1 | AJ17: 1 | AK17: 1 | AL17: =IF(AF17="TIPO I",'BASE DE LIQUIDACION 2025'!$B$3,'BASE DE LIQUIDACION 2025'!$B$4) -> 11251.224 | AM17: =IF(AF17="TIPO I",'BASE DE LIQUIDACION 2025'!$C$3,'BASE DE LIQUIDACION 2025'!$C$4) -> 126317.12 | AN17: =IF(AF17="TIPO I",'BASE DE LIQUIDACION 2025'!$D$3,'BASE DE LIQUIDACION 2025'!$D$4) -> 110808.28 | AO17: =AL17*AI17+AJ17*AM17+AK17*AN17 -> 248376.62
A18: MEDELLIN | B18: =VLOOKUP(A18,'CENTRO DE COSTOS'!A:D,4,FALSE) -> JUAN SEBASTIÁN RÍOS CASTRILLÓN | C18: =VLOOKUP(A18,'CENTRO DE COSTOS'!A:D,2,FALSE) -> 0004-0005 | D18: 5088 | E18: TA-25-684734 | F18: FO-25-1016320 | G18: 45807 | H18: 45812 | I18: 45807 | J18: 45811 | K18: 45811 | L18: ANTIOQUIA | M18: BELLO | N18: BARRIO PACHELY BELLO 1 | O18: 79661 | P18: CB CRECIMIENTO - NUEVO | Q18: APERTURA | R18: REDEBAN | S18: UNO A UNO | T18: UNO A UNO | U18: EJECUTADO | V18: 30-05-2025 SE REALIZA LLAMADA AL CLIENTE, SE HABLA CON EL SR JUAN DAVID GUTIERREZ OQUENDO SE VALIDA DIRECCIÓN OK, CANAL OK, DISPONIBILIDAD TOTAL, LLAMAR EL DÍA LA INSTALACIÓN PARA CONFIRMAR VISITA, AVISO EXTERIOR ALTURA APROX 3 METROS; TOMACORRIENTE CERCANO: SI; TIENE CABINA DE SEGURIDAD: NO // CONTACTO REALIZADO POR LA APP 3/6/2025 SE REALIZA INSTALACIÓN DE CORRESPONSAL, SE INSTALAN EQUIPOS CON PRUEBAS EXITOSAS, SE CAPACITA Y SE EVALÚA AL CLIENTE, SE INSTALA PUBLICIDAD COMPLETA, CB QUEDA OPERATIVO. USUARIO SOMOS BANCOLOMBIA ACTIVO | W18: ZAPATA LOPEZ EDWARD ASDRUBAL | X18: SXUZZ187 | Y18: 1175437 | Z18: N/A | AA18: 1239626 | AB18: N/A | AC18: N/A | AD18: N/A | AE18: 40 ROLLOS | AF18: TIPO I | AG18: TERRESTRE | AH18: VISITA_TÉCNICA | AI18: 1 | AJ18: 1 | AK18: 1 | AL18: =IF(AF18="TIPO I",'BASE DE LIQUIDACION 2025'!$B$3,'BASE DE LIQUIDACION 2025'!$B$4) -> 11251.224 | AM18: =IF(AF18="TIPO I",'BASE DE LIQUIDACION 2025'!$C$3,'BASE DE LIQUIDACION 2025'!$C$4) -> 126317.12 | AN18: =IF(AF18="TIPO I",'BASE DE LIQUIDACION 2025'!$D$3,'BASE DE LIQUIDACION 2025'!$D$4) -> 57411.974 | AO18: =AL18*AI18+AJ18*AM18+AK18*AN18 -> 194980.32
A19: BOGOTA | B19: =VLOOKUP(A19,'CENTRO DE COSTOS'!A:D,4,FALSE) -> WILLIAM ASDRUBAL ROZO ROZO | C19: =VLOOKUP(A19,'CENTRO DE COSTOS'!A:D,2,FALSE) -> 0004-0004 | D19: 11001 | E19: TA-25-684736 | F19: FO-25-1016326 | G19: 45807 | H19: 45812 | I19: 45807 | J19: 45811 | K19: 45811 | L19: CUNDINAMARCA | M19: BOGOTA | N19: BARRIO EL POA BOGOTA 1 | O19: 79614 | P19: CB CRECIMIENTO - NUEVO | Q19: APERTURA | R19: REDEBAN | S19: UNO A UNO | T19: UNO A UNO | U19: EJECUTADO | V19: 30-05-2025 SE REALIZA LLAMADA AL CLIENTE, SE HABLA CON LA SRA BLANCA NIDIA RAMIREZ QUINTERO SE VALIDA DIRECCIÓN OK, CANAL OK, DISPONIBILIDAD TOTAL, LLAMAR EL DÍA LA INSTALACIÓN PARA CONFIRMAR VISITA, AVISO EXTERIOR ALTURA APROX CLIENTE NO TIENE CONOCIMIENTO DE MEDIDAS; TOMACORRIENTE CERCANO: SI; TIENE CABINA DE SEGURIDAD: SI // CONTACTO REALIZADO POR LA APP 3/6/2025 SE REALIZA INSTALACIÓN DE CORRESPONSAL, SE INSTALAN EQUIPOS CON PRUEBAS EXITOSAS, SE CAPACITA Y SE EVALÚA AL CLIENTE, SE INSTALA PUBLICIDAD COMPLETA, CB QUEDA OPERATIVO. USUARIO SOMOS BANCOLOMBIA ACTIVO | W19: MURCIA HERNANDEZ HARVEY IGNACIO | X19: SXUZZ140 | Y19: 1040491 | Z19: N/A | AA19: 1110498 | AB19: N/A | AC19: N/A | AD19: N/A | AE19: 40 ROLLOS | AF19: TIPO I | AG19: TERRESTRE | AH19: VISITA_TÉCNICA | AI19: 1 | AJ19: 1 | AK19: 1 | AL19: =IF(AF19="TIPO I",'BASE DE LIQUIDACION 2025'!$B$3,'BASE DE LIQUIDACION 2025'!$B$4) -> 11251.224 | AM19: =IF(AF19="TIPO I",'BASE DE LIQUIDACION 2025'!$C$3,'BASE DE LIQUIDACION 2025'!$C$4) -> 126317.12 | AN19: =IF(AF19="TIPO I",'BASE DE LIQUIDACION 2025'!$D$3,'BASE DE LIQUIDACION 2025'!$D$4) -> 57411.974 | AO19: =AL19*AI19+AJ19*AM19+AK19*AN19 -> 194980.32
A20: MEDELLIN | B20: =VLOOKUP(A20,'CENTRO DE COSTOS'!A:D,4,FALSE) -> JUAN SEBASTIÁN RÍOS CASTRILLÓN | C20: =VLOOKUP(A20,'CENTRO DE COSTOS'!A:D,2,FALSE) -> 0004-0005 | D20: 5001 | E20: TA-25-684740 | F20: FO-25-1016330 | G20: 45807 | H20: 45812 | I20: 45807 | J20: 45811 | K20: 45811 | L20: ANTIOQUIA | M20: MEDELLIN | N20: BARRIO CALASANZ MEDELLIN 7 | O20: 79676 | P20: CB CRECIMIENTO - NUEVO | Q20: APERTURA | R20: REDEBAN | S20: UNO A UNO | T20: UNO A UNO | U20: EJECUTADO | V20: 30-05-2025 SE REALIZA LLAMADA AL CLIENTE, SE HABLA CON EL SR LUIS FERNANDO ARIAS RIOS SE VALIDA DIRECCIÓN OK, CANAL OK, DISPONIBILIDAD TOTAL, LLAMAR EL DÍA LA INSTALACIÓN PARA CONFIRMAR VISITA, AVISO EXTERIOR ALTURA APROX NO TIENE CONOCIMIENTO DE MEDIDAS; TOMACORRIENTE CERCANO: SI; TIENE CABINA DE SEGURIDAD: NO // CONTACTO REALIZADO POR LA APP 3/6/2025 SE REALIZA INSTALACIÓN DE CORRESPONSAL, SE INSTALAN EQUIPOS CON PRUEBAS EXITOSAS, SE CAPACITA Y SE EVALÚA AL CLIENTE, SE INSTALA PUBLICIDAD COMPLETA, CB QUEDA OPERATIVO. USUARIO SOMOS BANCOLOMBIA ACTIVO | W20: BADEL ACUÑA LUIS ALBERTO | X20: SXUZZ202 | Y20: 1092122 | Z20: N/A | AA20: 1239775 | AB20: N/A | AC20: N/A | AD20: N/A | AE20: 40 ROLLOS | AF20: TIPO I | AG20: TERRESTRE | AH20: VISITA_TÉCNICA | AI20: 1 | AJ20: 1 | AK20: 1 | AL20: =IF(AF20="TIPO I",'BASE DE LIQUIDACION 2025'!$B$3,'BASE DE LIQUIDACION 2025'!$B$4) -> 11251.224 | AM20: =IF(AF20="TIPO I",'BASE DE LIQUIDACION 2025'!$C$3,'BASE DE LIQUIDACION 2025'!$C$4) -> 126317.12 | AN20: =IF(AF20="TIPO I",'BASE DE LIQUIDACION 2025'!$D$3,'BASE DE LIQUIDACION 2025'!$D$4) -> 57411.974 | AO20: =AL20*AI20+AJ20*AM20+AK20*AN20 -> 194980.32
A21: CALI | B21: =VLOOKUP(A21,'CENTRO DE COSTOS'!A:D,4,FALSE) -> DIEGO FERNANDO HENAO CARDONA | C21: =VLOOKUP(A21,'CENTRO DE COSTOS'!A:D,2,FALSE) -> 0004-0003 | D21: 76001 | E21: TA-25-684743 | F21: FO-25-1016336 | G21: 45807 | H21: 45812 | I21: 45807 | J21: 45811 | K21: 45811 | L21: VALLE DEL CAUCA | M21: CALI | N21: BARRIO ALTOS DE SANTA ELENA CALI | O21: 79618 | P21: CB CRECIMIENTO - NUEVO | Q21: APERTURA | R21: REDEBAN | S21: UNO A UNO | T21: UNO A UNO | U21: EJECUTADO | V21: 30-05-2025 SE REALIZA LLAMADA AL CLIENTE, SE HABLA CON LA SRA DIANA MARCELA VELEZ HUERTAS SE VALIDA DIRECCIÓN OK, CANAL OK, DISPONIBILIDAD TOTAL, LLAMAR EL DÍA LA INSTALACIÓN PARA CONFIRMAR VISITA, AVISO EXTERIOR ALTURA APROX 2 METROS; TOMACORRIENTE CERCANO: SI; TIENE CABINA DE SEGURIDAD: NO // CONTACTO REALIZADO POR LA APP 3/6/2025 SE REALIZA INSTALACIÓN DE CORRESPONSAL, SE INSTALAN EQUIPOS CON PRUEBAS EXITOSAS, SE CAPACITA Y SE EVALÚA AL CLIENTE, SE INSTALA PUBLICIDAD COMPLETA, CB QUEDA OPERATIVO. USUARIO SOMOS BANCOLOMBIA ACTIVO | W21: MONTERO MUESES GIAN CARLO | X21: SXUZZ144 | Y21: 1074324 | Z21: N/A | AA21: 864190 | AB21: N/A | AC21: N/A | AD21: N/A | AE21: 40 ROLLOS | AF21: TIPO I | AG21: TERRESTRE | AH21: VISITA_TÉCNICA | AI21: 1 | AJ21: 1 | AK21: 1 | AL21: =IF(AF21="TIPO I",'BASE DE LIQUIDACION 2025'!$B$3,'BASE DE LIQUIDACION 2025'!$B$4) -> 11251.224 | AM21: =IF(AF21="TIPO I",'BASE DE LIQUIDACION 2025'!$C$3,'BASE DE LIQUIDACION 2025'!$C$4) -> 126317.12 | AN21: =IF(AF21="TIPO I",'BASE DE LIQUIDACION 2025'!$D$3,'BASE DE LIQUIDACION 2025'!$D$4) -> 57411.974 | AO21: =AL21*AI21+AJ21*AM21+AK21*AN21 -> 194980.32
A22: CALI | B22: =VLOOKUP(A22,'CENTRO DE COSTOS'!A:D,4,FALSE) -> DIEGO FERNANDO HENAO CARDONA | C22: =VLOOKUP(A22,'CENTRO DE COSTOS'!A:D,2,FALSE) -> 0004-0003 | D22: 76563 | E22: TA-25-684746 | F22: FO-25-1016342 | G22: 45807 | H22: 45812 | I22: 45807 | J22: 45811 | K22: 45811 | L22: VALLE DEL CAUCA | M22: PRADERA | N22: BARRIO CENTRO PRADERA 9 | O22: 79650 | P22: CB CRECIMIENTO - NUEVO | Q22: APERTURA | R22: REDEBAN | S22: UNO A UNO | T22: UNO A UNO | U22: EJECUTADO | V22: 30-05-2025 SE REALIZA LLAMADA AL CLIENTE, SE HABLA CON LA SRA YEDSICA LORENA PLAZA SALAZAR SE VALIDA DIRECCIÓN OK, CANAL OK, DISPONIBILIDAD TOTAL, LLAMAR EL DÍA LA INSTALACIÓN PARA CONFIRMAR VISITA, AVISO EXTERIOR ALTURA APROX 1,30 METROS; TOMACORRIENTE CERCANO: SI; TIENE CABINA DE SEGURIDAD: NO // CONTACTO REALIZADO POR LA APP 03-06 SE REALIZA INSTALACIÓN DE CORRESPONSAL, SE INSTALAN EQUIPOS CON PRUEBAS EXITOSAS, SE CAPACITA Y SE EVALÚA AL CLIENTE, SE INSTALA PUBLICIDAD COMPLETA, CB QUEDA OPERATIVO. USUARIO SOMOS BANCOLOMBIA ACTIVO | W22: TORRES GARCIA JENDRY JOSE | X22: SXUZZ176 | Y22: 868754 | Z22: N/A | AA22: 846414 | AB22: N/A | AC22: N/A | AD22: N/A | AE22: 40 ROLLOS | AF22: TIPO II | AG22: TERRESTRE | AH22: VISITA_TÉCNICA | AI22: 1 | AJ22: 1 | AK22: 1 | AL22: =IF(AF22="TIPO I",'BASE DE LIQUIDACION 2025'!$B$3,'BASE DE LIQUIDACION 2025'!$B$4) -> 11251.224 | AM22: =IF(AF22="TIPO I",'BASE DE LIQUIDACION 2025'!$C$3,'BASE DE LIQUIDACION 2025'!$C$4) -> 126317.12 | AN22: =IF(AF22="TIPO I",'BASE DE LIQUIDACION 2025'!$D$3,'BASE DE LIQUIDACION 2025'!$D$4) -> 110808.28 | AO22: =AL22*AI22+AJ22*AM22+AK22*AN22 -> 248376.62
A23: BOGOTA | B23: =VLOOKUP(A23,'CENTRO DE COSTOS'!A:D,4,FALSE) -> WILLIAM ASDRUBAL ROZO ROZO | C23: =VLOOKUP(A23,'CENTRO DE COSTOS'!A:D,2,FALSE) -> 0004-0004 | D23: 11001 | E23: TA-25-684748 | F23: FO-25-1016347 | G23: 45807 | H23: 45812 | I23: 45807 | J23: 45811 | K23: 45811 | L23: CUNDINAMARCA | M23: BOGOTA | N23: BARRIO VILLA ALAMOS BOGOTA | O23: 79609 | P23: CB CRECIMIENTO - NUEVO | Q23: APERTURA | R23: REDEBAN | S23: UNO A UNO | T23: UNO A UNO | U23: EJECUTADO | V23: 30-05-2025 SE REALIZA LLAMADA AL CLIENTE, SE HABLA CON LA SRA YESSICA SAAVEDRA PARRA SE VALIDA DIRECCIÓN OK, CANAL OK, DISPONIBILIDAD TOTAL, LLAMAR EL DÍA LA INSTALACIÓN PARA CONFIRMAR VISITA, AVISO EXTERIOR ALTURA APROX 2,50 A 3 METROS; TOMACORRIENTE CERCANO: SI; TIENE CABINA DE SEGURIDAD: NO // CONTACTO REALIZADO POR LA APP 3/6/2025 SE REALIZA INSTALACIÓN DE CORRESPONSAL, SE INSTALAN EQUIPOS CON PRUEBAS EXITOSAS, SE CAPACITA Y SE EVALÚA AL CLIENTE, SE INSTALA PUBLICIDAD COMPLETA, CB QUEDA OPERATIVO. USUARIO SOMOS BANCOLOMBIA ACTIVO | W23: GOMEZ VEGA DAVID SNEYDER | X23: SXUZZ135 | Y23: 1021069 | Z23: N/A | AA23: 1076249 | AB23: N/A | AC23: N/A | AD23: N/A | AE23: 40 ROLLOS | AF23: TIPO I | AG23: TERRESTRE | AH23: VISITA_TÉCNICA | AI23: 1 | AJ23: 1 | AK23: 1 | AL23: =IF(AF23="TIPO I",'BASE DE LIQUIDACION 2025'!$B$3,'BASE DE LIQUIDACION 2025'!$B$4) -> 11251.224 | AM23: =IF(AF23="TIPO I",'BASE DE LIQUIDACION 2025'!$C$3,'BASE DE LIQUIDACION 2025'!$C$4) -> 126317.12 | AN23: =IF(AF23="TIPO I",'BASE DE LIQUIDACION 2025'!$D$3,'BASE DE LIQUIDACION 2025'!$D$4) -> 57411.974 | AO23: =AL23*AI23+AJ23*AM23+AK23*AN23 -> 194980.32
A24: BOGOTA | B24: =VLOOKUP(A24,'CENTRO DE COSTOS'!A:D,4,FALSE) -> WILLIAM ASDRUBAL ROZO ROZO | C24: =VLOOKUP(A24,'CENTRO DE COSTOS'!A:D,2,FALSE) -> 0004-0004 | D24: 11001 | E24: TA-25-684749 | F24: FO-25-1016351 | G24: 45807 | H24: 45812 | I24: 45807 | J24: 45811 | K24: 45811 | L24: CUNDINAMARCA | M24: BOGOTA | N24: BARRIO SANTA LUCIA BOGOTA 11 | O24: 79615 | P24: CB CRECIMIENTO - NUEVO | Q24: APERTURA | R24: REDEBAN | S24: UNO A UNO | T24: UNO A UNO | U24: EJECUTADO | V24: 30-05-2025 SE REALIZA LLAMADA AL CLIENTE, SE HABLA CON LA SRA DORA EDITH NAVARRETE SE VALIDA DIRECCIÓN OK, CANAL OK, DISPONIBILIDAD TOTAL, LLAMAR EL DÍA LA INSTALACIÓN PARA CONFIRMAR VISITA, AVISO EXTERIOR ALTURA APROX 3 METROS; TOMACORRIENTE CERCANO: SI; TIENE CABINA DE SEGURIDAD: SI // CONTACTO REALIZADO POR LA APP 3/6/2025 SE REALIZA INSTALACIÓN DE CORRESPONSAL, SE INSTALAN EQUIPOS CON PRUEBAS EXITOSAS, SE CAPACITA Y SE EVALÚA AL CLIENTE, SE INSTALA PUBLICIDAD COMPLETA, CB QUEDA OPERATIVO. USUARIO SOMOS BANCOLOMBIA ACTIVO | W24: ROMERO ROJAS BREIDY JHOHAN | X24: SXUZZ141 | Y24: 1235482 | Z24: 917143 | AA24: 1139296-241597317561324755897568 | AB24: N/A | AC24: N/A | AD24: N/A | AE24: 40 ROLLOS | AF24: TIPO I | AG24: TERRESTRE | AH24: VISITA_TÉCNICA | AI24: 1 | AJ24: 1 | AK24: 1 | AL24: =IF(AF24="TIPO I",'BASE DE LIQUIDACION 2025'!$B$3,'BASE DE LIQUIDACION 2025'!$B$4) -> 11251.224 | AM24: =IF(AF24="TIPO I",'BASE DE LIQUIDACION 2025'!$C$3,'BASE DE LIQUIDACION 2025'!$C$4) -> 126317.12 | AN24: =IF(AF24="TIPO I",'BASE DE LIQUIDACION 2025'!$D$3,'BASE DE LIQUIDACION 2025'!$D$4) -> 57411.974 | AO24: =AL24*AI24+AJ24*AM24+AK24*AN24 -> 194980.32
A25: MEDELLIN | B25: =VLOOKUP(A25,'CENTRO DE COSTOS'!A:D,4,FALSE) -> JUAN SEBASTIÁN RÍOS CASTRILLÓN | C25: =VLOOKUP(A25,'CENTRO DE COSTOS'!A:D,2,FALSE) -> 0004-0005 | D25: 5079 | E25: TA-25-684752 | F25: FO-25-1016355 | G25: 45807 | H25: 45812 | I25: 45807 | J25: 45812 | K25: 45812 | L25: ANTIOQUIA | M25: BARBOSA | N25: BARRIO GGTO HATILLO BARBOSA BARBOSA | O25: 79624 | P25: CB CRECIMIENTO - NUEVO | Q25: APERTURA | R25: REDEBAN | S25: UNO A UNO | T25: UNO A UNO | U25: EJECUTADO | V25: 30-05-2025 SE REALIZA LLAMADA AL CLIENTE, SE HABLA CON LA SRA ALEJANDRA MARCELA MACIAS ECHEVERRI SE VALIDA DIRECCIÓN OK, CANAL OK, DISPONIBILIDAD TOTAL, LLAMAR EL DÍA LA INSTALACIÓN PARA CONFIRMAR VISITA, AVISO EXTERIOR ALTURA APROX 1,80 METROS; TOMACORRIENTE CERCANO: SI; TIENE CABINA DE SEGURIDAD: SI // CONTACTO REALIZADO POR LA APP 4/6/2025 SE REALIZA INSTALACIÓN DE CORRESPONSAL, SE INSTALAN EQUIPOS CON PRUEBAS EXITOSAS, SE CAPACITA Y SE EVALÚA AL CLIENTE, SE INSTALA PUBLICIDAD COMPLETA, CB QUEDA OPERATIVO. USUARIO SOMOS BANCOLOMBIA ACTIVO. SE PRESENTO NOVEDAD CON DIRECCIÓN YA QUE EN LISTA APARECE CORREGIMIENTO, PERO EN CAMARA DE COMERCIO NO, SE ESCALO CASO A RBM Y AUTORIZARON LA INSTALACIÓN YA QUE EL COMERCIO SI QUEDA EN EL CORREGIMIENTO | W25: ALVAREZ ARENAS VICTOR HUGO | X25: SXUZZ150 | Y25: 1051697 | Z25: N/A | AA25: 863827 | AB25: N/A | AC25: N/A | AD25: N/A | AE25: 40 ROLLOS | AF25: TIPO II | AG25: TERRESTRE | AH25: VISITA_TÉCNICA | AI25: 1 | AJ25: 1 | AK25: 1 | AL25: =IF(AF25="TIPO I",'BASE DE LIQUIDACION 2025'!$B$3,'BASE DE LIQUIDACION 2025'!$B$4) -> 11251.224 | AM25: =IF(AF25="TIPO I",'BASE DE LIQUIDACION 2025'!$C$3,'BASE DE LIQUIDACION 2025'!$C$4) -> 126317.12 | AN25: =IF(AF25="TIPO I",'BASE DE LIQUIDACION 2025'!$D$3,'BASE DE LIQUIDACION 2025'!$D$4) -> 110808.28 | AO25: =AL25*AI25+AJ25*AM25+AK25*AN25 -> 248376.62
A26: BOGOTA | B26: =VLOOKUP(A26,'CENTRO DE COSTOS'!A:D,4,FALSE) -> WILLIAM ASDRUBAL ROZO ROZO | C26: =VLOOKUP(A26,'CENTRO DE COSTOS'!A:D,2,FALSE) -> 0004-0004 | D26: 11001 | E26: TA-25-684755 | F26: FO-25-1016360 | G26: 45807 | H26: 45812 | I26: 45807 | J26: 45812 | K26: 45812 | L26: CUNDINAMARCA | M26: BOGOTA | N26: BARRIO LAS ACACIAS BOGOTA 1 | O26: 79610 | P26: CAMBIO DE REZON SOCIAL | Q26: APERTURA | R26: REDEBAN | S26: UNO A UNO | T26: UNO A UNO | U26: EJECUTADO | V26: 30-05-2025 SE REALIZA LLAMADA AL CLIENTE, SE HABLA CON LA HERMANA DEL SR JAIBER JULIAN LOPEZ MARTINEZ SE VALIDA DIRECCIÓN OK, CANAL OK, DISPONIBILIDAD TOTAL, LLAMAR EL DÍA LA INSTALACIÓN PARA CONFIRMAR VISITA, AVISO EXTERIOR ALTURA APROX 2; TOMACORRIENTE CERCANO: SI; TIENE CABINA DE SEGURIDAD: SI // CONTACTO REALIZADO POR LA APP 03-06 EN COMUNICACIÓN CON EL COMERCIO PARA VALIDAR APERTURA AL JAIBER JULIAN LOPEZ MARTINEZ / TELEFONO DE CONTACTO: 3222100576, MANIFIESTA RECIBIR EL DÍA DE MAÑANA 04-06-2025 4/6/2025 SE REALIZA INSTALACIÓN DE CORRESPONSAL, SE INSTALAN EQUIPOS CON PRUEBAS EXITOSAS, SE CAPACITA Y SE EVALÚA AL CLIENTE, SE INSTALA PUBLICIDAD COMPLETA, CB QUEDA OPERATIVO. USUARIO SOMOS BANCOLOMBIA ACTIVO | W26: ROMERO ROJAS BREIDY JHOHAN | X26: SXUZZ136 | Y26: 1235338 | Z26: 893558 | AA26: 984296-241587317561324755886591 | AB26: N/A | AC26: N/A | AD26: N/A | AE26: 40 ROLLOS | AF26: TIPO I | AG26: TERRESTRE | AH26: VISITA_TÉCNICA | AI26: 1 | AJ26: 1 | AK26: 1 | AL26: =IF(AF26="TIPO I",'BASE DE LIQUIDACION 2025'!$B$3,'BASE DE LIQUIDACION 2025'!$B$4) -> 11251.224 | AM26: =IF(AF26="TIPO I",'BASE DE LIQUIDACION 2025'!$C$3,'BASE DE LIQUIDACION 2025'!$C$4) -> 126317.12 | AN26: =IF(AF26="TIPO I",'BASE DE LIQUIDACION 2025'!$D$3,'BASE DE LIQUIDACION 2025'!$D$4) -> 57411.974 | AO26: =AL26*AI26+AJ26*AM26+AK26*AN26 -> 194980.32
A27: MEDELLIN | B27: =VLOOKUP(A27,'CENTRO DE COSTOS'!A:D,4,FALSE) -> JUAN SEBASTIÁN RÍOS CASTRILLÓN | C27: =VLOOKUP(A27,'CENTRO DE COSTOS'!A:D,2,FALSE) -> 0004-0005 | D27: 5308 | E27: TA-25-684757 | F27: FO-25-1016370 | G27: 45807 | H27: 45812 | I27: 45807 | J27: 45811 | K27: 45811 | L27: ANTIOQUIA | M27: GIRARDOTA | N27: BARRIO SANTA ANA GIRARDOTA 1 | O27: 79627 | P27: CAMBIO DE RAZON SOCIAL | Q27: APERTURA | R27: REDEBAN | S27: UNO A UNO | T27: UNO A UNO | U27: EJECUTADO | V27: 30-05-2025 SE REALIZA LLAMADA AL CLIENTE, SE HABLA CON LA SRA ANGELA YANETH BEDOYA JARAMILLOI SE VALIDA DIRECCIÓN OK, CANAL OK, DISPONIBILIDAD TOTAL, LLAMAR EL DÍA LA INSTALACIÓN PARA CONFIRMAR VISITA, AVISO EXTERIOR ALTURA APROX 2 METROS; TOMACORRIENTE CERCANO: SI; TIENE CABINA DE SEGURIDAD: SI // CONTACTO REALIZADO POR LA APP 03-06 SE REALIZA INSTALACIÓN DE CORRESPONSAL POR CAMBIO DE RAZON SOCIAL, SE INSTALAN EQUIPOS CON PRUEBAS EXITOSAS, NO SE CAPACITA Y SE EVALÚA AL CLIENTE, SE INSTALA FLANGGER Y DISPLAY DE HORARIO, EL AVISO YA ESTABA INSTALADO EN BUEN ESTADO, SE REGGRESA EL QUE SE LLEVO A BODEGA, CB QUEDA OPERATIVO. USUARIO SOMOS BANCOLOMBIA ACTIVO | W27: MARTINEZ TOVAR OSCAR DAVID | X27: SXUZZ153 | Y27: 771289 | Z27: N/A | AA27: 940524 | AB27: 1239756 | AC27: N/A | AD27: N/A | AE27: 40 ROLLOS | AF27: TIPO I | AG27: TERRESTRE | AH27: VISITA_TÉCNICA | AI27: 1 | AJ27: 0 | AK27: 2 | AL27: =IF(AF27="TIPO I",'BASE DE LIQUIDACION 2025'!$B$3,'BASE DE LIQUIDACION 2025'!$B$4) -> 11251.224 | AM27: =IF(AF27="TIPO I",'BASE DE LIQUIDACION 2025'!$C$3,'BASE DE LIQUIDACION 2025'!$C$4) -> 126317.12 | AN27: =IF(AF27="TIPO I",'BASE DE LIQUIDACION 2025'!$D$3,'BASE DE LIQUIDACION 2025'!$D$4) -> 57411.974 | AO27: =AL27*AI27+AJ27*AM27+AK27*AN27 -> 126075.17
A28: MEDELLIN | B28: =VLOOKUP(A28,'CENTRO DE COSTOS'!A:D,4,FALSE) -> JUAN SEBASTIÁN RÍOS CASTRILLÓN | C28: =VLOOKUP(A28,'CENTRO DE COSTOS'!A:D,2,FALSE) -> 0004-0005 | D28: 5001 | E28: TA-25-684760 | F28: FO-25-1016375 | G28: 45807 | H28: 45812 | I28: 45807 | J28: 45811 | K28: 45811 | L28: ANTIOQUIA | M28: MEDELLIN | N28: BARRIO BELLEN MEDELLIN | O28: 79669 | P28: CAMBIO DE RAZON SOCIAL | Q28: APERTURA | R28: REDEBAN | S28: UNO A UNO | T28: UNO A UNO | U28: EJECUTADO | V28: 30-05-2025 SE REALIZA LLAMADA AL CLIENTE, SE HABLA CON EL SR WALTER ANDRES HERNANDEZ GUERRA SE VALIDA DIRECCIÓN OK, CANAL OK, DISPONIBILIDAD TOTAL, LLAMAR EL DÍA LA INSTALACIÓN PARA CONFIRMAR VISITA, AVISO EXTERIOR ALTURA APROX 3 - 4 METROS; TOMACORRIENTE CERCANO: SI; TIENE CABINA DE SEGURIDAD: SI // CONTACTO REALIZADO POR LA APP 3/6/2025 SE REALIZA INSTALACIÓN DE CORRESPONSAL POR CAMBIO DE RAZON SOCIAL, SE INSTALAN EQUIPOS CON PRUEBAS EXITOSAS, SE CAPACITA Y SE EVALÚA AL CLIENTE, NO SE INSTALA PUBLICIDAD, CB QUEDA OPERATIVO. USUARIO SOMOS BANCOLOMBIA ACTIVO | W28: QUINTERO SANCHEZ JUAN SEBASTIAN | X28: SXUZZ195 | Y28: 772256 | Z28: N/A | AA28: 1239771 | AB28: N/A | AC28: N/A | AD28: N/A | AE28: 40 ROLLOS | AF28: TIPO I | AG28: TERRESTRE | AH28: VISITA_TÉCNICA | AI28: 0 | AJ28: 0 | AK28: 2 | AL28: =IF(AF28="TIPO I",'BASE DE LIQUIDACION 2025'!$B$3,'BASE DE LIQUIDACION 2025'!$B$4) -> 11251.224 | AM28: =IF(AF28="TIPO I",'BASE DE LIQUIDACION 2025'!$C$3,'BASE DE LIQUIDACION 2025'!$C$4) -> 126317.12 | AN28: =IF(AF28="TIPO I",'BASE DE LIQUIDACION 2025'!$D$3,'BASE DE LIQUIDACION 2025'!$D$4) -> 57411.974 | AO28: =AL28*AI28+AJ28*AM28+AK28*AN28 -> 114823.95
A29: CARTAGENA | B29: =VLOOKUP(A29,'CENTRO DE COSTOS'!A:D,4,FALSE) -> JOSE MAURICIO HERNANDEZ ROJAS | C29: =VLOOKUP(A29,'CENTRO DE COSTOS'!A:D,2,FALSE) -> 0004-0001 | D29: 13001 | E29: TA-25-684762 | F29: FO-25-1016379 | G29: 45807 | H29: 45812 | I29: 45807 | J29: 45812 | K29: 45812 | L29: BOLIVAR | M29: CARTAGENA | N29: BARRIO LOS ANGELES CARTAGENA DE INDIAS | O29: 79621 | P29: CB CRECIMIENTO - NUEVO | Q29: APERTURA | R29: REDEBAN | S29: UNO A UNO | T29: UNO A UNO | U29: EJECUTADO | V29: 30-05-2025 SE REALIZA LLAMADA AL CLIENTE, SE HABLA CON LA SRA GERALDINE OYOLA MENDOZA SE VALIDA DIRECCIÓN OK, CANAL OK, DISPONIBILIDAD TOTAL, LLAMAR EL DÍA LA INSTALACIÓN PARA CONFIRMAR VISITA, AVISO EXTERIOR ALTURA APROX 1,50 - 2 METROS; TOMACORRIENTE CERCANO: SI; TIENE CABINA DE SEGURIDAD: SI // CONTACTO REALIZADO POR LA APP 04-06 SE REALIZA INSTALACIÓN DE CORRESPONSAL, SE INSTALAN EQUIPOS CON PRUEBAS EXITOSAS, SE CAPACITA Y SE EVALÚA AL CLIENTE, SE INSTALA PUBLICIDAD COMPLETA, CB QUEDA OPERATIVO. USUARIO SOMOS BANCOLOMBIA ACTIVO | W29: CANEDO HERRERA ALEXANDER | X29: SXUZZ147 | Y29: 791031 | Z29: N/A | AA29: 529616 | AB29: N/A | AC29: N/A | AD29: N/A | AE29: 40 ROLLOS | AF29: TIPO I | AG29: TERRESTRE | AH29: VISITA_TÉCNICA | AI29: 1 | AJ29: 1 | AK29: 1 | AL29: =IF(AF29="TIPO I",'BASE DE LIQUIDACION 2025'!$B$3,'BASE DE LIQUIDACION 2025'!$B$4) -> 11251.224 | AM29: =IF(AF29="TIPO I",'BASE DE LIQUIDACION 2025'!$C$3,'BASE DE LIQUIDACION 2025'!$C$4) -> 126317.12 | AN29: =IF(AF29="TIPO I",'BASE DE LIQUIDACION 2025'!$D$3,'BASE DE LIQUIDACION 2025'!$D$4) -> 57411.974 | AO29: =AL29*AI29+AJ29*AM29+AK29*AN29 -> 194980.32
A30: TUNJA | B30: =VLOOKUP(A30,'CENTRO DE COSTOS'!A:D,4,FALSE) -> MIGUEL JULIÁN HERNÁNDEZ GUARÍN | C30: =VLOOKUP(A30,'CENTRO DE COSTOS'!A:D,2,FALSE) -> 0004-0008 | D30: 15759 | E30: TA-25-684764 | F30: FO-25-1033867 | G30: 45807 | H30: 45812 | I30: 45807 | J30: 45813 | K30: 45813 | L30: BOYACA | M30: SOGAMOSO | N30: BARRIO LA PRADERA SOGAMOSO 3 | O30: 79655 | P30: CB CRECIMIENTO - NUEVO | Q30: APERTURA | R30: REDEBAN | S30: UNO A UNO | T30: UNO A UNO | U30: EJECUTADO | V30: 30-05-2025 SE REALIZA LLAMADA AL CLIENTE, SE HABLA CON LA SRA LADIS ESPERANZA SOSA AMAROI SE VALIDA DIRECCIÓN OK, CANAL OK, DISPONIBILIDAD TOTAL, LLAMAR EL DÍA LA INSTALACIÓN PARA CONFIRMAR VISITA, AVISO EXTERIOR ALTURA APROX 3 METROS; TOMACORRIENTE CERCANO: SI; TIENE CABINA DE SEGURIDAD: NO // CONTACTO REALIZADO POR LA APP 3/6/2025 SE VISITA COMERCIO ,LA INSTALACIÓN EL DIA DE HOY ES FALLIDA COMERCIO SIN COMUNICACION RED DE INTERNET ,EL USUARIO INDICA QUE SE COMUNICARA CON EL PROVEDOR DEL INTERNET PARA QUE HABILITE LA RED DE COMUNICACIÓN EN EL COMERCIO A INSTALAR , SE REPROGRAMA VISITA PARA EL DIA JUEVES 05 DE JUNIO DEL 2025 INDICA QUE PARA ESE DIA TENDRIA LISTO EL PUNTO DE INTERNET 5/6/2025 SE REALIZA INSTALACIÓN DE CORRESPONSAL, SE INSTALAN EQUIPOS CON PRUEBAS EXITOSAS, SE CAPACITA Y SE EVALÚA AL CLIENTE, SE INSTALA PUBLICIDAD COMPLETA, CB QUEDA OPERATIVO. USUARIO SOMOS BANCOLOMBIA ACTIVO | W30: ALVARADO MORENO CRISTHIAN | X30: SXUZZ181 | Y30: 793119 | Z30: N/A | AA30: 905615 | AB30: N/A | AC30: USUARIO | AD30: SIN CANAL DE COMUNICACIÓN | AE30: 40 ROLLOS | AF30: TIPO II | AG30: TERRESTRE | AH30: VISITA_TÉCNICA | AI30: 1 | AJ30: 1 | AK30: 3 | AL30: =IF(AF30="TIPO I",'BASE DE LIQUIDACION 2025'!$B$3,'BASE DE LIQUIDACION 2025'!$B$4) -> 11251.224 | AM30: =IF(AF30="TIPO I",'BASE DE LIQUIDACION 2025'!$C$3,'BASE DE LIQUIDACION 2025'!$C$4) -> 126317.12 | AN30: =IF(AF30="TIPO I",'BASE DE LIQUIDACION 2025'!$D$3,'BASE DE LIQUIDACION 2025'!$D$4) -> 110808.28 | AO30: =AL30*AI30+AJ30*AM30+AK30*AN30 -> 469993.17
A31: MEDELLIN | B31: =VLOOKUP(A31,'CENTRO DE COSTOS'!A:D,4,FALSE) -> JUAN SEBASTIÁN RÍOS CASTRILLÓN | C31: =VLOOKUP(A31,'CENTRO DE COSTOS'!A:D,2,FALSE) -> 0004-0005 | D31: 5088 | E31: TA-25-684767 | F31: FO-25-1016389 | G31: 45807 | H31: 45812 | I31: 45807 | J31: 45811 | K31: 45811 | L31: ANTIOQUIA | M31: BELLO | N31: BARRIO BELLO BELLO 24 | O31: 79660 | P31: CB CRECIMIENTO - NUEVO | Q31: APERTURA | R31: REDEBAN | S31: UNO A UNO | T31: UNO A UNO | U31: EJECUTADO | V31: 30-05-2025 SE REALIZA LLAMADA AL CLIENTE, SE HABLA CON LA SRA JULIANA HOLGUIN BEDOYA SE VALIDA DIRECCIÓN OK, CANAL OK, DISPONIBILIDAD TOTAL, LLAMAR EL DÍA LA INSTALACIÓN PARA CONFIRMAR VISITA, AVISO EXTERIOR ALTURA APROX CLIENTE NO TIENE CONOCIMIENTO DE MEDIDAS; TOMACORRIENTE CERCANO: SI; TIENE CABINA DE SEGURIDAD: SI // CONTACTO REALIZADO POR LA APP 3/6/2025 SE REALIZA INSTALACIÓN DE CORRESPONSAL, SE INSTALAN EQUIPOS CON PRUEBAS EXITOSAS, SE CAPACITA Y SE EVALÚA AL CLIENTE, SE INSTALA PUBLICIDAD COMPLETA, CB QUEDA OPERATIVO. USUARIO SOMOS BANCOLOMBIA ACTIVO | X31: SXUZZ186 | Y31: 929521 | Z31: N/A | AA31: 1239599 | AB31: N/A | AC31: N/A | AD31: N/A | AE31: 40 ROLLOS | AF31: TIPO I | AG31: TERRESTRE | AH31: VISITA_TÉCNICA | AI31: 1 | AJ31: 1 | AK31: 1 | AL31: =IF(AF31="TIPO I",'BASE DE LIQUIDACION 2025'!$B$3,'BASE DE LIQUIDACION 2025'!$B$4) -> 11251.224 | AM31: =IF(AF31="TIPO I",'BASE DE LIQUIDACION 2025'!$C$3,'BASE DE LIQUIDACION 2025'!$C$4) -> 126317.12 | AN31: =IF(AF31="TIPO I",'BASE DE LIQUIDACION 2025'!$D$3,'BASE DE LIQUIDACION 2025'!$D$4) -> 57411.974 | AO31: =AL31*AI31+AJ31*AM31+AK31*AN31 -> 194980.32
A32: VILLAVICENCIO | B32: =VLOOKUP(A32,'CENTRO DE COSTOS'!A:D,4,FALSE) -> KEVIN ALEXIS CORZO BUSTOS | C32: =VLOOKUP(A32,'CENTRO DE COSTOS'!A:D,2,FALSE) -> 0004-0007 | D32: 50001 | E32: TA-25-684770 | F32: FO-25-1016394 | G32: 45807 | H32: 45812 | I32: 45807 | J32: 45811 | K32: 45811 | L32: META | M32: VILLAVICENCIO | N32: BARRIO VILLA DEL ORIENTE VILLAVICENCIO | O32: 79664 | P32: CB CRECIMIENTO - NUEVO | Q32: APERTURA | R32: REDEBAN | S32: UNO A UNO | T32: UNO A UNO | U32: EJECUTADO | V32: 30-05-2025 SE REALIZA LLAMADA AL CLIENTE, SE HABLA CON LA SRA MARIA MELIDA FORERO DIOSA SE VALIDA DIRECCIÓN OK, CANAL OK, DISPONIBILIDAD TOTAL, LLAMAR EL DÍA LA INSTALACIÓN PARA CONFIRMAR VISITA, AVISO EXTERIOR ALTURA APROX 1,20 METROS; TOMACORRIENTE CERCANO: SI; TIENE CABINA DE SEGURIDAD: SI // CONTACTO REALIZADO POR LA APP 3/6/2025 SE REALIZA INSTALACIÓN DE CORRESPONSAL, SE INSTALAN EQUIPOS CON PRUEBAS EXITOSAS, SE CAPACITA Y SE EVALÚA AL CLIENTE, SE INSTALA PUBLICIDAD COMPLETA, CB QUEDA OPERATIVO. USUARIO SOMOS BANCOLOMBIA ACTIVO | W32: ROZO JIMENEZ EDGAR ARMANDO | X32: SXUZZ190 | Y32: 750929 | Z32: N/A | AA32: 906002 | AB32: N/A | AC32: N/A | AD32: N/A | AE32: 40 ROLLOS | AF32: TIPO I | AG32: TERRESTRE | AH32: VISITA_TÉCNICA | AI32: 1 | AJ32: 1 | AK32: 1 | AL32: =IF(AF32="TIPO I",'BASE DE LIQUIDACION 2025'!$B$3,'BASE DE LIQUIDACION 2025'!$B$4) -> 11251.224 | AM32: =IF(AF32="TIPO I",'BASE DE LIQUIDACION 2025'!$C$3,'BASE DE LIQUIDACION 2025'!$C$4) -> 126317.12 | AN32: =IF(AF32="TIPO I",'BASE DE LIQUIDACION 2025'!$D$3,'BASE DE LIQUIDACION 2025'!$D$4) -> 57411.974 | AO32: =AL32*AI32+AJ32*AM32+AK32*AN32 -> 194980.32
A33: VILLAVICENCIO | B33: =VLOOKUP(A33,'CENTRO DE COSTOS'!A:D,4,FALSE) -> KEVIN ALEXIS CORZO BUSTOS | C33: =VLOOKUP(A33,'CENTRO DE COSTOS'!A:D,2,FALSE) -> 0004-0007 | D33: 50001 | E33: TA-25-684772 | F33: FO-25-1016402 | G33: 45807 | H33: 45812 | I33: 45807 | J33: 45811 | K33: 45811 | L33: META | M33: VILLAVICENCIO | N33: BARRIO ESTERO VILLAVICENCIO 17 | O33: 79663 | P33: CB CRECIMIENTO - NUEVO | Q33: APERTURA | R33: REDEBAN | S33: UNO A UNO | T33: UNO A UNO | U33: EJECUTADO | V33: 30-05 SE REALIZA LLAMADA AL CLIENTE, SE HABLA CON EL SR FABIO NELSON CASTAÑEDA OSORIO SE VALIDA DIRECCIÓN OK, CANAL OK, DISPONIBILIDAD TOTAL, LLAMAR EL DÍA LA INSTALACIÓN PARA CONFIRMAR VISITA, AVISO EXTERIOR ALTURA APROX DONDE EL TECNICO LO VEA CONVENIENTE METROS; TOMACORRIENTE CERCANO: SI; TIENE CABINA DE SEGURIDAD: SI 03-06 SE REALIZA INSTALACIÓN DE CORRESPONSAL, SE INSTALAN EQUIPOS CON PRUEBAS EXITOSAS, SE CAPACITA Y SE EVALÚA AL CLIENTE, SE INSTALA PUBLICIDAD COMPLETA, CB QUEDA OPERATIVO. USUARIO SOMOS BANCOLOMBIA ACTIVO | W33: ROZO JIMENEZ EDGAR ARMANDO | X33: SXUZZ189 | Y33: 930615 | Z33: N/A | AA33: 770645 | AB33: N/A | AC33: N/A | AD33: N/A | AE33: 40 ROLLOS | AF33: TIPO I | AG33: TERRESTRE | AH33: VISITA_TÉCNICA | AI33: 1 | AJ33: 1 | AK33: 1 | AL33: =IF(AF33="TIPO I",'BASE DE LIQUIDACION 2025'!$B$3,'BASE DE LIQUIDACION 2025'!$B$4) -> 11251.224 | AM33: =IF(AF33="TIPO I",'BASE DE LIQUIDACION 2025'!$C$3,'BASE DE LIQUIDACION 2025'!$C$4) -> 126317.12 | AN33: =IF(AF33="TIPO I",'BASE DE LIQUIDACION 2025'!$D$3,'BASE DE LIQUIDACION 2025'!$D$4) -> 57411.974 | AO33: =AL33*AI33+AJ33*AM33+AK33*AN33 -> 194980.32
A34: BOGOTA | B34: =VLOOKUP(A34,'CENTRO DE COSTOS'!A:D,4,FALSE) -> WILLIAM ASDRUBAL ROZO ROZO | C34: =VLOOKUP(A34,'CENTRO DE COSTOS'!A:D,2,FALSE) -> 0004-0004 | D34: 25290 | E34: TA-25-684774 | F34: FO-25-1016410 | G34: 45807 | H34: 45812 | I34: 45807 | J34: 45812 | K34: 45812 | L34: CUNDINAMARCA | M34: FUSAGASUGA | N34: BARRIO ACROPOLIS FUSAGUSUGA | O34: 79636 | P34: CB CRECIMIENTO - NUEVO | Q34: APERTURA | R34: REDEBAN | S34: UNO A UNO | T34: UNO A UNO | U34: EJECUTADO | V34: 30-05 SE REALIZA LLAMADA AL CLIENTE, SE HABLA CON EL SR HAROLD ALONSO RAMIREZ PERALTA, SE VALIDA DIRECCIÓN OK, CANAL OK, DISPONIBILIDAD TOTAL, LLAMAR EL DÍA LA INSTALACIÓN PARA CONFIRMAR VISITA, AVISO EXTERIOR ALTURA APROX DONDE EL TECNICO LO VEA CONVENIENTE METROS; TOMACORRIENTE CERCANO: SI; TIENE CABINA DE SEGURIDAD: SI 4/6/2025 SE REALIZA INSTALACIÓN DE CORRESPONSAL, SE INSTALAN EQUIPOS CON PRUEBAS EXITOSAS, SE CAPACITA Y SE EVALÚA AL CLIENTE, SE INSTALA PUBLICIDAD COMPLETA, CB QUEDA OPERATIVO. USUARIO SOMOS BANCOLOMBIA ACTIVO | W34: CORTES VELANDIA MIGUEL ANGEL | X34: SXUZZ162 | Y34: 991083 | Z34: N/A | AA34: 941150 | AB34: N/A | AC34: N/A | AD34: N/A | AE34: 40 ROLLOS | AF34: TIPO II | AG34: TERRESTRE | AH34: VISITA_TÉCNICA | AI34: 1 | AJ34: 1 | AK34: 1 | AL34: =IF(AF34="TIPO I",'BASE DE LIQUIDACION 2025'!$B$3,'BASE DE LIQUIDACION 2025'!$B$4) -> 11251.224 | AM34: =IF(AF34="TIPO I",'BASE DE LIQUIDACION 2025'!$C$3,'BASE DE LIQUIDACION 2025'!$C$4) -> 126317.12 | AN34: =IF(AF34="TIPO I",'BASE DE LIQUIDACION 2025'!$D$3,'BASE DE LIQUIDACION 2025'!$D$4) -> 110808.28 | AO34: =AL34*AI34+AJ34*AM34+AK34*AN34 -> 248376.62
A35: TUNJA | B35: =VLOOKUP(A35,'CENTRO DE COSTOS'!A:D,4,FALSE) -> MIGUEL JULIÁN HERNÁNDEZ GUARÍN | C35: =VLOOKUP(A35,'CENTRO DE COSTOS'!A:D,2,FALSE) -> 0004-0008 | D35: 68385 | E35: TA-25-684777 | F35: FO-25-1016414 | G35: 45807 | H35: 45812 | I35: 45807 | J35: 45812 | K35: 45812 | L35: SANTANDER | M35: LANDAZURI | N35: BARRIO LA INDIA LANDAZURI | O35: 79641 | P35: CB CRECIMIENTO - NUEVO | Q35: APERTURA | R35: REDEBAN | S35: UNO A UNO | T35: UNO A UNO | U35: EJECUTADO | V35: 30-05 SE REALIZA LLAMADA AL CLIENTE, SE HABLA CON LA SRA ELIANA MARIA MENA LEAL SE VALIDA DIRECCIÓN OK, CANAL OK, DISPONIBILIDAD TOTAL, LLAMAR EL DÍA LA INSTALACIÓN PARA CONFIRMAR VISITA, AVISO EXTERIOR ALTURA APROX 3 METROS; TOMACORRIENTE CERCANO: SI; TIENE CABINA DE SEGURIDAD: NO 4/6/2025 SE REALIZA INSTALACIÓN DE CORRESPONSAL, SE INSTALAN EQUIPOS CON PRUEBAS EXITOSAS, SE CAPACITA Y SE EVALÚA AL CLIENTE, SE INSTALA PUBLICIDAD COMPLETA, CB QUEDA OPERATIVO. USUARIO SOMOS BANCOLOMBIA ACTIVO | W35: REYES RAMIREZ DIEGO ALEXANDER | X35: SXUZZ167 | Y35: 1036960 | Z35: N/A | AA35: 997338 | AB35: N/A | AC35: N/A | AD35: N/A | AE35: 40 ROLLOS | AF35: TIPO III | AG35: TERRESTRE | AH35: VISITA_TÉCNICA | AI35: 1 | AJ35: 1 | AK35: 1 | AL35: =IF(AF35="TIPO I",'BASE DE LIQUIDACION 2025'!$B$3,'BASE DE LIQUIDACION 2025'!$B$4) -> 11251.224 | AM35: =IF(AF35="TIPO I",'BASE DE LIQUIDACION 2025'!$C$3,'BASE DE LIQUIDACION 2025'!$C$4) -> 126317.12 | AN35: =IF(AF35="TIPO I",'BASE DE LIQUIDACION 2025'!$D$3,'BASE DE LIQUIDACION 2025'!$D$4) -> 110808.28 | AO35: =AL35*AI35+AJ35*AM35+AK35*AN35 -> 248376.62
A36: CUCUTA | B36: =VLOOKUP(A36,'CENTRO DE COSTOS'!A:D,4,FALSE) -> MIGUEL JULIÁN HERNÁNDEZ GUARÍN | C36: =VLOOKUP(A36,'CENTRO DE COSTOS'!A:D,2,FALSE) -> 0004-0008 | D36: 54518 | E36: TA-25-684781 | F36: FO-25-1016417 | G36: 45807 | H36: 45812 | I36: 45807 | J36: 45812 | K36: 45812 | L36: NORTE DE SANTANDER | M36: PAMPLONA | N36: BARRIO GALAN PAMPLONA 2 | O36: 79646 | P36: CB CRECIMIENTO - NUEVO | Q36: APERTURA | R36: REDEBAN | S36: UNO A UNO | T36: UNO A UNO | U36: EJECUTADO | V36: 30-05 SE REALIZA LLAMADA AL CLIENTE, SE HABLA CON LA SRA YESSICA PAOLA ORDÓÑEZ VELAZCO, SE VALIDA DIRECCIÓN OK, CANAL OK, DISPONIBILIDAD TOTAL, LLAMAR EL DÍA LA INSTALACIÓN PARA CONFIRMAR VISITA, AVISO EXTERIOR ALTURA APROX DONDE EL TECNICO LO VEA CONVENIENTE METROS; TOMACORRIENTE CERCANO: SI; TIENE CABINA DE SEGURIDAD: NO 4/6/2025 SE REALIZA INSTALACIÓN DE CORRESPONSAL, SE INSTALAN EQUIPOS CON PRUEBAS EXITOSAS, SE CAPACITA Y SE EVALÚA AL CLIENTE, SE INSTALA PUBLICIDAD COMPLETA, CB QUEDA OPERATIVO. USUARIO SOMOS BANCOLOMBIA ACTIVO | W36: NARANJO AFANADOR RUBEN JESUS | X36: SXUZZ172 | Y36: 763376 | Z36: 1173852 | AA36: 1145445 | AB36: N/A | AC36: N/A | AD36: N/A | AE36: 40 ROLLOS | AF36: TIPO III | AG36: TERRESTRE | AH36: VISITA_TÉCNICA | AI36: 1 | AJ36: 1 | AK36: 1 | AL36: =IF(AF36="TIPO I",'BASE DE LIQUIDACION 2025'!$B$3,'BASE DE LIQUIDACION 2025'!$B$4) -> 11251.224 | AM36: =IF(AF36="TIPO I",'BASE DE LIQUIDACION 2025'!$C$3,'BASE DE LIQUIDACION 2025'!$C$4) -> 126317.12 | AN36: =IF(AF36="TIPO I",'BASE DE LIQUIDACION 2025'!$D$3,'BASE DE LIQUIDACION 2025'!$D$4) -> 110808.28 | AO36: =AL36*AI36+AJ36*AM36+AK36*AN36 -> 248376.62
A37: MEDELLIN | B37: =VLOOKUP(A37,'CENTRO DE COSTOS'!A:D,4,FALSE) -> JUAN SEBASTIÁN RÍOS CASTRILLÓN | C37: =VLOOKUP(A37,'CENTRO DE COSTOS'!A:D,2,FALSE) -> 0004-0005 | D37: 5036 | E37: TA-25-684784 | F37: FO-25-1016422 | G37: 45807 | H37: 45812 | I37: 45807 | J37: 45812 | K37: 45812 | L37: ANTIOQUIA | M37: ANGELOPOLIS | N37: BRRIO ANGELOPOLIS ANTIOQUIA, CERCA LA ESTACION ANGELOPOLIS | O37: 79635 | P37: CB CRECIMIENTO - NUEVO | Q37: APERTURA | R37: REDEBAN | S37: UNO A UNO | T37: UNO A UNO | U37: EJECUTADO | V37: 30-05 SE REALIZA LLAMADA AL CLIENTE, SE HABLA CON LA SRA ANGELA TATIANA MONCADA PARRA, SE VALIDA DIRECCIÓN OK, CANAL OK, DISPONIBILIDAD TOTAL, LLAMAR EL DÍA LA INSTALACIÓN PARA CONFIRMAR VISITA, AVISO EXTERIOR ALTURA APROX 1,20 METROS; TOMACORRIENTE CERCANO: SI; TIENE CABINA DE SEGURIDAD: NO 4/6/2025 SE REALIZA INSTALACIÓN DE CORRESPONSAL, SE INSTALAN EQUIPOS CON PRUEBAS EXITOSAS, SE CAPACITA Y SE EVALÚA AL CLIENTE, SE INSTALA PUBLICIDAD COMPLETA, CB QUEDA OPERATIVO. USUARIO SOMOS BANCOLOMBIA ACTIVO | W37: CASTAÑEDA PALACIO CARLOS FELIPE | X37: SXUZZ161 | Y37: 960504 | Z37: N/A | AA37: 789543 | AB37: N/A | AC37: N/A | AD37: N/A | AE37: 40 ROLLOS | AF37: TIPO II | AG37: TERRESTRE | AH37: VISITA_TÉCNICA | AI37: 1 | AJ37: 1 | AK37: 1 | AL37: =IF(AF37="TIPO I",'BASE DE LIQUIDACION 2025'!$B$3,'BASE DE LIQUIDACION 2025'!$B$4) -> 11251.224 | AM37: =IF(AF37="TIPO I",'BASE DE LIQUIDACION 2025'!$C$3,'BASE DE LIQUIDACION 2025'!$C$4) -> 126317.12 | AN37: =IF(AF37="TIPO I",'BASE DE LIQUIDACION 2025'!$D$3,'BASE DE LIQUIDACION 2025'!$D$4) -> 110808.28 | AO37: =AL37*AI37+AJ37*AM37+AK37*AN37 -> 248376.62
A38: CALI | B38: =VLOOKUP(A38,'CENTRO DE COSTOS'!A:D,4,FALSE) -> DIEGO FERNANDO HENAO CARDONA | C38: =VLOOKUP(A38,'CENTRO DE COSTOS'!A:D,2,FALSE) -> 0004-0003 | D38: 76001 | E38: TA-25-684789 | F38: FO-25-1016428 | G38: 45807 | H38: 45812 | I38: 45807 | J38: 45811 | K38: 45811 | L38: VALLE DEL CAUCA | M38: CALI | N38: BARRIO AGUA BLANCA CALI | O38: 79617 | P38: CB CRECIMIENTO - NUEVO | Q38: APERTURA | R38: REDEBAN | S38: UNO A UNO | T38: UNO A UNO | U38: EJECUTADO | V38: 30-05 SE REALIZA LLAMADA AL CLIENTE, SE HABLA CON LA SRA LIZETH MARIANA GALINDO ORTIZ, SE VALIDA DIRECCIÓN OK, CANAL OK, DISPONIBILIDAD TOTAL, LLAMAR EL DÍA LA INSTALACIÓN PARA CONFIRMAR VISITA, AVISO EXTERIOR ALTURA APROX DONDE EL TECNICO LO VEA CONVENIENTE METROS; TOMACORRIENTE CERCANO: SI; TIENE CABINA DE SEGURIDAD: NO 03-06 SE REALIZA INSTALACIÓN DE CORRESPONSAL, SE INSTALAN EQUIPOS CON PRUEBAS EXITOSAS, SE CAPACITA Y SE EVALÚA AL CLIENTE, SE INSTALA PUBLICIDAD COMPLETA, CB QUEDA OPERATIVO. USUARIO SOMOS BANCOLOMBIA ACTIVO | W38: MONTERO MUESES GIAN CARLO | X38: SXUZZ143 | Y38: 1171539 | Z38: N/A | AA38: 549981 | AB38: N/A | AC38: N/A | AD38: N/A | AE38: 40 ROLLOS | AF38: TIPO I | AG38: TERRESTRE | AH38: VISITA_TÉCNICA | AI38: 1 | AJ38: 1 | AK38: 1 | AL38: =IF(AF38="TIPO I",'BASE DE LIQUIDACION 2025'!$B$3,'BASE DE LIQUIDACION 2025'!$B$4) -> 11251.224 | AM38: =IF(AF38="TIPO I",'BASE DE LIQUIDACION 2025'!$C$3,'BASE DE LIQUIDACION 2025'!$C$4) -> 126317.12 | AN38: =IF(AF38="TIPO I",'BASE DE LIQUIDACION 2025'!$D$3,'BASE DE LIQUIDACION 2025'!$D$4) -> 57411.974 | AO38: =AL38*AI38+AJ38*AM38+AK38*AN38 -> 194980.32
A39: MEDELLIN | B39: =VLOOKUP(A39,'CENTRO DE COSTOS'!A:D,4,FALSE) -> JUAN SEBASTIÁN RÍOS CASTRILLÓN | C39: =VLOOKUP(A39,'CENTRO DE COSTOS'!A:D,2,FALSE) -> 0004-0005 | D39: 5001 | E39: TA-25-684791 | F39: FO-25-1016434 | G39: 45807 | H39: 45812 | I39: 45807 | J39: 45811 | K39: 45811 | L39: ANTIOQUIA | M39: MEDELLIN | N39: BARRIO LAURELES MEDELLIN 20 | O39: 79673 | P39: CB CRECIMIENTO - NUEVO | Q39: APERTURA | R39: REDEBAN | S39: UNO A UNO | T39: UNO A UNO | U39: EJECUTADO | V39: 30-05 SE REALIZA LLAMADA AL CLIENTE, SE HABLA CON LA SR ANDRES FELIPE GALVIS ESPINOSA SE VALIDA DIRECCIÓN OK, CANAL OK, DISPONIBILIDAD TOTAL, LLAMAR EL DÍA LA INSTALACIÓN PARA CONFIRMAR VISITA, AVISO EXTERIOR ALTURA APROX 2.50 METROS; TOMACORRIENTE CERCANO: SI; TIENE CABINA DE SEGURIDAD: NO 3/6/2025 SE REALIZA INSTALACIÓN DE CORRESPONSAL, SE INSTALAN EQUIPOS CON PRUEBAS EXITOSAS, SE CAPACITA Y SE EVALÚA AL CLIENTE, SE INSTALA PUBLICIDAD COMPLETA, CB QUEDA OPERATIVO. USUARIO SOMOS BANCOLOMBIA ACTIVO | W39: BADEL ACUÑA LUIS ALBERTO | X39: SXUZZ199 | Y39: 1051975 | Z39: N/A | AA39: 1239605 | AB39: N/A | AC39: N/A | AD39: N/A | AE39: 40 ROLLOS | AF39: TIPO I | AG39: TERRESTRE | AH39: VISITA_TÉCNICA | AI39: 1 | AJ39: 1 | AK39: 1 | AL39: =IF(AF39="TIPO I",'BASE DE LIQUIDACION 2025'!$B$3,'BASE DE LIQUIDACION 2025'!$B$4) -> 11251.224 | AM39: =IF(AF39="TIPO I",'BASE DE LIQUIDACION 2025'!$C$3,'BASE DE LIQUIDACION 2025'!$C$4) -> 126317.12 | AN39: =IF(AF39="TIPO I",'BASE DE LIQUIDACION 2025'!$D$3,'BASE DE LIQUIDACION 2025'!$D$4) -> 57411.974 | AO39: =AL39*AI39+AJ39*AM39+AK39*AN39 -> 194980.32
A40: BOGOTA | B40: =VLOOKUP(A40,'CENTRO DE COSTOS'!A:D,4,FALSE) -> WILLIAM ASDRUBAL ROZO ROZO | C40: =VLOOKUP(A40,'CENTRO DE COSTOS'!A:D,2,FALSE) -> 0004-0004 | D40: 11001 | E40: TA-25-684792 | F40: FO-25-1016438 | G40: 45807 | H40: 45812 | I40: 45807 | J40: 45811 | K40: 45811 | L40: CUNDINAMARCA | M40: BOGOTA | N40: BARRIO PUENTE ARANDA BOGOTA 8 | O40: 79604 | P40: CB CRECIMIENTO - NUEVO | Q40: APERTURA | R40: REDEBAN | S40: UNO A UNO | T40: UNO A UNO | U40: EJECUTADO | V40: 30-05 SE REALIZA LLAMADA AL CLIENTE, SE HABLA CON LA SRA SONIA MARCELA GARCIA PINEDA SE VALIDA DIRECCIÓN OK, CANAL OK, DISPONIBILIDAD TOTAL, LLAMAR EL DÍA LA INSTALACIÓN PARA CONFIRMAR VISITA, AVISO EXTERIOR ALTURA APROX 3 METROS; TOMACORRIENTE CERCANO: SI; TIENE CABINA DE SEGURIDAD: SI 3/6/2025 SE REALIZA INSTALACIÓN DE CORRESPONSAL, SE INSTALAN EQUIPOS CON PRUEBAS EXITOSAS, SE CAPACITA Y SE EVALÚA AL CLIENTE, SE INSTALA PUBLICIDAD COMPLETA, CB QUEDA OPERATIVO. USUARIO SOMOS BANCOLOMBIA ACTIVO | W40: GALINDO ROJAS LUIS FELIPE | X40: SXUZZ130 | Y40: 761448 | Z40: N/A | AA40: 1103440 | AB40: N/A | AC40: N/A | AD40: N/A | AE40: 40 ROLLOS | AF40: TIPO I | AG40: TERRESTRE | AH40: VISITA_TÉCNICA | AI40: 1 | AJ40: 1 | AK40: 1 | AL40: =IF(AF40="TIPO I",'BASE DE LIQUIDACION 2025'!$B$3,'BASE DE LIQUIDACION 2025'!$B$4) -> 11251.224 | AM40: =IF(AF40="TIPO I",'BASE DE LIQUIDACION 2025'!$C$3,'BASE DE LIQUIDACION 2025'!$C$4) -> 126317.12 | AN40: =IF(AF40="TIPO I",'BASE DE LIQUIDACION 2025'!$D$3,'BASE DE LIQUIDACION 2025'!$D$4) -> 57411.974 | AO40: =AL40*AI40+AJ40*AM40+AK40*AN40 -> 194980.32
A41: MEDELLIN | B41: =VLOOKUP(A41,'CENTRO DE COSTOS'!A:D,4,FALSE) -> JUAN SEBASTIÁN RÍOS CASTRILLÓN | C41: =VLOOKUP(A41,'CENTRO DE COSTOS'!A:D,2,FALSE) -> 0004-0005 | D41: 5079 | E41: TA-25-684795 | F41: FO-25-1050326 | G41: 45807 | H41: 45812 | I41: 45807 | J41: 45817 | K41: 45817 | L41: ANTIOQUIA | M41: BARBOSA | N41: BARRIO BARBOSA AUTOPISTA BARBOSA | O41: 79623 | P41: CB CRECIMIENTO - NUEVO | Q41: APERTURA | R41: REDEBAN | S41: UNO A UNO | T41: UNO A UNO | U41: EJECUTADO | V41: 30-05 SE REALIZA LLAMADA AL CLIENTE, SE HABLA CON LA SRA LIZETH MARIANA GALINDO ORTIZ, SE VALIDA DIRECCIÓN OK, CANAL OK, DISPONIBILIDAD TOTAL, LLAMAR EL DÍA LA INSTALACIÓN PARA CONFIRMAR VISITA, AVISO EXTERIOR ALTURA APROX DONDE EL TECNICO LO VEA CONVENIENTE METROS; TOMACORRIENTE CERCANO: SI; TIENE CABINA DE SEGURIDAD: NO 4/6/2025 LLEGAMOS A SITIO ENCONTRANDO OTRO PUNTO CERCANO A 30 METROS CODIGO 49691 PTM BARBOSA DROGUERÍA SE ESCALA CASO POR CERCANÍA DE 2 PUNTOS UNO DE AGREGADOR Y OTRO UNO A UNO. 05-06 ENTIDAD APRUEBA INSTALACIÓN 9/6/2025 SE REALIZA INSTALACIÓN DE CORRESPONSAL, SE INSTALAN EQUIPOS CON PRUEBAS EXITOSAS, SE CAPACITA Y SE EVALÚA AL CLIENTE, SE INSTALA PUBLICIDAD COMPLETA, CB QUEDA OPERATIVO. PLATAFORMA SOMOS BANCOLOMBIA CON CORREO ERRÓNEO, SE CAPACITA CON USUARIO DE PRUEBA | W41: BADEL ACUÑA LUIS ALBERTO | X41: SXUZZ149 | Y41: 1173964 | Z41: N/A | AA41: 529350 | AB41: N/A | AC41: BANCO | AD41: ESTUVO ESCALADO | AE41: 40 ROLLOS | AF41: TIPO II | AG41: TERRESTRE | AH41: VISITA_TÉCNICA | AI41: 1 | AJ41: 1 | AK41: 3 | AL41: =IF(AF41="TIPO I",'BASE DE LIQUIDACION 2025'!$B$3,'BASE DE LIQUIDACION 2025'!$B$4) -> 11251.224 | AM41: =IF(AF41="TIPO I",'BASE DE LIQUIDACION 2025'!$C$3,'BASE DE LIQUIDACION 2025'!$C$4) -> 126317.12 | AN41: =IF(AF41="TIPO I",'BASE DE LIQUIDACION 2025'!$D$3,'BASE DE LIQUIDACION 2025'!$D$4) -> 110808.28 | AO41: =AL41*AI41+AJ41*AM41+AK41*AN41 -> 469993.17
A42: CALI | B42: =VLOOKUP(A42,'CENTRO DE COSTOS'!A:D,4,FALSE) -> DIEGO FERNANDO HENAO CARDONA | C42: =VLOOKUP(A42,'CENTRO DE COSTOS'!A:D,2,FALSE) -> 0004-0003 | D42: 76036 | E42: TA-25-684802 | F42: FO-25-1016457 | G42: 45807 | H42: 45812 | I42: 45807 | J42: 45812 | K42: 45812 | L42: VALLE DEL CAUCA | M42: ANDALUCIA | N42: BARRIO CENTRO ANDALUCIA 7 | O42: 79594 | P42: CB CRECIMIENTO - NUEVO | Q42: APERTURA | R42: REDEBAN | S42: UNO A UNO | T42: UNO A UNO | U42: EJECUTADO | V42: 30-05 SE REALIZA LLAMADA AL CLIENTE, SE HABLA CON LA SRA MARIA ELCY ROMAN MILLAN, SE VALIDA DIRECCIÓN OK, CANAL OK, DISPONIBILIDAD TOTAL, LLAMAR EL DÍA LA INSTALACIÓN PARA CONFIRMAR VISITA, AVISO EXTERIOR ALTURA APROX DONDE EL TECNICO LO VEA CONVENIENTE METROS; TOMACORRIENTE CERCANO: SI; TIENE CABINA DE SEGURIDAD: SI 4/6/2025 SE REALIZA INSTALACIÓN DE CORRESPONSAL, SE INSTALAN EQUIPOS CON PRUEBAS EXITOSAS, SE CAPACITA Y SE EVALÚA AL CLIENTE, SE INSTALA PUBLICIDAD COMPLETA, CB QUEDA OPERATIVO. USUARIO SOMOS BANCOLOMBIA ACTIVO | W42: MONTERO MUESES GIAN CARLO | X42: SXUZZ120 | Y42: 1030999 | Z42: N/A | AA42: 749614 | AB42: N/A | AC42: N/A | AD42: N/A | AE42: 40 ROLLOS | AF42: TIPO II | AG42: TERRESTRE | AH42: VISITA_TÉCNICA | AI42: 1 | AJ42: 1 | AK42: 1 | AL42: =IF(AF42="TIPO I",'BASE DE LIQUIDACION 2025'!$B$3,'BASE DE LIQUIDACION 2025'!$B$4) -> 11251.224 | AM42: =IF(AF42="TIPO I",'BASE DE LIQUIDACION 2025'!$C$3,'BASE DE LIQUIDACION 2025'!$C$4) -> 126317.12 | AN42: =IF(AF42="TIPO I",'BASE DE LIQUIDACION 2025'!$D$3,'BASE DE LIQUIDACION 2025'!$D$4) -> 110808.28 | AO42: =AL42*AI42+AJ42*AM42+AK42*AN42 -> 248376.62
A43: PEREIRA | B43: =VLOOKUP(A43,'CENTRO DE COSTOS'!A:D,4,FALSE) -> DIEGO FERNANDO HENAO CARDONA | C43: =VLOOKUP(A43,'CENTRO DE COSTOS'!A:D,2,FALSE) -> 0004-0002 | D43: 66001 | E43: TA-25-684805 | F43: FO-25-1016460 | G43: 45807 | H43: 45812 | I43: 45807 | J43: 45811 | K43: 45811 | L43: RISARALDA | M43: PEREIRA | N43: BARRIO CUBA PEREIRA 12 | O43: 79648 | P43: CB CRECIMIENTO - NUEVO | Q43: APERTURA | R43: REDEBAN | S43: UNO A UNO | T43: UNO A UNO | U43: EJECUTADO | V43: 30-05 SE REALIZA LLAMADA AL CLIENTE, SE HABLA CON LA SRA LUZ ELENA QUINTERO RAMIREZ, SE VALIDA DIRECCIÓN OK, CANAL OK, DISPONIBILIDAD TOTAL, LLAMAR EL DÍA LA INSTALACIÓN PARA CONFIRMAR VISITA, AVISO EXTERIOR ALTURA APROX DONDE EL TECNICO LO VEA CONVENIENTE METROS; TOMACORRIENTE CERCANO: SI; TIENE CABINA DE SEGURIDAD: NO 3/6/2025 SE REALIZA INSTALACIÓN DE CORRESPONSAL, SE INSTALAN EQUIPOS CON PRUEBAS EXITOSAS, SE CAPACITA Y SE EVALÚA AL CLIENTE, SE INSTALA PUBLICIDAD COMPLETA, CB QUEDA OPERATIVO. USUARIO SOMOS BANCOLOMBIA ACTIVO | W43: ARROYAVE CANO MANUEL GUILLERMO | X43: SXUZZ174 | Y43: 975259 | Z43: N/A | AA43: 1217510 | AB43: N/A | AC43: N/A | AD43: N/A | AE43: 40 ROLLOS | AF43: TIPO I | AG43: TERRESTRE | AH43: VISITA_TÉCNICA | AI43: 1 | AJ43: 1 | AK43: 1 | AL43: =IF(AF43="TIPO I",'BASE DE LIQUIDACION 2025'!$B$3,'BASE DE LIQUIDACION 2025'!$B$4) -> 11251.224 | AM43: =IF(AF43="TIPO I",'BASE DE LIQUIDACION 2025'!$C$3,'BASE DE LIQUIDACION 2025'!$C$4) -> 126317.12 | AN43: =IF(AF43="TIPO I",'BASE DE LIQUIDACION 2025'!$D$3,'BASE DE LIQUIDACION 2025'!$D$4) -> 57411.974 | AO43: =AL43*AI43+AJ43*AM43+AK43*AN43 -> 194980.32
A44: BOGOTA | B44: =VLOOKUP(A44,'CENTRO DE COSTOS'!A:D,4,FALSE) -> WILLIAM ASDRUBAL ROZO ROZO | C44: =VLOOKUP(A44,'CENTRO DE COSTOS'!A:D,2,FALSE) -> 0004-0004 | D44: 25754 | E44: TA-25-684810 | F44: FO-25-1016470 | G44: 45807 | H44: 45812 | I44: 45807 | J44: 45812 | K44: 45812 | L44: CUNDINAMARCA | M44: SOACHA | N44: BARRIO SAN MATEO SOACHA SOACHA 2 | O44: 79653 | P44: CB CRECIMIENTO - NUEVO | Q44: APERTURA | R44: REDEBAN | S44: UNO A UNO | T44: UNO A UNO | U44: EJECUTADO | V44: 30-05 SE REALIZA LLAMADA AL CLIENTE, SE HABLA CON LA SRA MARIA ALEJANDRA CAMARGO TRIANA, SE VALIDA DIRECCIÓN OK, CANAL OK, DISPONIBILIDAD TOTAL, LLAMAR EL DÍA LA INSTALACIÓN PARA CONFIRMAR VISITA, AVISO EXTERIOR ALTURA APROX 2,10 METROS; TOMACORRIENTE CERCANO: SI; TIENE CABINA DE SEGURIDAD: NO 04-06 SE REALIZA INSTALACIÓN DE CORRESPONSAL, SE INSTALAN EQUIPOS CON PRUEBAS EXITOSAS, SE CAPACITA Y SE EVALÚA AL CLIENTE, SE INSTALA PUBLICIDAD COMPLETA, CB QUEDA OPERATIVO. USUARIO SOMOS BANCOLOMBIA ACTIVO | W44: SOTO LONDOÑO FREDY ALEXANDER | X44: SXUZZ179 | Y44: 1169818 | Z44: N/A | AA44: 1060154 | AB44: N/A | AC44: N/A | AD44: N/A | AE44: 40 ROLLOS | AF44: TIPO I | AG44: TERRESTRE | AH44: VISITA_TÉCNICA | AI44: 1 | AJ44: 1 | AK44: 1 | AL44: =IF(AF44="TIPO I",'BASE DE LIQUIDACION 2025'!$B$3,'BASE DE LIQUIDACION 2025'!$B$4) -> 11251.224 | AM44: =IF(AF44="TIPO I",'BASE DE LIQUIDACION 2025'!$C$3,'BASE DE LIQUIDACION 2025'!$C$4) -> 126317.12 | AN44: =IF(AF44="TIPO I",'BASE DE LIQUIDACION 2025'!$D$3,'BASE DE LIQUIDACION 2025'!$D$4) -> 57411.974 | AO44: =AL44*AI44+AJ44*AM44+AK44*AN44 -> 194980.32
A45: MEDELLIN | B45: =VLOOKUP(A45,'CENTRO DE COSTOS'!A:D,4,FALSE) -> JUAN SEBASTIÁN RÍOS CASTRILLÓN | C45: =VLOOKUP(A45,'CENTRO DE COSTOS'!A:D,2,FALSE) -> 0004-0005 | D45: 5360 | E45: TA-25-684811 | F45: FO-25-1016474 | G45: 45807 | H45: 45812 | I45: 45807 | J45: 45811 | K45: 45811 | L45: ANTIOQUIA | M45: ITAGUI | N45: BARRIO ITAGUI ITAGUI 33 | O45: 79628 | P45: CB CRECIMIENTO - NUEVO | Q45: APERTURA | R45: REDEBAN | S45: UNO A UNO | T45: UNO A UNO | U45: EJECUTADO | V45: 30-05 SE REALIZA LLAMADA AL CLIENTE, SE HABLA CON EL SR YOSMEN ENRIQUE BETANCUR LONDOÑO, SE VALIDA DIRECCIÓN OK, CANAL OK, DISPONIBILIDAD TOTAL, LLAMAR EL DÍA LA INSTALACIÓN PARA CONFIRMAR VISITA, AVISO EXTERIOR ALTURA APROX 2 METROS; TOMACORRIENTE CERCANO: SI; TIENE CABINA DE SEGURIDAD: SI 3/6/2025 SE REALIZA INSTALACIÓN DE CORRESPONSAL, SE INSTALAN EQUIPOS CON PRUEBAS EXITOSAS, SE CAPACITA Y SE EVALÚA AL CLIENTE, SE INSTALA PUBLICIDAD COMPLETA, CB QUEDA OPERATIVO. USUARIO SOMOS BANCOLOMBIA ACTIVO | W45: DIAZ ZABALA FRANCIS DUBAN | X45: SXUZZ154 | Y45: 857573 | Z45: N/A | AA45: 522270 | AB45: N/A | AC45: N/A | AD45: N/A | AE45: 40 ROLLOS | AF45: TIPO I | AG45: TERRESTRE | AH45: VISITA_TÉCNICA | AI45: 1 | AJ45: 1 | AK45: 1 | AL45: =IF(AF45="TIPO I",'BASE DE LIQUIDACION 2025'!$B$3,'BASE DE LIQUIDACION 2025'!$B$4) -> 11251.224 | AM45: =IF(AF45="TIPO I",'BASE DE LIQUIDACION 2025'!$C$3,'BASE DE LIQUIDACION 2025'!$C$4) -> 126317.12 | AN45: =IF(AF45="TIPO I",'BASE DE LIQUIDACION 2025'!$D$3,'BASE DE LIQUIDACION 2025'!$D$4) -> 57411.974 | AO45: =AL45*AI45+AJ45*AM45+AK45*AN45 -> 194980.32
A46: APARTADO | B46: =VLOOKUP(A46,'CENTRO DE COSTOS'!A:D,4,FALSE) -> JUAN SEBASTIÁN RÍOS CASTRILLÓN | C46: =VLOOKUP(A46,'CENTRO DE COSTOS'!A:D,2,FALSE) -> 0004-0005 | D46: 5172 | E46: TA-25-684812 | F46: FO-25-1016477 | G46: 45807 | H46: 45812 | I46: 45807 | J46: 45812 | K46: 45812 | L46: ANTIOQUIA | M46: CHIGORODO | N46: BARRIO BRISAS DEL RIO CHIGORODO 1 | O46: 79625 | P46: CB CRECIMIENTO - NUEVO | Q46: APERTURA | R46: REDEBAN | S46: UNO A UNO | T46: UNO A UNO | U46: EJECUTADO | V46: 30-05 SE REALIZA LLAMADA AL CLIENTE, SE HABLA CON EL SR UBEIMAR LUVAN MONSALVE MARIN, SE VALIDA DIRECCIÓN OK, CANAL OK, DISPONIBILIDAD TOTAL, LLAMAR EL DÍA LA INSTALACIÓN PARA CONFIRMAR VISITA, AVISO EXTERIOR ALTURA APROX DONDE EL TECNICO LO VEA CONVENIENTE METROS; TOMACORRIENTE CERCANO: SI; TIENE CABINA DE SEGURIDAD: SI 04-06 SE REALIZA INSTALACIÓN DE CORRESPONSAL, SE INSTALAN EQUIPOS CON PRUEBAS EXITOSAS, SE CAPACITA Y SE EVALÚA AL CLIENTE, SE INSTALA PUBLICIDAD COMPLETA, CB QUEDA OPERATIVO. USUARIO SOMOS BANCOLOMBIA ACTIVO | W46: MARTINEZ TOVAR OSCAR DAVID | X46: SXUZZ151 | Y46: 1232239 | Z46: N/A | AA46: 915724 | AB46: N/A | AC46: N/A | AD46: N/A | AE46: 40 ROLLOS | AF46: TIPO II | AG46: TERRESTRE | AH46: VISITA_TÉCNICA | AI46: 1 | AJ46: 1 | AK46: 1 | AL46: =IF(AF46="TIPO I",'BASE DE LIQUIDACION 2025'!$B$3,'BASE DE LIQUIDACION 2025'!$B$4) -> 11251.224 | AM46: =IF(AF46="TIPO I",'BASE DE LIQUIDACION 2025'!$C$3,'BASE DE LIQUIDACION 2025'!$C$4) -> 126317.12 | AN46: =IF(AF46="TIPO I",'BASE DE LIQUIDACION 2025'!$D$3,'BASE DE LIQUIDACION 2025'!$D$4) -> 110808.28 | AO46: =AL46*AI46+AJ46*AM46+AK46*AN46 -> 248376.62
A47: MEDELLIN | B47: =VLOOKUP(A47,'CENTRO DE COSTOS'!A:D,4,FALSE) -> JUAN SEBASTIÁN RÍOS CASTRILLÓN | C47: =VLOOKUP(A47,'CENTRO DE COSTOS'!A:D,2,FALSE) -> 0004-0005 | D47: 5001 | E47: TA-25-685350 | F47: FO-25-1016880 | G47: 45807 | H47: 45812 | I47: 45807 | J47: 45813 | K47: 45813 | L47: ANTIOQUIA | M47: MEDELLIN | N47: BARRIO CENTRO MEDELLIN 106 | O47: 79671 | P47: CB CRECIMIENTO - NUEVO | Q47: APERTURA | R47: REDEBAN | S47: UNO A UNO | T47: UNO A UNO | U47: EJECUTADO | V47: 30-05 SE REALIZA LLAMADA AL CLIENTE, SE HABLA CON LA SR LEON ADRIAN ARROYAVE MONSALVE SE VALIDA DIRECCIÓN OK, CANAL OK, DISPONIBILIDAD TOTAL, LLAMAR EL DÍA LA INSTALACIÓN PARA CONFIRMAR VISITA, AVISO EXTERIOR ALTURA APROX 2 METROS; TOMACORRIENTE CERCANO: SI; TIENE CABINA DE SEGURIDAD: NO - COMUNICACIÓN POR WPP 3/6/2025 SE COMUNICA CON EL SR LEÓN ADRIAN PARA LA INSTALACIÓN BARRIO CENTRO MEDELLIN 106 E INFORMA QUE HOY NO PUEDE ATENDER NO TIENE DISPONIBILIDAD Y LA PERSONA ENCARGADA TAMPOCO ESTA DISPONIBLE HOY QUE SE LA PROGRAMEN PARA OTRO DÍA 5/6/2025 SE REALIZA INSTALACIÓN DE CORRESPONSAL, SE INSTALAN EQUIPOS CON PRUEBAS EXITOSAS, SE CAPACITA Y SE EVALÚA AL CLIENTE, SE INSTALA PUBLICIDAD COMPLETA, CB QUEDA OPERATIVO. USUARIO SOMOS BANCOLOMBIA ACTIVO | W47: QUINTERO SANCHEZ JUAN SEBASTIAN | X47: SXUZZ197 | Y47: 1121097 | Z47: N/A | AA47: 522538 | AB47: N/A | AC47: USUARIO | AD47: SIN DISPONIBILIDAD | AE47: 40 ROLLOS | AF47: TIPO I | AG47: TERRESTRE | AH47: VISITA_TÉCNICA | AI47: 1 | AJ47: 1 | AK47: 1 | AL47: =IF(AF47="TIPO I",'BASE DE LIQUIDACION 2025'!$B$3,'BASE DE LIQUIDACION 2025'!$B$4) -> 11251.224 | AM47: =IF(AF47="TIPO I",'BASE DE LIQUIDACION 2025'!$C$3,'BASE DE LIQUIDACION 2025'!$C$4) -> 126317.12 | AN47: =IF(AF47="TIPO I",'BASE DE LIQUIDACION 2025'!$D$3,'BASE DE LIQUIDACION 2025'!$D$4) -> 57411.974 | AO47: =AL47*AI47+AJ47*AM47+AK47*AN47 -> 194980.32
A48: BOGOTA | B48: =VLOOKUP(A48,'CENTRO DE COSTOS'!A:D,4,FALSE) -> WILLIAM ASDRUBAL ROZO ROZO | C48: =VLOOKUP(A48,'CENTRO DE COSTOS'!A:D,2,FALSE) -> 0004-0004 | D48: 25754 | E48: TA-25-684814 | F48: FO-25-1016483 | G48: 45807 | H48: 45812 | I48: 45807 | J48: 45812 | K48: 45812 | L48: CUNDINAMARCA | M48: SOACHA | N48: BARRIO PRADO VEGAS SOACHA 2 | O48: 79654 | P48: CB CRECIMIENTO - NUEVO | Q48: APERTURA | R48: REDEBAN | S48: UNO A UNO | T48: UNO A UNO | U48: EJECUTADO | V48: 30-05 SE REALIZA LLAMADA AL CLIENTE, SE HABLA CON EL SR JOHAN SEBASTIAN BERNAL RODRIGUEZ, SE VALIDA DIRECCIÓN OK, CANAL OK, DISPONIBILIDAD TOTAL, LLAMAR EL DÍA LA INSTALACIÓN PARA CONFIRMAR VISITA, AVISO EXTERIOR ALTURA APROX DONDE EL TECNICO LO VEA CONVENIENTE METROS; TOMACORRIENTE CERCANO: SI; TIENE CABINA DE SEGURIDAD:NO 4/6/2025 SE REALIZA INSTALACIÓN DE CORRESPONSAL, SE INSTALAN EQUIPOS CON PRUEBAS EXITOSAS, SE CAPACITA Y SE EVALÚA AL CLIENTE, SE INSTALA PUBLICIDAD COMPLETA, CB QUEDA OPERATIVO. USUARIO SOMOS BANCOLOMBIA ACTIVO. NOTA: NO SE CUENTA CON TARJETA DE BANCOLOMBIA PARA REALIZAR PRUEBAS DE RETIRO | W48: SOTO LONDOÑO FREDY ALEXANDER | X48: SXUZZ180 | Y48: 732691 | Z48: N/A | AA48: 864627 | AB48: N/A | AC48: N/A | AD48: N/A | AE48: 40 ROLLOS | AF48: TIPO I | AG48: TERRESTRE | AH48: VISITA_TÉCNICA | AI48: 1 | AJ48: 1 | AK48: 1 | AL48: =IF(AF48="TIPO I",'BASE DE LIQUIDACION 2025'!$B$3,'BASE DE LIQUIDACION 2025'!$B$4) -> 11251.224 | AM48: =IF(AF48="TIPO I",'BASE DE LIQUIDACION 2025'!$C$3,'BASE DE LIQUIDACION 2025'!$C$4) -> 126317.12 | AN48: =IF(AF48="TIPO I",'BASE DE LIQUIDACION 2025'!$D$3,'BASE DE LIQUIDACION 2025'!$D$4) -> 57411.974 | AO48: =AL48*AI48+AJ48*AM48+AK48*AN48 -> 194980.32
A49: MEDELLIN | B49: =VLOOKUP(A49,'CENTRO DE COSTOS'!A:D,4,FALSE) -> JUAN SEBASTIÁN RÍOS CASTRILLÓN | C49: =VLOOKUP(A49,'CENTRO DE COSTOS'!A:D,2,FALSE) -> 0004-0005 | D49: 27361 | E49: TA-25-684817 | F49: FO-25-1016487 | G49: 45807 | H49: 45819 | I49: 45807 | J49: 45813 | K49: 45813 | L49: CHOCO | M49: ISTMINA | N49: BARRIO SANTA GENOVEVA ISTMINA CHOCO ISTMINA | O49: 79643 | P49: CB CRECIMIENTO - NUEVO | Q49: APERTURA | R49: REDEBAN | S49: UNO A UNO | T49: UNO A UNO | U49: EJECUTADO | V49: 30-05 SE REALIZA LLAMADA AL CLIENTE, SE HABLA CON EL SR PEDRO DAVID IBARGUEN CHALA SE VALIDA DIRECCIÓN OK, CANAL OK, DISPONIBILIDAD TOTAL, LLAMAR EL DÍA LA INSTALACIÓN PARA CONFIRMAR VISITA, AVISO EXTERIOR ALTURA APROX 2- 3 METROS; TOMACORRIENTE CERCANO: SI; TIENE CABINA DE SEGURIDAD:SI 5/6/2025 SE REALIZA INSTALACIÓN DE CORRESPONSAL, SE INSTALAN EQUIPOS CON PRUEBAS EXITOSAS, SE CAPACITA Y SE EVALÚA AL CLIENTE, SE INSTALA PUBLICIDAD COMPLETA, CB QUEDA OPERATIVO. USUARIO SOMOS BANCOLOMBIA ACTIVO | W49: ROBLEDO DIAZ ANDRES FELIPE | X49: SXUZZ169 | Y49: 763218 | Z49: 1115714 | AA49: 1239616 | AB49: N/A | AC49: N/A | AD49: N/A | AE49: 40 ROLLOS | AF49: TIPO IV ESPECIAL | AG49: AEREO | AH49: VISITA_TÉCNICA | AI49: 1 | AJ49: 1 | AK49: 1 | AL49: =IF(AF49="TIPO I",'BASE DE LIQUIDACION 2025'!$B$3,'BASE DE LIQUIDACION 2025'!$B$4) -> 11251.224 | AM49: =IF(AF49="TIPO I",'BASE DE LIQUIDACION 2025'!$C$3,'BASE DE LIQUIDACION 2025'!$C$4) -> 126317.12 | AN49: =IF(AF49="TIPO I",'BASE DE LIQUIDACION 2025'!$D$3,'BASE DE LIQUIDACION 2025'!$D$4) -> 110808.28 | AO49: =AL49*AI49+AJ49*AM49+AK49*AN49 -> 248376.62
A50: BOGOTA | B50: =VLOOKUP(A50,'CENTRO DE COSTOS'!A:D,4,FALSE) -> WILLIAM ASDRUBAL ROZO ROZO | C50: =VLOOKUP(A50,'CENTRO DE COSTOS'!A:D,2,FALSE) -> 0004-0004 | D50: 25772 | E50: TA-25-684821 | F50: FO-25-1016494 | G50: 45807 | H50: 45812 | I50: 45807 | J50: 45813 | K50: 45813 | L50: CUNDINAMARCA | M50: SUESCA | N50: BARRIO VEREDA CASICASGO SUESCA | O50: 79656 | P50: CAMBIO DE RAZON SOCIAL | Q50: APERTURA | R50: REDEBAN | S50: UNO A UNO | T50: UNO A UNO | U50: EJECUTADO | V50: 30-05 SE REALIZA LLAMADA AL CLIENTE, SE HABLA CON EL SR JOSE ARIEL GALLEGO RAMIREZ, SE VALIDA DIRECCIÓN OK, CANAL OK, DISPONIBILIDAD TOTAL, LLAMAR EL DÍA LA INSTALACIÓN PARA CONFIRMAR VISITA, AVISO EXTERIOR ALTURA APROX 2,20 METROS; TOMACORRIENTE CERCANO: SI; TIENE CABINA DE SEGURIDAD:SI 04-06 POR NOVEDAD PRESENTANDA CON EL AREA DE BODEGA SE REPROGRAMA ACTIVIDA PARA EL DIA SIGUIENTE, SE HABLA CON JOSE ARIEL GALLEGO RAMIREZ / TELEFONO DE CONTACTO: 3213003875 QUIEN MANIFIESTA RECIBE LA INSTALACIÓN EL DÍA DE MAÑANA 05-06-2025 5/6/2025 SE REALIZA INSTALACIÓN DE CORRESPONSAL, SE INSTALAN EQUIPOS CON PRUEBAS EXITOSAS, SE CAPACITA Y SE EVALÚA AL CLIENTE, SE INSTALA PUBLICIDAD COMPLETA, CB QUEDA OPERATIVO. USUARIO SOMOS BANCOLOMBIA ACTIVO | W50: ROMERO ROJAS BREIDY JHOHAN | X50: SXUZZ182 | Y50: 908497 | Z50: N/A | AA50: 892553 | AB50: N/A | AC50: LINEA | AD50: BODEGA NO REALIZA ENVIO OPORTUNAMENTE | AE50: 40 ROLLOS | AF50: TIPO II | AG50: TERRESTRE | AH50: VISITA_TÉCNICA | AI50: 1 | AJ50: 1 | AK50: 1 | AL50: =IF(AF50="TIPO I",'BASE DE LIQUIDACION 2025'!$B$3,'BASE DE LIQUIDACION 2025'!$B$4) -> 11251.224 | AM50: =IF(AF50="TIPO I",'BASE DE LIQUIDACION 2025'!$C$3,'BASE DE LIQUIDACION 2025'!$C$4) -> 126317.12 | AN50: =IF(AF50="TIPO I",'BASE DE LIQUIDACION 2025'!$D$3,'BASE DE LIQUIDACION 2025'!$D$4) -> 110808.28 | AO50: =AL50*AI50+AJ50*AM50+AK50*AN50 -> 248376.62
A51: CARTAGENA | B51: =VLOOKUP(A51,'CENTRO DE COSTOS'!A:D,4,FALSE) -> JOSE MAURICIO HERNANDEZ ROJAS | C51: =VLOOKUP(A51,'CENTRO DE COSTOS'!A:D,2,FALSE) -> 0004-0001 | D51: 13001 | E51: TA-25-684825 | F51: FO-25-1016502 | G51: 45807 | H51: 45812 | I51: 45807 | J51: 45812 | K51: 45812 | L51: BOLIVAR | M51: CARTAGENA | N51: BARRIO VIA AL MAR EDS PUERTA DE LAS AMERICAS CARTAGENA DE INDIAS | O51: 79622 | P51: CB CRECIMIENTO - NUEVO | Q51: APERTURA | R51: REDEBAN | S51: UNO A UNO | T51: UNO A UNO | U51: EJECUTADO | V51: 30-05 SE REALIZA LLAMADA AL CLIENTE, SE HABLA CON LA SR JUAN CARLOS MATUTE PACHECO SE VALIDA DIRECCIÓN OK, CANAL OK, DISPONIBILIDAD TOTAL, LLAMAR EL DÍA LA INSTALACIÓN PARA CONFIRMAR VISITA, AVISO EXTERIOR ALTURA APROX 2.50 METROS; TOMACORRIENTE CERCANO: SI; TIENE CABINA DE SEGURIDAD: SI 4/6/2025 SE REALIZA INSTALACIÓN DE CORRESPONSAL, SE INSTALAN EQUIPOS CON PRUEBAS EXITOSAS, SE CAPACITA Y SE EVALÚA AL CLIENTE, SE INSTALA PUBLICIDAD COMPLETA, CB QUEDA OPERATIVO. USUARIO SOMOS BANCOLOMBIA ACTIVO | W51: CANEDO HERRERA ALEXANDER | X51: SXUZZ148 | Y51: 931332 | Z51: N/A | AA51: 1097344 | AB51: N/A | AC51: N/A | AD51: N/A | AE51: 40 ROLLOS | AF51: TIPO I | AG51: TERRESTRE | AH51: VISITA_TÉCNICA | AI51: 1 | AJ51: 1 | AK51: 1 | AL51: =IF(AF51="TIPO I",'BASE DE LIQUIDACION 2025'!$B$3,'BASE DE LIQUIDACION 2025'!$B$4) -> 11251.224 | AM51: =IF(AF51="TIPO I",'BASE DE LIQUIDACION 2025'!$C$3,'BASE DE LIQUIDACION 2025'!$C$4) -> 126317.12 | AN51: =IF(AF51="TIPO I",'BASE DE LIQUIDACION 2025'!$D$3,'BASE DE LIQUIDACION 2025'!$D$4) -> 57411.974 | AO51: =AL51*AI51+AJ51*AM51+AK51*AN51 -> 194980.32
A52: VALLEDUPAR | B52: =VLOOKUP(A52,'CENTRO DE COSTOS'!A:D,4,FALSE) -> JOSE MAURICIO HERNANDEZ ROJAS | C52: =VLOOKUP(A52,'CENTRO DE COSTOS'!A:D,2,FALSE) -> 0004-0001 | D52: 20400 | E52: TA-25-684826 | F52: FO-25-1016505 | G52: 45807 | H52: 45812 | I52: 45807 | J52: 45812 | K52: 45812 | L52: CESAR | M52: LA JAGUA DE IBIRICO | N52: BARRIO JUAN RAMOS LA JAGUA DE IBIRICO | O52: 79639 | P52: CB CRECIMIENTO - NUEVO | Q52: APERTURA | R52: REDEBAN | S52: UNO A UNO | T52: UNO A UNO | U52: EJECUTADO | V52: 30-05 SE REALIZA LLAMADA AL CLIENTE, SE HABLA CON LA SRA rosania SE VALIDA DIRECCIÓN OK, CANAL OK, DISPONIBILIDAD TOTAL, LLAMAR EL DÍA LA INSTALACIÓN PARA CONFIRMAR VISITA, AVISO EXTERIOR ALTURA APROX 2 METROS; TOMACORRIENTE CERCANO: SI; TIENE CABINA DE SEGURIDAD: SI - COMUNICACIÓN POR WPP 4/6/2025 SE REALIZA INSTALACIÓN DE CORRESPONSAL, SE INSTALAN EQUIPOS CON PRUEBAS EXITOSAS, SE CAPACITA Y SE EVALÚA AL CLIENTE, SE INSTALA PUBLICIDAD COMPLETA, CB QUEDA OPERATIVO. USUARIO SOMOS BANCOLOMBIA ACTIVO | W52: MONTES DIAZ JOHN FRED | X52: SXUZZ165 | Y52: 1113419 | Z52: N/A | AA52: 1217245 | AB52: N/A | AC52: N/A | AD52: N/A | AE52: 40 ROLLOS | AF52: TIPO III | AG52: TERRESTRE | AH52: VISITA_TÉCNICA | AI52: 1 | AJ52: 1 | AK52: 1 | AL52: =IF(AF52="TIPO I",'BASE DE LIQUIDACION 2025'!$B$3,'BASE DE LIQUIDACION 2025'!$B$4) -> 11251.224 | AM52: =IF(AF52="TIPO I",'BASE DE LIQUIDACION 2025'!$C$3,'BASE DE LIQUIDACION 2025'!$C$4) -> 126317.12 | AN52: =IF(AF52="TIPO I",'BASE DE LIQUIDACION 2025'!$D$3,'BASE DE LIQUIDACION 2025'!$D$4) -> 110808.28 | AO52: =AL52*AI52+AJ52*AM52+AK52*AN52 -> 248376.62
A53: CUCUTA | B53: =VLOOKUP(A53,'CENTRO DE COSTOS'!A:D,4,FALSE) -> MIGUEL JULIÁN HERNÁNDEZ GUARÍN | C53: =VLOOKUP(A53,'CENTRO DE COSTOS'!A:D,2,FALSE) -> 0004-0008 | D53: 54874 | E53: TA-25-684827 | F53: FO-25-1016508 | G53: 45807 | H53: 45812 | I53: 45807 | J53: 45811 | K53: 45811 | L53: NORTE DE SANTANDER | M53: VILLA DEL ROSARIO | N53: BARRIO CENTRO VILLA DEL ROSARIO 5 | O53: 79662 | P53: CB CRECIMIENTO - NUEVO | Q53: APERTURA | R53: REDEBAN | S53: UNO A UNO | T53: UNO A UNO | U53: EJECUTADO | V53: 30-05 SE REALIZA LLAMADA AL CLIENTE, SE HABLA CON LA SR JUAN CARLOS CUTA RIBON SE VALIDA DIRECCIÓN OK, CANAL OK, DISPONIBILIDAD TOTAL, LLAMAR EL DÍA LA INSTALACIÓN PARA CONFIRMAR VISITA, AVISO EXTERIOR ALTURA APROX 2.50 METROS; TOMACORRIENTE CERCANO: SI; TIENE CABINA DE SEGURIDAD: EL SEÑOR INDICA QUE ESTA ES LA CAJA ESTA CERRADA MAS NO ESTA EL VIDRIO HASTA ARRIBA3/6/2025 SE REALIZA INSTALACIÓN DE CORRESPONSAL, SE INSTALAN EQUIPOS CON PRUEBAS EXITOSAS, SE CAPACITA Y SE EVALÚA AL CLIENTE, SE INSTALA PUBLICIDAD COMPLETA, CB QUEDA OPERATIVO. USUARIO SOMOS BANCOLOMBIA ACTIVO | W53: TORRES MANTILLA JOSE DANIEL | X53: SXUZZ188 | Y53: 1108261 | Z53: N/A | AA53: 830917 | AB53: N/A | AC53: N/A | AD53: N/A | AE53: 40 ROLLOS | AF53: TIPO I | AG53: TERRESTRE | AH53: VISITA_TÉCNICA | AI53: 1 | AJ53: 1 | AK53: 1 | AL53: =IF(AF53="TIPO I",'BASE DE LIQUIDACION 2025'!$B$3,'BASE DE LIQUIDACION 2025'!$B$4) -> 11251.224 | AM53: =IF(AF53="TIPO I",'BASE DE LIQUIDACION 2025'!$C$3,'BASE DE LIQUIDACION 2025'!$C$4) -> 126317.12 | AN53: =IF(AF53="TIPO I",'BASE DE LIQUIDACION 2025'!$D$3,'BASE DE LIQUIDACION 2025'!$D$4) -> 57411.974 | AO53: =AL53*AI53+AJ53*AM53+AK53*AN53 -> 194980.32
A54: BARRANQUILLA | B54: =VLOOKUP(A54,'CENTRO DE COSTOS'!A:D,4,FALSE) -> JOSE MAURICIO HERNANDEZ ROJAS | C54: =VLOOKUP(A54,'CENTRO DE COSTOS'!A:D,2,FALSE) -> 0004-0001 | D54: 8001 | E54: TA-25-684828 | F54: FO-25-1035630 | G54: 45807 | H54: 45812 | I54: 45807 | J54: 45812 | K54: 45812 | L54: ATLANTICO | M54: BARRANQUILLA | N54: BARRIO LA VICTORIA BARRANQUILLA 2 | O54: 79597 | P54: CB CRECIMIENTO - NUEVO | Q54: APERTURA | R54: REDEBAN | S54: UNO A UNO | T54: UNO A UNO | U54: EJECUTADO | V54: 30-05 SE REALIZA LLAMADA AL CLIENTE, SE HABLA CON LA SR LUIS GUILLERMO SERJE RAPELLO VALIDA DIRECCIÓN OK, DISPONIBILIDAD TOTAL, LLAMAR EL DÍA LA INSTALACIÓN PARA CONFIRMAR VISITA, AVISO EXTERIOR ALTURA APROX 2.00 METROS; TOMACORRIENTE CERCANO: SI; TIENE CABINA DE SEGURIDAD: USUARIO TIENE REJA 03-06 SE LOGRA COMUNICACION VÍA WASHAP AL NÚMERO 3008485338, Y ME CONTESTA LA SEÑORA MARIANELA CANTILLO, CON QUIÉN SE ACUERDA LLEGAR TIPO 11 AM PARA ATENDERME, SE LLAMA A SITIO, PERO NO CONTESTAN WASHAP, NO LE ENTRAN MENSAJES NI LLAMADAS , ES UN CONJUNTO CERRADO, PERO ME DICE EL VIGILANTE QUE ESTÁ A LA VUELTA ,SE DA LA VUELTA A LA MANZANA PERO NO SE LOGRA VER EL LOCAL, ME VOY A OTRO SITIO HACER OTRA ACTIVIDAD, Y AHORA EN LAS HORAS DE LA TARDE REGRESO, ESTÁ VEZ SI ME CONTESTAN LOS MENSAJES INDICANDOME QUE DÉBIDO AL PARO EN FUNDACIÓN, NO PUDO REGRESAR, QUE POR FAVOR REAGENDE LA VISITA PARA MAÑANA 4 DE JUNIO 4/6/2025 SE REALIZA INSTALACIÓN DE CORRESPONSAL, SE INSTALAN EQUIPOS CON PRUEBAS EXITOSAS, SE CAPACITA Y SE EVALÚA AL CLIENTE, SE INSTALA PUBLICIDAD COMPLETA, CB QUEDA OPERATIVO. USUARIO SOMOS BANCOLOMBIA ACTIVO | W54: DE AVILA SIADES ALBERTO ENRIQUE | X54: SXUZZ123 | Y54: 1045719 | Z54: N/A | AA54: 905781 | AB54: N/A | AC54: N/A | AD54: N/A | AE54: 40 ROLLOS | AF54: TIPO I | AG54: TERRESTRE | AH54: VISITA_TÉCNICA | AI54: 1 | AJ54: 1 | AK54: 3 | AL54: =IF(AF54="TIPO I",'BASE DE LIQUIDACION 2025'!$B$3,'BASE DE LIQUIDACION 2025'!$B$4) -> 11251.224 | AM54: =IF(AF54="TIPO I",'BASE DE LIQUIDACION 2025'!$C$3,'BASE DE LIQUIDACION 2025'!$C$4) -> 126317.12 | AN54: =IF(AF54="TIPO I",'BASE DE LIQUIDACION 2025'!$D$3,'BASE DE LIQUIDACION 2025'!$D$4) -> 57411.974 | AO54: =AL54*AI54+AJ54*AM54+AK54*AN54 -> 309804.27
A55: BOGOTA | B55: =VLOOKUP(A55,'CENTRO DE COSTOS'!A:D,4,FALSE) -> WILLIAM ASDRUBAL ROZO ROZO | C55: =VLOOKUP(A55,'CENTRO DE COSTOS'!A:D,2,FALSE) -> 0004-0004 | D55: 11001 | E55: TA-25-684829 | F55: FO-25-1016513 | G55: 45807 | H55: 45812 | I55: 45807 | J55: 45811 | K55: 45811 | L55: CUNDINAMARCA | M55: BOGOTA | N55: BARRIO CASTILLA BOGOTA 23 | O55: 79612 | P55: CAMBIO DE RAZON SOCIAL | Q55: APERTURA | R55: REDEBAN | S55: UNO A UNO | T55: UNO A UNO | U55: EJECUTADO | V55: 30-05 SE REALIZA LLAMADA AL CLIENTE, SE HABLA CON LA SRA YURY VANESSA GIL SOSA VALIDA DIRECCIÓN OK, DISPONIBILIDAD TOTAL, LLAMAR EL DÍA LA INSTALACIÓN PARA CONFIRMAR VISITA, AVISO EXTERIOR ALTURA APROX 3.00 METROS; TOMACORRIENTE CERCANO: SI; TIENE CABINA DE SEGURIDAD: SI 3/6/2025 SE REALIZA INSTALACIÓN DE CORRESPONSAL, SE INSTALAN EQUIPOS CON PRUEBAS EXITOSAS, SE CAPACITA Y SE EVALÚA AL CLIENTE, SE INSTALA PUBLICIDAD COMPLETA, CB QUEDA OPERATIVO. USUARIO SOMOS BANCOLOMBIA ACTIVO | W55: CORTES VELANDIA MIGUEL ANGEL | X55: SXUZZ138 | Y55: 792830 | Z55: N/A | AA55: 1110886 | AB55: N/A | AC55: N/A | AD55: N/A | AE55: 40 ROLLOS | AF55: TIPO I | AG55: TERRESTRE | AH55: VISITA_TÉCNICA | AI55: 1 | AJ55: 1 | AK55: 1 | AL55: =IF(AF55="TIPO I",'BASE DE LIQUIDACION 2025'!$B$3,'BASE DE LIQUIDACION 2025'!$B$4) -> 11251.224 | AM55: =IF(AF55="TIPO I",'BASE DE LIQUIDACION 2025'!$C$3,'BASE DE LIQUIDACION 2025'!$C$4) -> 126317.12 | AN55: =IF(AF55="TIPO I",'BASE DE LIQUIDACION 2025'!$D$3,'BASE DE LIQUIDACION 2025'!$D$4) -> 57411.974 | AO55: =AL55*AI55+AJ55*AM55+AK55*AN55 -> 194980.32
A56: CALI | B56: =VLOOKUP(A56,'CENTRO DE COSTOS'!A:D,4,FALSE) -> DIEGO FERNANDO HENAO CARDONA | C56: =VLOOKUP(A56,'CENTRO DE COSTOS'!A:D,2,FALSE) -> 0004-0003 | D56: 76130 | E56: TA-25-684833 | F56: FO-25-1016519 | G56: 45807 | H56: 45812 | I56: 45807 | J56: 45811 | K56: 45811 | L56: VALLE DEL CAUCA | M56: CANDELARIA | N56: BARRIO MANZANARES SECTOR 11 - CANDELARIA CANDELARIA | O56: 79620 | P56: CB CRECIMIENTO - NUEVO | Q56: APERTURA | R56: REDEBAN | S56: UNO A UNO | T56: UNO A UNO | U56: EJECUTADO | V56: 30-05 SE REALIZA LLAMADA AL CLIENTE, SE HABLA CON LA SRA YURI TATIANA OSORIO BARREIRO (JOHAN DAVIDA MANRIQUE ) VALIDA DIRECCIÓN OK, DISPONIBILIDAD TOTAL, LLAMAR EL DÍA LA INSTALACIÓN PARA CONFIRMAR VISITA, AVISO EXTERIOR ALTURA APROX 2.00 METROS; TOMACORRIENTE CERCANO: SI; TIENE CABINA DE SEGURIDAD: SI | W56: TORRES GARCIA JENDRY JOSE | X56: SXUZZ146 | Y56: 1051052 | Z56: N/A | AA56: 879299 | AB56: N/A | AC56: N/A | AD56: N/A | AE56: 40 ROLLOS | AF56: TIPO II | AG56: TERRESTRE | AH56: VISITA_TÉCNICA | AI56: 1 | AJ56: 1 | AK56: 1 | AL56: =IF(AF56="TIPO I",'BASE DE LIQUIDACION 2025'!$B$3,'BASE DE LIQUIDACION 2025'!$B$4) -> 11251.224 | AM56: =IF(AF56="TIPO I",'BASE DE LIQUIDACION 2025'!$C$3,'BASE DE LIQUIDACION 2025'!$C$4) -> 126317.12 | AN56: =IF(AF56="TIPO I",'BASE DE LIQUIDACION 2025'!$D$3,'BASE DE LIQUIDACION 2025'!$D$4) -> 110808.28 | AO56: =AL56*AI56+AJ56*AM56+AK56*AN56 -> 248376.62
A57: CALI | B57: =VLOOKUP(A57,'CENTRO DE COSTOS'!A:D,4,FALSE) -> DIEGO FERNANDO HENAO CARDONA | C57: =VLOOKUP(A57,'CENTRO DE COSTOS'!A:D,2,FALSE) -> 0004-0003 | D57: 19809 | E57: TA-25-684835 | F57: FO-25-1016522 | G57: 45807 | H57: 45819 | I57: 45807 | J57: 45827 | K57: 45827 | L57: CAUCA | M57: TIMBIQUI | N57: BARRIO PUERTO LUZ TIMBIQUI 1 | O57: 79657 | P57: CB CRECIMIENTO - NUEVO | Q57: APERTURA | R57: REDEBAN | S57: UNO A UNO | T57: UNO A UNO | U57: EJECUTADO | V57: 30-05 SE REALIZA LLAMADA AL CLIENTE, SE HABLA CON LA SR JAMINSON CAICEDO CAICEDO VALIDA DIRECCIÓN ( HERMINZA GOMEZ ESPOSA) OK, DISPONIBILIDAD TOTAL, LLAMAR EL DÍA LA INSTALACIÓN PARA CONFIRMAR VISITA, AVISO EXTERIOR ALTURA APROX 2.00 METROS; TOMACORRIENTE CERCANO: SI; TIENE CABINA DE SEGURIDAD: NO 11-06 DADO QUE PARA ESTA APERTURA SE DEBE DESPLAZAR POR VIA AEREA, SE TIENE DISPONIBILIDAD DEL VUELO PARA DIA MIERCOLES 18 DE JUNIO PARA DESPLAZAMIENTO DEL TÉCNICO A LA ZONA A REALIZAR ACTIVIDAD 19-06 SE REALIZA INSTALACIÓN DE CORRESPONSAL, SE INSTALAN EQUIPOS CON PRUEBAS EXITOSAS, SE CAPACITA Y SE EVALÚA AL CLIENTE, SE INSTALA PUBLICIDAD COMPLETA, CB QUEDA OPERATIVO. USUARIO SOMOS BANCOLOMBIA ACTIVO | W57: PAREDES CASTILLO DIEGO | X57: SXUZZ183 | Y57: 1106288 | Z57: N/A | AA57: 1114581 | AB57: N/A | AC57: FACTOR/EXTERNO | AD57: TRANSPORTE | AE57: 40 ROLLOS | AF57: TIPO IV ESPECIAL | AG57: AEREO | AH57: VISITA_TÉCNICA | AI57: 1 | AJ57: 1 | AK57: 1 | AL57: =IF(AF57="TIPO I",'BASE DE LIQUIDACION 2025'!$B$3,'BASE DE LIQUIDACION 2025'!$B$4) -> 11251.224 | AM57: =IF(AF57="TIPO I",'BASE DE LIQUIDACION 2025'!$C$3,'BASE DE LIQUIDACION 2025'!$C$4) -> 126317.12 | AN57: =IF(AF57="TIPO I",'BASE DE LIQUIDACION 2025'!$D$3,'BASE DE LIQUIDACION 2025'!$D$4) -> 110808.28 | AO57: =AL57*AI57+AJ57*AM57+AK57*AN57 -> 248376.62
A58: VALLEDUPAR | B58: =VLOOKUP(A58,'CENTRO DE COSTOS'!A:D,4,FALSE) -> JOSE MAURICIO HERNANDEZ ROJAS | C58: =VLOOKUP(A58,'CENTRO DE COSTOS'!A:D,2,FALSE) -> 0004-0001 | D58: 20001 | E58: TA-25-684837 | F58: FO-25-1016527 | G58: 45807 | H58: 45812 | I58: 45807 | J58: 45811 | K58: 45811 | L58: CESAR | M58: VALLEDUPAR | N58: BARRIO CIUDADELA 450 AÑOS VALLEDUPAR 1 | O58: 79659 | P58: CB CRECIMIENTO - NUEVO | Q58: APERTURA | R58: REDEBAN | S58: UNO A UNO | T58: UNO A UNO | U58: EJECUTADO | V58: 30-05 SE REALIZA LLAMADA AL CLIENTE, SE HABLA CON LA SRA EDITH YAMILE MALAVER ORTIZ SE VALIDA DIRECCIÓN OK, DISPONIBILIDAD TOTAL, LLAMAR EL DÍA LA INSTALACIÓN PARA CONFIRMAR VISITA, AVISO EXTERIOR ALTURA APROX 2.00 METROS; TOMACORRIENTE CERCANO: SI; TIENE CABINA DE SEGURIDAD: SI LA DISTANCIA SON 4 METROS DE DEL MODEN A AL DATAFONO 3/6/2025 SE REALIZA INSTALACIÓN DE CORRESPONSAL, SE INSTALAN EQUIPOS CON PRUEBAS EXITOSAS, SE CAPACITA Y SE EVALÚA AL CLIENTE, SE INSTALA PUBLICIDAD COMPLETA, CB QUEDA OPERATIVO. USUARIO SOMOS BANCOLOMBIA ACTIVO | W58: MAESTRE MENGUAL EDGAR ENRIQUE | X58: SXUZZ185 | Y58: 1045500 | Z58: N/A | AA58: 1139755 | AB58: N/A | AC58: N/A | AD58: N/A | AE58: 40 ROLLOS | AF58: TIPO I | AG58: TERRESTRE | AH58: VISITA_TÉCNICA | AI58: 1 | AJ58: 1 | AK58: 1 | AL58: =IF(AF58="TIPO I",'BASE DE LIQUIDACION 2025'!$B$3,'BASE DE LIQUIDACION 2025'!$B$4) -> 11251.224 | AM58: =IF(AF58="TIPO I",'BASE DE LIQUIDACION 2025'!$C$3,'BASE DE LIQUIDACION 2025'!$C$4) -> 126317.12 | AN58: =IF(AF58="TIPO I",'BASE DE LIQUIDACION 2025'!$D$3,'BASE DE LIQUIDACION 2025'!$D$4) -> 57411.974 | AO58: =AL58*AI58+AJ58*AM58+AK58*AN58 -> 194980.32
A59: BOGOTA | B59: =VLOOKUP(A59,'CENTRO DE COSTOS'!A:D,4,FALSE) -> WILLIAM ASDRUBAL ROZO ROZO | C59: =VLOOKUP(A59,'CENTRO DE COSTOS'!A:D,2,FALSE) -> 0004-0004 | D59: 11001 | E59: TA-25-684838 | F59: FO-25-1016531 | G59: 45807 | H59: 45812 | I59: 45807 | J59: 45811 | K59: 45811 | L59: CUNDINAMARCA | M59: BOGOTA | N59: BARRIO SAN ANTONIO BOGOTA 11 | O59: 79602 | P59: CB CRECIMIENTO - NUEVO | Q59: APERTURA | R59: REDEBAN | S59: UNO A UNO | T59: UNO A UNO | U59: EJECUTADO | V59: 30-05 SE REALIZA LLAMADA AL CLIENTE, SE HABLA CON LA SR CAMILO ALEXANDER VILLAMIL MONTAÑA ( NOS CONTESTAN EL HERMANO EDWIN ) SE VALIDA DIRECCIÓN OK, DISPONIBILIDAD TOTAL, LLAMAR EL DÍA LA INSTALACIÓN PARA CONFIRMAR VISITA, AVISO EXTERIOR ALTURA APROX 2.50 METROS; TOMACORRIENTE CERCANO: SI; TIENE CABINA DE SEGURIDAD: SI 3/6/2025 SE REALIZA INSTALACIÓN DE CORRESPONSAL, SE INSTALAN EQUIPOS CON PRUEBAS EXITOSAS, SE CAPACITA Y SE EVALÚA AL CLIENTE, SE INSTALA PUBLICIDAD COMPLETA, CB QUEDA OPERATIVO. USUARIO SOMOS BANCOLOMBIA ACTIVO | W59: GOMEZ VEGA DAVID SNEYDER | X59: SXUZZ128 | Y59: 1040953 | Z59: N/A | AA59: 893214 | AB59: N/A | AC59: N/A | AD59: N/A | AE59: 40 ROLLOS | AF59: TIPO I | AG59: TERRESTRE | AH59: VISITA_TÉCNICA | AI59: 1 | AJ59: 1 | AK59: 1 | AL59: =IF(AF59="TIPO I",'BASE DE LIQUIDACION 2025'!$B$3,'BASE DE LIQUIDACION 2025'!$B$4) -> 11251.224 | AM59: =IF(AF59="TIPO I",'BASE DE LIQUIDACION 2025'!$C$3,'BASE DE LIQUIDACION 2025'!$C$4) -> 126317.12 | AN59: =IF(AF59="TIPO I",'BASE DE LIQUIDACION 2025'!$D$3,'BASE DE LIQUIDACION 2025'!$D$4) -> 57411.974 | AO59: =AL59*AI59+AJ59*AM59+AK59*AN59 -> 194980.32
A60: MEDELLIN | B60: =VLOOKUP(A60,'CENTRO DE COSTOS'!A:D,4,FALSE) -> JUAN SEBASTIÁN RÍOS CASTRILLÓN | C60: =VLOOKUP(A60,'CENTRO DE COSTOS'!A:D,2,FALSE) -> 0004-0005 | D60: 5756 | E60: TA-25-684842 | F60: FO-25-1016534 | G60: 45807 | H60: 45812 | I60: 45807 | J60: 45813 | K60: 45813 | L60: ANTIOQUIA | M60: SONSON | N60: BARRIO SONSON SONSON 8 | O60: 79632 | P60: CB CRECIMIENTO - NUEVO | Q60: APERTURA | R60: REDEBAN | S60: UNO A UNO | T60: UNO A UNO | U60: EJECUTADO | V60: 30-05 SE REALIZA LLAMADA AL CLIENTE, SE HABLA CON LA SR DAVID SOTO JIMENEZ SE VALIDA DIRECCIÓN OK, DISPONIBILIDAD TOTAL, LLAMAR EL DÍA LA INSTALACIÓN PARA CONFIRMAR VISITA, AVISO EXTERIOR ALTURA APROX 2.50 METROS; TOMACORRIENTE CERCANO: SI; TIENE CABINA DE SEGURIDAD: NO , USUARIO INDICA QUE SE EL MODEN SE ENCUENTRA 20 METROS 04-6 SE PRESENTA NOVEDAD EN LA VIA LA UNIÓN-SONSÓN SE SALE DESDE MEDELLÍN EN RUTA UNIÓN SONSÓN PERO SE TIENE PROBLEMAS CON EL TRANSPORTE EN LA UNIÓN EL BUS SALE TARDE DESE MEDELLÍN Y SE PRESENTA NOVEDAD EN LA VIA POR FUERTES LLUVIAS. SE HABLA CON EL USUARIO Y NOS COMFIMA QUE EL CIERRA TEMPRANO HOY PERO QUE NOS PUEDE ATENDER MAÑANA A PRIMERA HORA 5/6/2025 SE REALIZA INSTALACIÓN DE CORRESPONSAL, SE INSTALAN EQUIPOS CON PRUEBAS EXITOSAS, SE CAPACITA Y SE EVALÚA AL CLIENTE, SE INSTALA PUBLICIDAD COMPLETA, CB QUEDA OPERATIVO. USUARIO SOMOS BANCOLOMBIA ACTIVO | W60: DIAZ ZABALA FRANCIS DUBAN | X60: SXUZZ158 | Y60: 1062093 | Z60: N/A | AA60: 1097531 | AB60: N/A | AC60: FACTOR/EXTERNO | AD60: TRANSPORTE | AE60: 40 ROLLOS | AF60: TIPO III | AG60: TERRESTRE | AH60: VISITA_TÉCNICA | AI60: 1 | AJ60: 1 | AK60: 1 | AL60: =IF(AF60="TIPO I",'BASE DE LIQUIDACION 2025'!$B$3,'BASE DE LIQUIDACION 2025'!$B$4) -> 11251.224 | AM60: =IF(AF60="TIPO I",'BASE DE LIQUIDACION 2025'!$C$3,'BASE DE LIQUIDACION 2025'!$C$4) -> 126317.12 | AN60: =IF(AF60="TIPO I",'BASE DE LIQUIDACION 2025'!$D$3,'BASE DE LIQUIDACION 2025'!$D$4) -> 110808.28 | AO60: =AL60*AI60+AJ60*AM60+AK60*AN60 -> 248376.62
A61: MEDELLIN | B61: =VLOOKUP(A61,'CENTRO DE COSTOS'!A:D,4,FALSE) -> JUAN SEBASTIÁN RÍOS CASTRILLÓN | C61: =VLOOKUP(A61,'CENTRO DE COSTOS'!A:D,2,FALSE) -> 0004-0005 | D61: 5001 | E61: TA-25-684849 | F61: FO-25-1016541 | G61: 45807 | H61: 45812 | I61: 45807 | J61: 45811 | K61: 45811 | L61: ANTIOQUIA | M61: MEDELLIN | N61: BARRIO BOSTON MEDELLIN 6 | O61: 79677 | P61: CB CRECIMIENTO - NUEVO | Q61: APERTURA | R61: REDEBAN | S61: UNO A UNO | T61: UNO A UNO | U61: EJECUTADO | V61: 30-05 SE REALIZA LLAMADA AL CLIENTE, SE HABLA CON LA SR ANDRES FELIPE ZAPATA LONDOÑO SE VALIDA DIRECCIÓN OK, DISPONIBILIDAD TOTAL, LLAMAR EL DÍA LA INSTALACIÓN PARA CONFIRMAR VISITA, AVISO EXTERIOR ALTURA APROX 2.50 METROS; TOMA CORRIENTE CERCANO: SI; TIENE CABINA DE SEGURIDAD: SI , USUARIO INDICA QUE SE EL MODEN SE ENCUENTRA 8 METROS 03-06 SE REALIZA INSTALACIÓN DE CORRESPONSAL, SE INSTALAN EQUIPOS CON PRUEBAS EXITOSAS, SE CAPACITA Y SE EVALÚA AL CLIENTE, SE INSTALA PUBLICIDAD COMPLETA, CB QUEDA OPERATIVO. USUARIO SOMOS BANCOLOMBIA ACTIVO | W61: PAREJA ECHAVARRIA JHON DAVID | X61: SXUZZ203 | Y61: 869106 | Z61: N/A | AA61: 1239749 | AB61: N/A | AC61: N/A | AD61: N/A | AE61: 40 ROLLOS | AF61: TIPO I | AG61: TERRESTRE | AH61: VISITA_TÉCNICA | AI61: 1 | AJ61: 1 | AK61: 1 | AL61: =IF(AF61="TIPO I",'BASE DE LIQUIDACION 2025'!$B$3,'BASE DE LIQUIDACION 2025'!$B$4) -> 11251.224 | AM61: =IF(AF61="TIPO I",'BASE DE LIQUIDACION 2025'!$C$3,'BASE DE LIQUIDACION 2025'!$C$4) -> 126317.12 | AN61: =IF(AF61="TIPO I",'BASE DE LIQUIDACION 2025'!$D$3,'BASE DE LIQUIDACION 2025'!$D$4) -> 57411.974 | AO61: =AL61*AI61+AJ61*AM61+AK61*AN61 -> 194980.32
... A70: MONTERIA | B70: =VLOOKUP(A70,'CENTRO DE COSTOS'!A:D,4,FALSE) -> JOSE MAURICIO HERNANDEZ ROJAS | C70: =VLOOKUP(A70,'CENTRO DE COSTOS'!A:D,2,FALSE) -> 0004-0001 | D70: 23675 | E70: TA-25-684953 | F70: FO-25-1016618 | G70: 45807 | H70: 45812 | I70: 45807 | J70: 45811 | K70: 45811 | L70: CORDOBA | M70: SAN BERNARDO DEL VIENTO | N70: BARRIO GUAYABAL SAN BERNARDO DEL VIENTO | O70: 79652 | P70: CB CRECIMIENTO - NUEVO | Q70: APERTURA | R70: REDEBAN | S70: UNO A UNO | T70: UNO A UNO | U70: EJECUTADO | V70: 30-05 SE REALIZA LLAMADA AL CLIENTE, SE HABLA CON LA SRA CANDELARIA ROSA RODRIGUEZ CASSERES SE VALIDA DIRECCIÓN OK, CANAL OK, DISPONIBILIDAD TOTAL, LLAMAR EL DÍA LA INSTALACIÓN PARA CONFIRMAR VISITA, AVISO EXTERIOR ALTURA APROX 2 METROS; TOMACORRIENTE CERCANO: SI; TIENE CABINA DE SEGURIDAD: SI 3/6/2025 SE REALIZA INSTALACIÓN DE CORRESPONSAL, SE INSTALAN EQUIPOS CON PRUEBAS EXITOSAS, SE CAPACITA Y SE EVALÚA AL CLIENTE, SE INSTALA PUBLICIDAD COMPLETA, CB QUEDA OPERATIVO. NO SE ACTIVA PÁGINA SOMOS BANCOLOMBIA YA QUE EL CORREO REGISTRADO POR EL CB ESTÁ ERRÓNEO Y NO DEJO RESTAURAR CONTRASEÑA. SE CAPACITÓ CON PÁGINA DE PRUEBA. | W70: COGOLLO VERTEL EDER LUIS | X70: SXUZZ178 | Y70: 1045037 | Z70: N/A | AA70: 863722 | AB70: N/A | AC70: N/A | AD70: N/A | AE70: 40 ROLLOS | AF70: TIPO II | AG70: TERRESTRE | AH70: VISITA_TÉCNICA | AI70: 1 | AJ70: 1 | AK70: 1 | AL70: =IF(AF70="TIPO I",'BASE DE LIQUIDACION 2025'!$B$3,'BASE DE LIQUIDACION 2025'!$B$4) -> 11251.224 | AM70: =IF(AF70="TIPO I",'BASE DE LIQUIDACION 2025'!$C$3,'BASE DE LIQUIDACION 2025'!$C$4) -> 126317.12 | AN70: =IF(AF70="TIPO I",'BASE DE LIQUIDACION 2025'!$D$3,'BASE DE LIQUIDACION 2025'!$D$4) -> 110808.28 | AO70: =AL70*AI70+AJ70*AM70+AK70*AN70 -> 248376.62
A71: BOGOTA | B71: =VLOOKUP(A71,'CENTRO DE COSTOS'!A:D,4,FALSE) -> WILLIAM ASDRUBAL ROZO ROZO | C71: =VLOOKUP(A71,'CENTRO DE COSTOS'!A:D,2,FALSE) -> 0004-0004 | D71: 25394 | E71: TA-25-684961 | F71: FO-25-1016625 | G71: 45807 | H71: 45812 | I71: 45807 | J71: 45813 | K71: 45813 | L71: CUNDINAMARCA | M71: LA PALMA | N71: BARRIO POZO ORTIZ LA PALMA LA PALMA | O71: 79644 | P71: CB CRECIMIENTO - NUEVO | Q71: APERTURA | R71: REDEBAN | S71: UNO A UNO | T71: UNO A UNO | U71: EJECUTADO | V71: 30-05 SE REALIZA LLAMADA AL CLIENTE, SE HABLA CON LA SRA KAROL TATIANA REAL LOZANO SE VALIDA DIRECCIÓN OK, CANAL OK, DISPONIBILIDAD TOTAL, LLAMAR EL DÍA LA INSTALACIÓN PARA CONFIRMAR VISITA, AVISO EXTERIOR ALTURA APROX 4 METROS; TOMACORRIENTE CERCANO: SI; TIENE CABINA DE SEGURIDAD: SI 4/6/2025 EN COMUNICACION CON EL COMERCIO KAROL TATIANA REAL LOZANO / TELEFONO DE CONTACTO: 3144477858, SE CONFIRMA VÍA CERRADA, COMERCIO ESTA PENDIENTE EL DÍA DE MAÑANA 05-06 PARA RECIVIR APERTURA SI DAN VÍA LIBRE 5/6/2025 SE REALIZA INSTALACIÓN DE CORRESPONSAL, SE INSTALAN EQUIPOS CON PRUEBAS EXITOSAS, SE CAPACITA Y SE EVALÚA AL CLIENTE, SE INSTALA PUBLICIDAD COMPLETA, CB QUEDA OPERATIVO. USUARIO SOMOS BANCOLOMBIA ACTIVO | W71: GALEANO SORIANO JUAN DAVID | X71: SXUZZ170 | Y71: 1172289 | Z71: 1216947 | AA71: 902150 | AB71: N/A | AC71: FACTOR/EXTERNO | AD71: TRANSPORTE | AE71: 40 ROLLOS | AF71: TIPO III | AG71: TERRESTRE | AH71: VISITA_TÉCNICA | AI71: 1 | AJ71: 1 | AK71: 1 | AL71: =IF(AF71="TIPO I",'BASE DE LIQUIDACION 2025'!$B$3,'BASE DE LIQUIDACION 2025'!$B$4) -> 11251.224 | AM71: =IF(AF71="TIPO I",'BASE DE LIQUIDACION 2025'!$C$3,'BASE DE LIQUIDACION 2025'!$C$4) -> 126317.12 | AN71: =IF(AF71="TIPO I",'BASE DE LIQUIDACION 2025'!$D$3,'BASE DE LIQUIDACION 2025'!$D$4) -> 110808.28 | AO71: =AL71*AI71+AJ71*AM71+AK71*AN71 -> 248376.62
A72: BOGOTA | B72: =VLOOKUP(A72,'CENTRO DE COSTOS'!A:D,4,FALSE) -> WILLIAM ASDRUBAL ROZO ROZO | C72: =VLOOKUP(A72,'CENTRO DE COSTOS'!A:D,2,FALSE) -> 0004-0004 | D72: 11001 | E72: TA-25-684975 | F72: FO-25-1016632 | G72: 45807 | H72: 45812 | I72: 45807 | J72: 45811 | K72: 45811 | L72: CUNDINAMARCA | M72: BOGOTA | N72: BARRIO LOMBARDIA BOGOTA 1 | O72: 79613 | P72: CB CRECIMIENTO - NUEVO | Q72: APERTURA | R72: REDEBAN | S72: UNO A UNO | T72: UNO A UNO | U72: EJECUTADO | V72: 30-05 SE REALIZA LLAMADA AL CLIENTE, SE HABLA CON LA SRA BEATRIZ CASTAÑEDA HIDALGO SE VALIDA DIRECCIÓN OK, CANAL OK, DISPONIBILIDAD TOTAL, LLAMAR EL DÍA LA INSTALACIÓN PARA CONFIRMAR VISITA, AVISO EXTERIOR ALTURA APROX 2 METROS; TOMACORRIENTE CERCANO: SI; TIENE CABINA DE SEGURIDAD: NO - COMUNICACIÓN POR WPP 03-06 SE REALIZA INSTALACIÓN DE CORRESPONSAL, SE INSTALAN EQUIPOS CON PRUEBAS EXITOSAS, SE CAPACITA Y SE EVALÚA AL CLIENTE, SE INSTALA PUBLICIDAD COMPLETA, CB QUEDA OPERATIVO. USUARIO SOMOS BANCOLOMBIA ACTIVO | W72: MURCIA HERNANDEZ HARVEY IGNACIO | X72: SXUZZ139 | Y72: 1069468 | Z72: N/A | AA72: 521136 | AB72: N/A | AC72: N/A | AD72: N/A | AE72: 40 ROLLOS | AF72: TIPO I | AG72: TERRESTRE | AH72: VISITA_TÉCNICA | AI72: 1 | AJ72: 1 | AK72: 1 | AL72: =IF(AF72="TIPO I",'BASE DE LIQUIDACION 2025'!$B$3,'BASE DE LIQUIDACION 2025'!$B$4) -> 11251.224 | AM72: =IF(AF72="TIPO I",'BASE DE LIQUIDACION 2025'!$C$3,'BASE DE LIQUIDACION 2025'!$C$4) -> 126317.12 | AN72: =IF(AF72="TIPO I",'BASE DE LIQUIDACION 2025'!$D$3,'BASE DE LIQUIDACION 2025'!$D$4) -> 57411.974 | AO72: =AL72*AI72+AJ72*AM72+AK72*AN72 -> 194980.32
A73: BOGOTA | B73: =VLOOKUP(A73,'CENTRO DE COSTOS'!A:D,4,FALSE) -> WILLIAM ASDRUBAL ROZO ROZO | C73: =VLOOKUP(A73,'CENTRO DE COSTOS'!A:D,2,FALSE) -> 0004-0004 | D73: 25168 | E73: TA-25-684987 | F73: FO-25-1016635 | G73: 45807 | H73: 45812 | I73: 45807 | J73: 45812 | K73: 45812 | L73: CUNDINAMARCA | M73: CHAGUANI | N73: BARRIO LA AMISTAD CHAGUANI | O73: 79638 | P73: CAMBIO DE REZON SOCIAL | Q73: APERTURA | R73: REDEBAN | S73: UNO A UNO | T73: UNO A UNO | U73: EJECUTADO | V73: 30-05 SE REALIZA LLAMADA AL CLIENTE, SE HABLA CON LA SR CAMILO ANDRES RUIZ HERNANDEZ SE VALIDA DIRECCIÓN OK, CANAL OK, DISPONIBILIDAD TOTAL, LLAMAR EL DÍA LA INSTALACIÓN PARA CONFIRMAR VISITA, AVISO EXTERIOR ALTURA APROX 2 METROS; TOMACORRIENTE CERCANO: SI; TIENE CABINA DE SEGURIDAD: NO - COMUNICACIÓN POR WPP 4/6/2025 SE REALIZA INSTALACIÓN DE CORRESPONSAL, SE INSTALAN EQUIPOS CON PRUEBAS EXITOSAS, SE CAPACITA Y SE EVALÚA AL CLIENTE, SE INSTALA PUBLICIDAD COMPLETA, CB QUEDA OPERATIVO. USUARIO SOMOS BANCOLOMBIA ACTIVO | W73: MURCIA HERNANDEZ HARVEY IGNACIO | X73: SXUZZ164 | Y73: 991301 | Z73: N/A | AA73: 1008506 | AB73: N/A | AC73: N/A | AD73: N/A | AE73: 40 ROLLOS | AF73: TIPO III | AG73: TERRESTRE | AH73: VISITA_TÉCNICA | AI73: 1 | AJ73: 1 | AK73: 1 | AL73: =IF(AF73="TIPO I",'BASE DE LIQUIDACION 2025'!$B$3,'BASE DE LIQUIDACION 2025'!$B$4) -> 11251.224 | AM73: =IF(AF73="TIPO I",'BASE DE LIQUIDACION 2025'!$C$3,'BASE DE LIQUIDACION 2025'!$C$4) -> 126317.12 | AN73: =IF(AF73="TIPO I",'BASE DE LIQUIDACION 2025'!$D$3,'BASE DE LIQUIDACION 2025'!$D$4) -> 110808.28 | AO73: =AL73*AI73+AJ73*AM73+AK73*AN73 -> 248376.62
A74: PASTO | B74: =VLOOKUP(A74,'CENTRO DE COSTOS'!A:D,4,FALSE) -> DIEGO FERNANDO HENAO CARDONA | C74: =VLOOKUP(A74,'CENTRO DE COSTOS'!A:D,2,FALSE) -> 0004-0003 | D74: 52001 | E74: TA-25-684997 | F74: FO-25-1016639 | G74: 45807 | H74: 45812 | I74: 45807 | J74: 45811 | K74: 45811 | L74: NARIÑO | M74: PASTO | N74: BARRIO PANDIACO PASTO 3 | O74: 79647 | P74: CB CRECIMIENTO - NUEVO | Q74: APERTURA | R74: REDEBAN | S74: UNO A UNO | T74: UNO A UNO | U74: EJECUTADO | V74: 30-05 SE REALIZA LLAMADA AL CLIENTE, SE HABLA CON LA SRA MAIRENA GALLARDO CABRERA SE VALIDA DIRECCIÓN OK, CANAL OK, DISPONIBILIDAD TOTAL, LLAMAR EL DÍA LA INSTALACIÓN PARA CONFIRMAR VISITA, AVISO EXTERIOR ALTURA APROX 3 METROS; TOMACORRIENTE CERCANO: SI; TIENE CABINA DE SEGURIDAD: SI 03-06 SE REALIZA INSTALACIÓN DE CORRESPONSAL, SE INSTALAN EQUIPOS CON PRUEBAS EXITOSAS, SE CAPACITA Y SE EVALÚA AL CLIENTE, SE INSTALA PUBLICIDAD COMPLETA, CB QUEDA OPERATIVO. USUARIO SOMOS BANCOLOMBIA ACTIVO | W74: REMICIO AMADO JOHN HEBER | X74: SXUZZ173 | Y74: 765055 | Z74: 989228 | AA74: 1233547 | AB74: N/A | AC74: N/A | AD74: N/A | AE74: 40 ROLLOS | AF74: TIPO I | AG74: TERRESTRE | AH74: VISITA_TÉCNICA | AI74: 1 | AJ74: 1 | AK74: 1 | AL74: =IF(AF74="TIPO I",'BASE DE LIQUIDACION 2025'!$B$3,'BASE DE LIQUIDACION 2025'!$B$4) -> 11251.224 | AM74: =IF(AF74="TIPO I",'BASE DE LIQUIDACION 2025'!$C$3,'BASE DE LIQUIDACION 2025'!$C$4) -> 126317.12 | AN74: =IF(AF74="TIPO I",'BASE DE LIQUIDACION 2025'!$D$3,'BASE DE LIQUIDACION 2025'!$D$4) -> 57411.974 | AO74: =AL74*AI74+AJ74*AM74+AK74*AN74 -> 194980.32
A75: CALI | B75: =VLOOKUP(A75,'CENTRO DE COSTOS'!A:D,4,FALSE) -> DIEGO FERNANDO HENAO CARDONA | C75: =VLOOKUP(A75,'CENTRO DE COSTOS'!A:D,2,FALSE) -> 0004-0003 | D75: 76109 | E75: TA-25-684999 | F75: FO-25-1016645 | G75: 45807 | H75: 45812 | I75: 45807 | J75: 45812 | K75: 45812 | L75: VALLE DEL CAUCA | M75: BUENAVENTURA | N75: BARRIO LOS TUBOS, PARTE BAJA BUENAVENTURA | O75: 79616 | P75: CB CRECIMIENTO - NUEVO | Q75: APERTURA | R75: REDEBAN | S75: UNO A UNO | T75: UNO A UNO | U75: EJECUTADO | V75: 30-05 SE REALIZA LLAMADA AL CLIENTE, SE HABLA CON LA SR DEYBER RAMIREZ SANCHEZ SE VALIDA DIRECCIÓN OK, CANAL OK, DISPONIBILIDAD TOTAL, LLAMAR EL DÍA LA INSTALACIÓN PARA CONFIRMAR VISITA, AVISO EXTERIOR ALTURA APROX 2 METROS; TOMACORRIENTE CERCANO: SI; TIENE CABINA DE SEGURIDAD: NO 04-06 SE REALIZA INSTALACIÓN DE CORRESPONSAL, SE INSTALAN EQUIPOS CON PRUEBAS EXITOSAS, SE CAPACITA Y SE EVALÚA AL CLIENTE, SE INSTALA PUBLICIDAD COMPLETA, CB QUEDA OPERATIVO. USUARIO SOMOS BANCOLOMBIA ACTIVO | W75: PAREDES CASTILLO DIEGO | X75: SXUZZ142 | Y75: 1116247 | Z75: N/A | AA75: 905531 | AB75: N/A | AC75: N/A | AD75: N/A | AE75: 40 ROLLOS | AF75: TIPO III | AG75: TERRESTRE | AH75: VISITA_TÉCNICA | AI75: 1 | AJ75: 1 | AK75: 1 | AL75: =IF(AF75="TIPO I",'BASE DE LIQUIDACION 2025'!$B$3,'BASE DE LIQUIDACION 2025'!$B$4) -> 11251.224 | AM75: =IF(AF75="TIPO I",'BASE DE LIQUIDACION 2025'!$C$3,'BASE DE LIQUIDACION 2025'!$C$4) -> 126317.12 | AN75: =IF(AF75="TIPO I",'BASE DE LIQUIDACION 2025'!$D$3,'BASE DE LIQUIDACION 2025'!$D$4) -> 110808.28 | AO75: =AL75*AI75+AJ75*AM75+AK75*AN75 -> 248376.62
A76: MEDELLIN | B76: =VLOOKUP(A76,'CENTRO DE COSTOS'!A:D,4,FALSE) -> JUAN SEBASTIÁN RÍOS CASTRILLÓN | C76: =VLOOKUP(A76,'CENTRO DE COSTOS'!A:D,2,FALSE) -> 0004-0005 | D76: 5440 | E76: TA-25-685005 | F76: FO-25-1016656 | G76: 45807 | H76: 45812 | I76: 45807 | J76: 45812 | K76: 45812 | L76: ANTIOQUIA | M76: MARINILLA | N76: BARRIO SECTOR LA GALERÍA MARINILLA | O76: 79667 | P76: CB CRECIMIENTO - NUEVO | Q76: APERTURA | R76: REDEBAN | S76: UNO A UNO | T76: UNO A UNO | U76: EJECUTADO | V76: 30-05 SE REALIZA LLAMADA AL CLIENTE, SE HABLA CON LA SRA LUZ MERY NARANJO GARCIA SE VALIDA DIRECCIÓN OK, CANAL OK, DISPONIBILIDAD TOTAL, LLAMAR EL DÍA LA INSTALACIÓN PARA CONFIRMAR VISITA, AVISO EXTERIOR ALTURA APROX 2 METROS; TOMACORRIENTE CERCANO: SI; TIENE CABINA DE SEGURIDAD: NO 04-06 SE REALIZA INSTALACIÓN DE CORRESPONSAL, SE INSTALAN EQUIPOS CON PRUEBAS EXITOSAS, SE CAPACITA Y SE EVALÚA AL CLIENTE, SE INSTALA PUBLICIDAD COMPLETA, CB QUEDA OPERATIVO. USUARIO SOMOS BANCOLOMBIA ACTIVO | W76: ZAPATA LOPEZ EDWARD ASDRUBAL | X76: SXUZZ193 | Y76: 793709 | Z76: N/A | AA76: 903064 | AB76: N/A | AC76: N/A | AD76: N/A | AE76: 40 ROLLOS | AF76: TIPO II | AG76: TERRESTRE | AH76: VISITA_TÉCNICA | AI76: 1 | AJ76: 1 | AK76: 1 | AL76: =IF(AF76="TIPO I",'BASE DE LIQUIDACION 2025'!$B$3,'BASE DE LIQUIDACION 2025'!$B$4) -> 11251.224 | AM76: =IF(AF76="TIPO I",'BASE DE LIQUIDACION 2025'!$C$3,'BASE DE LIQUIDACION 2025'!$C$4) -> 126317.12 | AN76: =IF(AF76="TIPO I",'BASE DE LIQUIDACION 2025'!$D$3,'BASE DE LIQUIDACION 2025'!$D$4) -> 110808.28 | AO76: =AL76*AI76+AJ76*AM76+AK76*AN76 -> 248376.62
A77: BOGOTA | B77: =VLOOKUP(A77,'CENTRO DE COSTOS'!A:D,4,FALSE) -> WILLIAM ASDRUBAL ROZO ROZO | C77: =VLOOKUP(A77,'CENTRO DE COSTOS'!A:D,2,FALSE) -> 0004-0004 | D77: 11001 | E77: TA-25-685006 | F77: FO-25-1016658 | G77: 45807 | H77: 45812 | I77: 45807 | J77: 45811 | K77: 45811 | L77: CUNDINAMARCA | M77: BOGOTA | N77: BARRIO ALTAMAR DINDALITO BOGOTA | O77: 79599 | P77: CB CRECIMIENTO - NUEVO | Q77: APERTURA | R77: REDEBAN | S77: UNO A UNO | T77: UNO A UNO | U77: EJECUTADO | V77: 30-05 SE REALIZA LLAMADA AL CLIENTE, SE HABLA CON LA SRA ANYI VIVIANA VERGARA DIAZ SE VALIDA DIRECCIÓN OK, CANAL OK, DISPONIBILIDAD TOTAL, LLAMAR EL DÍA LA INSTALACIÓN PARA CONFIRMAR VISITA, AVISO EXTERIOR ALTURA APROX 2.50 METROS; TOMACORRIENTE CERCANO: SI; TIENE CABINA DE SEGURIDAD: NO 3/6/2025 SE REALIZA INSTALACIÓN DE CORRESPONSAL, SE INSTALAN EQUIPOS CON PRUEBAS EXITOSAS, SE CAPACITA Y SE EVALÚA AL CLIENTE, SE INSTALA PUBLICIDAD COMPLETA, CB QUEDA OPERATIVO. USUARIO SOMOS BANCOLOMBIA ACTIVO | W77: ORTIZ MARTINEZ STIVEN | X77: SXUZZ125 | Y77: 888228 | Z77: N/A | AA77: 902284 | AB77: N/A | AC77: N/A | AD77: N/A | AE77: 40 ROLLOS | AF77: TIPO I | AG77: TERRESTRE | AH77: VISITA_TÉCNICA | AI77: 1 | AJ77: 1 | AK77: 1 | AL77: =IF(AF77="TIPO I",'BASE DE LIQUIDACION 2025'!$B$3,'BASE DE LIQUIDACION 2025'!$B$4) -> 11251.224 | AM77: =IF(AF77="TIPO I",'BASE DE LIQUIDACION 2025'!$C$3,'BASE DE LIQUIDACION 2025'!$C$4) -> 126317.12 | AN77: =IF(AF77="TIPO I",'BASE DE LIQUIDACION 2025'!$D$3,'BASE DE LIQUIDACION 2025'!$D$4) -> 57411.974 | AO77: =AL77*AI77+AJ77*AM77+AK77*AN77 -> 194980.32
A78: BOGOTA | B78: =VLOOKUP(A78,'CENTRO DE COSTOS'!A:D,4,FALSE) -> WILLIAM ASDRUBAL ROZO ROZO | C78: =VLOOKUP(A78,'CENTRO DE COSTOS'!A:D,2,FALSE) -> 0004-0004 | D78: 25035 | E78: TA-25-685007 | F78: FO-25-1016661 | G78: 45807 | H78: 45812 | I78: 45807 | J78: 45812 | K78: 45812 | L78: CUNDINAMARCA | M78: ANAPOIMA | N78: BARRIO CENTRO ANAPOIMA ANAPOIMA | O78: 79593 | P78: CB CRECIMIENTO - NUEVO | Q78: APERTURA | R78: REDEBAN | S78: UNO A UNO | T78: UNO A UNO | U78: EJECUTADO | V78: 30-05 SE REALIZA LLAMADA AL CLIENTE, SE HABLA CON LA SRA DIANA MILENA GIL SE VALIDA DIRECCIÓN OK, CANAL OK, DISPONIBILIDAD TOTAL, LLAMAR EL DÍA LA INSTALACIÓN PARA CONFIRMAR VISITA, AVISO EXTERIOR ALTURA: NO INDICA ALTURA, TOMACORRIENTE CERCANO: SI; TIENE CABINA DE SEGURIDAD: NO 04-06 SE REALIZA INSTALACIÓN DE CORRESPONSAL, SE INSTALAN EQUIPOS CON PRUEBAS EXITOSAS, SE CAPACITA Y SE EVALÚA AL CLIENTE, SE INSTALA PUBLICIDAD COMPLETA, CB QUEDA OPERATIVO. USUARIO SOMOS BANCOLOMBIA ACTIVO | W78: GALEANO SORIANO JUAN DAVID | X78: SXUZZ119 | Y78: 1069444 | Z78: N/A | AA78: 1008361 | AB78: N/A | AC78: N/A | AD78: N/A | AE78: 40 ROLLOS | AF78: TIPO II | AG78: TERRESTRE | AH78: VISITA_TÉCNICA | AI78: 1 | AJ78: 1 | AK78: 1 | AL78: =IF(AF78="TIPO I",'BASE DE LIQUIDACION 2025'!$B$3,'BASE DE LIQUIDACION 2025'!$B$4) -> 11251.224 | AM78: =IF(AF78="TIPO I",'BASE DE LIQUIDACION 2025'!$C$3,'BASE DE LIQUIDACION 2025'!$C$4) -> 126317.12 | AN78: =IF(AF78="TIPO I",'BASE DE LIQUIDACION 2025'!$D$3,'BASE DE LIQUIDACION 2025'!$D$4) -> 110808.28 | AO78: =AL78*AI78+AJ78*AM78+AK78*AN78 -> 248376.62
A79: MEDELLIN | B79: =VLOOKUP(A79,'CENTRO DE COSTOS'!A:D,4,FALSE) -> JUAN SEBASTIÁN RÍOS CASTRILLÓN | C79: =VLOOKUP(A79,'CENTRO DE COSTOS'!A:D,2,FALSE) -> 0004-0005 | D79: 5667 | E79: TA-25-685008 | F79: FO-25-1016664 | G79: 45807 | H79: 45812 | I79: 45807 | J79: 45812 | K79: 45812 | L79: ANTIOQUIA | M79: SAN RAFAEL | N79: SAN RAFAEL SAN RAFAEL 5 | O79: 79651 | P79: CB CRECIMIENTO - NUEVO | Q79: APERTURA | R79: REDEBAN | S79: UNO A UNO | T79: UNO A UNO | U79: EJECUTADO | V79: 30-05 SE REALIZA LLAMADA AL CLIENTE, SE HABLA CON LA SRA DEICY YANETH QUINCHIA CUERVO SE VALIDA DIRECCIÓN OK, CANAL OK, DISPONIBILIDAD TOTAL, LLAMAR EL DÍA LA INSTALACIÓN PARA CONFIRMAR VISITA, AVISO EXTERIOR ALTURA APROX 2.30 METROS; TOMACORRIENTE CERCANO: SI; TIENE CABINA DE SEGURIDAD: NO - COMUNICACIÓN POR WPP 04-06 SE REALIZA INSTALACIÓN DE CORRESPONSAL, SE INSTALAN EQUIPOS CON PRUEBAS EXITOSAS, SE CAPACITA Y SE EVALÚA AL CLIENTE, SE INSTALA PUBLICIDAD COMPLETA, CB QUEDA OPERATIVO. USUARIO SOMOS BANCOLOMBIA ACTIVO | W79: PAREJA ECHAVARRIA JHON DAVID | X79: SXUZZ177 | Y79: 1107042 | Z79: N/A | AA79: 974706 | AB79: N/A | AC79: N/A | AD79: N/A | AE79: 40 ROLLOS | AF79: TIPO III | AG79: TERRESTRE | AH79: VISITA_TÉCNICA | AI79: 1 | AJ79: 1 | AK79: 1 | AL79: =IF(AF79="TIPO I",'BASE DE LIQUIDACION 2025'!$B$3,'BASE DE LIQUIDACION 2025'!$B$4) -> 11251.224 | AM79: =IF(AF79="TIPO I",'BASE DE LIQUIDACION 2025'!$C$3,'BASE DE LIQUIDACION 2025'!$C$4) -> 126317.12 | AN79: =IF(AF79="TIPO I",'BASE DE LIQUIDACION 2025'!$D$3,'BASE DE LIQUIDACION 2025'!$D$4) -> 110808.28 | AO79: =AL79*AI79+AJ79*AM79+AK79*AN79 -> 248376.62
A80: MEDELLIN | B80: =VLOOKUP(A80,'CENTRO DE COSTOS'!A:D,4,FALSE) -> JUAN SEBASTIÁN RÍOS CASTRILLÓN | C80: =VLOOKUP(A80,'CENTRO DE COSTOS'!A:D,2,FALSE) -> 0004-0005 | D80: 5001 | E80: TA-25-685010 | F80: FO-25-1016668 | G80: 45807 | H80: 45812 | I80: 45807 | J80: 45811 | K80: 45811 | L80: ANTIOQUIA | M80: MEDELLIN | N80: BARRIO BELEN MEDELLIN 14 | O80: 79672 | P80: CB CRECIMIENTO - NUEVO | Q80: APERTURA | R80: REDEBAN | S80: UNO A UNO | T80: UNO A UNO | U80: EJECUTADO | V80: 30-05 SE REALIZA LLAMADA AL CLIENTE, SE HABLA CON LA SRA CAROLINA ALCARAZ VIDALES SE VALIDA DIRECCIÓN OK, CANAL OK, DISPONIBILIDAD TOTAL, LLAMAR EL DÍA LA INSTALACIÓN PARA CONFIRMAR VISITA, AVISO EXTERIOR ALTURA APROX 2.50 METROS; TOMACORRIENTE CERCANO: SI; TIENE CABINA DE SEGURIDAD: NO 3/6/2025 SE REALIZA INSTALACIÓN DE CORRESPONSAL, SE INSTALAN EQUIPOS CON PRUEBAS EXITOSAS, SE CAPACITA Y SE EVALÚA AL CLIENTE, SE INSTALA PUBLICIDAD COMPLETA, CB QUEDA OPERATIVO. USUARIO SOMOS BANCOLOMBIA ACTIVO | W80: QUINTERO SANCHEZ JUAN SEBASTIAN | X80: SXUZZ198 | Y80: 1105537 | Z80: 1138632 | AA80: 1239755 | AB80: N/A | AC80: N/A | AD80: N/A | AE80: 40 ROLLOS | AF80: TIPO I | AG80: TERRESTRE | AH80: VISITA_TÉCNICA | AI80: 1 | AJ80: 1 | AK80: 1 | AL80: =IF(AF80="TIPO I",'BASE DE LIQUIDACION 2025'!$B$3,'BASE DE LIQUIDACION 2025'!$B$4) -> 11251.224 | AM80: =IF(AF80="TIPO I",'BASE DE LIQUIDACION 2025'!$C$3,'BASE DE LIQUIDACION 2025'!$C$4) -> 126317.12 | AN80: =IF(AF80="TIPO I",'BASE DE LIQUIDACION 2025'!$D$3,'BASE DE LIQUIDACION 2025'!$D$4) -> 57411.974 | AO80: =AL80*AI80+AJ80*AM80+AK80*AN80 -> 194980.32
A81: VALLEDUPAR | B81: =VLOOKUP(A81,'CENTRO DE COSTOS'!A:D,4,FALSE) -> JOSE MAURICIO HERNANDEZ ROJAS | C81: =VLOOKUP(A81,'CENTRO DE COSTOS'!A:D,2,FALSE) -> 0004-0001 | D81: 20250 | E81: TA-25-685013 | F81: FO-25-1016671 | G81: 45807 | H81: 45812 | I81: 45807 | J81: 45811 | K81: 45811 | L81: CESAR | M81: EL PASO | N81: BARRIO CENTRO EL PASO 9 | O81: 79634 | P81: CB CRECIMIENTO - NUEVO | Q81: APERTURA | R81: REDEBAN | S81: UNO A UNO | T81: UNO A UNO | U81: EJECUTADO | V81: 30-05 SE REALIZA LLAMADA AL CLIENTE, SE HABLA CON LA SRA YULIBETH SEGOVIA SURMAY SE VALIDA DIRECCIÓN OK, CANAL OK, DISPONIBILIDAD TOTAL, LLAMAR EL DÍA LA INSTALACIÓN PARA CONFIRMAR VISITA, AVISO EXTERIOR ALTURA APROX 4 METROS; TOMACORRIENTE CERCANO: SI; TIENE CABINA DE SEGURIDAD: SI - COMUNICACIÓN POR WPP // EL MODEM ESTA A 5 MT 3/6/2025 SE REALIZA INSTALACIÓN DE CORRESPONSAL, SE INSTALAN EQUIPOS CON PRUEBAS EXITOSAS, SE CAPACITA Y SE EVALÚA AL CLIENTE, SE INSTALA PUBLICIDAD COMPLETA, CB QUEDA OPERATIVO. USUARIO SOMOS BANCOLOMBIA ACTIVO | W81: MONTES DIAZ JOHN FRED | X81: SXUZZ160 | Y81: 1045466 | Z81: N/A | AA81: 1139998 | AB81: N/A | AC81: N/A | AD81: N/A | AE81: 40 ROLLOS | AF81: TIPO III | AG81: TERRESTRE | AH81: VISITA_TÉCNICA | AI81: 1 | AJ81: 1 | AK81: 1 | AL81: =IF(AF81="TIPO I",'BASE DE LIQUIDACION 2025'!$B$3,'BASE DE LIQUIDACION 2025'!$B$4) -> 11251.224 | AM81: =IF(AF81="TIPO I",'BASE DE LIQUIDACION 2025'!$C$3,'BASE DE LIQUIDACION 2025'!$C$4) -> 126317.12 | AN81: =IF(AF81="TIPO I",'BASE DE LIQUIDACION 2025'!$D$3,'BASE DE LIQUIDACION 2025'!$D$4) -> 110808.28 | AO81: =AL81*AI81+AJ81*AM81+AK81*AN81 -> 248376.62
A82: SANTA MARTA | B82: =VLOOKUP(A82,'CENTRO DE COSTOS'!A:D,4,FALSE) -> JOSE MAURICIO HERNANDEZ ROJAS | C82: =VLOOKUP(A82,'CENTRO DE COSTOS'!A:D,2,FALSE) -> 0004-0001 | D82: 47245 | E82: TA-25-685014 | F82: FO-25-1016686 | G82: 45807 | H82: 45812 | I82: 45807 | J82: 45817 | K82: 45817 | L82: MAGDALENA | M82: EL BANCO | N82: BARRIO PUEBLO NUEVO EL BANCO 1 | O82: 79631 | P82: CB CRECIMIENTO - NUEVO | Q82: APERTURA | R82: REDEBAN | S82: UNO A UNO | T82: UNO A UNO | U82: EJECUTADO | V82: 30-05 SE REALIZA LLAMADA AL CLIENTE, SE HABLA CON LA SR JORGE LUIS RANGEL CAMPO SE VALIDA DIRECCIÓN OK, CANAL OK, DISPONIBILIDAD TOTAL, LLAMAR EL DÍA LA INSTALACIÓN PARA CONFIRMAR VISITA, AVISO EXTERIOR ALTURA APROX 2 METROS; TOMACORRIENTE CERCANO: SI; TIENE CABINA DE SEGURIDAD: NO - EL MODEM ESTA A 6 MT 04-06 LA VÍA HACIA EL MUNICIPIO DE COPEY AÚN SE ENCUENTRA CERRADA DESDE LA Y DE CIÉNAGA HASTA BOSCONIA POR POBLADORES DE LA SIERRA, EN EL SECTOR DE SAN PEDRO DE LA SIERRA, EL PARO YA LLEVA 3 DÍAS SEGUIDOS 5/6/2025 SE REALIZA VALIDACIÓN NUEVAMENTE Y LA NOVEDAD CONTINUA 9/6/2025 SE REALIZA INSTALACIÓN DE CORRESPONSAL, SE INSTALAN EQUIPOS CON PRUEBAS EXITOSAS, SE CAPACITA Y SE EVALÚA AL CLIENTE, SE INSTALA PUBLICIDAD COMPLETA, CB QUEDA OPERATIVO. USUARIO SOMOS BANCOLOMBIA ACTIVO | W82: MONTES DIAZ JOHN FRED | X82: SXUZZ157 | Y82: 852906 | Z82: N/A | AA82: 535670 | AB82: N/A | AC82: FACTOR/EXTERNO | AD82: PARO | AE82: 40 ROLLOS | AF82: TIPO IV | AG82: TERRESTRE | AH82: VISITA_TÉCNICA | AI82: 1 | AJ82: 1 | AK82: 1 | AL82: =IF(AF82="TIPO I",'BASE DE LIQUIDACION 2025'!$B$3,'BASE DE LIQUIDACION 2025'!$B$4) -> 11251.224 | AM82: =IF(AF82="TIPO I",'BASE DE LIQUIDACION 2025'!$C$3,'BASE DE LIQUIDACION 2025'!$C$4) -> 126317.12 | AN82: =IF(AF82="TIPO I",'BASE DE LIQUIDACION 2025'!$D$3,'BASE DE LIQUIDACION 2025'!$D$4) -> 110808.28 | AO82: =AL82*AI82+AJ82*AM82+AK82*AN82 -> 248376.62
A83: MEDELLIN | B83: =VLOOKUP(A83,'CENTRO DE COSTOS'!A:D,4,FALSE) -> JUAN SEBASTIÁN RÍOS CASTRILLÓN | C83: =VLOOKUP(A83,'CENTRO DE COSTOS'!A:D,2,FALSE) -> 0004-0005 | D83: 5001 | E83: TA-25-685023 | F83: FO-25-1016690 | G83: 45807 | H83: 45812 | I83: 45807 | J83: 45811 | K83: 45811 | L83: ANTIOQUIA | M83: MEDELLIN | N83: BARRIO GUAYABAL MEDELLIN 13 | O83: 79675 | P83: CB CRECIMIENTO - NUEVO | Q83: APERTURA | R83: REDEBAN | S83: UNO A UNO | T83: UNO A UNO | U83: EJECUTADO | V83: 30-05 SE REALIZA LLAMADA AL CLIENTE, SE HABLA CON LA SRA YURANY ANDREA CIFUENTES CASTAÑEDA SE VALIDA DIRECCIÓN OK, CANAL OK, DISPONIBILIDAD TOTAL, LLAMAR EL DÍA LA INSTALACIÓN PARA CONFIRMAR VISITA, AVISO EXTERIOR ALTURA APROX 2.50 METROS; TOMACORRIENTE CERCANO: SI; TIENE CABINA DE SEGURIDAD: NO - COMUNICACIÓN POR WPP 3/6/2025 SE REALIZA INSTALACIÓN DE CORRESPONSAL, SE INSTALAN EQUIPOS CON PRUEBAS EXITOSAS, SE CAPACITA Y SE EVALÚA AL CLIENTE, SE INSTALA PUBLICIDAD COMPLETA, CB QUEDA OPERATIVO. USUARIO SOMOS BANCOLOMBIA ACTIVO | W83: DIAZ ZABALA FRANCIS DUBAN | X83: SXUZZ201 | Y83: 1030009 | Z83: N/A | AA83: 1217436 | AB83: N/A | AC83: N/A | AD83: N/A | AE83: 40 ROLLOS | AF83: TIPO I | AG83: TERRESTRE | AH83: VISITA_TÉCNICA | AI83: 1 | AJ83: 1 | AK83: 1 | AL83: =IF(AF83="TIPO I",'BASE DE LIQUIDACION 2025'!$B$3,'BASE DE LIQUIDACION 2025'!$B$4) -> 11251.224 | AM83: =IF(AF83="TIPO I",'BASE DE LIQUIDACION 2025'!$C$3,'BASE DE LIQUIDACION 2025'!$C$4) -> 126317.12 | AN83: =IF(AF83="TIPO I",'BASE DE LIQUIDACION 2025'!$D$3,'BASE DE LIQUIDACION 2025'!$D$4) -> 57411.974 | AO83: =AL83*AI83+AJ83*AM83+AK83*AN83 -> 194980.32
A84: BOGOTA | B84: =VLOOKUP(A84,'CENTRO DE COSTOS'!A:D,4,FALSE) -> WILLIAM ASDRUBAL ROZO ROZO | C84: =VLOOKUP(A84,'CENTRO DE COSTOS'!A:D,2,FALSE) -> 0004-0004 | D84: 11001 | E84: TA-25-685025 | F84: FO-25-1016695 | G84: 45807 | H84: 45812 | I84: 45807 | J84: 45811 | K84: 45811 | L84: CUNDINAMARCA | M84: BOGOTA | N84: BARRIO GRAN BRITALIA BOGOTA 2 | O84: 79606 | P84: CB CRECIMIENTO - NUEVO | Q84: APERTURA | R84: REDEBAN | S84: UNO A UNO | T84: UNO A UNO | U84: EJECUTADO | V84: 30-05 SE REALIZA LLAMADA AL CLIENTE, SE HABLA CON LA SRA GREIS JULIETH ROJAS HERNANDEZ SE VALIDA DIRECCIÓN OK, CANAL OK, DISPONIBILIDAD TOTAL, LLAMAR EL DÍA LA INSTALACIÓN PARA CONFIRMAR VISITA, AVISO EXTERIOR ALTURA APROX 3 METROS; TOMACORRIENTE CERCANO: SI; TIENE CABINA DE SEGURIDAD: NO 3/6/2025 SE REALIZA INSTALACIÓN DE CORRESPONSAL, SE INSTALAN EQUIPOS CON PRUEBAS EXITOSAS, SE CAPACITA Y SE EVALÚA AL CLIENTE, SE INSTALA PUBLICIDAD COMPLETA, CB QUEDA OPERATIVO. USUARIO SOMOS BANCOLOMBIA ACTIVO | W84: ORTIZ MARTINEZ STIVEN | X84: SXUZZ132 | Y84: 1227607 | Z84: N/A | AA84: 984392 | AB84: N/A | AC84: N/A | AD84: N/A | AE84: 40 ROLLOS | AF84: TIPO I | AG84: TERRESTRE | AH84: VISITA_TÉCNICA | AI84: 1 | AJ84: 1 | AK84: 1 | AL84: =IF(AF84="TIPO I",'BASE DE LIQUIDACION 2025'!$B$3,'BASE DE LIQUIDACION 2025'!$B$4) -> 11251.224 | AM84: =IF(AF84="TIPO I",'BASE DE LIQUIDACION 2025'!$C$3,'BASE DE LIQUIDACION 2025'!$C$4) -> 126317.12 | AN84: =IF(AF84="TIPO I",'BASE DE LIQUIDACION 2025'!$D$3,'BASE DE LIQUIDACION 2025'!$D$4) -> 57411.974 | AO84: =AL84*AI84+AJ84*AM84+AK84*AN84 -> 194980.32
A85: BOGOTA | B85: =VLOOKUP(A85,'CENTRO DE COSTOS'!A:D,4,FALSE) -> WILLIAM ASDRUBAL ROZO ROZO | C85: =VLOOKUP(A85,'CENTRO DE COSTOS'!A:D,2,FALSE) -> 0004-0004 | D85: 11001 | E85: TA-25-685028 | F85: FO-25-1016701 | G85: 45807 | H85: 45812 | I85: 45807 | J85: 45811 | K85: 45811 | L85: CUNDINAMARCA | M85: BOGOTA | N85: BARRIO LA ESTRELLA BOGOTA 2 | O85: 79605 | P85: CB CRECIMIENTO - NUEVO | Q85: APERTURA | R85: REDEBAN | S85: UNO A UNO | T85: UNO A UNO | U85: EJECUTADO | V85: 30-05 SE REALIZA LLAMADA AL CLIENTE, SE HABLA CON LA SR SNEIDER SAAVEDRA SAAVEDRA SE VALIDA DIRECCIÓN OK, CANAL OK, DISPONIBILIDAD TOTAL, LLAMAR EL DÍA LA INSTALACIÓN PARA CONFIRMAR VISITA, AVISO EXTERIOR ALTURA APROX 2 METROS; TOMACORRIENTE CERCANO: SI; TIENE CABINA DE SEGURIDAD: SI - EL MODEM ESTA A 4 MT 03-06 SE REALIZA INSTALACIÓN DE CORRESPONSAL, SE INSTALAN EQUIPOS CON PRUEBAS EXITOSAS, SE CAPACITA Y SE EVALÚA AL CLIENTE, SE INSTALA PUBLICIDAD COMPLETA, CB QUEDA OPERATIVO. USUARIO SOMOS BANCOLOMBIA ACTIVO NOTA: SE SOLICITA AUTORIZACIÓN DE INSTALACIÓN DE COMBO 2600 CON MAGICBOX 241597317561324755896013 Y PINPAD, PERO AL INSTALAR EL PINPAD Y SOLICITAR EL CAMBIO DE EQUIPO , EL PINPAD NO FUNCIONA 5/6/2025 SE REALIZA INSTALACIÓN DE PINPAD PENDIENTE | W85: ROMERO ROJAS BREIDY JHOHAN | X85: SXUZZ131 | Y85: 1235225 | Z85: 771812 | AA85: 1076276-241597317561324755896013 | AB85: N/A | AC85: N/A | AD85: N/A | AE85: 40 ROLLOS | AF85: TIPO I | AG85: TERRESTRE | AH85: VISITA_TÉCNICA | AI85: 1 | AJ85: 1 | AK85: 1 | AL85: =IF(AF85="TIPO I",'BASE DE LIQUIDACION 2025'!$B$3,'BASE DE LIQUIDACION 2025'!$B$4) -> 11251.224 | AM85: =IF(AF85="TIPO I",'BASE DE LIQUIDACION 2025'!$C$3,'BASE DE LIQUIDACION 2025'!$C$4) -> 126317.12 | AN85: =IF(AF85="TIPO I",'BASE DE LIQUIDACION 2025'!$D$3,'BASE DE LIQUIDACION 2025'!$D$4) -> 57411.974 | AO85: =AL85*AI85+AJ85*AM85+AK85*AN85 -> 194980.32
A86: BOGOTA | B86: =VLOOKUP(A86,'CENTRO DE COSTOS'!A:D,4,FALSE) -> WILLIAM ASDRUBAL ROZO ROZO | C86: =VLOOKUP(A86,'CENTRO DE COSTOS'!A:D,2,FALSE) -> 0004-0004 | D86: 11001 | E86: TA-25-685040 | F86: FO-25-1016711 | G86: 45807 | H86: 45812 | I86: 45807 | J86: 45811 | K86: 45811 | L86: CUNDINAMARCA | M86: BOGOTA | N86: BARRIO SAN FRANCISCO BOGOTA 13 | O86: 79611 | P86: CB CRECIMIENTO - NUEVO | Q86: APERTURA | R86: REDEBAN | S86: UNO A UNO | T86: UNO A UNO | U86: EJECUTADO | V86: 30-05 SE REALIZA LLAMADA AL CLIENTE, SE HABLA CON LA SRA LEIDY ALEXANDRA GARCIA ACUÑA SE VALIDA DIRECCIÓN OK, CANAL OK, DISPONIBILIDAD TOTAL, LLAMAR EL DÍA LA INSTALACIÓN PARA CONFIRMAR VISITA, AVISO EXTERIOR ALTURA: NO INDICA ALTURA; TOMACORRIENTE CERCANO: SI; TIENE CABINA DE SEGURIDAD: NO 03-06 SE REALIZA INSTALACIÓN DE CORRESPONSAL, SE INSTALAN EQUIPOS CON PRUEBAS EXITOSAS, SE CAPACITA Y SE EVALÚA AL CLIENTE, SE INSTALA PUBLICIDAD COMPLETA, CB QUEDA OPERATIVO. USUARIO SOMOS BANCOLOMBIA ACTIVO | W86: GALEANO SORIANO JUAN DAVID | X86: SXUZZ137 | Y86: 1069587 | Z86: N/A | AA86: 1076627 | AB86: N/A | AC86: N/A | AD86: N/A | AE86: 40 ROLLOS | AF86: TIPO I | AG86: TERRESTRE | AH86: VISITA_TÉCNICA | AI86: 1 | AJ86: 1 | AK86: 1 | AL86: =IF(AF86="TIPO I",'BASE DE LIQUIDACION 2025'!$B$3,'BASE DE LIQUIDACION 2025'!$B$4) -> 11251.224 | AM86: =IF(AF86="TIPO I",'BASE DE LIQUIDACION 2025'!$C$3,'BASE DE LIQUIDACION 2025'!$C$4) -> 126317.12 | AN86: =IF(AF86="TIPO I",'BASE DE LIQUIDACION 2025'!$D$3,'BASE DE LIQUIDACION 2025'!$D$4) -> 57411.974 | AO86: =AL86*AI86+AJ86*AM86+AK86*AN86 -> 194980.32
A87: MEDELLIN | B87: =VLOOKUP(A87,'CENTRO DE COSTOS'!A:D,4,FALSE) -> JUAN SEBASTIÁN RÍOS CASTRILLÓN | C87: =VLOOKUP(A87,'CENTRO DE COSTOS'!A:D,2,FALSE) -> 0004-0005 | D87: 5313 | E87: TA-25-685049 | F87: FO-25-1016716 | G87: 45807 | H87: 45812 | I87: 45807 | J87: 45812 | K87: 45812 | L87: ANTIOQUIA | M87: GRANADA | N87: BARRIO GRANADA GRANADA 1 | O87: 79642 | P87: CAMBIO DE REZON SOCIAL | Q87: APERTURA | R87: REDEBAN | S87: UNO A UNO | T87: UNO A UNO | U87: EJECUTADO | V87: 30-05 SE REALIZA LLAMADA AL CLIENTE, SE HABLA CON LA SRA YURANI QUINTERO SE VALIDA DIRECCIÓN OK, CANAL OK, DISPONIBILIDAD TOTAL, LLAMAR EL DÍA LA INSTALACIÓN PARA CONFIRMAR VISITA, USUARIO INDICA QUE TIENE TODA LA PUBLICIDAD; TOMACORRIENTE CERCANO: SI; TIENE CABINA DE SEGURIDAD: NO - CAMBIO DE RAZON SOCIAL 77402 4/6/2025 SE REALIZA INSTALACIÓN DE CORRESPONSAL, SE INSTALAN EQUIPOS CON PRUEBAS EXITOSAS, SE CAPACITA Y SE EVALÚA AL CLIENTE, SE INSTALA PUBLICIDAD COMPLETA, CB QUEDA OPERATIVO. USUARIO SOMOS BANCOLOMBIA ACTIVO | W87: ZAPATA LOPEZ EDWARD ASDRUBAL | X87: SXUZZ168 | Y87: 1171355 | Z87: N/A | AA87: 1239618 | AB87: N/A | AC87: N/A | AD87: N/A | AE87: 40 ROLLOS | AF87: TIPO II | AG87: TERRESTRE | AH87: VISITA_TÉCNICA | AI87: 1 | AJ87: 1 | AK87: 1 | AL87: =IF(AF87="TIPO I",'BASE DE LIQUIDACION 2025'!$B$3,'BASE DE LIQUIDACION 2025'!$B$4) -> 11251.224 | AM87: =IF(AF87="TIPO I",'BASE DE LIQUIDACION 2025'!$C$3,'BASE DE LIQUIDACION 2025'!$C$4) -> 126317.12 | AN87: =IF(AF87="TIPO I",'BASE DE LIQUIDACION 2025'!$D$3,'BASE DE LIQUIDACION 2025'!$D$4) -> 110808.28 | AO87: =AL87*AI87+AJ87*AM87+AK87*AN87 -> 248376.62
A88: NEIVA | B88: =VLOOKUP(A88,'CENTRO DE COSTOS'!A:D,4,FALSE) -> KEVIN ALEXIS CORZO BUSTOS | C88: =VLOOKUP(A88,'CENTRO DE COSTOS'!A:D,2,FALSE) -> 0004-0007 | D88: 41551 | E88: TA-25-695240 | F88: FO-25-1029526 | G88: 45811 | H88: 45813 | I88: 45811 | J88: 45813 | K88: 45813 | L88: HUILA | M88: PITALITO | N88: BARRIO CACHINGOS PITALITO | O88: 79682 | P88: CB CRECIMIENTO - NUEVO | Q88: APERTURA | R88: REDEBAN | S88: UNO A UNO | T88: UNO A UNO | U88: EJECUTADO | V88: 31-05 SE REALIZA LLAMADA AL CLIENTE, SE HABLA CON EL SR JUAN DIEGO AVILEZ OSORIO, SE VALIDA DIRECCIÓN OK, CANAL OK, DISPONIBILIDAD TOTAL, LLAMAR EL DÍA LA INSTALACIÓN PARA CONFIRMAR VISITA, AVISO EXTERIOR ALTURA APROX DONDE EL TECNICO LO VEA CONVENIENTE, METROS; TOMACORRIENTE CERCANO: SI; TIENE CABINA DE SEGURIDAD:SI 5/6/2025 SE REALIZA INSTALACIÓN DE CORRESPONSAL, SE INSTALAN EQUIPOS CON PRUEBAS EXITOSAS, SE CAPACITA Y SE EVALÚA AL CLIENTE, SE INSTALA PUBLICIDAD COMPLETA, CB QUEDA OPERATIVO. USUARIO SOMOS BANCOLOMBIA ACTIVO | W88: ANDRADE HERNANDEZ JUAN CARLOS | X88: SXXZZ082 | Y88: 1088304 | Z88: N/A | AA88: 1103004 | AB88: N/A | AC88: N/A | AD88: N/A | AE88: 40 ROLLOS | AF88: TIPO III | AG88: TERRESTRE | AH88: VISITA_TÉCNICA | AI88: 1 | AJ88: 1 | AK88: 1 | AL88: =IF(AF88="TIPO I",'BASE DE LIQUIDACION 2025'!$B$3,'BASE DE LIQUIDACION 2025'!$B$4) -> 11251.224 | AM88: =IF(AF88="TIPO I",'BASE DE LIQUIDACION 2025'!$C$3,'BASE DE LIQUIDACION 2025'!$C$4) -> 126317.12 | AN88: =IF(AF88="TIPO I",'BASE DE LIQUIDACION 2025'!$D$3,'BASE DE LIQUIDACION 2025'!$D$4) -> 110808.28 | AO88: =AL88*AI88+AJ88*AM88+AK88*AN88 -> 248376.62
A89: SINCELEJO | B89: =VLOOKUP(A89,'CENTRO DE COSTOS'!A:D,4,FALSE) -> JOSE MAURICIO HERNANDEZ ROJAS | C89: =VLOOKUP(A89,'CENTRO DE COSTOS'!A:D,2,FALSE) -> 0004-0001 | D89: 70001 | E89: TA-25-695241 | F89: FO-25-1029534 | G89: 45811 | H89: 45813 | I89: 45811 | J89: 45812 | K89: 45812 | L89: SUCRE | M89: SINCELEJO | N89: BARRIO CALLE SUCRE SINCELEJO | O89: 79684 | P89: CB CRECIMIENTO - NUEVO | Q89: APERTURA | R89: REDEBAN | S89: UNO A UNO | T89: UNO A UNO | U89: EJECUTADO | V89: 3-06-2025 SE REALIZA LLAMADA AL CLIENTE, SE HABLA CON EL SR LUIS FERNANDO PACHECO BERTEL SE VALIDA DIRECCIÓN OK, CANAL OK, DISPONIBILIDAD TOTAL, LLAMAR EL DÍA DE LA INSTALACIÓN PARA CONFIRMAR VISITA, ALTURA APROX 2 METROS; TOMACORRIENTE CERCANO: SI; TIENE CABINA DE SEGURIDAD: NO // CONTACTO REALIZADO POR WHATSAPP 8:10 a. m. 4/6/2025 SE REALIZA INSTALACIÓN DE CORRESPONSAL, SE INSTALAN EQUIPOS CON PRUEBAS EXITOSAS, SE CAPACITA Y SE EVALÚA AL CLIENTE, SE INSTALA PUBLICIDAD COMPLETA, CB QUEDA OPERATIVO. USUARIO SOMOS BANCOLOMBIA ACTIVO | W89: CACERES HERNANDEZ ANDRES | X89: SXXZZ084 | Y89: 963801 | Z89: N/A | AA89: 1145979 | AB89: N/A | AC89: N/A | AD89: N/A | AE89: 40 ROLLOS | AF89: TIPO I | AG89: TERRESTRE | AH89: VISITA_TÉCNICA | AI89: 1 | AJ89: 1 | AK89: 1 | AL89: =IF(AF89="TIPO I",'BASE DE LIQUIDACION 2025'!$B$3,'BASE DE LIQUIDACION 2025'!$B$4) -> 11251.224 | AM89: =IF(AF89="TIPO I",'BASE DE LIQUIDACION 2025'!$C$3,'BASE DE LIQUIDACION 2025'!$C$4) -> 126317.12 | AN89: =IF(AF89="TIPO I",'BASE DE LIQUIDACION 2025'!$D$3,'BASE DE LIQUIDACION 2025'!$D$4) -> 57411.974 | AO89: =AL89*AI89+AJ89*AM89+AK89*AN89 -> 194980.32
A90: PASTO | B90: =VLOOKUP(A90,'CENTRO DE COSTOS'!A:D,4,FALSE) -> DIEGO FERNANDO HENAO CARDONA | C90: =VLOOKUP(A90,'CENTRO DE COSTOS'!A:D,2,FALSE) -> 0004-0003 | D90: 52378 | E90: TA-25-695242 | F90: FO-25-1029540 | G90: 45811 | H90: 45813 | I90: 45811 | J90: 45812 | K90: 45812 | L90: NARIÑO | M90: LA CRUZ | N90: BARRIO CRR CIUDAD DE DIOS LA CRUZ | O90: 79679 | P90: CB CRECIMIENTO - NUEVO | Q90: APERTURA | R90: REDEBAN | S90: UNO A UNO | T90: UNO A UNO | U90: EJECUTADO | V90: 03-06 SE REALIZA LLAMADA AL CLIENTE, SE HABLA CON LA SRA ANA CRISTINA ANGULO ORTIZ SE VALIDA DIRECCIÓN OK, CANAL OK, DISPONIBILIDAD TOTAL, LLAMAR EL DÍA LA INSTALACIÓN PARA CONFIRMAR VISITA, AVISO EXTERIOR ALTURA APROX 3 METROS; TOMACORRIENTE CERCANO: SI; TIENE CABINA DE SEGURIDAD: SI - COMUNICACIÓN POR WPP 04-06 SE REALIZA INSTALACIÓN DE CORRESPONSAL, SE INSTALAN EQUIPOS CON PRUEBAS EXITOSAS, SE CAPACITA Y SE EVALÚA AL CLIENTE, SE INSTALA PUBLICIDAD COMPLETA, CB QUEDA OPERATIVO. USUARIO SOMOS BANCOLOMBIA ACTIVO | W90: PAZ MARTINEZ RICHARD HUMBERTO | X90: SXXZZ079 | Y90: 1169272 | Z90: N/A | AA90: 1217150 | AB90: N/A | AC90: N/A | AD90: N/A | AE90: 40 ROLLOS | AF90: TIPO III | AG90: TERRESTRE | AH90: VISITA_TÉCNICA | AI90: 1 | AJ90: 1 | AK90: 1 | AL90: =IF(AF90="TIPO I",'BASE DE LIQUIDACION 2025'!$B$3,'BASE DE LIQUIDACION 2025'!$B$4) -> 11251.224 | AM90: =IF(AF90="TIPO I",'BASE DE LIQUIDACION 2025'!$C$3,'BASE DE LIQUIDACION 2025'!$C$4) -> 126317.12 | AN90: =IF(AF90="TIPO I",'BASE DE LIQUIDACION 2025'!$D$3,'BASE DE LIQUIDACION 2025'!$D$4) -> 110808.28 | AO90: =AL90*AI90+AJ90*AM90+AK90*AN90 -> 248376.62
A91: BOGOTA | B91: =VLOOKUP(A91,'CENTRO DE COSTOS'!A:D,4,FALSE) -> WILLIAM ASDRUBAL ROZO ROZO | C91: =VLOOKUP(A91,'CENTRO DE COSTOS'!A:D,2,FALSE) -> 0004-0004 | D91: 11001 | E91: TA-25-695243 | F91: FO-25-1029544 | G91: 45811 | H91: 45813 | I91: 45811 | J91: 45813 | K91: 45813 | L91: CUNDINAMARCA | M91: BOGOTA | N91: BARRIO DANUBIO AZUL BOGOTA 9 | O91: 79678 | P91: CB CRECIMIENTO - NUEVO | Q91: APERTURA | R91: REDEBAN | S91: UNO A UNO | T91: UNO A UNO | U91: EJECUTADO | V91: 3-06-2025 SE REALIZA LLAMADA AL CLIENTE, SE HABLA CON LA SRA JULIETH ANDREA MESA RINCON SE VALIDA DIRECCIÓN OK, CANAL OK, DISPONIBILIDAD TOTAL, LLAMAR EL DÍA DE LA INSTALACIÓN PARA CONFIRMAR VISITA, ALTURA APROX 2 METROS; TOMACORRIENTE CERCANO: SI; TIENE CABINA DE SEGURIDAD: SI // CONTACTO REALIZADO POR WHATSAPP 8:18 a. m. 5/6/2025 SE REALIZA INSTALACIÓN DE CORRESPONSAL, SE INSTALAN EQUIPOS CON PRUEBAS EXITOSAS, SE CAPACITA Y SE EVALÚA AL CLIENTE, SE INSTALA PUBLICIDAD COMPLETA, CB QUEDA OPERATIVO. USUARIO SOMOS BANCOLOMBIA ACTIVO | W91: GOMEZ VEGA DAVID SNEYDER | X91: SXXZZ078 | Y91: 957082 | Z91: N/A | AA91: 1110281 | AB91: N/A | AC91: N/A | AD91: N/A | AE91: 40 ROLLOS | AF91: TIPO I | AG91: TERRESTRE | AH91: VISITA_TÉCNICA | AI91: 1 | AJ91: 1 | AK91: 1 | AL91: =IF(AF91="TIPO I",'BASE DE LIQUIDACION 2025'!$B$3,'BASE DE LIQUIDACION 2025'!$B$4) -> 11251.224 | AM91: =IF(AF91="TIPO I",'BASE DE LIQUIDACION 2025'!$C$3,'BASE DE LIQUIDACION 2025'!$C$4) -> 126317.12 | AN91: =IF(AF91="TIPO I",'BASE DE LIQUIDACION 2025'!$D$3,'BASE DE LIQUIDACION 2025'!$D$4) -> 57411.974 | AO91: =AL91*AI91+AJ91*AM91+AK91*AN91 -> 194980.32
A92: VILLAVICENCIO | B92: =VLOOKUP(A92,'CENTRO DE COSTOS'!A:D,4,FALSE) -> KEVIN ALEXIS CORZO BUSTOS | C92: =VLOOKUP(A92,'CENTRO DE COSTOS'!A:D,2,FALSE) -> 0004-0007 | D92: 50001 | E92: TA-25-695244 | F92: FO-25-1029553 | G92: 45811 | H92: 45813 | I92: 45811 | J92: 45813 | K92: 45813 | L92: META | M92: VILLAVICENCIO | N92: BARRIO JORDAN VILLAVICENCIO 12 | O92: 79685 | P92: CB CRECIMIENTO - NUEVO | Q92: APERTURA | R92: REDEBAN | S92: UNO A UNO | T92: UNO A UNO | U92: EJECUTADO | V92: 31-05 SE REALIZA COMUNICACION CON LA SRA OLGA LUCIA RODRIGUEZ OCAMPO, SE VALIDA DIRECCIÓN OK, CANAL OK, DISPONIBILIDAD TOTAL, LLAMAR EL DÍA LA INSTALACIÓN PARA CONFIRMAR VISITA, AVISO EXTERIOR ALTURA APROX DONDE EL TECNICO LO VEA CONVENIENTE, METROS; TOMACORRIENTE CERCANO: SI; TIENE CABINA DE SEGURIDAD:SI 5/6/2025 SE REALIZA INSTALACIÓN DE CORRESPONSAL, SE INSTALAN EQUIPOS CON PRUEBAS EXITOSAS, SE CAPACITA Y SE EVALÚA AL CLIENTE, SE INSTALA PUBLICIDAD COMPLETA, CB QUEDA OPERATIVO. USUARIO SOMOS BANCOLOMBIA ACTIVO | W92: CASTRILLON URREA LONDIER LEANDRO | X92: SXXZZ085 | Y92: 923342 | Z92: N/A | AA92: 953591 | AB92: N/A | AC92: N/A | AD92: N/A | AE92: 40 ROLLOS | AF92: TIPO I | AG92: TERRESTRE | AH92: VISITA_TÉCNICA | AI92: 1 | AJ92: 1 | AK92: 1 | AL92: =IF(AF92="TIPO I",'BASE DE LIQUIDACION 2025'!$B$3,'BASE DE LIQUIDACION 2025'!$B$4) -> 11251.224 | AM92: =IF(AF92="TIPO I",'BASE DE LIQUIDACION 2025'!$C$3,'BASE DE LIQUIDACION 2025'!$C$4) -> 126317.12 | AN92: =IF(AF92="TIPO I",'BASE DE LIQUIDACION 2025'!$D$3,'BASE DE LIQUIDACION 2025'!$D$4) -> 57411.974 | AO92: =AL92*AI92+AJ92*AM92+AK92*AN92 -> 194980.32
A93: CALI | B93: =VLOOKUP(A93,'CENTRO DE COSTOS'!A:D,4,FALSE) -> DIEGO FERNANDO HENAO CARDONA | C93: =VLOOKUP(A93,'CENTRO DE COSTOS'!A:D,2,FALSE) -> 0004-0003 | D93: 76520 | E93: TA-25-695247 | F93: FO-25-1029559 | G93: 45811 | H93: 45813 | I93: 45811 | J93: 45813 | K93: 45813 | L93: VALLE DEL CAUCA | M93: PALMIRA | N93: BARRIO LOS SAUCES PALMIRA | O93: 79681 | P93: CAMBIO DE RAZON SOCIAL | Q93: APERTURA | R93: REDEBAN | S93: UNO A UNO | T93: UNO A UNO | U93: EJECUTADO | V93: 3-06-2025 SE REALIZA LLAMADA AL CLIENTE, SE HABLA CON EL SR BRAYAN ALBADAM VANEGAS SE VALIDA DIRECCIÓN OK, CANAL OK, DISPONIBILIDAD TOTAL, LLAMAR EL DÍA DE LA INSTALACIÓN PARA CONFIRMAR VISITA, PUBLICIDAD OK // CONTACTO REALIZADO POR WHATSAPP 8:25 a. m. 5/6/2025 SE REALIZA INSTALACIÓN DE CORRESPONSAL, SE INSTALAN EQUIPOS CON PRUEBAS EXITOSAS, SE CAPACITA Y SE EVALÚA AL CLIENTE, SE INSTALA PUBLICIDAD COMPLETA, CB QUEDA OPERATIVO. USUARIO SOMOS BANCOLOMBIA ACTIVO | W93: TORRES GARCIA JENDRY JOSE | X93: SXXZZ081 | Y93: 869019 | Z93: N/A | AA93: 549358 | AB93: N/A | AC93: N/A | AD93: N/A | AE93: 40 ROLLOS | AF93: TIPO I | AG93: TERRESTRE | AH93: VISITA_TÉCNICA | AI93: 1 | AJ93: 1 | AK93: 1 | AL93: =IF(AF93="TIPO I",'BASE DE LIQUIDACION 2025'!$B$3,'BASE DE LIQUIDACION 2025'!$B$4) -> 11251.224 | AM93: =IF(AF93="TIPO I",'BASE DE LIQUIDACION 2025'!$C$3,'BASE DE LIQUIDACION 2025'!$C$4) -> 126317.12 | AN93: =IF(AF93="TIPO I",'BASE DE LIQUIDACION 2025'!$D$3,'BASE DE LIQUIDACION 2025'!$D$4) -> 57411.974 | AO93: =AL93*AI93+AJ93*AM93+AK93*AN93 -> 194980.32
A94: SINCELEJO | B94: =VLOOKUP(A94,'CENTRO DE COSTOS'!A:D,4,FALSE) -> JOSE MAURICIO HERNANDEZ ROJAS | C94: =VLOOKUP(A94,'CENTRO DE COSTOS'!A:D,2,FALSE) -> 0004-0001 | D94: 70717 | E94: TA-25-695248 | F94: FO-25-1029565 | G94: 45811 | H94: 45813 | I94: 45811 | J94: 45813 | K94: 45813 | L94: SUCRE | M94: SAN PEDRO | N94: BARRIO SAN MARTIN SAN PEDRO 2 | O94: 79683 | P94: CB CRECIMIENTO - NUEVO | Q94: APERTURA | R94: REDEBAN | S94: UNO A UNO | T94: UNO A UNO | U94: EJECUTADO | V94: 31-05 SE REALIZA LLAMADA AL CLIENTE, SE HABLA CON LA SRA LUISA FERNANDA BANQUET FUNIELES, SE VALIDA DIRECCIÓN OK, CANAL OK, DISPONIBILIDAD TOTAL, LLAMAR EL DÍA LA INSTALACIÓN PARA CONFIRMAR VISITA, AVISO EXTERIOR ALTURA APROX DONDE EL TECNICO LO VEA CONVENIENTE, METROS; TOMACORRIENTE CERCANO: SI; TIENE CABINA DE SEGURIDAD:SI 5/6/2025 SE REALIZA INSTALACIÓN DE CORRESPONSAL, SE INSTALAN EQUIPOS CON PRUEBAS EXITOSAS, SE CAPACITA Y SE EVALÚA AL CLIENTE, SE INSTALA PUBLICIDAD COMPLETA, CB QUEDA OPERATIVO. USUARIO SOMOS BANCOLOMBIA ACTIVO | W94: CACERES HERNANDEZ ANDRES | X94: SXXZZ083 | Y94: 794606 | Z94: N/A | AA94: 1178939 | AB94: N/A | AC94: N/A | AD94: N/A | AE94: 40 ROLLOS | AF94: TIPO II | AG94: TERRESTRE | AH94: VISITA_TÉCNICA | AI94: 1 | AJ94: 1 | AK94: 1 | AL94: =IF(AF94="TIPO I",'BASE DE LIQUIDACION 2025'!$B$3,'BASE DE LIQUIDACION 2025'!$B$4) -> 11251.224 | AM94: =IF(AF94="TIPO I",'BASE DE LIQUIDACION 2025'!$C$3,'BASE DE LIQUIDACION 2025'!$C$4) -> 126317.12 | AN94: =IF(AF94="TIPO I",'BASE DE LIQUIDACION 2025'!$D$3,'BASE DE LIQUIDACION 2025'!$D$4) -> 110808.28 | AO94: =AL94*AI94+AJ94*AM94+AK94*AN94 -> 248376.62
A95: NEIVA | B95: =VLOOKUP(A95,'CENTRO DE COSTOS'!A:D,4,FALSE) -> KEVIN ALEXIS CORZO BUSTOS | C95: =VLOOKUP(A95,'CENTRO DE COSTOS'!A:D,2,FALSE) -> 0004-0007 | D95: 41001 | E95: TA-25-695250 | F95: FO-25-1029575 | G95: 45811 | H95: 45813 | I95: 45811 | J95: 45812 | K95: 45812 | L95: HUILA | M95: NEIVA | N95: BARRIO ZONA INDUSTRIAL NEIVA 11 | O95: 79680 | P95: CB CRECIMIENTO - NUEVO | Q95: APERTURA | R95: REDEBAN | S95: UNO A UNO | T95: UNO A UNO | U95: EJECUTADO | V95: 31-05 SE REALIZA LLAMADA AL CLIENTE, SE HABLA CON LA SRA ADRIANA ARIAS CAPERA, SE VALIDA DIRECCIÓN OK, CANAL OK, DISPONIBILIDAD TOTAL, LLAMAR EL DÍA LA INSTALACIÓN PARA CONFIRMAR VISITA, AVISO EXTERIOR ALTURA APROX DONDE EL TECNICO LO VEA CONVENIENTE, METROS; TOMACORRIENTE CERCANO: SI; TIENE CABINA DE SEGURIDAD:SI 4/6/2025 SE REALIZA INSTALACIÓN DE CORRESPONSAL, SE INSTALAN EQUIPOS CON PRUEBAS EXITOSAS, SE CAPACITA Y SE EVALÚA AL CLIENTE, SE INSTALA PUBLICIDAD COMPLETA, CB QUEDA OPERATIVO. USUARIO SOMOS BANCOLOMBIA ACTIVO | W95: DIAZ VARGAS JONATHAN MIGUEL | X95: SXXZZ080 | Y95: 959134 | Z95: N/A | AA95: 534976 | AB95: N/A | AC95: N/A | AD95: N/A | AE95: 40 ROLLOS | AF95: TIPO I | AG95: TERRESTRE | AH95: VISITA_TÉCNICA | AI95: 1 | AJ95: 1 | AK95: 1 | AL95: =IF(AF95="TIPO I",'BASE DE LIQUIDACION 2025'!$B$3,'BASE DE LIQUIDACION 2025'!$B$4) -> 11251.224 | AM95: =IF(AF95="TIPO I",'BASE DE LIQUIDACION 2025'!$C$3,'BASE DE LIQUIDACION 2025'!$C$4) -> 126317.12 | AN95: =IF(AF95="TIPO I",'BASE DE LIQUIDACION 2025'!$D$3,'BASE DE LIQUIDACION 2025'!$D$4) -> 57411.974 | AO95: =AL95*AI95+AJ95*AM95+AK95*AN95 -> 194980.32
A96: BOGOTA | B96: =VLOOKUP(A96,'CENTRO DE COSTOS'!A:D,4,FALSE) -> WILLIAM ASDRUBAL ROZO ROZO | C96: =VLOOKUP(A96,'CENTRO DE COSTOS'!A:D,2,FALSE) -> 0004-0004 | D96: 11001 | E96: TA-25-695253 | F96: FO-25-1029583 | G96: 45811 | H96: 45813 | I96: 45811 | J96: 45813 | K96: 45813 | L96: CUNDINAMARCA | M96: BOGOTA | N96: BARRIO ALAMOS BOGOTA 11 | O96: 79538 | P96: CAMBIO DE RAZON SOCIAL | Q96: APERTURA | R96: REDEBAN | S96: UNO A UNO | T96: UNO A UNO | U96: EJECUTADO | V96: 31-05 SE REALIZA LLAMADA AL CLIENTE, SE HABLA CON EL SR BRAYAN LEONARDO RIVEROS GRANADOS, SE VALIDA DIRECCIÓN OK, CANAL OK, DISPONIBILIDAD TOTAL, LLAMAR EL DÍA LA INSTALACIÓN PARA CONFIRMAR VISITA, AVISO EXTERIOR ALTURA APROX 2,20, METROS; TOMACORRIENTE CERCANO: SI; TIENE CABINA DE SEGURIDAD:SI 5/6/2025 SE REALIZA INSTALACIÓN DE CORRESPONSAL, SE INSTALAN EQUIPOS CON PRUEBAS EXITOSAS, SE CAPACITA Y SE EVALÚA AL CLIENTE, SE INSTALA PUBLICIDAD COMPLETA, CB QUEDA OPERATIVO. NO SÉ TIENE ACCESO A PÁGINA SOMOS BANCOLOMBIA POR CORREO ERRADO DE CLIENTE, SOLICITA SOPORTE POR WHATSAPP Y LE INDICAN QUE ESTÁ DISPONIBLE EL DÍA MIÉRCOLES DE LA SIGUIENTE SEMANA | W96: MURCIA HERNANDEZ HARVEY IGNACIO | X96: LMUZZ972 | Y96: 1171028 | Z96: N/A | AA96: 1097312 | AB96: N/A | AC96: N/A | AD96: N/A | AE96: 40 ROLLOS | AF96: TIPO I | AG96: TERRESTRE | AH96: VISITA_TÉCNICA | AI96: 1 | AJ96: 1 | AK96: 1 | AL96: =IF(AF96="TIPO I",'BASE DE LIQUIDACION 2025'!$B$3,'BASE DE LIQUIDACION 2025'!$B$4) -> 11251.224 | AM96: =IF(AF96="TIPO I",'BASE DE LIQUIDACION 2025'!$C$3,'BASE DE LIQUIDACION 2025'!$C$4) -> 126317.12 | AN96: =IF(AF96="TIPO I",'BASE DE LIQUIDACION 2025'!$D$3,'BASE DE LIQUIDACION 2025'!$D$4) -> 57411.974 | AO96: =AL96*AI96+AJ96*AM96+AK96*AN96 -> 194980.32
A97: BOGOTA | B97: =VLOOKUP(A97,'CENTRO DE COSTOS'!A:D,4,FALSE) -> WILLIAM ASDRUBAL ROZO ROZO | C97: =VLOOKUP(A97,'CENTRO DE COSTOS'!A:D,2,FALSE) -> 0004-0004 | D97: 11001 | E97: TA-25-695255 | F97: FO-25-1029588 | G97: 45811 | H97: 45813 | I97: 45811 | J97: 45813 | K97: 45813 | L97: CUNDINAMARCA | M97: BOGOTA | N97: BARRIO BOSA BASILIA BOGOTA | O97: 79532 | P97: CB CRECIMIENTO - OTRAS LISTAS | Q97: APERTURA | R97: REDEBAN | S97: UNO A UNO | T97: UNO A UNO | U97: EJECUTADO | V97: 31-05 SE REALIZA LLAMADA AL CLIENTE, SE HABLA CON LA SRA ROSA DELIA CALDERON MEJIA, SE VALIDA DIRECCIÓN OK, CANAL OK, DISPONIBILIDAD TOTAL, LLAMAR EL DÍA LA INSTALACIÓN PARA CONFIRMAR VISITA, AVISO EXTERIOR ALTURA APROX 2 METROS; TOMACORRIENTE CERCANO: SI; TIENE CABINA DE SEGURIDAD:SI 5/6/2025 SE REALIZA INSTALACIÓN DE CORRESPONSAL, SE INSTALAN EQUIPOS CON PRUEBAS EXITOSAS, SE CAPACITA Y SE EVALÚA AL CLIENTE, SE INSTALA PUBLICIDAD COMPLETA, CB QUEDA OPERATIVO. USUARIO SOMOS BANCOLOMBIA ACTIVO | W97: LOZADA ROJAS CHRISTIAN ANDRES | X97: LMUZZ966 | Y97: 917143 | Z97: N/A | AA97: 893413 | AB97: N/A | AC97: N/A | AD97: N/A | AE97: 40 ROLLOS | AF97: TIPO I | AG97: TERRESTRE | AH97: VISITA_TÉCNICA | AI97: 1 | AJ97: 1 | AK97: 1 | AL97: =IF(AF97="TIPO I",'BASE DE LIQUIDACION 2025'!$B$3,'BASE DE LIQUIDACION 2025'!$B$4) -> 11251.224 | AM97: =IF(AF97="TIPO I",'BASE DE LIQUIDACION 2025'!$C$3,'BASE DE LIQUIDACION 2025'!$C$4) -> 126317.12 | AN97: =IF(AF97="TIPO I",'BASE DE LIQUIDACION 2025'!$D$3,'BASE DE LIQUIDACION 2025'!$D$4) -> 57411.974 | AO97: =AL97*AI97+AJ97*AM97+AK97*AN97 -> 194980.32
... A116: CALI | B116: =VLOOKUP(A116,'CENTRO DE COSTOS'!A:D,4,FALSE) -> DIEGO FERNANDO HENAO CARDONA | C116: =VLOOKUP(A116,'CENTRO DE COSTOS'!A:D,2,FALSE) -> 0004-0003 | D116: 76001 | E116: TA-25-716026 | F116: FO-25-1047053 | G116: 45813 | H116: 45817 | I116: 45813 | J116: 45814 | K116: 45814 | L116: VALLE DEL CAUCA | M116: CALI | N116: PTM CALI PUNTO RAJAAM | O116: 79695 | P116: CB CRECIMIENTO ALIANZA - NUEVO | Q116: APERTURA | R116: REDEBAN | S116: AGREGADOR | T116: COMCARD - PTM | U116: EJECUTADO | V116: 05-06 PROGRAMACIÓN REALIZADA POR LA ALIANZA 6/6/2025 SE REALIZA INSTALACIÓN DE CORRESPONSAL, SE INSTALAN EQUIPOS CON PRUEBAS EXITOSAS, SE CAPACITA Y SE EVALÚA AL CLIENTE, SE INSTALA PUBLICIDAD COMPLETA, CB QUEDA OPERATIVO. USUARIO SOMOS BANCOLOMBIA ACTIVO | W116: MONTERO MUESES GIAN CARLO | X116: V1YZZ437 | Y116: 980000 | Z116: N/A | AA116: 905641 | AB116: N/A | AC116: N/A | AD116: N/A | AE116: 40 ROLLOS | AF116: TIPO I | AG116: TERRESTRE | AH116: VISITA_TÉCNICA | AI116: 1 | AJ116: 1 | AK116: 1 | AL116: =IF(AF116="TIPO I",'BASE DE LIQUIDACION 2025'!$B$3,'BASE DE LIQUIDACION 2025'!$B$4) -> 11251.224 | AM116: =IF(AF116="TIPO I",'BASE DE LIQUIDACION 2025'!$C$3,'BASE DE LIQUIDACION 2025'!$C$4) -> 126317.12 | AN116: =IF(AF116="TIPO I",'BASE DE LIQUIDACION 2025'!$D$3,'BASE DE LIQUIDACION 2025'!$D$4) -> 57411.974 | AO116: =AL116*AI116+AJ116*AM116+AK116*AN116 -> 194980.32
A117: CALI | B117: =VLOOKUP(A117,'CENTRO DE COSTOS'!A:D,4,FALSE) -> DIEGO FERNANDO HENAO CARDONA | C117: =VLOOKUP(A117,'CENTRO DE COSTOS'!A:D,2,FALSE) -> 0004-0003 | D117: 76001 | E117: TA-25-716027 | F117: FO-25-1047057 | G117: 45813 | H117: 45817 | I117: 45813 | J117: 45814 | K117: 45814 | L117: VALLE DEL CAUCA | M117: CALI | N117: PTM CALI SABE SOLUCIONES | O117: 79693 | P117: CB CRECIMIENTO ALIANZA - NUEVO | Q117: APERTURA | R117: REDEBAN | S117: AGREGADOR | T117: COMCARD - PTM | U117: EJECUTADO | V117: 05-06 PROGRAMACIÓN REALIZADA POR LA ALIANZA 6/6/2025 SE REALIZA INSTALACIÓN DE CORRESPONSAL, SE INSTALAN EQUIPOS CON PRUEBAS EXITOSAS, SE CAPACITA Y SE EVALÚA AL CLIENTE, SE INSTALA PUBLICIDAD COMPLETA, CB QUEDA OPERATIVO. USUARIO SOMOS BANCOLOMBIA ACTIVO | W117: MONTERO MUESES GIAN CARLO | X117: V1YZZ435 | Y117: 1235481 | Z117: 1091058 | AA117: 546939-241587317561324755887299 | AB117: N/A | AC117: N/A | AD117: N/A | AE117: 40 ROLLOS | AF117: TIPO I | AG117: TERRESTRE | AH117: VISITA_TÉCNICA | AI117: 1 | AJ117: 1 | AK117: 1 | AL117: =IF(AF117="TIPO I",'BASE DE LIQUIDACION 2025'!$B$3,'BASE DE LIQUIDACION 2025'!$B$4) -> 11251.224 | AM117: =IF(AF117="TIPO I",'BASE DE LIQUIDACION 2025'!$C$3,'BASE DE LIQUIDACION 2025'!$C$4) -> 126317.12 | AN117: =IF(AF117="TIPO I",'BASE DE LIQUIDACION 2025'!$D$3,'BASE DE LIQUIDACION 2025'!$D$4) -> 57411.974 | AO117: =AL117*AI117+AJ117*AM117+AK117*AN117 -> 194980.32
A118: CALI | B118: =VLOOKUP(A118,'CENTRO DE COSTOS'!A:D,4,FALSE) -> DIEGO FERNANDO HENAO CARDONA | C118: =VLOOKUP(A118,'CENTRO DE COSTOS'!A:D,2,FALSE) -> 0004-0003 | D118: 76109 | E118: TA-25-716029 | F118: FO-25-1047059 | G118: 45813 | H118: 45817 | I118: 45813 | J118: 45817 | K118: 45817 | L118: VALLE DEL CAUCA | M118: BUENAVENTURA | N118: PTM BUENAVENTURA DROGUERIA Y M | O118: 79692 | P118: CB CRECIMIENTO ALIANZA - NUEVO | Q118: APERTURA | R118: REDEBAN | S118: AGREGADOR | T118: COMCARD - PTM | U118: EJECUTADO | V118: 05-06 PROGRAMACIÓN REALIZADA POR LA ALIANZA 06-06 SE REPROGRAMA LA VISITA PARA OTRO DÍA POR TEMAS DE BLOQUEOS INTERMITENTES EN LA VÍA NO HAY GARANTÍA DE UN VIAJE NORMAL DE IDA Y REGRESO 09-06 SE REALIZA INSTALACIÓN DE CORRESPONSAL, SE INSTALAN EQUIPOS CON PRUEBAS EXITOSAS, SE CAPACITA Y SE EVALÚA AL CLIENTE, SE INSTALA PUBLICIDAD COMPLETA, CB QUEDA OPERATIVO. USUARIO SOMOS BANCOLOMBIA ACTIVO | W118: HERRERA MONAR GEOVANNY | X118: V1YZZ434 | Y118: 1216809 | Z118: N/A | AA118: 1145970 | AB118: N/A | AC118: N/A | AD118: N/A | AE118: 40 ROLLOS | AF118: TIPO III | AG118: TERRESTRE | AH118: VISITA_TÉCNICA | AI118: 1 | AJ118: 1 | AK118: 1 | AL118: =IF(AF118="TIPO I",'BASE DE LIQUIDACION 2025'!$B$3,'BASE DE LIQUIDACION 2025'!$B$4) -> 11251.224 | AM118: =IF(AF118="TIPO I",'BASE DE LIQUIDACION 2025'!$C$3,'BASE DE LIQUIDACION 2025'!$C$4) -> 126317.12 | AN118: =IF(AF118="TIPO I",'BASE DE LIQUIDACION 2025'!$D$3,'BASE DE LIQUIDACION 2025'!$D$4) -> 110808.28 | AO118: =AL118*AI118+AJ118*AM118+AK118*AN118 -> 248376.62
A119: CALI | B119: =VLOOKUP(A119,'CENTRO DE COSTOS'!A:D,4,FALSE) -> DIEGO FERNANDO HENAO CARDONA | C119: =VLOOKUP(A119,'CENTRO DE COSTOS'!A:D,2,FALSE) -> 0004-0003 | D119: 76130 | E119: TA-25-716030 | F119: FO-25-1047061 | G119: 45813 | H119: 45817 | I119: 45813 | J119: 45814 | K119: 45814 | L119: VALLE DEL CAUCA | M119: CANDELARIA | N119: PTM CANDELARIA FINANCELL | O119: 79696 | P119: CB CRECIMIENTO ALIANZA - NUEVO | Q119: APERTURA | R119: REDEBAN | S119: AGREGADOR | T119: COMCARD - PTM | U119: EJECUTADO | V119: 05-06 PROGRAMACIÓN REALIZADA POR LA ALIANZA 6/6/2025 SE REALIZA INSTALACIÓN DE CORRESPONSAL, SE INSTALAN EQUIPOS CON PRUEBAS EXITOSAS, SE CAPACITA Y SE EVALÚA AL CLIENTE, SE INSTALA PUBLICIDAD COMPLETA, CB QUEDA OPERATIVO. USUARIO SOMOS BANCOLOMBIA ACTIVO | W119: TORRES GARCIA JENDRY JOSE | X119: V1YZZ438 | Y119: 929893 | Z119: N/A | AA119: 1145985 | AB119: N/A | AC119: N/A | AD119: N/A | AE119: 40 ROLLOS | AF119: TIPO II | AG119: TERRESTRE | AH119: VISITA_TÉCNICA | AI119: 1 | AJ119: 1 | AK119: 1 | AL119: =IF(AF119="TIPO I",'BASE DE LIQUIDACION 2025'!$B$3,'BASE DE LIQUIDACION 2025'!$B$4) -> 11251.224 | AM119: =IF(AF119="TIPO I",'BASE DE LIQUIDACION 2025'!$C$3,'BASE DE LIQUIDACION 2025'!$C$4) -> 126317.12 | AN119: =IF(AF119="TIPO I",'BASE DE LIQUIDACION 2025'!$D$3,'BASE DE LIQUIDACION 2025'!$D$4) -> 110808.28 | AO119: =AL119*AI119+AJ119*AM119+AK119*AN119 -> 248376.62
A120: CALI | B120: =VLOOKUP(A120,'CENTRO DE COSTOS'!A:D,4,FALSE) -> DIEGO FERNANDO HENAO CARDONA | C120: =VLOOKUP(A120,'CENTRO DE COSTOS'!A:D,2,FALSE) -> 0004-0003 | D120: 76892 | E120: TA-25-716032 | F120: FO-25-1047063 | G120: 45813 | H120: 45817 | I120: 45813 | J120: 45817 | K120: 45817 | L120: VALLE DEL CAUCA | M120: YUMBO | N120: PTM YUMBO PAPELERIA MILU YUMBO | O120: 79709 | P120: CB CRECIMIENTO ALIANZA - NUEVO | Q120: APERTURA | R120: REDEBAN | S120: AGREGADOR | T120: COMCARD - PTM | U120: EJECUTADO | V120: 05-06 PROGRAMACIÓN REALIZADA POR LA ALIANZA 9/6/2025 SE REALIZA INSTALACIÓN DE CORRESPONSAL, SE INSTALAN EQUIPOS CON PRUEBAS EXITOSAS, SE CAPACITA Y SE EVALÚA AL CLIENTE, SE INSTALA PUBLICIDAD COMPLETA, CB QUEDA OPERATIVO. USUARIO SOMOS BANCOLOMBIA ACTIVO | W120: HERRERA MONAR GEOVANNY | X120: V1YZZ451 | Y120: 1092185 | Z120: N/A | AA120: 903690 | AB120: N/A | AC120: N/A | AD120: N/A | AE120: 40 ROLLOS | AF120: TIPO I | AG120: TERRESTRE | AH120: VISITA_TÉCNICA | AI120: 1 | AJ120: 1 | AK120: 1 | AL120: =IF(AF120="TIPO I",'BASE DE LIQUIDACION 2025'!$B$3,'BASE DE LIQUIDACION 2025'!$B$4) -> 11251.224 | AM120: =IF(AF120="TIPO I",'BASE DE LIQUIDACION 2025'!$C$3,'BASE DE LIQUIDACION 2025'!$C$4) -> 126317.12 | AN120: =IF(AF120="TIPO I",'BASE DE LIQUIDACION 2025'!$D$3,'BASE DE LIQUIDACION 2025'!$D$4) -> 57411.974 | AO120: =AL120*AI120+AJ120*AM120+AK120*AN120 -> 194980.32
A121: BOGOTA | B121: =VLOOKUP(A121,'CENTRO DE COSTOS'!A:D,4,FALSE) -> WILLIAM ASDRUBAL ROZO ROZO | C121: =VLOOKUP(A121,'CENTRO DE COSTOS'!A:D,2,FALSE) -> 0004-0004 | D121: 11001 | E121: TA-25-716033 | F121: FO-25-1047067 | G121: 45813 | H121: 45817 | I121: 45813 | J121: 45817 | K121: 45817 | L121: CUNDINAMARCA | M121: BOGOTA | N121: PTM BOGOTA DONDE LEO TU SERVIC | O121: 79686 | P121: CB CRECIMIENTO ALIANZA - NUEVO | Q121: APERTURA | R121: REDEBAN | S121: AGREGADOR | T121: COMCARD - PTM | U121: EJECUTADO | V121: 05-06 PROGRAMACIÓN REALIZADA POR LA ALIANZA 9/6/2025 SE REALIZA INSTALACIÓN DE CORRESPONSAL, SE INSTALAN EQUIPOS CON PRUEBAS EXITOSAS, SE CAPACITA Y SE EVALÚA AL CLIENTE, SE INSTALA PUBLICIDAD COMPLETA, CB QUEDA OPERATIVO. USUARIO SOMOS BANCOLOMBIA ACTIVO | W121: GOMEZ VEGA DAVID SNEYDER | X121: V1YZZ428 | Y121: 728799 | Z121: N/A | AA121: 1103032 | AB121: N/A | AC121: N/A | AD121: N/A | AE121: 40 ROLLOS | AF121: TIPO I | AG121: TERRESTRE | AH121: VISITA_TÉCNICA | AI121: 1 | AJ121: 1 | AK121: 1 | AL121: =IF(AF121="TIPO I",'BASE DE LIQUIDACION 2025'!$B$3,'BASE DE LIQUIDACION 2025'!$B$4) -> 11251.224 | AM121: =IF(AF121="TIPO I",'BASE DE LIQUIDACION 2025'!$C$3,'BASE DE LIQUIDACION 2025'!$C$4) -> 126317.12 | AN121: =IF(AF121="TIPO I",'BASE DE LIQUIDACION 2025'!$D$3,'BASE DE LIQUIDACION 2025'!$D$4) -> 57411.974 | AO121: =AL121*AI121+AJ121*AM121+AK121*AN121 -> 194980.32
A122: BOGOTA | B122: =VLOOKUP(A122,'CENTRO DE COSTOS'!A:D,4,FALSE) -> WILLIAM ASDRUBAL ROZO ROZO | C122: =VLOOKUP(A122,'CENTRO DE COSTOS'!A:D,2,FALSE) -> 0004-0004 | D122: 11001 | E122: TA-25-716038 | F122: FO-25-1047072 | G122: 45813 | H122: 45817 | I122: 45813 | J122: 45814 | K122: 45814 | L122: CUNDINAMARCA | M122: BOGOTA | N122: PTM BOGOTA LIZZVAN S | O122: 79687 | P122: CB CRECIMIENTO ALIANZA - NUEVO | Q122: APERTURA | R122: REDEBAN | S122: AGREGADOR | T122: COMCARD - PTM | U122: EJECUTADO | V122: 05-06 PROGRAMACIÓN REALIZADA POR LA ALIANZA 6/6/2025 SE REALIZA INSTALACIÓN DE CORRESPONSAL, SE INSTALAN EQUIPOS CON PRUEBAS EXITOSAS, SE CAPACITA Y SE EVALÚA AL CLIENTE, SE INSTALA PUBLICIDAD COMPLETA, CB QUEDA OPERATIVO. USUARIO SOMOS BANCOLOMBIA ACTIVO | W122: SOTO LONDOÑO FREDY ALEXANDER | X122: V1YZZ429 | Y122: 783184 | Z122: N/A | AA122: 1114506 | AB122: N/A | AC122: N/A | AD122: N/A | AE122: 40 ROLLOS | AF122: TIPO I | AG122: TERRESTRE | AH122: VISITA_TÉCNICA | AI122: 1 | AJ122: 1 | AK122: 1 | AL122: =IF(AF122="TIPO I",'BASE DE LIQUIDACION 2025'!$B$3,'BASE DE LIQUIDACION 2025'!$B$4) -> 11251.224 | AM122: =IF(AF122="TIPO I",'BASE DE LIQUIDACION 2025'!$C$3,'BASE DE LIQUIDACION 2025'!$C$4) -> 126317.12 | AN122: =IF(AF122="TIPO I",'BASE DE LIQUIDACION 2025'!$D$3,'BASE DE LIQUIDACION 2025'!$D$4) -> 57411.974 | AO122: =AL122*AI122+AJ122*AM122+AK122*AN122 -> 194980.32
A123: BOGOTA | B123: =VLOOKUP(A123,'CENTRO DE COSTOS'!A:D,4,FALSE) -> WILLIAM ASDRUBAL ROZO ROZO | C123: =VLOOKUP(A123,'CENTRO DE COSTOS'!A:D,2,FALSE) -> 0004-0004 | D123: 11001 | E123: TA-25-716040 | F123: FO-25-1047078 | G123: 45813 | H123: 45817 | I123: 45813 | J123: 45814 | K123: 45814 | L123: CUNDINAMARCA | M123: BOGOTA | N123: PTM BOGOTA MC RAM | O123: 79688 | P123: CB CRECIMIENTO ALIANZA - NUEVO | Q123: APERTURA | R123: REDEBAN | S123: AGREGADOR | T123: COMCARD - PTM | U123: EJECUTADO/CANCELADO | V123: 05-06 PROGRAMACIÓN REALIZADA POR LA ALIANZA 6/6/2025 NO ES POSIBLE REALIZAR APERTURA YA QUE EL CLIENTE MANEJA MÁS CORRESPONSALES EN EL PUNTO | W123: SOTO LONDOÑO FREDY ALEXANDER | X123: V1YZZ430 | Y123: N/A | Z123: N/A | AA123: N/A | AB123: N/A | AC123: N/A | AD123: N/A | AE123: 0 | AF123: TIPO I | AG123: TERRESTRE | AH123: VISITA_TÉCNICA | AI123: 0 | AJ123: 0 | AK123: 2 | AL123: =IF(AF123="TIPO I",'BASE DE LIQUIDACION 2025'!$B$3,'BASE DE LIQUIDACION 2025'!$B$4) -> 11251.224 | AM123: =IF(AF123="TIPO I",'BASE DE LIQUIDACION 2025'!$C$3,'BASE DE LIQUIDACION 2025'!$C$4) -> 126317.12 | AN123: =IF(AF123="TIPO I",'BASE DE LIQUIDACION 2025'!$D$3,'BASE DE LIQUIDACION 2025'!$D$4) -> 57411.974 | AO123: =AL123*AI123+AJ123*AM123+AK123*AN123 -> 114823.95
A124: BOGOTA | B124: =VLOOKUP(A124,'CENTRO DE COSTOS'!A:D,4,FALSE) -> WILLIAM ASDRUBAL ROZO ROZO | C124: =VLOOKUP(A124,'CENTRO DE COSTOS'!A:D,2,FALSE) -> 0004-0004 | D124: 11001 | E124: TA-25-716042 | F124: FO-25-1047084 | G124: 45813 | H124: 45817 | I124: 45813 | J124: 45814 | K124: 45814 | L124: CUNDINAMARCA | M124: BOGOTA | N124: PTM BOGOTA LENCERIA PEREZ FRIA | O124: 79689 | P124: CB CRECIMIENTO ALIANZA - NUEVO | Q124: APERTURA | R124: REDEBAN | S124: AGREGADOR | T124: COMCARD - PTM | U124: EJECUTADO | V124: 05-06 PROGRAMACIÓN REALIZADA POR LA ALIANZA 6/6/2025 SE REALIZA INSTALACIÓN DE CORRESPONSAL, SE INSTALAN EQUIPOS CON PRUEBAS EXITOSAS, SE CAPACITA Y SE EVALÚA AL CLIENTE, SE INSTALA PUBLICIDAD COMPLETA, CB QUEDA OPERATIVO. USUARIO SOMOS BANCOLOMBIA ACTIVO | W124: HERNANDEZ NARANJO OSCAR EDUARDO | X124: V1YZZ431 | Y124: 1106701 | Z124: N/A | AA124: 962069 | AB124: N/A | AC124: N/A | AD124: N/A | AE124: 40 ROLLOS | AF124: TIPO I | AG124: TERRESTRE | AH124: VISITA_TÉCNICA | AI124: 1 | AJ124: 1 | AK124: 1 | AL124: =IF(AF124="TIPO I",'BASE DE LIQUIDACION 2025'!$B$3,'BASE DE LIQUIDACION 2025'!$B$4) -> 11251.224 | AM124: =IF(AF124="TIPO I",'BASE DE LIQUIDACION 2025'!$C$3,'BASE DE LIQUIDACION 2025'!$C$4) -> 126317.12 | AN124: =IF(AF124="TIPO I",'BASE DE LIQUIDACION 2025'!$D$3,'BASE DE LIQUIDACION 2025'!$D$4) -> 57411.974 | AO124: =AL124*AI124+AJ124*AM124+AK124*AN124 -> 194980.32
A125: PASTO | B125: =VLOOKUP(A125,'CENTRO DE COSTOS'!A:D,4,FALSE) -> DIEGO FERNANDO HENAO CARDONA | C125: =VLOOKUP(A125,'CENTRO DE COSTOS'!A:D,2,FALSE) -> 0004-0003 | D125: 52001 | E125: TA-25-716049 | F125: FO-25-1047093 | G125: 45813 | H125: 45817 | I125: 45813 | J125: 45817 | K125: 45817 | L125: NARIÑO | M125: PASTO | N125: PTM PASTO MAS BELLA PELUQUERIA | O125: 78990 | P125: CB CRECIMIENTO ALIANZA - OTRAS LISTAS | Q125: APERTURA | R125: REDEBAN | S125: AGREGADOR | T125: COMCARD - PTM | U125: EJECUTADO/CANCELADO | V125: 05-06 PROGRAMACIÓN REALIZADA POR LA ALIANZA 6/6/2025 SE REALIZA VISITA DE APERTURA AL CB PTM CON CÓDIGO 3007078990 PTM PASTO MAS BELLA PELUQUERIA , DIRECCIÓN CR 32 NO 16 A 07 , COORDENADAS 1.219494, -77.283634, PERO SE ENCUENTRA CERCANÍA CON CORRESPONSAL UNO A UNO INSTALADO CON CÓDIGO 3007014514 BARRIO LAS AMERICAS V , DIRECCIÓN CR 32 NO 16 A 18, COORDENADAS 1.219484, -77.283534, QUEDANDO A MENOS DE 10 MTS DE DISTANCIA UNO DEL OTRO, SE REALIZA ESCALAMIENTO POR CERCANÍA EN ESPERA DE COMO PROCEDER. 9/6/2025 ENTIDAD SOLICITA CANCELAR ACTIVIDAD | W125: REMICIO AMADO JOHN HEBER | X125: FATZZ360 | Y125: N/A | Z125: N/A | AA125: N/A | AB125: N/A | AC125: N/A | AD125: N/A | AE125: 0 | AF125: TIPO I | AG125: TERRESTRE | AH125: VISITA_TÉCNICA | AI125: 0 | AJ125: 0 | AK125: 2 | AL125: =IF(AF125="TIPO I",'BASE DE LIQUIDACION 2025'!$B$3,'BASE DE LIQUIDACION 2025'!$B$4) -> 11251.224 | AM125: =IF(AF125="TIPO I",'BASE DE LIQUIDACION 2025'!$C$3,'BASE DE LIQUIDACION 2025'!$C$4) -> 126317.12 | AN125: =IF(AF125="TIPO I",'BASE DE LIQUIDACION 2025'!$D$3,'BASE DE LIQUIDACION 2025'!$D$4) -> 57411.974 | AO125: =AL125*AI125+AJ125*AM125+AK125*AN125 -> 114823.95
A126: MEDELLIN | B126: =VLOOKUP(A126,'CENTRO DE COSTOS'!A:D,4,FALSE) -> JUAN SEBASTIÁN RÍOS CASTRILLÓN | C126: =VLOOKUP(A126,'CENTRO DE COSTOS'!A:D,2,FALSE) -> 0004-0005 | D126: 5001 | E126: TA-25-722185 | F126: FO-25-1063444 | G126: 45817 | H126: 45819 | I126: 45817 | J126: 45818 | K126: 45818 | L126: ANTIOQUIA | M126: MEDELLIN | N126: PTM MEDELLIN MUN VARIEDADES | O126: 79730 | P126: CB CRECIMIENTO ALIANZA - NUEVO | Q126: APERTURA | R126: REDEBAN | S126: AGREGADOR | T126: COMCARD - PTM | U126: EJECUTADO | V126: 09-06 PROGRAMACIÓN REALIZADA POR LA ALIANZA 10/6/2025 SE REALIZA INSTALACIÓN DE CORRESPONSAL, SE INSTALAN EQUIPOS CON PRUEBAS EXITOSAS, SE CAPACITA Y SE EVALÚA AL CLIENTE, SE INSTALA PUBLICIDAD COMPLETA, CB QUEDA OPERATIVO. USUARIO SOMOS BANCOLOMBIA ACTIVO | W126: QUINTERO SANCHEZ JUAN SEBASTIAN | X126: F1WZZ958 | Y126: 760033 | Z126: N/A | AA126: 1238545 | AB126: N/A | AC126: N/A | AD126: N/A | AE126: 40 ROLLOS | AF126: TIPO I | AG126: TERRESTRE | AH126: VISITA_TÉCNICA | AI126: 1 | AJ126: 1 | AK126: 1 | AL126: =IF(AF126="TIPO I",'BASE DE LIQUIDACION 2025'!$B$3,'BASE DE LIQUIDACION 2025'!$B$4) -> 11251.224 | AM126: =IF(AF126="TIPO I",'BASE DE LIQUIDACION 2025'!$C$3,'BASE DE LIQUIDACION 2025'!$C$4) -> 126317.12 | AN126: =IF(AF126="TIPO I",'BASE DE LIQUIDACION 2025'!$D$3,'BASE DE LIQUIDACION 2025'!$D$4) -> 57411.974 | AO126: =AL126*AI126+AJ126*AM126+AK126*AN126 -> 194980.32
...

Sheet PUBLICIDAD OC
A1: Ciudad Sede | B1: COORDINADOR | C1: CENTRO DE COSTOS LÍNEACOM | D1: Código DANE | E1: TA | F1: FO | G1: Fecha asignacion a Linea Comunicaciones | H1: Fecha del cierre del ticket (DD/MM/AAAA) | I1: Departamento | J1: Ciudad | K1: Nombre Cb | L1: Cb | M1: Tipo de Actividad | N1: Solicitud | O1: Descripción | P1: Red | Q1: FORMATO | R1: CADENA | S1: Estado | T1: Causal | U1: DOCUMENTACIÓN SYTEX | V1: Técnico | W1: TERMINAL | X1: Tipo | Y1: Tipo de Trayecto | Z1: Forma de Atención | AA1: Dias de visita | AB1: Transporte Aviso Exterior | AC1: Valor Actividad | AD1: Valor transporte aviso | AE1: VALOR TOTAL INSTALACION DE PUBLICIDAD
A2: CALI | B2: =VLOOKUP(A2,'CENTRO DE COSTOS'!A:D,4,FALSE) -> DIEGO FERNANDO HENAO CARDONA | C2: =VLOOKUP(A2,'CENTRO DE COSTOS'!A:D,2,FALSE) -> 0004-0003 | D2: 76606 | E2: 2231563 | F2: FO-25-1012528 | G2: 45806.651 | H2: 45811.513 | I2: VALLE DEL CAUCA | J2: RESTREPO | K2: BARRIO CENTRO RESTREPO 2 | L2: 41253 | M2: ORDEN DE CAMBIO | N2: PUBLICIDAD | O2: AVISO EXTERIOR | P2: REDEBAN | Q2: CB UNO A UNO | R2: CB UNO A UNO | S2: EJECUTADO_EXITOSO | T2: EJECUTADO EXITOSO | U2: 03/06/2025 EN LA VISITA TÉCNICA SE REALIZÓ LA INSTALACIÓN DE LA PUBLICIDAD EXTERIOR PARA EL CB CERRAR | V2: SANCHEZ URREGO ROBINSON DAVID | W2: 0 | X2: TIPO II | Y2: =VLOOKUP(D2,TIPOLOGIA!A:E,5,0) -> TERRESTRE | Z2: VISITA_TÉCNICA | AA2: 1 | AB2: 1 | AC2: =IF(OR(Z2="SOPORTE_TELEFÓNICO",Z2="ENVÍO"),0,IF(X2="TIPO I",'BASE DE LIQUIDACION 2025'!$I$4,IF(X2="TIPO II",'BASE DE LIQUIDACION 2025'!$I$5,IF(X2="TIPO III",'BASE DE LIQUIDACION 2025'!$I$6,IF(X2="TIPO IV",'BASE DE LIQUIDACION 2025'!$I$7,'BASE DE LIQUIDACION 2025'!$I$8))))) -> 232858.6 | AD2: =IF(OR(Z2="SOPORTE_TELEFÓNICO",Z2="ENVÍO"),0,IF(X2="TIPO I",'BASE DE LIQUIDACION 2025'!$J$4,IF(X2="TIPO II",'BASE DE LIQUIDACION 2025'!$J$5,IF(X2="TIPO III",'BASE DE LIQUIDACION 2025'!$J$6,IF(X2="TIPO IV",'BASE DE LIQUIDACION 2025'!$J$7,'BASE DE LIQUIDACION 2025'!$J$8))))) -> 110808.28 | AE2: =IF(Z2="SOPORTE_TELEFÓNICO",'BASE DE LIQUIDACION 2025'!$L$4,IF(Z2="ENVÍO",'BASE DE LIQUIDACION 2025'!$K$4,AC2*AA2+AD2*AB2)) -> 343666.88
A3: IBAGUE | B3: =VLOOKUP(A3,'CENTRO DE COSTOS'!A:D,4,FALSE) -> KEVIN ALEXIS CORZO BUSTOS | C3: =VLOOKUP(A3,'CENTRO DE COSTOS'!A:D,2,FALSE) -> 0004-0007 | D3: 73001 | E3: 2245169 | F3: FO-25-1030952 | G3: 45811.483 | H3: 45811.666 | I3: TOLIMA | J3: IBAGUE | K3: BARRIO JORDAN 7 ETAPA IBAGUE 8 | L3: 75800 | M3: ORDEN DE CAMBIO | N3: PUBLICIDAD | O3: AVISO EXTERIOR | P3: REDEBAN | Q3: CB UNO A UNO | R3: CB UNO A UNO | S3: EJECUTADO_EXITOSO | T3: EJECUTADO EXITOSO | U3: 03/06/2025 SE INSTALA AVISO EXTERIOR SIN PROBLEMA CERRAR | V3: VARGAS HERRERA JHON JAIRO | W3: 0 | X3: TIPO I | Y3: =VLOOKUP(D3,TIPOLOGIA!A:E,5,0) -> TERRESTRE | Z3: VISITA_TÉCNICA | AA3: 1 | AB3: 1 | AC3: =IF(OR(Z3="SOPORTE_TELEFÓNICO",Z3="ENVÍO"),0,IF(X3="TIPO I",'BASE DE LIQUIDACION 2025'!$I$4,IF(X3="TIPO II",'BASE DE LIQUIDACION 2025'!$I$5,IF(X3="TIPO III",'BASE DE LIQUIDACION 2025'!$I$6,IF(X3="TIPO IV",'BASE DE LIQUIDACION 2025'!$I$7,'BASE DE LIQUIDACION 2025'!$I$8))))) -> 96001.196 | AD3: =IF(OR(Z3="SOPORTE_TELEFÓNICO",Z3="ENVÍO"),0,IF(X3="TIPO I",'BASE DE LIQUIDACION 2025'!$J$4,IF(X3="TIPO II",'BASE DE LIQUIDACION 2025'!$J$5,IF(X3="TIPO III",'BASE DE LIQUIDACION 2025'!$J$6,IF(X3="TIPO IV",'BASE DE LIQUIDACION 2025'!$J$7,'BASE DE LIQUIDACION 2025'!$J$8))))) -> 57411.974 | AE3: =IF(Z3="SOPORTE_TELEFÓNICO",'BASE DE LIQUIDACION 2025'!$L$4,IF(Z3="ENVÍO",'BASE DE LIQUIDACION 2025'!$K$4,AC3*AA3+AD3*AB3)) -> 153413.17
A4: BOGOTA | B4: =VLOOKUP(A4,'CENTRO DE COSTOS'!A:D,4,FALSE) -> WILLIAM ASDRUBAL ROZO ROZO | C4: =VLOOKUP(A4,'CENTRO DE COSTOS'!A:D,2,FALSE) -> 0004-0004 | D4: 11001 | E4: 2250398 | F4: FO-25-1037271 | G4: 45812.363 | H4: 45812.708 | I4: CUNDINAMARCA | J4: BOGOTA | K4: PTM BOGOTA PAPELERIA LOS YIYOS | L4: 61498 | M4: ORDEN DE CAMBIO | N4: PUBLICIDAD | O4: AVISO EXTERIOR | P4: REDEBAN | Q4: AGREGADOR | R4: COMCARD - PTM | S4: EJECUTADO_EXITOSO | T4: EJECUTADO EXITOSO | U4: 04/06/2025 SE INSTALA PUBLICIDAD AVISO EXTERIOR YA QUE NO SE TIENE INSTALADO , COMERCIO INDICA QUE FUE POR ROBO NO SE INSTALA NI FLANGER NI DISPLAY YA QUE COMERCIO CUENTA CON ELLOS CERRAR | V4: GARCIA PASTRANA KEVIN FERNANDO | W4: 0 | X4: TIPO I | Y4: =VLOOKUP(D4,TIPOLOGIA!A:E,5,0) -> TERRESTRE | Z4: VISITA_TÉCNICA | AA4: 1 | AB4: 1 | AC4: =IF(OR(Z4="SOPORTE_TELEFÓNICO",Z4="ENVÍO"),0,IF(X4="TIPO I",'BASE DE LIQUIDACION 2025'!$I$4,IF(X4="TIPO II",'BASE DE LIQUIDACION 2025'!$I$5,IF(X4="TIPO III",'BASE DE LIQUIDACION 2025'!$I$6,IF(X4="TIPO IV",'BASE DE LIQUIDACION 2025'!$I$7,'BASE DE LIQUIDACION 2025'!$I$8))))) -> 96001.196 | AD4: =IF(OR(Z4="SOPORTE_TELEFÓNICO",Z4="ENVÍO"),0,IF(X4="TIPO I",'BASE DE LIQUIDACION 2025'!$J$4,IF(X4="TIPO II",'BASE DE LIQUIDACION 2025'!$J$5,IF(X4="TIPO III",'BASE DE LIQUIDACION 2025'!$J$6,IF(X4="TIPO IV",'BASE DE LIQUIDACION 2025'!$J$7,'BASE DE LIQUIDACION 2025'!$J$8))))) -> 57411.974 | AE4: =IF(Z4="SOPORTE_TELEFÓNICO",'BASE DE LIQUIDACION 2025'!$L$4,IF(Z4="ENVÍO",'BASE DE LIQUIDACION 2025'!$K$4,AC4*AA4+AD4*AB4)) -> 153413.17
A5: BUCARAMANGA | B5: =VLOOKUP(A5,'CENTRO DE COSTOS'!A:D,4,FALSE) -> MIGUEL JULIÁN HERNÁNDEZ GUARÍN | C5: =VLOOKUP(A5,'CENTRO DE COSTOS'!A:D,2,FALSE) -> 0004-0008 | D5: 68547 | E5: 2248104 | F5: FO-25-1034013 | G5: 45811.654 | H5: 45812.71 | I5: SANTANDER | J5: PIEDECUESTA | K5: COMCARD PIEDECUESTA MARYESS | L5: 34367 | M5: ORDEN DE CAMBIO | N5: PUBLICIDAD | O5: AVISO EXTERIOR | P5: REDEBAN | Q5: AGREGADOR | R5: COMCARD - PTM | S5: EJECUTADO_CANCELADO | T5: PETICIÓN USUARIO | U5: 04/06/2025 SE REALIZA VISITA PARA INSTALACIÓN DE AVISO PERO AL MOMENTO DE LA VISITA SE LLEGA Y LA SEÑORA MARÍA INDICA QUE NO NECESITA EL AVISO EXTERIOR, QUE LO QUE ELLA SOLICITA ES UN FLANGEER POR LO TANTO SE INFORMA AL COORDINADOR Y DEBIDO QUE LA SEÑORA DICE NO HABER SOLICITADO AVISO SE HARA DEVOLUCIÓN A BODEGA BUCARAMANGA CERRAR | V5: PEÑA DIAZ IVAN YESID | W5: 0 | X5: TIPO II | Y5: =VLOOKUP(D5,TIPOLOGIA!A:E,5,0) -> TERRESTRE | Z5: VISITA_TÉCNICA | AA5: 1 | AB5: 1 | AC5: =IF(OR(Z5="SOPORTE_TELEFÓNICO",Z5="ENVÍO"),0,IF(X5="TIPO I",'BASE DE LIQUIDACION 2025'!$I$4,IF(X5="TIPO II",'BASE DE LIQUIDACION 2025'!$I$5,IF(X5="TIPO III",'BASE DE LIQUIDACION 2025'!$I$6,IF(X5="TIPO IV",'BASE DE LIQUIDACION 2025'!$I$7,'BASE DE LIQUIDACION 2025'!$I$8))))) -> 232858.6 | AD5: =IF(OR(Z5="SOPORTE_TELEFÓNICO",Z5="ENVÍO"),0,IF(X5="TIPO I",'BASE DE LIQUIDACION 2025'!$J$4,IF(X5="TIPO II",'BASE DE LIQUIDACION 2025'!$J$5,IF(X5="TIPO III",'BASE DE LIQUIDACION 2025'!$J$6,IF(X5="TIPO IV",'BASE DE LIQUIDACION 2025'!$J$7,'BASE DE LIQUIDACION 2025'!$J$8))))) -> 110808.28 | AE5: =IF(Z5="SOPORTE_TELEFÓNICO",'BASE DE LIQUIDACION 2025'!$L$4,IF(Z5="ENVÍO",'BASE DE LIQUIDACION 2025'!$K$4,AC5*AA5+AD5*AB5)) -> 343666.88
A6: CUCUTA | B6: =VLOOKUP(A6,'CENTRO DE COSTOS'!A:D,4,FALSE) -> MIGUEL JULIÁN HERNÁNDEZ GUARÍN | C6: =VLOOKUP(A6,'CENTRO DE COSTOS'!A:D,2,FALSE) -> 0004-0008 | D6: 54001 | E6: 2250358 | F6: FO-25-1037297 | G6: 45812.355 | H6: 45812.713 | I6: NORTE DE SANTANDER | J6: CUCUTA | K6: PTM CUCUTA DROGUERIA NORFARSAL | L6: 61013 | M6: ORDEN DE CAMBIO | N6: PUBLICIDAD | O6: AVISO EXTERIOR | P6: REDEBAN | Q6: AGREGADOR | R6: COMCARD - PTM | S6: EJECUTADO_EXITOSO | T6: EJECUTADO EXITOSO | U6: 04/06/2025 SE INSTALA AVISO EXTERIOR OK CERRAR | V6: DURAN ACOSTA FRANK YONNY | W6: 0 | X6: TIPO I | Y6: =VLOOKUP(D6,TIPOLOGIA!A:E,5,0) -> TERRESTRE | Z6: VISITA_TÉCNICA | AA6: 1 | AB6: 1 | AC6: =IF(OR(Z6="SOPORTE_TELEFÓNICO",Z6="ENVÍO"),0,IF(X6="TIPO I",'BASE DE LIQUIDACION 2025'!$I$4,IF(X6="TIPO II",'BASE DE LIQUIDACION 2025'!$I$5,IF(X6="TIPO III",'BASE DE LIQUIDACION 2025'!$I$6,IF(X6="TIPO IV",'BASE DE LIQUIDACION 2025'!$I$7,'BASE DE LIQUIDACION 2025'!$I$8))))) -> 96001.196 | AD6: =IF(OR(Z6="SOPORTE_TELEFÓNICO",Z6="ENVÍO"),0,IF(X6="TIPO I",'BASE DE LIQUIDACION 2025'!$J$4,IF(X6="TIPO II",'BASE DE LIQUIDACION 2025'!$J$5,IF(X6="TIPO III",'BASE DE LIQUIDACION 2025'!$J$6,IF(X6="TIPO IV",'BASE DE LIQUIDACION 2025'!$J$7,'BASE DE LIQUIDACION 2025'!$J$8))))) -> 57411.974 | AE6: =IF(Z6="SOPORTE_TELEFÓNICO",'BASE DE LIQUIDACION 2025'!$L$4,IF(Z6="ENVÍO",'BASE DE LIQUIDACION 2025'!$K$4,AC6*AA6+AD6*AB6)) -> 153413.17
A7: BOGOTA | B7: =VLOOKUP(A7,'CENTRO DE COSTOS'!A:D,4,FALSE) -> WILLIAM ASDRUBAL ROZO ROZO | C7: =VLOOKUP(A7,'CENTRO DE COSTOS'!A:D,2,FALSE) -> 0004-0004 | D7: 11001 | E7: 2238186 | F7: FO-25-1021077 | G7: 45808.442 | H7: 45813.503 | I7: CUNDINAMARCA | J7: BOGOTA | K7: BARRIO BARRIOS UNIDOS 3 BOGOTA | L7: 31950 | M7: ORDEN DE CAMBIO | N7: PUBLICIDAD | O7: AVISO EXTERIOR | P7: REDEBAN | Q7: CB UNO A UNO | R7: CB UNO A UNO | S7: EJECUTADO_EXITOSO | T7: EJECUTADO EXITOSO | U7: 05/06/2025 SE REALIZA INSTALACIÓN DE AVISO EXTERIOR, EN LA FACHADA DEL COMERCIO, SE DEJA CHASEADO Y ASEGURADO, COMERCIO INDICA QUE EL ANTERIOR FUE HURTADO CERRAR | V7: GARCIA PASTRANA KEVIN FERNANDO | W7: 0 | X7: TIPO I | Y7: =VLOOKUP(D7,TIPOLOGIA!A:E,5,0) -> TERRESTRE | Z7: VISITA_TÉCNICA | AA7: 1 | AB7: 1 | AC7: =IF(OR(Z7="SOPORTE_TELEFÓNICO",Z7="ENVÍO"),0,IF(X7="TIPO I",'BASE DE LIQUIDACION 2025'!$I$4,IF(X7="TIPO II",'BASE DE LIQUIDACION 2025'!$I$5,IF(X7="TIPO III",'BASE DE LIQUIDACION 2025'!$I$6,IF(X7="TIPO IV",'BASE DE LIQUIDACION 2025'!$I$7,'BASE DE LIQUIDACION 2025'!$I$8))))) -> 96001.196 | AD7: =IF(OR(Z7="SOPORTE_TELEFÓNICO",Z7="ENVÍO"),0,IF(X7="TIPO I",'BASE DE LIQUIDACION 2025'!$J$4,IF(X7="TIPO II",'BASE DE LIQUIDACION 2025'!$J$5,IF(X7="TIPO III",'BASE DE LIQUIDACION 2025'!$J$6,IF(X7="TIPO IV",'BASE DE LIQUIDACION 2025'!$J$7,'BASE DE LIQUIDACION 2025'!$J$8))))) -> 57411.974 | AE7: =IF(Z7="SOPORTE_TELEFÓNICO",'BASE DE LIQUIDACION 2025'!$L$4,IF(Z7="ENVÍO",'BASE DE LIQUIDACION 2025'!$K$4,AC7*AA7+AD7*AB7)) -> 153413.17
A8: MONTERIA | B8: =VLOOKUP(A8,'CENTRO DE COSTOS'!A:D,4,FALSE) -> JOSE MAURICIO HERNANDEZ ROJAS | C8: =VLOOKUP(A8,'CENTRO DE COSTOS'!A:D,2,FALSE) -> 0004-0001 | D8: 5154 | E8: 2240971 | F8: FO-25-1026206 | G8: 45811.333 | H8: 45813.506 | I8: ANTIOQUIA | J8: CAUCASIA | K8: DISTRICOL MAXBARATO | L8: 44420 | M8: ORDEN DE CAMBIO | N8: PUBLICIDAD | O8: AVISO EXTERIOR | P8: REDEBAN | Q8: AGREGADOR | R8: DISTRICOL | S8: EJECUTADO_EXITOSO | T8: EJECUTADO EXITOSO | U8: 05/06/2025 SE REALIZA VISITA TÉCNICA PARA INSTALACIÓN DE AVISO EXTERIOR. SE INSTALA AVISO SIN NOVEDAD. CERRAR | V8: CASSIANI PEREZ RAUL RAMIRO | W8: 0 | X8: TIPO II | Y8: =VLOOKUP(D8,TIPOLOGIA!A:E,5,0) -> TERRESTRE | Z8: VISITA_TÉCNICA | AA8: 1 | AB8: 1 | AC8: =IF(OR(Z8="SOPORTE_TELEFÓNICO",Z8="ENVÍO"),0,IF(X8="TIPO I",'BASE DE LIQUIDACION 2025'!$I$4,IF(X8="TIPO II",'BASE DE LIQUIDACION 2025'!$I$5,IF(X8="TIPO III",'BASE DE LIQUIDACION 2025'!$I$6,IF(X8="TIPO IV",'BASE DE LIQUIDACION 2025'!$I$7,'BASE DE LIQUIDACION 2025'!$I$8))))) -> 232858.6 | AD8: =IF(OR(Z8="SOPORTE_TELEFÓNICO",Z8="ENVÍO"),0,IF(X8="TIPO I",'BASE DE LIQUIDACION 2025'!$J$4,IF(X8="TIPO II",'BASE DE LIQUIDACION 2025'!$J$5,IF(X8="TIPO III",'BASE DE LIQUIDACION 2025'!$J$6,IF(X8="TIPO IV",'BASE DE LIQUIDACION 2025'!$J$7,'BASE DE LIQUIDACION 2025'!$J$8))))) -> 110808.28 | AE8: =IF(Z8="SOPORTE_TELEFÓNICO",'BASE DE LIQUIDACION 2025'!$L$4,IF(Z8="ENVÍO",'BASE DE LIQUIDACION 2025'!$K$4,AC8*AA8+AD8*AB8)) -> 343666.88
A9: BOGOTA | B9: =VLOOKUP(A9,'CENTRO DE COSTOS'!A:D,4,FALSE) -> WILLIAM ASDRUBAL ROZO ROZO | C9: =VLOOKUP(A9,'CENTRO DE COSTOS'!A:D,2,FALSE) -> 0004-0004 | D9: 11001 | E9: 2253356 | F9: FO-25-1041290 | G9: 45812.548 | H9: 45813.536 | I9: CUNDINAMARCA | J9: BOGOTA | K9: BARRIO FLORIDA BLANCA BOGOTA | L9: 76103 | M9: ORDEN DE CAMBIO | N9: PUBLICIDAD | O9: AVISO EXTERIOR | P9: REDEBAN | Q9: CB UNO A UNO | R9: CB UNO A UNO | S9: EJECUTADO_EXITOSO | T9: EJECUTADO EXITOSO | U9: 05/06/2025 SE REALIZA INSTALACIÓN DE AVISO EXTERIOR SIN BORDE DE ALUMINIO POR SOLICITUD DEL CLIENTE CERRAR | V9: MURCIA HERNANDEZ HARVEY IGNACIO | W9: 0 | X9: TIPO I | Y9: =VLOOKUP(D9,TIPOLOGIA!A:E,5,0) -> TERRESTRE | Z9: VISITA_TÉCNICA | AA9: 1 | AB9: 1 | AC9: =IF(OR(Z9="SOPORTE_TELEFÓNICO",Z9="ENVÍO"),0,IF(X9="TIPO I",'BASE DE LIQUIDACION 2025'!$I$4,IF(X9="TIPO II",'BASE DE LIQUIDACION 2025'!$I$5,IF(X9="TIPO III",'BASE DE LIQUIDACION 2025'!$I$6,IF(X9="TIPO IV",'BASE DE LIQUIDACION 2025'!$I$7,'BASE DE LIQUIDACION 2025'!$I$8))))) -> 96001.196 | AD9: =IF(OR(Z9="SOPORTE_TELEFÓNICO",Z9="ENVÍO"),0,IF(X9="TIPO I",'BASE DE LIQUIDACION 2025'!$J$4,IF(X9="TIPO II",'BASE DE LIQUIDACION 2025'!$J$5,IF(X9="TIPO III",'BASE DE LIQUIDACION 2025'!$J$6,IF(X9="TIPO IV",'BASE DE LIQUIDACION 2025'!$J$7,'BASE DE LIQUIDACION 2025'!$J$8))))) -> 57411.974 | AE9: =IF(Z9="SOPORTE_TELEFÓNICO",'BASE DE LIQUIDACION 2025'!$L$4,IF(Z9="ENVÍO",'BASE DE LIQUIDACION 2025'!$K$4,AC9*AA9+AD9*AB9)) -> 153413.17
A10: BUCARAMANGA | B10: =VLOOKUP(A10,'CENTRO DE COSTOS'!A:D,4,FALSE) -> MIGUEL JULIÁN HERNÁNDEZ GUARÍN | C10: =VLOOKUP(A10,'CENTRO DE COSTOS'!A:D,2,FALSE) -> 0004-0008 | D10: 68081 | E10: 2250719 | F10: FO-25-1037308 | G10: 45812.365 | H10: 45813.636 | I10: SANTANDER | J10: BARRANCABERMEJA | K10: PTM BARRANCABERMEJA CAMPESTRE | L10: 40691 | M10: ORDEN DE CAMBIO | N10: PUBLICIDAD | O10: AVISO EXTERIOR | P10: REDEBAN | Q10: AGREGADOR | R10: COMCARD - PTM | S10: EJECUTADO_EXITOSO | T10: EJECUTADO EXITOSO | U10: 05/06/2025 SE INSTALA AVISO EXTERIOR OK CERRAR | V10: GELVEZ MOGOLLON JOSE ELISEO | W10: 0 | X10: TIPO III | Y10: =VLOOKUP(D10,TIPOLOGIA!A:E,5,0) -> TERRESTRE | Z10: VISITA_TÉCNICA | AA10: 1 | AB10: 1 | AC10: =IF(OR(Z10="SOPORTE_TELEFÓNICO",Z10="ENVÍO"),0,IF(X10="TIPO I",'BASE DE LIQUIDACION 2025'!$I$4,IF(X10="TIPO II",'BASE DE LIQUIDACION 2025'!$I$5,IF(X10="TIPO III",'BASE DE LIQUIDACION 2025'!$I$6,IF(X10="TIPO IV",'BASE DE LIQUIDACION 2025'!$I$7,'BASE DE LIQUIDACION 2025'!$I$8))))) -> 344774.57 | AD10: =IF(OR(Z10="SOPORTE_TELEFÓNICO",Z10="ENVÍO"),0,IF(X10="TIPO I",'BASE DE LIQUIDACION 2025'!$J$4,IF(X10="TIPO II",'BASE DE LIQUIDACION 2025'!$J$5,IF(X10="TIPO III",'BASE DE LIQUIDACION 2025'!$J$6,IF(X10="TIPO IV",'BASE DE LIQUIDACION 2025'!$J$7,'BASE DE LIQUIDACION 2025'!$J$8))))) -> 110808.28 | AE10: =IF(Z10="SOPORTE_TELEFÓNICO",'BASE DE LIQUIDACION 2025'!$L$4,IF(Z10="ENVÍO",'BASE DE LIQUIDACION 2025'!$K$4,AC10*AA10+AD10*AB10)) -> 455582.84
A11: BOGOTA | B11: =VLOOKUP(A11,'CENTRO DE COSTOS'!A:D,4,FALSE) -> WILLIAM ASDRUBAL ROZO ROZO | C11: =VLOOKUP(A11,'CENTRO DE COSTOS'!A:D,2,FALSE) -> 0004-0004 | D11: 25402 | E11: 2236494 | F11: FO-25-1018508 | G11: 45807.66 | H11: 45813.643 | I11: CUNDINAMARCA | J11: LA VEGA | K11: BARRIO EL VINO BARRIO EL VINO | L11: 23945 | M11: ORDEN DE CAMBIO | N11: PUBLICIDAD | O11: AVISO EXTERIOR | P11: REDEBAN | Q11: CB UNO A UNO | R11: CB UNO A UNO | S11: EJECUTADO_EXITOSO | T11: EJECUTADO EXITOSO | U11: 05/06/2025 SE REALIZA INSTALACIÓN DE AVISO EXTERIOR NO SE MANIPULAN TERMINALES CERRAR | V11: SOTO LONDOÑO FREDY ALEXANDER | W11: 0 | X11: TIPO II | Y11: =VLOOKUP(D11,TIPOLOGIA!A:E,5,0) -> TERRESTRE | Z11: VISITA_TÉCNICA | AA11: 1 | AB11: 1 | AC11: =IF(OR(Z11="SOPORTE_TELEFÓNICO",Z11="ENVÍO"),0,IF(X11="TIPO I",'BASE DE LIQUIDACION 2025'!$I$4,IF(X11="TIPO II",'BASE DE LIQUIDACION 2025'!$I$5,IF(X11="TIPO III",'BASE DE LIQUIDACION 2025'!$I$6,IF(X11="TIPO IV",'BASE DE LIQUIDACION 2025'!$I$7,'BASE DE LIQUIDACION 2025'!$I$8))))) -> 232858.6 | AD11: =IF(OR(Z11="SOPORTE_TELEFÓNICO",Z11="ENVÍO"),0,IF(X11="TIPO I",'BASE DE LIQUIDACION 2025'!$J$4,IF(X11="TIPO II",'BASE DE LIQUIDACION 2025'!$J$5,IF(X11="TIPO III",'BASE DE LIQUIDACION 2025'!$J$6,IF(X11="TIPO IV",'BASE DE LIQUIDACION 2025'!$J$7,'BASE DE LIQUIDACION 2025'!$J$8))))) -> 110808.28 | AE11: =IF(Z11="SOPORTE_TELEFÓNICO",'BASE DE LIQUIDACION 2025'!$L$4,IF(Z11="ENVÍO",'BASE DE LIQUIDACION 2025'!$K$4,AC11*AA11+AD11*AB11)) -> 343666.88
A12: MEDELLIN | B12: =VLOOKUP(A12,'CENTRO DE COSTOS'!A:D,4,FALSE) -> JUAN SEBASTIÁN RÍOS CASTRILLÓN | C12: =VLOOKUP(A12,'CENTRO DE COSTOS'!A:D,2,FALSE) -> 0004-0005 | D12: 5001 | E12: 2238475 | F12: FO-25-1021988 | G12: 45811.333 | H12: 45813.647 | I12: ANTIOQUIA | J12: MEDELLIN | K12: BARRIO PLAZA MINORISTA III MED | L12: 13959 | M12: ORDEN DE CAMBIO | N12: PUBLICIDAD | O12: AVISO EXTERIOR | P12: REDEBAN | Q12: CB UNO A UNO | R12: CB UNO A UNO | S12: EJECUTADO_EXITOSO | T12: EJECUTADO EXITOSO | U12: 05/06/2025 SE INSTALA AVISO EXTERIOR OK CERRAR | V12: QUINTERO SANCHEZ JUAN SEBASTIAN | W12: 0 | X12: TIPO I | Y12: =VLOOKUP(D12,TIPOLOGIA!A:E,5,0) -> TERRESTRE | Z12: VISITA_TÉCNICA | AA12: 1 | AB12: 1 | AC12: =IF(OR(Z12="SOPORTE_TELEFÓNICO",Z12="ENVÍO"),0,IF(X12="TIPO I",'BASE DE LIQUIDACION 2025'!$I$4,IF(X12="TIPO II",'BASE DE LIQUIDACION 2025'!$I$5,IF(X12="TIPO III",'BASE DE LIQUIDACION 2025'!$I$6,IF(X12="TIPO IV",'BASE DE LIQUIDACION 2025'!$I$7,'BASE DE LIQUIDACION 2025'!$I$8))))) -> 96001.196 | AD12: =IF(OR(Z12="SOPORTE_TELEFÓNICO",Z12="ENVÍO"),0,IF(X12="TIPO I",'BASE DE LIQUIDACION 2025'!$J$4,IF(X12="TIPO II",'BASE DE LIQUIDACION 2025'!$J$5,IF(X12="TIPO III",'BASE DE LIQUIDACION 2025'!$J$6,IF(X12="TIPO IV",'BASE DE LIQUIDACION 2025'!$J$7,'BASE DE LIQUIDACION 2025'!$J$8))))) -> 57411.974 | AE12: =IF(Z12="SOPORTE_TELEFÓNICO",'BASE DE LIQUIDACION 2025'!$L$4,IF(Z12="ENVÍO",'BASE DE LIQUIDACION 2025'!$K$4,AC12*AA12+AD12*AB12)) -> 153413.17
A13: VILLAVICENCIO | B13: =VLOOKUP(A13,'CENTRO DE COSTOS'!A:D,4,FALSE) -> KEVIN ALEXIS CORZO BUSTOS | C13: =VLOOKUP(A13,'CENTRO DE COSTOS'!A:D,2,FALSE) -> 0004-0007 | D13: 50001 | E13: 2243325 | F13: FO-25-1029341 | G13: 45811.402 | H13: 45813.686 | I13: META | J13: VILLAVICENCIO | K13: BARRIO ESPERANZA VILLAVICENCIO | L13: 53198 | M13: ORDEN DE CAMBIO | N13: PUBLICIDAD | O13: AVISO EXTERIOR | P13: REDEBAN | Q13: CB UNO A UNO | R13: CB UNO A UNO | S13: EJECUTADO_EXITOSO | T13: EJECUTADO EXITOSO | U13: 05/06/2025 SE INSTALA AVISO EXTERIOR CERRAR | V13: CASTRILLON URREA LONDIER LEANDRO | W13: 0 | X13: TIPO I | Y13: =VLOOKUP(D13,TIPOLOGIA!A:E,5,0) -> TERRESTRE | Z13: VISITA_TÉCNICA | AA13: 1 | AB13: 1 | AC13: =IF(OR(Z13="SOPORTE_TELEFÓNICO",Z13="ENVÍO"),0,IF(X13="TIPO I",'BASE DE LIQUIDACION 2025'!$I$4,IF(X13="TIPO II",'BASE DE LIQUIDACION 2025'!$I$5,IF(X13="TIPO III",'BASE DE LIQUIDACION 2025'!$I$6,IF(X13="TIPO IV",'BASE DE LIQUIDACION 2025'!$I$7,'BASE DE LIQUIDACION 2025'!$I$8))))) -> 96001.196 | AD13: =IF(OR(Z13="SOPORTE_TELEFÓNICO",Z13="ENVÍO"),0,IF(X13="TIPO I",'BASE DE LIQUIDACION 2025'!$J$4,IF(X13="TIPO II",'BASE DE LIQUIDACION 2025'!$J$5,IF(X13="TIPO III",'BASE DE LIQUIDACION 2025'!$J$6,IF(X13="TIPO IV",'BASE DE LIQUIDACION 2025'!$J$7,'BASE DE LIQUIDACION 2025'!$J$8))))) -> 57411.974 | AE13: =IF(Z13="SOPORTE_TELEFÓNICO",'BASE DE LIQUIDACION 2025'!$L$4,IF(Z13="ENVÍO",'BASE DE LIQUIDACION 2025'!$K$4,AC13*AA13+AD13*AB13)) -> 153413.17
... A17: BOGOTA | B17: =VLOOKUP(A17,'CENTRO DE COSTOS'!A:D,4,FALSE) -> WILLIAM ASDRUBAL ROZO ROZO | C17: =VLOOKUP(A17,'CENTRO DE COSTOS'!A:D,2,FALSE) -> 0004-0004 | D17: 11001 | E17: 2248758 | F17: FO-25-1034533 | G17: 45811.7 | H17: 45814.504 | I17: CUNDINAMARCA | J17: BOGOTA | K17: BARRIO SAN JORGE BOGOTA | L17: 25655 | M17: ORDEN DE CAMBIO | N17: PUBLICIDAD | O17: AVISO EXTERIOR | P17: REDEBAN | Q17: CB UNO A UNO | R17: CB UNO A UNO | S17: EJECUTADO_EXITOSO | T17: EJECUTADO EXITOSO | U17: 06/06/2025 SE VISITA CB PARA INSTALACIÓN DE AVISO EXTERIOR POR ROBO DEL EXISTENTE SE PROCEDE CON INSTALACIÓN Y SE DEJA CB OPERANDO SIN NOVEDAD CERRAR | V17: ROMERO ROJAS BREIDY JHOHAN | W17: 0 | X17: TIPO I | Y17: =VLOOKUP(D17,TIPOLOGIA!A:E,5,0) -> TERRESTRE | Z17: VISITA_TÉCNICA | AA17: 1 | AB17: 1 | AC17: =IF(OR(Z17="SOPORTE_TELEFÓNICO",Z17="ENVÍO"),0,IF(X17="TIPO I",'BASE DE LIQUIDACION 2025'!$I$4,IF(X17="TIPO II",'BASE DE LIQUIDACION 2025'!$I$5,IF(X17="TIPO III",'BASE DE LIQUIDACION 2025'!$I$6,IF(X17="TIPO IV",'BASE DE LIQUIDACION 2025'!$I$7,'BASE DE LIQUIDACION 2025'!$I$8))))) -> 96001.196 | AD17: =IF(OR(Z17="SOPORTE_TELEFÓNICO",Z17="ENVÍO"),0,IF(X17="TIPO I",'BASE DE LIQUIDACION 2025'!$J$4,IF(X17="TIPO II",'BASE DE LIQUIDACION 2025'!$J$5,IF(X17="TIPO III",'BASE DE LIQUIDACION 2025'!$J$6,IF(X17="TIPO IV",'BASE DE LIQUIDACION 2025'!$J$7,'BASE DE LIQUIDACION 2025'!$J$8))))) -> 57411.974 | AE17: =IF(Z17="SOPORTE_TELEFÓNICO",'BASE DE LIQUIDACION 2025'!$L$4,IF(Z17="ENVÍO",'BASE DE LIQUIDACION 2025'!$K$4,AC17*AA17+AD17*AB17)) -> 153413.17
A18: VILLAVICENCIO | B18: =VLOOKUP(A18,'CENTRO DE COSTOS'!A:D,4,FALSE) -> KEVIN ALEXIS CORZO BUSTOS | C18: =VLOOKUP(A18,'CENTRO DE COSTOS'!A:D,2,FALSE) -> 0004-0007 | D18: 50001 | E18: 2254815 | F18: FO-25-1042449 | G18: 45812.654 | H18: 45814.505 | I18: META | J18: VILLAVICENCIO | K18: BARRIO LA FLORENCIA VILLAVICEN | L18: 75273 | M18: ORDEN DE CAMBIO | N18: PUBLICIDAD | O18: AVISO EXTERIOR | P18: REDEBAN | Q18: CB UNO A UNO | R18: CB UNO A UNO | S18: EJECUTADO_EXITOSO | T18: EJECUTADO EXITOSO | U18: 06/06/2025 SE REALIZA INSTALACIÓN DE AVISO EXTERIOR SOLICITADO POR EL COMERCIO SE ENTREGA INSLADO DONDE INDICA EL COMERCIO CERRAR | V18: ROZO JIMENEZ EDGAR ARMANDO | W18: EXZZZ712 | X18: TIPO I | Y18: =VLOOKUP(D18,TIPOLOGIA!A:E,5,0) -> TERRESTRE | Z18: VISITA_TÉCNICA | AA18: 1 | AB18: 1 | AC18: =IF(OR(Z18="SOPORTE_TELEFÓNICO",Z18="ENVÍO"),0,IF(X18="TIPO I",'BASE DE LIQUIDACION 2025'!$I$4,IF(X18="TIPO II",'BASE DE LIQUIDACION 2025'!$I$5,IF(X18="TIPO III",'BASE DE LIQUIDACION 2025'!$I$6,IF(X18="TIPO IV",'BASE DE LIQUIDACION 2025'!$I$7,'BASE DE LIQUIDACION 2025'!$I$8))))) -> 96001.196 | AD18: =IF(OR(Z18="SOPORTE_TELEFÓNICO",Z18="ENVÍO"),0,IF(X18="TIPO I",'BASE DE LIQUIDACION 2025'!$J$4,IF(X18="TIPO II",'BASE DE LIQUIDACION 2025'!$J$5,IF(X18="TIPO III",'BASE DE LIQUIDACION 2025'!$J$6,IF(X18="TIPO IV",'BASE DE LIQUIDACION 2025'!$J$7,'BASE DE LIQUIDACION 2025'!$J$8))))) -> 57411.974 | AE18: =IF(Z18="SOPORTE_TELEFÓNICO",'BASE DE LIQUIDACION 2025'!$L$4,IF(Z18="ENVÍO",'BASE DE LIQUIDACION 2025'!$K$4,AC18*AA18+AD18*AB18)) -> 153413.17
A19: APARTADO | B19: =VLOOKUP(A19,'CENTRO DE COSTOS'!A:D,4,FALSE) -> JUAN SEBASTIÁN RÍOS CASTRILLÓN | C19: =VLOOKUP(A19,'CENTRO DE COSTOS'!A:D,2,FALSE) -> 0004-0005 | D19: 5490 | E19: 2249271 | F19: FO-25-1037264 | G19: 45811.768 | H19: 45814.557 | I19: ANTIOQUIA | J19: NECOCLI | K19: BARRIO AUTOPISTA AL MAR 2 NECOCLI | L19: 77956 | M19: ORDEN DE CAMBIO | N19: PUBLICIDAD | O19: AVISO EXTERIOR | P19: REDEBAN | Q19: CB UNO A UNO | R19: CB UNO A UNO | S19: EJECUTADO_EXITOSO | T19: EJECUTADO EXITOSO | U19: 06/06/2025 SE CAMBIA AVISO EXTERIOR, EL QUE SE ENCONTRABA EN EL COMERCIO ESTABA PARTIDO OK. INSTALACIÓN AVISO OK CERRAR | V19: COGOLLO VERTEL EDER LUIS | W19: 0 | X19: TIPO II | Y19: =VLOOKUP(D19,TIPOLOGIA!A:E,5,0) -> TERRESTRE | Z19: VISITA_TÉCNICA | AA19: 1 | AB19: 1 | AC19: =IF(OR(Z19="SOPORTE_TELEFÓNICO",Z19="ENVÍO"),0,IF(X19="TIPO I",'BASE DE LIQUIDACION 2025'!$I$4,IF(X19="TIPO II",'BASE DE LIQUIDACION 2025'!$I$5,IF(X19="TIPO III",'BASE DE LIQUIDACION 2025'!$I$6,IF(X19="TIPO IV",'BASE DE LIQUIDACION 2025'!$I$7,'BASE DE LIQUIDACION 2025'!$I$8))))) -> 232858.6 | AD19: =IF(OR(Z19="SOPORTE_TELEFÓNICO",Z19="ENVÍO"),0,IF(X19="TIPO I",'BASE DE LIQUIDACION 2025'!$J$4,IF(X19="TIPO II",'BASE DE LIQUIDACION 2025'!$J$5,IF(X19="TIPO III",'BASE DE LIQUIDACION 2025'!$J$6,IF(X19="TIPO IV",'BASE DE LIQUIDACION 2025'!$J$7,'BASE DE LIQUIDACION 2025'!$J$8))))) -> 110808.28 | AE19: =IF(Z19="SOPORTE_TELEFÓNICO",'BASE DE LIQUIDACION 2025'!$L$4,IF(Z19="ENVÍO",'BASE DE LIQUIDACION 2025'!$K$4,AC19*AA19+AD19*AB19)) -> 343666.88
A20: SANTA MARTA | B20: =VLOOKUP(A20,'CENTRO DE COSTOS'!A:D,4,FALSE) -> JOSE MAURICIO HERNANDEZ ROJAS | C20: =VLOOKUP(A20,'CENTRO DE COSTOS'!A:D,2,FALSE) -> 0004-0001 | D20: 47001 | E20: 2261133 | F20: FO-25-1048128 | G20: 45813.644 | H20: 45814.689 | I20: MAGDALENA | J20: SANTA MARTA | K20: BARRIO CENTRO SANTA MARTA 11 | L20: 40613 | M20: ORDEN DE CAMBIO | N20: PUBLICIDAD | O20: AVISO EXTERIOR | P20: REDEBAN | Q20: CB UNO A UNO | R20: CB UNO A UNO | S20: EJECUTADO_EXITOSO | T20: EJECUTADO EXITOSO | U20: 06/06/2025 SE REALIZA REUBICACIÓN DE ANUNCIO EXTERIOR, YA QUE EL INQUILINO DE LA VIVIENDA DE ARRIBA LE HABÍA RETIRADO EL LETRERO PORQUE LE DAÑABA LA FACHADA SE REUBICA EL ANUNCIO EN EL ÚNICO SITIO DONDE SE PUEDE ACOMODAR EN EL LOCAL Y QUE NO ESTORBE CERRAR | V20: THOMAS CAMPO SIGIFREDO SEGUNDO | W20: 0 | X20: TIPO I | Y20: =VLOOKUP(D20,TIPOLOGIA!A:E,5,0) -> TERRESTRE | Z20: VISITA_TÉCNICA | AA20: 1 | AB20: 1 | AC20: =IF(OR(Z20="SOPORTE_TELEFÓNICO",Z20="ENVÍO"),0,IF(X20="TIPO I",'BASE DE LIQUIDACION 2025'!$I$4,IF(X20="TIPO II",'BASE DE LIQUIDACION 2025'!$I$5,IF(X20="TIPO III",'BASE DE LIQUIDACION 2025'!$I$6,IF(X20="TIPO IV",'BASE DE LIQUIDACION 2025'!$I$7,'BASE DE LIQUIDACION 2025'!$I$8))))) -> 96001.196 | AD20: =IF(OR(Z20="SOPORTE_TELEFÓNICO",Z20="ENVÍO"),0,IF(X20="TIPO I",'BASE DE LIQUIDACION 2025'!$J$4,IF(X20="TIPO II",'BASE DE LIQUIDACION 2025'!$J$5,IF(X20="TIPO III",'BASE DE LIQUIDACION 2025'!$J$6,IF(X20="TIPO IV",'BASE DE LIQUIDACION 2025'!$J$7,'BASE DE LIQUIDACION 2025'!$J$8))))) -> 57411.974 | AE20: =IF(Z20="SOPORTE_TELEFÓNICO",'BASE DE LIQUIDACION 2025'!$L$4,IF(Z20="ENVÍO",'BASE DE LIQUIDACION 2025'!$K$4,AC20*AA20+AD20*AB20)) -> 153413.17
