Workbook
Name ACTIVIDAD: [1]Hoja2!$P$2:$P$30
Name Clientes: [2]Clientes!$A$2:$A$100
Name COORDINADOR: [1]Hoja2!$D$2:$D$30
Name Coordinadores: [3]Coordinadores!$A$2:$A$1000
Name DOCUMENTADOR: [1]Hoja2!$A$2:$A$30
Name ES: [1]Hoja2!$K$2:$K$30
Name ESS: [1]Hoja2!$K$2:$K$30
Name Estado: [2]Formulas!$K$2:$K$5000
Name ESTADOACTIVIDAD: [1]Hoja2!$M$2:$M$30
Name ESTADOSCIERRES: '[4]lista desplegable'!$CX$1:$DA$1
Name Facturacion: '[5]Listas desplegables'!$AO$1:$AR$1
Name solicitudes: '[5]Listas desplegables'!$U$1:$AF$1
Name Tecnicos: [2]Tecnicos!$A$2:$A$1000

Sheet RESUMEN
A1: LÍNEA COMUNICACIONES S.A.S | F1: FACTURACIÓN CORRESPONSALES BANCARIOS TIQUIETES AÉREOS
A2: FACTURACIÓN VISITAS FALLIDAS CORRESPONSALES BANCARIOS | F2: =A3 -> JUNIO 2025
A3: JUNIO 2025
F4: CONCEPTOS | G4: TRAYECTOS | H4: TOTAL | I4: % ADMINISTRACIÓN | J4: TOTAL
A5: CONCEPTOS | B5: CANT | D5: TOTAL | I5: =H5*0.12 -> 0 | J5: =H5+I5 -> 0
A6: =CONCATENATE("CIERRES NO EXITOSOS ",A3) -> CIERRES NO EXITOSOS JUNIO 2025 | B6: =COUNTA(CIERRES!A:A)-1 -> 90 | D6: =CIERRES!AE92 -> 10083278 | I6: =H6*0.12 -> 0 | J6: =H6+I6 -> 0
A7: TIQUETES | B7: 0 | D7: =J10 -> 0 | I7: =H7*0.12 -> 0 | J7: =H7+I7 -> 0
A8: SUBTOTAL | D8: =SUM(D6:D7) -> 10083278
A9: IVA | D9: =D8*0.19 -> 1915822.8
A10: TOTAL | D10: =SUM(D8:D9) -> 11999101 | F10: TOTAL | H10: =SUM(H5:H7) -> 0 | I10: =SUM(I5:I7) -> 0 | J10: =SUM(J5:J7) -> 0

Sheet BASE DE LIQUIDACION 2025
A1: CIERRE CB - VISITAS FALLIDAS O CIERRES NO EXITOSOS TARIFAS 2024 | D1: Incremento 2025
A2: Tipificación | B2: Descripción | C2: Tarifa | D2: 0.052
A3: Tipo I | B3: Metropolitano | C3: =42357*(1+$D$2) -> 44559.564
A4: Tipo II | B4: Hasta 3 horas | C4: =127767*(1+$D$2) -> 134410.88
A5: Tipo III | B5: De 3 a 5 horas | C5: =211886*(1+$D$2) -> 222904.07
A6: Tipo IV | B6: Más de 5 horas | C6: =441834*(1+$D$2) -> 464809.37
A7: Trayecto Especial | B7: No incluye valor del Tiquete | C7: Valor de actividad Tipo IV + Valor tiquete aéreo (o fluvial) + 12% administración)
A9: Gestión telefonica | B9: =36031*(1+$D$2) -> 37904.612

Sheet Tabla Dinámica
A3: COORDINADOR | B3: CENTRO DE COSTOS LINEACOM | C3: % | D3: Suma de VALOR TOTAL2 | E3: NOMBRE CC
A4: DIEGO FERNANDO HENAO CARDONA | B4: 0004-0002 | C4: 0.025927543 | D4: 261434.62 | E4: =VLOOKUP(B4,'CENTRO DE COSTOS'!B:C,2,0) -> Redeban Eje Cafetero (Pereira)
B5: 0004-0003 | C5: 0.17909631 | D5: 1805877.9 | E5: =VLOOKUP(B5,'CENTRO DE COSTOS'!B:C,2,0) -> Redeban Suroccidente (Cali)
A6: JOSE MAURICIO HERNANDEZ ROJAS | B6: 0004-0001 | C6: 0.24191066 | D6: 2439252.4 | E6: =VLOOKUP(B6,'CENTRO DE COSTOS'!B:C,2,0) -> Redeban Costa (Barranqullla)
A7: JUAN SEBASTIÁN RÍOS CASTRILLÓN | B7: 0004-0005 | C7: 0.11496876 | D7: 1159261.9 | E7: =VLOOKUP(B7,'CENTRO DE COSTOS'!B:C,2,0) -> Redeban Noroccidente (Medellín)
A8: KEVIN ALEXIS CORZO BUSTOS | B8: 0004-0007 | C8: 0.22684054 | D8: 2287296.3 | E8: =VLOOKUP(B8,'CENTRO DE COSTOS'!B:C,2,0) -> Redeban Oriente (Otros)
A9: MIGUEL JULIÁN HERNÁNDEZ GUARÍN | B9: 0004-0008 | C9: 0.11374433 | D9: 1146915.6 | E9: =VLOOKUP(B9,'CENTRO DE COSTOS'!B:C,2,0) -> Redeban Santander
A10: WILLIAM ASDRUBAL ROZO ROZO | B10: 0004-0004 | C10: 0.097511859 | D10: 983239.18 | E10: =VLOOKUP(B10,'CENTRO DE COSTOS'!B:C,2,0) -> Redeban Centro ( Bogotá)
A11: Total general | C11: 1 | D11: 10083278

Sheet CIERRES
A1: Ciudad Sede | B1: COORDINADOR | C1: CENTRO DE COSTOS LINEACOM | D1: Código DANE | E1: TA | F1: FO | G1: Fecha Asignación a Línea Comunicaciones (DD/MM/AAAA) | H1: Fecha del cierre del ticket (DD/MM/AAAA) | I1: Departamento | J1: Ciudad | K1: Nmbre del cb | L1: CB | M1: TIPO DE ACTIVIDAD | N1: SOLICITUD | O1: DESCRIPCIÓN | P1: RED | Q1: FORMATO | R1: CADENA | S1: ESTADO | T1: CAUSAL | U1: OBSERVACIÓN | V1: TECNICO | W1: TERMINAL | X1: TIPOLOGIA | Y1: TIPO DE TRAYECTO | Z1: FORMA DE ATENCIÓN | AA1: SERIAL / PLACA- GUIA | AB1: LECTOR | AC1: Dias de visita | AD1: VALOR ACTIVIDAD | AE1: VALOR TOTAL
A2: PASTO | B2: =VLOOKUP(A2,'CENTRO DE COSTOS'!A:D,4,FALSE) -> DIEGO FERNANDO HENAO CARDONA | C2: =VLOOKUP(A2,'CENTRO DE COSTOS'!A:C,2,FALSE) -> 0004-0003 | D2: 52110 | E2: TA-25-680336 | F2: FO-25-1006058 | G2: 45805.551 | H2: 45810.611 | I2: NARIÑO | J2: BUESACO | K2: DISTRICOL MISCELANEA, VARIEDAD | L2: 44480 | M2: ORDEN DE CAMBIO | N2: CIERRE | O2: CIERRE | P2: REDEBAN | Q2: AGREGADOR | R2: DISTRICOL | S2: NO_EXITOSO | T2: CB NO ENTREGA EQUIPO | U2: 02-06-2025 SOPORTE TELEFÓNICO: SE LLAMA AL CONTACTO E INDICA QUE NO AH SOLITARIO EL CIERRE DEL CORRESPONSAL. | V2: BOLAÑOS TABORDA JORGE ENRIQUE | W2: 0 | X2: TIPO II | Y2: =VLOOKUP(D2,TIPOLOGIAS!A:F,5,0) -> TERRESTRE | Z2: SOPORTE_TELEFÓNICO | AA2: 0 | AB2: 0 | AC2: 0 | AD2: =IF(AND(Z2="SOPORTE_TELEFÓNICO",OR(T2="SIN CONTACTO CON EL CB",T2="NÚMEROS DE CONTACTO ERRADOS")),0,IF(Z2="SOPORTE_TELEFÓNICO",'BASE DE LIQUIDACION 2025'!$B$9,IF(X2="TIPO I",'BASE DE LIQUIDACION 2025'!$C$3,IF(X2="TIPO II",'BASE DE LIQUIDACION 2025'!$C$4,IF(X2="TIPO III",'BASE DE LIQUIDACION 2025'!$C$5,'BASE DE LIQUIDACION 2025'!$C$6))))) -> 37904.612 | AE2: =IF(Z2="SOPORTE_TELEFÓNICO",AD2,CIERRES!AC2*CIERRES!AD2) -> 37904.612
A3: PASTO | B3: =VLOOKUP(A3,'CENTRO DE COSTOS'!A:D,4,FALSE) -> DIEGO FERNANDO HENAO CARDONA | C3: =VLOOKUP(A3,'CENTRO DE COSTOS'!A:C,2,FALSE) -> 0004-0003 | D3: 52110 | E3: TA-25-682391 | F3: FO-25-1011023 | G3: 45806.485 | H3: 45810.619 | I3: NARIÑO | J3: BUESACO | K3: BARRIO GGT SANTA MARIA BUESACO | L3: 78244 | M3: ORDEN DE CAMBIO | N3: CIERRE | O3: CIERRE | P3: REDEBAN | Q3: CB UNO A UNO | R3: CB UNO A UNO | S3: NO_EXITOSO | T3: CB NO ENTREGA EQUIPO | U3: 02-06-2025 SOPORTE TELEFÓNICO: CLIENTE INDICA QUE NO AH SOLICITADO EL CIERRE DEL CORREPONSAL. | V3: BOLAÑOS TABORDA JORGE ENRIQUE | W3: 0 | X3: TIPO II | Y3: =VLOOKUP(D3,TIPOLOGIAS!A:F,5,0) -> TERRESTRE | Z3: SOPORTE_TELEFÓNICO | AA3: 0 | AB3: 0 | AC3: 0 | AD3: =IF(AND(Z3="SOPORTE_TELEFÓNICO",OR(T3="SIN CONTACTO CON EL CB",T3="NÚMEROS DE CONTACTO ERRADOS")),0,IF(Z3="SOPORTE_TELEFÓNICO",'BASE DE LIQUIDACION 2025'!$B$9,IF(X3="TIPO I",'BASE DE LIQUIDACION 2025'!$C$3,IF(X3="TIPO II",'BASE DE LIQUIDACION 2025'!$C$4,IF(X3="TIPO III",'BASE DE LIQUIDACION 2025'!$C$5,'BASE DE LIQUIDACION 2025'!$C$6))))) -> 37904.612 | AE3: =IF(Z3="SOPORTE_TELEFÓNICO",AD3,CIERRES!AC3*CIERRES!AD3) -> 37904.612
A4: NEIVA | B4: =VLOOKUP(A4,'CENTRO DE COSTOS'!A:D,4,FALSE) -> KEVIN ALEXIS CORZO BUSTOS | C4: =VLOOKUP(A4,'CENTRO DE COSTOS'!A:C,2,FALSE) -> 0004-0007 | D4: 18460 | E4: TA-25-673749 | F4: FO-25-992079 | G4: 45803.534 | H4: 45811.345 | I4: CAQUETA | J4: MILAN | K4: DISTRICOL DROG MUNDO FARMACO | L4: 57007 | M4: ORDEN DE CAMBIO | N4: CIERRE | O4: CIERRE | P4: REDEBAN | Q4: AGREGADOR | R4: DISTRICOL | S4: NO_EXITOSO | T4: CB NO ENTREGA EQUIPO | U4: 03-06-2025 SE LLEGA A LA DIRECCIÓN INDICANDA PERO COMERCIO SE ENCUENTRA CERRADO, SE LLAMA AL CLIENTE Y MANIFIESTA QUE SE ENCUENTRA HOSPITALIZADA EN LA CLÍNICA DE FLORENCIA Y NO TIENE QUIEN HAGA LA ENTREGA DE LOS EQUIPOS, INDICA QUE CUANDO SALGA DE LA HOSPITALIZACIÓN LLAMARÁ PARA SOLICITAR LA ENTREGA DE LOS EQUIPOS. | V4: BERMUDEZ SANCHEZ JOSE NEYBER | W4: XPRZZ673 | X4: TIPO IV | Y4: =VLOOKUP(D4,TIPOLOGIAS!A:F,5,0) -> TERRESTRE | Z4: VISITA_TÉCNICA | AA4: 0 | AB4: 0 | AC4: 1 | AD4: =IF(AND(Z4="SOPORTE_TELEFÓNICO",OR(T4="SIN CONTACTO CON EL CB",T4="NÚMEROS DE CONTACTO ERRADOS")),0,IF(Z4="SOPORTE_TELEFÓNICO",'BASE DE LIQUIDACION 2025'!$B$9,IF(X4="TIPO I",'BASE DE LIQUIDACION 2025'!$C$3,IF(X4="TIPO II",'BASE DE LIQUIDACION 2025'!$C$4,IF(X4="TIPO III",'BASE DE LIQUIDACION 2025'!$C$5,'BASE DE LIQUIDACION 2025'!$C$6))))) -> 464809.37 | AE4: =IF(Z4="SOPORTE_TELEFÓNICO",AD4,CIERRES!AC4*CIERRES!AD4) -> 464809.37
A5: BOGOTA | B5: =VLOOKUP(A5,'CENTRO DE COSTOS'!A:D,4,FALSE) -> WILLIAM ASDRUBAL ROZO ROZO | C5: =VLOOKUP(A5,'CENTRO DE COSTOS'!A:C,2,FALSE) -> 0004-0004 | D5: 11001 | E5: TA-25-686012 | F5: FO-25-1018582 | G5: 45807.653 | H5: 45811.636 | I5: CUNDINAMARCA | J5: BOGOTA | K5: BARRIO NORMANDIA II BOGOTA | L5: 13548 | M5: ORDEN DE CAMBIO | N5: CIERRE | O5: RECUPERACION DE EQUIPOS | P5: REDEBAN | Q5: CB UNO A UNO | R5: CB UNO A UNO | S5: NO_EXITOSO | T5: CB NO ENTREGA EQUIPO | U5: 03-06-2025 DIRECCIÓN NO EXISTE, SE SE TIENE CONTACTO CON EL COMERCIO VÍA TELEFÓNICA EL SEÑOR FABIO INDICA QUE NO SE ENCUENTRA EN LA CIUDAD DE BOGOTÁ. | V5: GARCIA PASTRANA KEVIN FERNANDO | W5: 0 | X5: TIPO I | Y5: =VLOOKUP(D5,TIPOLOGIAS!A:F,5,0) -> TERRESTRE | Z5: VISITA_TÉCNICA | AA5: 0 | AB5: 0 | AC5: 1 | AD5: =IF(AND(Z5="SOPORTE_TELEFÓNICO",OR(T5="SIN CONTACTO CON EL CB",T5="NÚMEROS DE CONTACTO ERRADOS")),0,IF(Z5="SOPORTE_TELEFÓNICO",'BASE DE LIQUIDACION 2025'!$B$9,IF(X5="TIPO I",'BASE DE LIQUIDACION 2025'!$C$3,IF(X5="TIPO II",'BASE DE LIQUIDACION 2025'!$C$4,IF(X5="TIPO III",'BASE DE LIQUIDACION 2025'!$C$5,'BASE DE LIQUIDACION 2025'!$C$6))))) -> 44559.564 | AE5: =IF(Z5="SOPORTE_TELEFÓNICO",AD5,CIERRES!AC5*CIERRES!AD5) -> 44559.564
A6: NEIVA | B6: =VLOOKUP(A6,'CENTRO DE COSTOS'!A:D,4,FALSE) -> KEVIN ALEXIS CORZO BUSTOS | C6: =VLOOKUP(A6,'CENTRO DE COSTOS'!A:C,2,FALSE) -> 0004-0007 | D6: 18150 | E6: TA-25-682373 | F6: FO-25-1010988 | G6: 45806.485 | H6: 45811.685 | I6: CAQUETA | J6: CARTAGENA DEL CHAIRA | K6: BARRIO BELLA VISTA CARTAGENA DEL CHAIRA | L6: 76062 | M6: ORDEN DE CAMBIO | N6: CIERRE | O6: CIERRE | P6: REDEBAN | Q6: CB UNO A UNO | R6: CB UNO A UNO | S6: NO_EXITOSO | T6: CB NO ENTREGA EQUIPO | U6: 03-06-2025 SE REALIZA VISITA AL CORRESPONSAL Y CLIENTE MANIFIESTA QUE NO PERMITE EL RETIRO DEL CORRESPONSAL YA QUE SE ENCUENTRA EN UNA GESTIÓN DE LA FACTURACION ELECTRÓNICA CON LA ENTIDAD Y ESPERA UNA RESPUESTA POR PARTE DEL BANCO, YA QUE ELLOS NO HAN SOLICITADO EL CIERRE DEL CORRESPONSAL. | V6: BERMUDEZ SANCHEZ JOSE NEYBER | W6: FA0BZ311 | X6: TIPO IV ESPECIAL | Y6: =VLOOKUP(D6,TIPOLOGIAS!A:F,5,0) -> TERRESTRE | Z6: VISITA_TÉCNICA | AA6: 0 | AB6: 0 | AC6: 1 | AD6: =IF(AND(Z6="SOPORTE_TELEFÓNICO",OR(T6="SIN CONTACTO CON EL CB",T6="NÚMEROS DE CONTACTO ERRADOS")),0,IF(Z6="SOPORTE_TELEFÓNICO",'BASE DE LIQUIDACION 2025'!$B$9,IF(X6="TIPO I",'BASE DE LIQUIDACION 2025'!$C$3,IF(X6="TIPO II",'BASE DE LIQUIDACION 2025'!$C$4,IF(X6="TIPO III",'BASE DE LIQUIDACION 2025'!$C$5,'BASE DE LIQUIDACION 2025'!$C$6))))) -> 464809.37 | AE6: =IF(Z6="SOPORTE_TELEFÓNICO",AD6,CIERRES!AC6*CIERRES!AD6) -> 464809.37
A7: PASTO | B7: =VLOOKUP(A7,'CENTRO DE COSTOS'!A:D,4,FALSE) -> DIEGO FERNANDO HENAO CARDONA | C7: =VLOOKUP(A7,'CENTRO DE COSTOS'!A:C,2,FALSE) -> 0004-0003 | D7: 52079 | E7: TA-25-682390 | F7: FO-25-1011020 | G7: 45806.485 | H7: 45812.355 | I7: NARIÑO | J7: BARBACOAS | K7: BARRIO CL DEL COMERCIO BARBACOAS | L7: 78063 | M7: ORDEN DE CAMBIO | N7: CIERRE | O7: CIERRE | P7: REDEBAN | Q7: CB UNO A UNO | R7: CB UNO A UNO | S7: NO_EXITOSO | T7: CB NO ENTREGA EQUIPO | U7: 04-06-2025 SE REALIZA LLAMADA TELEFONICA EL CLIENTE PARA VALIDAR CIERRE, CLIENTE INFORMA QUE NO HA SOLICITADO NINGUN CIERRE , QUE TENIA UN TEMA DE FACTURACION CON LA ENTIDAD PERO QUE YA FUE RESUELTO, POR LO TENTO NO DESEA ENTREGAR EQUIPOS, | V7: HENAO CARDONA DIEGO FERNANDO | W7: 0 | X7: TIPO IV | Y7: =VLOOKUP(D7,TIPOLOGIAS!A:F,5,0) -> TERRESTRE | Z7: SOPORTE_TELEFÓNICO | AA7: 0 | AB7: 0 | AC7: 0 | AD7: =IF(AND(Z7="SOPORTE_TELEFÓNICO",OR(T7="SIN CONTACTO CON EL CB",T7="NÚMEROS DE CONTACTO ERRADOS")),0,IF(Z7="SOPORTE_TELEFÓNICO",'BASE DE LIQUIDACION 2025'!$B$9,IF(X7="TIPO I",'BASE DE LIQUIDACION 2025'!$C$3,IF(X7="TIPO II",'BASE DE LIQUIDACION 2025'!$C$4,IF(X7="TIPO III",'BASE DE LIQUIDACION 2025'!$C$5,'BASE DE LIQUIDACION 2025'!$C$6))))) -> 37904.612 | AE7: =IF(Z7="SOPORTE_TELEFÓNICO",AD7,CIERRES!AC7*CIERRES!AD7) -> 37904.612
A8: BARRANQUILLA | B8: =VLOOKUP(A8,'CENTRO DE COSTOS'!A:D,4,FALSE) -> JOSE MAURICIO HERNANDEZ ROJAS | C8: =VLOOKUP(A8,'CENTRO DE COSTOS'!A:C,2,FALSE) -> 0004-0001 | D8: 8001 | E8: TA-25-683192 | F8: FO-25-1013175 | G8: 45806.669 | H8: 45812.43 | I8: ATLANTICO | J8: BARRANQUILLA | K8: BARRIO RIOMAR BARRANQUILLA 2 | L8: 75043 | M8: ORDEN DE CAMBIO | N8: CIERRE | O8: CIERRE | P8: REDEBAN | Q8: CB UNO A UNO | R8: CB UNO A UNO | S8: ILOCALIZADO | T8: CB CERRADO - DESOCUPADO | U8: 04-06-2025 SE REALIZA VISITA AL COMERCIO PARA REALIZAR EL CIERRE DEL CORRESPONSAL BANCOLOMBIA PERO NO ES POSIBLE TRATO COMUNICACION CON EL NÚMERO ASOCIADO EN LA TAREA PERO NO CONTESTAN 3007345725 | V8: PEÑALOZA GUTIERREZ RAFAEL GUSTAVO | W8: 0 | X8: TIPO I | Y8: =VLOOKUP(D8,TIPOLOGIAS!A:F,5,0) -> TERRESTRE | Z8: VISITA_TÉCNICA | AA8: 0 | AB8: 0 | AC8: 1 | AD8: =IF(AND(Z8="SOPORTE_TELEFÓNICO",OR(T8="SIN CONTACTO CON EL CB",T8="NÚMEROS DE CONTACTO ERRADOS")),0,IF(Z8="SOPORTE_TELEFÓNICO",'BASE DE LIQUIDACION 2025'!$B$9,IF(X8="TIPO I",'BASE DE LIQUIDACION 2025'!$C$3,IF(X8="TIPO II",'BASE DE LIQUIDACION 2025'!$C$4,IF(X8="TIPO III",'BASE DE LIQUIDACION 2025'!$C$5,'BASE DE LIQUIDACION 2025'!$C$6))))) -> 44559.564 | AE8: =IF(Z8="SOPORTE_TELEFÓNICO",AD8,CIERRES!AC8*CIERRES!AD8) -> 44559.564
A9: BUCARAMANGA | B9: =VLOOKUP(A9,'CENTRO DE COSTOS'!A:D,4,FALSE) -> MIGUEL JULIÁN HERNÁNDEZ GUARÍN | C9: =VLOOKUP(A9,'CENTRO DE COSTOS'!A:C,2,FALSE) -> 0004-0008 | D9: 68001 | E9: TA-25-680768 | F9: FO-25-1007152 | G9: 45805.582 | H9: 45812.601 | I9: SANTANDER | J9: BUCARAMANGA | K9: BARRIO CAMPOHERMOSO BUCARAMANA | L9: 73231 | M9: ORDEN DE CAMBIO | N9: CIERRE | O9: CIERRE | P9: REDEBAN | Q9: CB UNO A UNO | R9: CB UNO A UNO | S9: NO_EXITOSO | T9: CB NO ENTREGA EQUIPO | U9: 04-06-2025 SE ESTABLECE COMUNICACIÓN CON LA SEÑORA MARIA FERNANDA VIA WHATSAPP SE LE INFORMA QUE EL BANCO DIO LA INDICACIÓN DE CERRAR ORDEN DE TRABAJO GENERADA YA QUE EL CLIENTE NO CUENTA CON DISPONIBILIDAD PARA ENTREGAR LOS EQUIPOS SE LE INFORMA QUE TAN PRONTO TENGA DISPONIBILIDAD SE COMUNIQUE CON LA LINEA 018000953344 Y SOLICITE LA RECOLECCIÓN DE LOS MISMOS | V9: BARRERA ORTEGA MARLON STWAR | W9: 0 | X9: TIPO I | Y9: =VLOOKUP(D9,TIPOLOGIAS!A:F,5,0) -> TERRESTRE | Z9: VISITA_TÉCNICA | AA9: 0 | AB9: 0 | AC9: 1 | AD9: =IF(AND(Z9="SOPORTE_TELEFÓNICO",OR(T9="SIN CONTACTO CON EL CB",T9="NÚMEROS DE CONTACTO ERRADOS")),0,IF(Z9="SOPORTE_TELEFÓNICO",'BASE DE LIQUIDACION 2025'!$B$9,IF(X9="TIPO I",'BASE DE LIQUIDACION 2025'!$C$3,IF(X9="TIPO II",'BASE DE LIQUIDACION 2025'!$C$4,IF(X9="TIPO III",'BASE DE LIQUIDACION 2025'!$C$5,'BASE DE LIQUIDACION 2025'!$C$6))))) -> 44559.564 | AE9: =IF(Z9="SOPORTE_TELEFÓNICO",AD9,CIERRES!AC9*CIERRES!AD9) -> 44559.564
A10: PEREIRA | B10: =VLOOKUP(A10,'CENTRO DE COSTOS'!A:D,4,FALSE) -> DIEGO FERNANDO HENAO CARDONA | C10: =VLOOKUP(A10,'CENTRO DE COSTOS'!A:C,2,FALSE) -> 0004-0002 | D10: 66400 | E10: TA-25-682398 | F10: FO-25-1011040 | G10: 45806.485 | H10: 45812.666 | I10: RISARALDA | J10: LA VIRGINIA | K10: LA VIRGINIA - LOS LIBERTADORES | L10: 71934 | M10: ORDEN DE CAMBIO | N10: CIERRE | O10: CIERRE | P10: REDEBAN | Q10: CB UNO A UNO | R10: CB UNO A UNO | S10: NO_EXITOSO | T10: CB NO ENTREGA EQUIPO | U10: 04-06-2025 VISITAMOS COMERCIO PERO LA PERSONA QUE ESTÁ A CARGO NO TIENE CONOCIMIENTO, NO FUE POSIBLE COMUNICARSE CON EL ADMINISTRADOR YA QUE ESTA EN UNA REUNIÓN PERO NOS INDICA QUE EL TAMPOCO DEBE TENER CONOCIMIENTO DE QUE REALIZARAN EL CIERRE DEL CORRESPONSAL, ELLOS REALIZARÁN LA VALIDACIÓN CON EL ASESOR DE LA ZONA PARA CONTINUAR CON EL CORRESPONSAL. | V10: ARROYAVE CANO MANUEL GUILLERMO | W10: LN00M144 | X10: TIPO I | Y10: =VLOOKUP(D10,TIPOLOGIAS!A:F,5,0) -> TERRESTRE | Z10: VISITA_TÉCNICA | AA10: 0 | AB10: 0 | AC10: 1 | AD10: =IF(AND(Z10="SOPORTE_TELEFÓNICO",OR(T10="SIN CONTACTO CON EL CB",T10="NÚMEROS DE CONTACTO ERRADOS")),0,IF(Z10="SOPORTE_TELEFÓNICO",'BASE DE LIQUIDACION 2025'!$B$9,IF(X10="TIPO I",'BASE DE LIQUIDACION 2025'!$C$3,IF(X10="TIPO II",'BASE DE LIQUIDACION 2025'!$C$4,IF(X10="TIPO III",'BASE DE LIQUIDACION 2025'!$C$5,'BASE DE LIQUIDACION 2025'!$C$6))))) -> 44559.564 | AE10: =IF(Z10="SOPORTE_TELEFÓNICO",AD10,CIERRES!AC10*CIERRES!AD10) -> 44559.564
A11: VILLAVICENCIO | B11: =VLOOKUP(A11,'CENTRO DE COSTOS'!A:D,4,FALSE) -> KEVIN ALEXIS CORZO BUSTOS | C11: =VLOOKUP(A11,'CENTRO DE COSTOS'!A:C,2,FALSE) -> 0004-0007 | D11: 50001 | E11: TA-25-682444 | F11: FO-25-1011076 | G11: 45806.485 | H11: 45812.698 | I11: META | J11: VILLAVICENCIO | K11: BARRIO MANANTIAL VILLAVICENCIO | L11: 69923 | M11: ORDEN DE CAMBIO | N11: CIERRE | O11: RECUPERACION DE EQUIPOS | P11: REDEBAN | Q11: CB UNO A UNO | R11: CB UNO A UNO | S11: ILOCALIZADO | T11: CB CERRADO - DESOCUPADO | U11: 04-06-2025 SE REALIZA VISITA AL PUNTO Y COMERCIO SE ENCUENTRA CERRADO, NO ES POSIBLE CONTACTO TELEFONICO CON EL CLIENTE | V11: PEDREROS CONTRERAS MICHAEL STEVENS | W11: 0 | X11: TIPO I | Y11: =VLOOKUP(D11,TIPOLOGIAS!A:F,5,0) -> TERRESTRE | Z11: VISITA_TÉCNICA | AA11: 0 | AB11: 0 | AC11: 1 | AD11: =IF(AND(Z11="SOPORTE_TELEFÓNICO",OR(T11="SIN CONTACTO CON EL CB",T11="NÚMEROS DE CONTACTO ERRADOS")),0,IF(Z11="SOPORTE_TELEFÓNICO",'BASE DE LIQUIDACION 2025'!$B$9,IF(X11="TIPO I",'BASE DE LIQUIDACION 2025'!$C$3,IF(X11="TIPO II",'BASE DE LIQUIDACION 2025'!$C$4,IF(X11="TIPO III",'BASE DE LIQUIDACION 2025'!$C$5,'BASE DE LIQUIDACION 2025'!$C$6))))) -> 44559.564 | AE11: =IF(Z11="SOPORTE_TELEFÓNICO",AD11,CIERRES!AC11*CIERRES!AD11) -> 44559.564
A12: MONTERIA | B12: =VLOOKUP(A12,'CENTRO DE COSTOS'!A:D,4,FALSE) -> JOSE MAURICIO HERNANDEZ ROJAS | C12: =VLOOKUP(A12,'CENTRO DE COSTOS'!A:C,2,FALSE) -> 0004-0001 | D12: 23001 | E12: TA-25-682386 | F12: FO-25-1011009 | G12: 45806.485 | H12: 45812.76 | I12: CORDOBA | J12: MONTERIA | K12: BARRIO CENTRO MONTERIA | L12: 74413 | M12: ORDEN DE CAMBIO | N12: CIERRE | O12: CIERRE | P12: REDEBAN | Q12: CB UNO A UNO | R12: CB UNO A UNO | S12: NO_EXITOSO | T12: CB NO ENTREGA EQUIPO | U12: 04-06-2025 SE LLEGA AL SITIO Y NOS INFORMAN QUE LA PERSONA ENCARGADA NO SE ENCUENTRA, QUE REGRESEMOS EN OTRA OCASIÓN PARA EFECTUAR LA ENTREGA. NOS ATIENDE MARÍA ALEJANDRA ORTEGA SÁNCHEZ. | V12: CASSIANI PEREZ RAUL RAMIRO | W12: 0 | X12: TIPO I | Y12: =VLOOKUP(D12,TIPOLOGIAS!A:F,5,0) -> TERRESTRE | Z12: VISITA_TÉCNICA | AA12: 0 | AB12: 0 | AC12: 1 | AD12: =IF(AND(Z12="SOPORTE_TELEFÓNICO",OR(T12="SIN CONTACTO CON EL CB",T12="NÚMEROS DE CONTACTO ERRADOS")),0,IF(Z12="SOPORTE_TELEFÓNICO",'BASE DE LIQUIDACION 2025'!$B$9,IF(X12="TIPO I",'BASE DE LIQUIDACION 2025'!$C$3,IF(X12="TIPO II",'BASE DE LIQUIDACION 2025'!$C$4,IF(X12="TIPO III",'BASE DE LIQUIDACION 2025'!$C$5,'BASE DE LIQUIDACION 2025'!$C$6))))) -> 44559.564 | AE12: =IF(Z12="SOPORTE_TELEFÓNICO",AD12,CIERRES!AC12*CIERRES!AD12) -> 44559.564
A13: CALI | B13: =VLOOKUP(A13,'CENTRO DE COSTOS'!A:D,4,FALSE) -> DIEGO FERNANDO HENAO CARDONA | C13: =VLOOKUP(A13,'CENTRO DE COSTOS'!A:C,2,FALSE) -> 0004-0003 | D13: 19001 | E13: TA-25-682381 | F13: FO-25-1011001 | G13: 45806.485 | H13: 45813.636 | I13: CAUCA | J13: POPAYAN | K13: BARRIO BELLAVISTA POPAYAN 1 | L13: 76647 | M13: ORDEN DE CAMBIO | N13: CIERRE | O13: CIERRE | P13: REDEBAN | Q13: CB UNO A UNO | R13: CB UNO A UNO | S13: ILOCALIZADO | T13: CB CERRADO - DESOCUPADO | U13: 05-06-2025 SE REALIZA LLAMADA CELULAR CB NO RESPONDE SE LLEGA AL SITIO SE ENCUENTRA CERRADO COMERCIO | V13: GIMBUEL LASSO LUIS GERMAN | W13: LA2ZZ430 | X13: TIPO III | Y13: =VLOOKUP(D13,TIPOLOGIAS!A:F,5,0) -> TERRESTRE | Z13: VISITA_TÉCNICA | AA13: 0 | AB13: 0 | AC13: 1 | AD13: =IF(AND(Z13="SOPORTE_TELEFÓNICO",OR(T13="SIN CONTACTO CON EL CB",T13="NÚMEROS DE CONTACTO ERRADOS")),0,IF(Z13="SOPORTE_TELEFÓNICO",'BASE DE LIQUIDACION 2025'!$B$9,IF(X13="TIPO I",'BASE DE LIQUIDACION 2025'!$C$3,IF(X13="TIPO II",'BASE DE LIQUIDACION 2025'!$C$4,IF(X13="TIPO III",'BASE DE LIQUIDACION 2025'!$C$5,'BASE DE LIQUIDACION 2025'!$C$6))))) -> 222904.07 | AE13: =IF(Z13="SOPORTE_TELEFÓNICO",AD13,CIERRES!AC13*CIERRES!AD13) -> 222904.07
A14: TUNJA | B14: =VLOOKUP(A14,'CENTRO DE COSTOS'!A:D,4,FALSE) -> MIGUEL JULIÁN HERNÁNDEZ GUARÍN | C14: =VLOOKUP(A14,'CENTRO DE COSTOS'!A:C,2,FALSE) -> 0004-0008 | D14: 15759 | E14: TA-25-716434 | F14: FO-25-1049138 | G14: 45813.674 | H14: 45814.521 | I14: BOYACA | J14: SOGAMOSO | K14: BARRIO EL LIBERTADOR | L14: 25666 | M14: ORDEN DE CAMBIO | N14: CIERRE | O14: CIERRE | P14: REDEBAN | Q14: CB UNO A UNO | R14: CB UNO A UNO | S14: SOLICITUD_CANCELADA | T14: CANCELADO POR LA ENTIDAD | U14: 06-06-2025 SE CIERRA ORDEN , SE NO SE ATIENDE ACTIVIDAD , SE CANCELA ORDEN POR SOLICITUD DE LA ENTIDAD | V14: ALVARADO MORENO CRISTHIAN | W14: 0 | X14: TIPO II | Y14: =VLOOKUP(D14,TIPOLOGIAS!A:F,5,0) -> TERRESTRE | Z14: SOPORTE_TELEFÓNICO | AA14: 0 | AB14: 0 | AC14: 0 | AD14: =IF(AND(Z14="SOPORTE_TELEFÓNICO",OR(T14="SIN CONTACTO CON EL CB",T14="NÚMEROS DE CONTACTO ERRADOS")),0,IF(Z14="SOPORTE_TELEFÓNICO",'BASE DE LIQUIDACION 2025'!$B$9,IF(X14="TIPO I",'BASE DE LIQUIDACION 2025'!$C$3,IF(X14="TIPO II",'BASE DE LIQUIDACION 2025'!$C$4,IF(X14="TIPO III",'BASE DE LIQUIDACION 2025'!$C$5,'BASE DE LIQUIDACION 2025'!$C$6))))) -> 37904.612 | AE14: =IF(Z14="SOPORTE_TELEFÓNICO",AD14,CIERRES!AC14*CIERRES!AD14) -> 37904.612
A15: BOGOTA | B15: =VLOOKUP(A15,'CENTRO DE COSTOS'!A:D,4,FALSE) -> WILLIAM ASDRUBAL ROZO ROZO | C15: =VLOOKUP(A15,'CENTRO DE COSTOS'!A:C,2,FALSE) -> 0004-0004 | D15: 11001 | E15: TA-25-716462 | F15: FO-25-1049196 | G15: 45813.674 | H15: 45814.57 | I15: CUNDINAMARCA | J15: BOGOTA | K15: BARRIO MINUTO DE DIOS BOGOTA 8 | L15: 66835 | M15: ORDEN DE CAMBIO | N15: CIERRE | O15: CIERRE | P15: REDEBAN | Q15: CB UNO A UNO | R15: CB UNO A UNO | S15: ILOCALIZADO | T15: CB CERRADO - DESOCUPADO | U15: 06-06-2025 SE REALIZS VISITA A CB PARA REALIZAR CIERRE SE ENCUENTRA CERRADO ,SE INTENTA COMUNICAR CON CLIENTE NO CONTESTAN | V15: GALINDO ROJAS LUIS FELIPE | W15: 0 | X15: TIPO I | Y15: =VLOOKUP(D15,TIPOLOGIAS!A:F,5,0) -> TERRESTRE | Z15: VISITA_TÉCNICA | AA15: 0 | AB15: 0 | AC15: 1 | AD15: =IF(AND(Z15="SOPORTE_TELEFÓNICO",OR(T15="SIN CONTACTO CON EL CB",T15="NÚMEROS DE CONTACTO ERRADOS")),0,IF(Z15="SOPORTE_TELEFÓNICO",'BASE DE LIQUIDACION 2025'!$B$9,IF(X15="TIPO I",'BASE DE LIQUIDACION 2025'!$C$3,IF(X15="TIPO II",'BASE DE LIQUIDACION 2025'!$C$4,IF(X15="TIPO III",'BASE DE LIQUIDACION 2025'!$C$5,'BASE DE LIQUIDACION 2025'!$C$6))))) -> 44559.564 | AE15: =IF(Z15="SOPORTE_TELEFÓNICO",AD15,CIERRES!AC15*CIERRES!AD15) -> 44559.564
A16: MONTERIA | B16: =VLOOKUP(A16,'CENTRO DE COSTOS'!A:D,4,FALSE) -> JOSE MAURICIO HERNANDEZ ROJAS | C16: =VLOOKUP(A16,'CENTRO DE COSTOS'!A:C,2,FALSE) -> 0004-0001 | D16: 23001 | E16: TA-25-716443 | F16: FO-25-1049157 | G16: 45813.674 | H16: 45814.597 | I16: CORDOBA | J16: MONTERIA | K16: BARRIO EL DORADO MONTERIA CORD | L16: 72141 | M16: ORDEN DE CAMBIO | N16: CIERRE | O16: CIERRE | P16: REDEBAN | Q16: CB UNO A UNO | R16: CB UNO A UNO | S16: NO_EXITOSO | T16: CB NO ENTREGA EQUIPO | U16: 06-06-2025 SE LLEGA A CB, IMFOAM QUE NO ESTÁ LA PERSONA ENCARGADA DEL CB, POR ESE MOTIVO NO PERMITEN EL RETIRO DE LOS EQUIPOS DEL PUNTO | V16: COGOLLO ROSSO CAMILO ANDRES | W16: NN00N610 | X16: TIPO I | Y16: =VLOOKUP(D16,TIPOLOGIAS!A:F,5,0) -> TERRESTRE | Z16: VISITA_TÉCNICA | AA16: 0 | AB16: 0 | AC16: 1 | AD16: =IF(AND(Z16="SOPORTE_TELEFÓNICO",OR(T16="SIN CONTACTO CON EL CB",T16="NÚMEROS DE CONTACTO ERRADOS")),0,IF(Z16="SOPORTE_TELEFÓNICO",'BASE DE LIQUIDACION 2025'!$B$9,IF(X16="TIPO I",'BASE DE LIQUIDACION 2025'!$C$3,IF(X16="TIPO II",'BASE DE LIQUIDACION 2025'!$C$4,IF(X16="TIPO III",'BASE DE LIQUIDACION 2025'!$C$5,'BASE DE LIQUIDACION 2025'!$C$6))))) -> 44559.564 | AE16: =IF(Z16="SOPORTE_TELEFÓNICO",AD16,CIERRES!AC16*CIERRES!AD16) -> 44559.564
A17: CALI | B17: =VLOOKUP(A17,'CENTRO DE COSTOS'!A:D,4,FALSE) -> DIEGO FERNANDO HENAO CARDONA | C17: =VLOOKUP(A17,'CENTRO DE COSTOS'!A:C,2,FALSE) -> 0004-0003 | D17: 19532 | E17: TA-25-683193 | F17: FO-25-1013178 | G17: 45806.669 | H17: 45814.64 | I17: CAUCA | J17: PATIA | K17: BARRIO PATIA PATIA | L17: 77803 | M17: ORDEN DE CAMBIO | N17: CIERRE | O17: CIERRE | P17: REDEBAN | Q17: CB UNO A UNO | R17: CB UNO A UNO | S17: ILOCALIZADO | T17: CB CERRADO - DESOCUPADO | U17: 06-06-2025 SE REALIZA LLAMADA CELULAR CB NO RESPONDE SE ENCUENTRA COMERCIO CERRADO | V17: GIMBUEL LASSO LUIS GERMAN | W17: 10OZZ064 | X17: TIPO IV | Y17: =VLOOKUP(D17,TIPOLOGIAS!A:F,5,0) -> TERRESTRE | Z17: VISITA_TÉCNICA | AA17: 0 | AB17: 0 | AC17: 1 | AD17: =IF(AND(Z17="SOPORTE_TELEFÓNICO",OR(T17="SIN CONTACTO CON EL CB",T17="NÚMEROS DE CONTACTO ERRADOS")),0,IF(Z17="SOPORTE_TELEFÓNICO",'BASE DE LIQUIDACION 2025'!$B$9,IF(X17="TIPO I",'BASE DE LIQUIDACION 2025'!$C$3,IF(X17="TIPO II",'BASE DE LIQUIDACION 2025'!$C$4,IF(X17="TIPO III",'BASE DE LIQUIDACION 2025'!$C$5,'BASE DE LIQUIDACION 2025'!$C$6))))) -> 464809.37 | AE17: =IF(Z17="SOPORTE_TELEFÓNICO",AD17,CIERRES!AC17*CIERRES!AD17) -> 464809.37
A18: BOGOTA | B18: =VLOOKUP(A18,'CENTRO DE COSTOS'!A:D,4,FALSE) -> WILLIAM ASDRUBAL ROZO ROZO | C18: =VLOOKUP(A18,'CENTRO DE COSTOS'!A:C,2,FALSE) -> 0004-0004 | D18: 11001 | E18: TA-25-716460 | F18: FO-25-1049191 | G18: 45813.674 | H18: 45814.653 | I18: CUNDINAMARCA | J18: BOGOTA | K18: BARRIO TIERRA BUENA KENNEDY BO | L18: 59263 | M18: ORDEN DE CAMBIO | N18: CIERRE | O18: CIERRE | P18: REDEBAN | Q18: CB UNO A UNO | R18: CB UNO A UNO | S18: ILOCALIZADO | T18: CB CERRADO - DESOCUPADO | U18: 06-06-2025 SE LLEGA A SITIO SE LLAMAN A LOS NÚMEROS DE CONTACTO NO CONTESTAN SE VÁLIDA EN PORTERÍA NO RESPONDEN NI DAN INFORMACIÓN, ESTO DEBIDO A QUE NO EXISTE CORRESPONSAL BANCARIO A LA VISTA. | V18: INFANTE SIERRA MANUEL FERNANDO | W18: 0 | X18: TIPO I | Y18: =VLOOKUP(D18,TIPOLOGIAS!A:F,5,0) -> TERRESTRE | Z18: VISITA_TÉCNICA | AA18: 0 | AB18: 0 | AC18: 1 | AD18: =IF(AND(Z18="SOPORTE_TELEFÓNICO",OR(T18="SIN CONTACTO CON EL CB",T18="NÚMEROS DE CONTACTO ERRADOS")),0,IF(Z18="SOPORTE_TELEFÓNICO",'BASE DE LIQUIDACION 2025'!$B$9,IF(X18="TIPO I",'BASE DE LIQUIDACION 2025'!$C$3,IF(X18="TIPO II",'BASE DE LIQUIDACION 2025'!$C$4,IF(X18="TIPO III",'BASE DE LIQUIDACION 2025'!$C$5,'BASE DE LIQUIDACION 2025'!$C$6))))) -> 44559.564 | AE18: =IF(Z18="SOPORTE_TELEFÓNICO",AD18,CIERRES!AC18*CIERRES!AD18) -> 44559.564
A19: NEIVA | B19: =VLOOKUP(A19,'CENTRO DE COSTOS'!A:D,4,FALSE) -> KEVIN ALEXIS CORZO BUSTOS | C19: =VLOOKUP(A19,'CENTRO DE COSTOS'!A:C,2,FALSE) -> 0004-0007 | D19: 41001 | E19: TA-25-716446 | F19: FO-25-1049163 | G19: 45813.674 | H19: 45814.653 | I19: HUILA | J19: NEIVA | K19: BARRIO ALTICO NEIVA 3 | L19: 76201 | M19: ORDEN DE CAMBIO | N19: CIERRE | O19: CIERRE | P19: REDEBAN | Q19: CB UNO A UNO | R19: CB UNO A UNO | S19: NO_EXITOSO | T19: CB NO ENTREGA EQUIPO | U19: 06-06-2025 SE REALIZA VISITA AL PUNTO , PERSONA ENCARGADA INDICA QUE NO HA HECHO SOLICITUD PARA EL CIERRE DEL PUNTO, INDICA QUE SE VA A COMUNICAR CON EL BANCO PARA VALIDAR, POR AHORA NO ENTREGA EQUIPOS, CIERRE FALLIDO . | V19: DEVIA REINOSO JUAN CARLOS | W19: FA0GZ493 | X19: TIPO I | Y19: =VLOOKUP(D19,TIPOLOGIAS!A:F,5,0) -> TERRESTRE | Z19: VISITA_TÉCNICA | AA19: 0 | AB19: 0 | AC19: 1 | AD19: =IF(AND(Z19="SOPORTE_TELEFÓNICO",OR(T19="SIN CONTACTO CON EL CB",T19="NÚMEROS DE CONTACTO ERRADOS")),0,IF(Z19="SOPORTE_TELEFÓNICO",'BASE DE LIQUIDACION 2025'!$B$9,IF(X19="TIPO I",'BASE DE LIQUIDACION 2025'!$C$3,IF(X19="TIPO II",'BASE DE LIQUIDACION 2025'!$C$4,IF(X19="TIPO III",'BASE DE LIQUIDACION 2025'!$C$5,'BASE DE LIQUIDACION 2025'!$C$6))))) -> 44559.564 | AE19: =IF(Z19="SOPORTE_TELEFÓNICO",AD19,CIERRES!AC19*CIERRES!AD19) -> 44559.564
A20: VILLAVICENCIO | B20: =VLOOKUP(A20,'CENTRO DE COSTOS'!A:D,4,FALSE) -> KEVIN ALEXIS CORZO BUSTOS | C20: =VLOOKUP(A20,'CENTRO DE COSTOS'!A:C,2,FALSE) -> 0004-0007 | D20: 50287 | E20: TA-25-716448 | F20: FO-25-1049168 | G20: 45813.674 | H20: 45814.72 | I20: META | J20: FUENTE DE ORO | K20: BARRIO CENTRO 1 FUENTE DE ORO | L20: 34950 | M20: ORDEN DE CAMBIO | N20: CIERRE | O20: CIERRE | P20: REDEBAN | Q20: CB UNO A UNO | R20: CB UNO A UNO | S20: ILOCALIZADO | T20: CB CERRADO - DESOCUPADO | U20: 06-06-2025 SE REALIZA VISITA Y COMERCIO SE ENCUENTRA CERRADO, SE REALIZA CONTACTO TELEFONICO Y NO ES POSIBLE | V20: PEDREROS CONTRERAS MICHAEL STEVENS | W20: NONE | X20: TIPO III | Y20: =VLOOKUP(D20,TIPOLOGIAS!A:F,5,0) -> TERRESTRE | Z20: VISITA_TÉCNICA | AA20: 0 | AB20: 0 | AC20: 1 | AD20: =IF(AND(Z20="SOPORTE_TELEFÓNICO",OR(T20="SIN CONTACTO CON EL CB",T20="NÚMEROS DE CONTACTO ERRADOS")),0,IF(Z20="SOPORTE_TELEFÓNICO",'BASE DE LIQUIDACION 2025'!$B$9,IF(X20="TIPO I",'BASE DE LIQUIDACION 2025'!$C$3,IF(X20="TIPO II",'BASE DE LIQUIDACION 2025'!$C$4,IF(X20="TIPO III",'BASE DE LIQUIDACION 2025'!$C$5,'BASE DE LIQUIDACION 2025'!$C$6))))) -> 222904.07 | AE20: =IF(Z20="SOPORTE_TELEFÓNICO",AD20,CIERRES!AC20*CIERRES!AD20) -> 222904.07
A21: BUCARAMANGA | B21: =VLOOKUP(A21,'CENTRO DE COSTOS'!A:D,4,FALSE) -> MIGUEL JULIÁN HERNÁNDEZ GUARÍN | C21: =VLOOKUP(A21,'CENTRO DE COSTOS'!A:C,2,FALSE) -> 0004-0008 | D21: 68255 | E21: TA-25-719474 | F21: FO-25-1053434 | G21: 45814.458 | H21: 45814.741 | I21: SANTANDER | J21: EL PLAYON | K21: PTM EL PLAYON DAYECEL | L21: 62274 | M21: ORDEN DE CAMBIO | N21: CIERRE | O21: CIERRE | P21: REDEBAN | Q21: AGREGADOR | R21: COMCARD - PTM | S21: ILOCALIZADO | T21: CB CERRADO - DESOCUPADO | U21: 06-06-2025 SE INTENTA COMUCACION CON LA ADMINISTRADORA ELCIDA ACERO AL CELULAR 3163547179 Y WHATSAPP NO FUE POSIBLE, SE LLEGA A DIRECCIÓN CRA 8 #11-83, Y YA NO ESTÁ EL CORRESPONSAL, ADMINISTRADOR DEL LOCAL EXISTENTE, INFORMA QUE ELLOS TOMARON EL LOCAL APROXIMADAMENTE 3 MESES, QUE EL PROPIETARIO ANTERIOR SE FUE PARA EL MUNICIPIO DE RIO NEGRO, SE DEJA MENSAJE POR WHATSAPP, SE REALIZA LLAMADA TELEFÓNICA Y CLIENTE NO CONTESTA SE PROCEDE A CERRAR LA ORDEN. | V21: MARTINEZ FLOREZ DONIS ALBERTO | W21: 0 | X21: TIPO II | Y21: =VLOOKUP(D21,TIPOLOGIAS!A:F,5,0) -> TERRESTRE | Z21: VISITA_TÉCNICA | AA21: 0 | AB21: 0 | AC21: 1 | AD21: =IF(AND(Z21="SOPORTE_TELEFÓNICO",OR(T21="SIN CONTACTO CON EL CB",T21="NÚMEROS DE CONTACTO ERRADOS")),0,IF(Z21="SOPORTE_TELEFÓNICO",'BASE DE LIQUIDACION 2025'!$B$9,IF(X21="TIPO I",'BASE DE LIQUIDACION 2025'!$C$3,IF(X21="TIPO II",'BASE DE LIQUIDACION 2025'!$C$4,IF(X21="TIPO III",'BASE DE LIQUIDACION 2025'!$C$5,'BASE DE LIQUIDACION 2025'!$C$6))))) -> 134410.88 | AE21: =IF(Z21="SOPORTE_TELEFÓNICO",AD21,CIERRES!AC21*CIERRES!AD21) -> 134410.88
A22: MANIZALES | B22: =VLOOKUP(A22,'CENTRO DE COSTOS'!A:D,4,FALSE) -> DIEGO FERNANDO HENAO CARDONA | C22: =VLOOKUP(A22,'CENTRO DE COSTOS'!A:C,2,FALSE) -> 0004-0002 | D22: 17001 | E22: TA-25-716437 | F22: FO-25-1049142 | G22: 45813.674 | H22: 45815.397 | I22: CALDAS | J22: MANIZALES | K22: BARRIO SANTOS MANIZALES 1 | L22: 51030 | M22: ORDEN DE CAMBIO | N22: CIERRE | O22: CIERRE | P22: REDEBAN | Q22: CB UNO A UNO | R22: CB UNO A UNO | S22: ILOCALIZADO | T22: CB CERRADO - DESOCUPADO | U22: 07-06-2025 SE LLEGA A DIRECCIÓN REGISTRADA EN EL CUAL EL ESTABLECIMIENTO SE ENCUENTRA CERRADO Y SIN PUBLICIDAD DEL CORRESPONSAL Y CON AVISO SE ARRIENDA, SE PREGUNTA EN COMERCIOS CERCANOS DICEN QUE CERRARON HACE 3 SEMANAS APROX, SE TRATA COMUNICACIÓN CON USUARIO PERO NO HAY RESPUESTA | V22: AGUIRRE HENAO RAUL EDUARDO | W22: 0 | X22: TIPO I | Y22: =VLOOKUP(D22,TIPOLOGIAS!A:F,5,0) -> TERRESTRE | Z22: VISITA_TÉCNICA | AA22: 0 | AB22: 0 | AC22: 1 | AD22: =IF(AND(Z22="SOPORTE_TELEFÓNICO",OR(T22="SIN CONTACTO CON EL CB",T22="NÚMEROS DE CONTACTO ERRADOS")),0,IF(Z22="SOPORTE_TELEFÓNICO",'BASE DE LIQUIDACION 2025'!$B$9,IF(X22="TIPO I",'BASE DE LIQUIDACION 2025'!$C$3,IF(X22="TIPO II",'BASE DE LIQUIDACION 2025'!$C$4,IF(X22="TIPO III",'BASE DE LIQUIDACION 2025'!$C$5,'BASE DE LIQUIDACION 2025'!$C$6))))) -> 44559.564 | AE22: =IF(Z22="SOPORTE_TELEFÓNICO",AD22,CIERRES!AC22*CIERRES!AD22) -> 44559.564
A23: MONTERIA | B23: =VLOOKUP(A23,'CENTRO DE COSTOS'!A:D,4,FALSE) -> JOSE MAURICIO HERNANDEZ ROJAS | C23: =VLOOKUP(A23,'CENTRO DE COSTOS'!A:C,2,FALSE) -> 0004-0001 | D23: 23001 | E23: TA-25-719466 | F23: FO-25-1053413 | G23: 45814.458 | H23: 45815.448 | I23: CORDOBA | J23: MONTERIA | K23: PTM MONTERIA INVERSIONES DO CA | L23: 76641 | M23: ORDEN DE CAMBIO | N23: CIERRE | O23: CIERRE | P23: REDEBAN | Q23: AGREGADOR | R23: COMCARD - PTM | S23: ILOCALIZADO | T23: CB CERRADO - DESOCUPADO | U23: 07-06-2025 SE LLEGA A CB, ESTÁ CERRADO, SE PREGUNTA EN LUGARES CERCANOS INFORMAN QUE TIENE TIEMPO QUE NO ABREN, SE MARCA A NÚMERO ASIGNADO 3164976081, INFORMAN QUE ES NÚMERO EQUIVOCADO | V23: COGOLLO ROSSO CAMILO ANDRES | W23: LA2ZZ424 | X23: TIPO I | Y23: =VLOOKUP(D23,TIPOLOGIAS!A:F,5,0) -> TERRESTRE | Z23: VISITA_TÉCNICA | AA23: 0 | AB23: 0 | AC23: 1 | AD23: =IF(AND(Z23="SOPORTE_TELEFÓNICO",OR(T23="SIN CONTACTO CON EL CB",T23="NÚMEROS DE CONTACTO ERRADOS")),0,IF(Z23="SOPORTE_TELEFÓNICO",'BASE DE LIQUIDACION 2025'!$B$9,IF(X23="TIPO I",'BASE DE LIQUIDACION 2025'!$C$3,IF(X23="TIPO II",'BASE DE LIQUIDACION 2025'!$C$4,IF(X23="TIPO III",'BASE DE LIQUIDACION 2025'!$C$5,'BASE DE LIQUIDACION 2025'!$C$6))))) -> 44559.564 | AE23: =IF(Z23="SOPORTE_TELEFÓNICO",AD23,CIERRES!AC23*CIERRES!AD23) -> 44559.564
A24: VILLAVICENCIO | B24: =VLOOKUP(A24,'CENTRO DE COSTOS'!A:D,4,FALSE) -> KEVIN ALEXIS CORZO BUSTOS | C24: =VLOOKUP(A24,'CENTRO DE COSTOS'!A:C,2,FALSE) -> 0004-0007 | D24: 50001 | E24: TA-25-716447 | F24: FO-25-1049165 | G24: 45813.674 | H24: 45815.49 | I24: META | J24: VILLAVICENCIO | K24: BARRIO PANORAMA VILLAVICENCIO | L24: 67216 | M24: ORDEN DE CAMBIO | N24: CIERRE | O24: CIERRE | P24: REDEBAN | Q24: CB UNO A UNO | R24: CB UNO A UNO | S24: NO_EXITOSO | T24: CB NO ENTREGA EQUIPO | U24: 07-06-2025 SE LLEGA AL COMERCIO SE VALIDA QUE EL CLIENTE NO ENTREGA EL EQUIPO YA QUE ESTA SOLICITANDO LA ACTIVACIÓN PORQUE HACE POCO REALIZO UN TRASLADO | V24: ROZO JIMENEZ EDGAR ARMANDO | W24: AAL06558 | X24: TIPO I | Y24: =VLOOKUP(D24,TIPOLOGIAS!A:F,5,0) -> TERRESTRE | Z24: VISITA_TÉCNICA | AA24: 0 | AB24: 0 | AC24: 1 | AD24: =IF(AND(Z24="SOPORTE_TELEFÓNICO",OR(T24="SIN CONTACTO CON EL CB",T24="NÚMEROS DE CONTACTO ERRADOS")),0,IF(Z24="SOPORTE_TELEFÓNICO",'BASE DE LIQUIDACION 2025'!$B$9,IF(X24="TIPO I",'BASE DE LIQUIDACION 2025'!$C$3,IF(X24="TIPO II",'BASE DE LIQUIDACION 2025'!$C$4,IF(X24="TIPO III",'BASE DE LIQUIDACION 2025'!$C$5,'BASE DE LIQUIDACION 2025'!$C$6))))) -> 44559.564 | AE24: =IF(Z24="SOPORTE_TELEFÓNICO",AD24,CIERRES!AC24*CIERRES!AD24) -> 44559.564
A25: BOGOTA | B25: =VLOOKUP(A25,'CENTRO DE COSTOS'!A:D,4,FALSE) -> WILLIAM ASDRUBAL ROZO ROZO | C25: =VLOOKUP(A25,'CENTRO DE COSTOS'!A:C,2,FALSE) -> 0004-0004 | D25: 11001 | E25: TA-25-719482 | F25: FO-25-1053457 | G25: 45814.458 | H25: 45815.548 | I25: CUNDINAMARCA | J25: BOGOTA | K25: PAGAFACIL BOSA | L25: 26555 | M25: ORDEN DE CAMBIO | N25: CIERRE | O25: RECUPERACION DE EQUIPOS | P25: REDEBAN | Q25: ROBUSTO | R25: PAGAFACIL | S25: NO_EXITOSO | T25: CB NO ENTREGA EQUIPO | U25: 07-06-2025 SE REALIZA VISITA A A CB PARA REALIZAR RETIRO DE EQUIPOS CLIENTE NO TIENE NINGÚN EQUIPO PARA RETIRAR INFORMA QUE TIENE SON UNOS CABLES PERO SE VALIDAN Y NO SON DE REDEBAN ,Y LOS DATAFONOS QUE TIENEN SON LOS QUE ACTUALMENTE ESTÁN UTILIZANDO | V25: GALINDO ROJAS LUIS FELIPE | W25: 0 | X25: TIPO I | Y25: =VLOOKUP(D25,TIPOLOGIAS!A:F,5,0) -> TERRESTRE | Z25: VISITA_TÉCNICA | AA25: 0 | AB25: 0 | AC25: 1 | AD25: =IF(AND(Z25="SOPORTE_TELEFÓNICO",OR(T25="SIN CONTACTO CON EL CB",T25="NÚMEROS DE CONTACTO ERRADOS")),0,IF(Z25="SOPORTE_TELEFÓNICO",'BASE DE LIQUIDACION 2025'!$B$9,IF(X25="TIPO I",'BASE DE LIQUIDACION 2025'!$C$3,IF(X25="TIPO II",'BASE DE LIQUIDACION 2025'!$C$4,IF(X25="TIPO III",'BASE DE LIQUIDACION 2025'!$C$5,'BASE DE LIQUIDACION 2025'!$C$6))))) -> 44559.564 | AE25: =IF(Z25="SOPORTE_TELEFÓNICO",AD25,CIERRES!AC25*CIERRES!AD25) -> 44559.564
A26: CUCUTA | B26: =VLOOKUP(A26,'CENTRO DE COSTOS'!A:D,4,FALSE) -> MIGUEL JULIÁN HERNÁNDEZ GUARÍN | C26: =VLOOKUP(A26,'CENTRO DE COSTOS'!A:C,2,FALSE) -> 0004-0008 | D26: 54518 | E26: TA-25-716452 | F26: FO-25-1049177 | G26: 45813.674 | H26: 45815.602 | I26: NORTE DE SANTANDER | J26: PAMPLONA | K26: BARRIO SIMON BOLIVAR PAMPLONA | L26: 29182 | M26: ORDEN DE CAMBIO | N26: CIERRE | O26: CIERRE | P26: REDEBAN | Q26: CB UNO A UNO | R26: CB UNO A UNO | S26: NO_EXITOSO | T26: CB NO ENTREGA EQUIPO | U26: 07-06-2025 SE REALIZA VISITA, ME INFORMAN QUE EL COMERCIO CAMBIO DE DUEÑO Y LOS EQUIPOS NO SE ENCUENTRAN EN EL LOCAL. SE INTENTA CONTACTAR TELEFÓNICAMENTE AL CLIENTE, PERO NO RESPONDE EL NÚMERO DE CONTACTO. 3124598287 | V26: PACHECO BUITRAGO JAVIER ALONSO | W26: 0 | X26: TIPO III | Y26: =VLOOKUP(D26,TIPOLOGIAS!A:F,5,0) -> TERRESTRE | Z26: VISITA_TÉCNICA | AA26: 0 | AB26: 0 | AC26: 1 | AD26: =IF(AND(Z26="SOPORTE_TELEFÓNICO",OR(T26="SIN CONTACTO CON EL CB",T26="NÚMEROS DE CONTACTO ERRADOS")),0,IF(Z26="SOPORTE_TELEFÓNICO",'BASE DE LIQUIDACION 2025'!$B$9,IF(X26="TIPO I",'BASE DE LIQUIDACION 2025'!$C$3,IF(X26="TIPO II",'BASE DE LIQUIDACION 2025'!$C$4,IF(X26="TIPO III",'BASE DE LIQUIDACION 2025'!$C$5,'BASE DE LIQUIDACION 2025'!$C$6))))) -> 222904.07 | AE26: =IF(Z26="SOPORTE_TELEFÓNICO",AD26,CIERRES!AC26*CIERRES!AD26) -> 222904.07
A27: BOGOTA | B27: =VLOOKUP(A27,'CENTRO DE COSTOS'!A:D,4,FALSE) -> WILLIAM ASDRUBAL ROZO ROZO | C27: =VLOOKUP(A27,'CENTRO DE COSTOS'!A:C,2,FALSE) -> 0004-0004 | D27: 11001 | E27: TA-25-719483 | F27: FO-25-1053459 | G27: 45814.458 | H27: 45815.603 | I27: CUNDINAMARCA | J27: BOGOTA | K27: MULTIPAGAS CHAPINERO | L27: 22814 | M27: ORDEN DE CAMBIO | N27: CIERRE | O27: RECUPERACION DE EQUIPOS | P27: REDEBAN | Q27: ROBUSTO | R27: MULTIPAGAS | S27: NO_EXITOSO | T27: CB NO ENTREGA EQUIPO | U27: 07-06-2025 COMERCIO NO PERMITE EL RETIRO DE LOS EQUIPOS QUE ESTÁN RELACIONADOS DENTRO DE LA TA EN SYTEX, INDICA QUE NO ESTÁN SOLICITANDO CIERRE SINO EL RETIRO DE EQUIPOS QUE TIENEN ALMACENADOS DESDE HACE MUCHO TIEMPO. SE CONSULTA CON EL COORDINADOR DE LA ZONA E INDICA QUE NO SE PUEDE REALIZAR EL CIERRE | V27: GARCIA PASTRANA KEVIN FERNANDO | W27: BBBBV322 | X27: TIPO I | Y27: =VLOOKUP(D27,TIPOLOGIAS!A:F,5,0) -> TERRESTRE | Z27: VISITA_TÉCNICA | AA27: 0 | AB27: 0 | AC27: 1 | AD27: =IF(AND(Z27="SOPORTE_TELEFÓNICO",OR(T27="SIN CONTACTO CON EL CB",T27="NÚMEROS DE CONTACTO ERRADOS")),0,IF(Z27="SOPORTE_TELEFÓNICO",'BASE DE LIQUIDACION 2025'!$B$9,IF(X27="TIPO I",'BASE DE LIQUIDACION 2025'!$C$3,IF(X27="TIPO II",'BASE DE LIQUIDACION 2025'!$C$4,IF(X27="TIPO III",'BASE DE LIQUIDACION 2025'!$C$5,'BASE DE LIQUIDACION 2025'!$C$6))))) -> 44559.564 | AE27: =IF(Z27="SOPORTE_TELEFÓNICO",AD27,CIERRES!AC27*CIERRES!AD27) -> 44559.564
A28: APARTADO | B28: =VLOOKUP(A28,'CENTRO DE COSTOS'!A:D,4,FALSE) -> JUAN SEBASTIÁN RÍOS CASTRILLÓN | C28: =VLOOKUP(A28,'CENTRO DE COSTOS'!A:C,2,FALSE) -> 0004-0005 | D28: 5490 | E28: TA-25-721683 | F28: FO-25-1061522 | G28: 45817.387 | H28: 45817.435 | I28: ANTIOQUIA | J28: NECOCLI | K28: PTM NECOCLI AUTOSERVICIO MAX D | L28: 51222 | M28: ORDEN DE CAMBIO | N28: CIERRE | O28: CIERRE | P28: REDEBAN | Q28: AGREGADOR | R28: COMCARD - PTM | S28: NO_EXITOSO | T28: CB NO ENTREGA EQUIPO | U28: 09-06-2025 PTM INDICA QUE EQUIPO YA FUERON ENTREGADOS A A REDEBAN BODEGA MEDELLÍN. | V28: DIAZ ZABALA FRANCIS DUBAN | W28: 0 | X28: TIPO II | Y28: =VLOOKUP(D28,TIPOLOGIAS!A:F,5,0) -> TERRESTRE | Z28: VISITA_TÉCNICA | AA28: 0 | AB28: 0 | AC28: 1 | AD28: =IF(AND(Z28="SOPORTE_TELEFÓNICO",OR(T28="SIN CONTACTO CON EL CB",T28="NÚMEROS DE CONTACTO ERRADOS")),0,IF(Z28="SOPORTE_TELEFÓNICO",'BASE DE LIQUIDACION 2025'!$B$9,IF(X28="TIPO I",'BASE DE LIQUIDACION 2025'!$C$3,IF(X28="TIPO II",'BASE DE LIQUIDACION 2025'!$C$4,IF(X28="TIPO III",'BASE DE LIQUIDACION 2025'!$C$5,'BASE DE LIQUIDACION 2025'!$C$6))))) -> 134410.88 | AE28: =IF(Z28="SOPORTE_TELEFÓNICO",AD28,CIERRES!AC28*CIERRES!AD28) -> 134410.88
A29: CALI | B29: =VLOOKUP(A29,'CENTRO DE COSTOS'!A:D,4,FALSE) -> DIEGO FERNANDO HENAO CARDONA | C29: =VLOOKUP(A29,'CENTRO DE COSTOS'!A:C,2,FALSE) -> 0004-0003 | D29: 76001 | E29: TA-25-720448 | F29: FO-25-1057186 | G29: 45814.519 | H29: 45817.465 | I29: VALLE DEL CAUCA | J29: CALI | K29: BARRIO VILLA DEL PRADO CALI 1 | L29: 62001 | M29: ORDEN DE CAMBIO | N29: CIERRE | O29: CIERRE | P29: REDEBAN | Q29: CB UNO A UNO | R29: CB UNO A UNO | S29: NO_EXITOSO | T29: CB NO ENTREGA EQUIPO | U29: 09-06-2025 CLIENTE ME COMUNICA QUE NO PUEDE ENTREGAR LOS EQUIPOS EL DÍA DE HOY SE LE COMUNICA QUE TIENE QUE VOLVER A SOLICITAR EL RETIRO DE LOS EQUIPOS | V29: HENAO CARDONA DIEGO FERNANDO | W29: 0 | X29: TIPO I | Y29: =VLOOKUP(D29,TIPOLOGIAS!A:F,5,0) -> TERRESTRE | Z29: SOPORTE_TELEFÓNICO | AA29: 0 | AB29: 0 | AC29: 0 | AD29: =IF(AND(Z29="SOPORTE_TELEFÓNICO",OR(T29="SIN CONTACTO CON EL CB",T29="NÚMEROS DE CONTACTO ERRADOS")),0,IF(Z29="SOPORTE_TELEFÓNICO",'BASE DE LIQUIDACION 2025'!$B$9,IF(X29="TIPO I",'BASE DE LIQUIDACION 2025'!$C$3,IF(X29="TIPO II",'BASE DE LIQUIDACION 2025'!$C$4,IF(X29="TIPO III",'BASE DE LIQUIDACION 2025'!$C$5,'BASE DE LIQUIDACION 2025'!$C$6))))) -> 37904.612 | AE29: =IF(Z29="SOPORTE_TELEFÓNICO",AD29,CIERRES!AC29*CIERRES!AD29) -> 37904.612
A30: MEDELLIN | B30: =VLOOKUP(A30,'CENTRO DE COSTOS'!A:D,4,FALSE) -> JUAN SEBASTIÁN RÍOS CASTRILLÓN | C30: =VLOOKUP(A30,'CENTRO DE COSTOS'!A:C,2,FALSE) -> 0004-0005 | D30: 5360 | E30: TA-25-719458 | F30: FO-25-1053386 | G30: 45814.458 | H30: 45817.54 | I30: ANTIOQUIA | J30: ITAGUI | K30: PTM ITAGUI D1 FARMA S A S | L30: 42723 | M30: ORDEN DE CAMBIO | N30: CIERRE | O30: CIERRE | P30: REDEBAN | Q30: AGREGADOR | R30: COMCARD - PTM | S30: NO_EXITOSO | T30: CB NO ENTREGA EQUIPO | U30: 09-06-2025 SE VISITA PUNTO Y ACTUALES DUEÑOS DE LOCAL INFORMAN QUE LOS EQUIPOS YA SE LOS LLEVARON A LA OFICINA DE PTM, NO FIRMAN POR QUE NO SON LA PERSONA QUE TENIA EL CB | V30: QUINTERO SANCHEZ JUAN SEBASTIAN | W30: GZ7ZZ115 | X30: TIPO I | Y30: =VLOOKUP(D30,TIPOLOGIAS!A:F,5,0) -> TERRESTRE | Z30: VISITA_TÉCNICA | AA30: 0 | AB30: 0 | AC30: 1 | AD30: =IF(AND(Z30="SOPORTE_TELEFÓNICO",OR(T30="SIN CONTACTO CON EL CB",T30="NÚMEROS DE CONTACTO ERRADOS")),0,IF(Z30="SOPORTE_TELEFÓNICO",'BASE DE LIQUIDACION 2025'!$B$9,IF(X30="TIPO I",'BASE DE LIQUIDACION 2025'!$C$3,IF(X30="TIPO II",'BASE DE LIQUIDACION 2025'!$C$4,IF(X30="TIPO III",'BASE DE LIQUIDACION 2025'!$C$5,'BASE DE LIQUIDACION 2025'!$C$6))))) -> 44559.564 | AE30: =IF(Z30="SOPORTE_TELEFÓNICO",AD30,CIERRES!AC30*CIERRES!AD30) -> 44559.564
A31: BARRANQUILLA | B31: =VLOOKUP(A31,'CENTRO DE COSTOS'!A:D,4,FALSE) -> JOSE MAURICIO HERNANDEZ ROJAS | C31: =VLOOKUP(A31,'CENTRO DE COSTOS'!A:C,2,FALSE) -> 0004-0001 | D31: 47205 | E31: TA-25-719471 | F31: FO-25-1053423 | G31: 45814.458 | H31: 45817.582 | I31: MAGDALENA | J31: CONCORDIA | K31: DISTRICOL FERRETERIA SAN ISIDR | L31: 35491 | M31: ORDEN DE CAMBIO | N31: CIERRE | O31: CIERRE | P31: REDEBAN | Q31: AGREGADOR | R31: DISTRICOL | S31: NO_EXITOSO | T31: CB NO ENTREGA EQUIPO | U31: 09-06-2025 SE REALIZA VISITA TÉCNICA, CLIENTE INDICA QUE ENVÍO LOS EQUIPOS A MEDELLÍN, PUBLICIDAD LE DIÓ DISPOSICIÓN FINAL. | V31: DE AGUAS MUÑOZ DAVID JOSE | W31: GZ000512 | X31: TIPO III | Y31: =VLOOKUP(D31,TIPOLOGIAS!A:F,5,0) -> TERRESTRE | Z31: VISITA_TÉCNICA | AA31: 0 | AB31: 0 | AC31: 1 | AD31: =IF(AND(Z31="SOPORTE_TELEFÓNICO",OR(T31="SIN CONTACTO CON EL CB",T31="NÚMEROS DE CONTACTO ERRADOS")),0,IF(Z31="SOPORTE_TELEFÓNICO",'BASE DE LIQUIDACION 2025'!$B$9,IF(X31="TIPO I",'BASE DE LIQUIDACION 2025'!$C$3,IF(X31="TIPO II",'BASE DE LIQUIDACION 2025'!$C$4,IF(X31="TIPO III",'BASE DE LIQUIDACION 2025'!$C$5,'BASE DE LIQUIDACION 2025'!$C$6))))) -> 222904.07 | AE31: =IF(Z31="SOPORTE_TELEFÓNICO",AD31,CIERRES!AC31*CIERRES!AD31) -> 222904.07
A32: MEDELLIN | B32: =VLOOKUP(A32,'CENTRO DE COSTOS'!A:D,4,FALSE) -> JUAN SEBASTIÁN RÍOS CASTRILLÓN | C32: =VLOOKUP(A32,'CENTRO DE COSTOS'!A:C,2,FALSE) -> 0004-0005 | D32: 5001 | E32: TA-25-719455 | F32: FO-25-1053377 | G32: 45814.458 | H32: 45817.625 | I32: ANTIOQUIA | J32: MEDELLIN | K32: PTM MED SU SALUD | L32: 39315 | M32: ORDEN DE CAMBIO | N32: CIERRE | O32: CIERRE | P32: REDEBAN | Q32: AGREGADOR | R32: COMCARD - PTM | S32: ILOCALIZADO | T32: CB CERRADO - DESOCUPADO | U32: 09-06-2025 SE LLEGA A DIRECCIÓN Y YA SE ENCUENTRA OTRO COMERCIO NO TIENEN IDEA DE LOS EQUIPOS, NO ES POSIBLE COMUNICACIÓN CON EL CLIENTE | V32: DIAZ ZABALA FRANCIS DUBAN | W32: 0 | X32: TIPO I | Y32: =VLOOKUP(D32,TIPOLOGIAS!A:F,5,0) -> TERRESTRE | Z32: VISITA_TÉCNICA | AA32: 0 | AB32: 0 | AC32: 1 | AD32: =IF(AND(Z32="SOPORTE_TELEFÓNICO",OR(T32="SIN CONTACTO CON EL CB",T32="NÚMEROS DE CONTACTO ERRADOS")),0,IF(Z32="SOPORTE_TELEFÓNICO",'BASE DE LIQUIDACION 2025'!$B$9,IF(X32="TIPO I",'BASE DE LIQUIDACION 2025'!$C$3,IF(X32="TIPO II",'BASE DE LIQUIDACION 2025'!$C$4,IF(X32="TIPO III",'BASE DE LIQUIDACION 2025'!$C$5,'BASE DE LIQUIDACION 2025'!$C$6))))) -> 44559.564 | AE32: =IF(Z32="SOPORTE_TELEFÓNICO",AD32,CIERRES!AC32*CIERRES!AD32) -> 44559.564
A33: MEDELLIN | B33: =VLOOKUP(A33,'CENTRO DE COSTOS'!A:D,4,FALSE) -> JUAN SEBASTIÁN RÍOS CASTRILLÓN | C33: =VLOOKUP(A33,'CENTRO DE COSTOS'!A:C,2,FALSE) -> 0004-0005 | D33: 5001 | E33: TA-25-719452 | F33: FO-25-1053374 | G33: 45814.458 | H33: 45817.698 | I33: ANTIOQUIA | J33: MEDELLIN | K33: COMCARD MED PIEDRANET 2 | L33: 32236 | M33: ORDEN DE CAMBIO | N33: CIERRE | O33: CIERRE | P33: REDEBAN | Q33: AGREGADOR | R33: COMCARD - PTM | S33: ILOCALIZADO | T33: CB CERRADO - DESOCUPADO | U33: 09-06-2025 SE LLEGA A LA DIRECCIÓN NO SE ENCUENTRA PUNTO ,SE REALIZA LLAMADA AL USUARIO Y NO CONTESTA | V33: CERPA SUAREZ DUVAN CAMILO | W33: 111DZ920 | X33: TIPO I | Y33: =VLOOKUP(D33,TIPOLOGIAS!A:F,5,0) -> TERRESTRE | Z33: VISITA_TÉCNICA | AA33: 0 | AB33: 0 | AC33: 1 | AD33: =IF(AND(Z33="SOPORTE_TELEFÓNICO",OR(T33="SIN CONTACTO CON EL CB",T33="NÚMEROS DE CONTACTO ERRADOS")),0,IF(Z33="SOPORTE_TELEFÓNICO",'BASE DE LIQUIDACION 2025'!$B$9,IF(X33="TIPO I",'BASE DE LIQUIDACION 2025'!$C$3,IF(X33="TIPO II",'BASE DE LIQUIDACION 2025'!$C$4,IF(X33="TIPO III",'BASE DE LIQUIDACION 2025'!$C$5,'BASE DE LIQUIDACION 2025'!$C$6))))) -> 44559.564 | AE33: =IF(Z33="SOPORTE_TELEFÓNICO",AD33,CIERRES!AC33*CIERRES!AD33) -> 44559.564
A34: BARRANQUILLA | B34: =VLOOKUP(A34,'CENTRO DE COSTOS'!A:D,4,FALSE) -> JOSE MAURICIO HERNANDEZ ROJAS | C34: =VLOOKUP(A34,'CENTRO DE COSTOS'!A:C,2,FALSE) -> 0004-0001 | D34: 8001 | E34: TA-25-716466 | F34: FO-25-1049203 | G34: 45813.674 | H34: 45818.284 | I34: ATLANTICO | J34: BARRANQUILLA | K34: BARRIO FERRY I BARRANQUILLA | L34: 23367 | M34: ORDEN DE CAMBIO | N34: CIERRE | O34: RECUPERACION DE EQUIPOS | P34: REDEBAN | Q34: CB UNO A UNO | R34: CB UNO A UNO | S34: NO_EXITOSO | T34: CB NO ENTREGA EQUIPO | U34: 10-06-2025 SE REALIZA VISITA AL COMERCIO PARA REALIZAR EL CIERRE DEL CORRESPONSAL BANCOLOMBIA PERO NO ES POSIBLE TRATO COMUNICACION CON EL NÚMERO DADO 3246098339 PERO NO CONTESTAN PREGUNTO Y ME DICEN QUE EL ENCARGADO ESTÁ DE VIAJE LE MANIFIESTO QUE CUANDO LLEGUE SE COMUNIQUE ALA LÍNEA DE SOPORTE PARA REAGENDAR VISITA | V34: PEÑALOZA GUTIERREZ RAFAEL GUSTAVO | W34: AA7ZZ984-11119862-ABC04331 | X34: TIPO I | Y34: =VLOOKUP(D34,TIPOLOGIAS!A:F,5,0) -> TERRESTRE | Z34: VISITA_TÉCNICA | AA34: 0 | AB34: 0 | AC34: 1 | AD34: =IF(AND(Z34="SOPORTE_TELEFÓNICO",OR(T34="SIN CONTACTO CON EL CB",T34="NÚMEROS DE CONTACTO ERRADOS")),0,IF(Z34="SOPORTE_TELEFÓNICO",'BASE DE LIQUIDACION 2025'!$B$9,IF(X34="TIPO I",'BASE DE LIQUIDACION 2025'!$C$3,IF(X34="TIPO II",'BASE DE LIQUIDACION 2025'!$C$4,IF(X34="TIPO III",'BASE DE LIQUIDACION 2025'!$C$5,'BASE DE LIQUIDACION 2025'!$C$6))))) -> 44559.564 | AE34: =IF(Z34="SOPORTE_TELEFÓNICO",AD34,CIERRES!AC34*CIERRES!AD34) -> 44559.564
A35: TUNJA | B35: =VLOOKUP(A35,'CENTRO DE COSTOS'!A:D,4,FALSE) -> MIGUEL JULIÁN HERNÁNDEZ GUARÍN | C35: =VLOOKUP(A35,'CENTRO DE COSTOS'!A:C,2,FALSE) -> 0004-0008 | D35: 15667 | E35: TA-25-722650 | F35: FO-25-1064604 | G35: 45817.565 | H35: 45818.461 | I35: BOYACA | J35: SAN LUIS DE GACENO | K35: CENTRO SAN LUIS DE GACENO BOYA | L35: 24216 | M35: ORDEN DE CAMBIO | N35: CIERRE | O35: CIERRE | P35: REDEBAN | Q35: CB UNO A UNO | R35: CB UNO A UNO | S35: NO_EXITOSO | T35: CB NO ENTREGA EQUIPO | U35: 10-06-2025 SE CIERRA ORDEN , CLIENTE INDICA POR GESTION TELEFÓNICA VIA WHATSAPP AL NÚMERO CELULAR 3106091366 QUE DESCONOCE LOS MOTIVOS POR EL CUAL LE CIERRAN EL PUNTO QUE SE VA A COMUNICAR CON LA ENTIDAD BANCARIA , SE LE RECUERDA LA LINEA NACIONAL 018000953344 DEL BANCO PARA QUE HAGA SU SOLICITUD. SE PROCEDE A CERRAR ORDEN | V35: ALVARADO MORENO CRISTHIAN | W35: 0 | X35: TIPO III | Y35: =VLOOKUP(D35,TIPOLOGIAS!A:F,5,0) -> TERRESTRE | Z35: VISITA_TÉCNICA | AA35: 0 | AC35: 1 | AD35: =IF(AND(Z35="SOPORTE_TELEFÓNICO",OR(T35="SIN CONTACTO CON EL CB",T35="NÚMEROS DE CONTACTO ERRADOS")),0,IF(Z35="SOPORTE_TELEFÓNICO",'BASE DE LIQUIDACION 2025'!$B$9,IF(X35="TIPO I",'BASE DE LIQUIDACION 2025'!$C$3,IF(X35="TIPO II",'BASE DE LIQUIDACION 2025'!$C$4,IF(X35="TIPO III",'BASE DE LIQUIDACION 2025'!$C$5,'BASE DE LIQUIDACION 2025'!$C$6))))) -> 222904.07 | AE35: =IF(Z35="SOPORTE_TELEFÓNICO",AD35,CIERRES!AC35*CIERRES!AD35) -> 222904.07
A36: PASTO | B36: =VLOOKUP(A36,'CENTRO DE COSTOS'!A:D,4,FALSE) -> DIEGO FERNANDO HENAO CARDONA | C36: =VLOOKUP(A36,'CENTRO DE COSTOS'!A:C,2,FALSE) -> 0004-0003 | D36: 52001 | E36: TA-25-722651 | F36: FO-25-1064609 | G36: 45817.565 | H36: 45818.656 | I36: NARIÑO | J36: PASTO | K36: BARRIO ALTAMIRA PASTO | L36: 75662 | M36: ORDEN DE CAMBIO | N36: CIERRE | O36: CIERRE | P36: REDEBAN | Q36: CB UNO A UNO | R36: CB UNO A UNO | S36: ILOCALIZADO | T36: CB CERRADO - DESOCUPADO | U36: 10-06-2025 SE LLEGÓ A DIRECCIÓN INDICADA PERO SE ENCUENTRA EL CORRESPONSAL CERRADO, SE INTENTO COMUNICACIÓN A LOS TELÉFONOS DE LA USUARIA, PERO NO CONTESTA LLAMADAS NI WHATSAPP. | V36: GUERRERO RAMIREZ OSCAR DARIO | W36: FA01Z642 | X36: TIPO I | Y36: =VLOOKUP(D36,TIPOLOGIAS!A:F,5,0) -> TERRESTRE | Z36: VISITA_TÉCNICA | AA36: 0 | AB36: 0 | AC36: 1 | AD36: =IF(AND(Z36="SOPORTE_TELEFÓNICO",OR(T36="SIN CONTACTO CON EL CB",T36="NÚMEROS DE CONTACTO ERRADOS")),0,IF(Z36="SOPORTE_TELEFÓNICO",'BASE DE LIQUIDACION 2025'!$B$9,IF(X36="TIPO I",'BASE DE LIQUIDACION 2025'!$C$3,IF(X36="TIPO II",'BASE DE LIQUIDACION 2025'!$C$4,IF(X36="TIPO III",'BASE DE LIQUIDACION 2025'!$C$5,'BASE DE LIQUIDACION 2025'!$C$6))))) -> 44559.564 | AE36: =IF(Z36="SOPORTE_TELEFÓNICO",AD36,CIERRES!AC36*CIERRES!AD36) -> 44559.564
A37: PASTO | B37: =VLOOKUP(A37,'CENTRO DE COSTOS'!A:D,4,FALSE) -> DIEGO FERNANDO HENAO CARDONA | C37: =VLOOKUP(A37,'CENTRO DE COSTOS'!A:C,2,FALSE) -> 0004-0003 | D37: 52356 | E37: TA-25-716449 | F37: FO-25-1049170 | G37: 45813.674 | H37: 45819.392 | I37: NARIÑO | J37: IPIALES | K37: BARRIO ESMERALDA IPIALES 1 | L37: 63875 | M37: ORDEN DE CAMBIO | N37: CIERRE | O37: CIERRE | P37: REDEBAN | Q37: CB UNO A UNO | R37: CB UNO A UNO | S37: NO_EXITOSO | T37: CB NO ENTREGA EQUIPO | U37: 11-06-2025 SE HABLA CON EL CLIENTE Y SE REALIZA VALIDACION DE CIERRE, PERO EL CLIENTE INDICA QUE AUN ESTA EN UN PROCESO CON LA ENTIDAD POR ELLO NO VA A ANTREGAR LOS EQUIPOS AUN PUES ESTA EN ESPERA DE UNA RESPUESTA DE LA ENTIDAD | V37: HENAO CARDONA DIEGO FERNANDO | W37: 0 | X37: TIPO II | Y37: =VLOOKUP(D37,TIPOLOGIAS!A:F,5,0) -> TERRESTRE | Z37: SOPORTE_TELEFÓNICO | AA37: 0 | AB37: 0 | AC37: 0 | AD37: =IF(AND(Z37="SOPORTE_TELEFÓNICO",OR(T37="SIN CONTACTO CON EL CB",T37="NÚMEROS DE CONTACTO ERRADOS")),0,IF(Z37="SOPORTE_TELEFÓNICO",'BASE DE LIQUIDACION 2025'!$B$9,IF(X37="TIPO I",'BASE DE LIQUIDACION 2025'!$C$3,IF(X37="TIPO II",'BASE DE LIQUIDACION 2025'!$C$4,IF(X37="TIPO III",'BASE DE LIQUIDACION 2025'!$C$5,'BASE DE LIQUIDACION 2025'!$C$6))))) -> 37904.612 | AE37: =IF(Z37="SOPORTE_TELEFÓNICO",AD37,CIERRES!AC37*CIERRES!AD37) -> 37904.612
A38: MANIZALES | B38: =VLOOKUP(A38,'CENTRO DE COSTOS'!A:D,4,FALSE) -> DIEGO FERNANDO HENAO CARDONA | C38: =VLOOKUP(A38,'CENTRO DE COSTOS'!A:C,2,FALSE) -> 0004-0002 | D38: 17777 | E38: TA-25-719465 | F38: FO-25-1053410 | G38: 45814.458 | H38: 45819.672 | I38: CALDAS | J38: SUPIA | K38: DISTRICOL NAF BOUTIQUE | L38: 44439 | M38: ORDEN DE CAMBIO | N38: CIERRE | O38: CIERRE | P38: REDEBAN | Q38: AGREGADOR | R38: DISTRICOL | S38: NO_EXITOSO | T38: CB NO ENTREGA EQUIPO | U38: 11-06-2025 SE HABLA TELEFONICAMENTE CON EL SEÑOR YEISON QUIEN FIGURA EN EL CONTACTO PERO EL INDICA QUE ESE NEGOCIO SE ACABO HACE MAS DE 2 AÑOS Y LOS EQUIPOS FUERON DEVUELTOS, QUE EL CORTO TODO CONTACTO CON LA ENTIDAD HACE MUCHO RATO, INDICA QUE EL NO DEBE FIGURAR EN NADA DE ESO PUES ESO NO EXISTE HACE YA MUCHO TIEMPO. | V38: HENAO CARDONA DIEGO FERNANDO | W38: 0 | X38: TIPO II | Y38: =VLOOKUP(D38,TIPOLOGIAS!A:F,5,0) -> TERRESTRE | Z38: SOPORTE_TELEFÓNICO | AA38: 0 | AB38: 0 | AC38: 0 | AD38: =IF(AND(Z38="SOPORTE_TELEFÓNICO",OR(T38="SIN CONTACTO CON EL CB",T38="NÚMEROS DE CONTACTO ERRADOS")),0,IF(Z38="SOPORTE_TELEFÓNICO",'BASE DE LIQUIDACION 2025'!$B$9,IF(X38="TIPO I",'BASE DE LIQUIDACION 2025'!$C$3,IF(X38="TIPO II",'BASE DE LIQUIDACION 2025'!$C$4,IF(X38="TIPO III",'BASE DE LIQUIDACION 2025'!$C$5,'BASE DE LIQUIDACION 2025'!$C$6))))) -> 37904.612 | AE38: =IF(Z38="SOPORTE_TELEFÓNICO",AD38,CIERRES!AC38*CIERRES!AD38) -> 37904.612
A39: SANTA MARTA | B39: =VLOOKUP(A39,'CENTRO DE COSTOS'!A:D,4,FALSE) -> JOSE MAURICIO HERNANDEZ ROJAS | C39: =VLOOKUP(A39,'CENTRO DE COSTOS'!A:C,2,FALSE) -> 0004-0001 | D39: 47001 | E39: TA-25-722824 | F39: FO-25-1065060 | G39: 45817.674 | H39: 45820.481 | I39: MAGDALENA | J39: SANTA MARTA | K39: DISTRICOL DROG Y VAR EBENEZER | L39: 70400 | M39: ORDEN DE CAMBIO | N39: CIERRE | O39: RECUPERACION DE EQUIPOS | P39: REDEBAN | Q39: AGREGADOR | R39: DISTRICOL | S39: NO_EXITOSO | T39: CB NO ENTREGA EQUIPO | U39: 12-06-2025 SE LLAMA AL NÚMERO INDICADO Y LA USUARIA MARLEN ROJAS INDICA QUE EL EQUIPO YA FUE ENTREGADO | V39: RUA ALVAREZ RICHARD ANDRES | W39: 0 | X39: TIPO I | Y39: =VLOOKUP(D39,TIPOLOGIAS!A:F,5,0) -> TERRESTRE | Z39: SOPORTE_TELEFÓNICO | AA39: 0 | AB39: 0 | AC39: 0 | AD39: =IF(AND(Z39="SOPORTE_TELEFÓNICO",OR(T39="SIN CONTACTO CON EL CB",T39="NÚMEROS DE CONTACTO ERRADOS")),0,IF(Z39="SOPORTE_TELEFÓNICO",'BASE DE LIQUIDACION 2025'!$B$9,IF(X39="TIPO I",'BASE DE LIQUIDACION 2025'!$C$3,IF(X39="TIPO II",'BASE DE LIQUIDACION 2025'!$C$4,IF(X39="TIPO III",'BASE DE LIQUIDACION 2025'!$C$5,'BASE DE LIQUIDACION 2025'!$C$6))))) -> 37904.612 | AE39: =IF(Z39="SOPORTE_TELEFÓNICO",AD39,CIERRES!AC39*CIERRES!AD39) -> 37904.612
A40: BOGOTA | B40: =VLOOKUP(A40,'CENTRO DE COSTOS'!A:D,4,FALSE) -> WILLIAM ASDRUBAL ROZO ROZO | C40: =VLOOKUP(A40,'CENTRO DE COSTOS'!A:C,2,FALSE) -> 0004-0004 | D40: 25386 | E40: TA-25-722660 | F40: FO-25-1069367 | G40: 45817.565 | H40: 45820.546 | I40: CUNDINAMARCA | J40: LA MESA | K40: BARRIO CENTRO LA MESA 7 | L40: 76271 | M40: ORDEN DE CAMBIO | N40: CIERRE | O40: RECUPERACION DE EQUIPOS | P40: REDEBAN | Q40: CB UNO A UNO | R40: CB UNO A UNO | S40: EJECUTADO_EXITOSO | T40: CIERRE EXITOSO | U40: 12-06-2025 DURANTE LA VISITA TECNICA SE REALIZA RETIRO DE DATAFONO, LECTOR DE CODIGO DE BARRAS POR CIERRE DE PUNTO PUBLICIDAD FUE RETIRADA Y DESTRUIDA POR COMERCIO INDICAN | V40: GALEANO SORIANO JUAN DAVID | W40: EG0OZ133 | X40: TIPO II | Y40: =VLOOKUP(D40,TIPOLOGIAS!A:F,5,0) -> TERRESTRE | Z40: VISITA_TÉCNICA | AA40: 1072112 | AB40: 775711 | AC40: 1 | AD40: =IF(AND(Z40="SOPORTE_TELEFÓNICO",OR(T40="SIN CONTACTO CON EL CB",T40="NÚMEROS DE CONTACTO ERRADOS")),0,IF(Z40="SOPORTE_TELEFÓNICO",'BASE DE LIQUIDACION 2025'!$B$9,IF(X40="TIPO I",'BASE DE LIQUIDACION 2025'!$C$3,IF(X40="TIPO II",'BASE DE LIQUIDACION 2025'!$C$4,IF(X40="TIPO III",'BASE DE LIQUIDACION 2025'!$C$5,'BASE DE LIQUIDACION 2025'!$C$6))))) -> 134410.88 | AE40: =IF(Z40="SOPORTE_TELEFÓNICO",AD40,CIERRES!AC40*CIERRES!AD40) -> 134410.88
A41: BOGOTA | B41: =VLOOKUP(A41,'CENTRO DE COSTOS'!A:D,4,FALSE) -> WILLIAM ASDRUBAL ROZO ROZO | C41: =VLOOKUP(A41,'CENTRO DE COSTOS'!A:C,2,FALSE) -> 0004-0004 | D41: 11001 | E41: TA-25-722815 | F41: FO-25-1082752 | G41: 45817.674 | H41: 45820.713 | I41: CUNDINAMARCA | J41: BOGOTA | K41: PTM BOGOTA CIGARRERIA EL REFUG | L41: 68147 | M41: ORDEN DE CAMBIO | N41: CIERRE | O41: CIERRE | P41: REDEBAN | Q41: AGREGADOR | R41: COMCARD - PTM | S41: EJECUTADO_EXITOSO | T41: CIERRE EXITOSO | U41: 12-06-2025 SE VISITA DIRECCIÓN INDICADA POR EL CLIENTE PARA ENTREGAR LOS EQUIPOS, SE RETIRAN DATÁFONO EL CUAL ESTÁ ALERTADO (LLT), LECTOR DE BARRAS, BASE Y CABLEADO, NO UPS, NO SE MANIPULAN EQUIPOS, PUBLICIDAD NO TIENEN YA QUE FUE DESTRUIDA POR CLIENTE. | V41: VEGA MANRIQUE JONATAN MAURICIO | W41: 9L08Z750 - AAQ0P940 | X41: TIPO I | Y41: =VLOOKUP(D41,TIPOLOGIAS!A:F,5,0) -> TERRESTRE | Z41: VISITA_TÉCNICA | AA41: 894557 | AB41: 932471 | AC41: 1 | AD41: =IF(AND(Z41="SOPORTE_TELEFÓNICO",OR(T41="SIN CONTACTO CON EL CB",T41="NÚMEROS DE CONTACTO ERRADOS")),0,IF(Z41="SOPORTE_TELEFÓNICO",'BASE DE LIQUIDACION 2025'!$B$9,IF(X41="TIPO I",'BASE DE LIQUIDACION 2025'!$C$3,IF(X41="TIPO II",'BASE DE LIQUIDACION 2025'!$C$4,IF(X41="TIPO III",'BASE DE LIQUIDACION 2025'!$C$5,'BASE DE LIQUIDACION 2025'!$C$6))))) -> 44559.564 | AE41: =IF(Z41="SOPORTE_TELEFÓNICO",AD41,CIERRES!AC41*CIERRES!AD41) -> 44559.564
A42: BUCARAMANGA | B42: =VLOOKUP(A42,'CENTRO DE COSTOS'!A:D,4,FALSE) -> MIGUEL JULIÁN HERNÁNDEZ GUARÍN | C42: =VLOOKUP(A42,'CENTRO DE COSTOS'!A:C,2,FALSE) -> 0004-0008 | D42: 68001 | E42: TA-25-719473 | F42: FO-25-1055503 | G42: 45814.458 | H42: 45820.877 | I42: SANTANDER | J42: BUCARAMANGA | K42: PTM BUCARAMANGA PUNTO SERVIS B | L42: 78127 | M42: ORDEN DE CAMBIO | N42: CIERRE | O42: CIERRE | P42: REDEBAN | Q42: AGREGADOR | R42: COMCARD - PTM | S42: EJECUTADO_EXITOSO | T42: CIERRE EXITOSO | U42: 12-06-2025 SE REALIZA VISITA A LA DIRECCIÓN DADA POR EL CLIENTE DÓNDE LA SRA MARIA PAZ TARAZONA HACE ENTREGA VOLUNTARIA DE DATÁFONO, PINPAD, HUB Y LECTORA DE BARRAS, BASE Y SUS RESPECTIVOS CABLEADO. DIRECCIÓN PROPORCIONADA CRA 1A 55A 25 CENTAUROS 2 | V42: GONZALEZ ESTUPIÑAN YEISON WALTER ANTONIO | W42: LMOZZ278-LMOZZ350 | X42: TIPO I | Y42: =VLOOKUP(D42,TIPOLOGIAS!A:F,5,0) -> TERRESTRE | Z42: VISITA_TÉCNICA | AA42: 1219060 | AB42: 1145440 1119308 NO SERIALIZADO | AC42: 1 | AD42: =IF(AND(Z42="SOPORTE_TELEFÓNICO",OR(T42="SIN CONTACTO CON EL CB",T42="NÚMEROS DE CONTACTO ERRADOS")),0,IF(Z42="SOPORTE_TELEFÓNICO",'BASE DE LIQUIDACION 2025'!$B$9,IF(X42="TIPO I",'BASE DE LIQUIDACION 2025'!$C$3,IF(X42="TIPO II",'BASE DE LIQUIDACION 2025'!$C$4,IF(X42="TIPO III",'BASE DE LIQUIDACION 2025'!$C$5,'BASE DE LIQUIDACION 2025'!$C$6))))) -> 44559.564 | AE42: =IF(Z42="SOPORTE_TELEFÓNICO",AD42,CIERRES!AC42*CIERRES!AD42) -> 44559.564
A43: BOGOTA | B43: =VLOOKUP(A43,'CENTRO DE COSTOS'!A:D,4,FALSE) -> WILLIAM ASDRUBAL ROZO ROZO | C43: =VLOOKUP(A43,'CENTRO DE COSTOS'!A:C,2,FALSE) -> 0004-0004 | D43: 25214 | E43: TA-25-722810 | F43: FO-25-1065021 | G43: 45817.674 | H43: 45821.499 | I43: CUNDINAMARCA | J43: COTA | K43: DISTRICOL JN ELECTRONICA | L43: 44112 | M43: ORDEN DE CAMBIO | N43: CIERRE | O43: CIERRE | P43: REDEBAN | Q43: AGREGADOR | R43: DISTRICOL | S43: ILOCALIZADO | T43: CB CERRADO - DESOCUPADO | U43: 13-06-2025 SE VISITA COMERCIO POR CIERRE DE PUNTO AL LLEGAR A LA DIRECCIÓN REGISTRADA YA NO SE ENCUENTRA NINGÚN COMERCIO ACTIVO EN LA DIRECCIÓN SE INTENTA COMUNICACIÓN A NÚMEROS REGISTRADOS : 3123289164, 3187292927 PERO SE VA A BUZÓN DE MENSAJES SE VALIDA CON COMERCIOS CERCANOS QUIENES CONFIRMAN HACE 2 MESES EL CLIENTE SE FUE Y NO SABEN DE EL SE PROCEDE A DILIGENCIAR FORMATO ILOCALIZABLE Y ACTA DE CIERRE FINALIZANDO ACTIVIDAD SIN MÁS NOVEDAD | V43: ROMERO ROJAS BREIDY JHOHAN | W43: 0 | X43: TIPO II | Y43: =VLOOKUP(D43,TIPOLOGIAS!A:F,5,0) -> TERRESTRE | Z43: VISITA_TÉCNICA | AA43: 0 | AB43: 0 | AC43: 1 | AD43: =IF(AND(Z43="SOPORTE_TELEFÓNICO",OR(T43="SIN CONTACTO CON EL CB",T43="NÚMEROS DE CONTACTO ERRADOS")),0,IF(Z43="SOPORTE_TELEFÓNICO",'BASE DE LIQUIDACION 2025'!$B$9,IF(X43="TIPO I",'BASE DE LIQUIDACION 2025'!$C$3,IF(X43="TIPO II",'BASE DE LIQUIDACION 2025'!$C$4,IF(X43="TIPO III",'BASE DE LIQUIDACION 2025'!$C$5,'BASE DE LIQUIDACION 2025'!$C$6))))) -> 134410.88 | AE43: =IF(Z43="SOPORTE_TELEFÓNICO",AD43,CIERRES!AC43*CIERRES!AD43) -> 134410.88
A44: IBAGUE | B44: =VLOOKUP(A44,'CENTRO DE COSTOS'!A:D,4,FALSE) -> KEVIN ALEXIS CORZO BUSTOS | C44: =VLOOKUP(A44,'CENTRO DE COSTOS'!A:C,2,FALSE) -> 0004-0007 | D44: 73001 | E44: TA-25-755299 | F44: FO-25-1083790 | G44: 45820.583 | H44: 45821.622 | I44: TOLIMA | J44: IBAGUE | K44: EL CARMEN IBAGUE TOLIMA | L44: 72512 | M44: ORDEN DE CAMBIO | N44: CIERRE | O44: CIERRE | P44: REDEBAN | Q44: CB UNO A UNO | R44: CB UNO A UNO | S44: ILOCALIZADO | T44: CB CERRADO - DESOCUPADO | U44: 13-06-2025 SE VISITA COMERCIO PERO SE ENCUENTRA CERRADO, SE COMUNICA AL NÚMERO 3182218150 SIN NINGÚN RESULTADO. VISITA FALLIDA | V44: BARRAGAN TAFUR EDWIN ESTEBAN | W44: 0 | X44: TIPO I | Y44: =VLOOKUP(D44,TIPOLOGIAS!A:F,5,0) -> TERRESTRE | Z44: VISITA_TÉCNICA | AA44: 0 | AB44: 0 | AC44: 1 | AD44: =IF(AND(Z44="SOPORTE_TELEFÓNICO",OR(T44="SIN CONTACTO CON EL CB",T44="NÚMEROS DE CONTACTO ERRADOS")),0,IF(Z44="SOPORTE_TELEFÓNICO",'BASE DE LIQUIDACION 2025'!$B$9,IF(X44="TIPO I",'BASE DE LIQUIDACION 2025'!$C$3,IF(X44="TIPO II",'BASE DE LIQUIDACION 2025'!$C$4,IF(X44="TIPO III",'BASE DE LIQUIDACION 2025'!$C$5,'BASE DE LIQUIDACION 2025'!$C$6))))) -> 44559.564 | AE44: =IF(Z44="SOPORTE_TELEFÓNICO",AD44,CIERRES!AC44*CIERRES!AD44) -> 44559.564
A45: BOGOTA | B45: =VLOOKUP(A45,'CENTRO DE COSTOS'!A:D,4,FALSE) -> WILLIAM ASDRUBAL ROZO ROZO | C45: =VLOOKUP(A45,'CENTRO DE COSTOS'!A:C,2,FALSE) -> 0004-0004 | D45: 25286 | E45: TA-25-755291 | F45: FO-25-1083776 | G45: 45820.583 | H45: 45821.69 | I45: CUNDINAMARCA | J45: FUNZA | K45: BARRIO FUNZA FUNZA 3 | L45: 46905 | M45: ORDEN DE CAMBIO | N45: CIERRE | O45: CIERRE | P45: REDEBAN | Q45: CB UNO A UNO | R45: CB UNO A UNO | S45: ILOCALIZADO | T45: CB CERRADO - DESOCUPADO | U45: 13-06-2025 SE REALIZA VISITA A LA DIRECCIÓN ASIGNADA POR EL CLIENTE PARA EJECUTAR CIERRE DE CB, PERO AL LLEGAR AL PUNTO LA CASA 04 DEL BLOQUE 39 SE ENCUENTRA DESOCUPADO NO HAY NINGÚN COMERCIO. SE INTENTA CONTACTO CON EL CLIENTE AL NÚMERO 3114725417 Y NO HAY RESPUESTA. | V45: CORTES VELANDIA MIGUEL ANGEL | W45: 0 | X45: TIPO II | Y45: =VLOOKUP(D45,TIPOLOGIAS!A:F,5,0) -> TERRESTRE | Z45: VISITA_TÉCNICA | AA45: 0 | AB45: 0 | AC45: 1 | AD45: =IF(AND(Z45="SOPORTE_TELEFÓNICO",OR(T45="SIN CONTACTO CON EL CB",T45="NÚMEROS DE CONTACTO ERRADOS")),0,IF(Z45="SOPORTE_TELEFÓNICO",'BASE DE LIQUIDACION 2025'!$B$9,IF(X45="TIPO I",'BASE DE LIQUIDACION 2025'!$C$3,IF(X45="TIPO II",'BASE DE LIQUIDACION 2025'!$C$4,IF(X45="TIPO III",'BASE DE LIQUIDACION 2025'!$C$5,'BASE DE LIQUIDACION 2025'!$C$6))))) -> 134410.88 | AE45: =IF(Z45="SOPORTE_TELEFÓNICO",AD45,CIERRES!AC45*CIERRES!AD45) -> 134410.88
A46: CALI | B46: =VLOOKUP(A46,'CENTRO DE COSTOS'!A:D,4,FALSE) -> DIEGO FERNANDO HENAO CARDONA | C46: =VLOOKUP(A46,'CENTRO DE COSTOS'!A:C,2,FALSE) -> 0004-0003 | D46: 19001 | E46: TA-25-724916 | F46: FO-25-1083761 | G46: 45818.526 | H46: 45821.694 | I46: CAUCA | J46: POPAYAN | K46: BARRIO EL EMPEDRADO POPAYAN | L46: 59632 | M46: ORDEN DE CAMBIO | N46: CIERRE | O46: RECUPERACION DE EQUIPOS | P46: REDEBAN | Q46: CB UNO A UNO | R46: CB UNO A UNO | S46: EJECUTADO_EXITOSO | T46: CIERRE EXITOSO | U46: 13-06-2025 SE INGRESA SE RECOGE DATÁFONO LECTOR BASE FUENTE CABLE MAGIC BOSS ESTADO OKAY NO SE RECOGE PUBLICIDAD YA QUE SE INFORMA SE DESTRUYÓ ANTES DEL TRASTEO | V46: GIMBUEL LASSO LUIS GERMAN | W46: JA008894 | X46: TIPO III | Y46: =VLOOKUP(D46,TIPOLOGIAS!A:F,5,0) -> TERRESTRE | Z46: VISITA_TÉCNICA | AA46: 960400 | AB46: 805215 | AC46: 1 | AD46: =IF(AND(Z46="SOPORTE_TELEFÓNICO",OR(T46="SIN CONTACTO CON EL CB",T46="NÚMEROS DE CONTACTO ERRADOS")),0,IF(Z46="SOPORTE_TELEFÓNICO",'BASE DE LIQUIDACION 2025'!$B$9,IF(X46="TIPO I",'BASE DE LIQUIDACION 2025'!$C$3,IF(X46="TIPO II",'BASE DE LIQUIDACION 2025'!$C$4,IF(X46="TIPO III",'BASE DE LIQUIDACION 2025'!$C$5,'BASE DE LIQUIDACION 2025'!$C$6))))) -> 222904.07 | AE46: =IF(Z46="SOPORTE_TELEFÓNICO",AD46,CIERRES!AC46*CIERRES!AD46) -> 222904.07
A47: BARRANQUILLA | B47: =VLOOKUP(A47,'CENTRO DE COSTOS'!A:D,4,FALSE) -> JOSE MAURICIO HERNANDEZ ROJAS | C47: =VLOOKUP(A47,'CENTRO DE COSTOS'!A:C,2,FALSE) -> 0004-0001 | D47: 8433 | E47: TA-25-755288 | F47: FO-25-1083770 | G47: 45820.583 | H47: 45822.431 | I47: ATLANTICO | J47: MALAMBO | K47: BARRIO CENTRO MALAMBO 2 | L47: 67355 | M47: ORDEN DE CAMBIO | N47: CIERRE | O47: CIERRE | P47: REDEBAN | Q47: CB UNO A UNO | R47: CB UNO A UNO | S47: NO_EXITOSO | T47: CB NO ENTREGA EQUIPO | U47: 14-06-2025 SE REALIZA VISITA TÉCNICA, CLIENTE INDICA QUE ESTÁ GESTIONANDO LA REACTIVACIÓN DEL CB CON LA ENTIDAD. | V47: DE AGUAS MUÑOZ DAVID JOSE | W47: 6A0TZ943 | X47: TIPO II | Y47: =VLOOKUP(D47,TIPOLOGIAS!A:F,5,0) -> TERRESTRE | Z47: VISITA_TÉCNICA | AA47: 0 | AB47: 0 | AC47: 1 | AD47: =IF(AND(Z47="SOPORTE_TELEFÓNICO",OR(T47="SIN CONTACTO CON EL CB",T47="NÚMEROS DE CONTACTO ERRADOS")),0,IF(Z47="SOPORTE_TELEFÓNICO",'BASE DE LIQUIDACION 2025'!$B$9,IF(X47="TIPO I",'BASE DE LIQUIDACION 2025'!$C$3,IF(X47="TIPO II",'BASE DE LIQUIDACION 2025'!$C$4,IF(X47="TIPO III",'BASE DE LIQUIDACION 2025'!$C$5,'BASE DE LIQUIDACION 2025'!$C$6))))) -> 134410.88 | AE47: =IF(Z47="SOPORTE_TELEFÓNICO",AD47,CIERRES!AC47*CIERRES!AD47) -> 134410.88
A48: CALI | B48: =VLOOKUP(A48,'CENTRO DE COSTOS'!A:D,4,FALSE) -> DIEGO FERNANDO HENAO CARDONA | C48: =VLOOKUP(A48,'CENTRO DE COSTOS'!A:C,2,FALSE) -> 0004-0003 | D48: 76001 | E48: TA-25-756340 | F48: FO-25-1087054 | G48: 45821.504 | H48: 45822.519 | I48: VALLE DEL CAUCA | J48: CALI | K48: BARRIO JORDAN CALI 1 | L48: 71559 | M48: ORDEN DE CAMBIO | N48: CIERRE | O48: CIERRE | P48: REDEBAN | Q48: CB UNO A UNO | R48: CB UNO A UNO | S48: ILOCALIZADO | T48: CB CERRADO - DESOCUPADO | U48: 14-06-2025 SE VISITA EL COMERCIO ESTA CERRADO, SE CONSULTA A VECINOS CERCANOS INFORMA QUE SE FUERON Y CERRARON HACE 4 DÍAS, LLAMA AL CLIENTE A LOS NÚMEROS 3173568257, 3153694893 SIN RESPUESTA. LA VISITA ES FALLIDA CIERRE NO EXISITOSO | V48: HERRERA MONAR GEOVANNY | W48: A30KZ126 | X48: TIPO I | Y48: =VLOOKUP(D48,TIPOLOGIAS!A:F,5,0) -> TERRESTRE | Z48: VISITA_TÉCNICA | AA48: 0 | AB48: 0 | AC48: 1 | AD48: =IF(AND(Z48="SOPORTE_TELEFÓNICO",OR(T48="SIN CONTACTO CON EL CB",T48="NÚMEROS DE CONTACTO ERRADOS")),0,IF(Z48="SOPORTE_TELEFÓNICO",'BASE DE LIQUIDACION 2025'!$B$9,IF(X48="TIPO I",'BASE DE LIQUIDACION 2025'!$C$3,IF(X48="TIPO II",'BASE DE LIQUIDACION 2025'!$C$4,IF(X48="TIPO III",'BASE DE LIQUIDACION 2025'!$C$5,'BASE DE LIQUIDACION 2025'!$C$6))))) -> 44559.564 | AE48: =IF(Z48="SOPORTE_TELEFÓNICO",AD48,CIERRES!AC48*CIERRES!AD48) -> 44559.564
A49: VILLAVICENCIO | B49: =VLOOKUP(A49,'CENTRO DE COSTOS'!A:D,4,FALSE) -> KEVIN ALEXIS CORZO BUSTOS | C49: =VLOOKUP(A49,'CENTRO DE COSTOS'!A:C,2,FALSE) -> 0004-0007 | D49: 50330 | E49: TA-25-756339 | F49: FO-25-1087051 | G49: 45821.504 | H49: 45822.523 | I49: META | J49: MESETAS | K49: JARDIN MESETAS | L49: 17174 | M49: ORDEN DE CAMBIO | N49: CIERRE | O49: CIERRE | P49: REDEBAN | Q49: CB UNO A UNO | R49: CB UNO A UNO | S49: NO_EXITOSO | T49: CB NO ENTREGA EQUIPO | U49: 14-06-2025 SE REALIZA VISITA AL PUNTO Y COMERCIO SE ENCUENTRA CERRADO, SE REALIZA CONTACTO TELEFÓNICO Y EL SEÑOR FERNANDO INDICA QUE NO SE ENCUENTRA EN EL PUEBLO | V49: PEDREROS CONTRERAS MICHAEL STEVENS | W49: NONE | X49: TIPO III | Y49: =VLOOKUP(D49,TIPOLOGIAS!A:F,5,0) -> TERRESTRE | Z49: VISITA_TÉCNICA | AA49: 0 | AC49: 1 | AD49: =IF(AND(Z49="SOPORTE_TELEFÓNICO",OR(T49="SIN CONTACTO CON EL CB",T49="NÚMEROS DE CONTACTO ERRADOS")),0,IF(Z49="SOPORTE_TELEFÓNICO",'BASE DE LIQUIDACION 2025'!$B$9,IF(X49="TIPO I",'BASE DE LIQUIDACION 2025'!$C$3,IF(X49="TIPO II",'BASE DE LIQUIDACION 2025'!$C$4,IF(X49="TIPO III",'BASE DE LIQUIDACION 2025'!$C$5,'BASE DE LIQUIDACION 2025'!$C$6))))) -> 222904.07 | AE49: =IF(Z49="SOPORTE_TELEFÓNICO",AD49,CIERRES!AC49*CIERRES!AD49) -> 222904.07
A50: PASTO | B50: =VLOOKUP(A50,'CENTRO DE COSTOS'!A:D,4,FALSE) -> DIEGO FERNANDO HENAO CARDONA | C50: =VLOOKUP(A50,'CENTRO DE COSTOS'!A:C,2,FALSE) -> 0004-0003 | D50: 86568 | E50: TA-25-722811 | F50: FO-25-1065025 | G50: 45817.674 | H50: 45824.38 | I50: PUTUMAYO | J50: PUERTO ASIS | K50: DISTRICOL AUTOSERVICIO SUPER E | L50: 47839 | M50: ORDEN DE CAMBIO | N50: CIERRE | O50: CIERRE | P50: REDEBAN | Q50: AGREGADOR | R50: DISTRICOL | S50: NO_EXITOSO | T50: CB NO ENTREGA EQUIPO | U50: 16-06-2025 SE INTENTA COMUNICACION CON EL CLIENTE EN VARIOS OCACIONES Y POR VARIOS MEDIOS PERO NO ES POSIBLE HASTA EL DIA DE AYER QUE NOS ATIENDE LA EX ESPOSA DEL CLIENTE QUIEN INDICA QUE ESE PUNTO YA NO EXISTE Y SE EXPAREJA DEBERIA TENER LOS EQUIPO PERO NO TIENE MAS INFORMACION DEL CASO, NOS ENTREGA UN NUMERO PARA CONTACTO DIRERCTAMENTE CON EL, PERO NO CONSTESTA NI MENSAJES NI LLAMADAS, SE LE INDCIA A A LA MUJER QUE ES PARA EL RETIRO DE LOS EQUIPOS DEL CORRESPONSAL, PERO INDICA QUE DEBE SER CON EL QUE ELLA NO TIENE NI IDEA DE DONDE SE ENCONTRARAN . | V50: HENAO CARDONA DIEGO FERNANDO | W50: 0 | X50: TIPO IV | Y50: =VLOOKUP(D50,TIPOLOGIAS!A:F,5,0) -> TERRESTRE | Z50: SOPORTE_TELEFÓNICO | AA50: 0 | AB50: 0 | AC50: 0 | AD50: =IF(AND(Z50="SOPORTE_TELEFÓNICO",OR(T50="SIN CONTACTO CON EL CB",T50="NÚMEROS DE CONTACTO ERRADOS")),0,IF(Z50="SOPORTE_TELEFÓNICO",'BASE DE LIQUIDACION 2025'!$B$9,IF(X50="TIPO I",'BASE DE LIQUIDACION 2025'!$C$3,IF(X50="TIPO II",'BASE DE LIQUIDACION 2025'!$C$4,IF(X50="TIPO III",'BASE DE LIQUIDACION 2025'!$C$5,'BASE DE LIQUIDACION 2025'!$C$6))))) -> 37904.612 | AE50: =IF(Z50="SOPORTE_TELEFÓNICO",AD50,CIERRES!AC50*CIERRES!AD50) -> 37904.612
A51: APARTADO | B51: =VLOOKUP(A51,'CENTRO DE COSTOS'!A:D,4,FALSE) -> JUAN SEBASTIÁN RÍOS CASTRILLÓN | C51: =VLOOKUP(A51,'CENTRO DE COSTOS'!A:C,2,FALSE) -> 0004-0005 | D51: 5045 | E51: TA-25-722817 | F51: FO-25-1065042 | G51: 45817.674 | H51: 45824.549 | I51: ANTIOQUIA | J51: APARTADO | K51: PTM APARTADO CAPRICHOS BOUTIQU | L51: 75588 | M51: ORDEN DE CAMBIO | N51: CIERRE | O51: CIERRE | P51: REDEBAN | Q51: AGREGADOR | R51: COMCARD - PTM | S51: NO_EXITOSO | T51: CB NO ENTREGA EQUIPO | U51: 16-06-2025 SE ESTABLECE COMUNICACIÓN CON USUARIO SR JHOAN QUIÉN SE ENCUENTRA DE VIAJE SOLICITA REPROGRAMAR VISITA. SE LE INFORMA A USUARIO COMUNICARSE A LA LÍNEA NUEVAMENTE CUANDO TENGA LA DISPONIBILIDAD PARA EL RETIRO | V51: JULIO TUBERQUIA JOSE SEBASTIAN | W51: 0 | X51: TIPO I | Y51: =VLOOKUP(D51,TIPOLOGIAS!A:F,5,0) -> TERRESTRE | Z51: SOPORTE_TELEFÓNICO | AA51: 0 | AB51: 0 | AC51: 0 | AD51: =IF(AND(Z51="SOPORTE_TELEFÓNICO",OR(T51="SIN CONTACTO CON EL CB",T51="NÚMEROS DE CONTACTO ERRADOS")),0,IF(Z51="SOPORTE_TELEFÓNICO",'BASE DE LIQUIDACION 2025'!$B$9,IF(X51="TIPO I",'BASE DE LIQUIDACION 2025'!$C$3,IF(X51="TIPO II",'BASE DE LIQUIDACION 2025'!$C$4,IF(X51="TIPO III",'BASE DE LIQUIDACION 2025'!$C$5,'BASE DE LIQUIDACION 2025'!$C$6))))) -> 37904.612 | AE51: =IF(Z51="SOPORTE_TELEFÓNICO",AD51,CIERRES!AC51*CIERRES!AD51) -> 37904.612
A52: BOGOTA | B52: =VLOOKUP(A52,'CENTRO DE COSTOS'!A:D,4,FALSE) -> WILLIAM ASDRUBAL ROZO ROZO | C52: =VLOOKUP(A52,'CENTRO DE COSTOS'!A:C,2,FALSE) -> 0004-0004 | D52: 11001 | E52: TA-25-756338 | F52: FO-25-1091756 | G52: 45821.504 | H52: 45824.653 | I52: CUNDINAMARCA | J52: BOGOTA | K52: PTM BOGOTA @SHADDAI | L52: 69773 | M52: ORDEN DE CAMBIO | N52: CIERRE | O52: RECUPERACION DE EQUIPOS | P52: REDEBAN | Q52: AGREGADOR | R52: COMCARD - PTM | S52: EJECUTADO_EXITOSO | T52: CIERRE EXITOSO | U52: 16-06-2025 SE RETIRA DATÁFONO Y LECTORA Y PUBLICIDAD SE DESTRUYE | V52: INFANTE SIERRA MANUEL FERNANDO | W52: NN000799 | X52: TIPO I | Y52: =VLOOKUP(D52,TIPOLOGIAS!A:F,5,0) -> TERRESTRE | Z52: VISITA_TÉCNICA | AA52: 761528 | AB52: 902783 | AC52: 1 | AD52: =IF(AND(Z52="SOPORTE_TELEFÓNICO",OR(T52="SIN CONTACTO CON EL CB",T52="NÚMEROS DE CONTACTO ERRADOS")),0,IF(Z52="SOPORTE_TELEFÓNICO",'BASE DE LIQUIDACION 2025'!$B$9,IF(X52="TIPO I",'BASE DE LIQUIDACION 2025'!$C$3,IF(X52="TIPO II",'BASE DE LIQUIDACION 2025'!$C$4,IF(X52="TIPO III",'BASE DE LIQUIDACION 2025'!$C$5,'BASE DE LIQUIDACION 2025'!$C$6))))) -> 44559.564 | AE52: =IF(Z52="SOPORTE_TELEFÓNICO",AD52,CIERRES!AC52*CIERRES!AD52) -> 44559.564
A53: MEDELLIN | B53: =VLOOKUP(A53,'CENTRO DE COSTOS'!A:D,4,FALSE) -> JUAN SEBASTIÁN RÍOS CASTRILLÓN | C53: =VLOOKUP(A53,'CENTRO DE COSTOS'!A:C,2,FALSE) -> 0004-0005 | D53: 5001 | E53: TA-25-781408 | F53: FO-25-1099103 | G53: 45824.647 | H53: 45825.521 | I53: ANTIOQUIA | J53: MEDELLIN | K53: BARRIO MANRIQUE GAITAN MEDELLI | L53: 13408 | M53: ORDEN DE CAMBIO | N53: CIERRE | O53: CIERRE | P53: REDEBAN | Q53: CB UNO A UNO | R53: CB UNO A UNO | S53: NO_EXITOSO | T53: CB NO ENTREGA EQUIPO | U53: 17-06-2025 SE VISITA PUNTO Y EN LOCAL NO SE ENCUENTRA EL ADMINISTRADOR, EL TRABAJADOR NOS DICE QUE NO SABE NADA DEL TEMA INTENTA COMUNOCARCE CON EL DUEÑO SIN ÉXITO. HACE INTENTO DE COMUNICACIÓN EN LOS NÚMEROS REGISTRADO SIN ÉXITO | V53: DIAZ ZABALA FRANCIS DUBAN | W53: 0 | X53: TIPO I | Y53: =VLOOKUP(D53,TIPOLOGIAS!A:F,5,0) -> TERRESTRE | Z53: VISITA_TÉCNICA | AA53: 0 | AB53: 0 | AC53: 1 | AD53: =IF(AND(Z53="SOPORTE_TELEFÓNICO",OR(T53="SIN CONTACTO CON EL CB",T53="NÚMEROS DE CONTACTO ERRADOS")),0,IF(Z53="SOPORTE_TELEFÓNICO",'BASE DE LIQUIDACION 2025'!$B$9,IF(X53="TIPO I",'BASE DE LIQUIDACION 2025'!$C$3,IF(X53="TIPO II",'BASE DE LIQUIDACION 2025'!$C$4,IF(X53="TIPO III",'BASE DE LIQUIDACION 2025'!$C$5,'BASE DE LIQUIDACION 2025'!$C$6))))) -> 44559.564 | AE53: =IF(Z53="SOPORTE_TELEFÓNICO",AD53,CIERRES!AC53*CIERRES!AD53) -> 44559.564
A54: MEDELLIN | B54: =VLOOKUP(A54,'CENTRO DE COSTOS'!A:D,4,FALSE) -> JUAN SEBASTIÁN RÍOS CASTRILLÓN | C54: =VLOOKUP(A54,'CENTRO DE COSTOS'!A:C,2,FALSE) -> 0004-0005 | D54: 5001 | E54: TA-25-781390 | F54: FO-25-1099066 | G54: 45824.647 | H54: 45825.588 | I54: ANTIOQUIA | J54: MEDELLIN | K54: COMCARD MED OSMAR | L54: 28227 | M54: ORDEN DE CAMBIO | N54: CIERRE | O54: CIERRE | P54: REDEBAN | Q54: AGREGADOR | R54: COMCARD - PTM | S54: ILOCALIZADO | T54: CB CERRADO - DESOCUPADO | U54: 17-06-2025 SE VISITA COMERCIO Y SE ENCUENTRA LOCAL CERRADO. SE INTENTA COMUNICACIÓN CON EL CLIENTE A LOS NÚMEROS REGISTRADO SIN ÉXITO | V54: DIAZ ZABALA FRANCIS DUBAN | W54: 0 | X54: TIPO I | Y54: =VLOOKUP(D54,TIPOLOGIAS!A:F,5,0) -> TERRESTRE | Z54: VISITA_TÉCNICA | AA54: 0 | AB54: 0 | AC54: 1 | AD54: =IF(AND(Z54="SOPORTE_TELEFÓNICO",OR(T54="SIN CONTACTO CON EL CB",T54="NÚMEROS DE CONTACTO ERRADOS")),0,IF(Z54="SOPORTE_TELEFÓNICO",'BASE DE LIQUIDACION 2025'!$B$9,IF(X54="TIPO I",'BASE DE LIQUIDACION 2025'!$C$3,IF(X54="TIPO II",'BASE DE LIQUIDACION 2025'!$C$4,IF(X54="TIPO III",'BASE DE LIQUIDACION 2025'!$C$5,'BASE DE LIQUIDACION 2025'!$C$6))))) -> 44559.564 | AE54: =IF(Z54="SOPORTE_TELEFÓNICO",AD54,CIERRES!AC54*CIERRES!AD54) -> 44559.564
A55: MEDELLIN | B55: =VLOOKUP(A55,'CENTRO DE COSTOS'!A:D,4,FALSE) -> JUAN SEBASTIÁN RÍOS CASTRILLÓN | C55: =VLOOKUP(A55,'CENTRO DE COSTOS'!A:C,2,FALSE) -> 0004-0005 | D55: 5001 | E55: TA-25-789479 | F55: FO-25-1104657 | G55: 45825.627 | H55: 45826.46 | I55: ANTIOQUIA | J55: MEDELLIN | K55: BARRIO ROBLEDO ALTAMIRA MEDELL | L55: 69515 | M55: ORDEN DE CAMBIO | N55: CIERRE | O55: CIERRE | P55: REDEBAN | Q55: CB UNO A UNO | R55: CB UNO A UNO | S55: ILOCALIZADO | T55: CB CERRADO - DESOCUPADO | U55: 18-06-2025 SE LLEGA AL SITIO Y EN PORTERÍA NOS DICEN QUE ESE COMERCIO NO EXISTE Y QUE NO CONOCEN A NADIE CON ESE NOMBRE, SE LLAMA AL CLIENTES SI ÉXITO VIGILANCIA TAMBIÉN LLAMA A LOS NÚMERO HABER SI ES DE ALGÚN PROPIETARIO Y NADA | V55: DIAZ ZABALA FRANCIS DUBAN | W55: 0 | X55: TIPO I | Y55: =VLOOKUP(D55,TIPOLOGIAS!A:F,5,0) -> TERRESTRE | Z55: VISITA_TÉCNICA | AA55: 0 | AB55: 0 | AC55: 1 | AD55: =IF(AND(Z55="SOPORTE_TELEFÓNICO",OR(T55="SIN CONTACTO CON EL CB",T55="NÚMEROS DE CONTACTO ERRADOS")),0,IF(Z55="SOPORTE_TELEFÓNICO",'BASE DE LIQUIDACION 2025'!$B$9,IF(X55="TIPO I",'BASE DE LIQUIDACION 2025'!$C$3,IF(X55="TIPO II",'BASE DE LIQUIDACION 2025'!$C$4,IF(X55="TIPO III",'BASE DE LIQUIDACION 2025'!$C$5,'BASE DE LIQUIDACION 2025'!$C$6))))) -> 44559.564 | AE55: =IF(Z55="SOPORTE_TELEFÓNICO",AD55,CIERRES!AC55*CIERRES!AD55) -> 44559.564
A56: CUCUTA | B56: =VLOOKUP(A56,'CENTRO DE COSTOS'!A:D,4,FALSE) -> MIGUEL JULIÁN HERNÁNDEZ GUARÍN | C56: =VLOOKUP(A56,'CENTRO DE COSTOS'!A:C,2,FALSE) -> 0004-0008 | D56: 54405 | E56: TA-25-789476 | F56: FO-25-1104651 | G56: 45825.627 | H56: 45826.49 | I56: NORTE DE SANTANDER | J56: LOS PATIOS | K56: BARRIO LA SABANA LOS PATIOS 3 | L56: 64594 | M56: ORDEN DE CAMBIO | N56: CIERRE | O56: CIERRE | P56: REDEBAN | Q56: CB UNO A UNO | R56: CB UNO A UNO | S56: NO_EXITOSO | T56: CB NO ENTREGA EQUIPO | U56: 18-06-2025 SE VISITA COMERCIO Y NOS INDICAN QUE LA TITULAR NO SE ENCUENTRA QUE ESTÁ DE VIAJE Y NO CUENTAN CON LA DISPONIBILIDAD PARA ENTREGAR LOS EQUIPOS. | V56: TORRES MANTILLA JOSE DANIEL | W56: 0 | X56: TIPO I | Y56: =VLOOKUP(D56,TIPOLOGIAS!A:F,5,0) -> TERRESTRE | Z56: VISITA_TÉCNICA | AA56: 0 | AB56: 0 | AC56: 1 | AD56: =IF(AND(Z56="SOPORTE_TELEFÓNICO",OR(T56="SIN CONTACTO CON EL CB",T56="NÚMEROS DE CONTACTO ERRADOS")),0,IF(Z56="SOPORTE_TELEFÓNICO",'BASE DE LIQUIDACION 2025'!$B$9,IF(X56="TIPO I",'BASE DE LIQUIDACION 2025'!$C$3,IF(X56="TIPO II",'BASE DE LIQUIDACION 2025'!$C$4,IF(X56="TIPO III",'BASE DE LIQUIDACION 2025'!$C$5,'BASE DE LIQUIDACION 2025'!$C$6))))) -> 44559.564 | AE56: =IF(Z56="SOPORTE_TELEFÓNICO",AD56,CIERRES!AC56*CIERRES!AD56) -> 44559.564
A57: CALI | B57: =VLOOKUP(A57,'CENTRO DE COSTOS'!A:D,4,FALSE) -> DIEGO FERNANDO HENAO CARDONA | C57: =VLOOKUP(A57,'CENTRO DE COSTOS'!A:C,2,FALSE) -> 0004-0003 | D57: 76111 | E57: TA-25-789455 | F57: FO-25-1104599 | G57: 45825.627 | H57: 45826.593 | I57: VALLE DEL CAUCA | J57: GUADALAJARA DE BUGA | K57: BARRIO JOSE MARIA CABAL CENTRO | L57: 34841 | M57: ORDEN DE CAMBIO | N57: CIERRE | O57: CIERRE | P57: REDEBAN | Q57: CB UNO A UNO | R57: CB UNO A UNO | S57: ILOCALIZADO | T57: CB CERRADO - DESOCUPADO | U57: 18-06-2025 SE LLEGA AL COMERCIO PERO ESTA CERRADO SE LLAMA AL CLIENTE Y NO CONTESTA SE ESPERA 20 MUNITOS PARA VER SI LLEGABA PERO NADA | V57: CUERO RUIZ JHONNY | W57: BL01M688 | X57: TIPO II | Y57: =VLOOKUP(D57,TIPOLOGIAS!A:F,5,0) -> TERRESTRE | Z57: VISITA_TÉCNICA | AA57: 0 | AB57: 0 | AC57: 1 | AD57: =IF(AND(Z57="SOPORTE_TELEFÓNICO",OR(T57="SIN CONTACTO CON EL CB",T57="NÚMEROS DE CONTACTO ERRADOS")),0,IF(Z57="SOPORTE_TELEFÓNICO",'BASE DE LIQUIDACION 2025'!$B$9,IF(X57="TIPO I",'BASE DE LIQUIDACION 2025'!$C$3,IF(X57="TIPO II",'BASE DE LIQUIDACION 2025'!$C$4,IF(X57="TIPO III",'BASE DE LIQUIDACION 2025'!$C$5,'BASE DE LIQUIDACION 2025'!$C$6))))) -> 134410.88 | AE57: =IF(Z57="SOPORTE_TELEFÓNICO",AD57,CIERRES!AC57*CIERRES!AD57) -> 134410.88
A58: CALI | B58: =VLOOKUP(A58,'CENTRO DE COSTOS'!A:D,4,FALSE) -> DIEGO FERNANDO HENAO CARDONA | C58: =VLOOKUP(A58,'CENTRO DE COSTOS'!A:C,2,FALSE) -> 0004-0003 | D58: 76001 | E58: TA-25-789484 | F58: FO-25-1104674 | G58: 45825.627 | H58: 45826.669 | I58: VALLE DEL CAUCA | J58: CALI | K58: BARRIO MONTEBELLO CALI 4 | L58: 75934 | M58: ORDEN DE CAMBIO | N58: CIERRE | O58: CIERRE | P58: REDEBAN | Q58: CB UNO A UNO | R58: CB UNO A UNO | S58: NO_EXITOSO | T58: CB NO ENTREGA EQUIPO | U58: 18-06-2025 SE LLAMA AL NÚMERO DE CONTACTO, CORRESPONSAL INDICA QUE NO AH SOLICITADO EL CIERRE Y QUE LLAMÓ A BANCOLOMBIA PARA VALIDAR EL PORQUÉ DEL BLOQUEO. PERO INDICA QUE DESEA CONTINUAR CON EL SERVICIO POR LO CUAL NO AUTORIZA CIERRE | V58: BOLAÑOS TABORDA JORGE ENRIQUE | W58: 0 | X58: TIPO I | Y58: =VLOOKUP(D58,TIPOLOGIAS!A:F,5,0) -> TERRESTRE | Z58: SOPORTE_TELEFÓNICO | AA58: 0 | AB58: 0 | AC58: 0 | AD58: =IF(AND(Z58="SOPORTE_TELEFÓNICO",OR(T58="SIN CONTACTO CON EL CB",T58="NÚMEROS DE CONTACTO ERRADOS")),0,IF(Z58="SOPORTE_TELEFÓNICO",'BASE DE LIQUIDACION 2025'!$B$9,IF(X58="TIPO I",'BASE DE LIQUIDACION 2025'!$C$3,IF(X58="TIPO II",'BASE DE LIQUIDACION 2025'!$C$4,IF(X58="TIPO III",'BASE DE LIQUIDACION 2025'!$C$5,'BASE DE LIQUIDACION 2025'!$C$6))))) -> 37904.612 | AE58: =IF(Z58="SOPORTE_TELEFÓNICO",AD58,CIERRES!AC58*CIERRES!AD58) -> 37904.612
A59: CALI | B59: =VLOOKUP(A59,'CENTRO DE COSTOS'!A:D,4,FALSE) -> DIEGO FERNANDO HENAO CARDONA | C59: =VLOOKUP(A59,'CENTRO DE COSTOS'!A:C,2,FALSE) -> 0004-0003 | D59: 76001 | E59: TA-25-789456 | F59: FO-25-1104604 | G59: 45825.627 | H59: 45826.697 | I59: VALLE DEL CAUCA | J59: CALI | K59: BARRIO FLORALIA CALI 1 | L59: 36012 | M59: ORDEN DE CAMBIO | N59: CIERRE | O59: CIERRE | P59: REDEBAN | Q59: CB UNO A UNO | R59: CB UNO A UNO | S59: NO_EXITOSO | T59: CB NO ENTREGA EQUIPO | U59: 18-06-2025 SE VISITA LE CORRESPONSAL, CON EL SEÑOR CRISTIAN BERMEO Y CLIENTE INFORMA QUE TUVO PROBLEMAS CON UNOS CRÉDITOS CON LA ENTIDAD PERO YA QUE SE PUSO AL DÍA. DICE QUE PRETENDE COMUNICARSE CON EL BANCO YA QUE DESEA CONTINUAR CON EL SERVICIO. CLIENTE NO SE ENCUENTRA EN EL PUNTO | V59: BOLAÑOS TABORDA JORGE ENRIQUE | W59: GZCZZ685 | X59: TIPO I | Y59: =VLOOKUP(D59,TIPOLOGIAS!A:F,5,0) -> TERRESTRE | Z59: VISITA_TÉCNICA | AA59: 0 | AB59: 0 | AC59: 1 | AD59: =IF(AND(Z59="SOPORTE_TELEFÓNICO",OR(T59="SIN CONTACTO CON EL CB",T59="NÚMEROS DE CONTACTO ERRADOS")),0,IF(Z59="SOPORTE_TELEFÓNICO",'BASE DE LIQUIDACION 2025'!$B$9,IF(X59="TIPO I",'BASE DE LIQUIDACION 2025'!$C$3,IF(X59="TIPO II",'BASE DE LIQUIDACION 2025'!$C$4,IF(X59="TIPO III",'BASE DE LIQUIDACION 2025'!$C$5,'BASE DE LIQUIDACION 2025'!$C$6))))) -> 44559.564 | AE59: =IF(Z59="SOPORTE_TELEFÓNICO",AD59,CIERRES!AC59*CIERRES!AD59) -> 44559.564
A60: CARTAGENA | B60: =VLOOKUP(A60,'CENTRO DE COSTOS'!A:D,4,FALSE) -> JOSE MAURICIO HERNANDEZ ROJAS | C60: =VLOOKUP(A60,'CENTRO DE COSTOS'!A:C,2,FALSE) -> 0004-0001 | D60: 13580 | E60: TA-25-755289 | F60: FO-25-1083772 | G60: 45820.583 | H60: 45826.735 | I60: BOLIVAR | J60: REGIDOR | K60: BARRIO LA UNION REGIDOR | L60: 41418 | M60: ORDEN DE CAMBIO | N60: CIERRE | O60: CIERRE | P60: REDEBAN | Q60: CB UNO A UNO | R60: CB UNO A UNO | S60: NO_EXITOSO | T60: CB NO ENTREGA EQUIPO | U60: 18-06-2025 SE LLEGA A SITIO LA CUAL QUIEN ATIENDE LA CUAL NOS IDICA QUE EL PROPIETARIO DE CB SE LO LLEVO PARA OTRO MUNICIPIO | V60: MAESTRE MENGUAL EDGAR ENRIQUE | W60: ON008838 | X60: TIPO IV | Y60: =VLOOKUP(D60,TIPOLOGIAS!A:F,5,0) -> TERRESTRE | Z60: VISITA_TÉCNICA | AA60: 0 | AB60: 0 | AC60: 1 | AD60: =IF(AND(Z60="SOPORTE_TELEFÓNICO",OR(T60="SIN CONTACTO CON EL CB",T60="NÚMEROS DE CONTACTO ERRADOS")),0,IF(Z60="SOPORTE_TELEFÓNICO",'BASE DE LIQUIDACION 2025'!$B$9,IF(X60="TIPO I",'BASE DE LIQUIDACION 2025'!$C$3,IF(X60="TIPO II",'BASE DE LIQUIDACION 2025'!$C$4,IF(X60="TIPO III",'BASE DE LIQUIDACION 2025'!$C$5,'BASE DE LIQUIDACION 2025'!$C$6))))) -> 464809.37 | AE60: =IF(Z60="SOPORTE_TELEFÓNICO",AD60,CIERRES!AC60*CIERRES!AD60) -> 464809.37
A61: VALLEDUPAR | B61: =VLOOKUP(A61,'CENTRO DE COSTOS'!A:D,4,FALSE) -> JOSE MAURICIO HERNANDEZ ROJAS | C61: =VLOOKUP(A61,'CENTRO DE COSTOS'!A:C,2,FALSE) -> 0004-0001 | D61: 20517 | E61: TA-25-756320 | F61: FO-25-1087005 | G61: 45821.504 | H61: 45827.38 | I61: CESAR | J61: PAILITAS | K61: DISTRICOL VIDRIERA Y MARQUETER | L61: 38219 | M61: ORDEN DE CAMBIO | N61: CIERRE | O61: CIERRE | P61: REDEBAN | Q61: AGREGADOR | R61: DISTRICOL | S61: NO_EXITOSO | T61: CB NO ENTREGA EQUIPO | U61: 19-06-2025 SE LLEGA A DIRECCIÓN NOS ATIENDE EL SEÑOR CARLOS MARIO NOS INDICA QUE LOS EQUIPOS FUERON ENVIADOS A LA CIUDAD DE MEDELLIN A NOMBRE DE LA SEÑORA VALENTINA ESCOBAR EL DIA 09/06/2025 | V61: MAESTRE MENGUAL EDGAR ENRIQUE | W61: 9A00W509 | X61: TIPO IV | Y61: =VLOOKUP(D61,TIPOLOGIAS!A:F,5,0) -> TERRESTRE | Z61: VISITA_TÉCNICA | AA61: 0 | AB61: 0 | AC61: 1 | AD61: =IF(AND(Z61="SOPORTE_TELEFÓNICO",OR(T61="SIN CONTACTO CON EL CB",T61="NÚMEROS DE CONTACTO ERRADOS")),0,IF(Z61="SOPORTE_TELEFÓNICO",'BASE DE LIQUIDACION 2025'!$B$9,IF(X61="TIPO I",'BASE DE LIQUIDACION 2025'!$C$3,IF(X61="TIPO II",'BASE DE LIQUIDACION 2025'!$C$4,IF(X61="TIPO III",'BASE DE LIQUIDACION 2025'!$C$5,'BASE DE LIQUIDACION 2025'!$C$6))))) -> 464809.37 | AE61: =IF(Z61="SOPORTE_TELEFÓNICO",AD61,CIERRES!AC61*CIERRES!AD61) -> 464809.37
A62: PASTO | B62: =VLOOKUP(A62,'CENTRO DE COSTOS'!A:D,4,FALSE) -> DIEGO FERNANDO HENAO CARDONA | C62: =VLOOKUP(A62,'CENTRO DE COSTOS'!A:C,2,FALSE) -> 0004-0003 | D62: 52019 | E62: TA-25-789462 | F62: FO-25-1104617 | G62: 45825.627 | H62: 45827.524 | I62: NARIÑO | J62: ALBAN | K62: BARRIO SUR ALBAN ALBAN | L62: 51948 | M62: ORDEN DE CAMBIO | N62: CIERRE | O62: CIERRE | P62: REDEBAN | Q62: CB UNO A UNO | R62: CB UNO A UNO | S62: NO_EXITOSO | T62: CB NO ENTREGA EQUIPO | U62: 19-06-2025 SE REALIZA VALIDACION CON EL CLIENTE LA SEÑORA LUZ DARY INFORMA QUE A ELLA LE LLEGO UN MENSAJE DE TEXTO PERO NADIE LE HA COMUNICADO NADA Y EN LA LINEA NO LE DAN INFORMACION ELLA INDICA QUE PRIMERO DEBE VALIDAR CON LA ENTIDAD PARA SABER QUE PASO POR QUE ELLA ESTA AL DIA EN TODO, POR TAL MOTIVO NO ACCEDE A LA ENTREGA DE EQUIPOS HASTA TANTO NO LE BRINDEN LA INFORMACION PERTIENENTE | V62: HENAO CARDONA DIEGO FERNANDO | W62: 0 | X62: TIPO II | Y62: =VLOOKUP(D62,TIPOLOGIAS!A:F,5,0) -> TERRESTRE | Z62: SOPORTE_TELEFÓNICO | AA62: 0 | AB62: 0 | AC62: 0 | AD62: =IF(AND(Z62="SOPORTE_TELEFÓNICO",OR(T62="SIN CONTACTO CON EL CB",T62="NÚMEROS DE CONTACTO ERRADOS")),0,IF(Z62="SOPORTE_TELEFÓNICO",'BASE DE LIQUIDACION 2025'!$B$9,IF(X62="TIPO I",'BASE DE LIQUIDACION 2025'!$C$3,IF(X62="TIPO II",'BASE DE LIQUIDACION 2025'!$C$4,IF(X62="TIPO III",'BASE DE LIQUIDACION 2025'!$C$5,'BASE DE LIQUIDACION 2025'!$C$6))))) -> 37904.612 | AE62: =IF(Z62="SOPORTE_TELEFÓNICO",AD62,CIERRES!AC62*CIERRES!AD62) -> 37904.612
A63: MEDELLIN | B63: =VLOOKUP(A63,'CENTRO DE COSTOS'!A:D,4,FALSE) -> JUAN SEBASTIÁN RÍOS CASTRILLÓN | C63: =VLOOKUP(A63,'CENTRO DE COSTOS'!A:C,2,FALSE) -> 0004-0005 | D63: 27205 | E63: TA-25-781403 | F63: FO-25-1099094 | G63: 45824.647 | H63: 45827.705 | I63: CHOCO | J63: CONDOTO | K63: BARRIO VILLA FRANCO CONDOTO | L63: 77743 | M63: ORDEN DE CAMBIO | N63: CIERRE | O63: CIERRE | P63: REDEBAN | Q63: CB UNO A UNO | R63: CB UNO A UNO | S63: ILOCALIZADO | T63: CB CERRADO - DESOCUPADO | U63: 19-06-2025 SE LLEGA A SITIO SE ENCUENTRA COMERCIO CERRADO, SE TOCA PUERTAS, SE AVERIGUA EN EL COMERCIO DEL ALDO Y COMENTAN QUE NO HAN ABIERTO LA FARMACIA NI LA CASA EL DÍA DE HOY | V63: ROBLEDO DIAZ ANDRES FELIPE | W63: 10NZZ033 | X63: TIPO IV ESPECIAL | Y63: =VLOOKUP(D63,TIPOLOGIAS!A:F,5,0) -> AEREO | Z63: VISITA_TÉCNICA | AA63: 0 | AB63: 0 | AC63: 1 | AD63: =IF(AND(Z63="SOPORTE_TELEFÓNICO",OR(T63="SIN CONTACTO CON EL CB",T63="NÚMEROS DE CONTACTO ERRADOS")),0,IF(Z63="SOPORTE_TELEFÓNICO",'BASE DE LIQUIDACION 2025'!$B$9,IF(X63="TIPO I",'BASE DE LIQUIDACION 2025'!$C$3,IF(X63="TIPO II",'BASE DE LIQUIDACION 2025'!$C$4,IF(X63="TIPO III",'BASE DE LIQUIDACION 2025'!$C$5,'BASE DE LIQUIDACION 2025'!$C$6))))) -> 464809.37 | AE63: =IF(Z63="SOPORTE_TELEFÓNICO",AD63,CIERRES!AC63*CIERRES!AD63) -> 464809.37
A64: BUCARAMANGA | B64: =VLOOKUP(A64,'CENTRO DE COSTOS'!A:D,4,FALSE) -> MIGUEL JULIÁN HERNÁNDEZ GUARÍN | C64: =VLOOKUP(A64,'CENTRO DE COSTOS'!A:C,2,FALSE) -> 0004-0008 | D64: 81001 | E64: TA-25-756332 | F64: FO-25-1087035 | G64: 45821.504 | H64: 45827.728 | I64: ARAUCA | J64: ARAUCA | K64: DISTRICOL GANADEROS | L64: 72184 | M64: ORDEN DE CAMBIO | N64: CIERRE | O64: CIERRE | P64: REDEBAN | Q64: AGREGADOR | R64: DISTRICOL | S64: NO_EXITOSO | T64: CB NO ENTREGA EQUIPO | U64: 19-06-2025 SE LOGRA COMUNICACIÓN CON LA SEÑORA SARAY 3102419686 VÍA WASAT, CONFIRMA GUÍA POR MEDIO DE EMPRESA DE TRANSPORTE INTERRAPIDISIMO CON NÚMERO DE GUÍA 700160079151, CON LA CUAL HIZO LA DEVOLUCIÓN DE EQUIPOS A LA EMPRESA DISTRICOL EN LA CIUDAD DE MEDELLÍN, INFORMANDO QUE ELLA YA NO CUENTA CON ESTOS EQUIPOS, SE ADJUNTA FOTO DE GUÍA SUMINISTRADA POR CLIENTE. | V64: SANTOS GONZALEZ JOHAN FABIAN | W64: 0 | X64: TIPO IV ESPECIAL | Y64: =VLOOKUP(D64,TIPOLOGIAS!A:F,5,0) -> AEREO | Z64: SOPORTE_TELEFÓNICO | AA64: 0 | AB64: 0 | AC64: 0 | AD64: =IF(AND(Z64="SOPORTE_TELEFÓNICO",OR(T64="SIN CONTACTO CON EL CB",T64="NÚMEROS DE CONTACTO ERRADOS")),0,IF(Z64="SOPORTE_TELEFÓNICO",'BASE DE LIQUIDACION 2025'!$B$9,IF(X64="TIPO I",'BASE DE LIQUIDACION 2025'!$C$3,IF(X64="TIPO II",'BASE DE LIQUIDACION 2025'!$C$4,IF(X64="TIPO III",'BASE DE LIQUIDACION 2025'!$C$5,'BASE DE LIQUIDACION 2025'!$C$6))))) -> 37904.612 | AE64: =IF(Z64="SOPORTE_TELEFÓNICO",AD64,CIERRES!AC64*CIERRES!AD64) -> 37904.612
A65: BOGOTA | B65: =VLOOKUP(A65,'CENTRO DE COSTOS'!A:D,4,FALSE) -> WILLIAM ASDRUBAL ROZO ROZO | C65: =VLOOKUP(A65,'CENTRO DE COSTOS'!A:C,2,FALSE) -> 0004-0004 | D65: 11001 | E65: TA-25-793217 | F65: FO-25-1114285 | G65: 45827.563 | H65: 45828.602 | I65: CUNDINAMARCA | J65: BOGOTA | K65: BARRIO BOSA 14 BOGOTA | L65: 28568 | M65: ORDEN DE CAMBIO | N65: CIERRE | O65: CIERRE | P65: REDEBAN | Q65: CB UNO A UNO | R65: CB UNO A UNO | S65: ILOCALIZADO | T65: CB CERRADO - DESOCUPADO | U65: 20-06-2025 SE LLEGA A DIRECCIÓN CL 56FSUR 105A 03 COMERCIAL YA NO EXISTE EN EL PUNTO SE INTENTA CONTACTÓ TELEFÓNICO CON CLIENTE A NÚMERO REGISTRADO 3183140634 TELÉFONO APAGADO. SE PREGUNTA EN COMERCIO VECINO POR EL CLIENTE HEYBAR MERA COLLAZOS EL CUAL INFORMAN QUE EL SEÑOR SE ENCUENTRA EN CHILE Y VENDIÓ EL COMERCIO | V65: ORTIZ MARTINEZ STIVEN | W65: 0 | X65: TIPO I | Y65: =VLOOKUP(D65,TIPOLOGIAS!A:F,5,0) -> TERRESTRE | Z65: VISITA_TÉCNICA | AA65: 0 | AB65: 0 | AC65: 1 | AD65: =IF(AND(Z65="SOPORTE_TELEFÓNICO",OR(T65="SIN CONTACTO CON EL CB",T65="NÚMEROS DE CONTACTO ERRADOS")),0,IF(Z65="SOPORTE_TELEFÓNICO",'BASE DE LIQUIDACION 2025'!$B$9,IF(X65="TIPO I",'BASE DE LIQUIDACION 2025'!$C$3,IF(X65="TIPO II",'BASE DE LIQUIDACION 2025'!$C$4,IF(X65="TIPO III",'BASE DE LIQUIDACION 2025'!$C$5,'BASE DE LIQUIDACION 2025'!$C$6))))) -> 44559.564 | AE65: =IF(Z65="SOPORTE_TELEFÓNICO",AD65,CIERRES!AC65*CIERRES!AD65) -> 44559.564
A66: TUNJA | B66: =VLOOKUP(A66,'CENTRO DE COSTOS'!A:D,4,FALSE) -> MIGUEL JULIÁN HERNÁNDEZ GUARÍN | C66: =VLOOKUP(A66,'CENTRO DE COSTOS'!A:C,2,FALSE) -> 0004-0008 | D66: 15238 | E66: TA-25-793202 | F66: FO-25-1114254 | G66: 45827.563 | H66: 45828.61 | I66: BOYACA | J66: DUITAMA | K66: BOYACA DUITAMA 2 | L66: 71876 | M66: ORDEN DE CAMBIO | N66: CIERRE | O66: CIERRE | P66: REDEBAN | Q66: CB UNO A UNO | R66: CB UNO A UNO | S66: SOLICITUD_CANCELADA | T66: CANCELADO POR LA ENTIDAD | U66: 20-06-2025 SE VISITA PUNTO CLIENTE NO PERMITE EL RETIRO DE LOS EQUIPOS CLIENTE LLAMA A LA ENTIDAD PARA REPORTAR LA NOVEDAD LE INDICAN QUE EL TEMA DEL BLOQUEO FUE DEBIDO A INACTIVIDAD POR EL TEMA DEL TRASLADO EL CUAL YA REGISTRA REALIZADO LE INDICAN NO ENTREGAR LOS EQUIPOS YA QUE ESTA ESCALADO EL CASO PARA LA REACTIVACION DEL PUNTO NUEVAMENTE. | V66: RODRIGUEZ MURCIA YERSON IVAN | W66: LN00M086 | X66: TIPO II | Y66: =VLOOKUP(D66,TIPOLOGIAS!A:F,5,0) -> TERRESTRE | Z66: VISITA_TÉCNICA | AA66: 0 | AB66: 0 | AC66: 1 | AD66: =IF(AND(Z66="SOPORTE_TELEFÓNICO",OR(T66="SIN CONTACTO CON EL CB",T66="NÚMEROS DE CONTACTO ERRADOS")),0,IF(Z66="SOPORTE_TELEFÓNICO",'BASE DE LIQUIDACION 2025'!$B$9,IF(X66="TIPO I",'BASE DE LIQUIDACION 2025'!$C$3,IF(X66="TIPO II",'BASE DE LIQUIDACION 2025'!$C$4,IF(X66="TIPO III",'BASE DE LIQUIDACION 2025'!$C$5,'BASE DE LIQUIDACION 2025'!$C$6))))) -> 134410.88 | AE66: =IF(Z66="SOPORTE_TELEFÓNICO",AD66,CIERRES!AC66*CIERRES!AD66) -> 134410.88
A67: BOGOTA | B67: =VLOOKUP(A67,'CENTRO DE COSTOS'!A:D,4,FALSE) -> WILLIAM ASDRUBAL ROZO ROZO | C67: =VLOOKUP(A67,'CENTRO DE COSTOS'!A:C,2,FALSE) -> 0004-0004 | D67: 11001 | E67: TA-25-793242 | F67: FO-25-1114319 | G67: 45827.563 | H67: 45828.621 | I67: CUNDINAMARCA | J67: BOGOTA | K67: BARRIO FLORESTA 5 | L67: 31094 | M67: ORDEN DE CAMBIO | N67: CIERRE | O67: CIERRE | P67: REDEBAN | Q67: CB UNO A UNO | R67: CB UNO A UNO | S67: NO_EXITOSO | T67: CB NO ENTREGA EQUIPO | U67: 20-06-2025 SE REALIZA VISITA A DIRECCIÓN DE COMERCIO, SE ENCUENTRA COMERCIO CERRADO, SE REALIZA LLAMADA TELEFÓNICA SE HABLA CON LA SRA DERLY TATIANA RODRIGUEZ QUIEN INDICA QUE YA NO TRABAJA EN ESTE COMERCIO, INDICADA COMUNICARSE CON LA SRA.GLADYS GARZÓN AL NÚMERO 3005546601 QUIEN ES LA DUEÑA DEL COMERCIO, SE INDICA A LA SRA DERLY QUE DEBEN COMUNICARSE NUEVAMENTE Y SOLICITAR LA VISITA DE RETIRO DE LOS EQUIPOS CUANDO LA SRA. GLADYS GARZÓN SE ENCUENTRE DE REGRESO EN LA CIUDAD, INDICA QUE DESCONOCE LA FECHA EXACTA DE REGRESO DE LA SRA. GLADIS A LA CIUDAD | V67: MURCIA HERNANDEZ HARVEY IGNACIO | W67: BYZZZ591 | X67: TIPO I | Y67: =VLOOKUP(D67,TIPOLOGIAS!A:F,5,0) -> TERRESTRE | Z67: VISITA_TÉCNICA | AA67: 0 | AC67: 1 | AD67: =IF(AND(Z67="SOPORTE_TELEFÓNICO",OR(T67="SIN CONTACTO CON EL CB",T67="NÚMEROS DE CONTACTO ERRADOS")),0,IF(Z67="SOPORTE_TELEFÓNICO",'BASE DE LIQUIDACION 2025'!$B$9,IF(X67="TIPO I",'BASE DE LIQUIDACION 2025'!$C$3,IF(X67="TIPO II",'BASE DE LIQUIDACION 2025'!$C$4,IF(X67="TIPO III",'BASE DE LIQUIDACION 2025'!$C$5,'BASE DE LIQUIDACION 2025'!$C$6))))) -> 44559.564 | AE67: =IF(Z67="SOPORTE_TELEFÓNICO",AD67,CIERRES!AC67*CIERRES!AD67) -> 44559.564
A68: CUCUTA | B68: =VLOOKUP(A68,'CENTRO DE COSTOS'!A:D,4,FALSE) -> MIGUEL JULIÁN HERNÁNDEZ GUARÍN | C68: =VLOOKUP(A68,'CENTRO DE COSTOS'!A:C,2,FALSE) -> 0004-0008 | D68: 54001 | E68: TA-25-793210 | F68: FO-25-1114274 | G68: 45827.563 | H68: 45828.637 | I68: NORTE DE SANTANDER | J68: CUCUTA | K68: BARRIO SAN LUIS CUCUTA 23 | L68: 71617 | M68: ORDEN DE CAMBIO | N68: CIERRE | O68: CIERRE | P68: REDEBAN | Q68: CB UNO A UNO | R68: CB UNO A UNO | S68: ILOCALIZADO | T68: CB CERRADO - DESOCUPADO | U68: 20-06-2025 SE REALIZÓ VISITA A LA DIRECCIÓN ASIGNADA Y SE ENCUENTRA QUE YA NO EXISTE EL CB SE INTENTARON LLAMADAS A LOS NÚMEROS 3115427001-3156162219 Y NO SE OBTUVO COMUNICACIÓN | V68: MORA VEGA JEAMPIER | W68: 0 | X68: TIPO I | Y68: =VLOOKUP(D68,TIPOLOGIAS!A:F,5,0) -> TERRESTRE | Z68: VISITA_TÉCNICA | AA68: 0 | AB68: 0 | AC68: 1 | AD68: =IF(AND(Z68="SOPORTE_TELEFÓNICO",OR(T68="SIN CONTACTO CON EL CB",T68="NÚMEROS DE CONTACTO ERRADOS")),0,IF(Z68="SOPORTE_TELEFÓNICO",'BASE DE LIQUIDACION 2025'!$B$9,IF(X68="TIPO I",'BASE DE LIQUIDACION 2025'!$C$3,IF(X68="TIPO II",'BASE DE LIQUIDACION 2025'!$C$4,IF(X68="TIPO III",'BASE DE LIQUIDACION 2025'!$C$5,'BASE DE LIQUIDACION 2025'!$C$6))))) -> 44559.564 | AE68: =IF(Z68="SOPORTE_TELEFÓNICO",AD68,CIERRES!AC68*CIERRES!AD68) -> 44559.564
A69: CUCUTA | B69: =VLOOKUP(A69,'CENTRO DE COSTOS'!A:D,4,FALSE) -> MIGUEL JULIÁN HERNÁNDEZ GUARÍN | C69: =VLOOKUP(A69,'CENTRO DE COSTOS'!A:C,2,FALSE) -> 0004-0008 | D69: 54001 | E69: TA-25-793223 | F69: FO-25-1114299 | G69: 45827.563 | H69: 45828.736 | I69: NORTE DE SANTANDER | J69: CUCUTA | K69: PTM CUCUTA AUTOPARTES EL TRAIL | L69: 49137 | M69: ORDEN DE CAMBIO | N69: CIERRE | O69: RECUPERACION DE EQUIPOS | P69: REDEBAN | Q69: AGREGADOR | R69: COMCARD - PTM | S69: ILOCALIZADO | T69: CB CERRADO - DESOCUPADO | U69: 20-06-2025 SE VISITA CB EN DIRECCION, NO SE ENCUENTRA CB EN SITIO, SE INTENTA COMUNICACION CON EL CLIENTE SIN RESPUESTA, CB ILOCALIZABLE. | V69: NARANJO AFANADOR RUBEN JESUS | W69: 0 | X69: TIPO I | Y69: =VLOOKUP(D69,TIPOLOGIAS!A:F,5,0) -> TERRESTRE | Z69: VISITA_TÉCNICA | AA69: 0 | AB69: 0 | AC69: 1 | AD69: =IF(AND(Z69="SOPORTE_TELEFÓNICO",OR(T69="SIN CONTACTO CON EL CB",T69="NÚMEROS DE CONTACTO ERRADOS")),0,IF(Z69="SOPORTE_TELEFÓNICO",'BASE DE LIQUIDACION 2025'!$B$9,IF(X69="TIPO I",'BASE DE LIQUIDACION 2025'!$C$3,IF(X69="TIPO II",'BASE DE LIQUIDACION 2025'!$C$4,IF(X69="TIPO III",'BASE DE LIQUIDACION 2025'!$C$5,'BASE DE LIQUIDACION 2025'!$C$6))))) -> 44559.564 | AE69: =IF(Z69="SOPORTE_TELEFÓNICO",AD69,CIERRES!AC69*CIERRES!AD69) -> 44559.564
A70: BOGOTA | B70: =VLOOKUP(A70,'CENTRO DE COSTOS'!A:D,4,FALSE) -> WILLIAM ASDRUBAL ROZO ROZO | C70: =VLOOKUP(A70,'CENTRO DE COSTOS'!A:C,2,FALSE) -> 0004-0004 | D70: 25754 | E70: TA-25-789495 | F70: FO-25-1110047 | G70: 45825.627 | H70: 45828.755 | I70: CUNDINAMARCA | J70: SOACHA | K70: BARRIO DUCALES 1 SECTOR SOACHA | L70: 66140 | M70: ORDEN DE CAMBIO | N70: CIERRE | O70: RECUPERACION DE EQUIPOS | P70: REDEBAN | Q70: CB UNO A UNO | R70: CB UNO A UNO | S70: EJECUTADO_EXITOSO | T70: CIERRE EXITOSO | U70: 20-06-2025 SE REALIZA RETIRO DE EQUIPOS SIN NOVEDAD. | V70: LOZADA ROJAS CHRISTIAN ANDRES | W70: 1A00N052 | X70: TIPO I | Y70: =VLOOKUP(D70,TIPOLOGIAS!A:F,5,0) -> TERRESTRE | Z70: VISITA_TÉCNICA | AA70: 1074903 | AB70: 547376 | AC70: 1 | AD70: =IF(AND(Z70="SOPORTE_TELEFÓNICO",OR(T70="SIN CONTACTO CON EL CB",T70="NÚMEROS DE CONTACTO ERRADOS")),0,IF(Z70="SOPORTE_TELEFÓNICO",'BASE DE LIQUIDACION 2025'!$B$9,IF(X70="TIPO I",'BASE DE LIQUIDACION 2025'!$C$3,IF(X70="TIPO II",'BASE DE LIQUIDACION 2025'!$C$4,IF(X70="TIPO III",'BASE DE LIQUIDACION 2025'!$C$5,'BASE DE LIQUIDACION 2025'!$C$6))))) -> 44559.564 | AE70: =IF(Z70="SOPORTE_TELEFÓNICO",AD70,CIERRES!AC70*CIERRES!AD70) -> 44559.564
A71: PEREIRA | B71: =VLOOKUP(A71,'CENTRO DE COSTOS'!A:D,4,FALSE) -> DIEGO FERNANDO HENAO CARDONA | C71: =VLOOKUP(A71,'CENTRO DE COSTOS'!A:C,2,FALSE) -> 0004-0002 | D71: 63001 | E71: TA-25-793211 | F71: FO-25-1114276 | G71: 45827.563 | H71: 45829.428 | I71: QUINDIO | J71: ARMENIA | K71: BARRIO LA GRECIA ARMENIA | L71: 73952 | M71: ORDEN DE CAMBIO | N71: CIERRE | O71: CIERRE | P71: REDEBAN | Q71: CB UNO A UNO | R71: CB UNO A UNO | S71: ILOCALIZADO | T71: CB CERRADO - DESOCUPADO | U71: 21-06-2025 SE VISITA DIRECCIÓN PERO NO HAY NADIE EN COMERCIO SE ENTRA CERRADO, SE LLAMA A CONTACTO PERO TAMPOCO HAY RESPUESTA. | V71: SANCHEZ SOLORZANO JUAN SEBASTIAN | W71: MN0SZ966 | X71: TIPO II | Y71: =VLOOKUP(D71,TIPOLOGIAS!A:F,5,0) -> TERRESTRE | Z71: VISITA_TÉCNICA | AA71: 0 | AB71: 0 | AC71: 1 | AD71: =IF(AND(Z71="SOPORTE_TELEFÓNICO",OR(T71="SIN CONTACTO CON EL CB",T71="NÚMEROS DE CONTACTO ERRADOS")),0,IF(Z71="SOPORTE_TELEFÓNICO",'BASE DE LIQUIDACION 2025'!$B$9,IF(X71="TIPO I",'BASE DE LIQUIDACION 2025'!$C$3,IF(X71="TIPO II",'BASE DE LIQUIDACION 2025'!$C$4,IF(X71="TIPO III",'BASE DE LIQUIDACION 2025'!$C$5,'BASE DE LIQUIDACION 2025'!$C$6))))) -> 134410.88 | AE71: =IF(Z71="SOPORTE_TELEFÓNICO",AD71,CIERRES!AC71*CIERRES!AD71) -> 134410.88
A72: CALI | B72: =VLOOKUP(A72,'CENTRO DE COSTOS'!A:D,4,FALSE) -> DIEGO FERNANDO HENAO CARDONA | C72: =VLOOKUP(A72,'CENTRO DE COSTOS'!A:C,2,FALSE) -> 0004-0003 | D72: 76001 | E72: TA-25-793215 | F72: FO-25-1114281 | G72: 45827.563 | H72: 45829.491 | I72: VALLE DEL CAUCA | J72: CALI | K72: BARRIO VALLE DEL LILI CALI 8 | L72: 75111 | M72: ORDEN DE CAMBIO | N72: CIERRE | O72: CIERRE | P72: REDEBAN | Q72: CB UNO A UNO | R72: CB UNO A UNO | S72: NO_EXITOSO | T72: CB NO ENTREGA EQUIPO | U72: 21-06-2025 SE LLAMA AL CONTACTO Y CONTESTA LA SEÑORA PAOLA LÓPEZ Y SE INFORMA SOBRE LA ACTIVIDAD A REALIZAR E INDICA QUE SE HABÍA DESCUADRADO Y NO HABÍA COMPENSANDO OPORTUNAMENTE PERO QUE YA VA A REALIZAR EL PROCESO DE COMPENSACIÓN Y DESEA CONTINUAR CON LA OPERACIÓN. NO DESEA CERRAR EL CB Y DICE YA ESTÁ EN LA SOLUCIÓN CON EL BANCO | V72: BOLAÑOS TABORDA JORGE ENRIQUE | W72: 0 | X72: TIPO I | Y72: =VLOOKUP(D72,TIPOLOGIAS!A:F,5,0) -> TERRESTRE | Z72: SOPORTE_TELEFÓNICO | AA72: 0 | AB72: 0 | AC72: 0 | AD72: =IF(AND(Z72="SOPORTE_TELEFÓNICO",OR(T72="SIN CONTACTO CON EL CB",T72="NÚMEROS DE CONTACTO ERRADOS")),0,IF(Z72="SOPORTE_TELEFÓNICO",'BASE DE LIQUIDACION 2025'!$B$9,IF(X72="TIPO I",'BASE DE LIQUIDACION 2025'!$C$3,IF(X72="TIPO II",'BASE DE LIQUIDACION 2025'!$C$4,IF(X72="TIPO III",'BASE DE LIQUIDACION 2025'!$C$5,'BASE DE LIQUIDACION 2025'!$C$6))))) -> 37904.612 | AE72: =IF(Z72="SOPORTE_TELEFÓNICO",AD72,CIERRES!AC72*CIERRES!AD72) -> 37904.612
A73: CALI | B73: =VLOOKUP(A73,'CENTRO DE COSTOS'!A:D,4,FALSE) -> DIEGO FERNANDO HENAO CARDONA | C73: =VLOOKUP(A73,'CENTRO DE COSTOS'!A:C,2,FALSE) -> 0004-0003 | D73: 19573 | E73: TA-25-793205 | F73: FO-25-1114261 | G73: 45827.563 | H73: 45829.494 | I73: CAUCA | J73: PUERTO TEJADA | K73: BARRIO CENTRO PUERTO TEJADA 10 | L73: 75686 | M73: ORDEN DE CAMBIO | N73: CIERRE | O73: CIERRE | P73: REDEBAN | Q73: CB UNO A UNO | R73: CB UNO A UNO | S73: ILOCALIZADO | T73: CB CERRADO - DESOCUPADO | U73: 21-06-2025 SE VISITA EL COMERCIO SE ENCUENTRA CERRADO, SE LLAMA AL CLIENTE A LOS NÚMEROS 3156920109, 3215931292 SIN RESPUESTA, LA VISITA ES FALLIDA CIERRE NO EXISITOSO | V73: HERRERA MONAR GEOVANNY | W73: 1000R504 | X73: TIPO II | Y73: =VLOOKUP(D73,TIPOLOGIAS!A:F,5,0) -> TERRESTRE | Z73: VISITA_TÉCNICA | AA73: 0 | AB73: 0 | AC73: 1 | AD73: =IF(AND(Z73="SOPORTE_TELEFÓNICO",OR(T73="SIN CONTACTO CON EL CB",T73="NÚMEROS DE CONTACTO ERRADOS")),0,IF(Z73="SOPORTE_TELEFÓNICO",'BASE DE LIQUIDACION 2025'!$B$9,IF(X73="TIPO I",'BASE DE LIQUIDACION 2025'!$C$3,IF(X73="TIPO II",'BASE DE LIQUIDACION 2025'!$C$4,IF(X73="TIPO III",'BASE DE LIQUIDACION 2025'!$C$5,'BASE DE LIQUIDACION 2025'!$C$6))))) -> 134410.88 | AE73: =IF(Z73="SOPORTE_TELEFÓNICO",AD73,CIERRES!AC73*CIERRES!AD73) -> 134410.88
A74: PASTO | B74: =VLOOKUP(A74,'CENTRO DE COSTOS'!A:D,4,FALSE) -> DIEGO FERNANDO HENAO CARDONA | C74: =VLOOKUP(A74,'CENTRO DE COSTOS'!A:C,2,FALSE) -> 0004-0003 | D74: 86865 | E74: TA-25-789449 | F74: FO-25-1104583 | G74: 45825.627 | H74: 45832.364 | I74: PUTUMAYO | J74: VALLE DEL GUAMUEZ | K74: VALLE DEL GUAMUEZ II PUTUMAYO | L74: 13589 | M74: ORDEN DE CAMBIO | N74: CIERRE | O74: CIERRE | P74: REDEBAN | Q74: CB UNO A UNO | R74: CB UNO A UNO | S74: NO_EXITOSO | T74: CB NO ENTREGA EQUIPO | U74: 24-06-2025 SE HABLA CON LA ESPOSA DEL SEÑOR WILSON QUE ES LA ENCARGADA DEL CB PERO INDICA QUE ESTAN EN UN PROCESO DE REACTIVACION CON LA ENTIDAD, POR LO TANTO ESTAN EN ESPERA DE RESPUESTA DE LA ENTIDAD YA QUE ESTAN AL DIA EN TODO POR LO TANTO NO DESEA CERRAR EL CORRESPONSAL. | V74: HENAO CARDONA DIEGO FERNANDO | W74: 0 | X74: TIPO IV | Y74: =VLOOKUP(D74,TIPOLOGIAS!A:F,5,0) -> TERRESTRE | Z74: SOPORTE_TELEFÓNICO | AA74: 0 | AB74: 0 | AC74: 0 | AD74: =IF(AND(Z74="SOPORTE_TELEFÓNICO",OR(T74="SIN CONTACTO CON EL CB",T74="NÚMEROS DE CONTACTO ERRADOS")),0,IF(Z74="SOPORTE_TELEFÓNICO",'BASE DE LIQUIDACION 2025'!$B$9,IF(X74="TIPO I",'BASE DE LIQUIDACION 2025'!$C$3,IF(X74="TIPO II",'BASE DE LIQUIDACION 2025'!$C$4,IF(X74="TIPO III",'BASE DE LIQUIDACION 2025'!$C$5,'BASE DE LIQUIDACION 2025'!$C$6))))) -> 37904.612 | AE74: =IF(Z74="SOPORTE_TELEFÓNICO",AD74,CIERRES!AC74*CIERRES!AD74) -> 37904.612
A75: MONTERIA | B75: =VLOOKUP(A75,'CENTRO DE COSTOS'!A:D,4,FALSE) -> JOSE MAURICIO HERNANDEZ ROJAS | C75: =VLOOKUP(A75,'CENTRO DE COSTOS'!A:C,2,FALSE) -> 0004-0001 | D75: 23807 | E75: TA-25-789469 | F75: FO-25-1104634 | G75: 45825.627 | H75: 45832.486 | I75: CORDOBA | J75: TIERRALTA | K75: BARRIO LA PAZ TIERRALTA | L75: 60080 | M75: ORDEN DE CAMBIO | N75: CIERRE | O75: CIERRE | P75: REDEBAN | Q75: CB UNO A UNO | R75: CB UNO A UNO | S75: NO_EXITOSO | T75: CB NO ENTREGA EQUIPO | U75: 24-06-2025 SE LLEGA A CB, INFMAN QUE EL ENCARGADO DEL CB RECOGIÓ LOS EQUIPOS Y ELLOS NO SABEN DÓNDE LOS GUARDO Y TAMPOCO SE ENCUENTRA LA PERSONA ENCARGADA EN EL MUNICIPIO LE INTENTAN COMUNICAR CON LA PERSONA, NO CONTESTA | V75: COGOLLO ROSSO CAMILO ANDRES | W75: MA00B486 | X75: TIPO III | Y75: =VLOOKUP(D75,TIPOLOGIAS!A:F,5,0) -> TERRESTRE | Z75: VISITA_TÉCNICA | AA75: 0 | AB75: 0 | AC75: 1 | AD75: =IF(AND(Z75="SOPORTE_TELEFÓNICO",OR(T75="SIN CONTACTO CON EL CB",T75="NÚMEROS DE CONTACTO ERRADOS")),0,IF(Z75="SOPORTE_TELEFÓNICO",'BASE DE LIQUIDACION 2025'!$B$9,IF(X75="TIPO I",'BASE DE LIQUIDACION 2025'!$C$3,IF(X75="TIPO II",'BASE DE LIQUIDACION 2025'!$C$4,IF(X75="TIPO III",'BASE DE LIQUIDACION 2025'!$C$5,'BASE DE LIQUIDACION 2025'!$C$6))))) -> 222904.07 | AE75: =IF(Z75="SOPORTE_TELEFÓNICO",AD75,CIERRES!AC75*CIERRES!AD75) -> 222904.07
A76: VILLAVICENCIO | B76: =VLOOKUP(A76,'CENTRO DE COSTOS'!A:D,4,FALSE) -> KEVIN ALEXIS CORZO BUSTOS | C76: =VLOOKUP(A76,'CENTRO DE COSTOS'!A:C,2,FALSE) -> 0004-0007 | D76: 50313 | E76: TA-25-789475 | F76: FO-25-1118927 | G76: 45825.627 | H76: 45832.504 | I76: META | J76: GRANADA | K76: BARRIO VILLA OLIMPICA GRANADA | L76: 64162 | M76: ORDEN DE CAMBIO | N76: CIERRE | O76: CIERRE | P76: REDEBAN | Q76: CB UNO A UNO | R76: CB UNO A UNO | S76: EJECUTADO_EXITOSO | T76: CIERRE EXITOSO | U76: 24-06-2025 SE REALIZA CIERRE A SOLICITUD DE CLIENTE, ORUEBAS OK | V76: PEDREROS CONTRERAS MICHAEL STEVENS | W76: LA01Z147 | X76: TIPO II | Y76: =VLOOKUP(D76,TIPOLOGIAS!A:F,5,0) -> TERRESTRE | Z76: VISITA_TÉCNICA | AA76: 786587 | AB76: 1113870 | AC76: 1 | AD76: =IF(AND(Z76="SOPORTE_TELEFÓNICO",OR(T76="SIN CONTACTO CON EL CB",T76="NÚMEROS DE CONTACTO ERRADOS")),0,IF(Z76="SOPORTE_TELEFÓNICO",'BASE DE LIQUIDACION 2025'!$B$9,IF(X76="TIPO I",'BASE DE LIQUIDACION 2025'!$C$3,IF(X76="TIPO II",'BASE DE LIQUIDACION 2025'!$C$4,IF(X76="TIPO III",'BASE DE LIQUIDACION 2025'!$C$5,'BASE DE LIQUIDACION 2025'!$C$6))))) -> 134410.88 | AE76: =IF(Z76="SOPORTE_TELEFÓNICO",AD76,CIERRES!AC76*CIERRES!AD76) -> 134410.88
A77: MONTERIA | B77: =VLOOKUP(A77,'CENTRO DE COSTOS'!A:D,4,FALSE) -> JOSE MAURICIO HERNANDEZ ROJAS | C77: =VLOOKUP(A77,'CENTRO DE COSTOS'!A:C,2,FALSE) -> 0004-0001 | D77: 23068 | E77: TA-25-793207 | F77: FO-25-1114268 | G77: 45827.563 | H77: 45832.543 | I77: CORDOBA | J77: AYAPEL | K77: BARRIO CENTRO AYAPEL 4 | L77: 66024 | M77: ORDEN DE CAMBIO | N77: CIERRE | O77: CIERRE | P77: REDEBAN | Q77: CB UNO A UNO | R77: CB UNO A UNO | S77: NO_EXITOSO | T77: CB NO ENTREGA EQUIPO | U77: 24-06-2025 SE LLEGÓ A SITIO Y EL CLIENTE INFORMA QUE ESTÁ OPERANDO DE MANERA NORMAL, QUE NO SOLICITÓ CIERRE, QUE TENÍA PENDIENTE UN TRASLADO Y LO REALIZARON LA SEMANA PASADA. | V77: CALDERA SALCEDO CARLOS JULIO | W77: 9A00N488 | X77: TIPO III | Y77: =VLOOKUP(D77,TIPOLOGIAS!A:F,5,0) -> TERRESTRE | Z77: VISITA_TÉCNICA | AA77: 0 | AB77: 0 | AC77: 1 | AD77: =IF(AND(Z77="SOPORTE_TELEFÓNICO",OR(T77="SIN CONTACTO CON EL CB",T77="NÚMEROS DE CONTACTO ERRADOS")),0,IF(Z77="SOPORTE_TELEFÓNICO",'BASE DE LIQUIDACION 2025'!$B$9,IF(X77="TIPO I",'BASE DE LIQUIDACION 2025'!$C$3,IF(X77="TIPO II",'BASE DE LIQUIDACION 2025'!$C$4,IF(X77="TIPO III",'BASE DE LIQUIDACION 2025'!$C$5,'BASE DE LIQUIDACION 2025'!$C$6))))) -> 222904.07 | AE77: =IF(Z77="SOPORTE_TELEFÓNICO",AD77,CIERRES!AC77*CIERRES!AD77) -> 222904.07
A78: MONTERIA | B78: =VLOOKUP(A78,'CENTRO DE COSTOS'!A:D,4,FALSE) -> JOSE MAURICIO HERNANDEZ ROJAS | C78: =VLOOKUP(A78,'CENTRO DE COSTOS'!A:C,2,FALSE) -> 0004-0001 | D78: 23500 | E78: TA-25-789454 | F78: FO-25-1104595 | G78: 45825.627 | H78: 45832.625 | I78: CORDOBA | J78: MOÑITOS | K78: BARRIO MIRAMAR MONITOS | L78: 31698 | M78: ORDEN DE CAMBIO | N78: CIERRE | O78: CIERRE | P78: REDEBAN | Q78: CB UNO A UNO | R78: CB UNO A UNO | S78: NO_EXITOSO | T78: CB NO ENTREGA EQUIPO | U78: 24-06-2025 SE LLEGA AL SITIO ATIENDE EL SR FRAI NARVÁEZ CON CC 11170895 INFORMA QUE NO ENTREGA LOS EQUIPOS YA QUE EL PROPIETARIO DEL CB INDICA QUE EL BANCO NO A NOTIFICADO EL CIERRE Y ESTÁ SE DIGORA A UNA SUCURSAL PARA SECCORARCE DEL MOTIVO DEL CIERRE, E INTENTAR ACTIVAR NUEVAMENTE, POR LO QUE NO ENTREGAN EQUIPOS. | V78: CASSIANI PEREZ RAUL RAMIRO | W78: 0 | X78: TIPO III | Y78: =VLOOKUP(D78,TIPOLOGIAS!A:F,5,0) -> TERRESTRE | Z78: VISITA_TÉCNICA | AA78: 0 | AB78: 0 | AC78: 1 | AD78: =IF(AND(Z78="SOPORTE_TELEFÓNICO",OR(T78="SIN CONTACTO CON EL CB",T78="NÚMEROS DE CONTACTO ERRADOS")),0,IF(Z78="SOPORTE_TELEFÓNICO",'BASE DE LIQUIDACION 2025'!$B$9,IF(X78="TIPO I",'BASE DE LIQUIDACION 2025'!$C$3,IF(X78="TIPO II",'BASE DE LIQUIDACION 2025'!$C$4,IF(X78="TIPO III",'BASE DE LIQUIDACION 2025'!$C$5,'BASE DE LIQUIDACION 2025'!$C$6))))) -> 222904.07 | AE78: =IF(Z78="SOPORTE_TELEFÓNICO",AD78,CIERRES!AC78*CIERRES!AD78) -> 222904.07
A79: NEIVA | B79: =VLOOKUP(A79,'CENTRO DE COSTOS'!A:D,4,FALSE) -> KEVIN ALEXIS CORZO BUSTOS | C79: =VLOOKUP(A79,'CENTRO DE COSTOS'!A:C,2,FALSE) -> 0004-0007 | D79: 18001 | E79: TA-25-793204 | F79: FO-25-1114258 | G79: 45827.563 | H79: 45832.632 | I79: CAQUETA | J79: FLORENCIA | K79: BARRIO LA ESTRELLA FLORENCIA | L79: 78426 | M79: ORDEN DE CAMBIO | N79: CIERRE | O79: CIERRE | P79: REDEBAN | Q79: CB UNO A UNO | R79: CB UNO A UNO | S79: SOLICITUD_CANCELADA | T79: CANCELADO POR LA ENTIDAD | U79: 24-06-2025 SE REALIZA VISITA AL CB Y CLIENTE NO PERMITE EL CIERRE YA QUE NO HA SOLICITADO EL CIERRE, MANIFIESTA QUE EL DÍA JUEVES 19 DE JUNIO LE HICIERON EL TRASLADO DEL CB Y HASTA EL MOMENTO NO LE HAN DESBLOQUEADO EL CB, MANIFIESTA QUE ESTÁ A LA ESPERA DE UN CORREO DEL BANCO PARA EL DESBLOQUEO. | V79: BERMUDEZ SANCHEZ JOSE NEYBER | W79: V10ZZ346 | X79: TIPO IV | Y79: =VLOOKUP(D79,TIPOLOGIAS!A:F,5,0) -> TERRESTRE | Z79: VISITA_TÉCNICA | AA79: 0 | AB79: 0 | AC79: 1 | AD79: =IF(AND(Z79="SOPORTE_TELEFÓNICO",OR(T79="SIN CONTACTO CON EL CB",T79="NÚMEROS DE CONTACTO ERRADOS")),0,IF(Z79="SOPORTE_TELEFÓNICO",'BASE DE LIQUIDACION 2025'!$B$9,IF(X79="TIPO I",'BASE DE LIQUIDACION 2025'!$C$3,IF(X79="TIPO II",'BASE DE LIQUIDACION 2025'!$C$4,IF(X79="TIPO III",'BASE DE LIQUIDACION 2025'!$C$5,'BASE DE LIQUIDACION 2025'!$C$6))))) -> 464809.37 | AE79: =IF(Z79="SOPORTE_TELEFÓNICO",AD79,CIERRES!AC79*CIERRES!AD79) -> 464809.37
A80: MEDELLIN | B80: =VLOOKUP(A80,'CENTRO DE COSTOS'!A:D,4,FALSE) -> JUAN SEBASTIÁN RÍOS CASTRILLÓN | C80: =VLOOKUP(A80,'CENTRO DE COSTOS'!A:C,2,FALSE) -> 0004-0005 | D80: 5088 | E80: TA-25-793198 | F80: FO-25-1114246 | G80: 45827.563 | H80: 45832.703 | I80: ANTIOQUIA | J80: BELLO | K80: BARRIO LA GABRIELA CALLE VIEJA | L80: 57039 | M80: ORDEN DE CAMBIO | N80: CIERRE | O80: CIERRE | P80: REDEBAN | Q80: CB UNO A UNO | R80: CB UNO A UNO | S80: NO_EXITOSO | T80: CB NO ENTREGA EQUIPO | U80: 24-06-2025 SE COMUNICA CON EL NÚMERO PARA CONFIRMAR VISITA Y ME INDICA EL CLIENTE QUE LA ENCARGADA NO SE ENCUENTRA EN COLOMBIA Y EL OTRO ENCARGADO NO ESTA EN MEDELLÍN EN EL MOMENTO Y EN LOCAL SE ENCUENTRA CERRADO | V80: ZAPATA LOPEZ EDWARD ASDRUBAL | W80: 0 | X80: TIPO I | Y80: =VLOOKUP(D80,TIPOLOGIAS!A:F,5,0) -> TERRESTRE | Z80: SOPORTE_TELEFÓNICO | AA80: 0 | AB80: 0 | AC80: 0 | AD80: =IF(AND(Z80="SOPORTE_TELEFÓNICO",OR(T80="SIN CONTACTO CON EL CB",T80="NÚMEROS DE CONTACTO ERRADOS")),0,IF(Z80="SOPORTE_TELEFÓNICO",'BASE DE LIQUIDACION 2025'!$B$9,IF(X80="TIPO I",'BASE DE LIQUIDACION 2025'!$C$3,IF(X80="TIPO II",'BASE DE LIQUIDACION 2025'!$C$4,IF(X80="TIPO III",'BASE DE LIQUIDACION 2025'!$C$5,'BASE DE LIQUIDACION 2025'!$C$6))))) -> 37904.612 | AE80: =IF(Z80="SOPORTE_TELEFÓNICO",AD80,CIERRES!AC80*CIERRES!AD80) -> 37904.612
A81: MEDELLIN | B81: =VLOOKUP(A81,'CENTRO DE COSTOS'!A:D,4,FALSE) -> JUAN SEBASTIÁN RÍOS CASTRILLÓN | C81: =VLOOKUP(A81,'CENTRO DE COSTOS'!A:C,2,FALSE) -> 0004-0005 | D81: 5656 | E81: TA-25-789474 | F81: FO-25-1104647 | G81: 45825.627 | H81: 45833.333 | I81: ANTIOQUIA | J81: SAN JERONIMO | K81: BARRIO VEREDA EL POMAR SAN JER | L81: 64064 | M81: ORDEN DE CAMBIO | N81: CIERRE | O81: CIERRE | P81: REDEBAN | Q81: CB UNO A UNO | R81: CB UNO A UNO | S81: NO_EXITOSO | T81: CB NO ENTREGA EQUIPO | U81: 25-06-2025 SE LLAMA AL 3206513467 Y SE HABLA CON LA SEÑORA CAMILA LA CUAL INFORMA QUE LOS DÍAS MARTES Y VIERNES TIENE TERAPIA EN MEDELLÍN POR LO CUAL NO NOS PUEDE ATENDER EL DÍA DE HOY SOLICITA REPROGRAMAR OTRO DÍA QUE NO SEA MARTES O VIERNES | V81: ALVAREZ ARENAS VICTOR HUGO | W81: 0 | X81: TIPO II | Y81: =VLOOKUP(D81,TIPOLOGIAS!A:F,5,0) -> TERRESTRE | Z81: SOPORTE_TELEFÓNICO | AA81: 0 | AB81: 0 | AC81: 0 | AD81: =IF(AND(Z81="SOPORTE_TELEFÓNICO",OR(T81="SIN CONTACTO CON EL CB",T81="NÚMEROS DE CONTACTO ERRADOS")),0,IF(Z81="SOPORTE_TELEFÓNICO",'BASE DE LIQUIDACION 2025'!$B$9,IF(X81="TIPO I",'BASE DE LIQUIDACION 2025'!$C$3,IF(X81="TIPO II",'BASE DE LIQUIDACION 2025'!$C$4,IF(X81="TIPO III",'BASE DE LIQUIDACION 2025'!$C$5,'BASE DE LIQUIDACION 2025'!$C$6))))) -> 37904.612 | AE81: =IF(Z81="SOPORTE_TELEFÓNICO",AD81,CIERRES!AC81*CIERRES!AD81) -> 37904.612
A82: CALI | B82: =VLOOKUP(A82,'CENTRO DE COSTOS'!A:D,4,FALSE) -> DIEGO FERNANDO HENAO CARDONA | C82: =VLOOKUP(A82,'CENTRO DE COSTOS'!A:C,2,FALSE) -> 0004-0003 | D82: 19532 | E82: TA-25-789497 | F82: FO-25-1104699 | G82: 45825.627 | H82: 45833.351 | I82: CAUCA | J82: PATIA | K82: BARRIO PATIA PATIA | L82: 77803 | M82: ORDEN DE CAMBIO | N82: CIERRE | O82: RECUPERACION DE EQUIPOS | P82: REDEBAN | Q82: CB UNO A UNO | R82: CB UNO A UNO | S82: NO_EXITOSO | T82: CB NO ENTREGA EQUIPO | U82: 25-06-2025 SE REALIZA VALIDACION CON EL CLIENTE PARA REALIZACION DE CIERRE, SE ENCUENTRA QUE LA ZONA EN ESTE MOMENTO NO SE PUEDE ACCEDER POR ESTAR EN CONFLICTO ARMADO Y ZONA ROJA, EL CLIENTE TIENE LOS EQUIPO EN EL SITIO PERO NO SE PUEDE CONCRETAR EL ENVIO DE LOS MISMOS YA QUE POR LOS PROBLEMAS PRESENTES EN LA ZONA NO HAY TRANSPORTADORA EN EL MOMENTO, SE QUEDA EN ESPERA DE QUE MEJORE LA SITUACION PARA DESPLAZAMIENTO DEL TECNICO A LA ZONA O SE PUEDA REALIAZR EL ENVIO DE LOS EQUIPO A LA CIUDAD DE POPAYAN POR SEGURIDAD. | V82: HENAO CARDONA DIEGO FERNANDO | W82: 0 | X82: TIPO IV | Y82: =VLOOKUP(D82,TIPOLOGIAS!A:F,5,0) -> TERRESTRE | Z82: SOPORTE_TELEFÓNICO | AA82: 0 | AB82: 0 | AC82: 0 | AD82: =IF(AND(Z82="SOPORTE_TELEFÓNICO",OR(T82="SIN CONTACTO CON EL CB",T82="NÚMEROS DE CONTACTO ERRADOS")),0,IF(Z82="SOPORTE_TELEFÓNICO",'BASE DE LIQUIDACION 2025'!$B$9,IF(X82="TIPO I",'BASE DE LIQUIDACION 2025'!$C$3,IF(X82="TIPO II",'BASE DE LIQUIDACION 2025'!$C$4,IF(X82="TIPO III",'BASE DE LIQUIDACION 2025'!$C$5,'BASE DE LIQUIDACION 2025'!$C$6))))) -> 37904.612 | AE82: =IF(Z82="SOPORTE_TELEFÓNICO",AD82,CIERRES!AC82*CIERRES!AD82) -> 37904.612
A83: CALI | B83: =VLOOKUP(A83,'CENTRO DE COSTOS'!A:D,4,FALSE) -> DIEGO FERNANDO HENAO CARDONA | C83: =VLOOKUP(A83,'CENTRO DE COSTOS'!A:C,2,FALSE) -> 0004-0003 | D83: 19473 | E83: TA-25-789467 | F83: FO-25-1104629 | G83: 45825.627 | H83: 45833.375 | I83: CAUCA | J83: MORALES | K83: BARRIO CENTRO MORALES 2 | L83: 58865 | M83: ORDEN DE CAMBIO | N83: CIERRE | O83: CIERRE | P83: REDEBAN | Q83: CB UNO A UNO | R83: CB UNO A UNO | S83: NO_EXITOSO | T83: CB NO ENTREGA EQUIPO | U83: 24-06-2025 SE REALIZA LLAMDA AL CLIENTE EN REPETIDAS OCACIONES, NO ATIENDE, SE DEJE MANSAJE DE VOZ Y POR WHAT APP, EL DIA DE HOY NOS CONTESTA LA ENCARGADA DEL CB INDICAN QUE ELLOS ESTAN REALIZANDO UN TRAMITE CON ENTIDAD YA QUE NO LES HABIAN NOTIFICADO EL CIERRE Y ESTAN A LA ESPERA DE RESPUESTA PARA MIRAR COMO PROCEDER, INDICA QUE SI DEFEINITIVAMENTE SE VA A CERRAR ELLOS NOTIFICARAN PARA LA RECOJIDA DE LOS EQUIPPOS. | V83: HENAO CARDONA DIEGO FERNANDO | W83: 0 | X83: TIPO III | Y83: =VLOOKUP(D83,TIPOLOGIAS!A:F,5,0) -> TERRESTRE | Z83: SOPORTE_TELEFÓNICO | AA83: 0 | AB83: 0 | AC83: 0 | AD83: =IF(AND(Z83="SOPORTE_TELEFÓNICO",OR(T83="SIN CONTACTO CON EL CB",T83="NÚMEROS DE CONTACTO ERRADOS")),0,IF(Z83="SOPORTE_TELEFÓNICO",'BASE DE LIQUIDACION 2025'!$B$9,IF(X83="TIPO I",'BASE DE LIQUIDACION 2025'!$C$3,IF(X83="TIPO II",'BASE DE LIQUIDACION 2025'!$C$4,IF(X83="TIPO III",'BASE DE LIQUIDACION 2025'!$C$5,'BASE DE LIQUIDACION 2025'!$C$6))))) -> 37904.612 | AE83: =IF(Z83="SOPORTE_TELEFÓNICO",AD83,CIERRES!AC83*CIERRES!AD83) -> 37904.612
A84: BOGOTA | B84: =VLOOKUP(A84,'CENTRO DE COSTOS'!A:D,4,FALSE) -> WILLIAM ASDRUBAL ROZO ROZO | C84: =VLOOKUP(A84,'CENTRO DE COSTOS'!A:C,2,FALSE) -> 0004-0004 | D84: 25899 | E84: TA-25-789458 | F84: FO-25-1104608 | G84: 45825.627 | H84: 45833.465 | I84: CUNDINAMARCA | J84: ZIPAQUIRA | K84: BARRIO SAN PABLO ZIPAQUIRA | L84: 40361 | M84: ORDEN DE CAMBIO | N84: CIERRE | O84: CIERRE | P84: REDEBAN | Q84: CB UNO A UNO | R84: CB UNO A UNO | S84: NO_EXITOSO | T84: CB NO ENTREGA EQUIPO | U84: 18-06-2025 SE REALIZA VISITA AL COMERCIO PARA EJECUTAR CIERRE DE CB BANCOLOMBIA PERO AL LLEGAR AL PUNTO LA SRA. ANDRÉS MEJORAN INFORMA QUE NO ESTÁ AUTORIZADO PARA ENTREGAR LOS EQUIPOS, PORQUE NO SE ENCUENTRA LA PERSONA ENCARGADA. | V84: CORTES VELANDIA MIGUEL ANGEL | W84: 0 | X84: TIPO II | Y84: =VLOOKUP(D84,TIPOLOGIAS!A:F,5,0) -> TERRESTRE | Z84: VISITA_TÉCNICA | AA84: 0 | AB84: 0 | AC84: 1 | AD84: =IF(AND(Z84="SOPORTE_TELEFÓNICO",OR(T84="SIN CONTACTO CON EL CB",T84="NÚMEROS DE CONTACTO ERRADOS")),0,IF(Z84="SOPORTE_TELEFÓNICO",'BASE DE LIQUIDACION 2025'!$B$9,IF(X84="TIPO I",'BASE DE LIQUIDACION 2025'!$C$3,IF(X84="TIPO II",'BASE DE LIQUIDACION 2025'!$C$4,IF(X84="TIPO III",'BASE DE LIQUIDACION 2025'!$C$5,'BASE DE LIQUIDACION 2025'!$C$6))))) -> 134410.88 | AE84: =IF(Z84="SOPORTE_TELEFÓNICO",AD84,CIERRES!AC84*CIERRES!AD84) -> 134410.88
A85: MEDELLIN | B85: =VLOOKUP(A85,'CENTRO DE COSTOS'!A:D,4,FALSE) -> JUAN SEBASTIÁN RÍOS CASTRILLÓN | C85: =VLOOKUP(A85,'CENTRO DE COSTOS'!A:C,2,FALSE) -> 0004-0005 | D85: 5148 | E85: TA-25-793200 | F85: FO-25-1114250 | G85: 45827.563 | H85: 45833.476 | I85: ANTIOQUIA | J85: EL CARMEN DE VIBORAL | K85: BARRIO CARMEN DE VIVORAL EL CARMEN DE VIBORAL | L85: 77264 | M85: ORDEN DE CAMBIO | N85: CIERRE | O85: CIERRE | P85: REDEBAN | Q85: CB UNO A UNO | R85: CB UNO A UNO | S85: SOLICITUD_CANCELADA | T85: CANCELADO POR LA ENTIDAD | U85: 25-06-2025 SE VISITA COMERCIO Y LA USUARIA INDICA QUE HUBO UN MAL ENTENDIDO PORQUE ELLOS SOLICITARON FUE UN TRASLADO, YA SE ESTÁN COMUNICANDO CON REDEBAN PARA ACLARAR TODO, POR LO TANTO NO SE PERMITE EL RETIRO SE EQUIPO | V85: RUA ALVAREZ RICHARD ANDRES | W85: SX9ZZ552 | X85: TIPO II | Y85: =VLOOKUP(D85,TIPOLOGIAS!A:F,5,0) -> TERRESTRE | Z85: VISITA_TÉCNICA | AA85: 0 | AB85: 0 | AC85: 1 | AD85: =IF(AND(Z85="SOPORTE_TELEFÓNICO",OR(T85="SIN CONTACTO CON EL CB",T85="NÚMEROS DE CONTACTO ERRADOS")),0,IF(Z85="SOPORTE_TELEFÓNICO",'BASE DE LIQUIDACION 2025'!$B$9,IF(X85="TIPO I",'BASE DE LIQUIDACION 2025'!$C$3,IF(X85="TIPO II",'BASE DE LIQUIDACION 2025'!$C$4,IF(X85="TIPO III",'BASE DE LIQUIDACION 2025'!$C$5,'BASE DE LIQUIDACION 2025'!$C$6))))) -> 134410.88 | AE85: =IF(Z85="SOPORTE_TELEFÓNICO",AD85,CIERRES!AC85*CIERRES!AD85) -> 134410.88
A86: BUCARAMANGA | B86: =VLOOKUP(A86,'CENTRO DE COSTOS'!A:D,4,FALSE) -> MIGUEL JULIÁN HERNÁNDEZ GUARÍN | C86: =VLOOKUP(A86,'CENTRO DE COSTOS'!A:C,2,FALSE) -> 0004-0008 | D86: 68001 | E86: TA-25-793224 | F86: FO-25-1118936 | G86: 45827.563 | H86: 45835.344 | I86: SANTANDER | J86: BUCARAMANGA | K86: PTM BUCARAMANGA DROGUERIA FARM | L86: 73960 | M86: ORDEN DE CAMBIO | N86: CIERRE | O86: RECUPERACION DE EQUIPOS | P86: REDEBAN | Q86: AGREGADOR | R86: COMCARD - PTM | S86: NO_EXITOSO | T86: CB NO ENTREGA EQUIPO | U86: 26-06-2025 SE VISITA COMERCIO PARA RETIRAR EQUIPOS DE CB BANCOLOMBIA PERO AL MOMENTO EL SEÑOR INDICA SOLO TENER LA PLACA 911628 PERO AL VERIFICAR EN SISTEMA PERTENECE A UN CODIGO DE COMERCIO PERSONAL DE LA DROGUERÍA. POR LO ANTERIOR SE INDICA QUE NO ES LA PLACA DE EL CORRESPONSAL, YA QUE SE SOLICITA INVENTARIO CON REDEBAN, QUIEN NOS INDICA LA PLACAS INSTALADAS EN CORRESPONSAL BANCARIO, Y SE LE DA LA INFORMACIÓN AL SEÑOR PARA QUE VERIFIQUE Y BUSQUE YA QUE DICE NO ENCONTRÓ MÁS . | V86: PEÑA DIAZ IVAN YESID | W86: MN0SZ974 | X86: TIPO I | Y86: =VLOOKUP(D86,TIPOLOGIAS!A:F,5,0) -> TERRESTRE | Z86: VISITA_TÉCNICA | AA86: 0 | AB86: 0 | AC86: 2 | AD86: =IF(AND(Z86="SOPORTE_TELEFÓNICO",OR(T86="SIN CONTACTO CON EL CB",T86="NÚMEROS DE CONTACTO ERRADOS")),0,IF(Z86="SOPORTE_TELEFÓNICO",'BASE DE LIQUIDACION 2025'!$B$9,IF(X86="TIPO I",'BASE DE LIQUIDACION 2025'!$C$3,IF(X86="TIPO II",'BASE DE LIQUIDACION 2025'!$C$4,IF(X86="TIPO III",'BASE DE LIQUIDACION 2025'!$C$5,'BASE DE LIQUIDACION 2025'!$C$6))))) -> 44559.564 | AE86: =IF(Z86="SOPORTE_TELEFÓNICO",AD86,CIERRES!AC86*CIERRES!AD86) -> 89119.128
A87: VILLAVICENCIO | B87: =VLOOKUP(A87,'CENTRO DE COSTOS'!A:D,4,FALSE) -> KEVIN ALEXIS CORZO BUSTOS | C87: =VLOOKUP(A87,'CENTRO DE COSTOS'!A:C,2,FALSE) -> 0004-0007 | D87: 50006 | E87: TA-25-793209 | F87: FO-25-1114272 | G87: 45827.563 | H87: 45835.423 | I87: META | J87: ACACIAS | K87: BARRIO BACHUE ACACIAS 1 | L87: 48109 | M87: ORDEN DE CAMBIO | N87: CIERRE | O87: CIERRE | P87: REDEBAN | Q87: CB UNO A UNO | R87: CB UNO A UNO | S87: ILOCALIZADO | T87: CB CERRADO - DESOCUPADO | U87: 27-06-2025 SE REALIZA VISITA A COMERCIO LOCAL CERRADO NO EXISTE CB NO ES POSIBLE COMUNICACIÓN CON TITULAR 3133560603 | V87: CASTRILLON URREA LONDIER LEANDRO | W87: 0 | X87: TIPO II | Y87: =VLOOKUP(D87,TIPOLOGIAS!A:F,5,0) -> TERRESTRE | Z87: VISITA_TÉCNICA | AA87: 0 | AB87: 0 | AC87: 1 | AD87: =IF(AND(Z87="SOPORTE_TELEFÓNICO",OR(T87="SIN CONTACTO CON EL CB",T87="NÚMEROS DE CONTACTO ERRADOS")),0,IF(Z87="SOPORTE_TELEFÓNICO",'BASE DE LIQUIDACION 2025'!$B$9,IF(X87="TIPO I",'BASE DE LIQUIDACION 2025'!$C$3,IF(X87="TIPO II",'BASE DE LIQUIDACION 2025'!$C$4,IF(X87="TIPO III",'BASE DE LIQUIDACION 2025'!$C$5,'BASE DE LIQUIDACION 2025'!$C$6))))) -> 134410.88 | AE87: =IF(Z87="SOPORTE_TELEFÓNICO",AD87,CIERRES!AC87*CIERRES!AD87) -> 134410.88
A88: MEDELLIN | B88: =VLOOKUP(A88,'CENTRO DE COSTOS'!A:D,4,FALSE) -> JUAN SEBASTIÁN RÍOS CASTRILLÓN | C88: =VLOOKUP(A88,'CENTRO DE COSTOS'!A:C,2,FALSE) -> 0004-0005 | D88: 5001 | E88: TA-25-799605 | F88: FO-25-1130557 | G88: 45832.599 | H88: 45835.458 | I88: ANTIOQUIA | J88: MEDELLIN | K88: PTM KOLORADO VARIEDADES | L88: 59432 | M88: ORDEN DE CAMBIO | N88: CIERRE | O88: CIERRE | P88: REDEBAN | Q88: AGREGADOR | R88: COMCARD - PTM | S88: ILOCALIZADO | T88: AGENDADO | U88: 27-06-2025 SE LLEGA A LA DIRECCIÓN SUMINISTRADA POR LA APLICACIÓN SYTEX Y SE IDENTIFICA QUE ES UNA CASA FAMILIAR, LA CUAL SE TOCA Y NO ABREN LA PUERTA, SE REALIZA GESTIÓN TELEFÓNICA Y NO HAY RESPUESTA. | V88: BARRIENTOS HERNANDEZ CRISTIAN HORACIO | W88: 0 | X88: TIPO I | Y88: =VLOOKUP(D88,TIPOLOGIAS!A:F,5,0) -> TERRESTRE | Z88: VISITA_TÉCNICA | AA88: 0 | AB88: 0 | AC88: 1 | AD88: =IF(AND(Z88="SOPORTE_TELEFÓNICO",OR(T88="SIN CONTACTO CON EL CB",T88="NÚMEROS DE CONTACTO ERRADOS")),0,IF(Z88="SOPORTE_TELEFÓNICO",'BASE DE LIQUIDACION 2025'!$B$9,IF(X88="TIPO I",'BASE DE LIQUIDACION 2025'!$C$3,IF(X88="TIPO II",'BASE DE LIQUIDACION 2025'!$C$4,IF(X88="TIPO III",'BASE DE LIQUIDACION 2025'!$C$5,'BASE DE LIQUIDACION 2025'!$C$6))))) -> 44559.564 | AE88: =IF(Z88="SOPORTE_TELEFÓNICO",AD88,CIERRES!AC88*CIERRES!AD88) -> 44559.564
A89: SANTA MARTA | B89: =VLOOKUP(A89,'CENTRO DE COSTOS'!A:D,4,FALSE) -> JOSE MAURICIO HERNANDEZ ROJAS | C89: =VLOOKUP(A89,'CENTRO DE COSTOS'!A:C,2,FALSE) -> 0004-0001 | D89: 44001 | E89: TA-25-799611 | F89: FO-25-1130571 | G89: 45832.599 | H89: 45835.541 | I89: LA GUAJIRA | J89: RIOHACHA | K89: DISTRICOL BUENA VISTA GUAJIRA | L89: 73212 | M89: ORDEN DE CAMBIO | N89: CIERRE | O89: CIERRE | P89: REDEBAN | Q89: AGREGADOR | R89: DISTRICOL | S89: NO_EXITOSO | T89: CB NO ENTREGA EQUIPO | U89: 27-06-2025 SE REALIZA LA VISITA EN SITIO SE ENCUENTRA EL LOCAL COMERCIAL CERRADO SE HACE GESTIÓN TELEFÓNICA EL CLIENTE MANIFESTÓ INICIALMENTE QUE IBA A ENTREGAR LOS EQUIPOS EN OTRA DIRECCIÓN PERO DESPUÉS DE MEDIA HORA EL CLIENTE INFORMA NUEVAMENTE QUE NO PUEDE ENTREGAR LOS EQUIPOS EN EL MOMENTO YA QUE NO TIENE LA DISPONIBILIDAD | V89: THOMAS CAMPO SIGIFREDO SEGUNDO | W89: SV00T092 | X89: TIPO III | Y89: =VLOOKUP(D89,TIPOLOGIAS!A:F,5,0) -> TERRESTRE | Z89: VISITA_TÉCNICA | AA89: 0 | AB89: 0 | AC89: 1 | AD89: =IF(AND(Z89="SOPORTE_TELEFÓNICO",OR(T89="SIN CONTACTO CON EL CB",T89="NÚMEROS DE CONTACTO ERRADOS")),0,IF(Z89="SOPORTE_TELEFÓNICO",'BASE DE LIQUIDACION 2025'!$B$9,IF(X89="TIPO I",'BASE DE LIQUIDACION 2025'!$C$3,IF(X89="TIPO II",'BASE DE LIQUIDACION 2025'!$C$4,IF(X89="TIPO III",'BASE DE LIQUIDACION 2025'!$C$5,'BASE DE LIQUIDACION 2025'!$C$6))))) -> 222904.07 | AE89: =IF(Z89="SOPORTE_TELEFÓNICO",AD89,CIERRES!AC89*CIERRES!AD89) -> 222904.07
A90: CUCUTA | B90: =VLOOKUP(A90,'CENTRO DE COSTOS'!A:D,4,FALSE) -> MIGUEL JULIÁN HERNÁNDEZ GUARÍN | C90: =VLOOKUP(A90,'CENTRO DE COSTOS'!A:C,2,FALSE) -> 0004-0008 | D90: 54001 | E90: TA-25-799607 | F90: FO-25-1130562 | G90: 45832.599 | H90: 45835.683 | I90: NORTE DE SANTANDER | J90: CUCUTA | K90: PTM CUCUTA MULTISERVICIOS YADI | L90: 55696 | M90: ORDEN DE CAMBIO | N90: CIERRE | O90: CIERRE | P90: REDEBAN | Q90: AGREGADOR | R90: COMCARD - PTM | S90: ILOCALIZADO | T90: CB CERRADO - DESOCUPADO | U90: 27-06-2025 SE REALIZARON LLAMADAS TELEFÓNICA AL NÚMERO ASIGNADO 3115098944 Y SE ENCUENTRA APAGADO, SE PROCEDE A REALIZAR VISITA, SE LLEGA AL CONJUNTO RESIDENCIAL Y VIGILANCIA SE COMUNICA CON LA SEÑORA DIANA DÓNDE NO PERMITE LA ENTRADA. | V90: MORA VEGA JEAMPIER | W90: 0 | X90: TIPO I | Y90: =VLOOKUP(D90,TIPOLOGIAS!A:F,5,0) -> TERRESTRE | Z90: VISITA_TÉCNICA | AA90: 0 | AB90: 0 | AC90: 1 | AD90: =IF(AND(Z90="SOPORTE_TELEFÓNICO",OR(T90="SIN CONTACTO CON EL CB",T90="NÚMEROS DE CONTACTO ERRADOS")),0,IF(Z90="SOPORTE_TELEFÓNICO",'BASE DE LIQUIDACION 2025'!$B$9,IF(X90="TIPO I",'BASE DE LIQUIDACION 2025'!$C$3,IF(X90="TIPO II",'BASE DE LIQUIDACION 2025'!$C$4,IF(X90="TIPO III",'BASE DE LIQUIDACION 2025'!$C$5,'BASE DE LIQUIDACION 2025'!$C$6))))) -> 44559.564 | AE90: =IF(Z90="SOPORTE_TELEFÓNICO",AD90,CIERRES!AC90*CIERRES!AD90) -> 44559.564
A91: CALI | B91: =VLOOKUP(A91,'CENTRO DE COSTOS'!A:D,4,FALSE) -> DIEGO FERNANDO HENAO CARDONA | C91: =VLOOKUP(A91,'CENTRO DE COSTOS'!A:C,2,FALSE) -> 0004-0003 | D91: 76001 | E91: TA-25-809570 | F91: FO-25-1148149 | G91: 45836.333 | H91: 45836.465 | I91: VALLE DEL CAUCA | J91: CALI | K91: BARRIO SANTA BARBARA CALI 2 | L91: 58693 | M91: ORDEN DE CAMBIO | N91: CIERRE | O91: CIERRE | P91: REDEBAN | Q91: CB UNO A UNO | R91: CB UNO A UNO | S91: NO_EXITOSO | T91: CB NO ENTREGA EQUIPO | U91: 28-06-2025 SE HABLA CON EL CLIENTE E INDICA QUE HOY SE PONE AL DIA CON LA COMPENSACIÓN PARA QUE LE VUELVAN A REATIVAR EL CB, EL CLIENTE NO QUISO PROPORCIONAR EL CORREO ELECTRÓNICO | V91: PAREDES CASTILLO DIEGO | W91: 0 | X91: TIPO I | Y91: =VLOOKUP(D91,TIPOLOGIAS!A:F,5,0) -> TERRESTRE | Z91: SOPORTE_TELEFÓNICO | AA91: 0 | AB91: 0 | AC91: 0 | AD91: =IF(AND(Z91="SOPORTE_TELEFÓNICO",OR(T91="SIN CONTACTO CON EL CB",T91="NÚMEROS DE CONTACTO ERRADOS")),0,IF(Z91="SOPORTE_TELEFÓNICO",'BASE DE LIQUIDACION 2025'!$B$9,IF(X91="TIPO I",'BASE DE LIQUIDACION 2025'!$C$3,IF(X91="TIPO II",'BASE DE LIQUIDACION 2025'!$C$4,IF(X91="TIPO III",'BASE DE LIQUIDACION 2025'!$C$5,'BASE DE LIQUIDACION 2025'!$C$6))))) -> 37904.612 | AE91: =IF(Z91="SOPORTE_TELEFÓNICO",AD91,CIERRES!AC91*CIERRES!AD91) -> 37904.612
AE92: =SUM(AE2:AE91) -> 10083278

Sheet TIPOLOGIAS
A1: COD. CIUDAD | B1: CIUDAD | C1: DEPARTAMENTO | D1: DESDE DONDE SE ATIENDE | E1: TIPO DE TRAYECTO NUEVO | F1: TIPOLOGIA NUEVA
A2: 91430 | B2: LA VICTORIA | C2: AMAZONAS | D2: BOGOTA | E2: AEREO | F2: TIPO IV ESPECIAL
A3: 91669 | B3: PUERTO SANTANDER | C3: AMAZONAS | D3: BOGOTA | E3: AEREO | F3: TIPO IV ESPECIAL
A4: 91263 | B4: EL ENCANTO | C4: AMAZONAS | D4: BOGOTA | E4: AEREO | F4: TIPO IV ESPECIAL
A5: 91405 | B5: LA CHORRERA | C5: AMAZONAS | D5: BOGOTA | E5: AEREO | F5: TIPO IV ESPECIAL
A6: 91407 | B6: LA PEDRERA | C6: AMAZONAS | D6: BOGOTA | E6: AEREO | F6: TIPO IV ESPECIAL
A7: 91001 | B7: LETICIA | C7: AMAZONAS | D7: BOGOTA | E7: AEREO | F7: TIPO IV ESPECIAL
A8: 91460 | B8: MIRITI - PARANA | C8: AMAZONAS | D8: BOGOTA | E8: AEREO | F8: TIPO IV ESPECIAL
A9: 91530 | B9: PUERTO ALEGRIA | C9: AMAZONAS | D9: BOGOTA | E9: AEREO | F9: TIPO IV ESPECIAL
A10: 91536 | B10: PUERTO ARICA | C10: AMAZONAS | D10: BOGOTA | E10: AEREO | F10: TIPO IV ESPECIAL
A11: 91540 | B11: PUERTO NARIÑO | C11: AMAZONAS | D11: BOGOTA | E11: AEREO | F11: TIPO IV ESPECIAL
A12: 91798 | B12: TARAPACA | C12: AMAZONAS | D12: BOGOTA | E12: AEREO | F12: TIPO IV ESPECIAL
A13: 5055 | B13: ARGELIA | C13: ANTIOQUIA | D13: MEDELLIN | E13: TERRESTRE | F13: TIPO IV
... A1124: 23682 | B1124: SAN JOSE DE URE | C1124: CORDOBA | D1124: MONTERIA | E1124: TERRESTRE | F1124: TIPO III

Sheet CENTRO DE COSTOS
A1: CIUDAD | B1: CENTRO_COSTO | C1: DESCRIPCION | D1: COORDINADOR
A2: APARTADO | B2: 0004-0005 | C2: Redeban Noroccidente (Medellín) | D2: JUAN SEBASTIÁN RÍOS CASTRILLÓN
A3: BARRANQUILLA | B3: 0004-0001 | C3: Redeban Costa (Barranqullla) | D3: JOSE MAURICIO HERNANDEZ ROJAS
A4: BOGOTA | B4: 0004-0004 | C4: Redeban Centro ( Bogotá) | D4: WILLIAM ASDRUBAL ROZO ROZO
A5: BUCARAMANGA | B5: 0004-0008 | C5: Redeban Santander | D5: MIGUEL JULIÁN HERNÁNDEZ GUARÍN
A6: CALI | B6: 0004-0003 | C6: Redeban Suroccidente (Cali) | D6: DIEGO FERNANDO HENAO CARDONA
A7: CARTAGENA | B7: 0004-0001 | C7: Redeban Costa (Barranqullla) | D7: JOSE MAURICIO HERNANDEZ ROJAS
A8: CUCUTA | B8: 0004-0008 | C8: Redeban Santander | D8: MIGUEL JULIÁN HERNÁNDEZ GUARÍN
A9: FLORENCIA | B9: 0004-0007 | C9: Redeban Oriente (Otros) | D9: KEVIN ALEXIS CORZO BUSTOS
A10: IBAGUE | B10: 0004-0007 | C10: Redeban Oriente (Otros) | D10: KEVIN ALEXIS CORZO BUSTOS
A11: MANIZALES | B11: 0004-0002 | C11: Redeban Eje Cafetero (Pereira) | D11: DIEGO FERNANDO HENAO CARDONA
A12: MEDELLIN | B12: 0004-0005 | C12: Redeban Noroccidente (Medellín) | D12: JUAN SEBASTIÁN RÍOS CASTRILLÓN
... A23: YOPAL | B23: 0004-0007 | C23: Redeban Oriente (Otros) | D23: KEVIN ALEXIS CORZO BUSTOS
