Workbook
Name A: #REF!
Name ACTIVIDAD: [1]Hoja2!$P$2:$P$30
Name Actividad: [2]Formulas!$H$2:$H$5000
Name arearesponsable: '[3]Listas desplegables'!$BB$2:$BB$100
Name Clientes: [4]Clientes!$A$2:$A$100
Name Clientes: [2]Clientes!$A$2:$A$100
Name COORDINADOR: [1]Hoja2!$D$2:$D$30
Name Coordinadores: [5]Coordinadores!$A$2:$A$1000
Name Coordinadores: [2]Coordinadores!$A$2:$A$1000
Name DOCUMENTADOR: [1]Hoja2!$A$2:$A$30
Name ES: [1]Hoja2!$K$2:$K$30
Name ESS: [1]Hoja2!$K$2:$K$30
Name Estado: [4]Formulas!$K$2:$K$5000
Name Estado: [2]Formulas!$K$2:$K$5000
Name ESTADOACTIVIDAD: [1]Hoja2!$M$2:$M$30
Name ESTADOS: '[6]Listas desplegables'!$B$1:$D$1
Name ESTADOSCIERRES: '[7]lista desplegable'!$CX$1:$DA$1
Name Facturacion: '[8]Listas desplegables'!$AO$1:$AR$1
Name FACTURACIÓN: '[6]Listas desplegables'!$Y$1:$AB$1
Name falla: #REF!
Name Fallas: '[9]Listas desplegables'!$F$2:$L$2
Name Grupo_Falla: '[10]Listas Desplegables'!$CH$2:$CH$5
Name inconservmanager: '[11]Listas desplegables'!$BC$2:$BC$100
Name INCUMPLIMIENTO: '[3]Listas desplegables'!$AK$1:$AN$1
Name LISTA: [12]Dptos!$A$1139:$A$1171
Name LISTA2: #REF!
Name LOLO: [13]Coordinadores!$A$2:$A$1000
Name solicitudes: '[8]Listas desplegables'!$U$1:$AF$1
Name solicitudes: '[14]Listas desplegables'!$AF$1:$AQ$1
Name Tecnicos: [4]Tecnicos!$A$2:$A$1000
Name Tecnicos: [2]Tecnicos!$A$2:$A$1000
Name Version: [2]Formulas!$I$2:$I$3

Sheet RESUMEN
A1: LÍNEA COMUNICACIONES S.A.S | F1: FACTURACIÓN CORRESPONSALES BANCARIOS TIQUIETES AEREOS
A2: FACTURACIÓN PROYECTO CB BANCOLOMBIA | F2: =A3 -> 45838
A3: 45838
F4: CONCEPTOS | G4: TRAYECTOS | H4: TOTAL | I4: % Administración | J4: TOTAL
A5: CONCEPTOS | B5: CANTIDAD | C5: VALOR UNITARIO | D5: VALOR TOTAL | F5: INCIDENTE 2242568 | G5: MEDELLIN- ISTMINA-MEDELLIN | H5: 850800 | I5: =H5*0.12 -> 102096 | J5: =H5+I5 -> 952896
A6: Adecuaciones CB | B6: =COUNTA(ADECUACIONES!A:A)-1 -> 45 | C6: 0 | D6: =ADECUACIONES!AM47 -> 7602999.8 | F6: INCIDENTE 2268184 | G6: MEDELLIN-QUIBDO-MEDELLIN | H6: 457600 | I6: =H6*0.12 -> 54912 | J6: =H6+I6 -> 512512
A7: Incidentes | B7: =COUNTA(INCIDENTES!A:A)-1 -> 185 | C7: 0 | D7: =INCIDENTES!AM187 -> 17712902 | I7: =H7*0.12 -> 0 | J7: =H7+I7 -> 0
A8: Ordenes de Cambio | B8: =COUNTA(OC!A:A)-1 -> 5 | C8: 0 | D8: =OC!AH7 -> 511514.45 | I8: =H8*0.12 -> 0 | J8: =H8+I8 -> 0
A9: Tiquetes | B9: 2 | C9: 0 | D9: =J12 -> 1465408 | I9: =H9*0.12 -> 0 | J9: =H9+I9 -> 0
A10: SUBTOTAL | D10: =SUM(D6:D9) -> 27292825 | I10: =H10*0.12 -> 0 | J10: =H10+I10 -> 0
A11: Iva | D11: =D10*0.19 -> 5185636.7 | I11: =H11*0.12 -> 0 | J11: =H11+I11 -> 0
A12: TOTAL | D12: =D10+D11 -> 32478461 | F12: TOTAL | H12: =SUM(H5:H11) -> 1308400 | I12: =SUM(I5:I11) -> 157008 | J12: =SUM(J5:J11) -> 1465408

Sheet BASE LIQUIDACION
A1: TARIFAS 2025 | E1: Incremento 2025
A2: Tipificación | B2: Descripción | C2: Dia actividad Exitosa | D2: Dia actividad Fallida | E2: 0.052
A3: Tipo I | B3: Metropolitano | C3: =62700.07*(1+$E$2) -> 65960.474 | D3: =42357.4*(1+$E$2) -> 44559.985
A4: Tipo II | B4: Hasta 3 horas | C4: =155716.31*(1+$E$2) -> 163813.56 | D4: =127766.53*(1+$E$2) -> 134410.39
A5: Tipo III | B5: De 3 a 5 horas | C5: =262099.22*(1+$E$2) -> 275728.38 | D5: =211886.19*(1+$E$2) -> 222904.27
A6: Tipo IV | B6: Más de 5 horas | C6: =455883.78*(1+$E$2) -> 479589.74 | D6: =441833.68*(1+$E$2) -> 464809.03
A7: Destino aereo | B7: No incluye valor del Tiquete | C7: =455883.78*(1+$E$2) -> 479589.74 | D7: =441833.68*(1+$E$2) -> 464809.03
A8: *Donde se requiera transporte aéreo o fluvial se factura adicional a tarifa TIPO IV el valor del tiquete + el 12% de admon.
A10: Gestión Telefónica | B10: =36031.04*(1+$E$2) -> 37904.654
A11: Mts Acometida electrica | B11: =30182.1*(1+$E$2) -> 31751.569
A12: Mts Acometida datos | B12: =15432.22*(1+$E$2) -> 16234.695
A13: switche | B13: =244669.03*(1+$E$2) -> 257391.82
A14: Router | B14: =291399.51*(1+$E$2) -> 306552.28
A15: Envio operador Logistico | B15: =53547.34*(1+$E$2) -> 56331.802

Sheet Tablas dinámicas
A2: ADECUACIONES | J2: NOMBRE CC | K2: Suma de VALOR | L2: Suma de VALOR2
A3: COORDINADOR | B3: CENTRO DE COSTOS LÍNEACOM | C3: % | D3: $ | E3: NOMBRE CC | F3: VALOR | J3: Redeban Centro ( Bogotá) | K3: 2202836.5 | L3: 0.085734376
A4: DIEGO FERNANDO HENAO CARDONA | B4: 0004-0002 | C4: 0.076073103 | D4: 568214.34 | E4: =VLOOKUP(B4,'CENTRO DE COSTOS'!B:C,2,0) -> Redeban Eje Cafetero (Pereira) | F4: =D4 -> 568214.34 | J4: Redeban Costa (Barranqullla) | K4: 1811081.3 | L4: 0.070487268
B5: 0004-0003 | C5: 0.2094254 | D5: 1564265.3 | E5: =VLOOKUP(B5,'CENTRO DE COSTOS'!B:C,2,0) -> Redeban Suroccidente (Cali) | F5: =D5 -> 1564265.3 | J5: Redeban Eje Cafetero (Pereira) | K5: 2058226.4 | L5: 0.080106152
A6: JOSE MAURICIO HERNANDEZ ROJAS | B6: 0004-0001 | C6: 0.01193147 | D6: 89119.97 | E6: =VLOOKUP(B6,'CENTRO DE COSTOS'!B:C,2,0) -> Redeban Costa (Barranqullla) | F6: =D6 -> 89119.97 | J6: Redeban Noroccidente (Medellín) | K6: 8916103.2 | L6: 0.34701466
A7: JUAN SEBASTIÁN RÍOS CASTRILLÓN | B7: 0004-0005 | C7: 0.1087279 | D7: 812123.5 | E7: =VLOOKUP(B7,'CENTRO DE COSTOS'!B:C,2,0) -> Redeban Noroccidente (Medellín) | F7: =D7 -> 812123.5 | J7: Redeban Oriente (Otros) | K7: 2740326.7 | L7: 0.10665349
A8: KEVIN ALEXIS CORZO BUSTOS | B8: 0004-0007 | C8: 0.12723136 | D8: 950331.69 | E8: =VLOOKUP(B8,'CENTRO DE COSTOS'!B:C,2,0) -> Redeban Oriente (Otros) | F8: =D8 -> 950331.69 | J8: Redeban Santander | K8: 4195509.5 | L8: 0.16328919
A9: MIGUEL JULIÁN HERNÁNDEZ GUARÍN | B9: 0004-0008 | C9: 0.35038225 | D9: 2617117.1 | E9: =VLOOKUP(B9,'CENTRO DE COSTOS'!B:C,2,0) -> Redeban Santander | F9: =D9 -> 2617117.1 | J9: Redeban Suroccidente (Cali) | K9: 3769653.2 | L9: 0.14671487
A10: WILLIAM ASDRUBAL ROZO ROZO | B10: 0004-0004 | C10: 0.11622852 | D10: 868147.99 | E10: =VLOOKUP(B10,'CENTRO DE COSTOS'!B:C,2,0) -> Redeban Centro ( Bogotá) | F10: =D10 -> 868147.99 | J10: Total general | K10: 25693737 | L10: 1
A11: Total general | C11: 1 | D11: 7469319.9
A15: INCIDENTES
A16: COORDINADOR | B16: CENTRO DE COSTOS LÍNEACOM | C16: % | D16: $ | E16: NOMBRE CC
A17: DIEGO FERNANDO HENAO CARDONA | B17: 0004-0002 | C17: 0.084120152 | D17: 1490012 | E17: =VLOOKUP(B17,'CENTRO DE COSTOS'!B:C,2,0) -> Redeban Eje Cafetero (Pereira) | F17: =D17 -> 1490012
B18: 0004-0003 | C18: 0.12078356 | D18: 2139427.4 | E18: =VLOOKUP(B18,'CENTRO DE COSTOS'!B:C,2,0) -> Redeban Suroccidente (Cali) | F18: =D18 -> 2139427.4
A19: JOSE MAURICIO HERNANDEZ ROJAS | B19: 0004-0001 | C19: 0.09507514 | D19: 1684056.7 | E19: =VLOOKUP(B19,'CENTRO DE COSTOS'!B:C,2,0) -> Redeban Costa (Barranqullla) | F19: =D19 -> 1684056.7
A20: JUAN SEBASTIÁN RÍOS CASTRILLÓN | B20: 0004-0005 | C20: 0.44195193 | D20: 7828251.3 | E20: =VLOOKUP(B20,'CENTRO DE COSTOS'!B:C,2,0) -> Redeban Noroccidente (Medellín) | F20: =D20 -> 7828251.3
A21: KEVIN ALEXIS CORZO BUSTOS | B21: 0004-0007 | C21: 0.101056 | D21: 1789995 | E21: =VLOOKUP(B21,'CENTRO DE COSTOS'!B:C,2,0) -> Redeban Oriente (Otros) | F21: =D21 -> 1789995
A22: MIGUEL JULIÁN HERNÁNDEZ GUARÍN | B22: 0004-0008 | C22: 0.089109756 | D22: 1578392.4 | E22: =VLOOKUP(B22,'CENTRO DE COSTOS'!B:C,2,0) -> Redeban Santander | F22: =D22 -> 1578392.4
A23: WILLIAM ASDRUBAL ROZO ROZO | B23: 0004-0004 | C23: 0.067903471 | D23: 1202767.6 | E23: =VLOOKUP(B23,'CENTRO DE COSTOS'!B:C,2,0) -> Redeban Centro ( Bogotá) | F23: =D23 -> 1202767.6
A24: Total general | C24: 1 | D24: 17712902
A29: OC
A30: COORDINADOR | B30: CENTRO DE COSTOS LÍNEACOM | C30: % | D30: $ | E30: NOMBRE CC
A31: DIEGO FERNANDO HENAO CARDONA | B31: 0004-0003 | C31: 0.12895134 | D31: 65960.474 | E31: =VLOOKUP(B31,'CENTRO DE COSTOS'!B:C,2,0) -> Redeban Suroccidente (Cali) | F31: =D31 -> 65960.474
A32: JOSE MAURICIO HERNANDEZ ROJAS | B32: 0004-0001 | C32: 0.074102801 | D32: 37904.654 | E32: =VLOOKUP(B32,'CENTRO DE COSTOS'!B:C,2,0) -> Redeban Costa (Barranqullla) | F32: =D32 -> 37904.654
A33: JUAN SEBASTIÁN RÍOS CASTRILLÓN | B33: 0004-0005 | C33: 0.53904318 | D33: 275728.38 | E33: =VLOOKUP(B33,'CENTRO DE COSTOS'!B:C,2,0) -> Redeban Noroccidente (Medellín) | F33: =D33 -> 275728.38
A34: WILLIAM ASDRUBAL ROZO ROZO | B34: 0004-0004 | C34: 0.25790268 | D34: 131920.95 | E34: =VLOOKUP(B34,'CENTRO DE COSTOS'!B:C,2,0) -> Redeban Centro ( Bogotá) | F34: =D34 -> 131920.95
A35: Total general | C35: 1 | D35: 511514.45 | E35: =VLOOKUP(B35,'CENTRO DE COSTOS'!B:C,2,0) -> #N/A | F35: =D35 -> 511514.45

Sheet ADECUACIONES
A1: CIUDAD | B1: COORDINADOR | C1: CENTRO DE COSTOS LÍNEACOM | D1: CÓDIGO DANE | E1: TA | F1: FO | G1: FECHA LISTA | H1: FECHA LIMITE | I1: FECHA SOLICITUD DE LA ACTIVIDAD | J1: FECHA INICIO DE LA ACTIVIDAD | K1: FECHA ULTIMA ACTUALIZACION | L1: DEPARTAMENTO | M1: CIUDAD | N1: NOMBRE PUNTO | O1: CÓDIGO PUNTO | P1: TIPO DE APERTURA | Q1: ACTIVIDAD | R1: RED | S1: FORMATO | T1: CADENA | U1: ESTADO | V1: OBSERVACIONES CLIENTE | W1: NOMBRE DEL TECNICO | X1: TERMINALES | Y1: PLACA DATAFONOS INSTALADOS | Z1: PLACA DATAFONOS RETIRADOS | AA1: PLACA LECTOR INSTALADO | AB1: PLACA LECTOR RETIRADO | AC1: CANTIDAD ROLLOS ENTREGADOS | AD1: TIPIFICACION | AE1: TIPO DE TRAYECTO | AF1: FORMA DE ATENCIÓN | AG1: ACOMETIDA DATOS (metros) | AH1: ACOMETIDA ELECTRICA (metros) | AI1: SWITCH | AJ1: ROUTER | AK1: VISITAS | AL1: VALOR DIAS ACTIVIDAD FACTURABLES | AM1: VALOR FACTURABLE A BANCOLMBIA TECNOLOGIA
A2: MEDELLIN | B2: =VLOOKUP(A2,'CENTRO DE COSTOS'!A:D,4,FALSE) -> JUAN SEBASTIÁN RÍOS CASTRILLÓN | C2: =VLOOKUP(A2,'CENTRO DE COSTOS'!A:C,2,FALSE) -> 0004-0005 | D2: 27361 | E2: TA-25-680473 | F2: FO-25-1006417 | G2: 45805 | H2: 45817 | I2: 45805 | J2: 45812 | K2: 45812 | L2: CHOCO | M2: ISTMINA | N2: BARRIO CUBIS SEC MESETA ALTA ISTMINA CHOCO ISTMINA | O2: 79563 | P2: CB CRECIMIENTO - NUEVO | Q2: APERTURA | R2: REDEBAN | S2: UNO A UNO | T2: UNO A UNO | U2: EJECUTADO | V2: 28-05 SE REALIZA LLAMADA AL CLIENTE, SE HABLA CON LA SRA JOAN AVENDAÑO DAZA SE VALIDA DIRECCIÓN OK, CANAL OK, DISPONIBILIDAD TOTAL, LLAMAR EL DÍA LA INSTALACIÓN PARA CONFIRMAR VISITA, AVISO EXTERIOR ALTURA APROX 2 METROS; TOMACORRIENTE CERCANO: SI; TIENE CABINA DE SEGURIDAD: SI 04-06 SE REALIZA INSTALACIÓN DE CORRESPONSAL, SE INSTALAN EQUIPOS CON PRUEBAS EXITOSAS, SE CAPACITA Y SE EVALÚA AL CLIENTE, SE INSTALA PUBLICIDAD COMPLETA, CB QUEDA OPERATIVO. USUARIO SOMOS BANCOLOMBIA ACTIVO. SE INSTALAN 10 MT DE CABLE UTP | W2: ROBLEDO DIAZ ANDRES FELIPE | X2: LMUZZ997 | Y2: 771855 | Z2: N/A | AA2: 1146028 | AB2: N/A | AC2: 40 ROLLOS | AD2: =VLOOKUP(D2,TIPOLOGIAS!A:F,6,0) -> TIPO IV ESPECIAL | AE2: =VLOOKUP(D2,TIPOLOGIAS!A:F,5,0) -> AEREO | AF2: VISITA _TECNICA | AG2: 10 | AH2: 0 | AI2: 0 | AJ2: 0 | AK2: 0 | AL2: =IF(AD2="TIPO I",'BASE LIQUIDACION'!$D$3,IF(AD2="TIPO II",'BASE LIQUIDACION'!$D$4,IF(AD2="TIPO III",'BASE LIQUIDACION'!$D$5,'BASE LIQUIDACION'!$D$7))) -> 464809.03 | AM2: =AG2*'BASE LIQUIDACION'!$B$12+AH2*'BASE LIQUIDACION'!$B$11+AI2*'BASE LIQUIDACION'!$B$13+AJ2*'BASE LIQUIDACION'!$B$14+AK2*AL2 -> 162346.95
A3: APARTADO | B3: =VLOOKUP(A3,'CENTRO DE COSTOS'!A:D,4,FALSE) -> JUAN SEBASTIÁN RÍOS CASTRILLÓN | C3: =VLOOKUP(A3,'CENTRO DE COSTOS'!A:C,2,FALSE) -> 0004-0005 | D3: 5837 | E3: TA-25-695256 | F3: FO-25-1029598 | G3: 45811 | H3: 45813 | I3: 45811 | J3: 45819 | K3: 45819 | L3: ANTIOQUIA | M3: TURBO | N3: BARRIO CGT NUEVA COLONIA TURBO ANTIOQUIA TURBO | O3: 79383 | P3: CB CRECIMIENTO - OTRAS LISTAS | Q3: APERTURA | R3: REDEBAN | S3: UNO A UNO | T3: UNO A UNO | U3: EJECUTADO | V3: 31-05 SE REALIZA LLAMADA AL CLIENTE, SE HABLA CON EL SR MAURICIO RIVERA ARIAS, SE VALIDA DIRECCIÓN OK, CANAL OK, DISPONIBILIDAD TOTAL, LLAMAR EL DÍA LA INSTALACIÓN PARA CONFIRMAR VISITA, AVISO EXTERIOR ALTURA APROX DONDE EL TECNICO LO VEA CONVENIENTE METROS; TOMACORRIENTE CERCANO: SI; TIENE CABINA DE SEGURIDAD:NO// MODEM SE ENCUEN TRA A 10 METROS DE DISTANCIA 05-06 SE REALIZA LLAMADA A USUARIO PARA CONFIRMAR LA INSTALACIÓN DEL CORRESPONSAL, USUARIO INFORMA DE NO PODER ATENDER POR NOVEDAD MEDICA DE LA ESPOSA, USUARIO PIDE POR FAVOR PROGRAMAR PARA LA PRÓXIMA SEMANA OK 11-06 SE REALIZA INSTALACIÓN DE CORRESPONSAL, SE INSTALAN EQUIPOS CON PRUEBAS EXITOSAS, SE CAPACITA Y SE EVALÚA AL CLIENTE, SE INSTALA PUBLICIDAD COMPLETA, CB QUEDA OPERATIVO. USUARIO SOMOS BANCOLOMBIA ACTIVO. SE INSTALAN 10 MT DE CABLE UTP | W3: JULIO TUBERQUIA JOSE SEBASTIAN | X3: 10XZZ921 | Y3: 1051048 | Z3: N/A | AA3: 545397 | AB3: N/A | AC3: 40 ROLLOS | AD3: =VLOOKUP(D3,TIPOLOGIAS!A:F,6,0) -> TIPO II | AE3: =VLOOKUP(D3,TIPOLOGIAS!A:F,5,0) -> TERRESTRE | AF3: VISITA _TECNICA | AG3: 10 | AH3: 0 | AI3: 0 | AJ3: 0 | AK3: 0 | AL3: =IF(AD3="TIPO I",'BASE LIQUIDACION'!$D$3,IF(AD3="TIPO II",'BASE LIQUIDACION'!$D$4,IF(AD3="TIPO III",'BASE LIQUIDACION'!$D$5,'BASE LIQUIDACION'!$D$7))) -> 134410.39 | AM3: =AG3*'BASE LIQUIDACION'!$B$12+AH3*'BASE LIQUIDACION'!$B$11+AI3*'BASE LIQUIDACION'!$B$13+AJ3*'BASE LIQUIDACION'!$B$14+AK3*AL3 -> 162346.95
A4: CALI | B4: =VLOOKUP(A4,'CENTRO DE COSTOS'!A:D,4,FALSE) -> DIEGO FERNANDO HENAO CARDONA | C4: =VLOOKUP(A4,'CENTRO DE COSTOS'!A:C,2,FALSE) -> 0004-0003 | D4: 76318 | E4: TA-25-721875 | F4: FO-25-1062664 | G4: 45817 | H4: 45819 | I4: 45817 | J4: 45818 | K4: 45818 | L4: VALLE DEL CAUCA | M4: GUACARI | N4: BARRIO EL FARO GUACARI GUACARI | O4: 79774 | P4: CB CRECIMIENTO - NUEVO | Q4: APERTURA | R4: REDEBAN | S4: UNO A UNO | T4: UNO A UNO | U4: EJECUTADO | V4: 9-06-2025 SE REALIZA LLAMADA AL CLIENTE, SE HABLA CON EL SR JORGE LUIS PEÑA CORTES SE VALIDA DIRECCIÓN OK, CANAL OK, DISPONIBILIDAD TOTAL, LLAMAR EL DÍA 10/6/2025 SE REALIZA INSTALACIÓN DE CORRESPONSAL, SE INSTALAN EQUIPOS CON PRUEBAS EXITOSAS, SE CAPACITA Y SE EVALÚA AL CLIENTE, SE INSTALA PUBLICIDAD COMPLETA, CB QUEDA OPERATIVO. USUARIO SOMOS BANCOLOMBIA ACTIVO. SE INSTALAN 17 MT DE CABLE UTP | W4: TORRES GARCIA JENDRY JOSE | X4: F1XZZ006 | Y4: 851866 | Z4: N/A | AA4: 932961 | AB4: N/A | AC4: 40 ROLLOS | AD4: =VLOOKUP(D4,TIPOLOGIAS!A:F,6,0) -> TIPO II | AE4: =VLOOKUP(D4,TIPOLOGIAS!A:F,5,0) -> TERRESTRE | AF4: VISITA _TECNICA | AG4: 17 | AH4: 0 | AI4: 0 | AJ4: 0 | AK4: 0 | AL4: =IF(AD4="TIPO I",'BASE LIQUIDACION'!$D$3,IF(AD4="TIPO II",'BASE LIQUIDACION'!$D$4,IF(AD4="TIPO III",'BASE LIQUIDACION'!$D$5,'BASE LIQUIDACION'!$D$7))) -> 134410.39 | AM4: =AG4*'BASE LIQUIDACION'!$B$12+AH4*'BASE LIQUIDACION'!$B$11+AI4*'BASE LIQUIDACION'!$B$13+AJ4*'BASE LIQUIDACION'!$B$14+AK4*AL4 -> 275989.82
A5: TUNJA | B5: =VLOOKUP(A5,'CENTRO DE COSTOS'!A:D,4,FALSE) -> MIGUEL JULIÁN HERNÁNDEZ GUARÍN | C5: =VLOOKUP(A5,'CENTRO DE COSTOS'!A:C,2,FALSE) -> 0004-0008 | D5: 15176 | E5: TA-25-721906 | F5: FO-25-1062920 | G5: 45817 | H5: 45819 | I5: 45817 | J5: 45818 | K5: 45818 | L5: BOYACA | M5: CHIQUINQUIRA | N5: BARRIO LA POLA CHIQUINQUIRA 2 | O5: 79763 | P5: CB CRECIMIENTO - NUEVO | Q5: APERTURA | R5: REDEBAN | S5: UNO A UNO | T5: UNO A UNO | U5: EJECUTADO | V5: 07-06 SE REALIZA LLAMADA AL CLIENTE, SE HABLA CON LA SRA KAROL MAITE GONZÁLEZ PORRAS SE VALIDA DIRECCIÓN OK, CANAL OK, DISPONIBILIDAD TOTAL, LLAMAR EL DÍA LA INSTALACIÓN PARA CONFIRMAR VISITA, AVISO EXTERIOR ALTURA APROX 2.70 METROS; TOMACORRIENTE CERCANO: SI; TIENE CABINA DE SEGURIDAD: SI - EL MODEM ESTA A 8 MT - COMUNICACIÓN POR WPP 10/6/2025 SE REALIZA INSTALACIÓN DE CORRESPONSAL, SE INSTALAN EQUIPOS CON PRUEBAS EXITOSAS, SE CAPACITA Y SE EVALÚA AL CLIENTE, SE INSTALA PUBLICIDAD COMPLETA, CB QUEDA OPERATIVO. USUARIO SOMOS BANCOLOMBIA ACTIVO. SE INSTALAN 15 MT DE CABLE UTP | W5: SOLER HOYOS CRISTIAN LEONARDO | X5: F1XZZ029 | Y5: 916662 | Z5: N/A | AA5: 1077082 | AB5: N/A | AC5: 40 ROLLOS | AD5: =VLOOKUP(D5,TIPOLOGIAS!A:F,6,0) -> TIPO III | AE5: =VLOOKUP(D5,TIPOLOGIAS!A:F,5,0) -> TERRESTRE | AF5: VISITA _TECNICA | AG5: 15 | AH5: 0 | AI5: 0 | AJ5: 0 | AK5: 0 | AL5: =IF(AD5="TIPO I",'BASE LIQUIDACION'!$D$3,IF(AD5="TIPO II",'BASE LIQUIDACION'!$D$4,IF(AD5="TIPO III",'BASE LIQUIDACION'!$D$5,'BASE LIQUIDACION'!$D$7))) -> 222904.27 | AM5: =AG5*'BASE LIQUIDACION'!$B$12+AH5*'BASE LIQUIDACION'!$B$11+AI5*'BASE LIQUIDACION'!$B$13+AJ5*'BASE LIQUIDACION'!$B$14+AK5*AL5 -> 243520.43
A6: CALI | B6: =VLOOKUP(A6,'CENTRO DE COSTOS'!A:D,4,FALSE) -> DIEGO FERNANDO HENAO CARDONA | C6: =VLOOKUP(A6,'CENTRO DE COSTOS'!A:C,2,FALSE) -> 0004-0003 | D6: 76233 | E6: TA-25-721931 | F6: FO-25-1062997 | G6: 45817 | H6: 45819 | I6: 45817 | J6: 45818 | K6: 45818 | L6: VALLE DEL CAUCA | M6: DAGUA | N6: BARRIO PRIMERO DE MAYO DAGUA DAGUA | O6: 79769 | P6: CB CRECIMIENTO - NUEVO | Q6: APERTURA | R6: REDEBAN | S6: UNO A UNO | T6: UNO A UNO | U6: EJECUTADO | V6: 9-06-2025 SE REALIZA LLAMADA AL CLIENTE, SE HABLA CON LA SRA KIMBERLY MARTINEZ TORRES SE VALIDA DIRECCIÓN OK, CANAL OK, DISPONIBILIDAD TOTAL, LLAMAR EL DÍA LA INSTALACIÓN PARA CONFIRMAR VISITA, AVISO EXTERIOR ALTURA APROX 1,70 METROS; TOMACORRIENTE CERCANO: SI; TIENE CABINA DE SEGURIDAD: SI // CONTACTO REALIZADO POR LA APP 10-06 SE REALIZA INSTALACIÓN DE CORRESPONSAL, SE INSTALAN EQUIPOS CON PRUEBAS EXITOSAS, SE CAPACITA Y SE EVALÚA AL CLIENTE, SE INSTALA PUBLICIDAD COMPLETA, CB QUEDA OPERATIVO. USUARIO SOMOS BANCOLOMBIA ACTIVO. SE INSTALAN 10 MT DE CABLE UTP | W6: BOLAÑOS TABORDA JORGE ENRIQUE | X6: F1XZZ043 | Y6: 994427 | Z6: N/A | AA6: 933109 | AB6: N/A | AC6: 40 ROLLOS | AD6: =VLOOKUP(D6,TIPOLOGIAS!A:F,6,0) -> TIPO II | AE6: =VLOOKUP(D6,TIPOLOGIAS!A:F,5,0) -> TERRESTRE | AF6: VISITA _TECNICA | AG6: 10 | AH6: 0 | AI6: 0 | AJ6: 0 | AK6: 0 | AL6: =IF(AD6="TIPO I",'BASE LIQUIDACION'!$D$3,IF(AD6="TIPO II",'BASE LIQUIDACION'!$D$4,IF(AD6="TIPO III",'BASE LIQUIDACION'!$D$5,'BASE LIQUIDACION'!$D$7))) -> 134410.39 | AM6: =AG6*'BASE LIQUIDACION'!$B$12+AH6*'BASE LIQUIDACION'!$B$11+AI6*'BASE LIQUIDACION'!$B$13+AJ6*'BASE LIQUIDACION'!$B$14+AK6*AL6 -> 162346.95
A7: BOGOTA | B7: =VLOOKUP(A7,'CENTRO DE COSTOS'!A:D,4,FALSE) -> WILLIAM ASDRUBAL ROZO ROZO | C7: =VLOOKUP(A7,'CENTRO DE COSTOS'!A:C,2,FALSE) -> 0004-0004 | D7: 11001 | E7: TA-25-721993 | F7: FO-25-1063185 | G7: 45817 | H7: 45819 | I7: 45817 | J7: 45819 | K7: 45819 | L7: CUNDINAMARCA | M7: BOGOTA | N7: BARRIO LAS MARGARITAS BOGOTA 4 | O7: 79749 | P7: CB CRECIMIENTO - NUEVO | Q7: APERTURA | R7: REDEBAN | S7: UNO A UNO | T7: UNO A UNO | U7: EJECUTADO | V7: 07-06 SE REALIZA LLAMADA AL CLIENTE, SE HABLA CON LA SR LEONARDO SORIANO GALEANO SE VALIDA DIRECCIÓN OK, CANAL OK, DISPONIBILIDAD TOTAL, LLAMAR EL DÍA LA INSTALACIÓN PARA CONFIRMAR VISITA, AVISO EXTERIOR ALTURA: NO INDICA ALTURA; TOMACORRIENTE CERCANO: SI; TIENE CABINA DE SEGURIDAD: NO - EL MODEM ESTA A 10 MT 11/6/2025 SE REALIZA INSTALACIÓN DE CORRESPONSAL, SE INSTALAN EQUIPOS CON PRUEBAS EXITOSAS, SE CAPACITA Y SE EVALÚA AL CLIENTE, SE INSTALA PUBLICIDAD COMPLETA, CB QUEDA OPERATIVO. USUARIO SOMOS BANCOLOMBIA ACTIVO. SE INSTALAN 18 MT DE CABLE UTP | W7: GOMEZ VEGA DAVID SNEYDER | X7: F1XZZ090 | Y7: 1235210 | Z7: N/A | AA7: 1238697-241587317561324755886660 | AB7: N/A | AC7: 40 ROLLOS | AD7: =VLOOKUP(D7,TIPOLOGIAS!A:F,6,0) -> TIPO I | AE7: =VLOOKUP(D7,TIPOLOGIAS!A:F,5,0) -> TERRESTRE | AF7: VISITA _TECNICA | AG7: 18 | AH7: 0 | AI7: 0 | AJ7: 0 | AK7: 0 | AL7: =IF(AD7="TIPO I",'BASE LIQUIDACION'!$D$3,IF(AD7="TIPO II",'BASE LIQUIDACION'!$D$4,IF(AD7="TIPO III",'BASE LIQUIDACION'!$D$5,'BASE LIQUIDACION'!$D$7))) -> 44559.985 | AM7: =AG7*'BASE LIQUIDACION'!$B$12+AH7*'BASE LIQUIDACION'!$B$11+AI7*'BASE LIQUIDACION'!$B$13+AJ7*'BASE LIQUIDACION'!$B$14+AK7*AL7 -> 292224.52
A8: BUCARAMANGA | B8: =VLOOKUP(A8,'CENTRO DE COSTOS'!A:D,4,FALSE) -> MIGUEL JULIÁN HERNÁNDEZ GUARÍN | C8: =VLOOKUP(A8,'CENTRO DE COSTOS'!A:C,2,FALSE) -> 0004-0008 | D8: 68001 | E8: TA-25-736405 | F8: FO-25-1073947 | G8: 45819 | H8: 45821 | I8: 45819 | J8: 45820 | K8: 45820 | L8: SANTANDER | M8: BUCARAMANGA | N8: BARRIO CENTRO BUCARAMANGA BUCARAMANGA | O8: 79843 | P8: CB CRECIMIENTO - NUEVO | Q8: APERTURA | R8: REDEBAN | S8: UNO A UNO | T8: UNO A UNO | U8: EJECUTADO | V8: 10-06 SE REALIZA LLAMADA AL CLIENTE, SE HABLA CON LA SR OMAR CARRILLO QUIÑONESSE VALIDA DIRECCIÓN OK, CANAL OK, DISPONIBILIDAD TOTAL, LLAMAR EL DÍA LA INSTALACIÓN PARA CONFIRMAR VISITA, AVISO EXTERIOR ALTURA APROX 2 METROS; TOMACORRIENTE CERCANO: SI; TIENE CABINA DE SEGURIDAD: NO - COMUNICACION POR WPP 12/6/2025SE REALIZA INSTALACIÓN DE CORRESPONSAL, SE INSTALAN EQUIPOS CON PRUEBAS EXITOSAS, SE CAPACITA Y SE EVALÚA AL CLIENTE, SE INSTALA PUBLICIDAD COMPLETA, CB QUEDA OPERATIVO. USUARIO SOMOS BANCOLOMBIA ACTIVO. SE INSTALAN 10 MT DE CABLE UTP | W8: GONZALEZ ESTUPIÑAN YEISON WALTER ANTONIO | X8: FAUZZ210 | Y8: 1120059 | Z8: N/A | AA8: 1071354 | AB8: N/A | AC8: 40 ROLLOS | AD8: =VLOOKUP(D8,TIPOLOGIAS!A:F,6,0) -> TIPO I | AE8: =VLOOKUP(D8,TIPOLOGIAS!A:F,5,0) -> TERRESTRE | AF8: VISITA _TECNICA | AG8: 10 | AH8: 0 | AI8: 0 | AJ8: 0 | AK8: 0 | AL8: =IF(AD8="TIPO I",'BASE LIQUIDACION'!$D$3,IF(AD8="TIPO II",'BASE LIQUIDACION'!$D$4,IF(AD8="TIPO III",'BASE LIQUIDACION'!$D$5,'BASE LIQUIDACION'!$D$7))) -> 44559.985 | AM8: =AG8*'BASE LIQUIDACION'!$B$12+AH8*'BASE LIQUIDACION'!$B$11+AI8*'BASE LIQUIDACION'!$B$13+AJ8*'BASE LIQUIDACION'!$B$14+AK8*AL8 -> 162346.95
A9: CALI | B9: =VLOOKUP(A9,'CENTRO DE COSTOS'!A:D,4,FALSE) -> DIEGO FERNANDO HENAO CARDONA | C9: =VLOOKUP(A9,'CENTRO DE COSTOS'!A:C,2,FALSE) -> 0004-0003 | D9: 76111 | E9: TA-25-736409 | F9: FO-25-1073958 | G9: 45819 | H9: 45821 | I9: 45819 | J9: 45820 | K9: 45820 | L9: VALLE DEL CAUCA | M9: GUADALAJARA DE BUGA | N9: BARRIO CENTRO GUADALAJARA DE BUGA GUADALAJARA DE BUGA | O9: 79848 | P9: CB CRECIMIENTO - NUEVO | Q9: APERTURA | R9: REDEBAN | S9: UNO A UNO | T9: UNO A UNO | U9: EJECUTADO | V9: 11-06 SE REALIZA LLAMADA AL CLIENTE, SE HABLA CON EL SR JAVIER MAURICIO PLAZA VARGAS, SE VALIDA DIRECCIÓN OK, CANAL OK, DISPONIBILIDAD TOTAL, LLAMAR EL DÍA LA INSTALACIÓN PARA CONFIRMAR VISITA, AVISO EXTERIOR ALTURA APROX 3 METROS; TOMACORRIENTE CERCANO: SI; TIENE CABINA DE SEGURIDAD: NO- MODEM A 4 METROS 12-06 SE REALIZA INSTALACIÓN DE CORRESPONSAL, SE INSTALAN EQUIPOS CON PRUEBAS EXITOSAS, SE CAPACITA Y SE EVALÚA AL CLIENTE, SE INSTALA PUBLICIDAD COMPLETA, CB QUEDA OPERATIVO. USUARIO SOMOS BANCOLOMBIA ACTIVO. SE INSTALAN 20 MT DE CABLE UTP | W9: MONTERO MUESES GIAN CARLO | X9: FAUZZ213 | Y9: 1242553 | Z9: N/A | AA9: 940518-241597317561324755900749 | AB9: N/A | AC9: 40 ROLLOS | AD9: =VLOOKUP(D9,TIPOLOGIAS!A:F,6,0) -> TIPO II | AE9: =VLOOKUP(D9,TIPOLOGIAS!A:F,5,0) -> TERRESTRE | AF9: VISITA _TECNICA | AG9: 20 | AH9: 0 | AI9: 0 | AJ9: 0 | AK9: 0 | AL9: =IF(AD9="TIPO I",'BASE LIQUIDACION'!$D$3,IF(AD9="TIPO II",'BASE LIQUIDACION'!$D$4,IF(AD9="TIPO III",'BASE LIQUIDACION'!$D$5,'BASE LIQUIDACION'!$D$7))) -> 134410.39 | AM9: =AG9*'BASE LIQUIDACION'!$B$12+AH9*'BASE LIQUIDACION'!$B$11+AI9*'BASE LIQUIDACION'!$B$13+AJ9*'BASE LIQUIDACION'!$B$14+AK9*AL9 -> 324693.91
A10: BUCARAMANGA | B10: =VLOOKUP(A10,'CENTRO DE COSTOS'!A:D,4,FALSE) -> MIGUEL JULIÁN HERNÁNDEZ GUARÍN | C10: =VLOOKUP(A10,'CENTRO DE COSTOS'!A:C,2,FALSE) -> 0004-0008 | D10: 68307 | E10: TA-25-755918 | F10: FO-25-1085436 | G10: 45821 | H10: 45825 | I10: 45821 | J10: 45824 | K10: 45824 | L10: SANTANDER | M10: GIRON | N10: BARRIO VEREDA CHOCOITA SECTOR TRES ESQUINAS GIRON | O10: 79867 | P10: CB CRECIMIENTO - NUEVO | Q10: APERTURA | R10: REDEBAN | S10: UNO A UNO | T10: UNO A UNO | U10: EJECUTADO | V10: 13-06 SE REALIZA LLAMADA AL CLIENTE, SE HABLA CON LA SR LIBARDO GOMEZ GOMEZ SE VALIDA DIRECCIÓN OK, CANAL OK, DISPONIBILIDAD TOTAL, LLAMAR EL DÍA LA INSTALACIÓN PARA CONFIRMAR VISITA, AVISO EXTERIOR ALTURA APROX 3 METROS; TOMACORRIENTE CERCANO: SI; TIENE CABINA DE SEGURIDAD: NO - COMUNICACIÓN POR WPP - EL MODEM ESTA A 5 MT // SE DEBEN COMUNICAR POR WPP YA QUE LA SEÑAL ES MALA 16/6/2025 SE REALIZA INSTALACIÓN DE CORRESPONSAL, SE INSTALAN EQUIPOS CON PRUEBAS EXITOSAS, SE CAPACITA Y SE EVALÚA AL CLIENTE, SE INSTALA PUBLICIDAD COMPLETA, CB QUEDA OPERATIVO. USUARIO SOMOS BANCOLOMBIA ACTIVO. SE INSTALAN 12 MT DE CABLE UTP | W10: SANTOS GONZALEZ JOHAN FABIAN | X10: FAWZZ662 | Y10: 914673 | Z10: N/A | AA10: 905863 | AB10: N/A | AC10: 40 ROLLOS | AD10: =VLOOKUP(D10,TIPOLOGIAS!A:F,6,0) -> TIPO I | AE10: =VLOOKUP(D10,TIPOLOGIAS!A:F,5,0) -> TERRESTRE | AF10: VISITA _TECNICA | AG10: 12 | AH10: 0 | AI10: 0 | AJ10: 0 | AK10: 0 | AL10: =IF(AD10="TIPO I",'BASE LIQUIDACION'!$D$3,IF(AD10="TIPO II",'BASE LIQUIDACION'!$D$4,IF(AD10="TIPO III",'BASE LIQUIDACION'!$D$5,'BASE LIQUIDACION'!$D$7))) -> 44559.985 | AM10: =AG10*'BASE LIQUIDACION'!$B$12+AH10*'BASE LIQUIDACION'!$B$11+AI10*'BASE LIQUIDACION'!$B$13+AJ10*'BASE LIQUIDACION'!$B$14+AK10*AL10 -> 194816.35
A11: PEREIRA | B11: =VLOOKUP(A11,'CENTRO DE COSTOS'!A:D,4,FALSE) -> DIEGO FERNANDO HENAO CARDONA | C11: =VLOOKUP(A11,'CENTRO DE COSTOS'!A:C,2,FALSE) -> 0004-0002 | D11: 66001 | E11: TA-25-790519 | F11: FO-25-1106940 | G11: 45826 | H11: 45828 | I11: 45826 | J11: 45828 | K11: 45828 | L11: RISARALDA | M11: PEREIRA | N11: BARRIO BETULIA BAJA PEREIRA | O11: 79947 | P11: CB CRECIMIENTO - NUEVO | Q11: APERTURA | R11: REDEBAN | S11: UNO A UNO | T11: UNO A UNO | U11: EJECUTADO | V11: 17-06 SE REALIZA LLAMADA AL CLIENTE, SE HABLA CON LA SRA NATHALI RIVERA MARTINEZ SE VALIDA DIRECCIÓN OK, CANAL OK, DISPONIBILIDAD TOTAL, LLAMAR EL DÍA LA INSTALACIÓN PARA CONFIRMAR VISITA, AVISO EXTERIOR ALTURA APROX 2 METROS; TOMACORRIENTE CERCANO: SI; TIENE CABINA DE SEGURIDAD: SI // CONTACTO REALIZADO POR LA APP 20/6/2025 SE REALIZA INSTALACIÓN DE CORRESPONSAL, SE INSTALAN EQUIPOS CON PRUEBAS EXITOSAS, SE CAPACITA Y SE EVALÚA AL CLIENTE, SE INSTALA PUBLICIDAD COMPLETA, CB QUEDA OPERATIVO. USUARIO SOMOS BANCOLOMBIA ACTIVO. SE INSTALAN 10 MT DE CABLE UTP | W11: ARROYAVE CANO MANUEL GUILLERMO | X11: SAVZZ109 | Y11: 1235257 | Z11: N/A | AA11: 1071586-241597317561324755899579 | AB11: N/A | AC11: 40 ROLLOS | AD11: =VLOOKUP(D11,TIPOLOGIAS!A:F,6,0) -> TIPO I | AE11: =VLOOKUP(D11,TIPOLOGIAS!A:F,5,0) -> TERRESTRE | AF11: VISITA _TECNICA | AG11: 10 | AH11: 0 | AI11: 0 | AJ11: 0 | AK11: 0 | AL11: =IF(AD11="TIPO I",'BASE LIQUIDACION'!$D$3,IF(AD11="TIPO II",'BASE LIQUIDACION'!$D$4,IF(AD11="TIPO III",'BASE LIQUIDACION'!$D$5,'BASE LIQUIDACION'!$D$7))) -> 44559.985 | AM11: =AG11*'BASE LIQUIDACION'!$B$12+AH11*'BASE LIQUIDACION'!$B$11+AI11*'BASE LIQUIDACION'!$B$13+AJ11*'BASE LIQUIDACION'!$B$14+AK11*AL11 -> 162346.95
A12: BUCARAMANGA | B12: =VLOOKUP(A12,'CENTRO DE COSTOS'!A:D,4,FALSE) -> MIGUEL JULIÁN HERNÁNDEZ GUARÍN | C12: =VLOOKUP(A12,'CENTRO DE COSTOS'!A:C,2,FALSE) -> 0004-0008 | D12: 68001 | E12: TA-25-790557 | F12: FO-25-1107050 | G12: 45826 | H12: 45828 | I12: 45826 | J12: 45827 | K12: 45827 | L12: SANTANDER | M12: BUCARAMANGA | N12: BARRIO LAS MERCEDES BUCARAMANGA | O12: 79935 | P12: CB CRECIMIENTO - NUEVO | Q12: APERTURA | R12: REDEBAN | S12: UNO A UNO | T12: UNO A UNO | U12: EJECUTADO | V12: 17-06 SE REALIZA LLAMADA AL CLIENTE, SE HABLA CON LA SRA FRANCEDID ESTEPA SE VALIDA DIRECCIÓN OK, CANAL OK, DISPONIBILIDAD TOTAL, LLAMAR EL DÍA LA INSTALACIÓN PARA CONFIRMAR VISITA, AVISO EXTERIOR ALTURA APROX 3 METROS; TOMACORRIENTE CERCANO: SI; TIENE CABINA DE SEGURIDAD: SI - COMUNICACIÓN POR WPP 19/6/2025 SE REALIZA INSTALACIÓN DE CORRESPONSAL, SE INSTALAN EQUIPOS CON PRUEBAS EXITOSAS, SE CAPACITA Y SE EVALÚA AL CLIENTE, SE INSTALA PUBLICIDAD COMPLETA, CB QUEDA OPERATIVO. USUARIO SOMOS BANCOLOMBIA ACTIVO. SE INSTALAN 10 MT DE CABLE UTP | W12: SANTOS GONZALEZ JOHAN FABIAN | X12: SAVZZ135 | Y12: 1074974 | Z12: N/A | AA12: 1060202 | AB12: N/A | AC12: 40 ROLLOS | AD12: =VLOOKUP(D12,TIPOLOGIAS!A:F,6,0) -> TIPO I | AE12: =VLOOKUP(D12,TIPOLOGIAS!A:F,5,0) -> TERRESTRE | AF12: VISITA _TECNICA | AG12: 10 | AH12: 0 | AI12: 0 | AJ12: 0 | AK12: 0 | AL12: =IF(AD12="TIPO I",'BASE LIQUIDACION'!$D$3,IF(AD12="TIPO II",'BASE LIQUIDACION'!$D$4,IF(AD12="TIPO III",'BASE LIQUIDACION'!$D$5,'BASE LIQUIDACION'!$D$7))) -> 44559.985 | AM12: =AG12*'BASE LIQUIDACION'!$B$12+AH12*'BASE LIQUIDACION'!$B$11+AI12*'BASE LIQUIDACION'!$B$13+AJ12*'BASE LIQUIDACION'!$B$14+AK12*AL12 -> 162346.95
A13: BOGOTA | B13: =VLOOKUP(A13,'CENTRO DE COSTOS'!A:D,4,FALSE) -> WILLIAM ASDRUBAL ROZO ROZO | C13: =VLOOKUP(A13,'CENTRO DE COSTOS'!A:C,2,FALSE) -> 0004-0004 | D13: 25473 | E13: TA-25-790574 | F13: FO-25-1107071 | G13: 45826 | H13: 45828 | I13: 45826 | J13: 45828 | K13: 45828 | L13: CUNDINAMARCA | M13: MOSQUERA | N13: BARRIO EL POBLADO MOSQUERA 5 | O13: 79945 | P13: CB CRECIMIENTO - NUEVO | Q13: APERTURA | R13: REDEBAN | S13: UNO A UNO | T13: UNO A UNO | U13: EJECUTADO | V13: 18-06 SE REALIZA LLAMADA AL CLIENTE, SE HABLA CON LA SRA NORMA KRISTYNNA MONTEALEGRE QUINTANA SE VALIDA DIRECCIÓN OK, CANAL OK, DISPONIBILIDAD TOTAL, LLAMAR EL DÍA LA INSTALACIÓN PARA CONFIRMAR VISITA, AVISO EXTERIOR ALTURA APROX 2 METROS; TOMACORRIENTE CERCANO: SI; TIENE CABINA DE SEGURIDAD: NO - COMUNICACION POR WPP - EL MODEM ESTA A 8 MT 20/6/2025 SE REALIZA INSTALACIÓN DE CORRESPONSAL, SE INSTALAN EQUIPOS CON PRUEBAS EXITOSAS, SE CAPACITA Y SE EVALÚA AL CLIENTE, SE INSTALA PUBLICIDAD COMPLETA, CB QUEDA OPERATIVO. USUARIO SOMOS BANCOLOMBIA ACTIVO. SE INSTALAN 13 MT DE CABLE UTP | W13: VEGA MANRIQUE JONATAN MAURICIO | X13: SAVZZ140 | Y13: 1235389 | Z13: N/A | AA13: 1238706-243637317561365457309488 | AB13: N/A | AC13: 40 ROLLOS | AD13: =VLOOKUP(D13,TIPOLOGIAS!A:F,6,0) -> TIPO I | AE13: =VLOOKUP(D13,TIPOLOGIAS!A:F,5,0) -> TERRESTRE | AF13: VISITA _TECNICA | AG13: 13 | AH13: 0 | AI13: 0 | AJ13: 0 | AK13: 0 | AL13: =IF(AD13="TIPO I",'BASE LIQUIDACION'!$D$3,IF(AD13="TIPO II",'BASE LIQUIDACION'!$D$4,IF(AD13="TIPO III",'BASE LIQUIDACION'!$D$5,'BASE LIQUIDACION'!$D$7))) -> 44559.985 | AM13: =AG13*'BASE LIQUIDACION'!$B$12+AH13*'BASE LIQUIDACION'!$B$11+AI13*'BASE LIQUIDACION'!$B$13+AJ13*'BASE LIQUIDACION'!$B$14+AK13*AL13 -> 211051.04
A14: BUCARAMANGA | B14: =VLOOKUP(A14,'CENTRO DE COSTOS'!A:D,4,FALSE) -> MIGUEL JULIÁN HERNÁNDEZ GUARÍN | C14: =VLOOKUP(A14,'CENTRO DE COSTOS'!A:C,2,FALSE) -> 0004-0008 | D14: 68500 | E14: TA-25-799030 | F14: FO-25-1128521 | G14: 45832 | H14: 45834 | I14: 45832 | J14: 45833 | K14: 45833 | L14: SANTANDER | M14: OIBA | N14: BARRIO POIMA OIBA OIBA | O14: 80035 | P14: CB CRECIMIENTO - NUEVO | Q14: APERTURA | R14: REDEBAN | S14: UNO A UNO | T14: UNO A UNO | U14: EJECUTADO | V14: 21-06 SE REALIZA LLAMADA AL CLIENTE, SE HABLA CON LA SRA SANDRA MILENA PABON SILVA, SE VALIDA DIRECCIÓN OK, CANAL OK, DISPONIBILIDAD TOTAL, LLAMAR EL DÍA LA INSTALACIÓN PARA CONFIRMAR VISITA, AVISO EXTERIOR ALTURA APROX 1,50 METROS; TOMACORRIENTE CERCANO: SI; TIENE CABINA DE SEGURIDAD: NO// TOMACORRIENTE A 6 METROS 25/6/2025 SE REALIZA INSTALACIÓN DE CORRESPONSAL, SE INSTALAN EQUIPOS CON PRUEBAS EXITOSAS, SE CAPACITA Y SE EVALÚA AL CLIENTE, SE INSTALA PUBLICIDAD COMPLETA, CB QUEDA OPERATIVO. USUARIO SOMOS BANCOLOMBIA ACTIVO. SE INSTALAN 10 MT DE CABLE UTP | W14: GELVEZ MOGOLLON JOSE ELISEO | X14: SAXZZ451 | Y14: 1052001 | Z14: N/A | AA14: 1103658 | AB14: N/A | AC14: 40 ROLLOS | AD14: =VLOOKUP(D14,TIPOLOGIAS!A:F,6,0) -> TIPO III | AE14: =VLOOKUP(D14,TIPOLOGIAS!A:F,5,0) -> TERRESTRE | AF14: VISITA _TECNICA | AG14: 10 | AH14: 0 | AI14: 0 | AJ14: 0 | AK14: 0 | AL14: =IF(AD14="TIPO I",'BASE LIQUIDACION'!$D$3,IF(AD14="TIPO II",'BASE LIQUIDACION'!$D$4,IF(AD14="TIPO III",'BASE LIQUIDACION'!$D$5,'BASE LIQUIDACION'!$D$7))) -> 222904.27 | AM14: =AG14*'BASE LIQUIDACION'!$B$12+AH14*'BASE LIQUIDACION'!$B$11+AI14*'BASE LIQUIDACION'!$B$13+AJ14*'BASE LIQUIDACION'!$B$14+AK14*AL14 -> 162346.95
A15: BUCARAMANGA | B15: =VLOOKUP(A15,'CENTRO DE COSTOS'!A:D,4,FALSE) -> MIGUEL JULIÁN HERNÁNDEZ GUARÍN | C15: =VLOOKUP(A15,'CENTRO DE COSTOS'!A:C,2,FALSE) -> 0004-0008 | D15: 68615 | E15: TA-25-799038 | F15: FO-25-1128558 | G15: 45832 | H15: 45834 | I15: 45832 | J15: 45833 | K15: 45833 | L15: SANTANDER | M15: RIONEGRO | N15: BARRIO CENTRO RIONEGRO 3 | O15: 80055 | P15: CB CRECIMIENTO - NUEVO | Q15: APERTURA | R15: REDEBAN | S15: UNO A UNO | T15: UNO A UNO | U15: EJECUTADO | V15: 24-06-2025 SE REALIZA LLAMADA AL CLIENTE, SE HABLA CON LA SRA LIZY ANDREA JAIMES OLAVE SE VALIDA DIRECCIÓN OK, CANAL OK, DISPONIBILIDAD TOTAL, LLAMAR EL DÍA LA INSTALACIÓN PARA CONFIRMAR VISITA, AVISO EXTERIOR ALTURA APROX CLIENTE NO TIENE CONOCIMIENTO DE MEDIDAS; TOMACORRIENTE CERCANO: SI; TIENE CABINA DE SEGURIDAD: SI // CONTACTO REALIZADO POR LA APP // CLIENTE INDICA QUE SI NO CONTESTA POR LLAMADA, S ECOMUNIQUEN POR WHATSAPP QUE ES MAS FIJO 25/6/2025 SE REALIZA INSTALACIÓN DE CORRESPONSAL, SE INSTALAN EQUIPOS CON PRUEBAS EXITOSAS, SE CAPACITA Y SE EVALÚA AL CLIENTE, SE INSTALA PUBLICIDAD COMPLETA, CB QUEDA OPERATIVO. USUARIO SOMOS BANCOLOMBIA ACTIVO. SE INSTALAN 10 MT DE CABLE UTP | W15: SANTOS GONZALEZ JOHAN FABIAN | X15: SAXZZ458 | Y15: 1240742 | Z15: N/A | AA15: 879503 | AB15: N/A | AC15: 40 ROLLOS | AD15: =VLOOKUP(D15,TIPOLOGIAS!A:F,6,0) -> TIPO II | AE15: =VLOOKUP(D15,TIPOLOGIAS!A:F,5,0) -> TERRESTRE | AF15: VISITA _TECNICA | AG15: 10 | AH15: 0 | AI15: 0 | AJ15: 0 | AK15: 0 | AL15: =IF(AD15="TIPO I",'BASE LIQUIDACION'!$D$3,IF(AD15="TIPO II",'BASE LIQUIDACION'!$D$4,IF(AD15="TIPO III",'BASE LIQUIDACION'!$D$5,'BASE LIQUIDACION'!$D$7))) -> 134410.39 | AM15: =AG15*'BASE LIQUIDACION'!$B$12+AH15*'BASE LIQUIDACION'!$B$11+AI15*'BASE LIQUIDACION'!$B$13+AJ15*'BASE LIQUIDACION'!$B$14+AK15*AL15 -> 162346.95
A16: TUNJA | B16: =VLOOKUP(A16,'CENTRO DE COSTOS'!A:D,4,FALSE) -> MIGUEL JULIÁN HERNÁNDEZ GUARÍN | C16: =VLOOKUP(A16,'CENTRO DE COSTOS'!A:C,2,FALSE) -> 0004-0008 | D16: 15001 | E16: TA-25-799125 | F16: FO-25-1128655 | G16: 45832 | H16: 45834 | I16: 45832 | J16: 45833 | K16: 45833 | L16: BOYACA | M16: TUNJA | N16: BARRIO TUNJUELITO TUNJA 1 | O16: 80068 | P16: CB CRECIMIENTO - NUEVO | Q16: APERTURA | R16: REDEBAN | S16: UNO A UNO | T16: UNO A UNO | U16: EJECUTADO | V16: 24-06-2025 SE REALIZA LLAMADA AL CLIENTE, SE HABLA CON LA SRA DIANA ESPERANZA GONZÁLEZ IBAÑEZ SE VALIDA DIRECCIÓN OK, CANAL OK, DISPONIBILIDAD TOTAL, LLAMAR EL DÍA LA INSTALACIÓN PARA CONFIRMAR VISITA, AVISO EXTERIOR ALTURA APROX 1,80 METROS; TOMACORRIENTE CERCANO: SI; TIENE CABINA DE SEGURIDAD: NO // CONTACTO REALIZADO POR LA APP 25/6/2025 SE REALIZA INSTALACIÓN DE CORRESPONSAL, SE INSTALAN EQUIPOS CON PRUEBAS EXITOSAS, SE CAPACITA Y SE EVALÚA AL CLIENTE, SE INSTALA PUBLICIDAD COMPLETA, CB QUEDA OPERATIVO. USUARIO SOMOS BANCOLOMBIA ACTIVO. SE INSTALAN 6 MT DE CABLE UTP | W16: SOLER HOYOS CRISTIAN LEONARDO | X16: SAXZZ466 | Y16: 1242413 | Z16: 274888 | AA16: 903638-243637317561365457310152 | AB16: N/A | AC16: 40 ROLLOS | AD16: =VLOOKUP(D16,TIPOLOGIAS!A:F,6,0) -> TIPO I | AE16: =VLOOKUP(D16,TIPOLOGIAS!A:F,5,0) -> TERRESTRE | AF16: VISITA _TECNICA | AG16: 6 | AH16: 0 | AI16: 0 | AJ16: 0 | AK16: 0 | AL16: =IF(AD16="TIPO I",'BASE LIQUIDACION'!$D$3,IF(AD16="TIPO II",'BASE LIQUIDACION'!$D$4,IF(AD16="TIPO III",'BASE LIQUIDACION'!$D$5,'BASE LIQUIDACION'!$D$7))) -> 44559.985 | AM16: =AG16*'BASE LIQUIDACION'!$B$12+AH16*'BASE LIQUIDACION'!$B$11+AI16*'BASE LIQUIDACION'!$B$13+AJ16*'BASE LIQUIDACION'!$B$14+AK16*AL16 -> 97408.173
A17: CALI | B17: =VLOOKUP(A17,'CENTRO DE COSTOS'!A:D,4,FALSE) -> DIEGO FERNANDO HENAO CARDONA | C17: =VLOOKUP(A17,'CENTRO DE COSTOS'!A:C,2,FALSE) -> 0004-0003 | D17: 76001 | E17: TA-25-799143 | F17: FO-25-1128724 | G17: 45832 | H17: 45834 | I17: 45832 | J17: 45833 | K17: 45833 | L17: VALLE DEL CAUCA | M17: CALI | N17: BARRIO COMUNEROS I CALI 2 | O17: 79989 | P17: CB CRECIMIENTO - NUEVO | Q17: APERTURA | R17: REDEBAN | S17: UNO A UNO | T17: UNO A UNO | U17: EJECUTADO | V17: 24-06-2025 SE REALIZA LLAMADA AL CLIENTE, SE HABLA CON LA ESPOSA DE SR CARLOS JAVIER LEFFA ZAMBRANO SE VALIDA DIRECCIÓN OK, CANAL OK, DISPONIBILIDAD TOTAL, LLAMAR EL DÍA LA INSTALACIÓN PARA CONFIRMAR VISITA, AVISO EXTERIOR ALTURA APROX CLIENTE NO TIENE CONOCIMIENTO DE MEDIDAS; TOMACORRIENTE CERCANO: SI; TIENE CABINA DE SEGURIDAD: SI // CONTACTO REALIZADO POR WHATSAPP 25/6/2025 SE REALIZA INSTALACIÓN DE CORRESPONSAL, SE INSTALAN EQUIPOS CON PRUEBAS EXITOSAS, SE CAPACITA Y SE EVALÚA AL CLIENTE, SE INSTALA PUBLICIDAD COMPLETA, CB QUEDA OPERATIVO. USUARIO SOMOS BANCOLOMBIA ACTIVO. SE INSTALA 6 MT DE CABLE UTP | W17: MONTERO MUESES GIAN CARLO | X17: SAXZZ479 | Y17: 1175384 | Z17: N/A | AA17: 914088 | AB17: N/A | AC17: 40 ROLLOS | AD17: =VLOOKUP(D17,TIPOLOGIAS!A:F,6,0) -> TIPO I | AE17: =VLOOKUP(D17,TIPOLOGIAS!A:F,5,0) -> TERRESTRE | AF17: VISITA _TECNICA | AG17: 6 | AH17: 0 | AI17: 0 | AJ17: 0 | AK17: 0 | AL17: =IF(AD17="TIPO I",'BASE LIQUIDACION'!$D$3,IF(AD17="TIPO II",'BASE LIQUIDACION'!$D$4,IF(AD17="TIPO III",'BASE LIQUIDACION'!$D$5,'BASE LIQUIDACION'!$D$7))) -> 44559.985 | AM17: =AG17*'BASE LIQUIDACION'!$B$12+AH17*'BASE LIQUIDACION'!$B$11+AI17*'BASE LIQUIDACION'!$B$13+AJ17*'BASE LIQUIDACION'!$B$14+AK17*AL17 -> 97408.173
A18: PEREIRA | B18: =VLOOKUP(A18,'CENTRO DE COSTOS'!A:D,4,FALSE) -> DIEGO FERNANDO HENAO CARDONA | C18: =VLOOKUP(A18,'CENTRO DE COSTOS'!A:C,2,FALSE) -> 0004-0002 | D18: 66001 | E18: TA-25-799158 | F18: FO-25-1128788 | G18: 45832 | H18: 45834 | I18: 45832 | J18: 45834 | K18: 45834 | L18: RISARALDA | M18: PEREIRA | N18: BARRIO CENTRO PEREIRA 48 | O18: 80044 | P18: CB CRECIMIENTO - NUEVO | Q18: APERTURA | R18: REDEBAN | S18: UNO A UNO | T18: UNO A UNO | U18: EJECUTADO | V18: 24-06 SE REALIZA LLAMADA AL CLIENTE, SE HABLA CON LA SRA YULI ANDREA BECERRA YA QUE SR CARLOS ANDRES ARIZA GONZALEZ NO SE ENCUENTRA SE VALIDA DIRECCIÓN OK, DISPONIBILIDAD TOTAL, LLAMAR EL DÍA LA INSTALACIÓN PARA CONFIRMAR VISITA, AVISO EXTERIOR ALTURA APROX 2.00 METROS; TOMA CORRIENTE CERCANO: SI; TIENE CABINA DE SEGURIDAD: NO , USUARIO INDICA QUE SE EL MODEN SE ENCUENTRA 10 METROS 26/6/2025 SE REALIZA INSTALACIÓN DE CORRESPONSAL, SE INSTALAN EQUIPOS CON PRUEBAS EXITOSAS, SE CAPACITA Y SE EVALÚA AL CLIENTE, SE INSTALA PUBLICIDAD COMPLETA, CB QUEDA OPERATIVO. USUARIO SOMOS BANCOLOMBIA ACTIVO. SE INSTALAN 15 MT DE CABLE UTP | W18: FRANCO CAÑAVERAL YAMID RAUL | X18: SAXZZ492 | Y18: 1235358 | Z18: N/A | AA18: 1076556-241587317561324755887228 | AB18: N/A | AC18: 40 ROLLOS | AD18: =VLOOKUP(D18,TIPOLOGIAS!A:F,6,0) -> TIPO I | AE18: =VLOOKUP(D18,TIPOLOGIAS!A:F,5,0) -> TERRESTRE | AF18: VISITA _TECNICA | AG18: 15 | AH18: 0 | AI18: 0 | AJ18: 0 | AK18: 0 | AL18: =IF(AD18="TIPO I",'BASE LIQUIDACION'!$D$3,IF(AD18="TIPO II",'BASE LIQUIDACION'!$D$4,IF(AD18="TIPO III",'BASE LIQUIDACION'!$D$5,'BASE LIQUIDACION'!$D$7))) -> 44559.985 | AM18: =AG18*'BASE LIQUIDACION'!$B$12+AH18*'BASE LIQUIDACION'!$B$11+AI18*'BASE LIQUIDACION'!$B$13+AJ18*'BASE LIQUIDACION'!$B$14+AK18*AL18 -> 243520.43
A19: MEDELLIN | B19: =VLOOKUP(A19,'CENTRO DE COSTOS'!A:D,4,FALSE) -> JUAN SEBASTIÁN RÍOS CASTRILLÓN | C19: =VLOOKUP(A19,'CENTRO DE COSTOS'!A:C,2,FALSE) -> 0004-0005 | D19: 5690 | E19: TA-25-799214 | F19: FO-25-1128965 | G19: 45832 | H19: 45834 | I19: 45832 | J19: 45834 | K19: 45834 | L19: ANTIOQUIA | M19: SANTO DOMINGO | N19: BARRIO CENTRO SANTO DOMINGO | O19: 80054 | P19: CB CRECIMIENTO - NUEVO | Q19: APERTURA | R19: REDEBAN | S19: UNO A UNO | T19: UNO A UNO | U19: EJECUTADO | V19: 21-06 SE REALIZA LLAMADA AL CLIENTE, SE HABLA CON LA SR SANTIAGO RESTREPO CASTRILLON SE VALIDA DIRECCIÓN OK, CANAL OK, DISPONIBILIDAD TOTAL, LLAMAR EL DÍA LA INSTALACIÓN PARA CONFIRMAR VISITA, AVISO EXTERIOR ALTURA APROX 3 METROS; TOMACORRIENTE CERCANO: SI; TIENE CABINA DE SEGURIDAD: NO - COMUNICACIÓN POR WPP 26/6/2025 ESCALAMOS NOVEDAD DE INSTALACIÓN. EN DIRECCIÓN TENEMOS LT LA MAQUINA VRD PORCESITO, PERO DOCUMENTO DE CÁMARA DE COMERCIO QUE NOS FACILITA USUARIO TIENE DIRECCIÓN CON NOMENCLATURA COMPLETA CALLE 39 64ª 35 INTERIOR 701 EN MEDELLIN. USUARIO INFORMA QUE ESA DIRECCIÓN ES DE LA OFICINA PRINCIPAL EN MEDELLIN. TAMBIÉN NOS FACILITA UNA FOTO DE UNA FACTURA DE UN PROVEEDOR DONDE SALE LA MISMA DIRECCIÓN EN MEDELLIN, PERO ABAJO SI DICE PORSECITO. 26/6/2025 SEGÚN LO CONVERSADO, SE EVIDENCIÓ QUE EN LA SEGUNDA HOJA DEL CERTIFICADO DE CÁMARA DE COMERCIO SE ENCUENTRA REGISTRADA LA DIRECCIÓN CORRECTA. POR LO TANTO, SE DEBE PROCEDER CON LA IMPLEMENTACIÓN DEL CB 3007080054. 26/6/2025 SE REALIZA INSTALACIÓN DE CORRESPONSAL, SE INSTALAN EQUIPOS CON PRUEBAS EXITOSAS, SE CAPACITA Y SE EVALÚA AL CLIENTE, SE INSTALA PUBLICIDAD COMPLETA, CB QUEDA OPERATIVO. USUARIO SOMOS BANCOLOMBIA ACTIVO. SE INSTALANN 12 MT DE CABLE UTP | W19: ZAPATA LOPEZ EDWARD ASDRUBAL | X19: SAXZZ525 | Y19: 1254223 | Z19: N/A | AA19: 1238897-243627317561365457299638 | AB19: N/A | AC19: 40 ROLLOS | AD19: =VLOOKUP(D19,TIPOLOGIAS!A:F,6,0) -> TIPO II | AE19: =VLOOKUP(D19,TIPOLOGIAS!A:F,5,0) -> TERRESTRE | AF19: VISITA _TECNICA | AG19: 12 | AH19: 0 | AI19: 0 | AJ19: 0 | AK19: 0 | AL19: =IF(AD19="TIPO I",'BASE LIQUIDACION'!$D$3,IF(AD19="TIPO II",'BASE LIQUIDACION'!$D$4,IF(AD19="TIPO III",'BASE LIQUIDACION'!$D$5,'BASE LIQUIDACION'!$D$7))) -> 134410.39 | AM19: =AG19*'BASE LIQUIDACION'!$B$12+AH19*'BASE LIQUIDACION'!$B$11+AI19*'BASE LIQUIDACION'!$B$13+AJ19*'BASE LIQUIDACION'!$B$14+AK19*AL19 -> 194816.35
A20: MEDELLIN | B20: =VLOOKUP(A20,'CENTRO DE COSTOS'!A:D,4,FALSE) -> JUAN SEBASTIÁN RÍOS CASTRILLÓN | C20: =VLOOKUP(A20,'CENTRO DE COSTOS'!A:C,2,FALSE) -> 0004-0005 | D20: 5001 | E20: TA-25-799289 | F20: FO-25-1129202 | G20: 45832 | H20: 45834 | I20: 45832 | J20: 45834 | K20: 45834 | L20: ANTIOQUIA | M20: MEDELLIN | N20: BARRIO BELEN MEDELLIN 15 | O20: 80087 | P20: CB CRECIMIENTO - NUEVO | Q20: APERTURA | R20: REDEBAN | S20: UNO A UNO | T20: UNO A UNO | U20: EJECUTADO | V20: 21-06 SE REALIZA LLAMADA AL CLIENTE, SE HABLA CON LA SR MARTIN ALONSO HERNANDEZ LARREA SE VALIDA DIRECCIÓN OK, CANAL OK, DISPONIBILIDAD TOTAL, LLAMAR EL DÍA LA INSTALACIÓN PARA CONFIRMAR VISITA, AVISO EXTERIOR ALTURA APROX 3 METROS; TOMACORRIENTE CERCANO: SI; TIENE CABINA DE SEGURIDAD: NO - EL MODEM ESTA A 5 MT 26/6/2025 SE REALIZA INSTALACIÓN DE CORRESPONSAL, SE INSTALAN EQUIPOS CON PRUEBAS EXITOSAS, SE CAPACITA Y SE EVALÚA AL CLIENTE, SE INSTALA PUBLICIDAD COMPLETA, CB QUEDA OPERATIVO. USUARIO SOMOS BANCOLOMBIA ACTIVO. SE INSTALAN 7 MT DE CABLE UTP | W20: ALVAREZ ARENAS VICTOR HUGO | X20: SAXZZ563 | Y20: 1254482 | Z20: N/A | AA20: 1238899-243627317561365457298717 | AB20: N/A | AC20: 40 ROLLOS | AD20: =VLOOKUP(D20,TIPOLOGIAS!A:F,6,0) -> TIPO I | AE20: =VLOOKUP(D20,TIPOLOGIAS!A:F,5,0) -> TERRESTRE | AF20: VISITA _TECNICA | AG20: 7 | AH20: 0 | AI20: 0 | AJ20: 0 | AK20: 0 | AL20: =IF(AD20="TIPO I",'BASE LIQUIDACION'!$D$3,IF(AD20="TIPO II",'BASE LIQUIDACION'!$D$4,IF(AD20="TIPO III",'BASE LIQUIDACION'!$D$5,'BASE LIQUIDACION'!$D$7))) -> 44559.985 | AM20: =AG20*'BASE LIQUIDACION'!$B$12+AH20*'BASE LIQUIDACION'!$B$11+AI20*'BASE LIQUIDACION'!$B$13+AJ20*'BASE LIQUIDACION'!$B$14+AK20*AL20 -> 113642.87
A21: BOGOTA | B21: =VLOOKUP(A21,'CENTRO DE COSTOS'!A:D,4,FALSE) -> WILLIAM ASDRUBAL ROZO ROZO | C21: =VLOOKUP(A21,'CENTRO DE COSTOS'!A:C,2,FALSE) -> 0004-0004 | D21: 11001 | E21: TA-25-799293 | F21: FO-25-1129213 | G21: 45832 | H21: 45834 | I21: 45832 | J21: 45833 | K21: 45833 | L21: CUNDINAMARCA | M21: BOGOTA | N21: BARRIO SAN DIEGO BOGOTA | O21: 79977 | P21: CB CRECIMIENTO - NUEVO | Q21: APERTURA | R21: REDEBAN | S21: UNO A UNO | T21: UNO A UNO | U21: EJECUTADO | V21: 21-06 SE REALIZA LLAMADA AL CLIENTE, SE HABLA CON LA SR AARON EULICES AGUILERA JUNCA SE VALIDA DIRECCIÓN OK, CANAL OK, DISPONIBILIDAD TOTAL, LLAMAR EL DÍA LA INSTALACIÓN PARA CONFIRMAR VISITA, AVISO EXTERIOR ALTURA: NO INDICA ALTURA; TOMACORRIENTE CERCANO: SI; TIENE CABINA DE SEGURIDAD: NO - COMUNICACIÓN POR WPP / EL MODEM ESTA A 6 MT 25/6/2025 NOTA; ESTANDO EN SITIO EL COMERCIO INFORMA NO TENER PERMISO DE INSTALAR LA PUBLICIDAD EN LA PARTE EXTERIOR DEL LOCAL, PIDE SEA INSTALADO EN EL VIDRIO POR LA PARTE INTERNA SIN EL MARCO. DE ACUERDO A LA AUTORIZACIÓN VÍA WHATSAPP, SE INSTALA SEGÚN SOLICITUD DEL COMERCIO. SE REALIZA INSTALACIÓN DE CORRESPONSAL, SE INSTALAN EQUIPOS CON PRUEBAS EXITOSAS, SE CAPACITA Y SE EVALÚA AL CLIENTE, SE INSTALA PUBLICIDAD COMPLETA, CB QUEDA OPERATIVO. USUARIO SOMOS BANCOLOMBIA ACTIVO. SE INSTALAN 6 MT DE CABLE UTP | W21: GOMEZ VEGA DAVID SNEYDER | X21: SAXZZ565 | Y21: 1235380 | Z21: N/A | AA21: 528124-241587317561324755886735 | AB21: N/A | AC21: 40 ROLLOS | AD21: =VLOOKUP(D21,TIPOLOGIAS!A:F,6,0) -> TIPO I | AE21: =VLOOKUP(D21,TIPOLOGIAS!A:F,5,0) -> TERRESTRE | AF21: VISITA _TECNICA | AG21: 6 | AH21: 0 | AI21: 0 | AJ21: 0 | AK21: 0 | AL21: =IF(AD21="TIPO I",'BASE LIQUIDACION'!$D$3,IF(AD21="TIPO II",'BASE LIQUIDACION'!$D$4,IF(AD21="TIPO III",'BASE LIQUIDACION'!$D$5,'BASE LIQUIDACION'!$D$7))) -> 44559.985 | AM21: =AG21*'BASE LIQUIDACION'!$B$12+AH21*'BASE LIQUIDACION'!$B$11+AI21*'BASE LIQUIDACION'!$B$13+AJ21*'BASE LIQUIDACION'!$B$14+AK21*AL21 -> 97408.173
A22: PEREIRA | B22: =VLOOKUP(A22,'CENTRO DE COSTOS'!A:D,4,FALSE) -> DIEGO FERNANDO HENAO CARDONA | C22: =VLOOKUP(A22,'CENTRO DE COSTOS'!A:C,2,FALSE) -> 0004-0002 | D22: 66001 | E22: TA-25-799295 | F22: FO-25-1129221 | G22: 45832 | H22: 45834 | I22: 45832 | J22: 45833 | K22: 45833 | L22: RISARALDA | M22: PEREIRA | N22: BARRIO BELMONTE PEREIRA 6 | O22: 80043 | P22: CB CRECIMIENTO - NUEVO | Q22: APERTURA | R22: REDEBAN | S22: UNO A UNO | T22: UNO A UNO | U22: EJECUTADO | V22: 24-06 SE REALIZA LLAMADA AL CLIENTE, SE HABLA CON LA SR ORLANDO ZAPATA OROZCO SE VALIDA DIRECCIÓN OK, CANAL OK, DISPONIBILIDAD TOTAL, LLAMAR EL DÍA LA INSTALACIÓN PARA CONFIRMAR VISITA, AVISO EXTERIOR ALTURA: NO INDICA ALTURA; TOMACORRIENTE CERCANO: SI; TIENE CABINA DE SEGURIDAD: NO - EL MODEM ESTA A 10 MT 25/6/2025 SE REALIZA INSTALACIÓN DE CORRESPONSAL, SE INSTALAN EQUIPOS CON PRUEBAS EXITOSAS, SE CAPACITA Y SE EVALÚA AL CLIENTE, SE INSTALA PUBLICIDAD COMPLETA, CB QUEDA OPERATIVO. USUARIO SOMOS BANCOLOMBIA ACTIVO | W22: ARROYAVE CANO MANUEL GUILLERMO | X22: SAXZZ567 | Y22: 1235292 | Z22: N/A | AA22: 1217682-241597317561324755901244 | AB22: N/A | AC22: 40 ROLLOS | AD22: =VLOOKUP(D22,TIPOLOGIAS!A:F,6,0) -> TIPO I | AE22: =VLOOKUP(D22,TIPOLOGIAS!A:F,5,0) -> TERRESTRE | AF22: VISITA _TECNICA | AG22: 10 | AH22: 0 | AI22: 0 | AJ22: 0 | AK22: 0 | AL22: =IF(AD22="TIPO I",'BASE LIQUIDACION'!$D$3,IF(AD22="TIPO II",'BASE LIQUIDACION'!$D$4,IF(AD22="TIPO III",'BASE LIQUIDACION'!$D$5,'BASE LIQUIDACION'!$D$7))) -> 44559.985 | AM22: =AG22*'BASE LIQUIDACION'!$B$12+AH22*'BASE LIQUIDACION'!$B$11+AI22*'BASE LIQUIDACION'!$B$13+AJ22*'BASE LIQUIDACION'!$B$14+AK22*AL22 -> 162346.95
A23: CUCUTA | B23: =VLOOKUP(A23,'CENTRO DE COSTOS'!A:D,4,FALSE) -> MIGUEL JULIÁN HERNÁNDEZ GUARÍN | C23: =VLOOKUP(A23,'CENTRO DE COSTOS'!A:C,2,FALSE) -> 0004-0008 | D23: 54498 | E23: TA-25-721901 | F23: FO-25-1062900 | G23: 45817 | H23: 45819 | I23: 45817 | J23: 45818 | K23: 45818 | L23: NORTE DE SANTANDER | M23: OCAÑA | N23: BARRIO EDIFICIO MIRADORES DE LA COLINA OCAÑA | O23: 79815 | P23: CB CRECIMIENTO - NUEVO | Q23: APERTURA | R23: REDEBAN | S23: UNO A UNO | T23: UNO A UNO | U23: EJECUTADO | V23: 07-06 SE REALIZA LLAMADA AL CLIENTE, SE HABLA CON LA S JULIO CESAR JAIME SEPÚLVEDA SE VALIDA DIRECCIÓN OK, CANAL OK, DISPONIBILIDAD TOTAL, LLAMAR EL DÍA LA INSTALACIÓN PARA CONFIRMAR VISITA, AVISO EXTERIOR ALTURA APROX 2.50 METROS; TOMACORRIENTE CERCANO: SI; TIENE CABINA DE SEGURIDAD: NO, EL MODEM ESTA A 6 MT - COMUNICACIÓN POR WPP 10-06 SE REALIZA INSTALACIÓN DE CORRESPONSAL, SE INSTALAN EQUIPOS CON PRUEBAS EXITOSAS, SE CAPACITA Y SE EVALÚA AL CLIENTE, SE INSTALA PUBLICIDAD COMPLETA, CB QUEDA OPERATIVO. USUARIO SOMOS BANCOLOMBIA ACTIVO. SE INSTALA SWITCH 224B0A0009381 | W23: GELVEZ MOGOLLON JOSE ELISEO | X23: F1XZZ025 | Y23: 801650 | Z23: N/A | AA23: 513517 | AB23: N/A | AC23: 40 ROLLOS | AD23: =VLOOKUP(D23,TIPOLOGIAS!A:F,6,0) -> TIPO IV | AE23: =VLOOKUP(D23,TIPOLOGIAS!A:F,5,0) -> TERRESTRE | AF23: VISITA _TECNICA | AG23: 0 | AH23: 0 | AI23: 1 | AJ23: 0 | AK23: 0 | AL23: =IF(AD23="TIPO I",'BASE LIQUIDACION'!$D$3,IF(AD23="TIPO II",'BASE LIQUIDACION'!$D$4,IF(AD23="TIPO III",'BASE LIQUIDACION'!$D$5,'BASE LIQUIDACION'!$D$7))) -> 464809.03 | AM23: =AG23*'BASE LIQUIDACION'!$B$12+AH23*'BASE LIQUIDACION'!$B$11+AI23*'BASE LIQUIDACION'!$B$13+AJ23*'BASE LIQUIDACION'!$B$14+AK23*AL23 -> 257391.82
A24: CALI | B24: =VLOOKUP(A24,'CENTRO DE COSTOS'!A:D,4,FALSE) -> DIEGO FERNANDO HENAO CARDONA | C24: =VLOOKUP(A24,'CENTRO DE COSTOS'!A:C,2,FALSE) -> 0004-0003 | D24: 19698 | E24: TA-25-799178 | F24: FO-25-1128861 | G24: 45832 | H24: 45834 | I24: 45832 | J24: 45834 | K24: 45834 | L24: CAUCA | M24: SANTANDER DE QUILICHAO | N24: BARRIO CENTENARIO SANTANDER DE QUILICHAO 5 | O24: 80062 | P24: CB CRECIMIENTO - NUEVO | Q24: APERTURA | R24: REDEBAN | S24: UNO A UNO | T24: UNO A UNO | U24: EJECUTADO | V24: 24-06 SE REALIZA LLAMADA AL CLIENTE, SE HABLA CON LA SRA JUAN JOSE DELGADO ARIAS SE VALIDA DIRECCIÓN OK, CANAL OK, DISPONIBILIDAD TOTAL, LLAMAR EL DÍA LA INSTALACIÓN PARA CONFIRMAR VISITA, AVISO EXTERIOR ALTURA APROX 3 METROS; TOMACORRIENTE CERCANO: SI; TIENE CABINA DE SEGURIDAD: NO - COMUNICACIÓN POR WPP / EL MODEM NO TIENE PUERTO DISPONIBLES LLEVAR SWITCH 26/6/2025 SE REALIZA INSTALACIÓN DE CORRESPONSAL, SE INSTALAN EQUIPOS CON PRUEBAS EXITOSAS, SE CAPACITA Y SE EVALÚA AL CLIENTE, SE INSTALA PUBLICIDAD COMPLETA, CB QUEDA OPERATIVO. USUARIO SOMOS BANCOLOMBIA ACTIVO. SE INSTALA WITCH QS013CC000233 | W24: MONTERO MUESES GIAN CARLO | X24: SAXZZ504 | Y24: 1254318 | Z24: N/A | AA24: 1233700-243637317561365457309861 | AB24: N/A | AC24: 40 ROLLOS | AD24: =VLOOKUP(D24,TIPOLOGIAS!A:F,6,0) -> TIPO II | AE24: =VLOOKUP(D24,TIPOLOGIAS!A:F,5,0) -> TERRESTRE | AF24: VISITA _TECNICA | AG24: 0 | AH24: 0 | AI24: 1 | AJ24: 0 | AK24: 0 | AL24: =IF(AD24="TIPO I",'BASE LIQUIDACION'!$D$3,IF(AD24="TIPO II",'BASE LIQUIDACION'!$D$4,IF(AD24="TIPO III",'BASE LIQUIDACION'!$D$5,'BASE LIQUIDACION'!$D$7))) -> 134410.39 | AM24: =AG24*'BASE LIQUIDACION'!$B$12+AH24*'BASE LIQUIDACION'!$B$11+AI24*'BASE LIQUIDACION'!$B$13+AJ24*'BASE LIQUIDACION'!$B$14+AK24*AL24 -> 257391.82
A25: TUNJA | B25: =VLOOKUP(A25,'CENTRO DE COSTOS'!A:D,4,FALSE) -> MIGUEL JULIÁN HERNÁNDEZ GUARÍN | C25: =VLOOKUP(A25,'CENTRO DE COSTOS'!A:C,2,FALSE) -> 0004-0008 | D25: 15681 | E25: TA-25-755896 | F25: FO-25-1085382 | G25: 45821 | H25: 45825 | I25: 45821 | J25: 45825 | K25: 45825 | L25: BOYACA | M25: SAN PABLO DE BORBUR | N25: BARRIO CHACARO SAN PABLO DE BORBUR | O25: 79858 | P25: CB CRECIMIENTO - NUEVO | Q25: APERTURA | R25: REDEBAN | S25: UNO A UNO | T25: UNO A UNO | U25: EJECUTADO | V25: 13-06 SE REALIZA LLAMADA AL CLIENTE, SE HABLA CON LA SRA HEIDY TATIANA OSORIO RUEDA SE VALIDA DIRECCIÓN OK, CANAL OK, DISPONIBILIDAD TOTAL, LLAMAR EL DÍA LA INSTALACIÓN PARA CONFIRMAR VISITA, AVISO EXTERIOR ALTURA APROX CLEINTE NO TIENE CONOCIMIENTO DE MEDIDAS; TOMACORRIENTE CERCANO: SI; TIENE CABINA DE SEGURIDAD: NO // CONTACTO REALIZADO POR LA APP 16-06 ME ENCUENTRO EN RUTA HACIA LA ZONA DE CHIQUINQUIRÁ POR TEMAS DE TRASPORTE YA QUE NO ES MUY SEGUIDO NO SE LOGRARIA LLEGAR AL SITIO DE LA INSTALACION , EN COMUNICACIÓN CON EL CLIENTE LA SEÑORA TATIANA OSORIO AL NÚMERO CELULAR 3046464134 SE LE INDICA QUE SE ATENDERA ACTIVIDAD EL DÍA DE MAÑANA 17 JUNIO DEL 2025 EN TRANSCURSO DE DIA , CLIENTE CONFORME 17/6/2025 SE REALIZA INSTALACIÓN DE CORRESPONSAL, SE INSTALAN EQUIPOS CON PRUEBAS EXITOSAS, SE CAPACITA Y SE EVALÚA AL CLIENTE, SE INSTALA PUBLICIDAD COMPLETA, CB QUEDA OPERATIVO. USUARIO SOMOS BANCOLOMBIA ACTIVO. SE INTALO ROUTER E0682016411002194 | W25: ALVARADO MORENO CRISTHIAN | X25: FAWZZ650 | Y25: 771689 | Z25: 869561 | AA25: 1071457 | AB25: N/A | AC25: 40 ROLLOS | AD25: =VLOOKUP(D25,TIPOLOGIAS!A:F,6,0) -> TIPO IV | AE25: =VLOOKUP(D25,TIPOLOGIAS!A:F,5,0) -> TERRESTRE | AF25: VISITA _TECNICA | AG25: 0 | AH25: 0 | AI25: 0 | AJ25: 1 | AK25: 0 | AL25: =IF(AD25="TIPO I",'BASE LIQUIDACION'!$D$3,IF(AD25="TIPO II",'BASE LIQUIDACION'!$D$4,IF(AD25="TIPO III",'BASE LIQUIDACION'!$D$5,'BASE LIQUIDACION'!$D$7))) -> 464809.03 | AM25: =AG25*'BASE LIQUIDACION'!$B$12+AH25*'BASE LIQUIDACION'!$B$11+AI25*'BASE LIQUIDACION'!$B$13+AJ25*'BASE LIQUIDACION'!$B$14+AK25*AL25 -> 306552.28
A26: NEIVA | B26: =VLOOKUP(A26,'CENTRO DE COSTOS'!A:D,4,FALSE) -> KEVIN ALEXIS CORZO BUSTOS | C26: =VLOOKUP(A26,'CENTRO DE COSTOS'!A:C,2,FALSE) -> 0004-0007 | D26: 18001 | E26: TA-25-755897 | F26: FO-25-1085384 | G26: 45821 | H26: 45825 | I26: 45821 | J26: 45825 | K26: 45825 | L26: CAQUETA | M26: FLORENCIA | N26: BARRIO COOPERATIVA FLORENCIA 1 | O26: 79866 | P26: CB CRECIMIENTO - NUEVO | Q26: APERTURA | R26: REDEBAN | S26: UNO A UNO | T26: UNO A UNO | U26: EJECUTADO | V26: 13-06 SE REALIZA LLAMADA AL CLIENTE, SE HABLA CON EL SR OINER RUIZ ALVAREZ SE VALIDA DIRECCIÓN OK, CANAL OK, DISPONIBILIDAD TOTAL, LLAMAR EL DÍA LA INSTALACIÓN PARA CONFIRMAR VISITA, AVISO EXTERIOR ALTURA APROX 2 METROS; TOMACORRIENTE CERCANO: SI; TIENE CABINA DE SEGURIDAD: NO // CONTACTO REALIZADO POR LA APP 16-06 EN COMUNICACIÓN CON EL CLIENTE EL SEÑOR OINER RUIZ, AL NÚMERO 3115485300, INDICA QUE NOS PUEDE RECIBIR A PARTIR DE MAÑANA MARTES 17 DE JUNIO , EN EL TRANSCURSO DEL DIA. 17-06 SE REALIZA INSTALACIÓN DE CORRESPONSAL, SE INSTALAN EQUIPOS CON PRUEBAS EXITOSAS, SE CAPACITA Y SE EVALÚA AL CLIENTE, SE INSTALA PUBLICIDAD COMPLETA, CB QUEDA OPERATIVO. USUARIO SOMOS BANCOLOMBIA ACTIVO | W26: DEVIA REINOSO JUAN CARLOS | X26: FAWZZ651 | Y26: 1050463 | Z26: N/A | AA26: 1076442 | AB26: N/A | AC26: 40 ROLLOS | AD26: =VLOOKUP(D26,TIPOLOGIAS!A:F,6,0) -> TIPO IV | AE26: =VLOOKUP(D26,TIPOLOGIAS!A:F,5,0) -> TERRESTRE | AF26: VISITA _TECNICA | AG26: 0 | AH26: 0 | AI26: 0 | AJ26: 1 | AK26: 0 | AL26: =IF(AD26="TIPO I",'BASE LIQUIDACION'!$D$3,IF(AD26="TIPO II",'BASE LIQUIDACION'!$D$4,IF(AD26="TIPO III",'BASE LIQUIDACION'!$D$5,'BASE LIQUIDACION'!$D$7))) -> 464809.03 | AM26: =AG26*'BASE LIQUIDACION'!$B$12+AH26*'BASE LIQUIDACION'!$B$11+AI26*'BASE LIQUIDACION'!$B$13+AJ26*'BASE LIQUIDACION'!$B$14+AK26*AL26 -> 306552.28
A27: TUNJA | B27: =VLOOKUP(A27,'CENTRO DE COSTOS'!A:D,4,FALSE) -> MIGUEL JULIÁN HERNÁNDEZ GUARÍN | C27: =VLOOKUP(A27,'CENTRO DE COSTOS'!A:C,2,FALSE) -> 0004-0008 | D27: 15759 | E27: TA-25-684764 | F27: FO-25-1033867 | G27: 45807 | H27: 45812 | I27: 45807 | J27: 45813 | K27: 45813 | L27: BOYACA | M27: SOGAMOSO | N27: BARRIO LA PRADERA SOGAMOSO 3 | O27: 79655 | P27: CB CRECIMIENTO - NUEVO | Q27: APERTURA | R27: REDEBAN | S27: UNO A UNO | T27: UNO A UNO | U27: EJECUTADO | V27: 30-05-2025 SE REALIZA LLAMADA AL CLIENTE, SE HABLA CON LA SRA LADIS ESPERANZA SOSA AMAROI SE VALIDA DIRECCIÓN OK, CANAL OK, DISPONIBILIDAD TOTAL, LLAMAR EL DÍA LA INSTALACIÓN PARA CONFIRMAR VISITA, AVISO EXTERIOR ALTURA APROX 3 METROS; TOMACORRIENTE CERCANO: SI; TIENE CABINA DE SEGURIDAD: NO // CONTACTO REALIZADO POR LA APP 3/6/2025 SE VISITA COMERCIO ,LA INSTALACIÓN EL DIA DE HOY ES FALLIDA COMERCIO SIN COMUNICACION RED DE INTERNET ,EL USUARIO INDICA QUE SE COMUNICARA CON EL PROVEDOR DEL INTERNET PARA QUE HABILITE LA RED DE COMUNICACIÓN EN EL COMERCIO A INSTALAR , SE REPROGRAMA VISITA PARA EL DIA JUEVES 05 DE JUNIO DEL 2025 INDICA QUE PARA ESE DIA TENDRIA LISTO EL PUNTO DE INTERNET 5/6/2025 SE REALIZA INSTALACIÓN DE CORRESPONSAL, SE INSTALAN EQUIPOS CON PRUEBAS EXITOSAS, SE CAPACITA Y SE EVALÚA AL CLIENTE, SE INSTALA PUBLICIDAD COMPLETA, CB QUEDA OPERATIVO. USUARIO SOMOS BANCOLOMBIA ACTIVO | W27: ALVARADO MORENO CRISTHIAN | X27: SXUZZ181 | Y27: 793119 | Z27: N/A | AA27: 905615 | AB27: N/A | AC27: 40 ROLLOS | AD27: =VLOOKUP(D27,TIPOLOGIAS!A:F,6,0) -> TIPO II | AE27: =VLOOKUP(D27,TIPOLOGIAS!A:F,5,0) -> TERRESTRE | AF27: VISITA _TECNICA | AG27: 0 | AH27: 0 | AI27: 0 | AJ27: 0 | AK27: 1 | AL27: =IF(AD27="TIPO I",'BASE LIQUIDACION'!$D$3,IF(AD27="TIPO II",'BASE LIQUIDACION'!$D$4,IF(AD27="TIPO III",'BASE LIQUIDACION'!$D$5,'BASE LIQUIDACION'!$D$7))) -> 134410.39 | AM27: =AG27*'BASE LIQUIDACION'!$B$12+AH27*'BASE LIQUIDACION'!$B$11+AI27*'BASE LIQUIDACION'!$B$13+AJ27*'BASE LIQUIDACION'!$B$14+AK27*AL27 -> 134410.39
A28: MEDELLIN | B28: =VLOOKUP(A28,'CENTRO DE COSTOS'!A:D,4,FALSE) -> JUAN SEBASTIÁN RÍOS CASTRILLÓN | C28: =VLOOKUP(A28,'CENTRO DE COSTOS'!A:C,2,FALSE) -> 0004-0005 | D28: 5079 | E28: TA-25-684795 | F28: FO-25-1050326 | G28: 45807 | H28: 45812 | I28: 45807 | J28: 45817 | K28: 45817 | L28: ANTIOQUIA | M28: BARBOSA | N28: BARRIO BARBOSA AUTOPISTA BARBOSA | O28: 79623 | P28: CB CRECIMIENTO - NUEVO | Q28: APERTURA | R28: REDEBAN | S28: UNO A UNO | T28: UNO A UNO | U28: EJECUTADO | V28: 30-05 SE REALIZA LLAMADA AL CLIENTE, SE HABLA CON LA SRA LIZETH MARIANA GALINDO ORTIZ, SE VALIDA DIRECCIÓN OK, CANAL OK, DISPONIBILIDAD TOTAL, LLAMAR EL DÍA LA INSTALACIÓN PARA CONFIRMAR VISITA, AVISO EXTERIOR ALTURA APROX DONDE EL TECNICO LO VEA CONVENIENTE METROS; TOMACORRIENTE CERCANO: SI; TIENE CABINA DE SEGURIDAD: NO 4/6/2025 LLEGAMOS A SITIO ENCONTRANDO OTRO PUNTO CERCANO A 30 METROS CODIGO 49691 PTM BARBOSA DROGUERÍA SE ESCALA CASO POR CERCANÍA DE 2 PUNTOS UNO DE AGREGADOR Y OTRO UNO A UNO. 05-06 ENTIDAD APRUEBA INSTALACIÓN 9/6/2025 SE REALIZA INSTALACIÓN DE CORRESPONSAL, SE INSTALAN EQUIPOS CON PRUEBAS EXITOSAS, SE CAPACITA Y SE EVALÚA AL CLIENTE, SE INSTALA PUBLICIDAD COMPLETA, CB QUEDA OPERATIVO. PLATAFORMA SOMOS BANCOLOMBIA CON CORREO ERRÓNEO, SE CAPACITA CON USUARIO DE PRUEBA | W28: BADEL ACUÑA LUIS ALBERTO | X28: SXUZZ149 | Y28: 1173964 | Z28: N/A | AA28: 529350 | AB28: N/A | AC28: 40 ROLLOS | AD28: =VLOOKUP(D28,TIPOLOGIAS!A:F,6,0) -> TIPO II | AE28: =VLOOKUP(D28,TIPOLOGIAS!A:F,5,0) -> TERRESTRE | AF28: VISITA _TECNICA | AG28: 0 | AH28: 0 | AI28: 0 | AJ28: 0 | AK28: 1 | AL28: =IF(AD28="TIPO I",'BASE LIQUIDACION'!$D$3,IF(AD28="TIPO II",'BASE LIQUIDACION'!$D$4,IF(AD28="TIPO III",'BASE LIQUIDACION'!$D$5,'BASE LIQUIDACION'!$D$7))) -> 134410.39 | AM28: =AG28*'BASE LIQUIDACION'!$B$12+AH28*'BASE LIQUIDACION'!$B$11+AI28*'BASE LIQUIDACION'!$B$13+AJ28*'BASE LIQUIDACION'!$B$14+AK28*AL28 -> 134410.39
A29: BARRANQUILLA | B29: =VLOOKUP(A29,'CENTRO DE COSTOS'!A:D,4,FALSE) -> JOSE MAURICIO HERNANDEZ ROJAS | C29: =VLOOKUP(A29,'CENTRO DE COSTOS'!A:C,2,FALSE) -> 0004-0001 | D29: 8001 | E29: TA-25-684828 | F29: FO-25-1035630 | G29: 45807 | H29: 45812 | I29: 45807 | J29: 45812 | K29: 45812 | L29: ATLANTICO | M29: BARRANQUILLA | N29: BARRIO LA VICTORIA BARRANQUILLA 2 | O29: 79597 | P29: CB CRECIMIENTO - NUEVO | Q29: APERTURA | R29: REDEBAN | S29: UNO A UNO | T29: UNO A UNO | U29: EJECUTADO | V29: 30-05 SE REALIZA LLAMADA AL CLIENTE, SE HABLA CON LA SR LUIS GUILLERMO SERJE RAPELLO VALIDA DIRECCIÓN OK, DISPONIBILIDAD TOTAL, LLAMAR EL DÍA LA INSTALACIÓN PARA CONFIRMAR VISITA, AVISO EXTERIOR ALTURA APROX 2.00 METROS; TOMACORRIENTE CERCANO: SI; TIENE CABINA DE SEGURIDAD: USUARIO TIENE REJA 03-06 SE LOGRA COMUNICACION VÍA WASHAP AL NÚMERO 3008485338, Y ME CONTESTA LA SEÑORA MARIANELA CANTILLO, CON QUIÉN SE ACUERDA LLEGAR TIPO 11 AM PARA ATENDERME, SE LLAMA A SITIO, PERO NO CONTESTAN WASHAP, NO LE ENTRAN MENSAJES NI LLAMADAS , ES UN CONJUNTO CERRADO, PERO ME DICE EL VIGILANTE QUE ESTÁ A LA VUELTA ,SE DA LA VUELTA A LA MANZANA PERO NO SE LOGRA VER EL LOCAL, ME VOY A OTRO SITIO HACER OTRA ACTIVIDAD, Y AHORA EN LAS HORAS DE LA TARDE REGRESO, ESTÁ VEZ SI ME CONTESTAN LOS MENSAJES INDICANDOME QUE DÉBIDO AL PARO EN FUNDACIÓN, NO PUDO REGRESAR, QUE POR FAVOR REAGENDE LA VISITA PARA MAÑANA 4 DE JUNIO 4/6/2025 SE REALIZA INSTALACIÓN DE CORRESPONSAL, SE INSTALAN EQUIPOS CON PRUEBAS EXITOSAS, SE CAPACITA Y SE EVALÚA AL CLIENTE, SE INSTALA PUBLICIDAD COMPLETA, CB QUEDA OPERATIVO. USUARIO SOMOS BANCOLOMBIA ACTIVO | W29: DE AVILA SIADES ALBERTO ENRIQUE | X29: SXUZZ123 | Y29: 1045719 | Z29: N/A | AA29: 905781 | AB29: N/A | AC29: 40 ROLLOS | AD29: =VLOOKUP(D29,TIPOLOGIAS!A:F,6,0) -> TIPO I | AE29: =VLOOKUP(D29,TIPOLOGIAS!A:F,5,0) -> TERRESTRE | AF29: VISITA _TECNICA | AG29: 0 | AH29: 0 | AI29: 0 | AJ29: 0 | AK29: 1 | AL29: =IF(AD29="TIPO I",'BASE LIQUIDACION'!$D$3,IF(AD29="TIPO II",'BASE LIQUIDACION'!$D$4,IF(AD29="TIPO III",'BASE LIQUIDACION'!$D$5,'BASE LIQUIDACION'!$D$7))) -> 44559.985 | AM29: =AG29*'BASE LIQUIDACION'!$B$12+AH29*'BASE LIQUIDACION'!$B$11+AI29*'BASE LIQUIDACION'!$B$13+AJ29*'BASE LIQUIDACION'!$B$14+AK29*AL29 -> 44559.985
A30: BOGOTA | B30: =VLOOKUP(A30,'CENTRO DE COSTOS'!A:D,4,FALSE) -> WILLIAM ASDRUBAL ROZO ROZO | C30: =VLOOKUP(A30,'CENTRO DE COSTOS'!A:C,2,FALSE) -> 0004-0004 | D30: 11001 | E30: TA-25-716040 | F30: FO-25-1047078 | G30: 45813 | H30: 45817 | I30: 45813 | J30: 45814 | K30: 45814 | L30: CUNDINAMARCA | M30: BOGOTA | N30: PTM BOGOTA MC RAM | O30: 79688 | P30: CB CRECIMIENTO ALIANZA - NUEVO | Q30: APERTURA | R30: REDEBAN | S30: AGREGADOR | T30: COMCARD - PTM | U30: EJECUTADO/CANCELADO | V30: 05-06 PROGRAMACIÓN REALIZADA POR LA ALIANZA 6/6/2025 NO ES POSIBLE REALIZAR APERTURA YA QUE EL CLIENTE MANEJA MÁS CORRESPONSALES EN EL PUNTO | W30: SOTO LONDOÑO FREDY ALEXANDER | X30: V1YZZ430 | Y30: N/A | Z30: N/A | AA30: N/A | AB30: N/A | AC30: 0 | AD30: =VLOOKUP(D30,TIPOLOGIAS!A:F,6,0) -> TIPO I | AE30: =VLOOKUP(D30,TIPOLOGIAS!A:F,5,0) -> TERRESTRE | AF30: VISITA _TECNICA | AG30: 0 | AH30: 0 | AI30: 0 | AJ30: 0 | AK30: 1 | AL30: =IF(AD30="TIPO I",'BASE LIQUIDACION'!$D$3,IF(AD30="TIPO II",'BASE LIQUIDACION'!$D$4,IF(AD30="TIPO III",'BASE LIQUIDACION'!$D$5,'BASE LIQUIDACION'!$D$7))) -> 44559.985 | AM30: =AG30*'BASE LIQUIDACION'!$B$12+AH30*'BASE LIQUIDACION'!$B$11+AI30*'BASE LIQUIDACION'!$B$13+AJ30*'BASE LIQUIDACION'!$B$14+AK30*AL30 -> 44559.985
A31: PASTO | B31: =VLOOKUP(A31,'CENTRO DE COSTOS'!A:D,4,FALSE) -> DIEGO FERNANDO HENAO CARDONA | C31: =VLOOKUP(A31,'CENTRO DE COSTOS'!A:C,2,FALSE) -> 0004-0003 | D31: 52001 | E31: TA-25-716049 | F31: FO-25-1047093 | G31: 45813 | H31: 45817 | I31: 45813 | J31: 45817 | K31: 45817 | L31: NARIÑO | M31: PASTO | N31: PTM PASTO MAS BELLA PELUQUERIA | O31: 78990 | P31: CB CRECIMIENTO ALIANZA - OTRAS LISTAS | Q31: APERTURA | R31: REDEBAN | S31: AGREGADOR | T31: COMCARD - PTM | U31: EJECUTADO/CANCELADO | V31: 05-06 PROGRAMACIÓN REALIZADA POR LA ALIANZA 6/6/2025 SE REALIZA VISITA DE APERTURA AL CB PTM CON CÓDIGO 3007078990 PTM PASTO MAS BELLA PELUQUERIA , DIRECCIÓN CR 32 NO 16 A 07 , COORDENADAS 1.219494, -77.283634, PERO SE ENCUENTRA CERCANÍA CON CORRESPONSAL UNO A UNO INSTALADO CON CÓDIGO 3007014514 BARRIO LAS AMERICAS V , DIRECCIÓN CR 32 NO 16 A 18, COORDENADAS 1.219484, -77.283534, QUEDANDO A MENOS DE 10 MTS DE DISTANCIA UNO DEL OTRO, SE REALIZA ESCALAMIENTO POR CERCANÍA EN ESPERA DE COMO PROCEDER. 9/6/2025 ENTIDAD SOLICITA CANCELAR ACTIVIDAD | W31: REMICIO AMADO JOHN HEBER | X31: FATZZ360 | Y31: N/A | Z31: N/A | AA31: N/A | AB31: N/A | AC31: 0 | AD31: =VLOOKUP(D31,TIPOLOGIAS!A:F,6,0) -> TIPO I | AE31: =VLOOKUP(D31,TIPOLOGIAS!A:F,5,0) -> TERRESTRE | AF31: VISITA _TECNICA | AG31: 0 | AH31: 0 | AI31: 0 | AJ31: 0 | AK31: 1 | AL31: =IF(AD31="TIPO I",'BASE LIQUIDACION'!$D$3,IF(AD31="TIPO II",'BASE LIQUIDACION'!$D$4,IF(AD31="TIPO III",'BASE LIQUIDACION'!$D$5,'BASE LIQUIDACION'!$D$7))) -> 44559.985 | AM31: =AG31*'BASE LIQUIDACION'!$B$12+AH31*'BASE LIQUIDACION'!$B$11+AI31*'BASE LIQUIDACION'!$B$13+AJ31*'BASE LIQUIDACION'!$B$14+AK31*AL31 -> 44559.985
A32: PASTO | B32: =VLOOKUP(A32,'CENTRO DE COSTOS'!A:D,4,FALSE) -> DIEGO FERNANDO HENAO CARDONA | C32: =VLOOKUP(A32,'CENTRO DE COSTOS'!A:C,2,FALSE) -> 0004-0003 | D32: 52399 | E32: TA-25-722197 | F32: FO-25-1078152 | G32: 45817 | H32: 45819 | I32: 45817 | J32: 45824 | K32: 45824 | L32: NARIÑO | M32: LA UNION | N32: PTM LA UNION MAS BELLA FAJAS Y | O32: 79724 | P32: CB CRECIMIENTO ALIANZA - NUEVO | Q32: APERTURA | R32: REDEBAN | S32: AGREGADOR | T32: COMCARD - PTM | U32: EJECUTADO | V32: 09-06 PROGRAMACIÓN REALIZADA POR LA ALIANZA 11/6/2025 SE REALIZA VISITA DE APERTURA AL CB PTM CON CÓDIGO 3007079724 PTM LA UNION MAS BELLA FAJAS , DIRECCIÓN CL 13 CS 7 -54 , COORDENADAS 1.600294, -77.132148, PERO SE ENCUENTRA CERCANÍA CON CORRESPONSAL DISTRICOL INSTALADO CON CÓDIGO 3007041205 DISTRICOL CYBERTRONICA , DIRECCIÓN CL 13 3 12, COORDENADAS 1.600144, -77.132003, QUEDANDO A MENOS DE 30 MTS DE DISTANCIA UNO DEL OTRO, SE REALIZA ESCALAMIENTO POR CERCANÍA EN ESPERA DE COMO PROCEDER. SE ANOTA QUE EL TECNICO AL LLEGAR INSPECCIONO LA ZONA DESDE LA ENTRADA PRINCIPAL DEL CB A INSTALAR Y NO ENCONTRO CERCANIA, PROCEDIO A INICIALIZAR EL EQUIPO, PERO AL PERCATARSE QUE ESTE TENIA OTRO INGRESO SE VALIDA HACIA ESA PARTE Y SE ENCUENTRA LA CERCANIA. 12/06/2025 ENTIDAD APRUEBA INSTALACIÓN 16/6/2025 SE REALIZA INSTALACIÓN DE CORRESPONSAL, SE INSTALAN EQUIPOS CON PRUEBAS EXITOSAS, SE CAPACITA Y SE EVALÚA AL CLIENTE, SE INSTALA PUBLICIDAD COMPLETA, CB QUEDA OPERATIVO. USUARIO SOMOS BANCOLOMBIA ACTIVO | W32: PAZ MARTINEZ RICHARD HUMBERTO | X32: F1WZZ970 | Y32: 1072759 | Z32: N/A | AA32: 940722 | AB32: N/A | AC32: 40 ROLLOS | AD32: =VLOOKUP(D32,TIPOLOGIAS!A:F,6,0) -> TIPO III | AE32: =VLOOKUP(D32,TIPOLOGIAS!A:F,5,0) -> TERRESTRE | AF32: VISITA _TECNICA | AG32: 0 | AH32: 0 | AI32: 0 | AJ32: 0 | AK32: 1 | AL32: =IF(AD32="TIPO I",'BASE LIQUIDACION'!$D$3,IF(AD32="TIPO II",'BASE LIQUIDACION'!$D$4,IF(AD32="TIPO III",'BASE LIQUIDACION'!$D$5,'BASE LIQUIDACION'!$D$7))) -> 222904.27 | AM32: =AG32*'BASE LIQUIDACION'!$B$12+AH32*'BASE LIQUIDACION'!$B$11+AI32*'BASE LIQUIDACION'!$B$13+AJ32*'BASE LIQUIDACION'!$B$14+AK32*AL32 -> 222904.27
A33: CALI | B33: =VLOOKUP(A33,'CENTRO DE COSTOS'!A:D,4,FALSE) -> DIEGO FERNANDO HENAO CARDONA | C33: =VLOOKUP(A33,'CENTRO DE COSTOS'!A:C,2,FALSE) -> 0004-0003 | D33: 76001 | E33: TA-25-722209 | F33: FO-25-1063504 | G33: 45817 | H33: 45819 | I33: 45817 | J33: 45818 | K33: 45818 | L33: VALLE DEL CAUCA | M33: CALI | N33: PTM CALI PAPELERIA Y COMUNICAC | O33: 79694 | P33: CB CRECIMIENTO ALIANZA - OTRAS LISTAS | Q33: APERTURA | R33: REDEBAN | S33: AGREGADOR | T33: COMCARD - PTM | U33: EJECUTADO/CANCELADO | V33: 09-06 PROGRAMACIÓN REALIZADA POR LA ALIANZA 10/6/2025 SE REALIZA VISITA AL PUNTO CB 3007079694 PTM CALI PAPELERIA Y COMUNICACIONES, PARA REALIZAR IMPLEMENTACIÓN ,PERO AL LLEGAR AL SITIO SE ENCUENTRA QUE ALLÍ EN LA DIRECCION REGISTRADA PARA LA APERTURA BANCOLOMBIA OPERA UN PUNTO CORRESPONSAL BANCO DE BOGOTA ACTIVO POR LO CUAL SE PROCEDE A REALIZAR CANCELACIÓN DE DICHA IMPLEMENTACIÓN Y SE GENERA EL REPORTE PERTINENTE, AL LLEGAR EL LOCAL SE ENCUENTRA CERRADO, SE INTENTA COMUNICACION CON EL CLIENTE PERO NO ATIENDE LAS LLAMADAS, SE LE DEJA MENSAJE DE LA NOVEDAD ENCONTRADA. | W33: SANCHEZ URREGO ROBINSON DAVID | X33: V1YZZ436 | Y33: N/A | Z33: N/A | AA33: N/A | AB33: N/A | AC33: 0 | AD33: =VLOOKUP(D33,TIPOLOGIAS!A:F,6,0) -> TIPO I | AE33: =VLOOKUP(D33,TIPOLOGIAS!A:F,5,0) -> TERRESTRE | AF33: VISITA _TECNICA | AG33: 0 | AH33: 0 | AI33: 0 | AJ33: 0 | AK33: 1 | AL33: =IF(AD33="TIPO I",'BASE LIQUIDACION'!$D$3,IF(AD33="TIPO II",'BASE LIQUIDACION'!$D$4,IF(AD33="TIPO III",'BASE LIQUIDACION'!$D$5,'BASE LIQUIDACION'!$D$7))) -> 44559.985 | AM33: =AG33*'BASE LIQUIDACION'!$B$12+AH33*'BASE LIQUIDACION'!$B$11+AI33*'BASE LIQUIDACION'!$B$13+AJ33*'BASE LIQUIDACION'!$B$14+AK33*AL33 -> 44559.985
A34: IBAGUE | B34: =VLOOKUP(A34,'CENTRO DE COSTOS'!A:D,4,FALSE) -> KEVIN ALEXIS CORZO BUSTOS | C34: =VLOOKUP(A34,'CENTRO DE COSTOS'!A:C,2,FALSE) -> 0004-0007 | D34: 73585 | E34: TA-25-721955 | F34: FO-25-1072237 | G34: 45817 | H34: 45819 | I34: 45817 | J34: 45819 | K34: 45819 | L34: TOLIMA | M34: PURIFICACION | N34: BARRIO PLAZA DE FERIAS PURIFICACION | O34: 79785 | P34: CB CRECIMIENTO - NUEVO | Q34: APERTURA | R34: REDEBAN | S34: UNO A UNO | T34: UNO A UNO | U34: EJECUTADO | V34: 06-06 SE REALIZA LLAMADA AL CLIENTE, SE HABLA CON LA SR ARIEL MARTINEZ PERALTA SE VALIDA DIRECCIÓN OK, CANAL OK, DISPONIBILIDAD TOTAL, LLAMAR EL DÍA LA INSTALACIÓN PARA CONFIRMAR VISITA, AVISO EXTERIOR ALTURA APROX 3.20 METROS; TOMACORRIENTE CERCANO: SI; TIENE CABINA DE SEGURIDAD: NO 10-6 SE VISITA COMERCIO PERO NO SE LOGRA TERMINAR LA ACTIVIDAD PORQUE EL USUARIO YA VA A CERRAR, SE DEBE CONTINUAR EL DIA SIGUIENTE 11-06 SE REALIZA INSTALACIÓN DE CORRESPONSAL, SE INSTALAN EQUIPOS CON PRUEBAS EXITOSAS, SE CAPACITA Y SE EVALÚA AL CLIENTE, SE INSTALA PUBLICIDAD COMPLETA, CB QUEDA OPERATIVO. USUARIO SOMOS BANCOLOMBIA ACTIVO | W34: GUTIERREZ CAMILO ANDRES | X34: F1XZZ060 | Y34: 810162 | Z34: N/A | AA34: 905326 | AB34: N/A | AC34: 40 ROLLOS | AD34: =VLOOKUP(D34,TIPOLOGIAS!A:F,6,0) -> TIPO II | AE34: =VLOOKUP(D34,TIPOLOGIAS!A:F,5,0) -> TERRESTRE | AF34: VISITA _TECNICA | AG34: 0 | AH34: 0 | AI34: 0 | AJ34: 0 | AK34: 1 | AL34: =IF(AD34="TIPO I",'BASE LIQUIDACION'!$D$3,IF(AD34="TIPO II",'BASE LIQUIDACION'!$D$4,IF(AD34="TIPO III",'BASE LIQUIDACION'!$D$5,'BASE LIQUIDACION'!$D$7))) -> 134410.39 | AM34: =AG34*'BASE LIQUIDACION'!$B$12+AH34*'BASE LIQUIDACION'!$B$11+AI34*'BASE LIQUIDACION'!$B$13+AJ34*'BASE LIQUIDACION'!$B$14+AK34*AL34 -> 134410.39
A35: CUCUTA | B35: =VLOOKUP(A35,'CENTRO DE COSTOS'!A:D,4,FALSE) -> MIGUEL JULIÁN HERNÁNDEZ GUARÍN | C35: =VLOOKUP(A35,'CENTRO DE COSTOS'!A:C,2,FALSE) -> 0004-0008 | D35: 54498 | E35: TA-25-721958 | F35: FO-25-1063081 | G35: 45817 | H35: 45819 | I35: 45817 | J35: 45818 | K35: 45818 | L35: NORTE DE SANTANDER | M35: OCAÑA | N35: BARRIO EL CENTRO OCAÑA 8 | O35: 79814 | P35: CB CRECIMIENTO - NUEVO | Q35: APERTURA | R35: REDEBAN | S35: UNO A UNO | T35: UNO A UNO | U35: EJECUTADO/CANCELADO | V35: 09-06 SE REALIZA LLAMADA AL CLIENTE, SE HABLA CON LA SRA LAURA SMIRTH LOPEZ RAMIREZ SE VALIDA DIRECCIÓN OK, CANAL OK, DISPONIBILIDAD TOTAL, LLAMAR EL DÍA LA INSTALACIÓN PARA CONFIRMAR VISITA, AVISO EXTERIOR ALTURA APROX 3 METROS; TOMACORRIENTE CERCANO: SI; TIENE CABINA DE SEGURIDAD: SI 10/6/2025 SE LLEGA AL SITIO DE LA ORDEN, DONDE SE IDENTIFICA QUE A POCOS METROS SE ENCUENTRA YA UN CORRESPONSAL DE ALIANZA DISTRICOL EN LA CALLE 10 #11-25 CENTRO OCAÑA CB:47707 DISTRICOL PIÑATERIA SE ESCALA APERTURA PARA CONFIRMAR SI PODEMOS PROCEDER CON LA ORDEN O SI CANCELARNOS.10/6/2025 ENTIDAD SOLIICTA NO IMPLEMENTAR | W35: GELVEZ MOGOLLON JOSE ELISEO | X35: F1XZZ062 | Y35: N/A | Z35: N/A | AA35: N/A | AB35: N/A | AC35: 0 | AD35: =VLOOKUP(D35,TIPOLOGIAS!A:F,6,0) -> TIPO IV | AE35: =VLOOKUP(D35,TIPOLOGIAS!A:F,5,0) -> TERRESTRE | AF35: VISITA _TECNICA | AG35: 0 | AH35: 0 | AI35: 0 | AJ35: 0 | AK35: 1 | AL35: =IF(AD35="TIPO I",'BASE LIQUIDACION'!$D$3,IF(AD35="TIPO II",'BASE LIQUIDACION'!$D$4,IF(AD35="TIPO III",'BASE LIQUIDACION'!$D$5,'BASE LIQUIDACION'!$D$7))) -> 464809.03 | AM35: =AG35*'BASE LIQUIDACION'!$B$12+AH35*'BASE LIQUIDACION'!$B$11+AI35*'BASE LIQUIDACION'!$B$13+AJ35*'BASE LIQUIDACION'!$B$14+AK35*AL35 -> 464809.03
A36: BUCARAMANGA | B36: =VLOOKUP(A36,'CENTRO DE COSTOS'!A:D,4,FALSE) -> MIGUEL JULIÁN HERNÁNDEZ GUARÍN | C36: =VLOOKUP(A36,'CENTRO DE COSTOS'!A:C,2,FALSE) -> 0004-0008 | D36: 68679 | E36: TA-25-741690 | F36: FO-25-1084320 | G36: 45818 | H36: 45820 | I36: 45818 | J36: 45821 | K36: 45821 | L36: SANTANDER | M36: SAN GIL | N36: PTM SAN GIL TIENDA DE ROPA SOY | O36: 79835 | P36: CB CRECIMIENTO ALIANZA - NUEVO | Q36: APERTURA | R36: REDEBAN | S36: AGREGADOR | T36: COMCARD - PTM | U36: EJECUTADO/CANCELADO | V36: 11-06 PROGRAMACIÓN REALIZADA POR LA ALIANZA 12/6/2025 SE LLEGA AL SITIO DE LA ORDEN, DONDE SE IDENTIFICA QUE A POCOS METROS SE ENCUENTRA YA UN CORRESPONSAL EN LA CALLE 10 #10-54 SANGIL CB:74611 BARRIO CENTRO SANGIL SE ESCALA APERTURA PARA CONFIRMAR SI PODEMOS PROCEDER CON LA ORDEN O SI CANCELARNOS. 13/6/2025 ENTIDAD SOLICITA CANCELAR ACTIVIDAD | W36: HERRERA LUQUE SAUL JAVIER | X36: FAVZZ675 | Y36: N/A | Z36: N/A | AA36: N/A | AB36: N/A | AC36: 0 | AD36: =VLOOKUP(D36,TIPOLOGIAS!A:F,6,0) -> TIPO II | AE36: =VLOOKUP(D36,TIPOLOGIAS!A:F,5,0) -> TERRESTRE | AF36: VISITA _TECNICA | AG36: 0 | AH36: 0 | AI36: 0 | AJ36: 0 | AK36: 1 | AL36: =IF(AD36="TIPO I",'BASE LIQUIDACION'!$D$3,IF(AD36="TIPO II",'BASE LIQUIDACION'!$D$4,IF(AD36="TIPO III",'BASE LIQUIDACION'!$D$5,'BASE LIQUIDACION'!$D$7))) -> 134410.39 | AM36: =AG36*'BASE LIQUIDACION'!$B$12+AH36*'BASE LIQUIDACION'!$B$11+AI36*'BASE LIQUIDACION'!$B$13+AJ36*'BASE LIQUIDACION'!$B$14+AK36*AL36 -> 134410.39
A37: CALI | B37: =VLOOKUP(A37,'CENTRO DE COSTOS'!A:D,4,FALSE) -> DIEGO FERNANDO HENAO CARDONA | C37: =VLOOKUP(A37,'CENTRO DE COSTOS'!A:C,2,FALSE) -> 0004-0003 | D37: 76248 | E37: TA-25-736407 | F37: FO-25-1073950 | G37: 45819 | H37: 45821 | I37: 45819 | J37: 45820 | K37: 45820 | L37: VALLE DEL CAUCA | M37: EL CERRITO | N37: BARRIO CENTRO EL CERRITO 14 | O37: 79846 | P37: CB CRECIMIENTO - NUEVO | Q37: APERTURA | R37: REDEBAN | S37: UNO A UNO | T37: UNO A UNO | U37: EJECUTADO/CANCELADO | V37: 11-06 SE REALIZA LLAMADA AL CLIENTE, SE HABLA CON EL SR JAVIER MAURICIO PLAZA VARGAS, SE VALIDA DIRECCIÓN OK, CANAL OK, DISPONIBILIDAD TOTAL, LLAMAR EL DÍA LA INSTALACIÓN PARA CONFIRMAR VISITA, AVISO EXTERIOR ALTURA APROX DONDE EL TECNICO LO VEA CONVENIENTE; TOMACORRIENTE CERCANO: SI; TIENE CABINA DE SEGURIDAD: NO 12/6/2025 SE CANCELA LA INSTALACIÓN SEL SERVICIO POR MOTIVO QUE EL COMERCIO TIENE INCONVENIENTE CON LA CONEXIÓN DE LA RED LAN. SE INTENTO COMUNICACION DE DIFERENTES FORMA Y VARIAS IP FIJAS Y NO FUE POSIBLE. MÓDEM SE ENCUENTRA CONFIGURADO PADA CONEXIÓN BAJO IP FIJA. SE LE INDICA A EL COMERCIO QUE SE DEBE DE COMUNICAR CON EL OPERADOR DE RED PARA LA SOLUCIÓN DEL INCONVENIENTE. | W37: TORRES GARCIA JENDRY JOSE | X37: FAUZZ211 | Y37: N/A | Z37: N/A | AA37: N/A | AB37: N/A | AC37: 0 | AD37: =VLOOKUP(D37,TIPOLOGIAS!A:F,6,0) -> TIPO II | AE37: =VLOOKUP(D37,TIPOLOGIAS!A:F,5,0) -> TERRESTRE | AF37: VISITA _TECNICA | AG37: 0 | AH37: 0 | AI37: 0 | AJ37: 0 | AK37: 1 | AL37: =IF(AD37="TIPO I",'BASE LIQUIDACION'!$D$3,IF(AD37="TIPO II",'BASE LIQUIDACION'!$D$4,IF(AD37="TIPO III",'BASE LIQUIDACION'!$D$5,'BASE LIQUIDACION'!$D$7))) -> 134410.39 | AM37: =AG37*'BASE LIQUIDACION'!$B$12+AH37*'BASE LIQUIDACION'!$B$11+AI37*'BASE LIQUIDACION'!$B$13+AJ37*'BASE LIQUIDACION'!$B$14+AK37*AL37 -> 134410.39
A38: NEIVA | B38: =VLOOKUP(A38,'CENTRO DE COSTOS'!A:D,4,FALSE) -> KEVIN ALEXIS CORZO BUSTOS | C38: =VLOOKUP(A38,'CENTRO DE COSTOS'!A:C,2,FALSE) -> 0004-0007 | D38: 18001 | E38: TA-25-755889 | F38: FO-25-1085356 | G38: 45821 | H38: 45825 | I38: 45821 | J38: 45825 | K38: 45825 | L38: CAQUETA | M38: FLORENCIA | N38: BARRIO CENTRO FLORENCIA 38 | O38: 79863 | P38: CB CRECIMIENTO - NUEVO | Q38: APERTURA | R38: REDEBAN | S38: UNO A UNO | T38: UNO A UNO | U38: EJECUTADO/CANCELADO | V38: 13-06 SE REALIZA LLAMADA AL CLIENTE, SE HABLA CON EL SR JUAN CAMILO SANCHEZ SILVA SE VALIDA DIRECCIÓN OK, CANAL OK, DISPONIBILIDAD TOTAL, LLAMAR EL DÍA LA INSTALACIÓN PARA CONFIRMAR VISITA, AVISO EXTERIOR ALTURA APROX 2,50 METROS; TOMACORRIENTE CERCANO: SI; TIENE CABINA DE SEGURIDAD: SI // CONTACTO REALIZADO POR LA APP 16-06 SE REALIZÓ VISITA PARA IMPLEMENTACIÓN DEL CB 79863, PERO SE EVIDENCIA QUE EL COMERCIO ESTA UBICADO EN LA CARRERA 16 # 15 – 37 EN UN LOCAL DE ESA DIRECCIÓN, SIN EMBARGO EL USUARIO INDICA QUE AHÍ LA DIRECCIÓN ES CARRERA 16 # 15 – 36, NOS ENTREGA CÁMARA DE COMERCIO Y RECIBO DE SERVICIOS PÚBLICOS Y ESTOS COINCIDEN, SE VALIDA LA ACERA DONDE EL USUARIO INDICA Y ESTA ES LA ACERA DONDE VAN LAS DIRECCIONES DE NÚMEROS IMPARES, TAMBIÉN SE VALIDAN EN LOS LOCALES QUE ESTÁN EN LA DIRECCIÓN Y SE EVIDENCIA QUE HAY UNO DICE QUE CARRERA 16 # 15 – 37 LOCAL 4, ADEMÁS DONDE EL USUARIO DICE INSTALAR TIENE OTRO NOMBRE DE COMERCIO DIFERENTE AL QUE SE RELACIONA EN LISTA DE CHEQUEO. POR FAVOR NOS INDICAN COMO PROCEDER. 17/6/2025 SE CANCELA ACTIVIDAD POR DIRECCIÓN ERRADA | W38: DEVIA REINOSO JUAN CARLOS | X38: FAWZZ645 | Y38: N/A | Z38: N/A | AA38: N/A | AB38: N/A | AC38: 0 | AD38: =VLOOKUP(D38,TIPOLOGIAS!A:F,6,0) -> TIPO IV | AE38: =VLOOKUP(D38,TIPOLOGIAS!A:F,5,0) -> TERRESTRE | AF38: VISITA _TECNICA | AG38: 0 | AH38: 0 | AI38: 0 | AJ38: 0 | AK38: 1 | AL38: =IF(AD38="TIPO I",'BASE LIQUIDACION'!$D$3,IF(AD38="TIPO II",'BASE LIQUIDACION'!$D$4,IF(AD38="TIPO III",'BASE LIQUIDACION'!$D$5,'BASE LIQUIDACION'!$D$7))) -> 464809.03 | AM38: =AG38*'BASE LIQUIDACION'!$B$12+AH38*'BASE LIQUIDACION'!$B$11+AI38*'BASE LIQUIDACION'!$B$13+AJ38*'BASE LIQUIDACION'!$B$14+AK38*AL38 -> 464809.03
A39: SINCELEJO | B39: =VLOOKUP(A39,'CENTRO DE COSTOS'!A:D,4,FALSE) -> JOSE MAURICIO HERNANDEZ ROJAS | C39: =VLOOKUP(A39,'CENTRO DE COSTOS'!A:C,2,FALSE) -> 0004-0001 | D39: 70001 | E39: TA-25-791004 | F39: FO-25-1114527 | G39: 45826 | H39: 45828 | I39: 45826 | J39: 45833 | K39: 45833 | L39: SUCRE | M39: SINCELEJO | N39: DISTRICOL DROGAS C&P | O39: 79913 | P39: CB CRECIMIENTO ALIANZA - NUEVO | Q39: APERTURA | R39: REDEBAN | S39: AGREGADOR | T39: DISTRICOL | U39: EJECUTADO | V39: 18-06 PROGRAMACIÓN REALIZADA POR LA ALIANZA 19/6/2025 NOTA: SE REALIZA VISITA PARA IMPLEMENTACIÓN CB 79913 BANCOLOMBIA, PERO SEGÚN LAS COORDENADAS TOMADAS POR GOOGLE MAPS NOS DA UNA DIRECCIÓN DIFERENTE, EL COMERCIO INDICA QUE SIEMPRE HA ESTADO EN ESA DIRECCIÓN CR 17E # 42D 42 BRR NORMANDIA Y LA CÁMARA DE COMERCIO Y EL RECIBO DE SERVICIOS PÚBLICOS COINCIDEN CON LA DE LA LISTA DE CHEQUEO, SE VALIDA EN UNA CASA VECINA Y TIENE LA DIRECCIÓN CR 17E # 42D-62, ES DECIR QUE AL PARECER POR GOOGLE MAPS LA DIRECCIÓN ES ERRADA Y ES COMO LA QUE INDICA EN LISTA DE CHEQUEO Y EL USUARIO. 19-06 SE VISITA COMERCIO PARA LA INSTALACIÓN DEL CB, PERO NO ES POSIBLE REALIZAR LA INSTALACIÓN PORQUE NO CUENTA CON CANAL DE INTERNET EN SITIO, SE REPROGRAMA LA VISITA. 25/6/2025 SE REALIZA INSTALACIÓN DE CORRESPONSAL, SE INSTALAN EQUIPOS CON PRUEBAS EXITOSAS, SE CAPACITA Y SE EVALÚA AL CLIENTE, SE INSTALA PUBLICIDAD COMPLETA, CB QUEDA OPERATIVO. USUARIO SOMOS BANCOLOMBIA ACTIVO. LAS COORDENADAS TOMADAS EN EL COMERCIO NO COINCIDE CON LA DIRECCIÓN. | W39: SANTOS GUZMAN CHRISTIAN FELIPE | X39: SAUZZ970 | Y39: 1021451 | Z39: N/A | AA39: 932263 | AB39: N/A | AC39: 40 ROLLOS | AD39: =VLOOKUP(D39,TIPOLOGIAS!A:F,6,0) -> TIPO I | AE39: =VLOOKUP(D39,TIPOLOGIAS!A:F,5,0) -> TERRESTRE | AF39: VISITA _TECNICA | AG39: 0 | AH39: 0 | AI39: 0 | AJ39: 0 | AK39: 1 | AL39: =IF(AD39="TIPO I",'BASE LIQUIDACION'!$D$3,IF(AD39="TIPO II",'BASE LIQUIDACION'!$D$4,IF(AD39="TIPO III",'BASE LIQUIDACION'!$D$5,'BASE LIQUIDACION'!$D$7))) -> 44559.985 | AM39: =AG39*'BASE LIQUIDACION'!$B$12+AH39*'BASE LIQUIDACION'!$B$11+AI39*'BASE LIQUIDACION'!$B$13+AJ39*'BASE LIQUIDACION'!$B$14+AK39*AL39 -> 44559.985
A40: MEDELLIN | B40: =VLOOKUP(A40,'CENTRO DE COSTOS'!A:D,4,FALSE) -> JUAN SEBASTIÁN RÍOS CASTRILLÓN | C40: =VLOOKUP(A40,'CENTRO DE COSTOS'!A:C,2,FALSE) -> 0004-0005 | D40: 5001 | E40: TA-25-790517 | F40: FO-25-1106932 | G40: 45826 | H40: 45828 | I40: 45826 | J40: 45827 | K40: 45827 | L40: ANTIOQUIA | M40: MEDELLIN | N40: BARRIO BELEN LOS ALPES MEDELLIN 2 | O40: 79964 | P40: CB CRECIMIENTO - NUEVO | Q40: APERTURA | R40: REDEBAN | S40: UNO A UNO | T40: UNO A UNO | U40: EJECUTADO/CANCELADO | V40: 17-06 SE REALIZA LLAMADA AL CLIENTE, SE HABLA CON LA SRA ZULAY RAMIREZ OSORNO SE VALIDA DIRECCIÓN OK, CANAL OK, DISPONIBILIDAD TOTAL, LLAMAR EL DÍA LA INSTALACIÓN PARA CONFIRMAR VISITA, AVISO EXTERIOR ALTURA APROX CLIENTE NO TIENE CONOCIMIENTO DE MEDIDAS; TOMACORRIENTE CERCANO: SI; TIENE CABINA DE SEGURIDAD: NO // CONTACTO REALIZADO POR LA APP 19/6/2025 SE LLEGA A PUNTO Y CLIENTE INDICA QUE NO TIENE INTERNET EN EL LOCAL DONDE VA A QUEDAR EL CORRESPONSAL, PIDE QUE SE APLACE VISITA HASTA GESTIONAR EL INTERNET | W40: BADEL ACUÑA LUIS ALBERTO | X40: SAVZZ107 | Y40: N/A | Z40: N/A | AA40: N/A | AB40: N/A | AC40: 0 | AD40: =VLOOKUP(D40,TIPOLOGIAS!A:F,6,0) -> TIPO I | AE40: =VLOOKUP(D40,TIPOLOGIAS!A:F,5,0) -> TERRESTRE | AF40: VISITA _TECNICA | AG40: 0 | AH40: 0 | AI40: 0 | AJ40: 0 | AK40: 1 | AL40: =IF(AD40="TIPO I",'BASE LIQUIDACION'!$D$3,IF(AD40="TIPO II",'BASE LIQUIDACION'!$D$4,IF(AD40="TIPO III",'BASE LIQUIDACION'!$D$5,'BASE LIQUIDACION'!$D$7))) -> 44559.985 | AM40: =AG40*'BASE LIQUIDACION'!$B$12+AH40*'BASE LIQUIDACION'!$B$11+AI40*'BASE LIQUIDACION'!$B$13+AJ40*'BASE LIQUIDACION'!$B$14+AK40*AL40 -> 44559.985
A41: BOGOTA | B41: =VLOOKUP(A41,'CENTRO DE COSTOS'!A:D,4,FALSE) -> WILLIAM ASDRUBAL ROZO ROZO | C41: =VLOOKUP(A41,'CENTRO DE COSTOS'!A:C,2,FALSE) -> 0004-0004 | D41: 25299 | E41: TA-25-799131 | F41: FO-25-1128673 | G41: 45832 | H41: 45834 | I41: 45832 | J41: 45834 | K41: 45834 | L41: CUNDINAMARCA | M41: GAMA | N41: BARRIO CENTRO GAMA 2 | O41: 80029 | P41: CB CRECIMIENTO - NUEVO | Q41: APERTURA | R41: REDEBAN | S41: UNO A UNO | T41: UNO A UNO | U41: EJECUTADO/CANCELADO | V41: 24-06-2025 SE REALIZA LLAMADA AL CLIENTE, SE HABLA CON EL SR ELKIN ALFONSO RAMIREZ RODRIGUEZ SE VALIDA DIRECCIÓN OK, CANAL OK, DISPONIBILIDAD TOTAL, LLAMAR EL DÍA LA INSTALACIÓN PARA CONFIRMAR VISITA, AVISO EXTERIOR ALTURA APROX 3 METROS MAX; TOMACORRIENTE CERCANO: SI; TIENE CABINA DE SEGURIDAD: SI // CONTACTO REALIZADO POR LA APP 26/6/2025 EN VISITA AL COMERCIO 3007080029 PARA REALIZAR APERTURA, SE ENCUENTRA QUE ESTA EN OTRA DIRECCIÓN CR 3 5-26, ANTES DE VIAJAR SE CONFIRMO DATOS DE LA DIRECCIÓN QUIEN CONFIRMÓ CL 3 5-42. ESTANDO EN SITIO EL COMERCIO SE ENCUENTRA UBICADO EN OTRO LADO, POR LO SIGUIENTE SE CANCELA INSTALACIÓN.DIRECCIÓN LISTA DE CHEQUEO: CL 3 5 42, CENTRO DIRECCIÓN COMERCIO: CR 3 5-26 CÁMARA DE COMERCIO: CR 3 4-46 | W41: MURCIA HERNANDEZ HARVEY IGNACIO | X41: SAXZZ470 | Y41: N/A | Z41: N/A | AA41: N/A | AB41: N/A | AC41: 0 | AD41: =VLOOKUP(D41,TIPOLOGIAS!A:F,6,0) -> TIPO III | AE41: =VLOOKUP(D41,TIPOLOGIAS!A:F,5,0) -> TERRESTRE | AF41: VISITA _TECNICA | AG41: 0 | AH41: 0 | AI41: 0 | AJ41: 0 | AK41: 1 | AL41: =IF(AD41="TIPO I",'BASE LIQUIDACION'!$D$3,IF(AD41="TIPO II",'BASE LIQUIDACION'!$D$4,IF(AD41="TIPO III",'BASE LIQUIDACION'!$D$5,'BASE LIQUIDACION'!$D$7))) -> 222904.27 | AM41: =AG41*'BASE LIQUIDACION'!$B$12+AH41*'BASE LIQUIDACION'!$B$11+AI41*'BASE LIQUIDACION'!$B$13+AJ41*'BASE LIQUIDACION'!$B$14+AK41*AL41 -> 222904.27
A42: TUNJA | B42: =VLOOKUP(A42,'CENTRO DE COSTOS'!A:D,4,FALSE) -> MIGUEL JULIÁN HERNÁNDEZ GUARÍN | C42: =VLOOKUP(A42,'CENTRO DE COSTOS'!A:C,2,FALSE) -> 0004-0008 | D42: 15293 | E42: TA-25-799217 | F42: FO-25-1136294 | G42: 45832 | H42: 45834 | I42: 45832 | J42: 45834 | K42: 45834 | L42: BOYACA | M42: GACHANTIVA | N42: BARRIO VEREDA SAAVEDRA GACHANTIVA | O42: 79970 | P42: CB CRECIMIENTO - NUEVO | Q42: APERTURA | R42: REDEBAN | S42: UNO A UNO | T42: UNO A UNO | U42: EJECUTADO | V42: 24-06 SE REALIZA LLAMADA AL CLIENTE, SE HABLA CON LA SRA ERIKA LISBETH AMADOR CORTES SE VALIDA DIRECCIÓN OK, CANAL OK, DISPONIBILIDAD TOTAL, LLAMAR EL DÍA LA INSTALACIÓN PARA CONFIRMAR VISITA, AVISO EXTERIOR ALTURA APROX 1.50 METROS; TOMACORRIENTE CERCANO: SI; TIENE CABINA DE SEGURIDAD: SI- COMUNICACIÓN POR WPP 25/6/2025 SE COMUNICA PREVIAMENTE CON CLIENTE AL NÚMERO TELEFÓNICO 3133391626 LA SEÑORA ERIKA CONFIRMA ATENCIÓN PARA APERTURA....SE LLEGA A SITIO Y COMERCIO SE ENCUENTRA SIN ENERGÍA SE DA ESPERA DOS HORA Y LA FALLA CONTINUA CLIENTE SOLICITA VISITAR EL DIA DE MAÑANA 26/6/2025 SE REALIZA INSTALACIÓN DE CORRESPONSAL, SE INSTALAN EQUIPOS CON PRUEBAS EXITOSAS, SE CAPACITA Y SE EVALÚA AL CLIENTE, SE INSTALA PUBLICIDAD COMPLETA, CB QUEDA OPERATIVO. USUARIO SOMOS BANCOLOMBIA ACTIVO | W42: GONZALEZ GONZALEZ MARIO ALBERTO | X42: SAXZZ527 | Y42: 929580 | Z42: 295354-709254 | AA42: 908080 | AB42: N/A | AC42: 40 ROLLOS | AD42: =VLOOKUP(D42,TIPOLOGIAS!A:F,6,0) -> TIPO II | AE42: =VLOOKUP(D42,TIPOLOGIAS!A:F,5,0) -> TERRESTRE | AF42: VISITA _TECNICA | AG42: 0 | AH42: 0 | AI42: 0 | AJ42: 0 | AK42: 1 | AL42: =IF(AD42="TIPO I",'BASE LIQUIDACION'!$D$3,IF(AD42="TIPO II",'BASE LIQUIDACION'!$D$4,IF(AD42="TIPO III",'BASE LIQUIDACION'!$D$5,'BASE LIQUIDACION'!$D$7))) -> 134410.39 | AM42: =AG42*'BASE LIQUIDACION'!$B$12+AH42*'BASE LIQUIDACION'!$B$11+AI42*'BASE LIQUIDACION'!$B$13+AJ42*'BASE LIQUIDACION'!$B$14+AK42*AL42 -> 134410.39
A43: IBAGUE | B43: =VLOOKUP(A43,'CENTRO DE COSTOS'!A:D,4,FALSE) -> KEVIN ALEXIS CORZO BUSTOS | C43: =VLOOKUP(A43,'CENTRO DE COSTOS'!A:C,2,FALSE) -> 0004-0007 | D43: 73001 | E43: TA-25-804002 | F43: FO-25-1139009 | G43: 45834 | H43: 45839 | I43: 45834 | J43: 45835 | K43: 45835 | L43: TOLIMA | M43: IBAGUE | N43: MULTIPAGAS IBAGUE | O43: 23580 | P43: DATAFONO ADICIONAL - ALIANZA | Q43: APERTURA | R43: REDEBAN | S43: ROBUSTO | T43: MULTIPAGAS | U43: EJECUTADO/CANCELADO | V43: 26-06 SE REALIZA LLAMADA AL CLIENTE, SE HABLA CON LA SRA Nudi Céspedes SE VALIDA DIRECCIÓN OK, CANAL OK, DISPONIBILIDAD TOTAL, LLAMAR EL DÍA LA INSTALACIÓN PARA CONFIRMAR VISITA, 27/6/2025 SE VISITA CB MULTIPAGAS QUIEN ATIENDE LA SEÑORITA LUDY CESPEDES PERSONA ENCARGADA QUIEN INFORMA QUE NO NECESITA OTRO DATÁFONO ADICIONAL PARÁ EL PUNTO | W43: N/A | X43: V1ZZZ967 | Y43: N/A | Z43: N/A | AA43: N/A | AB43: N/A | AC43: 0 | AD43: =VLOOKUP(D43,TIPOLOGIAS!A:F,6,0) -> TIPO I | AE43: =VLOOKUP(D43,TIPOLOGIAS!A:F,5,0) -> TERRESTRE | AF43: VISITA _TECNICA | AG43: 0 | AH43: 0 | AI43: 0 | AJ43: 0 | AK43: 1 | AL43: =IF(AD43="TIPO I",'BASE LIQUIDACION'!$D$3,IF(AD43="TIPO II",'BASE LIQUIDACION'!$D$4,IF(AD43="TIPO III",'BASE LIQUIDACION'!$D$5,'BASE LIQUIDACION'!$D$7))) -> 44559.985 | AM43: =AG43*'BASE LIQUIDACION'!$B$12+AH43*'BASE LIQUIDACION'!$B$11+AI43*'BASE LIQUIDACION'!$B$13+AJ43*'BASE LIQUIDACION'!$B$14+AK43*AL43 -> 44559.985
A44: CALI | B44: =VLOOKUP(A44,'CENTRO DE COSTOS'!A:D,4,FALSE) -> DIEGO FERNANDO HENAO CARDONA | C44: =VLOOKUP(A44,'CENTRO DE COSTOS'!A:C,2,FALSE) -> 0004-0003 | D44: 76001 | E44: TA-25-680500 | F44: FO-25-1027231 | G44: 45805 | H44: 45807 | I44: 45805 | J44: 45811 | K44: 45811 | L44: VALLE DEL CAUCA | M44: CALI | N44: BARRIO VILLA DEL LAGO CALI 2 | O44: 79361 | P44: CB CRECIMIENTO - OTRAS LISTAS | Q44: APERTURA | R44: REDEBAN | S44: UNO A UNO | T44: UNO A UNO | U44: EJECUTADO | V44: 28-05 SE REALIZA LLAMADA AL CLIENTE, SE HABLA CON LA SRA DEISY (HIJA) SE VALIDA DIRECCIÓN OK, CANAL OK, DISPONIBILIDAD TOTAL, LLAMAR EL DÍA LA INSTALACIÓN PARA CONFIRMAR VISITA, AVISO EXTERIOR ALTURA: NO INDICA ALTURA; TOMACORRIENTE CERCANO: SI; TIENE CABINA DE SEGURIDAD: NO - COMUNICACIÓN POR WPP 30/5/2025 SE LLEGA AL PUNTO DESPUES DE LAS 4 PM YA QUE SE TUVO INCONVENIENTE CON VARIOS CAMBIOS DE EQUIPOS EN LA PRIMERA APERTURA, SE CONFIGURAN EQUIPOS PERO AL MOMENTO DE INICIALIZAR SE ENCUENTRA QUE LA TERMINAL NO ESTA EN BASE 24 , YA NO SE CUENTA CON SOPORTE DE REDEBAN, POR LO CUAL NO SE PUEDE LLEVAR A CABO LA APERTURA 3/6/2025 SE REALIZA INSTALACIÓN DE CORRESPONSAL, SE INSTALAN EQUIPOS CON PRUEBAS EXITOSAS, SE CAPACITA Y SE EVALÚA AL CLIENTE, SE INSTALA PUBLICIDAD COMPLETA, CB QUEDA OPERATIVO. USUARIO SOMOS BANCOLOMBIA ACTIVO | W44: HERRERA MONAR GEOVANNY | X44: 10XZZ899 | Y44: 1219158 | Z44: 1006564 | AA44: 789713 | AB44: N/A | AC44: 40 ROLLOS | AD44: =VLOOKUP(D44,TIPOLOGIAS!A:F,6,0) -> TIPO I | AE44: =VLOOKUP(D44,TIPOLOGIAS!A:F,5,0) -> TERRESTRE | AF44: VISITA _TECNICA | AG44: 0 | AH44: 0 | AI44: 0 | AJ44: 0 | AK44: 1 | AL44: =IF(AD44="TIPO I",'BASE LIQUIDACION'!$D$3,IF(AD44="TIPO II",'BASE LIQUIDACION'!$D$4,IF(AD44="TIPO III",'BASE LIQUIDACION'!$D$5,'BASE LIQUIDACION'!$D$7))) -> 44559.985 | AM44: =AG44*'BASE LIQUIDACION'!$B$12+AH44*'BASE LIQUIDACION'!$B$11+AI44*'BASE LIQUIDACION'!$B$13+AJ44*'BASE LIQUIDACION'!$B$14+AK44*AL44 -> 44559.985
A45: BOGOTA | B45: =VLOOKUP(A45,'CENTRO DE COSTOS'!A:D,4,FALSE) -> WILLIAM ASDRUBAL ROZO ROZO | C45: =VLOOKUP(A45,'CENTRO DE COSTOS'!A:C,2,FALSE) -> 0004-0004 | D45: 11001 | E45: TA-25-685028 | F45: FO-25-1016701 | G45: 45807 | H45: 45812 | I45: 45807 | J45: 45811 | K45: 45811 | L45: CUNDINAMARCA | M45: BOGOTA | N45: BARRIO LA ESTRELLA BOGOTA 2 | O45: 79605 | P45: CB CRECIMIENTO - NUEVO | Q45: APERTURA | R45: REDEBAN | S45: UNO A UNO | T45: UNO A UNO | U45: EJECUTADO | V45: 30-05 SE REALIZA LLAMADA AL CLIENTE, SE HABLA CON LA SR SNEIDER SAAVEDRA SAAVEDRA SE VALIDA DIRECCIÓN OK, CANAL OK, DISPONIBILIDAD TOTAL, LLAMAR EL DÍA LA INSTALACIÓN PARA CONFIRMAR VISITA, AVISO EXTERIOR ALTURA APROX 2 METROS; TOMACORRIENTE CERCANO: SI; TIENE CABINA DE SEGURIDAD: SI - EL MODEM ESTA A 4 MT 03-06 SE REALIZA INSTALACIÓN DE CORRESPONSAL, SE INSTALAN EQUIPOS CON PRUEBAS EXITOSAS, SE CAPACITA Y SE EVALÚA AL CLIENTE, SE INSTALA PUBLICIDAD COMPLETA, CB QUEDA OPERATIVO. USUARIO SOMOS BANCOLOMBIA ACTIVO NOTA: SE SOLICITA AUTORIZACIÓN DE INSTALACIÓN DE COMBO 2600 CON MAGICBOX 241597317561324755896013 Y PINPAD, PERO AL INSTALAR EL PINPAD Y SOLICITAR EL CAMBIO DE EQUIPO , EL PINPAD NO FUNCIONA 5/6/2025 SE REALIZA INSTALACIÓN DE PINPAD PENDIENTE | W45: ROMERO ROJAS BREIDY JHOHAN | X45: SXUZZ131 | Y45: 1235225 | Z45: 771812 | AA45: 1076276-241597317561324755896013 | AB45: N/A | AC45: 40 ROLLOS | AD45: =VLOOKUP(D45,TIPOLOGIAS!A:F,6,0) -> TIPO I | AE45: =VLOOKUP(D45,TIPOLOGIAS!A:F,5,0) -> TERRESTRE | AF45: VISITA _TECNICA | AG45: 0 | AH45: 0 | AI45: 0 | AJ45: 0 | AK45: 1 | AL45: =IF(AD45="TIPO I",'BASE LIQUIDACION'!$D$3,IF(AD45="TIPO II",'BASE LIQUIDACION'!$D$4,IF(AD45="TIPO III",'BASE LIQUIDACION'!$D$5,'BASE LIQUIDACION'!$D$7))) -> 44559.985 | AM45: =AG45*'BASE LIQUIDACION'!$B$12+AH45*'BASE LIQUIDACION'!$B$11+AI45*'BASE LIQUIDACION'!$B$13+AJ45*'BASE LIQUIDACION'!$B$14+AK45*AL45 -> 44559.985
A46: BOGOTA | B46: =VLOOKUP(A46,'CENTRO DE COSTOS'!A:D,4,FALSE) -> WILLIAM ASDRUBAL ROZO ROZO | C46: =VLOOKUP(A46,'CENTRO DE COSTOS'!A:C,2,FALSE) -> 0004-0004 | D46: 11001 | E46: TA-25-721929 | F46: FO-25-1072112 | G46: 45817 | H46: 45819 | I46: 45817 | J46: 45819 | K46: 45819 | L46: CUNDINAMARCA | M46: BOGOTA | N46: BARRIO FLORENCIA BOGOTA 1 | O46: 79744 | P46: CB CRECIMIENTO - NUEVO | Q46: APERTURA | R46: REDEBAN | S46: UNO A UNO | T46: UNO A UNO | U46: EJECUTADO | V46: 06-06 SE REALIZA LLAMADA AL CLIENTE, SE HABLA CON EL SR RAUL MARTINEZ RAMOS SE VALIDA DIRECCIÓN OK, CANAL OK, DISPONIBILIDAD TOTAL, LLAMAR EL DÍA LA INSTALACIÓN PARA CONFIRMAR VISITA, AVISO EXTERIOR ALTURA APROX DONDE EL TECNICO LO VEA CONVENIENTE; TOMACORRIENTE CERCANO: SI; TIENE CABINA DE SEGURIDAD: SI 10/6/2025 SE VISITA COMERCIO POR APERTURA LA USUARIO YA TIENE INSTALO FLANGGER Y AVISO, INDICA QUE HACE 4 MESES ESTABA INSTALADO UN CORRESPONSAL ALLI PERO EL DUEÑO DEJO LA PUBLICDAD Y SE LLEVO LOS EQUIOPOS.INTENTAR REALIZAR TRANSACCIONES DE PRUEBA EL DATAFONO NO COMUNICA POR FALLA EN EL EQUIPO SE REALIZA CAMBIO DE EQUIPO MY EL EQUIPO CAMBIADO SE QUEDA EN RG Y NO PERMITE TRANSAR SE ESCALA CASO CON ÁREA ENCARGADA PERO POR LA HORA NO SE BRINDA SOLUCIÓN INMEDIATA SE INDICA A CLIENTE QUE SE CONTINUARÁ CON PROCESO DE INSTALACION EL DÍA DE MAÑANA CLIENTE ACEPTA Y SE FINALIZA ACTIVIDAD SIN MÁS NOVEDAD 11/6/2025 SE REALIZA INSTALACIÓN DE CORRESPONSAL, SE INSTALAN EQUIPOS CON PRUEBAS EXITOSAS, SE CAPACITA Y SE EVALÚA AL CLIENTE,NO SE INSTALA PUBLICIDAD USUARIO YA LA TENIA INSTALADA, CB QUEDA OPERATIVO. USUARIO SOMOS BANCOLOMBIA ACTIVO | W46: MURCIA HERNANDEZ HARVEY IGNACIO | X46: F1XZZ041 | Y46: 963322 | Z46: 246040 | AA46: 1238702 | AB46: N/A | AC46: 40 ROLLOS | AD46: =VLOOKUP(D46,TIPOLOGIAS!A:F,6,0) -> TIPO I | AE46: =VLOOKUP(D46,TIPOLOGIAS!A:F,5,0) -> TERRESTRE | AF46: VISITA _TECNICA | AG46: 0 | AH46: 0 | AI46: 0 | AJ46: 0 | AK46: 1 | AL46: =IF(AD46="TIPO I",'BASE LIQUIDACION'!$D$3,IF(AD46="TIPO II",'BASE LIQUIDACION'!$D$4,IF(AD46="TIPO III",'BASE LIQUIDACION'!$D$5,'BASE LIQUIDACION'!$D$7))) -> 44559.985 | AM46: =AG46*'BASE LIQUIDACION'!$B$12+AH46*'BASE LIQUIDACION'!$B$11+AI46*'BASE LIQUIDACION'!$B$13+AJ46*'BASE LIQUIDACION'!$B$14+AK46*AL46 -> 44559.985
AM47: =SUM(AM2:AM46) -> 7602999.8

Sheet TIPOLOGIAS
A1: COD. CIUDAD | B1: CIUDAD | C1: DEPARTAMENTO | D1: DESDE DONDE SE ATIENDE | E1: TIPO DE TRAYECTO NUEVO | F1: TIPOLOGIA NUEVA
A2: 91430 | B2: LA VICTORIA | C2: AMAZONAS | D2: BOGOTA | E2: AEREO | F2: TIPO IV ESPECIAL
A3: 91669 | B3: PUERTO SANTANDER | C3: AMAZONAS | D3: BOGOTA | E3: AEREO | F3: TIPO IV ESPECIAL
A4: 91263 | B4: EL ENCANTO | C4: AMAZONAS | D4: BOGOTA | E4: AEREO | F4: TIPO IV ESPECIAL
A5: 91405 | B5: LA CHORRERA | C5: AMAZONAS | D5: BOGOTA | E5: AEREO | F5: TIPO IV ESPECIAL
A6: 91407 | B6: LA PEDRERA | C6: AMAZONAS | D6: BOGOTA | E6: AEREO | F6: TIPO IV ESPECIAL
A7: 91001 | B7: LETICIA | C7: AMAZONAS | D7: BOGOTA | E7: AEREO | F7: TIPO IV ESPECIAL
A8: 91460 | B8: MIRITI - PARANA | C8: AMAZONAS | D8: BOGOTA | E8: AEREO | F8: TIPO IV ESPECIAL
A9: 91530 | B9: PUERTO ALEGRIA | C9: AMAZONAS | D9: BOGOTA | E9: AEREO | F9: TIPO IV ESPECIAL
A10: 91536 | B10: PUERTO ARICA | C10: AMAZONAS | D10: BOGOTA | E10: AEREO | F10: TIPO IV ESPECIAL
A11: 91540 | B11: PUERTO NARIÑO | C11: AMAZONAS | D11: BOGOTA | E11: AEREO | F11: TIPO IV ESPECIAL
A12: 91798 | B12: TARAPACA | C12: AMAZONAS | D12: BOGOTA | E12: AEREO | F12: TIPO IV ESPECIAL
A13: 5055 | B13: ARGELIA | C13: ANTIOQUIA | D13: MEDELLIN | E13: TERRESTRE | F13: TIPO IV
... A1124: 23682 | B1124: SAN JOSE DE URE | C1124: CORDOBA | D1124: MONTERIA | E1124: TERRESTRE | F1124: TIPO III

Sheet INCIDENTES
A1: Ciudad Sede | B1: COORDINADOR | C1: CENTRO DE COSTOS LÍNEACOM | D1: Código DANE | E1: TA | F1: FO | G1: Fecha Asignación a Línea Comunicaciones (DD/MM/AAAA HH:MM) | H1: Fecha cierre del ticket (DD/MM/AAAA HH:MM) | I1: Departamento | J1: Ciudad | K1: CB Implementado | L1: Punto(Redes) | M1: Tipo Actividad | N1: Red | O1: FORMATO | P1: CADENA | Q1: Estado | R1: OBSERVACIONES | S1: Técnico | T1: Forma de Atención | U1: TERMINAL | V1: Acometida | W1: Grupo_Falla | X1: Categoría | Y1: Falla | Z1: Cambio Activo | AA1: CODIGOS DE DAÑO DATAFONOS | AB1: CODIGOS DE DAÑO LECTOR | AC1: CODIGOS DE DAÑO HUB | AD1: CODIGOS DE DAÑO PINPAD | AE1: Otro Activos | AF1: Tipo | AG1: Tipo de Trayecto | AH1: Dias de visita | AI1: ACOMETIDA DATOS | AJ1: ACOMETIDA ELÉCTRICA | AK1: SWITCH | AL1: VALOR DIAS ACTIVIDAD FACTURABLES | AM1: VALOR FACTURABLE
A2: BARRANQUILLA | B2: =VLOOKUP(A2,'CENTRO DE COSTOS'!A:D,4,FALSE) -> JOSE MAURICIO HERNANDEZ ROJAS | C2: =VLOOKUP(A2,'CENTRO DE COSTOS'!A:D,2,FALSE) -> 0004-0001 | D2: 8433 | E2: 2238837 | F2: FO-25-1022758 | G2: 45808.7 | H2: 45809.607 | I2: ATLANTICO | J2: MALAMBO | K2: PTM MALAMBO TIENDA Y REFRESQUE | L2: 62426 | M2: INCIDENTE | N2: REDEBAN | O2: AGREGADOR | Q2: CERRADO | R2: 1-06 SE ESCALA PARA VISITA. LLAMAR ANTES DE VISITAR Y CONFIRMAR DATOS, DIRECCION Y SOLICITUD 0 01-06 SE REALIZA VISITA SE PROCEDE A VALIDAR CONEXIONES Y TODO OK, POSIBLE DAÑO EN EL MODEM DEL INTERNET DEL CLIENTE ,SE PRUEBA CON OTRO MODEM SE HACEN PRUEBAS Y TODO OK ,POSIBLE DAÑO EN EL ROUTER DEL CLIENTE LOS PUERTOS DE RED | S2: PORRAS CASTRO DARLON NASCK | T2: VISITA_TÉCNICA | U2: FUA0I085 - HA00N753 | V2: NO | W2: USUARIO | X2: COMUNICACION | Y2: CANAL DEL COMERCIO | Z2: No | AA2: 0 | AB2: 0 | AC2: 0 | AD2: 0 | AE2: 0 | AF2: =VLOOKUP(D2,TIPOLOGIAS!A:H,6,0) -> TIPO II | AG2: =VLOOKUP(D2,TIPOLOGIAS!A:H,5,0) -> TERRESTRE | AH2: 1 | AI2: 0 | AJ2: 0 | AK2: 0 | AL2: =IF(T2="SOPORTE_TELEFÓNICO",'BASE LIQUIDACION'!$B$10,IF(AF2="TIPO I",'BASE LIQUIDACION'!$C$3,IF(AF2="TIPO II",'BASE LIQUIDACION'!$C$4,IF(AF2="TIPO III",'BASE LIQUIDACION'!$C$5,'BASE LIQUIDACION'!$C$7)))) -> 163813.56 | AM2: =IF(T2="SOPORTE_TELEFÓNICO",'BASE LIQUIDACION'!$B$10,(AH2*AL2+AI2*'BASE LIQUIDACION'!$B$12+AJ2*'BASE LIQUIDACION'!$B$11+INCIDENTES!AK2*'BASE LIQUIDACION'!$B$13)) -> 163813.56
A3: PASTO | B3: =VLOOKUP(A3,'CENTRO DE COSTOS'!A:D,4,FALSE) -> DIEGO FERNANDO HENAO CARDONA | C3: =VLOOKUP(A3,'CENTRO DE COSTOS'!A:D,2,FALSE) -> 0004-0003 | D3: 86001 | E3: 2243676 | F3: FO-25-1029545 | G3: 45811.421 | H3: 45811.549 | I3: PUTUMAYO | J3: MOCOA | K3: MULTIPAGAS MOCOA | L3: 45950 | M3: INCIDENTE | N3: REDEBAN | O3: ROBUSTO | Q3: CERRADO | R3: 03-06 SE REALIZA CONTACTO CON LA SEÑORA LORENA AL NUMERO 3209035833 QUIEN INDICA QUE EL DATAFONO LE ARROJA ERROR SIN TONO Y NO LE PERMITE OPERAR, SE HACEN VALIDACIONES Y SE ESCALA PARA VISITA TECNICA 0 03-06 SE REALIZA VALIDACION TELEFONICA CON LA USUARIA QUIEN INDICA QUE EL DATAFONO NO LE DEJA TRANSAR PERO FUE DE UN MOMENTO A OTRO, SE LE DAN INDICACIONES PARA VALIDAR LAS CONEXIONES, SE ENCUENTRA UN CABLE MAL CONECTADO, SE LE INDICA AL CLIENTE COMO DEBE DE IR LA CONEXION ADECUADA, SE PROCEDER A REALIARLA Y CONFIRMA OPERATIVIDAD DEL SERVICIO | S3: HENAO CARDONA DIEGO FERNANDO | T3: SOPORTE_TELEFÓNICO | U3: 0 | V3: NO | W3: USUARIO | X3: COMUNICACION | Y3: CONEXIONES DE COMERCIO | Z3: No | AA3: 0 | AB3: 0 | AC3: 0 | AD3: 0 | AE3: 0 | AF3: =VLOOKUP(D3,TIPOLOGIAS!A:H,6,0) -> TIPO IV | AG3: =VLOOKUP(D3,TIPOLOGIAS!A:H,5,0) -> TERRESTRE | AH3: 0 | AI3: 0 | AJ3: 0 | AK3: 0 | AL3: =IF(T3="SOPORTE_TELEFÓNICO",'BASE LIQUIDACION'!$B$10,IF(AF3="TIPO I",'BASE LIQUIDACION'!$C$3,IF(AF3="TIPO II",'BASE LIQUIDACION'!$C$4,IF(AF3="TIPO III",'BASE LIQUIDACION'!$C$5,'BASE LIQUIDACION'!$C$7)))) -> 37904.654 | AM3: =IF(T3="SOPORTE_TELEFÓNICO",'BASE LIQUIDACION'!$B$10,(AH3*AL3+AI3*'BASE LIQUIDACION'!$B$12+AJ3*'BASE LIQUIDACION'!$B$11+INCIDENTES!AK3*'BASE LIQUIDACION'!$B$13)) -> 37904.654
A4: IBAGUE | B4: =VLOOKUP(A4,'CENTRO DE COSTOS'!A:D,4,FALSE) -> KEVIN ALEXIS CORZO BUSTOS | C4: =VLOOKUP(A4,'CENTRO DE COSTOS'!A:D,2,FALSE) -> 0004-0007 | D4: 73001 | E4: 2238476 | F4: FO-25-1021495 | G4: 45808.547 | H4: 45811.631 | I4: TOLIMA | J4: IBAGUE | K4: BARRIO CENTRO IBAGUE 47 | L4: 73076 | M4: INCIDENTE | N4: REDEBAN | O4: CB UNO A UNO | Q4: CERRADO | R4: 31-05 SE ESCALA PARA VISITA. LLAMAR ANTES DE VISITAR Y CONFIRMAR DATOS, DIRECCION Y SOLICITUD 01/06/2025 EN COMUNICACIÓN CON LA SEÑORA ALEJANDRA AL NUMERO DE CONTACTO DE LA ORDEN QUE NOS PUEDE ATENDER EL MARTES A PARTIR DE LAS 7AM. 03-06 SE VÁLIDA ERROR EN COMUNICACIÓN DEBIDO A QUE EL CLIENTE TIENE UNA MALA CONEXIÓN PARA EL DATÁFONO, SE RECOMIENDA VALIDAR PROVEEDOR DE SERVICIOS DE INTERNET DEL CLIENTE. SE REALIZA PRUEBAS DE FUNCIONAMIENTO OK. | S4: BARRAGAN TAFUR EDWIN ESTEBAN | T4: VISITA_TÉCNICA | U4: MN00R030 | V4: NO | W4: USUARIO | X4: COMUNICACION | Y4: CONEXIONES DE COMERCIO | Z4: No | AA4: 0 | AB4: 0 | AC4: 0 | AD4: 0 | AE4: 0 | AF4: =VLOOKUP(D4,TIPOLOGIAS!A:H,6,0) -> TIPO I | AG4: =VLOOKUP(D4,TIPOLOGIAS!A:H,5,0) -> TERRESTRE | AH4: 1 | AI4: 0 | AJ4: 0 | AK4: 0 | AL4: =IF(T4="SOPORTE_TELEFÓNICO",'BASE LIQUIDACION'!$B$10,IF(AF4="TIPO I",'BASE LIQUIDACION'!$C$3,IF(AF4="TIPO II",'BASE LIQUIDACION'!$C$4,IF(AF4="TIPO III",'BASE LIQUIDACION'!$C$5,'BASE LIQUIDACION'!$C$7)))) -> 65960.474 | AM4: =IF(T4="SOPORTE_TELEFÓNICO",'BASE LIQUIDACION'!$B$10,(AH4*AL4+AI4*'BASE LIQUIDACION'!$B$12+AJ4*'BASE LIQUIDACION'!$B$11+INCIDENTES!AK4*'BASE LIQUIDACION'!$B$13)) -> 65960.474
A5: MEDELLIN | B5: =VLOOKUP(A5,'CENTRO DE COSTOS'!A:D,4,FALSE) -> JUAN SEBASTIÁN RÍOS CASTRILLÓN | C5: =VLOOKUP(A5,'CENTRO DE COSTOS'!A:D,2,FALSE) -> 0004-0005 | D5: 5001 | E5: 2242577 | F5: FO-25-1028603 | G5: 45811.372 | H5: 45811.637 | I5: ANTIOQUIA | J5: MEDELLIN | K5: PAGAFACIL COLTEJER II | L5: 29112 | M5: INCIDENTE | N5: REDEBAN | O5: ROBUSTO | Q5: CERRADO | R5: 3-06 SE ESCALA PARA VISITA. LLAMAR ANTES DE VISITAR Y CONFIRMAR DATOS, DIRECCION Y SOLICITUD 0 03-06 SE HACE MANTENIMIENTO DE EQUIPO Y CABLEADO TODO OK | S5: MORENO MEDINA JUAN PABLO | T5: VISITA_TÉCNICA | U5: BBBBE639 | V5: NO | W5: USUARIO | X5: MANTENIMIENTO | Y5: MANTENIMIENTO GENERAL | Z5: No | AA5: 0 | AB5: 0 | AC5: 0 | AD5: 0 | AE5: 0 | AF5: =VLOOKUP(D5,TIPOLOGIAS!A:H,6,0) -> TIPO I | AG5: =VLOOKUP(D5,TIPOLOGIAS!A:H,5,0) -> TERRESTRE | AH5: 1 | AI5: 0 | AJ5: 0 | AK5: 0 | AL5: =IF(T5="SOPORTE_TELEFÓNICO",'BASE LIQUIDACION'!$B$10,IF(AF5="TIPO I",'BASE LIQUIDACION'!$C$3,IF(AF5="TIPO II",'BASE LIQUIDACION'!$C$4,IF(AF5="TIPO III",'BASE LIQUIDACION'!$C$5,'BASE LIQUIDACION'!$C$7)))) -> 65960.474 | AM5: =IF(T5="SOPORTE_TELEFÓNICO",'BASE LIQUIDACION'!$B$10,(AH5*AL5+AI5*'BASE LIQUIDACION'!$B$12+AJ5*'BASE LIQUIDACION'!$B$11+INCIDENTES!AK5*'BASE LIQUIDACION'!$B$13)) -> 65960.474
A6: CALI | B6: =VLOOKUP(A6,'CENTRO DE COSTOS'!A:D,4,FALSE) -> DIEGO FERNANDO HENAO CARDONA | C6: =VLOOKUP(A6,'CENTRO DE COSTOS'!A:D,2,FALSE) -> 0004-0003 | D6: 76001 | E6: 2244482 | F6: FO-25-1030127 | G6: 45811.456 | H6: 45811.67 | I6: VALLE DEL CAUCA | J6: CALI | K6: BARRIO LOS ANDES CALI | L6: 57564 | M6: INCIDENTE | N6: REDEBAN | O6: CB UNO A UNO | Q6: CERRADO | R6: 3-06 SE ESCALA PARA VISITA. LLAMAR ANTES DE VISITAR Y CONFIRMAR DATOS, DIRECCION Y SOLICITUD 0 03-06 SE HACEN PRUEVAS Y NOS DAMOS CUENTA QUR LA CONEXIÓN DEL ESTABLECIMIENTO ESTABA INTERMITENTE CONECTAMOS DIRECTAMENTE AL ROUTER Y FUNCIONA CORRECTAMENTE | S6: CUERO RUIZ JHONNY | T6: VISITA_TÉCNICA | U6: 9A09Z495 | V6: NO | W6: USUARIO | X6: COMUNICACION | Y6: CONEXIONES DE COMERCIO | Z6: No | AA6: 0 | AB6: 0 | AC6: 0 | AD6: 0 | AE6: 0 | AF6: =VLOOKUP(D6,TIPOLOGIAS!A:H,6,0) -> TIPO I | AG6: =VLOOKUP(D6,TIPOLOGIAS!A:H,5,0) -> TERRESTRE | AH6: 1 | AI6: 0 | AJ6: 0 | AK6: 0 | AL6: =IF(T6="SOPORTE_TELEFÓNICO",'BASE LIQUIDACION'!$B$10,IF(AF6="TIPO I",'BASE LIQUIDACION'!$C$3,IF(AF6="TIPO II",'BASE LIQUIDACION'!$C$4,IF(AF6="TIPO III",'BASE LIQUIDACION'!$C$5,'BASE LIQUIDACION'!$C$7)))) -> 65960.474 | AM6: =IF(T6="SOPORTE_TELEFÓNICO",'BASE LIQUIDACION'!$B$10,(AH6*AL6+AI6*'BASE LIQUIDACION'!$B$12+AJ6*'BASE LIQUIDACION'!$B$11+INCIDENTES!AK6*'BASE LIQUIDACION'!$B$13)) -> 65960.474
A7: MEDELLIN | B7: =VLOOKUP(A7,'CENTRO DE COSTOS'!A:D,4,FALSE) -> JUAN SEBASTIÁN RÍOS CASTRILLÓN | C7: =VLOOKUP(A7,'CENTRO DE COSTOS'!A:D,2,FALSE) -> 0004-0005 | D7: 5091 | E7: 2239287 | F7: FO-25-1023137 | G7: 45809.442 | H7: 45812.343 | I7: ANTIOQUIA | J7: BETANIA | K7: BARRIO CENTRO BETANIA | L7: 66548 | M7: INCIDENTE | N7: REDEBAN | O7: CB UNO A UNO | Q7: CERRADO | R7: 1-06 SE ESCALA PARA VISITA. LLAMAR ANTES DE VISITAR Y CONFIRMAR DATOS, DIRECCION Y SOLICITUD 04/06/2025 VISITA NO PUDO SER AGENDADA DESDE DÍA MARTES YA QUE NO SE CUENTA CON EQUIPOS EN BODEGA. DISTRIBUIDOR TUVO NOVEDAD CON ENTREGA Y AUN NO LLEGAN EQUIPOS A BODEGA. 04-06 SE LLAMA AL 3225845336 Y SE HABLA CON LA SRA MARÍA JOSÉ LA CUAL INDICA QUE YA EL COMERCIO FUNCIONA BIEN Y NO NECESITA VISITA | S7: ALVAREZ ARENAS VICTOR HUGO | T7: SOPORTE_TELEFÓNICO | U7: 0 | V7: NO | W7: USUARIO | X7: COMUNICACION | Y7: CANAL DEL COMERCIO | Z7: No | AA7: 0 | AB7: 0 | AC7: 0 | AD7: 0 | AE7: 0 | AF7: =VLOOKUP(D7,TIPOLOGIAS!A:H,6,0) -> TIPO III | AG7: =VLOOKUP(D7,TIPOLOGIAS!A:H,5,0) -> TERRESTRE | AH7: 0 | AI7: 0 | AJ7: 0 | AK7: 0 | AL7: =IF(T7="SOPORTE_TELEFÓNICO",'BASE LIQUIDACION'!$B$10,IF(AF7="TIPO I",'BASE LIQUIDACION'!$C$3,IF(AF7="TIPO II",'BASE LIQUIDACION'!$C$4,IF(AF7="TIPO III",'BASE LIQUIDACION'!$C$5,'BASE LIQUIDACION'!$C$7)))) -> 37904.654 | AM7: =IF(T7="SOPORTE_TELEFÓNICO",'BASE LIQUIDACION'!$B$10,(AH7*AL7+AI7*'BASE LIQUIDACION'!$B$12+AJ7*'BASE LIQUIDACION'!$B$11+INCIDENTES!AK7*'BASE LIQUIDACION'!$B$13)) -> 37904.654
A8: VALLEDUPAR | B8: =VLOOKUP(A8,'CENTRO DE COSTOS'!A:D,4,FALSE) -> JOSE MAURICIO HERNANDEZ ROJAS | C8: =VLOOKUP(A8,'CENTRO DE COSTOS'!A:D,2,FALSE) -> 0004-0001 | D8: 20383 | E8: 2249361 | F8: FO-25-1036197 | G8: 45812.333 | H8: 45812.363 | I8: CESAR | J8: LA GLORIA | K8: BARRIO SIMANAÑA LA GLORIA | L8: 75732 | M8: INCIDENTE | N8: REDEBAN | O8: CB UNO A UNO | Q8: CERRADO | R8: 04-06 SE REALIZA CONTACTO TELEFONICO CON LA SRA MARGY CORDERO AL NUMERO 3023025760 INDICA QUE ESTA MAÑANA CONECTO EL DATAFONO Y QUE YA ESTA FUNCIONANDO CON NORMALIDAD QUE NO ES NECESARIA LA VISITA Y QUE SE HABIA INTENTADO COMUNICAR CON LA LINEA PERO NO LE RESPONDIAN SE LE INDICA QUE SE CERRARA LA VISITA Y ELLA AUTORIZA INDICA CB OK 0 0 | S8: 0 | T8: SOPORTE_TELEFÓNICO | U8: 0 | V8: NO | W8: USUARIO | X8: COMUNICACION | Y8: CONEXIONES DE COMERCIO | Z8: No | AA8: 0 | AB8: 0 | AC8: 0 | AD8: 0 | AE8: 0 | AF8: =VLOOKUP(D8,TIPOLOGIAS!A:H,6,0) -> TIPO IV | AG8: =VLOOKUP(D8,TIPOLOGIAS!A:H,5,0) -> TERRESTRE | AH8: 0 | AI8: 0 | AJ8: 0 | AK8: 0 | AL8: =IF(T8="SOPORTE_TELEFÓNICO",'BASE LIQUIDACION'!$B$10,IF(AF8="TIPO I",'BASE LIQUIDACION'!$C$3,IF(AF8="TIPO II",'BASE LIQUIDACION'!$C$4,IF(AF8="TIPO III",'BASE LIQUIDACION'!$C$5,'BASE LIQUIDACION'!$C$7)))) -> 37904.654 | AM8: =IF(T8="SOPORTE_TELEFÓNICO",'BASE LIQUIDACION'!$B$10,(AH8*AL8+AI8*'BASE LIQUIDACION'!$B$12+AJ8*'BASE LIQUIDACION'!$B$11+INCIDENTES!AK8*'BASE LIQUIDACION'!$B$13)) -> 37904.654
A9: APARTADO | B9: =VLOOKUP(A9,'CENTRO DE COSTOS'!A:D,4,FALSE) -> JUAN SEBASTIÁN RÍOS CASTRILLÓN | C9: =VLOOKUP(A9,'CENTRO DE COSTOS'!A:D,2,FALSE) -> 0004-0005 | D9: 5045 | E9: 2245980 | F9: FO-25-1031771 | G9: 45811.532 | H9: 45812.383 | I9: ANTIOQUIA | J9: APARTADO | K9: DISTRICOL DROGUERIA PORVENIR | L9: 70794 | M9: INCIDENTE | N9: REDEBAN | O9: AGREGADOR | Q9: CERRADO | R9: 3-06 SE ESCALA PARA VISITA. LLAMAR ANTES DE VISITAR Y CONFIRMAR DATOS, DIRECCION Y SOLICITUD 0 04-06 TAPABDSTAFONO MALA, SE REALIZA CAMBIO Y DSTSFONO QUEDA OPERATIVO | S9: CASTRO HENAO DANIEL ESTEBAN | T9: VISITA_TÉCNICA | U9: A30IZ529 | V9: NO | W9: USUARIO | X9: MANTENIMIENTO | Y9: MANTENIMIENTO GENERAL | Z9: No | AA9: 0 | AB9: 0 | AC9: 0 | AD9: 0 | AE9: 0 | AF9: =VLOOKUP(D9,TIPOLOGIAS!A:H,6,0) -> TIPO I | AG9: =VLOOKUP(D9,TIPOLOGIAS!A:H,5,0) -> TERRESTRE | AH9: 1 | AI9: 0 | AJ9: 0 | AK9: 0 | AL9: =IF(T9="SOPORTE_TELEFÓNICO",'BASE LIQUIDACION'!$B$10,IF(AF9="TIPO I",'BASE LIQUIDACION'!$C$3,IF(AF9="TIPO II",'BASE LIQUIDACION'!$C$4,IF(AF9="TIPO III",'BASE LIQUIDACION'!$C$5,'BASE LIQUIDACION'!$C$7)))) -> 65960.474 | AM9: =IF(T9="SOPORTE_TELEFÓNICO",'BASE LIQUIDACION'!$B$10,(AH9*AL9+AI9*'BASE LIQUIDACION'!$B$12+AJ9*'BASE LIQUIDACION'!$B$11+INCIDENTES!AK9*'BASE LIQUIDACION'!$B$13)) -> 65960.474
A10: BOGOTA | B10: =VLOOKUP(A10,'CENTRO DE COSTOS'!A:D,4,FALSE) -> WILLIAM ASDRUBAL ROZO ROZO | C10: =VLOOKUP(A10,'CENTRO DE COSTOS'!A:D,2,FALSE) -> 0004-0004 | D10: 11001 | E10: 2247152 | F10: FO-25-1033782 | G10: 45811.613 | H10: 45812.489 | I10: CUNDINAMARCA | J10: BOGOTA | K10: DISTRICOL FERRELECTRICOS ALCON | L10: 49043 | M10: INCIDENTE | N10: REDEBAN | O10: AGREGADOR | Q10: CERRADO | R10: 3-06 SE ESCALA PARA VISITA. LLAMAR ANTES DE VISITAR Y CONFIRMAR DATOS, DIRECCION Y SOLICITUD 0 04-06 SE RESTABLECE CLAVE DE SUPERVISOR, COMERCIO REALIZA PRUEBAS DE FUNCIONAMIENTO, CIERRE FUNCIONA OK | S10: MICHELI LOPEZ MIGUEL ANGEL | T10: VISITA_TÉCNICA | U10: AD00O680 | V10: NO | W10: USUARIO | X10: CIERRE | Y10: COMERCIO NO REALIZA CIERRE | Z10: No | AA10: 0 | AB10: 0 | AC10: 0 | AD10: 0 | AE10: 0 | AF10: =VLOOKUP(D10,TIPOLOGIAS!A:H,6,0) -> TIPO I | AG10: =VLOOKUP(D10,TIPOLOGIAS!A:H,5,0) -> TERRESTRE | AH10: 1 | AI10: 0 | AJ10: 0 | AK10: 0 | AL10: =IF(T10="SOPORTE_TELEFÓNICO",'BASE LIQUIDACION'!$B$10,IF(AF10="TIPO I",'BASE LIQUIDACION'!$C$3,IF(AF10="TIPO II",'BASE LIQUIDACION'!$C$4,IF(AF10="TIPO III",'BASE LIQUIDACION'!$C$5,'BASE LIQUIDACION'!$C$7)))) -> 65960.474 | AM10: =IF(T10="SOPORTE_TELEFÓNICO",'BASE LIQUIDACION'!$B$10,(AH10*AL10+AI10*'BASE LIQUIDACION'!$B$12+AJ10*'BASE LIQUIDACION'!$B$11+INCIDENTES!AK10*'BASE LIQUIDACION'!$B$13)) -> 65960.474
A11: MEDELLIN | B11: =VLOOKUP(A11,'CENTRO DE COSTOS'!A:D,4,FALSE) -> JUAN SEBASTIÁN RÍOS CASTRILLÓN | C11: =VLOOKUP(A11,'CENTRO DE COSTOS'!A:D,2,FALSE) -> 0004-0005 | D11: 5001 | E11: 2249086 | F11: FO-25-1034661 | G11: 45811.731 | H11: 45812.509 | I11: ANTIOQUIA | J11: MEDELLIN | K11: COMCARD MEDELLIN SALVADOR BELL | L11: 23659 | M11: INCIDENTE | N11: REDEBAN | O11: AGREGADOR | Q11: CERRADO | R11: 3-06 SE ESCALA PARA VISITA. LLAMAR ANTES DE VISITAR Y CONFIRMAR DATOS, DIRECCION Y SOLICITUD 0 04-06 SE REALIZA MANTENIMIENTO Y SE CONFIGURA PARÁMETROS DE NUEVO | S11: CERPA SUAREZ DUVAN CAMILO | T11: VISITA_TÉCNICA | U11: ABC0D992 | V11: NO | W11: USUARIO | X11: MANTENIMIENTO | Y11: MANTENIMIENTO GENERAL | Z11: No | AA11: 0 | AB11: 0 | AC11: 0 | AD11: 0 | AE11: 0 | AF11: =VLOOKUP(D11,TIPOLOGIAS!A:H,6,0) -> TIPO I | AG11: =VLOOKUP(D11,TIPOLOGIAS!A:H,5,0) -> TERRESTRE | AH11: 1 | AI11: 0 | AJ11: 0 | AK11: 0 | AL11: =IF(T11="SOPORTE_TELEFÓNICO",'BASE LIQUIDACION'!$B$10,IF(AF11="TIPO I",'BASE LIQUIDACION'!$C$3,IF(AF11="TIPO II",'BASE LIQUIDACION'!$C$4,IF(AF11="TIPO III",'BASE LIQUIDACION'!$C$5,'BASE LIQUIDACION'!$C$7)))) -> 65960.474 | AM11: =IF(T11="SOPORTE_TELEFÓNICO",'BASE LIQUIDACION'!$B$10,(AH11*AL11+AI11*'BASE LIQUIDACION'!$B$12+AJ11*'BASE LIQUIDACION'!$B$11+INCIDENTES!AK11*'BASE LIQUIDACION'!$B$13)) -> 65960.474
A12: TUNJA | B12: =VLOOKUP(A12,'CENTRO DE COSTOS'!A:D,4,FALSE) -> MIGUEL JULIÁN HERNÁNDEZ GUARÍN | C12: =VLOOKUP(A12,'CENTRO DE COSTOS'!A:D,2,FALSE) -> 0004-0008 | D12: 15001 | E12: 2249070 | F12: FO-25-1034562 | G12: 45811.726 | H12: 45812.518 | I12: BOYACA | J12: TUNJA | K12: BARRIO CENTRO TUNJA 31 | L12: 79424 | M12: INCIDENTE | N12: REDEBAN | O12: CB UNO A UNO | Q12: CERRADO | R12: 3-06 SE ESCALA PARA VISITA. LLAMAR ANTES DE VISITAR Y CONFIRMAR DATOS, DIRECCION Y SOLICITUD 0 04-06 SE REALIZA VISITA AL COMERCIO, SE VALIDA QUE EL CLIENTE ESTA HACIENDO MALA MANIPULACIÓN DEL DATAFONO Y LECTOR, SE HACEN PRUEBAS OK. | S12: SOLER HOYOS CRISTIAN LEONARDO | T12: VISITA_TÉCNICA | U12: 10XZZ962 | V12: NO | W12: USUARIO | X12: LECTOR DE BARRAS | Y12: ERROR PAGOS PARCIALES DE FACTURAS | Z12: No | AA12: 0 | AB12: 0 | AC12: 0 | AD12: 0 | AE12: 0 | AF12: =VLOOKUP(D12,TIPOLOGIAS!A:H,6,0) -> TIPO I | AG12: =VLOOKUP(D12,TIPOLOGIAS!A:H,5,0) -> TERRESTRE | AH12: 1 | AI12: 0 | AJ12: 0 | AK12: 0 | AL12: =IF(T12="SOPORTE_TELEFÓNICO",'BASE LIQUIDACION'!$B$10,IF(AF12="TIPO I",'BASE LIQUIDACION'!$C$3,IF(AF12="TIPO II",'BASE LIQUIDACION'!$C$4,IF(AF12="TIPO III",'BASE LIQUIDACION'!$C$5,'BASE LIQUIDACION'!$C$7)))) -> 65960.474 | AM12: =IF(T12="SOPORTE_TELEFÓNICO",'BASE LIQUIDACION'!$B$10,(AH12*AL12+AI12*'BASE LIQUIDACION'!$B$12+AJ12*'BASE LIQUIDACION'!$B$11+INCIDENTES!AK12*'BASE LIQUIDACION'!$B$13)) -> 65960.474
A13: MEDELLIN | B13: =VLOOKUP(A13,'CENTRO DE COSTOS'!A:D,4,FALSE) -> JUAN SEBASTIÁN RÍOS CASTRILLÓN | C13: =VLOOKUP(A13,'CENTRO DE COSTOS'!A:D,2,FALSE) -> 0004-0005 | D13: 5001 | E13: 2251343 | F13: FO-25-1038564 | G13: 45812.401 | H13: 45812.558 | I13: ANTIOQUIA | J13: MEDELLIN | K13: BARRIO ROBLEDO BELLO HORIZONTE | L13: 47724 | M13: INCIDENTE | N13: REDEBAN | O13: CB UNO A UNO | Q13: CERRADO | R13: 4-06 SE ESCALA PARA VISITA. LLAMAR ANTES DE VISITAR Y CONFIRMAR DATOS, DIRECCION Y SOLICITUD 0 04-06 SE REALIZA MANTENIMIENTO Y SE CAMBIA CABLE ENTORCHADO | S13: CERPA SUAREZ DUVAN CAMILO | T13: VISITA_TÉCNICA | U13: XP00F471-9CUZZ009 | V13: NO | W13: USUARIO | X13: MANTENIMIENTO | Y13: MANTENIMIENTO GENERAL | Z13: No | AA13: 0 | AB13: 0 | AC13: 0 | AD13: 0 | AE13: Cable de red | AF13: =VLOOKUP(D13,TIPOLOGIAS!A:H,6,0) -> TIPO I | AG13: =VLOOKUP(D13,TIPOLOGIAS!A:H,5,0) -> TERRESTRE | AH13: 1 | AI13: 0 | AJ13: 0 | AK13: 0 | AL13: =IF(T13="SOPORTE_TELEFÓNICO",'BASE LIQUIDACION'!$B$10,IF(AF13="TIPO I",'BASE LIQUIDACION'!$C$3,IF(AF13="TIPO II",'BASE LIQUIDACION'!$C$4,IF(AF13="TIPO III",'BASE LIQUIDACION'!$C$5,'BASE LIQUIDACION'!$C$7)))) -> 65960.474 | AM13: =IF(T13="SOPORTE_TELEFÓNICO",'BASE LIQUIDACION'!$B$10,(AH13*AL13+AI13*'BASE LIQUIDACION'!$B$12+AJ13*'BASE LIQUIDACION'!$B$11+INCIDENTES!AK13*'BASE LIQUIDACION'!$B$13)) -> 65960.474
A14: MEDELLIN | B14: =VLOOKUP(A14,'CENTRO DE COSTOS'!A:D,4,FALSE) -> JUAN SEBASTIÁN RÍOS CASTRILLÓN | C14: =VLOOKUP(A14,'CENTRO DE COSTOS'!A:D,2,FALSE) -> 0004-0005 | D14: 5001 | E14: 2253135 | F14: FO-25-1041040 | G14: 45812.51 | H14: 45812.658 | I14: ANTIOQUIA | J14: MEDELLIN | K14: BARRIO ARANJUEZ SAN CAYETANO M | L14: 43256 | M14: INCIDENTE | N14: REDEBAN | O14: CB UNO A UNO | Q14: CERRADO | R14: 4-06 SE ESCALA PARA VISITA. LLAMAR ANTES DE VISITAR Y CONFIRMAR DATOS, DIRECCION Y SOLICITUD 0 04-06 SE REALIZA MANTENIMIENTO Y SE CONFIGURA PARÁMETROS DE NUEVO | S14: CERPA SUAREZ DUVAN CAMILO | T14: VISITA_TÉCNICA | U14: 9ACZZ042 | V14: NO | W14: USUARIO | X14: MANTENIMIENTO | Y14: MANTENIMIENTO GENERAL | Z14: No | AA14: 0 | AB14: 0 | AC14: 0 | AD14: 0 | AE14: 0 | AF14: =VLOOKUP(D14,TIPOLOGIAS!A:H,6,0) -> TIPO I | AG14: =VLOOKUP(D14,TIPOLOGIAS!A:H,5,0) -> TERRESTRE | AH14: 1 | AI14: 0 | AJ14: 0 | AK14: 0 | AL14: =IF(T14="SOPORTE_TELEFÓNICO",'BASE LIQUIDACION'!$B$10,IF(AF14="TIPO I",'BASE LIQUIDACION'!$C$3,IF(AF14="TIPO II",'BASE LIQUIDACION'!$C$4,IF(AF14="TIPO III",'BASE LIQUIDACION'!$C$5,'BASE LIQUIDACION'!$C$7)))) -> 65960.474 | AM14: =IF(T14="SOPORTE_TELEFÓNICO",'BASE LIQUIDACION'!$B$10,(AH14*AL14+AI14*'BASE LIQUIDACION'!$B$12+AJ14*'BASE LIQUIDACION'!$B$11+INCIDENTES!AK14*'BASE LIQUIDACION'!$B$13)) -> 65960.474
A15: TUNJA | B15: =VLOOKUP(A15,'CENTRO DE COSTOS'!A:D,4,FALSE) -> MIGUEL JULIÁN HERNÁNDEZ GUARÍN | C15: =VLOOKUP(A15,'CENTRO DE COSTOS'!A:D,2,FALSE) -> 0004-0008 | D15: 15001 | E15: 2244959 | F15: FO-25-1030481 | G15: 45811.469 | H15: 45812.675 | I15: BOYACA | J15: TUNJA | K15: BARRIO SAN ANTONIO TUNJA | L15: 71303 | M15: INCIDENTE | N15: REDEBAN | O15: CB UNO A UNO | Q15: CERRADO | R15: 3-06 SE ESCALA PARA VISITA. LLAMAR ANTES DE VISITAR Y CONFIRMAR DATOS, DIRECCION Y SOLICITUD 04/06/2025 SE LOGRA COMUNICACION CON LA SEÑORA BLANCA SUSANA BOHORQUEZ PARA CONFIRMAR LA VISITA, CLIENTE INFORMA QUE EN EL MOMENTO NO CUENTA CON SERVICIO DE RED ELECTRICA EN LA ZONA POR ARREGLOS DE LA EMPRESA DE ENERGIA, CLIENTE SOLICITA QUE SE LE LLAME A LAS 2PM PARA CONFIRMAR LA VISITA. 04/06/2025 SE LOGRA COMUNICACION CON EL CLIENTE, CLIENTE MANIFIESTA QUE YA TIENE SERVICIO DE LUZ ELÉCTRICA, SE VISITARA A LAS 3PM. 04-06 SE REALIZA VISITA AL COMERCIO, SE VALIDA QUE EL INTERNET DEL CLIENTE PRESENTA FALLAS, SE HACEN PRUEBAS OK. | S15: SOLER HOYOS CRISTIAN LEONARDO | T15: VISITA_TÉCNICA | U15: SV00C126 | V15: NO | W15: USUARIO | X15: COMUNICACION | Y15: CANAL DEL COMERCIO | Z15: No | AA15: 0 | AB15: 0 | AC15: 0 | AD15: 0 | AE15: 0 | AF15: =VLOOKUP(D15,TIPOLOGIAS!A:H,6,0) -> TIPO I | AG15: =VLOOKUP(D15,TIPOLOGIAS!A:H,5,0) -> TERRESTRE | AH15: 1 | AI15: 0 | AJ15: 0 | AK15: 0 | AL15: =IF(T15="SOPORTE_TELEFÓNICO",'BASE LIQUIDACION'!$B$10,IF(AF15="TIPO I",'BASE LIQUIDACION'!$C$3,IF(AF15="TIPO II",'BASE LIQUIDACION'!$C$4,IF(AF15="TIPO III",'BASE LIQUIDACION'!$C$5,'BASE LIQUIDACION'!$C$7)))) -> 65960.474 | AM15: =IF(T15="SOPORTE_TELEFÓNICO",'BASE LIQUIDACION'!$B$10,(AH15*AL15+AI15*'BASE LIQUIDACION'!$B$12+AJ15*'BASE LIQUIDACION'!$B$11+INCIDENTES!AK15*'BASE LIQUIDACION'!$B$13)) -> 65960.474
A16: PASTO | B16: =VLOOKUP(A16,'CENTRO DE COSTOS'!A:D,4,FALSE) -> DIEGO FERNANDO HENAO CARDONA | C16: =VLOOKUP(A16,'CENTRO DE COSTOS'!A:D,2,FALSE) -> 0004-0003 | D16: 52001 | E16: 2253326 | F16: FO-25-1041046 | G16: 45812.527 | H16: 45812.676 | I16: NARIÑO | J16: PASTO | K16: BARRIO CENTRO PASTO 35 | L16: 76097 | M16: INCIDENTE | N16: REDEBAN | O16: CB UNO A UNO | Q16: CERRADO | R16: 4-06 SE ESCALA PARA VISITA. LLAMAR ANTES DE VISITAR Y CONFIRMAR DATOS, DIRECCION Y SOLICITUD 0 04-06 SE VISITA EL CB PARA VERIFICAR FALLA, USUARIA REPORTO DATAFONO SIN CONEXIÓN, FUE DEBIDO A UNA CAIDA DE ENERGÍA, PERO EN EL MOMENTO FUNCIONA SIN INCONVENIENTES, SE VERIFICA CABLEADO OK, SE TOMAN PRUEBAS OK, CB OPERATIVO | S16: GUERRERO RAMIREZ OSCAR DARIO | T16: VISITA_TÉCNICA | U16: LA0EZ272 | V16: NO | W16: USUARIO | X16: COMUNICACION | Y16: CANAL DEL COMERCIO | Z16: No | AA16: 0 | AB16: 0 | AC16: 0 | AD16: 0 | AE16: 0 | AF16: =VLOOKUP(D16,TIPOLOGIAS!A:H,6,0) -> TIPO I | AG16: =VLOOKUP(D16,TIPOLOGIAS!A:H,5,0) -> TERRESTRE | AH16: 1 | AI16: 0 | AJ16: 0 | AK16: 0 | AL16: =IF(T16="SOPORTE_TELEFÓNICO",'BASE LIQUIDACION'!$B$10,IF(AF16="TIPO I",'BASE LIQUIDACION'!$C$3,IF(AF16="TIPO II",'BASE LIQUIDACION'!$C$4,IF(AF16="TIPO III",'BASE LIQUIDACION'!$C$5,'BASE LIQUIDACION'!$C$7)))) -> 65960.474 | AM16: =IF(T16="SOPORTE_TELEFÓNICO",'BASE LIQUIDACION'!$B$10,(AH16*AL16+AI16*'BASE LIQUIDACION'!$B$12+AJ16*'BASE LIQUIDACION'!$B$11+INCIDENTES!AK16*'BASE LIQUIDACION'!$B$13)) -> 65960.474
A17: CALI | B17: =VLOOKUP(A17,'CENTRO DE COSTOS'!A:D,4,FALSE) -> DIEGO FERNANDO HENAO CARDONA | C17: =VLOOKUP(A17,'CENTRO DE COSTOS'!A:D,2,FALSE) -> 0004-0003 | D17: 19110 | E17: 2245754 | F17: FO-25-1031198 | G17: 45811.51 | H17: 45812.713 | I17: CAUCA | J17: BUENOS AIRES | K17: DISTRICOL VARIEDADES Y ESTILOS | L17: 44111 | M17: INCIDENTE | N17: REDEBAN | O17: AGREGADOR | Q17: CERRADO | R17: 3-06 SE ESCALA PARA VISITA. LLAMAR ANTES DE VISITAR Y CONFIRMAR DATOS, DIRECCION Y SOLICITUD 0 04-06 SE HABLA CON EL CLIENTE QUIEN INDICA QUE EL EQUIPO EL DIA DE HOY A OPERADO CON NORMALIDAD, A TRANZADO SIN PROBLEMA, EL CLIENTE INDICA QUE DE UN MOMENTO A OTRO SE QUEDA SIN CONEXION, SE REALIZA VALIDACIONES EL CLIENTE INDICA QUE EL DATAFONO SIEMPRE QUEDA CON LA RED ACTIVA PERO NO LE PERMITE TRANZAR, SE LE INDICA REVISAR EL SERVICIO DE INTERNET PUES PUEDE ESTA PRESENTANDO CAIDAS Y ESO AFECTA EL FUNCIONAMIENTO DEL EQUIPO, | S17: HENAO CARDONA DIEGO FERNANDO | T17: SOPORTE_TELEFÓNICO | U17: 0 | V17: NO | W17: USUARIO | X17: COMUNICACION | Y17: CANAL DEL COMERCIO | Z17: No | AA17: 0 | AB17: 0 | AC17: 0 | AD17: 0 | AE17: 0 | AF17: =VLOOKUP(D17,TIPOLOGIAS!A:H,6,0) -> TIPO II | AG17: =VLOOKUP(D17,TIPOLOGIAS!A:H,5,0) -> TERRESTRE | AH17: 0 | AI17: 0 | AJ17: 0 | AK17: 0 | AL17: =IF(T17="SOPORTE_TELEFÓNICO",'BASE LIQUIDACION'!$B$10,IF(AF17="TIPO I",'BASE LIQUIDACION'!$C$3,IF(AF17="TIPO II",'BASE LIQUIDACION'!$C$4,IF(AF17="TIPO III",'BASE LIQUIDACION'!$C$5,'BASE LIQUIDACION'!$C$7)))) -> 37904.654 | AM17: =IF(T17="SOPORTE_TELEFÓNICO",'BASE LIQUIDACION'!$B$10,(AH17*AL17+AI17*'BASE LIQUIDACION'!$B$12+AJ17*'BASE LIQUIDACION'!$B$11+INCIDENTES!AK17*'BASE LIQUIDACION'!$B$13)) -> 37904.654
A18: CUCUTA | B18: =VLOOKUP(A18,'CENTRO DE COSTOS'!A:D,4,FALSE) -> MIGUEL JULIÁN HERNÁNDEZ GUARÍN | C18: =VLOOKUP(A18,'CENTRO DE COSTOS'!A:D,2,FALSE) -> 0004-0008 | D18: 54874 | E18: 2251383 | F18: FO-25-1038911 | G18: 45812.408 | H18: 45812.786 | I18: NORTE DE SANTANDER | J18: VILLA DEL ROSARIO | K18: PTM VILLA DEL ROSARIO PLASTIC | L18: 75547 | M18: INCIDENTE | N18: REDEBAN | O18: AGREGADOR | Q18: CERRADO | R18: 4-06 SE ESCALA PARA VISITA. LLAMAR ANTES DE VISITAR Y CONFIRMAR DATOS, DIRECCION Y SOLICITUD 0 04-06 SE VISITA COMERCIO Y SE REALIZA MANTENIMIENTO PREVENTIVO AL DATAFONO, SE ENCUENTRA BATERÍA DESAJUSTADA, SE VERIFICAN PARÁMETROS, SE REALIZAN PRUEBAS DE IMPRESIÓN CONSTANTES SE VERIFICA CON EL CLIENTE QUE EL EQUIPO QUEDÓ FUNCIONANDO OK, CIERRES Y PRUEBAS OK. | S18: TORRES MANTILLA JOSE DANIEL | T18: VISITA_TÉCNICA | U18: SX00J104 - LN00U394 | V18: NO | W18: USUARIO | X18: MANTENIMIENTO | Y18: MANTENIMIENTO GENERAL | Z18: No | AA18: 0 | AB18: 0 | AC18: 0 | AD18: 0 | AE18: 0 | AF18: =VLOOKUP(D18,TIPOLOGIAS!A:H,6,0) -> TIPO I | AG18: =VLOOKUP(D18,TIPOLOGIAS!A:H,5,0) -> TERRESTRE | AH18: 1 | AI18: 0 | AJ18: 0 | AK18: 0 | AL18: =IF(T18="SOPORTE_TELEFÓNICO",'BASE LIQUIDACION'!$B$10,IF(AF18="TIPO I",'BASE LIQUIDACION'!$C$3,IF(AF18="TIPO II",'BASE LIQUIDACION'!$C$4,IF(AF18="TIPO III",'BASE LIQUIDACION'!$C$5,'BASE LIQUIDACION'!$C$7)))) -> 65960.474 | AM18: =IF(T18="SOPORTE_TELEFÓNICO",'BASE LIQUIDACION'!$B$10,(AH18*AL18+AI18*'BASE LIQUIDACION'!$B$12+AJ18*'BASE LIQUIDACION'!$B$11+INCIDENTES!AK18*'BASE LIQUIDACION'!$B$13)) -> 65960.474
A19: VALLEDUPAR | B19: =VLOOKUP(A19,'CENTRO DE COSTOS'!A:D,4,FALSE) -> JOSE MAURICIO HERNANDEZ ROJAS | C19: =VLOOKUP(A19,'CENTRO DE COSTOS'!A:D,2,FALSE) -> 0004-0001 | D19: 20001 | E19: 2250781 | F19: FO-25-1037765 | G19: 45812.375 | H19: 45813.356 | I19: CESAR | J19: VALLEDUPAR | K19: NUEVA ESPERANZA 2 | L19: 68355 | M19: INCIDENTE | N19: REDEBAN | O19: CB UNO A UNO | Q19: CERRADO | R19: 4-06 SE ESCALA PARA VISITA. LLAMAR ANTES DE VISITAR Y CONFIRMAR DATOS, DIRECCION Y SOLICITUD 0 05-06 SE REALIZA VISITÁ POR SOLICITUD DE CLIENTE LA CUAL NOS INDICA QUE EL EQUIPO NO LE PERMITE REALIZAR CIERRE LE ALARECE CLAVE INCORRECTA, SE LLEGA A SITIO Y SE REALIZAN CONFIGURACIÓN SE CLAVE SUPERVISOR QUEDANDO OPERATIVO PRUEBAS OK CIERRE EXITOSO | S19: MAESTRE MENGUAL EDGAR ENRIQUE | T19: VISITA_TÉCNICA | U19: AALFZ677 | V19: NO | W19: USUARIO | X19: USUARIOS | Y19: USUARIOS BLOQUEADOS | Z19: No | AA19: 0 | AB19: 0 | AC19: 0 | AD19: 0 | AE19: 0 | AF19: =VLOOKUP(D19,TIPOLOGIAS!A:H,6,0) -> TIPO I | AG19: =VLOOKUP(D19,TIPOLOGIAS!A:H,5,0) -> TERRESTRE | AH19: 1 | AI19: 0 | AJ19: 0 | AK19: 0 | AL19: =IF(T19="SOPORTE_TELEFÓNICO",'BASE LIQUIDACION'!$B$10,IF(AF19="TIPO I",'BASE LIQUIDACION'!$C$3,IF(AF19="TIPO II",'BASE LIQUIDACION'!$C$4,IF(AF19="TIPO III",'BASE LIQUIDACION'!$C$5,'BASE LIQUIDACION'!$C$7)))) -> 65960.474 | AM19: =IF(T19="SOPORTE_TELEFÓNICO",'BASE LIQUIDACION'!$B$10,(AH19*AL19+AI19*'BASE LIQUIDACION'!$B$12+AJ19*'BASE LIQUIDACION'!$B$11+INCIDENTES!AK19*'BASE LIQUIDACION'!$B$13)) -> 65960.474
A20: MEDELLIN | B20: =VLOOKUP(A20,'CENTRO DE COSTOS'!A:D,4,FALSE) -> JUAN SEBASTIÁN RÍOS CASTRILLÓN | C20: =VLOOKUP(A20,'CENTRO DE COSTOS'!A:D,2,FALSE) -> 0004-0005 | D20: 5088 | E20: 2251354 | F20: FO-25-1038554 | G20: 45812.403 | H20: 45813.378 | I20: ANTIOQUIA | J20: BELLO | K20: BARRIO ARAUCARIAS 1 BELLO | L20: 56825 | M20: INCIDENTE | N20: REDEBAN | O20: CB UNO A UNO | Q20: CERRADO | R20: 4-06 SE ESCALA PARA VISITA. LLAMAR ANTES DE VISITAR Y CONFIRMAR DATOS, DIRECCION Y SOLICITUD 0 05-06 SE LLAMA AL USUARIO E INDICA QUE YA ESTÁ ACTIVO EL CB DE NUEVO , ERA UN PROBLEMA CON LA ENTIDAD DEL INTERNET | S20: MONTOYA VELEZ ANDRES FELIPE | T20: SOPORTE_TELEFÓNICO | U20: 0 | V20: NO | W20: USUARIO | X20: COMUNICACION | Y20: CONEXIONES DE COMERCIO | Z20: No | AA20: 0 | AB20: 0 | AC20: 0 | AD20: 0 | AE20: 0 | AF20: =VLOOKUP(D20,TIPOLOGIAS!A:H,6,0) -> TIPO I | AG20: =VLOOKUP(D20,TIPOLOGIAS!A:H,5,0) -> TERRESTRE | AH20: 0 | AI20: 0 | AJ20: 0 | AK20: 0 | AL20: =IF(T20="SOPORTE_TELEFÓNICO",'BASE LIQUIDACION'!$B$10,IF(AF20="TIPO I",'BASE LIQUIDACION'!$C$3,IF(AF20="TIPO II",'BASE LIQUIDACION'!$C$4,IF(AF20="TIPO III",'BASE LIQUIDACION'!$C$5,'BASE LIQUIDACION'!$C$7)))) -> 37904.654 | AM20: =IF(T20="SOPORTE_TELEFÓNICO",'BASE LIQUIDACION'!$B$10,(AH20*AL20+AI20*'BASE LIQUIDACION'!$B$12+AJ20*'BASE LIQUIDACION'!$B$11+INCIDENTES!AK20*'BASE LIQUIDACION'!$B$13)) -> 37904.654
A21: MEDELLIN | B21: =VLOOKUP(A21,'CENTRO DE COSTOS'!A:D,4,FALSE) -> JUAN SEBASTIÁN RÍOS CASTRILLÓN | C21: =VLOOKUP(A21,'CENTRO DE COSTOS'!A:D,2,FALSE) -> 0004-0005 | D21: 5360 | E21: 2253177 | F21: FO-25-1041313 | G21: 45812.525 | H21: 45813.415 | I21: ANTIOQUIA | J21: ITAGUI | K21: COMCARD ITAGUI LUCETE | L21: 31145 | M21: INCIDENTE | N21: REDEBAN | O21: AGREGADOR | Q21: CERRADO | R21: 04-06 SE REALIZA CONTACTO CON LA SEÑORA FELENI AL NUMERO 3127054614 QUIEN INDICA QUE LE CAMBIARON EL DATAFONO POR DETERIORO DEL TECLADO PERO EL NUEVO NO LEE LAS TARJETAS APENAS LA INSERTA DICE TRANSACCION CANCELADA O RECHAZO GENERAL, SE HACEN VALIDACIONES Y SE ESCALA PARA VISITA TECNICA 0 05-06 SE HACE MANTENIMIENTO DE EQUIPO Y CABLEADO TODO OK | S21: MORENO MEDINA JUAN PABLO | T21: VISITA_TÉCNICA | U21: 11113849 | V21: NO | W21: USUARIO | X21: LECTOR DE TARJETAS | Y21: OBSTRUCCION DEL LECTOR | Z21: No | AA21: 0 | AB21: 0 | AC21: 0 | AD21: 0 | AE21: 0 | AF21: =VLOOKUP(D21,TIPOLOGIAS!A:H,6,0) -> TIPO I | AG21: =VLOOKUP(D21,TIPOLOGIAS!A:H,5,0) -> TERRESTRE | AH21: 1 | AI21: 0 | AJ21: 0 | AK21: 0 | AL21: =IF(T21="SOPORTE_TELEFÓNICO",'BASE LIQUIDACION'!$B$10,IF(AF21="TIPO I",'BASE LIQUIDACION'!$C$3,IF(AF21="TIPO II",'BASE LIQUIDACION'!$C$4,IF(AF21="TIPO III",'BASE LIQUIDACION'!$C$5,'BASE LIQUIDACION'!$C$7)))) -> 65960.474 | AM21: =IF(T21="SOPORTE_TELEFÓNICO",'BASE LIQUIDACION'!$B$10,(AH21*AL21+AI21*'BASE LIQUIDACION'!$B$12+AJ21*'BASE LIQUIDACION'!$B$11+INCIDENTES!AK21*'BASE LIQUIDACION'!$B$13)) -> 65960.474
A22: CARTAGENA | B22: =VLOOKUP(A22,'CENTRO DE COSTOS'!A:D,4,FALSE) -> JOSE MAURICIO HERNANDEZ ROJAS | C22: =VLOOKUP(A22,'CENTRO DE COSTOS'!A:D,2,FALSE) -> 0004-0001 | D22: 13873 | E22: 2245774 | F22: FO-25-1031298 | G22: 45811.515 | H22: 45813.425 | I22: BOLIVAR | J22: VILLANUEVA | K22: BARRIO CL GRANDE VILLANUEVA. | L22: 74954 | M22: INCIDENTE | N22: REDEBAN | O22: CB UNO A UNO | Q22: CERRADO | R22: 3-06 SE ESCALA PARA VISITA. LLAMAR ANTES DE VISITAR Y CONFIRMAR DATOS, DIRECCION Y SOLICITUD 05/06/2025 HAY PROTESTAS EN LA SALIDA DE CARTAGENA POR TAL MOTIVO HAY TRANCÓN EN LA VÍA 05-06 SE REALIZA LIMPIEZA EN LA RANURA TENÍA SUCIO QUEDA FUNCIONANDO SIN PROBLEMAS SE HACEN PRUEBAS TODO OK | S22: CANEDO HERRERA ALEXANDER | T22: VISITA_TÉCNICA | U22: EHZZZ870 | V22: NO | W22: USUARIO | X22: LECTOR DE TARJETAS | Y22: OBSTRUCCION DEL LECTOR | Z22: No | AA22: 0 | AB22: 0 | AC22: 0 | AD22: 0 | AE22: 0 | AF22: =VLOOKUP(D22,TIPOLOGIAS!A:H,6,0) -> TIPO II | AG22: =VLOOKUP(D22,TIPOLOGIAS!A:H,5,0) -> TERRESTRE | AH22: 1 | AI22: 0 | AJ22: 0 | AK22: 0 | AL22: =IF(T22="SOPORTE_TELEFÓNICO",'BASE LIQUIDACION'!$B$10,IF(AF22="TIPO I",'BASE LIQUIDACION'!$C$3,IF(AF22="TIPO II",'BASE LIQUIDACION'!$C$4,IF(AF22="TIPO III",'BASE LIQUIDACION'!$C$5,'BASE LIQUIDACION'!$C$7)))) -> 163813.56 | AM22: =IF(T22="SOPORTE_TELEFÓNICO",'BASE LIQUIDACION'!$B$10,(AH22*AL22+AI22*'BASE LIQUIDACION'!$B$12+AJ22*'BASE LIQUIDACION'!$B$11+INCIDENTES!AK22*'BASE LIQUIDACION'!$B$13)) -> 163813.56
A23: APARTADO | B23: =VLOOKUP(A23,'CENTRO DE COSTOS'!A:D,4,FALSE) -> JUAN SEBASTIÁN RÍOS CASTRILLÓN | C23: =VLOOKUP(A23,'CENTRO DE COSTOS'!A:D,2,FALSE) -> 0004-0005 | D23: 5147 | E23: 2255738 | F23: FO-25-1043010 | G23: 45812.734 | H23: 45813.429 | I23: ANTIOQUIA | J23: CAREPA | K23: DISTRICOL ABARROTES LOS DUENDE | L23: 40705 | M23: INCIDENTE | N23: REDEBAN | O23: AGREGADOR | Q23: CERRADO | R23: 04-06 SE ESCALA PARA VISITA, LLAMAR ANTES DE VISITAR Y CONFIRMAR DATOS, DIRECCION Y SOLICITUD 0 05-06 SE HABLO CON USUARIO Y NOS INFORMA QUE EL EQUIPO AYER NO PERMITIA HACER NADA Y YA HOY AMANECIÓ BUENO. CB ESTA OPERATIVO. SE CIERRA INCIDENTE. | S23: RIOS CASTRILLON JUAN SEBASTIAN | T23: SOPORTE_TELEFÓNICO | U23: 0 | V23: NO | W23: USUARIO | X23: NO ENCIENDE | Y23: CONEXIONES DE COMERCIO | Z23: No | AA23: 0 | AB23: 0 | AC23: 0 | AD23: 0 | AE23: 0 | AF23: =VLOOKUP(D23,TIPOLOGIAS!A:H,6,0) -> TIPO I | AG23: =VLOOKUP(D23,TIPOLOGIAS!A:H,5,0) -> TERRESTRE | AH23: 0 | AI23: 0 | AJ23: 0 | AK23: 0 | AL23: =IF(T23="SOPORTE_TELEFÓNICO",'BASE LIQUIDACION'!$B$10,IF(AF23="TIPO I",'BASE LIQUIDACION'!$C$3,IF(AF23="TIPO II",'BASE LIQUIDACION'!$C$4,IF(AF23="TIPO III",'BASE LIQUIDACION'!$C$5,'BASE LIQUIDACION'!$C$7)))) -> 37904.654 | AM23: =IF(T23="SOPORTE_TELEFÓNICO",'BASE LIQUIDACION'!$B$10,(AH23*AL23+AI23*'BASE LIQUIDACION'!$B$12+AJ23*'BASE LIQUIDACION'!$B$11+INCIDENTES!AK23*'BASE LIQUIDACION'!$B$13)) -> 37904.654
A24: VILLAVICENCIO | B24: =VLOOKUP(A24,'CENTRO DE COSTOS'!A:D,4,FALSE) -> KEVIN ALEXIS CORZO BUSTOS | C24: =VLOOKUP(A24,'CENTRO DE COSTOS'!A:D,2,FALSE) -> 0004-0007 | D24: 50006 | E24: 2249363 | F24: FO-25-1035510 | G24: 45812.333 | H24: 45813.441 | I24: META | J24: ACACIAS | K24: BARRIO BACHUE ACACIAS 11 | L24: 67760 | M24: INCIDENTE | N24: REDEBAN | O24: CB UNO A UNO | Q24: CERRADO | R24: 4-06 SE ESCALA PARA VISITA. LLAMAR ANTES DE VISITAR Y CONFIRMAR DATOS, DIRECCION Y SOLICITUD 0 05-06 ME COMUNICO CON LA SEÑORA JESSICA DIAZ Y SE LE INDICA LA FORMA CORRECTA DE HACER EL CIERRE Y LA CLAVE 1526. YA LE ESTÁ FUNCIONANDO CORRECTAMENTE. CLIENTE INFORMA QUE YA SOLUCIONÓ EL INCONVENIENTE DEL CIERRE. DATAFONO LE ESTÁ FUNCIONANDO CORRECTAMENTE | S24: GARZON RUIZ LUIS MIGUEL | T24: SOPORTE_TELEFÓNICO | U24: 0 | V24: NO | W24: USUARIO | X24: USUARIOS | Y24: MALA MANIPULACION POS | Z24: No | AA24: 0 | AB24: 0 | AC24: 0 | AD24: 0 | AE24: 0 | AF24: =VLOOKUP(D24,TIPOLOGIAS!A:H,6,0) -> TIPO II | AG24: =VLOOKUP(D24,TIPOLOGIAS!A:H,5,0) -> TERRESTRE | AH24: 0 | AI24: 0 | AJ24: 0 | AK24: 0 | AL24: =IF(T24="SOPORTE_TELEFÓNICO",'BASE LIQUIDACION'!$B$10,IF(AF24="TIPO I",'BASE LIQUIDACION'!$C$3,IF(AF24="TIPO II",'BASE LIQUIDACION'!$C$4,IF(AF24="TIPO III",'BASE LIQUIDACION'!$C$5,'BASE LIQUIDACION'!$C$7)))) -> 37904.654 | AM24: =IF(T24="SOPORTE_TELEFÓNICO",'BASE LIQUIDACION'!$B$10,(AH24*AL24+AI24*'BASE LIQUIDACION'!$B$12+AJ24*'BASE LIQUIDACION'!$B$11+INCIDENTES!AK24*'BASE LIQUIDACION'!$B$13)) -> 37904.654
A25: MEDELLIN | B25: =VLOOKUP(A25,'CENTRO DE COSTOS'!A:D,4,FALSE) -> JUAN SEBASTIÁN RÍOS CASTRILLÓN | C25: =VLOOKUP(A25,'CENTRO DE COSTOS'!A:D,2,FALSE) -> 0004-0005 | D25: 5001 | E25: 2257315 | F25: FO-25-1044494 | G25: 45813.377 | H25: 45813.457 | I25: ANTIOQUIA | J25: MEDELLIN | K25: BARRIO SAN PABLO MEDELLIN 3 | L25: 76332 | M25: INCIDENTE | N25: REDEBAN | O25: CB UNO A UNO | Q25: CERRADO | R25: 05-06 SE ESCALA PARA VISITA, LLAMAR ANTES DE VISITAR Y CONFIRMAR DATOS, DIRECCION Y SOLICITUD 0 05-06 SE HACE MANTENIMIENTO DE EQUIPO Y CABLEADO TODO OK | S25: MORENO MEDINA JUAN PABLO | T25: VISITA_TÉCNICA | U25: V10OZ409 | V25: NO | W25: USUARIO | X25: MANTENIMIENTO | Y25: MANTENIMIENTO GENERAL | Z25: No | AA25: 0 | AB25: 0 | AC25: 0 | AD25: 0 | AE25: 0 | AF25: =VLOOKUP(D25,TIPOLOGIAS!A:H,6,0) -> TIPO I | AG25: =VLOOKUP(D25,TIPOLOGIAS!A:H,5,0) -> TERRESTRE | AH25: 1 | AI25: 0 | AJ25: 0 | AK25: 0 | AL25: =IF(T25="SOPORTE_TELEFÓNICO",'BASE LIQUIDACION'!$B$10,IF(AF25="TIPO I",'BASE LIQUIDACION'!$C$3,IF(AF25="TIPO II",'BASE LIQUIDACION'!$C$4,IF(AF25="TIPO III",'BASE LIQUIDACION'!$C$5,'BASE LIQUIDACION'!$C$7)))) -> 65960.474 | AM25: =IF(T25="SOPORTE_TELEFÓNICO",'BASE LIQUIDACION'!$B$10,(AH25*AL25+AI25*'BASE LIQUIDACION'!$B$12+AJ25*'BASE LIQUIDACION'!$B$11+INCIDENTES!AK25*'BASE LIQUIDACION'!$B$13)) -> 65960.474
A26: MEDELLIN | B26: =VLOOKUP(A26,'CENTRO DE COSTOS'!A:D,4,FALSE) -> JUAN SEBASTIÁN RÍOS CASTRILLÓN | C26: =VLOOKUP(A26,'CENTRO DE COSTOS'!A:D,2,FALSE) -> 0004-0005 | D26: 5001 | E26: 2253155 | F26: FO-25-1041042 | G26: 45812.516 | H26: 45813.512 | I26: ANTIOQUIA | J26: MEDELLIN | K26: COMCARD MED PAPELERIA DETALLES | L26: 27547 | M26: INCIDENTE | N26: REDEBAN | O26: AGREGADOR | Q26: CERRADO | R26: 4-06 SE ESCALA PARA VISITA. LLAMAR ANTES DE VISITAR Y CONFIRMAR DATOS, DIRECCION Y SOLICITUD 0 05-06 SE REALIZA MANTENIMIENTO AL EQUIPO | S26: CERPA SUAREZ DUVAN CAMILO | T26: VISITA_TÉCNICA | U26: 99DZZ430-HA006830 | V26: NO | W26: USUARIO | X26: MANTENIMIENTO | Y26: MANTENIMIENTO GENERAL | Z26: No | AA26: 0 | AB26: 0 | AC26: 0 | AD26: 0 | AE26: 0 | AF26: =VLOOKUP(D26,TIPOLOGIAS!A:H,6,0) -> TIPO I | AG26: =VLOOKUP(D26,TIPOLOGIAS!A:H,5,0) -> TERRESTRE | AH26: 1 | AI26: 0 | AJ26: 0 | AK26: 0 | AL26: =IF(T26="SOPORTE_TELEFÓNICO",'BASE LIQUIDACION'!$B$10,IF(AF26="TIPO I",'BASE LIQUIDACION'!$C$3,IF(AF26="TIPO II",'BASE LIQUIDACION'!$C$4,IF(AF26="TIPO III",'BASE LIQUIDACION'!$C$5,'BASE LIQUIDACION'!$C$7)))) -> 65960.474 | AM26: =IF(T26="SOPORTE_TELEFÓNICO",'BASE LIQUIDACION'!$B$10,(AH26*AL26+AI26*'BASE LIQUIDACION'!$B$12+AJ26*'BASE LIQUIDACION'!$B$11+INCIDENTES!AK26*'BASE LIQUIDACION'!$B$13)) -> 65960.474
A27: MEDELLIN | B27: =VLOOKUP(A27,'CENTRO DE COSTOS'!A:D,4,FALSE) -> JUAN SEBASTIÁN RÍOS CASTRILLÓN | C27: =VLOOKUP(A27,'CENTRO DE COSTOS'!A:D,2,FALSE) -> 0004-0005 | D27: 5088 | E27: 2240557 | F27: FO-25-1025646 | G27: 45810.49 | H27: 45813.533 | I27: ANTIOQUIA | J27: BELLO | K27: PTM BELLO GRANERO EL JULI | L27: 69093 | M27: INCIDENTE | N27: REDEBAN | O27: AGREGADOR | Q27: CERRADO | R27: 02-06 DEBIDO A FALLO, SOLICITUD DEL CLIENTE, REQUIERE CAMBIO DE DATAFONO, NO ESTA DISPONIBLE EL SOPORTE DE ACTIVOS PARA PARTE DE RBM, POR LO CUAL SE PROGRAMA ACTIVIDAD PARA DIA HABIL 03/06/2025 SEGÚN EL DAÑO SE NECESITA CAMBIO EQUIPO Y NO HAY EQUIPOS EN BODEGA LOS QUE HAY SE VAN A UTILIZAR EN APERTURAS SE APLAZA VISITA 05-06 SE REALIZÓ LIMPIEZA DE LECTOR CHIP | S27: CASTAÑEDA PALACIO CARLOS FELIPE | T27: VISITA_TÉCNICA | U27: A103Z499 A104Z891 | V27: NO | W27: USUARIO | X27: LECTOR DE TARJETAS | Y27: OBSTRUCCION DEL LECTOR | Z27: No | AA27: 0 | AB27: 0 | AC27: 0 | AD27: 0 | AE27: 0 | AF27: =VLOOKUP(D27,TIPOLOGIAS!A:H,6,0) -> TIPO I | AG27: =VLOOKUP(D27,TIPOLOGIAS!A:H,5,0) -> TERRESTRE | AH27: 1 | AI27: 0 | AJ27: 0 | AK27: 0 | AL27: =IF(T27="SOPORTE_TELEFÓNICO",'BASE LIQUIDACION'!$B$10,IF(AF27="TIPO I",'BASE LIQUIDACION'!$C$3,IF(AF27="TIPO II",'BASE LIQUIDACION'!$C$4,IF(AF27="TIPO III",'BASE LIQUIDACION'!$C$5,'BASE LIQUIDACION'!$C$7)))) -> 65960.474 | AM27: =IF(T27="SOPORTE_TELEFÓNICO",'BASE LIQUIDACION'!$B$10,(AH27*AL27+AI27*'BASE LIQUIDACION'!$B$12+AJ27*'BASE LIQUIDACION'!$B$11+INCIDENTES!AK27*'BASE LIQUIDACION'!$B$13)) -> 65960.474
A28: MEDELLIN | B28: =VLOOKUP(A28,'CENTRO DE COSTOS'!A:D,4,FALSE) -> JUAN SEBASTIÁN RÍOS CASTRILLÓN | C28: =VLOOKUP(A28,'CENTRO DE COSTOS'!A:D,2,FALSE) -> 0004-0005 | D28: 5088 | E28: 2257980 | F28: FO-25-1045165 | G28: 45813.419 | H28: 45813.548 | I28: ANTIOQUIA | J28: BELLO | K28: REVAL SUPERMERCADO OR | L28: 31253 | M28: INCIDENTE | N28: REDEBAN | O28: ROBUSTO | Q28: CERRADO | R28: 05-06 SE ESCALA PARA VISITA, LLAMAR ANTES DE VISITAR Y CONFIRMAR DATOS, DIRECCION Y SOLICITUD 0 05-06 SE REALIZÓ LIMPIEZA DE LECTOR CHIP | S28: CASTAÑEDA PALACIO CARLOS FELIPE | T28: VISITA_TÉCNICA | U28: 11113605 - 1113608 | V28: NO | W28: USUARIO | X28: LECTOR DE TARJETAS | Y28: OBSTRUCCION DEL LECTOR | Z28: No | AA28: 0 | AB28: 0 | AC28: 0 | AD28: 0 | AE28: 0 | AF28: =VLOOKUP(D28,TIPOLOGIAS!A:H,6,0) -> TIPO I | AG28: =VLOOKUP(D28,TIPOLOGIAS!A:H,5,0) -> TERRESTRE | AH28: 1 | AI28: 0 | AJ28: 0 | AK28: 0 | AL28: =IF(T28="SOPORTE_TELEFÓNICO",'BASE LIQUIDACION'!$B$10,IF(AF28="TIPO I",'BASE LIQUIDACION'!$C$3,IF(AF28="TIPO II",'BASE LIQUIDACION'!$C$4,IF(AF28="TIPO III",'BASE LIQUIDACION'!$C$5,'BASE LIQUIDACION'!$C$7)))) -> 65960.474 | AM28: =IF(T28="SOPORTE_TELEFÓNICO",'BASE LIQUIDACION'!$B$10,(AH28*AL28+AI28*'BASE LIQUIDACION'!$B$12+AJ28*'BASE LIQUIDACION'!$B$11+INCIDENTES!AK28*'BASE LIQUIDACION'!$B$13)) -> 65960.474
A29: CARTAGENA | B29: =VLOOKUP(A29,'CENTRO DE COSTOS'!A:D,4,FALSE) -> JOSE MAURICIO HERNANDEZ ROJAS | C29: =VLOOKUP(A29,'CENTRO DE COSTOS'!A:D,2,FALSE) -> 0004-0001 | D29: 13001 | E29: 2247140 | F29: FO-25-1033794 | G29: 45811.611 | H29: 45813.558 | I29: BOLIVAR | J29: CARTAGENA | K29: BARRIO AV EL CONSULADAO BRR ESCALLONVILLA CARTAGENA DE INDIAS | L29: 79072 | M29: INCIDENTE | N29: REDEBAN | O29: CB UNO A UNO | Q29: CERRADO | R29: 3-06 SE ESCALA PARA VISITA. LLAMAR ANTES DE VISITAR Y CONFIRMAR DATOS, DIRECCION Y SOLICITUD ..05-06 ACTIVIDAD PROGRAMADA PARA EL DÍA DE HOY 05-06-2025 05/06/2025 SE LLEGA AL SITIO Y NO SE ENCUENTRA LA PERSONA EN CARGADA INFORMA QUE LLEGA EN UNA HORA SE REGRESARA AL SITIO 05-06 SE VALIDA PROBLEMA DE LECTORA Y SE ENCUENTRA OPERATIVA SE DAN INDICACIONES DE COMO PODER LEER LA FACTURA CORRECTAMENTE Y TODO QUEDA OK | S29: MARTINEZ SALGUEDO ANDRES AUGUSTO | T29: VISITA_TÉCNICA | U29: SASZZ647 | V29: NO | W29: USUARIO | X29: LECTOR DE BARRAS | Y29: CAPACITACION MANIPULACION DE COMERCIO | Z29: No | AA29: 0 | AB29: 0 | AC29: 0 | AD29: 0 | AE29: 0 | AF29: =VLOOKUP(D29,TIPOLOGIAS!A:H,6,0) -> TIPO I | AG29: =VLOOKUP(D29,TIPOLOGIAS!A:H,5,0) -> TERRESTRE | AH29: 1 | AI29: 0 | AJ29: 0 | AK29: 0 | AL29: =IF(T29="SOPORTE_TELEFÓNICO",'BASE LIQUIDACION'!$B$10,IF(AF29="TIPO I",'BASE LIQUIDACION'!$C$3,IF(AF29="TIPO II",'BASE LIQUIDACION'!$C$4,IF(AF29="TIPO III",'BASE LIQUIDACION'!$C$5,'BASE LIQUIDACION'!$C$7)))) -> 65960.474 | AM29: =IF(T29="SOPORTE_TELEFÓNICO",'BASE LIQUIDACION'!$B$10,(AH29*AL29+AI29*'BASE LIQUIDACION'!$B$12+AJ29*'BASE LIQUIDACION'!$B$11+INCIDENTES!AK29*'BASE LIQUIDACION'!$B$13)) -> 65960.474
A30: CALI | B30: =VLOOKUP(A30,'CENTRO DE COSTOS'!A:D,4,FALSE) -> DIEGO FERNANDO HENAO CARDONA | C30: =VLOOKUP(A30,'CENTRO DE COSTOS'!A:D,2,FALSE) -> 0004-0003 | D30: 76001 | E30: 2257374 | F30: FO-25-1044528 | G30: 45813.385 | H30: 45813.606 | I30: VALLE DEL CAUCA | J30: CALI | K30: BARRIO COMUNEROS I CALI 1 | L30: 73730 | M30: INCIDENTE | N30: REDEBAN | O30: CB UNO A UNO | Q30: CERRADO | R30: 05-06 SE ESCALA PARA VISITA, LLAMAR ANTES DE VISITAR Y CONFIRMAR DATOS, DIRECCION Y SOLICITUD 0 05-06 SE LLAMA AL COMERCIO Y ME DICE QUE YA SE SOLUCIONO LA FALLA | S30: CUERO RUIZ JHONNY | T30: SOPORTE_TELEFÓNICO | U30: 0 | V30: NO | W30: USUARIO | X30: COMUNICACION | Y30: CONEXIONES DE COMERCIO | Z30: No | AA30: 0 | AB30: 0 | AC30: 0 | AD30: 0 | AE30: 0 | AF30: =VLOOKUP(D30,TIPOLOGIAS!A:H,6,0) -> TIPO I | AG30: =VLOOKUP(D30,TIPOLOGIAS!A:H,5,0) -> TERRESTRE | AH30: 0 | AI30: 0 | AJ30: 0 | AK30: 0 | AL30: =IF(T30="SOPORTE_TELEFÓNICO",'BASE LIQUIDACION'!$B$10,IF(AF30="TIPO I",'BASE LIQUIDACION'!$C$3,IF(AF30="TIPO II",'BASE LIQUIDACION'!$C$4,IF(AF30="TIPO III",'BASE LIQUIDACION'!$C$5,'BASE LIQUIDACION'!$C$7)))) -> 37904.654 | AM30: =IF(T30="SOPORTE_TELEFÓNICO",'BASE LIQUIDACION'!$B$10,(AH30*AL30+AI30*'BASE LIQUIDACION'!$B$12+AJ30*'BASE LIQUIDACION'!$B$11+INCIDENTES!AK30*'BASE LIQUIDACION'!$B$13)) -> 37904.654
A31: CUCUTA | B31: =VLOOKUP(A31,'CENTRO DE COSTOS'!A:D,4,FALSE) -> MIGUEL JULIÁN HERNÁNDEZ GUARÍN | C31: =VLOOKUP(A31,'CENTRO DE COSTOS'!A:D,2,FALSE) -> 0004-0008 | D31: 54001 | E31: 2259951 | F31: FO-25-1047107 | G31: 45813.558 | H31: 45813.64 | I31: NORTE DE SANTANDER | J31: CUCUTA | K31: BARRIO SAN LUIS CUCUTA 17 | L31: 58678 | M31: INCIDENTE | N31: REDEBAN | O31: CB UNO A UNO | Q31: CERRADO | R31: 05-06 SE ESCALA PARA VISITA, LLAMAR ANTES DE VISITAR Y CONFIRMAR DATOS, DIRECCION Y SOLICITUD 0 05-06 SE REALIZA VISITA AL COMERCIO Y SE ENCUENTRA DATAFONO SIN REALIZAR TRANSACCIONES DE RETIRO, SE REALIZA INCIALIZACION OK, PRUEBAS EXITOSAS | S31: MORA VEGA JEAMPIER | T31: VISITA_TÉCNICA | U31: IVZZZ993 | V31: NO | W31: USUARIO | X31: MANTENIMIENTO | Y31: MANTENIMIENTO GENERAL | Z31: No | AA31: 0 | AB31: 0 | AC31: 0 | AD31: 0 | AE31: 0 | AF31: =VLOOKUP(D31,TIPOLOGIAS!A:H,6,0) -> TIPO I | AG31: =VLOOKUP(D31,TIPOLOGIAS!A:H,5,0) -> TERRESTRE | AH31: 1 | AI31: 0 | AJ31: 0 | AK31: 0 | AL31: =IF(T31="SOPORTE_TELEFÓNICO",'BASE LIQUIDACION'!$B$10,IF(AF31="TIPO I",'BASE LIQUIDACION'!$C$3,IF(AF31="TIPO II",'BASE LIQUIDACION'!$C$4,IF(AF31="TIPO III",'BASE LIQUIDACION'!$C$5,'BASE LIQUIDACION'!$C$7)))) -> 65960.474 | AM31: =IF(T31="SOPORTE_TELEFÓNICO",'BASE LIQUIDACION'!$B$10,(AH31*AL31+AI31*'BASE LIQUIDACION'!$B$12+AJ31*'BASE LIQUIDACION'!$B$11+INCIDENTES!AK31*'BASE LIQUIDACION'!$B$13)) -> 65960.474
A32: BUCARAMANGA | B32: =VLOOKUP(A32,'CENTRO DE COSTOS'!A:D,4,FALSE) -> MIGUEL JULIÁN HERNÁNDEZ GUARÍN | C32: =VLOOKUP(A32,'CENTRO DE COSTOS'!A:D,2,FALSE) -> 0004-0008 | D32: 68406 | E32: 2257993 | F32: FO-25-1045161 | G32: 45813.422 | H32: 45813.642 | I32: SANTANDER | J32: LEBRIJA | K32: BARRIO CENTRO LEBRIJA 3 | L32: 39413 | M32: INCIDENTE | N32: REDEBAN | O32: CB UNO A UNO | Q32: CERRADO | R32: 05-06 SE ESCALA PARA VISITA, LLAMAR ANTES DE VISITAR Y CONFIRMAR DATOS, DIRECCION Y SOLICITUD 0 05-06 SE REALIZA VISITA AL COMERCIO CB, SE VALIDA Y SE ENCUENTRA QUE EL DATÁFONO PERDIÓ LA CONFIGURACIÓN DE LOS USUARIOS PARA EL CORRESPONSAL Y CLAVES PARA REALIZAR CIERRE Y DEMÁS SE REALIZA EL FORMATEO DEL DATÁFONO SE DESCARGA SISTEMA OPERATIVO NUEVO Y VERSIÓN 9.90 SE HACEN LAS RESPECTIVAS CONFIGURACIONES PRUEBAS OKAY | S32: GONZALEZ ESTUPIÑAN YEISON WALTER ANTONIO | T32: VISITA_TÉCNICA | U32: AA08Z557 | V32: NO | W32: USUARIO | X32: USUARIOS | Y32: MALA MANIPULACION POS | Z32: No | AA32: 0 | AB32: 0 | AC32: 0 | AD32: 0 | AE32: 0 | AF32: =VLOOKUP(D32,TIPOLOGIAS!A:H,6,0) -> TIPO II | AG32: =VLOOKUP(D32,TIPOLOGIAS!A:H,5,0) -> TERRESTRE | AH32: 1 | AI32: 0 | AJ32: 0 | AK32: 0 | AL32: =IF(T32="SOPORTE_TELEFÓNICO",'BASE LIQUIDACION'!$B$10,IF(AF32="TIPO I",'BASE LIQUIDACION'!$C$3,IF(AF32="TIPO II",'BASE LIQUIDACION'!$C$4,IF(AF32="TIPO III",'BASE LIQUIDACION'!$C$5,'BASE LIQUIDACION'!$C$7)))) -> 163813.56 | AM32: =IF(T32="SOPORTE_TELEFÓNICO",'BASE LIQUIDACION'!$B$10,(AH32*AL32+AI32*'BASE LIQUIDACION'!$B$12+AJ32*'BASE LIQUIDACION'!$B$11+INCIDENTES!AK32*'BASE LIQUIDACION'!$B$13)) -> 163813.56
A33: MEDELLIN | B33: =VLOOKUP(A33,'CENTRO DE COSTOS'!A:D,4,FALSE) -> JUAN SEBASTIÁN RÍOS CASTRILLÓN | C33: =VLOOKUP(A33,'CENTRO DE COSTOS'!A:D,2,FALSE) -> 0004-0005 | D33: 27361 | E33: 2242568 | F33: FO-25-1028617 | G33: 45811.37 | H33: 45814.33 | I33: CHOCO | J33: ISTMINA | K33: BARRIO CUBIS ISTMINA CHOCO 2 | L33: 33856 | M33: INCIDENTE | N33: REDEBAN | O33: CB UNO A UNO | Q33: CERRADO | R33: 03-06 SE REALIZA CONTACTO CON LA SEÑORA JOHANA AL NUMERO 3182063717 QUIEN INDICA QUE EL DATAFONO LE ARROJA ERROR TCP IP CABLE DE RED DESCONECTADO, SE HACEN VALIDACIONES Y SE ESCALA PARA VISITA TECNICA 0 06-06 SE LLEGABA SITIO, SE REALIZA MANTENIMIENTO Y SE EVIDENCIA FALLA EN CANAL DE COMERCIO SE REALIZAN ADECUADOS Y EL CB QUEDA OPERATIVO | S33: ROBLEDO DIAZ ANDRES FELIPE | T33: VISITA_TÉCNICA | U33: 1MZZZ115 | V33: NO | W33: USUARIO | X33: COMUNICACION | Y33: CANAL DEL COMERCIO | Z33: No | AA33: 0 | AB33: 0 | AC33: 0 | AD33: 0 | AE33: 0 | AF33: =VLOOKUP(D33,TIPOLOGIAS!A:H,6,0) -> TIPO IV ESPECIAL | AG33: =VLOOKUP(D33,TIPOLOGIAS!A:H,5,0) -> AEREO | AH33: 1 | AI33: 0 | AJ33: 0 | AK33: 0 | AL33: =IF(T33="SOPORTE_TELEFÓNICO",'BASE LIQUIDACION'!$B$10,IF(AF33="TIPO I",'BASE LIQUIDACION'!$C$3,IF(AF33="TIPO II",'BASE LIQUIDACION'!$C$4,IF(AF33="TIPO III",'BASE LIQUIDACION'!$C$5,'BASE LIQUIDACION'!$C$7)))) -> 479589.74 | AM33: =IF(T33="SOPORTE_TELEFÓNICO",'BASE LIQUIDACION'!$B$10,(AH33*AL33+AI33*'BASE LIQUIDACION'!$B$12+AJ33*'BASE LIQUIDACION'!$B$11+INCIDENTES!AK33*'BASE LIQUIDACION'!$B$13)) -> 479589.74
A34: CUCUTA | B34: =VLOOKUP(A34,'CENTRO DE COSTOS'!A:D,4,FALSE) -> MIGUEL JULIÁN HERNÁNDEZ GUARÍN | C34: =VLOOKUP(A34,'CENTRO DE COSTOS'!A:D,2,FALSE) -> 0004-0008 | D34: 54405 | E34: 2258236 | F34: FO-25-1045385 | G34: 45813.428 | H34: 45814.348 | I34: NORTE DE SANTANDER | J34: LOS PATIOS | K34: BARRIO LLANO GRANDE LOS PATIOS 3 | L34: 76013 | M34: INCIDENTE | N34: REDEBAN | O34: CB UNO A UNO | Q34: CERRADO | R34: 05-06 SE ESCALA PARA VISITA, LLAMAR ANTES DE VISITAR Y CONFIRMAR DATOS, DIRECCION Y SOLICITUD 0 05-06 SE CONTACTA TELEFÓNICAMENTE A LA SEÑORA CARMEN MONTERREY, SE REALIZA CAMBIO DE CLAVE DE SUPERVISOR. CLIENTE TIENE CONOCIMIENTO PREVIO DE LA CLAVE DE ADMINISTRADOR PARA REALIZAR EL CAMBIO. SE CONFIRMA SERVICIO OPERATIVO POR PARTE DEL CLIENTE. | S34: PACHECO BUITRAGO JAVIER ALONSO | T34: SOPORTE_TELEFÓNICO | U34: 0 | V34: NO | W34: USUARIO | X34: USUARIOS | Y34: USUARIOS BLOQUEADOS | Z34: No | AA34: 0 | AB34: 0 | AC34: 0 | AD34: 0 | AE34: 0 | AF34: =VLOOKUP(D34,TIPOLOGIAS!A:H,6,0) -> TIPO I | AG34: =VLOOKUP(D34,TIPOLOGIAS!A:H,5,0) -> TERRESTRE | AH34: 0 | AI34: 0 | AJ34: 0 | AK34: 0 | AL34: =IF(T34="SOPORTE_TELEFÓNICO",'BASE LIQUIDACION'!$B$10,IF(AF34="TIPO I",'BASE LIQUIDACION'!$C$3,IF(AF34="TIPO II",'BASE LIQUIDACION'!$C$4,IF(AF34="TIPO III",'BASE LIQUIDACION'!$C$5,'BASE LIQUIDACION'!$C$7)))) -> 37904.654 | AM34: =IF(T34="SOPORTE_TELEFÓNICO",'BASE LIQUIDACION'!$B$10,(AH34*AL34+AI34*'BASE LIQUIDACION'!$B$12+AJ34*'BASE LIQUIDACION'!$B$11+INCIDENTES!AK34*'BASE LIQUIDACION'!$B$13)) -> 37904.654
A35: BOGOTA | B35: =VLOOKUP(A35,'CENTRO DE COSTOS'!A:D,4,FALSE) -> WILLIAM ASDRUBAL ROZO ROZO | C35: =VLOOKUP(A35,'CENTRO DE COSTOS'!A:D,2,FALSE) -> 0004-0004 | D35: 11001 | E35: 2262247 | F35: FO-25-1050909 | G35: 45814.333 | H35: 45814.645 | I35: CUNDINAMARCA | J35: BOGOTA | K35: PTM REDES JC | L35: 53571 | M35: INCIDENTE | N35: REDEBAN | O35: AGREGADOR | Q35: CERRADO | R35: 06-06 SE ESCALA PARA VISITA, LLAMAR ANTES DE VISITAR Y CONFIRMAR DATOS, DIRECCION Y SOLICITUD 0 06-06 DURANTE LA VISITA TECNICA PARA ATENDER INCIDENTE REPORTADO POR CORRESPONSAL BANCARIO, CORRESPONSAL NOS INDICA QUE EL DAÑO YA FUE SOLUCIONADO, SE HACEN PRUEBAS CONFIRMANDO QUE SERVICIO SE ENCUENTRA FUNCIONAL Y OPERATIVO A CONFORMIDAD DEL CB SIN NOVEDAD EN EL INCIDENTE SALDO OK | S35: GALEANO SORIANO JUAN DAVID | T35: VISITA_TÉCNICA | U35: TR0VZ648-TR0FZ326 | V35: NO | W35: USUARIO | X35: MANTENIMIENTO | Y35: MANTENIMIENTO GENERAL | Z35: No | AA35: 0 | AB35: 0 | AC35: 0 | AD35: 0 | AE35: 0 | AF35: =VLOOKUP(D35,TIPOLOGIAS!A:H,6,0) -> TIPO I | AG35: =VLOOKUP(D35,TIPOLOGIAS!A:H,5,0) -> TERRESTRE | AH35: 1 | AI35: 0 | AJ35: 0 | AK35: 0 | AL35: =IF(T35="SOPORTE_TELEFÓNICO",'BASE LIQUIDACION'!$B$10,IF(AF35="TIPO I",'BASE LIQUIDACION'!$C$3,IF(AF35="TIPO II",'BASE LIQUIDACION'!$C$4,IF(AF35="TIPO III",'BASE LIQUIDACION'!$C$5,'BASE LIQUIDACION'!$C$7)))) -> 65960.474 | AM35: =IF(T35="SOPORTE_TELEFÓNICO",'BASE LIQUIDACION'!$B$10,(AH35*AL35+AI35*'BASE LIQUIDACION'!$B$12+AJ35*'BASE LIQUIDACION'!$B$11+INCIDENTES!AK35*'BASE LIQUIDACION'!$B$13)) -> 65960.474
A36: PEREIRA | B36: =VLOOKUP(A36,'CENTRO DE COSTOS'!A:D,4,FALSE) -> DIEGO FERNANDO HENAO CARDONA | C36: =VLOOKUP(A36,'CENTRO DE COSTOS'!A:D,2,FALSE) -> 0004-0002 | D36: 63001 | E36: 2262511 | F36: FO-25-1050897 | G36: 45814.333 | H36: 45815.434 | I36: QUINDIO | J36: ARMENIA | K36: BARRIO LAS COLINAS ARMENIA | L36: 67674 | M36: INCIDENTE | N36: REDEBAN | O36: CB UNO A UNO | Q36: CERRADO | R36: 06-06 SE ESCALA PARA VISITA, LLAMAR ANTES DE VISITAR Y CONFIRMAR DATOS, DIRECCION Y SOLICITUD 0 07-06 SE VISITA COMERCIO, NO SE PERMITE EL INGRESO A TÉCNICO PARA REALIZAR LA VERIFICACIÓN FÍSICA Y LECTURA DE PLACA DE DATAFONO CLIENTE INDICA QUE YA ESTÁ FUNCIONANDO EL DATAFONO Y QUE EL DÍA DE AYER EL PASO EL REPORTE DE QUE YA ESTABA FUNCIONANDO. | S36: SANCHEZ SOLORZANO JUAN SEBASTIAN | T36: VISITA_TÉCNICA | U36: AAQ0N448 | V36: NO | W36: USUARIO | X36: MANTENIMIENTO | Y36: MANTENIMIENTO GENERAL | Z36: No | AA36: 0 | AB36: 0 | AC36: 0 | AD36: 0 | AE36: 0 | AF36: =VLOOKUP(D36,TIPOLOGIAS!A:H,6,0) -> TIPO II | AG36: =VLOOKUP(D36,TIPOLOGIAS!A:H,5,0) -> TERRESTRE | AH36: 1 | AI36: 0 | AJ36: 0 | AK36: 0 | AL36: =IF(T36="SOPORTE_TELEFÓNICO",'BASE LIQUIDACION'!$B$10,IF(AF36="TIPO I",'BASE LIQUIDACION'!$C$3,IF(AF36="TIPO II",'BASE LIQUIDACION'!$C$4,IF(AF36="TIPO III",'BASE LIQUIDACION'!$C$5,'BASE LIQUIDACION'!$C$7)))) -> 163813.56 | AM36: =IF(T36="SOPORTE_TELEFÓNICO",'BASE LIQUIDACION'!$B$10,(AH36*AL36+AI36*'BASE LIQUIDACION'!$B$12+AJ36*'BASE LIQUIDACION'!$B$11+INCIDENTES!AK36*'BASE LIQUIDACION'!$B$13)) -> 163813.56
A37: BOGOTA | B37: =VLOOKUP(A37,'CENTRO DE COSTOS'!A:D,4,FALSE) -> WILLIAM ASDRUBAL ROZO ROZO | C37: =VLOOKUP(A37,'CENTRO DE COSTOS'!A:D,2,FALSE) -> 0004-0004 | D37: 11001 | E37: 2265056 | F37: FO-25-1053149 | G37: 45814.476 | H37: 45815.459 | I37: CUNDINAMARCA | J37: BOGOTA | K37: BARRIO SAN CIPRIANO BOGOTA 4 | L37: 79607 | M37: INCIDENTE | N37: REDEBAN | O37: CB UNO A UNO | Q37: CERRADO | R37: 06-06 SE ESCALA PARA VISITA, LLAMAR ANTES DE VISITAR Y CONFIRMAR DATOS, DIRECCION Y SOLICITUD 0 07-06 SE VISITA CORRESPONSAL BANCARIO POR REUBICACIÓN DE CABLE DE RED YA QUE EL CABLE EXISTENTE ESTABA MAL UBICADO Y HACIA QUE LA GENTE SE TRIPEZAEA SE PROCEDE A GENERAR CAMBIO DE CABLE INSTALANDO UN NUEVO CABLE DE 8 MTRS A SOLICITUD DE CLIENTE , SE PROCEDE A INSTALAR Y SE REALIZAN TRANSACCIONES DE PRUEBA OK,SE DEJA CB OPERANDO SIN NOVEDAD | S37: ROMERO ROJAS BREIDY JHOHAN | T37: VISITA_TÉCNICA | U37: SXUZZ133 | V37: SI | W37: USUARIO | X37: COMUNICACION | Y37: CONEXIONES DE COMERCIO | Z37: No | AA37: 0 | AB37: 0 | AC37: 0 | AD37: 0 | AE37: Cable de red | AF37: =VLOOKUP(D37,TIPOLOGIAS!A:H,6,0) -> TIPO I | AG37: =VLOOKUP(D37,TIPOLOGIAS!A:H,5,0) -> TERRESTRE | AH37: 1 | AI37: 8 | AJ37: 0 | AK37: 0 | AL37: =IF(T37="SOPORTE_TELEFÓNICO",'BASE LIQUIDACION'!$B$10,IF(AF37="TIPO I",'BASE LIQUIDACION'!$C$3,IF(AF37="TIPO II",'BASE LIQUIDACION'!$C$4,IF(AF37="TIPO III",'BASE LIQUIDACION'!$C$5,'BASE LIQUIDACION'!$C$7)))) -> 65960.474 | AM37: =IF(T37="SOPORTE_TELEFÓNICO",'BASE LIQUIDACION'!$B$10,(AH37*AL37+AI37*'BASE LIQUIDACION'!$B$12+AJ37*'BASE LIQUIDACION'!$B$11+INCIDENTES!AK37*'BASE LIQUIDACION'!$B$13)) -> 195838.04
A38: CALI | B38: =VLOOKUP(A38,'CENTRO DE COSTOS'!A:D,4,FALSE) -> DIEGO FERNANDO HENAO CARDONA | C38: =VLOOKUP(A38,'CENTRO DE COSTOS'!A:D,2,FALSE) -> 0004-0003 | D38: 76001 | E38: 2268464 | F38: FO-25-1057042 | G38: 45815.428 | H38: 45815.53 | I38: VALLE DEL CAUCA | J38: CALI | K38: PTM CALI ALL NET CENTRO DE SOL | L38: 45396 | M38: INCIDENTE | N38: REDEBAN | O38: AGREGADOR | Q38: CERRADO | R38: 07-06 SE ESCALA PARA VISITA, LLAMAR ANTES DE VISITAR Y CONFIRMAR DATOS, DIRECCION Y SOLICITUD 0 07-06 CLIENTE CAMBIO CONFIGURACIÓN DEL EQUIPO POR ESO NO FUNCIONABA SE VUELVE A CONFIGURAR Y FUNCIONA CORRECTAMENTE | S38: CUERO RUIZ JHONNY | T38: VISITA_TÉCNICA | U38: AC0MZ730 | V38: NO | W38: USUARIO | X38: MANTENIMIENTO | Y38: MANTENIMIENTO GENERAL | Z38: No | AA38: 0 | AB38: 0 | AC38: 0 | AD38: 0 | AE38: 0 | AF38: =VLOOKUP(D38,TIPOLOGIAS!A:H,6,0) -> TIPO I | AG38: =VLOOKUP(D38,TIPOLOGIAS!A:H,5,0) -> TERRESTRE | AH38: 1 | AI38: 0 | AJ38: 0 | AK38: 0 | AL38: =IF(T38="SOPORTE_TELEFÓNICO",'BASE LIQUIDACION'!$B$10,IF(AF38="TIPO I",'BASE LIQUIDACION'!$C$3,IF(AF38="TIPO II",'BASE LIQUIDACION'!$C$4,IF(AF38="TIPO III",'BASE LIQUIDACION'!$C$5,'BASE LIQUIDACION'!$C$7)))) -> 65960.474 | AM38: =IF(T38="SOPORTE_TELEFÓNICO",'BASE LIQUIDACION'!$B$10,(AH38*AL38+AI38*'BASE LIQUIDACION'!$B$12+AJ38*'BASE LIQUIDACION'!$B$11+INCIDENTES!AK38*'BASE LIQUIDACION'!$B$13)) -> 65960.474
A39: MANIZALES | B39: =VLOOKUP(A39,'CENTRO DE COSTOS'!A:D,4,FALSE) -> DIEGO FERNANDO HENAO CARDONA | C39: =VLOOKUP(A39,'CENTRO DE COSTOS'!A:D,2,FALSE) -> 0004-0002 | D39: 17001 | E39: 2268488 | F39: FO-25-1057348 | G39: 45815.444 | H39: 45815.51 | I39: CALDAS | J39: MANIZALES | K39: BARRIO COLINAS MANIZALES | L39: 75659 | M39: INCIDENTE | N39: REDEBAN | O39: CB UNO A UNO | Q39: CERRADO | R39: 07-06 SE ESCALA PARA VISITA, LLAMAR ANTES DE VISITAR Y CONFIRMAR DATOS, DIRECCION Y SOLICITUD 0 07-06 SE REALIZA VALIDACION CON EL CLIENTE, PERO SE ENCUENTRA QUE EL CLIENTE ESTABA REALIZANDO EL CIERRE DEMANERA INCORRECTA, A TRAVES DEL MODULO DE COMERCIO Y EL DATAOFNO NO ES MIXTO, SE LE EXPLICA CORRECTAMENTE LA UBICACION DE LA OPCION DE CIERRE Y EL PROCESO CORRECTO Y EL CLIENTE LO REALIZA SON ONCONVENIENTE | S39: HENAO CARDONA DIEGO FERNANDO | T39: SOPORTE_TELEFÓNICO | U39: 0 | V39: NO | W39: USUARIO | X39: CIERRE | Y39: COMERCIO NO REALIZA CIERRE | Z39: No | AA39: 0 | AB39: 0 | AC39: 0 | AD39: 0 | AE39: 0 | AF39: =VLOOKUP(D39,TIPOLOGIAS!A:H,6,0) -> TIPO I | AG39: =VLOOKUP(D39,TIPOLOGIAS!A:H,5,0) -> TERRESTRE | AH39: 0 | AI39: 0 | AJ39: 0 | AK39: 0 | AL39: =IF(T39="SOPORTE_TELEFÓNICO",'BASE LIQUIDACION'!$B$10,IF(AF39="TIPO I",'BASE LIQUIDACION'!$C$3,IF(AF39="TIPO II",'BASE LIQUIDACION'!$C$4,IF(AF39="TIPO III",'BASE LIQUIDACION'!$C$5,'BASE LIQUIDACION'!$C$7)))) -> 37904.654 | AM39: =IF(T39="SOPORTE_TELEFÓNICO",'BASE LIQUIDACION'!$B$10,(AH39*AL39+AI39*'BASE LIQUIDACION'!$B$12+AJ39*'BASE LIQUIDACION'!$B$11+INCIDENTES!AK39*'BASE LIQUIDACION'!$B$13)) -> 37904.654
A40: MEDELLIN | B40: =VLOOKUP(A40,'CENTRO DE COSTOS'!A:D,4,FALSE) -> JUAN SEBASTIÁN RÍOS CASTRILLÓN | C40: =VLOOKUP(A40,'CENTRO DE COSTOS'!A:D,2,FALSE) -> 0004-0005 | D40: 5001 | E40: 2268558 | F40: FO-25-1058020 | G40: 45815.53 | H40: 45816.42 | I40: ANTIOQUIA | J40: MEDELLIN | K40: BARRIO BAYADERA MEDELLIN 2 | L40: 50309 | M40: INCIDENTE | N40: REDEBAN | O40: CB UNO A UNO | Q40: CERRADO | R40: 07-06 SE ESCALA PARA VISITA, LLAMAR ANTES DE VISITAR Y CONFIRMAR DATOS, DIRECCION Y SOLICITUD 0 08-06 SE REALIZÓ LIMPIEZA DE LECTOR CHIP | S40: CASTAÑEDA PALACIO CARLOS FELIPE | T40: VISITA_TÉCNICA | U40: XP00W434 | V40: NO | W40: USUARIO | X40: LECTOR DE TARJETAS | Y40: OBSTRUCCION DEL LECTOR | Z40: No | AA40: 0 | AB40: 0 | AC40: 0 | AD40: 0 | AE40: 0 | AF40: =VLOOKUP(D40,TIPOLOGIAS!A:H,6,0) -> TIPO I | AG40: =VLOOKUP(D40,TIPOLOGIAS!A:H,5,0) -> TERRESTRE | AH40: 1 | AI40: 0 | AJ40: 0 | AK40: 0 | AL40: =IF(T40="SOPORTE_TELEFÓNICO",'BASE LIQUIDACION'!$B$10,IF(AF40="TIPO I",'BASE LIQUIDACION'!$C$3,IF(AF40="TIPO II",'BASE LIQUIDACION'!$C$4,IF(AF40="TIPO III",'BASE LIQUIDACION'!$C$5,'BASE LIQUIDACION'!$C$7)))) -> 65960.474 | AM40: =IF(T40="SOPORTE_TELEFÓNICO",'BASE LIQUIDACION'!$B$10,(AH40*AL40+AI40*'BASE LIQUIDACION'!$B$12+AJ40*'BASE LIQUIDACION'!$B$11+INCIDENTES!AK40*'BASE LIQUIDACION'!$B$13)) -> 65960.474
A41: CUCUTA | B41: =VLOOKUP(A41,'CENTRO DE COSTOS'!A:D,4,FALSE) -> MIGUEL JULIÁN HERNÁNDEZ GUARÍN | C41: =VLOOKUP(A41,'CENTRO DE COSTOS'!A:D,2,FALSE) -> 0004-0008 | D41: 54099 | E41: 2268565 | F41: FO-25-1058289 | G41: 45815.55 | H41: 45817.49 | I41: NORTE DE SANTANDER | J41: BOCHALEMA | K41: BARRIO BOCHALEMA BOCHALEMA 1 | L41: 57278 | M41: INCIDENTE | N41: REDEBAN | O41: CB UNO A UNO | Q41: CERRADO | R41: 07-06 SE ESCALA PARA VISITA, LLAMAR ANTES DE VISITAR Y CONFIRMAR DATOS, DIRECCION Y SOLICITUD 0 09-06 SE REALIZÓ VISITA AL COMERCIO Y SE REALIZA MANTENIMIENTO AL DATAFONO, SE FORMATEA EQUIPO, SE MONTA SISTEMA OPERATIVO Y VERSIÓN, PRUEBAS EXITOSAS | S41: MORA VEGA JEAMPIER | T41: VISITA_TÉCNICA | U41: TRSZZ845 | V41: NO | W41: USUARIO | X41: MANTENIMIENTO | Y41: MANTENIMIENTO GENERAL | Z41: No | AA41: 0 | AB41: 0 | AC41: 0 | AD41: 0 | AE41: 0 | AF41: =VLOOKUP(D41,TIPOLOGIAS!A:H,6,0) -> TIPO II | AG41: =VLOOKUP(D41,TIPOLOGIAS!A:H,5,0) -> TERRESTRE | AH41: 1 | AI41: 0 | AJ41: 0 | AK41: 0 | AL41: =IF(T41="SOPORTE_TELEFÓNICO",'BASE LIQUIDACION'!$B$10,IF(AF41="TIPO I",'BASE LIQUIDACION'!$C$3,IF(AF41="TIPO II",'BASE LIQUIDACION'!$C$4,IF(AF41="TIPO III",'BASE LIQUIDACION'!$C$5,'BASE LIQUIDACION'!$C$7)))) -> 163813.56 | AM41: =IF(T41="SOPORTE_TELEFÓNICO",'BASE LIQUIDACION'!$B$10,(AH41*AL41+AI41*'BASE LIQUIDACION'!$B$12+AJ41*'BASE LIQUIDACION'!$B$11+INCIDENTES!AK41*'BASE LIQUIDACION'!$B$13)) -> 163813.56
A42: APARTADO | B42: =VLOOKUP(A42,'CENTRO DE COSTOS'!A:D,4,FALSE) -> JUAN SEBASTIÁN RÍOS CASTRILLÓN | C42: =VLOOKUP(A42,'CENTRO DE COSTOS'!A:D,2,FALSE) -> 0004-0005 | D42: 5045 | E42: 2271509 | F42: FO-25-1061535 | G42: 45817.387 | H42: 45817.493 | I42: ANTIOQUIA | J42: APARTADO | K42: DISTRICOL COMUNICACIONES KATEB | L42: 35610 | M42: INCIDENTE | N42: REDEBAN | O42: AGREGADOR | Q42: CERRADO | R42: 09-06 SE ESCALA PARA VISITA, LLAMAR ANTES DE VISITAR Y CONFIRMAR DATOS, DIRECCION Y SOLICITUD 0 09-06 CLIENTE INDICA QUE EN MOMENTO NO PUEDE ATENDER TÉCNICO DE REDEBAN POR QUE NO PARAR LA OPERACIÓN DE SU PUNTO. CLIENTE INDICA QUE VA SOLICITAR OTRA TAREA EN HORARIO ESPECÍFICO. | S42: CASTRO HENAO DANIEL ESTEBAN | T42: VISITA_TÉCNICA | U42: CLIENTE INDICA QUE EN MOMENTO NO PUEDE ATENDER TÉCNICO DE REDEBAN POR QUE NO PARAR LA OPERACIÓN DE SU PUNTO. CLIENTE INDICA QUE VA SOLICITAR OTRA TAREA EN HORARIO ESPECÍFICO. | V42: NO | W42: USUARIO | X42: MANTENIMIENTO | Y42: MANTENIMIENTO GENERAL | Z42: No | AA42: 0 | AB42: 0 | AC42: 0 | AD42: 0 | AE42: 0 | AF42: =VLOOKUP(D42,TIPOLOGIAS!A:H,6,0) -> TIPO I | AG42: =VLOOKUP(D42,TIPOLOGIAS!A:H,5,0) -> TERRESTRE | AH42: 1 | AI42: 0 | AJ42: 0 | AK42: 0 | AL42: =IF(T42="SOPORTE_TELEFÓNICO",'BASE LIQUIDACION'!$B$10,IF(AF42="TIPO I",'BASE LIQUIDACION'!$C$3,IF(AF42="TIPO II",'BASE LIQUIDACION'!$C$4,IF(AF42="TIPO III",'BASE LIQUIDACION'!$C$5,'BASE LIQUIDACION'!$C$7)))) -> 65960.474 | AM42: =IF(T42="SOPORTE_TELEFÓNICO",'BASE LIQUIDACION'!$B$10,(AH42*AL42+AI42*'BASE LIQUIDACION'!$B$12+AJ42*'BASE LIQUIDACION'!$B$11+INCIDENTES!AK42*'BASE LIQUIDACION'!$B$13)) -> 65960.474
A43: BOGOTA | B43: =VLOOKUP(A43,'CENTRO DE COSTOS'!A:D,4,FALSE) -> WILLIAM ASDRUBAL ROZO ROZO | C43: =VLOOKUP(A43,'CENTRO DE COSTOS'!A:D,2,FALSE) -> 0004-0004 | D43: 11001 | E43: 2268418 | F43: FO-25-1056793 | G43: 45815.401 | H43: 45817.542 | I43: CUNDINAMARCA | J43: BOGOTA | K43: BARRIO LAS FERIAS BOGOTA 3 | L43: 49448 | M43: INCIDENTE | N43: REDEBAN | O43: CB UNO A UNO | Q43: CERRADO | R43: 07-06 SE ESCALA PARA VISITA, LLAMAR ANTES DE VISITAR Y CONFIRMAR DATOS, DIRECCION Y SOLICITUD 07/06/2025 SE REALIZA COMUNICACIÓN A LA LÍNEA 3163297345 DONDE CLIENTE CONFIRMA FALLA DE CONEXIÓN, NO HAY SOPORTE DE RBM PARA VISITAR, SE PROGRAMA PARA LA PRÓXIMA SEMANA. 09-06 SE REALIZA VISITA A CB PARA ATENDER INCIDENTE SE REALIZA REPORTE CON REDEBAN SOBRE FALLA RECHAZO GENERAL,SE REALIZAN PRUEBAS OK | S43: GALINDO ROJAS LUIS FELIPE | T43: VISITA_TÉCNICA | U43: AD00P298 | V43: NO | W43: ENTIDAD | X43: ERROR DE TRANSACCIONES | Y43: TRANSACCION NO PERMITIDA | Z43: No | AA43: 0 | AB43: 0 | AC43: 0 | AD43: 0 | AE43: 0 | AF43: =VLOOKUP(D43,TIPOLOGIAS!A:H,6,0) -> TIPO I | AG43: =VLOOKUP(D43,TIPOLOGIAS!A:H,5,0) -> TERRESTRE | AH43: 1 | AI43: 0 | AJ43: 0 | AK43: 0 | AL43: =IF(T43="SOPORTE_TELEFÓNICO",'BASE LIQUIDACION'!$B$10,IF(AF43="TIPO I",'BASE LIQUIDACION'!$C$3,IF(AF43="TIPO II",'BASE LIQUIDACION'!$C$4,IF(AF43="TIPO III",'BASE LIQUIDACION'!$C$5,'BASE LIQUIDACION'!$C$7)))) -> 65960.474 | AM43: =IF(T43="SOPORTE_TELEFÓNICO",'BASE LIQUIDACION'!$B$10,(AH43*AL43+AI43*'BASE LIQUIDACION'!$B$12+AJ43*'BASE LIQUIDACION'!$B$11+INCIDENTES!AK43*'BASE LIQUIDACION'!$B$13)) -> 65960.474
A44: APARTADO | B44: =VLOOKUP(A44,'CENTRO DE COSTOS'!A:D,4,FALSE) -> JUAN SEBASTIÁN RÍOS CASTRILLÓN | C44: =VLOOKUP(A44,'CENTRO DE COSTOS'!A:D,2,FALSE) -> 0004-0005 | D44: 5045 | E44: 2268612 | F44: FO-25-1057440 | G44: 45815.46 | H44: 45817.546 | I44: ANTIOQUIA | J44: APARTADO | K44: DISTRICOL MISCELANEA ARTEMISA | L44: 44405 | M44: INCIDENTE | N44: REDEBAN | O44: AGREGADOR | Q44: CERRADO | R44: 07-06 SE ESCALA PARA VISITA, LLAMAR ANTES DE VISITAR Y CONFIRMAR DATOS, DIRECCION Y SOLICITUD 07/06/2025 SEGÚN DESCRIPCIÓN DE INCIDENTE EN PUNTO ES NECESARIO CAMBIO DE PLACA. POR HORA DE CREACIÓN DE ACTIVIDAD NO SE LOGRA VISITAR SITIO TIPO II PARA SOLUCIÓN ANTES DE VENCIMIENTO, VISITA SE REALIZARÁ EN DÍA HÁBIL. 09-06 SE VERIFICA DATAFONO PERO NO SE ENCUENTRA ANOMALÍA, SE REALIZA PRUEBA. | S44: CASTRO HENAO DANIEL ESTEBAN | T44: VISITA_TÉCNICA | U44: AB19Z210 | V44: NO | W44: USUARIO | X44: CIERRE | Y44: COMERCIO NO REALIZA CIERRE | Z44: No | AA44: 0 | AB44: 0 | AC44: 0 | AD44: 0 | AE44: 0 | AF44: =VLOOKUP(D44,TIPOLOGIAS!A:H,6,0) -> TIPO I | AG44: =VLOOKUP(D44,TIPOLOGIAS!A:H,5,0) -> TERRESTRE | AH44: 1 | AI44: 0 | AJ44: 0 | AK44: 0 | AL44: =IF(T44="SOPORTE_TELEFÓNICO",'BASE LIQUIDACION'!$B$10,IF(AF44="TIPO I",'BASE LIQUIDACION'!$C$3,IF(AF44="TIPO II",'BASE LIQUIDACION'!$C$4,IF(AF44="TIPO III",'BASE LIQUIDACION'!$C$5,'BASE LIQUIDACION'!$C$7)))) -> 65960.474 | AM44: =IF(T44="SOPORTE_TELEFÓNICO",'BASE LIQUIDACION'!$B$10,(AH44*AL44+AI44*'BASE LIQUIDACION'!$B$12+AJ44*'BASE LIQUIDACION'!$B$11+INCIDENTES!AK44*'BASE LIQUIDACION'!$B$13)) -> 65960.474
A45: MEDELLIN | B45: =VLOOKUP(A45,'CENTRO DE COSTOS'!A:D,4,FALSE) -> JUAN SEBASTIÁN RÍOS CASTRILLÓN | C45: =VLOOKUP(A45,'CENTRO DE COSTOS'!A:D,2,FALSE) -> 0004-0005 | D45: 5120 | E45: 2260533 | F45: FO-25-1047754 | G45: 45813.609 | H45: 45817.602 | I45: ANTIOQUIA | J45: CACERES | K45: DISTRICOL MIL COSAS Y ALGO MAS | L45: 66858 | M45: INCIDENTE | N45: REDEBAN | O45: AGREGADOR | Q45: CERRADO | R45: 05-06 SE REALIZA CONTACTO CON LA SEÑORA MARLYS AL NUMERO 3137654516 QUIEN INDICA QUE EL DATAFONO SALE ERROR CONEXION CABLE RED DESCONECTADO, SE HACEN VALIDACIONES Y SE ESCALA PARA VISITA TECNICA 0 09-06 SE VISITA SITIO, SE REVISAN CONEXIONES DEL DATAFONO OK. SE DETECTA PROBLEMAS EN CANAL DE COMERCIO (SWITCH) SE REINICIA CONSTANTEMENTE, DATAFONO SE CONECTA DIRECTO AL MODEM Y SE LE INFORMA AL CB DAÑO EN CANAL DE COMUNICACIÓN OK. PRUEBAS EXITOSAS | S45: COGOLLO VERTEL EDER LUIS | T45: VISITA_TÉCNICA | U45: 4A0AZ386 | V45: NO | W45: USUARIO | X45: COMUNICACION | Y45: CANAL DEL COMERCIO | Z45: No | AA45: 0 | AB45: 0 | AC45: 0 | AD45: 0 | AE45: 0 | AF45: =VLOOKUP(D45,TIPOLOGIAS!A:H,6,0) -> TIPO IV | AG45: =VLOOKUP(D45,TIPOLOGIAS!A:H,5,0) -> TERRESTRE | AH45: 1 | AI45: 0 | AJ45: 0 | AK45: 0 | AL45: =IF(T45="SOPORTE_TELEFÓNICO",'BASE LIQUIDACION'!$B$10,IF(AF45="TIPO I",'BASE LIQUIDACION'!$C$3,IF(AF45="TIPO II",'BASE LIQUIDACION'!$C$4,IF(AF45="TIPO III",'BASE LIQUIDACION'!$C$5,'BASE LIQUIDACION'!$C$7)))) -> 479589.74 | AM45: =IF(T45="SOPORTE_TELEFÓNICO",'BASE LIQUIDACION'!$B$10,(AH45*AL45+AI45*'BASE LIQUIDACION'!$B$12+AJ45*'BASE LIQUIDACION'!$B$11+INCIDENTES!AK45*'BASE LIQUIDACION'!$B$13)) -> 479589.74
A46: MEDELLIN | B46: =VLOOKUP(A46,'CENTRO DE COSTOS'!A:D,4,FALSE) -> JUAN SEBASTIÁN RÍOS CASTRILLÓN | C46: =VLOOKUP(A46,'CENTRO DE COSTOS'!A:D,2,FALSE) -> 0004-0005 | D46: 5400 | E46: 2269488 | F46: FO-25-1060456 | G46: 45816.633 | H46: 45817.62 | I46: ANTIOQUIA | J46: LA UNION | K46: PARQUE PRINCIPAL LA UNION ANTI | L46: 69294 | M46: INCIDENTE | N46: REDEBAN | O46: CB UNO A UNO | Q46: CERRADO | R46: 08-06 SE ESCALA PARA VISITA, LLAMAR ANTES DE VISITAR Y CONFIRMAR DATOS, DIRECCION Y SOLICITUD 0 09-06 SE REALIZÓ GESTIÓN TELEFÓNICA SE HABLO CON LA SEÑORA CLAUDIA CALLE, SE REALIZÓ RESTABLECE CLAVE SUPERVISOR SE REALIZA UNA PRUEBA SIENDO EXITOSA | S46: CASTAÑEDA PALACIO CARLOS FELIPE | T46: SOPORTE_TELEFÓNICO | U46: 0 | V46: NO | W46: USUARIO | X46: USUARIOS | Y46: USUARIOS BLOQUEADOS | Z46: No | AA46: 0 | AB46: 0 | AC46: 0 | AD46: 0 | AE46: 0 | AF46: =VLOOKUP(D46,TIPOLOGIAS!A:H,6,0) -> TIPO II | AG46: =VLOOKUP(D46,TIPOLOGIAS!A:H,5,0) -> TERRESTRE | AH46: 0 | AI46: 0 | AJ46: 0 | AK46: 0 | AL46: =IF(T46="SOPORTE_TELEFÓNICO",'BASE LIQUIDACION'!$B$10,IF(AF46="TIPO I",'BASE LIQUIDACION'!$C$3,IF(AF46="TIPO II",'BASE LIQUIDACION'!$C$4,IF(AF46="TIPO III",'BASE LIQUIDACION'!$C$5,'BASE LIQUIDACION'!$C$7)))) -> 37904.654 | AM46: =IF(T46="SOPORTE_TELEFÓNICO",'BASE LIQUIDACION'!$B$10,(AH46*AL46+AI46*'BASE LIQUIDACION'!$B$12+AJ46*'BASE LIQUIDACION'!$B$11+INCIDENTES!AK46*'BASE LIQUIDACION'!$B$13)) -> 37904.654
A47: SINCELEJO | B47: =VLOOKUP(A47,'CENTRO DE COSTOS'!A:D,4,FALSE) -> JOSE MAURICIO HERNANDEZ ROJAS | C47: =VLOOKUP(A47,'CENTRO DE COSTOS'!A:D,2,FALSE) -> 0004-0001 | D47: 70001 | E47: 2268175 | F47: FO-25-1058818 | G47: 45815.373 | H47: 45817.676 | I47: SUCRE | J47: SINCELEJO | K47: BARRIO PIONEROS SINCELEJO 4 | L47: 77185 | M47: INCIDENTE | N47: REDEBAN | O47: CB UNO A UNO | Q47: CERRADO | R47: 07-06 SE ESCALA PARA VISITA, LLAMAR ANTES DE VISITAR Y CONFIRMAR DATOS, DIRECCION Y SOLICITUD 0 07-06 SE VISITA COMERCIO POR FALLA, YA QUE LE SALE FALLA DE COMUNICACIÓN VERIFIQUE PARÁMETROS, SE INTENTA INICIALIZAR LA TERMINAL DEL COMERCIO PERO NO ES POSIBLE, HAY QUE ESCALAR CON RBM YA QUE LA TERMINAL NO ESTÁ EN BASE 24, COD: 12 TERMINAL NO EXISTE EN PTD O CSECD, SE REPROGRAMAR PAR EL LUNES YA QUE NO HAY SOPORTE DE ACTIVOS RBM. 0 09-06 SE VISITA COMERCIO NUEVAMENTE, YA QUE SALE "FALLA DE COMUNICACIÓN VERIFIQUE PARÁMETROS" SE ESCALA CON RBM Y SE CONFIRMA QUE LA TERMINAL ESTÁ BLOQUEADA, SE HABLA CON LA ENCARGADA _DEL CB_ Y SE LE INFORMA PARA QUE SE COMUNIQUE CON INCOCREDITO PARA LA ACTIVACIÓN DEL CODIGO UNICO, UNA VEZ QUE LE ACTIVEN LA TERMINAL LLAMAR NUEVAMENTE A LA ENTIDAD PARA AGENDAR LA VISITA; EL USUARIO YA SE ENCUENTRA EN EL PROCESO CON INCOCREDITO. | S47: CACERES HERNANDEZ ANDRES | T47: VISITA_TÉCNICA | U47: FAEZZ033 - SX6ZZ444 | V47: NO | W47: ENTIDAD | X47: ERROR DE TRANSACCIONES | Y47: TRANSACCION NO PERMITIDA | Z47: No | AA47: 0 | AB47: 0 | AC47: 0 | AD47: 0 | AE47: 0 | AF47: =VLOOKUP(D47,TIPOLOGIAS!A:H,6,0) -> TIPO I | AG47: =VLOOKUP(D47,TIPOLOGIAS!A:H,5,0) -> TERRESTRE | AH47: 2 | AI47: 0 | AJ47: 0 | AK47: 0 | AL47: =IF(T47="SOPORTE_TELEFÓNICO",'BASE LIQUIDACION'!$B$10,IF(AF47="TIPO I",'BASE LIQUIDACION'!$C$3,IF(AF47="TIPO II",'BASE LIQUIDACION'!$C$4,IF(AF47="TIPO III",'BASE LIQUIDACION'!$C$5,'BASE LIQUIDACION'!$C$7)))) -> 65960.474 | AM47: =IF(T47="SOPORTE_TELEFÓNICO",'BASE LIQUIDACION'!$B$10,(AH47*AL47+AI47*'BASE LIQUIDACION'!$B$12+AJ47*'BASE LIQUIDACION'!$B$11+INCIDENTES!AK47*'BASE LIQUIDACION'!$B$13)) -> 131920.95
A48: PEREIRA | B48: =VLOOKUP(A48,'CENTRO DE COSTOS'!A:D,4,FALSE) -> DIEGO FERNANDO HENAO CARDONA | C48: =VLOOKUP(A48,'CENTRO DE COSTOS'!A:D,2,FALSE) -> 0004-0002 | D48: 63001 | E48: 2272102 | F48: FO-25-1061913 | G48: 45817.411 | H48: 45817.699 | I48: QUINDIO | J48: ARMENIA | K48: BARRIO LA CASTILLA ARMENIA | L48: 79275 | M48: INCIDENTE | N48: REDEBAN | O48: CB UNO A UNO | Q48: CERRADO | R48: 09-06 SE ESCALA PARA VISITA, LLAMAR ANTES DE VISITAR Y CONFIRMAR DATOS, DIRECCION Y SOLICITUD 0 09-06 SE LLEGA A COMERCIO SE VÁLIDA SERVICIO OK FALLA CONSISTE EN CONEXIONES DE PROVEEDOR INTERNET CLIENTE. | S48: SANCHEZ SOLORZANO JUAN SEBASTIAN | T48: VISITA_TÉCNICA | U48: A4WZZ802 | V48: NO | W48: USUARIO | X48: COMUNICACION | Y48: CONEXIONES DE COMERCIO | Z48: No | AA48: 0 | AB48: 0 | AC48: 0 | AD48: 0 | AE48: 0 | AF48: =VLOOKUP(D48,TIPOLOGIAS!A:H,6,0) -> TIPO II | AG48: =VLOOKUP(D48,TIPOLOGIAS!A:H,5,0) -> TERRESTRE | AH48: 1 | AI48: 0 | AJ48: 0 | AK48: 0 | AL48: =IF(T48="SOPORTE_TELEFÓNICO",'BASE LIQUIDACION'!$B$10,IF(AF48="TIPO I",'BASE LIQUIDACION'!$C$3,IF(AF48="TIPO II",'BASE LIQUIDACION'!$C$4,IF(AF48="TIPO III",'BASE LIQUIDACION'!$C$5,'BASE LIQUIDACION'!$C$7)))) -> 163813.56 | AM48: =IF(T48="SOPORTE_TELEFÓNICO",'BASE LIQUIDACION'!$B$10,(AH48*AL48+AI48*'BASE LIQUIDACION'!$B$12+AJ48*'BASE LIQUIDACION'!$B$11+INCIDENTES!AK48*'BASE LIQUIDACION'!$B$13)) -> 163813.56
A49: CUCUTA | B49: =VLOOKUP(A49,'CENTRO DE COSTOS'!A:D,4,FALSE) -> MIGUEL JULIÁN HERNÁNDEZ GUARÍN | C49: =VLOOKUP(A49,'CENTRO DE COSTOS'!A:D,2,FALSE) -> 0004-0008 | D49: 54001 | E49: 2274080 | F49: FO-25-1063441 | G49: 45817.531 | H49: 45818.437 | I49: NORTE DE SANTANDER | J49: CUCUTA | K49: BARRIO EL CENTRO CUCUTA 79 | L49: 78626 | M49: INCIDENTE | N49: REDEBAN | O49: CB UNO A UNO | Q49: CERRADO | R49: 09-06 SE ESCALA PARA VISITA, LLAMAR ANTES DE VISITAR Y CONFIRMAR DATOS, DIRECCION Y SOLICITUD 10/06/2025 SE VISITA EL PUNTO SE ENCUENTRA CERRADO, SE PROCEDE A LLAMAR AL CLIENTE Y NO SE OBTIENE RESPUESTA, SE ESCALA A COORDINADOR QUIEN NOS INDICA QUE ESPEREMOS HASTA LAS 10:00 AM. 10-06 SE VISITA COMERCIO Y SE ENCUENTRA CERRADO, SE LLAMA AL CLIENTE Y NOS INDICA QUE EL DATAFONO SE ENCUENTRA OPERATIVO, NO SE ADJUNTAN PRUEBAS PORQUE EL CLIENTE SE ENCUENTRA EN URGENCIAS. | S49: TORRES MANTILLA JOSE DANIEL | T49: VISITA_TÉCNICA | U49: 0 | V49: NO | W49: USUARIO | X49: COMUNICACION | Y49: CANAL DEL COMERCIO | Z49: No | AA49: 0 | AB49: 0 | AC49: 0 | AD49: 0 | AE49: 0 | AF49: =VLOOKUP(D49,TIPOLOGIAS!A:H,6,0) -> TIPO I | AG49: =VLOOKUP(D49,TIPOLOGIAS!A:H,5,0) -> TERRESTRE | AH49: 1 | AI49: 0 | AJ49: 0 | AK49: 0 | AL49: =IF(T49="SOPORTE_TELEFÓNICO",'BASE LIQUIDACION'!$B$10,IF(AF49="TIPO I",'BASE LIQUIDACION'!$C$3,IF(AF49="TIPO II",'BASE LIQUIDACION'!$C$4,IF(AF49="TIPO III",'BASE LIQUIDACION'!$C$5,'BASE LIQUIDACION'!$C$7)))) -> 65960.474 | AM49: =IF(T49="SOPORTE_TELEFÓNICO",'BASE LIQUIDACION'!$B$10,(AH49*AL49+AI49*'BASE LIQUIDACION'!$B$12+AJ49*'BASE LIQUIDACION'!$B$11+INCIDENTES!AK49*'BASE LIQUIDACION'!$B$13)) -> 65960.474
A50: CALI | B50: =VLOOKUP(A50,'CENTRO DE COSTOS'!A:D,4,FALSE) -> DIEGO FERNANDO HENAO CARDONA | C50: =VLOOKUP(A50,'CENTRO DE COSTOS'!A:D,2,FALSE) -> 0004-0003 | D50: 19824 | E50: 2279311 | F50: FO-25-1066772 | G50: 45818.387 | H50: 45818.463 | I50: CAUCA | J50: TOTORO | K50: BARRIO TOTORO TOTORO | L50: 69035 | M50: INCIDENTE | N50: REDEBAN | O50: CB UNO A UNO | Q50: CERRADO | R50: 10-06 SE ESCALA PARA VISITA, LLAMAR ANTES DE VISITAR Y CONFIRMAR DATOS, DIRECCION Y SOLICITUD 0 10-06 SE REALIZA VALIDACION CON EL CLIENTE QUIEN INDICA QUE EL SERVICIO YA SE RESTABLECIO, ERA UN PROBLEMA CON EL PROVEEDOR DE INTERNET, EL CLIENTE YA ESTA TRANSANDO NORMAL. SE CIERRA CASO | S50: HENAO CARDONA DIEGO FERNANDO | T50: SOPORTE_TELEFÓNICO | U50: 0 | V50: NO | W50: USUARIO | X50: COMUNICACION | Y50: CANAL DEL COMERCIO | Z50: No | AA50: 0 | AB50: 0 | AC50: 0 | AD50: 0 | AE50: 0 | AF50: =VLOOKUP(D50,TIPOLOGIAS!A:H,6,0) -> TIPO III | AG50: =VLOOKUP(D50,TIPOLOGIAS!A:H,5,0) -> TERRESTRE | AH50: 0 | AI50: 0 | AJ50: 0 | AK50: 0 | AL50: =IF(T50="SOPORTE_TELEFÓNICO",'BASE LIQUIDACION'!$B$10,IF(AF50="TIPO I",'BASE LIQUIDACION'!$C$3,IF(AF50="TIPO II",'BASE LIQUIDACION'!$C$4,IF(AF50="TIPO III",'BASE LIQUIDACION'!$C$5,'BASE LIQUIDACION'!$C$7)))) -> 37904.654 | AM50: =IF(T50="SOPORTE_TELEFÓNICO",'BASE LIQUIDACION'!$B$10,(AH50*AL50+AI50*'BASE LIQUIDACION'!$B$12+AJ50*'BASE LIQUIDACION'!$B$11+INCIDENTES!AK50*'BASE LIQUIDACION'!$B$13)) -> 37904.654
A51: CALI | B51: =VLOOKUP(A51,'CENTRO DE COSTOS'!A:D,4,FALSE) -> DIEGO FERNANDO HENAO CARDONA | C51: =VLOOKUP(A51,'CENTRO DE COSTOS'!A:D,2,FALSE) -> 0004-0003 | D51: 19392 | E51: 2279305 | F51: FO-25-1066777 | G51: 45818.386 | H51: 45818.465 | I51: CAUCA | J51: LA SIERRA | K51: BARRIO LA SIERRA LA SIERRA | L51: 76459 | M51: INCIDENTE | N51: REDEBAN | O51: CB UNO A UNO | Q51: CERRADO | R51: 10-06 SE ESCALA PARA VISITA, LLAMAR ANTES DE VISITAR Y CONFIRMAR DATOS, DIRECCION Y SOLICITUD 0 10-06 SE REALIZA VALIDACIÓN CON EL CLIENTE QUIEN INDICA QUE EL SERVICIO YA SE RESTABLECIÓ, ERA UN PROBLEMA CON EL PROVEEDOR DE INTERNET, EL CLIENTE YA ESTA CON TRANSACCIÓN NORMAL. SE CIERRA CASO | S51: HENAO CARDONA DIEGO FERNANDO | T51: SOPORTE_TELEFÓNICO | U51: 0 | V51: NO | W51: USUARIO | X51: COMUNICACION | Y51: CANAL DEL COMERCIO | Z51: No | AA51: 0 | AB51: 0 | AC51: 0 | AD51: 0 | AE51: 0 | AF51: =VLOOKUP(D51,TIPOLOGIAS!A:H,6,0) -> TIPO III | AG51: =VLOOKUP(D51,TIPOLOGIAS!A:H,5,0) -> TERRESTRE | AH51: 0 | AI51: 0 | AJ51: 0 | AK51: 0 | AL51: =IF(T51="SOPORTE_TELEFÓNICO",'BASE LIQUIDACION'!$B$10,IF(AF51="TIPO I",'BASE LIQUIDACION'!$C$3,IF(AF51="TIPO II",'BASE LIQUIDACION'!$C$4,IF(AF51="TIPO III",'BASE LIQUIDACION'!$C$5,'BASE LIQUIDACION'!$C$7)))) -> 37904.654 | AM51: =IF(T51="SOPORTE_TELEFÓNICO",'BASE LIQUIDACION'!$B$10,(AH51*AL51+AI51*'BASE LIQUIDACION'!$B$12+AJ51*'BASE LIQUIDACION'!$B$11+INCIDENTES!AK51*'BASE LIQUIDACION'!$B$13)) -> 37904.654
A52: MEDELLIN | B52: =VLOOKUP(A52,'CENTRO DE COSTOS'!A:D,4,FALSE) -> JUAN SEBASTIÁN RÍOS CASTRILLÓN | C52: =VLOOKUP(A52,'CENTRO DE COSTOS'!A:D,2,FALSE) -> 0004-0005 | D52: 5088 | E52: 2275410 | F52: FO-25-1064328 | G52: 45817.627 | H52: 45818.524 | I52: ANTIOQUIA | J52: BELLO | K52: BARRIO LA GABRIELA BELLO 2 | L52: 56388 | M52: INCIDENTE | N52: REDEBAN | O52: CB UNO A UNO | Q52: CERRADO | R52: 09-06 SE ESCALA PARA VISITA, LLAMAR ANTES DE VISITAR Y CONFIRMAR DATOS, DIRECCION Y SOLICITUD 0 10-06 SE HACE MANTENIMIENTO DE EQUIPO Y CABLEADO | S52: MORENO MEDINA JUAN PABLO | T52: VISITA_TÉCNICA | U52: 9B0ZZ145 | V52: NO | W52: USUARIO | X52: MANTENIMIENTO | Y52: MANTENIMIENTO GENERAL | Z52: No | AA52: 0 | AB52: 0 | AC52: 0 | AD52: 0 | AE52: 0 | AF52: =VLOOKUP(D52,TIPOLOGIAS!A:H,6,0) -> TIPO I | AG52: =VLOOKUP(D52,TIPOLOGIAS!A:H,5,0) -> TERRESTRE | AH52: 1 | AI52: 0 | AJ52: 0 | AK52: 0 | AL52: =IF(T52="SOPORTE_TELEFÓNICO",'BASE LIQUIDACION'!$B$10,IF(AF52="TIPO I",'BASE LIQUIDACION'!$C$3,IF(AF52="TIPO II",'BASE LIQUIDACION'!$C$4,IF(AF52="TIPO III",'BASE LIQUIDACION'!$C$5,'BASE LIQUIDACION'!$C$7)))) -> 65960.474 | AM52: =IF(T52="SOPORTE_TELEFÓNICO",'BASE LIQUIDACION'!$B$10,(AH52*AL52+AI52*'BASE LIQUIDACION'!$B$12+AJ52*'BASE LIQUIDACION'!$B$11+INCIDENTES!AK52*'BASE LIQUIDACION'!$B$13)) -> 65960.474
A53: MEDELLIN | B53: =VLOOKUP(A53,'CENTRO DE COSTOS'!A:D,4,FALSE) -> JUAN SEBASTIÁN RÍOS CASTRILLÓN | C53: =VLOOKUP(A53,'CENTRO DE COSTOS'!A:D,2,FALSE) -> 0004-0005 | D53: 5440 | E53: 2275844 | F53: FO-25-1064536 | G53: 45817.649 | H53: 45818.617 | I53: ANTIOQUIA | J53: MARINILLA | K53: MULTIPAGAS MARINILLA | L53: 20726 | M53: INCIDENTE | N53: REDEBAN | O53: ROBUSTO | Q53: CERRADO | R53: 09-06 SE ESCALA PARA VISITA, LLAMAR ANTES DE VISITAR Y CONFIRMAR DATOS, DIRECCION Y SOLICITUD 0 10-06 SE FORMATEA EL EQUIPO DEJANDO LOS PARÁMETROS OK, INICIALIZACION OK, FUERON 2 EQUIPOS A LOS QUE SE LES HIZO ESTE PROCESO | S53: RUA ALVAREZ RICHARD ANDRES | T53: VISITA_TÉCNICA | U53: AAAAX315-AAAAX316 | V53: NO | W53: USUARIO | X53: MANTENIMIENTO | Y53: MANTENIMIENTO GENERAL | Z53: No | AA53: 0 | AB53: 0 | AC53: 0 | AD53: 0 | AE53: 0 | AF53: =VLOOKUP(D53,TIPOLOGIAS!A:H,6,0) -> TIPO II | AG53: =VLOOKUP(D53,TIPOLOGIAS!A:H,5,0) -> TERRESTRE | AH53: 1 | AI53: 0 | AJ53: 0 | AK53: 0 | AL53: =IF(T53="SOPORTE_TELEFÓNICO",'BASE LIQUIDACION'!$B$10,IF(AF53="TIPO I",'BASE LIQUIDACION'!$C$3,IF(AF53="TIPO II",'BASE LIQUIDACION'!$C$4,IF(AF53="TIPO III",'BASE LIQUIDACION'!$C$5,'BASE LIQUIDACION'!$C$7)))) -> 163813.56 | AM53: =IF(T53="SOPORTE_TELEFÓNICO",'BASE LIQUIDACION'!$B$10,(AH53*AL53+AI53*'BASE LIQUIDACION'!$B$12+AJ53*'BASE LIQUIDACION'!$B$11+INCIDENTES!AK53*'BASE LIQUIDACION'!$B$13)) -> 163813.56
A54: MEDELLIN | B54: =VLOOKUP(A54,'CENTRO DE COSTOS'!A:D,4,FALSE) -> JUAN SEBASTIÁN RÍOS CASTRILLÓN | C54: =VLOOKUP(A54,'CENTRO DE COSTOS'!A:D,2,FALSE) -> 0004-0005 | D54: 5209 | E54: 2268754 | F54: FO-25-1058979 | G54: 45815.589 | H54: 45818.619 | I54: ANTIOQUIA | J54: CONCORDIA | K54: BARRIO UNICO CIUDAD BOLIVAR | L54: 14866 | M54: INCIDENTE | N54: REDEBAN | O54: CB UNO A UNO | Q54: CERRADO | R54: 07-06 SE ESCALA PARA VISITA, LLAMAR ANTES DE VISITAR Y CONFIRMAR DATOS, DIRECCION Y SOLICITUD 0 10-06 SE ENVIDENCIA PROBLEMAS CON EL CANAL DE COMUNICACIÓN SE CONECTA DIRECTAMENTE AL CANAL Y FUNCIONA NORMALMENTE LM | S54: CASTAÑEDA PALACIO CARLOS FELIPE | T54: VISITA_TÉCNICA | U54: JAZZZ622 | V54: NO | W54: USUARIO | X54: COMUNICACION | Y54: CANAL DEL COMERCIO | Z54: No | AA54: 0 | AB54: 0 | AC54: 0 | AD54: 0 | AE54: 0 | AF54: =VLOOKUP(D54,TIPOLOGIAS!A:H,6,0) -> TIPO III | AG54: =VLOOKUP(D54,TIPOLOGIAS!A:H,5,0) -> TERRESTRE | AH54: 1 | AI54: 0 | AJ54: 0 | AK54: 0 | AL54: =IF(T54="SOPORTE_TELEFÓNICO",'BASE LIQUIDACION'!$B$10,IF(AF54="TIPO I",'BASE LIQUIDACION'!$C$3,IF(AF54="TIPO II",'BASE LIQUIDACION'!$C$4,IF(AF54="TIPO III",'BASE LIQUIDACION'!$C$5,'BASE LIQUIDACION'!$C$7)))) -> 275728.38 | AM54: =IF(T54="SOPORTE_TELEFÓNICO",'BASE LIQUIDACION'!$B$10,(AH54*AL54+AI54*'BASE LIQUIDACION'!$B$12+AJ54*'BASE LIQUIDACION'!$B$11+INCIDENTES!AK54*'BASE LIQUIDACION'!$B$13)) -> 275728.38
A55: TUNJA | B55: =VLOOKUP(A55,'CENTRO DE COSTOS'!A:D,4,FALSE) -> MIGUEL JULIÁN HERNÁNDEZ GUARÍN | C55: =VLOOKUP(A55,'CENTRO DE COSTOS'!A:D,2,FALSE) -> 0004-0008 | D55: 15759 | E55: 2275102 | F55: FO-25-1064077 | G55: 45817.608 | H55: 45818.624 | I55: BOYACA | J55: SOGAMOSO | K55: BARRIO SOGAMOSO SOGAMOSO | L55: 77977 | M55: INCIDENTE | N55: REDEBAN | O55: CB UNO A UNO | Q55: CERRADO | R55: 09-06 SE ESCALA PARA VISITA, LLAMAR ANTES DE VISITAR Y CONFIRMAR DATOS, DIRECCION Y SOLICITUD 0 10-06 SE ESTABLECE COMUNICACIÓN TELEFÓNICA CON LA SEÑORA YESI ALFONSO AL DE CONTACTO 3213914853 CLIENTE INDICA QUE LE DATAFONO SE ENCUENTRA FUNCIONANDO CORRECTAMENTE OPERATIVO INFORMA QUE LA SOLICITUD QUE REALIZO ES DEBIDO A QUE REQUERÍA QUÉ LA INFORMACIÓN DEL TITULAR DE NEQUI LE APARECIERA EN PANTALLA ANTES DE FINALIZAR LA TRANSACCIÓN IGUAL QUE BANCOLOMBIA SE LE INDICA QUE PARA NEQUI NUNCA HAN TENIDO ESA OPCIÓN YA ES UN TEMA DE LA ENTIDAD EL NOMBRE DE TITULAR NEQUI SOLO SE VE REFLEJADO EN LA TIRILLA UNA VEZ FINALIZADA LA TX NO ANTES DE FINALIZAR LA TX SE LE INFORMA QUE SE PROCEDERÁ CON EL CIERRE DE LA ORDEN DE TRABAJO GENERADA YA QUE SE EVIDENCIA QUE EL EQUIPO ESTA FUNCIONANDO CORRECTAMENTE Y NO REQUIERE DE LA ASISTENCIA TÉCNICA CLIENTE COMPRENDE QUEDANDO CONFORME. | S55: RODRIGUEZ MURCIA YERSON IVAN | T55: SOPORTE_TELEFÓNICO | U55: 0 | V55: NO | W55: USUARIO | X55: MANTENIMIENTO | Y55: MANTENIMIENTO GENERAL | Z55: No | AA55: 0 | AB55: 0 | AC55: 0 | AD55: 0 | AE55: 0 | AF55: =VLOOKUP(D55,TIPOLOGIAS!A:H,6,0) -> TIPO II | AG55: =VLOOKUP(D55,TIPOLOGIAS!A:H,5,0) -> TERRESTRE | AH55: 0 | AI55: 0 | AJ55: 0 | AK55: 0 | AL55: =IF(T55="SOPORTE_TELEFÓNICO",'BASE LIQUIDACION'!$B$10,IF(AF55="TIPO I",'BASE LIQUIDACION'!$C$3,IF(AF55="TIPO II",'BASE LIQUIDACION'!$C$4,IF(AF55="TIPO III",'BASE LIQUIDACION'!$C$5,'BASE LIQUIDACION'!$C$7)))) -> 37904.654 | AM55: =IF(T55="SOPORTE_TELEFÓNICO",'BASE LIQUIDACION'!$B$10,(AH55*AL55+AI55*'BASE LIQUIDACION'!$B$12+AJ55*'BASE LIQUIDACION'!$B$11+INCIDENTES!AK55*'BASE LIQUIDACION'!$B$13)) -> 37904.654
A56: MEDELLIN | B56: =VLOOKUP(A56,'CENTRO DE COSTOS'!A:D,4,FALSE) -> JUAN SEBASTIÁN RÍOS CASTRILLÓN | C56: =VLOOKUP(A56,'CENTRO DE COSTOS'!A:D,2,FALSE) -> 0004-0005 | D56: 5887 | E56: 2277281 | F56: FO-25-1065819 | G56: 45818.333 | H56: 45818.625 | I56: ANTIOQUIA | J56: YARUMAL | K56: TERMINAL DE TRANSPORTE YARUMAL | L56: 17989 | M56: INCIDENTE | N56: REDEBAN | O56: CB UNO A UNO | Q56: CERRADO | R56: 10-06 SE ESCALA PARA VISITA, LLAMAR ANTES DE VISITAR Y CONFIRMAR DATOS, DIRECCION Y SOLICITUD 0 10-06 SE HACE MANTENIMIENTO OK SE CREA CLAVE SUPERVISOR OK. EQUIPOS OPERATIVOS | S56: DIAZ ZABALA FRANCIS DUBAN | T56: VISITA_TÉCNICA | U56: A00JZ413 | V56: NO | W56: USUARIO | X56: MANTENIMIENTO | Y56: MANTENIMIENTO GENERAL | Z56: No | AA56: 0 | AB56: 0 | AC56: 0 | AD56: 0 | AE56: 0 | AF56: =VLOOKUP(D56,TIPOLOGIAS!A:H,6,0) -> TIPO III | AG56: =VLOOKUP(D56,TIPOLOGIAS!A:H,5,0) -> TERRESTRE | AH56: 1 | AI56: 0 | AJ56: 0 | AK56: 0 | AL56: =IF(T56="SOPORTE_TELEFÓNICO",'BASE LIQUIDACION'!$B$10,IF(AF56="TIPO I",'BASE LIQUIDACION'!$C$3,IF(AF56="TIPO II",'BASE LIQUIDACION'!$C$4,IF(AF56="TIPO III",'BASE LIQUIDACION'!$C$5,'BASE LIQUIDACION'!$C$7)))) -> 275728.38 | AM56: =IF(T56="SOPORTE_TELEFÓNICO",'BASE LIQUIDACION'!$B$10,(AH56*AL56+AI56*'BASE LIQUIDACION'!$B$12+AJ56*'BASE LIQUIDACION'!$B$11+INCIDENTES!AK56*'BASE LIQUIDACION'!$B$13)) -> 275728.38
A57: VILLAVICENCIO | B57: =VLOOKUP(A57,'CENTRO DE COSTOS'!A:D,4,FALSE) -> KEVIN ALEXIS CORZO BUSTOS | C57: =VLOOKUP(A57,'CENTRO DE COSTOS'!A:D,2,FALSE) -> 0004-0007 | D57: 50001 | E57: 2275836 | F57: FO-25-1064543 | G57: 45817.647 | H57: 45818.64 | I57: META | J57: VILLAVICENCIO | K57: BARRIO MANANTIAL VILLAVICENCIO | L57: 74210 | M57: INCIDENTE | N57: REDEBAN | O57: CB UNO A UNO | Q57: CERRADO | R57: 09-06 SE ESCALA PARA VISITA, LLAMAR ANTES DE VISITAR Y CONFIRMAR DATOS, DIRECCION Y SOLICITUD 0 10-06 SE VISITA CB Y AL LLEGAT AL SITIO EL COMERCIO SE ENCUENTRA CERRADO. ME COMUNICO CON CLIENTE Y E INFORMA QUE SOLO ABREN EN HORAS DE LA MAÑANA Y QUE EL DIA DE HOY LA LECTORA LES HA FUNCIONANDO NORMALMENTE | S57: GARZON RUIZ LUIS MIGUEL | T57: VISITA_TÉCNICA | U57: 0 | V57: NO | W57: USUARIO | X57: LECTOR DE BARRAS | Y57: CAPACITACION MANIPULACION DE COMERCIO | Z57: No | AA57: 0 | AB57: 0 | AC57: 0 | AD57: 0 | AE57: 0 | AF57: =VLOOKUP(D57,TIPOLOGIAS!A:H,6,0) -> TIPO I | AG57: =VLOOKUP(D57,TIPOLOGIAS!A:H,5,0) -> TERRESTRE | AH57: 1 | AI57: 0 | AJ57: 0 | AK57: 0 | AL57: =IF(T57="SOPORTE_TELEFÓNICO",'BASE LIQUIDACION'!$B$10,IF(AF57="TIPO I",'BASE LIQUIDACION'!$C$3,IF(AF57="TIPO II",'BASE LIQUIDACION'!$C$4,IF(AF57="TIPO III",'BASE LIQUIDACION'!$C$5,'BASE LIQUIDACION'!$C$7)))) -> 65960.474 | AM57: =IF(T57="SOPORTE_TELEFÓNICO",'BASE LIQUIDACION'!$B$10,(AH57*AL57+AI57*'BASE LIQUIDACION'!$B$12+AJ57*'BASE LIQUIDACION'!$B$11+INCIDENTES!AK57*'BASE LIQUIDACION'!$B$13)) -> 65960.474
A58: CALI | B58: =VLOOKUP(A58,'CENTRO DE COSTOS'!A:D,4,FALSE) -> DIEGO FERNANDO HENAO CARDONA | C58: =VLOOKUP(A58,'CENTRO DE COSTOS'!A:D,2,FALSE) -> 0004-0003 | D58: 19473 | E58: 2278861 | F58: FO-25-1066409 | G58: 45818.376 | H58: 45818.651 | I58: CAUCA | J58: MORALES | K58: BARRIO CHIMBORAZO MORALES | L58: 60816 | M58: INCIDENTE | N58: REDEBAN | O58: CB UNO A UNO | Q58: CERRADO | R58: 10-06 SE ESCALA PARA VISITA, LLAMAR ANTES DE VISITAR Y CONFIRMAR DATOS, DIRECCION Y SOLICITUD 0 10-06 SE REALIZA VALIDACION CON EL CLIENTE QUIEN INDICA QUE EL SERVICIO YA SE RESTABLECIO, ERA UN PROBLEMA CON EL PROVEEDOR DE INTERNET, EL CLIENTE YA ESTA TRANSACION NORMAL. SE CIERRA CASO | S58: HENAO CARDONA DIEGO FERNANDO | T58: SOPORTE_TELEFÓNICO | U58: 0 | V58: NO | W58: USUARIO | X58: COMUNICACION | Y58: CANAL DEL COMERCIO | Z58: No | AA58: 0 | AB58: 0 | AC58: 0 | AD58: 0 | AE58: 0 | AF58: =VLOOKUP(D58,TIPOLOGIAS!A:H,6,0) -> TIPO III | AG58: =VLOOKUP(D58,TIPOLOGIAS!A:H,5,0) -> TERRESTRE | AH58: 0 | AI58: 0 | AJ58: 0 | AK58: 0 | AL58: =IF(T58="SOPORTE_TELEFÓNICO",'BASE LIQUIDACION'!$B$10,IF(AF58="TIPO I",'BASE LIQUIDACION'!$C$3,IF(AF58="TIPO II",'BASE LIQUIDACION'!$C$4,IF(AF58="TIPO III",'BASE LIQUIDACION'!$C$5,'BASE LIQUIDACION'!$C$7)))) -> 37904.654 | AM58: =IF(T58="SOPORTE_TELEFÓNICO",'BASE LIQUIDACION'!$B$10,(AH58*AL58+AI58*'BASE LIQUIDACION'!$B$12+AJ58*'BASE LIQUIDACION'!$B$11+INCIDENTES!AK58*'BASE LIQUIDACION'!$B$13)) -> 37904.654
A59: MEDELLIN | B59: =VLOOKUP(A59,'CENTRO DE COSTOS'!A:D,4,FALSE) -> JUAN SEBASTIÁN RÍOS CASTRILLÓN | C59: =VLOOKUP(A59,'CENTRO DE COSTOS'!A:D,2,FALSE) -> 0004-0005 | D59: 5368 | E59: 2277286 | F59: FO-25-1065812 | G59: 45818.333 | H59: 45818.681 | I59: ANTIOQUIA | J59: JERICO | K59: BARRIO PUENTE IGLESIAS JERICO | L59: 58393 | M59: INCIDENTE | N59: REDEBAN | O59: CB UNO A UNO | Q59: CERRADO | R59: 10-06 SE ESCALA PARA VISITA, LLAMAR ANTES DE VISITAR Y CONFIRMAR DATOS, DIRECCION Y SOLICITUD 0 10-06 SE LE EXPLICA AL CORRESPONSAL COMO REALIZAR CIERRES POS OK LECTOR OK | S59: CASTAÑEDA PALACIO CARLOS FELIPE | T59: VISITA_TÉCNICA | U59: TXZZZ476 | V59: NO | W59: USUARIO | X59: CIERRE | Y59: COMERCIO NO REALIZA CIERRE | Z59: No | AA59: 0 | AB59: 0 | AC59: 0 | AD59: 0 | AE59: 0 | AF59: =VLOOKUP(D59,TIPOLOGIAS!A:H,6,0) -> TIPO III | AG59: =VLOOKUP(D59,TIPOLOGIAS!A:H,5,0) -> TERRESTRE | AH59: 1 | AI59: 0 | AJ59: 0 | AK59: 0 | AL59: =IF(T59="SOPORTE_TELEFÓNICO",'BASE LIQUIDACION'!$B$10,IF(AF59="TIPO I",'BASE LIQUIDACION'!$C$3,IF(AF59="TIPO II",'BASE LIQUIDACION'!$C$4,IF(AF59="TIPO III",'BASE LIQUIDACION'!$C$5,'BASE LIQUIDACION'!$C$7)))) -> 275728.38 | AM59: =IF(T59="SOPORTE_TELEFÓNICO",'BASE LIQUIDACION'!$B$10,(AH59*AL59+AI59*'BASE LIQUIDACION'!$B$12+AJ59*'BASE LIQUIDACION'!$B$11+INCIDENTES!AK59*'BASE LIQUIDACION'!$B$13)) -> 275728.38
A60: CALI | B60: =VLOOKUP(A60,'CENTRO DE COSTOS'!A:D,4,FALSE) -> DIEGO FERNANDO HENAO CARDONA | C60: =VLOOKUP(A60,'CENTRO DE COSTOS'!A:D,2,FALSE) -> 0004-0003 | D60: 19050 | E60: 2278813 | F60: FO-25-1066263 | G60: 45818.367 | H60: 45819.375 | I60: CAUCA | J60: ARGELIA | K60: PTM ARGELIA ELECTRICOS Y VARI | L60: 66182 | M60: INCIDENTE | N60: REDEBAN | O60: AGREGADOR | Q60: CERRADO | R60: 10-06 SE ESCALA PARA VISITA, LLAMAR ANTES DE VISITAR Y CONFIRMAR DATOS, DIRECCION Y SOLICITUD 0 11-06 SE HABLA CON EL CLIENTE QUIEN INDICA QUE DEBIDO A UNA CAIDA DEL PROVEEDOR DE INTERNET EL SERVICIO SE CAYO PERO QUE EN EL TRANSCURSO DEL DIA SE RESTABLECIO Y ESTA OERANDO SIN PROBLEMA. | S60: HENAO CARDONA DIEGO FERNANDO | T60: SOPORTE_TELEFÓNICO | U60: 0 | V60: NO | W60: USUARIO | X60: COMUNICACION | Y60: CANAL DEL COMERCIO | Z60: No | AA60: 0 | AB60: 0 | AC60: 0 | AD60: 0 | AE60: 0 | AF60: =VLOOKUP(D60,TIPOLOGIAS!A:H,6,0) -> TIPO IV | AG60: =VLOOKUP(D60,TIPOLOGIAS!A:H,5,0) -> TERRESTRE | AH60: 0 | AI60: 0 | AJ60: 0 | AK60: 0 | AL60: =IF(T60="SOPORTE_TELEFÓNICO",'BASE LIQUIDACION'!$B$10,IF(AF60="TIPO I",'BASE LIQUIDACION'!$C$3,IF(AF60="TIPO II",'BASE LIQUIDACION'!$C$4,IF(AF60="TIPO III",'BASE LIQUIDACION'!$C$5,'BASE LIQUIDACION'!$C$7)))) -> 37904.654 | AM60: =IF(T60="SOPORTE_TELEFÓNICO",'BASE LIQUIDACION'!$B$10,(AH60*AL60+AI60*'BASE LIQUIDACION'!$B$12+AJ60*'BASE LIQUIDACION'!$B$11+INCIDENTES!AK60*'BASE LIQUIDACION'!$B$13)) -> 37904.654
A61: MEDELLIN | B61: =VLOOKUP(A61,'CENTRO DE COSTOS'!A:D,4,FALSE) -> JUAN SEBASTIÁN RÍOS CASTRILLÓN | C61: =VLOOKUP(A61,'CENTRO DE COSTOS'!A:D,2,FALSE) -> 0004-0005 | D61: 5001 | E61: 2282464 | F61: FO-25-1069515 | G61: 45818.617 | H61: 45819.412 | I61: ANTIOQUIA | J61: MEDELLIN | K61: PTM MEDELLIN ABARROTES CASTRO | L61: 50147 | M61: INCIDENTE | N61: REDEBAN | O61: AGREGADOR | Q61: CERRADO | R61: 10-06 SE ESCALA PARA VISITA, LLAMAR ANTES DE VISITAR Y CONFIRMAR DATOS, DIRECCION Y SOLICITUD 0 11-06 SE LLAMA AL SEÑOR JORGE E INDICA QUE EL CB FUNCIONA CORRECTAMENTE | S61: MORENO MEDINA JUAN PABLO | T61: SOPORTE_TELEFÓNICO | U61: 0 | V61: NO | W61: USUARIO | X61: MANTENIMIENTO | Y61: MANTENIMIENTO GENERAL | Z61: No | AA61: 0 | AB61: 0 | AC61: 0 | AD61: 0 | AE61: 0 | AF61: =VLOOKUP(D61,TIPOLOGIAS!A:H,6,0) -> TIPO I | AG61: =VLOOKUP(D61,TIPOLOGIAS!A:H,5,0) -> TERRESTRE | AH61: 0 | AI61: 0 | AJ61: 0 | AK61: 0 | AL61: =IF(T61="SOPORTE_TELEFÓNICO",'BASE LIQUIDACION'!$B$10,IF(AF61="TIPO I",'BASE LIQUIDACION'!$C$3,IF(AF61="TIPO II",'BASE LIQUIDACION'!$C$4,IF(AF61="TIPO III",'BASE LIQUIDACION'!$C$5,'BASE LIQUIDACION'!$C$7)))) -> 37904.654 | AM61: =IF(T61="SOPORTE_TELEFÓNICO",'BASE LIQUIDACION'!$B$10,(AH61*AL61+AI61*'BASE LIQUIDACION'!$B$12+AJ61*'BASE LIQUIDACION'!$B$11+INCIDENTES!AK61*'BASE LIQUIDACION'!$B$13)) -> 37904.654
A62: BOGOTA | B62: =VLOOKUP(A62,'CENTRO DE COSTOS'!A:D,4,FALSE) -> WILLIAM ASDRUBAL ROZO ROZO | C62: =VLOOKUP(A62,'CENTRO DE COSTOS'!A:D,2,FALSE) -> 0004-0004 | D62: 11001 | E62: 2286870 | F62: FO-25-1073856 | G62: 45819.401 | H62: 45819.522 | I62: CUNDINAMARCA | J62: BOGOTA | K62: BARRIO PALOQUEMAO | L62: 12232 | M62: INCIDENTE | N62: REDEBAN | O62: CB UNO A UNO | Q62: CERRADO | R62: 11-06 SE ESCALA PARA VISITA. LLAMAR ANTES DE VISITAR, CONFIRMAR FALLA Y DATOS 0 11-06 SE LLEGA AL PUNTO DATÁFONO SE ENCUENTRA FUNCIONANDO EN PERFECTAS CONDICIONES, LA FALLA PUDO SER AL MÓDEM DEL CB QUE ALTERAN EN IP FIJA A DHCP, CB REALIZA PRUEBAS OK | S62: MICHELI LOPEZ MIGUEL ANGEL | T62: VISITA_TÉCNICA | U62: JAAAQ389 | V62: NO | W62: USUARIO | X62: COMUNICACION | Y62: CONEXIONES DE COMERCIO | Z62: No | AA62: 0 | AB62: 0 | AC62: 0 | AD62: 0 | AE62: 0 | AF62: =VLOOKUP(D62,TIPOLOGIAS!A:H,6,0) -> TIPO I | AG62: =VLOOKUP(D62,TIPOLOGIAS!A:H,5,0) -> TERRESTRE | AH62: 1 | AI62: 0 | AJ62: 0 | AK62: 0 | AL62: =IF(T62="SOPORTE_TELEFÓNICO",'BASE LIQUIDACION'!$B$10,IF(AF62="TIPO I",'BASE LIQUIDACION'!$C$3,IF(AF62="TIPO II",'BASE LIQUIDACION'!$C$4,IF(AF62="TIPO III",'BASE LIQUIDACION'!$C$5,'BASE LIQUIDACION'!$C$7)))) -> 65960.474 | AM62: =IF(T62="SOPORTE_TELEFÓNICO",'BASE LIQUIDACION'!$B$10,(AH62*AL62+AI62*'BASE LIQUIDACION'!$B$12+AJ62*'BASE LIQUIDACION'!$B$11+INCIDENTES!AK62*'BASE LIQUIDACION'!$B$13)) -> 65960.474
A63: MEDELLIN | B63: =VLOOKUP(A63,'CENTRO DE COSTOS'!A:D,4,FALSE) -> JUAN SEBASTIÁN RÍOS CASTRILLÓN | C63: =VLOOKUP(A63,'CENTRO DE COSTOS'!A:D,2,FALSE) -> 0004-0005 | D63: 5001 | E63: 2284400 | F63: FO-25-1070559 | G63: 45818.724 | H63: 45819.584 | I63: ANTIOQUIA | J63: MEDELLIN | K63: BARRIO PLAYON MEDELLIN 2 | L63: 36971 | M63: INCIDENTE | N63: REDEBAN | O63: CB UNO A UNO | Q63: CERRADO | R63: 10-06 SE ESCALA PARA VISITA. LLAMAR ANTES DE VISITAR, CONFIRMAR FALLA Y DATOS 0 11-06 SE REALIZA MANTENIMIENTO A LA IMPRESORA Y EQUIPO POR QUE NO LEÍA TARJETA | S63: CERPA SUAREZ DUVAN CAMILO | T63: VISITA_TÉCNICA | U63: AB00H664 | V63: NO | W63: USUARIO | X63: MANTENIMIENTO | Y63: MANTENIMIENTO GENERAL | Z63: No | AA63: 0 | AB63: 0 | AC63: 0 | AD63: 0 | AE63: 0 | AF63: =VLOOKUP(D63,TIPOLOGIAS!A:H,6,0) -> TIPO I | AG63: =VLOOKUP(D63,TIPOLOGIAS!A:H,5,0) -> TERRESTRE | AH63: 1 | AI63: 0 | AJ63: 0 | AK63: 0 | AL63: =IF(T63="SOPORTE_TELEFÓNICO",'BASE LIQUIDACION'!$B$10,IF(AF63="TIPO I",'BASE LIQUIDACION'!$C$3,IF(AF63="TIPO II",'BASE LIQUIDACION'!$C$4,IF(AF63="TIPO III",'BASE LIQUIDACION'!$C$5,'BASE LIQUIDACION'!$C$7)))) -> 65960.474 | AM63: =IF(T63="SOPORTE_TELEFÓNICO",'BASE LIQUIDACION'!$B$10,(AH63*AL63+AI63*'BASE LIQUIDACION'!$B$12+AJ63*'BASE LIQUIDACION'!$B$11+INCIDENTES!AK63*'BASE LIQUIDACION'!$B$13)) -> 65960.474
A64: NEIVA | B64: =VLOOKUP(A64,'CENTRO DE COSTOS'!A:D,4,FALSE) -> KEVIN ALEXIS CORZO BUSTOS | C64: =VLOOKUP(A64,'CENTRO DE COSTOS'!A:D,2,FALSE) -> 0004-0007 | D64: 41797 | E64: 2278833 | F64: FO-25-1066403 | G64: 45818.372 | H64: 45819.619 | I64: HUILA | J64: TESALIA | K64: BARRIO VENECIA TESALIA | L64: 54453 | M64: INCIDENTE | N64: REDEBAN | O64: CB UNO A UNO | Q64: CERRADO | R64: 10-06 SE ESCALA PARA VISITA, LLAMAR ANTES DE VISITAR Y CONFIRMAR DATOS, DIRECCION Y SOLICITUD 0 11-06 SE REALIZA FORMATEO , CONFIGURACIÓN Y SE INICIALIZA DATAFONO , SE CREA USUARIO Y CLAVE CON EL CLIENTE, SE REALIZA PRUEBAS OK | S64: ANDRADE HERNANDEZ JUAN CARLOS | T64: VISITA_TÉCNICA | U64: XP5ZZ733 | V64: NO | W64: USUARIO | X64: COMUNICACION | Y64: CONEXIONES DE COMERCIO | Z64: No | AA64: 0 | AB64: 0 | AC64: 0 | AD64: 0 | AE64: 0 | AF64: =VLOOKUP(D64,TIPOLOGIAS!A:H,6,0) -> TIPO II | AG64: =VLOOKUP(D64,TIPOLOGIAS!A:H,5,0) -> TERRESTRE | AH64: 1 | AI64: 0 | AJ64: 0 | AK64: 0 | AL64: =IF(T64="SOPORTE_TELEFÓNICO",'BASE LIQUIDACION'!$B$10,IF(AF64="TIPO I",'BASE LIQUIDACION'!$C$3,IF(AF64="TIPO II",'BASE LIQUIDACION'!$C$4,IF(AF64="TIPO III",'BASE LIQUIDACION'!$C$5,'BASE LIQUIDACION'!$C$7)))) -> 163813.56 | AM64: =IF(T64="SOPORTE_TELEFÓNICO",'BASE LIQUIDACION'!$B$10,(AH64*AL64+AI64*'BASE LIQUIDACION'!$B$12+AJ64*'BASE LIQUIDACION'!$B$11+INCIDENTES!AK64*'BASE LIQUIDACION'!$B$13)) -> 163813.56
A65: CUCUTA | B65: =VLOOKUP(A65,'CENTRO DE COSTOS'!A:D,4,FALSE) -> MIGUEL JULIÁN HERNÁNDEZ GUARÍN | C65: =VLOOKUP(A65,'CENTRO DE COSTOS'!A:D,2,FALSE) -> 0004-0008 | D65: 54874 | E65: 2284339 | F65: FO-25-1070683 | G65: 45818.735 | H65: 45819.667 | I65: NORTE DE SANTANDER | J65: VILLA DEL ROSARIO | K65: PTM VILLA DEL ROSARIO PAPELERI | L65: 78996 | M65: INCIDENTE | N65: REDEBAN | O65: AGREGADOR | Q65: CERRADO | R65: 10-06 SE ESCALA PARA VISITA. LLAMAR ANTES DE VISITAR, CONFIRMAR FALLA Y DATOS 0 11-06 SE REALIZA VISITA, SE ENCUENTRA CONEXIÓN DEL COMERCIO MAL CONECTADO, SE REALIZAN PRUEBAS Y CIERRES OK. | S65: PACHECO BUITRAGO JAVIER ALONSO | T65: VISITA_TÉCNICA | U65: FATZZ900-FATZZ535 | V65: NO | W65: USUARIO | X65: COMUNICACION | Y65: CONEXIONES DE COMERCIO | Z65: No | AA65: 0 | AB65: 0 | AC65: 0 | AD65: 0 | AE65: 0 | AF65: =VLOOKUP(D65,TIPOLOGIAS!A:H,6,0) -> TIPO I | AG65: =VLOOKUP(D65,TIPOLOGIAS!A:H,5,0) -> TERRESTRE | AH65: 1 | AI65: 0 | AJ65: 0 | AK65: 0 | AL65: =IF(T65="SOPORTE_TELEFÓNICO",'BASE LIQUIDACION'!$B$10,IF(AF65="TIPO I",'BASE LIQUIDACION'!$C$3,IF(AF65="TIPO II",'BASE LIQUIDACION'!$C$4,IF(AF65="TIPO III",'BASE LIQUIDACION'!$C$5,'BASE LIQUIDACION'!$C$7)))) -> 65960.474 | AM65: =IF(T65="SOPORTE_TELEFÓNICO",'BASE LIQUIDACION'!$B$10,(AH65*AL65+AI65*'BASE LIQUIDACION'!$B$12+AJ65*'BASE LIQUIDACION'!$B$11+INCIDENTES!AK65*'BASE LIQUIDACION'!$B$13)) -> 65960.474
A66: MEDELLIN | B66: =VLOOKUP(A66,'CENTRO DE COSTOS'!A:D,4,FALSE) -> JUAN SEBASTIÁN RÍOS CASTRILLÓN | C66: =VLOOKUP(A66,'CENTRO DE COSTOS'!A:D,2,FALSE) -> 0004-0005 | D66: 27001 | E66: 2268184 | F66: FO-25-1056510 | G66: 45815.381 | H66: 45819.747 | I66: CHOCO | J66: QUIBDO | K66: BARRIO VILLA LA PAZ CORREGIMIE | L66: 66808 | M66: INCIDENTE | N66: REDEBAN | O66: CB UNO A UNO | Q66: CERRADO | R66: 07-06 SE LLAMA AL 3108257270; SE REALIZA CONTACTO CON USUARIO, SE CONFIRMA DATOS Y FALLA, CB INFORMA QUE YA LE FUNCIONA PERO ES CONSTANTE QUE SE LE QUEDE SIN CONEXION Y EL INTERNET FUNCIONA BIEN EN LOS OTROS EQUIPOS, SE ESCALA PARA VISITA. LLAMAR ANTES DE VISITAR 10/06/2025 EN SITIO SE PRESENTAN PROBLEMAS DE CANAL. USUARIA INFORMA QUE EL DÍA LUNES EL PROVEEDOR DE INTERNET ESTUVO MUY INTERMITENTE TODO EL DÍA Y DEBIDO A ESTO HAN SIDO LAS NOVEDADES DE CONEXIÓN EN EL SECTOR. SE ACUERDA CON USUARIA SEGUIMIENTO Y ESPERA HASTA EL DÍA DE MAÑANA QUE EL PROVEEDOR SOLUCIONE LA NOVEDAD PARA CONFIRMAR SI ES PROBLEMA DE DATAFONO FINALMENTE. VISITA PENDIENTE. 11-06 SE REALIZA VISITA Y SE CONFIRMA CORRECTO FUNCIONAMIENTO DEL EQUIPO Y DEL MÁGIC BOX, SE DETECTA FALLA DE PARTE DE CONEXION DEL COMERCIO | S66: QUINTERO SANCHEZ JUAN SEBASTIAN | T66: VISITA_TÉCNICA | U66: 3A0CZ768 | V66: NO | W66: USUARIO | X66: COMUNICACION | Y66: CANAL DEL COMERCIO | Z66: No | AA66: 0 | AB66: 0 | AC66: 0 | AD66: 0 | AE66: 0 | AF66: =VLOOKUP(D66,TIPOLOGIAS!A:H,6,0) -> TIPO IV ESPECIAL | AG66: =VLOOKUP(D66,TIPOLOGIAS!A:H,5,0) -> AEREO | AH66: 1 | AI66: 0 | AJ66: 0 | AK66: 0 | AL66: =IF(T66="SOPORTE_TELEFÓNICO",'BASE LIQUIDACION'!$B$10,IF(AF66="TIPO I",'BASE LIQUIDACION'!$C$3,IF(AF66="TIPO II",'BASE LIQUIDACION'!$C$4,IF(AF66="TIPO III",'BASE LIQUIDACION'!$C$5,'BASE LIQUIDACION'!$C$7)))) -> 479589.74 | AM66: =IF(T66="SOPORTE_TELEFÓNICO",'BASE LIQUIDACION'!$B$10,(AH66*AL66+AI66*'BASE LIQUIDACION'!$B$12+AJ66*'BASE LIQUIDACION'!$B$11+INCIDENTES!AK66*'BASE LIQUIDACION'!$B$13)) -> 479589.74
A67: SINCELEJO | B67: =VLOOKUP(A67,'CENTRO DE COSTOS'!A:D,4,FALSE) -> JOSE MAURICIO HERNANDEZ ROJAS | C67: =VLOOKUP(A67,'CENTRO DE COSTOS'!A:D,2,FALSE) -> 0004-0001 | D67: 70001 | E67: 2286271 | F67: FO-25-1073681 | G67: 45819.373 | H67: 45820.317 | I67: SUCRE | J67: SINCELEJO | K67: BARRIO PIONEROS SINCELEJO 4 | L67: 77185 | M67: INCIDENTE | N67: REDEBAN | O67: CB UNO A UNO | Q67: CERRADO | R67: 11-06 SE ESCALA PARA VISITA. LLAMAR ANTES DE VISITAR, CONFIRMAR FALLA Y DATOS 0 11-06 SE VISITA COMERCIO POR FALLA, SE CONFIGURA DATÁFONO NUEVAMENTE, SE DEJA CON LA VERSIÓN 9.90, SE REALIZAN PRUEBAS OK DEL COMERCIO, NO SE REALIZAN PRUEBAS DEL CB YA QUE SE ENCUENTRA BLOQUEADO POR PARTE DE LA ENTIDAD, SE LLAMO ALA LÍNEA Y LE INFORMARON QUE HASTA EL DÍA DE MAÑANA NO SE HABILITA, COMERCIO MIXTO CU: 22684591 TERMINAL: FAEZZ033. | S67: CACERES HERNANDEZ ANDRES | T67: VISITA_TÉCNICA | U67: FAEZZ033 - SX6ZZ444 | V67: NO | W67: ENTIDAD | X67: ERROR DE TRANSACCIONES | Y67: TRANSACCION NO PERMITIDA | Z67: No | AA67: 0 | AB67: 0 | AC67: 0 | AD67: 0 | AE67: 0 | AF67: =VLOOKUP(D67,TIPOLOGIAS!A:H,6,0) -> TIPO I | AG67: =VLOOKUP(D67,TIPOLOGIAS!A:H,5,0) -> TERRESTRE | AH67: 1 | AI67: 0 | AJ67: 0 | AK67: 0 | AL67: =IF(T67="SOPORTE_TELEFÓNICO",'BASE LIQUIDACION'!$B$10,IF(AF67="TIPO I",'BASE LIQUIDACION'!$C$3,IF(AF67="TIPO II",'BASE LIQUIDACION'!$C$4,IF(AF67="TIPO III",'BASE LIQUIDACION'!$C$5,'BASE LIQUIDACION'!$C$7)))) -> 65960.474 | AM67: =IF(T67="SOPORTE_TELEFÓNICO",'BASE LIQUIDACION'!$B$10,(AH67*AL67+AI67*'BASE LIQUIDACION'!$B$12+AJ67*'BASE LIQUIDACION'!$B$11+INCIDENTES!AK67*'BASE LIQUIDACION'!$B$13)) -> 65960.474
A68: VILLAVICENCIO | B68: =VLOOKUP(A68,'CENTRO DE COSTOS'!A:D,4,FALSE) -> KEVIN ALEXIS CORZO BUSTOS | C68: =VLOOKUP(A68,'CENTRO DE COSTOS'!A:D,2,FALSE) -> 0004-0007 | D68: 50001 | E68: 2290866 | F68: FO-25-1077032 | G68: 45819.68 | H68: 45820.485 | I68: META | J68: VILLAVICENCIO | K68: BARRIO PORVENIR VILLAVICENCIO | L68: 75353 | M68: INCIDENTE | N68: REDEBAN | O68: CB UNO A UNO | Q68: CERRADO | R68: 11-06 SE ESCALA PARA VISITA. LLAMAR ANTES DE VISITAR, CONFIRMAR FALLA Y DATOS 0 12-06 ME.COMUNICO CON CLIENTE LA SEÑORA TATIANA RIAÑO Y ME INFORMA QUE EL DIA DE HOY YA LE ESTA FUNCIONANDO CORRECTAMENTE EL DATAFONO. ERA UN PROBLEMA CON EL INTERNET DEL COMERCIO. INFORMAN QUE ESTAN HACIENDO TRANSACCIONES SIN NINGÚN PROBLEMA | S68: GARZON RUIZ LUIS MIGUEL | T68: SOPORTE_TELEFÓNICO | U68: 0 | V68: NO | W68: USUARIO | X68: COMUNICACION | Y68: CANAL DEL COMERCIO | Z68: No | AA68: 0 | AB68: 0 | AC68: 0 | AD68: 0 | AE68: 0 | AF68: =VLOOKUP(D68,TIPOLOGIAS!A:H,6,0) -> TIPO I | AG68: =VLOOKUP(D68,TIPOLOGIAS!A:H,5,0) -> TERRESTRE | AH68: 0 | AI68: 0 | AJ68: 0 | AK68: 0 | AL68: =IF(T68="SOPORTE_TELEFÓNICO",'BASE LIQUIDACION'!$B$10,IF(AF68="TIPO I",'BASE LIQUIDACION'!$C$3,IF(AF68="TIPO II",'BASE LIQUIDACION'!$C$4,IF(AF68="TIPO III",'BASE LIQUIDACION'!$C$5,'BASE LIQUIDACION'!$C$7)))) -> 37904.654 | AM68: =IF(T68="SOPORTE_TELEFÓNICO",'BASE LIQUIDACION'!$B$10,(AH68*AL68+AI68*'BASE LIQUIDACION'!$B$12+AJ68*'BASE LIQUIDACION'!$B$11+INCIDENTES!AK68*'BASE LIQUIDACION'!$B$13)) -> 37904.654
A69: BARRANQUILLA | B69: =VLOOKUP(A69,'CENTRO DE COSTOS'!A:D,4,FALSE) -> JOSE MAURICIO HERNANDEZ ROJAS | C69: =VLOOKUP(A69,'CENTRO DE COSTOS'!A:D,2,FALSE) -> 0004-0001 | D69: 8560 | E69: 2288579 | F69: FO-25-1075307 | G69: 45819.497 | H69: 45820.518 | I69: ATLANTICO | J69: PONEDERA | K69: PTM PONEDERA BABY JULI | L69: 56886 | M69: INCIDENTE | N69: REDEBAN | O69: AGREGADOR | Q69: CERRADO | R69: 11-06 SE ESCALA PARA VISITA. LLAMAR ANTES DE VISITAR, CONFIRMAR FALLA Y DATOS 0 12-06 SE REALIZA VISITA SE VALIDA DATAFONO ,LECTOR Y TODO OK ,CABLES OK , SE PROCEDE A REALIZAR PRUEBAS Y TODO OK ,POSIBLE MANIPULACIÓN DEL CLIENTE , SE LE INDICA COMO REALIZAR EL MANEJO PARA EL PAGO DE FACTURAS POR CÓDIGOS DE BARRAS, Y TODO OK CB OK OPERATIVO | S69: PORRAS CASTRO DARLON NASCK | T69: VISITA_TÉCNICA | U69: 9CQZZ644 | V69: NO | W69: USUARIO | X69: LECTOR DE BARRAS | Y69: CAPACITACION MANIPULACION DE COMERCIO | Z69: No | AA69: 0 | AB69: 0 | AC69: 0 | AD69: 0 | AE69: 0 | AF69: =VLOOKUP(D69,TIPOLOGIAS!A:H,6,0) -> TIPO II | AG69: =VLOOKUP(D69,TIPOLOGIAS!A:H,5,0) -> TERRESTRE | AH69: 1 | AI69: 0 | AJ69: 0 | AK69: 0 | AL69: =IF(T69="SOPORTE_TELEFÓNICO",'BASE LIQUIDACION'!$B$10,IF(AF69="TIPO I",'BASE LIQUIDACION'!$C$3,IF(AF69="TIPO II",'BASE LIQUIDACION'!$C$4,IF(AF69="TIPO III",'BASE LIQUIDACION'!$C$5,'BASE LIQUIDACION'!$C$7)))) -> 163813.56 | AM69: =IF(T69="SOPORTE_TELEFÓNICO",'BASE LIQUIDACION'!$B$10,(AH69*AL69+AI69*'BASE LIQUIDACION'!$B$12+AJ69*'BASE LIQUIDACION'!$B$11+INCIDENTES!AK69*'BASE LIQUIDACION'!$B$13)) -> 163813.56
A70: CALI | B70: =VLOOKUP(A70,'CENTRO DE COSTOS'!A:D,4,FALSE) -> DIEGO FERNANDO HENAO CARDONA | C70: =VLOOKUP(A70,'CENTRO DE COSTOS'!A:D,2,FALSE) -> 0004-0003 | D70: 76111 | E70: 2287072 | F70: FO-25-1074064 | G70: 45819.414 | H70: 45820.565 | I70: VALLE DEL CAUCA | J70: GUADALAJARA DE BUGA | K70: BARRIO CENTRO GUADALAJARA DE B | L70: 67292 | M70: INCIDENTE | N70: REDEBAN | O70: CB UNO A UNO | Q70: CERRADO | R70: 11-06 SE ESCALA PARA VISITA. LLAMAR ANTES DE VISITAR, CONFIRMAR FALLA Y DATOS 0 12-06 SE INICIALIZA TERMINAL DE EQUIPO DE CB BANCOLOMBIA PURO DEBIDO A HORA DESCONFIGURADA, SE REALIZAN PRUEBAS OK. | S70: MONTERO MUESES GIAN CARLO | T70: VISITA_TÉCNICA | U70: AAJ05746 | V70: NO | W70: USUARIO | X70: MANTENIMIENTO | Y70: MANTENIMIENTO GENERAL | Z70: No | AA70: 0 | AB70: 0 | AC70: 0 | AD70: 0 | AE70: 0 | AF70: =VLOOKUP(D70,TIPOLOGIAS!A:H,6,0) -> TIPO II | AG70: =VLOOKUP(D70,TIPOLOGIAS!A:H,5,0) -> TERRESTRE | AH70: 1 | AI70: 0 | AJ70: 0 | AK70: 0 | AL70: =IF(T70="SOPORTE_TELEFÓNICO",'BASE LIQUIDACION'!$B$10,IF(AF70="TIPO I",'BASE LIQUIDACION'!$C$3,IF(AF70="TIPO II",'BASE LIQUIDACION'!$C$4,IF(AF70="TIPO III",'BASE LIQUIDACION'!$C$5,'BASE LIQUIDACION'!$C$7)))) -> 163813.56 | AM70: =IF(T70="SOPORTE_TELEFÓNICO",'BASE LIQUIDACION'!$B$10,(AH70*AL70+AI70*'BASE LIQUIDACION'!$B$12+AJ70*'BASE LIQUIDACION'!$B$11+INCIDENTES!AK70*'BASE LIQUIDACION'!$B$13)) -> 163813.56
A71: BOGOTA | B71: =VLOOKUP(A71,'CENTRO DE COSTOS'!A:D,4,FALSE) -> WILLIAM ASDRUBAL ROZO ROZO | C71: =VLOOKUP(A71,'CENTRO DE COSTOS'!A:D,2,FALSE) -> 0004-0004 | D71: 25486 | E71: 2288553 | F71: FO-25-1075208 | G71: 45819.493 | H71: 45820.567 | I71: CUNDINAMARCA | J71: NEMOCON | K71: BARRIO VILLA LUZ NEMOCON | L71: 77905 | M71: INCIDENTE | N71: REDEBAN | O71: CB UNO A UNO | Q71: CERRADO | R71: 11-06 SE ESCALA PARA VISITA. LLAMAR ANTES DE VISITAR, CONFIRMAR FALLA Y DATOS 0 12-06 SE REALIZA VISITA A COMERCIO, SE REALIZA REVISIÓN DE CABLEADO FÍSICO SE ENCUENTRA OK, PRUEBAS DE COMUNICACIÓN DATAFONO OK, SE REALIZA ACOMPAÑAMIENTO DURANTE 20 MINUTOS PARA VALIDAR FUNCIONAMIENTO NO SE PRESENTAN FALLAS, PRUEBAS DE TRANSACCIONES OK, SE ENCUENTRA DATAFONO CONECTADO A EQUIPO DE RESPALDO DE ENERGÍA, SE CONECTA DIRECTO AL TOMA CORRIENTE Y NO PRESENTA FALLAS DE ENCENDIDO E REINICIO. | S71: MURCIA HERNANDEZ HARVEY IGNACIO | T71: VISITA_TÉCNICA | U71: A1MZZ089 | V71: NO | W71: USUARIO | X71: MANTENIMIENTO | Y71: MANTENIMIENTO GENERAL | Z71: No | AA71: 0 | AB71: 0 | AC71: 0 | AD71: 0 | AE71: 0 | AF71: =VLOOKUP(D71,TIPOLOGIAS!A:H,6,0) -> TIPO II | AG71: =VLOOKUP(D71,TIPOLOGIAS!A:H,5,0) -> TERRESTRE | AH71: 1 | AI71: 0 | AJ71: 0 | AK71: 0 | AL71: =IF(T71="SOPORTE_TELEFÓNICO",'BASE LIQUIDACION'!$B$10,IF(AF71="TIPO I",'BASE LIQUIDACION'!$C$3,IF(AF71="TIPO II",'BASE LIQUIDACION'!$C$4,IF(AF71="TIPO III",'BASE LIQUIDACION'!$C$5,'BASE LIQUIDACION'!$C$7)))) -> 163813.56 | AM71: =IF(T71="SOPORTE_TELEFÓNICO",'BASE LIQUIDACION'!$B$10,(AH71*AL71+AI71*'BASE LIQUIDACION'!$B$12+AJ71*'BASE LIQUIDACION'!$B$11+INCIDENTES!AK71*'BASE LIQUIDACION'!$B$13)) -> 163813.56
A72: BOGOTA | B72: =VLOOKUP(A72,'CENTRO DE COSTOS'!A:D,4,FALSE) -> WILLIAM ASDRUBAL ROZO ROZO | C72: =VLOOKUP(A72,'CENTRO DE COSTOS'!A:D,2,FALSE) -> 0004-0004 | D72: 25777 | E72: 2295174 | F72: FO-25-1081664 | G72: 45820.497 | H72: 45820.576 | I72: CUNDINAMARCA | J72: SUPATA | K72: BARRIO VEREDA LA MAGOLA SUPATA | L72: 26368 | M72: INCIDENTE | N72: REDEBAN | O72: CB UNO A UNO | Q72: CERRADO | R72: 12-06 SE ESCALA SOLICITUD A LA RED PARA VALIDAR SU ATENCION.. RESPUESTA DE LA RED: DE ACUERDO CON TU SOLICITUD POR FAVOR INDICARLE AL CLIENTE QUE DEBE COMUNICARSE CON LA ENTIDAD, SON ELLOS LOS ENCARGADOS DE GESTIONAR ESTE TIPO DE SOLICITUDES. PROCEDER CON EL CIERRE DEL CASO. 0 0 | S72: 0 | T72: SOPORTE_TELEFÓNICO | U72: 0 | V72: NO | W72: USUARIO | X72: MANTENIMIENTO | Y72: MANTENIMIENTO GENERAL | Z72: No | AA72: 0 | AB72: 0 | AC72: 0 | AD72: 0 | AE72: 0 | AF72: =VLOOKUP(D72,TIPOLOGIAS!A:H,6,0) -> TIPO II | AG72: =VLOOKUP(D72,TIPOLOGIAS!A:H,5,0) -> TERRESTRE | AH72: 0 | AI72: 0 | AJ72: 0 | AK72: 0 | AL72: =IF(T72="SOPORTE_TELEFÓNICO",'BASE LIQUIDACION'!$B$10,IF(AF72="TIPO I",'BASE LIQUIDACION'!$C$3,IF(AF72="TIPO II",'BASE LIQUIDACION'!$C$4,IF(AF72="TIPO III",'BASE LIQUIDACION'!$C$5,'BASE LIQUIDACION'!$C$7)))) -> 37904.654 | AM72: =IF(T72="SOPORTE_TELEFÓNICO",'BASE LIQUIDACION'!$B$10,(AH72*AL72+AI72*'BASE LIQUIDACION'!$B$12+AJ72*'BASE LIQUIDACION'!$B$11+INCIDENTES!AK72*'BASE LIQUIDACION'!$B$13)) -> 37904.654
A73: MEDELLIN | B73: =VLOOKUP(A73,'CENTRO DE COSTOS'!A:D,4,FALSE) -> JUAN SEBASTIÁN RÍOS CASTRILLÓN | C73: =VLOOKUP(A73,'CENTRO DE COSTOS'!A:D,2,FALSE) -> 0004-0005 | D73: 5440 | E73: 2287976 | F73: FO-25-1074802 | G73: 45819.46 | H73: 45820.66 | I73: ANTIOQUIA | J73: MARINILLA | K73: DISTRICOL CAFE JUANITA | L73: 52755 | M73: INCIDENTE | N73: REDEBAN | O73: AGREGADOR | Q73: CERRADO | R73: 11-06 SE ESCALA PARA VISITA. LLAMAR ANTES DE VISITAR, CONFIRMAR FALLA Y DATOS 0 12-06 SE LLAMA A CLIENTE PARA CONFIRMAR VISITA Y EL SEÑOR LUIS DAVID MUÑOZ COMENTA QUE SE COMUNICÓ A LA LINEA FUE A SOLICITAR ROLLOS PARA EL DATAFONO NO A PEDIR SERVICIO TÉCNICO. SE LE INDICA QUE LLAME NUEVAMENTE A SOLICITAR. | S73: BADEL ACUÑA LUIS ALBERTO | T73: SOPORTE_TELEFÓNICO | U73: 0 | V73: NO | W73: USUARIO | X73: MANTENIMIENTO | Y73: MANTENIMIENTO GENERAL | Z73: No | AA73: 0 | AB73: 0 | AC73: 0 | AD73: 0 | AE73: 0 | AF73: =VLOOKUP(D73,TIPOLOGIAS!A:H,6,0) -> TIPO II | AG73: =VLOOKUP(D73,TIPOLOGIAS!A:H,5,0) -> TERRESTRE | AH73: 0 | AI73: 0 | AJ73: 0 | AK73: 0 | AL73: =IF(T73="SOPORTE_TELEFÓNICO",'BASE LIQUIDACION'!$B$10,IF(AF73="TIPO I",'BASE LIQUIDACION'!$C$3,IF(AF73="TIPO II",'BASE LIQUIDACION'!$C$4,IF(AF73="TIPO III",'BASE LIQUIDACION'!$C$5,'BASE LIQUIDACION'!$C$7)))) -> 37904.654 | AM73: =IF(T73="SOPORTE_TELEFÓNICO",'BASE LIQUIDACION'!$B$10,(AH73*AL73+AI73*'BASE LIQUIDACION'!$B$12+AJ73*'BASE LIQUIDACION'!$B$11+INCIDENTES!AK73*'BASE LIQUIDACION'!$B$13)) -> 37904.654
