Workbook
Name A: #REF!
Name A: #REF!
Name ACTIVIDAD: [1]Hoja2!$P$2:$P$30
Name Actividad: [2]Formulas!$H$2:$H$5000
Name Analistas: '[3]Listas Desplegables'!$T$2:$T$7
Name arearesponsable: '[4]Listas desplegables'!$BB$2:$BB$100
Name CCO: [5]Tecnicos!$A$2:$A$1000
Name Clientes: [6]Clientes!$A$2:$A$100
Name Clientes: [2]Clientes!$A$2:$A$100
Name COORDINADOR: [1]Hoja2!$D$2:$D$30
Name Coordinadores: [7]Coordinadores!$A$2:$A$1000
Name Coordinadores: [2]Coordinadores!$A$2:$A$1000
Name DOCUMENTADOR: [1]Hoja2!$A$2:$A$30
Name ES: [1]Hoja2!$K$2:$K$30
Name ESS: [1]Hoja2!$K$2:$K$30
Name Estado: [6]Formulas!$K$2:$K$5000
Name Estado: [2]Formulas!$K$2:$K$5000
Name ESTADOACTIVIDAD: [1]Hoja2!$M$2:$M$30
Name ESTADOS: '[8]Listas desplegables'!$B$1:$D$1
Name ESTADOS: '[9]Listas desplegables'!$B$1:$D$1
Name ESTADOSCIERRES: '[10]lista desplegable'!$CX$1:$DA$1
Name Facturacion: '[11]Listas desplegables'!$AO$1:$AR$1
Name FACTURACIÓN: '[8]Listas desplegables'!$Y$1:$AB$1
Name FACTURACIÓN: '[9]Listas desplegables'!$Y$1:$AB$1
Name falla: #REF!
Name Fallas: '[12]Listas desplegables'!$F$2:$L$2
Name Fallas: '[13]Listas desplegables'!$F$2:$L$2
Name Grupo_Falla: '[14]Listas Desplegables'!$CH$2:$CH$5
Name Grupo_Falla: '[15]Listas Desplegables'!$CH$2:$CH$5
Name inconservmanager: '[16]Listas desplegables'!$BC$2:$BC$100
Name inconservmanager: '[4]Listas desplegables'!$BC$2:$BC$100
Name INCUMPLIMIENTO: '[4]Listas desplegables'!$AK$1:$AN$1
Name INCUMPLIMIENTO: '[17]Listas desplegables'!$AT$1:$AX$1
Name LISTA: [18]Dptos!$A$1139:$A$1171
Name LISTA: [19]Dptos!$A$1139:$A$1171
Name LISTA2: #REF!
Name LISTA2: #REF!
Name LOLO: [20]Coordinadores!$A$2:$A$1000
Name solicitudes: '[11]Listas desplegables'!$U$1:$AF$1
Name solicitudes: '[21]Listas desplegables'!$AF$1:$AQ$1
Name Tecnicos: [6]Tecnicos!$A$2:$A$1000
Name Tecnicos: [2]Tecnicos!$A$2:$A$1000
Name Version: [22]Formulas!$I$2:$I$3
Name Version: [2]Formulas!$I$2:$I$3

Sheet Detalle REDEBAN
A1: FACTURACIÓN ACTIVIDADES REDEBAN CB BANCOLOMBIA Y AVAL
A2: 1 AL 30 DE JUNIO 2025
A4: CONCEPTOS | B4: CANTIDAD | C4: TOTAL
A5: Aperturas Bancolombia | B5: =COUNTA('APERTURAS BANCOLOMBIA'!$A:$A)-1 -> 512 | C5: ='APERTURAS BANCOLOMBIA'!AK514 -> 88508256
A6: Incidentes Bancolombia | B6: =COUNTA('INCIDENTES BANCOLOMBIA'!A:A)-1 -> 1087 | C6: ='INCIDENTES BANCOLOMBIA'!AM1089 -> 1.7392227e+08
A7: Gestión de Campo Bancolombia | B7: =COUNTA('OC BANCOLOMBIA'!A:A)-1 -> 504 | C7: ='OC BANCOLOMBIA'!AK506 -> 76580751
A8: Soporte Papelería Bancolombia | B8: =COUNTA(PAPELERIA!A:A)-1 -> 971 | C8: =PAPELERIA!AF973 -> 41393662
A9: Aperturas Aval | B9: =COUNTA('APERTURAS AVAL'!A:A)-1 -> 236 | C9: ='APERTURAS AVAL'!AJ238 -> 40577199
A10: Incidentes Aval | B10: =COUNTA('INCIDENTES AVAL'!A:A)-1 -> 308 | C10: ='INCIDENTES AVAL'!AO310 -> 36230429
A11: Gestión de Campo Aval | B11: =COUNTA('OC AVAL'!A:A)-1 -> 132 | C11: ='OC AVAL'!AF134 -> 15917098
A12: Aperturas BBVA | B12: =COUNTA('APERTURAS BBVA'!A:A)-1 -> 0 | C12: ='APERTURAS BBVA'!AH3 -> 0
A13: Gestión de Campo BBVA | B13: =COUNTA('OC BBVA'!A:A)-1 -> 2 | C13: ='OC BBVA'!AO4 -> 289935.74
A14: Incidentes BBVA | B14: =COUNTA('INCIDENTES BBVA'!A:A)-1 -> 0 | C14: ='INCIDENTES BBVA'!AN4 -> 0
A15: SUBTOTAL | C15: =SUM(C5:C14) -> 4.734196e+08
A16: Iva | C16: =C15*0.19 -> 89949724
A17: TOTAL | B17: TOTAL | C17: =C15+C16 -> 5.6336933e+08

Sheet BASE LIQUIDACION REDEBAN 2025
A1: Tipificación | B1: Implementaciones | C1: Incidentes – Ordenes de Cambio | D1: Fallida | G1: Tipificación | H1: Actividad sin cambio de datafono | J1: Actividad + adicional cambio de datafono | L1: Visita Fallida | N1: Incremento 2025
A2: TIPO I | B2: =71384.4052*(1+$N$2) -> 75096.394 | C2: =62699.6885*(1+$N$2) -> 65960.072 | D2: =35693.4343*(1+$N$2) -> 37549.493 | H2: Instalación Pinpad + HUB | I2: Segunda actividad en mismo comercio, misma visita | J2: Instalación Pinpad + HUB | K2: Segunda actividad en mismo comercio, misma visita | N2: 0.052
A3: TIPO II | B3: =155716.4408*(1+$N$2) -> 163813.7 | C3: =137802.16*(1+$N$2) -> 144967.87 | D3: =117879.8485*(1+$N$2) -> 124009.6 | G3: Tipo I | H3: =31819.23994686*(1+$N$2) -> 33473.84 | I3: =26222.67548178*(1+$N$2) -> 27586.255 | J3: =51196.46628516*(1+$N$2) -> 53858.683 | K3: =42157.66342524*(1+$N$2) -> 44349.862 | L3: =28948.10610808*(1+$N$2) -> 30453.408
A4: TIPO III | B4: =262099.6015*(1+$N$2) -> 275728.78 | C4: =262099.6015*(1+$N$2) -> 275728.78 | D4: =262099.6015*(1+$N$2) -> 275728.78 | G4: Tipo II | H4: =98014.03066668*(1+$N$2) -> 103110.76 | I4: =26222.67548178*(1+$N$2) -> 27586.255 | J4: =119562.49505524*(1+$N$2) -> 125779.74 | K4: =42157.66342524*(1+$N$2) -> 44349.862 | L4: =94765.6295813*(1+$N$2) -> 99693.442
A5: TIPO IV | B5: =479878.9419*(1+$N$2) -> 504832.65 | C5: =455882.9625*(1+$N$2) -> 479588.88 | D5: =370911.6746*(1+$N$2) -> 390199.08 | G5: Tipo III | H5: =189140.9827006*(1+$N$2) -> 198976.31 | I5: =26222.67548178*(1+$N$2) -> 27586.255 | J5: =200461.60194168*(1+$N$2) -> 210885.61 | K5: =42157.66342524*(1+$N$2) -> 44349.862 | L5: =171492.68108896*(1+$N$2) -> 180410.3
A6: Destino Aéreo | B6: =939603.5767*(1+$N$2) -> 988462.96 | C6: a partir del 5to servicio | G6: Tipo IV | H6: =461621.60109668*(1+$N$2) -> 485625.92 | I6: =26222.67548178*(1+$N$2) -> 27586.255 | J6: =461621.60109668*(1+$N$2) -> 485625.92 | K6: =42157.66342524*(1+$N$2) -> 44349.862 | L6: =461621.60109668*(1+$N$2) -> 485625.92
G7: * Tipo IV Especial Donde se requiera desplazamiento aéreo o fluvial será facturado el valor de la actividad y adicional el valor de $988.463 por cada 5 actividades de esta tipología
A8: Tarifas para día adicional de actividades:
A9: Tipificación | B9: Día adicional- menos de dos horas | C9: Medio día adicional | D9: Día adicional- más de 4 horas
A10: Tipo I | B10: =71384.4052*(1+$N$2) -> 75096.394 | C10: =133455.9267*(1+$N$2) -> 140395.63 | D10: =191225.1201*(1+$N$2) -> 201168.83 | G10: Actividad | H10: Unidad | I10: Valor Unitario
A11: Tipo II | B11: =133455.9267*(1+$N$2) -> 140395.63 | C11: =191225.1201*(1+$N$2) -> 201168.83 | D11: =257740.6152*(1+$N$2) -> 271143.13 | G11: Gestión telefónica y cierre de incidente de bloqueo | H11: Unidad | I11: =17639.19516086*(1+$N$2) -> 18556.433
A12: Tipo III | B12: =186821.7926*(1+$N$2) -> 196536.53 | C12: =248892.0824*(1+$N$2) -> 261834.47 | D12: =306662.5075*(1+$N$2) -> 322608.96 | G12: Servicio de cierre de incidente de bloqueo | H12: Unidad | I12: =4810.80785492*(1+$N$2) -> 5060.9699
A13: Tipo IV | B13: =186821.7926*(1+$N$2) -> 196536.53 | C13: =248892.0824*(1+$N$2) -> 261834.47 | D13: =306662.5075*(1+$N$2) -> 322608.96
A16: Servicio | B16: Tarifa actividad | D16: VALOR DE LA TERMINAL ADICIONAL | E16: VALOR DE INSTALACIÓN DE BASE EN "Y"
A17: Papelería – Tarifa única | B17: =34010.9321*(1+$N$2) -> 35779.501 | D17: =20537.3658*(1+$N$2) -> 21605.309 | E17: =10737.9606*(1+$N$2) -> 11296.335
A18: Papelería Tipo II - Visita técnica | B18: =64310*(1+$N$2) -> 67654.12
A19: Solución telefónica | B19: =39202.5476*(1+$N$2) -> 41241.08
A22: Traifas 2024
A23: Tipificación | B23: Implementaciones | C23: Incidentes – Ordenes de Cambio | D23: Fallida | G23: Tipificación | H23: Actividad sin cambio de datafono | J23: Actividad + adicional cambio de datafono | L23: Visita Fallida
A24: TIPO I | B24: 71384.405 | C24: 62699.689 | D24: 35693.434 | H24: Instalación Pinpad + HUB | I24: Segunda actividad en mismo comercio, misma visita | J24: Instalación Pinpad + HUB | K24: Segunda actividad en mismo comercio, misma visita
A25: TIPO II | B25: 155716.44 | C25: 137802.16 | D25: 117879.85 | G25: Tipo I | H25: 31819.24 | I25: 26222.675 | J25: 51196.466 | K25: 42157.663 | L25: 28948.106
A26: TIPO III | B26: 262099.6 | C26: 262099.6 | D26: 262099.6 | G26: Tipo II | H26: 98014.031 | I26: 26222.675 | J26: 119562.5 | K26: 42157.663 | L26: 94765.63
A27: TIPO IV | B27: 479878.94 | C27: 455882.96 | D27: 370911.67 | G27: Tipo III | H27: 189140.98 | I27: 26222.675 | J27: 200461.6 | K27: 42157.663 | L27: 171492.68
A28: Destino Aéreo | B28: 939603.58 | C28: a partir del 5to servicio | G28: Tipo IV | H28: 461621.6 | I28: 26222.675 | J28: 461621.6 | K28: 42157.663 | L28: 461621.6
G29: * Tipo IV Especial Donde se requiera desplazamiento aéreo o fluvial será facturado el valor de la actividad y adicional el valor de $939,604 por cada 5 actividades de esta tipología
A30: Tarifas para día adicional de actividades:
A31: Tipificación | B31: Día adicional- menos de dos horas | C31: Medio día adicional | D31: Día adicional- más de 4 horas
A32: Tipo I | B32: 71384.405 | C32: 133455.93 | D32: 191225.12 | G32: Actividad | H32: Unidad | I32: Valor Unitario
A33: Tipo II | B33: 133455.93 | C33: 191225.12 | D33: 257740.62 | G33: Gestión telefónica y cierre de incidente de bloqueo | H33: Unidad | I33: 17639.195
A34: Tipo III | B34: 186821.79 | C34: 248892.08 | D34: 306662.51 | G34: Servicio de cierre de incidente de bloqueo | H34: Unidad | I34: 4810.8079
A35: Tipo IV | B35: 186821.79 | C35: 248892.08 | D35: 306662.51
A38: Servicio | B38: Tarifa actividad | D38: VALOR DE LA TERMINAL ADICIONAL | E38: VALOR DE INSTALACIÓN DE BASE EN "Y"
A39: Papelería – Tarifa única | B39: 34010.932 | D39: 20537.366 | E39: 10737.961
A40: Papelería Tipo II - Visita técnica | B40: 64310
A41: Solución telefónica | B41: 39202.548

Sheet CENTRO DE COSTOS
A1: CIUDAD | B1: CENTRO_COSTO | C1: DESCRIPCION | D1: COORDINADOR
A2: APARTADO | B2: 0004-0005 | C2: Redeban Noroccidente (Medellín) | D2: JUAN SEBASTIÁN RÍOS CASTRILLÓN
A3: BARRANQUILLA | B3: 0004-0001 | C3: Redeban Costa (Barranqullla) | D3: JOSE MAURICIO HERNANDEZ ROJAS
A4: BOGOTA | B4: 0004-0004 | C4: Redeban Centro ( Bogotá) | D4: WILLIAM ASDRUBAL ROZO ROZO
A5: BUCARAMANGA | B5: 0004-0008 | C5: Redeban Santander | D5: MIGUEL JULIÁN HERNÁNDEZ GUARÍN
A6: CALI | B6: 0004-0003 | C6: Redeban Suroccidente (Cali) | D6: DIEGO FERNANDO HENAO CARDONA
A7: CARTAGENA | B7: 0004-0001 | C7: Redeban Costa (Barranqullla) | D7: JOSE MAURICIO HERNANDEZ ROJAS
A8: CUCUTA | B8: 0004-0008 | C8: Redeban Santander | D8: MIGUEL JULIÁN HERNÁNDEZ GUARÍN
A9: FLORENCIA | B9: 0004-0007 | C9: Redeban Oriente (Otros) | D9: KEVIN ALEXIS CORZO BUSTOS
A10: IBAGUE | B10: 0004-0007 | C10: Redeban Oriente (Otros) | D10: KEVIN ALEXIS CORZO BUSTOS
A11: MANIZALES | B11: 0004-0002 | C11: Redeban Eje Cafetero (Pereira) | D11: DIEGO FERNANDO HENAO CARDONA
A12: MEDELLIN | B12: 0004-0005 | C12: Redeban Noroccidente (Medellín) | D12: JUAN SEBASTIÁN RÍOS CASTRILLÓN
... A23: YOPAL | B23: 0004-0007 | C23: Redeban Oriente (Otros) | D23: KEVIN ALEXIS CORZO BUSTOS

Sheet Tablas dinámicas
A1: APERTURAS BANCOLOMBIA | G1: NOMBRE DE CC | H1: Suma de VALOR CC | I1: Suma de VALOR CC2
A2: COORDINADOR | B2: CENTRO DE COSTOS | C2: Suma de VALOR FACTURABLE A LA RED | D2: NOMBRE DE CC | E2: VALOR CC | G2: Redeban Centro ( Bogotá) | H2: 57891327 | I2: 0.12228333
A3: DIEGO FERNANDO HENAO CARDONA | B3: 0004-0002 | C3: 4042347.6 | D3: =VLOOKUP(B3,'CENTRO DE COSTOS'!B:C,2,0) -> Redeban Eje Cafetero (Pereira) | E3: =C3 -> 4042347.6 | G3: Redeban Costa (Barranqullla) | H3: 73951110 | I3: 0.15620627
B4: 0004-0003 | C4: 16115364 | D4: =VLOOKUP(B4,'CENTRO DE COSTOS'!B:C,2,0) -> Redeban Suroccidente (Cali) | E4: =C4 -> 16115364 | G4: Redeban Eje Cafetero (Pereira) | H4: 20201376 | I4: 0.042671186
A5: JOSE MAURICIO HERNANDEZ ROJAS | B5: 0004-0001 | C5: 14611827 | D5: =VLOOKUP(B5,'CENTRO DE COSTOS'!B:C,2,0) -> Redeban Costa (Barranqullla) | E5: =C5 -> 14611827 | G5: Redeban Noroccidente (Medellín) | H5: 94649348 | I5: 0.19992697
A6: JUAN SEBASTIÁN RÍOS CASTRILLÓN | B6: 0004-0005 | C6: 17750937 | D6: =VLOOKUP(B6,'CENTRO DE COSTOS'!B:C,2,0) -> Redeban Noroccidente (Medellín) | E6: =C6 -> 17750937 | G6: Redeban Oriente (Otros) | H6: 77158103 | I6: 0.16298037
A7: KEVIN ALEXIS CORZO BUSTOS | B7: 0004-0007 | C7: 13719277 | D7: =VLOOKUP(B7,'CENTRO DE COSTOS'!B:C,2,0) -> Redeban Oriente (Otros) | E7: =C7 -> 13719277 | G7: Redeban Santander | H7: 87798894 | I7: 0.18545682
A8: MIGUEL JULIÁN HERNÁNDEZ GUARÍN | B8: 0004-0008 | C8: 13834110 | D8: =VLOOKUP(B8,'CENTRO DE COSTOS'!B:C,2,0) -> Redeban Santander | E8: =C8 -> 13834110 | G8: Redeban Suroccidente (Cali) | H8: 61769445 | I8: 0.13047505
A9: WILLIAM ASDRUBAL ROZO ROZO | B9: 0004-0004 | C9: 8434394.3 | D9: =VLOOKUP(B9,'CENTRO DE COSTOS'!B:C,2,0) -> Redeban Centro ( Bogotá) | E9: =C9 -> 8434394.3 | G9: Total general | H9: 4.734196e+08 | I9: 1
A10: Total general | C10: 88508256
A15: INCIDENTES BANCOLOMBIA
A16: COORDINADOR | B16: CENTRO DE COSTOS | C16: Suma de VALOR FACTURABLE A LA RED | D16: NOMBRE DE CC | E16: VALOR CC
A17: DIEGO FERNANDO HENAO CARDONA | B17: 0004-0002 | C17: 6532633.7 | D17: =VLOOKUP(B17,'CENTRO DE COSTOS'!B:C,2,0) -> Redeban Eje Cafetero (Pereira) | E17: =C17 -> 6532633.7
B18: 0004-0003 | C18: 19798837 | D18: =VLOOKUP(B18,'CENTRO DE COSTOS'!B:C,2,0) -> Redeban Suroccidente (Cali) | E18: =C18 -> 19798837
A19: JOSE MAURICIO HERNANDEZ ROJAS | B19: 0004-0001 | C19: 29495276 | D19: =VLOOKUP(B19,'CENTRO DE COSTOS'!B:C,2,0) -> Redeban Costa (Barranqullla) | E19: =C19 -> 29495276
A20: JUAN SEBASTIÁN RÍOS CASTRILLÓN | B20: 0004-0005 | C20: 41891791 | D20: =VLOOKUP(B20,'CENTRO DE COSTOS'!B:C,2,0) -> Redeban Noroccidente (Medellín) | E20: =C20 -> 41891791
A21: KEVIN ALEXIS CORZO BUSTOS | B21: 0004-0007 | C21: 29538126 | D21: =VLOOKUP(B21,'CENTRO DE COSTOS'!B:C,2,0) -> Redeban Oriente (Otros) | E21: =C21 -> 29538126
A22: MIGUEL JULIÁN HERNÁNDEZ GUARÍN | B22: 0004-0008 | C22: 28604867 | D22: =VLOOKUP(B22,'CENTRO DE COSTOS'!B:C,2,0) -> Redeban Santander | E22: =C22 -> 28604867
A23: WILLIAM ASDRUBAL ROZO ROZO | B23: 0004-0004 | C23: 18060740 | D23: =VLOOKUP(B23,'CENTRO DE COSTOS'!B:C,2,0) -> Redeban Centro ( Bogotá) | E23: =C23 -> 18060740
A24: Total general | C24: 1.7392227e+08
A30: ORDENES DE CAMBIO BANCOLOMBIA
A31: COORDINADOR | B31: CENTRO DE COSTOS | C31: Suma de VALOR FACTURABLE A LA RED | D31: NOMBRE DE CC | E31: VALOR CC
A32: DIEGO FERNANDO HENAO CARDONA | B32: 0004-0002 | C32: 4000237.7 | D32: =VLOOKUP(B32,'CENTRO DE COSTOS'!B:C,2,0) -> Redeban Eje Cafetero (Pereira) | E32: =C32 -> 4000237.7
B33: 0004-0003 | C33: 9269370.8 | D33: =VLOOKUP(B33,'CENTRO DE COSTOS'!B:C,2,0) -> Redeban Suroccidente (Cali) | E33: =C33 -> 9269370.8
A34: JOSE MAURICIO HERNANDEZ ROJAS | B34: 0004-0001 | C34: 11963449 | D34: =VLOOKUP(B34,'CENTRO DE COSTOS'!B:C,2,0) -> Redeban Costa (Barranqullla) | E34: =C34 -> 11963449
A35: JUAN SEBASTIÁN RÍOS CASTRILLÓN | B35: 0004-0005 | C35: 13057799 | D35: =VLOOKUP(B35,'CENTRO DE COSTOS'!B:C,2,0) -> Redeban Noroccidente (Medellín) | E35: =C35 -> 13057799
A36: KEVIN ALEXIS CORZO BUSTOS | B36: 0004-0007 | C36: 11314313 | D36: =VLOOKUP(B36,'CENTRO DE COSTOS'!B:C,2,0) -> Redeban Oriente (Otros) | E36: =C36 -> 11314313
A37: MIGUEL JULIÁN HERNÁNDEZ GUARÍN | B37: 0004-0008 | C37: 14859474 | D37: =VLOOKUP(B37,'CENTRO DE COSTOS'!B:C,2,0) -> Redeban Santander | E37: =C37 -> 14859474
A38: WILLIAM ASDRUBAL ROZO ROZO | B38: 0004-0004 | C38: 12116106 | D38: =VLOOKUP(B38,'CENTRO DE COSTOS'!B:C,2,0) -> Redeban Centro ( Bogotá) | E38: =C38 -> 12116106
A39: Total general | C39: 76580751
A45: PAPELERIA BANCOLOMBIA
A46: COORDINADOR | B46: CENTRO DE COSTOS | C46: Suma de VALOR FACTURABLE A LA RED | D46: NOMBRE DE CC | E46: VALOR CC
A47: DIEGO FERNANDO HENAO CARDONA | B47: 0004-0002 | C47: 1666652.6 | D47: =VLOOKUP(B47,'CENTRO DE COSTOS'!B:C,2,0) -> Redeban Eje Cafetero (Pereira) | E47: =C47 -> 1666652.6
B48: 0004-0003 | C48: 6669879.6 | D48: =VLOOKUP(B48,'CENTRO DE COSTOS'!B:C,2,0) -> Redeban Suroccidente (Cali) | E48: =C48 -> 6669879.6
A49: JOSE MAURICIO HERNANDEZ ROJAS | B49: 0004-0001 | C49: 7453888.9 | D49: =VLOOKUP(B49,'CENTRO DE COSTOS'!B:C,2,0) -> Redeban Costa (Barranqullla) | E49: =C49 -> 7453888.9
A50: JUAN SEBASTIÁN RÍOS CASTRILLÓN | B50: 0004-0005 | C50: 11941816 | D50: =VLOOKUP(B50,'CENTRO DE COSTOS'!B:C,2,0) -> Redeban Noroccidente (Medellín) | E50: =C50 -> 11941816
A51: KEVIN ALEXIS CORZO BUSTOS | B51: 0004-0007 | C51: 3482961.8 | D51: =VLOOKUP(B51,'CENTRO DE COSTOS'!B:C,2,0) -> Redeban Oriente (Otros) | E51: =C51 -> 3482961.8
A52: MIGUEL JULIÁN HERNÁNDEZ GUARÍN | B52: 0004-0008 | C52: 6474091.4 | D52: =VLOOKUP(B52,'CENTRO DE COSTOS'!B:C,2,0) -> Redeban Santander | E52: =C52 -> 6474091.4
A53: WILLIAM ASDRUBAL ROZO ROZO | B53: 0004-0004 | C53: 3704371.5 | D53: =VLOOKUP(B53,'CENTRO DE COSTOS'!B:C,2,0) -> Redeban Centro ( Bogotá) | E53: =C53 -> 3704371.5
A54: Total general | C54: 41393662
A60: APERTURAS BBVA
A61: COORDINADOR | B61: CENTRO DE COSTOS | C61: Suma de VALOR FACTURABLE A LA RED | D61: NOMBRE DE CC | E61: VALOR CC
A62: Total general | D62: =VLOOKUP(B62,'CENTRO DE COSTOS'!B:C,2,0) -> #N/A | E62: =C62 -> 0
A67: OC BBVA
A68: COORDINADOR | B68: CENTRO DE COSTOS | C68: Suma de VALOR FACTURABLE A LA RED | D68: NOMBRE DE CC | E68: VALOR CC
A69: DIEGO FERNANDO HENAO CARDONA | B69: 0004-0002 | C69: 289935.74 | D69: =VLOOKUP(B69,'CENTRO DE COSTOS'!B:C,2,0) -> Redeban Eje Cafetero (Pereira) | E69: =C69 -> 289935.74
A70: Total general | C70: 289935.74
A75: OC BBVA
A76: COORDINADOR | B76: CENTRO DE COSTOS | C76: Suma de VALOR FACTURABLE A LA RED | D76: NOMBRE DE CC | E76: VALOR CC
A77: Total general | D77: =VLOOKUP(B77,'CENTRO DE COSTOS'!B:C,2,0) -> #N/A | E77: =C77 -> 0
A83: APERTURAS AVAL
A84: COORDINADOR | B84: CENTRO DE COSTOS | C84: Suma de VALOR FACTURABLE A LA RED | D84: NOMBRE DE CC | E84: VALOR CC
A85: DIEGO FERNANDO HENAO CARDONA | B85: 0004-0002 | C85: 1722810.2 | D85: =VLOOKUP(B85,'CENTRO DE COSTOS'!B:C,2,0) -> Redeban Eje Cafetero (Pereira) | E85: =C85 -> 1722810.2
B86: 0004-0003 | C86: 4362524.4 | D86: =VLOOKUP(B86,'CENTRO DE COSTOS'!B:C,2,0) -> Redeban Suroccidente (Cali) | E86: =C86 -> 4362524.4
A87: JOSE MAURICIO HERNANDEZ ROJAS | B87: 0004-0001 | C87: 5002747.2 | D87: =VLOOKUP(B87,'CENTRO DE COSTOS'!B:C,2,0) -> Redeban Costa (Barranqullla) | E87: =C87 -> 5002747.2
A88: JUAN SEBASTIÁN RÍOS CASTRILLÓN | B88: 0004-0005 | C88: 4112119.7 | D88: =VLOOKUP(B88,'CENTRO DE COSTOS'!B:C,2,0) -> Redeban Noroccidente (Medellín) | E88: =C88 -> 4112119.7
A89: KEVIN ALEXIS CORZO BUSTOS | B89: 0004-0007 | C89: 10129246 | D89: =VLOOKUP(B89,'CENTRO DE COSTOS'!B:C,2,0) -> Redeban Oriente (Otros) | E89: =C89 -> 10129246
A90: MIGUEL JULIÁN HERNÁNDEZ GUARÍN | B90: 0004-0008 | C90: 9439909.3 | D90: =VLOOKUP(B90,'CENTRO DE COSTOS'!B:C,2,0) -> Redeban Santander | E90: =C90 -> 9439909.3
A91: WILLIAM ASDRUBAL ROZO ROZO | B91: 0004-0004 | C91: 5807842.4 | D91: =VLOOKUP(B91,'CENTRO DE COSTOS'!B:C,2,0) -> Redeban Centro ( Bogotá) | E91: =C91 -> 5807842.4
A92: Total general | C92: 40577199
A97: INCIDENTES AVAL
A98: COORDINADOR | B98: CENTRO DE COSTOS | C98: Suma de VALOR FACTURABLE A LA RED | D98: NOMBRE DE CC | E98: VALOR CC
A99: DIEGO FERNANDO HENAO CARDONA | B99: 0004-0002 | C99: 1483661.6 | D99: =VLOOKUP(B99,'CENTRO DE COSTOS'!B:C,2,0) -> Redeban Eje Cafetero (Pereira) | E99: =C99 -> 1483661.6
B100: 0004-0003 | C100: 4432868.9 | D100: =VLOOKUP(B100,'CENTRO DE COSTOS'!B:C,2,0) -> Redeban Suroccidente (Cali) | E100: =C100 -> 4432868.9
A101: JOSE MAURICIO HERNANDEZ ROJAS | B101: 0004-0001 | C101: 3709464.8 | D101: =VLOOKUP(B101,'CENTRO DE COSTOS'!B:C,2,0) -> Redeban Costa (Barranqullla) | E101: =C101 -> 3709464.8
A102: JUAN SEBASTIÁN RÍOS CASTRILLÓN | B102: 0004-0005 | C102: 5217415.3 | D102: =VLOOKUP(B102,'CENTRO DE COSTOS'!B:C,2,0) -> Redeban Noroccidente (Medellín) | E102: =C102 -> 5217415.3
A103: KEVIN ALEXIS CORZO BUSTOS | B103: 0004-0007 | C103: 5881006 | D103: =VLOOKUP(B103,'CENTRO DE COSTOS'!B:C,2,0) -> Redeban Oriente (Otros) | E103: =C103 -> 5881006
A104: MIGUEL JULIÁN HERNÁNDEZ GUARÍN | B104: 0004-0008 | C104: 8763602.7 | D104: =VLOOKUP(B104,'CENTRO DE COSTOS'!B:C,2,0) -> Redeban Santander | E104: =C104 -> 8763602.7
A105: WILLIAM ASDRUBAL ROZO ROZO | B105: 0004-0004 | C105: 6742410.1 | D105: =VLOOKUP(B105,'CENTRO DE COSTOS'!B:C,2,0) -> Redeban Centro ( Bogotá) | E105: =C105 -> 6742410.1
A106: Total general | C106: 36230429
A111: OC AVAL
A112: COORDINADOR | B112: CENTRO DE COSTOS | C112: Suma de VALOR FACTURABLE A LA RED | D112: NOMBRE DE CC | E112: VALOR CC
A113: DIEGO FERNANDO HENAO CARDONA | B113: 0004-0002 | C113: 463096.97 | D113: =VLOOKUP(B113,'CENTRO DE COSTOS'!B:C,2,0) -> Redeban Eje Cafetero (Pereira) | E113: =C113 -> 463096.97
B114: 0004-0003 | C114: 1120599.8 | D114: =VLOOKUP(B114,'CENTRO DE COSTOS'!B:C,2,0) -> Redeban Suroccidente (Cali) | E114: =C114 -> 1120599.8
A115: JOSE MAURICIO HERNANDEZ ROJAS | B115: 0004-0001 | C115: 1714457.7 | D115: =VLOOKUP(B115,'CENTRO DE COSTOS'!B:C,2,0) -> Redeban Costa (Barranqullla) | E115: =C115 -> 1714457.7
A116: JUAN SEBASTIÁN RÍOS CASTRILLÓN | B116: 0004-0005 | C116: 677469.09 | D116: =VLOOKUP(B116,'CENTRO DE COSTOS'!B:C,2,0) -> Redeban Noroccidente (Medellín) | E116: =C116 -> 677469.09
A117: KEVIN ALEXIS CORZO BUSTOS | B117: 0004-0007 | C117: 3093172.8 | D117: =VLOOKUP(B117,'CENTRO DE COSTOS'!B:C,2,0) -> Redeban Oriente (Otros) | E117: =C117 -> 3093172.8
A118: MIGUEL JULIÁN HERNÁNDEZ GUARÍN | B118: 0004-0008 | C118: 5822839.1 | D118: =VLOOKUP(B118,'CENTRO DE COSTOS'!B:C,2,0) -> Redeban Santander | E118: =C118 -> 5822839.1
A119: WILLIAM ASDRUBAL ROZO ROZO | B119: 0004-0004 | C119: 3025462.2 | D119: =VLOOKUP(B119,'CENTRO DE COSTOS'!B:C,2,0) -> Redeban Centro ( Bogotá) | E119: =C119 -> 3025462.2
A120: Total general | C120: 15917098

Sheet APERTURAS BANCOLOMBIA
A1: CIUDAD BASE | B1: COORDINADOR | C1: CENTRO DE COSTOS | D1: CÓDIGO DANE | E1: TA | F1: FO | G1: FECHA LISTA | H1: FECHA LIMITE | I1: FECHA SOLICITUD DE LA ACTIVIDAD | J1: FECHA INICIO DE LA ACTIVIDAD | K1: FECHA ULTIMA ACTUALIZACION | L1: DEPARTAMENTO | M1: CIUDAD | N1: NOMBRE PUNTO | O1: CÓDIGO PUNTO | P1: TIPO DE SOLICITUD | Q1: ACTIVIDAD | R1: RED ASOCIADA AL PUNTO | S1: FORMATO | T1: CADENA | U1: ESTADO RESULTADO DE ACTIVIDAD | V1: OBSERVACIONES RESULTADO DE ACTIVIDAD | W1: TÉCNICO | X1: TERMINALES | Y1: PLACA DATAFONOS INSTALADOS | Z1: PLACA DATAFONOS RETIRADOS | AA1: PLACA LECTOR INSTALADO | AB1: PLACA LECTOR RETIRADO | AC1: CANTIDAD ROLLOS ENTREGADOS | AD1: TIPO DE ATENCION | AE1: TIPO DE TRAYECTO | AF1: FORMA DE ATENCIÓN | AG1: DIAS ACTIVIDAD FACTURABLES A LA RED | AH1: DIAS ACOMPAÑAMIENTO FACTURABLES A RED | AI1: VALOR DIAS ACTIVIDAD FACTURABLES A LA RED | AJ1: VALOR DIAS ACOMPAÑAMIENTO FACTURABLES A RED MENOS DE 2 HORAS | AK1: VALOR FACTURABLE A LA RED | AL1: CU CB | AM1: COBRO ENTIDAD | AN1: ESTADO | AO1: TIPO | AP1: VAL TIPO | AQ1: VAL COSTO | AR1: OBSERVACIONES | AS1: OBSERVACIONES LINEA
A2: PASTO | B2: =VLOOKUP(A2,'CENTRO DE COSTOS'!A:D,4,FALSE) -> DIEGO FERNANDO HENAO CARDONA | C2: =VLOOKUP(A2,'CENTRO DE COSTOS'!A:D,2,FALSE) -> 0004-0003 | D2: 52490 | E2: TA-25-545965 | F2: FO-25-823658 | G2: 45796 | H2: 45805 | I2: 45796 | J2: 45813 | K2: 45813 | L2: NARIÑO | M2: OLAYA HERRERA | N2: BARRIO SAN MARTIN 2 CORREGIMIENTO DE BOAS DE SATINGA OLAYA HERRERA | O2: 79313 | P2: CB CRECIMIENTO - NUEVO | Q2: APERTURA | R2: REDEBAN | S2: UNO A UNO | T2: UNO A UNO | U2: EJECUTADO | V2: 19-05-2025 SE REALIZA LLAMADA AL CLIENTE, SE HABLA CON LA SRA ALEIDA RIASCOS PERLAZA, SE VALIDA DIRECCIÓN OK, CANAL OK, DISPONIBILIDAD TOTAL, LLAMAR EL DÍA LA INSTALACIÓN PARA CONFIRMAR VISITA, AVISO EXTERIOR ALTURA APROX NO TIENE CONOCIMIENTO DE MEDIDAS; TOMACORRIENTE CERCANO: SI; TIENE CABINA DE SEGURIDAD:NO // CONTACTO REALIZADO POR WHATSAPP 28-05 SE REPROGRAMA VISITA PARA LA PRÓXIMA SEMANA SEBIDO A QUE NO SE LOGRO CONSEGUIR TRANSPORTE INTERMUNICIPAL DE CALI A BUENAVENTURA POR CIERRE DE LA VIA 05-06 SE REALIZA INSTALACIÓN DE CORRESPONSAL, SE INSTALAN EQUIPOS CON PRUEBAS EXITOSAS, SE CAPACITA Y SE EVALÚA AL CLIENTE, SE INSTALA PUBLICIDAD COMPLETA, CB QUEDA OPERATIVO. USUARIO SOMOS BANCOLOMBIA ACTIVO | W2: PAREDES CASTILLO DIEGO | X2: A4WZZ840 | Y2: 1169751 | Z2: N/A | AA2: 860310 | AB2: N/A | AC2: 40 ROLLOS | AD2: TIPO IV ESPECIAL | AE2: FLUVIAL | AF2: VISITA_TÉCNICA | AG2: 1 | AH2: 0 | AI2: =IF(AD2="TIPO I",'BASE LIQUIDACION REDEBAN 2025'!$B$2,IF(AD2="TIPO II",'BASE LIQUIDACION REDEBAN 2025'!$B$3,IF(AD2="TIPO III",'BASE LIQUIDACION REDEBAN 2025'!$B$4,IF(AD2="TIPO IV",'BASE LIQUIDACION REDEBAN 2025'!$B$5,IF(AE2="AEREO",'BASE LIQUIDACION REDEBAN 2025'!$B$6,'BASE LIQUIDACION REDEBAN 2025'!$B$5))))) -> 504832.65 | AJ2: =IF(AD2="TIPO I",'BASE LIQUIDACION REDEBAN 2025'!$B$10,IF(AD2="TIPO II",'BASE LIQUIDACION REDEBAN 2025'!$B$11,IF(AD2="TIPO III",'BASE LIQUIDACION REDEBAN 2025'!$B$12,'BASE LIQUIDACION REDEBAN 2025'!$B$13))) -> 196536.53 | AK2: =AG2*AI2+AH2*AJ2 -> 504832.65
A3: BUCARAMANGA | B3: =VLOOKUP(A3,'CENTRO DE COSTOS'!A:D,4,FALSE) -> MIGUEL JULIÁN HERNÁNDEZ GUARÍN | C3: =VLOOKUP(A3,'CENTRO DE COSTOS'!A:D,2,FALSE) -> 0004-0008 | D3: 68276 | E3: TA-25-545971 | F3: FO-25-856966 | G3: 45800 | H3: 45804 | I3: 45800 | J3: 45811 | K3: 45811 | L3: SANTANDER | M3: FLORIDABLANCA | N3: BARRIO CASCO ANTIGUO FLORIDABLANCA FLORIDABLANCA | O3: 79387 | P3: CAMBIO DE RAZON SOCIAL | Q3: APERTURA | R3: REDEBAN | S3: UNO A UNO | T3: UNO A UNO | U3: EJECUTADO | V3: 23-05 SE REALIZA LLAMADA AL CLIENTE, SE HABLA CON LA SRA CARLOS ANDRES MORALES OTERO SE VALIDA DIRECCIÓN OK, CANAL OK, DISPONIBILIDAD TOTAL, LLAMAR EL DÍA LA INSTALACIÓN PARA CONFIRMAR VISITA - CAMBIO DE RAZON SOCIAL - USUARIO SOLICITA FECHA PARA EL MIERCOLES 28-05 SE ESTABLECE COMUNICACIÓN CON EL SEÑOR CARLOS AL NÚMERO 3183832689 QUIEN SOLICITA QUE SE REPROGRAME ACTIVIDAD PARA EL DIA 2 DE JUNIO DEL AÑO EN CURSO DEBIDO A QUE SE ENCUENTRA REALIZAN UNOS EXÁMENES Y NO NOS PUEDE ATENDER 31-05 SE ESTABLECE COMUNICACIÓN CON EL SEÑOR CARLOS AL NÚMERO 3183832689 QUIEN SOLICITA QUE SE REPROGRAME ACTIVIDAD PARA EL DIA 3 DE JUNIO DEL AÑO EN CURSO DEBIDO A QUE SE ENCUENTRA REALIZAN UNOS EXÁMENES Y NO NOS PUEDE ATENDER 3/6/2025 SE REALIZA INSTALACIÓN DE CORRESPONSAL, SE INSTALAN EQUIPOS CON PRUEBAS EXITOSAS, SE CAPACITA Y SE EVALÚA AL CLIENTE, SE INSTALA PUBLICIDAD COMPLETA, CB QUEDA OPERATIVO. USUARIO SOMOS BANCOLOMBIA ACTIVO | W3: BARRERA ORTEGA MARLON STWAR | X3: 10XZZ925-SXXZZ344 | Y3: 989054-1016076 | Z3: 793883 | AA3: 1103341-893140 | AB3: N/A | AC3: 40 ROLLOS | AD3: TIPO I | AE3: TERRESTRE | AF3: VISITA_TÉCNICA | AG3: 1 | AH3: 0 | AI3: =IF(AD3="TIPO I",'BASE LIQUIDACION REDEBAN 2025'!$B$2,IF(AD3="TIPO II",'BASE LIQUIDACION REDEBAN 2025'!$B$3,IF(AD3="TIPO III",'BASE LIQUIDACION REDEBAN 2025'!$B$4,IF(AD3="TIPO IV",'BASE LIQUIDACION REDEBAN 2025'!$B$5,IF(AE3="AEREO",'BASE LIQUIDACION REDEBAN 2025'!$B$6,'BASE LIQUIDACION REDEBAN 2025'!$B$5))))) -> 75096.394 | AJ3: =IF(AD3="TIPO I",'BASE LIQUIDACION REDEBAN 2025'!$B$10,IF(AD3="TIPO II",'BASE LIQUIDACION REDEBAN 2025'!$B$11,IF(AD3="TIPO III",'BASE LIQUIDACION REDEBAN 2025'!$B$12,'BASE LIQUIDACION REDEBAN 2025'!$B$13))) -> 75096.394 | AK3: =AG3*AI3+AH3*AJ3 -> 75096.394
A4: VILLAVICENCIO | B4: =VLOOKUP(A4,'CENTRO DE COSTOS'!A:D,4,FALSE) -> KEVIN ALEXIS CORZO BUSTOS | C4: =VLOOKUP(A4,'CENTRO DE COSTOS'!A:D,2,FALSE) -> 0004-0007 | D4: 50124 | E4: TA-25-554280 | F4: FO-25-842171 | G4: 45800 | H4: 45804 | I4: 45800 | J4: 45812 | K4: 45812 | L4: META | M4: CABUYARO | N4: BARRIO CENTRO CABUYARO 5 | O4: 79356 | P4: CB CRECIMIENTO - NUEVO | Q4: APERTURA | R4: REDEBAN | S4: UNO A UNO | T4: UNO A UNO | U4: EJECUTADO | V4: 23-05 SE REALIZA LLAMADA AL CLIENTE, SE HABLA CON LA SR JULIETTE DANIELA QUIJANO ORTIZ SE VALIDA DIRECCIÓN OK, CANAL OK, DISPONIBILIDAD TOTAL, LLAMAR EL DÍA LA INSTALACIÓN PARA CONFIRMAR VISITA, AVISO EXTERIOR ALTURA APROX 2.50 METROS; TOMACORRIENTE CERCANO: SI; TIENE CABINA DE SEGURIDAD: NO 27-05 DE REALIZA CONTACTO TELEFÓNICO 3208738350 CON LA SEÑORA JULIETTE QUIEN MANIFIESTA EL DÍA DE HOY 27 MAYO NO NOS PUEDE ATENDER. SOLICITA VISITA PARA EL DÍA MARTES 3 DE JUNIO 03-06 SE PROGR 4/6/2025 SE REALIZA INSTALACIÓN DE CORRESPONSAL, SE INSTALAN EQUIPOS CON PRUEBAS EXITOSAS, SE CAPACITA Y SE EVALÚA AL CLIENTE, SE INSTALA PUBLICIDAD COMPLETA, CB QUEDA OPERATIVO. USUARIO SOMOS BANCOLOMBIA ACTIVO | W4: CASTRILLON URREA LONDIER LEANDRO | X4: 10XZZ894 | Y4: 859272 | Z4: N/A | AA4: 915631 | AB4: N/A | AC4: 40 ROLLOS | AD4: TIPO III | AE4: TERRESTRE | AF4: VISITA_TÉCNICA | AG4: 1 | AH4: 0 | AI4: =IF(AD4="TIPO I",'BASE LIQUIDACION REDEBAN 2025'!$B$2,IF(AD4="TIPO II",'BASE LIQUIDACION REDEBAN 2025'!$B$3,IF(AD4="TIPO III",'BASE LIQUIDACION REDEBAN 2025'!$B$4,IF(AD4="TIPO IV",'BASE LIQUIDACION REDEBAN 2025'!$B$5,IF(AE4="AEREO",'BASE LIQUIDACION REDEBAN 2025'!$B$6,'BASE LIQUIDACION REDEBAN 2025'!$B$5))))) -> 275728.78 | AJ4: =IF(AD4="TIPO I",'BASE LIQUIDACION REDEBAN 2025'!$B$10,IF(AD4="TIPO II",'BASE LIQUIDACION REDEBAN 2025'!$B$11,IF(AD4="TIPO III",'BASE LIQUIDACION REDEBAN 2025'!$B$12,'BASE LIQUIDACION REDEBAN 2025'!$B$13))) -> 196536.53 | AK4: =AG4*AI4+AH4*AJ4 -> 275728.78
A5: CALI | B5: =VLOOKUP(A5,'CENTRO DE COSTOS'!A:D,4,FALSE) -> DIEGO FERNANDO HENAO CARDONA | C5: =VLOOKUP(A5,'CENTRO DE COSTOS'!A:D,2,FALSE) -> 0004-0003 | D5: 19397 | E5: TA-25-554298 | F5: FO-25-842246 | G5: 45805 | H5: 45807 | I5: 45805 | J5: 45811 | K5: 45811 | L5: CAUCA | M5: LA VEGA | N5: BARRIO SANTA MARIA LA VEGA | O5: 79561 | P5: CB CRECIMIENTO - NUEVO | Q5: APERTURA | R5: REDEBAN | S5: UNO A UNO | T5: UNO A UNO | U5: EJECUTADO | V5: 28-05-2025 SE REALIZA LLAMADA AL CLIENTE, SE HABLA CON EL SR LEINER ALEJANDRO GARCIA MAMIAN SE VALIDA DIRECCIÓN OK, CANAL OK, DISPONIBILIDAD TOTAL, LLAMAR EL DÍA LA INSTALACIÓN PARA CONFIRMAR VISITA, AVISO EXTERIOR ALTURA APROX 1,60 METROS; TOMACORRIENTE CERCANO: SI; TIENE CABINA DE SEGURIDAD: NO // CONTACTO REALIZADO POR LA APP 30-05 SE REALIZA LLAMADA CELULAR AL SEÑOR LEINER Y SE LE INFORMA QUE POR TEMAS DE EL PARO ARMADO NO SE CUENTA CON TRANSPORTE A LA ZONA SE REPROGRAMA VISITA CON EL CB PARA EL DÍA MARTES 3/6/2025 SE REALIZA INSTALACIÓN DE CORRESPONSAL, SE INSTALAN EQUIPOS CON PRUEBAS EXITOSAS, SE CAPACITA Y SE EVALÚA AL CLIENTE, SE INSTALA PUBLICIDAD COMPLETA, CB QUEDA OPERATIVO. USUARIO SOMOS BANCOLOMBIA ACTIVO | W5: GIMBUEL LASSO LUIS GERMAN | X5: LMUZZ995 | Y5: 761185 | Z5: N/A | AA5: 933206 | AB5: N/A | AC5: 40 ROLLOS | AD5: TIPO IV | AE5: TERRESTRE | AF5: VISITA_TÉCNICA | AG5: 1 | AH5: 0 | AI5: =IF(AD5="TIPO I",'BASE LIQUIDACION REDEBAN 2025'!$B$2,IF(AD5="TIPO II",'BASE LIQUIDACION REDEBAN 2025'!$B$3,IF(AD5="TIPO III",'BASE LIQUIDACION REDEBAN 2025'!$B$4,IF(AD5="TIPO IV",'BASE LIQUIDACION REDEBAN 2025'!$B$5,IF(AE5="AEREO",'BASE LIQUIDACION REDEBAN 2025'!$B$6,'BASE LIQUIDACION REDEBAN 2025'!$B$5))))) -> 504832.65 | AJ5: =IF(AD5="TIPO I",'BASE LIQUIDACION REDEBAN 2025'!$B$10,IF(AD5="TIPO II",'BASE LIQUIDACION REDEBAN 2025'!$B$11,IF(AD5="TIPO III",'BASE LIQUIDACION REDEBAN 2025'!$B$12,'BASE LIQUIDACION REDEBAN 2025'!$B$13))) -> 196536.53 | AK5: =AG5*AI5+AH5*AJ5 -> 504832.65
A6: APARTADO | B6: =VLOOKUP(A6,'CENTRO DE COSTOS'!A:D,4,FALSE) -> JUAN SEBASTIÁN RÍOS CASTRILLÓN | C6: =VLOOKUP(A6,'CENTRO DE COSTOS'!A:D,2,FALSE) -> 0004-0005 | D6: 27135 | E6: TA-25-554336 | F6: FO-25-842394 | G6: 45805 | H6: 45807 | I6: 45805 | J6: 45814 | K6: 45814 | L6: CHOCO | M6: EL CANTON DEL SAN PABLO | N6: BARRIO AVENIDA 20 DE JULIO CARTON DEL SAN PABLO CHOCO EL CANTON DEL SAN PABLO | O6: 79580 | P6: CB CRECIMIENTO - NUEVO | Q6: APERTURA | R6: REDEBAN | S6: UNO A UNO | T6: UNO A UNO | U6: EJECUTADO | V6: 28-05-2025 SE REALIZA LLAMADA AL CLIENTE, SE HABLA CON LA SRA DORIS MARIA PALACIOS CORDOBA SE VALIDA DIRECCIÓN OK, CANAL OK, DISPONIBILIDAD TOTAL, LLAMAR EL DÍA LA INSTALACIÓN PARA CONFIRMAR VISITA, AVISO EXTERIOR ALTURA APROX 3 - 4 METROS; TOMACORRIENTE CERCANO: SI; TIENE CABINA DE SEGURIDAD: NO // CONTACTO REALIZADO POR LA APP 06-06 SE REALIZA INSTALACIÓN DE CORRESPONSAL, SE INSTALAN EQUIPOS CON PRUEBAS EXITOSAS, SE CAPACITA Y SE EVALÚA AL CLIENTE, SE INSTALA PUBLICIDAD COMPLETA, CB QUEDA OPERATIVO. USUARIO SOMOS BANCOLOMBIA ACTIVO | W6: ROBLEDO DIAZ ANDRES FELIPE | X6: LMVZZ014 | Y6: 792636 | Z6: N/A | AA6: 905838 | AB6: N/A | AC6: 40 ROLLOS | AD6: TIPO IV | AE6: TERRESTRE | AF6: VISITA_TÉCNICA | AG6: 1 | AH6: 0 | AI6: =IF(AD6="TIPO I",'BASE LIQUIDACION REDEBAN 2025'!$B$2,IF(AD6="TIPO II",'BASE LIQUIDACION REDEBAN 2025'!$B$3,IF(AD6="TIPO III",'BASE LIQUIDACION REDEBAN 2025'!$B$4,IF(AD6="TIPO IV",'BASE LIQUIDACION REDEBAN 2025'!$B$5,IF(AE6="AEREO",'BASE LIQUIDACION REDEBAN 2025'!$B$6,'BASE LIQUIDACION REDEBAN 2025'!$B$5))))) -> 504832.65 | AJ6: =IF(AD6="TIPO I",'BASE LIQUIDACION REDEBAN 2025'!$B$10,IF(AD6="TIPO II",'BASE LIQUIDACION REDEBAN 2025'!$B$11,IF(AD6="TIPO III",'BASE LIQUIDACION REDEBAN 2025'!$B$12,'BASE LIQUIDACION REDEBAN 2025'!$B$13))) -> 196536.53 | AK6: =AG6*AI6+AH6*AJ6 -> 504832.65
A7: PASTO | B7: =VLOOKUP(A7,'CENTRO DE COSTOS'!A:D,4,FALSE) -> DIEGO FERNANDO HENAO CARDONA | C7: =VLOOKUP(A7,'CENTRO DE COSTOS'!A:D,2,FALSE) -> 0004-0003 | D7: 52320 | E7: TA-25-561190 | F7: FO-25-854599 | G7: 45805 | H7: 45807 | I7: 45805 | J7: 45811 | K7: 45811 | L7: NARIÑO | M7: GUAITARILLA | N7: BARRIO CENTRO GUAITARILLA | O7: 79558 | P7: CB CRECIMIENTO - NUEVO | Q7: APERTURA | R7: REDEBAN | S7: UNO A UNO | T7: UNO A UNO | U7: EJECUTADO | V7: 28-05 SE REALIZA LLAMADA AL CLIENTE, SE HABLA CON EL SR JOSE ARMANDO ROSERO MARTINEZ, SE VALIDA DIRECCIÓN OK, CANAL OK, DISPONIBILIDAD TOTAL, LLAMAR EL DÍA LA INSTALACIÓN PARA CONFIRMAR VISITA, AVISO EXTERIOR ALTURA APROX 2 METROS; TOMACORRIENTE CERCANO: SI; TIENE CABINA DE SEGURIDAD:SI //MODEN SE ENCUENTRA A 5 MEGTROS DE DISTANCIA DE DONDE VA SER INSTALADO EL DATAFONO 30-05 NO SE PUEDE NO SE LOGRA TRANSPORTE PARA EL MUNICIPIO DE GUAITARILLA DEBIDO A QUE ZONA NO HAY TRANSPORTE DISPONIBLE. SE VISITARÁ EL DÍA MARTES 03/06/2025 3/6/2025 SE REALIZA INSTALACIÓN DE CORRESPONSAL, SE INSTALAN EQUIPOS CON PRUEBAS EXITOSAS, SE CAPACITA Y SE EVALÚA AL CLIENTE, SE INSTALA PUBLICIDAD COMPLETA, CB QUEDA OPERATIVO. USUARIO SOMOS BANCOLOMBIA ACTIVO | W7: BOLAÑOS TABORDA JORGE ENRIQUE | X7: LMUZZ992 | Y7: 1115746 | Z7: N/A | AA7: 892665 | AB7: N/A | AC7: 40 ROLLOS | AD7: TIPO II | AE7: TERRESTRE | AF7: VISITA_TÉCNICA | AG7: 1 | AH7: 0 | AI7: =IF(AD7="TIPO I",'BASE LIQUIDACION REDEBAN 2025'!$B$2,IF(AD7="TIPO II",'BASE LIQUIDACION REDEBAN 2025'!$B$3,IF(AD7="TIPO III",'BASE LIQUIDACION REDEBAN 2025'!$B$4,IF(AD7="TIPO IV",'BASE LIQUIDACION REDEBAN 2025'!$B$5,IF(AE7="AEREO",'BASE LIQUIDACION REDEBAN 2025'!$B$6,'BASE LIQUIDACION REDEBAN 2025'!$B$5))))) -> 163813.7 | AJ7: =IF(AD7="TIPO I",'BASE LIQUIDACION REDEBAN 2025'!$B$10,IF(AD7="TIPO II",'BASE LIQUIDACION REDEBAN 2025'!$B$11,IF(AD7="TIPO III",'BASE LIQUIDACION REDEBAN 2025'!$B$12,'BASE LIQUIDACION REDEBAN 2025'!$B$13))) -> 140395.63 | AK7: =AG7*AI7+AH7*AJ7 -> 163813.7
A8: MEDELLIN | B8: =VLOOKUP(A8,'CENTRO DE COSTOS'!A:D,4,FALSE) -> JUAN SEBASTIÁN RÍOS CASTRILLÓN | C8: =VLOOKUP(A8,'CENTRO DE COSTOS'!A:D,2,FALSE) -> 0004-0005 | D8: 27361 | E8: TA-25-561193 | F8: FO-25-854607 | G8: 45805 | H8: 45817 | I8: 45805 | J8: 45812 | K8: 45812 | L8: CHOCO | M8: ISTMINA | N8: BARRIO CUBIS SEC MESETA ALTA ISTMINA CHOCO ISTMINA | O8: 79563 | P8: CB CRECIMIENTO - NUEVO | Q8: APERTURA | R8: REDEBAN | S8: UNO A UNO | T8: UNO A UNO | U8: EJECUTADO | V8: 28-05 SE REALIZA LLAMADA AL CLIENTE, SE HABLA CON LA SRA JOAN AVENDAÑO DAZA SE VALIDA DIRECCIÓN OK, CANAL OK, DISPONIBILIDAD TOTAL, LLAMAR EL DÍA LA INSTALACIÓN PARA CONFIRMAR VISITA, AVISO EXTERIOR ALTURA APROX 2 METROS; TOMACORRIENTE CERCANO: SI; TIENE CABINA DE SEGURIDAD: SI 04-06 SE REALIZA INSTALACIÓN DE CORRESPONSAL, SE INSTALAN EQUIPOS CON PRUEBAS EXITOSAS, SE CAPACITA Y SE EVALÚA AL CLIENTE, SE INSTALA PUBLICIDAD COMPLETA, CB QUEDA OPERATIVO. USUARIO SOMOS BANCOLOMBIA ACTIVO. SE INSTALAN 10 MT DE CABLE UTP | W8: ROBLEDO DIAZ ANDRES FELIPE | X8: LMUZZ997 | Y8: 771855 | Z8: N/A | AA8: 1146028 | AB8: N/A | AC8: 40 ROLLOS | AD8: TIPO IV ESPECIAL | AE8: AEREO | AF8: VISITA_TÉCNICA | AG8: 1 | AH8: 0 | AI8: =IF(AD8="TIPO I",'BASE LIQUIDACION REDEBAN 2025'!$B$2,IF(AD8="TIPO II",'BASE LIQUIDACION REDEBAN 2025'!$B$3,IF(AD8="TIPO III",'BASE LIQUIDACION REDEBAN 2025'!$B$4,IF(AD8="TIPO IV",'BASE LIQUIDACION REDEBAN 2025'!$B$5,IF(AE8="AEREO",'BASE LIQUIDACION REDEBAN 2025'!$B$6,'BASE LIQUIDACION REDEBAN 2025'!$B$5))))) -> 988462.96 | AJ8: =IF(AD8="TIPO I",'BASE LIQUIDACION REDEBAN 2025'!$B$10,IF(AD8="TIPO II",'BASE LIQUIDACION REDEBAN 2025'!$B$11,IF(AD8="TIPO III",'BASE LIQUIDACION REDEBAN 2025'!$B$12,'BASE LIQUIDACION REDEBAN 2025'!$B$13))) -> 196536.53 | AK8: =AG8*AI8+AH8*AJ8 -> 988462.96
A9: CALI | B9: =VLOOKUP(A9,'CENTRO DE COSTOS'!A:D,4,FALSE) -> DIEGO FERNANDO HENAO CARDONA | C9: =VLOOKUP(A9,'CENTRO DE COSTOS'!A:D,2,FALSE) -> 0004-0003 | D9: 76109 | E9: TA-25-561196 | F9: FO-25-854618 | G9: 45805 | H9: 45807 | I9: 45805 | J9: 45812 | K9: 45812 | L9: VALLE DEL CAUCA | M9: BUENAVENTURA | N9: BARRIO PUNTA DEL ESTE BUENAVENTURA | O9: 79355 | P9: CB CRECIMIENTO - OTRAS LISTAS | Q9: APERTURA | R9: REDEBAN | S9: UNO A UNO | T9: UNO A UNO | U9: EJECUTADO | V9: 28-05 SE REALIZA LLAMADA AL CLIENTE, SE HABLA CON LA SR JESSICA PAOLA VALENCIA BECERRA SE VALIDA DIRECCIÓN OK, CANAL OK, DISPONIBILIDAD TOTAL, LLAMAR EL DÍA LA INSTALACIÓN PARA CONFIRMAR VISITA, AVISO EXTERIOR ALTURA: NO INDICA ALTURA; TOMACORRIENTE CERCANO: SI; TIENE CABINA DE SEGURIDAD: NO 30-05 DEBIDO A PROBLEMAS EN LA VIA CALI - BUENAVENTURA POR CIERRES Y PROTESTAS NO SE CONSIGUE TRANSPORTE PARA EL PUERTO NO ESTAN SALIENDO LOS BUSES DESDE LA TERMINAL, SE DEBE REALIZAR DESPLAZAMIENTO EL PROXIMO MARTES VALIDANDO ESTADO DEL TRANSPORTE. 4/6/2025 SE REALIZA INSTALACIÓN DE CORRESPONSAL, SE INSTALAN EQUIPOS CON PRUEBAS EXITOSAS, SE CAPACITA Y SE EVALÚA AL CLIENTE, SE INSTALA PUBLICIDAD COMPLETA, CB QUEDA OPERATIVO. USUARIO SOMOS BANCOLOMBIA ACTIVO | W9: PAREDES CASTILLO DIEGO | X9: 10XZZ893 | Y9: 1072780 | Z9: N/A | AA9: 528290 | AB9: N/A | AC9: 40 ROLLOS | AD9: TIPO III | AE9: TERRESTRE | AF9: VISITA_TÉCNICA | AG9: 1 | AH9: 0 | AI9: =IF(AD9="TIPO I",'BASE LIQUIDACION REDEBAN 2025'!$B$2,IF(AD9="TIPO II",'BASE LIQUIDACION REDEBAN 2025'!$B$3,IF(AD9="TIPO III",'BASE LIQUIDACION REDEBAN 2025'!$B$4,IF(AD9="TIPO IV",'BASE LIQUIDACION REDEBAN 2025'!$B$5,IF(AE9="AEREO",'BASE LIQUIDACION REDEBAN 2025'!$B$6,'BASE LIQUIDACION REDEBAN 2025'!$B$5))))) -> 275728.78 | AJ9: =IF(AD9="TIPO I",'BASE LIQUIDACION REDEBAN 2025'!$B$10,IF(AD9="TIPO II",'BASE LIQUIDACION REDEBAN 2025'!$B$11,IF(AD9="TIPO III",'BASE LIQUIDACION REDEBAN 2025'!$B$12,'BASE LIQUIDACION REDEBAN 2025'!$B$13))) -> 196536.53 | AK9: =AG9*AI9+AH9*AJ9 -> 275728.78
A10: CALI | B10: =VLOOKUP(A10,'CENTRO DE COSTOS'!A:D,4,FALSE) -> DIEGO FERNANDO HENAO CARDONA | C10: =VLOOKUP(A10,'CENTRO DE COSTOS'!A:D,2,FALSE) -> 0004-0003 | D10: 76001 | E10: TA-25-561199 | F10: FO-25-854624 | G10: 45805 | H10: 45807 | I10: 45805 | J10: 45811 | K10: 45811 | L10: VALLE DEL CAUCA | M10: CALI | N10: BARRIO VILLA DEL LAGO CALI 2 | O10: 79361 | P10: CB CRECIMIENTO - OTRAS LISTAS | Q10: APERTURA | R10: REDEBAN | S10: UNO A UNO | T10: UNO A UNO | U10: EJECUTADO | V10: 28-05 SE REALIZA LLAMADA AL CLIENTE, SE HABLA CON LA SRA DEISY (HIJA) SE VALIDA DIRECCIÓN OK, CANAL OK, DISPONIBILIDAD TOTAL, LLAMAR EL DÍA LA INSTALACIÓN PARA CONFIRMAR VISITA, AVISO EXTERIOR ALTURA: NO INDICA ALTURA; TOMACORRIENTE CERCANO: SI; TIENE CABINA DE SEGURIDAD: NO - COMUNICACIÓN POR WPP 30/5/2025 SE LLEGA AL PUNTO DESPUES DE LAS 4 PM YA QUE SE TUVO INCONVENIENTE CON VARIOS CAMBIOS DE EQUIPOS EN LA PRIMERA APERTURA, SE CONFIGURAN EQUIPOS PERO AL MOMENTO DE INICIALIZAR SE ENCUENTRA QUE LA TERMINAL NO ESTA EN BASE 24 , YA NO SE CUENTA CON SOPORTE DE REDEBAN, POR LO CUAL NO SE PUEDE LLEVAR A CABO LA APERTURA 3/6/2025 SE REALIZA INSTALACIÓN DE CORRESPONSAL, SE INSTALAN EQUIPOS CON PRUEBAS EXITOSAS, SE CAPACITA Y SE EVALÚA AL CLIENTE, SE INSTALA PUBLICIDAD COMPLETA, CB QUEDA OPERATIVO. USUARIO SOMOS BANCOLOMBIA ACTIVO | W10: HERRERA MONAR GEOVANNY | X10: 10XZZ899 | Y10: 1219158 | Z10: 1006564 | AA10: 789713 | AB10: N/A | AC10: 40 ROLLOS | AD10: TIPO I | AE10: TERRESTRE | AF10: VISITA_TÉCNICA | AG10: 1 | AH10: 0 | AI10: =IF(AD10="TIPO I",'BASE LIQUIDACION REDEBAN 2025'!$B$2,IF(AD10="TIPO II",'BASE LIQUIDACION REDEBAN 2025'!$B$3,IF(AD10="TIPO III",'BASE LIQUIDACION REDEBAN 2025'!$B$4,IF(AD10="TIPO IV",'BASE LIQUIDACION REDEBAN 2025'!$B$5,IF(AE10="AEREO",'BASE LIQUIDACION REDEBAN 2025'!$B$6,'BASE LIQUIDACION REDEBAN 2025'!$B$5))))) -> 75096.394 | AJ10: =IF(AD10="TIPO I",'BASE LIQUIDACION REDEBAN 2025'!$B$10,IF(AD10="TIPO II",'BASE LIQUIDACION REDEBAN 2025'!$B$11,IF(AD10="TIPO III",'BASE LIQUIDACION REDEBAN 2025'!$B$12,'BASE LIQUIDACION REDEBAN 2025'!$B$13))) -> 75096.394 | AK10: =AG10*AI10+AH10*AJ10 -> 75096.394
A11: VILLAVICENCIO | B11: =VLOOKUP(A11,'CENTRO DE COSTOS'!A:D,4,FALSE) -> KEVIN ALEXIS CORZO BUSTOS | C11: =VLOOKUP(A11,'CENTRO DE COSTOS'!A:D,2,FALSE) -> 0004-0007 | D11: 50001 | E11: TA-25-561200 | F11: FO-25-854628 | G11: 45807 | H11: 45812 | I11: 45807 | J11: 45812 | K11: 45812 | L11: META | M11: VILLAVICENCIO | N11: BARRIOI CATUMARE VILLAVICENCIO | O11: 79665 | P11: CB CRECIMIENTO - NUEVO | Q11: APERTURA | R11: REDEBAN | S11: UNO A UNO | T11: UNO A UNO | U11: EJECUTADO | V11: 30-05-2025 SE REALIZA LLAMADA AL CLIENTE, SE HABLA CON LA SRA ERIKA FERNANDA MARRERO INFANTE SE VALIDA DIRECCIÓN OK, CANAL OK, DISPONIBILIDAD TOTAL, LLAMAR EL DÍA LA INSTALACIÓN PARA CONFIRMAR VISITA, AVISO EXTERIOR ALTURA: CLIENTE NO TIENE CONOCIMIENTO DE MEDIDAS; TOMACORRIENTE CERCANO: SI; TIENE CABINA DE SEGURIDAD: NO // CONTACTO REALIZADO POR LA APP 4/6/2025 SE REALIZA INSTALACIÓN DE CORRESPONSAL, SE INSTALAN EQUIPOS CON PRUEBAS EXITOSAS, SE CAPACITA Y SE EVALÚA AL CLIENTE, SE INSTALA PUBLICIDAD COMPLETA, CB QUEDA OPERATIVO. USUARIO SOMOS BANCOLOMBIA ACTIVO | W11: PEDREROS CONTRERAS MICHAEL STEVENS | X11: SXUZZ191 | Y11: 1040805 | Z11: 1138829 | AA11: 523819 | AB11: N/A | AC11: 40 ROLLOS | AD11: TIPO I | AE11: TERRESTRE | AF11: VISITA_TÉCNICA | AG11: 1 | AH11: 0 | AI11: =IF(AD11="TIPO I",'BASE LIQUIDACION REDEBAN 2025'!$B$2,IF(AD11="TIPO II",'BASE LIQUIDACION REDEBAN 2025'!$B$3,IF(AD11="TIPO III",'BASE LIQUIDACION REDEBAN 2025'!$B$4,IF(AD11="TIPO IV",'BASE LIQUIDACION REDEBAN 2025'!$B$5,IF(AE11="AEREO",'BASE LIQUIDACION REDEBAN 2025'!$B$6,'BASE LIQUIDACION REDEBAN 2025'!$B$5))))) -> 75096.394 | AJ11: =IF(AD11="TIPO I",'BASE LIQUIDACION REDEBAN 2025'!$B$10,IF(AD11="TIPO II",'BASE LIQUIDACION REDEBAN 2025'!$B$11,IF(AD11="TIPO III",'BASE LIQUIDACION REDEBAN 2025'!$B$12,'BASE LIQUIDACION REDEBAN 2025'!$B$13))) -> 75096.394 | AK11: =AG11*AI11+AH11*AJ11 -> 75096.394
A12: VILLAVICENCIO | B12: =VLOOKUP(A12,'CENTRO DE COSTOS'!A:D,4,FALSE) -> KEVIN ALEXIS CORZO BUSTOS | C12: =VLOOKUP(A12,'CENTRO DE COSTOS'!A:D,2,FALSE) -> 0004-0007 | D12: 50313 | E12: TA-25-561203 | F12: FO-25-854632 | G12: 45807 | H12: 45812 | I12: 45807 | J12: 45811 | K12: 45811 | L12: META | M12: GRANADA | N12: BARRIO RICAUTE GRANADA 2 | O12: 79637 | P12: CB CRECIMIENTO - NUEVO | Q12: APERTURA | R12: REDEBAN | S12: UNO A UNO | T12: UNO A UNO | U12: EJECUTADO | V12: 30-05-2025 SE REALIZA LLAMADA AL CLIENTE, SE HABLA CON LA SRA LEIDY VIVIANA PENAGOS ALARCON SE VALIDA DIRECCIÓN OK, CANAL OK, DISPONIBILIDAD TOTAL, LLAMAR EL DÍA LA INSTALACIÓN PARA CONFIRMAR VISITA, AVISO EXTERIOR ALTURA: CLIENTE NO TIENE CONOCIMIENTO DE MEDIDAS; TOMACORRIENTE CERCANO: SI; TIENE CABINA DE SEGURIDAD: NO // CONTACTO REALIZADO POR LA APP 3/6/2025 SE REALIZA VISITA PARA IMPLEMENTACIÓN, PERO SE EVIDENCIA QUE EL BARRIO NO COINCIDE CON EL RELACIONADO EN LISTA DE CHEQUEO, LA DIRECCIÓN CL 19 NRO 12 - 41 ESTÁ BIEN, PERO EL BARRIO ES CENTRO Y NO RICAUTE. POR FAVOR NOS INDICA COMO PROCEDER. 3/6/2025 SE REALIZA INSTALACIÓN DE CORRESPONSAL, SE INSTALAN EQUIPOS CON PRUEBAS EXITOSAS, SE CAPACITA Y SE EVALÚA AL CLIENTE, SE INSTALA PUBLICIDAD COMPLETA, CB QUEDA OPERATIVO. USUARIO SOMOS BANCOLOMBIA ACTIVO | W12: PEDREROS CONTRERAS MICHAEL STEVENS | X12: SXUZZ163 | Y12: 981893 | Z12: N/A | AA12: 514973 | AB12: N/A | AC12: 40 ROLLOS | AD12: TIPO II | AE12: TERRESTRE | AF12: VISITA_TÉCNICA | AG12: 1 | AH12: 0 | AI12: =IF(AD12="TIPO I",'BASE LIQUIDACION REDEBAN 2025'!$B$2,IF(AD12="TIPO II",'BASE LIQUIDACION REDEBAN 2025'!$B$3,IF(AD12="TIPO III",'BASE LIQUIDACION REDEBAN 2025'!$B$4,IF(AD12="TIPO IV",'BASE LIQUIDACION REDEBAN 2025'!$B$5,IF(AE12="AEREO",'BASE LIQUIDACION REDEBAN 2025'!$B$6,'BASE LIQUIDACION REDEBAN 2025'!$B$5))))) -> 163813.7 | AJ12: =IF(AD12="TIPO I",'BASE LIQUIDACION REDEBAN 2025'!$B$10,IF(AD12="TIPO II",'BASE LIQUIDACION REDEBAN 2025'!$B$11,IF(AD12="TIPO III",'BASE LIQUIDACION REDEBAN 2025'!$B$12,'BASE LIQUIDACION REDEBAN 2025'!$B$13))) -> 140395.63 | AK12: =AG12*AI12+AH12*AJ12 -> 163813.7
A13: NEIVA | B13: =VLOOKUP(A13,'CENTRO DE COSTOS'!A:D,4,FALSE) -> KEVIN ALEXIS CORZO BUSTOS | C13: =VLOOKUP(A13,'CENTRO DE COSTOS'!A:D,2,FALSE) -> 0004-0007 | D13: 41001 | E13: TA-25-561204 | F13: FO-25-854635 | G13: 45807 | H13: 45812 | I13: 45807 | J13: 45811 | K13: 45811 | L13: HUILA | M13: NEIVA | N13: BARRIO PRADOS DEL SAUCE NEIVA 1 | O13: 79645 | P13: CB CRECIMIENTO - NUEVO | Q13: APERTURA | R13: REDEBAN | S13: UNO A UNO | T13: UNO A UNO | U13: EJECUTADO | V13: 30-05-2025 SE REALIZA LLAMADA AL CLIENTE, SE HABLA CON EL SR JOSE ANDRES PERDOMO PERDOMO SE VALIDA DIRECCIÓN OK, CANAL OK, DISPONIBILIDAD TOTAL, LLAMAR EL DÍA LA INSTALACIÓN PARA CONFIRMAR VISITA, AVISO EXTERIOR ALTURA APROX 1,70 A 2 METROS; TOMACORRIENTE CERCANO: SI; TIENE CABINA DE SEGURIDAD: SI // CONTACTO REALIZADO POR LA APP 03-06 SE REALIZA INSTALACIÓN DE CORRESPONSAL, SE INSTALAN EQUIPOS CON PRUEBAS EXITOSAS, SE CAPACITA Y SE EVALÚA AL CLIENTE, SE INSTALA PUBLICIDAD COMPLETA, CB QUEDA OPERATIVO. USUARIO SOMOS BANCOLOMBIA ACTIVO | W13: DIAZ VARGAS JONATHAN MIGUEL | X13: SXUZZ171 | Y13: 792659 | Z13: N/A | AA13: 892883 | AB13: N/A | AC13: 40 ROLLOS | AD13: TIPO I | AE13: TERRESTRE | AF13: VISITA_TÉCNICA | AG13: 1 | AH13: 0 | AI13: =IF(AD13="TIPO I",'BASE LIQUIDACION REDEBAN 2025'!$B$2,IF(AD13="TIPO II",'BASE LIQUIDACION REDEBAN 2025'!$B$3,IF(AD13="TIPO III",'BASE LIQUIDACION REDEBAN 2025'!$B$4,IF(AD13="TIPO IV",'BASE LIQUIDACION REDEBAN 2025'!$B$5,IF(AE13="AEREO",'BASE LIQUIDACION REDEBAN 2025'!$B$6,'BASE LIQUIDACION REDEBAN 2025'!$B$5))))) -> 75096.394 | AJ13: =IF(AD13="TIPO I",'BASE LIQUIDACION REDEBAN 2025'!$B$10,IF(AD13="TIPO II",'BASE LIQUIDACION REDEBAN 2025'!$B$11,IF(AD13="TIPO III",'BASE LIQUIDACION REDEBAN 2025'!$B$12,'BASE LIQUIDACION REDEBAN 2025'!$B$13))) -> 75096.394 | AK13: =AG13*AI13+AH13*AJ13 -> 75096.394
A14: VILLAVICENCIO | B14: =VLOOKUP(A14,'CENTRO DE COSTOS'!A:D,4,FALSE) -> KEVIN ALEXIS CORZO BUSTOS | C14: =VLOOKUP(A14,'CENTRO DE COSTOS'!A:D,2,FALSE) -> 0004-0007 | D14: 50001 | E14: TA-25-561205 | F14: FO-25-854639 | G14: 45807 | H14: 45812 | I14: 45807 | J14: 45812 | K14: 45812 | L14: META | M14: VILLAVICENCIO | N14: BARRIO LA MADRID ETAPA 4 VILLAVICENCIO | O14: 79666 | P14: CB CRECIMIENTO - NUEVO | Q14: APERTURA | R14: REDEBAN | S14: UNO A UNO | T14: UNO A UNO | U14: EJECUTADO | V14: 30-05-2025 SE REALIZA LLAMADA AL CLIENTE, SE HABLA CON LA SRA CAROL JULIETH ARIZA FONTECHA SE VALIDA DIRECCIÓN OK, CANAL OK, DISPONIBILIDAD TOTAL, LLAMAR EL DÍA LA INSTALACIÓN PARA CONFIRMAR VISITA, AVISO EXTERIOR ALTURA: CLIENTE NO TIENE CONOCIMIENTO DE MEDIDAS; TOMACORRIENTE CERCANO: SI; TIENE CABINA DE SEGURIDAD: NO // CONTACTO REALIZADO POR LA APP 4/6/2025 SE REALIZA INSTALACIÓN DE CORRESPONSAL, SE INSTALAN EQUIPOS CON PRUEBAS EXITOSAS, SE CAPACITA Y SE EVALÚA AL CLIENTE, SE INSTALA PUBLICIDAD COMPLETA, CB QUEDA OPERATIVO. USUARIO SOMOS BANCOLOMBIA ACTIVO | W14: ROZO JIMENEZ EDGAR ARMANDO | X14: SXUZZ192 | Y14: 1169258 | Z14: N/A | AA14: 903879 | AB14: N/A | AC14: 40 ROLLOS | AD14: TIPO I | AE14: TERRESTRE | AF14: VISITA_TÉCNICA | AG14: 1 | AH14: 0 | AI14: =IF(AD14="TIPO I",'BASE LIQUIDACION REDEBAN 2025'!$B$2,IF(AD14="TIPO II",'BASE LIQUIDACION REDEBAN 2025'!$B$3,IF(AD14="TIPO III",'BASE LIQUIDACION REDEBAN 2025'!$B$4,IF(AD14="TIPO IV",'BASE LIQUIDACION REDEBAN 2025'!$B$5,IF(AE14="AEREO",'BASE LIQUIDACION REDEBAN 2025'!$B$6,'BASE LIQUIDACION REDEBAN 2025'!$B$5))))) -> 75096.394 | AJ14: =IF(AD14="TIPO I",'BASE LIQUIDACION REDEBAN 2025'!$B$10,IF(AD14="TIPO II",'BASE LIQUIDACION REDEBAN 2025'!$B$11,IF(AD14="TIPO III",'BASE LIQUIDACION REDEBAN 2025'!$B$12,'BASE LIQUIDACION REDEBAN 2025'!$B$13))) -> 75096.394 | AK14: =AG14*AI14+AH14*AJ14 -> 75096.394
A15: VALLEDUPAR | B15: =VLOOKUP(A15,'CENTRO DE COSTOS'!A:D,4,FALSE) -> JOSE MAURICIO HERNANDEZ ROJAS | C15: =VLOOKUP(A15,'CENTRO DE COSTOS'!A:D,2,FALSE) -> 0004-0001 | D15: 20238 | E15: TA-25-561209 | F15: FO-25-854645 | G15: 45807 | H15: 45812 | I15: 45807 | J15: 45814 | K15: 45814 | L15: CESAR | M15: EL COPEY | N15: BARRIO EL BOSQUE EL COPEY 1 | O15: 79633 | P15: CB CRECIMIENTO - NUEVO | Q15: APERTURA | R15: REDEBAN | S15: UNO A UNO | T15: UNO A UNO | U15: EJECUTADO | V15: 30-05-2025 SE REALIZA LLAMADA AL CLIENTE, SE HABLA CON LA SRA EDWIN CHINCHILLA MANOSALVA SE VALIDA DIRECCIÓN OK, CANAL OK, DISPONIBILIDAD TOTAL, LLAMAR EL DÍA LA INSTALACIÓN PARA CONFIRMAR VISITA, AVISO EXTERIOR ALTURA: 2,50 METROS; TOMACORRIENTE CERCANO: A 4 METROS ; TIENE CABINA DE SEGURIDAD: NO // CONTACTO REALIZADO POR WHATSAPP 03-06 NO SE PUEDE ACCEDER A LA APERTURA E INSTALACIÓN DE EQUIPOS EN COPEY YA QUE HAY PROTESTA Y PARO EN LA VIA SANTA MARTA Y BOSCONIA POR PARTE DE COMUNIDADES DE LA SIERRA DESDE EL DÍA DE AYER, INFORMAN FUENTES QUE EL PARO VA A SEGUIR HASTA EL RESTO DEL DÍA DE HOY 5/6/2025 SE REALIZA VALIDACIÓN NUEVAMENTE Y LA NOVEDAD CONTINUA6/6/2025 SE REALIZA INSTALACIÓN DE CORRESPONSAL, SE INSTALAN EQUIPOS CON PRUEBAS EXITOSAS, SE CAPACITA Y SE EVALÚA AL CLIENTE, SE INSTALA PUBLICIDAD COMPLETA, CB QUEDA OPERATIVO. USUARIO SOMOS BANCOLOMBIA ACTIVO | W15: MAESTRE MENGUAL EDGAR ENRIQUE | X15: SXUZZ159 | Y15: 929689 | Z15: N/A | AA15: 531715 | AB15: N/A | AC15: 40 ROLLOS | AD15: TIPO II | AE15: TERRESTRE | AF15: VISITA_TÉCNICA | AG15: 1 | AH15: 0 | AI15: =IF(AD15="TIPO I",'BASE LIQUIDACION REDEBAN 2025'!$B$2,IF(AD15="TIPO II",'BASE LIQUIDACION REDEBAN 2025'!$B$3,IF(AD15="TIPO III",'BASE LIQUIDACION REDEBAN 2025'!$B$4,IF(AD15="TIPO IV",'BASE LIQUIDACION REDEBAN 2025'!$B$5,IF(AE15="AEREO",'BASE LIQUIDACION REDEBAN 2025'!$B$6,'BASE LIQUIDACION REDEBAN 2025'!$B$5))))) -> 163813.7 | AJ15: =IF(AD15="TIPO I",'BASE LIQUIDACION REDEBAN 2025'!$B$10,IF(AD15="TIPO II",'BASE LIQUIDACION REDEBAN 2025'!$B$11,IF(AD15="TIPO III",'BASE LIQUIDACION REDEBAN 2025'!$B$12,'BASE LIQUIDACION REDEBAN 2025'!$B$13))) -> 140395.63 | AK15: =AG15*AI15+AH15*AJ15 -> 163813.7
A16: BARRANQUILLA | B16: =VLOOKUP(A16,'CENTRO DE COSTOS'!A:D,4,FALSE) -> JOSE MAURICIO HERNANDEZ ROJAS | C16: =VLOOKUP(A16,'CENTRO DE COSTOS'!A:D,2,FALSE) -> 0004-0001 | D16: 8001 | E16: TA-25-561210 | F16: FO-25-854649 | G16: 45807 | H16: 45812 | I16: 45807 | J16: 45811 | K16: 45811 | L16: ATLANTICO | M16: BARRANQUILLA | N16: BARRIO LA MAGDALENA BARRANQUILLA 4 | O16: 79598 | P16: CB CRECIMIENTO - NUEVO | Q16: APERTURA | R16: REDEBAN | S16: UNO A UNO | T16: UNO A UNO | U16: EJECUTADO | V16: 30-05-2025 SE REALIZA LLAMADA AL CLIENTE, SE HABLA CON LA SRA LIGIA MUÑOS SILVA SE VALIDA DIRECCIÓN OK, CANAL OK, DISPONIBILIDAD TOTAL, LLAMAR EL DÍA LA INSTALACIÓN PARA CONFIRMAR VISITA, AVISO EXTERIOR ALTURA: 2,10 METROS; TOMACORRIENTE CERCANO: SI; TIENE CABINA DE SEGURIDAD: SI // CONTACTO REALIZADO POR LA APP 3/6/2025 SE REALIZA INSTALACIÓN DE CORRESPONSAL, SE INSTALAN EQUIPOS CON PRUEBAS EXITOSAS, SE CAPACITA Y SE EVALÚA AL CLIENTE, SE INSTALA PUBLICIDAD COMPLETA, CB QUEDA OPERATIVO. USUARIO SOMOS BANCOLOMBIA ACTIVO | W16: DE AVILA SIADES ALBERTO ENRIQUE | X16: SXUZZ124 | Y16: 1115570 | Z16: N/A | AA16: 905668 | AB16: N/A | AC16: 40 ROLLOS | AD16: TIPO I | AE16: TERRESTRE | AF16: VISITA_TÉCNICA | AG16: 1 | AH16: 0 | AI16: =IF(AD16="TIPO I",'BASE LIQUIDACION REDEBAN 2025'!$B$2,IF(AD16="TIPO II",'BASE LIQUIDACION REDEBAN 2025'!$B$3,IF(AD16="TIPO III",'BASE LIQUIDACION REDEBAN 2025'!$B$4,IF(AD16="TIPO IV",'BASE LIQUIDACION REDEBAN 2025'!$B$5,IF(AE16="AEREO",'BASE LIQUIDACION REDEBAN 2025'!$B$6,'BASE LIQUIDACION REDEBAN 2025'!$B$5))))) -> 75096.394 | AJ16: =IF(AD16="TIPO I",'BASE LIQUIDACION REDEBAN 2025'!$B$10,IF(AD16="TIPO II",'BASE LIQUIDACION REDEBAN 2025'!$B$11,IF(AD16="TIPO III",'BASE LIQUIDACION REDEBAN 2025'!$B$12,'BASE LIQUIDACION REDEBAN 2025'!$B$13))) -> 75096.394 | AK16: =AG16*AI16+AH16*AJ16 -> 75096.394
A17: CALI | B17: =VLOOKUP(A17,'CENTRO DE COSTOS'!A:D,4,FALSE) -> DIEGO FERNANDO HENAO CARDONA | C17: =VLOOKUP(A17,'CENTRO DE COSTOS'!A:D,2,FALSE) -> 0004-0003 | D17: 76126 | E17: TA-25-561211 | F17: FO-25-854657 | G17: 45807 | H17: 45812 | I17: 45807 | J17: 45812 | K17: 45812 | L17: VALLE DEL CAUCA | M17: CALIMA | N17: BARRIO OBRERO CALIMA | O17: 79619 | P17: CB CRECIMIENTO - NUEVO | Q17: APERTURA | R17: REDEBAN | S17: UNO A UNO | T17: UNO A UNO | U17: EJECUTADO | V17: 30-05-2025 SE REALIZA LLAMADA AL CLIENTE, SE HABLA CON LA SRA SHARIN LOPEZ ARANA SE VALIDA DIRECCIÓN OK, CANAL OK, DISPONIBILIDAD TOTAL, LLAMAR EL DÍA LA INSTALACIÓN PARA CONFIRMAR VISITA, AVISO EXTERIOR ALTURA: 2 - 2,50 METROS; TOMACORRIENTE CERCANO: SI; TIENE CABINA DE SEGURIDAD: NO // CONTACTO REALIZADO POR LA APP 4/6/2025 SE REALIZA INSTALACIÓN DE CORRESPONSAL, SE INSTALAN EQUIPOS CON PRUEBAS EXITOSAS, SE CAPACITA Y SE EVALÚA AL CLIENTE, SE INSTALA PUBLICIDAD COMPLETA, CB QUEDA OPERATIVO. USUARIO SOMOS BANCOLOMBIA ACTIVO | W17: HERRERA MONAR GEOVANNY | X17: SXUZZ145 | Y17: 793073 | Z17: N/A | AA17: 750456 | AB17: N/A | AC17: 40 ROLLOS | AD17: TIPO II | AE17: TERRESTRE | AF17: VISITA_TÉCNICA | AG17: 1 | AH17: 0 | AI17: =IF(AD17="TIPO I",'BASE LIQUIDACION REDEBAN 2025'!$B$2,IF(AD17="TIPO II",'BASE LIQUIDACION REDEBAN 2025'!$B$3,IF(AD17="TIPO III",'BASE LIQUIDACION REDEBAN 2025'!$B$4,IF(AD17="TIPO IV",'BASE LIQUIDACION REDEBAN 2025'!$B$5,IF(AE17="AEREO",'BASE LIQUIDACION REDEBAN 2025'!$B$6,'BASE LIQUIDACION REDEBAN 2025'!$B$5))))) -> 163813.7 | AJ17: =IF(AD17="TIPO I",'BASE LIQUIDACION REDEBAN 2025'!$B$10,IF(AD17="TIPO II",'BASE LIQUIDACION REDEBAN 2025'!$B$11,IF(AD17="TIPO III",'BASE LIQUIDACION REDEBAN 2025'!$B$12,'BASE LIQUIDACION REDEBAN 2025'!$B$13))) -> 140395.63 | AK17: =AG17*AI17+AH17*AJ17 -> 163813.7
A18: MEDELLIN | B18: =VLOOKUP(A18,'CENTRO DE COSTOS'!A:D,4,FALSE) -> JUAN SEBASTIÁN RÍOS CASTRILLÓN | C18: =VLOOKUP(A18,'CENTRO DE COSTOS'!A:D,2,FALSE) -> 0004-0005 | D18: 5088 | E18: TA-25-561212 | F18: FO-25-854662 | G18: 45807 | H18: 45812 | I18: 45807 | J18: 45811 | K18: 45811 | L18: ANTIOQUIA | M18: BELLO | N18: BARRIO PACHELY BELLO 1 | O18: 79661 | P18: CB CRECIMIENTO - NUEVO | Q18: APERTURA | R18: REDEBAN | S18: UNO A UNO | T18: UNO A UNO | U18: EJECUTADO | V18: 30-05-2025 SE REALIZA LLAMADA AL CLIENTE, SE HABLA CON EL SR JUAN DAVID GUTIERREZ OQUENDO SE VALIDA DIRECCIÓN OK, CANAL OK, DISPONIBILIDAD TOTAL, LLAMAR EL DÍA LA INSTALACIÓN PARA CONFIRMAR VISITA, AVISO EXTERIOR ALTURA APROX 3 METROS; TOMACORRIENTE CERCANO: SI; TIENE CABINA DE SEGURIDAD: NO // CONTACTO REALIZADO POR LA APP 3/6/2025 SE REALIZA INSTALACIÓN DE CORRESPONSAL, SE INSTALAN EQUIPOS CON PRUEBAS EXITOSAS, SE CAPACITA Y SE EVALÚA AL CLIENTE, SE INSTALA PUBLICIDAD COMPLETA, CB QUEDA OPERATIVO. USUARIO SOMOS BANCOLOMBIA ACTIVO | W18: ZAPATA LOPEZ EDWARD ASDRUBAL | X18: SXUZZ187 | Y18: 1175437 | Z18: N/A | AA18: 1239626 | AB18: N/A | AC18: 40 ROLLOS | AD18: TIPO I | AE18: TERRESTRE | AF18: VISITA_TÉCNICA | AG18: 1 | AH18: 0 | AI18: =IF(AD18="TIPO I",'BASE LIQUIDACION REDEBAN 2025'!$B$2,IF(AD18="TIPO II",'BASE LIQUIDACION REDEBAN 2025'!$B$3,IF(AD18="TIPO III",'BASE LIQUIDACION REDEBAN 2025'!$B$4,IF(AD18="TIPO IV",'BASE LIQUIDACION REDEBAN 2025'!$B$5,IF(AE18="AEREO",'BASE LIQUIDACION REDEBAN 2025'!$B$6,'BASE LIQUIDACION REDEBAN 2025'!$B$5))))) -> 75096.394 | AJ18: =IF(AD18="TIPO I",'BASE LIQUIDACION REDEBAN 2025'!$B$10,IF(AD18="TIPO II",'BASE LIQUIDACION REDEBAN 2025'!$B$11,IF(AD18="TIPO III",'BASE LIQUIDACION REDEBAN 2025'!$B$12,'BASE LIQUIDACION REDEBAN 2025'!$B$13))) -> 75096.394 | AK18: =AG18*AI18+AH18*AJ18 -> 75096.394
A19: BOGOTA | B19: =VLOOKUP(A19,'CENTRO DE COSTOS'!A:D,4,FALSE) -> WILLIAM ASDRUBAL ROZO ROZO | C19: =VLOOKUP(A19,'CENTRO DE COSTOS'!A:D,2,FALSE) -> 0004-0004 | D19: 11001 | E19: TA-25-561213 | F19: FO-25-854669 | G19: 45807 | H19: 45812 | I19: 45807 | J19: 45811 | K19: 45811 | L19: CUNDINAMARCA | M19: BOGOTA | N19: BARRIO EL POA BOGOTA 1 | O19: 79614 | P19: CB CRECIMIENTO - NUEVO | Q19: APERTURA | R19: REDEBAN | S19: UNO A UNO | T19: UNO A UNO | U19: EJECUTADO | V19: 30-05-2025 SE REALIZA LLAMADA AL CLIENTE, SE HABLA CON LA SRA BLANCA NIDIA RAMIREZ QUINTERO SE VALIDA DIRECCIÓN OK, CANAL OK, DISPONIBILIDAD TOTAL, LLAMAR EL DÍA LA INSTALACIÓN PARA CONFIRMAR VISITA, AVISO EXTERIOR ALTURA APROX CLIENTE NO TIENE CONOCIMIENTO DE MEDIDAS; TOMACORRIENTE CERCANO: SI; TIENE CABINA DE SEGURIDAD: SI // CONTACTO REALIZADO POR LA APP 3/6/2025 SE REALIZA INSTALACIÓN DE CORRESPONSAL, SE INSTALAN EQUIPOS CON PRUEBAS EXITOSAS, SE CAPACITA Y SE EVALÚA AL CLIENTE, SE INSTALA PUBLICIDAD COMPLETA, CB QUEDA OPERATIVO. USUARIO SOMOS BANCOLOMBIA ACTIVO | W19: MURCIA HERNANDEZ HARVEY IGNACIO | X19: SXUZZ140 | Y19: 1040491 | Z19: N/A | AA19: 1110498 | AB19: N/A | AC19: 40 ROLLOS | AD19: TIPO I | AE19: TERRESTRE | AF19: VISITA_TÉCNICA | AG19: 1 | AH19: 0 | AI19: =IF(AD19="TIPO I",'BASE LIQUIDACION REDEBAN 2025'!$B$2,IF(AD19="TIPO II",'BASE LIQUIDACION REDEBAN 2025'!$B$3,IF(AD19="TIPO III",'BASE LIQUIDACION REDEBAN 2025'!$B$4,IF(AD19="TIPO IV",'BASE LIQUIDACION REDEBAN 2025'!$B$5,IF(AE19="AEREO",'BASE LIQUIDACION REDEBAN 2025'!$B$6,'BASE LIQUIDACION REDEBAN 2025'!$B$5))))) -> 75096.394 | AJ19: =IF(AD19="TIPO I",'BASE LIQUIDACION REDEBAN 2025'!$B$10,IF(AD19="TIPO II",'BASE LIQUIDACION REDEBAN 2025'!$B$11,IF(AD19="TIPO III",'BASE LIQUIDACION REDEBAN 2025'!$B$12,'BASE LIQUIDACION REDEBAN 2025'!$B$13))) -> 75096.394 | AK19: =AG19*AI19+AH19*AJ19 -> 75096.394
A20: MEDELLIN | B20: =VLOOKUP(A20,'CENTRO DE COSTOS'!A:D,4,FALSE) -> JUAN SEBASTIÁN RÍOS CASTRILLÓN | C20: =VLOOKUP(A20,'CENTRO DE COSTOS'!A:D,2,FALSE) -> 0004-0005 | D20: 5001 | E20: TA-25-561215 | F20: FO-25-854673 | G20: 45807 | H20: 45812 | I20: 45807 | J20: 45811 | K20: 45811 | L20: ANTIOQUIA | M20: MEDELLIN | N20: BARRIO CALASANZ MEDELLIN 7 | O20: 79676 | P20: CB CRECIMIENTO - NUEVO | Q20: APERTURA | R20: REDEBAN | S20: UNO A UNO | T20: UNO A UNO | U20: EJECUTADO | V20: 30-05-2025 SE REALIZA LLAMADA AL CLIENTE, SE HABLA CON EL SR LUIS FERNANDO ARIAS RIOS SE VALIDA DIRECCIÓN OK, CANAL OK, DISPONIBILIDAD TOTAL, LLAMAR EL DÍA LA INSTALACIÓN PARA CONFIRMAR VISITA, AVISO EXTERIOR ALTURA APROX NO TIENE CONOCIMIENTO DE MEDIDAS; TOMACORRIENTE CERCANO: SI; TIENE CABINA DE SEGURIDAD: NO // CONTACTO REALIZADO POR LA APP 3/6/2025 SE REALIZA INSTALACIÓN DE CORRESPONSAL, SE INSTALAN EQUIPOS CON PRUEBAS EXITOSAS, SE CAPACITA Y SE EVALÚA AL CLIENTE, SE INSTALA PUBLICIDAD COMPLETA, CB QUEDA OPERATIVO. USUARIO SOMOS BANCOLOMBIA ACTIVO | W20: BADEL ACUÑA LUIS ALBERTO | X20: SXUZZ202 | Y20: 1092122 | Z20: N/A | AA20: 1239775 | AB20: N/A | AC20: 40 ROLLOS | AD20: TIPO I | AE20: TERRESTRE | AF20: VISITA_TÉCNICA | AG20: 1 | AH20: 0 | AI20: =IF(AD20="TIPO I",'BASE LIQUIDACION REDEBAN 2025'!$B$2,IF(AD20="TIPO II",'BASE LIQUIDACION REDEBAN 2025'!$B$3,IF(AD20="TIPO III",'BASE LIQUIDACION REDEBAN 2025'!$B$4,IF(AD20="TIPO IV",'BASE LIQUIDACION REDEBAN 2025'!$B$5,IF(AE20="AEREO",'BASE LIQUIDACION REDEBAN 2025'!$B$6,'BASE LIQUIDACION REDEBAN 2025'!$B$5))))) -> 75096.394 | AJ20: =IF(AD20="TIPO I",'BASE LIQUIDACION REDEBAN 2025'!$B$10,IF(AD20="TIPO II",'BASE LIQUIDACION REDEBAN 2025'!$B$11,IF(AD20="TIPO III",'BASE LIQUIDACION REDEBAN 2025'!$B$12,'BASE LIQUIDACION REDEBAN 2025'!$B$13))) -> 75096.394 | AK20: =AG20*AI20+AH20*AJ20 -> 75096.394
A21: CALI | B21: =VLOOKUP(A21,'CENTRO DE COSTOS'!A:D,4,FALSE) -> DIEGO FERNANDO HENAO CARDONA | C21: =VLOOKUP(A21,'CENTRO DE COSTOS'!A:D,2,FALSE) -> 0004-0003 | D21: 76001 | E21: TA-25-561216 | F21: FO-25-854677 | G21: 45807 | H21: 45812 | I21: 45807 | J21: 45811 | K21: 45811 | L21: VALLE DEL CAUCA | M21: CALI | N21: BARRIO ALTOS DE SANTA ELENA CALI | O21: 79618 | P21: CB CRECIMIENTO - NUEVO | Q21: APERTURA | R21: REDEBAN | S21: UNO A UNO | T21: UNO A UNO | U21: EJECUTADO | V21: 30-05-2025 SE REALIZA LLAMADA AL CLIENTE, SE HABLA CON LA SRA DIANA MARCELA VELEZ HUERTAS SE VALIDA DIRECCIÓN OK, CANAL OK, DISPONIBILIDAD TOTAL, LLAMAR EL DÍA LA INSTALACIÓN PARA CONFIRMAR VISITA, AVISO EXTERIOR ALTURA APROX 2 METROS; TOMACORRIENTE CERCANO: SI; TIENE CABINA DE SEGURIDAD: NO // CONTACTO REALIZADO POR LA APP 3/6/2025 SE REALIZA INSTALACIÓN DE CORRESPONSAL, SE INSTALAN EQUIPOS CON PRUEBAS EXITOSAS, SE CAPACITA Y SE EVALÚA AL CLIENTE, SE INSTALA PUBLICIDAD COMPLETA, CB QUEDA OPERATIVO. USUARIO SOMOS BANCOLOMBIA ACTIVO | W21: MONTERO MUESES GIAN CARLO | X21: SXUZZ144 | Y21: 1074324 | Z21: N/A | AA21: 864190 | AB21: N/A | AC21: 40 ROLLOS | AD21: TIPO I | AE21: TERRESTRE | AF21: VISITA_TÉCNICA | AG21: 1 | AH21: 0 | AI21: =IF(AD21="TIPO I",'BASE LIQUIDACION REDEBAN 2025'!$B$2,IF(AD21="TIPO II",'BASE LIQUIDACION REDEBAN 2025'!$B$3,IF(AD21="TIPO III",'BASE LIQUIDACION REDEBAN 2025'!$B$4,IF(AD21="TIPO IV",'BASE LIQUIDACION REDEBAN 2025'!$B$5,IF(AE21="AEREO",'BASE LIQUIDACION REDEBAN 2025'!$B$6,'BASE LIQUIDACION REDEBAN 2025'!$B$5))))) -> 75096.394 | AJ21: =IF(AD21="TIPO I",'BASE LIQUIDACION REDEBAN 2025'!$B$10,IF(AD21="TIPO II",'BASE LIQUIDACION REDEBAN 2025'!$B$11,IF(AD21="TIPO III",'BASE LIQUIDACION REDEBAN 2025'!$B$12,'BASE LIQUIDACION REDEBAN 2025'!$B$13))) -> 75096.394 | AK21: =AG21*AI21+AH21*AJ21 -> 75096.394
A22: CALI | B22: =VLOOKUP(A22,'CENTRO DE COSTOS'!A:D,4,FALSE) -> DIEGO FERNANDO HENAO CARDONA | C22: =VLOOKUP(A22,'CENTRO DE COSTOS'!A:D,2,FALSE) -> 0004-0003 | D22: 76563 | E22: TA-25-561217 | F22: FO-25-854680 | G22: 45807 | H22: 45812 | I22: 45807 | J22: 45811 | K22: 45811 | L22: VALLE DEL CAUCA | M22: PRADERA | N22: BARRIO CENTRO PRADERA 9 | O22: 79650 | P22: CB CRECIMIENTO - NUEVO | Q22: APERTURA | R22: REDEBAN | S22: UNO A UNO | T22: UNO A UNO | U22: EJECUTADO | V22: 30-05-2025 SE REALIZA LLAMADA AL CLIENTE, SE HABLA CON LA SRA YEDSICA LORENA PLAZA SALAZAR SE VALIDA DIRECCIÓN OK, CANAL OK, DISPONIBILIDAD TOTAL, LLAMAR EL DÍA LA INSTALACIÓN PARA CONFIRMAR VISITA, AVISO EXTERIOR ALTURA APROX 1,30 METROS; TOMACORRIENTE CERCANO: SI; TIENE CABINA DE SEGURIDAD: NO // CONTACTO REALIZADO POR LA APP 03-06 SE REALIZA INSTALACIÓN DE CORRESPONSAL, SE INSTALAN EQUIPOS CON PRUEBAS EXITOSAS, SE CAPACITA Y SE EVALÚA AL CLIENTE, SE INSTALA PUBLICIDAD COMPLETA, CB QUEDA OPERATIVO. USUARIO SOMOS BANCOLOMBIA ACTIVO | W22: TORRES GARCIA JENDRY JOSE | X22: SXUZZ176 | Y22: 868754 | Z22: N/A | AA22: 846414 | AB22: N/A | AC22: 40 ROLLOS | AD22: TIPO II | AE22: TERRESTRE | AF22: VISITA_TÉCNICA | AG22: 1 | AH22: 0 | AI22: =IF(AD22="TIPO I",'BASE LIQUIDACION REDEBAN 2025'!$B$2,IF(AD22="TIPO II",'BASE LIQUIDACION REDEBAN 2025'!$B$3,IF(AD22="TIPO III",'BASE LIQUIDACION REDEBAN 2025'!$B$4,IF(AD22="TIPO IV",'BASE LIQUIDACION REDEBAN 2025'!$B$5,IF(AE22="AEREO",'BASE LIQUIDACION REDEBAN 2025'!$B$6,'BASE LIQUIDACION REDEBAN 2025'!$B$5))))) -> 163813.7 | AJ22: =IF(AD22="TIPO I",'BASE LIQUIDACION REDEBAN 2025'!$B$10,IF(AD22="TIPO II",'BASE LIQUIDACION REDEBAN 2025'!$B$11,IF(AD22="TIPO III",'BASE LIQUIDACION REDEBAN 2025'!$B$12,'BASE LIQUIDACION REDEBAN 2025'!$B$13))) -> 140395.63 | AK22: =AG22*AI22+AH22*AJ22 -> 163813.7
A23: BOGOTA | B23: =VLOOKUP(A23,'CENTRO DE COSTOS'!A:D,4,FALSE) -> WILLIAM ASDRUBAL ROZO ROZO | C23: =VLOOKUP(A23,'CENTRO DE COSTOS'!A:D,2,FALSE) -> 0004-0004 | D23: 11001 | E23: TA-25-561218 | F23: FO-25-854684 | G23: 45807 | H23: 45812 | I23: 45807 | J23: 45811 | K23: 45811 | L23: CUNDINAMARCA | M23: BOGOTA | N23: BARRIO VILLA ALAMOS BOGOTA | O23: 79609 | P23: CB CRECIMIENTO - NUEVO | Q23: APERTURA | R23: REDEBAN | S23: UNO A UNO | T23: UNO A UNO | U23: EJECUTADO | V23: 30-05-2025 SE REALIZA LLAMADA AL CLIENTE, SE HABLA CON LA SRA YESSICA SAAVEDRA PARRA SE VALIDA DIRECCIÓN OK, CANAL OK, DISPONIBILIDAD TOTAL, LLAMAR EL DÍA LA INSTALACIÓN PARA CONFIRMAR VISITA, AVISO EXTERIOR ALTURA APROX 2,50 A 3 METROS; TOMACORRIENTE CERCANO: SI; TIENE CABINA DE SEGURIDAD: NO // CONTACTO REALIZADO POR LA APP 3/6/2025 SE REALIZA INSTALACIÓN DE CORRESPONSAL, SE INSTALAN EQUIPOS CON PRUEBAS EXITOSAS, SE CAPACITA Y SE EVALÚA AL CLIENTE, SE INSTALA PUBLICIDAD COMPLETA, CB QUEDA OPERATIVO. USUARIO SOMOS BANCOLOMBIA ACTIVO | W23: GOMEZ VEGA DAVID SNEYDER | X23: SXUZZ135 | Y23: 1021069 | Z23: N/A | AA23: 1076249 | AB23: N/A | AC23: 40 ROLLOS | AD23: TIPO I | AE23: TERRESTRE | AF23: VISITA_TÉCNICA | AG23: 1 | AH23: 0 | AI23: =IF(AD23="TIPO I",'BASE LIQUIDACION REDEBAN 2025'!$B$2,IF(AD23="TIPO II",'BASE LIQUIDACION REDEBAN 2025'!$B$3,IF(AD23="TIPO III",'BASE LIQUIDACION REDEBAN 2025'!$B$4,IF(AD23="TIPO IV",'BASE LIQUIDACION REDEBAN 2025'!$B$5,IF(AE23="AEREO",'BASE LIQUIDACION REDEBAN 2025'!$B$6,'BASE LIQUIDACION REDEBAN 2025'!$B$5))))) -> 75096.394 | AJ23: =IF(AD23="TIPO I",'BASE LIQUIDACION REDEBAN 2025'!$B$10,IF(AD23="TIPO II",'BASE LIQUIDACION REDEBAN 2025'!$B$11,IF(AD23="TIPO III",'BASE LIQUIDACION REDEBAN 2025'!$B$12,'BASE LIQUIDACION REDEBAN 2025'!$B$13))) -> 75096.394 | AK23: =AG23*AI23+AH23*AJ23 -> 75096.394
A24: BOGOTA | B24: =VLOOKUP(A24,'CENTRO DE COSTOS'!A:D,4,FALSE) -> WILLIAM ASDRUBAL ROZO ROZO | C24: =VLOOKUP(A24,'CENTRO DE COSTOS'!A:D,2,FALSE) -> 0004-0004 | D24: 11001 | E24: TA-25-561219 | F24: FO-25-854690 | G24: 45807 | H24: 45812 | I24: 45807 | J24: 45811 | K24: 45811 | L24: CUNDINAMARCA | M24: BOGOTA | N24: BARRIO SANTA LUCIA BOGOTA 11 | O24: 79615 | P24: CB CRECIMIENTO - NUEVO | Q24: APERTURA | R24: REDEBAN | S24: UNO A UNO | T24: UNO A UNO | U24: EJECUTADO | V24: 30-05-2025 SE REALIZA LLAMADA AL CLIENTE, SE HABLA CON LA SRA DORA EDITH NAVARRETE SE VALIDA DIRECCIÓN OK, CANAL OK, DISPONIBILIDAD TOTAL, LLAMAR EL DÍA LA INSTALACIÓN PARA CONFIRMAR VISITA, AVISO EXTERIOR ALTURA APROX 3 METROS; TOMACORRIENTE CERCANO: SI; TIENE CABINA DE SEGURIDAD: SI // CONTACTO REALIZADO POR LA APP 3/6/2025 SE REALIZA INSTALACIÓN DE CORRESPONSAL, SE INSTALAN EQUIPOS CON PRUEBAS EXITOSAS, SE CAPACITA Y SE EVALÚA AL CLIENTE, SE INSTALA PUBLICIDAD COMPLETA, CB QUEDA OPERATIVO. USUARIO SOMOS BANCOLOMBIA ACTIVO | W24: ROMERO ROJAS BREIDY JHOHAN | X24: SXUZZ141 | Y24: 1235482 | Z24: 917143 | AA24: 1139296-241597317561324755897568 | AB24: N/A | AC24: 40 ROLLOS | AD24: TIPO I | AE24: TERRESTRE | AF24: VISITA_TÉCNICA | AG24: 1 | AH24: 0 | AI24: =IF(AD24="TIPO I",'BASE LIQUIDACION REDEBAN 2025'!$B$2,IF(AD24="TIPO II",'BASE LIQUIDACION REDEBAN 2025'!$B$3,IF(AD24="TIPO III",'BASE LIQUIDACION REDEBAN 2025'!$B$4,IF(AD24="TIPO IV",'BASE LIQUIDACION REDEBAN 2025'!$B$5,IF(AE24="AEREO",'BASE LIQUIDACION REDEBAN 2025'!$B$6,'BASE LIQUIDACION REDEBAN 2025'!$B$5))))) -> 75096.394 | AJ24: =IF(AD24="TIPO I",'BASE LIQUIDACION REDEBAN 2025'!$B$10,IF(AD24="TIPO II",'BASE LIQUIDACION REDEBAN 2025'!$B$11,IF(AD24="TIPO III",'BASE LIQUIDACION REDEBAN 2025'!$B$12,'BASE LIQUIDACION REDEBAN 2025'!$B$13))) -> 75096.394 | AK24: =AG24*AI24+AH24*AJ24 -> 75096.394
A25: MEDELLIN | B25: =VLOOKUP(A25,'CENTRO DE COSTOS'!A:D,4,FALSE) -> JUAN SEBASTIÁN RÍOS CASTRILLÓN | C25: =VLOOKUP(A25,'CENTRO DE COSTOS'!A:D,2,FALSE) -> 0004-0005 | D25: 5079 | E25: TA-25-561220 | F25: FO-25-854692 | G25: 45807 | H25: 45812 | I25: 45807 | J25: 45812 | K25: 45812 | L25: ANTIOQUIA | M25: BARBOSA | N25: BARRIO GGTO HATILLO BARBOSA BARBOSA | O25: 79624 | P25: CB CRECIMIENTO - NUEVO | Q25: APERTURA | R25: REDEBAN | S25: UNO A UNO | T25: UNO A UNO | U25: EJECUTADO | V25: 30-05-2025 SE REALIZA LLAMADA AL CLIENTE, SE HABLA CON LA SRA ALEJANDRA MARCELA MACIAS ECHEVERRI SE VALIDA DIRECCIÓN OK, CANAL OK, DISPONIBILIDAD TOTAL, LLAMAR EL DÍA LA INSTALACIÓN PARA CONFIRMAR VISITA, AVISO EXTERIOR ALTURA APROX 1,80 METROS; TOMACORRIENTE CERCANO: SI; TIENE CABINA DE SEGURIDAD: SI // CONTACTO REALIZADO POR LA APP 4/6/2025 SE REALIZA INSTALACIÓN DE CORRESPONSAL, SE INSTALAN EQUIPOS CON PRUEBAS EXITOSAS, SE CAPACITA Y SE EVALÚA AL CLIENTE, SE INSTALA PUBLICIDAD COMPLETA, CB QUEDA OPERATIVO. USUARIO SOMOS BANCOLOMBIA ACTIVO. SE PRESENTO NOVEDAD CON DIRECCIÓN YA QUE EN LISTA APARECE CORREGIMIENTO, PERO EN CAMARA DE COMERCIO NO, SE ESCALO CASO A RBM Y AUTORIZARON LA INSTALACIÓN YA QUE EL COMERCIO SI QUEDA EN EL CORREGIMIENTO | W25: ALVAREZ ARENAS VICTOR HUGO | X25: SXUZZ150 | Y25: 1051697 | Z25: N/A | AA25: 863827 | AB25: N/A | AC25: 40 ROLLOS | AD25: TIPO II | AE25: TERRESTRE | AF25: VISITA_TÉCNICA | AG25: 1 | AH25: 0 | AI25: =IF(AD25="TIPO I",'BASE LIQUIDACION REDEBAN 2025'!$B$2,IF(AD25="TIPO II",'BASE LIQUIDACION REDEBAN 2025'!$B$3,IF(AD25="TIPO III",'BASE LIQUIDACION REDEBAN 2025'!$B$4,IF(AD25="TIPO IV",'BASE LIQUIDACION REDEBAN 2025'!$B$5,IF(AE25="AEREO",'BASE LIQUIDACION REDEBAN 2025'!$B$6,'BASE LIQUIDACION REDEBAN 2025'!$B$5))))) -> 163813.7 | AJ25: =IF(AD25="TIPO I",'BASE LIQUIDACION REDEBAN 2025'!$B$10,IF(AD25="TIPO II",'BASE LIQUIDACION REDEBAN 2025'!$B$11,IF(AD25="TIPO III",'BASE LIQUIDACION REDEBAN 2025'!$B$12,'BASE LIQUIDACION REDEBAN 2025'!$B$13))) -> 140395.63 | AK25: =AG25*AI25+AH25*AJ25 -> 163813.7
A26: BOGOTA | B26: =VLOOKUP(A26,'CENTRO DE COSTOS'!A:D,4,FALSE) -> WILLIAM ASDRUBAL ROZO ROZO | C26: =VLOOKUP(A26,'CENTRO DE COSTOS'!A:D,2,FALSE) -> 0004-0004 | D26: 11001 | E26: TA-25-561221 | F26: FO-25-854696 | G26: 45807 | H26: 45812 | I26: 45807 | J26: 45812 | K26: 45812 | L26: CUNDINAMARCA | M26: BOGOTA | N26: BARRIO LAS ACACIAS BOGOTA 1 | O26: 79610 | P26: CAMBIO DE REZON SOCIAL | Q26: APERTURA | R26: REDEBAN | S26: UNO A UNO | T26: UNO A UNO | U26: EJECUTADO | V26: 30-05-2025 SE REALIZA LLAMADA AL CLIENTE, SE HABLA CON LA HERMANA DEL SR JAIBER JULIAN LOPEZ MARTINEZ SE VALIDA DIRECCIÓN OK, CANAL OK, DISPONIBILIDAD TOTAL, LLAMAR EL DÍA LA INSTALACIÓN PARA CONFIRMAR VISITA, AVISO EXTERIOR ALTURA APROX 2; TOMACORRIENTE CERCANO: SI; TIENE CABINA DE SEGURIDAD: SI // CONTACTO REALIZADO POR LA APP 03-06 EN COMUNICACIÓN CON EL COMERCIO PARA VALIDAR APERTURA AL JAIBER JULIAN LOPEZ MARTINEZ / TELEFONO DE CONTACTO: 3222100576, MANIFIESTA RECIBIR EL DÍA DE MAÑANA 04-06-2025 4/6/2025 SE REALIZA INSTALACIÓN DE CORRESPONSAL, SE INSTALAN EQUIPOS CON PRUEBAS EXITOSAS, SE CAPACITA Y SE EVALÚA AL CLIENTE, SE INSTALA PUBLICIDAD COMPLETA, CB QUEDA OPERATIVO. USUARIO SOMOS BANCOLOMBIA ACTIVO | W26: ROMERO ROJAS BREIDY JHOHAN | X26: SXUZZ136 | Y26: 1235338 | Z26: 893558 | AA26: 984296-241587317561324755886591 | AB26: N/A | AC26: 40 ROLLOS | AD26: TIPO I | AE26: TERRESTRE | AF26: VISITA_TÉCNICA | AG26: 1 | AH26: 0 | AI26: =IF(AD26="TIPO I",'BASE LIQUIDACION REDEBAN 2025'!$B$2,IF(AD26="TIPO II",'BASE LIQUIDACION REDEBAN 2025'!$B$3,IF(AD26="TIPO III",'BASE LIQUIDACION REDEBAN 2025'!$B$4,IF(AD26="TIPO IV",'BASE LIQUIDACION REDEBAN 2025'!$B$5,IF(AE26="AEREO",'BASE LIQUIDACION REDEBAN 2025'!$B$6,'BASE LIQUIDACION REDEBAN 2025'!$B$5))))) -> 75096.394 | AJ26: =IF(AD26="TIPO I",'BASE LIQUIDACION REDEBAN 2025'!$B$10,IF(AD26="TIPO II",'BASE LIQUIDACION REDEBAN 2025'!$B$11,IF(AD26="TIPO III",'BASE LIQUIDACION REDEBAN 2025'!$B$12,'BASE LIQUIDACION REDEBAN 2025'!$B$13))) -> 75096.394 | AK26: =AG26*AI26+AH26*AJ26 -> 75096.394
A27: MEDELLIN | B27: =VLOOKUP(A27,'CENTRO DE COSTOS'!A:D,4,FALSE) -> JUAN SEBASTIÁN RÍOS CASTRILLÓN | C27: =VLOOKUP(A27,'CENTRO DE COSTOS'!A:D,2,FALSE) -> 0004-0005 | D27: 5308 | E27: TA-25-561223 | F27: FO-25-854700 | G27: 45807 | H27: 45812 | I27: 45807 | J27: 45811 | K27: 45811 | L27: ANTIOQUIA | M27: GIRARDOTA | N27: BARRIO SANTA ANA GIRARDOTA 1 | O27: 79627 | P27: CAMBIO DE RAZON SOCIAL | Q27: APERTURA | R27: REDEBAN | S27: UNO A UNO | T27: UNO A UNO | U27: EJECUTADO | V27: 30-05-2025 SE REALIZA LLAMADA AL CLIENTE, SE HABLA CON LA SRA ANGELA YANETH BEDOYA JARAMILLOI SE VALIDA DIRECCIÓN OK, CANAL OK, DISPONIBILIDAD TOTAL, LLAMAR EL DÍA LA INSTALACIÓN PARA CONFIRMAR VISITA, AVISO EXTERIOR ALTURA APROX 2 METROS; TOMACORRIENTE CERCANO: SI; TIENE CABINA DE SEGURIDAD: SI // CONTACTO REALIZADO POR LA APP 03-06 SE REALIZA INSTALACIÓN DE CORRESPONSAL POR CAMBIO DE RAZON SOCIAL, SE INSTALAN EQUIPOS CON PRUEBAS EXITOSAS, NO SE CAPACITA Y SE EVALÚA AL CLIENTE, SE INSTALA FLANGGER Y DISPLAY DE HORARIO, EL AVISO YA ESTABA INSTALADO EN BUEN ESTADO, SE REGGRESA EL QUE SE LLEVO A BODEGA, CB QUEDA OPERATIVO. USUARIO SOMOS BANCOLOMBIA ACTIVO | W27: MARTINEZ TOVAR OSCAR DAVID | X27: SXUZZ153 | Y27: 771289 | Z27: N/A | AA27: 940524 | AB27: 1239756 | AC27: 40 ROLLOS | AD27: TIPO I | AE27: TERRESTRE | AF27: VISITA_TÉCNICA | AG27: 1 | AH27: 0 | AI27: =IF(AD27="TIPO I",'BASE LIQUIDACION REDEBAN 2025'!$B$2,IF(AD27="TIPO II",'BASE LIQUIDACION REDEBAN 2025'!$B$3,IF(AD27="TIPO III",'BASE LIQUIDACION REDEBAN 2025'!$B$4,IF(AD27="TIPO IV",'BASE LIQUIDACION REDEBAN 2025'!$B$5,IF(AE27="AEREO",'BASE LIQUIDACION REDEBAN 2025'!$B$6,'BASE LIQUIDACION REDEBAN 2025'!$B$5))))) -> 75096.394 | AJ27: =IF(AD27="TIPO I",'BASE LIQUIDACION REDEBAN 2025'!$B$10,IF(AD27="TIPO II",'BASE LIQUIDACION REDEBAN 2025'!$B$11,IF(AD27="TIPO III",'BASE LIQUIDACION REDEBAN 2025'!$B$12,'BASE LIQUIDACION REDEBAN 2025'!$B$13))) -> 75096.394 | AK27: =AG27*AI27+AH27*AJ27 -> 75096.394
A28: MEDELLIN | B28: =VLOOKUP(A28,'CENTRO DE COSTOS'!A:D,4,FALSE) -> JUAN SEBASTIÁN RÍOS CASTRILLÓN | C28: =VLOOKUP(A28,'CENTRO DE COSTOS'!A:D,2,FALSE) -> 0004-0005 | D28: 5001 | E28: TA-25-561224 | F28: FO-25-854708 | G28: 45807 | H28: 45812 | I28: 45807 | J28: 45811 | K28: 45811 | L28: ANTIOQUIA | M28: MEDELLIN | N28: BARRIO BELLEN MEDELLIN | O28: 79669 | P28: CAMBIO DE RAZON SOCIAL | Q28: APERTURA | R28: REDEBAN | S28: UNO A UNO | T28: UNO A UNO | U28: EJECUTADO | V28: 30-05-2025 SE REALIZA LLAMADA AL CLIENTE, SE HABLA CON EL SR WALTER ANDRES HERNANDEZ GUERRA SE VALIDA DIRECCIÓN OK, CANAL OK, DISPONIBILIDAD TOTAL, LLAMAR EL DÍA LA INSTALACIÓN PARA CONFIRMAR VISITA, AVISO EXTERIOR ALTURA APROX 3 - 4 METROS; TOMACORRIENTE CERCANO: SI; TIENE CABINA DE SEGURIDAD: SI // CONTACTO REALIZADO POR LA APP 3/6/2025 SE REALIZA INSTALACIÓN DE CORRESPONSAL POR CAMBIO DE RAZON SOCIAL, SE INSTALAN EQUIPOS CON PRUEBAS EXITOSAS, SE CAPACITA Y SE EVALÚA AL CLIENTE, NO SE INSTALA PUBLICIDAD, CB QUEDA OPERATIVO. USUARIO SOMOS BANCOLOMBIA ACTIVO | W28: QUINTERO SANCHEZ JUAN SEBASTIAN | X28: SXUZZ195 | Y28: 772256 | Z28: N/A | AA28: 1239771 | AB28: N/A | AC28: 40 ROLLOS | AD28: TIPO I | AE28: TERRESTRE | AF28: VISITA_TÉCNICA | AG28: 1 | AH28: 0 | AI28: =IF(AD28="TIPO I",'BASE LIQUIDACION REDEBAN 2025'!$B$2,IF(AD28="TIPO II",'BASE LIQUIDACION REDEBAN 2025'!$B$3,IF(AD28="TIPO III",'BASE LIQUIDACION REDEBAN 2025'!$B$4,IF(AD28="TIPO IV",'BASE LIQUIDACION REDEBAN 2025'!$B$5,IF(AE28="AEREO",'BASE LIQUIDACION REDEBAN 2025'!$B$6,'BASE LIQUIDACION REDEBAN 2025'!$B$5))))) -> 75096.394 | AJ28: =IF(AD28="TIPO I",'BASE LIQUIDACION REDEBAN 2025'!$B$10,IF(AD28="TIPO II",'BASE LIQUIDACION REDEBAN 2025'!$B$11,IF(AD28="TIPO III",'BASE LIQUIDACION REDEBAN 2025'!$B$12,'BASE LIQUIDACION REDEBAN 2025'!$B$13))) -> 75096.394 | AK28: =AG28*AI28+AH28*AJ28 -> 75096.394
A29: CARTAGENA | B29: =VLOOKUP(A29,'CENTRO DE COSTOS'!A:D,4,FALSE) -> JOSE MAURICIO HERNANDEZ ROJAS | C29: =VLOOKUP(A29,'CENTRO DE COSTOS'!A:D,2,FALSE) -> 0004-0001 | D29: 13001 | E29: TA-25-561225 | F29: FO-25-854716 | G29: 45807 | H29: 45812 | I29: 45807 | J29: 45812 | K29: 45812 | L29: BOLIVAR | M29: CARTAGENA | N29: BARRIO LOS ANGELES CARTAGENA DE INDIAS | O29: 79621 | P29: CB CRECIMIENTO - NUEVO | Q29: APERTURA | R29: REDEBAN | S29: UNO A UNO | T29: UNO A UNO | U29: EJECUTADO | V29: 30-05-2025 SE REALIZA LLAMADA AL CLIENTE, SE HABLA CON LA SRA GERALDINE OYOLA MENDOZA SE VALIDA DIRECCIÓN OK, CANAL OK, DISPONIBILIDAD TOTAL, LLAMAR EL DÍA LA INSTALACIÓN PARA CONFIRMAR VISITA, AVISO EXTERIOR ALTURA APROX 1,50 - 2 METROS; TOMACORRIENTE CERCANO: SI; TIENE CABINA DE SEGURIDAD: SI // CONTACTO REALIZADO POR LA APP 04-06 SE REALIZA INSTALACIÓN DE CORRESPONSAL, SE INSTALAN EQUIPOS CON PRUEBAS EXITOSAS, SE CAPACITA Y SE EVALÚA AL CLIENTE, SE INSTALA PUBLICIDAD COMPLETA, CB QUEDA OPERATIVO. USUARIO SOMOS BANCOLOMBIA ACTIVO | W29: CANEDO HERRERA ALEXANDER | X29: SXUZZ147 | Y29: 791031 | Z29: N/A | AA29: 529616 | AB29: N/A | AC29: 40 ROLLOS | AD29: TIPO I | AE29: TERRESTRE | AF29: VISITA_TÉCNICA | AG29: 1 | AH29: 0 | AI29: =IF(AD29="TIPO I",'BASE LIQUIDACION REDEBAN 2025'!$B$2,IF(AD29="TIPO II",'BASE LIQUIDACION REDEBAN 2025'!$B$3,IF(AD29="TIPO III",'BASE LIQUIDACION REDEBAN 2025'!$B$4,IF(AD29="TIPO IV",'BASE LIQUIDACION REDEBAN 2025'!$B$5,IF(AE29="AEREO",'BASE LIQUIDACION REDEBAN 2025'!$B$6,'BASE LIQUIDACION REDEBAN 2025'!$B$5))))) -> 75096.394 | AJ29: =IF(AD29="TIPO I",'BASE LIQUIDACION REDEBAN 2025'!$B$10,IF(AD29="TIPO II",'BASE LIQUIDACION REDEBAN 2025'!$B$11,IF(AD29="TIPO III",'BASE LIQUIDACION REDEBAN 2025'!$B$12,'BASE LIQUIDACION REDEBAN 2025'!$B$13))) -> 75096.394 | AK29: =AG29*AI29+AH29*AJ29 -> 75096.394
A30: TUNJA | B30: =VLOOKUP(A30,'CENTRO DE COSTOS'!A:D,4,FALSE) -> MIGUEL JULIÁN HERNÁNDEZ GUARÍN | C30: =VLOOKUP(A30,'CENTRO DE COSTOS'!A:D,2,FALSE) -> 0004-0008 | D30: 15759 | E30: TA-25-561226 | F30: FO-25-854724 | G30: 45807 | H30: 45812 | I30: 45807 | J30: 45813 | K30: 45813 | L30: BOYACA | M30: SOGAMOSO | N30: BARRIO LA PRADERA SOGAMOSO 3 | O30: 79655 | P30: CB CRECIMIENTO - NUEVO | Q30: APERTURA | R30: REDEBAN | S30: UNO A UNO | T30: UNO A UNO | U30: EJECUTADO | V30: 30-05-2025 SE REALIZA LLAMADA AL CLIENTE, SE HABLA CON LA SRA LADIS ESPERANZA SOSA AMAROI SE VALIDA DIRECCIÓN OK, CANAL OK, DISPONIBILIDAD TOTAL, LLAMAR EL DÍA LA INSTALACIÓN PARA CONFIRMAR VISITA, AVISO EXTERIOR ALTURA APROX 3 METROS; TOMACORRIENTE CERCANO: SI; TIENE CABINA DE SEGURIDAD: NO // CONTACTO REALIZADO POR LA APP 3/6/2025 SE VISITA COMERCIO ,LA INSTALACIÓN EL DIA DE HOY ES FALLIDA COMERCIO SIN COMUNICACION RED DE INTERNET ,EL USUARIO INDICA QUE SE COMUNICARA CON EL PROVEDOR DEL INTERNET PARA QUE HABILITE LA RED DE COMUNICACIÓN EN EL COMERCIO A INSTALAR , SE REPROGRAMA VISITA PARA EL DIA JUEVES 05 DE JUNIO DEL 2025 INDICA QUE PARA ESE DIA TENDRIA LISTO EL PUNTO DE INTERNET 5/6/2025 SE REALIZA INSTALACIÓN DE CORRESPONSAL, SE INSTALAN EQUIPOS CON PRUEBAS EXITOSAS, SE CAPACITA Y SE EVALÚA AL CLIENTE, SE INSTALA PUBLICIDAD COMPLETA, CB QUEDA OPERATIVO. USUARIO SOMOS BANCOLOMBIA ACTIVO | W30: ALVARADO MORENO CRISTHIAN | X30: SXUZZ181 | Y30: 793119 | Z30: N/A | AA30: 905615 | AB30: N/A | AC30: 40 ROLLOS | AD30: TIPO II | AE30: TERRESTRE | AF30: VISITA_TÉCNICA | AG30: 1 | AH30: 0 | AI30: =IF(AD30="TIPO I",'BASE LIQUIDACION REDEBAN 2025'!$B$2,IF(AD30="TIPO II",'BASE LIQUIDACION REDEBAN 2025'!$B$3,IF(AD30="TIPO III",'BASE LIQUIDACION REDEBAN 2025'!$B$4,IF(AD30="TIPO IV",'BASE LIQUIDACION REDEBAN 2025'!$B$5,IF(AE30="AEREO",'BASE LIQUIDACION REDEBAN 2025'!$B$6,'BASE LIQUIDACION REDEBAN 2025'!$B$5))))) -> 163813.7 | AJ30: =IF(AD30="TIPO I",'BASE LIQUIDACION REDEBAN 2025'!$B$10,IF(AD30="TIPO II",'BASE LIQUIDACION REDEBAN 2025'!$B$11,IF(AD30="TIPO III",'BASE LIQUIDACION REDEBAN 2025'!$B$12,'BASE LIQUIDACION REDEBAN 2025'!$B$13))) -> 140395.63 | AK30: =AG30*AI30+AH30*AJ30 -> 163813.7
A31: MEDELLIN | B31: =VLOOKUP(A31,'CENTRO DE COSTOS'!A:D,4,FALSE) -> JUAN SEBASTIÁN RÍOS CASTRILLÓN | C31: =VLOOKUP(A31,'CENTRO DE COSTOS'!A:D,2,FALSE) -> 0004-0005 | D31: 5088 | E31: TA-25-561227 | F31: FO-25-854727 | G31: 45807 | H31: 45812 | I31: 45807 | J31: 45811 | K31: 45811 | L31: ANTIOQUIA | M31: BELLO | N31: BARRIO BELLO BELLO 24 | O31: 79660 | P31: CB CRECIMIENTO - NUEVO | Q31: APERTURA | R31: REDEBAN | S31: UNO A UNO | T31: UNO A UNO | U31: EJECUTADO | V31: 30-05-2025 SE REALIZA LLAMADA AL CLIENTE, SE HABLA CON LA SRA JULIANA HOLGUIN BEDOYA SE VALIDA DIRECCIÓN OK, CANAL OK, DISPONIBILIDAD TOTAL, LLAMAR EL DÍA LA INSTALACIÓN PARA CONFIRMAR VISITA, AVISO EXTERIOR ALTURA APROX CLIENTE NO TIENE CONOCIMIENTO DE MEDIDAS; TOMACORRIENTE CERCANO: SI; TIENE CABINA DE SEGURIDAD: SI // CONTACTO REALIZADO POR LA APP 3/6/2025 SE REALIZA INSTALACIÓN DE CORRESPONSAL, SE INSTALAN EQUIPOS CON PRUEBAS EXITOSAS, SE CAPACITA Y SE EVALÚA AL CLIENTE, SE INSTALA PUBLICIDAD COMPLETA, CB QUEDA OPERATIVO. USUARIO SOMOS BANCOLOMBIA ACTIVO | X31: SXUZZ186 | Y31: 929521 | Z31: N/A | AA31: 1239599 | AB31: N/A | AC31: 40 ROLLOS | AD31: TIPO I | AE31: TERRESTRE | AF31: VISITA_TÉCNICA | AG31: 1 | AH31: 0 | AI31: =IF(AD31="TIPO I",'BASE LIQUIDACION REDEBAN 2025'!$B$2,IF(AD31="TIPO II",'BASE LIQUIDACION REDEBAN 2025'!$B$3,IF(AD31="TIPO III",'BASE LIQUIDACION REDEBAN 2025'!$B$4,IF(AD31="TIPO IV",'BASE LIQUIDACION REDEBAN 2025'!$B$5,IF(AE31="AEREO",'BASE LIQUIDACION REDEBAN 2025'!$B$6,'BASE LIQUIDACION REDEBAN 2025'!$B$5))))) -> 75096.394 | AJ31: =IF(AD31="TIPO I",'BASE LIQUIDACION REDEBAN 2025'!$B$10,IF(AD31="TIPO II",'BASE LIQUIDACION REDEBAN 2025'!$B$11,IF(AD31="TIPO III",'BASE LIQUIDACION REDEBAN 2025'!$B$12,'BASE LIQUIDACION REDEBAN 2025'!$B$13))) -> 75096.394 | AK31: =AG31*AI31+AH31*AJ31 -> 75096.394
A32: VILLAVICENCIO | B32: =VLOOKUP(A32,'CENTRO DE COSTOS'!A:D,4,FALSE) -> KEVIN ALEXIS CORZO BUSTOS | C32: =VLOOKUP(A32,'CENTRO DE COSTOS'!A:D,2,FALSE) -> 0004-0007 | D32: 50001 | E32: TA-25-561228 | F32: FO-25-854731 | G32: 45807 | H32: 45812 | I32: 45807 | J32: 45811 | K32: 45811 | L32: META | M32: VILLAVICENCIO | N32: BARRIO VILLA DEL ORIENTE VILLAVICENCIO | O32: 79664 | P32: CB CRECIMIENTO - NUEVO | Q32: APERTURA | R32: REDEBAN | S32: UNO A UNO | T32: UNO A UNO | U32: EJECUTADO | V32: 30-05-2025 SE REALIZA LLAMADA AL CLIENTE, SE HABLA CON LA SRA MARIA MELIDA FORERO DIOSA SE VALIDA DIRECCIÓN OK, CANAL OK, DISPONIBILIDAD TOTAL, LLAMAR EL DÍA LA INSTALACIÓN PARA CONFIRMAR VISITA, AVISO EXTERIOR ALTURA APROX 1,20 METROS; TOMACORRIENTE CERCANO: SI; TIENE CABINA DE SEGURIDAD: SI // CONTACTO REALIZADO POR LA APP 3/6/2025 SE REALIZA INSTALACIÓN DE CORRESPONSAL, SE INSTALAN EQUIPOS CON PRUEBAS EXITOSAS, SE CAPACITA Y SE EVALÚA AL CLIENTE, SE INSTALA PUBLICIDAD COMPLETA, CB QUEDA OPERATIVO. USUARIO SOMOS BANCOLOMBIA ACTIVO | W32: ROZO JIMENEZ EDGAR ARMANDO | X32: SXUZZ190 | Y32: 750929 | Z32: N/A | AA32: 906002 | AB32: N/A | AC32: 40 ROLLOS | AD32: TIPO I | AE32: TERRESTRE | AF32: VISITA_TÉCNICA | AG32: 1 | AH32: 0 | AI32: =IF(AD32="TIPO I",'BASE LIQUIDACION REDEBAN 2025'!$B$2,IF(AD32="TIPO II",'BASE LIQUIDACION REDEBAN 2025'!$B$3,IF(AD32="TIPO III",'BASE LIQUIDACION REDEBAN 2025'!$B$4,IF(AD32="TIPO IV",'BASE LIQUIDACION REDEBAN 2025'!$B$5,IF(AE32="AEREO",'BASE LIQUIDACION REDEBAN 2025'!$B$6,'BASE LIQUIDACION REDEBAN 2025'!$B$5))))) -> 75096.394 | AJ32: =IF(AD32="TIPO I",'BASE LIQUIDACION REDEBAN 2025'!$B$10,IF(AD32="TIPO II",'BASE LIQUIDACION REDEBAN 2025'!$B$11,IF(AD32="TIPO III",'BASE LIQUIDACION REDEBAN 2025'!$B$12,'BASE LIQUIDACION REDEBAN 2025'!$B$13))) -> 75096.394 | AK32: =AG32*AI32+AH32*AJ32 -> 75096.394
A33: VILLAVICENCIO | B33: =VLOOKUP(A33,'CENTRO DE COSTOS'!A:D,4,FALSE) -> KEVIN ALEXIS CORZO BUSTOS | C33: =VLOOKUP(A33,'CENTRO DE COSTOS'!A:D,2,FALSE) -> 0004-0007 | D33: 50001 | E33: TA-25-561229 | F33: FO-25-854737 | G33: 45807 | H33: 45812 | I33: 45807 | J33: 45811 | K33: 45811 | L33: META | M33: VILLAVICENCIO | N33: BARRIO ESTERO VILLAVICENCIO 17 | O33: 79663 | P33: CB CRECIMIENTO - NUEVO | Q33: APERTURA | R33: REDEBAN | S33: UNO A UNO | T33: UNO A UNO | U33: EJECUTADO | V33: 30-05 SE REALIZA LLAMADA AL CLIENTE, SE HABLA CON EL SR FABIO NELSON CASTAÑEDA OSORIO SE VALIDA DIRECCIÓN OK, CANAL OK, DISPONIBILIDAD TOTAL, LLAMAR EL DÍA LA INSTALACIÓN PARA CONFIRMAR VISITA, AVISO EXTERIOR ALTURA APROX DONDE EL TECNICO LO VEA CONVENIENTE METROS; TOMACORRIENTE CERCANO: SI; TIENE CABINA DE SEGURIDAD: SI 03-06 SE REALIZA INSTALACIÓN DE CORRESPONSAL, SE INSTALAN EQUIPOS CON PRUEBAS EXITOSAS, SE CAPACITA Y SE EVALÚA AL CLIENTE, SE INSTALA PUBLICIDAD COMPLETA, CB QUEDA OPERATIVO. USUARIO SOMOS BANCOLOMBIA ACTIVO | W33: ROZO JIMENEZ EDGAR ARMANDO | X33: SXUZZ189 | Y33: 930615 | Z33: N/A | AA33: 770645 | AB33: N/A | AC33: 40 ROLLOS | AD33: TIPO I | AE33: TERRESTRE | AF33: VISITA_TÉCNICA | AG33: 1 | AH33: 0 | AI33: =IF(AD33="TIPO I",'BASE LIQUIDACION REDEBAN 2025'!$B$2,IF(AD33="TIPO II",'BASE LIQUIDACION REDEBAN 2025'!$B$3,IF(AD33="TIPO III",'BASE LIQUIDACION REDEBAN 2025'!$B$4,IF(AD33="TIPO IV",'BASE LIQUIDACION REDEBAN 2025'!$B$5,IF(AE33="AEREO",'BASE LIQUIDACION REDEBAN 2025'!$B$6,'BASE LIQUIDACION REDEBAN 2025'!$B$5))))) -> 75096.394 | AJ33: =IF(AD33="TIPO I",'BASE LIQUIDACION REDEBAN 2025'!$B$10,IF(AD33="TIPO II",'BASE LIQUIDACION REDEBAN 2025'!$B$11,IF(AD33="TIPO III",'BASE LIQUIDACION REDEBAN 2025'!$B$12,'BASE LIQUIDACION REDEBAN 2025'!$B$13))) -> 75096.394 | AK33: =AG33*AI33+AH33*AJ33 -> 75096.394
A34: BOGOTA | B34: =VLOOKUP(A34,'CENTRO DE COSTOS'!A:D,4,FALSE) -> WILLIAM ASDRUBAL ROZO ROZO | C34: =VLOOKUP(A34,'CENTRO DE COSTOS'!A:D,2,FALSE) -> 0004-0004 | D34: 25290 | E34: TA-25-561230 | F34: FO-25-874199 | G34: 45807 | H34: 45812 | I34: 45807 | J34: 45812 | K34: 45812 | L34: CUNDINAMARCA | M34: FUSAGASUGA | N34: BARRIO ACROPOLIS FUSAGUSUGA | O34: 79636 | P34: CB CRECIMIENTO - NUEVO | Q34: APERTURA | R34: REDEBAN | S34: UNO A UNO | T34: UNO A UNO | U34: EJECUTADO | V34: 30-05 SE REALIZA LLAMADA AL CLIENTE, SE HABLA CON EL SR HAROLD ALONSO RAMIREZ PERALTA, SE VALIDA DIRECCIÓN OK, CANAL OK, DISPONIBILIDAD TOTAL, LLAMAR EL DÍA LA INSTALACIÓN PARA CONFIRMAR VISITA, AVISO EXTERIOR ALTURA APROX DONDE EL TECNICO LO VEA CONVENIENTE METROS; TOMACORRIENTE CERCANO: SI; TIENE CABINA DE SEGURIDAD: SI 4/6/2025 SE REALIZA INSTALACIÓN DE CORRESPONSAL, SE INSTALAN EQUIPOS CON PRUEBAS EXITOSAS, SE CAPACITA Y SE EVALÚA AL CLIENTE, SE INSTALA PUBLICIDAD COMPLETA, CB QUEDA OPERATIVO. USUARIO SOMOS BANCOLOMBIA ACTIVO | W34: CORTES VELANDIA MIGUEL ANGEL | X34: SXUZZ162 | Y34: 991083 | Z34: N/A | AA34: 941150 | AB34: N/A | AC34: 40 ROLLOS | AD34: TIPO II | AE34: TERRESTRE | AF34: VISITA_TÉCNICA | AG34: 1 | AH34: 0 | AI34: =IF(AD34="TIPO I",'BASE LIQUIDACION REDEBAN 2025'!$B$2,IF(AD34="TIPO II",'BASE LIQUIDACION REDEBAN 2025'!$B$3,IF(AD34="TIPO III",'BASE LIQUIDACION REDEBAN 2025'!$B$4,IF(AD34="TIPO IV",'BASE LIQUIDACION REDEBAN 2025'!$B$5,IF(AE34="AEREO",'BASE LIQUIDACION REDEBAN 2025'!$B$6,'BASE LIQUIDACION REDEBAN 2025'!$B$5))))) -> 163813.7 | AJ34: =IF(AD34="TIPO I",'BASE LIQUIDACION REDEBAN 2025'!$B$10,IF(AD34="TIPO II",'BASE LIQUIDACION REDEBAN 2025'!$B$11,IF(AD34="TIPO III",'BASE LIQUIDACION REDEBAN 2025'!$B$12,'BASE LIQUIDACION REDEBAN 2025'!$B$13))) -> 140395.63 | AK34: =AG34*AI34+AH34*AJ34 -> 163813.7
A35: TUNJA | B35: =VLOOKUP(A35,'CENTRO DE COSTOS'!A:D,4,FALSE) -> MIGUEL JULIÁN HERNÁNDEZ GUARÍN | C35: =VLOOKUP(A35,'CENTRO DE COSTOS'!A:D,2,FALSE) -> 0004-0008 | D35: 68385 | E35: TA-25-561231 | F35: FO-25-854747 | G35: 45807 | H35: 45812 | I35: 45807 | J35: 45812 | K35: 45812 | L35: SANTANDER | M35: LANDAZURI | N35: BARRIO LA INDIA LANDAZURI | O35: 79641 | P35: CB CRECIMIENTO - NUEVO | Q35: APERTURA | R35: REDEBAN | S35: UNO A UNO | T35: UNO A UNO | U35: EJECUTADO | V35: 30-05 SE REALIZA LLAMADA AL CLIENTE, SE HABLA CON LA SRA ELIANA MARIA MENA LEAL SE VALIDA DIRECCIÓN OK, CANAL OK, DISPONIBILIDAD TOTAL, LLAMAR EL DÍA LA INSTALACIÓN PARA CONFIRMAR VISITA, AVISO EXTERIOR ALTURA APROX 3 METROS; TOMACORRIENTE CERCANO: SI; TIENE CABINA DE SEGURIDAD: NO 4/6/2025 SE REALIZA INSTALACIÓN DE CORRESPONSAL, SE INSTALAN EQUIPOS CON PRUEBAS EXITOSAS, SE CAPACITA Y SE EVALÚA AL CLIENTE, SE INSTALA PUBLICIDAD COMPLETA, CB QUEDA OPERATIVO. USUARIO SOMOS BANCOLOMBIA ACTIVO | W35: REYES RAMIREZ DIEGO ALEXANDER | X35: SXUZZ167 | Y35: 1036960 | Z35: N/A | AA35: 997338 | AB35: N/A | AC35: 40 ROLLOS | AD35: TIPO III | AE35: TERRESTRE | AF35: VISITA_TÉCNICA | AG35: 1 | AH35: 0 | AI35: =IF(AD35="TIPO I",'BASE LIQUIDACION REDEBAN 2025'!$B$2,IF(AD35="TIPO II",'BASE LIQUIDACION REDEBAN 2025'!$B$3,IF(AD35="TIPO III",'BASE LIQUIDACION REDEBAN 2025'!$B$4,IF(AD35="TIPO IV",'BASE LIQUIDACION REDEBAN 2025'!$B$5,IF(AE35="AEREO",'BASE LIQUIDACION REDEBAN 2025'!$B$6,'BASE LIQUIDACION REDEBAN 2025'!$B$5))))) -> 275728.78 | AJ35: =IF(AD35="TIPO I",'BASE LIQUIDACION REDEBAN 2025'!$B$10,IF(AD35="TIPO II",'BASE LIQUIDACION REDEBAN 2025'!$B$11,IF(AD35="TIPO III",'BASE LIQUIDACION REDEBAN 2025'!$B$12,'BASE LIQUIDACION REDEBAN 2025'!$B$13))) -> 196536.53 | AK35: =AG35*AI35+AH35*AJ35 -> 275728.78
A36: CUCUTA | B36: =VLOOKUP(A36,'CENTRO DE COSTOS'!A:D,4,FALSE) -> MIGUEL JULIÁN HERNÁNDEZ GUARÍN | C36: =VLOOKUP(A36,'CENTRO DE COSTOS'!A:D,2,FALSE) -> 0004-0008 | D36: 54518 | E36: TA-25-561232 | F36: FO-25-854750 | G36: 45807 | H36: 45812 | I36: 45807 | J36: 45812 | K36: 45812 | L36: NORTE DE SANTANDER | M36: PAMPLONA | N36: BARRIO GALAN PAMPLONA 2 | O36: 79646 | P36: CB CRECIMIENTO - NUEVO | Q36: APERTURA | R36: REDEBAN | S36: UNO A UNO | T36: UNO A UNO | U36: EJECUTADO | V36: 30-05 SE REALIZA LLAMADA AL CLIENTE, SE HABLA CON LA SRA YESSICA PAOLA ORDÓÑEZ VELAZCO, SE VALIDA DIRECCIÓN OK, CANAL OK, DISPONIBILIDAD TOTAL, LLAMAR EL DÍA LA INSTALACIÓN PARA CONFIRMAR VISITA, AVISO EXTERIOR ALTURA APROX DONDE EL TECNICO LO VEA CONVENIENTE METROS; TOMACORRIENTE CERCANO: SI; TIENE CABINA DE SEGURIDAD: NO 4/6/2025 SE REALIZA INSTALACIÓN DE CORRESPONSAL, SE INSTALAN EQUIPOS CON PRUEBAS EXITOSAS, SE CAPACITA Y SE EVALÚA AL CLIENTE, SE INSTALA PUBLICIDAD COMPLETA, CB QUEDA OPERATIVO. USUARIO SOMOS BANCOLOMBIA ACTIVO | W36: NARANJO AFANADOR RUBEN JESUS | X36: SXUZZ172 | Y36: 763376 | Z36: 1173852 | AA36: 1145445 | AB36: N/A | AC36: 40 ROLLOS | AD36: TIPO III | AE36: TERRESTRE | AF36: VISITA_TÉCNICA | AG36: 1 | AH36: 0 | AI36: =IF(AD36="TIPO I",'BASE LIQUIDACION REDEBAN 2025'!$B$2,IF(AD36="TIPO II",'BASE LIQUIDACION REDEBAN 2025'!$B$3,IF(AD36="TIPO III",'BASE LIQUIDACION REDEBAN 2025'!$B$4,IF(AD36="TIPO IV",'BASE LIQUIDACION REDEBAN 2025'!$B$5,IF(AE36="AEREO",'BASE LIQUIDACION REDEBAN 2025'!$B$6,'BASE LIQUIDACION REDEBAN 2025'!$B$5))))) -> 275728.78 | AJ36: =IF(AD36="TIPO I",'BASE LIQUIDACION REDEBAN 2025'!$B$10,IF(AD36="TIPO II",'BASE LIQUIDACION REDEBAN 2025'!$B$11,IF(AD36="TIPO III",'BASE LIQUIDACION REDEBAN 2025'!$B$12,'BASE LIQUIDACION REDEBAN 2025'!$B$13))) -> 196536.53 | AK36: =AG36*AI36+AH36*AJ36 -> 275728.78
A37: MEDELLIN | B37: =VLOOKUP(A37,'CENTRO DE COSTOS'!A:D,4,FALSE) -> JUAN SEBASTIÁN RÍOS CASTRILLÓN | C37: =VLOOKUP(A37,'CENTRO DE COSTOS'!A:D,2,FALSE) -> 0004-0005 | D37: 5036 | E37: TA-25-561233 | F37: FO-25-854754 | G37: 45807 | H37: 45812 | I37: 45807 | J37: 45812 | K37: 45812 | L37: ANTIOQUIA | M37: ANGELOPOLIS | N37: BRRIO ANGELOPOLIS ANTIOQUIA, CERCA LA ESTACION ANGELOPOLIS | O37: 79635 | P37: CB CRECIMIENTO - NUEVO | Q37: APERTURA | R37: REDEBAN | S37: UNO A UNO | T37: UNO A UNO | U37: EJECUTADO | V37: 30-05 SE REALIZA LLAMADA AL CLIENTE, SE HABLA CON LA SRA ANGELA TATIANA MONCADA PARRA, SE VALIDA DIRECCIÓN OK, CANAL OK, DISPONIBILIDAD TOTAL, LLAMAR EL DÍA LA INSTALACIÓN PARA CONFIRMAR VISITA, AVISO EXTERIOR ALTURA APROX 1,20 METROS; TOMACORRIENTE CERCANO: SI; TIENE CABINA DE SEGURIDAD: NO 4/6/2025 SE REALIZA INSTALACIÓN DE CORRESPONSAL, SE INSTALAN EQUIPOS CON PRUEBAS EXITOSAS, SE CAPACITA Y SE EVALÚA AL CLIENTE, SE INSTALA PUBLICIDAD COMPLETA, CB QUEDA OPERATIVO. USUARIO SOMOS BANCOLOMBIA ACTIVO | W37: CASTAÑEDA PALACIO CARLOS FELIPE | X37: SXUZZ161 | Y37: 960504 | Z37: N/A | AA37: 789543 | AB37: N/A | AC37: 40 ROLLOS | AD37: TIPO II | AE37: TERRESTRE | AF37: VISITA_TÉCNICA | AG37: 1 | AH37: 0 | AI37: =IF(AD37="TIPO I",'BASE LIQUIDACION REDEBAN 2025'!$B$2,IF(AD37="TIPO II",'BASE LIQUIDACION REDEBAN 2025'!$B$3,IF(AD37="TIPO III",'BASE LIQUIDACION REDEBAN 2025'!$B$4,IF(AD37="TIPO IV",'BASE LIQUIDACION REDEBAN 2025'!$B$5,IF(AE37="AEREO",'BASE LIQUIDACION REDEBAN 2025'!$B$6,'BASE LIQUIDACION REDEBAN 2025'!$B$5))))) -> 163813.7 | AJ37: =IF(AD37="TIPO I",'BASE LIQUIDACION REDEBAN 2025'!$B$10,IF(AD37="TIPO II",'BASE LIQUIDACION REDEBAN 2025'!$B$11,IF(AD37="TIPO III",'BASE LIQUIDACION REDEBAN 2025'!$B$12,'BASE LIQUIDACION REDEBAN 2025'!$B$13))) -> 140395.63 | AK37: =AG37*AI37+AH37*AJ37 -> 163813.7
A38: CALI | B38: =VLOOKUP(A38,'CENTRO DE COSTOS'!A:D,4,FALSE) -> DIEGO FERNANDO HENAO CARDONA | C38: =VLOOKUP(A38,'CENTRO DE COSTOS'!A:D,2,FALSE) -> 0004-0003 | D38: 76001 | E38: TA-25-561234 | F38: FO-25-854758 | G38: 45807 | H38: 45812 | I38: 45807 | J38: 45811 | K38: 45811 | L38: VALLE DEL CAUCA | M38: CALI | N38: BARRIO AGUA BLANCA CALI | O38: 79617 | P38: CB CRECIMIENTO - NUEVO | Q38: APERTURA | R38: REDEBAN | S38: UNO A UNO | T38: UNO A UNO | U38: EJECUTADO | V38: 30-05 SE REALIZA LLAMADA AL CLIENTE, SE HABLA CON LA SRA LIZETH MARIANA GALINDO ORTIZ, SE VALIDA DIRECCIÓN OK, CANAL OK, DISPONIBILIDAD TOTAL, LLAMAR EL DÍA LA INSTALACIÓN PARA CONFIRMAR VISITA, AVISO EXTERIOR ALTURA APROX DONDE EL TECNICO LO VEA CONVENIENTE METROS; TOMACORRIENTE CERCANO: SI; TIENE CABINA DE SEGURIDAD: NO 03-06 SE REALIZA INSTALACIÓN DE CORRESPONSAL, SE INSTALAN EQUIPOS CON PRUEBAS EXITOSAS, SE CAPACITA Y SE EVALÚA AL CLIENTE, SE INSTALA PUBLICIDAD COMPLETA, CB QUEDA OPERATIVO. USUARIO SOMOS BANCOLOMBIA ACTIVO | W38: MONTERO MUESES GIAN CARLO | X38: SXUZZ143 | Y38: 1171539 | Z38: N/A | AA38: 549981 | AB38: N/A | AC38: 40 ROLLOS | AD38: TIPO I | AE38: TERRESTRE | AF38: VISITA_TÉCNICA | AG38: 1 | AH38: 0 | AI38: =IF(AD38="TIPO I",'BASE LIQUIDACION REDEBAN 2025'!$B$2,IF(AD38="TIPO II",'BASE LIQUIDACION REDEBAN 2025'!$B$3,IF(AD38="TIPO III",'BASE LIQUIDACION REDEBAN 2025'!$B$4,IF(AD38="TIPO IV",'BASE LIQUIDACION REDEBAN 2025'!$B$5,IF(AE38="AEREO",'BASE LIQUIDACION REDEBAN 2025'!$B$6,'BASE LIQUIDACION REDEBAN 2025'!$B$5))))) -> 75096.394 | AJ38: =IF(AD38="TIPO I",'BASE LIQUIDACION REDEBAN 2025'!$B$10,IF(AD38="TIPO II",'BASE LIQUIDACION REDEBAN 2025'!$B$11,IF(AD38="TIPO III",'BASE LIQUIDACION REDEBAN 2025'!$B$12,'BASE LIQUIDACION REDEBAN 2025'!$B$13))) -> 75096.394 | AK38: =AG38*AI38+AH38*AJ38 -> 75096.394
A39: MEDELLIN | B39: =VLOOKUP(A39,'CENTRO DE COSTOS'!A:D,4,FALSE) -> JUAN SEBASTIÁN RÍOS CASTRILLÓN | C39: =VLOOKUP(A39,'CENTRO DE COSTOS'!A:D,2,FALSE) -> 0004-0005 | D39: 5001 | E39: TA-25-561248 | F39: FO-25-854843 | G39: 45807 | H39: 45812 | I39: 45807 | J39: 45811 | K39: 45811 | L39: ANTIOQUIA | M39: MEDELLIN | N39: BARRIO LAURELES MEDELLIN 20 | O39: 79673 | P39: CB CRECIMIENTO - NUEVO | Q39: APERTURA | R39: REDEBAN | S39: UNO A UNO | T39: UNO A UNO | U39: EJECUTADO | V39: 30-05 SE REALIZA LLAMADA AL CLIENTE, SE HABLA CON LA SR ANDRES FELIPE GALVIS ESPINOSA SE VALIDA DIRECCIÓN OK, CANAL OK, DISPONIBILIDAD TOTAL, LLAMAR EL DÍA LA INSTALACIÓN PARA CONFIRMAR VISITA, AVISO EXTERIOR ALTURA APROX 2.50 METROS; TOMACORRIENTE CERCANO: SI; TIENE CABINA DE SEGURIDAD: NO 3/6/2025 SE REALIZA INSTALACIÓN DE CORRESPONSAL, SE INSTALAN EQUIPOS CON PRUEBAS EXITOSAS, SE CAPACITA Y SE EVALÚA AL CLIENTE, SE INSTALA PUBLICIDAD COMPLETA, CB QUEDA OPERATIVO. USUARIO SOMOS BANCOLOMBIA ACTIVO | W39: BADEL ACUÑA LUIS ALBERTO | X39: SXUZZ199 | Y39: 1051975 | Z39: N/A | AA39: 1239605 | AB39: N/A | AC39: 40 ROLLOS | AD39: TIPO I | AE39: TERRESTRE | AF39: VISITA_TÉCNICA | AG39: 1 | AH39: 0 | AI39: =IF(AD39="TIPO I",'BASE LIQUIDACION REDEBAN 2025'!$B$2,IF(AD39="TIPO II",'BASE LIQUIDACION REDEBAN 2025'!$B$3,IF(AD39="TIPO III",'BASE LIQUIDACION REDEBAN 2025'!$B$4,IF(AD39="TIPO IV",'BASE LIQUIDACION REDEBAN 2025'!$B$5,IF(AE39="AEREO",'BASE LIQUIDACION REDEBAN 2025'!$B$6,'BASE LIQUIDACION REDEBAN 2025'!$B$5))))) -> 75096.394 | AJ39: =IF(AD39="TIPO I",'BASE LIQUIDACION REDEBAN 2025'!$B$10,IF(AD39="TIPO II",'BASE LIQUIDACION REDEBAN 2025'!$B$11,IF(AD39="TIPO III",'BASE LIQUIDACION REDEBAN 2025'!$B$12,'BASE LIQUIDACION REDEBAN 2025'!$B$13))) -> 75096.394 | AK39: =AG39*AI39+AH39*AJ39 -> 75096.394
A40: BOGOTA | B40: =VLOOKUP(A40,'CENTRO DE COSTOS'!A:D,4,FALSE) -> WILLIAM ASDRUBAL ROZO ROZO | C40: =VLOOKUP(A40,'CENTRO DE COSTOS'!A:D,2,FALSE) -> 0004-0004 | D40: 11001 | E40: TA-25-561250 | F40: FO-25-854848 | G40: 45807 | H40: 45812 | I40: 45807 | J40: 45811 | K40: 45811 | L40: CUNDINAMARCA | M40: BOGOTA | N40: BARRIO PUENTE ARANDA BOGOTA 8 | O40: 79604 | P40: CB CRECIMIENTO - NUEVO | Q40: APERTURA | R40: REDEBAN | S40: UNO A UNO | T40: UNO A UNO | U40: EJECUTADO | V40: 30-05 SE REALIZA LLAMADA AL CLIENTE, SE HABLA CON LA SRA SONIA MARCELA GARCIA PINEDA SE VALIDA DIRECCIÓN OK, CANAL OK, DISPONIBILIDAD TOTAL, LLAMAR EL DÍA LA INSTALACIÓN PARA CONFIRMAR VISITA, AVISO EXTERIOR ALTURA APROX 3 METROS; TOMACORRIENTE CERCANO: SI; TIENE CABINA DE SEGURIDAD: SI 3/6/2025 SE REALIZA INSTALACIÓN DE CORRESPONSAL, SE INSTALAN EQUIPOS CON PRUEBAS EXITOSAS, SE CAPACITA Y SE EVALÚA AL CLIENTE, SE INSTALA PUBLICIDAD COMPLETA, CB QUEDA OPERATIVO. USUARIO SOMOS BANCOLOMBIA ACTIVO | W40: GALINDO ROJAS LUIS FELIPE | X40: SXUZZ130 | Y40: 761448 | Z40: N/A | AA40: 1103440 | AB40: N/A | AC40: 40 ROLLOS | AD40: TIPO I | AE40: TERRESTRE | AF40: VISITA_TÉCNICA | AG40: 1 | AH40: 0 | AI40: =IF(AD40="TIPO I",'BASE LIQUIDACION REDEBAN 2025'!$B$2,IF(AD40="TIPO II",'BASE LIQUIDACION REDEBAN 2025'!$B$3,IF(AD40="TIPO III",'BASE LIQUIDACION REDEBAN 2025'!$B$4,IF(AD40="TIPO IV",'BASE LIQUIDACION REDEBAN 2025'!$B$5,IF(AE40="AEREO",'BASE LIQUIDACION REDEBAN 2025'!$B$6,'BASE LIQUIDACION REDEBAN 2025'!$B$5))))) -> 75096.394 | AJ40: =IF(AD40="TIPO I",'BASE LIQUIDACION REDEBAN 2025'!$B$10,IF(AD40="TIPO II",'BASE LIQUIDACION REDEBAN 2025'!$B$11,IF(AD40="TIPO III",'BASE LIQUIDACION REDEBAN 2025'!$B$12,'BASE LIQUIDACION REDEBAN 2025'!$B$13))) -> 75096.394 | AK40: =AG40*AI40+AH40*AJ40 -> 75096.394
A41: MEDELLIN | B41: =VLOOKUP(A41,'CENTRO DE COSTOS'!A:D,4,FALSE) -> JUAN SEBASTIÁN RÍOS CASTRILLÓN | C41: =VLOOKUP(A41,'CENTRO DE COSTOS'!A:D,2,FALSE) -> 0004-0005 | D41: 5079 | E41: TA-25-561252 | F41: FO-25-854857 | G41: 45807 | H41: 45812 | I41: 45807 | J41: 45817 | K41: 45817 | L41: ANTIOQUIA | M41: BARBOSA | N41: BARRIO BARBOSA AUTOPISTA BARBOSA | O41: 79623 | P41: CB CRECIMIENTO - NUEVO | Q41: APERTURA | R41: REDEBAN | S41: UNO A UNO | T41: UNO A UNO | U41: EJECUTADO | V41: 30-05 SE REALIZA LLAMADA AL CLIENTE, SE HABLA CON LA SRA LIZETH MARIANA GALINDO ORTIZ, SE VALIDA DIRECCIÓN OK, CANAL OK, DISPONIBILIDAD TOTAL, LLAMAR EL DÍA LA INSTALACIÓN PARA CONFIRMAR VISITA, AVISO EXTERIOR ALTURA APROX DONDE EL TECNICO LO VEA CONVENIENTE METROS; TOMACORRIENTE CERCANO: SI; TIENE CABINA DE SEGURIDAD: NO 4/6/2025 LLEGAMOS A SITIO ENCONTRANDO OTRO PUNTO CERCANO A 30 METROS CODIGO 49691 PTM BARBOSA DROGUERÍA SE ESCALA CASO POR CERCANÍA DE 2 PUNTOS UNO DE AGREGADOR Y OTRO UNO A UNO. 05-06 ENTIDAD APRUEBA INSTALACIÓN 9/6/2025 SE REALIZA INSTALACIÓN DE CORRESPONSAL, SE INSTALAN EQUIPOS CON PRUEBAS EXITOSAS, SE CAPACITA Y SE EVALÚA AL CLIENTE, SE INSTALA PUBLICIDAD COMPLETA, CB QUEDA OPERATIVO. PLATAFORMA SOMOS BANCOLOMBIA CON CORREO ERRÓNEO, SE CAPACITA CON USUARIO DE PRUEBA | W41: BADEL ACUÑA LUIS ALBERTO | X41: SXUZZ149 | Y41: 1173964 | Z41: N/A | AA41: 529350 | AB41: N/A | AC41: 40 ROLLOS | AD41: TIPO II | AE41: TERRESTRE | AF41: VISITA_TÉCNICA | AG41: 1 | AH41: 0 | AI41: =IF(AD41="TIPO I",'BASE LIQUIDACION REDEBAN 2025'!$B$2,IF(AD41="TIPO II",'BASE LIQUIDACION REDEBAN 2025'!$B$3,IF(AD41="TIPO III",'BASE LIQUIDACION REDEBAN 2025'!$B$4,IF(AD41="TIPO IV",'BASE LIQUIDACION REDEBAN 2025'!$B$5,IF(AE41="AEREO",'BASE LIQUIDACION REDEBAN 2025'!$B$6,'BASE LIQUIDACION REDEBAN 2025'!$B$5))))) -> 163813.7 | AJ41: =IF(AD41="TIPO I",'BASE LIQUIDACION REDEBAN 2025'!$B$10,IF(AD41="TIPO II",'BASE LIQUIDACION REDEBAN 2025'!$B$11,IF(AD41="TIPO III",'BASE LIQUIDACION REDEBAN 2025'!$B$12,'BASE LIQUIDACION REDEBAN 2025'!$B$13))) -> 140395.63 | AK41: =AG41*AI41+AH41*AJ41 -> 163813.7
A42: CALI | B42: =VLOOKUP(A42,'CENTRO DE COSTOS'!A:D,4,FALSE) -> DIEGO FERNANDO HENAO CARDONA | C42: =VLOOKUP(A42,'CENTRO DE COSTOS'!A:D,2,FALSE) -> 0004-0003 | D42: 76036 | E42: TA-25-561253 | F42: FO-25-854861 | G42: 45807 | H42: 45812 | I42: 45807 | J42: 45812 | K42: 45812 | L42: VALLE DEL CAUCA | M42: ANDALUCIA | N42: BARRIO CENTRO ANDALUCIA 7 | O42: 79594 | P42: CB CRECIMIENTO - NUEVO | Q42: APERTURA | R42: REDEBAN | S42: UNO A UNO | T42: UNO A UNO | U42: EJECUTADO | V42: 30-05 SE REALIZA LLAMADA AL CLIENTE, SE HABLA CON LA SRA MARIA ELCY ROMAN MILLAN, SE VALIDA DIRECCIÓN OK, CANAL OK, DISPONIBILIDAD TOTAL, LLAMAR EL DÍA LA INSTALACIÓN PARA CONFIRMAR VISITA, AVISO EXTERIOR ALTURA APROX DONDE EL TECNICO LO VEA CONVENIENTE METROS; TOMACORRIENTE CERCANO: SI; TIENE CABINA DE SEGURIDAD: SI 4/6/2025 SE REALIZA INSTALACIÓN DE CORRESPONSAL, SE INSTALAN EQUIPOS CON PRUEBAS EXITOSAS, SE CAPACITA Y SE EVALÚA AL CLIENTE, SE INSTALA PUBLICIDAD COMPLETA, CB QUEDA OPERATIVO. USUARIO SOMOS BANCOLOMBIA ACTIVO | W42: MONTERO MUESES GIAN CARLO | X42: SXUZZ120 | Y42: 1030999 | Z42: N/A | AA42: 749614 | AB42: N/A | AC42: 40 ROLLOS | AD42: TIPO II | AE42: TERRESTRE | AF42: VISITA_TÉCNICA | AG42: 1 | AH42: 0 | AI42: =IF(AD42="TIPO I",'BASE LIQUIDACION REDEBAN 2025'!$B$2,IF(AD42="TIPO II",'BASE LIQUIDACION REDEBAN 2025'!$B$3,IF(AD42="TIPO III",'BASE LIQUIDACION REDEBAN 2025'!$B$4,IF(AD42="TIPO IV",'BASE LIQUIDACION REDEBAN 2025'!$B$5,IF(AE42="AEREO",'BASE LIQUIDACION REDEBAN 2025'!$B$6,'BASE LIQUIDACION REDEBAN 2025'!$B$5))))) -> 163813.7 | AJ42: =IF(AD42="TIPO I",'BASE LIQUIDACION REDEBAN 2025'!$B$10,IF(AD42="TIPO II",'BASE LIQUIDACION REDEBAN 2025'!$B$11,IF(AD42="TIPO III",'BASE LIQUIDACION REDEBAN 2025'!$B$12,'BASE LIQUIDACION REDEBAN 2025'!$B$13))) -> 140395.63 | AK42: =AG42*AI42+AH42*AJ42 -> 163813.7
A43: PEREIRA | B43: =VLOOKUP(A43,'CENTRO DE COSTOS'!A:D,4,FALSE) -> DIEGO FERNANDO HENAO CARDONA | C43: =VLOOKUP(A43,'CENTRO DE COSTOS'!A:D,2,FALSE) -> 0004-0002 | D43: 66001 | E43: TA-25-561255 | F43: FO-25-854870 | G43: 45807 | H43: 45812 | I43: 45807 | J43: 45811 | K43: 45811 | L43: RISARALDA | M43: PEREIRA | N43: BARRIO CUBA PEREIRA 12 | O43: 79648 | P43: CB CRECIMIENTO - NUEVO | Q43: APERTURA | R43: REDEBAN | S43: UNO A UNO | T43: UNO A UNO | U43: EJECUTADO | V43: 30-05 SE REALIZA LLAMADA AL CLIENTE, SE HABLA CON LA SRA LUZ ELENA QUINTERO RAMIREZ, SE VALIDA DIRECCIÓN OK, CANAL OK, DISPONIBILIDAD TOTAL, LLAMAR EL DÍA LA INSTALACIÓN PARA CONFIRMAR VISITA, AVISO EXTERIOR ALTURA APROX DONDE EL TECNICO LO VEA CONVENIENTE METROS; TOMACORRIENTE CERCANO: SI; TIENE CABINA DE SEGURIDAD: NO 3/6/2025 SE REALIZA INSTALACIÓN DE CORRESPONSAL, SE INSTALAN EQUIPOS CON PRUEBAS EXITOSAS, SE CAPACITA Y SE EVALÚA AL CLIENTE, SE INSTALA PUBLICIDAD COMPLETA, CB QUEDA OPERATIVO. USUARIO SOMOS BANCOLOMBIA ACTIVO | W43: ARROYAVE CANO MANUEL GUILLERMO | X43: SXUZZ174 | Y43: 975259 | Z43: N/A | AA43: 1217510 | AB43: N/A | AC43: 40 ROLLOS | AD43: TIPO I | AE43: TERRESTRE | AF43: VISITA_TÉCNICA | AG43: 1 | AH43: 0 | AI43: =IF(AD43="TIPO I",'BASE LIQUIDACION REDEBAN 2025'!$B$2,IF(AD43="TIPO II",'BASE LIQUIDACION REDEBAN 2025'!$B$3,IF(AD43="TIPO III",'BASE LIQUIDACION REDEBAN 2025'!$B$4,IF(AD43="TIPO IV",'BASE LIQUIDACION REDEBAN 2025'!$B$5,IF(AE43="AEREO",'BASE LIQUIDACION REDEBAN 2025'!$B$6,'BASE LIQUIDACION REDEBAN 2025'!$B$5))))) -> 75096.394 | AJ43: =IF(AD43="TIPO I",'BASE LIQUIDACION REDEBAN 2025'!$B$10,IF(AD43="TIPO II",'BASE LIQUIDACION REDEBAN 2025'!$B$11,IF(AD43="TIPO III",'BASE LIQUIDACION REDEBAN 2025'!$B$12,'BASE LIQUIDACION REDEBAN 2025'!$B$13))) -> 75096.394 | AK43: =AG43*AI43+AH43*AJ43 -> 75096.394
A44: BOGOTA | B44: =VLOOKUP(A44,'CENTRO DE COSTOS'!A:D,4,FALSE) -> WILLIAM ASDRUBAL ROZO ROZO | C44: =VLOOKUP(A44,'CENTRO DE COSTOS'!A:D,2,FALSE) -> 0004-0004 | D44: 25754 | E44: TA-25-561598 | F44: FO-25-856006 | G44: 45807 | H44: 45812 | I44: 45807 | J44: 45812 | K44: 45812 | L44: CUNDINAMARCA | M44: SOACHA | N44: BARRIO SAN MATEO SOACHA SOACHA 2 | O44: 79653 | P44: CB CRECIMIENTO - NUEVO | Q44: APERTURA | R44: REDEBAN | S44: UNO A UNO | T44: UNO A UNO | U44: EJECUTADO | V44: 30-05 SE REALIZA LLAMADA AL CLIENTE, SE HABLA CON LA SRA MARIA ALEJANDRA CAMARGO TRIANA, SE VALIDA DIRECCIÓN OK, CANAL OK, DISPONIBILIDAD TOTAL, LLAMAR EL DÍA LA INSTALACIÓN PARA CONFIRMAR VISITA, AVISO EXTERIOR ALTURA APROX 2,10 METROS; TOMACORRIENTE CERCANO: SI; TIENE CABINA DE SEGURIDAD: NO 04-06 SE REALIZA INSTALACIÓN DE CORRESPONSAL, SE INSTALAN EQUIPOS CON PRUEBAS EXITOSAS, SE CAPACITA Y SE EVALÚA AL CLIENTE, SE INSTALA PUBLICIDAD COMPLETA, CB QUEDA OPERATIVO. USUARIO SOMOS BANCOLOMBIA ACTIVO | W44: SOTO LONDOÑO FREDY ALEXANDER | X44: SXUZZ179 | Y44: 1169818 | Z44: N/A | AA44: 1060154 | AB44: N/A | AC44: 40 ROLLOS | AD44: TIPO I | AE44: TERRESTRE | AF44: VISITA_TÉCNICA | AG44: 1 | AH44: 0 | AI44: =IF(AD44="TIPO I",'BASE LIQUIDACION REDEBAN 2025'!$B$2,IF(AD44="TIPO II",'BASE LIQUIDACION REDEBAN 2025'!$B$3,IF(AD44="TIPO III",'BASE LIQUIDACION REDEBAN 2025'!$B$4,IF(AD44="TIPO IV",'BASE LIQUIDACION REDEBAN 2025'!$B$5,IF(AE44="AEREO",'BASE LIQUIDACION REDEBAN 2025'!$B$6,'BASE LIQUIDACION REDEBAN 2025'!$B$5))))) -> 75096.394 | AJ44: =IF(AD44="TIPO I",'BASE LIQUIDACION REDEBAN 2025'!$B$10,IF(AD44="TIPO II",'BASE LIQUIDACION REDEBAN 2025'!$B$11,IF(AD44="TIPO III",'BASE LIQUIDACION REDEBAN 2025'!$B$12,'BASE LIQUIDACION REDEBAN 2025'!$B$13))) -> 75096.394 | AK44: =AG44*AI44+AH44*AJ44 -> 75096.394
A45: MEDELLIN | B45: =VLOOKUP(A45,'CENTRO DE COSTOS'!A:D,4,FALSE) -> JUAN SEBASTIÁN RÍOS CASTRILLÓN | C45: =VLOOKUP(A45,'CENTRO DE COSTOS'!A:D,2,FALSE) -> 0004-0005 | D45: 5360 | E45: TA-25-561599 | F45: FO-25-856009 | G45: 45807 | H45: 45812 | I45: 45807 | J45: 45811 | K45: 45811 | L45: ANTIOQUIA | M45: ITAGUI | N45: BARRIO ITAGUI ITAGUI 33 | O45: 79628 | P45: CB CRECIMIENTO - NUEVO | Q45: APERTURA | R45: REDEBAN | S45: UNO A UNO | T45: UNO A UNO | U45: EJECUTADO | V45: 30-05 SE REALIZA LLAMADA AL CLIENTE, SE HABLA CON EL SR YOSMEN ENRIQUE BETANCUR LONDOÑO, SE VALIDA DIRECCIÓN OK, CANAL OK, DISPONIBILIDAD TOTAL, LLAMAR EL DÍA LA INSTALACIÓN PARA CONFIRMAR VISITA, AVISO EXTERIOR ALTURA APROX 2 METROS; TOMACORRIENTE CERCANO: SI; TIENE CABINA DE SEGURIDAD: SI 3/6/2025 SE REALIZA INSTALACIÓN DE CORRESPONSAL, SE INSTALAN EQUIPOS CON PRUEBAS EXITOSAS, SE CAPACITA Y SE EVALÚA AL CLIENTE, SE INSTALA PUBLICIDAD COMPLETA, CB QUEDA OPERATIVO. USUARIO SOMOS BANCOLOMBIA ACTIVO | W45: DIAZ ZABALA FRANCIS DUBAN | X45: SXUZZ154 | Y45: 857573 | Z45: N/A | AA45: 522270 | AB45: N/A | AC45: 40 ROLLOS | AD45: TIPO I | AE45: TERRESTRE | AF45: VISITA_TÉCNICA | AG45: 1 | AH45: 0 | AI45: =IF(AD45="TIPO I",'BASE LIQUIDACION REDEBAN 2025'!$B$2,IF(AD45="TIPO II",'BASE LIQUIDACION REDEBAN 2025'!$B$3,IF(AD45="TIPO III",'BASE LIQUIDACION REDEBAN 2025'!$B$4,IF(AD45="TIPO IV",'BASE LIQUIDACION REDEBAN 2025'!$B$5,IF(AE45="AEREO",'BASE LIQUIDACION REDEBAN 2025'!$B$6,'BASE LIQUIDACION REDEBAN 2025'!$B$5))))) -> 75096.394 | AJ45: =IF(AD45="TIPO I",'BASE LIQUIDACION REDEBAN 2025'!$B$10,IF(AD45="TIPO II",'BASE LIQUIDACION REDEBAN 2025'!$B$11,IF(AD45="TIPO III",'BASE LIQUIDACION REDEBAN 2025'!$B$12,'BASE LIQUIDACION REDEBAN 2025'!$B$13))) -> 75096.394 | AK45: =AG45*AI45+AH45*AJ45 -> 75096.394
A46: APARTADO | B46: =VLOOKUP(A46,'CENTRO DE COSTOS'!A:D,4,FALSE) -> JUAN SEBASTIÁN RÍOS CASTRILLÓN | C46: =VLOOKUP(A46,'CENTRO DE COSTOS'!A:D,2,FALSE) -> 0004-0005 | D46: 5172 | E46: TA-25-577586 | F46: FO-25-875351 | G46: 45807 | H46: 45812 | I46: 45807 | J46: 45812 | K46: 45812 | L46: ANTIOQUIA | M46: CHIGORODO | N46: BARRIO BRISAS DEL RIO CHIGORODO 1 | O46: 79625 | P46: CB CRECIMIENTO - NUEVO | Q46: APERTURA | R46: REDEBAN | S46: UNO A UNO | T46: UNO A UNO | U46: EJECUTADO | V46: 30-05 SE REALIZA LLAMADA AL CLIENTE, SE HABLA CON EL SR UBEIMAR LUVAN MONSALVE MARIN, SE VALIDA DIRECCIÓN OK, CANAL OK, DISPONIBILIDAD TOTAL, LLAMAR EL DÍA LA INSTALACIÓN PARA CONFIRMAR VISITA, AVISO EXTERIOR ALTURA APROX DONDE EL TECNICO LO VEA CONVENIENTE METROS; TOMACORRIENTE CERCANO: SI; TIENE CABINA DE SEGURIDAD: SI 04-06 SE REALIZA INSTALACIÓN DE CORRESPONSAL, SE INSTALAN EQUIPOS CON PRUEBAS EXITOSAS, SE CAPACITA Y SE EVALÚA AL CLIENTE, SE INSTALA PUBLICIDAD COMPLETA, CB QUEDA OPERATIVO. USUARIO SOMOS BANCOLOMBIA ACTIVO | W46: MARTINEZ TOVAR OSCAR DAVID | X46: SXUZZ151 | Y46: 1232239 | Z46: N/A | AA46: 915724 | AB46: N/A | AC46: 40 ROLLOS | AD46: TIPO II | AE46: TERRESTRE | AF46: VISITA_TÉCNICA | AG46: 1 | AH46: 0 | AI46: =IF(AD46="TIPO I",'BASE LIQUIDACION REDEBAN 2025'!$B$2,IF(AD46="TIPO II",'BASE LIQUIDACION REDEBAN 2025'!$B$3,IF(AD46="TIPO III",'BASE LIQUIDACION REDEBAN 2025'!$B$4,IF(AD46="TIPO IV",'BASE LIQUIDACION REDEBAN 2025'!$B$5,IF(AE46="AEREO",'BASE LIQUIDACION REDEBAN 2025'!$B$6,'BASE LIQUIDACION REDEBAN 2025'!$B$5))))) -> 163813.7 | AJ46: =IF(AD46="TIPO I",'BASE LIQUIDACION REDEBAN 2025'!$B$10,IF(AD46="TIPO II",'BASE LIQUIDACION REDEBAN 2025'!$B$11,IF(AD46="TIPO III",'BASE LIQUIDACION REDEBAN 2025'!$B$12,'BASE LIQUIDACION REDEBAN 2025'!$B$13))) -> 140395.63 | AK46: =AG46*AI46+AH46*AJ46 -> 163813.7
A47: MEDELLIN | B47: =VLOOKUP(A47,'CENTRO DE COSTOS'!A:D,4,FALSE) -> JUAN SEBASTIÁN RÍOS CASTRILLÓN | C47: =VLOOKUP(A47,'CENTRO DE COSTOS'!A:D,2,FALSE) -> 0004-0005 | D47: 5001 | E47: TA-25-577591 | F47: FO-25-875355 | G47: 45807 | H47: 45812 | I47: 45807 | J47: 45813 | K47: 45813 | L47: ANTIOQUIA | M47: MEDELLIN | N47: BARRIO CENTRO MEDELLIN 106 | O47: 79671 | P47: CB CRECIMIENTO - NUEVO | Q47: APERTURA | R47: REDEBAN | S47: UNO A UNO | T47: UNO A UNO | U47: EJECUTADO | V47: 30-05 SE REALIZA LLAMADA AL CLIENTE, SE HABLA CON LA SR LEON ADRIAN ARROYAVE MONSALVE SE VALIDA DIRECCIÓN OK, CANAL OK, DISPONIBILIDAD TOTAL, LLAMAR EL DÍA LA INSTALACIÓN PARA CONFIRMAR VISITA, AVISO EXTERIOR ALTURA APROX 2 METROS; TOMACORRIENTE CERCANO: SI; TIENE CABINA DE SEGURIDAD: NO - COMUNICACIÓN POR WPP 3/6/2025 SE COMUNICA CON EL SR LEÓN ADRIAN PARA LA INSTALACIÓN BARRIO CENTRO MEDELLIN 106 E INFORMA QUE HOY NO PUEDE ATENDER NO TIENE DISPONIBILIDAD Y LA PERSONA ENCARGADA TAMPOCO ESTA DISPONIBLE HOY QUE SE LA PROGRAMEN PARA OTRO DÍA 5/6/2025 SE REALIZA INSTALACIÓN DE CORRESPONSAL, SE INSTALAN EQUIPOS CON PRUEBAS EXITOSAS, SE CAPACITA Y SE EVALÚA AL CLIENTE, SE INSTALA PUBLICIDAD COMPLETA, CB QUEDA OPERATIVO. USUARIO SOMOS BANCOLOMBIA ACTIVO | W47: QUINTERO SANCHEZ JUAN SEBASTIAN | X47: SXUZZ197 | Y47: 1121097 | Z47: N/A | AA47: 522538 | AB47: N/A | AC47: 40 ROLLOS | AD47: TIPO I | AE47: TERRESTRE | AF47: VISITA_TÉCNICA | AG47: 1 | AH47: 0 | AI47: =IF(AD47="TIPO I",'BASE LIQUIDACION REDEBAN 2025'!$B$2,IF(AD47="TIPO II",'BASE LIQUIDACION REDEBAN 2025'!$B$3,IF(AD47="TIPO III",'BASE LIQUIDACION REDEBAN 2025'!$B$4,IF(AD47="TIPO IV",'BASE LIQUIDACION REDEBAN 2025'!$B$5,IF(AE47="AEREO",'BASE LIQUIDACION REDEBAN 2025'!$B$6,'BASE LIQUIDACION REDEBAN 2025'!$B$5))))) -> 75096.394 | AJ47: =IF(AD47="TIPO I",'BASE LIQUIDACION REDEBAN 2025'!$B$10,IF(AD47="TIPO II",'BASE LIQUIDACION REDEBAN 2025'!$B$11,IF(AD47="TIPO III",'BASE LIQUIDACION REDEBAN 2025'!$B$12,'BASE LIQUIDACION REDEBAN 2025'!$B$13))) -> 75096.394 | AK47: =AG47*AI47+AH47*AJ47 -> 75096.394
A48: BOGOTA | B48: =VLOOKUP(A48,'CENTRO DE COSTOS'!A:D,4,FALSE) -> WILLIAM ASDRUBAL ROZO ROZO | C48: =VLOOKUP(A48,'CENTRO DE COSTOS'!A:D,2,FALSE) -> 0004-0004 | D48: 25754 | E48: TA-25-577597 | F48: FO-25-875358 | G48: 45807 | H48: 45812 | I48: 45807 | J48: 45812 | K48: 45812 | L48: CUNDINAMARCA | M48: SOACHA | N48: BARRIO PRADO VEGAS SOACHA 2 | O48: 79654 | P48: CB CRECIMIENTO - NUEVO | Q48: APERTURA | R48: REDEBAN | S48: UNO A UNO | T48: UNO A UNO | U48: EJECUTADO | V48: 30-05 SE REALIZA LLAMADA AL CLIENTE, SE HABLA CON EL SR JOHAN SEBASTIAN BERNAL RODRIGUEZ, SE VALIDA DIRECCIÓN OK, CANAL OK, DISPONIBILIDAD TOTAL, LLAMAR EL DÍA LA INSTALACIÓN PARA CONFIRMAR VISITA, AVISO EXTERIOR ALTURA APROX DONDE EL TECNICO LO VEA CONVENIENTE METROS; TOMACORRIENTE CERCANO: SI; TIENE CABINA DE SEGURIDAD:NO 4/6/2025 SE REALIZA INSTALACIÓN DE CORRESPONSAL, SE INSTALAN EQUIPOS CON PRUEBAS EXITOSAS, SE CAPACITA Y SE EVALÚA AL CLIENTE, SE INSTALA PUBLICIDAD COMPLETA, CB QUEDA OPERATIVO. USUARIO SOMOS BANCOLOMBIA ACTIVO. NOTA: NO SE CUENTA CON TARJETA DE BANCOLOMBIA PARA REALIZAR PRUEBAS DE RETIRO | W48: SOTO LONDOÑO FREDY ALEXANDER | X48: SXUZZ180 | Y48: 732691 | Z48: N/A | AA48: 864627 | AB48: N/A | AC48: 40 ROLLOS | AD48: TIPO I | AE48: TERRESTRE | AF48: VISITA_TÉCNICA | AG48: 1 | AH48: 0 | AI48: =IF(AD48="TIPO I",'BASE LIQUIDACION REDEBAN 2025'!$B$2,IF(AD48="TIPO II",'BASE LIQUIDACION REDEBAN 2025'!$B$3,IF(AD48="TIPO III",'BASE LIQUIDACION REDEBAN 2025'!$B$4,IF(AD48="TIPO IV",'BASE LIQUIDACION REDEBAN 2025'!$B$5,IF(AE48="AEREO",'BASE LIQUIDACION REDEBAN 2025'!$B$6,'BASE LIQUIDACION REDEBAN 2025'!$B$5))))) -> 75096.394 | AJ48: =IF(AD48="TIPO I",'BASE LIQUIDACION REDEBAN 2025'!$B$10,IF(AD48="TIPO II",'BASE LIQUIDACION REDEBAN 2025'!$B$11,IF(AD48="TIPO III",'BASE LIQUIDACION REDEBAN 2025'!$B$12,'BASE LIQUIDACION REDEBAN 2025'!$B$13))) -> 75096.394 | AK48: =AG48*AI48+AH48*AJ48 -> 75096.394
A49: MEDELLIN | B49: =VLOOKUP(A49,'CENTRO DE COSTOS'!A:D,4,FALSE) -> JUAN SEBASTIÁN RÍOS CASTRILLÓN | C49: =VLOOKUP(A49,'CENTRO DE COSTOS'!A:D,2,FALSE) -> 0004-0005 | D49: 27361 | E49: TA-25-577602 | F49: FO-25-875361 | G49: 45807 | H49: 45819 | I49: 45807 | J49: 45813 | K49: 45813 | L49: CHOCO | M49: ISTMINA | N49: BARRIO SANTA GENOVEVA ISTMINA CHOCO ISTMINA | O49: 79643 | P49: CB CRECIMIENTO - NUEVO | Q49: APERTURA | R49: REDEBAN | S49: UNO A UNO | T49: UNO A UNO | U49: EJECUTADO | V49: 30-05 SE REALIZA LLAMADA AL CLIENTE, SE HABLA CON EL SR PEDRO DAVID IBARGUEN CHALA SE VALIDA DIRECCIÓN OK, CANAL OK, DISPONIBILIDAD TOTAL, LLAMAR EL DÍA LA INSTALACIÓN PARA CONFIRMAR VISITA, AVISO EXTERIOR ALTURA APROX 2- 3 METROS; TOMACORRIENTE CERCANO: SI; TIENE CABINA DE SEGURIDAD:SI 5/6/2025 SE REALIZA INSTALACIÓN DE CORRESPONSAL, SE INSTALAN EQUIPOS CON PRUEBAS EXITOSAS, SE CAPACITA Y SE EVALÚA AL CLIENTE, SE INSTALA PUBLICIDAD COMPLETA, CB QUEDA OPERATIVO. USUARIO SOMOS BANCOLOMBIA ACTIVO | W49: ROBLEDO DIAZ ANDRES FELIPE | X49: SXUZZ169 | Y49: 763218 | Z49: 1115714 | AA49: 1239616 | AB49: N/A | AC49: 40 ROLLOS | AD49: TIPO IV ESPECIAL | AE49: AEREO | AF49: VISITA_TÉCNICA | AG49: 1 | AH49: 0 | AI49: =IF(AD49="TIPO I",'BASE LIQUIDACION REDEBAN 2025'!$B$2,IF(AD49="TIPO II",'BASE LIQUIDACION REDEBAN 2025'!$B$3,IF(AD49="TIPO III",'BASE LIQUIDACION REDEBAN 2025'!$B$4,IF(AD49="TIPO IV",'BASE LIQUIDACION REDEBAN 2025'!$B$5,IF(AE49="AEREO",'BASE LIQUIDACION REDEBAN 2025'!$B$6,'BASE LIQUIDACION REDEBAN 2025'!$B$5))))) -> 988462.96 | AJ49: =IF(AD49="TIPO I",'BASE LIQUIDACION REDEBAN 2025'!$B$10,IF(AD49="TIPO II",'BASE LIQUIDACION REDEBAN 2025'!$B$11,IF(AD49="TIPO III",'BASE LIQUIDACION REDEBAN 2025'!$B$12,'BASE LIQUIDACION REDEBAN 2025'!$B$13))) -> 196536.53 | AK49: =AG49*AI49+AH49*AJ49 -> 988462.96
A50: BOGOTA | B50: =VLOOKUP(A50,'CENTRO DE COSTOS'!A:D,4,FALSE) -> WILLIAM ASDRUBAL ROZO ROZO | C50: =VLOOKUP(A50,'CENTRO DE COSTOS'!A:D,2,FALSE) -> 0004-0004 | D50: 25772 | E50: TA-25-577608 | F50: FO-25-875365 | G50: 45807 | H50: 45812 | I50: 45807 | J50: 45813 | K50: 45813 | L50: CUNDINAMARCA | M50: SUESCA | N50: BARRIO VEREDA CASICASGO SUESCA | O50: 79656 | P50: CAMBIO DE RAZON SOCIAL | Q50: APERTURA | R50: REDEBAN | S50: UNO A UNO | T50: UNO A UNO | U50: EJECUTADO | V50: 30-05 SE REALIZA LLAMADA AL CLIENTE, SE HABLA CON EL SR JOSE ARIEL GALLEGO RAMIREZ, SE VALIDA DIRECCIÓN OK, CANAL OK, DISPONIBILIDAD TOTAL, LLAMAR EL DÍA LA INSTALACIÓN PARA CONFIRMAR VISITA, AVISO EXTERIOR ALTURA APROX 2,20 METROS; TOMACORRIENTE CERCANO: SI; TIENE CABINA DE SEGURIDAD:SI 04-06 POR NOVEDAD PRESENTANDA CON EL AREA DE BODEGA SE REPROGRAMA ACTIVIDA PARA EL DIA SIGUIENTE, SE HABLA CON JOSE ARIEL GALLEGO RAMIREZ / TELEFONO DE CONTACTO: 3213003875 QUIEN MANIFIESTA RECIBE LA INSTALACIÓN EL DÍA DE MAÑANA 05-06-2025 5/6/2025 SE REALIZA INSTALACIÓN DE CORRESPONSAL, SE INSTALAN EQUIPOS CON PRUEBAS EXITOSAS, SE CAPACITA Y SE EVALÚA AL CLIENTE, SE INSTALA PUBLICIDAD COMPLETA, CB QUEDA OPERATIVO. USUARIO SOMOS BANCOLOMBIA ACTIVO | W50: ROMERO ROJAS BREIDY JHOHAN | X50: SXUZZ182 | Y50: 908497 | Z50: N/A | AA50: 892553 | AB50: N/A | AC50: 40 ROLLOS | AD50: TIPO II | AE50: TERRESTRE | AF50: VISITA_TÉCNICA | AG50: 1 | AH50: 0 | AI50: =IF(AD50="TIPO I",'BASE LIQUIDACION REDEBAN 2025'!$B$2,IF(AD50="TIPO II",'BASE LIQUIDACION REDEBAN 2025'!$B$3,IF(AD50="TIPO III",'BASE LIQUIDACION REDEBAN 2025'!$B$4,IF(AD50="TIPO IV",'BASE LIQUIDACION REDEBAN 2025'!$B$5,IF(AE50="AEREO",'BASE LIQUIDACION REDEBAN 2025'!$B$6,'BASE LIQUIDACION REDEBAN 2025'!$B$5))))) -> 163813.7 | AJ50: =IF(AD50="TIPO I",'BASE LIQUIDACION REDEBAN 2025'!$B$10,IF(AD50="TIPO II",'BASE LIQUIDACION REDEBAN 2025'!$B$11,IF(AD50="TIPO III",'BASE LIQUIDACION REDEBAN 2025'!$B$12,'BASE LIQUIDACION REDEBAN 2025'!$B$13))) -> 140395.63 | AK50: =AG50*AI50+AH50*AJ50 -> 163813.7
A51: CARTAGENA | B51: =VLOOKUP(A51,'CENTRO DE COSTOS'!A:D,4,FALSE) -> JOSE MAURICIO HERNANDEZ ROJAS | C51: =VLOOKUP(A51,'CENTRO DE COSTOS'!A:D,2,FALSE) -> 0004-0001 | D51: 13001 | E51: TA-25-577615 | F51: FO-25-892697 | G51: 45807 | H51: 45812 | I51: 45807 | J51: 45812 | K51: 45812 | L51: BOLIVAR | M51: CARTAGENA | N51: BARRIO VIA AL MAR EDS PUERTA DE LAS AMERICAS CARTAGENA DE INDIAS | O51: 79622 | P51: CB CRECIMIENTO - NUEVO | Q51: APERTURA | R51: REDEBAN | S51: UNO A UNO | T51: UNO A UNO | U51: EJECUTADO | V51: 30-05 SE REALIZA LLAMADA AL CLIENTE, SE HABLA CON LA SR JUAN CARLOS MATUTE PACHECO SE VALIDA DIRECCIÓN OK, CANAL OK, DISPONIBILIDAD TOTAL, LLAMAR EL DÍA LA INSTALACIÓN PARA CONFIRMAR VISITA, AVISO EXTERIOR ALTURA APROX 2.50 METROS; TOMACORRIENTE CERCANO: SI; TIENE CABINA DE SEGURIDAD: SI 4/6/2025 SE REALIZA INSTALACIÓN DE CORRESPONSAL, SE INSTALAN EQUIPOS CON PRUEBAS EXITOSAS, SE CAPACITA Y SE EVALÚA AL CLIENTE, SE INSTALA PUBLICIDAD COMPLETA, CB QUEDA OPERATIVO. USUARIO SOMOS BANCOLOMBIA ACTIVO | W51: CANEDO HERRERA ALEXANDER | X51: SXUZZ148 | Y51: 931332 | Z51: N/A | AA51: 1097344 | AB51: N/A | AC51: 40 ROLLOS | AD51: TIPO I | AE51: TERRESTRE | AF51: VISITA_TÉCNICA | AG51: 1 | AH51: 0 | AI51: =IF(AD51="TIPO I",'BASE LIQUIDACION REDEBAN 2025'!$B$2,IF(AD51="TIPO II",'BASE LIQUIDACION REDEBAN 2025'!$B$3,IF(AD51="TIPO III",'BASE LIQUIDACION REDEBAN 2025'!$B$4,IF(AD51="TIPO IV",'BASE LIQUIDACION REDEBAN 2025'!$B$5,IF(AE51="AEREO",'BASE LIQUIDACION REDEBAN 2025'!$B$6,'BASE LIQUIDACION REDEBAN 2025'!$B$5))))) -> 75096.394 | AJ51: =IF(AD51="TIPO I",'BASE LIQUIDACION REDEBAN 2025'!$B$10,IF(AD51="TIPO II",'BASE LIQUIDACION REDEBAN 2025'!$B$11,IF(AD51="TIPO III",'BASE LIQUIDACION REDEBAN 2025'!$B$12,'BASE LIQUIDACION REDEBAN 2025'!$B$13))) -> 75096.394 | AK51: =AG51*AI51+AH51*AJ51 -> 75096.394
A52: VALLEDUPAR | B52: =VLOOKUP(A52,'CENTRO DE COSTOS'!A:D,4,FALSE) -> JOSE MAURICIO HERNANDEZ ROJAS | C52: =VLOOKUP(A52,'CENTRO DE COSTOS'!A:D,2,FALSE) -> 0004-0001 | D52: 20400 | E52: TA-25-577619 | F52: FO-25-875373 | G52: 45807 | H52: 45812 | I52: 45807 | J52: 45812 | K52: 45812 | L52: CESAR | M52: LA JAGUA DE IBIRICO | N52: BARRIO JUAN RAMOS LA JAGUA DE IBIRICO | O52: 79639 | P52: CB CRECIMIENTO - NUEVO | Q52: APERTURA | R52: REDEBAN | S52: UNO A UNO | T52: UNO A UNO | U52: EJECUTADO | V52: 30-05 SE REALIZA LLAMADA AL CLIENTE, SE HABLA CON LA SRA rosania SE VALIDA DIRECCIÓN OK, CANAL OK, DISPONIBILIDAD TOTAL, LLAMAR EL DÍA LA INSTALACIÓN PARA CONFIRMAR VISITA, AVISO EXTERIOR ALTURA APROX 2 METROS; TOMACORRIENTE CERCANO: SI; TIENE CABINA DE SEGURIDAD: SI - COMUNICACIÓN POR WPP 4/6/2025 SE REALIZA INSTALACIÓN DE CORRESPONSAL, SE INSTALAN EQUIPOS CON PRUEBAS EXITOSAS, SE CAPACITA Y SE EVALÚA AL CLIENTE, SE INSTALA PUBLICIDAD COMPLETA, CB QUEDA OPERATIVO. USUARIO SOMOS BANCOLOMBIA ACTIVO | W52: MONTES DIAZ JOHN FRED | X52: SXUZZ165 | Y52: 1113419 | Z52: N/A | AA52: 1217245 | AB52: N/A | AC52: 40 ROLLOS | AD52: TIPO III | AE52: TERRESTRE | AF52: VISITA_TÉCNICA | AG52: 1 | AH52: 0 | AI52: =IF(AD52="TIPO I",'BASE LIQUIDACION REDEBAN 2025'!$B$2,IF(AD52="TIPO II",'BASE LIQUIDACION REDEBAN 2025'!$B$3,IF(AD52="TIPO III",'BASE LIQUIDACION REDEBAN 2025'!$B$4,IF(AD52="TIPO IV",'BASE LIQUIDACION REDEBAN 2025'!$B$5,IF(AE52="AEREO",'BASE LIQUIDACION REDEBAN 2025'!$B$6,'BASE LIQUIDACION REDEBAN 2025'!$B$5))))) -> 275728.78 | AJ52: =IF(AD52="TIPO I",'BASE LIQUIDACION REDEBAN 2025'!$B$10,IF(AD52="TIPO II",'BASE LIQUIDACION REDEBAN 2025'!$B$11,IF(AD52="TIPO III",'BASE LIQUIDACION REDEBAN 2025'!$B$12,'BASE LIQUIDACION REDEBAN 2025'!$B$13))) -> 196536.53 | AK52: =AG52*AI52+AH52*AJ52 -> 275728.78
A53: CUCUTA | B53: =VLOOKUP(A53,'CENTRO DE COSTOS'!A:D,4,FALSE) -> MIGUEL JULIÁN HERNÁNDEZ GUARÍN | C53: =VLOOKUP(A53,'CENTRO DE COSTOS'!A:D,2,FALSE) -> 0004-0008 | D53: 54874 | E53: TA-25-577624 | F53: FO-25-875376 | G53: 45807 | H53: 45812 | I53: 45807 | J53: 45811 | K53: 45811 | L53: NORTE DE SANTANDER | M53: VILLA DEL ROSARIO | N53: BARRIO CENTRO VILLA DEL ROSARIO 5 | O53: 79662 | P53: CB CRECIMIENTO - NUEVO | Q53: APERTURA | R53: REDEBAN | S53: UNO A UNO | T53: UNO A UNO | U53: EJECUTADO | V53: 30-05 SE REALIZA LLAMADA AL CLIENTE, SE HABLA CON LA SR JUAN CARLOS CUTA RIBON SE VALIDA DIRECCIÓN OK, CANAL OK, DISPONIBILIDAD TOTAL, LLAMAR EL DÍA LA INSTALACIÓN PARA CONFIRMAR VISITA, AVISO EXTERIOR ALTURA APROX 2.50 METROS; TOMACORRIENTE CERCANO: SI; TIENE CABINA DE SEGURIDAD: EL SEÑOR INDICA QUE ESTA ES LA CAJA ESTA CERRADA MAS NO ESTA EL VIDRIO HASTA ARRIBA3/6/2025 SE REALIZA INSTALACIÓN DE CORRESPONSAL, SE INSTALAN EQUIPOS CON PRUEBAS EXITOSAS, SE CAPACITA Y SE EVALÚA AL CLIENTE, SE INSTALA PUBLICIDAD COMPLETA, CB QUEDA OPERATIVO. USUARIO SOMOS BANCOLOMBIA ACTIVO | W53: TORRES MANTILLA JOSE DANIEL | X53: SXUZZ188 | Y53: 1108261 | Z53: N/A | AA53: 830917 | AB53: N/A | AC53: 40 ROLLOS | AD53: TIPO I | AE53: TERRESTRE | AF53: VISITA_TÉCNICA | AG53: 1 | AH53: 0 | AI53: =IF(AD53="TIPO I",'BASE LIQUIDACION REDEBAN 2025'!$B$2,IF(AD53="TIPO II",'BASE LIQUIDACION REDEBAN 2025'!$B$3,IF(AD53="TIPO III",'BASE LIQUIDACION REDEBAN 2025'!$B$4,IF(AD53="TIPO IV",'BASE LIQUIDACION REDEBAN 2025'!$B$5,IF(AE53="AEREO",'BASE LIQUIDACION REDEBAN 2025'!$B$6,'BASE LIQUIDACION REDEBAN 2025'!$B$5))))) -> 75096.394 | AJ53: =IF(AD53="TIPO I",'BASE LIQUIDACION REDEBAN 2025'!$B$10,IF(AD53="TIPO II",'BASE LIQUIDACION REDEBAN 2025'!$B$11,IF(AD53="TIPO III",'BASE LIQUIDACION REDEBAN 2025'!$B$12,'BASE LIQUIDACION REDEBAN 2025'!$B$13))) -> 75096.394 | AK53: =AG53*AI53+AH53*AJ53 -> 75096.394
A54: BARRANQUILLA | B54: =VLOOKUP(A54,'CENTRO DE COSTOS'!A:D,4,FALSE) -> JOSE MAURICIO HERNANDEZ ROJAS | C54: =VLOOKUP(A54,'CENTRO DE COSTOS'!A:D,2,FALSE) -> 0004-0001 | D54: 8001 | E54: TA-25-577628 | F54: FO-25-875379 | G54: 45807 | H54: 45812 | I54: 45807 | J54: 45812 | K54: 45812 | L54: ATLANTICO | M54: BARRANQUILLA | N54: BARRIO LA VICTORIA BARRANQUILLA 2 | O54: 79597 | P54: CB CRECIMIENTO - NUEVO | Q54: APERTURA | R54: REDEBAN | S54: UNO A UNO | T54: UNO A UNO | U54: EJECUTADO | V54: 30-05 SE REALIZA LLAMADA AL CLIENTE, SE HABLA CON LA SR LUIS GUILLERMO SERJE RAPELLO VALIDA DIRECCIÓN OK, DISPONIBILIDAD TOTAL, LLAMAR EL DÍA LA INSTALACIÓN PARA CONFIRMAR VISITA, AVISO EXTERIOR ALTURA APROX 2.00 METROS; TOMACORRIENTE CERCANO: SI; TIENE CABINA DE SEGURIDAD: USUARIO TIENE REJA 03-06 SE LOGRA COMUNICACION VÍA WASHAP AL NÚMERO 3008485338, Y ME CONTESTA LA SEÑORA MARIANELA CANTILLO, CON QUIÉN SE ACUERDA LLEGAR TIPO 11 AM PARA ATENDERME, SE LLAMA A SITIO, PERO NO CONTESTAN WASHAP, NO LE ENTRAN MENSAJES NI LLAMADAS , ES UN CONJUNTO CERRADO, PERO ME DICE EL VIGILANTE QUE ESTÁ A LA VUELTA ,SE DA LA VUELTA A LA MANZANA PERO NO SE LOGRA VER EL LOCAL, ME VOY A OTRO SITIO HACER OTRA ACTIVIDAD, Y AHORA EN LAS HORAS DE LA TARDE REGRESO, ESTÁ VEZ SI ME CONTESTAN LOS MENSAJES INDICANDOME QUE DÉBIDO AL PARO EN FUNDACIÓN, NO PUDO REGRESAR, QUE POR FAVOR REAGENDE LA VISITA PARA MAÑANA 4 DE JUNIO 4/6/2025 SE REALIZA INSTALACIÓN DE CORRESPONSAL, SE INSTALAN EQUIPOS CON PRUEBAS EXITOSAS, SE CAPACITA Y SE EVALÚA AL CLIENTE, SE INSTALA PUBLICIDAD COMPLETA, CB QUEDA OPERATIVO. USUARIO SOMOS BANCOLOMBIA ACTIVO | W54: DE AVILA SIADES ALBERTO ENRIQUE | X54: SXUZZ123 | Y54: 1045719 | Z54: N/A | AA54: 905781 | AB54: N/A | AC54: 40 ROLLOS | AD54: TIPO I | AE54: TERRESTRE | AF54: VISITA_TÉCNICA | AG54: 1 | AH54: 0 | AI54: =IF(AD54="TIPO I",'BASE LIQUIDACION REDEBAN 2025'!$B$2,IF(AD54="TIPO II",'BASE LIQUIDACION REDEBAN 2025'!$B$3,IF(AD54="TIPO III",'BASE LIQUIDACION REDEBAN 2025'!$B$4,IF(AD54="TIPO IV",'BASE LIQUIDACION REDEBAN 2025'!$B$5,IF(AE54="AEREO",'BASE LIQUIDACION REDEBAN 2025'!$B$6,'BASE LIQUIDACION REDEBAN 2025'!$B$5))))) -> 75096.394 | AJ54: =IF(AD54="TIPO I",'BASE LIQUIDACION REDEBAN 2025'!$B$10,IF(AD54="TIPO II",'BASE LIQUIDACION REDEBAN 2025'!$B$11,IF(AD54="TIPO III",'BASE LIQUIDACION REDEBAN 2025'!$B$12,'BASE LIQUIDACION REDEBAN 2025'!$B$13))) -> 75096.394 | AK54: =AG54*AI54+AH54*AJ54 -> 75096.394
A55: BOGOTA | B55: =VLOOKUP(A55,'CENTRO DE COSTOS'!A:D,4,FALSE) -> WILLIAM ASDRUBAL ROZO ROZO | C55: =VLOOKUP(A55,'CENTRO DE COSTOS'!A:D,2,FALSE) -> 0004-0004 | D55: 11001 | E55: TA-25-577633 | F55: FO-25-875382 | G55: 45807 | H55: 45812 | I55: 45807 | J55: 45811 | K55: 45811 | L55: CUNDINAMARCA | M55: BOGOTA | N55: BARRIO CASTILLA BOGOTA 23 | O55: 79612 | P55: CAMBIO DE RAZON SOCIAL | Q55: APERTURA | R55: REDEBAN | S55: UNO A UNO | T55: UNO A UNO | U55: EJECUTADO | V55: 30-05 SE REALIZA LLAMADA AL CLIENTE, SE HABLA CON LA SRA YURY VANESSA GIL SOSA VALIDA DIRECCIÓN OK, DISPONIBILIDAD TOTAL, LLAMAR EL DÍA LA INSTALACIÓN PARA CONFIRMAR VISITA, AVISO EXTERIOR ALTURA APROX 3.00 METROS; TOMACORRIENTE CERCANO: SI; TIENE CABINA DE SEGURIDAD: SI 3/6/2025 SE REALIZA INSTALACIÓN DE CORRESPONSAL, SE INSTALAN EQUIPOS CON PRUEBAS EXITOSAS, SE CAPACITA Y SE EVALÚA AL CLIENTE, SE INSTALA PUBLICIDAD COMPLETA, CB QUEDA OPERATIVO. USUARIO SOMOS BANCOLOMBIA ACTIVO | W55: CORTES VELANDIA MIGUEL ANGEL | X55: SXUZZ138 | Y55: 792830 | Z55: N/A | AA55: 1110886 | AB55: N/A | AC55: 40 ROLLOS | AD55: TIPO I | AE55: TERRESTRE | AF55: VISITA_TÉCNICA | AG55: 1 | AH55: 0 | AI55: =IF(AD55="TIPO I",'BASE LIQUIDACION REDEBAN 2025'!$B$2,IF(AD55="TIPO II",'BASE LIQUIDACION REDEBAN 2025'!$B$3,IF(AD55="TIPO III",'BASE LIQUIDACION REDEBAN 2025'!$B$4,IF(AD55="TIPO IV",'BASE LIQUIDACION REDEBAN 2025'!$B$5,IF(AE55="AEREO",'BASE LIQUIDACION REDEBAN 2025'!$B$6,'BASE LIQUIDACION REDEBAN 2025'!$B$5))))) -> 75096.394 | AJ55: =IF(AD55="TIPO I",'BASE LIQUIDACION REDEBAN 2025'!$B$10,IF(AD55="TIPO II",'BASE LIQUIDACION REDEBAN 2025'!$B$11,IF(AD55="TIPO III",'BASE LIQUIDACION REDEBAN 2025'!$B$12,'BASE LIQUIDACION REDEBAN 2025'!$B$13))) -> 75096.394 | AK55: =AG55*AI55+AH55*AJ55 -> 75096.394
A56: CALI | B56: =VLOOKUP(A56,'CENTRO DE COSTOS'!A:D,4,FALSE) -> DIEGO FERNANDO HENAO CARDONA | C56: =VLOOKUP(A56,'CENTRO DE COSTOS'!A:D,2,FALSE) -> 0004-0003 | D56: 76130 | E56: TA-25-577638 | F56: FO-25-875385 | G56: 45807 | H56: 45812 | I56: 45807 | J56: 45811 | K56: 45811 | L56: VALLE DEL CAUCA | M56: CANDELARIA | N56: BARRIO MANZANARES SECTOR 11 - CANDELARIA CANDELARIA | O56: 79620 | P56: CB CRECIMIENTO - NUEVO | Q56: APERTURA | R56: REDEBAN | S56: UNO A UNO | T56: UNO A UNO | U56: EJECUTADO | V56: 30-05 SE REALIZA LLAMADA AL CLIENTE, SE HABLA CON LA SRA YURI TATIANA OSORIO BARREIRO (JOHAN DAVIDA MANRIQUE ) VALIDA DIRECCIÓN OK, DISPONIBILIDAD TOTAL, LLAMAR EL DÍA LA INSTALACIÓN PARA CONFIRMAR VISITA, AVISO EXTERIOR ALTURA APROX 2.00 METROS; TOMACORRIENTE CERCANO: SI; TIENE CABINA DE SEGURIDAD: SI | W56: TORRES GARCIA JENDRY JOSE | X56: SXUZZ146 | Y56: 1051052 | Z56: N/A | AA56: 879299 | AB56: N/A | AC56: 40 ROLLOS | AD56: TIPO II | AE56: TERRESTRE | AF56: VISITA_TÉCNICA | AG56: 1 | AH56: 0 | AI56: =IF(AD56="TIPO I",'BASE LIQUIDACION REDEBAN 2025'!$B$2,IF(AD56="TIPO II",'BASE LIQUIDACION REDEBAN 2025'!$B$3,IF(AD56="TIPO III",'BASE LIQUIDACION REDEBAN 2025'!$B$4,IF(AD56="TIPO IV",'BASE LIQUIDACION REDEBAN 2025'!$B$5,IF(AE56="AEREO",'BASE LIQUIDACION REDEBAN 2025'!$B$6,'BASE LIQUIDACION REDEBAN 2025'!$B$5))))) -> 163813.7 | AJ56: =IF(AD56="TIPO I",'BASE LIQUIDACION REDEBAN 2025'!$B$10,IF(AD56="TIPO II",'BASE LIQUIDACION REDEBAN 2025'!$B$11,IF(AD56="TIPO III",'BASE LIQUIDACION REDEBAN 2025'!$B$12,'BASE LIQUIDACION REDEBAN 2025'!$B$13))) -> 140395.63 | AK56: =AG56*AI56+AH56*AJ56 -> 163813.7
A57: CALI | B57: =VLOOKUP(A57,'CENTRO DE COSTOS'!A:D,4,FALSE) -> DIEGO FERNANDO HENAO CARDONA | C57: =VLOOKUP(A57,'CENTRO DE COSTOS'!A:D,2,FALSE) -> 0004-0003 | D57: 19809 | E57: TA-25-577643 | F57: FO-25-875387 | G57: 45807 | H57: 45819 | I57: 45807 | J57: 45827 | K57: 45827 | L57: CAUCA | M57: TIMBIQUI | N57: BARRIO PUERTO LUZ TIMBIQUI 1 | O57: 79657 | P57: CB CRECIMIENTO - NUEVO | Q57: APERTURA | R57: REDEBAN | S57: UNO A UNO | T57: UNO A UNO | U57: EJECUTADO | V57: 30-05 SE REALIZA LLAMADA AL CLIENTE, SE HABLA CON LA SR JAMINSON CAICEDO CAICEDO VALIDA DIRECCIÓN ( HERMINZA GOMEZ ESPOSA) OK, DISPONIBILIDAD TOTAL, LLAMAR EL DÍA LA INSTALACIÓN PARA CONFIRMAR VISITA, AVISO EXTERIOR ALTURA APROX 2.00 METROS; TOMACORRIENTE CERCANO: SI; TIENE CABINA DE SEGURIDAD: NO 11-06 DADO QUE PARA ESTA APERTURA SE DEBE DESPLAZAR POR VIA AEREA, SE TIENE DISPONIBILIDAD DEL VUELO PARA DIA MIERCOLES 18 DE JUNIO PARA DESPLAZAMIENTO DEL TÉCNICO A LA ZONA A REALIZAR ACTIVIDAD 19-06 SE REALIZA INSTALACIÓN DE CORRESPONSAL, SE INSTALAN EQUIPOS CON PRUEBAS EXITOSAS, SE CAPACITA Y SE EVALÚA AL CLIENTE, SE INSTALA PUBLICIDAD COMPLETA, CB QUEDA OPERATIVO. USUARIO SOMOS BANCOLOMBIA ACTIVO | W57: PAREDES CASTILLO DIEGO | X57: SXUZZ183 | Y57: 1106288 | Z57: N/A | AA57: 1114581 | AB57: N/A | AC57: 40 ROLLOS | AD57: TIPO IV ESPECIAL | AE57: AEREO | AF57: VISITA_TÉCNICA | AG57: 1 | AH57: 0 | AI57: =IF(AD57="TIPO I",'BASE LIQUIDACION REDEBAN 2025'!$B$2,IF(AD57="TIPO II",'BASE LIQUIDACION REDEBAN 2025'!$B$3,IF(AD57="TIPO III",'BASE LIQUIDACION REDEBAN 2025'!$B$4,IF(AD57="TIPO IV",'BASE LIQUIDACION REDEBAN 2025'!$B$5,IF(AE57="AEREO",'BASE LIQUIDACION REDEBAN 2025'!$B$6,'BASE LIQUIDACION REDEBAN 2025'!$B$5))))) -> 988462.96 | AJ57: =IF(AD57="TIPO I",'BASE LIQUIDACION REDEBAN 2025'!$B$10,IF(AD57="TIPO II",'BASE LIQUIDACION REDEBAN 2025'!$B$11,IF(AD57="TIPO III",'BASE LIQUIDACION REDEBAN 2025'!$B$12,'BASE LIQUIDACION REDEBAN 2025'!$B$13))) -> 196536.53 | AK57: =AG57*AI57+AH57*AJ57 -> 988462.96
A58: VALLEDUPAR | B58: =VLOOKUP(A58,'CENTRO DE COSTOS'!A:D,4,FALSE) -> JOSE MAURICIO HERNANDEZ ROJAS | C58: =VLOOKUP(A58,'CENTRO DE COSTOS'!A:D,2,FALSE) -> 0004-0001 | D58: 20001 | E58: TA-25-577648 | F58: FO-25-875390 | G58: 45807 | H58: 45812 | I58: 45807 | J58: 45811 | K58: 45811 | L58: CESAR | M58: VALLEDUPAR | N58: BARRIO CIUDADELA 450 AÑOS VALLEDUPAR 1 | O58: 79659 | P58: CB CRECIMIENTO - NUEVO | Q58: APERTURA | R58: REDEBAN | S58: UNO A UNO | T58: UNO A UNO | U58: EJECUTADO | V58: 30-05 SE REALIZA LLAMADA AL CLIENTE, SE HABLA CON LA SRA EDITH YAMILE MALAVER ORTIZ SE VALIDA DIRECCIÓN OK, DISPONIBILIDAD TOTAL, LLAMAR EL DÍA LA INSTALACIÓN PARA CONFIRMAR VISITA, AVISO EXTERIOR ALTURA APROX 2.00 METROS; TOMACORRIENTE CERCANO: SI; TIENE CABINA DE SEGURIDAD: SI LA DISTANCIA SON 4 METROS DE DEL MODEN A AL DATAFONO 3/6/2025 SE REALIZA INSTALACIÓN DE CORRESPONSAL, SE INSTALAN EQUIPOS CON PRUEBAS EXITOSAS, SE CAPACITA Y SE EVALÚA AL CLIENTE, SE INSTALA PUBLICIDAD COMPLETA, CB QUEDA OPERATIVO. USUARIO SOMOS BANCOLOMBIA ACTIVO | W58: MAESTRE MENGUAL EDGAR ENRIQUE | X58: SXUZZ185 | Y58: 1045500 | Z58: N/A | AA58: 1139755 | AB58: N/A | AC58: 40 ROLLOS | AD58: TIPO I | AE58: TERRESTRE | AF58: VISITA_TÉCNICA | AG58: 1 | AH58: 0 | AI58: =IF(AD58="TIPO I",'BASE LIQUIDACION REDEBAN 2025'!$B$2,IF(AD58="TIPO II",'BASE LIQUIDACION REDEBAN 2025'!$B$3,IF(AD58="TIPO III",'BASE LIQUIDACION REDEBAN 2025'!$B$4,IF(AD58="TIPO IV",'BASE LIQUIDACION REDEBAN 2025'!$B$5,IF(AE58="AEREO",'BASE LIQUIDACION REDEBAN 2025'!$B$6,'BASE LIQUIDACION REDEBAN 2025'!$B$5))))) -> 75096.394 | AJ58: =IF(AD58="TIPO I",'BASE LIQUIDACION REDEBAN 2025'!$B$10,IF(AD58="TIPO II",'BASE LIQUIDACION REDEBAN 2025'!$B$11,IF(AD58="TIPO III",'BASE LIQUIDACION REDEBAN 2025'!$B$12,'BASE LIQUIDACION REDEBAN 2025'!$B$13))) -> 75096.394 | AK58: =AG58*AI58+AH58*AJ58 -> 75096.394
A59: BOGOTA | B59: =VLOOKUP(A59,'CENTRO DE COSTOS'!A:D,4,FALSE) -> WILLIAM ASDRUBAL ROZO ROZO | C59: =VLOOKUP(A59,'CENTRO DE COSTOS'!A:D,2,FALSE) -> 0004-0004 | D59: 11001 | E59: TA-25-577654 | F59: FO-25-875393 | G59: 45807 | H59: 45812 | I59: 45807 | J59: 45811 | K59: 45811 | L59: CUNDINAMARCA | M59: BOGOTA | N59: BARRIO SAN ANTONIO BOGOTA 11 | O59: 79602 | P59: CB CRECIMIENTO - NUEVO | Q59: APERTURA | R59: REDEBAN | S59: UNO A UNO | T59: UNO A UNO | U59: EJECUTADO | V59: 30-05 SE REALIZA LLAMADA AL CLIENTE, SE HABLA CON LA SR CAMILO ALEXANDER VILLAMIL MONTAÑA ( NOS CONTESTAN EL HERMANO EDWIN ) SE VALIDA DIRECCIÓN OK, DISPONIBILIDAD TOTAL, LLAMAR EL DÍA LA INSTALACIÓN PARA CONFIRMAR VISITA, AVISO EXTERIOR ALTURA APROX 2.50 METROS; TOMACORRIENTE CERCANO: SI; TIENE CABINA DE SEGURIDAD: SI 3/6/2025 SE REALIZA INSTALACIÓN DE CORRESPONSAL, SE INSTALAN EQUIPOS CON PRUEBAS EXITOSAS, SE CAPACITA Y SE EVALÚA AL CLIENTE, SE INSTALA PUBLICIDAD COMPLETA, CB QUEDA OPERATIVO. USUARIO SOMOS BANCOLOMBIA ACTIVO | W59: GOMEZ VEGA DAVID SNEYDER | X59: SXUZZ128 | Y59: 1040953 | Z59: N/A | AA59: 893214 | AB59: N/A | AC59: 40 ROLLOS | AD59: TIPO I | AE59: TERRESTRE | AF59: VISITA_TÉCNICA | AG59: 1 | AH59: 0 | AI59: =IF(AD59="TIPO I",'BASE LIQUIDACION REDEBAN 2025'!$B$2,IF(AD59="TIPO II",'BASE LIQUIDACION REDEBAN 2025'!$B$3,IF(AD59="TIPO III",'BASE LIQUIDACION REDEBAN 2025'!$B$4,IF(AD59="TIPO IV",'BASE LIQUIDACION REDEBAN 2025'!$B$5,IF(AE59="AEREO",'BASE LIQUIDACION REDEBAN 2025'!$B$6,'BASE LIQUIDACION REDEBAN 2025'!$B$5))))) -> 75096.394 | AJ59: =IF(AD59="TIPO I",'BASE LIQUIDACION REDEBAN 2025'!$B$10,IF(AD59="TIPO II",'BASE LIQUIDACION REDEBAN 2025'!$B$11,IF(AD59="TIPO III",'BASE LIQUIDACION REDEBAN 2025'!$B$12,'BASE LIQUIDACION REDEBAN 2025'!$B$13))) -> 75096.394 | AK59: =AG59*AI59+AH59*AJ59 -> 75096.394
A60: MEDELLIN | B60: =VLOOKUP(A60,'CENTRO DE COSTOS'!A:D,4,FALSE) -> JUAN SEBASTIÁN RÍOS CASTRILLÓN | C60: =VLOOKUP(A60,'CENTRO DE COSTOS'!A:D,2,FALSE) -> 0004-0005 | D60: 5756 | E60: TA-25-577660 | F60: FO-25-875397 | G60: 45807 | H60: 45812 | I60: 45807 | J60: 45813 | K60: 45813 | L60: ANTIOQUIA | M60: SONSON | N60: BARRIO SONSON SONSON 8 | O60: 79632 | P60: CB CRECIMIENTO - NUEVO | Q60: APERTURA | R60: REDEBAN | S60: UNO A UNO | T60: UNO A UNO | U60: EJECUTADO | V60: 30-05 SE REALIZA LLAMADA AL CLIENTE, SE HABLA CON LA SR DAVID SOTO JIMENEZ SE VALIDA DIRECCIÓN OK, DISPONIBILIDAD TOTAL, LLAMAR EL DÍA LA INSTALACIÓN PARA CONFIRMAR VISITA, AVISO EXTERIOR ALTURA APROX 2.50 METROS; TOMACORRIENTE CERCANO: SI; TIENE CABINA DE SEGURIDAD: NO , USUARIO INDICA QUE SE EL MODEN SE ENCUENTRA 20 METROS 04-6 SE PRESENTA NOVEDAD EN LA VIA LA UNIÓN-SONSÓN SE SALE DESDE MEDELLÍN EN RUTA UNIÓN SONSÓN PERO SE TIENE PROBLEMAS CON EL TRANSPORTE EN LA UNIÓN EL BUS SALE TARDE DESE MEDELLÍN Y SE PRESENTA NOVEDAD EN LA VIA POR FUERTES LLUVIAS. SE HABLA CON EL USUARIO Y NOS COMFIMA QUE EL CIERRA TEMPRANO HOY PERO QUE NOS PUEDE ATENDER MAÑANA A PRIMERA HORA 5/6/2025 SE REALIZA INSTALACIÓN DE CORRESPONSAL, SE INSTALAN EQUIPOS CON PRUEBAS EXITOSAS, SE CAPACITA Y SE EVALÚA AL CLIENTE, SE INSTALA PUBLICIDAD COMPLETA, CB QUEDA OPERATIVO. USUARIO SOMOS BANCOLOMBIA ACTIVO | W60: DIAZ ZABALA FRANCIS DUBAN | X60: SXUZZ158 | Y60: 1062093 | Z60: N/A | AA60: 1097531 | AB60: N/A | AC60: 40 ROLLOS | AD60: TIPO III | AE60: TERRESTRE | AF60: VISITA_TÉCNICA | AG60: 1 | AH60: 0 | AI60: =IF(AD60="TIPO I",'BASE LIQUIDACION REDEBAN 2025'!$B$2,IF(AD60="TIPO II",'BASE LIQUIDACION REDEBAN 2025'!$B$3,IF(AD60="TIPO III",'BASE LIQUIDACION REDEBAN 2025'!$B$4,IF(AD60="TIPO IV",'BASE LIQUIDACION REDEBAN 2025'!$B$5,IF(AE60="AEREO",'BASE LIQUIDACION REDEBAN 2025'!$B$6,'BASE LIQUIDACION REDEBAN 2025'!$B$5))))) -> 275728.78 | AJ60: =IF(AD60="TIPO I",'BASE LIQUIDACION REDEBAN 2025'!$B$10,IF(AD60="TIPO II",'BASE LIQUIDACION REDEBAN 2025'!$B$11,IF(AD60="TIPO III",'BASE LIQUIDACION REDEBAN 2025'!$B$12,'BASE LIQUIDACION REDEBAN 2025'!$B$13))) -> 196536.53 | AK60: =AG60*AI60+AH60*AJ60 -> 275728.78
A61: MEDELLIN | B61: =VLOOKUP(A61,'CENTRO DE COSTOS'!A:D,4,FALSE) -> JUAN SEBASTIÁN RÍOS CASTRILLÓN | C61: =VLOOKUP(A61,'CENTRO DE COSTOS'!A:D,2,FALSE) -> 0004-0005 | D61: 5001 | E61: TA-25-577667 | F61: FO-25-875399 | G61: 45807 | H61: 45812 | I61: 45807 | J61: 45811 | K61: 45811 | L61: ANTIOQUIA | M61: MEDELLIN | N61: BARRIO BOSTON MEDELLIN 6 | O61: 79677 | P61: CB CRECIMIENTO - NUEVO | Q61: APERTURA | R61: REDEBAN | S61: UNO A UNO | T61: UNO A UNO | U61: EJECUTADO | V61: 30-05 SE REALIZA LLAMADA AL CLIENTE, SE HABLA CON LA SR ANDRES FELIPE ZAPATA LONDOÑO SE VALIDA DIRECCIÓN OK, DISPONIBILIDAD TOTAL, LLAMAR EL DÍA LA INSTALACIÓN PARA CONFIRMAR VISITA, AVISO EXTERIOR ALTURA APROX 2.50 METROS; TOMA CORRIENTE CERCANO: SI; TIENE CABINA DE SEGURIDAD: SI , USUARIO INDICA QUE SE EL MODEN SE ENCUENTRA 8 METROS 03-06 SE REALIZA INSTALACIÓN DE CORRESPONSAL, SE INSTALAN EQUIPOS CON PRUEBAS EXITOSAS, SE CAPACITA Y SE EVALÚA AL CLIENTE, SE INSTALA PUBLICIDAD COMPLETA, CB QUEDA OPERATIVO. USUARIO SOMOS BANCOLOMBIA ACTIVO | W61: PAREJA ECHAVARRIA JHON DAVID | X61: SXUZZ203 | Y61: 869106 | Z61: N/A | AA61: 1239749 | AB61: N/A | AC61: 40 ROLLOS | AD61: TIPO I | AE61: TERRESTRE | AF61: VISITA_TÉCNICA | AG61: 1 | AH61: 0 | AI61: =IF(AD61="TIPO I",'BASE LIQUIDACION REDEBAN 2025'!$B$2,IF(AD61="TIPO II",'BASE LIQUIDACION REDEBAN 2025'!$B$3,IF(AD61="TIPO III",'BASE LIQUIDACION REDEBAN 2025'!$B$4,IF(AD61="TIPO IV",'BASE LIQUIDACION REDEBAN 2025'!$B$5,IF(AE61="AEREO",'BASE LIQUIDACION REDEBAN 2025'!$B$6,'BASE LIQUIDACION REDEBAN 2025'!$B$5))))) -> 75096.394 | AJ61: =IF(AD61="TIPO I",'BASE LIQUIDACION REDEBAN 2025'!$B$10,IF(AD61="TIPO II",'BASE LIQUIDACION REDEBAN 2025'!$B$11,IF(AD61="TIPO III",'BASE LIQUIDACION REDEBAN 2025'!$B$12,'BASE LIQUIDACION REDEBAN 2025'!$B$13))) -> 75096.394 | AK61: =AG61*AI61+AH61*AJ61 -> 75096.394
... A70: MONTERIA | B70: =VLOOKUP(A70,'CENTRO DE COSTOS'!A:D,4,FALSE) -> JOSE MAURICIO HERNANDEZ ROJAS | C70: =VLOOKUP(A70,'CENTRO DE COSTOS'!A:D,2,FALSE) -> 0004-0001 | D70: 23675 | E70: TA-25-577723 | F70: FO-25-875428 | G70: 45807 | H70: 45812 | I70: 45807 | J70: 45811 | K70: 45811 | L70: CORDOBA | M70: SAN BERNARDO DEL VIENTO | N70: BARRIO GUAYABAL SAN BERNARDO DEL VIENTO | O70: 79652 | P70: CB CRECIMIENTO - NUEVO | Q70: APERTURA | R70: REDEBAN | S70: UNO A UNO | T70: UNO A UNO | U70: EJECUTADO | V70: 30-05 SE REALIZA LLAMADA AL CLIENTE, SE HABLA CON LA SRA CANDELARIA ROSA RODRIGUEZ CASSERES SE VALIDA DIRECCIÓN OK, CANAL OK, DISPONIBILIDAD TOTAL, LLAMAR EL DÍA LA INSTALACIÓN PARA CONFIRMAR VISITA, AVISO EXTERIOR ALTURA APROX 2 METROS; TOMACORRIENTE CERCANO: SI; TIENE CABINA DE SEGURIDAD: SI 3/6/2025 SE REALIZA INSTALACIÓN DE CORRESPONSAL, SE INSTALAN EQUIPOS CON PRUEBAS EXITOSAS, SE CAPACITA Y SE EVALÚA AL CLIENTE, SE INSTALA PUBLICIDAD COMPLETA, CB QUEDA OPERATIVO. NO SE ACTIVA PÁGINA SOMOS BANCOLOMBIA YA QUE EL CORREO REGISTRADO POR EL CB ESTÁ ERRÓNEO Y NO DEJO RESTAURAR CONTRASEÑA. SE CAPACITÓ CON PÁGINA DE PRUEBA. | W70: COGOLLO VERTEL EDER LUIS | X70: SXUZZ178 | Y70: 1045037 | Z70: N/A | AA70: 863722 | AB70: N/A | AC70: 40 ROLLOS | AD70: TIPO II | AE70: TERRESTRE | AF70: VISITA_TÉCNICA | AG70: 1 | AH70: 0 | AI70: =IF(AD70="TIPO I",'BASE LIQUIDACION REDEBAN 2025'!$B$2,IF(AD70="TIPO II",'BASE LIQUIDACION REDEBAN 2025'!$B$3,IF(AD70="TIPO III",'BASE LIQUIDACION REDEBAN 2025'!$B$4,IF(AD70="TIPO IV",'BASE LIQUIDACION REDEBAN 2025'!$B$5,IF(AE70="AEREO",'BASE LIQUIDACION REDEBAN 2025'!$B$6,'BASE LIQUIDACION REDEBAN 2025'!$B$5))))) -> 163813.7 | AJ70: =IF(AD70="TIPO I",'BASE LIQUIDACION REDEBAN 2025'!$B$10,IF(AD70="TIPO II",'BASE LIQUIDACION REDEBAN 2025'!$B$11,IF(AD70="TIPO III",'BASE LIQUIDACION REDEBAN 2025'!$B$12,'BASE LIQUIDACION REDEBAN 2025'!$B$13))) -> 140395.63 | AK70: =AG70*AI70+AH70*AJ70 -> 163813.7
A71: BOGOTA | B71: =VLOOKUP(A71,'CENTRO DE COSTOS'!A:D,4,FALSE) -> WILLIAM ASDRUBAL ROZO ROZO | C71: =VLOOKUP(A71,'CENTRO DE COSTOS'!A:D,2,FALSE) -> 0004-0004 | D71: 25394 | E71: TA-25-577729 | F71: FO-25-875431 | G71: 45807 | H71: 45812 | I71: 45807 | J71: 45813 | K71: 45813 | L71: CUNDINAMARCA | M71: LA PALMA | N71: BARRIO POZO ORTIZ LA PALMA LA PALMA | O71: 79644 | P71: CB CRECIMIENTO - NUEVO | Q71: APERTURA | R71: REDEBAN | S71: UNO A UNO | T71: UNO A UNO | U71: EJECUTADO | V71: 30-05 SE REALIZA LLAMADA AL CLIENTE, SE HABLA CON LA SRA KAROL TATIANA REAL LOZANO SE VALIDA DIRECCIÓN OK, CANAL OK, DISPONIBILIDAD TOTAL, LLAMAR EL DÍA LA INSTALACIÓN PARA CONFIRMAR VISITA, AVISO EXTERIOR ALTURA APROX 4 METROS; TOMACORRIENTE CERCANO: SI; TIENE CABINA DE SEGURIDAD: SI 4/6/2025 EN COMUNICACION CON EL COMERCIO KAROL TATIANA REAL LOZANO / TELEFONO DE CONTACTO: 3144477858, SE CONFIRMA VÍA CERRADA, COMERCIO ESTA PENDIENTE EL DÍA DE MAÑANA 05-06 PARA RECIVIR APERTURA SI DAN VÍA LIBRE 5/6/2025 SE REALIZA INSTALACIÓN DE CORRESPONSAL, SE INSTALAN EQUIPOS CON PRUEBAS EXITOSAS, SE CAPACITA Y SE EVALÚA AL CLIENTE, SE INSTALA PUBLICIDAD COMPLETA, CB QUEDA OPERATIVO. USUARIO SOMOS BANCOLOMBIA ACTIVO | W71: GALEANO SORIANO JUAN DAVID | X71: SXUZZ170 | Y71: 1172289 | Z71: 1216947 | AA71: 902150 | AB71: N/A | AC71: 40 ROLLOS | AD71: TIPO III | AE71: TERRESTRE | AF71: VISITA_TÉCNICA | AG71: 1 | AH71: 0 | AI71: =IF(AD71="TIPO I",'BASE LIQUIDACION REDEBAN 2025'!$B$2,IF(AD71="TIPO II",'BASE LIQUIDACION REDEBAN 2025'!$B$3,IF(AD71="TIPO III",'BASE LIQUIDACION REDEBAN 2025'!$B$4,IF(AD71="TIPO IV",'BASE LIQUIDACION REDEBAN 2025'!$B$5,IF(AE71="AEREO",'BASE LIQUIDACION REDEBAN 2025'!$B$6,'BASE LIQUIDACION REDEBAN 2025'!$B$5))))) -> 275728.78 | AJ71: =IF(AD71="TIPO I",'BASE LIQUIDACION REDEBAN 2025'!$B$10,IF(AD71="TIPO II",'BASE LIQUIDACION REDEBAN 2025'!$B$11,IF(AD71="TIPO III",'BASE LIQUIDACION REDEBAN 2025'!$B$12,'BASE LIQUIDACION REDEBAN 2025'!$B$13))) -> 196536.53 | AK71: =AG71*AI71+AH71*AJ71 -> 275728.78
A72: BOGOTA | B72: =VLOOKUP(A72,'CENTRO DE COSTOS'!A:D,4,FALSE) -> WILLIAM ASDRUBAL ROZO ROZO | C72: =VLOOKUP(A72,'CENTRO DE COSTOS'!A:D,2,FALSE) -> 0004-0004 | D72: 11001 | E72: TA-25-577734 | F72: FO-25-875434 | G72: 45807 | H72: 45812 | I72: 45807 | J72: 45811 | K72: 45811 | L72: CUNDINAMARCA | M72: BOGOTA | N72: BARRIO LOMBARDIA BOGOTA 1 | O72: 79613 | P72: CB CRECIMIENTO - NUEVO | Q72: APERTURA | R72: REDEBAN | S72: UNO A UNO | T72: UNO A UNO | U72: EJECUTADO | V72: 30-05 SE REALIZA LLAMADA AL CLIENTE, SE HABLA CON LA SRA BEATRIZ CASTAÑEDA HIDALGO SE VALIDA DIRECCIÓN OK, CANAL OK, DISPONIBILIDAD TOTAL, LLAMAR EL DÍA LA INSTALACIÓN PARA CONFIRMAR VISITA, AVISO EXTERIOR ALTURA APROX 2 METROS; TOMACORRIENTE CERCANO: SI; TIENE CABINA DE SEGURIDAD: NO - COMUNICACIÓN POR WPP 03-06 SE REALIZA INSTALACIÓN DE CORRESPONSAL, SE INSTALAN EQUIPOS CON PRUEBAS EXITOSAS, SE CAPACITA Y SE EVALÚA AL CLIENTE, SE INSTALA PUBLICIDAD COMPLETA, CB QUEDA OPERATIVO. USUARIO SOMOS BANCOLOMBIA ACTIVO | W72: MURCIA HERNANDEZ HARVEY IGNACIO | X72: SXUZZ139 | Y72: 1069468 | Z72: N/A | AA72: 521136 | AB72: N/A | AC72: 40 ROLLOS | AD72: TIPO I | AE72: TERRESTRE | AF72: VISITA_TÉCNICA | AG72: 1 | AH72: 0 | AI72: =IF(AD72="TIPO I",'BASE LIQUIDACION REDEBAN 2025'!$B$2,IF(AD72="TIPO II",'BASE LIQUIDACION REDEBAN 2025'!$B$3,IF(AD72="TIPO III",'BASE LIQUIDACION REDEBAN 2025'!$B$4,IF(AD72="TIPO IV",'BASE LIQUIDACION REDEBAN 2025'!$B$5,IF(AE72="AEREO",'BASE LIQUIDACION REDEBAN 2025'!$B$6,'BASE LIQUIDACION REDEBAN 2025'!$B$5))))) -> 75096.394 | AJ72: =IF(AD72="TIPO I",'BASE LIQUIDACION REDEBAN 2025'!$B$10,IF(AD72="TIPO II",'BASE LIQUIDACION REDEBAN 2025'!$B$11,IF(AD72="TIPO III",'BASE LIQUIDACION REDEBAN 2025'!$B$12,'BASE LIQUIDACION REDEBAN 2025'!$B$13))) -> 75096.394 | AK72: =AG72*AI72+AH72*AJ72 -> 75096.394
A73: BOGOTA | B73: =VLOOKUP(A73,'CENTRO DE COSTOS'!A:D,4,FALSE) -> WILLIAM ASDRUBAL ROZO ROZO | C73: =VLOOKUP(A73,'CENTRO DE COSTOS'!A:D,2,FALSE) -> 0004-0004 | D73: 25168 | E73: TA-25-577740 | F73: FO-25-875436 | G73: 45807 | H73: 45812 | I73: 45807 | J73: 45812 | K73: 45812 | L73: CUNDINAMARCA | M73: CHAGUANI | N73: BARRIO LA AMISTAD CHAGUANI | O73: 79638 | P73: CAMBIO DE REZON SOCIAL | Q73: APERTURA | R73: REDEBAN | S73: UNO A UNO | T73: UNO A UNO | U73: EJECUTADO | V73: 30-05 SE REALIZA LLAMADA AL CLIENTE, SE HABLA CON LA SR CAMILO ANDRES RUIZ HERNANDEZ SE VALIDA DIRECCIÓN OK, CANAL OK, DISPONIBILIDAD TOTAL, LLAMAR EL DÍA LA INSTALACIÓN PARA CONFIRMAR VISITA, AVISO EXTERIOR ALTURA APROX 2 METROS; TOMACORRIENTE CERCANO: SI; TIENE CABINA DE SEGURIDAD: NO - COMUNICACIÓN POR WPP 4/6/2025 SE REALIZA INSTALACIÓN DE CORRESPONSAL, SE INSTALAN EQUIPOS CON PRUEBAS EXITOSAS, SE CAPACITA Y SE EVALÚA AL CLIENTE, SE INSTALA PUBLICIDAD COMPLETA, CB QUEDA OPERATIVO. USUARIO SOMOS BANCOLOMBIA ACTIVO | W73: MURCIA HERNANDEZ HARVEY IGNACIO | X73: SXUZZ164 | Y73: 991301 | Z73: N/A | AA73: 1008506 | AB73: N/A | AC73: 40 ROLLOS | AD73: TIPO III | AE73: TERRESTRE | AF73: VISITA_TÉCNICA | AG73: 1 | AH73: 0 | AI73: =IF(AD73="TIPO I",'BASE LIQUIDACION REDEBAN 2025'!$B$2,IF(AD73="TIPO II",'BASE LIQUIDACION REDEBAN 2025'!$B$3,IF(AD73="TIPO III",'BASE LIQUIDACION REDEBAN 2025'!$B$4,IF(AD73="TIPO IV",'BASE LIQUIDACION REDEBAN 2025'!$B$5,IF(AE73="AEREO",'BASE LIQUIDACION REDEBAN 2025'!$B$6,'BASE LIQUIDACION REDEBAN 2025'!$B$5))))) -> 275728.78 | AJ73: =IF(AD73="TIPO I",'BASE LIQUIDACION REDEBAN 2025'!$B$10,IF(AD73="TIPO II",'BASE LIQUIDACION REDEBAN 2025'!$B$11,IF(AD73="TIPO III",'BASE LIQUIDACION REDEBAN 2025'!$B$12,'BASE LIQUIDACION REDEBAN 2025'!$B$13))) -> 196536.53 | AK73: =AG73*AI73+AH73*AJ73 -> 275728.78
A74: PASTO | B74: =VLOOKUP(A74,'CENTRO DE COSTOS'!A:D,4,FALSE) -> DIEGO FERNANDO HENAO CARDONA | C74: =VLOOKUP(A74,'CENTRO DE COSTOS'!A:D,2,FALSE) -> 0004-0003 | D74: 52001 | E74: TA-25-577746 | F74: FO-25-875440 | G74: 45807 | H74: 45812 | I74: 45807 | J74: 45811 | K74: 45811 | L74: NARIÑO | M74: PASTO | N74: BARRIO PANDIACO PASTO 3 | O74: 79647 | P74: CB CRECIMIENTO - NUEVO | Q74: APERTURA | R74: REDEBAN | S74: UNO A UNO | T74: UNO A UNO | U74: EJECUTADO | V74: 30-05 SE REALIZA LLAMADA AL CLIENTE, SE HABLA CON LA SRA MAIRENA GALLARDO CABRERA SE VALIDA DIRECCIÓN OK, CANAL OK, DISPONIBILIDAD TOTAL, LLAMAR EL DÍA LA INSTALACIÓN PARA CONFIRMAR VISITA, AVISO EXTERIOR ALTURA APROX 3 METROS; TOMACORRIENTE CERCANO: SI; TIENE CABINA DE SEGURIDAD: SI 03-06 SE REALIZA INSTALACIÓN DE CORRESPONSAL, SE INSTALAN EQUIPOS CON PRUEBAS EXITOSAS, SE CAPACITA Y SE EVALÚA AL CLIENTE, SE INSTALA PUBLICIDAD COMPLETA, CB QUEDA OPERATIVO. USUARIO SOMOS BANCOLOMBIA ACTIVO | W74: REMICIO AMADO JOHN HEBER | X74: SXUZZ173 | Y74: 765055 | Z74: 989228 | AA74: 1233547 | AB74: N/A | AC74: 40 ROLLOS | AD74: TIPO I | AE74: TERRESTRE | AF74: VISITA_TÉCNICA | AG74: 1 | AH74: 0 | AI74: =IF(AD74="TIPO I",'BASE LIQUIDACION REDEBAN 2025'!$B$2,IF(AD74="TIPO II",'BASE LIQUIDACION REDEBAN 2025'!$B$3,IF(AD74="TIPO III",'BASE LIQUIDACION REDEBAN 2025'!$B$4,IF(AD74="TIPO IV",'BASE LIQUIDACION REDEBAN 2025'!$B$5,IF(AE74="AEREO",'BASE LIQUIDACION REDEBAN 2025'!$B$6,'BASE LIQUIDACION REDEBAN 2025'!$B$5))))) -> 75096.394 | AJ74: =IF(AD74="TIPO I",'BASE LIQUIDACION REDEBAN 2025'!$B$10,IF(AD74="TIPO II",'BASE LIQUIDACION REDEBAN 2025'!$B$11,IF(AD74="TIPO III",'BASE LIQUIDACION REDEBAN 2025'!$B$12,'BASE LIQUIDACION REDEBAN 2025'!$B$13))) -> 75096.394 | AK74: =AG74*AI74+AH74*AJ74 -> 75096.394
A75: CALI | B75: =VLOOKUP(A75,'CENTRO DE COSTOS'!A:D,4,FALSE) -> DIEGO FERNANDO HENAO CARDONA | C75: =VLOOKUP(A75,'CENTRO DE COSTOS'!A:D,2,FALSE) -> 0004-0003 | D75: 76109 | E75: TA-25-577755 | F75: FO-25-875442 | G75: 45807 | H75: 45812 | I75: 45807 | J75: 45812 | K75: 45812 | L75: VALLE DEL CAUCA | M75: BUENAVENTURA | N75: BARRIO LOS TUBOS, PARTE BAJA BUENAVENTURA | O75: 79616 | P75: CB CRECIMIENTO - NUEVO | Q75: APERTURA | R75: REDEBAN | S75: UNO A UNO | T75: UNO A UNO | U75: EJECUTADO | V75: 30-05 SE REALIZA LLAMADA AL CLIENTE, SE HABLA CON LA SR DEYBER RAMIREZ SANCHEZ SE VALIDA DIRECCIÓN OK, CANAL OK, DISPONIBILIDAD TOTAL, LLAMAR EL DÍA LA INSTALACIÓN PARA CONFIRMAR VISITA, AVISO EXTERIOR ALTURA APROX 2 METROS; TOMACORRIENTE CERCANO: SI; TIENE CABINA DE SEGURIDAD: NO 04-06 SE REALIZA INSTALACIÓN DE CORRESPONSAL, SE INSTALAN EQUIPOS CON PRUEBAS EXITOSAS, SE CAPACITA Y SE EVALÚA AL CLIENTE, SE INSTALA PUBLICIDAD COMPLETA, CB QUEDA OPERATIVO. USUARIO SOMOS BANCOLOMBIA ACTIVO | W75: PAREDES CASTILLO DIEGO | X75: SXUZZ142 | Y75: 1116247 | Z75: N/A | AA75: 905531 | AB75: N/A | AC75: 40 ROLLOS | AD75: TIPO III | AE75: TERRESTRE | AF75: VISITA_TÉCNICA | AG75: 1 | AH75: 0 | AI75: =IF(AD75="TIPO I",'BASE LIQUIDACION REDEBAN 2025'!$B$2,IF(AD75="TIPO II",'BASE LIQUIDACION REDEBAN 2025'!$B$3,IF(AD75="TIPO III",'BASE LIQUIDACION REDEBAN 2025'!$B$4,IF(AD75="TIPO IV",'BASE LIQUIDACION REDEBAN 2025'!$B$5,IF(AE75="AEREO",'BASE LIQUIDACION REDEBAN 2025'!$B$6,'BASE LIQUIDACION REDEBAN 2025'!$B$5))))) -> 275728.78 | AJ75: =IF(AD75="TIPO I",'BASE LIQUIDACION REDEBAN 2025'!$B$10,IF(AD75="TIPO II",'BASE LIQUIDACION REDEBAN 2025'!$B$11,IF(AD75="TIPO III",'BASE LIQUIDACION REDEBAN 2025'!$B$12,'BASE LIQUIDACION REDEBAN 2025'!$B$13))) -> 196536.53 | AK75: =AG75*AI75+AH75*AJ75 -> 275728.78
A76: MEDELLIN | B76: =VLOOKUP(A76,'CENTRO DE COSTOS'!A:D,4,FALSE) -> JUAN SEBASTIÁN RÍOS CASTRILLÓN | C76: =VLOOKUP(A76,'CENTRO DE COSTOS'!A:D,2,FALSE) -> 0004-0005 | D76: 5440 | E76: TA-25-577761 | F76: FO-25-875445 | G76: 45807 | H76: 45812 | I76: 45807 | J76: 45812 | K76: 45812 | L76: ANTIOQUIA | M76: MARINILLA | N76: BARRIO SECTOR LA GALERÍA MARINILLA | O76: 79667 | P76: CB CRECIMIENTO - NUEVO | Q76: APERTURA | R76: REDEBAN | S76: UNO A UNO | T76: UNO A UNO | U76: EJECUTADO | V76: 30-05 SE REALIZA LLAMADA AL CLIENTE, SE HABLA CON LA SRA LUZ MERY NARANJO GARCIA SE VALIDA DIRECCIÓN OK, CANAL OK, DISPONIBILIDAD TOTAL, LLAMAR EL DÍA LA INSTALACIÓN PARA CONFIRMAR VISITA, AVISO EXTERIOR ALTURA APROX 2 METROS; TOMACORRIENTE CERCANO: SI; TIENE CABINA DE SEGURIDAD: NO 04-06 SE REALIZA INSTALACIÓN DE CORRESPONSAL, SE INSTALAN EQUIPOS CON PRUEBAS EXITOSAS, SE CAPACITA Y SE EVALÚA AL CLIENTE, SE INSTALA PUBLICIDAD COMPLETA, CB QUEDA OPERATIVO. USUARIO SOMOS BANCOLOMBIA ACTIVO | W76: ZAPATA LOPEZ EDWARD ASDRUBAL | X76: SXUZZ193 | Y76: 793709 | Z76: N/A | AA76: 903064 | AB76: N/A | AC76: 40 ROLLOS | AD76: TIPO II | AE76: TERRESTRE | AF76: VISITA_TÉCNICA | AG76: 1 | AH76: 0 | AI76: =IF(AD76="TIPO I",'BASE LIQUIDACION REDEBAN 2025'!$B$2,IF(AD76="TIPO II",'BASE LIQUIDACION REDEBAN 2025'!$B$3,IF(AD76="TIPO III",'BASE LIQUIDACION REDEBAN 2025'!$B$4,IF(AD76="TIPO IV",'BASE LIQUIDACION REDEBAN 2025'!$B$5,IF(AE76="AEREO",'BASE LIQUIDACION REDEBAN 2025'!$B$6,'BASE LIQUIDACION REDEBAN 2025'!$B$5))))) -> 163813.7 | AJ76: =IF(AD76="TIPO I",'BASE LIQUIDACION REDEBAN 2025'!$B$10,IF(AD76="TIPO II",'BASE LIQUIDACION REDEBAN 2025'!$B$11,IF(AD76="TIPO III",'BASE LIQUIDACION REDEBAN 2025'!$B$12,'BASE LIQUIDACION REDEBAN 2025'!$B$13))) -> 140395.63 | AK76: =AG76*AI76+AH76*AJ76 -> 163813.7
A77: BOGOTA | B77: =VLOOKUP(A77,'CENTRO DE COSTOS'!A:D,4,FALSE) -> WILLIAM ASDRUBAL ROZO ROZO | C77: =VLOOKUP(A77,'CENTRO DE COSTOS'!A:D,2,FALSE) -> 0004-0004 | D77: 11001 | E77: TA-25-577767 | F77: FO-25-875451 | G77: 45807 | H77: 45812 | I77: 45807 | J77: 45811 | K77: 45811 | L77: CUNDINAMARCA | M77: BOGOTA | N77: BARRIO ALTAMAR DINDALITO BOGOTA | O77: 79599 | P77: CB CRECIMIENTO - NUEVO | Q77: APERTURA | R77: REDEBAN | S77: UNO A UNO | T77: UNO A UNO | U77: EJECUTADO | V77: 30-05 SE REALIZA LLAMADA AL CLIENTE, SE HABLA CON LA SRA ANYI VIVIANA VERGARA DIAZ SE VALIDA DIRECCIÓN OK, CANAL OK, DISPONIBILIDAD TOTAL, LLAMAR EL DÍA LA INSTALACIÓN PARA CONFIRMAR VISITA, AVISO EXTERIOR ALTURA APROX 2.50 METROS; TOMACORRIENTE CERCANO: SI; TIENE CABINA DE SEGURIDAD: NO 3/6/2025 SE REALIZA INSTALACIÓN DE CORRESPONSAL, SE INSTALAN EQUIPOS CON PRUEBAS EXITOSAS, SE CAPACITA Y SE EVALÚA AL CLIENTE, SE INSTALA PUBLICIDAD COMPLETA, CB QUEDA OPERATIVO. USUARIO SOMOS BANCOLOMBIA ACTIVO | W77: ORTIZ MARTINEZ STIVEN | X77: SXUZZ125 | Y77: 888228 | Z77: N/A | AA77: 902284 | AB77: N/A | AC77: 40 ROLLOS | AD77: TIPO I | AE77: TERRESTRE | AF77: VISITA_TÉCNICA | AG77: 1 | AH77: 0 | AI77: =IF(AD77="TIPO I",'BASE LIQUIDACION REDEBAN 2025'!$B$2,IF(AD77="TIPO II",'BASE LIQUIDACION REDEBAN 2025'!$B$3,IF(AD77="TIPO III",'BASE LIQUIDACION REDEBAN 2025'!$B$4,IF(AD77="TIPO IV",'BASE LIQUIDACION REDEBAN 2025'!$B$5,IF(AE77="AEREO",'BASE LIQUIDACION REDEBAN 2025'!$B$6,'BASE LIQUIDACION REDEBAN 2025'!$B$5))))) -> 75096.394 | AJ77: =IF(AD77="TIPO I",'BASE LIQUIDACION REDEBAN 2025'!$B$10,IF(AD77="TIPO II",'BASE LIQUIDACION REDEBAN 2025'!$B$11,IF(AD77="TIPO III",'BASE LIQUIDACION REDEBAN 2025'!$B$12,'BASE LIQUIDACION REDEBAN 2025'!$B$13))) -> 75096.394 | AK77: =AG77*AI77+AH77*AJ77 -> 75096.394
A78: BOGOTA | B78: =VLOOKUP(A78,'CENTRO DE COSTOS'!A:D,4,FALSE) -> WILLIAM ASDRUBAL ROZO ROZO | C78: =VLOOKUP(A78,'CENTRO DE COSTOS'!A:D,2,FALSE) -> 0004-0004 | D78: 25035 | E78: TA-25-577771 | F78: FO-25-875454 | G78: 45807 | H78: 45812 | I78: 45807 | J78: 45812 | K78: 45812 | L78: CUNDINAMARCA | M78: ANAPOIMA | N78: BARRIO CENTRO ANAPOIMA ANAPOIMA | O78: 79593 | P78: CB CRECIMIENTO - NUEVO | Q78: APERTURA | R78: REDEBAN | S78: UNO A UNO | T78: UNO A UNO | U78: EJECUTADO | V78: 30-05 SE REALIZA LLAMADA AL CLIENTE, SE HABLA CON LA SRA DIANA MILENA GIL SE VALIDA DIRECCIÓN OK, CANAL OK, DISPONIBILIDAD TOTAL, LLAMAR EL DÍA LA INSTALACIÓN PARA CONFIRMAR VISITA, AVISO EXTERIOR ALTURA: NO INDICA ALTURA, TOMACORRIENTE CERCANO: SI; TIENE CABINA DE SEGURIDAD: NO 04-06 SE REALIZA INSTALACIÓN DE CORRESPONSAL, SE INSTALAN EQUIPOS CON PRUEBAS EXITOSAS, SE CAPACITA Y SE EVALÚA AL CLIENTE, SE INSTALA PUBLICIDAD COMPLETA, CB QUEDA OPERATIVO. USUARIO SOMOS BANCOLOMBIA ACTIVO | W78: GALEANO SORIANO JUAN DAVID | X78: SXUZZ119 | Y78: 1069444 | Z78: N/A | AA78: 1008361 | AB78: N/A | AC78: 40 ROLLOS | AD78: TIPO II | AE78: TERRESTRE | AF78: VISITA_TÉCNICA | AG78: 1 | AH78: 0 | AI78: =IF(AD78="TIPO I",'BASE LIQUIDACION REDEBAN 2025'!$B$2,IF(AD78="TIPO II",'BASE LIQUIDACION REDEBAN 2025'!$B$3,IF(AD78="TIPO III",'BASE LIQUIDACION REDEBAN 2025'!$B$4,IF(AD78="TIPO IV",'BASE LIQUIDACION REDEBAN 2025'!$B$5,IF(AE78="AEREO",'BASE LIQUIDACION REDEBAN 2025'!$B$6,'BASE LIQUIDACION REDEBAN 2025'!$B$5))))) -> 163813.7 | AJ78: =IF(AD78="TIPO I",'BASE LIQUIDACION REDEBAN 2025'!$B$10,IF(AD78="TIPO II",'BASE LIQUIDACION REDEBAN 2025'!$B$11,IF(AD78="TIPO III",'BASE LIQUIDACION REDEBAN 2025'!$B$12,'BASE LIQUIDACION REDEBAN 2025'!$B$13))) -> 140395.63 | AK78: =AG78*AI78+AH78*AJ78 -> 163813.7
A79: MEDELLIN | B79: =VLOOKUP(A79,'CENTRO DE COSTOS'!A:D,4,FALSE) -> JUAN SEBASTIÁN RÍOS CASTRILLÓN | C79: =VLOOKUP(A79,'CENTRO DE COSTOS'!A:D,2,FALSE) -> 0004-0005 | D79: 5667 | E79: TA-25-577779 | F79: FO-25-875458 | G79: 45807 | H79: 45812 | I79: 45807 | J79: 45812 | K79: 45812 | L79: ANTIOQUIA | M79: SAN RAFAEL | N79: SAN RAFAEL SAN RAFAEL 5 | O79: 79651 | P79: CB CRECIMIENTO - NUEVO | Q79: APERTURA | R79: REDEBAN | S79: UNO A UNO | T79: UNO A UNO | U79: EJECUTADO | V79: 30-05 SE REALIZA LLAMADA AL CLIENTE, SE HABLA CON LA SRA DEICY YANETH QUINCHIA CUERVO SE VALIDA DIRECCIÓN OK, CANAL OK, DISPONIBILIDAD TOTAL, LLAMAR EL DÍA LA INSTALACIÓN PARA CONFIRMAR VISITA, AVISO EXTERIOR ALTURA APROX 2.30 METROS; TOMACORRIENTE CERCANO: SI; TIENE CABINA DE SEGURIDAD: NO - COMUNICACIÓN POR WPP 04-06 SE REALIZA INSTALACIÓN DE CORRESPONSAL, SE INSTALAN EQUIPOS CON PRUEBAS EXITOSAS, SE CAPACITA Y SE EVALÚA AL CLIENTE, SE INSTALA PUBLICIDAD COMPLETA, CB QUEDA OPERATIVO. USUARIO SOMOS BANCOLOMBIA ACTIVO | W79: PAREJA ECHAVARRIA JHON DAVID | X79: SXUZZ177 | Y79: 1107042 | Z79: N/A | AA79: 974706 | AB79: N/A | AC79: 40 ROLLOS | AD79: TIPO III | AE79: TERRESTRE | AF79: VISITA_TÉCNICA | AG79: 1 | AH79: 0 | AI79: =IF(AD79="TIPO I",'BASE LIQUIDACION REDEBAN 2025'!$B$2,IF(AD79="TIPO II",'BASE LIQUIDACION REDEBAN 2025'!$B$3,IF(AD79="TIPO III",'BASE LIQUIDACION REDEBAN 2025'!$B$4,IF(AD79="TIPO IV",'BASE LIQUIDACION REDEBAN 2025'!$B$5,IF(AE79="AEREO",'BASE LIQUIDACION REDEBAN 2025'!$B$6,'BASE LIQUIDACION REDEBAN 2025'!$B$5))))) -> 275728.78 | AJ79: =IF(AD79="TIPO I",'BASE LIQUIDACION REDEBAN 2025'!$B$10,IF(AD79="TIPO II",'BASE LIQUIDACION REDEBAN 2025'!$B$11,IF(AD79="TIPO III",'BASE LIQUIDACION REDEBAN 2025'!$B$12,'BASE LIQUIDACION REDEBAN 2025'!$B$13))) -> 196536.53 | AK79: =AG79*AI79+AH79*AJ79 -> 275728.78
A80: MEDELLIN | B80: =VLOOKUP(A80,'CENTRO DE COSTOS'!A:D,4,FALSE) -> JUAN SEBASTIÁN RÍOS CASTRILLÓN | C80: =VLOOKUP(A80,'CENTRO DE COSTOS'!A:D,2,FALSE) -> 0004-0005 | D80: 5001 | E80: TA-25-612260 | F80: FO-25-903254 | G80: 45807 | H80: 45812 | I80: 45807 | J80: 45811 | K80: 45811 | L80: ANTIOQUIA | M80: MEDELLIN | N80: BARRIO BELEN MEDELLIN 14 | O80: 79672 | P80: CB CRECIMIENTO - NUEVO | Q80: APERTURA | R80: REDEBAN | S80: UNO A UNO | T80: UNO A UNO | U80: EJECUTADO | V80: 30-05 SE REALIZA LLAMADA AL CLIENTE, SE HABLA CON LA SRA CAROLINA ALCARAZ VIDALES SE VALIDA DIRECCIÓN OK, CANAL OK, DISPONIBILIDAD TOTAL, LLAMAR EL DÍA LA INSTALACIÓN PARA CONFIRMAR VISITA, AVISO EXTERIOR ALTURA APROX 2.50 METROS; TOMACORRIENTE CERCANO: SI; TIENE CABINA DE SEGURIDAD: NO 3/6/2025 SE REALIZA INSTALACIÓN DE CORRESPONSAL, SE INSTALAN EQUIPOS CON PRUEBAS EXITOSAS, SE CAPACITA Y SE EVALÚA AL CLIENTE, SE INSTALA PUBLICIDAD COMPLETA, CB QUEDA OPERATIVO. USUARIO SOMOS BANCOLOMBIA ACTIVO | W80: QUINTERO SANCHEZ JUAN SEBASTIAN | X80: SXUZZ198 | Y80: 1105537 | Z80: 1138632 | AA80: 1239755 | AB80: N/A | AC80: 40 ROLLOS | AD80: TIPO I | AE80: TERRESTRE | AF80: VISITA_TÉCNICA | AG80: 1 | AH80: 0 | AI80: =IF(AD80="TIPO I",'BASE LIQUIDACION REDEBAN 2025'!$B$2,IF(AD80="TIPO II",'BASE LIQUIDACION REDEBAN 2025'!$B$3,IF(AD80="TIPO III",'BASE LIQUIDACION REDEBAN 2025'!$B$4,IF(AD80="TIPO IV",'BASE LIQUIDACION REDEBAN 2025'!$B$5,IF(AE80="AEREO",'BASE LIQUIDACION REDEBAN 2025'!$B$6,'BASE LIQUIDACION REDEBAN 2025'!$B$5))))) -> 75096.394 | AJ80: =IF(AD80="TIPO I",'BASE LIQUIDACION REDEBAN 2025'!$B$10,IF(AD80="TIPO II",'BASE LIQUIDACION REDEBAN 2025'!$B$11,IF(AD80="TIPO III",'BASE LIQUIDACION REDEBAN 2025'!$B$12,'BASE LIQUIDACION REDEBAN 2025'!$B$13))) -> 75096.394 | AK80: =AG80*AI80+AH80*AJ80 -> 75096.394
A81: VALLEDUPAR | B81: =VLOOKUP(A81,'CENTRO DE COSTOS'!A:D,4,FALSE) -> JOSE MAURICIO HERNANDEZ ROJAS | C81: =VLOOKUP(A81,'CENTRO DE COSTOS'!A:D,2,FALSE) -> 0004-0001 | D81: 20250 | E81: TA-25-612262 | F81: FO-25-903259 | G81: 45807 | H81: 45812 | I81: 45807 | J81: 45811 | K81: 45811 | L81: CESAR | M81: EL PASO | N81: BARRIO CENTRO EL PASO 9 | O81: 79634 | P81: CB CRECIMIENTO - NUEVO | Q81: APERTURA | R81: REDEBAN | S81: UNO A UNO | T81: UNO A UNO | U81: EJECUTADO | V81: 30-05 SE REALIZA LLAMADA AL CLIENTE, SE HABLA CON LA SRA YULIBETH SEGOVIA SURMAY SE VALIDA DIRECCIÓN OK, CANAL OK, DISPONIBILIDAD TOTAL, LLAMAR EL DÍA LA INSTALACIÓN PARA CONFIRMAR VISITA, AVISO EXTERIOR ALTURA APROX 4 METROS; TOMACORRIENTE CERCANO: SI; TIENE CABINA DE SEGURIDAD: SI - COMUNICACIÓN POR WPP // EL MODEM ESTA A 5 MT 3/6/2025 SE REALIZA INSTALACIÓN DE CORRESPONSAL, SE INSTALAN EQUIPOS CON PRUEBAS EXITOSAS, SE CAPACITA Y SE EVALÚA AL CLIENTE, SE INSTALA PUBLICIDAD COMPLETA, CB QUEDA OPERATIVO. USUARIO SOMOS BANCOLOMBIA ACTIVO | W81: MONTES DIAZ JOHN FRED | X81: SXUZZ160 | Y81: 1045466 | Z81: N/A | AA81: 1139998 | AB81: N/A | AC81: 40 ROLLOS | AD81: TIPO III | AE81: TERRESTRE | AF81: VISITA_TÉCNICA | AG81: 1 | AH81: 0 | AI81: =IF(AD81="TIPO I",'BASE LIQUIDACION REDEBAN 2025'!$B$2,IF(AD81="TIPO II",'BASE LIQUIDACION REDEBAN 2025'!$B$3,IF(AD81="TIPO III",'BASE LIQUIDACION REDEBAN 2025'!$B$4,IF(AD81="TIPO IV",'BASE LIQUIDACION REDEBAN 2025'!$B$5,IF(AE81="AEREO",'BASE LIQUIDACION REDEBAN 2025'!$B$6,'BASE LIQUIDACION REDEBAN 2025'!$B$5))))) -> 275728.78 | AJ81: =IF(AD81="TIPO I",'BASE LIQUIDACION REDEBAN 2025'!$B$10,IF(AD81="TIPO II",'BASE LIQUIDACION REDEBAN 2025'!$B$11,IF(AD81="TIPO III",'BASE LIQUIDACION REDEBAN 2025'!$B$12,'BASE LIQUIDACION REDEBAN 2025'!$B$13))) -> 196536.53 | AK81: =AG81*AI81+AH81*AJ81 -> 275728.78
A82: SANTA MARTA | B82: =VLOOKUP(A82,'CENTRO DE COSTOS'!A:D,4,FALSE) -> JOSE MAURICIO HERNANDEZ ROJAS | C82: =VLOOKUP(A82,'CENTRO DE COSTOS'!A:D,2,FALSE) -> 0004-0001 | D82: 47245 | E82: TA-25-612264 | F82: FO-25-903265 | G82: 45807 | H82: 45812 | I82: 45807 | J82: 45817 | K82: 45817 | L82: MAGDALENA | M82: EL BANCO | N82: BARRIO PUEBLO NUEVO EL BANCO 1 | O82: 79631 | P82: CB CRECIMIENTO - NUEVO | Q82: APERTURA | R82: REDEBAN | S82: UNO A UNO | T82: UNO A UNO | U82: EJECUTADO | V82: 30-05 SE REALIZA LLAMADA AL CLIENTE, SE HABLA CON LA SR JORGE LUIS RANGEL CAMPO SE VALIDA DIRECCIÓN OK, CANAL OK, DISPONIBILIDAD TOTAL, LLAMAR EL DÍA LA INSTALACIÓN PARA CONFIRMAR VISITA, AVISO EXTERIOR ALTURA APROX 2 METROS; TOMACORRIENTE CERCANO: SI; TIENE CABINA DE SEGURIDAD: NO - EL MODEM ESTA A 6 MT 04-06 LA VÍA HACIA EL MUNICIPIO DE COPEY AÚN SE ENCUENTRA CERRADA DESDE LA Y DE CIÉNAGA HASTA BOSCONIA POR POBLADORES DE LA SIERRA, EN EL SECTOR DE SAN PEDRO DE LA SIERRA, EL PARO YA LLEVA 3 DÍAS SEGUIDOS 5/6/2025 SE REALIZA VALIDACIÓN NUEVAMENTE Y LA NOVEDAD CONTINUA 9/6/2025 SE REALIZA INSTALACIÓN DE CORRESPONSAL, SE INSTALAN EQUIPOS CON PRUEBAS EXITOSAS, SE CAPACITA Y SE EVALÚA AL CLIENTE, SE INSTALA PUBLICIDAD COMPLETA, CB QUEDA OPERATIVO. USUARIO SOMOS BANCOLOMBIA ACTIVO | W82: MONTES DIAZ JOHN FRED | X82: SXUZZ157 | Y82: 852906 | Z82: N/A | AA82: 535670 | AB82: N/A | AC82: 40 ROLLOS | AD82: TIPO IV | AE82: TERRESTRE | AF82: VISITA_TÉCNICA | AG82: 1 | AH82: 0 | AI82: =IF(AD82="TIPO I",'BASE LIQUIDACION REDEBAN 2025'!$B$2,IF(AD82="TIPO II",'BASE LIQUIDACION REDEBAN 2025'!$B$3,IF(AD82="TIPO III",'BASE LIQUIDACION REDEBAN 2025'!$B$4,IF(AD82="TIPO IV",'BASE LIQUIDACION REDEBAN 2025'!$B$5,IF(AE82="AEREO",'BASE LIQUIDACION REDEBAN 2025'!$B$6,'BASE LIQUIDACION REDEBAN 2025'!$B$5))))) -> 504832.65 | AJ82: =IF(AD82="TIPO I",'BASE LIQUIDACION REDEBAN 2025'!$B$10,IF(AD82="TIPO II",'BASE LIQUIDACION REDEBAN 2025'!$B$11,IF(AD82="TIPO III",'BASE LIQUIDACION REDEBAN 2025'!$B$12,'BASE LIQUIDACION REDEBAN 2025'!$B$13))) -> 196536.53 | AK82: =AG82*AI82+AH82*AJ82 -> 504832.65
A83: MEDELLIN | B83: =VLOOKUP(A83,'CENTRO DE COSTOS'!A:D,4,FALSE) -> JUAN SEBASTIÁN RÍOS CASTRILLÓN | C83: =VLOOKUP(A83,'CENTRO DE COSTOS'!A:D,2,FALSE) -> 0004-0005 | D83: 5001 | E83: TA-25-612267 | F83: FO-25-903270 | G83: 45807 | H83: 45812 | I83: 45807 | J83: 45811 | K83: 45811 | L83: ANTIOQUIA | M83: MEDELLIN | N83: BARRIO GUAYABAL MEDELLIN 13 | O83: 79675 | P83: CB CRECIMIENTO - NUEVO | Q83: APERTURA | R83: REDEBAN | S83: UNO A UNO | T83: UNO A UNO | U83: EJECUTADO | V83: 30-05 SE REALIZA LLAMADA AL CLIENTE, SE HABLA CON LA SRA YURANY ANDREA CIFUENTES CASTAÑEDA SE VALIDA DIRECCIÓN OK, CANAL OK, DISPONIBILIDAD TOTAL, LLAMAR EL DÍA LA INSTALACIÓN PARA CONFIRMAR VISITA, AVISO EXTERIOR ALTURA APROX 2.50 METROS; TOMACORRIENTE CERCANO: SI; TIENE CABINA DE SEGURIDAD: NO - COMUNICACIÓN POR WPP 3/6/2025 SE REALIZA INSTALACIÓN DE CORRESPONSAL, SE INSTALAN EQUIPOS CON PRUEBAS EXITOSAS, SE CAPACITA Y SE EVALÚA AL CLIENTE, SE INSTALA PUBLICIDAD COMPLETA, CB QUEDA OPERATIVO. USUARIO SOMOS BANCOLOMBIA ACTIVO | W83: DIAZ ZABALA FRANCIS DUBAN | X83: SXUZZ201 | Y83: 1030009 | Z83: N/A | AA83: 1217436 | AB83: N/A | AC83: 40 ROLLOS | AD83: TIPO I | AE83: TERRESTRE | AF83: VISITA_TÉCNICA | AG83: 1 | AH83: 0 | AI83: =IF(AD83="TIPO I",'BASE LIQUIDACION REDEBAN 2025'!$B$2,IF(AD83="TIPO II",'BASE LIQUIDACION REDEBAN 2025'!$B$3,IF(AD83="TIPO III",'BASE LIQUIDACION REDEBAN 2025'!$B$4,IF(AD83="TIPO IV",'BASE LIQUIDACION REDEBAN 2025'!$B$5,IF(AE83="AEREO",'BASE LIQUIDACION REDEBAN 2025'!$B$6,'BASE LIQUIDACION REDEBAN 2025'!$B$5))))) -> 75096.394 | AJ83: =IF(AD83="TIPO I",'BASE LIQUIDACION REDEBAN 2025'!$B$10,IF(AD83="TIPO II",'BASE LIQUIDACION REDEBAN 2025'!$B$11,IF(AD83="TIPO III",'BASE LIQUIDACION REDEBAN 2025'!$B$12,'BASE LIQUIDACION REDEBAN 2025'!$B$13))) -> 75096.394 | AK83: =AG83*AI83+AH83*AJ83 -> 75096.394
A84: BOGOTA | B84: =VLOOKUP(A84,'CENTRO DE COSTOS'!A:D,4,FALSE) -> WILLIAM ASDRUBAL ROZO ROZO | C84: =VLOOKUP(A84,'CENTRO DE COSTOS'!A:D,2,FALSE) -> 0004-0004 | D84: 11001 | E84: TA-25-612270 | F84: FO-25-903277 | G84: 45807 | H84: 45812 | I84: 45807 | J84: 45811 | K84: 45811 | L84: CUNDINAMARCA | M84: BOGOTA | N84: BARRIO GRAN BRITALIA BOGOTA 2 | O84: 79606 | P84: CB CRECIMIENTO - NUEVO | Q84: APERTURA | R84: REDEBAN | S84: UNO A UNO | T84: UNO A UNO | U84: EJECUTADO | V84: 30-05 SE REALIZA LLAMADA AL CLIENTE, SE HABLA CON LA SRA GREIS JULIETH ROJAS HERNANDEZ SE VALIDA DIRECCIÓN OK, CANAL OK, DISPONIBILIDAD TOTAL, LLAMAR EL DÍA LA INSTALACIÓN PARA CONFIRMAR VISITA, AVISO EXTERIOR ALTURA APROX 3 METROS; TOMACORRIENTE CERCANO: SI; TIENE CABINA DE SEGURIDAD: NO 3/6/2025 SE REALIZA INSTALACIÓN DE CORRESPONSAL, SE INSTALAN EQUIPOS CON PRUEBAS EXITOSAS, SE CAPACITA Y SE EVALÚA AL CLIENTE, SE INSTALA PUBLICIDAD COMPLETA, CB QUEDA OPERATIVO. USUARIO SOMOS BANCOLOMBIA ACTIVO | W84: ORTIZ MARTINEZ STIVEN | X84: SXUZZ132 | Y84: 1227607 | Z84: N/A | AA84: 984392 | AB84: N/A | AC84: 40 ROLLOS | AD84: TIPO I | AE84: TERRESTRE | AF84: VISITA_TÉCNICA | AG84: 1 | AH84: 0 | AI84: =IF(AD84="TIPO I",'BASE LIQUIDACION REDEBAN 2025'!$B$2,IF(AD84="TIPO II",'BASE LIQUIDACION REDEBAN 2025'!$B$3,IF(AD84="TIPO III",'BASE LIQUIDACION REDEBAN 2025'!$B$4,IF(AD84="TIPO IV",'BASE LIQUIDACION REDEBAN 2025'!$B$5,IF(AE84="AEREO",'BASE LIQUIDACION REDEBAN 2025'!$B$6,'BASE LIQUIDACION REDEBAN 2025'!$B$5))))) -> 75096.394 | AJ84: =IF(AD84="TIPO I",'BASE LIQUIDACION REDEBAN 2025'!$B$10,IF(AD84="TIPO II",'BASE LIQUIDACION REDEBAN 2025'!$B$11,IF(AD84="TIPO III",'BASE LIQUIDACION REDEBAN 2025'!$B$12,'BASE LIQUIDACION REDEBAN 2025'!$B$13))) -> 75096.394 | AK84: =AG84*AI84+AH84*AJ84 -> 75096.394
A85: BOGOTA | B85: =VLOOKUP(A85,'CENTRO DE COSTOS'!A:D,4,FALSE) -> WILLIAM ASDRUBAL ROZO ROZO | C85: =VLOOKUP(A85,'CENTRO DE COSTOS'!A:D,2,FALSE) -> 0004-0004 | D85: 11001 | E85: TA-25-612272 | F85: FO-25-903280 | G85: 45807 | H85: 45812 | I85: 45807 | J85: 45811 | K85: 45811 | L85: CUNDINAMARCA | M85: BOGOTA | N85: BARRIO LA ESTRELLA BOGOTA 2 | O85: 79605 | P85: CB CRECIMIENTO - NUEVO | Q85: APERTURA | R85: REDEBAN | S85: UNO A UNO | T85: UNO A UNO | U85: EJECUTADO | V85: 30-05 SE REALIZA LLAMADA AL CLIENTE, SE HABLA CON LA SR SNEIDER SAAVEDRA SAAVEDRA SE VALIDA DIRECCIÓN OK, CANAL OK, DISPONIBILIDAD TOTAL, LLAMAR EL DÍA LA INSTALACIÓN PARA CONFIRMAR VISITA, AVISO EXTERIOR ALTURA APROX 2 METROS; TOMACORRIENTE CERCANO: SI; TIENE CABINA DE SEGURIDAD: SI - EL MODEM ESTA A 4 MT 03-06 SE REALIZA INSTALACIÓN DE CORRESPONSAL, SE INSTALAN EQUIPOS CON PRUEBAS EXITOSAS, SE CAPACITA Y SE EVALÚA AL CLIENTE, SE INSTALA PUBLICIDAD COMPLETA, CB QUEDA OPERATIVO. USUARIO SOMOS BANCOLOMBIA ACTIVO NOTA: SE SOLICITA AUTORIZACIÓN DE INSTALACIÓN DE COMBO 2600 CON MAGICBOX 241597317561324755896013 Y PINPAD, PERO AL INSTALAR EL PINPAD Y SOLICITAR EL CAMBIO DE EQUIPO , EL PINPAD NO FUNCIONA 5/6/2025 SE REALIZA INSTALACIÓN DE PINPAD PENDIENTE | W85: ROMERO ROJAS BREIDY JHOHAN | X85: SXUZZ131 | Y85: 1235225 | Z85: 771812 | AA85: 1076276-241597317561324755896013 | AB85: N/A | AC85: 40 ROLLOS | AD85: TIPO I | AE85: TERRESTRE | AF85: VISITA_TÉCNICA | AG85: 1 | AH85: 0 | AI85: =IF(AD85="TIPO I",'BASE LIQUIDACION REDEBAN 2025'!$B$2,IF(AD85="TIPO II",'BASE LIQUIDACION REDEBAN 2025'!$B$3,IF(AD85="TIPO III",'BASE LIQUIDACION REDEBAN 2025'!$B$4,IF(AD85="TIPO IV",'BASE LIQUIDACION REDEBAN 2025'!$B$5,IF(AE85="AEREO",'BASE LIQUIDACION REDEBAN 2025'!$B$6,'BASE LIQUIDACION REDEBAN 2025'!$B$5))))) -> 75096.394 | AJ85: =IF(AD85="TIPO I",'BASE LIQUIDACION REDEBAN 2025'!$B$10,IF(AD85="TIPO II",'BASE LIQUIDACION REDEBAN 2025'!$B$11,IF(AD85="TIPO III",'BASE LIQUIDACION REDEBAN 2025'!$B$12,'BASE LIQUIDACION REDEBAN 2025'!$B$13))) -> 75096.394 | AK85: =AG85*AI85+AH85*AJ85 -> 75096.394
A86: BOGOTA | B86: =VLOOKUP(A86,'CENTRO DE COSTOS'!A:D,4,FALSE) -> WILLIAM ASDRUBAL ROZO ROZO | C86: =VLOOKUP(A86,'CENTRO DE COSTOS'!A:D,2,FALSE) -> 0004-0004 | D86: 11001 | E86: TA-25-612273 | F86: FO-25-903286 | G86: 45807 | H86: 45812 | I86: 45807 | J86: 45811 | K86: 45811 | L86: CUNDINAMARCA | M86: BOGOTA | N86: BARRIO SAN FRANCISCO BOGOTA 13 | O86: 79611 | P86: CB CRECIMIENTO - NUEVO | Q86: APERTURA | R86: REDEBAN | S86: UNO A UNO | T86: UNO A UNO | U86: EJECUTADO | V86: 30-05 SE REALIZA LLAMADA AL CLIENTE, SE HABLA CON LA SRA LEIDY ALEXANDRA GARCIA ACUÑA SE VALIDA DIRECCIÓN OK, CANAL OK, DISPONIBILIDAD TOTAL, LLAMAR EL DÍA LA INSTALACIÓN PARA CONFIRMAR VISITA, AVISO EXTERIOR ALTURA: NO INDICA ALTURA; TOMACORRIENTE CERCANO: SI; TIENE CABINA DE SEGURIDAD: NO 03-06 SE REALIZA INSTALACIÓN DE CORRESPONSAL, SE INSTALAN EQUIPOS CON PRUEBAS EXITOSAS, SE CAPACITA Y SE EVALÚA AL CLIENTE, SE INSTALA PUBLICIDAD COMPLETA, CB QUEDA OPERATIVO. USUARIO SOMOS BANCOLOMBIA ACTIVO | W86: GALEANO SORIANO JUAN DAVID | X86: SXUZZ137 | Y86: 1069587 | Z86: N/A | AA86: 1076627 | AB86: N/A | AC86: 40 ROLLOS | AD86: TIPO I | AE86: TERRESTRE | AF86: VISITA_TÉCNICA | AG86: 1 | AH86: 0 | AI86: =IF(AD86="TIPO I",'BASE LIQUIDACION REDEBAN 2025'!$B$2,IF(AD86="TIPO II",'BASE LIQUIDACION REDEBAN 2025'!$B$3,IF(AD86="TIPO III",'BASE LIQUIDACION REDEBAN 2025'!$B$4,IF(AD86="TIPO IV",'BASE LIQUIDACION REDEBAN 2025'!$B$5,IF(AE86="AEREO",'BASE LIQUIDACION REDEBAN 2025'!$B$6,'BASE LIQUIDACION REDEBAN 2025'!$B$5))))) -> 75096.394 | AJ86: =IF(AD86="TIPO I",'BASE LIQUIDACION REDEBAN 2025'!$B$10,IF(AD86="TIPO II",'BASE LIQUIDACION REDEBAN 2025'!$B$11,IF(AD86="TIPO III",'BASE LIQUIDACION REDEBAN 2025'!$B$12,'BASE LIQUIDACION REDEBAN 2025'!$B$13))) -> 75096.394 | AK86: =AG86*AI86+AH86*AJ86 -> 75096.394
A87: MEDELLIN | B87: =VLOOKUP(A87,'CENTRO DE COSTOS'!A:D,4,FALSE) -> JUAN SEBASTIÁN RÍOS CASTRILLÓN | C87: =VLOOKUP(A87,'CENTRO DE COSTOS'!A:D,2,FALSE) -> 0004-0005 | D87: 5313 | E87: TA-25-612274 | F87: FO-25-903293 | G87: 45807 | H87: 45812 | I87: 45807 | J87: 45812 | K87: 45812 | L87: ANTIOQUIA | M87: GRANADA | N87: BARRIO GRANADA GRANADA 1 | O87: 79642 | P87: CAMBIO DE REZON SOCIAL | Q87: APERTURA | R87: REDEBAN | S87: UNO A UNO | T87: UNO A UNO | U87: EJECUTADO | V87: 30-05 SE REALIZA LLAMADA AL CLIENTE, SE HABLA CON LA SRA YURANI QUINTERO SE VALIDA DIRECCIÓN OK, CANAL OK, DISPONIBILIDAD TOTAL, LLAMAR EL DÍA LA INSTALACIÓN PARA CONFIRMAR VISITA, USUARIO INDICA QUE TIENE TODA LA PUBLICIDAD; TOMACORRIENTE CERCANO: SI; TIENE CABINA DE SEGURIDAD: NO - CAMBIO DE RAZON SOCIAL 77402 4/6/2025 SE REALIZA INSTALACIÓN DE CORRESPONSAL, SE INSTALAN EQUIPOS CON PRUEBAS EXITOSAS, SE CAPACITA Y SE EVALÚA AL CLIENTE, SE INSTALA PUBLICIDAD COMPLETA, CB QUEDA OPERATIVO. USUARIO SOMOS BANCOLOMBIA ACTIVO | W87: ZAPATA LOPEZ EDWARD ASDRUBAL | X87: SXUZZ168 | Y87: 1171355 | Z87: N/A | AA87: 1239618 | AB87: N/A | AC87: 40 ROLLOS | AD87: TIPO II | AE87: TERRESTRE | AF87: VISITA_TÉCNICA | AG87: 1 | AH87: 0 | AI87: =IF(AD87="TIPO I",'BASE LIQUIDACION REDEBAN 2025'!$B$2,IF(AD87="TIPO II",'BASE LIQUIDACION REDEBAN 2025'!$B$3,IF(AD87="TIPO III",'BASE LIQUIDACION REDEBAN 2025'!$B$4,IF(AD87="TIPO IV",'BASE LIQUIDACION REDEBAN 2025'!$B$5,IF(AE87="AEREO",'BASE LIQUIDACION REDEBAN 2025'!$B$6,'BASE LIQUIDACION REDEBAN 2025'!$B$5))))) -> 163813.7 | AJ87: =IF(AD87="TIPO I",'BASE LIQUIDACION REDEBAN 2025'!$B$10,IF(AD87="TIPO II",'BASE LIQUIDACION REDEBAN 2025'!$B$11,IF(AD87="TIPO III",'BASE LIQUIDACION REDEBAN 2025'!$B$12,'BASE LIQUIDACION REDEBAN 2025'!$B$13))) -> 140395.63 | AK87: =AG87*AI87+AH87*AJ87 -> 163813.7
A88: CALI | B88: =VLOOKUP(A88,'CENTRO DE COSTOS'!A:D,4,FALSE) -> DIEGO FERNANDO HENAO CARDONA | C88: =VLOOKUP(A88,'CENTRO DE COSTOS'!A:D,2,FALSE) -> 0004-0003 | D88: 76126 | E88: TA-25-612276 | F88: FO-25-903299 | G88: 45807 | H88: 45812 | I88: 45807 | J88: 45812 | K88: 45812 | L88: VALLE DEL CAUCA | M88: CALIMA | N88: BARRIO CENTRO 2 CALIMA | O88: 27388 | P88: DATAFONO ADICIONAL | Q88: APERTURA | R88: REDEBAN | S88: UNO A UNO | T88: UNO A UNO | U88: EJECUTADO | V88: 30-05 SE REALIZA LLAMADA AL CLIENTE, SE HABLA CON LA SRA NANCY MORENO SE VALIDA DIRECCIÓN OK, CANAL OK, DISPONIBILIDAD TOTAL, LLAMAR EL DÍA LA INSTALACIÓN PARA CONFIRMAR VISITA 05-06 SE REALIZA INSTALACIÓN DE DAT ADICIONAL, PRUEBAS EXITOSAS, CB QUEDA OPERATIVO | W88: HERRERA MONAR GEOVANNY | X88: SXUZZ737 | Y88: 987925 | Z88: N/A | AA88: 538473 | AB88: N/A | AC88: 60 ROLLOS | AD88: TIPO II | AE88: TERRESTRE | AF88: VISITA_TÉCNICA | AG88: 1 | AH88: 0 | AI88: =IF(AD88="TIPO I",'BASE LIQUIDACION REDEBAN 2025'!$B$2,IF(AD88="TIPO II",'BASE LIQUIDACION REDEBAN 2025'!$B$3,IF(AD88="TIPO III",'BASE LIQUIDACION REDEBAN 2025'!$B$4,IF(AD88="TIPO IV",'BASE LIQUIDACION REDEBAN 2025'!$B$5,IF(AE88="AEREO",'BASE LIQUIDACION REDEBAN 2025'!$B$6,'BASE LIQUIDACION REDEBAN 2025'!$B$5))))) -> 163813.7 | AJ88: =IF(AD88="TIPO I",'BASE LIQUIDACION REDEBAN 2025'!$B$10,IF(AD88="TIPO II",'BASE LIQUIDACION REDEBAN 2025'!$B$11,IF(AD88="TIPO III",'BASE LIQUIDACION REDEBAN 2025'!$B$12,'BASE LIQUIDACION REDEBAN 2025'!$B$13))) -> 140395.63 | AK88: =AG88*AI88+AH88*AJ88 -> 163813.7
A89: NEIVA | B89: =VLOOKUP(A89,'CENTRO DE COSTOS'!A:D,4,FALSE) -> KEVIN ALEXIS CORZO BUSTOS | C89: =VLOOKUP(A89,'CENTRO DE COSTOS'!A:D,2,FALSE) -> 0004-0007 | D89: 41551 | E89: TA-25-612277 | F89: FO-25-903306 | G89: 45811 | H89: 45813 | I89: 45811 | J89: 45813 | K89: 45813 | L89: HUILA | M89: PITALITO | N89: BARRIO CACHINGOS PITALITO | O89: 79682 | P89: CB CRECIMIENTO - NUEVO | Q89: APERTURA | R89: REDEBAN | S89: UNO A UNO | T89: UNO A UNO | U89: EJECUTADO | V89: 31-05 SE REALIZA LLAMADA AL CLIENTE, SE HABLA CON EL SR JUAN DIEGO AVILEZ OSORIO, SE VALIDA DIRECCIÓN OK, CANAL OK, DISPONIBILIDAD TOTAL, LLAMAR EL DÍA LA INSTALACIÓN PARA CONFIRMAR VISITA, AVISO EXTERIOR ALTURA APROX DONDE EL TECNICO LO VEA CONVENIENTE, METROS; TOMACORRIENTE CERCANO: SI; TIENE CABINA DE SEGURIDAD:SI 5/6/2025 SE REALIZA INSTALACIÓN DE CORRESPONSAL, SE INSTALAN EQUIPOS CON PRUEBAS EXITOSAS, SE CAPACITA Y SE EVALÚA AL CLIENTE, SE INSTALA PUBLICIDAD COMPLETA, CB QUEDA OPERATIVO. USUARIO SOMOS BANCOLOMBIA ACTIVO | W89: ANDRADE HERNANDEZ JUAN CARLOS | X89: SXXZZ082 | Y89: 1088304 | Z89: N/A | AA89: 1103004 | AB89: N/A | AC89: 40 ROLLOS | AD89: TIPO III | AE89: TERRESTRE | AF89: VISITA_TÉCNICA | AG89: 1 | AH89: 0 | AI89: =IF(AD89="TIPO I",'BASE LIQUIDACION REDEBAN 2025'!$B$2,IF(AD89="TIPO II",'BASE LIQUIDACION REDEBAN 2025'!$B$3,IF(AD89="TIPO III",'BASE LIQUIDACION REDEBAN 2025'!$B$4,IF(AD89="TIPO IV",'BASE LIQUIDACION REDEBAN 2025'!$B$5,IF(AE89="AEREO",'BASE LIQUIDACION REDEBAN 2025'!$B$6,'BASE LIQUIDACION REDEBAN 2025'!$B$5))))) -> 275728.78 | AJ89: =IF(AD89="TIPO I",'BASE LIQUIDACION REDEBAN 2025'!$B$10,IF(AD89="TIPO II",'BASE LIQUIDACION REDEBAN 2025'!$B$11,IF(AD89="TIPO III",'BASE LIQUIDACION REDEBAN 2025'!$B$12,'BASE LIQUIDACION REDEBAN 2025'!$B$13))) -> 196536.53 | AK89: =AG89*AI89+AH89*AJ89 -> 275728.78
A90: SINCELEJO | B90: =VLOOKUP(A90,'CENTRO DE COSTOS'!A:D,4,FALSE) -> JOSE MAURICIO HERNANDEZ ROJAS | C90: =VLOOKUP(A90,'CENTRO DE COSTOS'!A:D,2,FALSE) -> 0004-0001 | D90: 70001 | E90: TA-25-612278 | F90: FO-25-903316 | G90: 45811 | H90: 45813 | I90: 45811 | J90: 45812 | K90: 45812 | L90: SUCRE | M90: SINCELEJO | N90: BARRIO CALLE SUCRE SINCELEJO | O90: 79684 | P90: CB CRECIMIENTO - NUEVO | Q90: APERTURA | R90: REDEBAN | S90: UNO A UNO | T90: UNO A UNO | U90: EJECUTADO | V90: 3-06-2025 SE REALIZA LLAMADA AL CLIENTE, SE HABLA CON EL SR LUIS FERNANDO PACHECO BERTEL SE VALIDA DIRECCIÓN OK, CANAL OK, DISPONIBILIDAD TOTAL, LLAMAR EL DÍA DE LA INSTALACIÓN PARA CONFIRMAR VISITA, ALTURA APROX 2 METROS; TOMACORRIENTE CERCANO: SI; TIENE CABINA DE SEGURIDAD: NO // CONTACTO REALIZADO POR WHATSAPP 8:10 a. m. 4/6/2025 SE REALIZA INSTALACIÓN DE CORRESPONSAL, SE INSTALAN EQUIPOS CON PRUEBAS EXITOSAS, SE CAPACITA Y SE EVALÚA AL CLIENTE, SE INSTALA PUBLICIDAD COMPLETA, CB QUEDA OPERATIVO. USUARIO SOMOS BANCOLOMBIA ACTIVO | W90: CACERES HERNANDEZ ANDRES | X90: SXXZZ084 | Y90: 963801 | Z90: N/A | AA90: 1145979 | AB90: N/A | AC90: 40 ROLLOS | AD90: TIPO I | AE90: TERRESTRE | AF90: VISITA_TÉCNICA | AG90: 1 | AH90: 0 | AI90: =IF(AD90="TIPO I",'BASE LIQUIDACION REDEBAN 2025'!$B$2,IF(AD90="TIPO II",'BASE LIQUIDACION REDEBAN 2025'!$B$3,IF(AD90="TIPO III",'BASE LIQUIDACION REDEBAN 2025'!$B$4,IF(AD90="TIPO IV",'BASE LIQUIDACION REDEBAN 2025'!$B$5,IF(AE90="AEREO",'BASE LIQUIDACION REDEBAN 2025'!$B$6,'BASE LIQUIDACION REDEBAN 2025'!$B$5))))) -> 75096.394 | AJ90: =IF(AD90="TIPO I",'BASE LIQUIDACION REDEBAN 2025'!$B$10,IF(AD90="TIPO II",'BASE LIQUIDACION REDEBAN 2025'!$B$11,IF(AD90="TIPO III",'BASE LIQUIDACION REDEBAN 2025'!$B$12,'BASE LIQUIDACION REDEBAN 2025'!$B$13))) -> 75096.394 | AK90: =AG90*AI90+AH90*AJ90 -> 75096.394
A91: PASTO | B91: =VLOOKUP(A91,'CENTRO DE COSTOS'!A:D,4,FALSE) -> DIEGO FERNANDO HENAO CARDONA | C91: =VLOOKUP(A91,'CENTRO DE COSTOS'!A:D,2,FALSE) -> 0004-0003 | D91: 52378 | E91: TA-25-612281 | F91: FO-25-903325 | G91: 45811 | H91: 45813 | I91: 45811 | J91: 45812 | K91: 45812 | L91: NARIÑO | M91: LA CRUZ | N91: BARRIO CRR CIUDAD DE DIOS LA CRUZ | O91: 79679 | P91: CB CRECIMIENTO - NUEVO | Q91: APERTURA | R91: REDEBAN | S91: UNO A UNO | T91: UNO A UNO | U91: EJECUTADO | V91: 03-06 SE REALIZA LLAMADA AL CLIENTE, SE HABLA CON LA SRA ANA CRISTINA ANGULO ORTIZ SE VALIDA DIRECCIÓN OK, CANAL OK, DISPONIBILIDAD TOTAL, LLAMAR EL DÍA LA INSTALACIÓN PARA CONFIRMAR VISITA, AVISO EXTERIOR ALTURA APROX 3 METROS; TOMACORRIENTE CERCANO: SI; TIENE CABINA DE SEGURIDAD: SI - COMUNICACIÓN POR WPP 04-06 SE REALIZA INSTALACIÓN DE CORRESPONSAL, SE INSTALAN EQUIPOS CON PRUEBAS EXITOSAS, SE CAPACITA Y SE EVALÚA AL CLIENTE, SE INSTALA PUBLICIDAD COMPLETA, CB QUEDA OPERATIVO. USUARIO SOMOS BANCOLOMBIA ACTIVO | W91: PAZ MARTINEZ RICHARD HUMBERTO | X91: SXXZZ079 | Y91: 1169272 | Z91: N/A | AA91: 1217150 | AB91: N/A | AC91: 40 ROLLOS | AD91: TIPO III | AE91: TERRESTRE | AF91: VISITA_TÉCNICA | AG91: 1 | AH91: 0 | AI91: =IF(AD91="TIPO I",'BASE LIQUIDACION REDEBAN 2025'!$B$2,IF(AD91="TIPO II",'BASE LIQUIDACION REDEBAN 2025'!$B$3,IF(AD91="TIPO III",'BASE LIQUIDACION REDEBAN 2025'!$B$4,IF(AD91="TIPO IV",'BASE LIQUIDACION REDEBAN 2025'!$B$5,IF(AE91="AEREO",'BASE LIQUIDACION REDEBAN 2025'!$B$6,'BASE LIQUIDACION REDEBAN 2025'!$B$5))))) -> 275728.78 | AJ91: =IF(AD91="TIPO I",'BASE LIQUIDACION REDEBAN 2025'!$B$10,IF(AD91="TIPO II",'BASE LIQUIDACION REDEBAN 2025'!$B$11,IF(AD91="TIPO III",'BASE LIQUIDACION REDEBAN 2025'!$B$12,'BASE LIQUIDACION REDEBAN 2025'!$B$13))) -> 196536.53 | AK91: =AG91*AI91+AH91*AJ91 -> 275728.78
A92: BOGOTA | B92: =VLOOKUP(A92,'CENTRO DE COSTOS'!A:D,4,FALSE) -> WILLIAM ASDRUBAL ROZO ROZO | C92: =VLOOKUP(A92,'CENTRO DE COSTOS'!A:D,2,FALSE) -> 0004-0004 | D92: 11001 | E92: TA-25-612282 | F92: FO-25-903330 | G92: 45811 | H92: 45813 | I92: 45811 | J92: 45813 | K92: 45813 | L92: CUNDINAMARCA | M92: BOGOTA | N92: BARRIO DANUBIO AZUL BOGOTA 9 | O92: 79678 | P92: CB CRECIMIENTO - NUEVO | Q92: APERTURA | R92: REDEBAN | S92: UNO A UNO | T92: UNO A UNO | U92: EJECUTADO | V92: 3-06-2025 SE REALIZA LLAMADA AL CLIENTE, SE HABLA CON LA SRA JULIETH ANDREA MESA RINCON SE VALIDA DIRECCIÓN OK, CANAL OK, DISPONIBILIDAD TOTAL, LLAMAR EL DÍA DE LA INSTALACIÓN PARA CONFIRMAR VISITA, ALTURA APROX 2 METROS; TOMACORRIENTE CERCANO: SI; TIENE CABINA DE SEGURIDAD: SI // CONTACTO REALIZADO POR WHATSAPP 8:18 a. m. 5/6/2025 SE REALIZA INSTALACIÓN DE CORRESPONSAL, SE INSTALAN EQUIPOS CON PRUEBAS EXITOSAS, SE CAPACITA Y SE EVALÚA AL CLIENTE, SE INSTALA PUBLICIDAD COMPLETA, CB QUEDA OPERATIVO. USUARIO SOMOS BANCOLOMBIA ACTIVO | W92: GOMEZ VEGA DAVID SNEYDER | X92: SXXZZ078 | Y92: 957082 | Z92: N/A | AA92: 1110281 | AB92: N/A | AC92: 40 ROLLOS | AD92: TIPO I | AE92: TERRESTRE | AF92: VISITA_TÉCNICA | AG92: 1 | AH92: 0 | AI92: =IF(AD92="TIPO I",'BASE LIQUIDACION REDEBAN 2025'!$B$2,IF(AD92="TIPO II",'BASE LIQUIDACION REDEBAN 2025'!$B$3,IF(AD92="TIPO III",'BASE LIQUIDACION REDEBAN 2025'!$B$4,IF(AD92="TIPO IV",'BASE LIQUIDACION REDEBAN 2025'!$B$5,IF(AE92="AEREO",'BASE LIQUIDACION REDEBAN 2025'!$B$6,'BASE LIQUIDACION REDEBAN 2025'!$B$5))))) -> 75096.394 | AJ92: =IF(AD92="TIPO I",'BASE LIQUIDACION REDEBAN 2025'!$B$10,IF(AD92="TIPO II",'BASE LIQUIDACION REDEBAN 2025'!$B$11,IF(AD92="TIPO III",'BASE LIQUIDACION REDEBAN 2025'!$B$12,'BASE LIQUIDACION REDEBAN 2025'!$B$13))) -> 75096.394 | AK92: =AG92*AI92+AH92*AJ92 -> 75096.394
A93: VILLAVICENCIO | B93: =VLOOKUP(A93,'CENTRO DE COSTOS'!A:D,4,FALSE) -> KEVIN ALEXIS CORZO BUSTOS | C93: =VLOOKUP(A93,'CENTRO DE COSTOS'!A:D,2,FALSE) -> 0004-0007 | D93: 50001 | E93: TA-25-612285 | F93: FO-25-903332 | G93: 45811 | H93: 45813 | I93: 45811 | J93: 45813 | K93: 45813 | L93: META | M93: VILLAVICENCIO | N93: BARRIO JORDAN VILLAVICENCIO 12 | O93: 79685 | P93: CB CRECIMIENTO - NUEVO | Q93: APERTURA | R93: REDEBAN | S93: UNO A UNO | T93: UNO A UNO | U93: EJECUTADO | V93: 31-05 SE REALIZA COMUNICACION CON LA SRA OLGA LUCIA RODRIGUEZ OCAMPO, SE VALIDA DIRECCIÓN OK, CANAL OK, DISPONIBILIDAD TOTAL, LLAMAR EL DÍA LA INSTALACIÓN PARA CONFIRMAR VISITA, AVISO EXTERIOR ALTURA APROX DONDE EL TECNICO LO VEA CONVENIENTE, METROS; TOMACORRIENTE CERCANO: SI; TIENE CABINA DE SEGURIDAD:SI 5/6/2025 SE REALIZA INSTALACIÓN DE CORRESPONSAL, SE INSTALAN EQUIPOS CON PRUEBAS EXITOSAS, SE CAPACITA Y SE EVALÚA AL CLIENTE, SE INSTALA PUBLICIDAD COMPLETA, CB QUEDA OPERATIVO. USUARIO SOMOS BANCOLOMBIA ACTIVO | W93: CASTRILLON URREA LONDIER LEANDRO | X93: SXXZZ085 | Y93: 923342 | Z93: N/A | AA93: 953591 | AB93: N/A | AC93: 40 ROLLOS | AD93: TIPO I | AE93: TERRESTRE | AF93: VISITA_TÉCNICA | AG93: 1 | AH93: 0 | AI93: =IF(AD93="TIPO I",'BASE LIQUIDACION REDEBAN 2025'!$B$2,IF(AD93="TIPO II",'BASE LIQUIDACION REDEBAN 2025'!$B$3,IF(AD93="TIPO III",'BASE LIQUIDACION REDEBAN 2025'!$B$4,IF(AD93="TIPO IV",'BASE LIQUIDACION REDEBAN 2025'!$B$5,IF(AE93="AEREO",'BASE LIQUIDACION REDEBAN 2025'!$B$6,'BASE LIQUIDACION REDEBAN 2025'!$B$5))))) -> 75096.394 | AJ93: =IF(AD93="TIPO I",'BASE LIQUIDACION REDEBAN 2025'!$B$10,IF(AD93="TIPO II",'BASE LIQUIDACION REDEBAN 2025'!$B$11,IF(AD93="TIPO III",'BASE LIQUIDACION REDEBAN 2025'!$B$12,'BASE LIQUIDACION REDEBAN 2025'!$B$13))) -> 75096.394 | AK93: =AG93*AI93+AH93*AJ93 -> 75096.394
A94: CALI | B94: =VLOOKUP(A94,'CENTRO DE COSTOS'!A:D,4,FALSE) -> DIEGO FERNANDO HENAO CARDONA | C94: =VLOOKUP(A94,'CENTRO DE COSTOS'!A:D,2,FALSE) -> 0004-0003 | D94: 76520 | E94: TA-25-619947 | F94: FO-25-919699 | G94: 45811 | H94: 45813 | I94: 45811 | J94: 45813 | K94: 45813 | L94: VALLE DEL CAUCA | M94: PALMIRA | N94: BARRIO LOS SAUCES PALMIRA | O94: 79681 | P94: CAMBIO DE RAZON SOCIAL | Q94: APERTURA | R94: REDEBAN | S94: UNO A UNO | T94: UNO A UNO | U94: EJECUTADO | V94: 3-06-2025 SE REALIZA LLAMADA AL CLIENTE, SE HABLA CON EL SR BRAYAN ALBADAM VANEGAS SE VALIDA DIRECCIÓN OK, CANAL OK, DISPONIBILIDAD TOTAL, LLAMAR EL DÍA DE LA INSTALACIÓN PARA CONFIRMAR VISITA, PUBLICIDAD OK // CONTACTO REALIZADO POR WHATSAPP 8:25 a. m. 5/6/2025 SE REALIZA INSTALACIÓN DE CORRESPONSAL, SE INSTALAN EQUIPOS CON PRUEBAS EXITOSAS, SE CAPACITA Y SE EVALÚA AL CLIENTE, SE INSTALA PUBLICIDAD COMPLETA, CB QUEDA OPERATIVO. USUARIO SOMOS BANCOLOMBIA ACTIVO | W94: TORRES GARCIA JENDRY JOSE | X94: SXXZZ081 | Y94: 869019 | Z94: N/A | AA94: 549358 | AB94: N/A | AC94: 40 ROLLOS | AD94: TIPO I | AE94: TERRESTRE | AF94: VISITA_TÉCNICA | AG94: 1 | AH94: 0 | AI94: =IF(AD94="TIPO I",'BASE LIQUIDACION REDEBAN 2025'!$B$2,IF(AD94="TIPO II",'BASE LIQUIDACION REDEBAN 2025'!$B$3,IF(AD94="TIPO III",'BASE LIQUIDACION REDEBAN 2025'!$B$4,IF(AD94="TIPO IV",'BASE LIQUIDACION REDEBAN 2025'!$B$5,IF(AE94="AEREO",'BASE LIQUIDACION REDEBAN 2025'!$B$6,'BASE LIQUIDACION REDEBAN 2025'!$B$5))))) -> 75096.394 | AJ94: =IF(AD94="TIPO I",'BASE LIQUIDACION REDEBAN 2025'!$B$10,IF(AD94="TIPO II",'BASE LIQUIDACION REDEBAN 2025'!$B$11,IF(AD94="TIPO III",'BASE LIQUIDACION REDEBAN 2025'!$B$12,'BASE LIQUIDACION REDEBAN 2025'!$B$13))) -> 75096.394 | AK94: =AG94*AI94+AH94*AJ94 -> 75096.394
A95: SINCELEJO | B95: =VLOOKUP(A95,'CENTRO DE COSTOS'!A:D,4,FALSE) -> JOSE MAURICIO HERNANDEZ ROJAS | C95: =VLOOKUP(A95,'CENTRO DE COSTOS'!A:D,2,FALSE) -> 0004-0001 | D95: 70717 | E95: TA-25-619948 | F95: FO-25-919702 | G95: 45811 | H95: 45813 | I95: 45811 | J95: 45813 | K95: 45813 | L95: SUCRE | M95: SAN PEDRO | N95: BARRIO SAN MARTIN SAN PEDRO 2 | O95: 79683 | P95: CB CRECIMIENTO - NUEVO | Q95: APERTURA | R95: REDEBAN | S95: UNO A UNO | T95: UNO A UNO | U95: EJECUTADO | V95: 31-05 SE REALIZA LLAMADA AL CLIENTE, SE HABLA CON LA SRA LUISA FERNANDA BANQUET FUNIELES, SE VALIDA DIRECCIÓN OK, CANAL OK, DISPONIBILIDAD TOTAL, LLAMAR EL DÍA LA INSTALACIÓN PARA CONFIRMAR VISITA, AVISO EXTERIOR ALTURA APROX DONDE EL TECNICO LO VEA CONVENIENTE, METROS; TOMACORRIENTE CERCANO: SI; TIENE CABINA DE SEGURIDAD:SI 5/6/2025 SE REALIZA INSTALACIÓN DE CORRESPONSAL, SE INSTALAN EQUIPOS CON PRUEBAS EXITOSAS, SE CAPACITA Y SE EVALÚA AL CLIENTE, SE INSTALA PUBLICIDAD COMPLETA, CB QUEDA OPERATIVO. USUARIO SOMOS BANCOLOMBIA ACTIVO | W95: CACERES HERNANDEZ ANDRES | X95: SXXZZ083 | Y95: 794606 | Z95: N/A | AA95: 1178939 | AB95: N/A | AC95: 40 ROLLOS | AD95: TIPO II | AE95: TERRESTRE | AF95: VISITA_TÉCNICA | AG95: 1 | AH95: 0 | AI95: =IF(AD95="TIPO I",'BASE LIQUIDACION REDEBAN 2025'!$B$2,IF(AD95="TIPO II",'BASE LIQUIDACION REDEBAN 2025'!$B$3,IF(AD95="TIPO III",'BASE LIQUIDACION REDEBAN 2025'!$B$4,IF(AD95="TIPO IV",'BASE LIQUIDACION REDEBAN 2025'!$B$5,IF(AE95="AEREO",'BASE LIQUIDACION REDEBAN 2025'!$B$6,'BASE LIQUIDACION REDEBAN 2025'!$B$5))))) -> 163813.7 | AJ95: =IF(AD95="TIPO I",'BASE LIQUIDACION REDEBAN 2025'!$B$10,IF(AD95="TIPO II",'BASE LIQUIDACION REDEBAN 2025'!$B$11,IF(AD95="TIPO III",'BASE LIQUIDACION REDEBAN 2025'!$B$12,'BASE LIQUIDACION REDEBAN 2025'!$B$13))) -> 140395.63 | AK95: =AG95*AI95+AH95*AJ95 -> 163813.7
A96: NEIVA | B96: =VLOOKUP(A96,'CENTRO DE COSTOS'!A:D,4,FALSE) -> KEVIN ALEXIS CORZO BUSTOS | C96: =VLOOKUP(A96,'CENTRO DE COSTOS'!A:D,2,FALSE) -> 0004-0007 | D96: 41001 | E96: TA-25-619949 | F96: FO-25-919704 | G96: 45811 | H96: 45813 | I96: 45811 | J96: 45812 | K96: 45812 | L96: HUILA | M96: NEIVA | N96: BARRIO ZONA INDUSTRIAL NEIVA 11 | O96: 79680 | P96: CB CRECIMIENTO - NUEVO | Q96: APERTURA | R96: REDEBAN | S96: UNO A UNO | T96: UNO A UNO | U96: EJECUTADO | V96: 31-05 SE REALIZA LLAMADA AL CLIENTE, SE HABLA CON LA SRA ADRIANA ARIAS CAPERA, SE VALIDA DIRECCIÓN OK, CANAL OK, DISPONIBILIDAD TOTAL, LLAMAR EL DÍA LA INSTALACIÓN PARA CONFIRMAR VISITA, AVISO EXTERIOR ALTURA APROX DONDE EL TECNICO LO VEA CONVENIENTE, METROS; TOMACORRIENTE CERCANO: SI; TIENE CABINA DE SEGURIDAD:SI 4/6/2025 SE REALIZA INSTALACIÓN DE CORRESPONSAL, SE INSTALAN EQUIPOS CON PRUEBAS EXITOSAS, SE CAPACITA Y SE EVALÚA AL CLIENTE, SE INSTALA PUBLICIDAD COMPLETA, CB QUEDA OPERATIVO. USUARIO SOMOS BANCOLOMBIA ACTIVO | W96: DIAZ VARGAS JONATHAN MIGUEL | X96: SXXZZ080 | Y96: 959134 | Z96: N/A | AA96: 534976 | AB96: N/A | AC96: 40 ROLLOS | AD96: TIPO I | AE96: TERRESTRE | AF96: VISITA_TÉCNICA | AG96: 1 | AH96: 0 | AI96: =IF(AD96="TIPO I",'BASE LIQUIDACION REDEBAN 2025'!$B$2,IF(AD96="TIPO II",'BASE LIQUIDACION REDEBAN 2025'!$B$3,IF(AD96="TIPO III",'BASE LIQUIDACION REDEBAN 2025'!$B$4,IF(AD96="TIPO IV",'BASE LIQUIDACION REDEBAN 2025'!$B$5,IF(AE96="AEREO",'BASE LIQUIDACION REDEBAN 2025'!$B$6,'BASE LIQUIDACION REDEBAN 2025'!$B$5))))) -> 75096.394 | AJ96: =IF(AD96="TIPO I",'BASE LIQUIDACION REDEBAN 2025'!$B$10,IF(AD96="TIPO II",'BASE LIQUIDACION REDEBAN 2025'!$B$11,IF(AD96="TIPO III",'BASE LIQUIDACION REDEBAN 2025'!$B$12,'BASE LIQUIDACION REDEBAN 2025'!$B$13))) -> 75096.394 | AK96: =AG96*AI96+AH96*AJ96 -> 75096.394
A97: BOGOTA | B97: =VLOOKUP(A97,'CENTRO DE COSTOS'!A:D,4,FALSE) -> WILLIAM ASDRUBAL ROZO ROZO | C97: =VLOOKUP(A97,'CENTRO DE COSTOS'!A:D,2,FALSE) -> 0004-0004 | D97: 11001 | E97: TA-25-619954 | F97: FO-25-919708 | G97: 45811 | H97: 45813 | I97: 45811 | J97: 45813 | K97: 45813 | L97: CUNDINAMARCA | M97: BOGOTA | N97: BARRIO ALAMOS BOGOTA 11 | O97: 79538 | P97: CAMBIO DE RAZON SOCIAL | Q97: APERTURA | R97: REDEBAN | S97: UNO A UNO | T97: UNO A UNO | U97: EJECUTADO | V97: 31-05 SE REALIZA LLAMADA AL CLIENTE, SE HABLA CON EL SR BRAYAN LEONARDO RIVEROS GRANADOS, SE VALIDA DIRECCIÓN OK, CANAL OK, DISPONIBILIDAD TOTAL, LLAMAR EL DÍA LA INSTALACIÓN PARA CONFIRMAR VISITA, AVISO EXTERIOR ALTURA APROX 2,20, METROS; TOMACORRIENTE CERCANO: SI; TIENE CABINA DE SEGURIDAD:SI 5/6/2025 SE REALIZA INSTALACIÓN DE CORRESPONSAL, SE INSTALAN EQUIPOS CON PRUEBAS EXITOSAS, SE CAPACITA Y SE EVALÚA AL CLIENTE, SE INSTALA PUBLICIDAD COMPLETA, CB QUEDA OPERATIVO. NO SÉ TIENE ACCESO A PÁGINA SOMOS BANCOLOMBIA POR CORREO ERRADO DE CLIENTE, SOLICITA SOPORTE POR WHATSAPP Y LE INDICAN QUE ESTÁ DISPONIBLE EL DÍA MIÉRCOLES DE LA SIGUIENTE SEMANA | W97: MURCIA HERNANDEZ HARVEY IGNACIO | X97: LMUZZ972 | Y97: 1171028 | Z97: N/A | AA97: 1097312 | AB97: N/A | AC97: 40 ROLLOS | AD97: TIPO I | AE97: TERRESTRE | AF97: VISITA_TÉCNICA | AG97: 1 | AH97: 0 | AI97: =IF(AD97="TIPO I",'BASE LIQUIDACION REDEBAN 2025'!$B$2,IF(AD97="TIPO II",'BASE LIQUIDACION REDEBAN 2025'!$B$3,IF(AD97="TIPO III",'BASE LIQUIDACION REDEBAN 2025'!$B$4,IF(AD97="TIPO IV",'BASE LIQUIDACION REDEBAN 2025'!$B$5,IF(AE97="AEREO",'BASE LIQUIDACION REDEBAN 2025'!$B$6,'BASE LIQUIDACION REDEBAN 2025'!$B$5))))) -> 75096.394 | AJ97: =IF(AD97="TIPO I",'BASE LIQUIDACION REDEBAN 2025'!$B$10,IF(AD97="TIPO II",'BASE LIQUIDACION REDEBAN 2025'!$B$11,IF(AD97="TIPO III",'BASE LIQUIDACION REDEBAN 2025'!$B$12,'BASE LIQUIDACION REDEBAN 2025'!$B$13))) -> 75096.394 | AK97: =AG97*AI97+AH97*AJ97 -> 75096.394
... A117: CALI | B117: =VLOOKUP(A117,'CENTRO DE COSTOS'!A:D,4,FALSE) -> DIEGO FERNANDO HENAO CARDONA | C117: =VLOOKUP(A117,'CENTRO DE COSTOS'!A:D,2,FALSE) -> 0004-0003 | D117: 76001 | E117: TA-25-620025 | F117: FO-25-919803 | G117: 45813 | H117: 45817 | I117: 45813 | J117: 45814 | K117: 45814 | L117: VALLE DEL CAUCA | M117: CALI | N117: PTM CALI PUNTO RAJAAM | O117: 79695 | P117: CB CRECIMIENTO ALIANZA - NUEVO | Q117: APERTURA | R117: REDEBAN | S117: AGREGADOR | T117: COMCARD - PTM | U117: EJECUTADO | V117: 05-06 PROGRAMACIÓN REALIZADA POR LA ALIANZA 6/6/2025 SE REALIZA INSTALACIÓN DE CORRESPONSAL, SE INSTALAN EQUIPOS CON PRUEBAS EXITOSAS, SE CAPACITA Y SE EVALÚA AL CLIENTE, SE INSTALA PUBLICIDAD COMPLETA, CB QUEDA OPERATIVO. USUARIO SOMOS BANCOLOMBIA ACTIVO | W117: MONTERO MUESES GIAN CARLO | X117: V1YZZ437 | Y117: 980000 | Z117: N/A | AA117: 905641 | AB117: N/A | AC117: 40 ROLLOS | AD117: TIPO I | AE117: TERRESTRE | AF117: VISITA_TÉCNICA | AG117: 1 | AH117: 0 | AI117: =IF(AD117="TIPO I",'BASE LIQUIDACION REDEBAN 2025'!$B$2,IF(AD117="TIPO II",'BASE LIQUIDACION REDEBAN 2025'!$B$3,IF(AD117="TIPO III",'BASE LIQUIDACION REDEBAN 2025'!$B$4,IF(AD117="TIPO IV",'BASE LIQUIDACION REDEBAN 2025'!$B$5,IF(AE117="AEREO",'BASE LIQUIDACION REDEBAN 2025'!$B$6,'BASE LIQUIDACION REDEBAN 2025'!$B$5))))) -> 75096.394 | AJ117: =IF(AD117="TIPO I",'BASE LIQUIDACION REDEBAN 2025'!$B$10,IF(AD117="TIPO II",'BASE LIQUIDACION REDEBAN 2025'!$B$11,IF(AD117="TIPO III",'BASE LIQUIDACION REDEBAN 2025'!$B$12,'BASE LIQUIDACION REDEBAN 2025'!$B$13))) -> 75096.394 | AK117: =AG117*AI117+AH117*AJ117 -> 75096.394
A118: CALI | B118: =VLOOKUP(A118,'CENTRO DE COSTOS'!A:D,4,FALSE) -> DIEGO FERNANDO HENAO CARDONA | C118: =VLOOKUP(A118,'CENTRO DE COSTOS'!A:D,2,FALSE) -> 0004-0003 | D118: 76001 | E118: TA-25-620027 | F118: FO-25-919810 | G118: 45813 | H118: 45817 | I118: 45813 | J118: 45814 | K118: 45814 | L118: VALLE DEL CAUCA | M118: CALI | N118: PTM CALI SABE SOLUCIONES | O118: 79693 | P118: CB CRECIMIENTO ALIANZA - NUEVO | Q118: APERTURA | R118: REDEBAN | S118: AGREGADOR | T118: COMCARD - PTM | U118: EJECUTADO | V118: 05-06 PROGRAMACIÓN REALIZADA POR LA ALIANZA 6/6/2025 SE REALIZA INSTALACIÓN DE CORRESPONSAL, SE INSTALAN EQUIPOS CON PRUEBAS EXITOSAS, SE CAPACITA Y SE EVALÚA AL CLIENTE, SE INSTALA PUBLICIDAD COMPLETA, CB QUEDA OPERATIVO. USUARIO SOMOS BANCOLOMBIA ACTIVO | W118: MONTERO MUESES GIAN CARLO | X118: V1YZZ435 | Y118: 1235481 | Z118: 1091058 | AA118: 546939-241587317561324755887299 | AB118: N/A | AC118: 40 ROLLOS | AD118: TIPO I | AE118: TERRESTRE | AF118: VISITA_TÉCNICA | AG118: 1 | AH118: 0 | AI118: =IF(AD118="TIPO I",'BASE LIQUIDACION REDEBAN 2025'!$B$2,IF(AD118="TIPO II",'BASE LIQUIDACION REDEBAN 2025'!$B$3,IF(AD118="TIPO III",'BASE LIQUIDACION REDEBAN 2025'!$B$4,IF(AD118="TIPO IV",'BASE LIQUIDACION REDEBAN 2025'!$B$5,IF(AE118="AEREO",'BASE LIQUIDACION REDEBAN 2025'!$B$6,'BASE LIQUIDACION REDEBAN 2025'!$B$5))))) -> 75096.394 | AJ118: =IF(AD118="TIPO I",'BASE LIQUIDACION REDEBAN 2025'!$B$10,IF(AD118="TIPO II",'BASE LIQUIDACION REDEBAN 2025'!$B$11,IF(AD118="TIPO III",'BASE LIQUIDACION REDEBAN 2025'!$B$12,'BASE LIQUIDACION REDEBAN 2025'!$B$13))) -> 75096.394 | AK118: =AG118*AI118+AH118*AJ118 -> 75096.394
A119: CALI | B119: =VLOOKUP(A119,'CENTRO DE COSTOS'!A:D,4,FALSE) -> DIEGO FERNANDO HENAO CARDONA | C119: =VLOOKUP(A119,'CENTRO DE COSTOS'!A:D,2,FALSE) -> 0004-0003 | D119: 76109 | E119: TA-25-620028 | F119: FO-25-919813 | G119: 45813 | H119: 45817 | I119: 45813 | J119: 45817 | K119: 45817 | L119: VALLE DEL CAUCA | M119: BUENAVENTURA | N119: PTM BUENAVENTURA DROGUERIA Y M | O119: 79692 | P119: CB CRECIMIENTO ALIANZA - NUEVO | Q119: APERTURA | R119: REDEBAN | S119: AGREGADOR | T119: COMCARD - PTM | U119: EJECUTADO | V119: 05-06 PROGRAMACIÓN REALIZADA POR LA ALIANZA 06-06 SE REPROGRAMA LA VISITA PARA OTRO DÍA POR TEMAS DE BLOQUEOS INTERMITENTES EN LA VÍA NO HAY GARANTÍA DE UN VIAJE NORMAL DE IDA Y REGRESO 09-06 SE REALIZA INSTALACIÓN DE CORRESPONSAL, SE INSTALAN EQUIPOS CON PRUEBAS EXITOSAS, SE CAPACITA Y SE EVALÚA AL CLIENTE, SE INSTALA PUBLICIDAD COMPLETA, CB QUEDA OPERATIVO. USUARIO SOMOS BANCOLOMBIA ACTIVO | W119: HERRERA MONAR GEOVANNY | X119: V1YZZ434 | Y119: 1216809 | Z119: N/A | AA119: 1145970 | AB119: N/A | AC119: 40 ROLLOS | AD119: TIPO III | AE119: TERRESTRE | AF119: VISITA_TÉCNICA | AG119: 1 | AH119: 0 | AI119: =IF(AD119="TIPO I",'BASE LIQUIDACION REDEBAN 2025'!$B$2,IF(AD119="TIPO II",'BASE LIQUIDACION REDEBAN 2025'!$B$3,IF(AD119="TIPO III",'BASE LIQUIDACION REDEBAN 2025'!$B$4,IF(AD119="TIPO IV",'BASE LIQUIDACION REDEBAN 2025'!$B$5,IF(AE119="AEREO",'BASE LIQUIDACION REDEBAN 2025'!$B$6,'BASE LIQUIDACION REDEBAN 2025'!$B$5))))) -> 275728.78 | AJ119: =IF(AD119="TIPO I",'BASE LIQUIDACION REDEBAN 2025'!$B$10,IF(AD119="TIPO II",'BASE LIQUIDACION REDEBAN 2025'!$B$11,IF(AD119="TIPO III",'BASE LIQUIDACION REDEBAN 2025'!$B$12,'BASE LIQUIDACION REDEBAN 2025'!$B$13))) -> 196536.53 | AK119: =AG119*AI119+AH119*AJ119 -> 275728.78
A120: CALI | B120: =VLOOKUP(A120,'CENTRO DE COSTOS'!A:D,4,FALSE) -> DIEGO FERNANDO HENAO CARDONA | C120: =VLOOKUP(A120,'CENTRO DE COSTOS'!A:D,2,FALSE) -> 0004-0003 | D120: 76130 | E120: TA-25-620029 | F120: FO-25-919817 | G120: 45813 | H120: 45817 | I120: 45813 | J120: 45814 | K120: 45814 | L120: VALLE DEL CAUCA | M120: CANDELARIA | N120: PTM CANDELARIA FINANCELL | O120: 79696 | P120: CB CRECIMIENTO ALIANZA - NUEVO | Q120: APERTURA | R120: REDEBAN | S120: AGREGADOR | T120: COMCARD - PTM | U120: EJECUTADO | V120: 05-06 PROGRAMACIÓN REALIZADA POR LA ALIANZA 6/6/2025 SE REALIZA INSTALACIÓN DE CORRESPONSAL, SE INSTALAN EQUIPOS CON PRUEBAS EXITOSAS, SE CAPACITA Y SE EVALÚA AL CLIENTE, SE INSTALA PUBLICIDAD COMPLETA, CB QUEDA OPERATIVO. USUARIO SOMOS BANCOLOMBIA ACTIVO | W120: TORRES GARCIA JENDRY JOSE | X120: V1YZZ438 | Y120: 929893 | Z120: N/A | AA120: 1145985 | AB120: N/A | AC120: 40 ROLLOS | AD120: TIPO II | AE120: TERRESTRE | AF120: VISITA_TÉCNICA | AG120: 1 | AH120: 0 | AI120: =IF(AD120="TIPO I",'BASE LIQUIDACION REDEBAN 2025'!$B$2,IF(AD120="TIPO II",'BASE LIQUIDACION REDEBAN 2025'!$B$3,IF(AD120="TIPO III",'BASE LIQUIDACION REDEBAN 2025'!$B$4,IF(AD120="TIPO IV",'BASE LIQUIDACION REDEBAN 2025'!$B$5,IF(AE120="AEREO",'BASE LIQUIDACION REDEBAN 2025'!$B$6,'BASE LIQUIDACION REDEBAN 2025'!$B$5))))) -> 163813.7 | AJ120: =IF(AD120="TIPO I",'BASE LIQUIDACION REDEBAN 2025'!$B$10,IF(AD120="TIPO II",'BASE LIQUIDACION REDEBAN 2025'!$B$11,IF(AD120="TIPO III",'BASE LIQUIDACION REDEBAN 2025'!$B$12,'BASE LIQUIDACION REDEBAN 2025'!$B$13))) -> 140395.63 | AK120: =AG120*AI120+AH120*AJ120 -> 163813.7
A121: CALI | B121: =VLOOKUP(A121,'CENTRO DE COSTOS'!A:D,4,FALSE) -> DIEGO FERNANDO HENAO CARDONA | C121: =VLOOKUP(A121,'CENTRO DE COSTOS'!A:D,2,FALSE) -> 0004-0003 | D121: 76892 | E121: TA-25-620031 | F121: FO-25-919821 | G121: 45813 | H121: 45817 | I121: 45813 | J121: 45817 | K121: 45817 | L121: VALLE DEL CAUCA | M121: YUMBO | N121: PTM YUMBO PAPELERIA MILU YUMBO | O121: 79709 | P121: CB CRECIMIENTO ALIANZA - NUEVO | Q121: APERTURA | R121: REDEBAN | S121: AGREGADOR | T121: COMCARD - PTM | U121: EJECUTADO | V121: 05-06 PROGRAMACIÓN REALIZADA POR LA ALIANZA 9/6/2025 SE REALIZA INSTALACIÓN DE CORRESPONSAL, SE INSTALAN EQUIPOS CON PRUEBAS EXITOSAS, SE CAPACITA Y SE EVALÚA AL CLIENTE, SE INSTALA PUBLICIDAD COMPLETA, CB QUEDA OPERATIVO. USUARIO SOMOS BANCOLOMBIA ACTIVO | W121: HERRERA MONAR GEOVANNY | X121: V1YZZ451 | Y121: 1092185 | Z121: N/A | AA121: 903690 | AB121: N/A | AC121: 40 ROLLOS | AD121: TIPO I | AE121: TERRESTRE | AF121: VISITA_TÉCNICA | AG121: 1 | AH121: 0 | AI121: =IF(AD121="TIPO I",'BASE LIQUIDACION REDEBAN 2025'!$B$2,IF(AD121="TIPO II",'BASE LIQUIDACION REDEBAN 2025'!$B$3,IF(AD121="TIPO III",'BASE LIQUIDACION REDEBAN 2025'!$B$4,IF(AD121="TIPO IV",'BASE LIQUIDACION REDEBAN 2025'!$B$5,IF(AE121="AEREO",'BASE LIQUIDACION REDEBAN 2025'!$B$6,'BASE LIQUIDACION REDEBAN 2025'!$B$5))))) -> 75096.394 | AJ121: =IF(AD121="TIPO I",'BASE LIQUIDACION REDEBAN 2025'!$B$10,IF(AD121="TIPO II",'BASE LIQUIDACION REDEBAN 2025'!$B$11,IF(AD121="TIPO III",'BASE LIQUIDACION REDEBAN 2025'!$B$12,'BASE LIQUIDACION REDEBAN 2025'!$B$13))) -> 75096.394 | AK121: =AG121*AI121+AH121*AJ121 -> 75096.394
A122: BOGOTA | B122: =VLOOKUP(A122,'CENTRO DE COSTOS'!A:D,4,FALSE) -> WILLIAM ASDRUBAL ROZO ROZO | C122: =VLOOKUP(A122,'CENTRO DE COSTOS'!A:D,2,FALSE) -> 0004-0004 | D122: 11001 | E122: TA-25-620033 | F122: FO-25-919824 | G122: 45813 | H122: 45817 | I122: 45813 | J122: 45817 | K122: 45817 | L122: CUNDINAMARCA | M122: BOGOTA | N122: PTM BOGOTA DONDE LEO TU SERVIC | O122: 79686 | P122: CB CRECIMIENTO ALIANZA - NUEVO | Q122: APERTURA | R122: REDEBAN | S122: AGREGADOR | T122: COMCARD - PTM | U122: EJECUTADO | V122: 05-06 PROGRAMACIÓN REALIZADA POR LA ALIANZA 9/6/2025 SE REALIZA INSTALACIÓN DE CORRESPONSAL, SE INSTALAN EQUIPOS CON PRUEBAS EXITOSAS, SE CAPACITA Y SE EVALÚA AL CLIENTE, SE INSTALA PUBLICIDAD COMPLETA, CB QUEDA OPERATIVO. USUARIO SOMOS BANCOLOMBIA ACTIVO | W122: GOMEZ VEGA DAVID SNEYDER | X122: V1YZZ428 | Y122: 728799 | Z122: N/A | AA122: 1103032 | AB122: N/A | AC122: 40 ROLLOS | AD122: TIPO I | AE122: TERRESTRE | AF122: VISITA_TÉCNICA | AG122: 1 | AH122: 0 | AI122: =IF(AD122="TIPO I",'BASE LIQUIDACION REDEBAN 2025'!$B$2,IF(AD122="TIPO II",'BASE LIQUIDACION REDEBAN 2025'!$B$3,IF(AD122="TIPO III",'BASE LIQUIDACION REDEBAN 2025'!$B$4,IF(AD122="TIPO IV",'BASE LIQUIDACION REDEBAN 2025'!$B$5,IF(AE122="AEREO",'BASE LIQUIDACION REDEBAN 2025'!$B$6,'BASE LIQUIDACION REDEBAN 2025'!$B$5))))) -> 75096.394 | AJ122: =IF(AD122="TIPO I",'BASE LIQUIDACION REDEBAN 2025'!$B$10,IF(AD122="TIPO II",'BASE LIQUIDACION REDEBAN 2025'!$B$11,IF(AD122="TIPO III",'BASE LIQUIDACION REDEBAN 2025'!$B$12,'BASE LIQUIDACION REDEBAN 2025'!$B$13))) -> 75096.394 | AK122: =AG122*AI122+AH122*AJ122 -> 75096.394
A123: BOGOTA | B123: =VLOOKUP(A123,'CENTRO DE COSTOS'!A:D,4,FALSE) -> WILLIAM ASDRUBAL ROZO ROZO | C123: =VLOOKUP(A123,'CENTRO DE COSTOS'!A:D,2,FALSE) -> 0004-0004 | D123: 11001 | E123: TA-25-620034 | F123: FO-25-919827 | G123: 45813 | H123: 45817 | I123: 45813 | J123: 45814 | K123: 45814 | L123: CUNDINAMARCA | M123: BOGOTA | N123: PTM BOGOTA LIZZVAN S | O123: 79687 | P123: CB CRECIMIENTO ALIANZA - NUEVO | Q123: APERTURA | R123: REDEBAN | S123: AGREGADOR | T123: COMCARD - PTM | U123: EJECUTADO | V123: 05-06 PROGRAMACIÓN REALIZADA POR LA ALIANZA 6/6/2025 SE REALIZA INSTALACIÓN DE CORRESPONSAL, SE INSTALAN EQUIPOS CON PRUEBAS EXITOSAS, SE CAPACITA Y SE EVALÚA AL CLIENTE, SE INSTALA PUBLICIDAD COMPLETA, CB QUEDA OPERATIVO. USUARIO SOMOS BANCOLOMBIA ACTIVO | W123: SOTO LONDOÑO FREDY ALEXANDER | X123: V1YZZ429 | Y123: 783184 | Z123: N/A | AA123: 1114506 | AB123: N/A | AC123: 40 ROLLOS | AD123: TIPO I | AE123: TERRESTRE | AF123: VISITA_TÉCNICA | AG123: 1 | AH123: 0 | AI123: =IF(AD123="TIPO I",'BASE LIQUIDACION REDEBAN 2025'!$B$2,IF(AD123="TIPO II",'BASE LIQUIDACION REDEBAN 2025'!$B$3,IF(AD123="TIPO III",'BASE LIQUIDACION REDEBAN 2025'!$B$4,IF(AD123="TIPO IV",'BASE LIQUIDACION REDEBAN 2025'!$B$5,IF(AE123="AEREO",'BASE LIQUIDACION REDEBAN 2025'!$B$6,'BASE LIQUIDACION REDEBAN 2025'!$B$5))))) -> 75096.394 | AJ123: =IF(AD123="TIPO I",'BASE LIQUIDACION REDEBAN 2025'!$B$10,IF(AD123="TIPO II",'BASE LIQUIDACION REDEBAN 2025'!$B$11,IF(AD123="TIPO III",'BASE LIQUIDACION REDEBAN 2025'!$B$12,'BASE LIQUIDACION REDEBAN 2025'!$B$13))) -> 75096.394 | AK123: =AG123*AI123+AH123*AJ123 -> 75096.394
