Workbook
Name ACTIVIDAD: [1]Hoja2!$P$2:$P$30
Name Clientes: [2]Clientes!$A$2:$A$100
Name COORDINADOR: [1]Hoja2!$D$2:$D$30
Name Coordinadores: [3]Coordinadores!$A$2:$A$1000
Name DOCUMENTADOR: [1]Hoja2!$A$2:$A$30
Name ES: [1]Hoja2!$K$2:$K$30
Name ESS: [1]Hoja2!$K$2:$K$30
Name Estado: [2]Formulas!$K$2:$K$5000
Name ESTADOACTIVIDAD: [1]Hoja2!$M$2:$M$30
Name ESTADOSCIERRES: '[4]lista desplegable'!$CX$1:$DA$1
Name Facturacion: '[5]Listas desplegables'!$AO$1:$AR$1
Name solicitudes: '[5]Listas desplegables'!$U$1:$AF$1
Name Tecnicos: [2]Tecnicos!$A$2:$A$1000

Sheet RESUMEN
A1: LÍNEA COMUNICACIONES S.A.S | F1: FACTURACIÓN CORRESPONSALES BANCARIOS TIQUIETES AÉREOS
A2: FACTURACIÓN VISITAS FALLIDAS CORRESPONSALES BANCARIOS | F2: =A3 -> JULIO 2025
A3: JULIO 2025
F4: CONCEPTOS | G4: TRAYECTOS | H4: TOTAL | I4: % ADMINISTRACIÓN | J4: TOTAL
A5: CONCEPTOS | B5: CANT | D5: TOTAL | F5: ORDEN DE CAMBIO CB 72634 | G5: SINCELEJO-MAJAGUAL-SINCELEJO | H5: 300000 | I5: =H5*0.12 -> 36000 | J5: =H5+I5 -> 336000
A6: =CONCATENATE("CIERRES NO EXITOSOS ",A3) -> CIERRES NO EXITOSOS JULIO 2025 | B6: =COUNTA(CIERRES!A:A)-1 -> 162 | D6: =CIERRES!AD164 -> 16375995 | I6: =H6*0.12 -> 0 | J6: =H6+I6 -> 0
A7: TIQUETES | B7: 0 | D7: =J10 -> 336000 | I7: =H7*0.12 -> 0 | J7: =H7+I7 -> 0
A8: SUBTOTAL | D8: =SUM(D6:D7) -> 16711995
A9: IVA | D9: =D8*0.19 -> 3175279
A10: TOTAL | D10: =SUM(D8:D9) -> 19887274 | F10: TOTAL | H10: =SUM(H5:H7) -> 300000 | I10: =SUM(I5:I7) -> 36000 | J10: =SUM(J5:J7) -> 336000

Sheet BASE DE LIQUIDACION 2025
A1: CIERRE CB - VISITAS FALLIDAS O CIERRES NO EXITOSOS TARIFAS 2024 | D1: Incremento 2025
A2: Tipificación | B2: Descripción | C2: Tarifa | D2: 0.052
A3: Tipo I | B3: Metropolitano | C3: =42357*(1+$D$2) -> 44559.564
A4: Tipo II | B4: Hasta 3 horas | C4: =127767*(1+$D$2) -> 134410.88
A5: Tipo III | B5: De 3 a 5 horas | C5: =211886*(1+$D$2) -> 222904.07
A6: Tipo IV | B6: Más de 5 horas | C6: =441834*(1+$D$2) -> 464809.37
A7: Trayecto Especial | B7: No incluye valor del Tiquete | C7: Valor de actividad Tipo IV + Valor tiquete aéreo (o fluvial) + 12% administración)
A9: Gestión telefonica | B9: =36031*(1+$D$2) -> 37904.612

Sheet Tabla Dinámica
A3: COORDINADOR | B3: CENTRO DE COSTOS LÍNEACOM | C3: % | D3: Suma de VALOR TOTAL2 | E3: NOMBRE CC
A4: DIEGO FERNANDO HENAO CARDONA | B4: 0004-0002 | C4: 0.020593793 | D4: 337243.85 | E4: =VLOOKUP(B4,'CENTRO DE COSTOS'!B:C,2,0) -> Redeban Eje Cafetero (Pereira)
B5: 0004-0003 | C5: 0.12905852 | D5: 2113461.7 | E5: =VLOOKUP(B5,'CENTRO DE COSTOS'!B:C,2,0) -> Redeban Suroccidente (Cali)
A6: JOSE MAURICIO HERNANDEZ ROJAS | B6: 0004-0001 | C6: 0.11050911 | D6: 1809696.7 | E6: =VLOOKUP(B6,'CENTRO DE COSTOS'!B:C,2,0) -> Redeban Costa (Barranqullla)
A7: JUAN SEBASTIÁN RÍOS CASTRILLÓN | B7: 0004-0005 | C7: 0.24273546 | D7: 3975034.6 | E7: =VLOOKUP(B7,'CENTRO DE COSTOS'!B:C,2,0) -> Redeban Noroccidente (Medellín)
A8: KEVIN ALEXIS CORZO BUSTOS | B8: 0004-0007 | C8: 0.22036304 | D8: 3608664 | E8: =VLOOKUP(B8,'CENTRO DE COSTOS'!B:C,2,0) -> Redeban Oriente (Otros)
A9: MIGUEL JULIÁN HERNÁNDEZ GUARÍN | B9: 0004-0008 | C9: 0.08513693 | D9: 1394201.9 | E9: =VLOOKUP(B9,'CENTRO DE COSTOS'!B:C,2,0) -> Redeban Santander
A10: WILLIAM ASDRUBAL ROZO ROZO | B10: 0004-0004 | C10: 0.19160314 | D10: 3137692 | E10: =VLOOKUP(B10,'CENTRO DE COSTOS'!B:C,2,0) -> Redeban Centro ( Bogotá)
A11: Total general | C11: 1 | D11: 16375995

Sheet CIERRES
A1: CIUDAD SEDE | B1: COORDINADOR | C1: CENTRO DE COSTOS LÍNEACOM | D1: CÓDIGO DANE | E1: TA/CODIGO ACTIVIDAD | F1: CODIGO CB | G1: ACTIVIDAD | H1: DEPARTAMENTO | I1: CIUDAD | J1: NOMBRE DEL CB | K1: RED | L1: FO | M1: FECHA ASIGNACION A LINEA COMUNICACIONES | N1: FECHA DEL CIERRE DEL TICKET (DD/MM/AAAA) | O1: ACOMETIDA | P1: SOLICITUD | Q1: DESCRIPCIÓN | R1: FORMATO | S1: CADENA | T1: ESTADO | U1: CAUSAL ESTADO | V1: OBSERVACION | W1: FORMA DE ATENCIÓN | X1: TERMINAL | Y1: TIPIFICACION | Z1: TIPO DE TRAYECTO | AA1: NOMBRE DEL TECNICO | AB1: DIAS DE VISITA | AC1: VALOR ACTIVIDAD | AD1: VALOR TOTAL
A2: BOGOTA | B2: =VLOOKUP(A2,'CENTRO DE COSTOS'!A:D,4,FALSE) -> WILLIAM ASDRUBAL ROZO ROZO | C2: =VLOOKUP(A2,'CENTRO DE COSTOS'!A:C,2,FALSE) -> 0004-0004 | D2: 25736 | E2: TA-25-809615 | F2: 68733 | G2: ORDEN DE CAMBIO | H2: CUNDINAMARCA | I2: SESQUILE | J2: BARRIO CENTRO SESQUILE SESQUIL | K2: REDEBAN | L2: FO-25-1148318 | M2: 45836.333 | N2: 45839.467 | P2: CIERRE | Q2: RECUPERACION DE EQUIPOS | R2: CB UNO A UNO | S2: CB UNO A UNO | T2: ILOCALIZADO | U2: CB CERRADO - DESOCUPADO | V2: 01-07-2025 SE REALIZA DESPLAZAMIENTO A DIRECCIÓN DE COMERCIO, SE ENCUENTRA COMERCIO CERRADO, NO SE TIENE RESPUESTA A NÚMERO DE CONTACTO, SE REALIZA VALIDACIÓN CON COMERCIO UBICADO EN EL MISMO INMUEBLE Y NO CONOCEN A LA CLIENTE. | W2: VISITA_TÉCNICA | X2: 0 | Y2: TIPO II | Z2: TERRESTRE | AA2: MURCIA HERNANDEZ HARVEY IGNACIO | AB2: 1 | AC2: =IF(AND(W2="SOPORTE_TELEFÓNICO",OR(U2="SIN CONTACTO CON EL CB",U2="NÚMEROS DE CONTACTO ERRADOS")),0,IF(W2="SOPORTE_TELEFÓNICO",'BASE DE LIQUIDACION 2025'!$B$9,IF(Y2="TIPO I",'BASE DE LIQUIDACION 2025'!$C$3,IF(Y2="TIPO II",'BASE DE LIQUIDACION 2025'!$C$4,IF(Y2="TIPO III",'BASE DE LIQUIDACION 2025'!$C$5,'BASE DE LIQUIDACION 2025'!$C$6))))) -> 134410.88 | AD2: =IF(W2="SOPORTE_TELEFÓNICO",AC2,CIERRES!AB2*CIERRES!AC2) -> 134410.88
A3: PASTO | B3: =VLOOKUP(A3,'CENTRO DE COSTOS'!A:D,4,FALSE) -> DIEGO FERNANDO HENAO CARDONA | C3: =VLOOKUP(A3,'CENTRO DE COSTOS'!A:C,2,FALSE) -> 0004-0003 | D3: 52001 | E3: TA-25-809579 | F3: 76203 | G3: ORDEN DE CAMBIO | H3: NARIÑO | I3: PASTO | J3: BARRIO CENTRO PASTO 36 | K3: REDEBAN | L3: FO-25-1148186 | M3: 45836.333 | N3: 45839.552 | P3: CIERRE | Q3: CIERRE | R3: CB UNO A UNO | S3: CB UNO A UNO | T3: ILOCALIZADO | U3: CB CERRADO - DESOCUPADO | V3: 01-07-2025 SE LLEGÓ AL COMERCIO PERO ESTÁ CERRADO EL LOCAL, SE INTENTÓ COMUNICACIÓN TELEFÓNICA, PERO EL TELÉFONO ESTÁ ERRADO, HAY OTRO NÚMERO DE CELULAR PERO ESTÁ FUERA DE SERVICIO. | W3: VISITA_TÉCNICA | X3: 0 | Y3: TIPO I | Z3: TERRESTRE | AA3: GUERRERO RAMIREZ OSCAR DARIO | AB3: 1 | AC3: =IF(AND(W3="SOPORTE_TELEFÓNICO",OR(U3="SIN CONTACTO CON EL CB",U3="NÚMEROS DE CONTACTO ERRADOS")),0,IF(W3="SOPORTE_TELEFÓNICO",'BASE DE LIQUIDACION 2025'!$B$9,IF(Y3="TIPO I",'BASE DE LIQUIDACION 2025'!$C$3,IF(Y3="TIPO II",'BASE DE LIQUIDACION 2025'!$C$4,IF(Y3="TIPO III",'BASE DE LIQUIDACION 2025'!$C$5,'BASE DE LIQUIDACION 2025'!$C$6))))) -> 44559.564 | AD3: =IF(W3="SOPORTE_TELEFÓNICO",AC3,CIERRES!AB3*CIERRES!AC3) -> 44559.564
A4: CALI | B4: =VLOOKUP(A4,'CENTRO DE COSTOS'!A:D,4,FALSE) -> DIEGO FERNANDO HENAO CARDONA | C4: =VLOOKUP(A4,'CENTRO DE COSTOS'!A:C,2,FALSE) -> 0004-0003 | D4: 19698 | E4: TA-25-809571 | F4: 61823 | G4: ORDEN DE CAMBIO | H4: CAUCA | I4: SANTANDER DE QUILICHAO | J4: BARRIO GENERAL SANTANDER SANTA | K4: REDEBAN | L4: FO-25-1148154 | M4: 45836.333 | N4: 45839.572 | P4: CIERRE | Q4: CIERRE | R4: CB UNO A UNO | S4: CB UNO A UNO | T4: ILOCALIZADO | U4: SIN CONTACTO CON EL CB | V4: 01-07-2025 SE LLEGO AL SITIO Y NO SE ENCONTRÓ EL CB, SE INDAGO EN EL SECTOR E IMFORMARON QUE LA CLIENTE SE FUE PARA ESPAÑA Y QUE ENTREGARON EL LOCAL, EL NÚMERO DE CONTACTO SE VA A BUZON, NO CONTESTA LOS MENSAJES SE WHATSAPP | W4: VISITA_TÉCNICA | X4: 0 | Y4: TIPO II | Z4: TERRESTRE | AA4: PAREDES CASTILLO DIEGO | AB4: 1 | AC4: =IF(AND(W4="SOPORTE_TELEFÓNICO",OR(U4="SIN CONTACTO CON EL CB",U4="NÚMEROS DE CONTACTO ERRADOS")),0,IF(W4="SOPORTE_TELEFÓNICO",'BASE DE LIQUIDACION 2025'!$B$9,IF(Y4="TIPO I",'BASE DE LIQUIDACION 2025'!$C$3,IF(Y4="TIPO II",'BASE DE LIQUIDACION 2025'!$C$4,IF(Y4="TIPO III",'BASE DE LIQUIDACION 2025'!$C$5,'BASE DE LIQUIDACION 2025'!$C$6))))) -> 134410.88 | AD4: =IF(W4="SOPORTE_TELEFÓNICO",AC4,CIERRES!AB4*CIERRES!AC4) -> 134410.88
A5: MONTERIA | B5: =VLOOKUP(A5,'CENTRO DE COSTOS'!A:D,4,FALSE) -> JOSE MAURICIO HERNANDEZ ROJAS | C5: =VLOOKUP(A5,'CENTRO DE COSTOS'!A:C,2,FALSE) -> 0004-0001 | D5: 23001 | E5: TA-25-809568 | F5: 52374 | G5: ORDEN DE CAMBIO | H5: CORDOBA | I5: MONTERIA | J5: BARRIO PANAMA MONTERIA 1 | K5: REDEBAN | L5: FO-25-1148140 | M5: 45836.333 | N5: 45839.592 | P5: CIERRE | Q5: CIERRE | R5: CB UNO A UNO | S5: CB UNO A UNO | T5: NO_EXITOSO | U5: CB NO ENTREGA EQUIPO | V5: 01-07-2025 SE LLEGÓ A LA DIRECCIÓN Y SE ENCUENTRA EL LOCAL CERRADO, SE HACE VALIDACIÓN CON LOS VECINOS Y NO DAN RAZÓN DEL CLIENTE, SE INTENTÓ COMUNICACIÓN VÍA TELEFÓNICA Y EL CLIENTE INFORMA QUE NO SE ENCUENTRA EN EL LOCAL PORQUE HACE MUCHO TIEMPO LO ENTREGÓ QUE TIENE LOS EQUIPOS EN LA CASA DE UNA PRIMA PERO EN EL MOMENTO SE ENCUENTRA CERRADA Y NO HAY QUIÉN ENTREGUE LOS EQUIPOS, SE LE INDICA QUE DEBE LLAMAR A LA LÍNEA DE ATENCIÓN CUÁNDO TENGA LA DISPONIBILIDAD Y LOS EQUIPOS PARA PODER REALIZAR EL CIERRE DE CB. | W5: VISITA_TÉCNICA | X5: 0 | Y5: TIPO I | Z5: TERRESTRE | AA5: CALDERA SALCEDO CARLOS JULIO | AB5: 1 | AC5: =IF(AND(W5="SOPORTE_TELEFÓNICO",OR(U5="SIN CONTACTO CON EL CB",U5="NÚMEROS DE CONTACTO ERRADOS")),0,IF(W5="SOPORTE_TELEFÓNICO",'BASE DE LIQUIDACION 2025'!$B$9,IF(Y5="TIPO I",'BASE DE LIQUIDACION 2025'!$C$3,IF(Y5="TIPO II",'BASE DE LIQUIDACION 2025'!$C$4,IF(Y5="TIPO III",'BASE DE LIQUIDACION 2025'!$C$5,'BASE DE LIQUIDACION 2025'!$C$6))))) -> 44559.564 | AD5: =IF(W5="SOPORTE_TELEFÓNICO",AC5,CIERRES!AB5*CIERRES!AC5) -> 44559.564
A6: SANTA MARTA | B6: =VLOOKUP(A6,'CENTRO DE COSTOS'!A:D,4,FALSE) -> JOSE MAURICIO HERNANDEZ ROJAS | C6: =VLOOKUP(A6,'CENTRO DE COSTOS'!A:C,2,FALSE) -> 0004-0001 | D6: 47707 | E6: TA-25-809559 | F6: 11452 | G6: ORDEN DE CAMBIO | H6: MAGDALENA | I6: SANTA ANA | J6: SANTA ANA MAGDALENA | K6: REDEBAN | L6: FO-25-1148107 | M6: 45836.333 | N6: 45839.618 | P6: CIERRE | Q6: CIERRE | R6: CB UNO A UNO | S6: CB UNO A UNO | T6: NO_EXITOSO | U6: CB NO ENTREGA EQUIPO | V6: 01-07-2025 SE REALIZA VISITA POR RECUPERACIÓN DE EQUIPO ATIENDE EL SR LUIS GABRIEL YEPES INDICANDO QUE NO ENTREGARA LOS EQUIPOS YA QUE EL BANCO LE ADEUDA LAS COMISIONES DE LOS MESES MARZO ,ABRIL Y MAYO , SE COMUNICA CON EL BANCO Y LE INDICAN QUE LAS COMISIONES SE LAS CONSIGNARON A UNA CUENTA DEL BANCO AGRARIO Y EL CLIENTE INDICA QUE EL NO TIENE CUENTA CON ESE BANCO POR TAL MOTIVO SE NIEGA A ENTREGAR EQUIPOS HASTA QUE EL BANCO LE PAGE LOS MESES DE COMISIONES | W6: VISITA_TÉCNICA | X6: 0 | Y6: TIPO IV | Z6: TERRESTRE | AA6: MAESTRE MENGUAL EDGAR ENRIQUE | AB6: 1 | AC6: =IF(AND(W6="SOPORTE_TELEFÓNICO",OR(U6="SIN CONTACTO CON EL CB",U6="NÚMEROS DE CONTACTO ERRADOS")),0,IF(W6="SOPORTE_TELEFÓNICO",'BASE DE LIQUIDACION 2025'!$B$9,IF(Y6="TIPO I",'BASE DE LIQUIDACION 2025'!$C$3,IF(Y6="TIPO II",'BASE DE LIQUIDACION 2025'!$C$4,IF(Y6="TIPO III",'BASE DE LIQUIDACION 2025'!$C$5,'BASE DE LIQUIDACION 2025'!$C$6))))) -> 464809.37 | AD6: =IF(W6="SOPORTE_TELEFÓNICO",AC6,CIERRES!AB6*CIERRES!AC6) -> 464809.37
A7: VILLAVICENCIO | B7: =VLOOKUP(A7,'CENTRO DE COSTOS'!A:D,4,FALSE) -> KEVIN ALEXIS CORZO BUSTOS | C7: =VLOOKUP(A7,'CENTRO DE COSTOS'!A:C,2,FALSE) -> 0004-0007 | D7: 95015 | E7: TA-25-809563 | F7: 46949 | G7: ORDEN DE CAMBIO | H7: GUAVIARE | I7: CALAMAR | J7: BARRIO LA PAZ CALAMAR | K7: REDEBAN | L7: FO-25-1148127 | M7: 45836.333 | N7: 45840.344 | P7: CIERRE | Q7: CIERRE | R7: CB UNO A UNO | S7: CB UNO A UNO | T7: NO_EXITOSO | U7: CB NO ENTREGA EQUIPO | V7: 01-07-2025 SE REALIZA CONTACTO TELEFONICO CON EL CLIENTE EL CUAL INDICA QUE NO SE ENCUENTRA EN EL PAÍS Y QUE VA COMUNICARSE CON EL BANCO PARA CONOCIMIENTO DEL CIERRE | W7: SOPORTE_TELEFÓNICO | X7: 0 | Y7: TIPO IV ESPECIAL | Z7: AEREO | AA7: PEDREROS CONTRERAS MICHAEL STEVENS | AB7: 0 | AC7: =IF(AND(W7="SOPORTE_TELEFÓNICO",OR(U7="SIN CONTACTO CON EL CB",U7="NÚMEROS DE CONTACTO ERRADOS")),0,IF(W7="SOPORTE_TELEFÓNICO",'BASE DE LIQUIDACION 2025'!$B$9,IF(Y7="TIPO I",'BASE DE LIQUIDACION 2025'!$C$3,IF(Y7="TIPO II",'BASE DE LIQUIDACION 2025'!$C$4,IF(Y7="TIPO III",'BASE DE LIQUIDACION 2025'!$C$5,'BASE DE LIQUIDACION 2025'!$C$6))))) -> 37904.612 | AD7: =IF(W7="SOPORTE_TELEFÓNICO",AC7,CIERRES!AB7*CIERRES!AC7) -> 37904.612
A8: PEREIRA | B8: =VLOOKUP(A8,'CENTRO DE COSTOS'!A:D,4,FALSE) -> DIEGO FERNANDO HENAO CARDONA | C8: =VLOOKUP(A8,'CENTRO DE COSTOS'!A:C,2,FALSE) -> 0004-0002 | D8: 76147 | E8: TA-25-799609 | F8: 71044 | G8: ORDEN DE CAMBIO | H8: VALLE DEL CAUCA | I8: CARTAGO | J8: DISTRICOL DROG. SALUD Y VIDA | K8: REDEBAN | L8: FO-25-1130568 | M8: 45832.599 | N8: 45840.395 | P8: CIERRE | Q8: CIERRE | R8: AGREGADOR | S8: DISTRICOL | T8: NO_EXITOSO | U8: CB NO ENTREGA EQUIPO | V8: 02-07-2025 EN COMUNICACIÓN CON ASESOR DE DISTRICOL INFORMA QUE CLIENTE ENTREGO EQUIPOS DIRECTAMENTE EN OFICINAS DE DISTRICOL | W8: SOPORTE_TELEFÓNICO | X8: 0 | Y8: TIPO I | Z8: TERRESTRE | AA8: LOAIZA LOPEZ JHON FREDDY | AB8: 0 | AC8: =IF(AND(W8="SOPORTE_TELEFÓNICO",OR(U8="SIN CONTACTO CON EL CB",U8="NÚMEROS DE CONTACTO ERRADOS")),0,IF(W8="SOPORTE_TELEFÓNICO",'BASE DE LIQUIDACION 2025'!$B$9,IF(Y8="TIPO I",'BASE DE LIQUIDACION 2025'!$C$3,IF(Y8="TIPO II",'BASE DE LIQUIDACION 2025'!$C$4,IF(Y8="TIPO III",'BASE DE LIQUIDACION 2025'!$C$5,'BASE DE LIQUIDACION 2025'!$C$6))))) -> 37904.612 | AD8: =IF(W8="SOPORTE_TELEFÓNICO",AC8,CIERRES!AB8*CIERRES!AC8) -> 37904.612
A9: MONTERIA | B9: =VLOOKUP(A9,'CENTRO DE COSTOS'!A:D,4,FALSE) -> JOSE MAURICIO HERNANDEZ ROJAS | C9: =VLOOKUP(A9,'CENTRO DE COSTOS'!A:C,2,FALSE) -> 0004-0001 | D9: 23417 | E9: TA-25-809572 | F9: 67036 | G9: ORDEN DE CAMBIO | H9: CORDOBA | I9: LORICA | J9: CALLE CORREGIMIENTO LAS FLORES | K9: REDEBAN | L9: FO-25-1148159 | M9: 45836.333 | N9: 45840.517 | P9: CIERRE | Q9: CIERRE | R9: CB UNO A UNO | S9: CB UNO A UNO | T9: NO_EXITOSO | U9: CB NO ENTREGA EQUIPO | V9: 02-07-2025 NO SÉ REALIZA CIERRE, POR QUÉ CLIENTE INFORMA QUE ESTÁ EN PROCESO DE SOLICITUD DE TRASLADO PARA REACTIVAR EL SERVICIO, NO PERMITEN EL CIERRE | W9: VISITA_TÉCNICA | X9: 6Z0HZ993 | Y9: TIPO II | Z9: TERRESTRE | AA9: COGOLLO ROSSO CAMILO ANDRES | AB9: 1 | AC9: =IF(AND(W9="SOPORTE_TELEFÓNICO",OR(U9="SIN CONTACTO CON EL CB",U9="NÚMEROS DE CONTACTO ERRADOS")),0,IF(W9="SOPORTE_TELEFÓNICO",'BASE DE LIQUIDACION 2025'!$B$9,IF(Y9="TIPO I",'BASE DE LIQUIDACION 2025'!$C$3,IF(Y9="TIPO II",'BASE DE LIQUIDACION 2025'!$C$4,IF(Y9="TIPO III",'BASE DE LIQUIDACION 2025'!$C$5,'BASE DE LIQUIDACION 2025'!$C$6))))) -> 134410.88 | AD9: =IF(W9="SOPORTE_TELEFÓNICO",AC9,CIERRES!AB9*CIERRES!AC9) -> 134410.88
A10: MEDELLIN | B10: =VLOOKUP(A10,'CENTRO DE COSTOS'!A:D,4,FALSE) -> JUAN SEBASTIÁN RÍOS CASTRILLÓN | C10: =VLOOKUP(A10,'CENTRO DE COSTOS'!A:C,2,FALSE) -> 0004-0005 | D10: 5591 | E10: TA-25-809614 | F10: 57196 | G10: ORDEN DE CAMBIO | H10: ANTIOQUIA | I10: PUERTO TRIUNFO | J10: BARRIO CORREGIMIENTO DORADAL PÚERTO TRIUNFO | K10: REDEBAN | L10: FO-25-1148316 | M10: 45836.333 | N10: 45841.508 | P10: CIERRE | Q10: RECUPERACION DE EQUIPOS | R10: CB UNO A UNO | S10: CB UNO A UNO | T10: NO_EXITOSO | U10: CB NO ENTREGA EQUIPO | V10: 03-07-2025 SE LLEGA A LA DIRECCIÓN Y NO SE ENCONTRÓ CORRESPONSAL Y ADICIONAL ESTABA CERRADO, SE REALIZA GESTIÓN TELEFÓNICA Y PERSONA QUE ATIENDE INFORMA QUE LOS EQUIPOS NO ESTÁN EN DORADAL QUE AGENDEN OTRA VISITA PARA ACORDAR DIRECCIÓN DE RECOGIDA | W10: VISITA_TÉCNICA | X10: 0 | Y10: TIPO IV | Z10: TERRESTRE | AA10: BARRIENTOS HERNANDEZ CRISTIAN HORACIO | AB10: 1 | AC10: =IF(AND(W10="SOPORTE_TELEFÓNICO",OR(U10="SIN CONTACTO CON EL CB",U10="NÚMEROS DE CONTACTO ERRADOS")),0,IF(W10="SOPORTE_TELEFÓNICO",'BASE DE LIQUIDACION 2025'!$B$9,IF(Y10="TIPO I",'BASE DE LIQUIDACION 2025'!$C$3,IF(Y10="TIPO II",'BASE DE LIQUIDACION 2025'!$C$4,IF(Y10="TIPO III",'BASE DE LIQUIDACION 2025'!$C$5,'BASE DE LIQUIDACION 2025'!$C$6))))) -> 464809.37 | AD10: =IF(W10="SOPORTE_TELEFÓNICO",AC10,CIERRES!AB10*CIERRES!AC10) -> 464809.37
A11: BOGOTA | B11: =VLOOKUP(A11,'CENTRO DE COSTOS'!A:D,4,FALSE) -> WILLIAM ASDRUBAL ROZO ROZO | C11: =VLOOKUP(A11,'CENTRO DE COSTOS'!A:C,2,FALSE) -> 0004-0004 | D11: 25885 | E11: TA-25-809582 | F11: 78439 | G11: ORDEN DE CAMBIO | H11: CUNDINAMARCA | I11: YACOPI | J11: BARRIO CENTRO YACOPI 5 | K11: REDEBAN | L11: FO-25-1148196 | M11: 45836.333 | N11: 45842.466 | P11: CIERRE | Q11: CIERRE | R11: CB UNO A UNO | S11: CB UNO A UNO | T11: NO_EXITOSO | U11: CB NO ENTREGA EQUIPO | V11: 04-07-2025 SE LLEGA A SITIO SE ENCUENTRA CERRADO EL PUNTO, SE LLAMA AL CLIENTE # DE CONTACTO MARIA PAULA BELTRAN COTRINA 3227475455, LO CUAL INDICA NO ENTREGAR EQUIPOS NI HACER PROCEDIMIENTO DE RETIRO YA QUE LLEVA UN PROCESO VÍA TELEFÓNICA POR UN TEMA DE PAGO DE HONORARIOS CON LA PARTE COMERCIAL DEL COMERCIO. | W11: VISITA_TÉCNICA | X11: 0 | Y11: TIPO IV | Z11: TERRESTRE | AA11: INFANTE SIERRA MANUEL FERNANDO | AB11: 1 | AC11: =IF(AND(W11="SOPORTE_TELEFÓNICO",OR(U11="SIN CONTACTO CON EL CB",U11="NÚMEROS DE CONTACTO ERRADOS")),0,IF(W11="SOPORTE_TELEFÓNICO",'BASE DE LIQUIDACION 2025'!$B$9,IF(Y11="TIPO I",'BASE DE LIQUIDACION 2025'!$C$3,IF(Y11="TIPO II",'BASE DE LIQUIDACION 2025'!$C$4,IF(Y11="TIPO III",'BASE DE LIQUIDACION 2025'!$C$5,'BASE DE LIQUIDACION 2025'!$C$6))))) -> 464809.37 | AD11: =IF(W11="SOPORTE_TELEFÓNICO",AC11,CIERRES!AB11*CIERRES!AC11) -> 464809.37
A12: CALI | B12: =VLOOKUP(A12,'CENTRO DE COSTOS'!A:D,4,FALSE) -> DIEGO FERNANDO HENAO CARDONA | C12: =VLOOKUP(A12,'CENTRO DE COSTOS'!A:C,2,FALSE) -> 0004-0003 | D12: 19256 | E12: TA-25-809608 | F12: 32966 | G12: ORDEN DE CAMBIO | H12: CAUCA | I12: EL TAMBO | J12: BARRIO CENTRO EL TAMBO 1 | K12: REDEBAN | L12: FO-25-1148287 | M12: 45836.333 | N12: 45842.545 | P12: CIERRE | Q12: RECUPERACION DE EQUIPOS | R12: CB UNO A UNO | S12: CB UNO A UNO | T12: NO_EXITOSO | U12: CB NO ENTREGA EQUIPO | V12: 04-07-2025 SE REALIZA LLAMADA AL CLIENTE, E INDICA QUE ESTA POR FUERA DE LA CIUDAD, PARA PODER RECOJER LOS EQUIPOS DEL CIERRE, POR VENCIMIENTO DE LA ACTIVIDAD , SE CIERRA Y SE LE INDICA AL CLIENTE UNA VEZ RETORNE LLAMAR A LA LINEA PARA PODER VOLVER A PROGRAMAR EL CIERRE, | W12: SOPORTE_TELEFÓNICO | X12: 0 | Y12: TIPO III | Z12: TERRESTRE | AA12: HENAO CARDONA DIEGO FERNANDO | AB12: 0 | AC12: =IF(AND(W12="SOPORTE_TELEFÓNICO",OR(U12="SIN CONTACTO CON EL CB",U12="NÚMEROS DE CONTACTO ERRADOS")),0,IF(W12="SOPORTE_TELEFÓNICO",'BASE DE LIQUIDACION 2025'!$B$9,IF(Y12="TIPO I",'BASE DE LIQUIDACION 2025'!$C$3,IF(Y12="TIPO II",'BASE DE LIQUIDACION 2025'!$C$4,IF(Y12="TIPO III",'BASE DE LIQUIDACION 2025'!$C$5,'BASE DE LIQUIDACION 2025'!$C$6))))) -> 37904.612 | AD12: =IF(W12="SOPORTE_TELEFÓNICO",AC12,CIERRES!AB12*CIERRES!AC12) -> 37904.612
A13: BOGOTA | B13: =VLOOKUP(A13,'CENTRO DE COSTOS'!A:D,4,FALSE) -> WILLIAM ASDRUBAL ROZO ROZO | C13: =VLOOKUP(A13,'CENTRO DE COSTOS'!A:C,2,FALSE) -> 0004-0004 | D13: 25126 | E13: TA-25-809576 | F13: 69256 | G13: ORDEN DE CAMBIO | H13: CUNDINAMARCA | I13: CAJICA | J13: CHUNTAME CAJICA 3 | K13: REDEBAN | L13: FO-25-1182209 | M13: 45836.333 | N13: 45842.562 | P13: CIERRE | Q13: CIERRE | R13: CB UNO A UNO | S13: CB UNO A UNO | T13: NO_EXITOSO | U13: CB NO ENTREGA EQUIPO | V13: 04-07-2025 SE REALIZA VISITA AL COMERCIO PARA EJECUTAR CIERRE DE CB BANCOLOMBIA PERO AL LLEGAR AL PUNTO SE ENCUENTRA CERRADO, SE ESTABLECE COMUNICACIÓN CON LA CLIENTE QUIEN INFORMA QUE NO PUEDE ENTREGAR LOS EQUIPOS DEL CIERRE NO TIENE EL TIEMPO, QUE ELLA MUEVAMENTE SE CONTACTA CON BANCOLOMBIA PARA CUADRA VISTA NUEVAMENTE. | W13: VISITA_TÉCNICA | X13: 0 | Y13: TIPO II | Z13: TERRESTRE | AA13: CORTES VELANDIA MIGUEL ANGEL | AB13: 2 | AC13: =IF(AND(W13="SOPORTE_TELEFÓNICO",OR(U13="SIN CONTACTO CON EL CB",U13="NÚMEROS DE CONTACTO ERRADOS")),0,IF(W13="SOPORTE_TELEFÓNICO",'BASE DE LIQUIDACION 2025'!$B$9,IF(Y13="TIPO I",'BASE DE LIQUIDACION 2025'!$C$3,IF(Y13="TIPO II",'BASE DE LIQUIDACION 2025'!$C$4,IF(Y13="TIPO III",'BASE DE LIQUIDACION 2025'!$C$5,'BASE DE LIQUIDACION 2025'!$C$6))))) -> 134410.88 | AD13: =IF(W13="SOPORTE_TELEFÓNICO",AC13,CIERRES!AB13*CIERRES!AC13) -> 268821.77
A14: TUNJA | B14: =VLOOKUP(A14,'CENTRO DE COSTOS'!A:D,4,FALSE) -> MIGUEL JULIÁN HERNÁNDEZ GUARÍN | C14: =VLOOKUP(A14,'CENTRO DE COSTOS'!A:C,2,FALSE) -> 0004-0008 | D14: 15238 | E14: TA-25-833858 | F14: 71876 | G14: ORDEN DE CAMBIO | H14: BOYACA | I14: DUITAMA | J14: BOYACA DUITAMA 2 | K14: REDEBAN | L14: FO-25-1182463 | M14: 45842.333 | N14: 45842.591 | P14: CIERRE | Q14: CIERRE | R14: CB UNO A UNO | S14: CB UNO A UNO | T14: NO_EXITOSO | U14: CB NO ENTREGA EQUIPO | V14: 04-07-2025 EN COMUNICACIÓN CON LA LÍNEA 3212895583 EL SEÑOR HECTOR ALFONSO MONROY CUCUNUBA INFORMA QUE NO ENTREGARÁ EQUIPOS YA QUE NO FUE NOTIFICADO, INFORMA QUE SOLICITO UN TRASLADO DEL SERVICIO Y NO UNA SOLICITUD DE CIERRE, INFORMA QUE SE COMUNICARÁ CON ASESOR COMERCIAL Y CON EL BANCO PARA MAYOR EXPLICACIÓN Y PARA ACTIVACIÓN DEL SERVICIO. SE LE INFORMA TAMBIÉN QUE SE PUEDE COMUNICAR A LA LÍNEA 018000953344 PARA MAYOR INFORMACIÓN. SIN VOLUNTAD DE ENTREGA SE CIERRA ORDEN. | W14: SOPORTE_TELEFÓNICO | X14: 0 | Y14: TIPO II | Z14: TERRESTRE | AA14: HERRERA GARZON JEYSON STEVENT | AB14: 0 | AC14: =IF(AND(W14="SOPORTE_TELEFÓNICO",OR(U14="SIN CONTACTO CON EL CB",U14="NÚMEROS DE CONTACTO ERRADOS")),0,IF(W14="SOPORTE_TELEFÓNICO",'BASE DE LIQUIDACION 2025'!$B$9,IF(Y14="TIPO I",'BASE DE LIQUIDACION 2025'!$C$3,IF(Y14="TIPO II",'BASE DE LIQUIDACION 2025'!$C$4,IF(Y14="TIPO III",'BASE DE LIQUIDACION 2025'!$C$5,'BASE DE LIQUIDACION 2025'!$C$6))))) -> 37904.612 | AD14: =IF(W14="SOPORTE_TELEFÓNICO",AC14,CIERRES!AB14*CIERRES!AC14) -> 37904.612
A15: IBAGUE | B15: =VLOOKUP(A15,'CENTRO DE COSTOS'!A:D,4,FALSE) -> KEVIN ALEXIS CORZO BUSTOS | C15: =VLOOKUP(A15,'CENTRO DE COSTOS'!A:C,2,FALSE) -> 0004-0007 | D15: 73001 | E15: TA-25-833789 | F15: 48235 | G15: ORDEN DE CAMBIO | H15: TOLIMA | I15: IBAGUE | J15: DISTRICOL MIL SOLUTIONS | K15: REDEBAN | L15: FO-25-1182234 | M15: 45842.333 | N15: 45842.686 | P15: CIERRE | Q15: CIERRE | R15: AGREGADOR | S15: DISTRICOL | T15: ILOCALIZADO | U15: CB CERRADO - DESOCUPADO | V15: 04-07-2025 SE VISITA DIRECCIÓN INDICADA DE CB EVIDENCIA QUE YA NO ESTÁ , SE REALIZA CONSULTA CON VECINOS DESCONOCEN UBICACIÓN INTENTA CONTACTAR TELEFÓNICAMENTE # 3124979196-3203596257SIN RESPUESTA | W15: VISITA_TÉCNICA | X15: 0 | Y15: TIPO I | Z15: TERRESTRE | AA15: GUTIERREZ CAMILO ANDRES | AB15: 1 | AC15: =IF(AND(W15="SOPORTE_TELEFÓNICO",OR(U15="SIN CONTACTO CON EL CB",U15="NÚMEROS DE CONTACTO ERRADOS")),0,IF(W15="SOPORTE_TELEFÓNICO",'BASE DE LIQUIDACION 2025'!$B$9,IF(Y15="TIPO I",'BASE DE LIQUIDACION 2025'!$C$3,IF(Y15="TIPO II",'BASE DE LIQUIDACION 2025'!$C$4,IF(Y15="TIPO III",'BASE DE LIQUIDACION 2025'!$C$5,'BASE DE LIQUIDACION 2025'!$C$6))))) -> 44559.564 | AD15: =IF(W15="SOPORTE_TELEFÓNICO",AC15,CIERRES!AB15*CIERRES!AC15) -> 44559.564
A16: CALI | B16: =VLOOKUP(A16,'CENTRO DE COSTOS'!A:D,4,FALSE) -> DIEGO FERNANDO HENAO CARDONA | C16: =VLOOKUP(A16,'CENTRO DE COSTOS'!A:C,2,FALSE) -> 0004-0003 | D16: 19001 | E16: TA-25-833849 | F16: 43981 | G16: ORDEN DE CAMBIO | H16: CAUCA | I16: POPAYAN | J16: BARRIO CAMPO BELLO POPAYAN | K16: REDEBAN | L16: FO-25-1182431 | M16: 45842.333 | N16: 45843.378 | P16: CIERRE | Q16: CIERRE | R16: CB UNO A UNO | S16: CB UNO A UNO | T16: NO_EXITOSO | U16: CB NO ENTREGA EQUIPO | V16: 05-07-2025 SE HABLA CON LA SEÑORA LUZ QUIEN INDICA QUE ESTA EN ESPERA DE UNA INDICACION PARA VALIDAR SI SE CONTINUA CON EL SERVICIO, SOLICITA DAR UNA ESPERA Y YA CUANDO SE DEFINA TODO ELLA SE COMUNICA SI ES NECESARIO. | W16: SOPORTE_TELEFÓNICO | X16: 0 | Y16: TIPO III | Z16: TERRESTRE | AA16: HENAO CARDONA DIEGO FERNANDO | AB16: 0 | AC16: =IF(AND(W16="SOPORTE_TELEFÓNICO",OR(U16="SIN CONTACTO CON EL CB",U16="NÚMEROS DE CONTACTO ERRADOS")),0,IF(W16="SOPORTE_TELEFÓNICO",'BASE DE LIQUIDACION 2025'!$B$9,IF(Y16="TIPO I",'BASE DE LIQUIDACION 2025'!$C$3,IF(Y16="TIPO II",'BASE DE LIQUIDACION 2025'!$C$4,IF(Y16="TIPO III",'BASE DE LIQUIDACION 2025'!$C$5,'BASE DE LIQUIDACION 2025'!$C$6))))) -> 37904.612 | AD16: =IF(W16="SOPORTE_TELEFÓNICO",AC16,CIERRES!AB16*CIERRES!AC16) -> 37904.612
A17: VILLAVICENCIO | B17: =VLOOKUP(A17,'CENTRO DE COSTOS'!A:D,4,FALSE) -> KEVIN ALEXIS CORZO BUSTOS | C17: =VLOOKUP(A17,'CENTRO DE COSTOS'!A:C,2,FALSE) -> 0004-0007 | D17: 50001 | E17: TA-25-833860 | F17: 78305 | G17: ORDEN DE CAMBIO | H17: META | I17: VILLAVICENCIO | J17: BARRIO VILLA DEL RIO VILLAVICENCIO 1 | K17: REDEBAN | L17: FO-25-1182468 | M17: 45842.333 | N17: 45843.446 | P17: CIERRE | Q17: CIERRE | R17: CB UNO A UNO | S17: CB UNO A UNO | T17: ILOCALIZADO | U17: CB CERRADO - DESOCUPADO | V17: 05-07-2025 SE REALIZA VISITA A CB COMERCIO CERRADO NO ES POSIBLE COMUNICACIÓN 3124822757 | W17: VISITA_TÉCNICA | X17: 0 | Y17: TIPO I | Z17: TERRESTRE | AA17: CASTRILLON URREA LONDIER LEANDRO | AB17: 1 | AC17: =IF(AND(W17="SOPORTE_TELEFÓNICO",OR(U17="SIN CONTACTO CON EL CB",U17="NÚMEROS DE CONTACTO ERRADOS")),0,IF(W17="SOPORTE_TELEFÓNICO",'BASE DE LIQUIDACION 2025'!$B$9,IF(Y17="TIPO I",'BASE DE LIQUIDACION 2025'!$C$3,IF(Y17="TIPO II",'BASE DE LIQUIDACION 2025'!$C$4,IF(Y17="TIPO III",'BASE DE LIQUIDACION 2025'!$C$5,'BASE DE LIQUIDACION 2025'!$C$6))))) -> 44559.564 | AD17: =IF(W17="SOPORTE_TELEFÓNICO",AC17,CIERRES!AB17*CIERRES!AC17) -> 44559.564
A18: PEREIRA | B18: =VLOOKUP(A18,'CENTRO DE COSTOS'!A:D,4,FALSE) -> DIEGO FERNANDO HENAO CARDONA | C18: =VLOOKUP(A18,'CENTRO DE COSTOS'!A:C,2,FALSE) -> 0004-0002 | D18: 66001 | E18: TA-25-809574 | F18: 68391 | G18: ORDEN DE CAMBIO | H18: RISARALDA | I18: PEREIRA | J18: VEREDA TRIBUNA | K18: REDEBAN | L18: FO-25-1148163 | M18: 45836.333 | N18: 45843.601 | P18: CIERRE | Q18: CIERRE | R18: CB UNO A UNO | S18: CB UNO A UNO | T18: NO_EXITOSO | U18: CB NO ENTREGA EQUIPO | V18: 05-07-2025 SE VISITA COMERCIO CLIENTE INFORMA QUE DESEA CONTINUAR CON CB SE ENCUENTRA PENDIENTE REAPERTURA DE COMERCIO POR REMODELACIÓN PENDIENTE COMUNICACIÓN CON LA ENTIDAD | W18: VISITA_TÉCNICA | X18: AALFZ736 | Y18: TIPO I | Z18: TERRESTRE | AA18: LOAIZA LOPEZ JHON FREDDY | AB18: 1 | AC18: =IF(AND(W18="SOPORTE_TELEFÓNICO",OR(U18="SIN CONTACTO CON EL CB",U18="NÚMEROS DE CONTACTO ERRADOS")),0,IF(W18="SOPORTE_TELEFÓNICO",'BASE DE LIQUIDACION 2025'!$B$9,IF(Y18="TIPO I",'BASE DE LIQUIDACION 2025'!$C$3,IF(Y18="TIPO II",'BASE DE LIQUIDACION 2025'!$C$4,IF(Y18="TIPO III",'BASE DE LIQUIDACION 2025'!$C$5,'BASE DE LIQUIDACION 2025'!$C$6))))) -> 44559.564 | AD18: =IF(W18="SOPORTE_TELEFÓNICO",AC18,CIERRES!AB18*CIERRES!AC18) -> 44559.564
A19: BARRANQUILLA | B19: =VLOOKUP(A19,'CENTRO DE COSTOS'!A:D,4,FALSE) -> JOSE MAURICIO HERNANDEZ ROJAS | C19: =VLOOKUP(A19,'CENTRO DE COSTOS'!A:C,2,FALSE) -> 0004-0001 | D19: 8758 | E19: TA-25-809577 | F19: 71519 | G19: ORDEN DE CAMBIO | H19: ATLANTICO | I19: SOLEDAD | J19: BARRIO ALMENDROS SOLEDAD 5 | K19: REDEBAN | L19: FO-25-1148174 | M19: 45836.333 | N19: 45844.377 | P19: CIERRE | Q19: CIERRE | R19: CB UNO A UNO | S19: CB UNO A UNO | T19: ILOCALIZADO | U19: CB CERRADO - DESOCUPADO | V19: 06-07-2025 SE REALIZA VISITA AL COMERCIO PARA REALIZAR EL CIERRE DEL CORRESPONSAL BANCOLOMBIA PERO NO ES POSIBLE TRATO COMUNICACION CON EL NÚMERO DADO PERO NO CONTESTAN | W19: VISITA_TÉCNICA | X19: A30KZ086 | Y19: TIPO I | Z19: TERRESTRE | AA19: PEÑALOZA GUTIERREZ RAFAEL GUSTAVO | AB19: 1 | AC19: =IF(AND(W19="SOPORTE_TELEFÓNICO",OR(U19="SIN CONTACTO CON EL CB",U19="NÚMEROS DE CONTACTO ERRADOS")),0,IF(W19="SOPORTE_TELEFÓNICO",'BASE DE LIQUIDACION 2025'!$B$9,IF(Y19="TIPO I",'BASE DE LIQUIDACION 2025'!$C$3,IF(Y19="TIPO II",'BASE DE LIQUIDACION 2025'!$C$4,IF(Y19="TIPO III",'BASE DE LIQUIDACION 2025'!$C$5,'BASE DE LIQUIDACION 2025'!$C$6))))) -> 44559.564 | AD19: =IF(W19="SOPORTE_TELEFÓNICO",AC19,CIERRES!AB19*CIERRES!AC19) -> 44559.564
A20: CALI | B20: =VLOOKUP(A20,'CENTRO DE COSTOS'!A:D,4,FALSE) -> DIEGO FERNANDO HENAO CARDONA | C20: =VLOOKUP(A20,'CENTRO DE COSTOS'!A:C,2,FALSE) -> 0004-0003 | D20: 19001 | E20: TA-25-809567 | F20: 49086 | G20: ORDEN DE CAMBIO | H20: CAUCA | I20: POPAYAN | J20: BARRIO SANTA ELENA POPAYAN 1 | K20: REDEBAN | L20: FO-25-1148135 | M20: 45836.333 | N20: 45845.205 | P20: CIERRE | Q20: CIERRE | R20: CB UNO A UNO | S20: CB UNO A UNO | T20: ILOCALIZADO | U20: CB CERRADO - DESOCUPADO | V20: 06-07-2025 SE LLEGA AL COMERCIO SE ENCUENTRA CERRADO | W20: VISITA_TÉCNICA | X20: BA0O0050 | Y20: TIPO III | Z20: TERRESTRE | AA20: GIMBUEL LASSO LUIS GERMAN | AB20: 1 | AC20: =IF(AND(W20="SOPORTE_TELEFÓNICO",OR(U20="SIN CONTACTO CON EL CB",U20="NÚMEROS DE CONTACTO ERRADOS")),0,IF(W20="SOPORTE_TELEFÓNICO",'BASE DE LIQUIDACION 2025'!$B$9,IF(Y20="TIPO I",'BASE DE LIQUIDACION 2025'!$C$3,IF(Y20="TIPO II",'BASE DE LIQUIDACION 2025'!$C$4,IF(Y20="TIPO III",'BASE DE LIQUIDACION 2025'!$C$5,'BASE DE LIQUIDACION 2025'!$C$6))))) -> 222904.07 | AD20: =IF(W20="SOPORTE_TELEFÓNICO",AC20,CIERRES!AB20*CIERRES!AC20) -> 222904.07
A21: IBAGUE | B21: =VLOOKUP(A21,'CENTRO DE COSTOS'!A:D,4,FALSE) -> KEVIN ALEXIS CORZO BUSTOS | C21: =VLOOKUP(A21,'CENTRO DE COSTOS'!A:C,2,FALSE) -> 0004-0007 | D21: 73001 | E21: TA-25-835647 | F21: 69181 | G21: ORDEN DE CAMBIO | H21: TOLIMA | I21: IBAGUE | J21: BARRIO PORTALES DEL NORTE IBAG | K21: REDEBAN | L21: FO-25-1186228 | M21: 45842.69 | N21: 45845.47 | P21: CIERRE | Q21: RECUPERACION DE EQUIPOS | R21: CB UNO A UNO | S21: CB UNO A UNO | T21: ILOCALIZADO | U21: CB CERRADO - DESOCUPADO | V21: 07-07-2025 SE LLEGA A LA DIRECCIÓN Y NO EXISTE CB CON ESE CU. SE LLAMA A LA SEÑORA DIANA REYES, AL NÚMERO 3185539461, PARA HACER CONTACTO, LAS PRIMERAS LLAMADAS SUENA EL TELÉFONO Y A LA CUARTA APAGAN EL NÚMERO. ME INDICAN QUE VIVE EN EL SEGUNDO PISO, GOLPEÓ LA PUERTA PERO NADIE RESPONDE. | W21: VISITA_TÉCNICA | X21: A103Z587 | Y21: TIPO I | Z21: TERRESTRE | AA21: VARGAS HERRERA JHON JAIRO | AB21: 1 | AC21: =IF(AND(W21="SOPORTE_TELEFÓNICO",OR(U21="SIN CONTACTO CON EL CB",U21="NÚMEROS DE CONTACTO ERRADOS")),0,IF(W21="SOPORTE_TELEFÓNICO",'BASE DE LIQUIDACION 2025'!$B$9,IF(Y21="TIPO I",'BASE DE LIQUIDACION 2025'!$C$3,IF(Y21="TIPO II",'BASE DE LIQUIDACION 2025'!$C$4,IF(Y21="TIPO III",'BASE DE LIQUIDACION 2025'!$C$5,'BASE DE LIQUIDACION 2025'!$C$6))))) -> 44559.564 | AD21: =IF(W21="SOPORTE_TELEFÓNICO",AC21,CIERRES!AB21*CIERRES!AC21) -> 44559.564
A22: BOGOTA | B22: =VLOOKUP(A22,'CENTRO DE COSTOS'!A:D,4,FALSE) -> WILLIAM ASDRUBAL ROZO ROZO | C22: =VLOOKUP(A22,'CENTRO DE COSTOS'!A:C,2,FALSE) -> 0004-0004 | D22: 11001 | E22: TA-25-833864 | F22: 22764 | G22: ORDEN DE CAMBIO | H22: CUNDINAMARCA | I22: BOGOTA | J22: EXXON BARRIO UNICENTRO BOGOTÁ | K22: REDEBAN | L22: FO-25-1182484 | M22: 45842.333 | N22: 45845.587 | P22: CIERRE | Q22: RECUPERACION DE EQUIPOS | R22: CB UNO A UNO | S22: CB UNO A UNO | T22: ILOCALIZADO | U22: CB CERRADO - DESOCUPADO | V22: 07-07-2025 SE REALIZA VISITA AL COMERCIO PARA EJECUTAR CIERRE DE CB BANCOLOMBIA PERO AL LLEGAR AL PUNTO YA NO EXITE EL CB INFORMA LA SRA. LINA AZA | W22: VISITA_TÉCNICA | X22: 0 | Y22: TIPO I | Z22: TERRESTRE | AA22: CORTES VELANDIA MIGUEL ANGEL | AB22: 1 | AC22: =IF(AND(W22="SOPORTE_TELEFÓNICO",OR(U22="SIN CONTACTO CON EL CB",U22="NÚMEROS DE CONTACTO ERRADOS")),0,IF(W22="SOPORTE_TELEFÓNICO",'BASE DE LIQUIDACION 2025'!$B$9,IF(Y22="TIPO I",'BASE DE LIQUIDACION 2025'!$C$3,IF(Y22="TIPO II",'BASE DE LIQUIDACION 2025'!$C$4,IF(Y22="TIPO III",'BASE DE LIQUIDACION 2025'!$C$5,'BASE DE LIQUIDACION 2025'!$C$6))))) -> 44559.564 | AD22: =IF(W22="SOPORTE_TELEFÓNICO",AC22,CIERRES!AB22*CIERRES!AC22) -> 44559.564
A23: NEIVA | B23: =VLOOKUP(A23,'CENTRO DE COSTOS'!A:D,4,FALSE) -> KEVIN ALEXIS CORZO BUSTOS | C23: =VLOOKUP(A23,'CENTRO DE COSTOS'!A:C,2,FALSE) -> 0004-0007 | D23: 18001 | E23: TA-25-833859 | F23: 78426 | G23: ORDEN DE CAMBIO | H23: CAQUETA | I23: FLORENCIA | J23: BARRIO LA ESTRELLA FLORENCIA | K23: REDEBAN | L23: FO-25-1182466 | M23: 45842.333 | N23: 45845.612 | P23: CIERRE | Q23: CIERRE | R23: CB UNO A UNO | S23: CB UNO A UNO | T23: SOLICITUD_CANCELADA | U23: CANCELADO POR LA ENTIDAD | V23: 07-07-2025 SE LLEGA AL COMERCIO Y CLIENTE MANIFIESTA QUE NO HA SOLICITADO EL CIERRE, INDICA QUE ESTUVO TRABAJANDO HASTA EL DÍA JUEVES Y QUE NO ENTIENDE POR SE LO ESTÁN ENVIANDO A CERRAR, MANIFIESTA LLAMAR A LA LÍNEA BANCOLOMBIA Y SOLICITAR LA ACTIVACIÓN NUEVAMENTE. | W23: VISITA_TÉCNICA | X23: V10ZZ346 | Y23: TIPO IV | Z23: TERRESTRE | AA23: BERMUDEZ SANCHEZ JOSE NEYBER | AB23: 1 | AC23: =IF(AND(W23="SOPORTE_TELEFÓNICO",OR(U23="SIN CONTACTO CON EL CB",U23="NÚMEROS DE CONTACTO ERRADOS")),0,IF(W23="SOPORTE_TELEFÓNICO",'BASE DE LIQUIDACION 2025'!$B$9,IF(Y23="TIPO I",'BASE DE LIQUIDACION 2025'!$C$3,IF(Y23="TIPO II",'BASE DE LIQUIDACION 2025'!$C$4,IF(Y23="TIPO III",'BASE DE LIQUIDACION 2025'!$C$5,'BASE DE LIQUIDACION 2025'!$C$6))))) -> 464809.37 | AD23: =IF(W23="SOPORTE_TELEFÓNICO",AC23,CIERRES!AB23*CIERRES!AC23) -> 464809.37
A24: BOGOTA | B24: =VLOOKUP(A24,'CENTRO DE COSTOS'!A:D,4,FALSE) -> WILLIAM ASDRUBAL ROZO ROZO | C24: =VLOOKUP(A24,'CENTRO DE COSTOS'!A:C,2,FALSE) -> 0004-0004 | D24: 11001 | E24: TA-25-833828 | F24: 54832 | G24: ORDEN DE CAMBIO | H24: CUNDINAMARCA | I24: BOGOTA | J24: AUTOSERVICIO BOSQUES DEL VIRRE | K24: REDEBAN | L24: FO-25-1182377 | M24: 45842.333 | N24: 45845.644 | P24: CIERRE | Q24: CIERRE | R24: RETAIL | S24: CONTIGO | T24: ILOCALIZADO | U24: CB CERRADO - DESOCUPADO | V24: 07-07-2025 SE REALIZA VISITA A DIRECCIÓN DE COMERCIO, SE ENCUENTRA COMERCIO CERRADO Y CON OTRA RAZÓN SOCIAL, NO SÉ TIENE RESPUESTA TELEFÓNICA EN NÚMERO DE CONTACTO RELACIONADO EN LA TA. | W24: VISITA_TÉCNICA | X24: 0 | Y24: TIPO I | Z24: TERRESTRE | AA24: MURCIA HERNANDEZ HARVEY IGNACIO | AB24: 1 | AC24: =IF(AND(W24="SOPORTE_TELEFÓNICO",OR(U24="SIN CONTACTO CON EL CB",U24="NÚMEROS DE CONTACTO ERRADOS")),0,IF(W24="SOPORTE_TELEFÓNICO",'BASE DE LIQUIDACION 2025'!$B$9,IF(Y24="TIPO I",'BASE DE LIQUIDACION 2025'!$C$3,IF(Y24="TIPO II",'BASE DE LIQUIDACION 2025'!$C$4,IF(Y24="TIPO III",'BASE DE LIQUIDACION 2025'!$C$5,'BASE DE LIQUIDACION 2025'!$C$6))))) -> 44559.564 | AD24: =IF(W24="SOPORTE_TELEFÓNICO",AC24,CIERRES!AB24*CIERRES!AC24) -> 44559.564
A25: MEDELLIN | B25: =VLOOKUP(A25,'CENTRO DE COSTOS'!A:D,4,FALSE) -> JUAN SEBASTIÁN RÍOS CASTRILLÓN | C25: =VLOOKUP(A25,'CENTRO DE COSTOS'!A:C,2,FALSE) -> 0004-0005 | D25: 5313 | E25: TA-25-835642 | F25: 62141 | G25: ORDEN DE CAMBIO | H25: ANTIOQUIA | I25: GRANADA | J25: BARRIO SECTOR LA ASUNCION GRAN | K25: REDEBAN | L25: FO-25-1186215 | M25: 45842.69 | N25: 45846.401 | P25: CIERRE | Q25: CIERRE | R25: CB UNO A UNO | S25: CB UNO A UNO | T25: ILOCALIZADO | U25: CB CERRADO - DESOCUPADO | V25: 07-07-2025 SE LLEGA A LA DIRECCIÓN SUMINISTRADA POR LA APLICACIÓN SYTEX Y NO SE ENCONTRÓ EL COMERCIO, SE REALIZA GESTIÓN TELEFÓNICA Y USUARIA INFORMA QUE NO SE ENCUENTRA EN LA DIRECCIÓN Y NO HAY NADIE QUE ATIENDA YA QUE NO SE LES NOTIFICO DE LA VISITA | W25: VISITA_TÉCNICA | X25: 0 | Y25: TIPO II | Z25: TERRESTRE | AA25: BARRIENTOS HERNANDEZ CRISTIAN HORACIO | AB25: 1 | AC25: =IF(AND(W25="SOPORTE_TELEFÓNICO",OR(U25="SIN CONTACTO CON EL CB",U25="NÚMEROS DE CONTACTO ERRADOS")),0,IF(W25="SOPORTE_TELEFÓNICO",'BASE DE LIQUIDACION 2025'!$B$9,IF(Y25="TIPO I",'BASE DE LIQUIDACION 2025'!$C$3,IF(Y25="TIPO II",'BASE DE LIQUIDACION 2025'!$C$4,IF(Y25="TIPO III",'BASE DE LIQUIDACION 2025'!$C$5,'BASE DE LIQUIDACION 2025'!$C$6))))) -> 134410.88 | AD25: =IF(W25="SOPORTE_TELEFÓNICO",AC25,CIERRES!AB25*CIERRES!AC25) -> 134410.88
A26: CALI | B26: =VLOOKUP(A26,'CENTRO DE COSTOS'!A:D,4,FALSE) -> DIEGO FERNANDO HENAO CARDONA | C26: =VLOOKUP(A26,'CENTRO DE COSTOS'!A:C,2,FALSE) -> 0004-0003 | D26: 76001 | E26: TA-25-835646 | F26: 34502 | G26: ORDEN DE CAMBIO | H26: VALLE DEL CAUCA | I26: CALI | J26: BARRIO SAN LUIS CALI 1 | K26: REDEBAN | L26: FO-25-1191209 | M26: 45842.69 | N26: 45846.416 | P26: CIERRE | Q26: RECUPERACION DE EQUIPOS | R26: CB UNO A UNO | S26: CB UNO A UNO | T26: EJECUTADO_EXITOSO | U26: CIERRE EXITOSO | V26: 07-07-2025 SE RECOGEN EQUIPOS DATÁFONO,LECTOR, PINPAD Y HUD EN DIRECCIÓN DIFERENTE CLIENTE NO FIRMA | W26: VISITA_TÉCNICA | X26: 9A002807 | Y26: TIPO I | Z26: TERRESTRE | AA26: CUERO RUIZ JHONNY | AB26: 1 | AC26: =IF(AND(W26="SOPORTE_TELEFÓNICO",OR(U26="SIN CONTACTO CON EL CB",U26="NÚMEROS DE CONTACTO ERRADOS")),0,IF(W26="SOPORTE_TELEFÓNICO",'BASE DE LIQUIDACION 2025'!$B$9,IF(Y26="TIPO I",'BASE DE LIQUIDACION 2025'!$C$3,IF(Y26="TIPO II",'BASE DE LIQUIDACION 2025'!$C$4,IF(Y26="TIPO III",'BASE DE LIQUIDACION 2025'!$C$5,'BASE DE LIQUIDACION 2025'!$C$6))))) -> 44559.564 | AD26: =IF(W26="SOPORTE_TELEFÓNICO",AC26,CIERRES!AB26*CIERRES!AC26) -> 44559.564
A27: CALI | B27: =VLOOKUP(A27,'CENTRO DE COSTOS'!A:D,4,FALSE) -> DIEGO FERNANDO HENAO CARDONA | C27: =VLOOKUP(A27,'CENTRO DE COSTOS'!A:C,2,FALSE) -> 0004-0003 | D27: 76130 | E27: TA-25-833775 | F27: 47874 | G27: ORDEN DE CAMBIO | H27: VALLE DEL CAUCA | I27: CANDELARIA | J27: DISTRICOL KEYVIVAN | K27: REDEBAN | L27: FO-25-1182181 | M27: 45842.333 | N27: 45848.387 | P27: CIERRE | Q27: CIERRE | R27: AGREGADOR | S27: DISTRICOL | T27: NO_EXITOSO | U27: CB NO ENTREGA EQUIPO | V27: 10-07-2025 SE REALIZA LLAMADA AL CLIENTE, PERO EL SEÑOR ANDRES QUE NOS CONTESTA, INDICA QUE NO TIENE CONOCIMIENTO DE LOS EQUIPOS, YA QUE EL LOCAL FUE CERRADO, ALLA NO EXISTE EL PUNTO Y NO TIENE CONTACTO DE LA PERSONA QUE FIGURA COMO TITULAR, PIDE QUE VALIDEMOS POR QUE EL NO TIENE CONTACTO CON LA PERSONA | W27: SOPORTE_TELEFÓNICO | X27: 0 | Y27: TIPO II | Z27: TERRESTRE | AA27: HENAO CARDONA DIEGO FERNANDO | AB27: 0 | AC27: =IF(AND(W27="SOPORTE_TELEFÓNICO",OR(U27="SIN CONTACTO CON EL CB",U27="NÚMEROS DE CONTACTO ERRADOS")),0,IF(W27="SOPORTE_TELEFÓNICO",'BASE DE LIQUIDACION 2025'!$B$9,IF(Y27="TIPO I",'BASE DE LIQUIDACION 2025'!$C$3,IF(Y27="TIPO II",'BASE DE LIQUIDACION 2025'!$C$4,IF(Y27="TIPO III",'BASE DE LIQUIDACION 2025'!$C$5,'BASE DE LIQUIDACION 2025'!$C$6))))) -> 37904.612 | AD27: =IF(W27="SOPORTE_TELEFÓNICO",AC27,CIERRES!AB27*CIERRES!AC27) -> 37904.612
A28: VILLAVICENCIO | B28: =VLOOKUP(A28,'CENTRO DE COSTOS'!A:D,4,FALSE) -> KEVIN ALEXIS CORZO BUSTOS | C28: =VLOOKUP(A28,'CENTRO DE COSTOS'!A:C,2,FALSE) -> 0004-0007 | D28: 50568 | E28: TA-25-847309 | F28: 72483 | G28: ORDEN DE CAMBIO | H28: META | I28: PUERTO GAITAN | J28: BARRIO PUERTO GAITAN BATEAS | K28: REDEBAN | L28: FO-25-1207487 | M28: 45847.543 | N28: 45848.425 | P28: CIERRE | Q28: CIERRE | R28: CB UNO A UNO | S28: CB UNO A UNO | T28: ILOCALIZADO | U28: CB CERRADO - DESOCUPADO | V28: 10-07-2025 SE REALIZA VISITA A COMERCI CB NO EXISTE NO ES POSIBLE COMUNICACIÓN CON TITULAR 3124206522- 3107724187 SE INDAGA EN EL SECTOR NO DAN INFORMACIÓN ILOCALIZABLE | W28: VISITA_TÉCNICA | X28: 0 | Y28: TIPO III | Z28: TERRESTRE | AA28: CASTRILLON URREA LONDIER LEANDRO | AB28: 1 | AC28: =IF(AND(W28="SOPORTE_TELEFÓNICO",OR(U28="SIN CONTACTO CON EL CB",U28="NÚMEROS DE CONTACTO ERRADOS")),0,IF(W28="SOPORTE_TELEFÓNICO",'BASE DE LIQUIDACION 2025'!$B$9,IF(Y28="TIPO I",'BASE DE LIQUIDACION 2025'!$C$3,IF(Y28="TIPO II",'BASE DE LIQUIDACION 2025'!$C$4,IF(Y28="TIPO III",'BASE DE LIQUIDACION 2025'!$C$5,'BASE DE LIQUIDACION 2025'!$C$6))))) -> 222904.07 | AD28: =IF(W28="SOPORTE_TELEFÓNICO",AC28,CIERRES!AB28*CIERRES!AC28) -> 222904.07
A29: CALI | B29: =VLOOKUP(A29,'CENTRO DE COSTOS'!A:D,4,FALSE) -> DIEGO FERNANDO HENAO CARDONA | C29: =VLOOKUP(A29,'CENTRO DE COSTOS'!A:C,2,FALSE) -> 0004-0003 | D29: 76001 | E29: TA-25-846848 | F29: 58164 | G29: ORDEN DE CAMBIO | H29: VALLE DEL CAUCA | I29: CALI | J29: PTM CALI FERRE INDUSTRIAS LU | K29: REDEBAN | L29: FO-25-1205694 | M29: 45847.453 | N29: 45848.473 | P29: CIERRE | Q29: CIERRE | R29: AGREGADOR | S29: COMCARD - PTM | T29: ILOCALIZADO | U29: CB CERRADO - DESOCUPADO | V29: 10-07-2025 SE LLEGA AL COMERCIO PERO ESTABA CERRADO SE LLAMA AL CLIENTE PERO NO CONTESTA , SE VALIDA EN LA ZONA Y MANIFIESTAN QUE EL LOCAL SE ENCUENTRA CERRADO HACE VARIO TIEMPO, SE PUEDE VALIDAR QUE LA CORRESPONDENCIA EN EL SITIO LLEVA VARIO TIEMPO EN EL BUZON DEL LOCAL , HASTA ROLLOS ENTREGADOS POR INTERAPIDISIMO SE ENCUENTRA ALLI ABANDONADOS | W29: VISITA_TÉCNICA | X29: TUZZZ355 | Y29: TIPO I | Z29: TERRESTRE | AA29: CUERO RUIZ JHONNY | AB29: 1 | AC29: =IF(AND(W29="SOPORTE_TELEFÓNICO",OR(U29="SIN CONTACTO CON EL CB",U29="NÚMEROS DE CONTACTO ERRADOS")),0,IF(W29="SOPORTE_TELEFÓNICO",'BASE DE LIQUIDACION 2025'!$B$9,IF(Y29="TIPO I",'BASE DE LIQUIDACION 2025'!$C$3,IF(Y29="TIPO II",'BASE DE LIQUIDACION 2025'!$C$4,IF(Y29="TIPO III",'BASE DE LIQUIDACION 2025'!$C$5,'BASE DE LIQUIDACION 2025'!$C$6))))) -> 44559.564 | AD29: =IF(W29="SOPORTE_TELEFÓNICO",AC29,CIERRES!AB29*CIERRES!AC29) -> 44559.564
A30: IBAGUE | B30: =VLOOKUP(A30,'CENTRO DE COSTOS'!A:D,4,FALSE) -> KEVIN ALEXIS CORZO BUSTOS | C30: =VLOOKUP(A30,'CENTRO DE COSTOS'!A:C,2,FALSE) -> 0004-0007 | D30: 17380 | E30: TA-25-846836 | F30: 44954 | G30: ORDEN DE CAMBIO | H30: CALDAS | I30: LA DORADA | J30: DISTRICOL FUNERALES CASA SAGRA | K30: REDEBAN | L30: FO-25-1205632 | M30: 45847.453 | N30: 45848.683 | P30: CIERRE | Q30: CIERRE | R30: AGREGADOR | S30: DISTRICOL | T30: NO_EXITOSO | U30: CB NO ENTREGA EQUIPO | V30: 10-07-2025 SE HABLA CON LA SEÑORA CLAUDIA RODRÍGUEZ, AL NÚMERO DE TELÉFONO 3108301952, ME INDICA QUE LO EQUIPOS LOS ENVÍO A MEDELLÍN. | W30: SOPORTE_TELEFÓNICO | X30: 0 | Y30: TIPO III | Z30: TERRESTRE | AA30: VARGAS HERRERA JHON JAIRO | AB30: 0 | AC30: =IF(AND(W30="SOPORTE_TELEFÓNICO",OR(U30="SIN CONTACTO CON EL CB",U30="NÚMEROS DE CONTACTO ERRADOS")),0,IF(W30="SOPORTE_TELEFÓNICO",'BASE DE LIQUIDACION 2025'!$B$9,IF(Y30="TIPO I",'BASE DE LIQUIDACION 2025'!$C$3,IF(Y30="TIPO II",'BASE DE LIQUIDACION 2025'!$C$4,IF(Y30="TIPO III",'BASE DE LIQUIDACION 2025'!$C$5,'BASE DE LIQUIDACION 2025'!$C$6))))) -> 37904.612 | AD30: =IF(W30="SOPORTE_TELEFÓNICO",AC30,CIERRES!AB30*CIERRES!AC30) -> 37904.612
A31: NEIVA | B31: =VLOOKUP(A31,'CENTRO DE COSTOS'!A:D,4,FALSE) -> KEVIN ALEXIS CORZO BUSTOS | C31: =VLOOKUP(A31,'CENTRO DE COSTOS'!A:C,2,FALSE) -> 0004-0007 | D31: 41001 | E31: TA-25-846839 | F31: 45438 | G31: ORDEN DE CAMBIO | H31: HUILA | I31: NEIVA | J31: DISTRICOL SANCHEZ LUBRICANTES | K31: REDEBAN | L31: FO-25-1205647 | M31: 45847.453 | N31: 45848.701 | P31: CIERRE | Q31: CIERRE | R31: AGREGADOR | S31: DISTRICOL | T31: NO_EXITOSO | U31: CB NO ENTREGA EQUIPO | V31: 10-07-2025 SE LLEGA A SITIO, CLIENTE INDICA QUE YA REALIZÓ ENVÍO DE EQUIPOS A DISTRICOL EN MEDELLIN | W31: VISITA_TÉCNICA | X31: AC0MZ790 | Y31: TIPO I | Z31: TERRESTRE | AA31: DIAZ VARGAS JONATHAN MIGUEL | AB31: 1 | AC31: =IF(AND(W31="SOPORTE_TELEFÓNICO",OR(U31="SIN CONTACTO CON EL CB",U31="NÚMEROS DE CONTACTO ERRADOS")),0,IF(W31="SOPORTE_TELEFÓNICO",'BASE DE LIQUIDACION 2025'!$B$9,IF(Y31="TIPO I",'BASE DE LIQUIDACION 2025'!$C$3,IF(Y31="TIPO II",'BASE DE LIQUIDACION 2025'!$C$4,IF(Y31="TIPO III",'BASE DE LIQUIDACION 2025'!$C$5,'BASE DE LIQUIDACION 2025'!$C$6))))) -> 44559.564 | AD31: =IF(W31="SOPORTE_TELEFÓNICO",AC31,CIERRES!AB31*CIERRES!AC31) -> 44559.564
A32: BUCARAMANGA | B32: =VLOOKUP(A32,'CENTRO DE COSTOS'!A:D,4,FALSE) -> MIGUEL JULIÁN HERNÁNDEZ GUARÍN | C32: =VLOOKUP(A32,'CENTRO DE COSTOS'!A:C,2,FALSE) -> 0004-0008 | D32: 68755 | E32: TA-25-847303 | F32: 67285 | G32: ORDEN DE CAMBIO | H32: SANTANDER | I32: SOCORRO | J32: BARRIO NARANJITO SOCORRO | K32: REDEBAN | L32: FO-25-1207453 | M32: 45847.543 | N32: 45848.708 | P32: CIERRE | Q32: CIERRE | R32: CB UNO A UNO | S32: CB UNO A UNO | T32: SOLICITUD_CANCELADA | U32: CANCELADO POR LA ENTIDAD | V32: 10-07-2025 ENTIDAD SOLICITA CERRAR LA ORDEN | W32: SOPORTE_TELEFÓNICO | X32: 0 | Y32: TIPO III | Z32: TERRESTRE | AA32: GELVEZ MOGOLLON JOSE ELISEO | AB32: 0 | AC32: =IF(AND(W32="SOPORTE_TELEFÓNICO",OR(U32="SIN CONTACTO CON EL CB",U32="NÚMEROS DE CONTACTO ERRADOS")),0,IF(W32="SOPORTE_TELEFÓNICO",'BASE DE LIQUIDACION 2025'!$B$9,IF(Y32="TIPO I",'BASE DE LIQUIDACION 2025'!$C$3,IF(Y32="TIPO II",'BASE DE LIQUIDACION 2025'!$C$4,IF(Y32="TIPO III",'BASE DE LIQUIDACION 2025'!$C$5,'BASE DE LIQUIDACION 2025'!$C$6))))) -> 37904.612 | AD32: =IF(W32="SOPORTE_TELEFÓNICO",AC32,CIERRES!AB32*CIERRES!AC32) -> 37904.612
A33: MEDELLIN | B33: =VLOOKUP(A33,'CENTRO DE COSTOS'!A:D,4,FALSE) -> JUAN SEBASTIÁN RÍOS CASTRILLÓN | C33: =VLOOKUP(A33,'CENTRO DE COSTOS'!A:C,2,FALSE) -> 0004-0005 | D33: 15572 | E33: TA-25-846843 | F33: 52844 | G33: ORDEN DE CAMBIO | H33: BOYACA | I33: PUERTO BOYACA | J33: DISTRICOL PAPELERIA Y MISCELAN | K33: REDEBAN | L33: FO-25-1205668 | M33: 45847.453 | N33: 45848.717 | P33: CIERRE | Q33: CIERRE | R33: AGREGADOR | S33: DISTRICOL | T33: NO_EXITOSO | U33: CB NO ENTREGA EQUIPO | V33: 10-07-2025 SE LLEGA A SITO Y USUARIO CONFIRMA QUE LOS EQUIPOS SE ENVIARON DISTRICOL MEDELLÍN SE DESMONTA PUBLICIDAD INSTALADA | W33: VISITA_TÉCNICA | X33: BA01Z147 | Y33: TIPO IV | Z33: TERRESTRE | AA33: DIAZ ZABALA FRANCIS DUBAN | AB33: 1 | AC33: =IF(AND(W33="SOPORTE_TELEFÓNICO",OR(U33="SIN CONTACTO CON EL CB",U33="NÚMEROS DE CONTACTO ERRADOS")),0,IF(W33="SOPORTE_TELEFÓNICO",'BASE DE LIQUIDACION 2025'!$B$9,IF(Y33="TIPO I",'BASE DE LIQUIDACION 2025'!$C$3,IF(Y33="TIPO II",'BASE DE LIQUIDACION 2025'!$C$4,IF(Y33="TIPO III",'BASE DE LIQUIDACION 2025'!$C$5,'BASE DE LIQUIDACION 2025'!$C$6))))) -> 464809.37 | AD33: =IF(W33="SOPORTE_TELEFÓNICO",AC33,CIERRES!AB33*CIERRES!AC33) -> 464809.37
A34: YOPAL | B34: =VLOOKUP(A34,'CENTRO DE COSTOS'!A:D,4,FALSE) -> KEVIN ALEXIS CORZO BUSTOS | C34: =VLOOKUP(A34,'CENTRO DE COSTOS'!A:C,2,FALSE) -> 0004-0007 | D34: 85001 | E34: TA-25-835645 | F34: 77381 | G34: ORDEN DE CAMBIO | H34: CASANARE | I34: YOPAL | J34: BARRIO CIUDADELA COMFACASANARE YOPAL | K34: REDEBAN | L34: FO-25-1186224 | M34: 45842.69 | N34: 45849.481 | P34: CIERRE | Q34: CIERRE | R34: CB UNO A UNO | S34: CB UNO A UNO | T34: NO_EXITOSO | U34: MIXTO UNO A UNO NO COBRAR | V34: 11-07-2025 EN COMUNICACIÓN CON EL SEÑOR ENRIQUE CAMACHO, SE VISITA SITIO INDICADO. SE LLEGA AL SITO EN COMUNICACIÓN CON EL SEÑOR ENRIQUE INDICA QUE NO PUEDE ENTREGAR LOS EQUIPOS, EL NO SE ENCUENTRA EN MUNICIPIO Y LA PERSONA QUE VA HACER EL FAVOR DE ENTREGAR NO TIENE LAS LLAVES PARA ACCEDER AL COMERCIO. SE LE INFORMA UNA VEZ SE ENCUENTRE A DISPOSICIÓN DE ENTREGA SE COMUNIQUE A LA LINEA DEL BANCO Y SOLICITE LA ENTREGA. | W34: VISITA_TÉCNICA | X34: NONE | Y34: TIPO I | Z34: TERRESTRE | AA34: BERNAL ELAICA EDGAR ALEXIS | AB34: 1 | AC34: =IF(AND(W34="SOPORTE_TELEFÓNICO",OR(U34="SIN CONTACTO CON EL CB",U34="NÚMEROS DE CONTACTO ERRADOS")),0,IF(W34="SOPORTE_TELEFÓNICO",'BASE DE LIQUIDACION 2025'!$B$9,IF(Y34="TIPO I",'BASE DE LIQUIDACION 2025'!$C$3,IF(Y34="TIPO II",'BASE DE LIQUIDACION 2025'!$C$4,IF(Y34="TIPO III",'BASE DE LIQUIDACION 2025'!$C$5,'BASE DE LIQUIDACION 2025'!$C$6))))) -> 44559.564 | AD34: =IF(W34="SOPORTE_TELEFÓNICO",AC34,CIERRES!AB34*CIERRES!AC34) -> 44559.564
A35: MEDELLIN | B35: =VLOOKUP(A35,'CENTRO DE COSTOS'!A:D,4,FALSE) -> JUAN SEBASTIÁN RÍOS CASTRILLÓN | C35: =VLOOKUP(A35,'CENTRO DE COSTOS'!A:C,2,FALSE) -> 0004-0005 | D35: 5591 | E35: TA-25-846840 | F35: 49149 | G35: ORDEN DE CAMBIO | H35: ANTIOQUIA | I35: PUERTO TRIUNFO | J35: DISTRICOL VA EMMANUEL DORADAL | K35: REDEBAN | L35: FO-25-1205653 | M35: 45847.453 | N35: 45849.542 | P35: CIERRE | Q35: CIERRE | R35: AGREGADOR | S35: DISTRICOL | T35: NO_EXITOSO | U35: CB NO ENTREGA EQUIPO | V35: 11-07-2025 USUARIO MANIFISTA QUÉ YA LOS EQUIPOS FUERON ENVIADOS A DISTRICOL MEDELLÍN | W35: VISITA_TÉCNICA | X35: NA | Y35: TIPO IV | Z35: TERRESTRE | AA35: DIAZ ZABALA FRANCIS DUBAN | AB35: 1 | AC35: =IF(AND(W35="SOPORTE_TELEFÓNICO",OR(U35="SIN CONTACTO CON EL CB",U35="NÚMEROS DE CONTACTO ERRADOS")),0,IF(W35="SOPORTE_TELEFÓNICO",'BASE DE LIQUIDACION 2025'!$B$9,IF(Y35="TIPO I",'BASE DE LIQUIDACION 2025'!$C$3,IF(Y35="TIPO II",'BASE DE LIQUIDACION 2025'!$C$4,IF(Y35="TIPO III",'BASE DE LIQUIDACION 2025'!$C$5,'BASE DE LIQUIDACION 2025'!$C$6))))) -> 464809.37 | AD35: =IF(W35="SOPORTE_TELEFÓNICO",AC35,CIERRES!AB35*CIERRES!AC35) -> 464809.37
A36: BOGOTA | B36: =VLOOKUP(A36,'CENTRO DE COSTOS'!A:D,4,FALSE) -> WILLIAM ASDRUBAL ROZO ROZO | C36: =VLOOKUP(A36,'CENTRO DE COSTOS'!A:C,2,FALSE) -> 0004-0004 | D36: 25785 | E36: TA-25-839180 | F36: 51358 | G36: ORDEN DE CAMBIO | H36: CUNDINAMARCA | I36: TABIO | J36: CONTIGO_SUPERMARKET | K36: REDEBAN | L36: FO-25-1195929 | M36: 45845.639 | N36: 45849.717 | P36: CIERRE | Q36: RETIRO VOLUNTARIO | R36: RETAIL | S36: CONTIGO | T36: NO_EXITOSO | U36: CB NO ENTREGA EQUIPO | V36: 11-07-2025 SE REALIZA VISITA AL COMERCIO NOS ATIENDE LA SEÑORA DANIELA CASTRO LA CUAL NOS INDICA QUE YA FUE REALIZÓ LA ENTREGA DE LOS EQUIPOS | W36: VISITA_TÉCNICA | X36: NA | Y36: TIPO II | Z36: TERRESTRE | AA36: HERNANDEZ NARANJO OSCAR EDUARDO | AB36: 1 | AC36: =IF(AND(W36="SOPORTE_TELEFÓNICO",OR(U36="SIN CONTACTO CON EL CB",U36="NÚMEROS DE CONTACTO ERRADOS")),0,IF(W36="SOPORTE_TELEFÓNICO",'BASE DE LIQUIDACION 2025'!$B$9,IF(Y36="TIPO I",'BASE DE LIQUIDACION 2025'!$C$3,IF(Y36="TIPO II",'BASE DE LIQUIDACION 2025'!$C$4,IF(Y36="TIPO III",'BASE DE LIQUIDACION 2025'!$C$5,'BASE DE LIQUIDACION 2025'!$C$6))))) -> 134410.88 | AD36: =IF(W36="SOPORTE_TELEFÓNICO",AC36,CIERRES!AB36*CIERRES!AC36) -> 134410.88
A37: MONTERIA | B37: =VLOOKUP(A37,'CENTRO DE COSTOS'!A:D,4,FALSE) -> JOSE MAURICIO HERNANDEZ ROJAS | C37: =VLOOKUP(A37,'CENTRO DE COSTOS'!A:C,2,FALSE) -> 0004-0001 | D37: 23079 | E37: TA-25-839276 | F37: 62995 | G37: ORDEN DE CAMBIO | H37: CORDOBA | I37: BUENAVISTA | J37: BARRIO BOGOTA BUENAVISTA 1 | K37: REDEBAN | L37: FO-25-1196112 | M37: 45845.653 | N37: 45849.718 | P37: CIERRE | Q37: CIERRE | R37: CB UNO A UNO | S37: CB UNO A UNO | T37: ILOCALIZADO | U37: CB CERRADO - DESOCUPADO | V37: 11-07-2025 SE VISITA CB EN DIRECCIÓN DE RETIRO CRA 22 CLL 12F PERO NO SE ENCUENTRA QUIEN ENTREGUE EQUIPOS, LOCAL CERRADO. SE INTENTA COMUNICACIÓN AL NÚMERO 3145206981 PERO NO RESPONDE.SE CIERRA ACTIVIDAD COMO FALLIDA YA QUE NO SE LOGRA COMUNICACIÓN NI SE ENCUENTRA CB EN SITIO. | W37: VISITA_TÉCNICA | X37: NO SE INTERVIENE | Y37: TIPO II | Z37: TERRESTRE | AA37: COGOLLO VERTEL EDER LUIS | AB37: 1 | AC37: =IF(AND(W37="SOPORTE_TELEFÓNICO",OR(U37="SIN CONTACTO CON EL CB",U37="NÚMEROS DE CONTACTO ERRADOS")),0,IF(W37="SOPORTE_TELEFÓNICO",'BASE DE LIQUIDACION 2025'!$B$9,IF(Y37="TIPO I",'BASE DE LIQUIDACION 2025'!$C$3,IF(Y37="TIPO II",'BASE DE LIQUIDACION 2025'!$C$4,IF(Y37="TIPO III",'BASE DE LIQUIDACION 2025'!$C$5,'BASE DE LIQUIDACION 2025'!$C$6))))) -> 134410.88 | AD37: =IF(W37="SOPORTE_TELEFÓNICO",AC37,CIERRES!AB37*CIERRES!AC37) -> 134410.88
A38: TUNJA | B38: =VLOOKUP(A38,'CENTRO DE COSTOS'!A:D,4,FALSE) -> MIGUEL JULIÁN HERNÁNDEZ GUARÍN | C38: =VLOOKUP(A38,'CENTRO DE COSTOS'!A:C,2,FALSE) -> 0004-0008 | D38: 15238 | E38: TA-25-839281 | F38: 75698 | G38: ORDEN DE CAMBIO | H38: BOYACA | I38: DUITAMA | J38: BARRIO MANZANARES DUITAMA 4 | K38: REDEBAN | L38: FO-25-1202695 | M38: 45845.653 | N38: 45849.722 | P38: CIERRE | Q38: CIERRE | R38: CB UNO A UNO | S38: CB UNO A UNO | T38: EJECUTADO_EXITOSO | U38: CIERRE EXITOSO | V38: 11-07-2025 SE EJECUTA CIERRE CORRESPONSAL BANCARIO BANCOLOMBIA RETIRANDO LOS EQUIPOS EXISTENTES COMERCIO SIN PUBLICIDAD SE RETIRAN EL LA CALLE 15#9A-02 PUBLICIDAD EXISTENTE EN LA FACHADA CORRESPONDE AL CB 59684 EXISTENTE EN LA DIRECCIÓN DE ENTREGA. | W38: VISITA_TÉCNICA | X38: 1000R516 | Y38: TIPO II | Z38: TERRESTRE | AA38: RODRIGUEZ MURCIA YERSON IVAN | AB38: 1 | AC38: =IF(AND(W38="SOPORTE_TELEFÓNICO",OR(U38="SIN CONTACTO CON EL CB",U38="NÚMEROS DE CONTACTO ERRADOS")),0,IF(W38="SOPORTE_TELEFÓNICO",'BASE DE LIQUIDACION 2025'!$B$9,IF(Y38="TIPO I",'BASE DE LIQUIDACION 2025'!$C$3,IF(Y38="TIPO II",'BASE DE LIQUIDACION 2025'!$C$4,IF(Y38="TIPO III",'BASE DE LIQUIDACION 2025'!$C$5,'BASE DE LIQUIDACION 2025'!$C$6))))) -> 134410.88 | AD38: =IF(W38="SOPORTE_TELEFÓNICO",AC38,CIERRES!AB38*CIERRES!AC38) -> 134410.88
A39: CALI | B39: =VLOOKUP(A39,'CENTRO DE COSTOS'!A:D,4,FALSE) -> DIEGO FERNANDO HENAO CARDONA | C39: =VLOOKUP(A39,'CENTRO DE COSTOS'!A:C,2,FALSE) -> 0004-0003 | D39: 76001 | E39: TA-25-839293 | F39: 40257 | G39: ORDEN DE CAMBIO | H39: VALLE DEL CAUCA | I39: CALI | J39: PTM CALI EXITORNILLOS | K39: REDEBAN | L39: FO-25-1208329 | M39: 45845.653 | N39: 45849.744 | P39: CIERRE | Q39: CIERRE | R39: AGREGADOR | S39: COMCARD - PTM | T39: EJECUTADO_EXITOSO | U39: CIERRE EXITOSO | V39: 11-07-2025 SE REALIZA RETIRO DE EQUIPOS Y ACCESORIOS DE CB BANCOLOMBIA MIXTO, SON ENTREGADOS EN BODEGA DE LINEA COMUNICACIONES, LOS EQUIPOS SON RECOGIDOS EN DIRECCIÓN DIFERENTE A LA DEL COMERCIO EL CLIENTE NO CUENTA CON PUBLICIDAD. | W39: VISITA_TÉCNICA | X39: AB0HZ963 - UV001666 | Y39: TIPO I | Z39: TERRESTRE | AA39: MONTERO MUESES GIAN CARLO | AB39: 1 | AC39: =IF(AND(W39="SOPORTE_TELEFÓNICO",OR(U39="SIN CONTACTO CON EL CB",U39="NÚMEROS DE CONTACTO ERRADOS")),0,IF(W39="SOPORTE_TELEFÓNICO",'BASE DE LIQUIDACION 2025'!$B$9,IF(Y39="TIPO I",'BASE DE LIQUIDACION 2025'!$C$3,IF(Y39="TIPO II",'BASE DE LIQUIDACION 2025'!$C$4,IF(Y39="TIPO III",'BASE DE LIQUIDACION 2025'!$C$5,'BASE DE LIQUIDACION 2025'!$C$6))))) -> 44559.564 | AD39: =IF(W39="SOPORTE_TELEFÓNICO",AC39,CIERRES!AB39*CIERRES!AC39) -> 44559.564
A40: CUCUTA | B40: =VLOOKUP(A40,'CENTRO DE COSTOS'!A:D,4,FALSE) -> MIGUEL JULIÁN HERNÁNDEZ GUARÍN | C40: =VLOOKUP(A40,'CENTRO DE COSTOS'!A:C,2,FALSE) -> 0004-0008 | D40: 54405 | E40: TA-25-846847 | F40: 77857 | G40: ORDEN DE CAMBIO | H40: NORTE DE SANTANDER | I40: LOS PATIOS | J40: PTM PUNTOSERVIS LOS PATIOS 1 L | K40: REDEBAN | L40: FO-25-1205688 | M40: 45847.453 | N40: 45849.747 | P40: CIERRE | Q40: CIERRE | R40: AGREGADOR | S40: COMCARD - PTM | T40: ILOCALIZADO | U40: CB CERRADO - DESOCUPADO | V40: 11-07-2025 SE VISITA DIRECCIÓN DEL CB SE ENCUENTRA CERRADO, SE LLAMA AL CLIENTE SE VA BUZÓN DE VOZ, SE DEJA MENSAJE NO SE OBTIENE RESPUESTA. | W40: VISITA_TÉCNICA | X40: NA | Y40: TIPO I | Z40: TERRESTRE | AA40: TORRES MANTILLA JOSE DANIEL | AB40: 1 | AC40: =IF(AND(W40="SOPORTE_TELEFÓNICO",OR(U40="SIN CONTACTO CON EL CB",U40="NÚMEROS DE CONTACTO ERRADOS")),0,IF(W40="SOPORTE_TELEFÓNICO",'BASE DE LIQUIDACION 2025'!$B$9,IF(Y40="TIPO I",'BASE DE LIQUIDACION 2025'!$C$3,IF(Y40="TIPO II",'BASE DE LIQUIDACION 2025'!$C$4,IF(Y40="TIPO III",'BASE DE LIQUIDACION 2025'!$C$5,'BASE DE LIQUIDACION 2025'!$C$6))))) -> 44559.564 | AD40: =IF(W40="SOPORTE_TELEFÓNICO",AC40,CIERRES!AB40*CIERRES!AC40) -> 44559.564
A41: TUNJA | B41: =VLOOKUP(A41,'CENTRO DE COSTOS'!A:D,4,FALSE) -> MIGUEL JULIÁN HERNÁNDEZ GUARÍN | C41: =VLOOKUP(A41,'CENTRO DE COSTOS'!A:C,2,FALSE) -> 0004-0008 | D41: 15001 | E41: TA-25-853123 | F41: 66790 | G41: ORDEN DE CAMBIO | H41: BOYACA | I41: TUNJA | J41: BARRIO MALDONADO TUNJA 4 | K41: REDEBAN | L41: FO-25-1217992 | M41: 45849.485 | N41: 45849.776 | P41: CIERRE | Q41: CIERRE | R41: CB UNO A UNO | S41: CB UNO A UNO | T41: NO_EXITOSO | U41: CB NO ENTREGA EQUIPO | V41: 11-07-2025 SE VISITA COMERCIO ,INDICAN QUE NO ENTREGAN LOS EQUIPOS HASTA QUE NO CONFIRMEN CON LA ENTIDAD TEMAS RELACIONADOS QUE SE HAN PRESENTADO CON EL CORRESPONSAL | W41: VISITA_TÉCNICA | X41: 3A0CZ750 | Y41: TIPO I | Z41: TERRESTRE | AA41: ALVARADO MORENO CRISTHIAN | AB41: 1 | AC41: =IF(AND(W41="SOPORTE_TELEFÓNICO",OR(U41="SIN CONTACTO CON EL CB",U41="NÚMEROS DE CONTACTO ERRADOS")),0,IF(W41="SOPORTE_TELEFÓNICO",'BASE DE LIQUIDACION 2025'!$B$9,IF(Y41="TIPO I",'BASE DE LIQUIDACION 2025'!$C$3,IF(Y41="TIPO II",'BASE DE LIQUIDACION 2025'!$C$4,IF(Y41="TIPO III",'BASE DE LIQUIDACION 2025'!$C$5,'BASE DE LIQUIDACION 2025'!$C$6))))) -> 44559.564 | AD41: =IF(W41="SOPORTE_TELEFÓNICO",AC41,CIERRES!AB41*CIERRES!AC41) -> 44559.564
A42: CUCUTA | B42: =VLOOKUP(A42,'CENTRO DE COSTOS'!A:D,4,FALSE) -> MIGUEL JULIÁN HERNÁNDEZ GUARÍN | C42: =VLOOKUP(A42,'CENTRO DE COSTOS'!A:C,2,FALSE) -> 0004-0008 | D42: 54001 | E42: TA-25-853178 | F42: 66424 | G42: ORDEN DE CAMBIO | H42: NORTE DE SANTANDER | I42: CUCUTA | J42: BARRIO MOTILONES CUCUTA 18 | K42: REDEBAN | L42: FO-25-1218078 | M42: 45849.485 | N42: 45849.789 | P42: CIERRE | Q42: CIERRE | R42: CB UNO A UNO | S42: CB UNO A UNO | T42: ILOCALIZADO | U42: CB CERRADO - DESOCUPADO | V42: 11-07-2025 SE REALIZA VISITA,SE ENCUENTRA QUE EL COMERCIO YA NO EXISTE EN DIRECCIÓN LOS ENCARGADOS DEL NUEVO PUNTO NO TIENEN CONOCIMIENTO DE PARA DONDE SE TRASLADARON NO SE LOGRÓ COMUNICACIÓN CON EL CLIENTE PARA LA RECOLECCIÓN DE EQUIPOS | W42: VISITA_TÉCNICA | X42: 0 | Y42: TIPO I | Z42: TERRESTRE | AA42: DURAN ACOSTA FRANK YONNY | AB42: 1 | AC42: =IF(AND(W42="SOPORTE_TELEFÓNICO",OR(U42="SIN CONTACTO CON EL CB",U42="NÚMEROS DE CONTACTO ERRADOS")),0,IF(W42="SOPORTE_TELEFÓNICO",'BASE DE LIQUIDACION 2025'!$B$9,IF(Y42="TIPO I",'BASE DE LIQUIDACION 2025'!$C$3,IF(Y42="TIPO II",'BASE DE LIQUIDACION 2025'!$C$4,IF(Y42="TIPO III",'BASE DE LIQUIDACION 2025'!$C$5,'BASE DE LIQUIDACION 2025'!$C$6))))) -> 44559.564 | AD42: =IF(W42="SOPORTE_TELEFÓNICO",AC42,CIERRES!AB42*CIERRES!AC42) -> 44559.564
A43: BUCARAMANGA | B43: =VLOOKUP(A43,'CENTRO DE COSTOS'!A:D,4,FALSE) -> MIGUEL JULIÁN HERNÁNDEZ GUARÍN | C43: =VLOOKUP(A43,'CENTRO DE COSTOS'!A:C,2,FALSE) -> 0004-0008 | D43: 68001 | E43: TA-25-853234 | F43: 41962 | G43: ORDEN DE CAMBIO | H43: SANTANDER | I43: BUCARAMANGA | J43: PTM BUCARAMANGA MULTIPAGOS RCK | K43: REDEBAN | L43: FO-25-1218179 | M43: 45849.485 | N43: 45849.792 | P43: CIERRE | Q43: CIERRE | R43: AGREGADOR | S43: COMCARD - PTM | T43: NO_EXITOSO | U43: CB NO ENTREGA EQUIPO | V43: 11-07-2025 SE HACE PRESENCIA EN COMERCIO PERSONAL ENCARGADO INFORMA QUE NO TIENE CONOCIMIENTO DEL CIERRE SE COMUNICA CON EL DUEÑO EL SEÑOR EDWIN QUIEN INFORMA QUE DESCONOCE EL POR QUÉ EL CIERRE DEL CORRESPONSAL SE LE INFORMA QUE SE COLOQUE EN CONTACTO CON EL ASESOR DE PTM Y VALIDE LA CAUSAL DEL CIERRE Y LUEGO SOLICITE LA RECOLECCIÓN DE LOS EQUIPOS CLIENTE PERSONAL ACARGO NO FIRMA NOTIFICA QUE NO TIENE AUTORIZACIÓN | W43: VISITA_TÉCNICA | X43: NO SE MANIPULAN EQUIPOS | Y43: TIPO I | Z43: TERRESTRE | AA43: ORTEBARRERAGA MARLON STWAR | AB43: 1 | AC43: =IF(AND(W43="SOPORTE_TELEFÓNICO",OR(U43="SIN CONTACTO CON EL CB",U43="NÚMEROS DE CONTACTO ERRADOS")),0,IF(W43="SOPORTE_TELEFÓNICO",'BASE DE LIQUIDACION 2025'!$B$9,IF(Y43="TIPO I",'BASE DE LIQUIDACION 2025'!$C$3,IF(Y43="TIPO II",'BASE DE LIQUIDACION 2025'!$C$4,IF(Y43="TIPO III",'BASE DE LIQUIDACION 2025'!$C$5,'BASE DE LIQUIDACION 2025'!$C$6))))) -> 44559.564 | AD43: =IF(W43="SOPORTE_TELEFÓNICO",AC43,CIERRES!AB43*CIERRES!AC43) -> 44559.564
A44: MEDELLIN | B44: =VLOOKUP(A44,'CENTRO DE COSTOS'!A:D,4,FALSE) -> JUAN SEBASTIÁN RÍOS CASTRILLÓN | C44: =VLOOKUP(A44,'CENTRO DE COSTOS'!A:C,2,FALSE) -> 0004-0005 | D44: 5001 | E44: TA-25-853220 | F44: 55025 | G44: ORDEN DE CAMBIO | H44: ANTIOQUIA | I44: MEDELLIN | J44: BARRIO CENTRO MEDELLIN 80 | K44: REDEBAN | L44: FO-25-1218151 | M44: 45849.485 | N44: 45850.381 | P44: CIERRE | Q44: RECUPERACION DE EQUIPOS | R44: CB UNO A UNO | S44: CB UNO A UNO | T44: ILOCALIZADO | U44: CB CERRADO - DESOCUPADO | V44: 12-07-2025 SE LLEGA AL SITIO Y EL COMERCIO SE ENCUENTRA CERRADO SE INVITA COMUNICAR CON EL USUARIO Y NO TUVE RESPUESTA. SE ESPERA 30 MINUTOS Y NI HUBO RESPUESTA | W44: VISITA_TÉCNICA | X44: 9CQZZ891 | Y44: TIPO I | Z44: TERRESTRE | AA44: ZAPATA LOPEZ EDWARD ASDRUBAL | AB44: 1 | AC44: =IF(AND(W44="SOPORTE_TELEFÓNICO",OR(U44="SIN CONTACTO CON EL CB",U44="NÚMEROS DE CONTACTO ERRADOS")),0,IF(W44="SOPORTE_TELEFÓNICO",'BASE DE LIQUIDACION 2025'!$B$9,IF(Y44="TIPO I",'BASE DE LIQUIDACION 2025'!$C$3,IF(Y44="TIPO II",'BASE DE LIQUIDACION 2025'!$C$4,IF(Y44="TIPO III",'BASE DE LIQUIDACION 2025'!$C$5,'BASE DE LIQUIDACION 2025'!$C$6))))) -> 44559.564 | AD44: =IF(W44="SOPORTE_TELEFÓNICO",AC44,CIERRES!AB44*CIERRES!AC44) -> 44559.564
A45: VILLAVICENCIO | B45: =VLOOKUP(A45,'CENTRO DE COSTOS'!A:D,4,FALSE) -> KEVIN ALEXIS CORZO BUSTOS | C45: =VLOOKUP(A45,'CENTRO DE COSTOS'!A:C,2,FALSE) -> 0004-0007 | D45: 50001 | E45: TA-25-853171 | F45: 64155 | G45: ORDEN DE CAMBIO | H45: META | I45: VILLAVICENCIO | J45: BARRIO VIZCAYA VILLAVICENCIO 2 | K45: REDEBAN | L45: FO-25-1218062 | M45: 45849.485 | N45: 45850.381 | P45: CIERRE | Q45: CIERRE | R45: CB UNO A UNO | S45: CB UNO A UNO | T45: ILOCALIZADO | U45: CB CERRADO - DESOCUPADO | V45: 12-07-2025 SE REALIZA VISITA AL PUNTO Y COMERCIO DE ENCUENTRA CERRADO, SE INTENTA CONTACTO TELEFONICO Y NO ES POSIBLE | W45: VISITA_TÉCNICA | X45: NONE | Y45: TIPO I | Z45: TERRESTRE | AA45: PEDREROS CONTRERAS MICHAEL STEVENS | AB45: 1 | AC45: =IF(AND(W45="SOPORTE_TELEFÓNICO",OR(U45="SIN CONTACTO CON EL CB",U45="NÚMEROS DE CONTACTO ERRADOS")),0,IF(W45="SOPORTE_TELEFÓNICO",'BASE DE LIQUIDACION 2025'!$B$9,IF(Y45="TIPO I",'BASE DE LIQUIDACION 2025'!$C$3,IF(Y45="TIPO II",'BASE DE LIQUIDACION 2025'!$C$4,IF(Y45="TIPO III",'BASE DE LIQUIDACION 2025'!$C$5,'BASE DE LIQUIDACION 2025'!$C$6))))) -> 44559.564 | AD45: =IF(W45="SOPORTE_TELEFÓNICO",AC45,CIERRES!AB45*CIERRES!AC45) -> 44559.564
A46: VILLAVICENCIO | B46: =VLOOKUP(A46,'CENTRO DE COSTOS'!A:D,4,FALSE) -> KEVIN ALEXIS CORZO BUSTOS | C46: =VLOOKUP(A46,'CENTRO DE COSTOS'!A:C,2,FALSE) -> 0004-0007 | D46: 50001 | E46: TA-25-853173 | F46: 72605 | G46: ORDEN DE CAMBIO | H46: META | I46: VILLAVICENCIO | J46: BARRIO VIZCAYA VILLAVICENCIO 5 | K46: REDEBAN | L46: FO-25-1218066 | M46: 45849.485 | N46: 45850.394 | P46: CIERRE | Q46: CIERRE | R46: CB UNO A UNO | S46: CB UNO A UNO | T46: NO_EXITOSO | U46: CB NO ENTREGA EQUIPO | V46: 12-07-2025 SE REALIZA VISITA AL PUNTO Y PERSONA DE COMERCIO INFORMA QUE NO SABE ND DEL DATAFONO | W46: VISITA_TÉCNICA | X46: NONE | Y46: TIPO I | Z46: TERRESTRE | AA46: PEDREROS CONTRERAS MICHAEL STEVENS | AB46: 1 | AC46: =IF(AND(W46="SOPORTE_TELEFÓNICO",OR(U46="SIN CONTACTO CON EL CB",U46="NÚMEROS DE CONTACTO ERRADOS")),0,IF(W46="SOPORTE_TELEFÓNICO",'BASE DE LIQUIDACION 2025'!$B$9,IF(Y46="TIPO I",'BASE DE LIQUIDACION 2025'!$C$3,IF(Y46="TIPO II",'BASE DE LIQUIDACION 2025'!$C$4,IF(Y46="TIPO III",'BASE DE LIQUIDACION 2025'!$C$5,'BASE DE LIQUIDACION 2025'!$C$6))))) -> 44559.564 | AD46: =IF(W46="SOPORTE_TELEFÓNICO",AC46,CIERRES!AB46*CIERRES!AC46) -> 44559.564
A47: NEIVA | B47: =VLOOKUP(A47,'CENTRO DE COSTOS'!A:D,4,FALSE) -> KEVIN ALEXIS CORZO BUSTOS | C47: =VLOOKUP(A47,'CENTRO DE COSTOS'!A:C,2,FALSE) -> 0004-0007 | D47: 18001 | E47: TA-25-853134 | F47: 77627 | G47: ORDEN DE CAMBIO | H47: CAQUETA | I47: FLORENCIA | J47: BARRIO CENTRO FLORENCIA 36 | K47: REDEBAN | L47: FO-25-1218011 | M47: 45849.485 | N47: 45850.409 | P47: CIERRE | Q47: CIERRE | R47: CB UNO A UNO | S47: CB UNO A UNO | T47: SOLICITUD_CANCELADA | U47: CANCELADO POR LA ENTIDAD | V47: 12-07-2025 SE REALIZA VISITA AL CB Y CLIENTE MANIFIESTA QUE NO PERMITE EL CIERRE YA QUE LA SOLICITUD QUE REALIZÓ FUE UN TRASLADO Y NO EL CIERRE, POR TAL MOTIVO NO PERMITE EL CIERRE Y MANIFIESTA QUE ESTÁ EN COMUNICACIÓN CON LA ENTIDAD PARA EL DESBLOQUEO Y NO PARA EL CIERRE, CIERRE FALLIDO. | W47: VISITA_TÉCNICA | X47: F1JZZ376 | Y47: TIPO IV | Z47: TERRESTRE | AA47: BERMUDEZ SANCHEZ JOSE NEYBER | AB47: 1 | AC47: =IF(AND(W47="SOPORTE_TELEFÓNICO",OR(U47="SIN CONTACTO CON EL CB",U47="NÚMEROS DE CONTACTO ERRADOS")),0,IF(W47="SOPORTE_TELEFÓNICO",'BASE DE LIQUIDACION 2025'!$B$9,IF(Y47="TIPO I",'BASE DE LIQUIDACION 2025'!$C$3,IF(Y47="TIPO II",'BASE DE LIQUIDACION 2025'!$C$4,IF(Y47="TIPO III",'BASE DE LIQUIDACION 2025'!$C$5,'BASE DE LIQUIDACION 2025'!$C$6))))) -> 464809.37 | AD47: =IF(W47="SOPORTE_TELEFÓNICO",AC47,CIERRES!AB47*CIERRES!AC47) -> 464809.37
A48: CUCUTA | B48: =VLOOKUP(A48,'CENTRO DE COSTOS'!A:D,4,FALSE) -> MIGUEL JULIÁN HERNÁNDEZ GUARÍN | C48: =VLOOKUP(A48,'CENTRO DE COSTOS'!A:C,2,FALSE) -> 0004-0008 | D48: 54001 | E48: TA-25-853181 | F48: 72616 | G48: ORDEN DE CAMBIO | H48: NORTE DE SANTANDER | I48: CUCUTA | J48: BARRIO SAN LUIS CUCUTA 24 | K48: REDEBAN | L48: FO-25-1218083 | M48: 45849.485 | N48: 45850.416 | P48: CIERRE | Q48: CIERRE | R48: CB UNO A UNO | S48: CB UNO A UNO | T48: NO_EXITOSO | U48: CB NO ENTREGA EQUIPO | V48: 12-07-2025 SE REALIZÓ VISITA AL COMERCIO Y ADMINISTRADOR INDICA QUE SE ENCUENTRA EN CONCILIACIÓN CON EL ANTERIOR DUEÑO PARA QUE LE SEDA EL CORRESPONSAL, NO DESEA ENTREGAR EQUIPOS, SE LE MANIFIESTA QUE SE DEBE COMUNICAR CON EL BANCO AL 018000 LLEGADO EL CASO DESEA ENTREGAR LOS EQUIPOS. | W48: VISITA_TÉCNICA | X48: NONE | Y48: TIPO I | Z48: TERRESTRE | AA48: MORA VEGA JEAMPIER | AB48: 1 | AC48: =IF(AND(W48="SOPORTE_TELEFÓNICO",OR(U48="SIN CONTACTO CON EL CB",U48="NÚMEROS DE CONTACTO ERRADOS")),0,IF(W48="SOPORTE_TELEFÓNICO",'BASE DE LIQUIDACION 2025'!$B$9,IF(Y48="TIPO I",'BASE DE LIQUIDACION 2025'!$C$3,IF(Y48="TIPO II",'BASE DE LIQUIDACION 2025'!$C$4,IF(Y48="TIPO III",'BASE DE LIQUIDACION 2025'!$C$5,'BASE DE LIQUIDACION 2025'!$C$6))))) -> 44559.564 | AD48: =IF(W48="SOPORTE_TELEFÓNICO",AC48,CIERRES!AB48*CIERRES!AC48) -> 44559.564
A49: NEIVA | B49: =VLOOKUP(A49,'CENTRO DE COSTOS'!A:D,4,FALSE) -> KEVIN ALEXIS CORZO BUSTOS | C49: =VLOOKUP(A49,'CENTRO DE COSTOS'!A:C,2,FALSE) -> 0004-0007 | D49: 41001 | E49: TA-25-853156 | F49: 77285 | G49: ORDEN DE CAMBIO | H49: HUILA | I49: NEIVA | J49: BARRIO VILLA REGINA NEIVA 1 | K49: REDEBAN | L49: FO-25-1218050 | M49: 45849.485 | N49: 45850.472 | P49: CIERRE | Q49: CIERRE | R49: CB UNO A UNO | S49: CB UNO A UNO | T49: ILOCALIZADO | U49: CB CERRADO - DESOCUPADO | V49: 12-07-2025 SE REALIZA VISITA AL PUNTO, SE ENVIDENCIA COMERCIO SE ENCUENTRA CERRADO SE INTENTA COMUNICACIÓN CON CLIENTE PERO NO HAY RESPUESTA SE VA A CORREO DE VOZ . | W49: VISITA_TÉCNICA | X49: NONE | Y49: TIPO I | Z49: TERRESTRE | AA49: DEVIA REINOSO JUAN CARLOS | AB49: 1 | AC49: =IF(AND(W49="SOPORTE_TELEFÓNICO",OR(U49="SIN CONTACTO CON EL CB",U49="NÚMEROS DE CONTACTO ERRADOS")),0,IF(W49="SOPORTE_TELEFÓNICO",'BASE DE LIQUIDACION 2025'!$B$9,IF(Y49="TIPO I",'BASE DE LIQUIDACION 2025'!$C$3,IF(Y49="TIPO II",'BASE DE LIQUIDACION 2025'!$C$4,IF(Y49="TIPO III",'BASE DE LIQUIDACION 2025'!$C$5,'BASE DE LIQUIDACION 2025'!$C$6))))) -> 44559.564 | AD49: =IF(W49="SOPORTE_TELEFÓNICO",AC49,CIERRES!AB49*CIERRES!AC49) -> 44559.564
A50: PEREIRA | B50: =VLOOKUP(A50,'CENTRO DE COSTOS'!A:D,4,FALSE) -> DIEGO FERNANDO HENAO CARDONA | C50: =VLOOKUP(A50,'CENTRO DE COSTOS'!A:C,2,FALSE) -> 0004-0002 | D50: 63001 | E50: TA-25-846846 | F50: 70762 | G50: ORDEN DE CAMBIO | H50: QUINDIO | I50: ARMENIA | J50: DISTRICOL MAWI AXM | K50: REDEBAN | L50: FO-25-1205684 | M50: 45847.453 | N50: 45850.484 | P50: CIERRE | Q50: CIERRE | R50: AGREGADOR | S50: DISTRICOL | T50: NO_EXITOSO | U50: CB NO ENTREGA EQUIPO | V50: 12-07-2025 SE LLAMA AL SEÑOR WILLIAM FERNANDO SALEJ ISAZA AL TELÉFONO 3203592999 INDICA QUE DISTRICOL LE SOLICITÓ QUE ENVIARÁ LOS EQUIPOS A LA OFICINA DE ELLOS UBICADA EN MEDELLÍN. | W50: SOPORTE_TELEFÓNICO | X50: 0 | Y50: TIPO II | Z50: TERRESTRE | AA50: SANCHEZ SOLORZANO JUAN SEBASTIAN | AB50: 0 | AC50: =IF(AND(W50="SOPORTE_TELEFÓNICO",OR(U50="SIN CONTACTO CON EL CB",U50="NÚMEROS DE CONTACTO ERRADOS")),0,IF(W50="SOPORTE_TELEFÓNICO",'BASE DE LIQUIDACION 2025'!$B$9,IF(Y50="TIPO I",'BASE DE LIQUIDACION 2025'!$C$3,IF(Y50="TIPO II",'BASE DE LIQUIDACION 2025'!$C$4,IF(Y50="TIPO III",'BASE DE LIQUIDACION 2025'!$C$5,'BASE DE LIQUIDACION 2025'!$C$6))))) -> 37904.612 | AD50: =IF(W50="SOPORTE_TELEFÓNICO",AC50,CIERRES!AB50*CIERRES!AC50) -> 37904.612
A51: TUNJA | B51: =VLOOKUP(A51,'CENTRO DE COSTOS'!A:D,4,FALSE) -> MIGUEL JULIÁN HERNÁNDEZ GUARÍN | C51: =VLOOKUP(A51,'CENTRO DE COSTOS'!A:C,2,FALSE) -> 0004-0008 | D51: 15001 | E51: TA-25-853111 | F51: 35964 | G51: ORDEN DE CAMBIO | H51: BOYACA | I51: TUNJA | J51: BARRIO PORTAL DE OTONO TUNJA | K51: REDEBAN | L51: FO-25-1217980 | M51: 45849.485 | N51: 45850.576 | P51: CIERRE | Q51: CIERRE | R51: CB UNO A UNO | S51: CB UNO A UNO | T51: ILOCALIZADO | U51: CB CERRADO - DESOCUPADO | V51: 12-07-2025 SE VISITA COMERCIO , COMERCIO CERRADO , SE INTENTA COMUNICACIÓN CON EL USUARIO AL NUNERO CELULAR 3208465893 SE LLAMA EN VARIAS OCASIONES Y NO ES POSIBLE LA COMUNICACIÓN, SE DEJA MENSAJE VÍA WHATSAPP Y TAMPOCO HAY RESPUESTA , SE COERRA ORDEN POS ILOCALIZABLE | W51: VISITA_TÉCNICA | X51: 9A008539 | Y51: TIPO I | Z51: TERRESTRE | AA51: ALVARADO MORENO CRISTHIAN | AB51: 1 | AC51: =IF(AND(W51="SOPORTE_TELEFÓNICO",OR(U51="SIN CONTACTO CON EL CB",U51="NÚMEROS DE CONTACTO ERRADOS")),0,IF(W51="SOPORTE_TELEFÓNICO",'BASE DE LIQUIDACION 2025'!$B$9,IF(Y51="TIPO I",'BASE DE LIQUIDACION 2025'!$C$3,IF(Y51="TIPO II",'BASE DE LIQUIDACION 2025'!$C$4,IF(Y51="TIPO III",'BASE DE LIQUIDACION 2025'!$C$5,'BASE DE LIQUIDACION 2025'!$C$6))))) -> 44559.564 | AD51: =IF(W51="SOPORTE_TELEFÓNICO",AC51,CIERRES!AB51*CIERRES!AC51) -> 44559.564
A52: BARRANQUILLA | B52: =VLOOKUP(A52,'CENTRO DE COSTOS'!A:D,4,FALSE) -> JOSE MAURICIO HERNANDEZ ROJAS | C52: =VLOOKUP(A52,'CENTRO DE COSTOS'!A:C,2,FALSE) -> 0004-0001 | D52: 8758 | E52: TA-25-853103 | F52: 27329 | G52: ORDEN DE CAMBIO | H52: ATLANTICO | I52: SOLEDAD | J52: BARRIO SOLEDAD 2000 SOLEDAD | K52: REDEBAN | L52: FO-25-1217960 | M52: 45849.485 | N52: 45851.493 | P52: CIERRE | Q52: CIERRE | R52: CB UNO A UNO | S52: CB UNO A UNO | T52: NO_EXITOSO | U52: CB NO ENTREGA EQUIPO | V52: 13-07-2025 SE REALIZA VISITA AL COMERCIO PARA REALIZAR EL CIERRE DEL CORRESPONSAL BANCOLOMBIA PERO NO ES POSIBLE ME COMUNICO CON EL NÚMERO DADO Y ME MANIFIESTA QUE NO SE ENCUENTRA EN LA CIUDAD LE COMUNICO QUE CUANDO ESTÉ EN LA CIUDAD SE COMUNIQUE CON LA LÍNEA DE SOPORTE PARA REAGENDAR LA VISITA | W52: VISITA_TÉCNICA | X52: 9A003154 | Y52: TIPO I | Z52: TERRESTRE | AA52: PEÑALOZA GUTIERREZ RAFAEL GUSTAVO | AB52: 1 | AC52: =IF(AND(W52="SOPORTE_TELEFÓNICO",OR(U52="SIN CONTACTO CON EL CB",U52="NÚMEROS DE CONTACTO ERRADOS")),0,IF(W52="SOPORTE_TELEFÓNICO",'BASE DE LIQUIDACION 2025'!$B$9,IF(Y52="TIPO I",'BASE DE LIQUIDACION 2025'!$C$3,IF(Y52="TIPO II",'BASE DE LIQUIDACION 2025'!$C$4,IF(Y52="TIPO III",'BASE DE LIQUIDACION 2025'!$C$5,'BASE DE LIQUIDACION 2025'!$C$6))))) -> 44559.564 | AD52: =IF(W52="SOPORTE_TELEFÓNICO",AC52,CIERRES!AB52*CIERRES!AC52) -> 44559.564
A53: PEREIRA | B53: =VLOOKUP(A53,'CENTRO DE COSTOS'!A:D,4,FALSE) -> DIEGO FERNANDO HENAO CARDONA | C53: =VLOOKUP(A53,'CENTRO DE COSTOS'!A:C,2,FALSE) -> 0004-0002 | D53: 66170 | E53: TA-25-846841 | F53: 48233 | G53: ORDEN DE CAMBIO | H53: RISARALDA | I53: DOSQUEBRADAS | J53: DISTRICOL TECNOCOMPUTER JG | K53: REDEBAN | L53: FO-25-1205661 | M53: 45847.453 | N53: 45852.375 | P53: CIERRE | Q53: CIERRE | R53: AGREGADOR | S53: DISTRICOL | T53: ILOCALIZADO | U53: CB CERRADO - DESOCUPADO | V53: 14-07-2025 SE LLEGA AL PUNTO, EL ESTABLECIMIENTO ESTÁ SIN SERVICIO Y NO CONTESTAN LAS LLAMADAS. | W53: VISITA_TÉCNICA | X53: 0 | Y53: TIPO I | Z53: TERRESTRE | AA53: FRANCO CAÑAVERAL YAMID RAUL | AB53: 1 | AC53: =IF(AND(W53="SOPORTE_TELEFÓNICO",OR(U53="SIN CONTACTO CON EL CB",U53="NÚMEROS DE CONTACTO ERRADOS")),0,IF(W53="SOPORTE_TELEFÓNICO",'BASE DE LIQUIDACION 2025'!$B$9,IF(Y53="TIPO I",'BASE DE LIQUIDACION 2025'!$C$3,IF(Y53="TIPO II",'BASE DE LIQUIDACION 2025'!$C$4,IF(Y53="TIPO III",'BASE DE LIQUIDACION 2025'!$C$5,'BASE DE LIQUIDACION 2025'!$C$6))))) -> 44559.564 | AD53: =IF(W53="SOPORTE_TELEFÓNICO",AC53,CIERRES!AB53*CIERRES!AC53) -> 44559.564
A54: CUCUTA | B54: =VLOOKUP(A54,'CENTRO DE COSTOS'!A:D,4,FALSE) -> MIGUEL JULIÁN HERNÁNDEZ GUARÍN | C54: =VLOOKUP(A54,'CENTRO DE COSTOS'!A:C,2,FALSE) -> 0004-0008 | D54: 54810 | E54: TA-25-839291 | F54: 71753 | G54: ORDEN DE CAMBIO | H54: NORTE DE SANTANDER | I54: TIBU | J54: PTM TIBU SUPERMERCADO DO#A GLA | K54: REDEBAN | L54: FO-25-1196162 | M54: 45845.653 | N54: 45852.476 | P54: CIERRE | Q54: CIERRE | R54: AGREGADOR | S54: COMCARD - PTM | T54: NO_EXITOSO | U54: CB NO ENTREGA EQUIPO | V54: 14-07-2025 SE COMUNICA CON LA CLIENTE SORAIDA VIA WHATSAP AL # 3112320878, NOS INFORMA QUE NO PUDO VIAJAR EL DIA DE HOY, DEBIDO A LA SITUACION DE ORDEN PUBLICO PARA LA ENTREGA DE EQUIPOS, SE LE INFORMA QUE TAN PRONTO PUEDA SE COMUNIQUE CON LA ENTIDAD. | W54: SOPORTE_TELEFÓNICO | X54: 0 | Y54: TIPO IV ESPECIAL | Z54: TERRESTRE | AA54: NARANJO AFANADOR RUBEN JESUS | AB54: 0 | AC54: =IF(AND(W54="SOPORTE_TELEFÓNICO",OR(U54="SIN CONTACTO CON EL CB",U54="NÚMEROS DE CONTACTO ERRADOS")),0,IF(W54="SOPORTE_TELEFÓNICO",'BASE DE LIQUIDACION 2025'!$B$9,IF(Y54="TIPO I",'BASE DE LIQUIDACION 2025'!$C$3,IF(Y54="TIPO II",'BASE DE LIQUIDACION 2025'!$C$4,IF(Y54="TIPO III",'BASE DE LIQUIDACION 2025'!$C$5,'BASE DE LIQUIDACION 2025'!$C$6))))) -> 37904.612 | AD54: =IF(W54="SOPORTE_TELEFÓNICO",AC54,CIERRES!AB54*CIERRES!AC54) -> 37904.612
A55: CUCUTA | B55: =VLOOKUP(A55,'CENTRO DE COSTOS'!A:D,4,FALSE) -> MIGUEL JULIÁN HERNÁNDEZ GUARÍN | C55: =VLOOKUP(A55,'CENTRO DE COSTOS'!A:C,2,FALSE) -> 0004-0008 | D55: 54001 | E55: TA-25-853184 | F55: 77344 | G55: ORDEN DE CAMBIO | H55: CUCUTA | I55: NORTE DE SANTANDER | J55: BARRIO AGUAS CALIENTES CUCUTA | K55: REDEBAN | L55: FO-25-1222121 | M55: 45849.485 | N55: 45852.485 | P55: CIERRE | Q55: CIERRE | R55: CB UNO A UNO | S55: CB UNO A UNO | T55: EJECUTADO_EXITOSO | U55: CIERRE EXITOSO | V55: 14-07-2025 SE REALIZÓ VISITA AL COMERCIO Y SE REALIZA CIERRE DE CB, SE RECOJE DATAFONO, LECTORA CABLEADO, PUBLICIDAD FUE DESTRUIDA POR SU MAL ESTADO | W55: VISITA_TÉCNICA | X55: FAEZZ425 | Y55: TIPO I | Z55: TERRESTRE | AA55: HERNANDEZ GUARIN MIGUEL JULIAN | AB55: 1 | AC55: =IF(AND(W55="SOPORTE_TELEFÓNICO",OR(U55="SIN CONTACTO CON EL CB",U55="NÚMEROS DE CONTACTO ERRADOS")),0,IF(W55="SOPORTE_TELEFÓNICO",'BASE DE LIQUIDACION 2025'!$B$9,IF(Y55="TIPO I",'BASE DE LIQUIDACION 2025'!$C$3,IF(Y55="TIPO II",'BASE DE LIQUIDACION 2025'!$C$4,IF(Y55="TIPO III",'BASE DE LIQUIDACION 2025'!$C$5,'BASE DE LIQUIDACION 2025'!$C$6))))) -> 44559.564 | AD55: =IF(W55="SOPORTE_TELEFÓNICO",AC55,CIERRES!AB55*CIERRES!AC55) -> 44559.564
A56: PASTO | B56: =VLOOKUP(A56,'CENTRO DE COSTOS'!A:D,4,FALSE) -> DIEGO FERNANDO HENAO CARDONA | C56: =VLOOKUP(A56,'CENTRO DE COSTOS'!A:C,2,FALSE) -> 0004-0003 | D56: 86573 | E56: TA-25-809607 | F56: 51784 | G56: ORDEN DE CAMBIO | H56: PUTUMAYO | I56: LEGUIZAMO | J56: BARRIO MUELLE ALTERNO PUERTO L | K56: REDEBAN | L56: FO-25-1148281 | M56: 45836.333 | N56: 45853.355 | P56: CIERRE | Q56: CIERRE | R56: CB UNO A UNO | S56: CB UNO A UNO | T56: NO_EXITOSO | U56: CB NO ENTREGA EQUIPO | V56: 15-07-2025 SE LOGRA ENTABLAR COMUNICACION CON EL SEÑOR GERARDO, QUIEN INDICA QUE ESTAN EN VALIDACIONES CON LA ENTIDAD PARA REVISAR MOTIVO DEL CIERRE, YA QUE NO LE HAN INFORMADO NADA, TAN PRONTO TENGA LA RESPUESTA, SE COMUNICARA PARA PODER VALIDAR SI SE REALIZA RETIRO DE EQUIPO O COMO REALIZARA LA ENTREGA DE LOS MISMO | W56: SOPORTE_TELEFÓNICO | X56: 0 | Y56: TIPO IV | Z56: AEREO | AA56: GUERRERO RAMIREZ OSCAR DARIO | AB56: 0 | AC56: =IF(AND(W56="SOPORTE_TELEFÓNICO",OR(U56="SIN CONTACTO CON EL CB",U56="NÚMEROS DE CONTACTO ERRADOS")),0,IF(W56="SOPORTE_TELEFÓNICO",'BASE DE LIQUIDACION 2025'!$B$9,IF(Y56="TIPO I",'BASE DE LIQUIDACION 2025'!$C$3,IF(Y56="TIPO II",'BASE DE LIQUIDACION 2025'!$C$4,IF(Y56="TIPO III",'BASE DE LIQUIDACION 2025'!$C$5,'BASE DE LIQUIDACION 2025'!$C$6))))) -> 37904.612 | AD56: =IF(W56="SOPORTE_TELEFÓNICO",AC56,CIERRES!AB56*CIERRES!AC56) -> 37904.612
A57: BOGOTA | B57: =VLOOKUP(A57,'CENTRO DE COSTOS'!A:D,4,FALSE) -> WILLIAM ASDRUBAL ROZO ROZO | C57: =VLOOKUP(A57,'CENTRO DE COSTOS'!A:C,2,FALSE) -> 0004-0004 | D57: 25297 | E57: TA-25-853148 | F57: 22168 | G57: ORDEN DE CAMBIO | H57: CUNDINAMARCA | I57: GACHETA | J57: CENTRO GACHETA I CUNDINAMARCA | K57: REDEBAN | L57: FO-25-1218038 | M57: 45849.485 | N57: 45853.356 | P57: CIERRE | Q57: CIERRE | R57: CB UNO A UNO | S57: CB UNO A UNO | T57: NO_EXITOSO | U57: MIXTO UNO A UNO NO COBRAR | V57: 14-07-2025 SE REALIZA CONTACTO CON CLIENTE PARA CONFIRMAR VISITA CLIENTE INFORMA QUE DÍAS ANTERIORES YA FUE VISITADO Y LE REALIZARON EL CIERRE | W57: SOPORTE_TELEFÓNICO | X57: 0 | Y57: TIPO III | Z57: TERRESTRE | AA57: GALINDO ROJAS LUIS FELIPE | AB57: 0 | AC57: =IF(AND(W57="SOPORTE_TELEFÓNICO",OR(U57="SIN CONTACTO CON EL CB",U57="NÚMEROS DE CONTACTO ERRADOS")),0,IF(W57="SOPORTE_TELEFÓNICO",'BASE DE LIQUIDACION 2025'!$B$9,IF(Y57="TIPO I",'BASE DE LIQUIDACION 2025'!$C$3,IF(Y57="TIPO II",'BASE DE LIQUIDACION 2025'!$C$4,IF(Y57="TIPO III",'BASE DE LIQUIDACION 2025'!$C$5,'BASE DE LIQUIDACION 2025'!$C$6))))) -> 37904.612 | AD57: =IF(W57="SOPORTE_TELEFÓNICO",AC57,CIERRES!AB57*CIERRES!AC57) -> 37904.612
A58: NEIVA | B58: =VLOOKUP(A58,'CENTRO DE COSTOS'!A:D,4,FALSE) -> KEVIN ALEXIS CORZO BUSTOS | C58: =VLOOKUP(A58,'CENTRO DE COSTOS'!A:C,2,FALSE) -> 0004-0007 | D58: 41551 | E58: TA-25-853161 | F58: 59370 | G58: ORDEN DE CAMBIO | H58: HUILA | I58: PITALITO | J58: BARRIO CENTRO PITALITO 19 | K58: REDEBAN | L58: FO-25-1218059 | M58: 45849.485 | N58: 45853.438 | P58: CIERRE | Q58: CIERRE | R58: CB UNO A UNO | S58: CB UNO A UNO | T58: SOLICITUD_CANCELADA | U58: CANCELADO POR LA ENTIDAD | V58: 15-07-2025 SE CANCELA CIERRE POR SOLICITUD DE LA ENTIDAD | W58: SOPORTE_TELEFÓNICO | X58: 0 | Y58: TIPO III | Z58: TERRESTRE | AA58: ANDRADE HERNANDEZ JUAN CARLOS | AB58: 0 | AC58: =IF(AND(W58="SOPORTE_TELEFÓNICO",OR(U58="SIN CONTACTO CON EL CB",U58="NÚMEROS DE CONTACTO ERRADOS")),0,IF(W58="SOPORTE_TELEFÓNICO",'BASE DE LIQUIDACION 2025'!$B$9,IF(Y58="TIPO I",'BASE DE LIQUIDACION 2025'!$C$3,IF(Y58="TIPO II",'BASE DE LIQUIDACION 2025'!$C$4,IF(Y58="TIPO III",'BASE DE LIQUIDACION 2025'!$C$5,'BASE DE LIQUIDACION 2025'!$C$6))))) -> 37904.612 | AD58: =IF(W58="SOPORTE_TELEFÓNICO",AC58,CIERRES!AB58*CIERRES!AC58) -> 37904.612
A59: NEIVA | B59: =VLOOKUP(A59,'CENTRO DE COSTOS'!A:D,4,FALSE) -> KEVIN ALEXIS CORZO BUSTOS | C59: =VLOOKUP(A59,'CENTRO DE COSTOS'!A:C,2,FALSE) -> 0004-0007 | D59: 18001 | E59: TA-25-847305 | F59: 77200 | G59: ORDEN DE CAMBIO | H59: CAQUETA | I59: FLORENCIA | J59: BARRIO CENTRO FLORENCIA 35 | K59: REDEBAN | L59: FO-25-1221813 | M59: 45847.543 | N59: 45853.452 | P59: CIERRE | Q59: CIERRE | R59: CB UNO A UNO | S59: CB UNO A UNO | T59: EJECUTADO_EXITOSO | U59: CIERRE EXITOSO | V59: 15-07-2025 SE REALIZA RETIRO DE DATAFONO, LECTORA, BASE, FUENTE, AVISO EXTERIOR Y PUBLICIDAD, EL AVISO EXTERIOR Y LA PUBLICIDAD SE DESTRUYE, CIERRE EXITOSO. | W59: VISITA_TÉCNICA | X59: SX7ZZ202 | Y59: TIPO IV | Z59: TERRESTRE | AA59: BERMUDEZ SANCHEZ JOSE NEYBER | AB59: 1 | AC59: =IF(AND(W59="SOPORTE_TELEFÓNICO",OR(U59="SIN CONTACTO CON EL CB",U59="NÚMEROS DE CONTACTO ERRADOS")),0,IF(W59="SOPORTE_TELEFÓNICO",'BASE DE LIQUIDACION 2025'!$B$9,IF(Y59="TIPO I",'BASE DE LIQUIDACION 2025'!$C$3,IF(Y59="TIPO II",'BASE DE LIQUIDACION 2025'!$C$4,IF(Y59="TIPO III",'BASE DE LIQUIDACION 2025'!$C$5,'BASE DE LIQUIDACION 2025'!$C$6))))) -> 464809.37 | AD59: =IF(W59="SOPORTE_TELEFÓNICO",AC59,CIERRES!AB59*CIERRES!AC59) -> 464809.37
A60: MEDELLIN | B60: =VLOOKUP(A60,'CENTRO DE COSTOS'!A:D,4,FALSE) -> JUAN SEBASTIÁN RÍOS CASTRILLÓN | C60: =VLOOKUP(A60,'CENTRO DE COSTOS'!A:C,2,FALSE) -> 0004-0005 | D60: 5321 | E60: TA-25-846833 | F60: 45211 | G60: ORDEN DE CAMBIO | H60: ANTIOQUIA | I60: GUATAPE | J60: DISTRICOL AUTOSERVICIO LA TRIB | K60: REDEBAN | L60: FO-25-1205621 | M60: 45847.453 | N60: 45853.455 | P60: CIERRE | Q60: CIERRE | R60: AGREGADOR | S60: DISTRICOL | T60: NO_EXITOSO | U60: CB NO ENTREGA EQUIPO | V60: 15-07-2025 CIERRE FALLIDO SE LLEGA LA PUNTO PERO CLIENTE INFORMA QUE HACE 8 DÍAS ENVÍO LOS EQUIPOS A DISTRICOL | W60: VISITA_TÉCNICA | X60: GA0LZ478 | Y60: TIPO II | Z60: TERRESTRE | AA60: ALVAREZ ARENAS VICTOR HUGO | AB60: 1 | AC60: =IF(AND(W60="SOPORTE_TELEFÓNICO",OR(U60="SIN CONTACTO CON EL CB",U60="NÚMEROS DE CONTACTO ERRADOS")),0,IF(W60="SOPORTE_TELEFÓNICO",'BASE DE LIQUIDACION 2025'!$B$9,IF(Y60="TIPO I",'BASE DE LIQUIDACION 2025'!$C$3,IF(Y60="TIPO II",'BASE DE LIQUIDACION 2025'!$C$4,IF(Y60="TIPO III",'BASE DE LIQUIDACION 2025'!$C$5,'BASE DE LIQUIDACION 2025'!$C$6))))) -> 134410.88 | AD60: =IF(W60="SOPORTE_TELEFÓNICO",AC60,CIERRES!AB60*CIERRES!AC60) -> 134410.88
A61: BOGOTA | B61: =VLOOKUP(A61,'CENTRO DE COSTOS'!A:D,4,FALSE) -> WILLIAM ASDRUBAL ROZO ROZO | C61: =VLOOKUP(A61,'CENTRO DE COSTOS'!A:C,2,FALSE) -> 0004-0004 | D61: 11001 | E61: TA-25-853211 | F61: 57736 | G61: ORDEN DE CAMBIO | H61: CUNDINAMARCA | I61: BOGOTA | J61: BARRIO PIO XII BOGOTA 4 | K61: REDEBAN | L61: FO-25-1229260 | M61: 45849.485 | N61: 45853.667 | P61: CIERRE | Q61: CIERRE | R61: CB UNO A UNO | S61: CB UNO A UNO | T61: ILOCALIZADO | U61: CB CERRADO - DESOCUPADO | V61: 15-07-2025 SE REALIZA VISITA AL COMERCIO PARA EJECUTAR CIERRE DE CB BANCOLOMBIA PERO AL LLEGAR AL PUNTO SE ENCUENTRA CERRADO, SE INTENTA CONTACTO CON EL CLIENTE AL NÚMERO 3104724202 Y NO HAY RESPUESTA. 2 VISITA SE CIERRA ACTIVIDAD. | W61: VISITA_TÉCNICA | X61: 0 | Y61: TIPO I | Z61: TERRESTRE | AA61: CORTES VELANDIA MIGUEL ANGEL | AB61: 2 | AC61: =IF(AND(W61="SOPORTE_TELEFÓNICO",OR(U61="SIN CONTACTO CON EL CB",U61="NÚMEROS DE CONTACTO ERRADOS")),0,IF(W61="SOPORTE_TELEFÓNICO",'BASE DE LIQUIDACION 2025'!$B$9,IF(Y61="TIPO I",'BASE DE LIQUIDACION 2025'!$C$3,IF(Y61="TIPO II",'BASE DE LIQUIDACION 2025'!$C$4,IF(Y61="TIPO III",'BASE DE LIQUIDACION 2025'!$C$5,'BASE DE LIQUIDACION 2025'!$C$6))))) -> 44559.564 | AD61: =IF(W61="SOPORTE_TELEFÓNICO",AC61,CIERRES!AB61*CIERRES!AC61) -> 89119.128
A62: CUCUTA | B62: =VLOOKUP(A62,'CENTRO DE COSTOS'!A:D,4,FALSE) -> MIGUEL JULIÁN HERNÁNDEZ GUARÍN | C62: =VLOOKUP(A62,'CENTRO DE COSTOS'!A:C,2,FALSE) -> 0004-0008 | D62: 54001 | E62: TA-25-858530 | F62: 71022 | G62: ORDEN DE CAMBIO | H62: NORTE DE SANTANDER | I62: CUCUTA | J62: DISTRICOL CENTROPAG | K62: REDEBAN | L62: FO-25-1231199 | M62: 45853.333 | N62: 45854.348 | P62: CIERRE | Q62: CIERRE | R62: AGREGADOR | S62: DISTRICOL | T62: ILOCALIZADO | U62: CB CERRADO - DESOCUPADO | V62: 16-07-2025 SE VISITA COMERCIO Y SE ENCUENTRA CERRADO SE LLAMA AL CLIENTE Y NO CONTESTA, SE DEJA MENSAJE POR WHATSAPP Y NO SE OBTIENE RESPUESTA. | W62: VISITA_TÉCNICA | X62: 0 | Y62: TIPO I | Z62: TERRESTRE | AA62: TORRES MANTILLA JOSE DANIEL | AB62: 1 | AC62: =IF(AND(W62="SOPORTE_TELEFÓNICO",OR(U62="SIN CONTACTO CON EL CB",U62="NÚMEROS DE CONTACTO ERRADOS")),0,IF(W62="SOPORTE_TELEFÓNICO",'BASE DE LIQUIDACION 2025'!$B$9,IF(Y62="TIPO I",'BASE DE LIQUIDACION 2025'!$C$3,IF(Y62="TIPO II",'BASE DE LIQUIDACION 2025'!$C$4,IF(Y62="TIPO III",'BASE DE LIQUIDACION 2025'!$C$5,'BASE DE LIQUIDACION 2025'!$C$6))))) -> 44559.564 | AD62: =IF(W62="SOPORTE_TELEFÓNICO",AC62,CIERRES!AB62*CIERRES!AC62) -> 44559.564
A63: CALI | B63: =VLOOKUP(A63,'CENTRO DE COSTOS'!A:D,4,FALSE) -> DIEGO FERNANDO HENAO CARDONA | C63: =VLOOKUP(A63,'CENTRO DE COSTOS'!A:C,2,FALSE) -> 0004-0003 | D63: 76001 | E63: TA-25-853197 | F63: 12288 | G63: ORDEN DE CAMBIO | H63: VALLE DEL CAUCA | I63: CALI | J63: BARRIO VALLE GRANDE - CALI | K63: REDEBAN | L63: FO-25-1218109 | M63: 45849.485 | N63: 45854.454 | P63: CIERRE | Q63: CIERRE | R63: CB UNO A UNO | S63: CB UNO A UNO | T63: NO_EXITOSO | U63: CB NO ENTREGA EQUIPO | V63: 12-07-2025 SE LLEGA A SITIO Y EL CB YA NO EXISTE EN EL PUNTO, SE REALIZA COMUNICACION AL NÙMERO 3016621547, EL CUÀL MANIFIESTAN QUE LO ENTREGAN EN OTRA DIRECCIÒN DESPUES DE LAS 12 DE LA TARDE.SE VUELVE Y SE ESCRIBE A LAS 12 PARA QUE BRINDEN LA DIRECCIÒN YNUMERO DE CONTACTO DE LA PERSONA ENCARGADA, PERO NO BRINDAN DICHA INFORMACIÒN.SE SOLICITA REPROGRAMACIÒN DE LA VISITA PARA EL DÌA LUNES. | W63: VISITA_TÉCNICA | X63: 0 | Y63: TIPO I | Z63: TERRESTRE | AA63: TORRES GARCIA JENDRY JOSE | AB63: 1 | AC63: =IF(AND(W63="SOPORTE_TELEFÓNICO",OR(U63="SIN CONTACTO CON EL CB",U63="NÚMEROS DE CONTACTO ERRADOS")),0,IF(W63="SOPORTE_TELEFÓNICO",'BASE DE LIQUIDACION 2025'!$B$9,IF(Y63="TIPO I",'BASE DE LIQUIDACION 2025'!$C$3,IF(Y63="TIPO II",'BASE DE LIQUIDACION 2025'!$C$4,IF(Y63="TIPO III",'BASE DE LIQUIDACION 2025'!$C$5,'BASE DE LIQUIDACION 2025'!$C$6))))) -> 44559.564 | AD63: =IF(W63="SOPORTE_TELEFÓNICO",AC63,CIERRES!AB63*CIERRES!AC63) -> 44559.564
A64: BOGOTA | B64: =VLOOKUP(A64,'CENTRO DE COSTOS'!A:D,4,FALSE) -> WILLIAM ASDRUBAL ROZO ROZO | C64: =VLOOKUP(A64,'CENTRO DE COSTOS'!A:C,2,FALSE) -> 0004-0004 | D64: 11001 | E64: TA-25-853213 | F64: 78624 | G64: ORDEN DE CAMBIO | H64: CUNDINAMARCA | I64: BOGOTA | J64: BARRIO SANTA ANA BOGOTA 1 | K64: REDEBAN | L64: FO-25-1237472 | M64: 45849.485 | N64: 45854.591 | P64: CIERRE | Q64: CIERRE | R64: CB UNO A UNO | S64: CB UNO A UNO | T64: EJECUTADO_EXITOSO | U64: CIERRE EXITOSO | V64: 16-07-2025 SE RETIRA DATÁFONO LECTORA Y SE DESTRUYE PUBLICIDAD EN SITIO | W64: VISITA_TÉCNICA | X64: FAMZZ298 | Y64: TIPO I | Z64: TERRESTRE | AA64: INFANTE SIERRA MANUEL FERNANDO | AB64: 1 | AC64: =IF(AND(W64="SOPORTE_TELEFÓNICO",OR(U64="SIN CONTACTO CON EL CB",U64="NÚMEROS DE CONTACTO ERRADOS")),0,IF(W64="SOPORTE_TELEFÓNICO",'BASE DE LIQUIDACION 2025'!$B$9,IF(Y64="TIPO I",'BASE DE LIQUIDACION 2025'!$C$3,IF(Y64="TIPO II",'BASE DE LIQUIDACION 2025'!$C$4,IF(Y64="TIPO III",'BASE DE LIQUIDACION 2025'!$C$5,'BASE DE LIQUIDACION 2025'!$C$6))))) -> 44559.564 | AD64: =IF(W64="SOPORTE_TELEFÓNICO",AC64,CIERRES!AB64*CIERRES!AC64) -> 44559.564
A65: PASTO | B65: =VLOOKUP(A65,'CENTRO DE COSTOS'!A:D,4,FALSE) -> DIEGO FERNANDO HENAO CARDONA | C65: =VLOOKUP(A65,'CENTRO DE COSTOS'!A:C,2,FALSE) -> 0004-0003 | D65: 52838 | E65: TA-25-858456 | F65: 53979 | G65: ORDEN DE CAMBIO | H65: NARIÑO | I65: TUQUERRES | J65: BARRIO PAILERIA TUQUERRES 1 | K65: REDEBAN | L65: FO-25-1231053 | M65: 45853.333 | N65: 45854.673 | P65: CIERRE | Q65: RECUPERACION DE EQUIPOS | R65: CB UNO A UNO | S65: CB UNO A UNO | T65: NO_EXITOSO | U65: CB NO ENTREGA EQUIPO | V65: 16-07-2025 SE VISITA CLIENTE EN OTRA DIRECCIÓN PARA RECOGIDA DE EQUIPOS POR CIERRE DE CB. SE LLEGA A LAS 2:15, CLIENTE INFORMA QUE SE ENCUENTRA HACIENDO DILIGENCIAS PERSONALES Y QUE LA ESPERE HASTA LAS 3 PM. SE ESPERA EN EL SITIO HASTA LAS 4 PM PERO CLIENTE NO LLEGA. SE ESCALA E INDICAN CERRAR LA ACTIVIDAD, SE DEJA LA RAZÓN QUE DEBE SOLICITAR EN LA LÍNEA LA VISITA TÉCNICA PARA RECOGER EQUIPOS. CIERRE FALLIDO | W65: VISITA_TÉCNICA | X65: 0 | Y65: TIPO II | Z65: TERRESTRE | AA65: CASTILLO HERRERA ALEX RICARDO | AB65: 1 | AC65: =IF(AND(W65="SOPORTE_TELEFÓNICO",OR(U65="SIN CONTACTO CON EL CB",U65="NÚMEROS DE CONTACTO ERRADOS")),0,IF(W65="SOPORTE_TELEFÓNICO",'BASE DE LIQUIDACION 2025'!$B$9,IF(Y65="TIPO I",'BASE DE LIQUIDACION 2025'!$C$3,IF(Y65="TIPO II",'BASE DE LIQUIDACION 2025'!$C$4,IF(Y65="TIPO III",'BASE DE LIQUIDACION 2025'!$C$5,'BASE DE LIQUIDACION 2025'!$C$6))))) -> 134410.88 | AD65: =IF(W65="SOPORTE_TELEFÓNICO",AC65,CIERRES!AB65*CIERRES!AC65) -> 134410.88
A66: BOGOTA | B66: =VLOOKUP(A66,'CENTRO DE COSTOS'!A:D,4,FALSE) -> WILLIAM ASDRUBAL ROZO ROZO | C66: =VLOOKUP(A66,'CENTRO DE COSTOS'!A:C,2,FALSE) -> 0004-0004 | D66: 11001 | E66: TA-25-858581 | F66: 50669 | G66: ORDEN DE CAMBIO | H66: CUNDINAMARCA | I66: BOGOTA | J66: PTM BOGOTA JLB SOUND | K66: REDEBAN | L66: FO-25-1235916 | M66: 45853.333 | N66: 45854.735 | P66: CIERRE | Q66: CIERRE | R66: AGREGADOR | S66: COMCARD - PTM | T66: EJECUTADO_EXITOSO | U66: CIERRE EXITOSO | V66: 16-07-2025 SE REALIZA LA RECEPCIÓN DE EQUIPOS, DATAFONO LECTORA BASE FUENTE | W66: VISITA_TÉCNICA | X66: BA00Y369 | Y66: TIPO I | Z66: TERRESTRE | AA66: SOTO MUNAR DYLAN DAVID | AB66: 1 | AC66: =IF(AND(W66="SOPORTE_TELEFÓNICO",OR(U66="SIN CONTACTO CON EL CB",U66="NÚMEROS DE CONTACTO ERRADOS")),0,IF(W66="SOPORTE_TELEFÓNICO",'BASE DE LIQUIDACION 2025'!$B$9,IF(Y66="TIPO I",'BASE DE LIQUIDACION 2025'!$C$3,IF(Y66="TIPO II",'BASE DE LIQUIDACION 2025'!$C$4,IF(Y66="TIPO III",'BASE DE LIQUIDACION 2025'!$C$5,'BASE DE LIQUIDACION 2025'!$C$6))))) -> 44559.564 | AD66: =IF(W66="SOPORTE_TELEFÓNICO",AC66,CIERRES!AB66*CIERRES!AC66) -> 44559.564
A67: BOGOTA | B67: =VLOOKUP(A67,'CENTRO DE COSTOS'!A:D,4,FALSE) -> WILLIAM ASDRUBAL ROZO ROZO | C67: =VLOOKUP(A67,'CENTRO DE COSTOS'!A:C,2,FALSE) -> 0004-0004 | D67: 11001 | E67: TA-25-853223 | F67: 58583 | G67: ORDEN DE CAMBIO | H67: CUNDINAMARCA | I67: BOGOTA | J67: BARRIO TOBERIN BOGOTA 9 | K67: REDEBAN | L67: FO-25-1236167 | M67: 45849.485 | N67: 45855.351 | P67: CIERRE | Q67: RECUPERACION DE EQUIPOS | R67: CB UNO A UNO | S67: CB UNO A UNO | T67: ILOCALIZADO | U67: CB CERRADO - DESOCUPADO | V67: 17-07-2025 SE LLEGA LA DIRECCIÓN INDICADA, GUARDA INTENTA COMUNICARSE CON EL NÚMERO DEL APARTAMENTO 327 PERO NO ES POSIBLE LA COMUNICACIÓN SE INTENTA COMUNICACIÓN VÍA TELEFÓNICA AL NÚMERO 3003796709 Y TAMPOCO ES POSIBLE | W67: VISITA_TÉCNICA | X67: 0 | Y67: TIPO I | Z67: TERRESTRE | AA67: GARCIA PASTRANA KEVIN FERNANDO | AB67: 2 | AC67: =IF(AND(W67="SOPORTE_TELEFÓNICO",OR(U67="SIN CONTACTO CON EL CB",U67="NÚMEROS DE CONTACTO ERRADOS")),0,IF(W67="SOPORTE_TELEFÓNICO",'BASE DE LIQUIDACION 2025'!$B$9,IF(Y67="TIPO I",'BASE DE LIQUIDACION 2025'!$C$3,IF(Y67="TIPO II",'BASE DE LIQUIDACION 2025'!$C$4,IF(Y67="TIPO III",'BASE DE LIQUIDACION 2025'!$C$5,'BASE DE LIQUIDACION 2025'!$C$6))))) -> 44559.564 | AD67: =IF(W67="SOPORTE_TELEFÓNICO",AC67,CIERRES!AB67*CIERRES!AC67) -> 89119.128
A68: MEDELLIN | B68: =VLOOKUP(A68,'CENTRO DE COSTOS'!A:D,4,FALSE) -> JUAN SEBASTIÁN RÍOS CASTRILLÓN | C68: =VLOOKUP(A68,'CENTRO DE COSTOS'!A:C,2,FALSE) -> 0004-0005 | D68: 27001 | E68: TA-25-853150 | F68: 69593 | G68: ORDEN DE CAMBIO | H68: CHOCO | I68: QUIBDO | J68: BARRIO QUIBDO QUIBDO 5 | K68: REDEBAN | L68: FO-25-1218042 | M68: 45849.485 | N68: 45855.451 | P68: CIERRE | Q68: CIERRE | R68: CB UNO A UNO | S68: CB UNO A UNO | T68: NO_EXITOSO | U68: CB NO ENTREGA EQUIPO | V68: 17-07-2025 SE REALIZA VISITA AL PUNTO PARA EL CIERRE DEL CB, USUARIO NO SE ENCUENTRA EN SITIO, INFORMA EL SEÑOR QUE ESTÁ EN EL NEGOCIO QUE SE ENCUENTRA EN LA CIUDAD DE MEDELLIN, SE GESTIONA LLAMADA PERO NO RESPONDE OK | W68: VISITA_TÉCNICA | X68: 0 | Y68: TIPO IV ESPECIAL | Z68: AEREO | AA68: MARTINEZ TOVAR OSCAR DAVID | AB68: 1 | AC68: =IF(AND(W68="SOPORTE_TELEFÓNICO",OR(U68="SIN CONTACTO CON EL CB",U68="NÚMEROS DE CONTACTO ERRADOS")),0,IF(W68="SOPORTE_TELEFÓNICO",'BASE DE LIQUIDACION 2025'!$B$9,IF(Y68="TIPO I",'BASE DE LIQUIDACION 2025'!$C$3,IF(Y68="TIPO II",'BASE DE LIQUIDACION 2025'!$C$4,IF(Y68="TIPO III",'BASE DE LIQUIDACION 2025'!$C$5,'BASE DE LIQUIDACION 2025'!$C$6))))) -> 464809.37 | AD68: =IF(W68="SOPORTE_TELEFÓNICO",AC68,CIERRES!AB68*CIERRES!AC68) -> 464809.37
A69: IBAGUE | B69: =VLOOKUP(A69,'CENTRO DE COSTOS'!A:D,4,FALSE) -> KEVIN ALEXIS CORZO BUSTOS | C69: =VLOOKUP(A69,'CENTRO DE COSTOS'!A:C,2,FALSE) -> 0004-0007 | D69: 73001 | E69: TA-25-866217 | F69: 44044 | G69: ORDEN DE CAMBIO | H69: TOLIMA | I69: IBAGUE | J69: BARRIO CONDOMINIO EL VERGEL IB | K69: REDEBAN | L69: FO-25-1242999 | M69: 45855.333 | N69: 45855.471 | P69: CIERRE | Q69: CIERRE | R69: CB UNO A UNO | S69: CB UNO A UNO | T69: ILOCALIZADO | U69: CB CERRADO - DESOCUPADO | V69: 17-07-2025 SE LLEGA AL SITIO PARA VALIDAR ACTIVIDAD DE CIERRE, PERO EL COMERCIO SE ENCUENTRA CERRADO; SE VÁLIDA CONTACTO TELEFÓNICO AL NÚMERO 3183812523 SIN NINGÚN RESULTADO. | W69: VISITA_TÉCNICA | X69: 0 | Y69: TIPO I | Z69: TERRESTRE | AA69: BARRAGAN TAFUR EDWIN ESTEBAN | AB69: 1 | AC69: =IF(AND(W69="SOPORTE_TELEFÓNICO",OR(U69="SIN CONTACTO CON EL CB",U69="NÚMEROS DE CONTACTO ERRADOS")),0,IF(W69="SOPORTE_TELEFÓNICO",'BASE DE LIQUIDACION 2025'!$B$9,IF(Y69="TIPO I",'BASE DE LIQUIDACION 2025'!$C$3,IF(Y69="TIPO II",'BASE DE LIQUIDACION 2025'!$C$4,IF(Y69="TIPO III",'BASE DE LIQUIDACION 2025'!$C$5,'BASE DE LIQUIDACION 2025'!$C$6))))) -> 44559.564 | AD69: =IF(W69="SOPORTE_TELEFÓNICO",AC69,CIERRES!AB69*CIERRES!AC69) -> 44559.564
A70: CALI | B70: =VLOOKUP(A70,'CENTRO DE COSTOS'!A:D,4,FALSE) -> DIEGO FERNANDO HENAO CARDONA | C70: =VLOOKUP(A70,'CENTRO DE COSTOS'!A:C,2,FALSE) -> 0004-0003 | D70: 76001 | E70: TA-25-866221 | F70: 70371 | G70: ORDEN DE CAMBIO | H70: VALLE DEL CAUCA | I70: CALI | J70: BARRIO OASIS DE CAMFANDI CALI | K70: REDEBAN | L70: FO-25-1243017 | M70: 45855.333 | N70: 45855.481 | P70: CIERRE | Q70: CIERRE | R70: CB UNO A UNO | S70: CB UNO A UNO | T70: ILOCALIZADO | U70: CB CERRADO - DESOCUPADO | V70: 17-07-2025 SE LLEGA AL COMERCIO PERO EL COMERCIO ESTÁ CERRADO SE LLAMA AL CLIENTE Y EL CLIENTE NO CONTESTA | W70: VISITA_TÉCNICA | X70: NN006465 | Y70: TIPO I | Z70: TERRESTRE | AA70: CUERO RUIZ JHONNY | AB70: 1 | AC70: =IF(AND(W70="SOPORTE_TELEFÓNICO",OR(U70="SIN CONTACTO CON EL CB",U70="NÚMEROS DE CONTACTO ERRADOS")),0,IF(W70="SOPORTE_TELEFÓNICO",'BASE DE LIQUIDACION 2025'!$B$9,IF(Y70="TIPO I",'BASE DE LIQUIDACION 2025'!$C$3,IF(Y70="TIPO II",'BASE DE LIQUIDACION 2025'!$C$4,IF(Y70="TIPO III",'BASE DE LIQUIDACION 2025'!$C$5,'BASE DE LIQUIDACION 2025'!$C$6))))) -> 44559.564 | AD70: =IF(W70="SOPORTE_TELEFÓNICO",AC70,CIERRES!AB70*CIERRES!AC70) -> 44559.564
A71: MONTERIA | B71: =VLOOKUP(A71,'CENTRO DE COSTOS'!A:D,4,FALSE) -> JOSE MAURICIO HERNANDEZ ROJAS | C71: =VLOOKUP(A71,'CENTRO DE COSTOS'!A:C,2,FALSE) -> 0004-0001 | D71: 23001 | E71: TA-25-853146 | F71: 43549 | G71: ORDEN DE CAMBIO | H71: CORDOBA | I71: MONTERIA | J71: BARRIO CANTA CLARO MONTERIA | K71: REDEBAN | L71: FO-25-1218035 | M71: 45849.485 | N71: 45856.312 | P71: CIERRE | Q71: CIERRE | R71: CB UNO A UNO | S71: CB UNO A UNO | T71: ILOCALIZADO | U71: CB CERRADO - DESOCUPADO | V71: 17-07-2025 SE VISITA SITIO, NO SE ENCUENTRA CB EN DIRECCIÓN, SE LLAMA A LOS NÚMEROS REGISTRADOS PERO NO RESPONDEN. SE CIERRA ORDEN CON FALLIDA YA QUE NO SE ENCUENTRA NI SE LOGRA COMUNICACIÓN CON CB. | W71: VISITA_TÉCNICA | X71: 0 | Y71: TIPO I | Z71: TERRESTRE | AA71: COGOLLO VERTEL EDER LUIS | AB71: 1 | AC71: =IF(AND(W71="SOPORTE_TELEFÓNICO",OR(U71="SIN CONTACTO CON EL CB",U71="NÚMEROS DE CONTACTO ERRADOS")),0,IF(W71="SOPORTE_TELEFÓNICO",'BASE DE LIQUIDACION 2025'!$B$9,IF(Y71="TIPO I",'BASE DE LIQUIDACION 2025'!$C$3,IF(Y71="TIPO II",'BASE DE LIQUIDACION 2025'!$C$4,IF(Y71="TIPO III",'BASE DE LIQUIDACION 2025'!$C$5,'BASE DE LIQUIDACION 2025'!$C$6))))) -> 44559.564 | AD71: =IF(W71="SOPORTE_TELEFÓNICO",AC71,CIERRES!AB71*CIERRES!AC71) -> 44559.564
A72: BOGOTA | B72: =VLOOKUP(A72,'CENTRO DE COSTOS'!A:D,4,FALSE) -> WILLIAM ASDRUBAL ROZO ROZO | C72: =VLOOKUP(A72,'CENTRO DE COSTOS'!A:C,2,FALSE) -> 0004-0004 | D72: 25286 | E72: TA-25-858458 | F72: 62043 | G72: ORDEN DE CAMBIO | H72: CUNDINAMARCA | I72: FUNZA | J72: BARRIO VILLA ADRIANA FUNZA | K72: REDEBAN | L72: FO-25-1231058 | M72: 45853.333 | N72: 45856.438 | P72: CIERRE | Q72: RECUPERACION DE EQUIPOS | R72: CB UNO A UNO | S72: CB UNO A UNO | T72: ILOCALIZADO | U72: CB CERRADO - DESOCUPADO | V72: 18-07-2025 DURANTE LA VISITA TECNICA A COMERCIO AL LLEGAR SE EVIDENCIA QUE COMERCIO SE ENCUENTRA CERRADO SE LLAMA AL CELULAR 3204098814 SIN TENER RESPUESTA O CUELGA LA LLAMADA SE DEJA SOPORTÉ FOTOGRÁFICO | W72: VISITA_TÉCNICA | X72: KA00M315 | Y72: TIPO II | Z72: TERRESTRE | AA72: GALEANO SORIANO JUAN DAVID | AB72: 1 | AC72: =IF(AND(W72="SOPORTE_TELEFÓNICO",OR(U72="SIN CONTACTO CON EL CB",U72="NÚMEROS DE CONTACTO ERRADOS")),0,IF(W72="SOPORTE_TELEFÓNICO",'BASE DE LIQUIDACION 2025'!$B$9,IF(Y72="TIPO I",'BASE DE LIQUIDACION 2025'!$C$3,IF(Y72="TIPO II",'BASE DE LIQUIDACION 2025'!$C$4,IF(Y72="TIPO III",'BASE DE LIQUIDACION 2025'!$C$5,'BASE DE LIQUIDACION 2025'!$C$6))))) -> 134410.88 | AD72: =IF(W72="SOPORTE_TELEFÓNICO",AC72,CIERRES!AB72*CIERRES!AC72) -> 134410.88
A73: PASTO | B73: =VLOOKUP(A73,'CENTRO DE COSTOS'!A:D,4,FALSE) -> DIEGO FERNANDO HENAO CARDONA | C73: =VLOOKUP(A73,'CENTRO DE COSTOS'!A:C,2,FALSE) -> 0004-0003 | D73: 52720 | E73: TA-25-858484 | F73: 76209 | G73: ORDEN DE CAMBIO | H73: NARIÑO | I73: SAPUYES | J73: BARRIO GGT EL ESPINO SAPUYES | K73: REDEBAN | L73: FO-25-1231143 | M73: 45853.333 | N73: 45856.503 | P73: CIERRE | Q73: RECUPERACION DE EQUIPOS | R73: CB UNO A UNO | S73: CB UNO A UNO | T73: NO_EXITOSO | U73: CB NO ENTREGA EQUIPO | V73: 18-07-2025 SE LLAMA AL CLIENTE PARA REALIZAR EL CIERRE INDICA QUE LOS EQUIPOS LOS DEJO EN OTRA DIRECCIÓN QUE ES LA BOMBA DEL CORREGIMIENTO EL ESPINO QUE LOS RECOJA EN ESE SITIO SE LLEGA AL LUGAR PERO INDICAN QUE ALLÍ NO HAY EQUIPOS SE LLAMA ALA CLIENTE PERO YA NO SE OBTIENE RESPUESTA POR PARTE DE ELLA POR LO CUAL SE CIERRA LA TA | W73: VISITA_TÉCNICA | X73: FA0GZ501 | Y73: TIPO II | Z73: TERRESTRE | AA73: PAZ MARTINEZ RICHARD HUMBERTO | AB73: 1 | AC73: =IF(AND(W73="SOPORTE_TELEFÓNICO",OR(U73="SIN CONTACTO CON EL CB",U73="NÚMEROS DE CONTACTO ERRADOS")),0,IF(W73="SOPORTE_TELEFÓNICO",'BASE DE LIQUIDACION 2025'!$B$9,IF(Y73="TIPO I",'BASE DE LIQUIDACION 2025'!$C$3,IF(Y73="TIPO II",'BASE DE LIQUIDACION 2025'!$C$4,IF(Y73="TIPO III",'BASE DE LIQUIDACION 2025'!$C$5,'BASE DE LIQUIDACION 2025'!$C$6))))) -> 134410.88 | AD73: =IF(W73="SOPORTE_TELEFÓNICO",AC73,CIERRES!AB73*CIERRES!AC73) -> 134410.88
A74: MONTERIA | B74: =VLOOKUP(A74,'CENTRO DE COSTOS'!A:D,4,FALSE) -> JOSE MAURICIO HERNANDEZ ROJAS | C74: =VLOOKUP(A74,'CENTRO DE COSTOS'!A:C,2,FALSE) -> 0004-0001 | D74: 23162 | E74: TA-25-869951 | F74: 77163 | G74: ORDEN DE CAMBIO | H74: CORDOBA | I74: CERETE | J74: BARRIO SANTA CLARA CERETE | K74: REDEBAN | L74: FO-25-1249401 | M74: 45856.333 | N74: 45856.554 | P74: CIERRE | Q74: CIERRE | R74: CB UNO A UNO | S74: CB UNO A UNO | T74: NO_EXITOSO | U74: CB NO ENTREGA EQUIPO | V74: 18-07-2025 SE REALIZA VISITA AL PUNTO PARA RETIRO DE EQUIPOS POR CIERRE DE CORRESPONSAL, CLIENTE INDICA QUE TIENE INCONVENIENTES CON LA FACTURACIÓN ELÉCTRICA Y CUENTA CON RADICADO NÚMERO 13661274 PARA DAR SOLUCIÓN Y REACTIVAR EL SERVICIO, POR TAL MOTIVOS NO ENTREGA LOS EQUIPOS A RETIRAR. | W74: VISITA_TÉCNICA | X74: 0 | Y74: TIPO I | Z74: TERRESTRE | AA74: GONZALEZ FERRER JESUS ALEXANDER | AB74: 1 | AC74: =IF(AND(W74="SOPORTE_TELEFÓNICO",OR(U74="SIN CONTACTO CON EL CB",U74="NÚMEROS DE CONTACTO ERRADOS")),0,IF(W74="SOPORTE_TELEFÓNICO",'BASE DE LIQUIDACION 2025'!$B$9,IF(Y74="TIPO I",'BASE DE LIQUIDACION 2025'!$C$3,IF(Y74="TIPO II",'BASE DE LIQUIDACION 2025'!$C$4,IF(Y74="TIPO III",'BASE DE LIQUIDACION 2025'!$C$5,'BASE DE LIQUIDACION 2025'!$C$6))))) -> 44559.564 | AD74: =IF(W74="SOPORTE_TELEFÓNICO",AC74,CIERRES!AB74*CIERRES!AC74) -> 44559.564
A75: MONTERIA | B75: =VLOOKUP(A75,'CENTRO DE COSTOS'!A:D,4,FALSE) -> JOSE MAURICIO HERNANDEZ ROJAS | C75: =VLOOKUP(A75,'CENTRO DE COSTOS'!A:C,2,FALSE) -> 0004-0001 | D75: 23001 | E75: TA-25-869797 | F75: 49768 | G75: ORDEN DE CAMBIO | H75: CORDOBA | I75: MONTERIA | J75: BARRIO LAS PARCELAS MOCARI MON | K75: REDEBAN | L75: FO-25-1248805 | M75: 45856.333 | N75: 45856.607 | P75: CIERRE | Q75: CIERRE | R75: CB UNO A UNO | S75: CB UNO A UNO | T75: ILOCALIZADO | U75: CB CERRADO - DESOCUPADO | V75: 18-07-2025 SE REALIZA VISITA AL PUNTO PARA RETIRAR EQUIPOS POR CIERRE DE CORRESPONSAL, SE LLEGA AL COMERCIO ENCONTRANDO EL LOCAL CERRADO, SE INTENTA COMUNICACIÓN CON EL CLIENTE NUMERO SALE APAGADO, COMERCIOS VECINOS INFMAN QUE LA FERRETERÍA DONDE SE INSTALO EL CORRESPONSAL CERRO SUS PUERTAS AL PÚBLICO HACE MESES, NO SE RETIRAN EQUIPOS. | W75: VISITA_TÉCNICA | X75: 0 | Y75: TIPO I | Z75: TERRESTRE | AA75: GONZALEZ FERRER JESUS ALEXANDER | AB75: 1 | AC75: =IF(AND(W75="SOPORTE_TELEFÓNICO",OR(U75="SIN CONTACTO CON EL CB",U75="NÚMEROS DE CONTACTO ERRADOS")),0,IF(W75="SOPORTE_TELEFÓNICO",'BASE DE LIQUIDACION 2025'!$B$9,IF(Y75="TIPO I",'BASE DE LIQUIDACION 2025'!$C$3,IF(Y75="TIPO II",'BASE DE LIQUIDACION 2025'!$C$4,IF(Y75="TIPO III",'BASE DE LIQUIDACION 2025'!$C$5,'BASE DE LIQUIDACION 2025'!$C$6))))) -> 44559.564 | AD75: =IF(W75="SOPORTE_TELEFÓNICO",AC75,CIERRES!AB75*CIERRES!AC75) -> 44559.564
A76: IBAGUE | B76: =VLOOKUP(A76,'CENTRO DE COSTOS'!A:D,4,FALSE) -> KEVIN ALEXIS CORZO BUSTOS | C76: =VLOOKUP(A76,'CENTRO DE COSTOS'!A:C,2,FALSE) -> 0004-0007 | D76: 73001 | E76: TA-25-869954 | F76: 65524 | G76: ORDEN DE CAMBIO | H76: TOLIMA | I76: IBAGUE | J76: PTM IBAGUE DROGUERIA EDISALUD | K76: REDEBAN | L76: FO-25-1249413 | M76: 45856.333 | N76: 45856.617 | P76: CIERRE | Q76: CIERRE | R76: AGREGADOR | S76: COMCARD - PTM | T76: NO_EXITOSO | U76: CB NO ENTREGA EQUIPO | V76: 18-07-2025 SE LLEGA AL SITIO PARA REALIZAR ACTIVIDAD DE CIERRE, PERO NO ES POSIBLE DEBIDO A QUE NO SE ENCUENTRA LA PERSONA ENCARGADA NO HAY AUTORIZACIÓN PARA ENTREGAR EQUIPOS. | W76: VISITA_TÉCNICA | X76: 0 | Y76: TIPO I | Z76: TERRESTRE | AA76: BARRAGAN TAFUR EDWIN ESTEBAN | AB76: 1 | AC76: =IF(AND(W76="SOPORTE_TELEFÓNICO",OR(U76="SIN CONTACTO CON EL CB",U76="NÚMEROS DE CONTACTO ERRADOS")),0,IF(W76="SOPORTE_TELEFÓNICO",'BASE DE LIQUIDACION 2025'!$B$9,IF(Y76="TIPO I",'BASE DE LIQUIDACION 2025'!$C$3,IF(Y76="TIPO II",'BASE DE LIQUIDACION 2025'!$C$4,IF(Y76="TIPO III",'BASE DE LIQUIDACION 2025'!$C$5,'BASE DE LIQUIDACION 2025'!$C$6))))) -> 44559.564 | AD76: =IF(W76="SOPORTE_TELEFÓNICO",AC76,CIERRES!AB76*CIERRES!AC76) -> 44559.564
A77: IBAGUE | B77: =VLOOKUP(A77,'CENTRO DE COSTOS'!A:D,4,FALSE) -> KEVIN ALEXIS CORZO BUSTOS | C77: =VLOOKUP(A77,'CENTRO DE COSTOS'!A:C,2,FALSE) -> 0004-0007 | D77: 73001 | E77: TA-25-869824 | F77: 69876 | G77: ORDEN DE CAMBIO | H77: TOLIMA | I77: IBAGUE | J77: PTM IBAGUE TIENDA VALENCIA | K77: REDEBAN | L77: FO-25-1248935 | M77: 45856.333 | N77: 45856.659 | P77: CIERRE | Q77: CIERRE | R77: AGREGADOR | S77: COMCARD - PTM | T77: NO_EXITOSO | U77: CB NO ENTREGA EQUIPO | V77: 18-07-2025 SE LLEGA AL SITIO PARA REALIZAR ACTIVIDAD DE CIERRE, PERO NO ES POSIBLE DEBIDO A QUE NO SE ENCUENTRA LA PERSONA ENCARGADA NO HAY AUTORIZACIÓN PARA ENTREGAR EQUIPOS. CLIENTE NO FIRMA | W77: VISITA_TÉCNICA | X77: 0 | Y77: TIPO I | Z77: TERRESTRE | AA77: BARRAGAN TAFUR EDWIN ESTEBAN | AB77: 1 | AC77: =IF(AND(W77="SOPORTE_TELEFÓNICO",OR(U77="SIN CONTACTO CON EL CB",U77="NÚMEROS DE CONTACTO ERRADOS")),0,IF(W77="SOPORTE_TELEFÓNICO",'BASE DE LIQUIDACION 2025'!$B$9,IF(Y77="TIPO I",'BASE DE LIQUIDACION 2025'!$C$3,IF(Y77="TIPO II",'BASE DE LIQUIDACION 2025'!$C$4,IF(Y77="TIPO III",'BASE DE LIQUIDACION 2025'!$C$5,'BASE DE LIQUIDACION 2025'!$C$6))))) -> 44559.564 | AD77: =IF(W77="SOPORTE_TELEFÓNICO",AC77,CIERRES!AB77*CIERRES!AC77) -> 44559.564
A78: BOGOTA | B78: =VLOOKUP(A78,'CENTRO DE COSTOS'!A:D,4,FALSE) -> WILLIAM ASDRUBAL ROZO ROZO | C78: =VLOOKUP(A78,'CENTRO DE COSTOS'!A:C,2,FALSE) -> 0004-0004 | D78: 11001 | E78: TA-25-858451 | F78: 68172 | G78: ORDEN DE CAMBIO | H78: CUNDINAMARCA | I78: BOGOTA | J78: PALERMO BOGOTA CUNDINAMARCA1 | K78: REDEBAN | L78: FO-25-1241389 | M78: 45853.333 | N78: 45856.685 | P78: CIERRE | Q78: CIERRE | R78: CB UNO A UNO | S78: CB UNO A UNO | T78: EJECUTADO_EXITOSO | U78: CIERRE EXITOSO | V78: 18-07-2025 SE RECOGE DATÁFONO Y LECTORA CB HIZO DISPOSICIÓN FINAL DE LA PUBLICIDAD, PUBLICIDAD ACTUAL ES DEL CB BARRIO PALERMO SUR BOGOTA 2 80117 | W78: VISITA_TÉCNICA | X78: 9L08Z775 | Y78: TIPO I | Z78: TERRESTRE | AA78: MICHELI LOPEZ MIGUEL ANGEL | AB78: 1 | AC78: =IF(AND(W78="SOPORTE_TELEFÓNICO",OR(U78="SIN CONTACTO CON EL CB",U78="NÚMEROS DE CONTACTO ERRADOS")),0,IF(W78="SOPORTE_TELEFÓNICO",'BASE DE LIQUIDACION 2025'!$B$9,IF(Y78="TIPO I",'BASE DE LIQUIDACION 2025'!$C$3,IF(Y78="TIPO II",'BASE DE LIQUIDACION 2025'!$C$4,IF(Y78="TIPO III",'BASE DE LIQUIDACION 2025'!$C$5,'BASE DE LIQUIDACION 2025'!$C$6))))) -> 44559.564 | AD78: =IF(W78="SOPORTE_TELEFÓNICO",AC78,CIERRES!AB78*CIERRES!AC78) -> 44559.564
A79: BOGOTA | B79: =VLOOKUP(A79,'CENTRO DE COSTOS'!A:D,4,FALSE) -> WILLIAM ASDRUBAL ROZO ROZO | C79: =VLOOKUP(A79,'CENTRO DE COSTOS'!A:C,2,FALSE) -> 0004-0004 | D79: 11001 | E79: TA-25-858452 | F79: 10167 | G79: ORDEN DE CAMBIO | H79: CUNDINAMARCA | I79: BOGOTA | J79: PALERMO BOGOTA CUNDINAMARCA1 | K79: REDEBAN | L79: FO-25-1231036 | M79: 45853.333 | N79: 45856.715 | P79: CIERRE | Q79: RECUPERACION DE EQUIPOS | R79: CB UNO A UNO | S79: CB UNO A UNO | T79: ILOCALIZADO | U79: CB CERRADO - DESOCUPADO | V79: 18-07-2025 SE REALIZA VISITA DE CAMPO DONDE CB NO EXISTE EN DIRECCIÓN INDICADA, SE INTENTA CONTACTO A LA LINEA 3102491356 NO HAY RESPUESTA, SE INFORMA SUPERVISOR Y SE DA CIERRE A SOLICITUD. | W79: VISITA_TÉCNICA | X79: 0 | Y79: TIPO I | Z79: TERRESTRE | AA79: LOZADA ROJAS CHRISTIAN ANDRES | AB79: 1 | AC79: =IF(AND(W79="SOPORTE_TELEFÓNICO",OR(U79="SIN CONTACTO CON EL CB",U79="NÚMEROS DE CONTACTO ERRADOS")),0,IF(W79="SOPORTE_TELEFÓNICO",'BASE DE LIQUIDACION 2025'!$B$9,IF(Y79="TIPO I",'BASE DE LIQUIDACION 2025'!$C$3,IF(Y79="TIPO II",'BASE DE LIQUIDACION 2025'!$C$4,IF(Y79="TIPO III",'BASE DE LIQUIDACION 2025'!$C$5,'BASE DE LIQUIDACION 2025'!$C$6))))) -> 44559.564 | AD79: =IF(W79="SOPORTE_TELEFÓNICO",AC79,CIERRES!AB79*CIERRES!AC79) -> 44559.564
A80: MONTERIA | B80: =VLOOKUP(A80,'CENTRO DE COSTOS'!A:D,4,FALSE) -> JOSE MAURICIO HERNANDEZ ROJAS | C80: =VLOOKUP(A80,'CENTRO DE COSTOS'!A:C,2,FALSE) -> 0004-0001 | D80: 23001 | E80: TA-25-866162 | F80: 25760 | G80: ORDEN DE CAMBIO | H80: CORDOBA | I80: MONTERIA | J80: BARRIO LA GRANJA MONTERIA | K80: REDEBAN | L80: FO-25-1250195 | M80: 45855.333 | N80: 45856.77 | P80: CIERRE | Q80: CIERRE | R80: CB UNO A UNO | S80: CB UNO A UNO | T80: EJECUTADO_EXITOSO | U80: CIERRE EXITOSO | V80: 18-07-2025 SE REALIZA VISITA TÉCNICA PARA CIERRE DE CB, SE RETIRA DATAFONO PLACA 1141845, LECTOR ÓPTICO PLACA 540301, PINPAD PLACA 856523 Y HUB NO SERIALIZADO, EN SITIO YA NO SE ENCONTRÓ NADA DE PUBLICIDAD POR LO TANTO NO SE RETIRA. EL CIERRE SE EFECTÚA SIN NOVEDAD. | W80: VISITA_TÉCNICA | X80: A00VZ770 | Y80: TIPO I | Z80: TERRESTRE | AA80: ECHEVERRI ECHEVERRI EVELIN DANIELA | AB80: 1 | AC80: =IF(AND(W80="SOPORTE_TELEFÓNICO",OR(U80="SIN CONTACTO CON EL CB",U80="NÚMEROS DE CONTACTO ERRADOS")),0,IF(W80="SOPORTE_TELEFÓNICO",'BASE DE LIQUIDACION 2025'!$B$9,IF(Y80="TIPO I",'BASE DE LIQUIDACION 2025'!$C$3,IF(Y80="TIPO II",'BASE DE LIQUIDACION 2025'!$C$4,IF(Y80="TIPO III",'BASE DE LIQUIDACION 2025'!$C$5,'BASE DE LIQUIDACION 2025'!$C$6))))) -> 44559.564 | AD80: =IF(W80="SOPORTE_TELEFÓNICO",AC80,CIERRES!AB80*CIERRES!AC80) -> 44559.564
A81: VILLAVICENCIO | B81: =VLOOKUP(A81,'CENTRO DE COSTOS'!A:D,4,FALSE) -> KEVIN ALEXIS CORZO BUSTOS | C81: =VLOOKUP(A81,'CENTRO DE COSTOS'!A:C,2,FALSE) -> 0004-0007 | D81: 50001 | E81: TA-25-866194 | F81: 70251 | G81: ORDEN DE CAMBIO | H81: META | I81: VILLAVICENCIO | J81: BARRIO PORVENIR VILLAVICENCIO | K81: REDEBAN | L81: FO-25-1242982 | M81: 45855.333 | N81: 45857.391 | P81: CIERRE | Q81: CIERRE | R81: CB UNO A UNO | S81: CB UNO A UNO | T81: ILOCALIZADO | U81: CB CERRADO - DESOCUPADO | V81: 19-07-2025 SE VISITA DIRECCIÓN DE CB PERO AL LLEGAR AL SITIO COMERCIO SE ENCUENTRA CERRADO. NO ES POSIBLE RECUPERAR EQUIPOS | W81: VISITA_TÉCNICA | X81: LN009186 | Y81: TIPO I | Z81: TERRESTRE | AA81: GARZON RUIZ LUIS MIGUEL | AB81: 1 | AC81: =IF(AND(W81="SOPORTE_TELEFÓNICO",OR(U81="SIN CONTACTO CON EL CB",U81="NÚMEROS DE CONTACTO ERRADOS")),0,IF(W81="SOPORTE_TELEFÓNICO",'BASE DE LIQUIDACION 2025'!$B$9,IF(Y81="TIPO I",'BASE DE LIQUIDACION 2025'!$C$3,IF(Y81="TIPO II",'BASE DE LIQUIDACION 2025'!$C$4,IF(Y81="TIPO III",'BASE DE LIQUIDACION 2025'!$C$5,'BASE DE LIQUIDACION 2025'!$C$6))))) -> 44559.564 | AD81: =IF(W81="SOPORTE_TELEFÓNICO",AC81,CIERRES!AB81*CIERRES!AC81) -> 44559.564
A82: CALI | B82: =VLOOKUP(A82,'CENTRO DE COSTOS'!A:D,4,FALSE) -> DIEGO FERNANDO HENAO CARDONA | C82: =VLOOKUP(A82,'CENTRO DE COSTOS'!A:C,2,FALSE) -> 0004-0003 | D82: 19001 | E82: TA-25-858489 | F82: 76647 | G82: ORDEN DE CAMBIO | H82: CAUCA | I82: POPAYAN | J82: BARRIO BELLAVISTA POPAYAN 1 | K82: REDEBAN | L82: FO-25-1231153 | M82: 45853.333 | N82: 45857.4 | P82: CIERRE | Q82: RECUPERACION DE EQUIPOS | R82: CB UNO A UNO | S82: CB UNO A UNO | T82: ILOCALIZADO | U82: CB CERRADO - DESOCUPADO | V82: 19-07-2025 SE LLAMA AL CB NO RESPONDE SE DIRIGE AL SITIO SE ENCUENTRA COMERCIO CERRADO | W82: VISITA_TÉCNICA | X82: LA2ZZ430 | Y82: TIPO III | Z82: TERRESTRE | AA82: GIMBUEL LASSO LUIS GERMAN | AB82: 1 | AC82: =IF(AND(W82="SOPORTE_TELEFÓNICO",OR(U82="SIN CONTACTO CON EL CB",U82="NÚMEROS DE CONTACTO ERRADOS")),0,IF(W82="SOPORTE_TELEFÓNICO",'BASE DE LIQUIDACION 2025'!$B$9,IF(Y82="TIPO I",'BASE DE LIQUIDACION 2025'!$C$3,IF(Y82="TIPO II",'BASE DE LIQUIDACION 2025'!$C$4,IF(Y82="TIPO III",'BASE DE LIQUIDACION 2025'!$C$5,'BASE DE LIQUIDACION 2025'!$C$6))))) -> 222904.07 | AD82: =IF(W82="SOPORTE_TELEFÓNICO",AC82,CIERRES!AB82*CIERRES!AC82) -> 222904.07
A83: BOGOTA | B83: =VLOOKUP(A83,'CENTRO DE COSTOS'!A:D,4,FALSE) -> WILLIAM ASDRUBAL ROZO ROZO | C83: =VLOOKUP(A83,'CENTRO DE COSTOS'!A:C,2,FALSE) -> 0004-0004 | D83: 11001 | E83: TA-25-869812 | F83: 75361 | G83: ORDEN DE CAMBIO | H83: CUNDINAMARCA | I83: BOGOTA | J83: BARRIO VILLA DEL MAR BOGOTA 1 | K83: REDEBAN | L83: FO-25-1248896 | M83: 45856.333 | N83: 45857.403 | P83: CIERRE | Q83: CIERRE | R83: CB UNO A UNO | S83: CB UNO A UNO | T83: NO_EXITOSO | U83: CB NO ENTREGA EQUIPO | V83: 19-07-2025 SE LLEGA PREDIO COMERCIO INDICA NO REALIZAR CIERRE YA QUE EL ASESOR LE INDICO QUE VAN A VOLVER A TOMARLO | W83: VISITA_TÉCNICA | X83: 10008835 | Y83: TIPO I | Z83: TERRESTRE | AA83: INFANTE SIERRA MANUEL FERNANDO | AB83: 1 | AC83: =IF(AND(W83="SOPORTE_TELEFÓNICO",OR(U83="SIN CONTACTO CON EL CB",U83="NÚMEROS DE CONTACTO ERRADOS")),0,IF(W83="SOPORTE_TELEFÓNICO",'BASE DE LIQUIDACION 2025'!$B$9,IF(Y83="TIPO I",'BASE DE LIQUIDACION 2025'!$C$3,IF(Y83="TIPO II",'BASE DE LIQUIDACION 2025'!$C$4,IF(Y83="TIPO III",'BASE DE LIQUIDACION 2025'!$C$5,'BASE DE LIQUIDACION 2025'!$C$6))))) -> 44559.564 | AD83: =IF(W83="SOPORTE_TELEFÓNICO",AC83,CIERRES!AB83*CIERRES!AC83) -> 44559.564
A84: BOGOTA | B84: =VLOOKUP(A84,'CENTRO DE COSTOS'!A:D,4,FALSE) -> WILLIAM ASDRUBAL ROZO ROZO | C84: =VLOOKUP(A84,'CENTRO DE COSTOS'!A:C,2,FALSE) -> 0004-0004 | D84: 11001 | E84: TA-25-869814 | F84: 76941 | G84: ORDEN DE CAMBIO | H84: CUNDINAMARCA | I84: BOGOTA | J84: BARRIO MARANDU BOGOTA 2 | K84: REDEBAN | L84: FO-25-1248902 | M84: 45856.333 | N84: 45857.426 | P84: CIERRE | Q84: CIERRE | R84: CB UNO A UNO | S84: CB UNO A UNO | T84: NO_EXITOSO | U84: CB NO ENTREGA EQUIPO | V84: 19-07-2025 SE LLEGA A COMERCIO SE ENCUENTRA CERRADO ME COMUNICO CON LA SEÑORITA ALEXANDRA RAMÍREZ AL NÚMERO 3007076941 ME INDICA QUE NO SE ENCUENTRA EN LA CUIUDAD | W84: VISITA_TÉCNICA | X84: A18ZZ378 | Y84: TIPO I | Z84: TERRESTRE | AA84: INFANTE SIERRA MANUEL FERNANDO | AB84: 1 | AC84: =IF(AND(W84="SOPORTE_TELEFÓNICO",OR(U84="SIN CONTACTO CON EL CB",U84="NÚMEROS DE CONTACTO ERRADOS")),0,IF(W84="SOPORTE_TELEFÓNICO",'BASE DE LIQUIDACION 2025'!$B$9,IF(Y84="TIPO I",'BASE DE LIQUIDACION 2025'!$C$3,IF(Y84="TIPO II",'BASE DE LIQUIDACION 2025'!$C$4,IF(Y84="TIPO III",'BASE DE LIQUIDACION 2025'!$C$5,'BASE DE LIQUIDACION 2025'!$C$6))))) -> 44559.564 | AD84: =IF(W84="SOPORTE_TELEFÓNICO",AC84,CIERRES!AB84*CIERRES!AC84) -> 44559.564
A85: NEIVA | B85: =VLOOKUP(A85,'CENTRO DE COSTOS'!A:D,4,FALSE) -> KEVIN ALEXIS CORZO BUSTOS | C85: =VLOOKUP(A85,'CENTRO DE COSTOS'!A:C,2,FALSE) -> 0004-0007 | D85: 41001 | E85: TA-25-866170 | F85: 56850 | G85: ORDEN DE CAMBIO | H85: HUILA | I85: NEIVA | J85: BARRIO LOS COLORES NEIVA | K85: REDEBAN | L85: FO-25-1254448 | M85: 45855.333 | N85: 45857.451 | P85: CIERRE | Q85: CIERRE | R85: CB UNO A UNO | S85: CB UNO A UNO | T85: EJECUTADO_EXITOSO | U85: CIERRE EXITOSO | V85: 19-07-2025 CLIENTE ENTREGA DATAFONO CON SOPORTE, LECTOR DE BARRAS, CABLE MAGIC BOX, FUENTE DE PODER DATÁFONO,20 ROLLOS PAPEL RBM, PUBLICIDAD SE DESTRUYE EN SITIO | W85: VISITA_TÉCNICA | X85: IIOZZ198 | Y85: TIPO I | Z85: TERRESTRE | AA85: ANDRADE HERNANDEZ JUAN CARLOS | AB85: 1 | AC85: =IF(AND(W85="SOPORTE_TELEFÓNICO",OR(U85="SIN CONTACTO CON EL CB",U85="NÚMEROS DE CONTACTO ERRADOS")),0,IF(W85="SOPORTE_TELEFÓNICO",'BASE DE LIQUIDACION 2025'!$B$9,IF(Y85="TIPO I",'BASE DE LIQUIDACION 2025'!$C$3,IF(Y85="TIPO II",'BASE DE LIQUIDACION 2025'!$C$4,IF(Y85="TIPO III",'BASE DE LIQUIDACION 2025'!$C$5,'BASE DE LIQUIDACION 2025'!$C$6))))) -> 44559.564 | AD85: =IF(W85="SOPORTE_TELEFÓNICO",AC85,CIERRES!AB85*CIERRES!AC85) -> 44559.564
A86: IBAGUE | B86: =VLOOKUP(A86,'CENTRO DE COSTOS'!A:D,4,FALSE) -> KEVIN ALEXIS CORZO BUSTOS | C86: =VLOOKUP(A86,'CENTRO DE COSTOS'!A:C,2,FALSE) -> 0004-0007 | D86: 73001 | E86: TA-25-872207 | F86: 69180 | G86: ORDEN DE CAMBIO | H86: TOLIMA | I86: IBAGUE | J86: BARRIO JARDIN IBAGUE 3 | K86: REDEBAN | L86: FO-25-1254065 | M86: 45856.638 | N86: 45857.469 | P86: CIERRE | Q86: CIERRE | R86: CB UNO A UNO | S86: CB UNO A UNO | T86: NO_EXITOSO | U86: CB NO ENTREGA EQUIPO | V86: 19-07-2025 SE VISITA CB LA PERSONA QUE ATIENDE LA SEÑORITA EDITH MORALES INFORMA QUE POR EL MOMENTO NO HACE ENTREGA DE LOS ACTIVOS HASTA RECIBIR RESPUESTA POR PARTE DE ASESOR DE LA ENTIDAD | W86: VISITA_TÉCNICA | X86: A103Z586 | Y86: TIPO I | Z86: TERRESTRE | AA86: GUTIERREZ CAMILO ANDRES | AB86: 1 | AC86: =IF(AND(W86="SOPORTE_TELEFÓNICO",OR(U86="SIN CONTACTO CON EL CB",U86="NÚMEROS DE CONTACTO ERRADOS")),0,IF(W86="SOPORTE_TELEFÓNICO",'BASE DE LIQUIDACION 2025'!$B$9,IF(Y86="TIPO I",'BASE DE LIQUIDACION 2025'!$C$3,IF(Y86="TIPO II",'BASE DE LIQUIDACION 2025'!$C$4,IF(Y86="TIPO III",'BASE DE LIQUIDACION 2025'!$C$5,'BASE DE LIQUIDACION 2025'!$C$6))))) -> 44559.564 | AD86: =IF(W86="SOPORTE_TELEFÓNICO",AC86,CIERRES!AB86*CIERRES!AC86) -> 44559.564
A87: BOGOTA | B87: =VLOOKUP(A87,'CENTRO DE COSTOS'!A:D,4,FALSE) -> WILLIAM ASDRUBAL ROZO ROZO | C87: =VLOOKUP(A87,'CENTRO DE COSTOS'!A:C,2,FALSE) -> 0004-0004 | D87: 11001 | E87: TA-25-861440 | F87: 52038 | G87: ORDEN DE CAMBIO | H87: CUNDINAMARCA | I87: BOGOTA | J87: BARRIO MARIA PAZ KENNEDY BOGOTA | K87: REDEBAN | L87: FO-25-1242216 | M87: 45853.673 | N87: 45857.504 | P87: CIERRE | Q87: RECUPERACION DE EQUIPOS | R87: CB UNOA UNO | S87: CB UNOA UNO | T87: EJECUTADO_EXITOSO | U87: CIERRE EXITOSO | V87: 19-07-2025 SE REALIZA VISITA DE CAMPO DONDE SE RETIRAN EQUIPOS SIN NOVEDAD. | W87: VISITA_TÉCNICA | X87: 9C0DZ680 | Y87: TIPO I | Z87: TERRESTRE | AA87: LOZADA ROJAS CHRISTIAN ANDRES | AB87: 1 | AC87: =IF(AND(W87="SOPORTE_TELEFÓNICO",OR(U87="SIN CONTACTO CON EL CB",U87="NÚMEROS DE CONTACTO ERRADOS")),0,IF(W87="SOPORTE_TELEFÓNICO",'BASE DE LIQUIDACION 2025'!$B$9,IF(Y87="TIPO I",'BASE DE LIQUIDACION 2025'!$C$3,IF(Y87="TIPO II",'BASE DE LIQUIDACION 2025'!$C$4,IF(Y87="TIPO III",'BASE DE LIQUIDACION 2025'!$C$5,'BASE DE LIQUIDACION 2025'!$C$6))))) -> 44559.564 | AD87: =IF(W87="SOPORTE_TELEFÓNICO",AC87,CIERRES!AB87*CIERRES!AC87) -> 44559.564
A88: TUNJA | B88: =VLOOKUP(A88,'CENTRO DE COSTOS'!A:D,4,FALSE) -> MIGUEL JULIÁN HERNÁNDEZ GUARÍN | C88: =VLOOKUP(A88,'CENTRO DE COSTOS'!A:C,2,FALSE) -> 0004-0008 | D88: 15176 | E88: TA-25-869795 | F88: 24895 | G88: ORDEN DE CAMBIO | H88: BOYACA | I88: CHIQUINQUIRA | J88: CENTRO CHIQUINQUIRA BOYACA | K88: REDEBAN | L88: FO-25-1248792 | M88: 45856.333 | N88: 45859.439 | P88: CIERRE | Q88: CIERRE | R88: CB UNO A UNO | S88: CB UNO A UNO | T88: SOLICITUD_CANCELADA | U88: CANCELADO POR LA ENTIDAD | V88: 21-07-2025 SE LOGRA COMUNICACIÓN CON LA SEÑORA CLAUDIA PATRICIA RODRIGUEZ PINTO AL NÚMERO TELEFÓNICO 3104789724 QUIEN NOS MANIFIESTA QUE NO DESEA REALIZAR LA ENTREGA DE LOS EQUIPOS YA QUE ELLA NO A SOLICITADO SU RETIRO, CLIENTE INDICA QUE SE COMUNICARA CON LA ENTIDAD PARA LLEGAR A UN ACUERDO Y NO REALIZAR EL RETIRO DEL CB, SE CIERRA ORDEN YA QUE EL CLIENTE NO ENTREGA Y NO SE VISITA COMERCIO. | W88: SOPORTE_TELEFÓNICO | X88: 0 | Y88: TIPO III | Z88: TERRESTRE | AA88: SOLER HOYOS CRISTIAN LEONARDO | AB88: 0 | AC88: =IF(AND(W88="SOPORTE_TELEFÓNICO",OR(U88="SIN CONTACTO CON EL CB",U88="NÚMEROS DE CONTACTO ERRADOS")),0,IF(W88="SOPORTE_TELEFÓNICO",'BASE DE LIQUIDACION 2025'!$B$9,IF(Y88="TIPO I",'BASE DE LIQUIDACION 2025'!$C$3,IF(Y88="TIPO II",'BASE DE LIQUIDACION 2025'!$C$4,IF(Y88="TIPO III",'BASE DE LIQUIDACION 2025'!$C$5,'BASE DE LIQUIDACION 2025'!$C$6))))) -> 37904.612 | AD88: =IF(W88="SOPORTE_TELEFÓNICO",AC88,CIERRES!AB88*CIERRES!AC88) -> 37904.612
A89: MEDELLIN | B89: =VLOOKUP(A89,'CENTRO DE COSTOS'!A:D,4,FALSE) -> JUAN SEBASTIÁN RÍOS CASTRILLÓN | C89: =VLOOKUP(A89,'CENTRO DE COSTOS'!A:C,2,FALSE) -> 0004-0005 | D89: 5001 | E89: TA-25-858492 | F89: 74931 | G89: ORDEN DE CAMBIO | H89: ANTIOQUIA | I89: MEDELLIN | J89: DISTRICOL BALCONES DE SAN PABL | K89: REDEBAN | L89: FO-25-1231166 | M89: 45853.333 | N89: 45859.489 | P89: CIERRE | Q89: CIERRE | R89: AGREGADOR | S89: DISTRICOL | T89: ILOCALIZADO | U89: CB CERRADO - DESOCUPADO | V89: 19-07-2025 VISITA FALLIDA COMERCIO CERRADO | W89: VISITA_TÉCNICA | X89: EGZZZ359 | Y89: TIPO I | Z89: TERRESTRE | AA89: ALVAREZ ARENAS VICTOR HUGO | AB89: 1 | AC89: =IF(AND(W89="SOPORTE_TELEFÓNICO",OR(U89="SIN CONTACTO CON EL CB",U89="NÚMEROS DE CONTACTO ERRADOS")),0,IF(W89="SOPORTE_TELEFÓNICO",'BASE DE LIQUIDACION 2025'!$B$9,IF(Y89="TIPO I",'BASE DE LIQUIDACION 2025'!$C$3,IF(Y89="TIPO II",'BASE DE LIQUIDACION 2025'!$C$4,IF(Y89="TIPO III",'BASE DE LIQUIDACION 2025'!$C$5,'BASE DE LIQUIDACION 2025'!$C$6))))) -> 44559.564 | AD89: =IF(W89="SOPORTE_TELEFÓNICO",AC89,CIERRES!AB89*CIERRES!AC89) -> 44559.564
A90: BUCARAMANGA | B90: =VLOOKUP(A90,'CENTRO DE COSTOS'!A:D,4,FALSE) -> MIGUEL JULIÁN HERNÁNDEZ GUARÍN | C90: =VLOOKUP(A90,'CENTRO DE COSTOS'!A:C,2,FALSE) -> 0004-0008 | D90: 68001 | E90: TA-25-869805 | F90: 66430 | G90: ORDEN DE CAMBIO | H90: SANTANDER | I90: BUCARAMANGA | J90: BARRIO LA AURORA BUCARAMANGA 6 | K90: REDEBAN | L90: FO-25-1256319 | M90: 45856.333 | N90: 45859.516 | P90: CIERRE | Q90: CIERRE | R90: CB UNO A UNO | S90: CB UNO A UNO | T90: EJECUTADO_EXITOSO | U90: CIERRE EXITOSO | V90: 21-07-2025 SE REALIZA VISITA AL COMERCIO SE HACE RETIRO DE DATÁFONO, LECTOR DE BARRAS Y BASE PUBLICIDAD DESTRUIDA EN EL PUNTO | W90: VISITA_TÉCNICA | X90: 1A00Q930 | Y90: TIPO I | Z90: TERRESTRE | AA90: GONZALEZ ESTUPIÑAN YEISON WALTER ANTONIO | AB90: 1 | AC90: =IF(AND(W90="SOPORTE_TELEFÓNICO",OR(U90="SIN CONTACTO CON EL CB",U90="NÚMEROS DE CONTACTO ERRADOS")),0,IF(W90="SOPORTE_TELEFÓNICO",'BASE DE LIQUIDACION 2025'!$B$9,IF(Y90="TIPO I",'BASE DE LIQUIDACION 2025'!$C$3,IF(Y90="TIPO II",'BASE DE LIQUIDACION 2025'!$C$4,IF(Y90="TIPO III",'BASE DE LIQUIDACION 2025'!$C$5,'BASE DE LIQUIDACION 2025'!$C$6))))) -> 44559.564 | AD90: =IF(W90="SOPORTE_TELEFÓNICO",AC90,CIERRES!AB90*CIERRES!AC90) -> 44559.564
A91: MEDELLIN | B91: =VLOOKUP(A91,'CENTRO DE COSTOS'!A:D,4,FALSE) -> JUAN SEBASTIÁN RÍOS CASTRILLÓN | C91: =VLOOKUP(A91,'CENTRO DE COSTOS'!A:C,2,FALSE) -> 0004-0005 | D91: 5044 | E91: TA-25-853199 | F91: 67295 | G91: ORDEN DE CAMBIO | H91: ANTIOQUIA | I91: ANZA | J91: BARRIO CALLE LA PUNTA SECTRO E | K91: REDEBAN | L91: FO-25-1218116 | M91: 45849.485 | N91: 45859.522 | P91: CIERRE | Q91: CIERRE | R91: CB UNO A UNO | S91: CB UNO A UNO | T91: SOLICITUD_CANCELADA | U91: CANCELADO POR LA ENTIDAD | V91: 21-07-2025 ENTIDAD SOLICITA CANCELACION DE ESTE CIERRE. SE CANCELA SOLICITUD POR INDICACIÓN DE LA ENTIDAD. SE CIERRA TA. | W91: SOPORTE_TELEFÓNICO | X91: 0 | Y91: TIPO III | Z91: TERRESTRE | AA91: MORENO MEDINA JUAN PABLO | AB91: 0 | AC91: =IF(AND(W91="SOPORTE_TELEFÓNICO",OR(U91="SIN CONTACTO CON EL CB",U91="NÚMEROS DE CONTACTO ERRADOS")),0,IF(W91="SOPORTE_TELEFÓNICO",'BASE DE LIQUIDACION 2025'!$B$9,IF(Y91="TIPO I",'BASE DE LIQUIDACION 2025'!$C$3,IF(Y91="TIPO II",'BASE DE LIQUIDACION 2025'!$C$4,IF(Y91="TIPO III",'BASE DE LIQUIDACION 2025'!$C$5,'BASE DE LIQUIDACION 2025'!$C$6))))) -> 37904.612 | AD91: =IF(W91="SOPORTE_TELEFÓNICO",AC91,CIERRES!AB91*CIERRES!AC91) -> 37904.612
A92: BOGOTA | B92: =VLOOKUP(A92,'CENTRO DE COSTOS'!A:D,4,FALSE) -> WILLIAM ASDRUBAL ROZO ROZO | C92: =VLOOKUP(A92,'CENTRO DE COSTOS'!A:C,2,FALSE) -> 0004-0004 | D92: 25126 | E92: TA-25-869953 | F92: 50092 | G92: ORDEN DE CAMBIO | H92: CUNDINAMARCA | I92: CAJICA | J92: PTM CAJICA MAS FARMA 23 DROGU | K92: REDEBAN | L92: FO-25-1260841 | M92: 45856.333 | N92: 45859.607 | P92: CIERRE | Q92: CIERRE | R92: AGREGADOR | S92: COMCARD - PTM | T92: EJECUTADO_EXITOSO | U92: CIERRE EXITOSO | V92: 21-07-2025 SE RETIRA DATAFONO Y LECTORA SE DESTRUYE PUBLICIDAD EN SITIO | W92: VISITA_TÉCNICA | X92: II00T983 | Y92: TIPO II | Z92: TERRESTRE | AA92: INFANTE SIERRA MANUEL FERNANDO | AB92: 2 | AC92: =IF(AND(W92="SOPORTE_TELEFÓNICO",OR(U92="SIN CONTACTO CON EL CB",U92="NÚMEROS DE CONTACTO ERRADOS")),0,IF(W92="SOPORTE_TELEFÓNICO",'BASE DE LIQUIDACION 2025'!$B$9,IF(Y92="TIPO I",'BASE DE LIQUIDACION 2025'!$C$3,IF(Y92="TIPO II",'BASE DE LIQUIDACION 2025'!$C$4,IF(Y92="TIPO III",'BASE DE LIQUIDACION 2025'!$C$5,'BASE DE LIQUIDACION 2025'!$C$6))))) -> 134410.88 | AD92: =IF(W92="SOPORTE_TELEFÓNICO",AC92,CIERRES!AB92*CIERRES!AC92) -> 268821.77
A93: CALI | B93: =VLOOKUP(A93,'CENTRO DE COSTOS'!A:D,4,FALSE) -> DIEGO FERNANDO HENAO CARDONA | C93: =VLOOKUP(A93,'CENTRO DE COSTOS'!A:C,2,FALSE) -> 0004-0003 | D93: 76001 | E93: TA-25-866219 | F93: 52906 | G93: ORDEN DE CAMBIO | H93: VALLE DEL CAUCA | I93: CALI | J93: BARRIO LAURIANO GOMEZ CALI | K93: REDEBAN | L93: FO-25-1255851 | M93: 45855.333 | N93: 45859.656 | P93: CIERRE | Q93: CIERRE | R93: CB UNO A UNO | S93: CB UNO A UNO | T93: NO_EXITOSO | U93: CB NO ENTREGA EQUIPO | V93: 21-07-2025 SE LLAMA AL CLIENTE Y NOS INDICA QUE NO PUEDE ENTREGAR LOS EQUIPOS EL DIA DE HOY CERRAR ACTIVIDAD | W93: SOPORTE_TELEFÓNICO | X93: 0 | Y93: TIPO I | Z93: TERRESTRE | AA93: HENAO CARDONA DIEGO FERNANDO | AB93: 0 | AC93: =IF(AND(W93="SOPORTE_TELEFÓNICO",OR(U93="SIN CONTACTO CON EL CB",U93="NÚMEROS DE CONTACTO ERRADOS")),0,IF(W93="SOPORTE_TELEFÓNICO",'BASE DE LIQUIDACION 2025'!$B$9,IF(Y93="TIPO I",'BASE DE LIQUIDACION 2025'!$C$3,IF(Y93="TIPO II",'BASE DE LIQUIDACION 2025'!$C$4,IF(Y93="TIPO III",'BASE DE LIQUIDACION 2025'!$C$5,'BASE DE LIQUIDACION 2025'!$C$6))))) -> 37904.612 | AD93: =IF(W93="SOPORTE_TELEFÓNICO",AC93,CIERRES!AB93*CIERRES!AC93) -> 37904.612
A94: VALLEDUPAR | B94: =VLOOKUP(A94,'CENTRO DE COSTOS'!A:D,4,FALSE) -> JOSE MAURICIO HERNANDEZ ROJAS | C94: =VLOOKUP(A94,'CENTRO DE COSTOS'!A:C,2,FALSE) -> 0004-0001 | D94: 13074 | E94: TA-25-869793 | F94: 49948 | G94: ORDEN DE CAMBIO | H94: BOLIVAR | I94: BARRANCO DE LOBA | J94: BARRIO CENTRO BARRANCO DE LOBA | K94: REDEBAN | L94: FO-25-1248779 | M94: 45856.333 | N94: 45859.66 | P94: CIERRE | Q94: CIERRE | R94: CB UNO A UNO | S94: CB UNO A UNO | T94: NO_EXITOSO | U94: CB NO ENTREGA EQUIPO | V94: 21-07-2025 SE COMUNICA CON LA USUARIA Y MANIFIESTA QUE NO SE ENCUENTRA EN EL MUNICIPIO Y QUE LLEGA LA OTRA SEMANA, POR ENDE NO SE PUEDEN RECOGER LOS EQUIPOS | W94: SOPORTE_TELEFÓNICO | X94: 0 | Y94: TIPO IV | Z94: TERRESTRE | AA94: MONTES DIAZ JOHN FRED | AB94: 0 | AC94: =IF(AND(W94="SOPORTE_TELEFÓNICO",OR(U94="SIN CONTACTO CON EL CB",U94="NÚMEROS DE CONTACTO ERRADOS")),0,IF(W94="SOPORTE_TELEFÓNICO",'BASE DE LIQUIDACION 2025'!$B$9,IF(Y94="TIPO I",'BASE DE LIQUIDACION 2025'!$C$3,IF(Y94="TIPO II",'BASE DE LIQUIDACION 2025'!$C$4,IF(Y94="TIPO III",'BASE DE LIQUIDACION 2025'!$C$5,'BASE DE LIQUIDACION 2025'!$C$6))))) -> 37904.612 | AD94: =IF(W94="SOPORTE_TELEFÓNICO",AC94,CIERRES!AB94*CIERRES!AC94) -> 37904.612
A95: VALLEDUPAR | B95: =VLOOKUP(A95,'CENTRO DE COSTOS'!A:D,4,FALSE) -> JOSE MAURICIO HERNANDEZ ROJAS | C95: =VLOOKUP(A95,'CENTRO DE COSTOS'!A:C,2,FALSE) -> 0004-0001 | D95: 13074 | E95: TA-25-869794 | F95: 49949 | G95: ORDEN DE CAMBIO | H95: BOLIVAR | I95: BARRANCO DE LOBA | J95: BARRIO CENTRO BARRANCO DE LOBA | K95: REDEBAN | L95: FO-25-1248785 | M95: 45856.333 | N95: 45859.662 | P95: CIERRE | Q95: CIERRE | R95: CB UNO A UNO | S95: CB UNO A UNO | T95: NO_EXITOSO | U95: CB NO ENTREGA EQUIPO | V95: 21-07-2025 SE COMUNICA CON LA USUARIA Y MANIFIESTA QUE NO SE ENCUENTRA EN EL MUNICIPIO Y QUE LLEGA LA OTRA SEMANA, POR ENDE NO SE PUEDEN RECOGER LOS EQUIPOS | W95: SOPORTE_TELEFÓNICO | X95: 0 | Y95: TIPO IV | Z95: TERRESTRE | AA95: MONTES DIAZ JOHN FRED | AB95: 0 | AC95: =IF(AND(W95="SOPORTE_TELEFÓNICO",OR(U95="SIN CONTACTO CON EL CB",U95="NÚMEROS DE CONTACTO ERRADOS")),0,IF(W95="SOPORTE_TELEFÓNICO",'BASE DE LIQUIDACION 2025'!$B$9,IF(Y95="TIPO I",'BASE DE LIQUIDACION 2025'!$C$3,IF(Y95="TIPO II",'BASE DE LIQUIDACION 2025'!$C$4,IF(Y95="TIPO III",'BASE DE LIQUIDACION 2025'!$C$5,'BASE DE LIQUIDACION 2025'!$C$6))))) -> 37904.612 | AD95: =IF(W95="SOPORTE_TELEFÓNICO",AC95,CIERRES!AB95*CIERRES!AC95) -> 37904.612
A96: IBAGUE | B96: =VLOOKUP(A96,'CENTRO DE COSTOS'!A:D,4,FALSE) -> KEVIN ALEXIS CORZO BUSTOS | C96: =VLOOKUP(A96,'CENTRO DE COSTOS'!A:C,2,FALSE) -> 0004-0007 | D96: 73168 | E96: TA-25-869809 | F96: 59719 | G96: ORDEN DE CAMBIO | H96: TOLIMA | I96: CHAPARRAL | J96: BARRIO CORREGIMIENTO EL LIMON | K96: REDEBAN | L96: FO-25-1248889 | M96: 45856.333 | N96: 45859.747 | P96: CIERRE | Q96: CIERRE | R96: CB UNO A UNO | S96: CB UNO A UNO | T96: SOLICITUD_CANCELADA | U96: CANCELADO POR LA ENTIDAD | V96: 21-07 SE PROCEDE A CERRAR CASO POR SOLICITUD DE LA ENTIDAD 0 0 | W96: SOPORTE_TELEFÓNICO | X96: 0 | Y96: TIPO III | Z96: TERRESTRE | AA96: GUTIERREZ CAMILO ANDRES | AB96: 0 | AC96: =IF(AND(W96="SOPORTE_TELEFÓNICO",OR(U96="SIN CONTACTO CON EL CB",U96="NÚMEROS DE CONTACTO ERRADOS")),0,IF(W96="SOPORTE_TELEFÓNICO",'BASE DE LIQUIDACION 2025'!$B$9,IF(Y96="TIPO I",'BASE DE LIQUIDACION 2025'!$C$3,IF(Y96="TIPO II",'BASE DE LIQUIDACION 2025'!$C$4,IF(Y96="TIPO III",'BASE DE LIQUIDACION 2025'!$C$5,'BASE DE LIQUIDACION 2025'!$C$6))))) -> 37904.612 | AD96: =IF(W96="SOPORTE_TELEFÓNICO",AC96,CIERRES!AB96*CIERRES!AC96) -> 37904.612
A97: APARTADO | B97: =VLOOKUP(A97,'CENTRO DE COSTOS'!A:D,4,FALSE) -> JUAN SEBASTIÁN RÍOS CASTRILLÓN | C97: =VLOOKUP(A97,'CENTRO DE COSTOS'!A:C,2,FALSE) -> 0004-0005 | D97: 5147 | E97: TA-25-872203 | F97: 77105 | G97: ORDEN DE CAMBIO | H97: ANTIOQUIA | I97: CAREPA | J97: BARRIO 20 DE JULIO CAREPA ANTIOQUIA CAREPA | K97: REDEBAN | L97: FO-25-1254048 | M97: 45856.638 | N97: 45859.749 | P97: CIERRE | Q97: CIERRE | R97: CB UNO A UNO | S97: CB UNO A UNO | T97: SOLICITUD_CANCELADA | U97: CANCELADO POR LA ENTIDAD | V97: 21-07 SE PROCEDE A CERRAR CASO POR SOLICITUD DE LA ENTIDAD 0 0 | W97: SOPORTE_TELEFÓNICO | X97: 0 | Y97: TIPO I | Z97: TERRESTRE | AA97: RIOS CASTRILLON JUAN SEBASTIAN | AB97: 0 | AC97: =IF(AND(W97="SOPORTE_TELEFÓNICO",OR(U97="SIN CONTACTO CON EL CB",U97="NÚMEROS DE CONTACTO ERRADOS")),0,IF(W97="SOPORTE_TELEFÓNICO",'BASE DE LIQUIDACION 2025'!$B$9,IF(Y97="TIPO I",'BASE DE LIQUIDACION 2025'!$C$3,IF(Y97="TIPO II",'BASE DE LIQUIDACION 2025'!$C$4,IF(Y97="TIPO III",'BASE DE LIQUIDACION 2025'!$C$5,'BASE DE LIQUIDACION 2025'!$C$6))))) -> 37904.612 | AD97: =IF(W97="SOPORTE_TELEFÓNICO",AC97,CIERRES!AB97*CIERRES!AC97) -> 37904.612
A98: BOGOTA | B98: =VLOOKUP(A98,'CENTRO DE COSTOS'!A:D,4,FALSE) -> WILLIAM ASDRUBAL ROZO ROZO | C98: =VLOOKUP(A98,'CENTRO DE COSTOS'!A:C,2,FALSE) -> 0004-0004 | D98: 25754 | E98: TA-25-858474 | F98: 54868 | G98: ORDEN DE CAMBIO | H98: CUNDINAMARCA | I98: SOACHA | J98: BARRIO SOACHA SOACHA 6 | K98: REDEBAN | L98: FO-25-1231112 | M98: 45853.333 | N98: 45859.771 | P98: CIERRE | Q98: RECUPERACION DE EQUIPOS | R98: CB UNO A UNO | S98: CB UNO A UNO | T98: ILOCALIZADO | U98: CB CERRADO - DESOCUPADO | V98: 16-07-2025 SE REALIZA VISITA A CB PARA REALIZAR CIERRE NO SE ENCUENTRA LA SEÑORA ,SE INTENTA COMUNICAR CON CLIENTE NO CONTESTAN | W98: VISITA_TÉCNICA | X98: 0 | Y98: TIPO I | Z98: TERRESTRE | AA98: GALINDO ROJAS LUIS FELIPE | AB98: 1 | AC98: =IF(AND(W98="SOPORTE_TELEFÓNICO",OR(U98="SIN CONTACTO CON EL CB",U98="NÚMEROS DE CONTACTO ERRADOS")),0,IF(W98="SOPORTE_TELEFÓNICO",'BASE DE LIQUIDACION 2025'!$B$9,IF(Y98="TIPO I",'BASE DE LIQUIDACION 2025'!$C$3,IF(Y98="TIPO II",'BASE DE LIQUIDACION 2025'!$C$4,IF(Y98="TIPO III",'BASE DE LIQUIDACION 2025'!$C$5,'BASE DE LIQUIDACION 2025'!$C$6))))) -> 44559.564 | AD98: =IF(W98="SOPORTE_TELEFÓNICO",AC98,CIERRES!AB98*CIERRES!AC98) -> 44559.564
A99: MEDELLIN | B99: =VLOOKUP(A99,'CENTRO DE COSTOS'!A:D,4,FALSE) -> JUAN SEBASTIÁN RÍOS CASTRILLÓN | C99: =VLOOKUP(A99,'CENTRO DE COSTOS'!A:C,2,FALSE) -> 0004-0005 | D99: 5390 | E99: TA-25-858462 | F99: 52872 | G99: ORDEN DE CAMBIO | H99: ANTIOQUIA | I99: LA PINTADA | J99: BARRIO PUEBLO NUEVO LA PINTADA | K99: REDEBAN | L99: FO-25-1231071 | M99: 45853.333 | N99: 45859.776 | P99: CIERRE | Q99: CIERRE | R99: CB UNO A UNO | S99: CB UNO A UNO | T99: ILOCALIZADO | U99: CB CERRADO - DESOCUPADO | V99: 21-07-2025 SE VISITÓ DIRECCIÓN RELACIONADA EN EL LOCAL NO CONOCEN A LA PERSONA DE CONTACTO SE INTENTÓ COMUNICAR POR TELÉFONO Y VÍA WHATSAPP SIN RESPUESTA SE PROCEDE A CERRAR CASO | W99: VISITA_TÉCNICA | X99: 0 | Y99: TIPO II | Z99: TERRESTRE | AA99: CASTAÑEDA PALACIO CARLOS FELIPE | AB99: 1 | AC99: =IF(AND(W99="SOPORTE_TELEFÓNICO",OR(U99="SIN CONTACTO CON EL CB",U99="NÚMEROS DE CONTACTO ERRADOS")),0,IF(W99="SOPORTE_TELEFÓNICO",'BASE DE LIQUIDACION 2025'!$B$9,IF(Y99="TIPO I",'BASE DE LIQUIDACION 2025'!$C$3,IF(Y99="TIPO II",'BASE DE LIQUIDACION 2025'!$C$4,IF(Y99="TIPO III",'BASE DE LIQUIDACION 2025'!$C$5,'BASE DE LIQUIDACION 2025'!$C$6))))) -> 134410.88 | AD99: =IF(W99="SOPORTE_TELEFÓNICO",AC99,CIERRES!AB99*CIERRES!AC99) -> 134410.88
A100: MEDELLIN | B100: =VLOOKUP(A100,'CENTRO DE COSTOS'!A:D,4,FALSE) -> JUAN SEBASTIÁN RÍOS CASTRILLÓN | C100: =VLOOKUP(A100,'CENTRO DE COSTOS'!A:C,2,FALSE) -> 0004-0005 | D100: 5615 | E100: TA-25-866239 | F100: 70990 | G100: ORDEN DE CAMBIO | H100: ANTIOQUIA | I100: RIONEGRO | J100: BARRIO SAN FRANCISCO RIONEGRO | K100: REDEBAN | L100: FO-25-1243098 | M100: 45855.333 | N100: 45860.535 | P100: CIERRE | Q100: RECUPERACION DE EQUIPOS | R100: CB UNO A UNO | S100: CB UNO A UNO | T100: NO_EXITOSO | U100: CB NO ENTREGA EQUIPO | V100: 22-07-2025 SOLICITUD MAL ESCALADA CLIENTE SOLICITO RETIRO DE DATÁFONO DE CREDIBANCO SE ESCALA SOLICITUD A CREDIBANCO | W100: VISITA_TÉCNICA | X100: 0 | Y100: TIPO II | Z100: TERRESTRE | AA100: CASTAÑEDA PALACIO CARLOS FELIPE | AB100: 1 | AC100: =IF(AND(W100="SOPORTE_TELEFÓNICO",OR(U100="SIN CONTACTO CON EL CB",U100="NÚMEROS DE CONTACTO ERRADOS")),0,IF(W100="SOPORTE_TELEFÓNICO",'BASE DE LIQUIDACION 2025'!$B$9,IF(Y100="TIPO I",'BASE DE LIQUIDACION 2025'!$C$3,IF(Y100="TIPO II",'BASE DE LIQUIDACION 2025'!$C$4,IF(Y100="TIPO III",'BASE DE LIQUIDACION 2025'!$C$5,'BASE DE LIQUIDACION 2025'!$C$6))))) -> 134410.88 | AD100: =IF(W100="SOPORTE_TELEFÓNICO",AC100,CIERRES!AB100*CIERRES!AC100) -> 134410.88
...

Sheet TIPOLOGIAS
A1: COD. CIUDAD | B1: CIUDAD | C1: DEPARTAMENTO | D1: DESDE DONDE SE ATIENDE | E1: TIPO DE TRAYECTO NUEVO | F1: TIPOLOGIA NUEVA
A2: 91430 | B2: LA VICTORIA | C2: AMAZONAS | D2: BOGOTA | E2: AEREO | F2: TIPO IV ESPECIAL
A3: 91669 | B3: PUERTO SANTANDER | C3: AMAZONAS | D3: BOGOTA | E3: AEREO | F3: TIPO IV ESPECIAL
A4: 91263 | B4: EL ENCANTO | C4: AMAZONAS | D4: BOGOTA | E4: AEREO | F4: TIPO IV ESPECIAL
A5: 91405 | B5: LA CHORRERA | C5: AMAZONAS | D5: BOGOTA | E5: AEREO | F5: TIPO IV ESPECIAL
A6: 91407 | B6: LA PEDRERA | C6: AMAZONAS | D6: BOGOTA | E6: AEREO | F6: TIPO IV ESPECIAL
A7: 91001 | B7: LETICIA | C7: AMAZONAS | D7: BOGOTA | E7: AEREO | F7: TIPO IV ESPECIAL
A8: 91460 | B8: MIRITI - PARANA | C8: AMAZONAS | D8: BOGOTA | E8: AEREO | F8: TIPO IV ESPECIAL
A9: 91530 | B9: PUERTO ALEGRIA | C9: AMAZONAS | D9: BOGOTA | E9: AEREO | F9: TIPO IV ESPECIAL
A10: 91536 | B10: PUERTO ARICA | C10: AMAZONAS | D10: BOGOTA | E10: AEREO | F10: TIPO IV ESPECIAL
A11: 91540 | B11: PUERTO NARIÑO | C11: AMAZONAS | D11: BOGOTA | E11: AEREO | F11: TIPO IV ESPECIAL
A12: 91798 | B12: TARAPACA | C12: AMAZONAS | D12: BOGOTA | E12: AEREO | F12: TIPO IV ESPECIAL
A13: 5055 | B13: ARGELIA | C13: ANTIOQUIA | D13: MEDELLIN | E13: TERRESTRE | F13: TIPO IV
... A1124: 23682 | B1124: SAN JOSE DE URE | C1124: CORDOBA | D1124: MONTERIA | E1124: TERRESTRE | F1124: TIPO III

Sheet CENTRO DE COSTOS
A1: CIUDAD | B1: CENTRO_COSTO | C1: DESCRIPCION | D1: COORDINADOR
A2: APARTADO | B2: 0004-0005 | C2: Redeban Noroccidente (Medellín) | D2: JUAN SEBASTIÁN RÍOS CASTRILLÓN
A3: BARRANQUILLA | B3: 0004-0001 | C3: Redeban Costa (Barranqullla) | D3: JOSE MAURICIO HERNANDEZ ROJAS
A4: BOGOTA | B4: 0004-0004 | C4: Redeban Centro ( Bogotá) | D4: WILLIAM ASDRUBAL ROZO ROZO
A5: BUCARAMANGA | B5: 0004-0008 | C5: Redeban Santander | D5: MIGUEL JULIÁN HERNÁNDEZ GUARÍN
A6: CALI | B6: 0004-0003 | C6: Redeban Suroccidente (Cali) | D6: DIEGO FERNANDO HENAO CARDONA
A7: CARTAGENA | B7: 0004-0001 | C7: Redeban Costa (Barranqullla) | D7: JOSE MAURICIO HERNANDEZ ROJAS
A8: CUCUTA | B8: 0004-0008 | C8: Redeban Santander | D8: MIGUEL JULIÁN HERNÁNDEZ GUARÍN
A9: FLORENCIA | B9: 0004-0007 | C9: Redeban Oriente (Otros) | D9: KEVIN ALEXIS CORZO BUSTOS
A10: IBAGUE | B10: 0004-0007 | C10: Redeban Oriente (Otros) | D10: KEVIN ALEXIS CORZO BUSTOS
A11: MANIZALES | B11: 0004-0002 | C11: Redeban Eje Cafetero (Pereira) | D11: DIEGO FERNANDO HENAO CARDONA
A12: MEDELLIN | B12: 0004-0005 | C12: Redeban Noroccidente (Medellín) | D12: JUAN SEBASTIÁN RÍOS CASTRILLÓN
... A23: YOPAL | B23: 0004-0007 | C23: Redeban Oriente (Otros) | D23: KEVIN ALEXIS CORZO BUSTOS
