Workbook
Name A: #REF!
Name A: #REF!
Name ACTIVIDAD: [1]Hoja2!$P$2:$P$30
Name Actividad: [2]Formulas!$H$2:$H$5000
Name Analistas: '[3]Listas Desplegables'!$T$2:$T$7
Name arearesponsable: '[4]Listas desplegables'!$BB$2:$BB$100
Name CCO: [5]Tecnicos!$A$2:$A$1000
Name Clientes: [6]Clientes!$A$2:$A$100
Name Clientes: [2]Clientes!$A$2:$A$100
Name COORDINADOR: [1]Hoja2!$D$2:$D$30
Name Coordinadores: [7]Coordinadores!$A$2:$A$1000
Name Coordinadores: [2]Coordinadores!$A$2:$A$1000
Name DOCUMENTADOR: [1]Hoja2!$A$2:$A$30
Name ES: [1]Hoja2!$K$2:$K$30
Name ESS: [1]Hoja2!$K$2:$K$30
Name Estado: [6]Formulas!$K$2:$K$5000
Name Estado: [2]Formulas!$K$2:$K$5000
Name ESTADOACTIVIDAD: [1]Hoja2!$M$2:$M$30
Name ESTADOS: '[8]Listas desplegables'!$B$1:$D$1
Name ESTADOS: '[9]Listas desplegables'!$B$1:$D$1
Name ESTADOSCIERRES: '[10]lista desplegable'!$CX$1:$DA$1
Name Facturacion: '[11]Listas desplegables'!$AO$1:$AR$1
Name FACTURACIÓN: '[8]Listas desplegables'!$Y$1:$AB$1
Name FACTURACIÓN: '[9]Listas desplegables'!$Y$1:$AB$1
Name falla: #REF!
Name Fallas: '[12]Listas desplegables'!$F$2:$L$2
Name Fallas: '[13]Listas desplegables'!$F$2:$L$2
Name Grupo_Falla: '[14]Listas Desplegables'!$CH$2:$CH$5
Name Grupo_Falla: '[15]Listas Desplegables'!$CH$2:$CH$5
Name inconservmanager: '[16]Listas desplegables'!$BC$2:$BC$100
Name inconservmanager: '[4]Listas desplegables'!$BC$2:$BC$100
Name INCUMPLIMIENTO: '[4]Listas desplegables'!$AK$1:$AN$1
Name INCUMPLIMIENTO: '[17]Listas desplegables'!$AT$1:$AX$1
Name LISTA: [18]Dptos!$A$1139:$A$1171
Name LISTA: [19]Dptos!$A$1139:$A$1171
Name LISTA2: #REF!
Name LISTA2: [20]Hoja3!$A$1:$A$26
Name LOLO: [21]Coordinadores!$A$2:$A$1000
Name solicitudes: '[11]Listas desplegables'!$U$1:$AF$1
Name solicitudes: '[11]Listas desplegables'!$U$1:$AF$1
Name Tecnicos: [6]Tecnicos!$A$2:$A$1000
Name Tecnicos: [2]Tecnicos!$A$2:$A$1000
Name Version: [22]Formulas!$I$2:$I$3
Name Version: [2]Formulas!$I$2:$I$3

Sheet RESUMEN
A1: =CONCATENATE("TOTAL GENERAL MES ",A3) -> TOTAL GENERAL MES JULIO DE 2025 | J1: FACTURACIÓN CORRESPONSALES BANCARIOS TIQUIETES AEREOS
A2: MES | B2: NIT Proveedor | C2: Nombre Proveedor (el proveedor ya debe estar creado para el Grupo Bancolombia) | D2: Concepto Facturación | E2: Público al que le instalo la publicidad | F2: No. personas impactadas | G2: Valor a Facturar sin IVA | H2: Valor a Facturar con IVA | J2: CONCEPTOS | K2: TRAYECTOS | L2: TOTAL | M2: % Administración | N2: TOTAL
A3: JULIO DE 2025 | B3: 811013990-5 | C3: LINEA COMUNICACIONES S.A.S | D3: INSTALACION PUBLICIDAD APERTURAS CORRESPONSALES BANCARIOS | E3: OPERADOR DEL CORRESPONSAL BANCARIO | F3: =COUNTA('PUBLICIDAD APERTURAS'!A:A)-1 -> 631 | G3: ='PUBLICIDAD APERTURAS'!AE633 -> 1.4140627e+08 | H3: =G3*1.19 -> 1.6827346e+08 | J3: APERTURA CB 79956 | K3: CALI-TIMBIQUI-CALI | L3: 423000 | M3: =L3*0.12 -> 50760 | N3: =L3+M3 -> 473760
A4: =A3 -> JULIO DE 2025 | B4: 811013990-5 | C4: LINEA COMUNICACIONES S.A.S | D4: ORDENES DE CAMBIO POR DEMANDA | E4: OPERADOR DEL CORRESPONSAL BANCARIO | F4: =COUNTA('PUBLICIDAD OC'!A:A)-1 -> 126 | G4: ='PUBLICIDAD OC'!AF128 -> 28898150 | H4: =G4*1.19 -> 34388799 | J4: APERTURA CB 80067 | K4: APARTADO-BAJO BAUDO-APARTADO | L4: 685449 | M4: =L4*0.12 -> 82253.88 | N4: =L4+M4 -> 767702.88
A5: =A4 -> JULIO DE 2025 | B5: 811013990-5 | C5: LINEA COMUNICACIONES S.A.S | D5: TRAYECTOS ESPECIALES OC | E5: OPERADOR DEL CORRESPONSAL BANCARIO | F5: 11 | G5: =N13 -> 6569973.8 | H5: =G5*1.19 -> 7818268.8 | J5: APERTURA CB 80165 - 80166 | K5: MEDELLIN-ISTMINA-MEDELLIN | L5: 529500 | M5: =L5*0.12 -> 63540 | N5: =L5+M5 -> 593040
A6: TOTAL A FACTURAR | F6: =SUM(F3:F5) -> 768 | G6: =SUM(G3:G5) -> 1.7687439e+08 | H6: =SUM(H3:H5) -> 2.1048053e+08 | J6: APERTURA CB 80173 | K6: PASTO-OLAYA HERRERA-PASTO | L6: 300000 | M6: =L6*0.12 -> 36000 | N6: =L6+M6 -> 336000
J7: APERTURA CB 80365 | K7: MEDELLIN-QUIBDO-ME | L7: 292599 | M7: =L7*0.12 -> 35111.88 | N7: =L7+M7 -> 327710.88
J8: APERTURA CB 80455-80490-80382 | K8: MEDELLIN-ISTMINA-MEDELLIN | L8: 786900 | M8: =L8*0.12 -> 94428 | N8: =L8+M8 -> 881328
J9: APERTURA CB 80447 | K9: MEDELLIN-QUIBDO-MEDELLIN | L9: 392850 | M9: =L9*0.12 -> 47142 | N9: =L9+M9 -> 439992
J10: APERTURA CB 80530 | K10: CALI-GUAPI-CALI | L10: 571900 | M10: =L10*0.12 -> 68628 | N10: =L10+M10 -> 640528
J11: APERTURA CB 80541 | K11: TADO-MEDELLIN | L11: 392850 | M11: =L11*0.12 -> 47142 | N11: =L11+M11 -> 439992
J12: ORDEN DE CAMBIO CB 77681 | K12: VILLAVICENCIO-MAPIRIPAN-VILLAVICENCIO | L12: 1491000 | M12: =L12*0.12 -> 178920 | N12: =L12+M12 -> 1669920
J13: TOTAL | L13: =SUM(L3:L12) -> 5866048 | M13: =SUM(M3:M12) -> 703925.76 | N13: =SUM(N3:N12) -> 6569973.8

Sheet BASE DE LIQUIDACION 2025
A1: TARIFAS AÑO 2025 | G1: TARIFAS AÑO 2025 | N1: Incremento 2025
A2: TIPOLOGÍA | B2: Instalación de avisos internos | C2: Instalación de avisos EXTERNOS | D2: Transporte de señalización y aviso de 1,50m x 50 cm. | E2: Total Valor Actividad | G2: ORDENES DE CAMBIO | N2: 0.052
A3: TIPO I | B3: =10695.08*(1+$N$2) -> 11251.224 | C3: =120073.31*(1+$N$2) -> 126317.12 | D3: =54574.12*(1+$N$2) -> 57411.974 | E3: =185342.51*(1+$N$2) -> 194980.32 | G3: Tipificación | H3: Descripción | I3: Dia actividad | J3: Transporte | K3: Envio operador Logistico | L3: Gestión telefónica
A4: TIPO II - TIPO III - TIPO IV | B4: =10695.08*(1+$N$2) -> 11251.224 | C4: =120073.31*(1+$N$2) -> 126317.12 | D4: =105331.06*(1+$N$2) -> 110808.28 | E4: =236099.45*(1+$N$2) -> 248376.62 | G4: Tipo I | H4: Metropolitano | I4: =91255.89*(1+$N$2) -> 96001.196 | J4: =54574.12*(1+$N$2) -> 57411.974 | K4: =53547.34*(1+$N$2) -> 56331.802 | L4: =36031.04*(1+$N$2) -> 37904.654
G5: Tipo II | H5: Hasta 3 horas | I5: =221348.48*(1+$N$2) -> 232858.6 | J5: =105331.06*(1+$N$2) -> 110808.28 | K5: =53547.34*(1+$N$2) -> 56331.802 | L5: =36031.04*(1+$N$2) -> 37904.654
G6: Tipo III | H6: De 3 a 5 horas | I6: =327732.48*(1+$N$2) -> 344774.57 | J6: =105331.06*(1+$N$2) -> 110808.28 | K6: =53547.34*(1+$N$2) -> 56331.802 | L6: =36031.04*(1+$N$2) -> 37904.654
G7: Tipo IV | H7: Más de 5 horas | I7: =521514.86*(1+$N$2) -> 548633.63 | J7: =105331.06*(1+$N$2) -> 110808.28 | K7: =53547.34*(1+$N$2) -> 56331.802 | L7: =36031.04*(1+$N$2) -> 37904.654
G8: Destino Aereo* | H8: Viaje en Avión | I8: =521514.86*(1+$N$2) -> 548633.63 | J8: =105331.06*(1+$N$2) -> 110808.28 | K8: =53547.34*(1+$N$2) -> 56331.802 | L8: =36031.04*(1+$N$2) -> 37904.654
G9: * donde se requiera transporte aéreo o fluvial se factura adicional a tarifa TIPO IV el valor del tiquete + el 12% de admon

Sheet Tabla dinámica
A2: PUBLICIDAD APERTURAS | J2: NOMBRE CC | K2: Suma de VALOR | L2: Suma de VALOR2
A3: COORDINADOR | B3: CENTRO DE COSTOS LÍNEACOM | C3: % | D3: $ | E3: NOMBRE CC | F3: VALOR | J3: Redeban Centro ( Bogotá) | K3: 25583772 | L3: 0.15022377
A4: DIEGO FERNANDO HENAO CARDONA | B4: 0004-0002 | C4: 0.055926092 | D4: 7908299.9 | E4: =VLOOKUP(B4,'CENTRO DE COSTOS'!B:C,2,0) -> Redeban Eje Cafetero (Pereira) | F4: =D4 -> 7908299.9 | J4: Redeban Costa (Barranqullla) | K4: 24724978 | L4: 0.14518107
B5: 0004-0003 | C5: 0.15232589 | D5: 21539836 | E5: =VLOOKUP(B5,'CENTRO DE COSTOS'!B:C,2,0) -> Redeban Suroccidente (Cali) | F5: =D5 -> 21539836 | J5: Redeban Eje Cafetero (Pereira) | K5: 9321202.3 | L5: 0.054732593
A6: JOSE MAURICIO HERNANDEZ ROJAS | B6: 0004-0001 | C6: 0.13380842 | D6: 18921349 | E6: =VLOOKUP(B6,'CENTRO DE COSTOS'!B:C,2,0) -> Redeban Costa (Barranqullla) | F6: =D6 -> 18921349 | J6: Redeban Noroccidente (Medellín) | K6: 25905448 | L6: 0.1521126
A7: JUAN SEBASTIÁN RÍOS CASTRILLÓN | B7: 0004-0005 | C7: 0.14609403 | D7: 20658611 | E7: =VLOOKUP(B7,'CENTRO DE COSTOS'!B:C,2,0) -> Redeban Noroccidente (Medellín) | F7: =D7 -> 20658611 | J7: Redeban Oriente (Otros) | K7: 30795946 | L7: 0.18082881
A8: KEVIN ALEXIS CORZO BUSTOS | B8: 0004-0007 | C8: 0.19281002 | D8: 27264545 | E8: =VLOOKUP(B8,'CENTRO DE COSTOS'!B:C,2,0) -> Redeban Oriente (Otros) | F8: =D8 -> 27264545 | J8: Redeban Santander | K8: 28770277 | L8: 0.16893441
A9: MIGUEL JULIÁN HERNÁNDEZ GUARÍN | B9: 0004-0008 | C9: 0.17098927 | D9: 24178954 | E9: =VLOOKUP(B9,'CENTRO DE COSTOS'!B:C,2,0) -> Redeban Santander | F9: =D9 -> 24178954 | J9: Redeban Suroccidente (Cali) | K9: 25202795 | L9: 0.14798674
A10: WILLIAM ASDRUBAL ROZO ROZO | B10: 0004-0004 | C10: 0.14804629 | D10: 20934673 | E10: =VLOOKUP(B10,'CENTRO DE COSTOS'!B:C,2,0) -> Redeban Centro ( Bogotá) | F10: =D10 -> 20934673 | J10: Total general | K10: 1.7030442e+08 | L10: 1
A11: Total general | C11: 1 | D11: 1.4140627e+08
A21: COORDINADOR | B21: CENTRO DE COSTOS LÍNEACOM | C21: % | D21: $ | E21: NOMBRE CC | F21: VALOR
A22: DIEGO FERNANDO HENAO CARDONA | B22: 0004-0002 | C22: 0.048892486 | D22: 1412902.4 | E22: =VLOOKUP(B22,'CENTRO DE COSTOS'!B:C,2,0) -> Redeban Eje Cafetero (Pereira) | F22: =D22 -> 1412902.4
B23: 0004-0003 | C23: 0.12675411 | D23: 3662959.2 | E23: =VLOOKUP(B23,'CENTRO DE COSTOS'!B:C,2,0) -> Redeban Suroccidente (Cali) | F23: =D23 -> 3662959.2
A24: JOSE MAURICIO HERNANDEZ ROJAS | B24: 0004-0001 | C24: 0.20083045 | D24: 5803628.4 | E24: =VLOOKUP(B24,'CENTRO DE COSTOS'!B:C,2,0) -> Redeban Costa (Barranqullla) | F24: =D24 -> 5803628.4
A25: JUAN SEBASTIÁN RÍOS CASTRILLÓN | B25: 0004-0005 | C25: 0.18156309 | D25: 5246837.3 | E25: =VLOOKUP(B25,'CENTRO DE COSTOS'!B:C,2,0) -> Redeban Noroccidente (Medellín) | F25: =D25 -> 5246837.3
A26: KEVIN ALEXIS CORZO BUSTOS | B26: 0004-0007 | C26: 0.12220161 | D26: 3531400.6 | E26: =VLOOKUP(B26,'CENTRO DE COSTOS'!B:C,2,0) -> Redeban Oriente (Otros) | F26: =D26 -> 3531400.6
A27: MIGUEL JULIÁN HERNÁNDEZ GUARÍN | B27: 0004-0008 | C27: 0.15887947 | D27: 4591322.8 | E27: =VLOOKUP(B27,'CENTRO DE COSTOS'!B:C,2,0) -> Redeban Santander | F27: =D27 -> 4591322.8
A28: WILLIAM ASDRUBAL ROZO ROZO | B28: 0004-0004 | C28: 0.16087879 | D28: 4649099.4 | E28: =VLOOKUP(B28,'CENTRO DE COSTOS'!B:C,2,0) -> Redeban Centro ( Bogotá) | F28: =D28 -> 4649099.4
A29: Total general | C29: 1 | D29: 28898150

Sheet PUBLICIDAD APERTURAS
A1: CIUDAD SEDE | B1: COORDINADOR | C1: CENTRO DE COSTOS LÍNEACOM | D1: CÓDIGO DANE | E1: TA/CODIGO ACTIVIDAD | F1: CODIGO CB | G1: ACTIVIDAD | H1: TIPO DE APERTURA | I1: DEPARTAMENTO | J1: CIUDAD | K1: NOMBRE DEL CB | L1: RED | M1: FO | N1: FECHA LISTA | O1: FECHA ULTIMA ACTUALIZACION | P1: FORMATO | Q1: CADENA | R1: ESTADO | S1: OBSERVACIONES CLIENTE | T1: FORMA DE ATENCIÓN | U1: TERMINALES | V1: TIPIFICACION | W1: TIPO DE TRAYECTO | X1: NOMBRE DEL TECNICO | Y1: FLANGER, DISPLAY LEGAL, DISPLAY CARTA O TABLOIDE | Z1: INSTALACIÓN DE AVISOS EXTERNOS | AA1: TRANSPORTE DE AVISO POR INSTALACION O POR NO INSTALACION (IDA-REGRESO) | AB1: VALOR FLANGER, SEPARADOR, STICKER, DISPLAY | AC1: VALOR INSTALACIÓN DE AVISOS EXTERNOS | AD1: VALOR TRANSPORTE DE AVISO | AE1: VALOR TOTAL INSTALACION DE PUBLICIDAD
A2: MEDELLIN | B2: =VLOOKUP(A2,'CENTRO DE COSTOS'!A:D,4,FALSE) -> JUAN SEBASTIÁN RÍOS CASTRILLÓN | C2: =VLOOKUP(A2,'CENTRO DE COSTOS'!A:D,2,FALSE) -> 0004-0005 | D2: 5091 | E2: TA-25-792913 | F2: 79058 | G2: APERTURA | H2: CB CRECIMIENTO - OTRAS LISTAS | I2: ANTIOQUIA | J2: BETANIA | K2: BARRIO BETANIA ANTIOQUIA BETANIA | L2: REDEBAN | M2: FO-25-1167345 | N2: 45821 | O2: 45842 | P2: UNO A UNO | Q2: UNO A UNO | R2: EJECUTADO | S2: 13-06 SE ESTABLECE COMUNICACIÓN CON EL USUARIO EL CUAL IDNICA QUE EL NECESITA ES UN CORRESPONSAL CON UN CUPO BASTANTES GRANDE, QUE SI EL CORRESPONSAL ES SOLO POR 10 MILLONES NO LE INTERESA - COMUNICACIÓN POR WPP 13/6/2025 ESTE PUNTO FUE ENVIADO EN LA LISTA DE AYER, ME APOYAN POR FAVOR DEJÁNDOLO PENDIENTE HASTA LAS HORAS DE LA TARDE, ES DECIR, NO PROCESEN LA PROGRAMACIÓN, PERO TAMPOCO LO CANCELEN. 19/6/2025 POR FAVOR PROCEDER CON LA IMPLEMENTACIÓN, AGRADEZCO NOS CONFIRMEN CUANDO SE PROGRAME EL PUNTO. 26/6/2025 SE REALIZÓ VISITA NO SE LOGRA INSTALAR YA QUE EL CUPO ASIGNADO ES DE 10 MILLONES EL CB SOLICITO QUE FUERA MÁS ALTO, SE ESCALO TEMA A BANCO Y NO BRINDAN INFORMACIÓN OPORTUNA ADICIONAL NOS INDICA QUE SE DEBE CORREGIR EL CORREO ELECTRÓNICO RDESCOBARARANGO@YAHOO.ES SE POSPONE ACTIVIDAD 4/7/2025 SE REALIZA INSTALACIÓN DE CORRESPONSAL, SE INSTALAN EQUIPOS CON PRUEBAS EXITOSAS, SE CAPACITA Y SE EVALÚA AL CLIENTE, SE INSTALA PUBLICIDAD COMPLETA, CB QUEDA OPERATIVO. USUARIO SOMOS BANCOLOMBIA ACTIVO | T2: VISITA_TÉCNICA | U2: SASZZ633 | V2: TIPO III | W2: TERRESTRE | X2: QUINTERO SANCHEZ JUAN SEBASTIAN | Y2: 1 | Z2: 1 | AA2: 3 | AB2: =IF(V2="TIPO I",'BASE DE LIQUIDACION 2025'!$B$3,'BASE DE LIQUIDACION 2025'!$B$4) -> 11251.224 | AC2: =IF(V2="TIPO I",'BASE DE LIQUIDACION 2025'!$C$3,'BASE DE LIQUIDACION 2025'!$C$4) -> 126317.12 | AD2: =IF(V2="TIPO I",'BASE DE LIQUIDACION 2025'!$D$3,'BASE DE LIQUIDACION 2025'!$D$4) -> 110808.28 | AE2: =AB2*Y2+Z2*AC2+AA2*AD2 -> 469993.17
A3: SANTA MARTA | B3: =VLOOKUP(A3,'CENTRO DE COSTOS'!A:D,4,FALSE) -> JOSE MAURICIO HERNANDEZ ROJAS | C3: =VLOOKUP(A3,'CENTRO DE COSTOS'!A:D,2,FALSE) -> 0004-0001 | D3: 44430 | E3: TA-25-790987 | F3: 79898 | G3: APERTURA | H3: CB CRECIMIENTO ALIANZA - NUEVO | I3: LA GUAJIRA | J3: MAICAO | K3: DISTRICOL COMERCIALIZADORA | L3: REDEBAN | M3: FO-25-1186686 | N3: 45826 | O3: 45843 | P3: AGREGADOR | Q3: DISTRICOL | R3: EJECUTADO | S3: 18-06 PROGRAMACIÓN REALIZADA POR LA ALIANZA 21/6/2025 EN COMUNICACIÓN CON EL SEÑOR FRANCISCO VELÁZQUEZ AL NÚMERO 3003299172, ME INFORMA QUE EL PEAJE ENTRE MAICAO Y RIOHACHA FUE VOLADO POR EL ELN, Y QUE EL SECTOR ESTÁ EN ZONA ROJA POR PROBLEMAS DE ORDEN PÚBLICO , SE REPROGRAMA LA VISITA PARA LA PRÓXIMA SEMANA QUE SE RESTABLEZCA EL ORDEN EN EL SECTOR 26/6/2025 LA ALTERACIÓN AUN CONTINUA POR ESTE MOTIVO NO SE HA PODIDO REALIZAR IMPLEMENTACIÓN 2/7/2025 SE PROGRAMA VISITA PARA EL 04-07 04-07 NO SE LOGRA COMPLETAR LA APERTURA YA QUE EL CLIENTE MANIFIESTA NO TENER DISPOSICIÓN POR COMPROMISO FAMILIAR, QUEDA PENDIENTE LA CAPACITACIÓN ESTÁ QUEDA APLAZADA PARA EL DÍA SÁBADO 5 DE JULIO 5/7/2025 SE REALIZA INSTALACIÓN DE CORRESPONSAL, SE INSTALAN EQUIPOS CON PRUEBAS EXITOSAS, SE CAPACITA Y SE EVALÚA AL CLIENTE, SE INSTALA PUBLICIDAD COMPLETA, CB QUEDA OPERATIVO. USUARIO SOMOS BANCOLOMBIA ACTIVO | T3: VISITA_TÉCNICA | U3: SAUZZ961 | V3: TIPO IV | W3: TERRESTRE | X3: THOMAS CAMPO SIGIFREDO SEGUNDO | Y3: 1 | Z3: 1 | AA3: 3 | AB3: =IF(V3="TIPO I",'BASE DE LIQUIDACION 2025'!$B$3,'BASE DE LIQUIDACION 2025'!$B$4) -> 11251.224 | AC3: =IF(V3="TIPO I",'BASE DE LIQUIDACION 2025'!$C$3,'BASE DE LIQUIDACION 2025'!$C$4) -> 126317.12 | AD3: =IF(V3="TIPO I",'BASE DE LIQUIDACION 2025'!$D$3,'BASE DE LIQUIDACION 2025'!$D$4) -> 110808.28 | AE3: =AB3*Y3+Z3*AC3+AA3*AD3 -> 469993.17
A4: PASTO | B4: =VLOOKUP(A4,'CENTRO DE COSTOS'!A:D,4,FALSE) -> DIEGO FERNANDO HENAO CARDONA | C4: =VLOOKUP(A4,'CENTRO DE COSTOS'!A:D,2,FALSE) -> 0004-0003 | D4: 86568 | E4: TA-25-791021 | F4: 79905 | G4: APERTURA | H4: CB CRECIMIENTO ALIANZA - NUEVO | I4: PUTUMAYO | J4: PUERTO ASIS | K4: DISTRICOL AGROFER Y MAQ ASIS | L4: REDEBAN | M4: FO-25-1108021 | N4: 45826 | O4: 45852 | P4: AGREGADOR | Q4: DISTRICOL | R4: EJECUTADO | S4: 18-06 PROGRAMACIÓN REALIZADA POR LA ALIANZA (POR FAVOR CONTACTAR AL OPERADOR DEL PUNTO DE NOMBRE DANIEL MARCILIA, CEL: 3144338225 TODA VEZ QUE SERÁ LA PERSONA QUE RECIBIRÁ AL TÉCNICO. SE SOLICITA CONTACTO PREFERIBLEMENTE POR WHATSAPP YA QUE LA SEÑAL ES BASTANTE DÉBIL EN LA ZONA DE UBICACIÓN DEL PUNTO ) 20/6/2025 NO ES POSIBLE REALIZAR EL DESPLAZAMIENTO HACIA PUTUMAYO PARA REALIZAR APERTURA EL DIA 20 DE JUNIO, YA QUE DEBIDO A PROBLEMAS EN LA VIA CAIDA DE PUENTE EN EL MUNICIPIO DE COLON SE RESTRINGE EL PASO VEHICULAR HACIA LA ZONA Y NO SE ENCUENTRA TRANSPORTE DISPONIBLE 24/6/2025 LA APERTURA QUE SE MENCIONA A CONTINUACION NO HA SIDO POSIBLE LA REALIZACION YA QUE POR PROBLEMAS EN LA VIA, DERUMBE DE PUENTE HACIA EL MUNICIPIO DE COLON, NO HAY PASO PARA EL DEPARTAMENTO DE PUTUMAYO, SE VALIDO CON LA EMPRESA DE TRANSPORTES PERO ESTA NO ESTABA DESPACHANDO BUSES YA QUE SE ESTABAN QUEDANDO HASTA 12 HORAS EN LA VIA ESPERANDO UN PASO INTERMITENTE POR UNA ZONA PROVISIONAL, POR TANTO SE QUEDA A LA ESPERA DE QUE SE APERTURE LA VIA O SE PUEDE TENER UNA VIA ALTERNA EN CONDICIONES DE DESPLAZAMIENTO. 01-07 SE INTENTO VIAJAR PERO LOS BUSES HACIA LA ZONA NO ESTAN SALIENDO 09-07 SE ENCUENTRA AÚN NOVEDAD EN LA VÍA QUE DEL DEPARTAMENTO DE NARIÑO COMUNICA CON EL DEPARTAMENTO DE PUTUMAYO , YA QUE POR LA CAÍDA DEL PUENTE LA VÍA SE CERRÓ Y SE HABILITO UN PASO ALTERNO QUE DEBIDO AL INVIERNO SOLO ESTÁ PERMITIENDO EL PASO DE VEHÍCULOS LIVIANOS. 14-07 SE REALIZA INSTALACIÓN DE CORRESPONSAL, SE INSTALAN EQUIPOS CON PRUEBAS EXITOSAS, SE CAPACITA Y SE EVALÚA AL CLIENTE, SE INSTALA PUBLICIDAD COMPLETA, CB QUEDA OPERATIVO. USUARIO SOMOS BANCOLOMBIA ACTIV | T4: VISITA_TÉCNICA | U4: SAUZZ979 | V4: TIPO IV | W4: TERRESTRE | X4: ROMERO ROJAS BREIDY JHOHAN | Y4: 1 | Z4: 1 | AA4: 1 | AB4: =IF(V4="TIPO I",'BASE DE LIQUIDACION 2025'!$B$3,'BASE DE LIQUIDACION 2025'!$B$4) -> 11251.224 | AC4: =IF(V4="TIPO I",'BASE DE LIQUIDACION 2025'!$C$3,'BASE DE LIQUIDACION 2025'!$C$4) -> 126317.12 | AD4: =IF(V4="TIPO I",'BASE DE LIQUIDACION 2025'!$D$3,'BASE DE LIQUIDACION 2025'!$D$4) -> 110808.28 | AE4: =AB4*Y4+Z4*AC4+AA4*AD4 -> 248376.62
A5: CALI | B5: =VLOOKUP(A5,'CENTRO DE COSTOS'!A:D,4,FALSE) -> DIEGO FERNANDO HENAO CARDONA | C5: =VLOOKUP(A5,'CENTRO DE COSTOS'!A:D,2,FALSE) -> 0004-0003 | D5: 19809 | E5: TA-25-790617 | F5: 79956 | G5: APERTURA | H5: CB CRECIMIENTO - NUEVO | I5: CAUCA | J5: TIMBIQUI | K5: BARRIO LAS BRISAS TIMBIQUI | L5: REDEBAN | M5: FO-25-1107284 | N5: 45826 | O5: 45841 | P5: UNO A UNO | Q5: UNO A UNO | R5: EJECUTADO | S5: 18-06-2025 SE REALIZA LLAMADA AL CLIENTE, SE HABLA CON LA SRA YOLANDA TORRES PORTOCARRERO SE VALIDA DIRECCIÓN OK, CANAL OK, DISPONIBILIDAD TOTAL, LLAMAR EL DÍA LA INSTALACIÓN PARA CONFIRMAR VISITA, AVISO EXTERIOR ALTURA APROX 2 METROS; TOMACORRIENTE CERCANO: SI; TIENE CABINA DE SEGURIDAD: SI // CONTACTO REALIZADO POR WHATSAPP - ACTIVIDAD PROGRAMADA PARA DICHA FECHA POR TRANSPORTE 1/7/2025 SE REALIZARA VISITA DE APERTURA EL DIA 3 DE JULIO DADO NO SE LOGRA CONSEGUIR VUELO PARA ANTES 4/7/2025 SE REALIZA INSTALACIÓN DE CORRESPONSAL, SE INSTALAN EQUIPOS CON PRUEBAS EXITOSAS, SE CAPACITA Y SE EVALÚA AL CLIENTE, SE INSTALA PUBLICIDAD COMPLETA, CB QUEDA OPERATIVO. USUARIO SOMOS BANCOLOMBIA ACTIVO | T5: VISITA_TÉCNICA | U5: SAVZZ118 | V5: TIPO IV ESPECIAL | W5: AEREO | X5: PAREDES CASTILLO DIEGO | Y5: 1 | Z5: 1 | AA5: 1 | AB5: =IF(V5="TIPO I",'BASE DE LIQUIDACION 2025'!$B$3,'BASE DE LIQUIDACION 2025'!$B$4) -> 11251.224 | AC5: =IF(V5="TIPO I",'BASE DE LIQUIDACION 2025'!$C$3,'BASE DE LIQUIDACION 2025'!$C$4) -> 126317.12 | AD5: =IF(V5="TIPO I",'BASE DE LIQUIDACION 2025'!$D$3,'BASE DE LIQUIDACION 2025'!$D$4) -> 110808.28 | AE5: =AB5*Y5+Z5*AC5+AA5*AD5 -> 248376.62
A6: VILLAVICENCIO | B6: =VLOOKUP(A6,'CENTRO DE COSTOS'!A:D,4,FALSE) -> KEVIN ALEXIS CORZO BUSTOS | C6: =VLOOKUP(A6,'CENTRO DE COSTOS'!A:D,2,FALSE) -> 0004-0007 | D6: 95001 | E6: TA-25-799127 | F6: 80059 | G6: APERTURA | H6: CB CRECIMIENTO - NUEVO | I6: GUAVIARE | J6: SAN JOSE DEL GUAVIARE | K6: BARRIO EL PORVENIR SAN JOSE DEL GUAVIARE 4 | L6: REDEBAN | M6: FO-25-1128664 | N6: 45832 | O6: 45839 | P6: UNO A UNO | Q6: UNO A UNO | R6: EJECUTADO | S6: 21-06 SE REALIZA LLAMADA AL CLIENTE, SE HABLA CON LA SRA CLAUDIA FERNANDA PERDOMO GONZALEZ, SE VALIDA DIRECCIÓN OK, CANAL OK, DISPONIBILIDAD TOTAL, LLAMAR EL DÍA LA INSTALACIÓN PARA CONFIRMAR VISITA, AVISO EXTERIOR ALTURA APROX DONDE EL TECNICO LO VEA CONVENIENTE; TOMACORRIENTE CERCANO:SI; TIENE CABINA DE SEGURIDAD:NO// MODEM NO TIENE PUERTOS DISPONIBLES 26-6 EN COMUNICACIÓN CON EL USUARIO INDICA QUE NOS ATIENDE EL DIA MARTES POR QUE AUN ESTA ADECUANDO EL LOCAL 1/7/2025 SE REALIZA INSTALACIÓN DE CORRESPONSAL, SE INSTALAN EQUIPOS CON PRUEBAS EXITOSAS, SE CAPACITA Y SE EVALÚA AL CLIENTE, SE INSTALA PUBLICIDAD COMPLETA, CB QUEDA OPERATIVO. USUARIO SOMOS BANCOLOMBIA ACTIVO. SE INSTAAN 15 MT DE CABLE UTP | T6: VISITA_TÉCNICA | U6: SAXZZ468 | V6: TIPO IV | W6: TERRESTRE | X6: PEDREROS CONTRERAS MICHAEL STEVENS | Y6: 1 | Z6: 1 | AA6: 1 | AB6: =IF(V6="TIPO I",'BASE DE LIQUIDACION 2025'!$B$3,'BASE DE LIQUIDACION 2025'!$B$4) -> 11251.224 | AC6: =IF(V6="TIPO I",'BASE DE LIQUIDACION 2025'!$C$3,'BASE DE LIQUIDACION 2025'!$C$4) -> 126317.12 | AD6: =IF(V6="TIPO I",'BASE DE LIQUIDACION 2025'!$D$3,'BASE DE LIQUIDACION 2025'!$D$4) -> 110808.28 | AE6: =AB6*Y6+Z6*AC6+AA6*AD6 -> 248376.62
A7: PEREIRA | B7: =VLOOKUP(A7,'CENTRO DE COSTOS'!A:D,4,FALSE) -> DIEGO FERNANDO HENAO CARDONA | C7: =VLOOKUP(A7,'CENTRO DE COSTOS'!A:D,2,FALSE) -> 0004-0002 | D7: 66318 | E7: TA-25-799134 | F7: 80021 | G7: APERTURA | H7: CB CRECIMIENTO - NUEVO | I7: RISARALDA | J7: GUATICA | K7: BARRIO CENTRO GUATICA 4 | L7: REDEBAN | M7: FO-25-1158501 | N7: 45832 | O7: 45847 | P7: UNO A UNO | Q7: UNO A UNO | R7: EJECUTADO | S7: 24-06-2025 SE REALIZA LLAMADA AL CLIENTE, SE HABLA CON LA SRA ZHARICK QUINTERO TABARES SE VALIDA DIRECCIÓN OK, CANAL OK, DISPONIBILIDAD TOTAL, LLAMAR EL DÍA LA INSTALACIÓN PARA CONFIRMAR VISITA, AVISO EXTERIOR ALTURA APROX 3 METROS; TOMACORRIENTE CERCANO: SI; TIENE CABINA DE SEGURIDAD: SI // CONTACTO REALIZADO POR LA APP 27/6/2025 SE REALIZA VISITA DE APERTURA AL CB UNO A UNO CON CÓDIGO 3007080021 BARRIO CENTRO GUATICA 44, DIRECCIÓN CR 5 12 32 , COORDENADAS 5.315427, -75.798033, PERO SE ENCUENTRA CERCANÍA CON CORRESPONSAL DISTRICOL INSTALADO CON CÓDIGO 3007070765 DISTRICOL UNIVERSO ESCOLAR , DIRECCIÓN CL 13 12 66, COORDENADAS 5.315486, -75.797833, QUEDANDO A MENOS DE 25 MTS DE DISTANCIA UNO DEL OTRO A DOS CASAS EN LA MISMA CUADRA, SE REALIZA ESCALAMIENTO POR CERCANÍA EN ESPERA DE COMO PROCEDER. / ENTIDAD APRUEBA INSTALACIÓN 9/7/2025 SE REALIZA INSTALACIÓN DE CORRESPONSAL, SE INSTALAN EQUIPOS CON PRUEBAS EXITOSAS, SE CAPACITA Y SE EVALÚA AL CLIENTE, SE INSTALA PUBLICIDAD COMPLETA, CB QUEDA OPERATIVO. USUARIO SOMOS BANCOLOMBIA ACTIVO | T7: VISITA_TÉCNICA | U7: SAXZZ471 | V7: TIPO II | W7: TERRESTRE | X7: ARROYAVE CANO MANUEL GUILLERMO | Y7: 1 | Z7: 1 | AA7: 3 | AB7: =IF(V7="TIPO I",'BASE DE LIQUIDACION 2025'!$B$3,'BASE DE LIQUIDACION 2025'!$B$4) -> 11251.224 | AC7: =IF(V7="TIPO I",'BASE DE LIQUIDACION 2025'!$C$3,'BASE DE LIQUIDACION 2025'!$C$4) -> 126317.12 | AD7: =IF(V7="TIPO I",'BASE DE LIQUIDACION 2025'!$D$3,'BASE DE LIQUIDACION 2025'!$D$4) -> 110808.28 | AE7: =AB7*Y7+Z7*AC7+AA7*AD7 -> 469993.17
A8: APARTADO | B8: =VLOOKUP(A8,'CENTRO DE COSTOS'!A:D,4,FALSE) -> JUAN SEBASTIÁN RÍOS CASTRILLÓN | C8: =VLOOKUP(A8,'CENTRO DE COSTOS'!A:D,2,FALSE) -> 0004-0005 | D8: 27077 | E8: TA-25-799154 | F8: 80067 | G8: APERTURA | H8: CB CRECIMIENTO - NUEVO | I8: CHOCO | J8: BAJO BAUDO | K8: BARRIO EL SILENCIO BAJO BAUDO PIZARRO BAJO BAUDO | L8: REDEBAN | M8: FO-25-1128775 | N8: 45832 | O8: 45841 | P8: UNO A UNO | Q8: UNO A UNO | R8: EJECUTADO | S8: 24-06 SE REALIZA LLAMADA AL CLIENTE, SE HABLA CON LA SR KEYNER ESTIVEN IBARGUEN MINA SE VALIDA DIRECCIÓN OK, CANAL OK, DISPONIBILIDAD TOTAL, LLAMAR EL DÍA LA INSTALACIÓN PARA CONFIRMAR VISITA, AVISO EXTERIOR ALTURA APROX 2 METROS; TOMACORRIENTE CERCANO: SI; TIENE CABINA DE SEGURIDAD: SI 03-07 SE REALIZA INSTALACIÓN DE CORRESPONSAL, SE INSTALAN EQUIPOS CON PRUEBAS EXITOSAS, SE CAPACITA Y SE EVALÚA AL CLIENTE, SE INSTALA PUBLICIDAD COMPLETA, CB QUEDA OPERATIVO. USUARIO SOMOS BANCOLOMBIA ACTIVO | T8: VISITA_TÉCNICA | U8: SAXZZ488 | V8: TIPO IV ESPECIAL | W8: AEREO | X8: ROBLEDO DIAZ ANDRES FELIPE | Y8: 1 | Z8: 1 | AA8: 1 | AB8: =IF(V8="TIPO I",'BASE DE LIQUIDACION 2025'!$B$3,'BASE DE LIQUIDACION 2025'!$B$4) -> 11251.224 | AC8: =IF(V8="TIPO I",'BASE DE LIQUIDACION 2025'!$C$3,'BASE DE LIQUIDACION 2025'!$C$4) -> 126317.12 | AD8: =IF(V8="TIPO I",'BASE DE LIQUIDACION 2025'!$D$3,'BASE DE LIQUIDACION 2025'!$D$4) -> 110808.28 | AE8: =AB8*Y8+Z8*AC8+AA8*AD8 -> 248376.62
A9: PASTO | B9: =VLOOKUP(A9,'CENTRO DE COSTOS'!A:D,4,FALSE) -> DIEGO FERNANDO HENAO CARDONA | C9: =VLOOKUP(A9,'CENTRO DE COSTOS'!A:D,2,FALSE) -> 0004-0003 | D9: 52317 | E9: TA-25-799157 | F9: 80019 | G9: APERTURA | H9: CB CRECIMIENTO - NUEVO | I9: NARIÑO | J9: GUACHUCAL | K9: BARRIO CRR DE MIRAFLORES GUACHUCAL | L9: REDEBAN | M9: FO-25-1128785 | N9: 45832 | O9: 45839 | P9: UNO A UNO | Q9: UNO A UNO | R9: EJECUTADO | S9: 24-06 SE REALIZA LLAMADA AL CLIENTE, SE HABLA CON LA SR ARLEY ALEXANDER NARVAEZ CORTES SE VALIDA DIRECCIÓN OK, DISPONIBILIDAD TOTAL, LLAMAR EL DÍA LA INSTALACIÓN PARA CONFIRMAR VISITA, AVISO EXTERIOR ALTURA APROX 1.50 METROS; TOMA CORRIENTE CERCANO: SI; TIENE CABINA DE SEGURIDAD: SI , USUARIO INDICA QUE SE EL MODEN SE ENCUENTRA 5 METROS 26-06 POR MOTIVOS DE CIERRE DE LA VIA HACIA LA ZONA NO SE PUEDE REALIZAR DESPLAZAMIENTO HASTA EL SITIO POR LO CUAL SE DEBE REPROGRAMAR LA ACTIVIDAD PARA EL DÍA LUNES QUE YA SE NORMALICE EL TRANSPORTE HACIA EL LUGAR 1/7/2025 SE REALIZA INSTALACIÓN DE CORRESPONSAL, SE INSTALAN EQUIPOS CON PRUEBAS EXITOSAS, SE CAPACITA Y SE EVALÚA AL CLIENTE, SE INSTALA PUBLICIDAD COMPLETA, CB QUEDA OPERATIVO. USUARIO SOMOS BANCOLOMBIA ACTIVO | T9: VISITA_TÉCNICA | U9: SAXZZ491 | V9: TIPO II | W9: TERRESTRE | X9: PAZ MARTINEZ RICHARD HUMBERTO | Y9: 1 | Z9: 1 | AA9: 1 | AB9: =IF(V9="TIPO I",'BASE DE LIQUIDACION 2025'!$B$3,'BASE DE LIQUIDACION 2025'!$B$4) -> 11251.224 | AC9: =IF(V9="TIPO I",'BASE DE LIQUIDACION 2025'!$C$3,'BASE DE LIQUIDACION 2025'!$C$4) -> 126317.12 | AD9: =IF(V9="TIPO I",'BASE DE LIQUIDACION 2025'!$D$3,'BASE DE LIQUIDACION 2025'!$D$4) -> 110808.28 | AE9: =AB9*Y9+Z9*AC9+AA9*AD9 -> 248376.62
A10: BOGOTA | B10: =VLOOKUP(A10,'CENTRO DE COSTOS'!A:D,4,FALSE) -> WILLIAM ASDRUBAL ROZO ROZO | C10: =VLOOKUP(A10,'CENTRO DE COSTOS'!A:D,2,FALSE) -> 0004-0004 | D10: 25181 | E10: TA-25-799210 | F10: 80024 | G10: APERTURA | H10: CAMBIO DE RAZON SOCIAL | I10: CUNDINAMARCA | J10: CHOACHI | K10: BARRIO LAS PALMAS CHOACHÍ | L10: REDEBAN | M10: FO-25-1128955 | N10: 45832 | O10: 45839 | P10: UNO A UNO | Q10: UNO A UNO | R10: EJECUTADO | S10: 24-06 SE REALIZA LLAMADA AL CLIENTE, SE HABLA CON LA SRA NIDIA CAMILA BORBON RODRIGUEZ, SE VALIDA DIRECCIÓN OK, CANAL OK, DISPONIBILIDAD TOTAL, LLAMAR EL DÍA LA INSTALACIÓN PARA CONFIRMAR VISITA, AVISO EXTERIOR ALTURA APROX DONDE EL TECNICO LO VEA CONVENIENTE; TOMACORRIENTE CERCANO: SI; TIENE CABINA DE SEGURIDAD: NO 25-06 25-06 EN COMUNICACIÓN CON EL COMERCIO AL # 3115056967 LA SRA NIDIA PARA ADELANTAR APERTURA PARA EL DÍA DE MAÑANA 26-06-2025, SIN NOVEDAD / NUEVAMENTE EN COMUNICACIÓN CON EL COMERCIO AL # 3115056967 LA SRA NIDIA MANIFIESTA QUE NO PUEDE RECIBIR LA INSTALACIÓN EL DÍA 26 NI 27 DE JUNIO, PIDE SEA REPROGRAMADA PARA EL DÍA 01 Ó 02 DE JULIO YA QUE DEBE HACER CIERRE DEL COMERCIO EXISTENTE. 1/7/2025 SE REALIZA INSTALACIÓN DE CORRESPONSAL, SE INSTALAN EQUIPOS CON PRUEBAS EXITOSAS, SE CAPACITA Y SE EVALÚA AL CLIENTE, SE INSTALA PUBLICIDAD COMPLETA, CB QUEDA OPERATIVO. USUARIO SOMOS BANCOLOMBIA ACTIVO | T10: VISITA_TÉCNICA | U10: SAXZZ523 | V10: TIPO II | W10: TERRESTRE | X10: BUSTOS MORA DIEGO MANUEL | Y10: 1 | Z10: 1 | AA10: 1 | AB10: =IF(V10="TIPO I",'BASE DE LIQUIDACION 2025'!$B$3,'BASE DE LIQUIDACION 2025'!$B$4) -> 11251.224 | AC10: =IF(V10="TIPO I",'BASE DE LIQUIDACION 2025'!$C$3,'BASE DE LIQUIDACION 2025'!$C$4) -> 126317.12 | AD10: =IF(V10="TIPO I",'BASE DE LIQUIDACION 2025'!$D$3,'BASE DE LIQUIDACION 2025'!$D$4) -> 110808.28 | AE10: =AB10*Y10+Z10*AC10+AA10*AD10 -> 248376.62
A11: PASTO | B11: =VLOOKUP(A11,'CENTRO DE COSTOS'!A:D,4,FALSE) -> DIEGO FERNANDO HENAO CARDONA | C11: =VLOOKUP(A11,'CENTRO DE COSTOS'!A:D,2,FALSE) -> 0004-0003 | D11: 52696 | E11: TA-25-799256 | F11: 80061 | G11: APERTURA | H11: CB CRECIMIENTO - NUEVO | I11: NARIÑO | J11: SANTA BARBARA | K11: BARRIO LOS ANGELES SANTA BARBARA | L11: REDEBAN | M11: FO-25-1129108 | N11: 45832 | O11: 45846 | P11: UNO A UNO | Q11: UNO A UNO | R11: EJECUTADO | S11: 24-06 SE REALIZA LLAMADA AL CLIENTE, SE HABLA CON LA SR ALBERS ANDRES MARTINEZ CABALLERO SE VALIDA DIRECCIÓN OK, CANAL OK, DISPONIBILIDAD TOTAL, LLAMAR EL DÍA LA INSTALACIÓN PARA CONFIRMAR VISITA, AVISO EXTERIOR ALTURA APROX 2 METROS; TOMACORRIENTE CERCANO: SI; TIENE CABINA DE SEGURIDAD: NO 04-07 DEBIDO A QUE SE DEBE TOMAR TRANSPORTE FLUVIAL NO ES POSIBLE REALIZAR LA VISITA EL DIA DE HOY PUES NO SE LOGRA CONSEGUIR DESPLAZAMIENTO , SE REALIZARA DESPLAZAMIENTO LA PRÓXIMA SEMANA PARA VALIDAR SI SE CONSIGUE LANCHA PARA EL SITIO 08-07 SE REALIZA INSTALACIÓN DE CORRESPONSAL, SE INSTALAN EQUIPOS CON PRUEBAS EXITOSAS, SE CAPACITA Y SE EVALÚA AL CLIENTE, SE INSTALA PUBLICIDAD COMPLETA, CB QUEDA OPERATIVO. USUARIO SOMOS BANCOLOMBIA ACTIVO | T11: VISITA_TÉCNICA | U11: SAXZZ549 | V11: TIPO IV ESPECIAL | W11: TERRESTRE/FLUVIAL | X11: PAZ MARTINEZ RICHARD HUMBERTO | Y11: 1 | Z11: 1 | AA11: 1 | AB11: =IF(V11="TIPO I",'BASE DE LIQUIDACION 2025'!$B$3,'BASE DE LIQUIDACION 2025'!$B$4) -> 11251.224 | AC11: =IF(V11="TIPO I",'BASE DE LIQUIDACION 2025'!$C$3,'BASE DE LIQUIDACION 2025'!$C$4) -> 126317.12 | AD11: =IF(V11="TIPO I",'BASE DE LIQUIDACION 2025'!$D$3,'BASE DE LIQUIDACION 2025'!$D$4) -> 110808.28 | AE11: =AB11*Y11+Z11*AC11+AA11*AD11 -> 248376.62
A12: MANIZALES | B12: =VLOOKUP(A12,'CENTRO DE COSTOS'!A:D,4,FALSE) -> DIEGO FERNANDO HENAO CARDONA | C12: =VLOOKUP(A12,'CENTRO DE COSTOS'!A:D,2,FALSE) -> 0004-0002 | D12: 17001 | E12: TA-25-803977 | F12: 80103 | G12: APERTURA | H12: CB CRECIMIENTO ALIANZA - NUEVO | I12: CALDAS | J12: MANIZALES | K12: DISTRICOL TIENDA PLAN B | L12: REDEBAN | M12: FO-25-1138942 | N12: 45834 | O12: 45839 | P12: AGREGADOR | Q12: DISTRICOL | R12: EJECUTADO | S12: 26-06 PROGRAMACIÓN REALIZADA POR LA ALIANZA 1/7/2025 SE REALIZA INSTALACIÓN DE CORRESPONSAL, SE INSTALAN EQUIPOS CON PRUEBAS EXITOSAS, SE CAPACITA Y SE EVALÚA AL CLIENTE, SE INSTALA PUBLICIDAD COMPLETA, CB QUEDA OPERATIVO. USUARIO SOMOS BANCOLOMBIA ACTIVO | T12: VISITA_TÉCNICA | U12: V1ZZZ953 | V12: TIPO I | W12: TERRESTRE | X12: ARROYAVE CANO MANUEL GUILLERMO | Y12: 1 | Z12: 1 | AA12: 1 | AB12: =IF(V12="TIPO I",'BASE DE LIQUIDACION 2025'!$B$3,'BASE DE LIQUIDACION 2025'!$B$4) -> 11251.224 | AC12: =IF(V12="TIPO I",'BASE DE LIQUIDACION 2025'!$C$3,'BASE DE LIQUIDACION 2025'!$C$4) -> 126317.12 | AD12: =IF(V12="TIPO I",'BASE DE LIQUIDACION 2025'!$D$3,'BASE DE LIQUIDACION 2025'!$D$4) -> 57411.974 | AE12: =AB12*Y12+Z12*AC12+AA12*AD12 -> 194980.32
A13: NEIVA | B13: =VLOOKUP(A13,'CENTRO DE COSTOS'!A:D,4,FALSE) -> KEVIN ALEXIS CORZO BUSTOS | C13: =VLOOKUP(A13,'CENTRO DE COSTOS'!A:D,2,FALSE) -> 0004-0007 | D13: 18753 | E13: TA-25-803980 | F13: 80108 | G13: APERTURA | H13: CB CRECIMIENTO ALIANZA - NUEVO | I13: CAQUETA | J13: SAN VICENTE DEL CAGUAN | K13: DISTRICOL GUACAMAYAS.NET | L13: REDEBAN | M13: FO-25-1138951 | N13: 45834 | O13: 45842 | P13: AGREGADOR | Q13: DISTRICOL | R13: EJECUTADO | S13: 26-06 PROGRAMACIÓN REALIZADA POR LA ALIANZA 4/7/2025 SE REALIZA INSTALACIÓN DE CORRESPONSAL, SE INSTALAN EQUIPOS CON PRUEBAS EXITOSAS, SE CAPACITA Y SE EVALÚA AL CLIENTE, SE INSTALA PUBLICIDAD COMPLETA, CB QUEDA OPERATIVO. USUARIO SOMOS BANCOLOMBIA ACTIVO | T13: VISITA_TÉCNICA | U13: V1ZZZ954 | V13: TIPO IV ESPECIAL | W13: TERRESTRE / AEREO | X13: BERMUDEZ SANCHEZ JOSE NEYBER | Y13: 1 | Z13: 1 | AA13: 1 | AB13: =IF(V13="TIPO I",'BASE DE LIQUIDACION 2025'!$B$3,'BASE DE LIQUIDACION 2025'!$B$4) -> 11251.224 | AC13: =IF(V13="TIPO I",'BASE DE LIQUIDACION 2025'!$C$3,'BASE DE LIQUIDACION 2025'!$C$4) -> 126317.12 | AD13: =IF(V13="TIPO I",'BASE DE LIQUIDACION 2025'!$D$3,'BASE DE LIQUIDACION 2025'!$D$4) -> 110808.28 | AE13: =AB13*Y13+Z13*AC13+AA13*AD13 -> 248376.62
... A632: MONTERIA | B632: =VLOOKUP(A632,'CENTRO DE COSTOS'!A:D,4,FALSE) -> JOSE MAURICIO HERNANDEZ ROJAS | C632: =VLOOKUP(A632,'CENTRO DE COSTOS'!A:D,2,FALSE) -> 0004-0001 | D632: 23001 | E632: TA-25-904099 | F632: 80741 | G632: APERTURA | H632: CB CRECIMIENTO - NUEVO | I632: CORDOBA | J632: MONTERIA | K632: BARRIO VILLA ROCIO MONTERIA 1 | L632: REDEBAN | M632: FO-25-1305089 | N632: 45868 | O632: 45869 | P632: UNO A UNO | Q632: UNO A UNO | R632: EJECUTADO/CANCELADO | S632: 30-07-2025 SE REALIZA LLAMADA AL CLIENTE, SE HABLA CON EL SR EXNEIDER ANTONIO HERRERA NARVAEZ, VALIDA DIRECCIÓN OK, CANAL OK, DISPONIBILIDAD TOTAL, LLAMAR EL DÍA LA INSTALACIÓN PARA CONFIRMAR VISITA, AVISO EXTERIOR ALTURA APROX 2 METROS; TOMACORRIENTE CERCANO: SI; TIENE CABINA DE SEGURIDAD: NO 31/07/2025 INSTALACIÓN FALLIDA, SE LLEGÓ HASTA LA DIRECCIÓN Y EL LOCAL COMERCIAL TIENE UN NOMBRE DIFERENTE AL QUE SE RELACIONA EN LA LISTA DE CHEQUEO, SE ESCALÓ EL CASO A RBM Y SE LE INFORMA AL CLIENTE QUE DEBE ACTUALIZAR LA CÁMARA DE COMERCIO CON EL NOMBRE ACTUAL Y ESTE INFORMA QUE NO VA A REALIZAR EL PROCESO PORQUE LE GENERA GASTOS, ADICIONAL INFORMA QUE NO TIENE LA PERSONA PARA QUE LE ATIENDA EL CB Y DEBE CONTRATAR INTERNET Y ES COSTOSO. | T632: VISITA_TÉCNICA | U632: VAZZZ387 | V632: TIPO I | W632: TERRESTRE | X632: CALDERA SALCEDO CARLOS JULIO | Y632: 0 | Z632: 0 | AA632: 2 | AB632: =IF(V632="TIPO I",'BASE DE LIQUIDACION 2025'!$B$3,'BASE DE LIQUIDACION 2025'!$B$4) -> 11251.224 | AC632: =IF(V632="TIPO I",'BASE DE LIQUIDACION 2025'!$C$3,'BASE DE LIQUIDACION 2025'!$C$4) -> 126317.12 | AD632: =IF(V632="TIPO I",'BASE DE LIQUIDACION 2025'!$D$3,'BASE DE LIQUIDACION 2025'!$D$4) -> 57411.974 | AE632: =AB632*Y632+Z632*AC632+AA632*AD632 -> 114823.95
AE633: =SUM(AE2:AE632) -> 1.4140627e+08

Sheet PUBLICIDAD OC
A1: CIUDAD SEDE | B1: COORDINADOR | C1: CENTRO DE COSTOS LÍNEACOM | D1: CÓDIGO DANE | E1: TA/CODIGO ACTIVIDAD | F1: CODIGO CB | G1: ACTIVIDAD | H1: DEPARTAMENTO | I1: CIUDAD | J1: NOMBRE DEL CB | K1: RED | L1: FO | M1: FECHA ASIGNACION A LINEA COMUNICACIONES | N1: FECHA DEL CIERRE DEL TICKET (DD/MM/AAAA) | O1: ACOMETIDA | P1: SOLICITUD | Q1: DESCRIPCIÓN | R1: FORMATO | S1: CADENA | T1: ESTADO | U1: CAUSAL ESTADO | V1: OBSERVACION | W1: FORMA DE ATENCIÓN | X1: TERMINAL | Y1: TIPIFICACION | Z1: TIPO DE TRAYECTO | AA1: NOMBRE DEL TECNICO | AB1: DIAS DE VISITA | AC1: TRANSPORTE AVISO EXTERIOR | AD1: VALOR ACTIVIDAD | AE1: VALOR TRANSPORTE AVISO | AF1: VALOR TOTAL INSTALACION DE PUBLICIDAD
A2: MONTERIA | B2: =VLOOKUP(A2,'CENTRO DE COSTOS'!A:D,4,FALSE) -> JOSE MAURICIO HERNANDEZ ROJAS | C2: =VLOOKUP(A2,'CENTRO DE COSTOS'!A:D,2,FALSE) -> 0004-0001 | D2: 23682 | E2: 2352579 | F2: 37678 | G2: ORDEN DE CAMBIO | H2: CORDOBA | I2: SAN JOSE DE URE | J2: DISTRICOL FERRETERIA E INSUMOS | K2: REDEBAN | L2: FO-25-1133393 | M2: 45833.447 | N2: 45839.54 | P2: PUBLICIDAD | Q2: AVISO EXTERIOR | R2: AGREGADOR | S2: DISTRICOL | T2: EJECUTADO_EXITOSO | U2: EJECUTADO EXITOSO | V2: SE COMUNICA CB SR(A)JOSE, PARA SOLICITAR EL AVISO EXTERIOR YA QUE SE LE DAÑO 0 01/07/2025 SE INSTALA AVISO EXTERNO, CB INDICA QUE NUNCA INSTALARON OK. CERRAR | W2: VISITA_TÉCNICA | X2: 0 | Y2: TIPO III | Z2: TERRESTRE | AA2: COGOLLO VERTEL EDER LUIS | AB2: 1 | AC2: 1 | AD2: =IF(OR(W2="SOPORTE_TELEFÓNICO",W2="ENVÍO"),0,IF(Y2="TIPO I",'BASE DE LIQUIDACION 2025'!$I$4,IF(Y2="TIPO II",'BASE DE LIQUIDACION 2025'!$I$5,IF(Y2="TIPO III",'BASE DE LIQUIDACION 2025'!$I$6,IF(Y2="TIPO IV",'BASE DE LIQUIDACION 2025'!$I$7,'BASE DE LIQUIDACION 2025'!$I$8))))) -> 344774.57 | AE2: =IF(OR(W2="SOPORTE_TELEFÓNICO",W2="ENVÍO"),0,IF(Y2="TIPO I",'BASE DE LIQUIDACION 2025'!$J$4,IF(Y2="TIPO II",'BASE DE LIQUIDACION 2025'!$J$5,IF(Y2="TIPO III",'BASE DE LIQUIDACION 2025'!$J$6,IF(Y2="TIPO IV",'BASE DE LIQUIDACION 2025'!$J$7,'BASE DE LIQUIDACION 2025'!$J$8))))) -> 110808.28 | AF2: =IF(W2="SOPORTE_TELEFÓNICO",'BASE DE LIQUIDACION 2025'!$L$4,IF(W2="ENVÍO",'BASE DE LIQUIDACION 2025'!$K$4,AD2*AB2+AE2*AC2)) -> 455582.84
A3: MEDELLIN | B3: =VLOOKUP(A3,'CENTRO DE COSTOS'!A:D,4,FALSE) -> JUAN SEBASTIÁN RÍOS CASTRILLÓN | C3: =VLOOKUP(A3,'CENTRO DE COSTOS'!A:D,2,FALSE) -> 0004-0005 | D3: 5360 | E3: 2353671 | F3: 58298 | G3: ORDEN DE CAMBIO | H3: ANTIOQUIA | I3: ITAGUI | J3: BARRIO SANTA MARIA ITAGUI 8 | K3: REDEBAN | L3: FO-25-1134419 | M3: 45833.553 | N3: 45839.548 | P3: PUBLICIDAD | Q3: AVISO EXTERIOR | R3: CB UNO A UNO | S3: CB UNO A UNO | T3: EJECUTADO_EXITOSO | U3: EJECUTADO EXITOSO | V3: SE COMUNICA CB SR(A) GINA PARA SOLICITAR AVISO EXTERIOR EL QUE TENIA SE LE ROMPIÓ 01/07/2025 CLIENTE ABRE A LAS 10 01/07/2025 SE INSTALA AVISO EXTERIOR CERRAR | W3: VISITA_TÉCNICA | X3: 0 | Y3: TIPO I | Z3: TERRESTRE | AA3: MORENO MEDINA JUAN PABLO | AB3: 1 | AC3: 1 | AD3: =IF(OR(W3="SOPORTE_TELEFÓNICO",W3="ENVÍO"),0,IF(Y3="TIPO I",'BASE DE LIQUIDACION 2025'!$I$4,IF(Y3="TIPO II",'BASE DE LIQUIDACION 2025'!$I$5,IF(Y3="TIPO III",'BASE DE LIQUIDACION 2025'!$I$6,IF(Y3="TIPO IV",'BASE DE LIQUIDACION 2025'!$I$7,'BASE DE LIQUIDACION 2025'!$I$8))))) -> 96001.196 | AE3: =IF(OR(W3="SOPORTE_TELEFÓNICO",W3="ENVÍO"),0,IF(Y3="TIPO I",'BASE DE LIQUIDACION 2025'!$J$4,IF(Y3="TIPO II",'BASE DE LIQUIDACION 2025'!$J$5,IF(Y3="TIPO III",'BASE DE LIQUIDACION 2025'!$J$6,IF(Y3="TIPO IV",'BASE DE LIQUIDACION 2025'!$J$7,'BASE DE LIQUIDACION 2025'!$J$8))))) -> 57411.974 | AF3: =IF(W3="SOPORTE_TELEFÓNICO",'BASE DE LIQUIDACION 2025'!$L$4,IF(W3="ENVÍO",'BASE DE LIQUIDACION 2025'!$K$4,AD3*AB3+AE3*AC3)) -> 153413.17
A4: MEDELLIN | B4: =VLOOKUP(A4,'CENTRO DE COSTOS'!A:D,4,FALSE) -> JUAN SEBASTIÁN RÍOS CASTRILLÓN | C4: =VLOOKUP(A4,'CENTRO DE COSTOS'!A:D,2,FALSE) -> 0004-0005 | D4: 5001 | E4: 2355189 | F4: 46636 | G4: ORDEN DE CAMBIO | H4: ANTIOQUIA | I4: MEDELLIN | J4: BARRIO BELENCITO CORAZON MEDEL | K4: REDEBAN | L4: FO-25-1135724 | M4: 45833.669 | N4: 45839.565 | P4: PUBLICIDAD | Q4: AVISO EXTERIOR | R4: CB UNO A UNO | S4: CB UNO A UNO | T4: EJECUTADO_CANCELADO | U4: PETICIÓN BANCOLOMBIA | V4: SE COMUNICA SR@ OLGA BERRIO SOLICITA AVISO EXTERIOR POR DAÑO TOTAL 0 01/07/2025 SE VISITIA PUNTO Y NO SE INSTALA PUBLICIDAD PORQ YA CUENTA CON AVISO EXTERIOR EN BUEN ESTADO CERRAR | W4: VISITA_TÉCNICA | X4: 0 | Y4: TIPO I | Z4: TERRESTRE | AA4: HERNANDEZ CHAVARRIA JUAN CAMILO | AB4: 1 | AC4: 1 | AD4: =IF(OR(W4="SOPORTE_TELEFÓNICO",W4="ENVÍO"),0,IF(Y4="TIPO I",'BASE DE LIQUIDACION 2025'!$I$4,IF(Y4="TIPO II",'BASE DE LIQUIDACION 2025'!$I$5,IF(Y4="TIPO III",'BASE DE LIQUIDACION 2025'!$I$6,IF(Y4="TIPO IV",'BASE DE LIQUIDACION 2025'!$I$7,'BASE DE LIQUIDACION 2025'!$I$8))))) -> 96001.196 | AE4: =IF(OR(W4="SOPORTE_TELEFÓNICO",W4="ENVÍO"),0,IF(Y4="TIPO I",'BASE DE LIQUIDACION 2025'!$J$4,IF(Y4="TIPO II",'BASE DE LIQUIDACION 2025'!$J$5,IF(Y4="TIPO III",'BASE DE LIQUIDACION 2025'!$J$6,IF(Y4="TIPO IV",'BASE DE LIQUIDACION 2025'!$J$7,'BASE DE LIQUIDACION 2025'!$J$8))))) -> 57411.974 | AF4: =IF(W4="SOPORTE_TELEFÓNICO",'BASE DE LIQUIDACION 2025'!$L$4,IF(W4="ENVÍO",'BASE DE LIQUIDACION 2025'!$K$4,AD4*AB4+AE4*AC4)) -> 153413.17
A5: CUCUTA | B5: =VLOOKUP(A5,'CENTRO DE COSTOS'!A:D,4,FALSE) -> MIGUEL JULIÁN HERNÁNDEZ GUARÍN | C5: =VLOOKUP(A5,'CENTRO DE COSTOS'!A:D,2,FALSE) -> 0004-0008 | D5: 54001 | E5: 2362212 | F5: 33637 | G5: ORDEN DE CAMBIO | H5: NORTE DE SANTANDER | I5: CUCUTA | J5: BARRIO COLPET CUCUTA 1 | K5: REDEBAN | L5: FO-25-1142325 | M5: 45834.711 | N5: 45839.594 | P5: PUBLICIDAD | Q5: AVISO EXTERIOR | R5: CB UNO A UNO | S5: CB UNO A UNO | T5: EJECUTADO_EXITOSO | U5: EJECUTADO EXITOSO | V5: SE COMUNICA CB SR(A)ERIKA, INDICA QUE EL AVISO EXTERIOR EL NEGRO EL VIENTO LO TUMBO Y SE PARTIÓ SOLICITA LE COLABOREN POR FAVOR 0 01/07/2025 SE REALIZA INSTALACIÓN DE AVISO EXTERIOR OK CERRAR | W5: VISITA_TÉCNICA | X5: 9B00G007 | Y5: TIPO I | Z5: TERRESTRE | AA5: DURAN ACOSTA FRANK YONNY | AB5: 1 | AC5: 1 | AD5: =IF(OR(W5="SOPORTE_TELEFÓNICO",W5="ENVÍO"),0,IF(Y5="TIPO I",'BASE DE LIQUIDACION 2025'!$I$4,IF(Y5="TIPO II",'BASE DE LIQUIDACION 2025'!$I$5,IF(Y5="TIPO III",'BASE DE LIQUIDACION 2025'!$I$6,IF(Y5="TIPO IV",'BASE DE LIQUIDACION 2025'!$I$7,'BASE DE LIQUIDACION 2025'!$I$8))))) -> 96001.196 | AE5: =IF(OR(W5="SOPORTE_TELEFÓNICO",W5="ENVÍO"),0,IF(Y5="TIPO I",'BASE DE LIQUIDACION 2025'!$J$4,IF(Y5="TIPO II",'BASE DE LIQUIDACION 2025'!$J$5,IF(Y5="TIPO III",'BASE DE LIQUIDACION 2025'!$J$6,IF(Y5="TIPO IV",'BASE DE LIQUIDACION 2025'!$J$7,'BASE DE LIQUIDACION 2025'!$J$8))))) -> 57411.974 | AF5: =IF(W5="SOPORTE_TELEFÓNICO",'BASE DE LIQUIDACION 2025'!$L$4,IF(W5="ENVÍO",'BASE DE LIQUIDACION 2025'!$K$4,AD5*AB5+AE5*AC5)) -> 153413.17
A6: IBAGUE | B6: =VLOOKUP(A6,'CENTRO DE COSTOS'!A:D,4,FALSE) -> KEVIN ALEXIS CORZO BUSTOS | C6: =VLOOKUP(A6,'CENTRO DE COSTOS'!A:D,2,FALSE) -> 0004-0007 | D6: 73001 | E6: 2365966 | F6: 62018 | G6: ORDEN DE CAMBIO | H6: TOLIMA | I6: IBAGUE | J6: PTM IBAGUE VARIEDADES JENNY ' | K6: REDEBAN | L6: FO-25-1145290 | M6: 45835.522 | N6: 45839.599 | P6: PUBLICIDAD | Q6: AVISO EXTERIOR | R6: AGREGADOR | S6: COMCARD - PTM | T6: EJECUTADO_EXITOSO | U6: EJECUTADO EXITOSO | V6: SE COMUNICA CB SR(A) YENNY CASTRO PARA SOLICITAR AVISO EXTERIOR POR DAÑO TOTAL 0 01/07/2025 SE REALIZA INSTALACIÓN DE AVISO EXTERIOR SIN MARCO POR SOLICITUD DEL CLIENTE, INDICA ROBO CONSTANTE DE MARCO DE ALUMINIO. CERRAR | W6: VISITA_TÉCNICA | X6: KA00M290 | Y6: TIPO I | Z6: TERRESTRE | AA6: BARRAGAN TAFUR EDWIN ESTEBAN | AB6: 1 | AC6: 1 | AD6: =IF(OR(W6="SOPORTE_TELEFÓNICO",W6="ENVÍO"),0,IF(Y6="TIPO I",'BASE DE LIQUIDACION 2025'!$I$4,IF(Y6="TIPO II",'BASE DE LIQUIDACION 2025'!$I$5,IF(Y6="TIPO III",'BASE DE LIQUIDACION 2025'!$I$6,IF(Y6="TIPO IV",'BASE DE LIQUIDACION 2025'!$I$7,'BASE DE LIQUIDACION 2025'!$I$8))))) -> 96001.196 | AE6: =IF(OR(W6="SOPORTE_TELEFÓNICO",W6="ENVÍO"),0,IF(Y6="TIPO I",'BASE DE LIQUIDACION 2025'!$J$4,IF(Y6="TIPO II",'BASE DE LIQUIDACION 2025'!$J$5,IF(Y6="TIPO III",'BASE DE LIQUIDACION 2025'!$J$6,IF(Y6="TIPO IV",'BASE DE LIQUIDACION 2025'!$J$7,'BASE DE LIQUIDACION 2025'!$J$8))))) -> 57411.974 | AF6: =IF(W6="SOPORTE_TELEFÓNICO",'BASE DE LIQUIDACION 2025'!$L$4,IF(W6="ENVÍO",'BASE DE LIQUIDACION 2025'!$K$4,AD6*AB6+AE6*AC6)) -> 153413.17
A7: BOGOTA | B7: =VLOOKUP(A7,'CENTRO DE COSTOS'!A:D,4,FALSE) -> WILLIAM ASDRUBAL ROZO ROZO | C7: =VLOOKUP(A7,'CENTRO DE COSTOS'!A:D,2,FALSE) -> 0004-0004 | D7: 11001 | E7: 2367013 | F7: 39356 | G7: ORDEN DE CAMBIO | H7: CUNDINAMARCA | I7: BOGOTA | J7: PTM BOGOTA CENTRO DE PAGOS | K7: REDEBAN | L7: FO-25-1146812 | M7: 45835.648 | N7: 45839.693 | P7: PUBLICIDAD | Q7: AVISO EXTERIOR | R7: AGREGADOR | S7: COMCARD - PTM | T7: EJECUTADO_EXITOSO | U7: EJECUTADO EXITOSO | V7: SE COMUNICA CB SR(A) MARITZA CHAVES PARA SOLICITAR EL AVISO EXTERIOR YA QUE SE DAÑO, 0 01/07/2025 SE REALIZA VISITA AL COMERCIO PARA EJECUTAR INSTALACIÓN DE AVISO EXTERIOR POR SOLICITUD DEL CLIENTE OK CERRAR | W7: VISITA_TÉCNICA | X7: 0 | Y7: TIPO I | Z7: TERRESTRE | AA7: CORTES VELANDIA MIGUEL ANGEL | AB7: 1 | AC7: 1 | AD7: =IF(OR(W7="SOPORTE_TELEFÓNICO",W7="ENVÍO"),0,IF(Y7="TIPO I",'BASE DE LIQUIDACION 2025'!$I$4,IF(Y7="TIPO II",'BASE DE LIQUIDACION 2025'!$I$5,IF(Y7="TIPO III",'BASE DE LIQUIDACION 2025'!$I$6,IF(Y7="TIPO IV",'BASE DE LIQUIDACION 2025'!$I$7,'BASE DE LIQUIDACION 2025'!$I$8))))) -> 96001.196 | AE7: =IF(OR(W7="SOPORTE_TELEFÓNICO",W7="ENVÍO"),0,IF(Y7="TIPO I",'BASE DE LIQUIDACION 2025'!$J$4,IF(Y7="TIPO II",'BASE DE LIQUIDACION 2025'!$J$5,IF(Y7="TIPO III",'BASE DE LIQUIDACION 2025'!$J$6,IF(Y7="TIPO IV",'BASE DE LIQUIDACION 2025'!$J$7,'BASE DE LIQUIDACION 2025'!$J$8))))) -> 57411.974 | AF7: =IF(W7="SOPORTE_TELEFÓNICO",'BASE DE LIQUIDACION 2025'!$L$4,IF(W7="ENVÍO",'BASE DE LIQUIDACION 2025'!$K$4,AD7*AB7+AE7*AC7)) -> 153413.17
A8: CUCUTA | B8: =VLOOKUP(A8,'CENTRO DE COSTOS'!A:D,4,FALSE) -> MIGUEL JULIÁN HERNÁNDEZ GUARÍN | C8: =VLOOKUP(A8,'CENTRO DE COSTOS'!A:D,2,FALSE) -> 0004-0008 | D8: 54001 | E8: 2376015 | F8: 75195 | G8: ORDEN DE CAMBIO | H8: NORTE DE SANTANDER | I8: CUCUTA | J8: BARRIO TRIGAL DEL NORTE CUCUT | K8: REDEBAN | L8: FO-25-1163467 | M8: 45839.501 | N8: 45840.471 | P8: PUBLICIDAD | Q8: AVISO EXTERIOR | R8: CB UNO A UNO | S8: CB UNO A UNO | T8: EJECUTADO_EXITOSO | U8: EJECUTADO EXITOSO | V8: SE COMUNICA CB SR(A) SOFÍA PARA REPORTAR QUE LE ROBARON EL AVISO EXTERIOR EL NEGRO, SOLICITA LE COLABOREN POR FAVOR 0 02/07/2025 SE REALIZA INSTALACIÓN DE AVISO EXTERIOR OK CERRAR | W8: VISITA_TÉCNICA | X8: 0 | Y8: TIPO I | Z8: TERRESTRE | AA8: DURAN ACOSTA FRANK YONNY | AB8: 1 | AC8: 1 | AD8: =IF(OR(W8="SOPORTE_TELEFÓNICO",W8="ENVÍO"),0,IF(Y8="TIPO I",'BASE DE LIQUIDACION 2025'!$I$4,IF(Y8="TIPO II",'BASE DE LIQUIDACION 2025'!$I$5,IF(Y8="TIPO III",'BASE DE LIQUIDACION 2025'!$I$6,IF(Y8="TIPO IV",'BASE DE LIQUIDACION 2025'!$I$7,'BASE DE LIQUIDACION 2025'!$I$8))))) -> 96001.196 | AE8: =IF(OR(W8="SOPORTE_TELEFÓNICO",W8="ENVÍO"),0,IF(Y8="TIPO I",'BASE DE LIQUIDACION 2025'!$J$4,IF(Y8="TIPO II",'BASE DE LIQUIDACION 2025'!$J$5,IF(Y8="TIPO III",'BASE DE LIQUIDACION 2025'!$J$6,IF(Y8="TIPO IV",'BASE DE LIQUIDACION 2025'!$J$7,'BASE DE LIQUIDACION 2025'!$J$8))))) -> 57411.974 | AF8: =IF(W8="SOPORTE_TELEFÓNICO",'BASE DE LIQUIDACION 2025'!$L$4,IF(W8="ENVÍO",'BASE DE LIQUIDACION 2025'!$K$4,AD8*AB8+AE8*AC8)) -> 153413.17
A9: CALI | B9: =VLOOKUP(A9,'CENTRO DE COSTOS'!A:D,4,FALSE) -> DIEGO FERNANDO HENAO CARDONA | C9: =VLOOKUP(A9,'CENTRO DE COSTOS'!A:D,2,FALSE) -> 0004-0003 | D9: 76001 | E9: 2373408 | F9: 58951 | G9: ORDEN DE CAMBIO | H9: VALLE DEL CAUCA | I9: CALI | J9: BARRIO CENTRO CALI 34 | K9: REDEBAN | L9: FO-25-1162630 | M9: 45839.404 | N9: 45840.49 | P9: PUBLICIDAD | Q9: AVISO EXTERIOR | R9: CB UNO A UNO | S9: CB UNO A UNO | T9: EJECUTADO_EXITOSO | U9: EJECUTADO EXITOSO | V9: SE COMUNICA ANGIE, SOLICITA AVISO EXTERIOR, YA QUE EL QUE TENÍA FUE HURTADO. 0 02/07/2025 SE REALIZA INSTALACIÓN DE AVISO EXTERIOR SIN NOVEDAD. CERRAR | W9: VISITA_TÉCNICA | X9: 0 | Y9: TIPO I | Z9: TERRESTRE | AA9: TORRES GARCIA JENDRY JOSE | AB9: 1 | AC9: 1 | AD9: =IF(OR(W9="SOPORTE_TELEFÓNICO",W9="ENVÍO"),0,IF(Y9="TIPO I",'BASE DE LIQUIDACION 2025'!$I$4,IF(Y9="TIPO II",'BASE DE LIQUIDACION 2025'!$I$5,IF(Y9="TIPO III",'BASE DE LIQUIDACION 2025'!$I$6,IF(Y9="TIPO IV",'BASE DE LIQUIDACION 2025'!$I$7,'BASE DE LIQUIDACION 2025'!$I$8))))) -> 96001.196 | AE9: =IF(OR(W9="SOPORTE_TELEFÓNICO",W9="ENVÍO"),0,IF(Y9="TIPO I",'BASE DE LIQUIDACION 2025'!$J$4,IF(Y9="TIPO II",'BASE DE LIQUIDACION 2025'!$J$5,IF(Y9="TIPO III",'BASE DE LIQUIDACION 2025'!$J$6,IF(Y9="TIPO IV",'BASE DE LIQUIDACION 2025'!$J$7,'BASE DE LIQUIDACION 2025'!$J$8))))) -> 57411.974 | AF9: =IF(W9="SOPORTE_TELEFÓNICO",'BASE DE LIQUIDACION 2025'!$L$4,IF(W9="ENVÍO",'BASE DE LIQUIDACION 2025'!$K$4,AD9*AB9+AE9*AC9)) -> 153413.17
A10: CARTAGENA | B10: =VLOOKUP(A10,'CENTRO DE COSTOS'!A:D,4,FALSE) -> JOSE MAURICIO HERNANDEZ ROJAS | C10: =VLOOKUP(A10,'CENTRO DE COSTOS'!A:D,2,FALSE) -> 0004-0001 | D10: 13873 | E10: 2374317 | F10: 71584 | G10: ORDEN DE CAMBIO | H10: BOLIVAR | I10: VILLANUEVA | J10: BARRIO CALLE REAL | K10: REDEBAN | L10: FO-25-1162690 | M10: 45839.431 | N10: 45841.522 | P10: PUBLICIDAD | Q10: AVISO EXTERIOR | R10: CB UNO A UNO | S10: CB UNO A UNO | T10: EJECUTADO_EXITOSO | U10: EJECUTADO EXITOSO | V10: SE COMUNICA CB SR(A) NAYIB MALAMBO, PARA SOLICITAR AVISO EXTERIOR YA QUE EL QUE TENÍA LO DAÑARON Y SE ROBARON EL ACRÍLICO, SOLICITA DE SU AYUDA 0 03/07/2025 SE INSTALA AVISO EXTERIOR TODO OK CERRAR | W10: VISITA_TÉCNICA | X10: 0 | Y10: TIPO II | Z10: TERRESTRE | AA10: CANEDO HERRERA ALEXANDER | AB10: 1 | AC10: 1 | AD10: =IF(OR(W10="SOPORTE_TELEFÓNICO",W10="ENVÍO"),0,IF(Y10="TIPO I",'BASE DE LIQUIDACION 2025'!$I$4,IF(Y10="TIPO II",'BASE DE LIQUIDACION 2025'!$I$5,IF(Y10="TIPO III",'BASE DE LIQUIDACION 2025'!$I$6,IF(Y10="TIPO IV",'BASE DE LIQUIDACION 2025'!$I$7,'BASE DE LIQUIDACION 2025'!$I$8))))) -> 232858.6 | AE10: =IF(OR(W10="SOPORTE_TELEFÓNICO",W10="ENVÍO"),0,IF(Y10="TIPO I",'BASE DE LIQUIDACION 2025'!$J$4,IF(Y10="TIPO II",'BASE DE LIQUIDACION 2025'!$J$5,IF(Y10="TIPO III",'BASE DE LIQUIDACION 2025'!$J$6,IF(Y10="TIPO IV",'BASE DE LIQUIDACION 2025'!$J$7,'BASE DE LIQUIDACION 2025'!$J$8))))) -> 110808.28 | AF10: =IF(W10="SOPORTE_TELEFÓNICO",'BASE DE LIQUIDACION 2025'!$L$4,IF(W10="ENVÍO",'BASE DE LIQUIDACION 2025'!$K$4,AD10*AB10+AE10*AC10)) -> 343666.88
A11: BARRANQUILLA | B11: =VLOOKUP(A11,'CENTRO DE COSTOS'!A:D,4,FALSE) -> JOSE MAURICIO HERNANDEZ ROJAS | C11: =VLOOKUP(A11,'CENTRO DE COSTOS'!A:D,2,FALSE) -> 0004-0001 | D11: 8001 | E11: 2364133 | F11: 29787 | G11: ORDEN DE CAMBIO | H11: ATLANTICO | I11: BARRANQUILLA | J11: BARRIO UNION BARRANQUILLA | K11: REDEBAN | L11: FO-25-1142908 | M11: 45835.383 | N11: 45841.719 | P11: PUBLICIDAD | Q11: AVISO EXTERIOR | R11: CB UNO A UNO | S11: CB UNO A UNO | T11: EJECUTADO_EXITOSO | U11: EJECUTADO EXITOSO | V11: SE COMUNICA CB SR(A) PAOLA RINCÓN SOLICITA AVISO EXTERIOR POR HURTO, ESPERO LE PUEDAN COLABORAR 0 03/07/2025 SE INSTALA AVISO EXTERIOR, EL QUE ESTABA SE LO ROBARON CERRAR | W11: VISITA_TÉCNICA | X11: 0 | Y11: TIPO I | Z11: TERRESTRE | AA11: DE AVILA SIADES ALBERTO ENRIQUE | AB11: 1 | AC11: 1 | AD11: =IF(OR(W11="SOPORTE_TELEFÓNICO",W11="ENVÍO"),0,IF(Y11="TIPO I",'BASE DE LIQUIDACION 2025'!$I$4,IF(Y11="TIPO II",'BASE DE LIQUIDACION 2025'!$I$5,IF(Y11="TIPO III",'BASE DE LIQUIDACION 2025'!$I$6,IF(Y11="TIPO IV",'BASE DE LIQUIDACION 2025'!$I$7,'BASE DE LIQUIDACION 2025'!$I$8))))) -> 96001.196 | AE11: =IF(OR(W11="SOPORTE_TELEFÓNICO",W11="ENVÍO"),0,IF(Y11="TIPO I",'BASE DE LIQUIDACION 2025'!$J$4,IF(Y11="TIPO II",'BASE DE LIQUIDACION 2025'!$J$5,IF(Y11="TIPO III",'BASE DE LIQUIDACION 2025'!$J$6,IF(Y11="TIPO IV",'BASE DE LIQUIDACION 2025'!$J$7,'BASE DE LIQUIDACION 2025'!$J$8))))) -> 57411.974 | AF11: =IF(W11="SOPORTE_TELEFÓNICO",'BASE DE LIQUIDACION 2025'!$L$4,IF(W11="ENVÍO",'BASE DE LIQUIDACION 2025'!$K$4,AD11*AB11+AE11*AC11)) -> 153413.17
A12: VILLAVICENCIO | B12: =VLOOKUP(A12,'CENTRO DE COSTOS'!A:D,4,FALSE) -> KEVIN ALEXIS CORZO BUSTOS | C12: =VLOOKUP(A12,'CENTRO DE COSTOS'!A:D,2,FALSE) -> 0004-0007 | D12: 50313 | E12: 2358758 | F12: 72900 | G12: ORDEN DE CAMBIO | H12: META | I12: GRANADA | J12: GRANADA CENTRO | K12: REDEBAN | L12: FO-25-1138474 | M12: 45834.435 | N12: 45842.499 | P12: PUBLICIDAD | Q12: AVISO EXTERIOR | R12: CB UNO A UNO | S12: CB UNO A UNO | T12: EJECUTADO_EXITOSO | U12: EJECUTADO EXITOSO | V12: SE COMUNICA CB SR(A) LAURA PARA SOLICITAR AVISO EXTERIOR POR QUE SE LO ROBARON, 0 04/07/2025 SE INSTALA AVISO EXTERIOR OK SIN NOVEDADES SE LO ROBARON CERRAR | W12: VISITA_TÉCNICA | X12: 0 | Y12: TIPO II | Z12: TERRESTRE | AA12: CASTRILLON URREA LONDIER LEANDRO | AB12: 1 | AC12: 1 | AD12: =IF(OR(W12="SOPORTE_TELEFÓNICO",W12="ENVÍO"),0,IF(Y12="TIPO I",'BASE DE LIQUIDACION 2025'!$I$4,IF(Y12="TIPO II",'BASE DE LIQUIDACION 2025'!$I$5,IF(Y12="TIPO III",'BASE DE LIQUIDACION 2025'!$I$6,IF(Y12="TIPO IV",'BASE DE LIQUIDACION 2025'!$I$7,'BASE DE LIQUIDACION 2025'!$I$8))))) -> 232858.6 | AE12: =IF(OR(W12="SOPORTE_TELEFÓNICO",W12="ENVÍO"),0,IF(Y12="TIPO I",'BASE DE LIQUIDACION 2025'!$J$4,IF(Y12="TIPO II",'BASE DE LIQUIDACION 2025'!$J$5,IF(Y12="TIPO III",'BASE DE LIQUIDACION 2025'!$J$6,IF(Y12="TIPO IV",'BASE DE LIQUIDACION 2025'!$J$7,'BASE DE LIQUIDACION 2025'!$J$8))))) -> 110808.28 | AF12: =IF(W12="SOPORTE_TELEFÓNICO",'BASE DE LIQUIDACION 2025'!$L$4,IF(W12="ENVÍO",'BASE DE LIQUIDACION 2025'!$K$4,AD12*AB12+AE12*AC12)) -> 343666.88
A13: CUCUTA | B13: =VLOOKUP(A13,'CENTRO DE COSTOS'!A:D,4,FALSE) -> MIGUEL JULIÁN HERNÁNDEZ GUARÍN | C13: =VLOOKUP(A13,'CENTRO DE COSTOS'!A:D,2,FALSE) -> 0004-0008 | D13: 54261 | E13: 2368973 | F13: 55083 | G13: ORDEN DE CAMBIO | H13: NORTE DE SANTANDER | I13: EL ZULIA | J13: BARRIO VEREDA EL TABLAZO VIA A | K13: REDEBAN | L13: FO-25-1151928 | M13: 45839.333 | N13: 45842.505 | P13: PUBLICIDAD | Q13: AVISO EXTERIOR | R13: CB UNO A UNO | S13: CB UNO A UNO | T13: EJECUTADO_EXITOSO | U13: EJECUTADO EXITOSO | V13: SR(A) ASTRID SOLICITANDO AVISO EXTERIOR YA QUE EL QUE TENIA INSTALADO SE DAÑO. GRACIAS 01/07/2025 EN COMUNICACIÓN CON EL CLIENTE SE LE INFORMA A LA SRA ASTRID ROLON 3228570293 QUE EN EL MOMENTO POR ALTERACIÓN DE ORDEN PÚBLICO EN LA ZONA DEL CATATUMBO NO SE PODRÍA VIAJAR A REALIZAR LA ACTIVIDAD,SE PROGRAMA VISITA A LA ESPERA DE NORMALIDAD EN LA ZONA 04/07/2025 SE INSTALA AVISO EXTERIOR CERRAR | W13: VISITA_TÉCNICA | X13: 0 | Y13: TIPO II | Z13: TERRESTRE | AA13: PACHECO BUITRAGO JAVIER ALONSO | AB13: 1 | AC13: 1 | AD13: =IF(OR(W13="SOPORTE_TELEFÓNICO",W13="ENVÍO"),0,IF(Y13="TIPO I",'BASE DE LIQUIDACION 2025'!$I$4,IF(Y13="TIPO II",'BASE DE LIQUIDACION 2025'!$I$5,IF(Y13="TIPO III",'BASE DE LIQUIDACION 2025'!$I$6,IF(Y13="TIPO IV",'BASE DE LIQUIDACION 2025'!$I$7,'BASE DE LIQUIDACION 2025'!$I$8))))) -> 232858.6 | AE13: =IF(OR(W13="SOPORTE_TELEFÓNICO",W13="ENVÍO"),0,IF(Y13="TIPO I",'BASE DE LIQUIDACION 2025'!$J$4,IF(Y13="TIPO II",'BASE DE LIQUIDACION 2025'!$J$5,IF(Y13="TIPO III",'BASE DE LIQUIDACION 2025'!$J$6,IF(Y13="TIPO IV",'BASE DE LIQUIDACION 2025'!$J$7,'BASE DE LIQUIDACION 2025'!$J$8))))) -> 110808.28 | AF13: =IF(W13="SOPORTE_TELEFÓNICO",'BASE DE LIQUIDACION 2025'!$L$4,IF(W13="ENVÍO",'BASE DE LIQUIDACION 2025'!$K$4,AD13*AB13+AE13*AC13)) -> 343666.88
A14: IBAGUE | B14: =VLOOKUP(A14,'CENTRO DE COSTOS'!A:D,4,FALSE) -> KEVIN ALEXIS CORZO BUSTOS | C14: =VLOOKUP(A14,'CENTRO DE COSTOS'!A:D,2,FALSE) -> 0004-0007 | D14: 73001 | E14: 2391008 | F14: 77020 | G14: ORDEN DE CAMBIO | H14: TOLIMA | I14: IBAGUE | J14: BARRIO ARKALA IBAGUE 2 | K14: REDEBAN | L14: FO-25-1178683 | M14: 45841.488 | N14: 45842.528 | P14: PUBLICIDAD | Q14: AVISO EXTERIOR | R14: CB UNO A UNO | S14: CB UNO A UNO | T14: EJECUTADO_EXITOSO | U14: EJECUTADO EXITOSO | V14: SE COMUNICA CB SR(A) OSCAR PARA SOLICITAR AVISO EXTERIOR, EL ACTUAL SE LO ROBARON 0 04/07/2025 SE REALIZA INSTALACIÓN DE AVISO EXTERIOR "SE LO ROBARON CON MARCO" SOLICITUD DEL CLIENTE CERRAR | W14: VISITA_TÉCNICA | X14: 0 | Y14: TIPO I | Z14: TERRESTRE | AA14: GUTIERREZ CAMILO ANDRES | AB14: 1 | AC14: 1 | AD14: =IF(OR(W14="SOPORTE_TELEFÓNICO",W14="ENVÍO"),0,IF(Y14="TIPO I",'BASE DE LIQUIDACION 2025'!$I$4,IF(Y14="TIPO II",'BASE DE LIQUIDACION 2025'!$I$5,IF(Y14="TIPO III",'BASE DE LIQUIDACION 2025'!$I$6,IF(Y14="TIPO IV",'BASE DE LIQUIDACION 2025'!$I$7,'BASE DE LIQUIDACION 2025'!$I$8))))) -> 96001.196 | AE14: =IF(OR(W14="SOPORTE_TELEFÓNICO",W14="ENVÍO"),0,IF(Y14="TIPO I",'BASE DE LIQUIDACION 2025'!$J$4,IF(Y14="TIPO II",'BASE DE LIQUIDACION 2025'!$J$5,IF(Y14="TIPO III",'BASE DE LIQUIDACION 2025'!$J$6,IF(Y14="TIPO IV",'BASE DE LIQUIDACION 2025'!$J$7,'BASE DE LIQUIDACION 2025'!$J$8))))) -> 57411.974 | AF14: =IF(W14="SOPORTE_TELEFÓNICO",'BASE DE LIQUIDACION 2025'!$L$4,IF(W14="ENVÍO",'BASE DE LIQUIDACION 2025'!$K$4,AD14*AB14+AE14*AC14)) -> 153413.17
A15: BOGOTA | B15: =VLOOKUP(A15,'CENTRO DE COSTOS'!A:D,4,FALSE) -> WILLIAM ASDRUBAL ROZO ROZO | C15: =VLOOKUP(A15,'CENTRO DE COSTOS'!A:D,2,FALSE) -> 0004-0004 | D15: 11001 | E15: 2373262 | F15: 74893 | G15: ORDEN DE CAMBIO | H15: CUNDINAMARCA | I15: BOGOTA | J15: BARRIO POLICARPA BOGOTA 5 | K15: REDEBAN | L15: FO-25-1162642 | M15: 45839.401 | N15: 45842.576 | P15: PUBLICIDAD | Q15: AVISO EXTERIOR | R15: CB UNO A UNO | S15: CB UNO A UNO | T15: EJECUTADO_EXITOSO | U15: EJECUTADO EXITOSO | V15: SE COMUNICA CB SR(A) ALEJANDRO PARA SOLICITAR AVISO EXTERIOR YA QUE SE LO ROBARON 0 04/07/2025 SE LLEGA A LA DIRECCIÓN INDICADA, SE INSTALA AVISO EXTERIOR, NO SE MANIPULAN DATÁFONOS CERRAR | W15: VISITA_TÉCNICA | X15: 0 | Y15: TIPO I | Z15: TERRESTRE | AA15: GARCIA PASTRANA KEVIN FERNANDO | AB15: 1 | AC15: 1 | AD15: =IF(OR(W15="SOPORTE_TELEFÓNICO",W15="ENVÍO"),0,IF(Y15="TIPO I",'BASE DE LIQUIDACION 2025'!$I$4,IF(Y15="TIPO II",'BASE DE LIQUIDACION 2025'!$I$5,IF(Y15="TIPO III",'BASE DE LIQUIDACION 2025'!$I$6,IF(Y15="TIPO IV",'BASE DE LIQUIDACION 2025'!$I$7,'BASE DE LIQUIDACION 2025'!$I$8))))) -> 96001.196 | AE15: =IF(OR(W15="SOPORTE_TELEFÓNICO",W15="ENVÍO"),0,IF(Y15="TIPO I",'BASE DE LIQUIDACION 2025'!$J$4,IF(Y15="TIPO II",'BASE DE LIQUIDACION 2025'!$J$5,IF(Y15="TIPO III",'BASE DE LIQUIDACION 2025'!$J$6,IF(Y15="TIPO IV",'BASE DE LIQUIDACION 2025'!$J$7,'BASE DE LIQUIDACION 2025'!$J$8))))) -> 57411.974 | AF15: =IF(W15="SOPORTE_TELEFÓNICO",'BASE DE LIQUIDACION 2025'!$L$4,IF(W15="ENVÍO",'BASE DE LIQUIDACION 2025'!$K$4,AD15*AB15+AE15*AC15)) -> 153413.17
A16: BOGOTA | B16: =VLOOKUP(A16,'CENTRO DE COSTOS'!A:D,4,FALSE) -> WILLIAM ASDRUBAL ROZO ROZO | C16: =VLOOKUP(A16,'CENTRO DE COSTOS'!A:D,2,FALSE) -> 0004-0004 | D16: 11001 | E16: TA-25-830126 | F16: 43352 | G16: ORDEN DE CAMBIO | H16: CUNDINAMARCA | I16: BOGOTA | J16: BARRIO CORABASTOS BOGOTA 2 | K16: REDEBAN | L16: FO-25-1176456 | M16: 45841.333 | N16: 45842.581 | P16: PUBLICIDAD | Q16: AVISO EXTERIOR | R16: CB UNO A UNO | S16: CB UNO A UNO | T16: EJECUTADO_EXITOSO | U16: EJECUTADO EXITOSO | V16: SOLICITO POR FAVOR QUE PROGRAMEMOS LA INSTALACIÓN DE LA PUBLICIDAD (AVISO EXTERIOR), YA QUE EN ESTA OCASIÓN EL COMERCIO REQUIERE CONTAR CON ELLA Y LA ENTIDAD HA DADO SU APROBACIÓN PARA SU INSTALACIÓN 0 04/07/2025 SE REALIZA VISITA DE CAMPO DONDE SE INSTALA AVISO EXTERIOR DE ACUERDO A INDICACIONES A CLIENTE, NO SE MANIPULA EQUIPOS. CERRAR | W16: VISITA_TÉCNICA | X16: 0 | Y16: TIPO I | Z16: TERRESTRE | AA16: LOZADA ROJAS CHRISTIAN ANDRES | AB16: 1 | AC16: 1 | AD16: =IF(OR(W16="SOPORTE_TELEFÓNICO",W16="ENVÍO"),0,IF(Y16="TIPO I",'BASE DE LIQUIDACION 2025'!$I$4,IF(Y16="TIPO II",'BASE DE LIQUIDACION 2025'!$I$5,IF(Y16="TIPO III",'BASE DE LIQUIDACION 2025'!$I$6,IF(Y16="TIPO IV",'BASE DE LIQUIDACION 2025'!$I$7,'BASE DE LIQUIDACION 2025'!$I$8))))) -> 96001.196 | AE16: =IF(OR(W16="SOPORTE_TELEFÓNICO",W16="ENVÍO"),0,IF(Y16="TIPO I",'BASE DE LIQUIDACION 2025'!$J$4,IF(Y16="TIPO II",'BASE DE LIQUIDACION 2025'!$J$5,IF(Y16="TIPO III",'BASE DE LIQUIDACION 2025'!$J$6,IF(Y16="TIPO IV",'BASE DE LIQUIDACION 2025'!$J$7,'BASE DE LIQUIDACION 2025'!$J$8))))) -> 57411.974 | AF16: =IF(W16="SOPORTE_TELEFÓNICO",'BASE DE LIQUIDACION 2025'!$L$4,IF(W16="ENVÍO",'BASE DE LIQUIDACION 2025'!$K$4,AD16*AB16+AE16*AC16)) -> 153413.17
A17: BUCARAMANGA | B17: =VLOOKUP(A17,'CENTRO DE COSTOS'!A:D,4,FALSE) -> MIGUEL JULIÁN HERNÁNDEZ GUARÍN | C17: =VLOOKUP(A17,'CENTRO DE COSTOS'!A:D,2,FALSE) -> 0004-0008 | D17: 20710 | E17: 2390767 | F17: 40387 | G17: ORDEN DE CAMBIO | H17: CESAR | I17: SAN ALBERTO | J17: BARRIO LA PALMA SAN ALBERTO CE | K17: REDEBAN | L17: FO-25-1178682 | M17: 45841.491 | N17: 45843.378 | P17: PUBLICIDAD | Q17: AVISO EXTERIOR | R17: CB UNO A UNO | S17: CB UNO A UNO | T17: EJECUTADO_EXITOSO | U17: EJECUTADO EXITOSO | V17: SE COMUNICA CB SR(A)YESICA, PARA SOLICITAR AVISO PRINCIPAL EXTERIOR, EL QUE TENIA UN VENTARRÓN LO TUMBO Y LO PARTIO POR COMPLETO, 0 04/07/2025 INSTALACIÓN DE AVISO EXTERIOR, NO SE MANIPULA EQUIPOS. CERRAR | W17: VISITA_TÉCNICA | X17: 0 | Y17: TIPO III | Z17: TERRESTRE | AA17: SANTOS GONZALEZ JOHAN FABIAN | AB17: 1 | AC17: 1 | AD17: =IF(OR(W17="SOPORTE_TELEFÓNICO",W17="ENVÍO"),0,IF(Y17="TIPO I",'BASE DE LIQUIDACION 2025'!$I$4,IF(Y17="TIPO II",'BASE DE LIQUIDACION 2025'!$I$5,IF(Y17="TIPO III",'BASE DE LIQUIDACION 2025'!$I$6,IF(Y17="TIPO IV",'BASE DE LIQUIDACION 2025'!$I$7,'BASE DE LIQUIDACION 2025'!$I$8))))) -> 344774.57 | AE17: =IF(OR(W17="SOPORTE_TELEFÓNICO",W17="ENVÍO"),0,IF(Y17="TIPO I",'BASE DE LIQUIDACION 2025'!$J$4,IF(Y17="TIPO II",'BASE DE LIQUIDACION 2025'!$J$5,IF(Y17="TIPO III",'BASE DE LIQUIDACION 2025'!$J$6,IF(Y17="TIPO IV",'BASE DE LIQUIDACION 2025'!$J$7,'BASE DE LIQUIDACION 2025'!$J$8))))) -> 110808.28 | AF17: =IF(W17="SOPORTE_TELEFÓNICO",'BASE DE LIQUIDACION 2025'!$L$4,IF(W17="ENVÍO",'BASE DE LIQUIDACION 2025'!$K$4,AD17*AB17+AE17*AC17)) -> 455582.84
A18: PEREIRA | B18: =VLOOKUP(A18,'CENTRO DE COSTOS'!A:D,4,FALSE) -> DIEGO FERNANDO HENAO CARDONA | C18: =VLOOKUP(A18,'CENTRO DE COSTOS'!A:D,2,FALSE) -> 0004-0002 | D18: 66001 | E18: 2365669 | F18: 45906 | G18: ORDEN DE CAMBIO | H18: RISARALDA | I18: PEREIRA | J18: BARRIO CUBA PEREIRA 4 | K18: REDEBAN | L18: FO-25-1144496 | M18: 45835.495 | N18: 45843.63 | P18: PUBLICIDAD | Q18: AVISO EXTERIOR | R18: CB UNO A UNO | S18: CB UNO A UNO | T18: EJECUTADO_EXITOSO | U18: EJECUTADO EXITOSO | V18: SE COMUNICA CB SR(A)OMAR PARA SOLICITAR AVISO EXTERIOR YA QUE EL QUE TENIA SE LO ROBARON Y NO TIENE AVISO EN EL MOMENTO POR FAVOR 0 05/07/2025 VISITAMOS COMERCIO REALIZAMOS INSTALACIÓN DE AVISO EXTERIOR YA QUE EL QUE TENIA SE LO ROBARON. CERRAR | W18: VISITA_TÉCNICA | X18: 0 | Y18: TIPO I | Z18: TERRESTRE | AA18: ARROYAVE CANO MANUEL GUILLERMO | AB18: 1 | AC18: 1 | AD18: =IF(OR(W18="SOPORTE_TELEFÓNICO",W18="ENVÍO"),0,IF(Y18="TIPO I",'BASE DE LIQUIDACION 2025'!$I$4,IF(Y18="TIPO II",'BASE DE LIQUIDACION 2025'!$I$5,IF(Y18="TIPO III",'BASE DE LIQUIDACION 2025'!$I$6,IF(Y18="TIPO IV",'BASE DE LIQUIDACION 2025'!$I$7,'BASE DE LIQUIDACION 2025'!$I$8))))) -> 96001.196 | AE18: =IF(OR(W18="SOPORTE_TELEFÓNICO",W18="ENVÍO"),0,IF(Y18="TIPO I",'BASE DE LIQUIDACION 2025'!$J$4,IF(Y18="TIPO II",'BASE DE LIQUIDACION 2025'!$J$5,IF(Y18="TIPO III",'BASE DE LIQUIDACION 2025'!$J$6,IF(Y18="TIPO IV",'BASE DE LIQUIDACION 2025'!$J$7,'BASE DE LIQUIDACION 2025'!$J$8))))) -> 57411.974 | AF18: =IF(W18="SOPORTE_TELEFÓNICO",'BASE DE LIQUIDACION 2025'!$L$4,IF(W18="ENVÍO",'BASE DE LIQUIDACION 2025'!$K$4,AD18*AB18+AE18*AC18)) -> 153413.17
A19: MEDELLIN | B19: =VLOOKUP(A19,'CENTRO DE COSTOS'!A:D,4,FALSE) -> JUAN SEBASTIÁN RÍOS CASTRILLÓN | C19: =VLOOKUP(A19,'CENTRO DE COSTOS'!A:D,2,FALSE) -> 0004-0005 | D19: 5001 | E19: 2377706 | F19: 57524 | G19: ORDEN DE CAMBIO | H19: ANTIOQUIA | I19: MEDELLIN | J19: DISTRICOL MONIKCALZADOS | K19: REDEBAN | L19: FO-25-1167444 | M19: 45839.627 | N19: 45843.633 | P19: PUBLICIDAD | Q19: AVISO EXTERIOR | R19: AGREGADOR | S19: DISTRICOL | T19: EJECUTADO_EXITOSO | U19: EJECUTADO EXITOSO | V19: SE COMUNICA CB SR(A) VANESSA PARA SOLICITAR AVISO EXTERIOR YA QUE EL QUE TIENE SE ROMPIÓ, ESPERO LE PUEDAN COLABORAR, 0 05/07/2025 SE INSTALA AVISO EXTERIOR OK CERRAR | W19: VISITA_TÉCNICA | X19: 0 | Y19: TIPO I | Z19: TERRESTRE | AA19: QUINTERO SANCHEZ JUAN SEBASTIAN | AB19: 1 | AC19: 1 | AD19: =IF(OR(W19="SOPORTE_TELEFÓNICO",W19="ENVÍO"),0,IF(Y19="TIPO I",'BASE DE LIQUIDACION 2025'!$I$4,IF(Y19="TIPO II",'BASE DE LIQUIDACION 2025'!$I$5,IF(Y19="TIPO III",'BASE DE LIQUIDACION 2025'!$I$6,IF(Y19="TIPO IV",'BASE DE LIQUIDACION 2025'!$I$7,'BASE DE LIQUIDACION 2025'!$I$8))))) -> 96001.196 | AE19: =IF(OR(W19="SOPORTE_TELEFÓNICO",W19="ENVÍO"),0,IF(Y19="TIPO I",'BASE DE LIQUIDACION 2025'!$J$4,IF(Y19="TIPO II",'BASE DE LIQUIDACION 2025'!$J$5,IF(Y19="TIPO III",'BASE DE LIQUIDACION 2025'!$J$6,IF(Y19="TIPO IV",'BASE DE LIQUIDACION 2025'!$J$7,'BASE DE LIQUIDACION 2025'!$J$8))))) -> 57411.974 | AF19: =IF(W19="SOPORTE_TELEFÓNICO",'BASE DE LIQUIDACION 2025'!$L$4,IF(W19="ENVÍO",'BASE DE LIQUIDACION 2025'!$K$4,AD19*AB19+AE19*AC19)) -> 153413.17
A20: VILLAVICENCIO | B20: =VLOOKUP(A20,'CENTRO DE COSTOS'!A:D,4,FALSE) -> KEVIN ALEXIS CORZO BUSTOS | C20: =VLOOKUP(A20,'CENTRO DE COSTOS'!A:D,2,FALSE) -> 0004-0007 | D20: 50001 | E20: 2384544 | F20: 68824 | G20: ORDEN DE CAMBIO | H20: META | I20: VILLAVICENCIO | J20: BARRIO CENTRO VILLAVICENCIO | K20: REDEBAN | L20: FO-25-1174020 | M20: 45840.571 | N20: 45843.635 | P20: PUBLICIDAD | Q20: AVISO EXTERIOR | R20: CB UNO A UNO | S20: CB UNO A UNO | T20: EJECUTADO_EXITOSO | U20: EJECUTADO EXITOSO | V20: SE COMUNICA CB SR(A) CRISTIAN PARA SOLICITAR AVISO EXTERIOR YA QUE SE LO ROBARON 0 05/07/2025 SE INSTALA AVISO EXTERIOR, SE INSTALA SIN EL ALUMINIO YA QUE CLIENTE INFORMA QUE LO INSTALEMOS SIN ESO POR QUE SE LO ROBAN CERRAR | W20: VISITA_TÉCNICA | X20: 0 | Y20: TIPO I | Z20: TERRESTRE | AA20: PEDREROS CONTRERAS MICHAEL STEVENS | AB20: 1 | AC20: 1 | AD20: =IF(OR(W20="SOPORTE_TELEFÓNICO",W20="ENVÍO"),0,IF(Y20="TIPO I",'BASE DE LIQUIDACION 2025'!$I$4,IF(Y20="TIPO II",'BASE DE LIQUIDACION 2025'!$I$5,IF(Y20="TIPO III",'BASE DE LIQUIDACION 2025'!$I$6,IF(Y20="TIPO IV",'BASE DE LIQUIDACION 2025'!$I$7,'BASE DE LIQUIDACION 2025'!$I$8))))) -> 96001.196 | AE20: =IF(OR(W20="SOPORTE_TELEFÓNICO",W20="ENVÍO"),0,IF(Y20="TIPO I",'BASE DE LIQUIDACION 2025'!$J$4,IF(Y20="TIPO II",'BASE DE LIQUIDACION 2025'!$J$5,IF(Y20="TIPO III",'BASE DE LIQUIDACION 2025'!$J$6,IF(Y20="TIPO IV",'BASE DE LIQUIDACION 2025'!$J$7,'BASE DE LIQUIDACION 2025'!$J$8))))) -> 57411.974 | AF20: =IF(W20="SOPORTE_TELEFÓNICO",'BASE DE LIQUIDACION 2025'!$L$4,IF(W20="ENVÍO",'BASE DE LIQUIDACION 2025'!$K$4,AD20*AB20+AE20*AC20)) -> 153413.17
A21: CALI | B21: =VLOOKUP(A21,'CENTRO DE COSTOS'!A:D,4,FALSE) -> DIEGO FERNANDO HENAO CARDONA | C21: =VLOOKUP(A21,'CENTRO DE COSTOS'!A:D,2,FALSE) -> 0004-0003 | D21: 76001 | E21: 2400704 | F21: 70111 | G21: ORDEN DE CAMBIO | H21: VALLE DEL CAUCA | I21: CALI | J21: PTM CALI LA OFICINA JC | K21: REDEBAN | L21: FO-25-1190363 | M21: 45843.393 | N21: 45845.466 | P21: PUBLICIDAD | Q21: AVISO EXTERIOR | R21: AGREGADOR | S21: COMCARD - PTM | T21: EJECUTADO_EXITOSO | U21: EJECUTADO EXITOSO | V21: SE COMUNICA CB SR(A) DIANA SOLICITA AVISO EXTERIOR YA QUE SE LO DAÑO UN VENDAVAL Y YA NO CUENTA CON EL 0 07/07/2025 SE REALIZA INSTALACIÓN DE AVISO EXTERIOR SIN NOVEDAD. CERRAR | W21: VISITA_TÉCNICA | X21: 0 | Y21: TIPO I | Z21: TERRESTRE | AA21: TORRES GARCIA JENDRY JOSE | AB21: 1 | AC21: 1 | AD21: =IF(OR(W21="SOPORTE_TELEFÓNICO",W21="ENVÍO"),0,IF(Y21="TIPO I",'BASE DE LIQUIDACION 2025'!$I$4,IF(Y21="TIPO II",'BASE DE LIQUIDACION 2025'!$I$5,IF(Y21="TIPO III",'BASE DE LIQUIDACION 2025'!$I$6,IF(Y21="TIPO IV",'BASE DE LIQUIDACION 2025'!$I$7,'BASE DE LIQUIDACION 2025'!$I$8))))) -> 96001.196 | AE21: =IF(OR(W21="SOPORTE_TELEFÓNICO",W21="ENVÍO"),0,IF(Y21="TIPO I",'BASE DE LIQUIDACION 2025'!$J$4,IF(Y21="TIPO II",'BASE DE LIQUIDACION 2025'!$J$5,IF(Y21="TIPO III",'BASE DE LIQUIDACION 2025'!$J$6,IF(Y21="TIPO IV",'BASE DE LIQUIDACION 2025'!$J$7,'BASE DE LIQUIDACION 2025'!$J$8))))) -> 57411.974 | AF21: =IF(W21="SOPORTE_TELEFÓNICO",'BASE DE LIQUIDACION 2025'!$L$4,IF(W21="ENVÍO",'BASE DE LIQUIDACION 2025'!$K$4,AD21*AB21+AE21*AC21)) -> 153413.17
A22: BOGOTA | B22: =VLOOKUP(A22,'CENTRO DE COSTOS'!A:D,4,FALSE) -> WILLIAM ASDRUBAL ROZO ROZO | C22: =VLOOKUP(A22,'CENTRO DE COSTOS'!A:D,2,FALSE) -> 0004-0004 | D22: 25307 | E22: 2369628 | F22: 42102 | G22: ORDEN DE CAMBIO | H22: CUNDINAMARCA | I22: GIRARDOT | J22: BARRIO GRANADA GIRARDOT | K22: REDEBAN | L22: FO-25-1152444 | M22: 45839.333 | N22: 45845.62 | P22: PUBLICIDAD | Q22: AVISO EXTERIOR | R22: CB UNO A UNO | S22: CB UNO A UNO | T22: EJECUTADO_EXITOSO | U22: EJECUTADO EXITOSO | V22: SE COMUNICA CB SR(A) LUIS ALBERTO LOMBO PARA SOLICITAR AVISO EXTERIOR POR DAÑO TOTAL GRACIAS 03/07/2025 NO SE VISITA COMERCIO CON ANTIPACIÓN PARA LA INSTALACIÓN DE LA PUBLICIDAD (AVISO EXTERIOR) YA QUE EN BODEGA NO HAY STOCK DE ESTE MATERIAL, PENDIENTE POR SUMINISTRO DE RBM 07/07/2025 SE REALIZA VISITA DE CAMPO DONDE SE INSTALA AVISO EXTERIOR DEBIDO A QUE ANTERIOR SE ROMPIÓ, NO SE MANIPULA EQUIPOS CERRAR | W22: VISITA_TÉCNICA | X22: 0 | Y22: TIPO III | Z22: TERRESTRE | AA22: LOZADA ROJAS CHRISTIAN ANDRES | AB22: 1 | AC22: 1 | AD22: =IF(OR(W22="SOPORTE_TELEFÓNICO",W22="ENVÍO"),0,IF(Y22="TIPO I",'BASE DE LIQUIDACION 2025'!$I$4,IF(Y22="TIPO II",'BASE DE LIQUIDACION 2025'!$I$5,IF(Y22="TIPO III",'BASE DE LIQUIDACION 2025'!$I$6,IF(Y22="TIPO IV",'BASE DE LIQUIDACION 2025'!$I$7,'BASE DE LIQUIDACION 2025'!$I$8))))) -> 344774.57 | AE22: =IF(OR(W22="SOPORTE_TELEFÓNICO",W22="ENVÍO"),0,IF(Y22="TIPO I",'BASE DE LIQUIDACION 2025'!$J$4,IF(Y22="TIPO II",'BASE DE LIQUIDACION 2025'!$J$5,IF(Y22="TIPO III",'BASE DE LIQUIDACION 2025'!$J$6,IF(Y22="TIPO IV",'BASE DE LIQUIDACION 2025'!$J$7,'BASE DE LIQUIDACION 2025'!$J$8))))) -> 110808.28 | AF22: =IF(W22="SOPORTE_TELEFÓNICO",'BASE DE LIQUIDACION 2025'!$L$4,IF(W22="ENVÍO",'BASE DE LIQUIDACION 2025'!$K$4,AD22*AB22+AE22*AC22)) -> 455582.84
A23: APARTADO | B23: =VLOOKUP(A23,'CENTRO DE COSTOS'!A:D,4,FALSE) -> JUAN SEBASTIÁN RÍOS CASTRILLÓN | C23: =VLOOKUP(A23,'CENTRO DE COSTOS'!A:D,2,FALSE) -> 0004-0005 | D23: 5480 | E23: 2377779 | F23: 43623 | G23: ORDEN DE CAMBIO | H23: ANTIOQUIA | I23: MUTATA | J23: DISTRICOL AGRO STIHL | K23: REDEBAN | L23: FO-25-1167438 | M23: 45839.64 | N23: 45845.622 | P23: PUBLICIDAD | Q23: AVISO EXTERIOR | R23: AGREGADOR | S23: DISTRICOL | T23: EJECUTADO_EXITOSO | U23: EJECUTADO EXITOSO | V23: SE COMUNICA ALBERTO PARA SOLICITAR AVISO EXTERIOR PORQUE PASO UN CARRO Y SE LO CAYO, SE LE ROMPIÓ 06/07/2025 SE REALIZA LLAMADA AL USUARIO PARA LA INSTALACIÓN DEL AVISO EXTERIOR, USUARIO INFORMA QUE LOS SÁBADOS CIERRA A LAS 3 Y POR ACTIVIDADES REALIZADAS EL DÍA SÁBADO NO SE LOGRA TOMAR TRANSPORTE HASTA EL CORREGIMIENTO PAVARANDO, USUARIO DICE QUE PARA LA OTRA SEMANA OK 07/07/2025 SE REALIZA INSTALACIÓN AVISO EXTERIOR CERRAR | W23: VISITA_TÉCNICA | X23: 0 | Y23: TIPO II | Z23: TERRESTRE | AA23: CASTRO HENAO DANIEL ESTEBAN | AB23: 1 | AC23: 1 | AD23: =IF(OR(W23="SOPORTE_TELEFÓNICO",W23="ENVÍO"),0,IF(Y23="TIPO I",'BASE DE LIQUIDACION 2025'!$I$4,IF(Y23="TIPO II",'BASE DE LIQUIDACION 2025'!$I$5,IF(Y23="TIPO III",'BASE DE LIQUIDACION 2025'!$I$6,IF(Y23="TIPO IV",'BASE DE LIQUIDACION 2025'!$I$7,'BASE DE LIQUIDACION 2025'!$I$8))))) -> 232858.6 | AE23: =IF(OR(W23="SOPORTE_TELEFÓNICO",W23="ENVÍO"),0,IF(Y23="TIPO I",'BASE DE LIQUIDACION 2025'!$J$4,IF(Y23="TIPO II",'BASE DE LIQUIDACION 2025'!$J$5,IF(Y23="TIPO III",'BASE DE LIQUIDACION 2025'!$J$6,IF(Y23="TIPO IV",'BASE DE LIQUIDACION 2025'!$J$7,'BASE DE LIQUIDACION 2025'!$J$8))))) -> 110808.28 | AF23: =IF(W23="SOPORTE_TELEFÓNICO",'BASE DE LIQUIDACION 2025'!$L$4,IF(W23="ENVÍO",'BASE DE LIQUIDACION 2025'!$K$4,AD23*AB23+AE23*AC23)) -> 343666.88
A24: BOGOTA | B24: =VLOOKUP(A24,'CENTRO DE COSTOS'!A:D,4,FALSE) -> WILLIAM ASDRUBAL ROZO ROZO | C24: =VLOOKUP(A24,'CENTRO DE COSTOS'!A:D,2,FALSE) -> 0004-0004 | D24: 11001 | E24: 2388758 | F24: 25685 | G24: ORDEN DE CAMBIO | H24: CUNDINAMARCA | I24: BOGOTA | J24: BARRIO CHAPINERO BOGOTA | K24: REDEBAN | L24: FO-25-1177807 | M24: 45841.378 | N24: 45845.627 | P24: PUBLICIDAD | Q24: AVISO EXTERIOR | R24: CB UNO A UNO | S24: CB UNO A UNO | T24: EJECUTADO_EXITOSO | U24: EJECUTADO EXITOSO | V24: LIGIA 25685 SE COMUNICA PARA REPORTAR QUE LE ROBARON EL AVISO EXTERIOR, SOLICITA ENVIÓ DE UNO 03/07/2025 NO SE VISITA COMERCIO CON ANTIPACIÓN PARA LA INSTALACIÓN DE LA PUBLICIDAD (AVISO EXTERIOR) YA QUE EN BODEGA NO HAY STOCK DE ESTE MATERIAL, PENDIENTE POR SUMINISTRO DE RBM 07/07/2025 SE REALIZA VISITA AL COMERCIO PARA EJECUTAR INSTALACIÓN DE AVISO EXTERIOR POR SOLICITUD DEL CLIENTE OK CERRAR | W24: VISITA_TÉCNICA | X24: 0 | Y24: TIPO I | Z24: TERRESTRE | AA24: CORTES VELANDIA MIGUEL ANGEL | AB24: 1 | AC24: 1 | AD24: =IF(OR(W24="SOPORTE_TELEFÓNICO",W24="ENVÍO"),0,IF(Y24="TIPO I",'BASE DE LIQUIDACION 2025'!$I$4,IF(Y24="TIPO II",'BASE DE LIQUIDACION 2025'!$I$5,IF(Y24="TIPO III",'BASE DE LIQUIDACION 2025'!$I$6,IF(Y24="TIPO IV",'BASE DE LIQUIDACION 2025'!$I$7,'BASE DE LIQUIDACION 2025'!$I$8))))) -> 96001.196 | AE24: =IF(OR(W24="SOPORTE_TELEFÓNICO",W24="ENVÍO"),0,IF(Y24="TIPO I",'BASE DE LIQUIDACION 2025'!$J$4,IF(Y24="TIPO II",'BASE DE LIQUIDACION 2025'!$J$5,IF(Y24="TIPO III",'BASE DE LIQUIDACION 2025'!$J$6,IF(Y24="TIPO IV",'BASE DE LIQUIDACION 2025'!$J$7,'BASE DE LIQUIDACION 2025'!$J$8))))) -> 57411.974 | AF24: =IF(W24="SOPORTE_TELEFÓNICO",'BASE DE LIQUIDACION 2025'!$L$4,IF(W24="ENVÍO",'BASE DE LIQUIDACION 2025'!$K$4,AD24*AB24+AE24*AC24)) -> 153413.17
A25: BUCARAMANGA | B25: =VLOOKUP(A25,'CENTRO DE COSTOS'!A:D,4,FALSE) -> MIGUEL JULIÁN HERNÁNDEZ GUARÍN | C25: =VLOOKUP(A25,'CENTRO DE COSTOS'!A:D,2,FALSE) -> 0004-0008 | D25: 68001 | E25: 2401549 | F25: 38505 | G25: ORDEN DE CAMBIO | H25: SANTANDER | I25: BUCARAMANGA | J25: BARRIO CENTRO BUCARAMANGA 14 | K25: REDEBAN | L25: FO-25-1190371 | M25: 45845.333 | N25: 45845.634 | P25: PUBLICIDAD | Q25: AVISO EXTERIOR | R25: CB UNO A UNO | S25: CB UNO A UNO | T25: EJECUTADO_EXITOSO | U25: EJECUTADO EXITOSO | V25: SE COMUNICA CB SR(A) LUZ MARINA CARRILLO PARA SOLICITAR PUBLICIDAD DE AVISO EXTERIOR YA QUE, EL QUE TIENE ESTA PARTIDO 0 07/07/2025 INSTALACIÓN DE AVISO EXTERIOR CERRAR | W25: VISITA_TÉCNICA | X25: 0 | Y25: TIPO I | Z25: TERRESTRE | AA25: PEÑA DIAZ IVAN YESID | AB25: 1 | AC25: 1 | AD25: =IF(OR(W25="SOPORTE_TELEFÓNICO",W25="ENVÍO"),0,IF(Y25="TIPO I",'BASE DE LIQUIDACION 2025'!$I$4,IF(Y25="TIPO II",'BASE DE LIQUIDACION 2025'!$I$5,IF(Y25="TIPO III",'BASE DE LIQUIDACION 2025'!$I$6,IF(Y25="TIPO IV",'BASE DE LIQUIDACION 2025'!$I$7,'BASE DE LIQUIDACION 2025'!$I$8))))) -> 96001.196 | AE25: =IF(OR(W25="SOPORTE_TELEFÓNICO",W25="ENVÍO"),0,IF(Y25="TIPO I",'BASE DE LIQUIDACION 2025'!$J$4,IF(Y25="TIPO II",'BASE DE LIQUIDACION 2025'!$J$5,IF(Y25="TIPO III",'BASE DE LIQUIDACION 2025'!$J$6,IF(Y25="TIPO IV",'BASE DE LIQUIDACION 2025'!$J$7,'BASE DE LIQUIDACION 2025'!$J$8))))) -> 57411.974 | AF25: =IF(W25="SOPORTE_TELEFÓNICO",'BASE DE LIQUIDACION 2025'!$L$4,IF(W25="ENVÍO",'BASE DE LIQUIDACION 2025'!$K$4,AD25*AB25+AE25*AC25)) -> 153413.17
A26: BOGOTA | B26: =VLOOKUP(A26,'CENTRO DE COSTOS'!A:D,4,FALSE) -> WILLIAM ASDRUBAL ROZO ROZO | C26: =VLOOKUP(A26,'CENTRO DE COSTOS'!A:D,2,FALSE) -> 0004-0004 | D26: 11001 | E26: 2389762 | F26: 78975 | G26: ORDEN DE CAMBIO | H26: CUNDINAMARCA | I26: BOGOTA | J26: PTM BOGOTA DIOS SEA ALABADO | K26: REDEBAN | L26: FO-25-1190330 | M26: 45841.429 | N26: 45845.637 | P26: PUBLICIDAD | Q26: AVISO EXTERIOR | R26: AGREGADOR | S26: COMCARD - PTM | T26: EJECUTADO_EXITOSO | U26: EJECUTADO EXITOSO | V26: SE COMUNICA CB SR(A) PAOLA PARA REPORTAR QUE SE CAYO EL AVISO EXTERIOR HACE UNA SEMANA , DONDE ESTA UBICADO CORRE MUCHO VIENTO Y NO ES ESTABLE, AGRADECE GESTIÓN Y COLABORACIÓN 0 05/07/2025 SE LLEGA A COMERCIO EL CUAL SE ENCUENTRA CERRADO SE REALIZA CONTRATO TELÉFONICO CON CLIENTE PAOLA GAITAN A NÚMERO REGISTRADO 3224090655 LA CUAL INFORMAN QUE LLEGA HASTA EL DÍA MARTES DE LA SEMANA SIGUIENTE SE ESCALA Y SE REPOGRAMA LA VISITA REPROGRAMAR 0 07/07/2025 DURANTE LA VISITA TECNICA SE REALIZA INSTALACIÓN DE AVISO EXTERIOR CON CHAZOS A LA PARED EN LUGAR INDICADO POR COMERCIO A CONFORMIDAD DE CORRESPONSAL NO SE MANIPULA EQUIPOS SIN NOVEDAD EN INSTALACIÓN CERRAR | W26: VISITA_TÉCNICA | X26: 0 | Y26: TIPO I | Z26: TERRESTRE | AA26: GALEANO SORIANO JUAN DAVID | AB26: 2 | AC26: 3 | AD26: =IF(OR(W26="SOPORTE_TELEFÓNICO",W26="ENVÍO"),0,IF(Y26="TIPO I",'BASE DE LIQUIDACION 2025'!$I$4,IF(Y26="TIPO II",'BASE DE LIQUIDACION 2025'!$I$5,IF(Y26="TIPO III",'BASE DE LIQUIDACION 2025'!$I$6,IF(Y26="TIPO IV",'BASE DE LIQUIDACION 2025'!$I$7,'BASE DE LIQUIDACION 2025'!$I$8))))) -> 96001.196 | AE26: =IF(OR(W26="SOPORTE_TELEFÓNICO",W26="ENVÍO"),0,IF(Y26="TIPO I",'BASE DE LIQUIDACION 2025'!$J$4,IF(Y26="TIPO II",'BASE DE LIQUIDACION 2025'!$J$5,IF(Y26="TIPO III",'BASE DE LIQUIDACION 2025'!$J$6,IF(Y26="TIPO IV",'BASE DE LIQUIDACION 2025'!$J$7,'BASE DE LIQUIDACION 2025'!$J$8))))) -> 57411.974 | AF26: =IF(W26="SOPORTE_TELEFÓNICO",'BASE DE LIQUIDACION 2025'!$L$4,IF(W26="ENVÍO",'BASE DE LIQUIDACION 2025'!$K$4,AD26*AB26+AE26*AC26)) -> 364238.32
A27: BOGOTA | B27: =VLOOKUP(A27,'CENTRO DE COSTOS'!A:D,4,FALSE) -> WILLIAM ASDRUBAL ROZO ROZO | C27: =VLOOKUP(A27,'CENTRO DE COSTOS'!A:D,2,FALSE) -> 0004-0004 | D27: 11001 | E27: 2391379 | F27: 69498 | G27: ORDEN DE CAMBIO | H27: CUNDINAMARCA | I27: BOGOTA | J27: PTM BOGOTA FERRETERIA Y ELECT | K27: REDEBAN | L27: FO-25-1179271 | M27: 45841.536 | N27: 45845.655 | P27: PUBLICIDAD | Q27: AVISO EXTERIOR | R27: AGREGADOR | S27: COMCARD - PTM | T27: EJECUTADO_EXITOSO | U27: EJECUTADO EXITOSO | V27: SE COMUNICA PARA REPORTAR QUE EL AVISO EXTERIOR SE PARTIÓ Y NO SIRVE, SOLICITA ENVIÓ DE UNO NUEVO 0 07/07/2025 SE INSTALA AVISO EXTERIOR, NO SE MANIPULAN DATÁFONOS CERRAR | W27: VISITA_TÉCNICA | X27: 0 | Y27: TIPO I | Z27: TERRESTRE | AA27: GARCIA PASTRANA KEVIN FERNANDO | AB27: 1 | AC27: 1 | AD27: =IF(OR(W27="SOPORTE_TELEFÓNICO",W27="ENVÍO"),0,IF(Y27="TIPO I",'BASE DE LIQUIDACION 2025'!$I$4,IF(Y27="TIPO II",'BASE DE LIQUIDACION 2025'!$I$5,IF(Y27="TIPO III",'BASE DE LIQUIDACION 2025'!$I$6,IF(Y27="TIPO IV",'BASE DE LIQUIDACION 2025'!$I$7,'BASE DE LIQUIDACION 2025'!$I$8))))) -> 96001.196 | AE27: =IF(OR(W27="SOPORTE_TELEFÓNICO",W27="ENVÍO"),0,IF(Y27="TIPO I",'BASE DE LIQUIDACION 2025'!$J$4,IF(Y27="TIPO II",'BASE DE LIQUIDACION 2025'!$J$5,IF(Y27="TIPO III",'BASE DE LIQUIDACION 2025'!$J$6,IF(Y27="TIPO IV",'BASE DE LIQUIDACION 2025'!$J$7,'BASE DE LIQUIDACION 2025'!$J$8))))) -> 57411.974 | AF27: =IF(W27="SOPORTE_TELEFÓNICO",'BASE DE LIQUIDACION 2025'!$L$4,IF(W27="ENVÍO",'BASE DE LIQUIDACION 2025'!$K$4,AD27*AB27+AE27*AC27)) -> 153413.17
A28: CARTAGENA | B28: =VLOOKUP(A28,'CENTRO DE COSTOS'!A:D,4,FALSE) -> JOSE MAURICIO HERNANDEZ ROJAS | C28: =VLOOKUP(A28,'CENTRO DE COSTOS'!A:D,2,FALSE) -> 0004-0001 | D28: 13062 | E28: 2378348 | F28: 46833 | G28: ORDEN DE CAMBIO | H28: BOLIVAR | I28: ARROYOHONDO | J28: DISTRICOL FARMACIA LA SUPERIOR | K28: REDEBAN | L28: FO-25-1167831 | M28: 45839.666 | N28: 45845.686 | P28: PUBLICIDAD | Q28: AVISO EXTERIOR | R28: AGREGADOR | S28: DISTRICOL | T28: EJECUTADO_EXITOSO | U28: EJECUTADO EXITOSO | V28: SE COMUNICA CB SR(A) LINA PARA SOLICITAR EL AVISO EXTERIOR YA QUE EL VIENTO LO CAYO Y SE PARTIÓ 0 07/07/2025 SE REALIZA VISITA TÉCNICA, SE INSTALA AVISO EXTERIOR. CERRAR | W28: VISITA_TÉCNICA | X28: 0 | Y28: TIPO II | Z28: TERRESTRE | AA28: DE AGUAS MUÑOZ DAVID JOSE | AB28: 1 | AC28: 1 | AD28: =IF(OR(W28="SOPORTE_TELEFÓNICO",W28="ENVÍO"),0,IF(Y28="TIPO I",'BASE DE LIQUIDACION 2025'!$I$4,IF(Y28="TIPO II",'BASE DE LIQUIDACION 2025'!$I$5,IF(Y28="TIPO III",'BASE DE LIQUIDACION 2025'!$I$6,IF(Y28="TIPO IV",'BASE DE LIQUIDACION 2025'!$I$7,'BASE DE LIQUIDACION 2025'!$I$8))))) -> 232858.6 | AE28: =IF(OR(W28="SOPORTE_TELEFÓNICO",W28="ENVÍO"),0,IF(Y28="TIPO I",'BASE DE LIQUIDACION 2025'!$J$4,IF(Y28="TIPO II",'BASE DE LIQUIDACION 2025'!$J$5,IF(Y28="TIPO III",'BASE DE LIQUIDACION 2025'!$J$6,IF(Y28="TIPO IV",'BASE DE LIQUIDACION 2025'!$J$7,'BASE DE LIQUIDACION 2025'!$J$8))))) -> 110808.28 | AF28: =IF(W28="SOPORTE_TELEFÓNICO",'BASE DE LIQUIDACION 2025'!$L$4,IF(W28="ENVÍO",'BASE DE LIQUIDACION 2025'!$K$4,AD28*AB28+AE28*AC28)) -> 343666.88
... A84: BOGOTA | B84: =VLOOKUP(A84,'CENTRO DE COSTOS'!A:D,4,FALSE) -> WILLIAM ASDRUBAL ROZO ROZO | C84: =VLOOKUP(A84,'CENTRO DE COSTOS'!A:D,2,FALSE) -> 0004-0004 | D84: 11001 | E84: 2434665 | F84: 66244 | G84: ORDEN DE CAMBIO | H84: CUNDINAMARCA | I84: BOGOTA | J84: BARRIO CANDELARIA LA NUEVA BOG | K84: REDEBAN | L84: FO-25-1218470 | M84: 45849.556 | N84: 45857.682 | P84: PUBLICIDAD | Q84: AVISO EXTERIOR | R84: CB UNO A UNO | S84: CB UNO A UNO | T84: EJECUTADO_EXITOSO | U84: EJECUTADO EXITOSO | V84: SE COMUNICA CB SR(A) CAROL PARA SOLICITAR AVISO EXTERIOR POR DAÑO 15/07/2025 NO SE VISITA COMERCIO PARA LA INSTALACIÓN DE OC PUBLICIDAD RBM, YA QUE NO HAY SUMINISTRO DE MATERIAL POR PARTE DE RBM. HAY ACUMULACIÓN DE ACTIVIDADES DE INSTALACIÓN DE AVISO, NO TODAS SE PUEDEN HACER AL TIEMPO QUE LLEGUE EL MATERIAL 19/07/2025 DURANTE LA VISITA TECNICA SE REALIZA INSTALACIÓN DE AVISO EXTERIOR CON CHAZOS A LA PARED EN LUGAR INDICADO POR COMERCIO A CONFORMIDAD DE CORRESPONSAL NO SE MANIPULA EQUIPOS SIN NOVEDAD EN INSTALACIÓN CERRAR | W84: VISITA_TÉCNICA | X84: 0 | Y84: TIPO I | Z84: TERRESTRE | AA84: GALEANO SORIANO JUAN DAVID | AB84: 1 | AC84: 1 | AD84: =IF(OR(W84="SOPORTE_TELEFÓNICO",W84="ENVÍO"),0,IF(Y84="TIPO I",'BASE DE LIQUIDACION 2025'!$I$4,IF(Y84="TIPO II",'BASE DE LIQUIDACION 2025'!$I$5,IF(Y84="TIPO III",'BASE DE LIQUIDACION 2025'!$I$6,IF(Y84="TIPO IV",'BASE DE LIQUIDACION 2025'!$I$7,'BASE DE LIQUIDACION 2025'!$I$8))))) -> 96001.196 | AE84: =IF(OR(W84="SOPORTE_TELEFÓNICO",W84="ENVÍO"),0,IF(Y84="TIPO I",'BASE DE LIQUIDACION 2025'!$J$4,IF(Y84="TIPO II",'BASE DE LIQUIDACION 2025'!$J$5,IF(Y84="TIPO III",'BASE DE LIQUIDACION 2025'!$J$6,IF(Y84="TIPO IV",'BASE DE LIQUIDACION 2025'!$J$7,'BASE DE LIQUIDACION 2025'!$J$8))))) -> 57411.974 | AF84: =IF(W84="SOPORTE_TELEFÓNICO",'BASE DE LIQUIDACION 2025'!$L$4,IF(W84="ENVÍO",'BASE DE LIQUIDACION 2025'!$K$4,AD84*AB84+AE84*AC84)) -> 153413.17
A85: VILLAVICENCIO | B85: =VLOOKUP(A85,'CENTRO DE COSTOS'!A:D,4,FALSE) -> KEVIN ALEXIS CORZO BUSTOS | C85: =VLOOKUP(A85,'CENTRO DE COSTOS'!A:D,2,FALSE) -> 0004-0007 | D85: 50001 | E85: 2469632 | F85: 71604 | G85: ORDEN DE CAMBIO | H85: META | I85: VILLAVICENCIO | J85: VILALVICENCIO EL RETIRO | K85: REDEBAN | L85: FO-25-1253936 | M85: 45856.719 | N85: 45859.457 | P85: PUBLICIDAD | Q85: AVISO EXTERIOR | R85: CB UNO A UNO | S85: CB UNO A UNO | T85: EJECUTADO_EXITOSO | U85: EJECUTADO EXITOSO | V85: SE COMUNICA CB SR(A) KAROL PARA SOLICITAR AVISO EXTERIOR POR QUE UN INDIGENTE SE LO ROMPIÓ 0 21/07/2025 SE INSTALA AVISO EXTERIOR SIN NOVEDAD CERRAR | W85: VISITA_TÉCNICA | X85: LN00F232 | Y85: TIPO I | Z85: TERRESTRE | AA85: CASTRILLON URREA LONDIER LEANDRO | AB85: 1 | AC85: 1 | AD85: =IF(OR(W85="SOPORTE_TELEFÓNICO",W85="ENVÍO"),0,IF(Y85="TIPO I",'BASE DE LIQUIDACION 2025'!$I$4,IF(Y85="TIPO II",'BASE DE LIQUIDACION 2025'!$I$5,IF(Y85="TIPO III",'BASE DE LIQUIDACION 2025'!$I$6,IF(Y85="TIPO IV",'BASE DE LIQUIDACION 2025'!$I$7,'BASE DE LIQUIDACION 2025'!$I$8))))) -> 96001.196 | AE85: =IF(OR(W85="SOPORTE_TELEFÓNICO",W85="ENVÍO"),0,IF(Y85="TIPO I",'BASE DE LIQUIDACION 2025'!$J$4,IF(Y85="TIPO II",'BASE DE LIQUIDACION 2025'!$J$5,IF(Y85="TIPO III",'BASE DE LIQUIDACION 2025'!$J$6,IF(Y85="TIPO IV",'BASE DE LIQUIDACION 2025'!$J$7,'BASE DE LIQUIDACION 2025'!$J$8))))) -> 57411.974 | AF85: =IF(W85="SOPORTE_TELEFÓNICO",'BASE DE LIQUIDACION 2025'!$L$4,IF(W85="ENVÍO",'BASE DE LIQUIDACION 2025'!$K$4,AD85*AB85+AE85*AC85)) -> 153413.17
A86: PEREIRA | B86: =VLOOKUP(A86,'CENTRO DE COSTOS'!A:D,4,FALSE) -> DIEGO FERNANDO HENAO CARDONA | C86: =VLOOKUP(A86,'CENTRO DE COSTOS'!A:D,2,FALSE) -> 0004-0002 | D86: 63001 | E86: 2453302 | F86: 18770 | G86: ORDEN DE CAMBIO | H86: QUINDIO | I86: ARMENIA | J86: BARRIO CENTRO XIX ARMENIA | K86: REDEBAN | L86: FO-25-1238034 | M86: 45854.363 | N86: 45859.464 | P86: PUBLICIDAD | Q86: AVISO EXTERIOR | R86: CB UNO A UNO | S86: CB UNO A UNO | T86: EJECUTADO_EXITOSO | U86: EJECUTADO EXITOSO | V86: SE COMUNICA CB SR(A) KELLY PARA SOLICITAR AVISO EXTERIOR EL QUE TENIA SE LE ROMPIÓ 0 21/07/2025 SE VISITÓ COMERCIO SE REALIZÓ INSTALACIÓN DE AVISO EXTERIOR CERRAR | W86: VISITA_TÉCNICA | X86: BL08Z663 | Y86: TIPO II | Z86: TERRESTRE | AA86: SANCHEZ SOLORZANO JUAN SEBASTIAN | AB86: 1 | AC86: 1 | AD86: =IF(OR(W86="SOPORTE_TELEFÓNICO",W86="ENVÍO"),0,IF(Y86="TIPO I",'BASE DE LIQUIDACION 2025'!$I$4,IF(Y86="TIPO II",'BASE DE LIQUIDACION 2025'!$I$5,IF(Y86="TIPO III",'BASE DE LIQUIDACION 2025'!$I$6,IF(Y86="TIPO IV",'BASE DE LIQUIDACION 2025'!$I$7,'BASE DE LIQUIDACION 2025'!$I$8))))) -> 232858.6 | AE86: =IF(OR(W86="SOPORTE_TELEFÓNICO",W86="ENVÍO"),0,IF(Y86="TIPO I",'BASE DE LIQUIDACION 2025'!$J$4,IF(Y86="TIPO II",'BASE DE LIQUIDACION 2025'!$J$5,IF(Y86="TIPO III",'BASE DE LIQUIDACION 2025'!$J$6,IF(Y86="TIPO IV",'BASE DE LIQUIDACION 2025'!$J$7,'BASE DE LIQUIDACION 2025'!$J$8))))) -> 110808.28 | AF86: =IF(W86="SOPORTE_TELEFÓNICO",'BASE DE LIQUIDACION 2025'!$L$4,IF(W86="ENVÍO",'BASE DE LIQUIDACION 2025'!$K$4,AD86*AB86+AE86*AC86)) -> 343666.88
A87: CALI | B87: =VLOOKUP(A87,'CENTRO DE COSTOS'!A:D,4,FALSE) -> DIEGO FERNANDO HENAO CARDONA | C87: =VLOOKUP(A87,'CENTRO DE COSTOS'!A:D,2,FALSE) -> 0004-0003 | D87: 76001 | E87: 2470852 | F87: 23115 | G87: ORDEN DE CAMBIO | H87: VALLE DEL CAUCA | I87: CALI | J87: BARRIO VALE DEL LILI CALI | K87: REDEBAN | L87: FO-25-1256065 | M87: 45859.333 | N87: 45859.466 | P87: PUBLICIDAD | Q87: AVISO EXTERIOR | R87: CB UNO A UNO | S87: CB UNO A UNO | T87: EJECUTADO_EXITOSO | U87: EJECUTADO EXITOSO | V87: 0 21/07/2025 SE INSTALA AVISO EXTERIOR YA QUE EL CLIENTE NO TENÍA CERRAR | W87: VISITA_TÉCNICA | X87: HZZZZ035 | Y87: TIPO I | Z87: TERRESTRE | AA87: CUERO RUIZ JHONNY | AB87: 1 | AC87: 1 | AD87: =IF(OR(W87="SOPORTE_TELEFÓNICO",W87="ENVÍO"),0,IF(Y87="TIPO I",'BASE DE LIQUIDACION 2025'!$I$4,IF(Y87="TIPO II",'BASE DE LIQUIDACION 2025'!$I$5,IF(Y87="TIPO III",'BASE DE LIQUIDACION 2025'!$I$6,IF(Y87="TIPO IV",'BASE DE LIQUIDACION 2025'!$I$7,'BASE DE LIQUIDACION 2025'!$I$8))))) -> 96001.196 | AE87: =IF(OR(W87="SOPORTE_TELEFÓNICO",W87="ENVÍO"),0,IF(Y87="TIPO I",'BASE DE LIQUIDACION 2025'!$J$4,IF(Y87="TIPO II",'BASE DE LIQUIDACION 2025'!$J$5,IF(Y87="TIPO III",'BASE DE LIQUIDACION 2025'!$J$6,IF(Y87="TIPO IV",'BASE DE LIQUIDACION 2025'!$J$7,'BASE DE LIQUIDACION 2025'!$J$8))))) -> 57411.974 | AF87: =IF(W87="SOPORTE_TELEFÓNICO",'BASE DE LIQUIDACION 2025'!$L$4,IF(W87="ENVÍO",'BASE DE LIQUIDACION 2025'!$K$4,AD87*AB87+AE87*AC87)) -> 153413.17
A88: PASTO | B88: =VLOOKUP(A88,'CENTRO DE COSTOS'!A:D,4,FALSE) -> DIEGO FERNANDO HENAO CARDONA | C88: =VLOOKUP(A88,'CENTRO DE COSTOS'!A:D,2,FALSE) -> 0004-0003 | D88: 52356 | E88: 2464992 | F88: 76092 | G88: ORDEN DE CAMBIO | H88: NARIÑO | I88: IPIALES | J88: BARRIO SAN FELIPE IPIALES 2 | K88: REDEBAN | L88: FO-25-1248832 | M88: 45856.359 | N88: 45859.547 | P88: PUBLICIDAD | Q88: AVISO EXTERIOR | R88: CB UNO A UNO | S88: CB UNO A UNO | T88: EJECUTADO_CANCELADO | U88: PETICIÓN BANCOLOMBIA | V88: SE COMUNICA CB SR(A)ANGELICA PARA SOLICITAR AVISO EXTERIOR PORQUE SE LO ROBARON POR FAVOR Y GRACIAS 0 21/07/2025 SE REALIZA VISITA PARA INSTALACIÓN PERO AL LLEGAR SE ENCUENTRA QUE YA TIENEN AVISO EN EL LUGAR POR LO CUAL NO SE PUEDE INSTALAR OTRO AVISO CERRAR | W88: VISITA_TÉCNICA | X88: LA0EZ267 | Y88: TIPO II | Z88: TERRESTRE | AA88: PAZ MARTINEZ RICHARD HUMBERTO | AB88: 1 | AC88: 1 | AD88: =IF(OR(W88="SOPORTE_TELEFÓNICO",W88="ENVÍO"),0,IF(Y88="TIPO I",'BASE DE LIQUIDACION 2025'!$I$4,IF(Y88="TIPO II",'BASE DE LIQUIDACION 2025'!$I$5,IF(Y88="TIPO III",'BASE DE LIQUIDACION 2025'!$I$6,IF(Y88="TIPO IV",'BASE DE LIQUIDACION 2025'!$I$7,'BASE DE LIQUIDACION 2025'!$I$8))))) -> 232858.6 | AE88: =IF(OR(W88="SOPORTE_TELEFÓNICO",W88="ENVÍO"),0,IF(Y88="TIPO I",'BASE DE LIQUIDACION 2025'!$J$4,IF(Y88="TIPO II",'BASE DE LIQUIDACION 2025'!$J$5,IF(Y88="TIPO III",'BASE DE LIQUIDACION 2025'!$J$6,IF(Y88="TIPO IV",'BASE DE LIQUIDACION 2025'!$J$7,'BASE DE LIQUIDACION 2025'!$J$8))))) -> 110808.28 | AF88: =IF(W88="SOPORTE_TELEFÓNICO",'BASE DE LIQUIDACION 2025'!$L$4,IF(W88="ENVÍO",'BASE DE LIQUIDACION 2025'!$K$4,AD88*AB88+AE88*AC88)) -> 343666.88
A89: MEDELLIN | B89: =VLOOKUP(A89,'CENTRO DE COSTOS'!A:D,4,FALSE) -> JUAN SEBASTIÁN RÍOS CASTRILLÓN | C89: =VLOOKUP(A89,'CENTRO DE COSTOS'!A:D,2,FALSE) -> 0004-0005 | D89: 5607 | E89: 2391119 | F89: 37829 | G89: ORDEN DE CAMBIO | H89: ANTIOQUIA | I89: RETIRO | J89: BARRIO EL RETIRO RETIRO 1 | K89: REDEBAN | L89: FO-25-1178784 | M89: 45841.504 | N89: 45859.615 | P89: PUBLICIDAD | Q89: AVISO EXTERIOR | R89: CB UNO A UNO | S89: CB UNO A UNO | T89: EJECUTADO_EXITOSO | U89: EJECUTADO EXITOSO | V89: SE COMUNICA CB SR(A) JUAN, SOLICITA AVISO EXTERIOR EL NEGRO INDICA QUE EN UNA LLUVIA FUERTE SE CAYO Y SE ROMPIÓ SOLICITA LE COLABOREN..10-7 ACTIVIDAD PENDIENTE POR INCONVENIENTES LOGISITICOS DE LA ENTIDAD ..10-7 ACTIVIDAD PENDIENTE POR INCONVENIENTES LOGISITICOS DE LA ENTIDAD 08/07/2025 NO SE CUENTA CON STOCK DE PUBLICIDAD PARA ATENDER ACTIVIDAD. PUBLICIDAD EN ZONA SE TIENE APARTADA PARA REALIZAR APERTURAS. SE ESTÁ A LA ESPERA DE ENTREGA POR PARTE DEL PROVEEDOR. 21/07/2025 SE INSTALA AVISO EXTERIOR EXITOSAMENTE CERRAR | W89: VISITA_TÉCNICA | X89: GZ00P322 | Y89: TIPO II | Z89: TERRESTRE | AA89: RUA ALVAREZ RICHARD ANDRES | AB89: 1 | AC89: 1 | AD89: =IF(OR(W89="SOPORTE_TELEFÓNICO",W89="ENVÍO"),0,IF(Y89="TIPO I",'BASE DE LIQUIDACION 2025'!$I$4,IF(Y89="TIPO II",'BASE DE LIQUIDACION 2025'!$I$5,IF(Y89="TIPO III",'BASE DE LIQUIDACION 2025'!$I$6,IF(Y89="TIPO IV",'BASE DE LIQUIDACION 2025'!$I$7,'BASE DE LIQUIDACION 2025'!$I$8))))) -> 232858.6 | AE89: =IF(OR(W89="SOPORTE_TELEFÓNICO",W89="ENVÍO"),0,IF(Y89="TIPO I",'BASE DE LIQUIDACION 2025'!$J$4,IF(Y89="TIPO II",'BASE DE LIQUIDACION 2025'!$J$5,IF(Y89="TIPO III",'BASE DE LIQUIDACION 2025'!$J$6,IF(Y89="TIPO IV",'BASE DE LIQUIDACION 2025'!$J$7,'BASE DE LIQUIDACION 2025'!$J$8))))) -> 110808.28 | AF89: =IF(W89="SOPORTE_TELEFÓNICO",'BASE DE LIQUIDACION 2025'!$L$4,IF(W89="ENVÍO",'BASE DE LIQUIDACION 2025'!$K$4,AD89*AB89+AE89*AC89)) -> 343666.88
A90: MONTERIA | B90: =VLOOKUP(A90,'CENTRO DE COSTOS'!A:D,4,FALSE) -> JOSE MAURICIO HERNANDEZ ROJAS | C90: =VLOOKUP(A90,'CENTRO DE COSTOS'!A:D,2,FALSE) -> 0004-0001 | D90: 23660 | E90: 2471405 | F90: 16084 | G90: ORDEN DE CAMBIO | H90: CORDOBA | I90: SAHAGUN | J90: ARRIO TRONCAL DE OCCIDENTE SA | K90: REDEBAN | L90: FO-25-1257166 | M90: 45859.333 | N90: 45859.631 | P90: PUBLICIDAD | Q90: AVISO EXTERIOR | R90: CB UNO A UNO | S90: CB UNO A UNO | T90: EJECUTADO_EXITOSO | U90: EJECUTADO EXITOSO | V90: SE COMUNICA CB SR(A) PARA SOLICITAR AVISO EXTERIOR POR DAÑO 0 21/07/2025 SE VISITA COMERCIO Y SE HACE INSTALACIÓN DE AVISÓ EXTERIOR YA QUE UNA TORMENTA SE LO PARTIO. CERRAR | W90: VISITA_TÉCNICA | X90: A00FZ127 | Y90: TIPO II | Z90: TERRESTRE | AA90: CACERES HERNANDEZ ANDRES | AB90: 1 | AC90: 1 | AD90: =IF(OR(W90="SOPORTE_TELEFÓNICO",W90="ENVÍO"),0,IF(Y90="TIPO I",'BASE DE LIQUIDACION 2025'!$I$4,IF(Y90="TIPO II",'BASE DE LIQUIDACION 2025'!$I$5,IF(Y90="TIPO III",'BASE DE LIQUIDACION 2025'!$I$6,IF(Y90="TIPO IV",'BASE DE LIQUIDACION 2025'!$I$7,'BASE DE LIQUIDACION 2025'!$I$8))))) -> 232858.6 | AE90: =IF(OR(W90="SOPORTE_TELEFÓNICO",W90="ENVÍO"),0,IF(Y90="TIPO I",'BASE DE LIQUIDACION 2025'!$J$4,IF(Y90="TIPO II",'BASE DE LIQUIDACION 2025'!$J$5,IF(Y90="TIPO III",'BASE DE LIQUIDACION 2025'!$J$6,IF(Y90="TIPO IV",'BASE DE LIQUIDACION 2025'!$J$7,'BASE DE LIQUIDACION 2025'!$J$8))))) -> 110808.28 | AF90: =IF(W90="SOPORTE_TELEFÓNICO",'BASE DE LIQUIDACION 2025'!$L$4,IF(W90="ENVÍO",'BASE DE LIQUIDACION 2025'!$K$4,AD90*AB90+AE90*AC90)) -> 343666.88
A91: MEDELLIN | B91: =VLOOKUP(A91,'CENTRO DE COSTOS'!A:D,4,FALSE) -> JUAN SEBASTIÁN RÍOS CASTRILLÓN | C91: =VLOOKUP(A91,'CENTRO DE COSTOS'!A:D,2,FALSE) -> 0004-0005 | D91: 5001 | E91: 2396163 | F91: 13212 | G91: ORDEN DE CAMBIO | H91: ANTIOQUIA | I91: MEDELLIN | J91: BARRIO LOMA DE LOS BERNAL MEDE | K91: REDEBAN | L91: FO-25-1183384 | M91: 45842.435 | N91: 45860.384 | P91: PUBLICIDAD | Q91: AVISO EXTERIOR | R91: CB UNO A UNO | S91: CB UNO A UNO | T91: EJECUTADO_EXITOSO | U91: EJECUTADO EXITOSO | V91: SE COMUNICA CB SR(A) BERTILDA PARA SOLICITAR AVISO EXTERIOR POR QUE SE CAYO Y SE ROMPIÓ..10-7 ACTIVIDAD PENDIENTE POR INCONVENIENTES LOGISITICOS DE LA ENTIDAD 10/07/2025 NO SE CUENTA CON PUBLICIDAD EN BODEGA MEDELLÍN, LAS POCAS EXISTENCIAS ESTÁN SEPARADAS PARA APERTURAS. SE ESTÁ A LA ESPERA DE DISTRIBUCIÓN DE PUBLICIDAD A NIVEL NACIONAL PARA ATENCIÓN DE ACTIVIDADES. 21/07/2025 SE REALIZA INSTALACIÓN DEL AVISO EXTERIOR EXITOSAMENTE OK, YA QUE EL ANTERIOR SE ENCONTRABA DETERIORADO OK CERRAR | W91: VISITA_TÉCNICA | X91: JAATZ273 | Y91: TIPO I | Z91: TERRESTRE | AA91: MARTINEZ TOVAR OSCAR DAVID | AB91: 1 | AC91: 1 | AD91: =IF(OR(W91="SOPORTE_TELEFÓNICO",W91="ENVÍO"),0,IF(Y91="TIPO I",'BASE DE LIQUIDACION 2025'!$I$4,IF(Y91="TIPO II",'BASE DE LIQUIDACION 2025'!$I$5,IF(Y91="TIPO III",'BASE DE LIQUIDACION 2025'!$I$6,IF(Y91="TIPO IV",'BASE DE LIQUIDACION 2025'!$I$7,'BASE DE LIQUIDACION 2025'!$I$8))))) -> 96001.196 | AE91: =IF(OR(W91="SOPORTE_TELEFÓNICO",W91="ENVÍO"),0,IF(Y91="TIPO I",'BASE DE LIQUIDACION 2025'!$J$4,IF(Y91="TIPO II",'BASE DE LIQUIDACION 2025'!$J$5,IF(Y91="TIPO III",'BASE DE LIQUIDACION 2025'!$J$6,IF(Y91="TIPO IV",'BASE DE LIQUIDACION 2025'!$J$7,'BASE DE LIQUIDACION 2025'!$J$8))))) -> 57411.974 | AF91: =IF(W91="SOPORTE_TELEFÓNICO",'BASE DE LIQUIDACION 2025'!$L$4,IF(W91="ENVÍO",'BASE DE LIQUIDACION 2025'!$K$4,AD91*AB91+AE91*AC91)) -> 153413.17
A92: PEREIRA | B92: =VLOOKUP(A92,'CENTRO DE COSTOS'!A:D,4,FALSE) -> DIEGO FERNANDO HENAO CARDONA | C92: =VLOOKUP(A92,'CENTRO DE COSTOS'!A:D,2,FALSE) -> 0004-0002 | D92: 66682 | E92: 2475844 | F92: 44209 | G92: ORDEN DE CAMBIO | H92: RISARALDA | I92: SANTA ROSA DE CABAL | J92: DISTRICOL PAPELERIA LA HERMOSA | K92: REDEBAN | L92: FO-25-1261384 | M92: 45859.519 | N92: 45860.472 | P92: PUBLICIDAD | Q92: AVISO EXTERIOR | R92: AGREGADOR | S92: DISTRICOL | T92: EJECUTADO_EXITOSO | U92: EJECUTADO EXITOSO | V92: SE COMUNICA CB SR(A)JUAN ESTEBAN MORALES PARA SOLICITAR AVISO EXTERIOR YA QUE CAYO Y SE PARTIO 0 22/07/2025 SE INSTALA AVISO EXTERIOR. CERRAR | W92: VISITA_TÉCNICA | X92: AC04Z206 | Y92: TIPO I | Z92: TERRESTRE | AA92: FRANCO CAÑAVERAL YAMID RAUL | AB92: 1 | AC92: 1 | AD92: =IF(OR(W92="SOPORTE_TELEFÓNICO",W92="ENVÍO"),0,IF(Y92="TIPO I",'BASE DE LIQUIDACION 2025'!$I$4,IF(Y92="TIPO II",'BASE DE LIQUIDACION 2025'!$I$5,IF(Y92="TIPO III",'BASE DE LIQUIDACION 2025'!$I$6,IF(Y92="TIPO IV",'BASE DE LIQUIDACION 2025'!$I$7,'BASE DE LIQUIDACION 2025'!$I$8))))) -> 96001.196 | AE92: =IF(OR(W92="SOPORTE_TELEFÓNICO",W92="ENVÍO"),0,IF(Y92="TIPO I",'BASE DE LIQUIDACION 2025'!$J$4,IF(Y92="TIPO II",'BASE DE LIQUIDACION 2025'!$J$5,IF(Y92="TIPO III",'BASE DE LIQUIDACION 2025'!$J$6,IF(Y92="TIPO IV",'BASE DE LIQUIDACION 2025'!$J$7,'BASE DE LIQUIDACION 2025'!$J$8))))) -> 57411.974 | AF92: =IF(W92="SOPORTE_TELEFÓNICO",'BASE DE LIQUIDACION 2025'!$L$4,IF(W92="ENVÍO",'BASE DE LIQUIDACION 2025'!$K$4,AD92*AB92+AE92*AC92)) -> 153413.17
A93: MEDELLIN | B93: =VLOOKUP(A93,'CENTRO DE COSTOS'!A:D,4,FALSE) -> JUAN SEBASTIÁN RÍOS CASTRILLÓN | C93: =VLOOKUP(A93,'CENTRO DE COSTOS'!A:D,2,FALSE) -> 0004-0005 | D93: 5615 | E93: 2455783 | F93: 77755 | G93: ORDEN DE CAMBIO | H93: ANTIOQUIA | I93: RIONEGRO | J93: PTM RIONEGRO DROGUERIA SANTA C | K93: REDEBAN | L93: FO-25-1240435 | M93: 45854.551 | N93: 45860.578 | P93: PUBLICIDAD | Q93: AVISO EXTERIOR | R93: AGREGADOR | S93: COMCARD - PTM | T93: EJECUTADO_EXITOSO | U93: EJECUTADO EXITOSO | V93: SE COMUNICA CB SR(A) SARA, SOLICITA AVISO EXTERIOR INDICA QUE EL QUE TENIA SE CAYO Y SE ROMPIÓ TOTALMENTE EL ESTABLECIMIENTO ESTA SIN AVISO 0 22/07/2025 INSTALACIÓN EXITOSA DE AVISO EXTERIOR CERRAR | W93: VISITA_TÉCNICA | X93: 0 | Y93: TIPO II | Z93: TERRESTRE | AA93: CASTAÑEDA PALACIO CARLOS FELIPE | AB93: 1 | AC93: 1 | AD93: =IF(OR(W93="SOPORTE_TELEFÓNICO",W93="ENVÍO"),0,IF(Y93="TIPO I",'BASE DE LIQUIDACION 2025'!$I$4,IF(Y93="TIPO II",'BASE DE LIQUIDACION 2025'!$I$5,IF(Y93="TIPO III",'BASE DE LIQUIDACION 2025'!$I$6,IF(Y93="TIPO IV",'BASE DE LIQUIDACION 2025'!$I$7,'BASE DE LIQUIDACION 2025'!$I$8))))) -> 232858.6 | AE93: =IF(OR(W93="SOPORTE_TELEFÓNICO",W93="ENVÍO"),0,IF(Y93="TIPO I",'BASE DE LIQUIDACION 2025'!$J$4,IF(Y93="TIPO II",'BASE DE LIQUIDACION 2025'!$J$5,IF(Y93="TIPO III",'BASE DE LIQUIDACION 2025'!$J$6,IF(Y93="TIPO IV",'BASE DE LIQUIDACION 2025'!$J$7,'BASE DE LIQUIDACION 2025'!$J$8))))) -> 110808.28 | AF93: =IF(W93="SOPORTE_TELEFÓNICO",'BASE DE LIQUIDACION 2025'!$L$4,IF(W93="ENVÍO",'BASE DE LIQUIDACION 2025'!$K$4,AD93*AB93+AE93*AC93)) -> 343666.88
A94: CALI | B94: =VLOOKUP(A94,'CENTRO DE COSTOS'!A:D,4,FALSE) -> DIEGO FERNANDO HENAO CARDONA | C94: =VLOOKUP(A94,'CENTRO DE COSTOS'!A:D,2,FALSE) -> 0004-0003 | D94: 76520 | E94: 2474787 | F94: 62346 | G94: ORDEN DE CAMBIO | H94: VALLE DEL CAUCA | I94: PALMIRA | J94: BARRIO BARRIO CENTRAL PALMIRA | K94: REDEBAN | L94: FO-25-1260622 | M94: 45859.463 | N94: 45860.656 | P94: PUBLICIDAD | Q94: AVISO EXTERIOR | R94: CB UNO A UNO | S94: CB UNO A UNO | T94: EJECUTADO_EXITOSO | U94: EJECUTADO EXITOSO | V94: SE COMUNICA CB SR(A) CONSTANZA PARA SOLICITAR AVISO EXTERIOR, INDICA QUE CUANDO LLEGÓ A SU ESTABLECIMIENTO LO ENCONTRÓ EN EL PISO, COMPLETAMENTE INSERVIBLE 0 22/07/2025 SE REALIZA INSTALACIÓN DE AVISO EXTERIOR CB BANCOLOMBIA CERRAR | W94: VISITA_TÉCNICA | X94: 0A00C268 | Y94: TIPO I | Z94: TERRESTRE | AA94: PAREDES CASTILLO DIEGO | AB94: 1 | AC94: 1 | AD94: =IF(OR(W94="SOPORTE_TELEFÓNICO",W94="ENVÍO"),0,IF(Y94="TIPO I",'BASE DE LIQUIDACION 2025'!$I$4,IF(Y94="TIPO II",'BASE DE LIQUIDACION 2025'!$I$5,IF(Y94="TIPO III",'BASE DE LIQUIDACION 2025'!$I$6,IF(Y94="TIPO IV",'BASE DE LIQUIDACION 2025'!$I$7,'BASE DE LIQUIDACION 2025'!$I$8))))) -> 96001.196 | AE94: =IF(OR(W94="SOPORTE_TELEFÓNICO",W94="ENVÍO"),0,IF(Y94="TIPO I",'BASE DE LIQUIDACION 2025'!$J$4,IF(Y94="TIPO II",'BASE DE LIQUIDACION 2025'!$J$5,IF(Y94="TIPO III",'BASE DE LIQUIDACION 2025'!$J$6,IF(Y94="TIPO IV",'BASE DE LIQUIDACION 2025'!$J$7,'BASE DE LIQUIDACION 2025'!$J$8))))) -> 57411.974 | AF94: =IF(W94="SOPORTE_TELEFÓNICO",'BASE DE LIQUIDACION 2025'!$L$4,IF(W94="ENVÍO",'BASE DE LIQUIDACION 2025'!$K$4,AD94*AB94+AE94*AC94)) -> 153413.17
A95: VALLEDUPAR | B95: =VLOOKUP(A95,'CENTRO DE COSTOS'!A:D,4,FALSE) -> JOSE MAURICIO HERNANDEZ ROJAS | C95: =VLOOKUP(A95,'CENTRO DE COSTOS'!A:D,2,FALSE) -> 0004-0001 | D95: 20001 | E95: 2470666 | F95: 52372 | G95: ORDEN DE CAMBIO | H95: CESAR | I95: VALLEDUPAR | J95: BARRIO LA ROCA VALLEDUPAR | K95: REDEBAN | L95: FO-25-1256800 | M95: 45859.333 | N95: 45861.391 | P95: PUBLICIDAD | Q95: AVISO EXTERIOR | R95: CB UNO A UNO | S95: CB UNO A UNO | T95: EJECUTADO_EXITOSO | U95: EJECUTADO EXITOSO | V95: SE COMUNICA CB SR. SAMIR, PARA SOLICITAR EL AVISO EXTERIOR POR FAVOR YA QUE ESTABA CRISTALIZADO, PASO UN VENTARRÓN, SE CAYÓ Y SE PARTIÓ 0 23/07/2025 SE REALIZA INSTALACIÓN DE AVISO EXTERIOR, YA QUE SE LO HABIAN ROBADO CERRAR | W95: VISITA_TÉCNICA | X95: XP0EZ778 | Y95: TIPO I | Z95: TERRESTRE | AA95: MONTES DIAZ JOHN FRED | AB95: 1 | AC95: 1 | AD95: =IF(OR(W95="SOPORTE_TELEFÓNICO",W95="ENVÍO"),0,IF(Y95="TIPO I",'BASE DE LIQUIDACION 2025'!$I$4,IF(Y95="TIPO II",'BASE DE LIQUIDACION 2025'!$I$5,IF(Y95="TIPO III",'BASE DE LIQUIDACION 2025'!$I$6,IF(Y95="TIPO IV",'BASE DE LIQUIDACION 2025'!$I$7,'BASE DE LIQUIDACION 2025'!$I$8))))) -> 96001.196 | AE95: =IF(OR(W95="SOPORTE_TELEFÓNICO",W95="ENVÍO"),0,IF(Y95="TIPO I",'BASE DE LIQUIDACION 2025'!$J$4,IF(Y95="TIPO II",'BASE DE LIQUIDACION 2025'!$J$5,IF(Y95="TIPO III",'BASE DE LIQUIDACION 2025'!$J$6,IF(Y95="TIPO IV",'BASE DE LIQUIDACION 2025'!$J$7,'BASE DE LIQUIDACION 2025'!$J$8))))) -> 57411.974 | AF95: =IF(W95="SOPORTE_TELEFÓNICO",'BASE DE LIQUIDACION 2025'!$L$4,IF(W95="ENVÍO",'BASE DE LIQUIDACION 2025'!$K$4,AD95*AB95+AE95*AC95)) -> 153413.17
A96: MEDELLIN | B96: =VLOOKUP(A96,'CENTRO DE COSTOS'!A:D,4,FALSE) -> JUAN SEBASTIÁN RÍOS CASTRILLÓN | C96: =VLOOKUP(A96,'CENTRO DE COSTOS'!A:D,2,FALSE) -> 0004-0005 | D96: 5266 | E96: 2358729 | F96: 47096 | G96: ORDEN DE CAMBIO | H96: ANTIOQUIA | I96: ENVIGADO | J96: BARRIO LA MINA ENVIGADO 2 | K96: REDEBAN | L96: FO-25-1138118 | M96: 45834.431 | N96: 45861.431 | P96: PUBLICIDAD | Q96: AVISO EXTERIOR | R96: CB UNO A UNO | S96: CB UNO A UNO | T96: EJECUTADO_CANCELADO | U96: PETICIÓN USUARIO | V96: SE COMUNICA CB SR(A) JESENIA VELEZ PARA SOLICITAR AVISO EXTERIOR POR ROBO, 03/07/2025 NO HAY AVISOS EN BODEGA 08/07/2025 NO SE CUENTA CON STOCK DE PUBLICIDAD PARA ATENDER ACTIVIDAD. PUBLICIDAD EN ZONA SE TIENE APARTADA PARA REALIZAR APERTURAS. SE ESTÁ A LA ESPERA DE ENTREGA POR PARTE DEL PROVEEDOR. 23/07/2025 ESTABLECIMIENTO CERRADO SE LLAMA AL CLIENTE Y DICE QUE VA HACER ENTREGA Y QUE YA NO NECESITA EL AVISO CERRAR | W96: VISITA_TÉCNICA | X96: 0 | Y96: TIPO I | Z96: TERRESTRE | AA96: MORENO MEDINA JUAN PABLO | AB96: 1 | AC96: 1 | AD96: =IF(OR(W96="SOPORTE_TELEFÓNICO",W96="ENVÍO"),0,IF(Y96="TIPO I",'BASE DE LIQUIDACION 2025'!$I$4,IF(Y96="TIPO II",'BASE DE LIQUIDACION 2025'!$I$5,IF(Y96="TIPO III",'BASE DE LIQUIDACION 2025'!$I$6,IF(Y96="TIPO IV",'BASE DE LIQUIDACION 2025'!$I$7,'BASE DE LIQUIDACION 2025'!$I$8))))) -> 96001.196 | AE96: =IF(OR(W96="SOPORTE_TELEFÓNICO",W96="ENVÍO"),0,IF(Y96="TIPO I",'BASE DE LIQUIDACION 2025'!$J$4,IF(Y96="TIPO II",'BASE DE LIQUIDACION 2025'!$J$5,IF(Y96="TIPO III",'BASE DE LIQUIDACION 2025'!$J$6,IF(Y96="TIPO IV",'BASE DE LIQUIDACION 2025'!$J$7,'BASE DE LIQUIDACION 2025'!$J$8))))) -> 57411.974 | AF96: =IF(W96="SOPORTE_TELEFÓNICO",'BASE DE LIQUIDACION 2025'!$L$4,IF(W96="ENVÍO",'BASE DE LIQUIDACION 2025'!$K$4,AD96*AB96+AE96*AC96)) -> 153413.17
A97: SANTA MARTA | B97: =VLOOKUP(A97,'CENTRO DE COSTOS'!A:D,4,FALSE) -> JOSE MAURICIO HERNANDEZ ROJAS | C97: =VLOOKUP(A97,'CENTRO DE COSTOS'!A:D,2,FALSE) -> 0004-0001 | D97: 44001 | E97: 2460691 | F97: 44781 | G97: ORDEN DE CAMBIO | H97: LA GUAJIRA | I97: RIOHACHA | J97: DISTRICOL TIENDA TIGRERA | K97: REDEBAN | L97: FO-25-1244319 | M97: 45855.44 | N97: 45861.434 | P97: PUBLICIDAD | Q97: AVISO EXTERIOR | R97: AGREGADOR | S97: DISTRICOL | T97: EJECUTADO_EXITOSO | U97: EJECUTADO EXITOSO | V97: SE COMUNICA CB SR(A) GONZALO PARA SOLICITAR AVISO EXTERIOR POR DAÑO TOTAL 0 23/07/2025 SE REALIZA INSTALACIÓN DE AVISO EXTERIOR A SATISFACCIÓN DEL CLIENTE CERRAR | W97: VISITA_TÉCNICA | X97: GA0EZ773 | Y97: TIPO III | Z97: TERRESTRE | AA97: THOMAS CAMPO SIGIFREDO SEGUNDO | AB97: 1 | AC97: 1 | AD97: =IF(OR(W97="SOPORTE_TELEFÓNICO",W97="ENVÍO"),0,IF(Y97="TIPO I",'BASE DE LIQUIDACION 2025'!$I$4,IF(Y97="TIPO II",'BASE DE LIQUIDACION 2025'!$I$5,IF(Y97="TIPO III",'BASE DE LIQUIDACION 2025'!$I$6,IF(Y97="TIPO IV",'BASE DE LIQUIDACION 2025'!$I$7,'BASE DE LIQUIDACION 2025'!$I$8))))) -> 344774.57 | AE97: =IF(OR(W97="SOPORTE_TELEFÓNICO",W97="ENVÍO"),0,IF(Y97="TIPO I",'BASE DE LIQUIDACION 2025'!$J$4,IF(Y97="TIPO II",'BASE DE LIQUIDACION 2025'!$J$5,IF(Y97="TIPO III",'BASE DE LIQUIDACION 2025'!$J$6,IF(Y97="TIPO IV",'BASE DE LIQUIDACION 2025'!$J$7,'BASE DE LIQUIDACION 2025'!$J$8))))) -> 110808.28 | AF97: =IF(W97="SOPORTE_TELEFÓNICO",'BASE DE LIQUIDACION 2025'!$L$4,IF(W97="ENVÍO",'BASE DE LIQUIDACION 2025'!$K$4,AD97*AB97+AE97*AC97)) -> 455582.84
A98: BUCARAMANGA | B98: =VLOOKUP(A98,'CENTRO DE COSTOS'!A:D,4,FALSE) -> MIGUEL JULIÁN HERNÁNDEZ GUARÍN | C98: =VLOOKUP(A98,'CENTRO DE COSTOS'!A:D,2,FALSE) -> 0004-0008 | D98: 68001 | E98: 2484354 | F98: 43432 | G98: ORDEN DE CAMBIO | H98: SANTANDER | I98: BUCARAMANGA | J98: BARRIO CENTRO BUCARAMANGA 24 | K98: REDEBAN | L98: FO-25-1267646 | M98: 45860.533 | N98: 45861.443 | P98: PUBLICIDAD | Q98: AVISO EXTERIOR | R98: CB UNO A UNO | S98: CB UNO A UNO | T98: EJECUTADO_EXITOSO | U98: EJECUTADO EXITOSO | V98: SE COMUNICA CB SR(A) MELISA PARA SOLICITAR AVISO EXTERIOR PORQUE SE CAYO Y SE PARTIÓ 0 23/07/2025 SE REALIZA VISITA AL COMERCIO SE INSTALA AVISO EXTERIOR CERRAR | W98: VISITA_TÉCNICA | X98: AC00M750 | Y98: TIPO I | Z98: TERRESTRE | AA98: MARIÑO PABON JORGE ENRIQUE | AB98: 1 | AC98: 1 | AD98: =IF(OR(W98="SOPORTE_TELEFÓNICO",W98="ENVÍO"),0,IF(Y98="TIPO I",'BASE DE LIQUIDACION 2025'!$I$4,IF(Y98="TIPO II",'BASE DE LIQUIDACION 2025'!$I$5,IF(Y98="TIPO III",'BASE DE LIQUIDACION 2025'!$I$6,IF(Y98="TIPO IV",'BASE DE LIQUIDACION 2025'!$I$7,'BASE DE LIQUIDACION 2025'!$I$8))))) -> 96001.196 | AE98: =IF(OR(W98="SOPORTE_TELEFÓNICO",W98="ENVÍO"),0,IF(Y98="TIPO I",'BASE DE LIQUIDACION 2025'!$J$4,IF(Y98="TIPO II",'BASE DE LIQUIDACION 2025'!$J$5,IF(Y98="TIPO III",'BASE DE LIQUIDACION 2025'!$J$6,IF(Y98="TIPO IV",'BASE DE LIQUIDACION 2025'!$J$7,'BASE DE LIQUIDACION 2025'!$J$8))))) -> 57411.974 | AF98: =IF(W98="SOPORTE_TELEFÓNICO",'BASE DE LIQUIDACION 2025'!$L$4,IF(W98="ENVÍO",'BASE DE LIQUIDACION 2025'!$K$4,AD98*AB98+AE98*AC98)) -> 153413.17
A99: CUCUTA | B99: =VLOOKUP(A99,'CENTRO DE COSTOS'!A:D,4,FALSE) -> MIGUEL JULIÁN HERNÁNDEZ GUARÍN | C99: =VLOOKUP(A99,'CENTRO DE COSTOS'!A:D,2,FALSE) -> 0004-0008 | D99: 54874 | E99: 2485605 | F99: 77332 | G99: ORDEN DE CAMBIO | H99: NORTE DE SANTANDER | I99: NORTE DE SANTANDER | J99: BARRIO BELLAVISTA VILLA DEL ROSARIO 1 | K99: REDEBAN | L99: FO-25-1268794 | M99: 45860.626 | N99: 45861.445 | P99: PUBLICIDAD | Q99: AVISO EXTERIOR | R99: CB UNO A UNO | S99: CB UNO A UNO | T99: EJECUTADO_EXITOSO | U99: EJECUTADO EXITOSO | V99: SE COMUNICA CB SR(A) LIZMAR PARA SOLCIITA EL AVISO EXTERIOR YA QUE SE CAYO Y SE PARTIO 23/07/2025 SE REALIZÓ LLAMADA TELEFÓNICA AL NÚMERO 3215906394 NO SE OBTIENE COMUNICACIÓN, SE PROCEDE A REALIZAR VISITA TÉCNICA 23/07/2025 SE REALIZÓ VISITA AL COMERCIO Y SE INSTALA AVISO EXTERIOR TODO OK CERRAR | W99: VISITA_TÉCNICA | X99: FACZZ909 | Y99: TIPO I | Z99: TERRESTRE | AA99: MORA VEGA JEAMPIER | AB99: 1 | AC99: 1 | AD99: =IF(OR(W99="SOPORTE_TELEFÓNICO",W99="ENVÍO"),0,IF(Y99="TIPO I",'BASE DE LIQUIDACION 2025'!$I$4,IF(Y99="TIPO II",'BASE DE LIQUIDACION 2025'!$I$5,IF(Y99="TIPO III",'BASE DE LIQUIDACION 2025'!$I$6,IF(Y99="TIPO IV",'BASE DE LIQUIDACION 2025'!$I$7,'BASE DE LIQUIDACION 2025'!$I$8))))) -> 96001.196 | AE99: =IF(OR(W99="SOPORTE_TELEFÓNICO",W99="ENVÍO"),0,IF(Y99="TIPO I",'BASE DE LIQUIDACION 2025'!$J$4,IF(Y99="TIPO II",'BASE DE LIQUIDACION 2025'!$J$5,IF(Y99="TIPO III",'BASE DE LIQUIDACION 2025'!$J$6,IF(Y99="TIPO IV",'BASE DE LIQUIDACION 2025'!$J$7,'BASE DE LIQUIDACION 2025'!$J$8))))) -> 57411.974 | AF99: =IF(W99="SOPORTE_TELEFÓNICO",'BASE DE LIQUIDACION 2025'!$L$4,IF(W99="ENVÍO",'BASE DE LIQUIDACION 2025'!$K$4,AD99*AB99+AE99*AC99)) -> 153413.17
A100: MEDELLIN | B100: =VLOOKUP(A100,'CENTRO DE COSTOS'!A:D,4,FALSE) -> JUAN SEBASTIÁN RÍOS CASTRILLÓN | C100: =VLOOKUP(A100,'CENTRO DE COSTOS'!A:D,2,FALSE) -> 0004-0005 | D100: 5001 | E100: 2404323 | F100: 38995 | G100: ORDEN DE CAMBIO | H100: ANTIOQUIA | I100: MEDELLIN | J100: PTM MED SOFIA LA 67 | K100: REDEBAN | L100: FO-25-1192776 | M100: 45845.394 | N100: 45861.499 | P100: PUBLICIDAD | Q100: AVISO EXTERIOR | R100: AGREGADOR | S100: COMCARD - PTM | T100: EJECUTADO_EXITOSO | U100: EJECUTADO EXITOSO | V100: SE COMUNICA CB SR(A)SAMIRA PARA SOLICITAR AVISO EXTERIOR POR HURTO..10-7 ACTIVIDAD PENDIENTE POR INCONVENIENTES LOGISITICOS DE LA ENTIDAD 10/07/2025 NO SE CUENTA CON PUBLICIDAD EN BODEGA MEDELLÍN, LAS POCAS EXISTENCIAS ESTÁN SEPARADAS PARA APERTURAS. SE ESTÁ A LA ESPERA DE DISTRIBUCIÓN DE PUBLICIDAD A NIVEL NACIONAL PARA ATENCIÓN DE ACTIVIDADES. 23/07/2025 SE REALIZA INSTALACIÓN DEL AVISO EXTERIOR EXITOSAMENTE OK, YA QUE EL ANTERIOR SE LO ROBARON OK CERRAR | W100: VISITA_TÉCNICA | X100: 9A06Z167 | Y100: TIPO I | Z100: TERRESTRE | AA100: MARTINEZ TOVAR OSCAR DAVID | AB100: 1 | AC100: 1 | AD100: =IF(OR(W100="SOPORTE_TELEFÓNICO",W100="ENVÍO"),0,IF(Y100="TIPO I",'BASE DE LIQUIDACION 2025'!$I$4,IF(Y100="TIPO II",'BASE DE LIQUIDACION 2025'!$I$5,IF(Y100="TIPO III",'BASE DE LIQUIDACION 2025'!$I$6,IF(Y100="TIPO IV",'BASE DE LIQUIDACION 2025'!$I$7,'BASE DE LIQUIDACION 2025'!$I$8))))) -> 96001.196 | AE100: =IF(OR(W100="SOPORTE_TELEFÓNICO",W100="ENVÍO"),0,IF(Y100="TIPO I",'BASE DE LIQUIDACION 2025'!$J$4,IF(Y100="TIPO II",'BASE DE LIQUIDACION 2025'!$J$5,IF(Y100="TIPO III",'BASE DE LIQUIDACION 2025'!$J$6,IF(Y100="TIPO IV",'BASE DE LIQUIDACION 2025'!$J$7,'BASE DE LIQUIDACION 2025'!$J$8))))) -> 57411.974 | AF100: =IF(W100="SOPORTE_TELEFÓNICO",'BASE DE LIQUIDACION 2025'!$L$4,IF(W100="ENVÍO",'BASE DE LIQUIDACION 2025'!$K$4,AD100*AB100+AE100*AC100)) -> 153413.17
A101: VALLEDUPAR | B101: =VLOOKUP(A101,'CENTRO DE COSTOS'!A:D,4,FALSE) -> JOSE MAURICIO HERNANDEZ ROJAS | C101: =VLOOKUP(A101,'CENTRO DE COSTOS'!A:D,2,FALSE) -> 0004-0001 | D101: 20400 | E101: 2477298 | F101: 38282 | G101: ORDEN DE CAMBIO | H101: CESAR | I101: LA JAGUA DE IBIRICO | J101: BARRIO CENTRO LA JAGUA DE IBIR | K101: REDEBAN | L101: FO-25-1262843 | M101: 45859.653 | N101: 45861.501 | P101: PUBLICIDAD | Q101: AVISO EXTERIOR | R101: CB UNO A UNO | S101: CB UNO A UNO | T101: EJECUTADO_EXITOSO | U101: EJECUTADO EXITOSO | V101: SE COMUNICA CB SR(A) RAMON PARA SOLICITAR AVISO EXTERIOR, YA QUE SE LO ARRANCARON Y LO PARTIERON 0 23/07/2025 SE INSTALA AVISO NUEVO YA QUE EL QUE ESTABA EN SITIO LAS FUERTES BRISAS LO PARTIERON, USUARIO INDICA QUE LOS RESTOS DEL AVISO LOS ECHÓ A LA BASURA CERRAR | W101: VISITA_TÉCNICA | X101: AB00U892 | Y101: TIPO III | Z101: TERRESTRE | AA101: BENITEZ CARVAJAL ALVARO JAVIER | AB101: 1 | AC101: 1 | AD101: =IF(OR(W101="SOPORTE_TELEFÓNICO",W101="ENVÍO"),0,IF(Y101="TIPO I",'BASE DE LIQUIDACION 2025'!$I$4,IF(Y101="TIPO II",'BASE DE LIQUIDACION 2025'!$I$5,IF(Y101="TIPO III",'BASE DE LIQUIDACION 2025'!$I$6,IF(Y101="TIPO IV",'BASE DE LIQUIDACION 2025'!$I$7,'BASE DE LIQUIDACION 2025'!$I$8))))) -> 344774.57 | AE101: =IF(OR(W101="SOPORTE_TELEFÓNICO",W101="ENVÍO"),0,IF(Y101="TIPO I",'BASE DE LIQUIDACION 2025'!$J$4,IF(Y101="TIPO II",'BASE DE LIQUIDACION 2025'!$J$5,IF(Y101="TIPO III",'BASE DE LIQUIDACION 2025'!$J$6,IF(Y101="TIPO IV",'BASE DE LIQUIDACION 2025'!$J$7,'BASE DE LIQUIDACION 2025'!$J$8))))) -> 110808.28 | AF101: =IF(W101="SOPORTE_TELEFÓNICO",'BASE DE LIQUIDACION 2025'!$L$4,IF(W101="ENVÍO",'BASE DE LIQUIDACION 2025'!$K$4,AD101*AB101+AE101*AC101)) -> 455582.84
A102: CUCUTA | B102: =VLOOKUP(A102,'CENTRO DE COSTOS'!A:D,4,FALSE) -> MIGUEL JULIÁN HERNÁNDEZ GUARÍN | C102: =VLOOKUP(A102,'CENTRO DE COSTOS'!A:D,2,FALSE) -> 0004-0008 | D102: 54001 | E102: 2486951 | F102: 44684 | G102: ORDEN DE CAMBIO | H102: NORTE DE SANTANDER | I102: CUCUTA | J102: PTM CUCUTA LA 12 MULTISERVICIO | K102: REDEBAN | L102: FO-25-1269675 | M102: 45860.746 | N102: 45861.503 | P102: PUBLICIDAD | Q102: AVISO EXTERIOR | R102: AGREGADOR | S102: COMCARD - PTM | T102: EJECUTADO_EXITOSO | U102: EJECUTADO EXITOSO | V102: SE COMUNICA CB SR(A)DAYANA SÁNCHEZ PARA SOLICITAR AVISO EXTERIOR YA QUE SE ROMPIÓ , GRACIAS 0 23/07/2025 SE REALIZA INSTALACIÓN DE AVISO EXTERIOR OK CERRAR | W102: VISITA_TÉCNICA | X102: AB1EZ110 | Y102: TIPO I | Z102: TERRESTRE | AA102: DURAN ACOSTA FRANK YONNY | AB102: 1 | AC102: 1 | AD102: =IF(OR(W102="SOPORTE_TELEFÓNICO",W102="ENVÍO"),0,IF(Y102="TIPO I",'BASE DE LIQUIDACION 2025'!$I$4,IF(Y102="TIPO II",'BASE DE LIQUIDACION 2025'!$I$5,IF(Y102="TIPO III",'BASE DE LIQUIDACION 2025'!$I$6,IF(Y102="TIPO IV",'BASE DE LIQUIDACION 2025'!$I$7,'BASE DE LIQUIDACION 2025'!$I$8))))) -> 96001.196 | AE102: =IF(OR(W102="SOPORTE_TELEFÓNICO",W102="ENVÍO"),0,IF(Y102="TIPO I",'BASE DE LIQUIDACION 2025'!$J$4,IF(Y102="TIPO II",'BASE DE LIQUIDACION 2025'!$J$5,IF(Y102="TIPO III",'BASE DE LIQUIDACION 2025'!$J$6,IF(Y102="TIPO IV",'BASE DE LIQUIDACION 2025'!$J$7,'BASE DE LIQUIDACION 2025'!$J$8))))) -> 57411.974 | AF102: =IF(W102="SOPORTE_TELEFÓNICO",'BASE DE LIQUIDACION 2025'!$L$4,IF(W102="ENVÍO",'BASE DE LIQUIDACION 2025'!$K$4,AD102*AB102+AE102*AC102)) -> 153413.17
A103: MEDELLIN | B103: =VLOOKUP(A103,'CENTRO DE COSTOS'!A:D,4,FALSE) -> JUAN SEBASTIÁN RÍOS CASTRILLÓN | C103: =VLOOKUP(A103,'CENTRO DE COSTOS'!A:D,2,FALSE) -> 0004-0005 | D103: 5001 | E103: 2387461 | F103: 10347 | G103: ORDEN DE CAMBIO | H103: ANTIOQUIA | I103: MEDELLIN | J103: BARRIO MANRIQUE GUADALUPE | K103: REDEBAN | L103: FO-25-1177760 | M103: 45841.333 | N103: 45861.521 | P103: PUBLICIDAD | Q103: AVISO EXTERIOR | R103: CB UNO A UNO | S103: CB UNO A UNO | T103: EJECUTADO_EXITOSO | U103: EJECUTADO EXITOSO | V103: SE COMUNICA CB SR(A) EVELIO PARA SOLICITAR AVISO EXTERIOR YA QUE EL QUE TENIA SE CAYO Y SE DAÑO..9-7 ACTIVIDAD PENDIENTE POR INCONVENIENTES LOGISITICOS DE LA ENTIDAD 08/07/2025 NO SE HACE ACTIVIDAD POR FALTA DE AVISOS EN BODEGA 23/07/2025 SE REALIZA INSTALACIÓN DEL AVISO EXTERIOR EXITOSAMENTE OK, AVISO ANTERIOR SE CAYÓ Y SE DETERIORO OK CERRAR | W103: VISITA_TÉCNICA | X103: IZ7ZZ598 | Y103: TIPO I | Z103: TERRESTRE | AA103: MARTINEZ TOVAR OSCAR DAVID | AB103: 1 | AC103: 1 | AD103: =IF(OR(W103="SOPORTE_TELEFÓNICO",W103="ENVÍO"),0,IF(Y103="TIPO I",'BASE DE LIQUIDACION 2025'!$I$4,IF(Y103="TIPO II",'BASE DE LIQUIDACION 2025'!$I$5,IF(Y103="TIPO III",'BASE DE LIQUIDACION 2025'!$I$6,IF(Y103="TIPO IV",'BASE DE LIQUIDACION 2025'!$I$7,'BASE DE LIQUIDACION 2025'!$I$8))))) -> 96001.196 | AE103: =IF(OR(W103="SOPORTE_TELEFÓNICO",W103="ENVÍO"),0,IF(Y103="TIPO I",'BASE DE LIQUIDACION 2025'!$J$4,IF(Y103="TIPO II",'BASE DE LIQUIDACION 2025'!$J$5,IF(Y103="TIPO III",'BASE DE LIQUIDACION 2025'!$J$6,IF(Y103="TIPO IV",'BASE DE LIQUIDACION 2025'!$J$7,'BASE DE LIQUIDACION 2025'!$J$8))))) -> 57411.974 | AF103: =IF(W103="SOPORTE_TELEFÓNICO",'BASE DE LIQUIDACION 2025'!$L$4,IF(W103="ENVÍO",'BASE DE LIQUIDACION 2025'!$K$4,AD103*AB103+AE103*AC103)) -> 153413.17
A104: MEDELLIN | B104: =VLOOKUP(A104,'CENTRO DE COSTOS'!A:D,4,FALSE) -> JUAN SEBASTIÁN RÍOS CASTRILLÓN | C104: =VLOOKUP(A104,'CENTRO DE COSTOS'!A:D,2,FALSE) -> 0004-0005 | D104: 5001 | E104: 2406708 | F104: 78163 | G104: ORDEN DE CAMBIO | H104: ANTIOQUIA | I104: MEDELLIN | J104: BARRIO RODEO ALTO MEDELLIN 2 | K104: REDEBAN | L104: FO-25-1194480 | M104: 45845.492 | N104: 45861.537 | P104: PUBLICIDAD | Q104: AVISO EXTERIOR | R104: CB UNO A UNO | S104: CB UNO A UNO | T104: EJECUTADO_EXITOSO | U104: EJECUTADO EXITOSO | V104: SE COMUNICA CB SR(A) ISABEL PARA SOLICITAR AVISO EXTERIOR, INDICA QUE DEBIDO A LAS FUERTES LLUVIAS, SE CAYO Y NO TIENE AVISO IDENTIFICACIÓN DE CORRESPONSAL, PARA LOS USUARIOS..11-7 ACTIVIDAD PENDIENTE POR INCONVENIENTES LOGISITICOS DE LA ENTIDAD 11/07/2025 NO SE CUENTA CON AVISO EXTERIOR EN BODEGA. LAS POCAS EXISTENCIAS SE TIENEN SEPARADAS PARA APERTURAS, ACTIVIDAD PENDIENTE SIN PUBLICIDAD. 23/07/2025 INSTALACIÓN DE AVISO EXTERIOR OK CERRAR | W104: VISITA_TÉCNICA | X104: LM0ZZ314 | Y104: TIPO I | Z104: TERRESTRE | AA104: PAREJA ECHAVARRIA JHON DAVID | AB104: 1 | AC104: 1 | AD104: =IF(OR(W104="SOPORTE_TELEFÓNICO",W104="ENVÍO"),0,IF(Y104="TIPO I",'BASE DE LIQUIDACION 2025'!$I$4,IF(Y104="TIPO II",'BASE DE LIQUIDACION 2025'!$I$5,IF(Y104="TIPO III",'BASE DE LIQUIDACION 2025'!$I$6,IF(Y104="TIPO IV",'BASE DE LIQUIDACION 2025'!$I$7,'BASE DE LIQUIDACION 2025'!$I$8))))) -> 96001.196 | AE104: =IF(OR(W104="SOPORTE_TELEFÓNICO",W104="ENVÍO"),0,IF(Y104="TIPO I",'BASE DE LIQUIDACION 2025'!$J$4,IF(Y104="TIPO II",'BASE DE LIQUIDACION 2025'!$J$5,IF(Y104="TIPO III",'BASE DE LIQUIDACION 2025'!$J$6,IF(Y104="TIPO IV",'BASE DE LIQUIDACION 2025'!$J$7,'BASE DE LIQUIDACION 2025'!$J$8))))) -> 57411.974 | AF104: =IF(W104="SOPORTE_TELEFÓNICO",'BASE DE LIQUIDACION 2025'!$L$4,IF(W104="ENVÍO",'BASE DE LIQUIDACION 2025'!$K$4,AD104*AB104+AE104*AC104)) -> 153413.17
A105: MEDELLIN | B105: =VLOOKUP(A105,'CENTRO DE COSTOS'!A:D,4,FALSE) -> JUAN SEBASTIÁN RÍOS CASTRILLÓN | C105: =VLOOKUP(A105,'CENTRO DE COSTOS'!A:D,2,FALSE) -> 0004-0005 | D105: 5001 | E105: 2470543 | F105: 52961 | G105: ORDEN DE CAMBIO | H105: ANTIOQUIA | I105: MEDELLIN | J105: BARRIO FLORESTA MEDELLIN 4 | K105: REDEBAN | L105: FO-25-1254830 | M105: 45857.456 | N105: 45861.615 | P105: PUBLICIDAD | Q105: AVISO EXTERIOR | R105: CB UNO A UNO | S105: CB UNO A UNO | T105: EJECUTADO_EXITOSO | U105: EJECUTADO EXITOSO | V105: SE COMUNICA CB SR(A) LILIANA GRAJALES PARA SOLICITAR INSTALAR AVISO EXTERIOR HIZO UN VENTARRÓN Y SE CAYO SOLO NECESITA INSTALARLO DE NUEVO 0 23/07/2025 INSTALACIÓN DE AVISO EXTERIOR OK CERRAR | W105: VISITA_TÉCNICA | X105: 9C0LZ876 | Y105: TIPO I | Z105: TERRESTRE | AA105: PAREJA ECHAVARRIA JHON DAVID | AB105: 1 | AC105: 1 | AD105: =IF(OR(W105="SOPORTE_TELEFÓNICO",W105="ENVÍO"),0,IF(Y105="TIPO I",'BASE DE LIQUIDACION 2025'!$I$4,IF(Y105="TIPO II",'BASE DE LIQUIDACION 2025'!$I$5,IF(Y105="TIPO III",'BASE DE LIQUIDACION 2025'!$I$6,IF(Y105="TIPO IV",'BASE DE LIQUIDACION 2025'!$I$7,'BASE DE LIQUIDACION 2025'!$I$8))))) -> 96001.196 | AE105: =IF(OR(W105="SOPORTE_TELEFÓNICO",W105="ENVÍO"),0,IF(Y105="TIPO I",'BASE DE LIQUIDACION 2025'!$J$4,IF(Y105="TIPO II",'BASE DE LIQUIDACION 2025'!$J$5,IF(Y105="TIPO III",'BASE DE LIQUIDACION 2025'!$J$6,IF(Y105="TIPO IV",'BASE DE LIQUIDACION 2025'!$J$7,'BASE DE LIQUIDACION 2025'!$J$8))))) -> 57411.974 | AF105: =IF(W105="SOPORTE_TELEFÓNICO",'BASE DE LIQUIDACION 2025'!$L$4,IF(W105="ENVÍO",'BASE DE LIQUIDACION 2025'!$K$4,AD105*AB105+AE105*AC105)) -> 153413.17
A106: MEDELLIN | B106: =VLOOKUP(A106,'CENTRO DE COSTOS'!A:D,4,FALSE) -> JUAN SEBASTIÁN RÍOS CASTRILLÓN | C106: =VLOOKUP(A106,'CENTRO DE COSTOS'!A:D,2,FALSE) -> 0004-0005 | D106: 5088 | E106: 2436262 | F106: 75632 | G106: ORDEN DE CAMBIO | H106: ANTIOQUIA | I106: BELLO | J106: PTM MEDELLIN SUPERMERCADO EL M | K106: REDEBAN | L106: FO-25-1220039 | M106: 45849.7 | N106: 45862.446 | P106: PUBLICIDAD | Q106: AVISO EXTERIOR | R106: AGREGADOR | S106: COMCARD - PTM | T106: EJECUTADO_EXITOSO | U106: EJECUTADO EXITOSO | V106: SE COMUNICA CB SR(A ) YULEDI PARA SOLICITAR AVISO EXTERIOR, EL QUE TENIA LO TUMBO LA LLUVIA Y SE PARTIÓ 0 24/07/2025 SE INSTALA AVISO EXTERIOR CERRAR | W106: VISITA_TÉCNICA | X106: FA00L834 | Y106: TIPO I | Z106: TERRESTRE | AA106: MORENO MEDINA JUAN PABLO | AB106: 1 | AC106: 1 | AD106: =IF(OR(W106="SOPORTE_TELEFÓNICO",W106="ENVÍO"),0,IF(Y106="TIPO I",'BASE DE LIQUIDACION 2025'!$I$4,IF(Y106="TIPO II",'BASE DE LIQUIDACION 2025'!$I$5,IF(Y106="TIPO III",'BASE DE LIQUIDACION 2025'!$I$6,IF(Y106="TIPO IV",'BASE DE LIQUIDACION 2025'!$I$7,'BASE DE LIQUIDACION 2025'!$I$8))))) -> 96001.196 | AE106: =IF(OR(W106="SOPORTE_TELEFÓNICO",W106="ENVÍO"),0,IF(Y106="TIPO I",'BASE DE LIQUIDACION 2025'!$J$4,IF(Y106="TIPO II",'BASE DE LIQUIDACION 2025'!$J$5,IF(Y106="TIPO III",'BASE DE LIQUIDACION 2025'!$J$6,IF(Y106="TIPO IV",'BASE DE LIQUIDACION 2025'!$J$7,'BASE DE LIQUIDACION 2025'!$J$8))))) -> 57411.974 | AF106: =IF(W106="SOPORTE_TELEFÓNICO",'BASE DE LIQUIDACION 2025'!$L$4,IF(W106="ENVÍO",'BASE DE LIQUIDACION 2025'!$K$4,AD106*AB106+AE106*AC106)) -> 153413.17
A107: PEREIRA | B107: =VLOOKUP(A107,'CENTRO DE COSTOS'!A:D,4,FALSE) -> DIEGO FERNANDO HENAO CARDONA | C107: =VLOOKUP(A107,'CENTRO DE COSTOS'!A:D,2,FALSE) -> 0004-0002 | D107: 66001 | E107: 2493172 | F107: 12549 | G107: ORDEN DE CAMBIO | H107: RISARALDA | I107: PEREIRA | J107: BARRIO CENTENAROIO PEREIRA | K107: REDEBAN | L107: FO-25-1274770 | M107: 45861.648 | N107: 45862.506 | P107: PUBLICIDAD | Q107: AVISO EXTERIOR | R107: CB UNO A UNO | S107: CB UNO A UNO | T107: EJECUTADO_EXITOSO | U107: EJECUTADO EXITOSO | V107: SE COMUNICA CB SR(A) DIEGO PARA SOLICITAR AVISO EXTERIOR POR PERDIDA 0 24/07/2025 SE VISITA COMERCIO SE REALIZA INSTALACIÓN DE LETRERO EXTERIOR CERRAR | W107: VISITA_TÉCNICA | X107: JAAEZ272 | Y107: TIPO I | Z107: TERRESTRE | AA107: LOAIZA LOPEZ JHON FREDDY | AB107: 1 | AC107: 1 | AD107: =IF(OR(W107="SOPORTE_TELEFÓNICO",W107="ENVÍO"),0,IF(Y107="TIPO I",'BASE DE LIQUIDACION 2025'!$I$4,IF(Y107="TIPO II",'BASE DE LIQUIDACION 2025'!$I$5,IF(Y107="TIPO III",'BASE DE LIQUIDACION 2025'!$I$6,IF(Y107="TIPO IV",'BASE DE LIQUIDACION 2025'!$I$7,'BASE DE LIQUIDACION 2025'!$I$8))))) -> 96001.196 | AE107: =IF(OR(W107="SOPORTE_TELEFÓNICO",W107="ENVÍO"),0,IF(Y107="TIPO I",'BASE DE LIQUIDACION 2025'!$J$4,IF(Y107="TIPO II",'BASE DE LIQUIDACION 2025'!$J$5,IF(Y107="TIPO III",'BASE DE LIQUIDACION 2025'!$J$6,IF(Y107="TIPO IV",'BASE DE LIQUIDACION 2025'!$J$7,'BASE DE LIQUIDACION 2025'!$J$8))))) -> 57411.974 | AF107: =IF(W107="SOPORTE_TELEFÓNICO",'BASE DE LIQUIDACION 2025'!$L$4,IF(W107="ENVÍO",'BASE DE LIQUIDACION 2025'!$K$4,AD107*AB107+AE107*AC107)) -> 153413.17
A108: MONTERIA | B108: =VLOOKUP(A108,'CENTRO DE COSTOS'!A:D,4,FALSE) -> JOSE MAURICIO HERNANDEZ ROJAS | C108: =VLOOKUP(A108,'CENTRO DE COSTOS'!A:D,2,FALSE) -> 0004-0001 | D108: 23660 | E108: 2482395 | F108: 57695 | G108: ORDEN DE CAMBIO | H108: CORDOBA | I108: SAHAGUN | J108: BARRIO CORREGIMIENTO COLOMBOY | K108: REDEBAN | L108: FO-25-1266474 | M108: 45860.41 | N108: 45862.528 | P108: PUBLICIDAD | Q108: AVISO EXTERIOR | R108: CB UNO A UNO | S108: CB UNO A UNO | T108: EJECUTADO_EXITOSO | U108: EJECUTADO EXITOSO | V108: SE COMUNICA CB SR(A)ALEXANDER PARA SOLICITAR AVISO EXTERIOR PORQUE UN VENDAVAL SE LO LLEVO Y ESTE MOMENTO SE ENCUENTRA SIN ESTE 0 24/07/2025 SE REALIZA VISITA TÉCNICA PARA INSTALACIÓN DE AVISO EXTERIOR, SE INSTALA AVISO SIN NOVEDAD. CERRAR | W108: VISITA_TÉCNICA | X108: 9A0CZ903 | Y108: TIPO II | Z108: TERRESTRE | AA108: CASSIANI PEREZ RAUL RAMIRO | AB108: 1 | AC108: 1 | AD108: =IF(OR(W108="SOPORTE_TELEFÓNICO",W108="ENVÍO"),0,IF(Y108="TIPO I",'BASE DE LIQUIDACION 2025'!$I$4,IF(Y108="TIPO II",'BASE DE LIQUIDACION 2025'!$I$5,IF(Y108="TIPO III",'BASE DE LIQUIDACION 2025'!$I$6,IF(Y108="TIPO IV",'BASE DE LIQUIDACION 2025'!$I$7,'BASE DE LIQUIDACION 2025'!$I$8))))) -> 232858.6 | AE108: =IF(OR(W108="SOPORTE_TELEFÓNICO",W108="ENVÍO"),0,IF(Y108="TIPO I",'BASE DE LIQUIDACION 2025'!$J$4,IF(Y108="TIPO II",'BASE DE LIQUIDACION 2025'!$J$5,IF(Y108="TIPO III",'BASE DE LIQUIDACION 2025'!$J$6,IF(Y108="TIPO IV",'BASE DE LIQUIDACION 2025'!$J$7,'BASE DE LIQUIDACION 2025'!$J$8))))) -> 110808.28 | AF108: =IF(W108="SOPORTE_TELEFÓNICO",'BASE DE LIQUIDACION 2025'!$L$4,IF(W108="ENVÍO",'BASE DE LIQUIDACION 2025'!$K$4,AD108*AB108+AE108*AC108)) -> 343666.88
... A113: MEDELLIN | B113: =VLOOKUP(A113,'CENTRO DE COSTOS'!A:D,4,FALSE) -> JUAN SEBASTIÁN RÍOS CASTRILLÓN | C113: =VLOOKUP(A113,'CENTRO DE COSTOS'!A:D,2,FALSE) -> 0004-0005 | D113: 5001 | E113: 2473139 | F113: 33405 | G113: ORDEN DE CAMBIO | H113: ANTIOQUIA | I113: MEDELLIN | J113: BARRIO LLANADITAS MEDELLIN | K113: REDEBAN | L113: FO-25-1259500 | M113: 45859.394 | N113: 45863.669 | P113: PUBLICIDAD | Q113: AVISO EXTERIOR | R113: CB UNO A UNO | S113: CB UNO A UNO | T113: EJECUTADO_EXITOSO | U113: EJECUTADO EXITOSO | V113: SE COMUNICA CB SR(A) BLADIMIR, PARA SOLICITAR AVISO EXTERIOR YA QUE POR VIENTO FUERTE SE ROMPIO 0 25/07/2025 INSTALACIÓN DE AVISO EXTERIOR OK CERRAR | W113: VISITA_TÉCNICA | X113: 17ZZZ289 | Y113: TIPO I | Z113: TERRESTRE | AA113: PAREJA ECHAVARRIA JHON DAVID | AB113: 1 | AC113: 1 | AD113: =IF(OR(W113="SOPORTE_TELEFÓNICO",W113="ENVÍO"),0,IF(Y113="TIPO I",'BASE DE LIQUIDACION 2025'!$I$4,IF(Y113="TIPO II",'BASE DE LIQUIDACION 2025'!$I$5,IF(Y113="TIPO III",'BASE DE LIQUIDACION 2025'!$I$6,IF(Y113="TIPO IV",'BASE DE LIQUIDACION 2025'!$I$7,'BASE DE LIQUIDACION 2025'!$I$8))))) -> 96001.196 | AE113: =IF(OR(W113="SOPORTE_TELEFÓNICO",W113="ENVÍO"),0,IF(Y113="TIPO I",'BASE DE LIQUIDACION 2025'!$J$4,IF(Y113="TIPO II",'BASE DE LIQUIDACION 2025'!$J$5,IF(Y113="TIPO III",'BASE DE LIQUIDACION 2025'!$J$6,IF(Y113="TIPO IV",'BASE DE LIQUIDACION 2025'!$J$7,'BASE DE LIQUIDACION 2025'!$J$8))))) -> 57411.974 | AF113: =IF(W113="SOPORTE_TELEFÓNICO",'BASE DE LIQUIDACION 2025'!$L$4,IF(W113="ENVÍO",'BASE DE LIQUIDACION 2025'!$K$4,AD113*AB113+AE113*AC113)) -> 153413.17
A114: VILLAVICENCIO | B114: =VLOOKUP(A114,'CENTRO DE COSTOS'!A:D,4,FALSE) -> KEVIN ALEXIS CORZO BUSTOS | C114: =VLOOKUP(A114,'CENTRO DE COSTOS'!A:D,2,FALSE) -> 0004-0007 | D114: 50325 | E114: EMAIL | F114: 77681 | G114: ORDEN DE CAMBIO | H114: META | I114: MAPIRIPAN | J114: BARRIO CENTRO MAPIRIPAN 4 | K114: REDEBAN | L114: FO-25-1225380 | M114: 45852.333 | N114: 45864.375 | P114: PUBLICIDAD | Q114: AVISO EXTERIOR | R114: CB UNO A UNO | S114: CB UNO A UNO | T114: EJECUTADO_EXITOSO | U114: EJECUTADO EXITOSO | V114: SE COMUNICA CB SR(A) ZULEIMA PARA SOLICITAR BASE DEL DATAFONO YA QUE LA TIENE ESTA DESPEGADA Y SE HA CAIDO EL DATAFONO 18/07/2025 POR DISPONIBILIDAD DE VUELO TIQUETES SEGÚN DISPONIBILIDAD PARA EL 21/07/2025 19/07/2025 SE REALIZA CONTACTO TELEFÓNICO CON LA SEÑORA ZULEIMA 3148670122 SE LE INFORMA QUE POR DISPONIBILIDAD DE AEROLÍNEA VISITA TÉCNICA QUEDA PROGRAMADA PARA EL DÍA 22 DE JULIO 22/07/2025 DEBIDO A MAL TIEMPO SE CANCELÓ EL VUELO, A LA ESPERA DE LA PROGRAMACIÓN. 23/07/2025 SE REALIZA CONTACTO TELEFÓNICO CON LA SEÑORA ZULEIMA 3148670122 SE LE INFORMA QUE POR MAL TIEMPO CLIMÁTICO SE RE PROGRAMA VISITA TÉCNICA PARA EL DÍA VIERNES 25 25/07/2025 SE INSTALA AVISO EXTERIOR OK SIN NOVEDADES CERRAR | W114: VISITA_TÉCNICA | X114: 10LZZ952 | Y114: TIPO IV ESPECIAL | Z114: AEREO | AA114: CASTRILLON URREA LONDIER LEANDRO | AB114: 1 | AC114: 1 | AD114: =IF(OR(W114="SOPORTE_TELEFÓNICO",W114="ENVÍO"),0,IF(Y114="TIPO I",'BASE DE LIQUIDACION 2025'!$I$4,IF(Y114="TIPO II",'BASE DE LIQUIDACION 2025'!$I$5,IF(Y114="TIPO III",'BASE DE LIQUIDACION 2025'!$I$6,IF(Y114="TIPO IV",'BASE DE LIQUIDACION 2025'!$I$7,'BASE DE LIQUIDACION 2025'!$I$8))))) -> 548633.63 | AE114: =IF(OR(W114="SOPORTE_TELEFÓNICO",W114="ENVÍO"),0,IF(Y114="TIPO I",'BASE DE LIQUIDACION 2025'!$J$4,IF(Y114="TIPO II",'BASE DE LIQUIDACION 2025'!$J$5,IF(Y114="TIPO III",'BASE DE LIQUIDACION 2025'!$J$6,IF(Y114="TIPO IV",'BASE DE LIQUIDACION 2025'!$J$7,'BASE DE LIQUIDACION 2025'!$J$8))))) -> 110808.28 | AF114: =IF(W114="SOPORTE_TELEFÓNICO",'BASE DE LIQUIDACION 2025'!$L$4,IF(W114="ENVÍO",'BASE DE LIQUIDACION 2025'!$K$4,AD114*AB114+AE114*AC114)) -> 659441.91
A115: BARRANQUILLA | B115: =VLOOKUP(A115,'CENTRO DE COSTOS'!A:D,4,FALSE) -> JOSE MAURICIO HERNANDEZ ROJAS | C115: =VLOOKUP(A115,'CENTRO DE COSTOS'!A:D,2,FALSE) -> 0004-0001 | D115: 8137 | E115: 2475694 | F115: 25807 | G115: ORDEN DE CAMBIO | H115: ATLANTICO | I115: CAMPO DE LA CRUZ | J115: DISTRICOL FERROMATERIALES NICO | K115: REDEBAN | L115: FO-25-1261390 | M115: 45859.512 | N115: 45864.377 | P115: PUBLICIDAD | Q115: AVISO EXTERIOR | R115: AGREGADOR | S115: DISTRICOL | T115: EJECUTADO_EXITOSO | U115: EJECUTADO EXITOSO | V115: SE COMUNICA CB SR(A) MARIA PARA SOLICITAR AVISO EXTERIOR POR PERDIDA 0 25/07/2025 SE INSTALAN AVISO EXTERIOR, EL QUE ESTABA SE LO ROBARON CERRAR | W115: VISITA_TÉCNICA | X115: 0 | Y115: TIPO II | Z115: TERRESTRE | AA115: DE AVILA SIADES ALBERTO ENRIQUE | AB115: 1 | AC115: 1 | AD115: =IF(OR(W115="SOPORTE_TELEFÓNICO",W115="ENVÍO"),0,IF(Y115="TIPO I",'BASE DE LIQUIDACION 2025'!$I$4,IF(Y115="TIPO II",'BASE DE LIQUIDACION 2025'!$I$5,IF(Y115="TIPO III",'BASE DE LIQUIDACION 2025'!$I$6,IF(Y115="TIPO IV",'BASE DE LIQUIDACION 2025'!$I$7,'BASE DE LIQUIDACION 2025'!$I$8))))) -> 232858.6 | AE115: =IF(OR(W115="SOPORTE_TELEFÓNICO",W115="ENVÍO"),0,IF(Y115="TIPO I",'BASE DE LIQUIDACION 2025'!$J$4,IF(Y115="TIPO II",'BASE DE LIQUIDACION 2025'!$J$5,IF(Y115="TIPO III",'BASE DE LIQUIDACION 2025'!$J$6,IF(Y115="TIPO IV",'BASE DE LIQUIDACION 2025'!$J$7,'BASE DE LIQUIDACION 2025'!$J$8))))) -> 110808.28 | AF115: =IF(W115="SOPORTE_TELEFÓNICO",'BASE DE LIQUIDACION 2025'!$L$4,IF(W115="ENVÍO",'BASE DE LIQUIDACION 2025'!$K$4,AD115*AB115+AE115*AC115)) -> 343666.88
A116: CALI | B116: =VLOOKUP(A116,'CENTRO DE COSTOS'!A:D,4,FALSE) -> DIEGO FERNANDO HENAO CARDONA | C116: =VLOOKUP(A116,'CENTRO DE COSTOS'!A:D,2,FALSE) -> 0004-0003 | D116: 19001 | E116: 2491360 | F116: 66792 | G116: ORDEN DE CAMBIO | H116: CAUCA | I116: POPAYAN | J116: BARRIO SAN EDUARDO POPAYAN 3 | K116: REDEBAN | L116: FO-25-1273127 | M116: 45861.503 | N116: 45864.437 | P116: PUBLICIDAD | Q116: AVISO EXTERIOR | R116: CB UNO A UNO | S116: CB UNO A UNO | T116: EJECUTADO_EXITOSO | U116: EJECUTADO EXITOSO | V116: SE COMUNICA CB SR(A) GUILLERMO PARA SOLICITAR AVISO EXTERIOR, EL QUE TENIA EL VIENTO LO TUMBÓ Y SE PARTIÓ 0 26/07/2025 SE INGRESA SE INSTALA NUEVO AVISO EXTERIOR OK CERRAR | W116: VISITA_TÉCNICA | X116: 0 | Y116: TIPO III | Z116: TERRESTRE | AA116: GIMBUEL LASSO LUIS GERMAN | AB116: 1 | AC116: 1 | AD116: =IF(OR(W116="SOPORTE_TELEFÓNICO",W116="ENVÍO"),0,IF(Y116="TIPO I",'BASE DE LIQUIDACION 2025'!$I$4,IF(Y116="TIPO II",'BASE DE LIQUIDACION 2025'!$I$5,IF(Y116="TIPO III",'BASE DE LIQUIDACION 2025'!$I$6,IF(Y116="TIPO IV",'BASE DE LIQUIDACION 2025'!$I$7,'BASE DE LIQUIDACION 2025'!$I$8))))) -> 344774.57 | AE116: =IF(OR(W116="SOPORTE_TELEFÓNICO",W116="ENVÍO"),0,IF(Y116="TIPO I",'BASE DE LIQUIDACION 2025'!$J$4,IF(Y116="TIPO II",'BASE DE LIQUIDACION 2025'!$J$5,IF(Y116="TIPO III",'BASE DE LIQUIDACION 2025'!$J$6,IF(Y116="TIPO IV",'BASE DE LIQUIDACION 2025'!$J$7,'BASE DE LIQUIDACION 2025'!$J$8))))) -> 110808.28 | AF116: =IF(W116="SOPORTE_TELEFÓNICO",'BASE DE LIQUIDACION 2025'!$L$4,IF(W116="ENVÍO",'BASE DE LIQUIDACION 2025'!$K$4,AD116*AB116+AE116*AC116)) -> 455582.84
A117: IBAGUE | B117: =VLOOKUP(A117,'CENTRO DE COSTOS'!A:D,4,FALSE) -> KEVIN ALEXIS CORZO BUSTOS | C117: =VLOOKUP(A117,'CENTRO DE COSTOS'!A:D,2,FALSE) -> 0004-0007 | D117: 73001 | E117: 2473555 | F117: 80155 | G117: ORDEN DE CAMBIO | H117: TOLIMA | I117: IBAGUE | J117: BARRIO JARDIN ALTOLSURE IBAGUE | K117: REDEBAN | L117: FO-25-1259723 | M117: 45859.408 | N117: 45864.491 | P117: PUBLICIDAD | Q117: AVISO EXTERIOR | R117: CB UNO A UNO | S117: CB UNO A UNO | T117: EJECUTADO_EXITOSO | U117: EJECUTADO EXITOSO | V117: SE COMUNICA CB SR(A) SOLICITA AVISO EXTERIOR YA QUE EL QUE TENIA SE LO ROBARON EL DÍA DE AYER 20/07/25 EN LA NOCHE 22/07/2025 POR NOVEDAD CON EL PARO NO HAN LLEGADO LOS AVISOS EXTERIORES QUE SE ENVIARON PARA ABASTECER LA ZONA DE IBAGUE DESDE EL 14/07/2025 26/07/2025 SE INSTALA AVISO EXTERIOR SIN PROBLEMA CERRAR | W117: VISITA_TÉCNICA | X117: 0 | Y117: TIPO I | Z117: TERRESTRE | AA117: VARGAS HERRERA JHON JAIRO | AB117: 1 | AC117: 1 | AD117: =IF(OR(W117="SOPORTE_TELEFÓNICO",W117="ENVÍO"),0,IF(Y117="TIPO I",'BASE DE LIQUIDACION 2025'!$I$4,IF(Y117="TIPO II",'BASE DE LIQUIDACION 2025'!$I$5,IF(Y117="TIPO III",'BASE DE LIQUIDACION 2025'!$I$6,IF(Y117="TIPO IV",'BASE DE LIQUIDACION 2025'!$I$7,'BASE DE LIQUIDACION 2025'!$I$8))))) -> 96001.196 | AE117: =IF(OR(W117="SOPORTE_TELEFÓNICO",W117="ENVÍO"),0,IF(Y117="TIPO I",'BASE DE LIQUIDACION 2025'!$J$4,IF(Y117="TIPO II",'BASE DE LIQUIDACION 2025'!$J$5,IF(Y117="TIPO III",'BASE DE LIQUIDACION 2025'!$J$6,IF(Y117="TIPO IV",'BASE DE LIQUIDACION 2025'!$J$7,'BASE DE LIQUIDACION 2025'!$J$8))))) -> 57411.974 | AF117: =IF(W117="SOPORTE_TELEFÓNICO",'BASE DE LIQUIDACION 2025'!$L$4,IF(W117="ENVÍO",'BASE DE LIQUIDACION 2025'!$K$4,AD117*AB117+AE117*AC117)) -> 153413.17
A118: SINCELEJO | B118: =VLOOKUP(A118,'CENTRO DE COSTOS'!A:D,4,FALSE) -> JOSE MAURICIO HERNANDEZ ROJAS | C118: =VLOOKUP(A118,'CENTRO DE COSTOS'!A:D,2,FALSE) -> 0004-0001 | D118: 70001 | E118: 2489845 | F118: 47054 | G118: ORDEN DE CAMBIO | H118: SUCRE | I118: SINCELEJO | J118: BARRIO CENTRO SINCELEJO 14 | K118: REDEBAN | L118: FO-25-1271659 | M118: 45861.422 | N118: 45864.625 | P118: PUBLICIDAD | Q118: AVISO EXTERIOR | R118: CB UNO A UNO | S118: CB UNO A UNO | T118: EJECUTADO_EXITOSO | U118: EJECUTADO EXITOSO | V118: SE COMUNICA CB SR(A) LAURA, REPORTA QUE LE ROBARON EL AVISO EXTERIOR, SOLICITA OTRO 0 26/07/2025 SE VISITA COMERCIO, SE HACE INSTALACIÓN DE AVISO EXTERIOR YA QUE SE LO ROBARON. CERRAR | W118: VISITA_TÉCNICA | X118: 0 | Y118: TIPO I | Z118: TERRESTRE | AA118: CACERES HERNANDEZ ANDRES | AB118: 1 | AC118: 1 | AD118: =IF(OR(W118="SOPORTE_TELEFÓNICO",W118="ENVÍO"),0,IF(Y118="TIPO I",'BASE DE LIQUIDACION 2025'!$I$4,IF(Y118="TIPO II",'BASE DE LIQUIDACION 2025'!$I$5,IF(Y118="TIPO III",'BASE DE LIQUIDACION 2025'!$I$6,IF(Y118="TIPO IV",'BASE DE LIQUIDACION 2025'!$I$7,'BASE DE LIQUIDACION 2025'!$I$8))))) -> 96001.196 | AE118: =IF(OR(W118="SOPORTE_TELEFÓNICO",W118="ENVÍO"),0,IF(Y118="TIPO I",'BASE DE LIQUIDACION 2025'!$J$4,IF(Y118="TIPO II",'BASE DE LIQUIDACION 2025'!$J$5,IF(Y118="TIPO III",'BASE DE LIQUIDACION 2025'!$J$6,IF(Y118="TIPO IV",'BASE DE LIQUIDACION 2025'!$J$7,'BASE DE LIQUIDACION 2025'!$J$8))))) -> 57411.974 | AF118: =IF(W118="SOPORTE_TELEFÓNICO",'BASE DE LIQUIDACION 2025'!$L$4,IF(W118="ENVÍO",'BASE DE LIQUIDACION 2025'!$K$4,AD118*AB118+AE118*AC118)) -> 153413.17
A119: MEDELLIN | B119: =VLOOKUP(A119,'CENTRO DE COSTOS'!A:D,4,FALSE) -> JUAN SEBASTIÁN RÍOS CASTRILLÓN | C119: =VLOOKUP(A119,'CENTRO DE COSTOS'!A:D,2,FALSE) -> 0004-0005 | D119: 5001 | E119: 2497566 | F119: 77050 | G119: ORDEN DE CAMBIO | H119: ANTIOQUIA | I119: MEDELLIN | J119: BARRIO EL SALVADOR MEDELLIN 5 | K119: REDEBAN | L119: FO-25-1278974 | M119: 45862.463 | N119: 45866.488 | P119: PUBLICIDAD | Q119: AVISO EXTERIOR | R119: CB UNO A UNO | S119: CB UNO A UNO | T119: EJECUTADO_EXITOSO | U119: EJECUTADO EXITOSO | V119: SE COMUNICA CB SR(A)LILIANA PARA SOLICITAR POR VAFOR SOLICTAR POR FAVOR UN AVISO EXTERIOR INDICA QUE EL TENIA SE LE DESPEGO Y SE LA DAÑO COMPLETAMENTE 0 28/07/2025 INSTALACIÓN DE AVISO EXTERIOR OK CERRAR | W119: VISITA_TÉCNICA | X119: 0 | Y119: TIPO I | Z119: TERRESTRE | AA119: PAREJA ECHAVARRIA JHON DAVID | AB119: 1 | AC119: 1 | AD119: =IF(OR(W119="SOPORTE_TELEFÓNICO",W119="ENVÍO"),0,IF(Y119="TIPO I",'BASE DE LIQUIDACION 2025'!$I$4,IF(Y119="TIPO II",'BASE DE LIQUIDACION 2025'!$I$5,IF(Y119="TIPO III",'BASE DE LIQUIDACION 2025'!$I$6,IF(Y119="TIPO IV",'BASE DE LIQUIDACION 2025'!$I$7,'BASE DE LIQUIDACION 2025'!$I$8))))) -> 96001.196 | AE119: =IF(OR(W119="SOPORTE_TELEFÓNICO",W119="ENVÍO"),0,IF(Y119="TIPO I",'BASE DE LIQUIDACION 2025'!$J$4,IF(Y119="TIPO II",'BASE DE LIQUIDACION 2025'!$J$5,IF(Y119="TIPO III",'BASE DE LIQUIDACION 2025'!$J$6,IF(Y119="TIPO IV",'BASE DE LIQUIDACION 2025'!$J$7,'BASE DE LIQUIDACION 2025'!$J$8))))) -> 57411.974 | AF119: =IF(W119="SOPORTE_TELEFÓNICO",'BASE DE LIQUIDACION 2025'!$L$4,IF(W119="ENVÍO",'BASE DE LIQUIDACION 2025'!$K$4,AD119*AB119+AE119*AC119)) -> 153413.17
A120: MEDELLIN | B120: =VLOOKUP(A120,'CENTRO DE COSTOS'!A:D,4,FALSE) -> JUAN SEBASTIÁN RÍOS CASTRILLÓN | C120: =VLOOKUP(A120,'CENTRO DE COSTOS'!A:D,2,FALSE) -> 0004-0005 | D120: 5001 | E120: 2496457 | F120: 70977 | G120: ORDEN DE CAMBIO | H120: ANTIOQUIA | I120: MEDELLIN | J120: BARRIO 12 DE OCTUBRE MEDELLIN | K120: REDEBAN | L120: FO-25-1277993 | M120: 45862.394 | N120: 45866.493 | P120: PUBLICIDAD | Q120: AVISO EXTERIOR | R120: CB UNO A UNO | S120: CB UNO A UNO | T120: EJECUTADO_EXITOSO | U120: EJECUTADO EXITOSO | V120: SE COMUNICA CB SR(A) DIANA PARA SOLICITAR AVISO EXTERIOR POR QUE SE LE DAÑO 0 28/07/2025 SE INSTALO AVISO EXTERIOR CERRAR | W120: VISITA_TÉCNICA | X120: 0 | Y120: TIPO I | Z120: TERRESTRE | AA120: MORENO MEDINA JUAN PABLO | AB120: 1 | AC120: 1 | AD120: =IF(OR(W120="SOPORTE_TELEFÓNICO",W120="ENVÍO"),0,IF(Y120="TIPO I",'BASE DE LIQUIDACION 2025'!$I$4,IF(Y120="TIPO II",'BASE DE LIQUIDACION 2025'!$I$5,IF(Y120="TIPO III",'BASE DE LIQUIDACION 2025'!$I$6,IF(Y120="TIPO IV",'BASE DE LIQUIDACION 2025'!$I$7,'BASE DE LIQUIDACION 2025'!$I$8))))) -> 96001.196 | AE120: =IF(OR(W120="SOPORTE_TELEFÓNICO",W120="ENVÍO"),0,IF(Y120="TIPO I",'BASE DE LIQUIDACION 2025'!$J$4,IF(Y120="TIPO II",'BASE DE LIQUIDACION 2025'!$J$5,IF(Y120="TIPO III",'BASE DE LIQUIDACION 2025'!$J$6,IF(Y120="TIPO IV",'BASE DE LIQUIDACION 2025'!$J$7,'BASE DE LIQUIDACION 2025'!$J$8))))) -> 57411.974 | AF120: =IF(W120="SOPORTE_TELEFÓNICO",'BASE DE LIQUIDACION 2025'!$L$4,IF(W120="ENVÍO",'BASE DE LIQUIDACION 2025'!$K$4,AD120*AB120+AE120*AC120)) -> 153413.17
A121: MEDELLIN | B121: =VLOOKUP(A121,'CENTRO DE COSTOS'!A:D,4,FALSE) -> JUAN SEBASTIÁN RÍOS CASTRILLÓN | C121: =VLOOKUP(A121,'CENTRO DE COSTOS'!A:D,2,FALSE) -> 0004-0005 | D121: 5001 | E121: 2498403 | F121: 50277 | G121: ORDEN DE CAMBIO | H121: ANTIOQUIA | I121: MEDELLIN | J121: BARRIO PLAZA DE FLORES MEDELLI | K121: REDEBAN | L121: FO-25-1279496 | M121: 45862.502 | N121: 45866.507 | P121: PUBLICIDAD | Q121: AVISO EXTERIOR | R121: CB UNO A UNO | S121: CB UNO A UNO | T121: EJECUTADO_EXITOSO | U121: EJECUTADO EXITOSO | V121: SE COMUNICA CB SR(A) KATALINA PARA SOLICITAR AVISO EXTERIOR POR ROBO 0 28/07/2025 INSTALACIÓN DE AVISO EXTERIOR OK CERRAR | W121: VISITA_TÉCNICA | X121: 0 | Y121: TIPO I | Z121: TERRESTRE | AA121: PAREJA ECHAVARRIA JHON DAVID | AB121: 1 | AC121: 1 | AD121: =IF(OR(W121="SOPORTE_TELEFÓNICO",W121="ENVÍO"),0,IF(Y121="TIPO I",'BASE DE LIQUIDACION 2025'!$I$4,IF(Y121="TIPO II",'BASE DE LIQUIDACION 2025'!$I$5,IF(Y121="TIPO III",'BASE DE LIQUIDACION 2025'!$I$6,IF(Y121="TIPO IV",'BASE DE LIQUIDACION 2025'!$I$7,'BASE DE LIQUIDACION 2025'!$I$8))))) -> 96001.196 | AE121: =IF(OR(W121="SOPORTE_TELEFÓNICO",W121="ENVÍO"),0,IF(Y121="TIPO I",'BASE DE LIQUIDACION 2025'!$J$4,IF(Y121="TIPO II",'BASE DE LIQUIDACION 2025'!$J$5,IF(Y121="TIPO III",'BASE DE LIQUIDACION 2025'!$J$6,IF(Y121="TIPO IV",'BASE DE LIQUIDACION 2025'!$J$7,'BASE DE LIQUIDACION 2025'!$J$8))))) -> 57411.974 | AF121: =IF(W121="SOPORTE_TELEFÓNICO",'BASE DE LIQUIDACION 2025'!$L$4,IF(W121="ENVÍO",'BASE DE LIQUIDACION 2025'!$K$4,AD121*AB121+AE121*AC121)) -> 153413.17
A122: BOGOTA | B122: =VLOOKUP(A122,'CENTRO DE COSTOS'!A:D,4,FALSE) -> WILLIAM ASDRUBAL ROZO ROZO | C122: =VLOOKUP(A122,'CENTRO DE COSTOS'!A:D,2,FALSE) -> 0004-0004 | D122: 11001 | E122: 2505994 | F122: 80429 | G122: ORDEN DE CAMBIO | H122: CUNDINAMARCA | I122: BOGOTA | J122: BARRIO VISION DE COLOMBIA BOGOTA 1 | K122: REDEBAN | L122: FO-25-1286651 | M122: 45863.634 | N122: 45866.635 | P122: PUBLICIDAD | Q122: AVISO EXTERIOR | R122: CB UNO A UNO | S122: CB UNO A UNO | T122: EJECUTADO_EXITOSO | U122: EJECUTADO EXITOSO | V122: SE COMUNICA CB SR(A) NATALIA PARA SOLICITAR POR FAVOR LE COLABOREN INSTALANDO EL AVISO EXTERIOR NUEVAMENTE, INDICA QUE SE SOLTÓ 0 28/07/2025 SE REALIZA LA INSTALACIÓN DE AVISO EXTERIOR SIN NOVEDAD CERRAR | W122: VISITA_TÉCNICA | X122: 0 | Y122: TIPO I | Z122: TERRESTRE | AA122: ORTIZ MARTINEZ STIVEN | AB122: 1 | AC122: 1 | AD122: =IF(OR(W122="SOPORTE_TELEFÓNICO",W122="ENVÍO"),0,IF(Y122="TIPO I",'BASE DE LIQUIDACION 2025'!$I$4,IF(Y122="TIPO II",'BASE DE LIQUIDACION 2025'!$I$5,IF(Y122="TIPO III",'BASE DE LIQUIDACION 2025'!$I$6,IF(Y122="TIPO IV",'BASE DE LIQUIDACION 2025'!$I$7,'BASE DE LIQUIDACION 2025'!$I$8))))) -> 96001.196 | AE122: =IF(OR(W122="SOPORTE_TELEFÓNICO",W122="ENVÍO"),0,IF(Y122="TIPO I",'BASE DE LIQUIDACION 2025'!$J$4,IF(Y122="TIPO II",'BASE DE LIQUIDACION 2025'!$J$5,IF(Y122="TIPO III",'BASE DE LIQUIDACION 2025'!$J$6,IF(Y122="TIPO IV",'BASE DE LIQUIDACION 2025'!$J$7,'BASE DE LIQUIDACION 2025'!$J$8))))) -> 57411.974 | AF122: =IF(W122="SOPORTE_TELEFÓNICO",'BASE DE LIQUIDACION 2025'!$L$4,IF(W122="ENVÍO",'BASE DE LIQUIDACION 2025'!$K$4,AD122*AB122+AE122*AC122)) -> 153413.17
A123: BUCARAMANGA | B123: =VLOOKUP(A123,'CENTRO DE COSTOS'!A:D,4,FALSE) -> MIGUEL JULIÁN HERNÁNDEZ GUARÍN | C123: =VLOOKUP(A123,'CENTRO DE COSTOS'!A:D,2,FALSE) -> 0004-0008 | D123: 68689 | E123: 2508678 | F123: 10668 | G123: ORDEN DE CAMBIO | H123: SANTANDER | I123: SAN VICENTE DE CHUCURI | J123: SAN VICENTE DE CHUCURI II - SA | K123: REDEBAN | L123: FO-25-1291543 | M123: 45866.333 | N123: 45866.643 | P123: PUBLICIDAD | Q123: AVISO EXTERIOR | R123: CB UNO A UNO | S123: CB UNO A UNO | T123: EJECUTADO_EXITOSO | U123: EJECUTADO EXITOSO | V123: SE COMUNICA CB SR(A) SAMUEL PARA SOLICITAR AVISO EXTERIOR, INDICA QUE UN VIENTO FUERTE LE CAYO EL LETRERO Y SE PARTIÓ, QUEDANDO INSERVIBLE, GRACIAS 0 28/07/2025 SE REALIZA INSTALACIÓN DE AVISO EXTERIOR SE COLOCA DONDE EL CLIENTE LO SOLICITO CERRAR | W123: VISITA_TÉCNICA | X123: 0 | Y123: TIPO III | Z123: TERRESTRE | AA123: GONZALEZ ESTUPIÑAN YEISON WALTER ANTONIO | AB123: 1 | AC123: 1 | AD123: =IF(OR(W123="SOPORTE_TELEFÓNICO",W123="ENVÍO"),0,IF(Y123="TIPO I",'BASE DE LIQUIDACION 2025'!$I$4,IF(Y123="TIPO II",'BASE DE LIQUIDACION 2025'!$I$5,IF(Y123="TIPO III",'BASE DE LIQUIDACION 2025'!$I$6,IF(Y123="TIPO IV",'BASE DE LIQUIDACION 2025'!$I$7,'BASE DE LIQUIDACION 2025'!$I$8))))) -> 344774.57 | AE123: =IF(OR(W123="SOPORTE_TELEFÓNICO",W123="ENVÍO"),0,IF(Y123="TIPO I",'BASE DE LIQUIDACION 2025'!$J$4,IF(Y123="TIPO II",'BASE DE LIQUIDACION 2025'!$J$5,IF(Y123="TIPO III",'BASE DE LIQUIDACION 2025'!$J$6,IF(Y123="TIPO IV",'BASE DE LIQUIDACION 2025'!$J$7,'BASE DE LIQUIDACION 2025'!$J$8))))) -> 110808.28 | AF123: =IF(W123="SOPORTE_TELEFÓNICO",'BASE DE LIQUIDACION 2025'!$L$4,IF(W123="ENVÍO",'BASE DE LIQUIDACION 2025'!$K$4,AD123*AB123+AE123*AC123)) -> 455582.84
A124: BARRANQUILLA | B124: =VLOOKUP(A124,'CENTRO DE COSTOS'!A:D,4,FALSE) -> JOSE MAURICIO HERNANDEZ ROJAS | C124: =VLOOKUP(A124,'CENTRO DE COSTOS'!A:D,2,FALSE) -> 0004-0001 | D124: 8436 | E124: 2509548 | F124: 15053 | G124: ORDEN DE CAMBIO | H124: ATLANTICO | I124: MANATI | J124: MANATI III ATLANTICO | K124: REDEBAN | L124: FO-25-1292381 | M124: 45866.333 | N124: 45866.665 | P124: PUBLICIDAD | Q124: AVISO EXTERIOR | R124: CB UNO A UNO | S124: CB UNO A UNO | T124: EJECUTADO_EXITOSO | U124: EJECUTADO EXITOSO | V124: E: REDEBAN DESCRIPCIÓN: SE COMUNICA CB SR(A) MONICA PARA SOLICITAR AVISO EXTERIOR, EL QUE TENIA SE LO CALLO LA LLUVIA Y SE PARTIÓ. 0 28/07/2025 SE REALIZA VISITA SE PROCEDE A INSTALAR AVISO EXTERIOR ,YA Q EL ELQ TENÍA SE CAYÓ Y SE PARTIÓ ,CLIENTE LO DESHECHO LO ARROJO A LA BASURA DICE Q SE PARTIÓ EN 3 PARTES CERRAR | W124: VISITA_TÉCNICA | X124: 0 | Y124: TIPO II | Z124: TERRESTRE | AA124: PORRAS CASTRO DARLON NASCK | AB124: 1 | AC124: 1 | AD124: =IF(OR(W124="SOPORTE_TELEFÓNICO",W124="ENVÍO"),0,IF(Y124="TIPO I",'BASE DE LIQUIDACION 2025'!$I$4,IF(Y124="TIPO II",'BASE DE LIQUIDACION 2025'!$I$5,IF(Y124="TIPO III",'BASE DE LIQUIDACION 2025'!$I$6,IF(Y124="TIPO IV",'BASE DE LIQUIDACION 2025'!$I$7,'BASE DE LIQUIDACION 2025'!$I$8))))) -> 232858.6 | AE124: =IF(OR(W124="SOPORTE_TELEFÓNICO",W124="ENVÍO"),0,IF(Y124="TIPO I",'BASE DE LIQUIDACION 2025'!$J$4,IF(Y124="TIPO II",'BASE DE LIQUIDACION 2025'!$J$5,IF(Y124="TIPO III",'BASE DE LIQUIDACION 2025'!$J$6,IF(Y124="TIPO IV",'BASE DE LIQUIDACION 2025'!$J$7,'BASE DE LIQUIDACION 2025'!$J$8))))) -> 110808.28 | AF124: =IF(W124="SOPORTE_TELEFÓNICO",'BASE DE LIQUIDACION 2025'!$L$4,IF(W124="ENVÍO",'BASE DE LIQUIDACION 2025'!$K$4,AD124*AB124+AE124*AC124)) -> 343666.88
A125: SINCELEJO | B125: =VLOOKUP(A125,'CENTRO DE COSTOS'!A:D,4,FALSE) -> JOSE MAURICIO HERNANDEZ ROJAS | C125: =VLOOKUP(A125,'CENTRO DE COSTOS'!A:D,2,FALSE) -> 0004-0001 | D125: 70001 | E125: 2503195 | F125: 38768 | G125: ORDEN DE CAMBIO | H125: SUCRE | I125: SINCELEJO | J125: BARRIO LIBERTAD SINCELEJO | K125: REDEBAN | L125: FO-25-1284101 | M125: 45863.414 | N125: 45867.397 | P125: PUBLICIDAD | Q125: AVISO EXTERIOR | R125: CB UNO A UNO | S125: CB UNO A UNO | T125: EJECUTADO_EXITOSO | U125: EJECUTADO EXITOSO | V125: SE COMUNICA CB SR(A) ENEIDA BURGOS, PARA SOLICITAR UN AVISO EXTERIOR YA QUE EL VIENTO LO CAYO Y LO PARTIO 0 28-07 SE VISITA SITIO SE VERIFICA INFORMACIÓN SE REALIZA INSTALACIÓN DE AVISO EXTERIOR ÚNICAMENTE, NO SE MANIPULA EQUIPOS. | W125: VISITA_TÉCNICA | X125: 0 | Y125: TIPO I | Z125: TERRESTRE | AA125: SANTOS GUZMAN CHRISTIAN FELIPE | AB125: 1 | AC125: 1 | AD125: =IF(OR(W125="SOPORTE_TELEFÓNICO",W125="ENVÍO"),0,IF(Y125="TIPO I",'BASE DE LIQUIDACION 2025'!$I$4,IF(Y125="TIPO II",'BASE DE LIQUIDACION 2025'!$I$5,IF(Y125="TIPO III",'BASE DE LIQUIDACION 2025'!$I$6,IF(Y125="TIPO IV",'BASE DE LIQUIDACION 2025'!$I$7,'BASE DE LIQUIDACION 2025'!$I$8))))) -> 96001.196 | AE125: =IF(OR(W125="SOPORTE_TELEFÓNICO",W125="ENVÍO"),0,IF(Y125="TIPO I",'BASE DE LIQUIDACION 2025'!$J$4,IF(Y125="TIPO II",'BASE DE LIQUIDACION 2025'!$J$5,IF(Y125="TIPO III",'BASE DE LIQUIDACION 2025'!$J$6,IF(Y125="TIPO IV",'BASE DE LIQUIDACION 2025'!$J$7,'BASE DE LIQUIDACION 2025'!$J$8))))) -> 57411.974 | AF125: =IF(W125="SOPORTE_TELEFÓNICO",'BASE DE LIQUIDACION 2025'!$L$4,IF(W125="ENVÍO",'BASE DE LIQUIDACION 2025'!$K$4,AD125*AB125+AE125*AC125)) -> 153413.17
A126: BOGOTA | B126: =VLOOKUP(A126,'CENTRO DE COSTOS'!A:D,4,FALSE) -> WILLIAM ASDRUBAL ROZO ROZO | C126: =VLOOKUP(A126,'CENTRO DE COSTOS'!A:D,2,FALSE) -> 0004-0004 | D126: 11001 | E126: 2506944 | F126: 79689 | G126: ORDEN DE CAMBIO | H126: CUNDINAMARCA | I126: BOGOTA | J126: PTM BOGOTA LENCERIA PEREZ FRIA | K126: REDEBAN | L126: FO-25-1287996 | M126: 45863.717 | N126: 45869.463 | P126: PUBLICIDAD | Q126: AVISO EXTERIOR | R126: AGREGADOR | S126: COMCARD - PTM | T126: EJECUTADO_CANCELADO | U126: PETICIÓN BANCOLOMBIA | V126: SE COMUNICA CB SR(A)HERNANDO PARA SOLICITAR AVISO EXTERIOR PORQUE SE LO ROBARON 0 31/07/2025 SE VISITA COMERCIO PARA INSTALACIÓN DE AVISO EXTERIOR AL LLEGAR AL PUNTO SE EVIDENCIA QUE EN EL PUNTO YA HAY PUBLICIDAD EXISTENTE INSTALADA Y ADICIONALMENTE NO HAY UNA PERSONA QUE ATIENDA DIRECTAMENTE AL TÉCNICO YA QUE EL CLIENTE DEJO RECOMENDADO A UN LOCAL VECINO CON INSTRUCCIONES DE SOLO RECIBIR EL AVISO EXTERIOR , SE INDIA A PERSONA ENCARGADQUE NO ES POSIBLE LA INSTALACIÓN BYA QUE EL CLIENTE CUENTA CON PUBLICIDAD EN EL COMERCIO Y LA ENTIDAD NO AUTORIZA MÁS DE UN AVISO POR COMERCIO NO SE ADJUNTA TIRILLA O BAUCHER DE PRUEBA YA QUE ELMCB NO ESTÁ SIENDO OPERADO EN EL MOMENTO Y SE FINALIZA ACTIVIDAD SIN MÁS NOVEDAD CERRAR | W126: VISITA_TÉCNICA | X126: 0 | Y126: TIPO I | Z126: TERRESTRE | AA126: ROMERO ROJAS BREIDY JHOHAN | AB126: 1 | AC126: 1 | AD126: =IF(OR(W126="SOPORTE_TELEFÓNICO",W126="ENVÍO"),0,IF(Y126="TIPO I",'BASE DE LIQUIDACION 2025'!$I$4,IF(Y126="TIPO II",'BASE DE LIQUIDACION 2025'!$I$5,IF(Y126="TIPO III",'BASE DE LIQUIDACION 2025'!$I$6,IF(Y126="TIPO IV",'BASE DE LIQUIDACION 2025'!$I$7,'BASE DE LIQUIDACION 2025'!$I$8))))) -> 96001.196 | AE126: =IF(OR(W126="SOPORTE_TELEFÓNICO",W126="ENVÍO"),0,IF(Y126="TIPO I",'BASE DE LIQUIDACION 2025'!$J$4,IF(Y126="TIPO II",'BASE DE LIQUIDACION 2025'!$J$5,IF(Y126="TIPO III",'BASE DE LIQUIDACION 2025'!$J$6,IF(Y126="TIPO IV",'BASE DE LIQUIDACION 2025'!$J$7,'BASE DE LIQUIDACION 2025'!$J$8))))) -> 57411.974 | AF126: =IF(W126="SOPORTE_TELEFÓNICO",'BASE DE LIQUIDACION 2025'!$L$4,IF(W126="ENVÍO",'BASE DE LIQUIDACION 2025'!$K$4,AD126*AB126+AE126*AC126)) -> 153413.17
A127: MEDELLIN | B127: =VLOOKUP(A127,'CENTRO DE COSTOS'!A:D,4,FALSE) -> JUAN SEBASTIÁN RÍOS CASTRILLÓN | C127: =VLOOKUP(A127,'CENTRO DE COSTOS'!A:D,2,FALSE) -> 0004-0005 | D127: 5001 | E127: 2522440 | F127: 39310 | G127: ORDEN DE CAMBIO | H127: ANTIOQUIA | I127: MEDELLIN | J127: PTM MED TRUSTIME | K127: REDEBAN | L127: FO-25-1301901 | M127: 45867.642 | N127: 45869.718 | P127: PUBLICIDAD | Q127: AVISO EXTERIOR | R127: AGREGADOR | S127: COMCARD - PTM | T127: EJECUTADO_EXITOSO | U127: EJECUTADO EXITOSO | V127: SE COMUNICA CB SR(A) ANGIE QUIEN SOLICITA AVISO EXTERIOR YA QUE SE LO ROBARON, POR FAVOR COLABORARLE. GRACIAS 0 31/07/2025 SE INSTALA AVISO EXTERIOR PORQUE A LA USUARIA SE LO ROBARON CERRAR | W127: VISITA_TÉCNICA | X127: 0 | Y127: TIPO I | Z127: TERRESTRE | AA127: RUA ALVAREZ RICHARD ANDRES | AB127: 1 | AC127: 1 | AD127: =IF(OR(W127="SOPORTE_TELEFÓNICO",W127="ENVÍO"),0,IF(Y127="TIPO I",'BASE DE LIQUIDACION 2025'!$I$4,IF(Y127="TIPO II",'BASE DE LIQUIDACION 2025'!$I$5,IF(Y127="TIPO III",'BASE DE LIQUIDACION 2025'!$I$6,IF(Y127="TIPO IV",'BASE DE LIQUIDACION 2025'!$I$7,'BASE DE LIQUIDACION 2025'!$I$8))))) -> 96001.196 | AE127: =IF(OR(W127="SOPORTE_TELEFÓNICO",W127="ENVÍO"),0,IF(Y127="TIPO I",'BASE DE LIQUIDACION 2025'!$J$4,IF(Y127="TIPO II",'BASE DE LIQUIDACION 2025'!$J$5,IF(Y127="TIPO III",'BASE DE LIQUIDACION 2025'!$J$6,IF(Y127="TIPO IV",'BASE DE LIQUIDACION 2025'!$J$7,'BASE DE LIQUIDACION 2025'!$J$8))))) -> 57411.974 | AF127: =IF(W127="SOPORTE_TELEFÓNICO",'BASE DE LIQUIDACION 2025'!$L$4,IF(W127="ENVÍO",'BASE DE LIQUIDACION 2025'!$K$4,AD127*AB127+AE127*AC127)) -> 153413.17
AF128: =SUM(AF2:AF127) -> 28898150

Sheet TIPOLOGIA
A1: COD. CIUDAD | B1: CIUDAD | C1: DEPARTAMENTO | D1: DESDE DONDE SE ATIENDE | E1: TIPO DE TRAYECTO NUEVO | F1: TIPOLOGIA NUEVA
A2: 91430 | B2: LA VICTORIA | C2: AMAZONAS | D2: BOGOTA | E2: AEREO | F2: TIPO IV ESPECIAL
A3: 91669 | B3: PUERTO SANTANDER | C3: AMAZONAS | D3: BOGOTA | E3: AEREO | F3: TIPO IV ESPECIAL
A4: 91263 | B4: EL ENCANTO | C4: AMAZONAS | D4: BOGOTA | E4: AEREO | F4: TIPO IV ESPECIAL
A5: 91405 | B5: LA CHORRERA | C5: AMAZONAS | D5: BOGOTA | E5: AEREO | F5: TIPO IV ESPECIAL
A6: 91407 | B6: LA PEDRERA | C6: AMAZONAS | D6: BOGOTA | E6: AEREO | F6: TIPO IV ESPECIAL
A7: 91001 | B7: LETICIA | C7: AMAZONAS | D7: BOGOTA | E7: AEREO | F7: TIPO IV ESPECIAL
A8: 91460 | B8: MIRITI - PARANA | C8: AMAZONAS | D8: BOGOTA | E8: AEREO | F8: TIPO IV ESPECIAL
A9: 91530 | B9: PUERTO ALEGRIA | C9: AMAZONAS | D9: BOGOTA | E9: AEREO | F9: TIPO IV ESPECIAL
A10: 91536 | B10: PUERTO ARICA | C10: AMAZONAS | D10: BOGOTA | E10: AEREO | F10: TIPO IV ESPECIAL
A11: 91540 | B11: PUERTO NARIÑO | C11: AMAZONAS | D11: BOGOTA | E11: AEREO | F11: TIPO IV ESPECIAL
A12: 91798 | B12: TARAPACA | C12: AMAZONAS | D12: BOGOTA | E12: AEREO | F12: TIPO IV ESPECIAL
A13: 5055 | B13: ARGELIA | C13: ANTIOQUIA | D13: MEDELLIN | E13: TERRESTRE | F13: TIPO IV
... A1124: 23682 | B1124: SAN JOSE DE URE | C1124: CORDOBA | D1124: MONTERIA | E1124: TERRESTRE | F1124: TIPO III

Sheet CENTRO DE COSTOS
A1: CIUDAD | B1: CENTRO_COSTO | C1: DESCRIPCION | D1: COORDINADOR
A2: APARTADO | B2: 0004-0005 | C2: Redeban Noroccidente (Medellín) | D2: JUAN SEBASTIÁN RÍOS CASTRILLÓN
A3: BARRANQUILLA | B3: 0004-0001 | C3: Redeban Costa (Barranqullla) | D3: JOSE MAURICIO HERNANDEZ ROJAS
A4: BOGOTA | B4: 0004-0004 | C4: Redeban Centro ( Bogotá) | D4: WILLIAM ASDRUBAL ROZO ROZO
A5: BUCARAMANGA | B5: 0004-0008 | C5: Redeban Santander | D5: MIGUEL JULIÁN HERNÁNDEZ GUARÍN
A6: CALI | B6: 0004-0003 | C6: Redeban Suroccidente (Cali) | D6: DIEGO FERNANDO HENAO CARDONA
A7: CARTAGENA | B7: 0004-0001 | C7: Redeban Costa (Barranqullla) | D7: JOSE MAURICIO HERNANDEZ ROJAS
A8: CUCUTA | B8: 0004-0008 | C8: Redeban Santander | D8: MIGUEL JULIÁN HERNÁNDEZ GUARÍN
A9: FLORENCIA | B9: 0004-0007 | C9: Redeban Oriente (Otros) | D9: KEVIN ALEXIS CORZO BUSTOS
A10: IBAGUE | B10: 0004-0007 | C10: Redeban Oriente (Otros) | D10: KEVIN ALEXIS CORZO BUSTOS
A11: MANIZALES | B11: 0004-0002 | C11: Redeban Eje Cafetero (Pereira) | D11: DIEGO FERNANDO HENAO CARDONA
A12: MEDELLIN | B12: 0004-0005 | C12: Redeban Noroccidente (Medellín) | D12: JUAN SEBASTIÁN RÍOS CASTRILLÓN
... A23: YOPAL | B23: 0004-0007 | C23: Redeban Oriente (Otros) | D23: KEVIN ALEXIS CORZO BUSTOS
