Workbook
Name A: #REF!
Name ACTIVIDAD: [1]Hoja2!$P$2:$P$30
Name Actividad: [2]Formulas!$H$2:$H$5000
Name arearesponsable: '[3]Listas desplegables'!$BB$2:$BB$100
Name Clientes: [4]Clientes!$A$2:$A$100
Name Clientes: [2]Clientes!$A$2:$A$100
Name COORDINADOR: [1]Hoja2!$D$2:$D$30
Name Coordinadores: [5]Coordinadores!$A$2:$A$1000
Name Coordinadores: [2]Coordinadores!$A$2:$A$1000
Name DOCUMENTADOR: [1]Hoja2!$A$2:$A$30
Name ES: [1]Hoja2!$K$2:$K$30
Name ESS: [1]Hoja2!$K$2:$K$30
Name Estado: [4]Formulas!$K$2:$K$5000
Name Estado: [2]Formulas!$K$2:$K$5000
Name ESTADOACTIVIDAD: [1]Hoja2!$M$2:$M$30
Name ESTADOS: '[6]Listas desplegables'!$B$1:$D$1
Name ESTADOSCIERRES: '[7]lista desplegable'!$CX$1:$DA$1
Name Facturacion: '[8]Listas desplegables'!$AO$1:$AR$1
Name FACTURACIÓN: '[6]Listas desplegables'!$Y$1:$AB$1
Name falla: #REF!
Name Fallas: '[9]Listas desplegables'!$F$2:$L$2
Name Grupo_Falla: '[10]Listas Desplegables'!$CH$2:$CH$5
Name inconservmanager: '[11]Listas desplegables'!$BC$2:$BC$100
Name INCUMPLIMIENTO: '[3]Listas desplegables'!$AK$1:$AN$1
Name LISTA: [12]Dptos!$A$1139:$A$1171
Name LISTA2: #REF!
Name LOLO: [13]Coordinadores!$A$2:$A$1000
Name solicitudes: '[8]Listas desplegables'!$U$1:$AF$1
Name solicitudes: '[14]Listas desplegables'!$AF$1:$AQ$1
Name Tecnicos: [4]Tecnicos!$A$2:$A$1000
Name Tecnicos: [2]Tecnicos!$A$2:$A$1000
Name Version: [2]Formulas!$I$2:$I$3

Sheet RESUMEN
A1: LÍNEA COMUNICACIONES S.A.S | F1: FACTURACIÓN CORRESPONSALES BANCARIOS TIQUIETES AEREOS
A2: FACTURACIÓN PROYECTO CB BANCOLOMBIA | F2: =A3 -> 45868
A3: 45868
F4: CONCEPTOS | G4: TRAYECTOS | H4: TOTAL | I4: % Administración | J4: TOTAL
A5: CONCEPTOS | B5: CANTIDAD | C5: VALOR UNITARIO | D5: VALOR TOTAL | I5: =H5*0.12 -> 0 | J5: =H5+I5 -> 0
A6: Adecuaciones CB | B6: =COUNTA(ADECUACIONES!A:A)-1 -> 69 | C6: 0 | D6: =ADECUACIONES!AE71 -> 13282763 | I6: =H6*0.12 -> 0 | J6: =H6+I6 -> 0
A7: Incidentes | B7: =COUNTA(INCIDENTES!A:A)-1 -> 208 | C7: 0 | D7: =INCIDENTES!AG210 -> 18322378 | I7: =H7*0.12 -> 0 | J7: =H7+I7 -> 0
A8: Ordenes de Cambio | B8: =COUNTA(OC!A:A)-1 -> 8 | C8: 0 | D8: =OC!AG10 -> 1010801.9 | I8: =H8*0.12 -> 0 | J8: =H8+I8 -> 0
A9: Tiquetes | B9: 0 | C9: 0 | D9: =J12 -> 0 | I9: =H9*0.12 -> 0 | J9: =H9+I9 -> 0
A10: SUBTOTAL | D10: =SUM(D6:D9) -> 32615942 | I10: =H10*0.12 -> 0 | J10: =H10+I10 -> 0
A11: Iva | D11: =D10*0.19 -> 6197029 | I11: =H11*0.12 -> 0 | J11: =H11+I11 -> 0
A12: TOTAL | D12: =D10+D11 -> 38812971 | F12: TOTAL | H12: =SUM(H5:H11) -> 0 | I12: =SUM(I5:I11) -> 0 | J12: =SUM(J5:J11) -> 0

Sheet BASE LIQUIDACION
A1: TARIFAS 2025 | E1: Incremento 2025
A2: Tipificación | B2: Descripción | C2: Dia actividad Exitosa | D2: Dia actividad Fallida | E2: 0.052
A3: Tipo I | B3: Metropolitano | C3: =62700.07*(1+$E$2) -> 65960.474 | D3: =42357.4*(1+$E$2) -> 44559.985
A4: Tipo II | B4: Hasta 3 horas | C4: =155716.31*(1+$E$2) -> 163813.56 | D4: =127766.53*(1+$E$2) -> 134410.39
A5: Tipo III | B5: De 3 a 5 horas | C5: =262099.22*(1+$E$2) -> 275728.38 | D5: =211886.19*(1+$E$2) -> 222904.27
A6: Tipo IV | B6: Más de 5 horas | C6: =455883.78*(1+$E$2) -> 479589.74 | D6: =441833.68*(1+$E$2) -> 464809.03
A7: Destino aereo | B7: No incluye valor del Tiquete | C7: =455883.78*(1+$E$2) -> 479589.74 | D7: =441833.68*(1+$E$2) -> 464809.03
A8: *Donde se requiera transporte aéreo o fluvial se factura adicional a tarifa TIPO IV el valor del tiquete + el 12% de admon.
A10: Gestión Telefónica | B10: =36031.04*(1+$E$2) -> 37904.654
A11: Mts Acometida electrica | B11: =30182.1*(1+$E$2) -> 31751.569
A12: Mts Acometida datos | B12: =15432.22*(1+$E$2) -> 16234.695
A13: switche | B13: =244669.03*(1+$E$2) -> 257391.82
A14: Router | B14: =291399.51*(1+$E$2) -> 306552.28
A15: Envio operador Logistico | B15: =53547.34*(1+$E$2) -> 56331.802

Sheet Tablas dinámicas
A2: ADECUACIONES | J2: NOMBRE CC | K2: Suma de VALOR | L2: Suma de VALOR2
A3: COORDINADOR | B3: CENTRO DE COSTOS LÍNEACOM | C3: % | D3: $ | E3: NOMBRE CC | F3: VALOR | J3: Redeban Centro ( Bogotá) | K3: 2098133.1 | L3: 0.064328454
A4: DIEGO FERNANDO HENAO CARDONA | B4: 0004-0002 | C4: 0.038828886 | D4: 515754.88 | E4: =VLOOKUP(B4,'CENTRO DE COSTOS'!B:C,2,0) -> Redeban Eje Cafetero (Pereira) | F4: =D4 -> 515754.88 | J4: Redeban Costa (Barranqullla) | K4: 3188171.7 | L4: 0.097748877
B5: 0004-0003 | C5: 0.20892662 | D5: 2775122.7 | E5: =VLOOKUP(B5,'CENTRO DE COSTOS'!B:C,2,0) -> Redeban Suroccidente (Cali) | F5: =D5 -> 2775122.7 | J5: Redeban Eje Cafetero (Pereira) | K5: 1898065 | L5: 0.058194394
A6: JOSE MAURICIO HERNANDEZ ROJAS | B6: 0004-0001 | C6: 0.13941229 | D6: 1851780.4 | E6: =VLOOKUP(B6,'CENTRO DE COSTOS'!B:C,2,0) -> Redeban Costa (Barranqullla) | F6: =D6 -> 1851780.4 | J6: Redeban Noroccidente (Medellín) | K6: 9497012.5 | L6: 0.29117701
A7: JUAN SEBASTIÁN RÍOS CASTRILLÓN | B7: 0004-0005 | C7: 0.13165335 | D7: 1748720.3 | E7: =VLOOKUP(B7,'CENTRO DE COSTOS'!B:C,2,0) -> Redeban Noroccidente (Medellín) | F7: =D7 -> 1748720.3 | J7: Redeban Oriente (Otros) | K7: 5197327.1 | L7: 0.15934929
A8: KEVIN ALEXIS CORZO BUSTOS | B8: 0004-0007 | C8: 0.18071535 | D8: 2400399.1 | E8: =VLOOKUP(B8,'CENTRO DE COSTOS'!B:C,2,0) -> Redeban Oriente (Otros) | F8: =D8 -> 2400399.1 | J8: Redeban Santander | K8: 6202314.1 | L8: 0.19016204
A9: MIGUEL JULIÁN HERNÁNDEZ GUARÍN | B9: 0004-0008 | C9: 0.24854912 | D9: 3301419 | E9: =VLOOKUP(B9,'CENTRO DE COSTOS'!B:C,2,0) -> Redeban Santander | F9: =D9 -> 3301419 | J9: Redeban Suroccidente (Cali) | K9: 4534918.7 | L9: 0.13903994
A10: WILLIAM ASDRUBAL ROZO ROZO | B10: 0004-0004 | C10: 0.051914376 | D10: 689566.34 | E10: =VLOOKUP(B10,'CENTRO DE COSTOS'!B:C,2,0) -> Redeban Centro ( Bogotá) | F10: =D10 -> 689566.34 | J10: Total general | K10: 32615942 | L10: 1
A11: Total general | C11: 1 | D11: 13282763
A15: INCIDENTES
A16: COORDINADOR | B16: CENTRO DE COSTOS LÍNEACOM | C16: % | D16: $ | E16: NOMBRE CC
A17: DIEGO FERNANDO HENAO CARDONA | B17: 0004-0002 | C17: 0.071843822 | D17: 1316349.7 | E17: =VLOOKUP(B17,'CENTRO DE COSTOS'!B:C,2,0) -> Redeban Eje Cafetero (Pereira) | F17: =D17 -> 1316349.7
B18: 0004-0003 | C18: 0.080997547 | D18: 1484067.7 | E18: =VLOOKUP(B18,'CENTRO DE COSTOS'!B:C,2,0) -> Redeban Suroccidente (Cali) | F18: =D18 -> 1484067.7
A19: JOSE MAURICIO HERNANDEZ ROJAS | B19: 0004-0001 | C19: 0.070868895 | D19: 1298486.7 | E19: =VLOOKUP(B19,'CENTRO DE COSTOS'!B:C,2,0) -> Redeban Costa (Barranqullla) | F19: =D19 -> 1298486.7
A20: JUAN SEBASTIÁN RÍOS CASTRILLÓN | B20: 0004-0005 | C20: 0.42081807 | D20: 7710387.5 | E20: =VLOOKUP(B20,'CENTRO DE COSTOS'!B:C,2,0) -> Redeban Noroccidente (Medellín) | F20: =D20 -> 7710387.5
A21: KEVIN ALEXIS CORZO BUSTOS | B21: 0004-0007 | C21: 0.15265093 | D21: 2796928 | E21: =VLOOKUP(B21,'CENTRO DE COSTOS'!B:C,2,0) -> Redeban Oriente (Otros) | F21: =D21 -> 2796928
A22: MIGUEL JULIÁN HERNÁNDEZ GUARÍN | B22: 0004-0008 | C22: 0.12801265 | D22: 2345496.1 | E22: =VLOOKUP(B22,'CENTRO DE COSTOS'!B:C,2,0) -> Redeban Santander | F22: =D22 -> 2345496.1
A23: WILLIAM ASDRUBAL ROZO ROZO | B23: 0004-0004 | C23: 0.074808094 | D23: 1370662.2 | E23: =VLOOKUP(B23,'CENTRO DE COSTOS'!B:C,2,0) -> Redeban Centro ( Bogotá) | F23: =D23 -> 1370662.2
A24: Total general | C24: 1 | D24: 18322378
A29: OC
A30: COORDINADOR | B30: CENTRO DE COSTOS LÍNEACOM | C30: % | D30: $ | E30: NOMBRE CC
A31: DIEGO FERNANDO HENAO CARDONA | B31: 0004-0003 | C31: 0.27278183 | D31: 275728.38 | E31: =VLOOKUP(B31,'CENTRO DE COSTOS'!B:C,2,0) -> Redeban Suroccidente (Cali) | F31: =D31 -> 275728.38
B32: 0004-0002 | C32: 0.065255592 | D32: 65960.474 | E32: =VLOOKUP(B32,'CENTRO DE COSTOS'!B:C,2,0) -> Redeban Eje Cafetero (Pereira) | F32: =D32 -> 65960.474
A33: JOSE MAURICIO HERNANDEZ ROJAS | B33: 0004-0001 | C33: 0.037499589 | D33: 37904.654 | E33: =VLOOKUP(B33,'CENTRO DE COSTOS'!B:C,2,0) -> Redeban Costa (Barranqullla) | F33: =D33 -> 37904.654
A34: JUAN SEBASTIÁN RÍOS CASTRILLÓN | B34: 0004-0005 | C34: 0.037499589 | D34: 37904.654 | E34: =VLOOKUP(B34,'CENTRO DE COSTOS'!B:C,2,0) -> Redeban Noroccidente (Medellín) | F34: =D34 -> 37904.654
A35: MIGUEL JULIÁN HERNÁNDEZ GUARÍN | B35: 0004-0008 | C35: 0.54946381 | D35: 555399.04 | E35: =VLOOKUP(B35,'CENTRO DE COSTOS'!B:C,2,0) -> Redeban Santander | F35: =D35 -> 555399.04
A36: WILLIAM ASDRUBAL ROZO ROZO | B36: 0004-0004 | C36: 0.037499589 | D36: 37904.654 | E36: =VLOOKUP(B36,'CENTRO DE COSTOS'!B:C,2,0) -> Redeban Centro ( Bogotá) | F36: =D36 -> 37904.654
A37: Total general | C37: 1 | D37: 1010801.9

Sheet ADECUACIONES
A1: CIUDAD SEDE | B1: COORDINADOR | C1: CENTRO DE COSTOS LÍNEACOM | D1: CÓDIGO DANE | E1: TA/CODIGO ACTIVIDAD | F1: CODIGO CB | G1: ACTIVIDAD | H1: TIPO DE APERTURA | I1: DEPARTAMENTO | J1: CIUDAD | K1: NOMBRE DEL CB | L1: RED | M1: FO | N1: FECHA LISTA | O1: FECHA ULTIMA ACTUALIZACION | P1: FORMATO | Q1: CADENA | R1: ESTADO | S1: OBSERVACIONES CLIENTE | T1: FORMA DE ATENCIÓN | U1: TERMINALES | V1: TIPIFICACION | W1: TIPO DE TRAYECTO | X1: NOMBRE DEL TECNICO | Y1: ACOMETIDA DATOS | Z1: ACOMETIDA ELECTRICA | AA1: SWITCH | AB1: ROUTER | AC1: VALOR DIAS ACTIVIDAD FACTURABLES | AD1: DIAS ACTIVIDAD FACTURABLES | AE1: VALOR TOTAL INSTALACION DE PUBLICIDAD
A2: MEDELLIN | B2: =VLOOKUP(A2,'CENTRO DE COSTOS'!A:D,4,FALSE) -> JUAN SEBASTIÁN RÍOS CASTRILLÓN | C2: =VLOOKUP(A2,'CENTRO DE COSTOS'!A:C,2,FALSE) -> 0004-0005 | D2: 5091 | E2: TA-25-792913 | F2: 79058 | G2: APERTURA | H2: CB CRECIMIENTO - OTRAS LISTAS | I2: ANTIOQUIA | J2: BETANIA | K2: BARRIO BETANIA ANTIOQUIA BETANIA | L2: REDEBAN | M2: FO-25-1167345 | N2: 45821 | O2: 45842 | P2: UNO A UNO | Q2: UNO A UNO | R2: EJECUTADO | S2: 13-06 SE ESTABLECE COMUNICACIÓN CON EL USUARIO EL CUAL IDNICA QUE EL NECESITA ES UN CORRESPONSAL CON UN CUPO BASTANTES GRANDE, QUE SI EL CORRESPONSAL ES SOLO POR 10 MILLONES NO LE INTERESA - COMUNICACIÓN POR WPP 13/6/2025 ESTE PUNTO FUE ENVIADO EN LA LISTA DE AYER, ME APOYAN POR FAVOR DEJÁNDOLO PENDIENTE HASTA LAS HORAS DE LA TARDE, ES DECIR, NO PROCESEN LA PROGRAMACIÓN, PERO TAMPOCO LO CANCELEN. 19/6/2025 POR FAVOR PROCEDER CON LA IMPLEMENTACIÓN, AGRADEZCO NOS CONFIRMEN CUANDO SE PROGRAME EL PUNTO. 26/6/2025 SE REALIZÓ VISITA NO SE LOGRA INSTALAR YA QUE EL CUPO ASIGNADO ES DE 10 MILLONES EL CB SOLICITO QUE FUERA MÁS ALTO, SE ESCALO TEMA A BANCO Y NO BRINDAN INFORMACIÓN OPORTUNA ADICIONAL NOS INDICA QUE SE DEBE CORREGIR EL CORREO ELECTRÓNICO RDESCOBARARANGO@YAHOO.ES SE POSPONE ACTIVIDAD 4/7/2025 SE REALIZA INSTALACIÓN DE CORRESPONSAL, SE INSTALAN EQUIPOS CON PRUEBAS EXITOSAS, SE CAPACITA Y SE EVALÚA AL CLIENTE, SE INSTALA PUBLICIDAD COMPLETA, CB QUEDA OPERATIVO. USUARIO SOMOS BANCOLOMBIA ACTIVO | T2: VISITA _TECNICA | U2: SASZZ633 | V2: TIPO III | W2: TERRESTRE | X2: QUINTERO SANCHEZ JUAN SEBASTIAN | Y2: 0 | Z2: 0 | AA2: 0 | AB2: 0 | AC2: 1 | AD2: =IF(V2="TIPO I",'BASE LIQUIDACION'!$D$3,IF(V2="TIPO II",'BASE LIQUIDACION'!$D$4,IF(V2="TIPO III",'BASE LIQUIDACION'!$D$5,'BASE LIQUIDACION'!$D$7))) -> 222904.27 | AE2: =Y2*'BASE LIQUIDACION'!$B$12+Z2*'BASE LIQUIDACION'!$B$11+AA2*'BASE LIQUIDACION'!$B$13+AB2*'BASE LIQUIDACION'!$B$14+AC2*AD2 -> 222904.27
A3: SANTA MARTA | B3: =VLOOKUP(A3,'CENTRO DE COSTOS'!A:D,4,FALSE) -> JOSE MAURICIO HERNANDEZ ROJAS | C3: =VLOOKUP(A3,'CENTRO DE COSTOS'!A:C,2,FALSE) -> 0004-0001 | D3: 44430 | E3: TA-25-790987 | F3: 79898 | G3: APERTURA | H3: CB CRECIMIENTO ALIANZA - NUEVO | I3: LA GUAJIRA | J3: MAICAO | K3: DISTRICOL COMERCIALIZADORA | L3: REDEBAN | M3: FO-25-1186686 | N3: 45826 | O3: 45843 | P3: AGREGADOR | Q3: DISTRICOL | R3: EJECUTADO | S3: 18-06 PROGRAMACIÓN REALIZADA POR LA ALIANZA 21/6/2025 EN COMUNICACIÓN CON EL SEÑOR FRANCISCO VELÁZQUEZ AL NÚMERO 3003299172, ME INFORMA QUE EL PEAJE ENTRE MAICAO Y RIOHACHA FUE VOLADO POR EL ELN, Y QUE EL SECTOR ESTÁ EN ZONA ROJA POR PROBLEMAS DE ORDEN PÚBLICO , SE REPROGRAMA LA VISITA PARA LA PRÓXIMA SEMANA QUE SE RESTABLEZCA EL ORDEN EN EL SECTOR 26/6/2025 LA ALTERACIÓN AUN CONTINUA POR ESTE MOTIVO NO SE HA PODIDO REALIZAR IMPLEMENTACIÓN 2/7/2025 SE PROGRAMA VISITA PARA EL 04-07 04-07 NO SE LOGRA COMPLETAR LA APERTURA YA QUE EL CLIENTE MANIFIESTA NO TENER DISPOSICIÓN POR COMPROMISO FAMILIAR, QUEDA PENDIENTE LA CAPACITACIÓN ESTÁ QUEDA APLAZADA PARA EL DÍA SÁBADO 5 DE JULIO 5/7/2025 SE REALIZA INSTALACIÓN DE CORRESPONSAL, SE INSTALAN EQUIPOS CON PRUEBAS EXITOSAS, SE CAPACITA Y SE EVALÚA AL CLIENTE, SE INSTALA PUBLICIDAD COMPLETA, CB QUEDA OPERATIVO. USUARIO SOMOS BANCOLOMBIA ACTIVO | T3: VISITA _TECNICA | U3: SAUZZ961 | V3: TIPO IV | W3: TERRESTRE | X3: THOMAS CAMPO SIGIFREDO SEGUNDO | Y3: 0 | Z3: 0 | AA3: 0 | AB3: 0 | AC3: 1 | AD3: =IF(V3="TIPO I",'BASE LIQUIDACION'!$D$3,IF(V3="TIPO II",'BASE LIQUIDACION'!$D$4,IF(V3="TIPO III",'BASE LIQUIDACION'!$D$5,'BASE LIQUIDACION'!$D$7))) -> 464809.03 | AE3: =Y3*'BASE LIQUIDACION'!$B$12+Z3*'BASE LIQUIDACION'!$B$11+AA3*'BASE LIQUIDACION'!$B$13+AB3*'BASE LIQUIDACION'!$B$14+AC3*AD3 -> 464809.03
A4: PEREIRA | B4: =VLOOKUP(A4,'CENTRO DE COSTOS'!A:D,4,FALSE) -> DIEGO FERNANDO HENAO CARDONA | C4: =VLOOKUP(A4,'CENTRO DE COSTOS'!A:C,2,FALSE) -> 0004-0002 | D4: 66318 | E4: TA-25-799134 | F4: 80021 | G4: APERTURA | H4: CB CRECIMIENTO - NUEVO | I4: RISARALDA | J4: GUATICA | K4: BARRIO CENTRO GUATICA 4 | L4: REDEBAN | M4: FO-25-1158501 | N4: 45832 | O4: 45847 | P4: UNO A UNO | Q4: UNO A UNO | R4: EJECUTADO | S4: 24-06-2025 SE REALIZA LLAMADA AL CLIENTE, SE HABLA CON LA SRA ZHARICK QUINTERO TABARES SE VALIDA DIRECCIÓN OK, CANAL OK, DISPONIBILIDAD TOTAL, LLAMAR EL DÍA LA INSTALACIÓN PARA CONFIRMAR VISITA, AVISO EXTERIOR ALTURA APROX 3 METROS; TOMACORRIENTE CERCANO: SI; TIENE CABINA DE SEGURIDAD: SI // CONTACTO REALIZADO POR LA APP 27/6/2025 SE REALIZA VISITA DE APERTURA AL CB UNO A UNO CON CÓDIGO 3007080021 BARRIO CENTRO GUATICA 44, DIRECCIÓN CR 5 12 32 , COORDENADAS 5.315427, -75.798033, PERO SE ENCUENTRA CERCANÍA CON CORRESPONSAL DISTRICOL INSTALADO CON CÓDIGO 3007070765 DISTRICOL UNIVERSO ESCOLAR , DIRECCIÓN CL 13 12 66, COORDENADAS 5.315486, -75.797833, QUEDANDO A MENOS DE 25 MTS DE DISTANCIA UNO DEL OTRO A DOS CASAS EN LA MISMA CUADRA, SE REALIZA ESCALAMIENTO POR CERCANÍA EN ESPERA DE COMO PROCEDER. / ENTIDAD APRUEBA INSTALACIÓN 9/7/2025 SE REALIZA INSTALACIÓN DE CORRESPONSAL, SE INSTALAN EQUIPOS CON PRUEBAS EXITOSAS, SE CAPACITA Y SE EVALÚA AL CLIENTE, SE INSTALA PUBLICIDAD COMPLETA, CB QUEDA OPERATIVO. USUARIO SOMOS BANCOLOMBIA ACTIVO | T4: VISITA _TECNICA | U4: SAXZZ471 | V4: TIPO II | W4: TERRESTRE | X4: ARROYAVE CANO MANUEL GUILLERMO | Y4: 0 | Z4: 0 | AA4: 0 | AB4: 0 | AC4: 1 | AD4: =IF(V4="TIPO I",'BASE LIQUIDACION'!$D$3,IF(V4="TIPO II",'BASE LIQUIDACION'!$D$4,IF(V4="TIPO III",'BASE LIQUIDACION'!$D$5,'BASE LIQUIDACION'!$D$7))) -> 134410.39 | AE4: =Y4*'BASE LIQUIDACION'!$B$12+Z4*'BASE LIQUIDACION'!$B$11+AA4*'BASE LIQUIDACION'!$B$13+AB4*'BASE LIQUIDACION'!$B$14+AC4*AD4 -> 134410.39
A5: PEREIRA | B5: =VLOOKUP(A5,'CENTRO DE COSTOS'!A:D,4,FALSE) -> DIEGO FERNANDO HENAO CARDONA | C5: =VLOOKUP(A5,'CENTRO DE COSTOS'!A:C,2,FALSE) -> 0004-0002 | D5: 66001 | E5: TA-25-803999 | F5: 23092 | G5: APERTURA | H5: DATAFONO ADICIONAL - ALIANZA | I5: RISARALDA | J5: PEREIRA | K5: MULTIPAGAS PLAZA DE BOLIVAR PEREIRA | L5: REDEBAN | M5: FO-25-1138992 | N5: 45834 | O5: 45839 | P5: ROBUSTO | Q5: MULTIPAGAS | R5: EJECUTADO/CANCELADO | S5: 26-06 SE REALIZA LLAMADA AL CLIENTE, SE HABLA CON LA SRA CLAUDIA OSORIO SE VALIDA DIRECCIÓN OK, CANAL OK, DISPONIBILIDAD TOTAL, LLAMAR EL DÍA LA INSTALACIÓN PARA CONFIRMAR VISITA, 1/7/2025 SE REALIZA VISITA, EL CLIENTE INDICA QUE NO SE PUEDE DAR INGRESO YA QUE DE CENTRO DE GESTIÓN DE MULTIPAGAS SOLICITAN UN ERRADICADO PARA EL INGRESO, SE LE INDICA AL CLIENTE QUE SE VA A REALIZAR UNA INSTALACIÓN DE DATÁFONO ADICIONAL POR PETICIÓN DE MULTIPAGAS, PERO INDICA QUE UNA VEZ VALIDEN CON EL CENTRO DE GESTIÓN LLAMAN NUEVAMENTE A SOLICITAR LA INSTALACIÓN. | T5: VISITA _TECNICA | U5: V1ZZZ965 | V5: TIPO I | W5: TERRESTRE | X5: FRANCO CAÑAVERAL YAMID RAUL | Y5: 0 | Z5: 0 | AA5: 0 | AB5: 0 | AC5: 1 | AD5: =IF(V5="TIPO I",'BASE LIQUIDACION'!$D$3,IF(V5="TIPO II",'BASE LIQUIDACION'!$D$4,IF(V5="TIPO III",'BASE LIQUIDACION'!$D$5,'BASE LIQUIDACION'!$D$7))) -> 44559.985 | AE5: =Y5*'BASE LIQUIDACION'!$B$12+Z5*'BASE LIQUIDACION'!$B$11+AA5*'BASE LIQUIDACION'!$B$13+AB5*'BASE LIQUIDACION'!$B$14+AC5*AD5 -> 44559.985
A6: SINCELEJO | B6: =VLOOKUP(A6,'CENTRO DE COSTOS'!A:D,4,FALSE) -> JOSE MAURICIO HERNANDEZ ROJAS | C6: =VLOOKUP(A6,'CENTRO DE COSTOS'!A:C,2,FALSE) -> 0004-0001 | D6: 70742 | E6: TA-25-820441 | F6: 80190 | G6: APERTURA | H6: CB CRECIMIENTO - NUEVO | I6: SUCRE | J6: SAN LUIS DE SINCE | K6: BARRIO EL TREBOL SAN LUIS DE SINCE | L6: REDEBAN | M6: FO-25-1161762 | N6: 45839 | O6: 45841 | P6: UNO A UNO | Q6: UNO A UNO | R6: EJECUTADO/CANCELADO | S6: 28-06 SE REALIZA LLAMADA AL CLIENTE, SE HABLA CON EL SR HECTOR MAURICIO HERAZO GALVAN, SE VALIDA DIRECCIÓN OK, CANAL OK, DISPONIBILIDAD TOTAL, LLAMAR EL DÍA LA INSTALACIÓN PARA CONFIRMAR VISITA, AVISO EXTERIOR ALTURA APROX 3 METROS; TOMACORRIENTE CERCANO: SI; TIENE CABINA DE SEGURIDAD: NO 3/7/2025 SE LLEGA A LA DIRECCIÓN RELACIONADA EN LA LISTA DE CHEQUEO CRA 14 12 5,EL TRÉBOL, PERO SE EVIDENCIA QUE EN ESA DIRECCIÓN NO ESTÁ EL COMERCIO, EL COMERCIO ESTA UBICADO EN LA CRA 13 12 03. POR TAL MOTIVO SE CANCELA. | T6: VISITA _TECNICA | U6: F1ZZZ689 | V6: TIPO II | W6: TERRESTRE | X6: SANTOS GUZMAN CHRISTIAN FELIPE | Y6: 0 | Z6: 0 | AA6: 0 | AB6: 0 | AC6: 1 | AD6: =IF(V6="TIPO I",'BASE LIQUIDACION'!$D$3,IF(V6="TIPO II",'BASE LIQUIDACION'!$D$4,IF(V6="TIPO III",'BASE LIQUIDACION'!$D$5,'BASE LIQUIDACION'!$D$7))) -> 134410.39 | AE6: =Y6*'BASE LIQUIDACION'!$B$12+Z6*'BASE LIQUIDACION'!$B$11+AA6*'BASE LIQUIDACION'!$B$13+AB6*'BASE LIQUIDACION'!$B$14+AC6*AD6 -> 134410.39
A7: CALI | B7: =VLOOKUP(A7,'CENTRO DE COSTOS'!A:D,4,FALSE) -> DIEGO FERNANDO HENAO CARDONA | C7: =VLOOKUP(A7,'CENTRO DE COSTOS'!A:C,2,FALSE) -> 0004-0003 | D7: 19001 | E7: TA-25-820966 | F7: 80185 | G7: APERTURA | H7: CB CRECIMIENTO - NUEVO | I7: CAUCA | J7: POPAYAN | K7: BARRIO ESMERALDA POPAYAN 5 | L7: REDEBAN | M7: FO-25-1174585 | N7: 45839 | O7: 45850 | P7: UNO A UNO | Q7: UNO A UNO | R7: EJECUTADO | S7: 01-07-2025 SE REALIZA LLAMADA AL CLIENTE, SE HABLA CON LA SRA SANDRA LORENA PAMPLONA DORADO SE VALIDA DIRECCIÓN OK, CANAL OK, DISPONIBILIDAD TOTAL, LLAMAR EL DÍA LA INSTALACIÓN PARA CONFIRMAR VISITA, AVISO EXTERIOR ALTURA APROX CLIENTE NO TIENE CONOCIMIENTO DE MEDIDAS; TOMACORRIENTE CERCANO: SI; TIENE CABINA DE SEGURIDAD: SI // CONTACTO REALIZADO POR LA APP 2/7/2025 SE REALIZA VISITA DE APERTURA AL CB UNO A UNO CON CÓDIGO 3007080021 BARRIO ESMERALDA POPAYAN 5 , DIRECCIÓN CR 18 7 B 11 LC 1 , COORDENADAS 2.442165, -76.616340, PERO SE ENCUENTRA CERCANÍA CON CORRESPONSAL PTM INSTALADO CON CÓDIGO 3007072845 PTM POPAYAN VARIEDADES , DIRECCIÓN CR 18 7 A 15, COORDENADAS 2.442495, -76.616620, QUEDANDO A MENOS DE 30 MTS DE DISTANCIA UNO DEL OTRO , SE REALIZA ESCALAMIENTO POR CERCANÍA EN ESPERA DE COMO PROCEDER. 2/7/2025 ENTIDAD APRUEBA INSTALACIÓN 02-07 SE REALIZÓ LLAMADA DE VALIDACIÓN Y EL CLIENTE, EL SEÑOR JONATHAN MORA ME COMENTÓ QUE NO PUEDE ATENDERNOS EL DÍA DE HOY PORQUE NO LE HABÍAN INFORMADO NADA, QUE PORFA PARA EL DÍA VIERNES POR LA TARDE O PARA LA OTRA SEMANA PERO QUE SE LE INFORME ANTES PARA ÉL ESTAR PREPARADO. 11/7/2025 EN NUEVA COMUNICACIÓN CON EL USUARIO INDICA QUE NOS ATIENDE EL DIA DE MAÑANA 12-07 SE REALIZA INSTALACIÓN DE CORRESPONSAL, SE INSTALAN EQUIPOS CON PRUEBAS EXITOSAS, SE CAPACITA Y SE EVALÚA AL CLIENTE, SE INSTALA PUBLICIDAD COMPLETA, CB QUEDA OPERATIVO. USUARIO SOMOS BANCOLOMBIA ACTIVO | T7: VISITA _TECNICA | U7: F1ZZZ726 | V7: TIPO III | W7: TERRESTRE | X7: GIMBUEL LASSO LUIS GERMAN | Y7: 0 | Z7: 0 | AA7: 0 | AB7: 0 | AC7: 1 | AD7: =IF(V7="TIPO I",'BASE LIQUIDACION'!$D$3,IF(V7="TIPO II",'BASE LIQUIDACION'!$D$4,IF(V7="TIPO III",'BASE LIQUIDACION'!$D$5,'BASE LIQUIDACION'!$D$7))) -> 222904.27 | AE7: =Y7*'BASE LIQUIDACION'!$B$12+Z7*'BASE LIQUIDACION'!$B$11+AA7*'BASE LIQUIDACION'!$B$13+AB7*'BASE LIQUIDACION'!$B$14+AC7*AD7 -> 222904.27
A8: BOGOTA | B8: =VLOOKUP(A8,'CENTRO DE COSTOS'!A:D,4,FALSE) -> WILLIAM ASDRUBAL ROZO ROZO | C8: =VLOOKUP(A8,'CENTRO DE COSTOS'!A:C,2,FALSE) -> 0004-0004 | D8: 25320 | E8: TA-25-821243 | F8: 80152 | G8: APERTURA | H8: CB CRECIMIENTO - NUEVO | I8: CUNDINAMARCA | J8: GUADUAS | K8: BARRIO CENTRO GUADUAS 5 | L8: REDEBAN | M8: FO-25-1180211 | N8: 45839 | O8: 45847 | P8: UNO A UNO | Q8: UNO A UNO | R8: EJECUTADO | S8: 1-07-2025 SE REALIZA COMUNICACION CON CLIENTE, SE HABLA CON LA SRA ARAMINTA GALINDO ROJAS SE VALIDA DIRECCIÓN OK, CANAL OK, DISPONIBILIDAD TOTAL, LLAMAR EL DÍA DE LA INSTALACIÓN PARA CONFIRMAR VISITA, ALTURA APROX 2 METROS; TOMACORRIENTE CERCANO: SI; TIENE CABINA DE SEGURIDAD: NO // CONTACTO REALIZADO POR WHATSAPP 10:49 a. m. 3/7/2025 SE VISITA COMERCIO, SE EVIDENCIA QUE EL CLIENTE NO TIENE UN PUNTO DE RED LISTO PARA CONECTAR EL EQUIPO CB BANCOLOMBIA A INSTALAR, EL CLIENTE INDICA QUE SI PODEMOS REPROGRAMAR LA VISITA PARA EL DÍA MIERCOLES 9 DE JULIO QUE YA TENDRÍA EL PUNTO DE INTERNET, SE INFORMA AL COORDINADOR QUIEN INDICA REPROGRAMAR VISITA PARA DICHA FECHA. 09-07 SE REALIZA INSTALACIÓN DE CORRESPONSAL, SE INSTALAN EQUIPOS CON PRUEBAS EXITOSAS, SE CAPACITA Y SE EVALÚA AL CLIENTE, SE INSTALA PUBLICIDAD COMPLETA, CB QUEDA OPERATIVO. USUARIO SOMOS BANCOLOMBIA ACTIVO | T8: VISITA _TECNICA | U8: F1ZZZ749 | V8: TIPO III | W8: TERRESTRE | X8: BUSTOS MORA DIEGO MANUEL | Y8: 0 | Z8: 0 | AA8: 0 | AB8: 0 | AC8: 1 | AD8: =IF(V8="TIPO I",'BASE LIQUIDACION'!$D$3,IF(V8="TIPO II",'BASE LIQUIDACION'!$D$4,IF(V8="TIPO III",'BASE LIQUIDACION'!$D$5,'BASE LIQUIDACION'!$D$7))) -> 222904.27 | AE8: =Y8*'BASE LIQUIDACION'!$B$12+Z8*'BASE LIQUIDACION'!$B$11+AA8*'BASE LIQUIDACION'!$B$13+AB8*'BASE LIQUIDACION'!$B$14+AC8*AD8 -> 222904.27
A9: NEIVA | B9: =VLOOKUP(A9,'CENTRO DE COSTOS'!A:D,4,FALSE) -> KEVIN ALEXIS CORZO BUSTOS | C9: =VLOOKUP(A9,'CENTRO DE COSTOS'!A:C,2,FALSE) -> 0004-0007 | D9: 18001 | E9: TA-25-821658 | F9: 79863 | G9: APERTURA | H9: CB CRECIMIENTO - OTRAS LISTAS | I9: CAQUETA | J9: FLORENCIA | K9: BARRIO CENTRO FLORENCIA 38 | L9: REDEBAN | M9: FO-25-1163140 | N9: 45839 | O9: 45840 | P9: UNO A UNO | Q9: UNO A UNO | R9: EJECUTADO/CANCELADO | S9: 01-07 SE REALIZA LLAMADA AL CLIENTE, SE HABLA CON LA SR JUAN CAMILO SANCHEZ SILVASE VALIDA DIRECCIÓN OK, CANAL OK, DISPONIBILIDAD TOTAL, LLAMAR EL DÍA LA INSTALACIÓN PARA CONFIRMAR VISITA, AVISO EXTERIOR ALTURA APROX 2.50 METROS; TOMACORRIENTE CERCANO: SI; TIENE CABINA DE SEGURIDAD: NO 2/7/2025 SALIÓ NUEVAMENTE ESTA APERTURA, SE REALIZÓ VISITA PARA IMPLEMENTACIÓN DEL CB 79863, PERO SE EVIDENCIA QUE EL COMERCIO ESTÁ UBICADO EN LA CARRERA 16 # 15 – 37 EN UN LOCAL DE ESA DIRECCIÓN, SIN EMBARGO EL USUARIO INDICA QUE AHÍ LA DIRECCIÓN ES CARRERA 16 # 15 – 36, NOS INDICA QUE CÁMARA DE COMERCIO Y RECIBO DE SERVICIOS PÚBLICOS APARECEN DE ESA FORMA, SE VALIDA LA ACERA DONDE EL USUARIO INDICA Y ESTA ES LA ACERA DONDE VAN LAS DIRECCIONES DE NÚMEROS IMPARES, ADICIONAL SE EVIDENCIA QUE PARA ESTA VISITA PEGARON UNA NOMENCLATURA CON LA DIRECCIÓN CARRERA 16 # 15 – 36 DONDE ESTA DEBE IR EN LA ACERA DEL FRENTE, PUES LA DEL FRENTE VAN LAS DIRECCIONES PARES TAMBIÉN SE VALIDAN EN LOS LOCALES QUE ESTÁN EN LA DIRECCIÓN Y SE EVIDENCIA QUE HAY UNO DICE QUE CARRERA 16 # 15 – 37 LOCAL 4, ADEMÁS DONDE EL USUARIO DICE INSTALAR TIENE OTRO NOMBRE DE COMERCIO DIFERENTE AL QUE SE RELACIONA EN LISTA DE CHEQUEO. SEGÚN LO CONVERSADO SE PROCEDE CON LA CANCELACIÓN DE LA APERTURA | T9: VISITA _TECNICA | U9: F1ZZZ594 | V9: TIPO IV | W9: TERRESTRE | X9: BERMUDEZ SANCHEZ JOSE NEYBER | Y9: 0 | Z9: 0 | AA9: 0 | AB9: 0 | AC9: 1 | AD9: =IF(V9="TIPO I",'BASE LIQUIDACION'!$D$3,IF(V9="TIPO II",'BASE LIQUIDACION'!$D$4,IF(V9="TIPO III",'BASE LIQUIDACION'!$D$5,'BASE LIQUIDACION'!$D$7))) -> 464809.03 | AE9: =Y9*'BASE LIQUIDACION'!$B$12+Z9*'BASE LIQUIDACION'!$B$11+AA9*'BASE LIQUIDACION'!$B$13+AB9*'BASE LIQUIDACION'!$B$14+AC9*AD9 -> 464809.03
A10: NEIVA | B10: =VLOOKUP(A10,'CENTRO DE COSTOS'!A:D,4,FALSE) -> KEVIN ALEXIS CORZO BUSTOS | C10: =VLOOKUP(A10,'CENTRO DE COSTOS'!A:C,2,FALSE) -> 0004-0007 | D10: 41001 | E10: TA-25-821800 | F10: 76738 | G10: APERTURA | H10: DATAFONO ADICIONAL | I10: HUILA | J10: NEIVA | K10: BARRIO IPANEMA NEIVA 2 | L10: REDEBAN | M10: FO-25-1163305 | N10: 45839 | O10: 45841 | P10: UNO A UNO | Q10: UNO A UNO | R10: EJECUTADO/CANCELADO | S10: 01-07 SE REALIZA LLAMADA AL CLIENTE, SE HABLA CON LA SR ERIK JESCE PERDOMO RODRIGUEZ SE VALIDA DIRECCIÓN OK, CANAL OK, DISPONIBILIDAD TOTAL, LLAMAR EL DÍA LA INSTALACIÓN PARA CONFIRMAR VISITA 3/7/2025 SE LLEGA A SITIO, SE ENCUENTRA LOCAL DESOCUPADO, SE LLAMA A CLIENTE E INDICA QUE YA NO NECESITA EL DATAFONO ADICIONAL. | T10: VISITA _TECNICA | U10: F1ZZZ785 | V10: TIPO I | W10: TERRESTRE | X10: DIAZ VARGAS JONATHAN MIGUEL | Y10: 0 | Z10: 0 | AA10: 0 | AB10: 0 | AC10: 1 | AD10: =IF(V10="TIPO I",'BASE LIQUIDACION'!$D$3,IF(V10="TIPO II",'BASE LIQUIDACION'!$D$4,IF(V10="TIPO III",'BASE LIQUIDACION'!$D$5,'BASE LIQUIDACION'!$D$7))) -> 44559.985 | AE10: =Y10*'BASE LIQUIDACION'!$B$12+Z10*'BASE LIQUIDACION'!$B$11+AA10*'BASE LIQUIDACION'!$B$13+AB10*'BASE LIQUIDACION'!$B$14+AC10*AD10 -> 44559.985
A11: PEREIRA | B11: =VLOOKUP(A11,'CENTRO DE COSTOS'!A:D,4,FALSE) -> DIEGO FERNANDO HENAO CARDONA | C11: =VLOOKUP(A11,'CENTRO DE COSTOS'!A:C,2,FALSE) -> 0004-0002 | D11: 66001 | E11: TA-25-831668 | F11: 80221 | G11: APERTURA | H11: CB CRECIMIENTO ALIANZA - NUEVO | I11: RISARALDA | J11: PEREIRA | K11: PTM PEREIRA SUPER SERVICIOS PU | L11: REDEBAN | M11: FO-25-1195655 | N11: 45841 | O11: 45846 | P11: AGREGADOR | Q11: COMCARD - PTM | R11: EJECUTADO | S11: 03-07 PROGRAMACIÓN REALIZADA POR LA ALIANZA 7/7/2025 SE REALIZA VISITA DE APERTURA AL CB PTM CON CÓDIGO 3007080221 PTM PEREIRA SUPERSERVICIOS , DIRECCIÓN CR 8 NO 15-20 LC 74 , COORDENADAS 4.813491, -75.691164, PERO SE ENCUENTRA CERCANÍA CON CORRESPONSAL UNO A UNO INSTALADO CON CÓDIGO 3007075477 BARRIO CENTRO PEREIRA 49 , DIRECCIÓN CR 8 14 73, COORDENADAS 4.813375,-75.690848, QUEDANDO A MENOS DE 30 MTS DE DISTANCIA UNO DEL OTRO , Y SE ENCUENTRA CERCANIA CON CORRESPONSAL DISTRICOL INSTALADO CON CODIGO 3007079902 DISTRICOL MULTICENTER, DIRECCION CR 8 15 62, CORDENADAS 4.813540,-75.691522, QUEDANDO A MENOS DE 40 MTS, SE REALIZA ESCALAMIENTO POR DOBLE CERCANÍA EN ESPERA DE COMO PROCEDER. / ENTIDAD APRUEBA INSTALACIÓN 8/7/2025 SE REALIZA INSTALACIÓN DE CORRESPONSAL, SE INSTALAN EQUIPOS CON PRUEBAS EXITOSAS, SE CAPACITA Y SE EVALÚA AL CLIENTE, SE INSTALA PUBLICIDAD COMPLETA, CB QUEDA OPERATIVO. USUARIO SOMOS BANCOLOMBIA ACTIVO | T11: VISITA _TECNICA | U11: F4ZZZ852 | V11: TIPO I | W11: TERRESTRE | X11: FRANCO CAÑAVERAL YAMID RAUL | Y11: 0 | Z11: 0 | AA11: 0 | AB11: 0 | AC11: 1 | AD11: =IF(V11="TIPO I",'BASE LIQUIDACION'!$D$3,IF(V11="TIPO II",'BASE LIQUIDACION'!$D$4,IF(V11="TIPO III",'BASE LIQUIDACION'!$D$5,'BASE LIQUIDACION'!$D$7))) -> 44559.985 | AE11: =Y11*'BASE LIQUIDACION'!$B$12+Z11*'BASE LIQUIDACION'!$B$11+AA11*'BASE LIQUIDACION'!$B$13+AB11*'BASE LIQUIDACION'!$B$14+AC11*AD11 -> 44559.985
A12: SINCELEJO | B12: =VLOOKUP(A12,'CENTRO DE COSTOS'!A:D,4,FALSE) -> JOSE MAURICIO HERNANDEZ ROJAS | C12: =VLOOKUP(A12,'CENTRO DE COSTOS'!A:C,2,FALSE) -> 0004-0001 | D12: 70001 | E12: TA-25-837839 | F12: 80305 | G12: APERTURA | H12: CB CRECIMIENTO - NUEVO | I12: SUCRE | J12: SINCELEJO | K12: BARRIO LA FE SINCELEJO 1 | L12: REDEBAN | M12: FO-25-1193644 | N12: 45845 | O12: 45846 | P12: UNO A UNO | Q12: UNO A UNO | R12: EJECUTADO/CANCELADO | S12: 5-07 SE REALIZA LLAMADA AL CLIENTE, SE HABLA CON EL FABIAN LIEVANO ROJAS, SE VALIDA DIRECCIÓN OK, CANAL OK, DISPONIBILIDAD TOTAL, LLAMAR EL DÍA LA INSTALACIÓN PARA CONFIRMAR VISITA, AVISO EXTERIOR ALTURA APROX DONDE EL TECNICO LO VEA CONVENIENTE, TOMACORRIENTE CERCANO: SI; TIENE CABINA DE SEGURIDAD: SI 8/7/2025 SE REALIZA VISITA PARA IMPLEMENTACIÓN DEL CB, PERO SE EVIDENCIA QUE EL PUNTO ESTÁ UBICADO EN LA DIRECCIÓN CRA 24 # 5 – 53, AUNQUE EL USUARIO MUESTRA CÁMARA DE COMERCIO Y RECIBO DE ENERGÍA ESTOS NO CORRESPONDEN A LA RELACIONADA EN LA LISTA DE CHEQUEO CR 24 24C 11,LA FE, POR TAL RAZÓN SE CANCELA ACTIVIDAD | T12: VISITA _TECNICA | U12: FAZZZ513 | V12: TIPO I | W12: TERRESTRE | X12: SANTOS GUZMAN CHRISTIAN FELIPE | Y12: 0 | Z12: 0 | AA12: 0 | AB12: 0 | AC12: 1 | AD12: =IF(V12="TIPO I",'BASE LIQUIDACION'!$D$3,IF(V12="TIPO II",'BASE LIQUIDACION'!$D$4,IF(V12="TIPO III",'BASE LIQUIDACION'!$D$5,'BASE LIQUIDACION'!$D$7))) -> 44559.985 | AE12: =Y12*'BASE LIQUIDACION'!$B$12+Z12*'BASE LIQUIDACION'!$B$11+AA12*'BASE LIQUIDACION'!$B$13+AB12*'BASE LIQUIDACION'!$B$14+AC12*AD12 -> 44559.985
A13: CALI | B13: =VLOOKUP(A13,'CENTRO DE COSTOS'!A:D,4,FALSE) -> DIEGO FERNANDO HENAO CARDONA | C13: =VLOOKUP(A13,'CENTRO DE COSTOS'!A:C,2,FALSE) -> 0004-0003 | D13: 76670 | E13: TA-25-837933 | F13: 80302 | G13: APERTURA | H13: CB CRECIMIENTO - NUEVO | I13: VALLE DEL CAUCA | J13: SAN PEDRO | K13: BARRIO JARDIN SAN PEDRO | L13: REDEBAN | M13: FO-25-1193861 | N13: 45845 | O13: 45847 | P13: UNO A UNO | Q13: UNO A UNO | R13: EJECUTADO/CANCELADO | S13: 07-07-2025 SE REALIZA LLAMADA AL CLIENTE, SE HABLA CON LA SRA ANDREA VILLALOBOS VAZQUEZOROZCO SE VALIDA DIRECCIÓN OK, CANAL OK, DISPONIBILIDAD TOTAL, LLAMAR EL DÍA LA INSTALACIÓN PARA CONFIRMAR VISITA, AVISO EXTERIOR ALTURA APROX 2 METROS; TOMACORRIENTE CERCANO: SI; TIENE CABINA DE SEGURIDAD: SI // CONTACTO REALIZADO POR LA APP 9/7/2025 SE VISITÓ COMERCIO, CLIENTE SIN ADECUACIÓN PARA INSTALACIÓN; NO HAY PUERTOS DE RED DISPONIBLES PARA INSTALACION DEL EQUIPO EN UBICACIÓN ASIGNADA. EN OFICINA PRINCIPAL NO ES POSIBLE INSTALAR DEBIDO A QUE NO PUEDE ATENDER A CLIENTES ALLÁ PORQUE ES RIESGOSO PARA EL COMERCIO A DEMÁS ES ZONA ADMINISTRATIVA NO ADECUADA PARA PARA ATENCIÓN. A DEMÁS TAMPOCO SE PUDO DEJAR PARCIALMENTE EQUIPO ALLÁ DEBIDO QUE TAMPOCO HAY PUERTOS DISPONIBLE. CLIENTE TOMA LA DECISIÓN DE RE PROGRAMAR E INDICA QUE VA REALIZAR LA ADECUACIÓN PARA QUE QUEDE OPERATIVO DE LA FORMA CORRECTA. | T13: VISITA _TECNICA | U13: FAZZZ539 | V13: TIPO II | W13: TERRESTRE | X13: BOLAÑOS TABORDA JORGE ENRIQUE | Y13: 0 | Z13: 0 | AA13: 0 | AB13: 0 | AC13: 1 | AD13: =IF(V13="TIPO I",'BASE LIQUIDACION'!$D$3,IF(V13="TIPO II",'BASE LIQUIDACION'!$D$4,IF(V13="TIPO III",'BASE LIQUIDACION'!$D$5,'BASE LIQUIDACION'!$D$7))) -> 134410.39 | AE13: =Y13*'BASE LIQUIDACION'!$B$12+Z13*'BASE LIQUIDACION'!$B$11+AA13*'BASE LIQUIDACION'!$B$13+AB13*'BASE LIQUIDACION'!$B$14+AC13*AD13 -> 134410.39
... A70: TUNJA | B70: =VLOOKUP(A70,'CENTRO DE COSTOS'!A:D,4,FALSE) -> MIGUEL JULIÁN HERNÁNDEZ GUARÍN | C70: =VLOOKUP(A70,'CENTRO DE COSTOS'!A:C,2,FALSE) -> 0004-0008 | D70: 15238 | E70: TA-25-904103 | F70: 80731 | G70: APERTURA | H70: CB CRECIMIENTO - NUEVO | I70: BOYACA | J70: DUITAMA | K70: BARRIO LA GRUTA DUITAMA 1 | L70: REDEBAN | M70: FO-25-1305107 | N70: 45868 | O70: 45869 | P70: UNO A UNO | Q70: UNO A UNO | R70: EJECUTADO | S70: 30-07 SE REALIZA LLAMADA AL CLIENTE, SE HABLA CON LA SR RUBEN ARMANDO LEAL SUAREZ SE VALIDA DIRECCIÓN OK, CANAL OK, DISPONIBILIDAD TOTAL, LLAMAR EL DÍA LA INSTALACIÓN PARA CONFIRMAR VISITA, AVISO EXTERIOR ALTURA APROX 2.5 METROS; TOMACORRIENTE CERCANO: SI; TIENE CABINA DE SEGURIDAD: NO - EL MODEM ESTA A 10 MT 31-07 SE REALIZA INSTALACIÓN DE CORRESPONSAL, SE INSTALAN EQUIPOS CON PRUEBAS EXITOSAS, SE CAPACITA Y SE EVALÚA AL CLIENTE, SE INSTALA PUBLICIDAD COMPLETA, CB QUEDA OPERATIVO. USUARIO SOMOS BANCOLOMBIA ACTIVO. SE INSTALA ROUTER | T70: VISITA _TECNICA | U70: VAZZZ391 | V70: TIPO II | W70: TERRESTRE | X70: RODRIGUEZ MURCIA YERSON IVAN | Y70: 0 | Z70: 0 | AA70: 0 | AB70: 1 | AC70: 0 | AD70: =IF(V70="TIPO I",'BASE LIQUIDACION'!$D$3,IF(V70="TIPO II",'BASE LIQUIDACION'!$D$4,IF(V70="TIPO III",'BASE LIQUIDACION'!$D$5,'BASE LIQUIDACION'!$D$7))) -> 134410.39 | AE70: =Y70*'BASE LIQUIDACION'!$B$12+Z70*'BASE LIQUIDACION'!$B$11+AA70*'BASE LIQUIDACION'!$B$13+AB70*'BASE LIQUIDACION'!$B$14+AC70*AD70 -> 306552.28
AE71: =SUM(AE2:AE70) -> 13282763

Sheet TIPOLOGIAS
A1: COD. CIUDAD | B1: CIUDAD | C1: DEPARTAMENTO | D1: DESDE DONDE SE ATIENDE | E1: TIPO DE TRAYECTO NUEVO | F1: TIPOLOGIA NUEVA
A2: 91430 | B2: LA VICTORIA | C2: AMAZONAS | D2: BOGOTA | E2: AEREO | F2: TIPO IV ESPECIAL
A3: 91669 | B3: PUERTO SANTANDER | C3: AMAZONAS | D3: BOGOTA | E3: AEREO | F3: TIPO IV ESPECIAL
A4: 91263 | B4: EL ENCANTO | C4: AMAZONAS | D4: BOGOTA | E4: AEREO | F4: TIPO IV ESPECIAL
A5: 91405 | B5: LA CHORRERA | C5: AMAZONAS | D5: BOGOTA | E5: AEREO | F5: TIPO IV ESPECIAL
A6: 91407 | B6: LA PEDRERA | C6: AMAZONAS | D6: BOGOTA | E6: AEREO | F6: TIPO IV ESPECIAL
A7: 91001 | B7: LETICIA | C7: AMAZONAS | D7: BOGOTA | E7: AEREO | F7: TIPO IV ESPECIAL
A8: 91460 | B8: MIRITI - PARANA | C8: AMAZONAS | D8: BOGOTA | E8: AEREO | F8: TIPO IV ESPECIAL
A9: 91530 | B9: PUERTO ALEGRIA | C9: AMAZONAS | D9: BOGOTA | E9: AEREO | F9: TIPO IV ESPECIAL
A10: 91536 | B10: PUERTO ARICA | C10: AMAZONAS | D10: BOGOTA | E10: AEREO | F10: TIPO IV ESPECIAL
A11: 91540 | B11: PUERTO NARIÑO | C11: AMAZONAS | D11: BOGOTA | E11: AEREO | F11: TIPO IV ESPECIAL
A12: 91798 | B12: TARAPACA | C12: AMAZONAS | D12: BOGOTA | E12: AEREO | F12: TIPO IV ESPECIAL
A13: 5055 | B13: ARGELIA | C13: ANTIOQUIA | D13: MEDELLIN | E13: TERRESTRE | F13: TIPO IV
... A1124: 23682 | B1124: SAN JOSE DE URE | C1124: CORDOBA | D1124: MONTERIA | E1124: TERRESTRE | F1124: TIPO III

Sheet INCIDENTES
A1: CIUDAD SEDE | B1: COORDINADOR | C1: CENTRO DE COSTOS LÍNEACOM | D1: CÓDIGO DANE | E1: TA/CODIGO ACTIVIDAD | F1: CODIGO CB | G1: ACTIVIDAD | H1: DEPARTAMENTO | I1: CIUDAD | J1: NOMBRE DEL CB | K1: RED | L1: FO | M1: FECHA ASIGNACIÓN A LÍNEA COMUNICACIONES (DD/MM/AAAA HH:MM) | N1: FECHA CIERRE DEL TICKET (DD/MM/AAAA HH:MM) | O1: ACOMETIDA | P1: GRUPO_FALLA | Q1: CATEGORÍA | R1: FALLA | S1: FORMATO | T1: CADENA | U1: ESTADO | V1: OBSERVACION | W1: FORMA DE ATENCIÓN | X1: TERMINAL | Y1: TIPIFICACION | Z1: TIPO DE TRAYECTO | AA1: NOMBRE DEL TECNICO | AB1: DIAS DE VISITA | AC1: ACOMETIDA DATOS | AD1: ACOMETIDA ELÉCTRICA | AE1: SWITCH | AF1: VALOR DIAS ACTIVIDAD FACTURABLES | AG1: VALOR DIAS ACOMPAÑAMIENTO FACTURABLES
A2: CUCUTA | B2: =VLOOKUP(A2,'CENTRO DE COSTOS'!A:D,4,FALSE) -> MIGUEL JULIÁN HERNÁNDEZ GUARÍN | C2: =VLOOKUP(A2,'CENTRO DE COSTOS'!A:D,2,FALSE) -> 0004-0008 | D2: 54001 | E2: 2373443 | F2: 74274 | G2: INCIDENTE | H2: NORTE DE SANTANDER | I2: CUCUTA | J2: BARRIO LA LIBERTAD CUCUTA 20 | K2: REDEBAN | L2: FO-25-1159231 | M2: 45839.408 | N2: 45839.622 | O2: NO | P2: USUARIO | Q2: MANTENIMIENTO | R2: MANTENIMIENTO GENERAL | S2: CB UNO A UNO | U2: CERRADO | V2: 01-07 SE ESCALA PARA VISITA. LLAMAR ANTES DE VISITAR, CONFIRMAR FALLA Y DATOS 0 01-07 SE REALIZÓ VISITA AL COMERCIO Y CLIENTE MANIFIESTA QUE SE LE CALLO EL CUBRE TECLADO, SE REALIZA MANTENIMIENTO Y SE COLOCA CUBRE TECLADO NUEVO | W2: VISITA_TÉCNICA | X2: MN3ZZ476 | Y2: TIPO I | Z2: TERRESTRE | AA2: MORA VEGA JEAMPIER | AB2: 1 | AC2: 0 | AD2: 0 | AE2: 0 | AF2: =IF(W2="SOPORTE_TELEFÓNICO",'BASE LIQUIDACION'!$B$10,IF(Y2="TIPO I",'BASE LIQUIDACION'!$C$3,IF(Y2="TIPO II",'BASE LIQUIDACION'!$C$4,IF(Y2="TIPO III",'BASE LIQUIDACION'!$C$5,'BASE LIQUIDACION'!$C$7)))) -> 65960.474 | AG2: =IF(W2="SOPORTE_TELEFÓNICO",'BASE LIQUIDACION'!$B$10,(AB2*AF2+AC2*'BASE LIQUIDACION'!$B$12+AD2*'BASE LIQUIDACION'!$B$11+INCIDENTES!AE2*'BASE LIQUIDACION'!$B$13)) -> 65960.474
A3: NEIVA | B3: =VLOOKUP(A3,'CENTRO DE COSTOS'!A:D,4,FALSE) -> KEVIN ALEXIS CORZO BUSTOS | C3: =VLOOKUP(A3,'CENTRO DE COSTOS'!A:D,2,FALSE) -> 0004-0007 | D3: 18001 | E3: 2373754 | F3: 76544 | G3: INCIDENTE | H3: CAQUETA | I3: FLORENCIA | J3: OPRAP EXITO GRAN PLAZA FLORENCIA | K3: REDEBAN | L3: FO-25-1159163 | M3: 45839.417 | N3: 45839.64 | O3: NO | P3: USUARIO | Q3: USUARIOS | R3: MALA MANIPULACION POS | S3: ROBUSTO | U3: CERRADO | V3: 01-07 SE ESCALA PARA VISITA. LLAMAR ANTES DE VISITAR, CONFIRMAR FALLA Y DATOS 0 01-07 SE LLEGA AL CB Y CB SE ENCUENTRA FUNCIONANDO CON NORMALIDAD, SE EVIDENCIA QUE EL USUARIO REALIZA MALA LA MANIPULACIÓN DEL DATÁFONO AL MOMENTO DE REALIZAR EL CIERRE Y ESTO GENERA EL LLENADO DE MEMORIA Y ENDE SE REINICIA EL DATÁFONO. | W3: VISITA_TÉCNICA | X3: 103ZZ224 | Y3: TIPO IV | Z3: TERRESTRE | AA3: BERMUDEZ SANCHEZ JOSE NEYBER | AB3: 1 | AC3: 0 | AD3: 0 | AE3: 0 | AF3: =IF(W3="SOPORTE_TELEFÓNICO",'BASE LIQUIDACION'!$B$10,IF(Y3="TIPO I",'BASE LIQUIDACION'!$C$3,IF(Y3="TIPO II",'BASE LIQUIDACION'!$C$4,IF(Y3="TIPO III",'BASE LIQUIDACION'!$C$5,'BASE LIQUIDACION'!$C$7)))) -> 479589.74 | AG3: =IF(W3="SOPORTE_TELEFÓNICO",'BASE LIQUIDACION'!$B$10,(AB3*AF3+AC3*'BASE LIQUIDACION'!$B$12+AD3*'BASE LIQUIDACION'!$B$11+INCIDENTES!AE3*'BASE LIQUIDACION'!$B$13)) -> 479589.74
A4: MEDELLIN | B4: =VLOOKUP(A4,'CENTRO DE COSTOS'!A:D,4,FALSE) -> JUAN SEBASTIÁN RÍOS CASTRILLÓN | C4: =VLOOKUP(A4,'CENTRO DE COSTOS'!A:D,2,FALSE) -> 0004-0005 | D4: 5001 | E4: 2376452 | F4: 78286 | G4: INCIDENTE | H4: ANTIOQUIA | I4: MEDELLIN | J4: BARRIO ROBLEDO MIRAMAR MEDELLIN 3 | K4: REDEBAN | L4: FO-25-1165748 | M4: 45839.547 | N4: 45839.651 | O4: NO | P4: USUARIO | Q4: LECTOR DE TARJETAS | R4: OBSTRUCCION DEL LECTOR | S4: CB UNO A UNO | U4: CERRADO | V4: 01-07 SE ESCALA PARA VISITA. LLAMAR ANTES DE VISITAR, CONFIRMAR FALLA Y DATOS 0 01-07 SE REALIZA MANTENIMIENTO GENERAL | W4: VISITA_TÉCNICA | X4: SXNZZ611 | Y4: TIPO I | Z4: TERRESTRE | AA4: HERNANDEZ CHAVARRIA JUAN CAMILO | AB4: 1 | AC4: 0 | AD4: 0 | AE4: 0 | AF4: =IF(W4="SOPORTE_TELEFÓNICO",'BASE LIQUIDACION'!$B$10,IF(Y4="TIPO I",'BASE LIQUIDACION'!$C$3,IF(Y4="TIPO II",'BASE LIQUIDACION'!$C$4,IF(Y4="TIPO III",'BASE LIQUIDACION'!$C$5,'BASE LIQUIDACION'!$C$7)))) -> 65960.474 | AG4: =IF(W4="SOPORTE_TELEFÓNICO",'BASE LIQUIDACION'!$B$10,(AB4*AF4+AC4*'BASE LIQUIDACION'!$B$12+AD4*'BASE LIQUIDACION'!$B$11+INCIDENTES!AE4*'BASE LIQUIDACION'!$B$13)) -> 65960.474
A5: VALLEDUPAR | B5: =VLOOKUP(A5,'CENTRO DE COSTOS'!A:D,4,FALSE) -> JOSE MAURICIO HERNANDEZ ROJAS | C5: =VLOOKUP(A5,'CENTRO DE COSTOS'!A:D,2,FALSE) -> 0004-0001 | D5: 20032 | E5: 2359858 | F5: 12343 | G5: INCIDENTE | H5: CESAR | I5: ASTREA | J5: ASTREA II - CESAR | K5: REDEBAN | L5: FO-25-1139132 | M5: 45834.497 | N5: 45839.658 | O5: NO | P5: USUARIO | Q5: LECTOR DE TARJETAS | R5: OBSTRUCCION DEL LECTOR | S5: CB UNO A UNO | U5: CERRADO | V5: 26-06 SE INTENTA COMUNICACION CON CB AL NUMERO 3106382156 SIN RESPUESTA, FAVOR LLAMAR A CLIENTE ANTES DE DESPLAZARSE PARA VALIDAR SOLICITUD Y DATOS 28/06/2025 SE REQUIERE CAMBIO DE EQUIPO Y POR LA HORA NO SE PODRIA REALIZAR DEBIDO A QUE SOPORTEDE REDEBAN NO LABORA DESPUES DE 1 PM 01-07 SE LLAMA A LA USUARIA LISETH RIVERA, LA CUAL INDICA QUE DURANTE TRES DIAS PRESENTABA FALLAS CON EL LECTOR DE TARJETA, YA QUE NO LEIA NINGUNA, PERO QUE DESPUES SE ARREGLO EL SERVICIO Y HASTA EL MOMENTO ESTA FUNCIONANDO CORRECTAMENTE SIN NINGUNA NOVEDAD, POR ENDE INDICA QUE NO REQUIERE VISITA TÉCNICA | W5: SOPORTE_TELEFÓNICO | X5: 0 | Y5: TIPO III | Z5: TERRESTRE | AA5: MONTES DIAZ JOHN FRED | AB5: 0 | AC5: 0 | AD5: 0 | AE5: 0 | AF5: =IF(W5="SOPORTE_TELEFÓNICO",'BASE LIQUIDACION'!$B$10,IF(Y5="TIPO I",'BASE LIQUIDACION'!$C$3,IF(Y5="TIPO II",'BASE LIQUIDACION'!$C$4,IF(Y5="TIPO III",'BASE LIQUIDACION'!$C$5,'BASE LIQUIDACION'!$C$7)))) -> 37904.654 | AG5: =IF(W5="SOPORTE_TELEFÓNICO",'BASE LIQUIDACION'!$B$10,(AB5*AF5+AC5*'BASE LIQUIDACION'!$B$12+AD5*'BASE LIQUIDACION'!$B$11+INCIDENTES!AE5*'BASE LIQUIDACION'!$B$13)) -> 37904.654
A6: CALI | B6: =VLOOKUP(A6,'CENTRO DE COSTOS'!A:D,4,FALSE) -> DIEGO FERNANDO HENAO CARDONA | C6: =VLOOKUP(A6,'CENTRO DE COSTOS'!A:D,2,FALSE) -> 0004-0003 | D6: 76111 | E6: 2379555 | F6: 15527 | G6: INCIDENTE | H6: VALLE DEL CAUCA | I6: GUADALAJARA DE BUGA | J6: MULTIPAGAS BUGA | K6: REDEBAN | L6: FO-25-1169391 | M6: 45840.333 | N6: 45840.426 | O6: NO | P6: USUARIO | Q6: USUARIOS | R6: USUARIOS BLOQUEADOS | S6: ROBUSTO | U6: CERRADO | V6: 02-07 SE ESCALA PARA VISITA. LLAMAR ANTES DE VISITAR, CONFIRMAR FALLA Y DATOS 0 02-07 SE LLAMA A LA SEÑORA KELLY PARA VALIDAR INCIDENTE, PERO INDICA QUE ESTA MAÑANA AL LLEGAR Y REALIZAR EL CIERRE YA LES FUNCIONO NORMAL, AL PARECER EL USUARIO ESTABA COMO BLOQUEADO, EL DATAFONO YA ESTA OPERANDO NORMALMENTE. | W6: SOPORTE_TELEFÓNICO | X6: 0 | Y6: TIPO II | Z6: TERRESTRE | AA6: HENAO CARDONA DIEGO FERNANDO | AB6: 0 | AC6: 0 | AD6: 0 | AE6: 0 | AF6: =IF(W6="SOPORTE_TELEFÓNICO",'BASE LIQUIDACION'!$B$10,IF(Y6="TIPO I",'BASE LIQUIDACION'!$C$3,IF(Y6="TIPO II",'BASE LIQUIDACION'!$C$4,IF(Y6="TIPO III",'BASE LIQUIDACION'!$C$5,'BASE LIQUIDACION'!$C$7)))) -> 37904.654 | AG6: =IF(W6="SOPORTE_TELEFÓNICO",'BASE LIQUIDACION'!$B$10,(AB6*AF6+AC6*'BASE LIQUIDACION'!$B$12+AD6*'BASE LIQUIDACION'!$B$11+INCIDENTES!AE6*'BASE LIQUIDACION'!$B$13)) -> 37904.654
A7: MEDELLIN | B7: =VLOOKUP(A7,'CENTRO DE COSTOS'!A:D,4,FALSE) -> JUAN SEBASTIÁN RÍOS CASTRILLÓN | C7: =VLOOKUP(A7,'CENTRO DE COSTOS'!A:D,2,FALSE) -> 0004-0005 | D7: 5088 | E7: 2377476 | F7: 74249 | G7: INCIDENTE | H7: ANTIOQUIA | I7: BELLO | J7: DISTRICOL FERRO DEPÓSITO JUAN | K7: REDEBAN | L7: FO-25-1167175 | M7: 45839.618 | N7: 45840.458 | O7: NO | P7: USUARIO | Q7: MANTENIMIENTO | R7: MANTENIMIENTO GENERAL | S7: AGREGADOR | U7: CERRADO | V7: 01-07 SE ESCALA PARA VISITA. LLAMAR ANTES DE VISITAR, CONFIRMAR FALLA Y DATOS 0 02-07 SE REALIZA MANTENIMIENTO AL EQUIPO | W7: VISITA_TÉCNICA | X7: MN3ZZ451 | Y7: TIPO I | Z7: TERRESTRE | AA7: CERPA SUAREZ DUVAN CAMILO | AB7: 1 | AC7: 0 | AD7: 0 | AE7: 0 | AF7: =IF(W7="SOPORTE_TELEFÓNICO",'BASE LIQUIDACION'!$B$10,IF(Y7="TIPO I",'BASE LIQUIDACION'!$C$3,IF(Y7="TIPO II",'BASE LIQUIDACION'!$C$4,IF(Y7="TIPO III",'BASE LIQUIDACION'!$C$5,'BASE LIQUIDACION'!$C$7)))) -> 65960.474 | AG7: =IF(W7="SOPORTE_TELEFÓNICO",'BASE LIQUIDACION'!$B$10,(AB7*AF7+AC7*'BASE LIQUIDACION'!$B$12+AD7*'BASE LIQUIDACION'!$B$11+INCIDENTES!AE7*'BASE LIQUIDACION'!$B$13)) -> 65960.474
A8: MEDELLIN | B8: =VLOOKUP(A8,'CENTRO DE COSTOS'!A:D,4,FALSE) -> JUAN SEBASTIÁN RÍOS CASTRILLÓN | C8: =VLOOKUP(A8,'CENTRO DE COSTOS'!A:D,2,FALSE) -> 0004-0005 | D8: 5001 | E8: 2378083 | F8: 10228 | G8: INCIDENTE | H8: ANTIOQUIA | I8: MEDELLIN | J8: BARRIO MANRIQUE ORIENTAL | K8: REDEBAN | L8: FO-25-1167420 | M8: 45839.654 | N8: 45840.466 | O8: NO | P8: USUARIO | Q8: MANTENIMIENTO | R8: MANTENIMIENTO GENERAL | S8: CB UNO A UNO | U8: CERRADO | V8: 01-07 SE ESCALA PARA VISITA. LLAMAR ANTES DE VISITAR, CONFIRMAR FALLA Y DATOS 0 02-07 SE LLEGÓ A SITIO CORRESPONSAL INFORMA QUE EL EQUIPO SE ENCUENTRA FUNCIONANDO NORMALMENTE | W8: VISITA_TÉCNICA | X8: JRZZZ707 | Y8: TIPO I | Z8: TERRESTRE | AA8: CASTAÑEDA PALACIO CARLOS FELIPE | AB8: 1 | AC8: 0 | AD8: 0 | AE8: 0 | AF8: =IF(W8="SOPORTE_TELEFÓNICO",'BASE LIQUIDACION'!$B$10,IF(Y8="TIPO I",'BASE LIQUIDACION'!$C$3,IF(Y8="TIPO II",'BASE LIQUIDACION'!$C$4,IF(Y8="TIPO III",'BASE LIQUIDACION'!$C$5,'BASE LIQUIDACION'!$C$7)))) -> 65960.474 | AG8: =IF(W8="SOPORTE_TELEFÓNICO",'BASE LIQUIDACION'!$B$10,(AB8*AF8+AC8*'BASE LIQUIDACION'!$B$12+AD8*'BASE LIQUIDACION'!$B$11+INCIDENTES!AE8*'BASE LIQUIDACION'!$B$13)) -> 65960.474
A9: PEREIRA | B9: =VLOOKUP(A9,'CENTRO DE COSTOS'!A:D,4,FALSE) -> DIEGO FERNANDO HENAO CARDONA | C9: =VLOOKUP(A9,'CENTRO DE COSTOS'!A:D,2,FALSE) -> 0004-0002 | D9: 76147 | E9: 2380625 | F9: 59182 | G9: INCIDENTE | H9: VALLE DEL CAUCA | I9: CARTAGO | J9: BARRIO GUAYACANES CARTAGO | K9: REDEBAN | L9: FO-25-1171516 | M9: 45840.347 | N9: 45840.472 | O9: NO | P9: USUARIO | Q9: NO ENCIENDE | R9: CONEXIONES DE COMERCIO | S9: CB UNO A UNO | U9: CERRADO | V9: 02-07 SE ESCALA PARA VISITA. LLAMAR ANTES DE VISITAR, CONFIRMAR FALLA Y DATOS 0 02-07 SE REALIZA VALIDACION CON EL SEÑOR ALEJANDRO QUIEN REPORTA PROBLEMAS CON EL PIN PAD, SE REVISA CONEXIONES Y SE ENCUENTRA QUE EL PIN PAD NO ESTA BIEN CONECTADO, SE PROCCEDE A REALIZAR CONEXION CORRECTA Y EL SERVICIO EMPIEZA A OPERAR SIN PROBLEMAS. | W9: SOPORTE_TELEFÓNICO | X9: 0 | Y9: TIPO I | Z9: TERRESTRE | AA9: HENAO CARDONA DIEGO FERNANDO | AB9: 0 | AC9: 0 | AD9: 0 | AE9: 0 | AF9: =IF(W9="SOPORTE_TELEFÓNICO",'BASE LIQUIDACION'!$B$10,IF(Y9="TIPO I",'BASE LIQUIDACION'!$C$3,IF(Y9="TIPO II",'BASE LIQUIDACION'!$C$4,IF(Y9="TIPO III",'BASE LIQUIDACION'!$C$5,'BASE LIQUIDACION'!$C$7)))) -> 37904.654 | AG9: =IF(W9="SOPORTE_TELEFÓNICO",'BASE LIQUIDACION'!$B$10,(AB9*AF9+AC9*'BASE LIQUIDACION'!$B$12+AD9*'BASE LIQUIDACION'!$B$11+INCIDENTES!AE9*'BASE LIQUIDACION'!$B$13)) -> 37904.654
A10: MEDELLIN | B10: =VLOOKUP(A10,'CENTRO DE COSTOS'!A:D,4,FALSE) -> JUAN SEBASTIÁN RÍOS CASTRILLÓN | C10: =VLOOKUP(A10,'CENTRO DE COSTOS'!A:D,2,FALSE) -> 0004-0005 | D10: 5308 | E10: 2378675 | F10: 41627 | G10: INCIDENTE | H10: ANTIOQUIA | I10: GIRARDOTA | J10: BARRIO GIRARDOTA GIRARDOTA | K10: REDEBAN | L10: FO-25-1168257 | M10: 45839.685 | N10: 45840.491 | O10: NO | P10: USUARIO | Q10: MANTENIMIENTO | R10: MANTENIMIENTO GENERAL | S10: CB UNO A UNO | U10: CERRADO | V10: 01-07 SE ESCALA PARA VISITA. LLAMAR ANTES DE VISITAR, CONFIRMAR FALLA Y DATOS 0 02-07 SE REALIZA MANTENIMIENTO Y SE CONECTA CABLE DE PODER BIEN | W10: VISITA_TÉCNICA | X10: EF01Z882 | Y10: TIPO I | Z10: TERRESTRE | AA10: CERPA SUAREZ DUVAN CAMILO | AB10: 1 | AC10: 0 | AD10: 0 | AE10: 0 | AF10: =IF(W10="SOPORTE_TELEFÓNICO",'BASE LIQUIDACION'!$B$10,IF(Y10="TIPO I",'BASE LIQUIDACION'!$C$3,IF(Y10="TIPO II",'BASE LIQUIDACION'!$C$4,IF(Y10="TIPO III",'BASE LIQUIDACION'!$C$5,'BASE LIQUIDACION'!$C$7)))) -> 65960.474 | AG10: =IF(W10="SOPORTE_TELEFÓNICO",'BASE LIQUIDACION'!$B$10,(AB10*AF10+AC10*'BASE LIQUIDACION'!$B$12+AD10*'BASE LIQUIDACION'!$B$11+INCIDENTES!AE10*'BASE LIQUIDACION'!$B$13)) -> 65960.474
A11: BOGOTA | B11: =VLOOKUP(A11,'CENTRO DE COSTOS'!A:D,4,FALSE) -> WILLIAM ASDRUBAL ROZO ROZO | C11: =VLOOKUP(A11,'CENTRO DE COSTOS'!A:D,2,FALSE) -> 0004-0004 | D11: 11001 | E11: 2379253 | F11: 60017 | G11: INCIDENTE | H11: CUNDINAMARCA | I11: BOGOTA | J11: PTM BOGOTA PUNTOSERVICE BOGOT | K11: REDEBAN | L11: FO-25-1169432 | M11: 45839.719 | N11: 45840.494 | O11: NO | P11: USUARIO | Q11: COMUNICACION | R11: CANAL DEL COMERCIO | S11: AGREGADOR | U11: CERRADO | V11: 01-07 SE ESCALA PARA VISITA. LLAMAR ANTES DE VISITAR, CONFIRMAR FALLA Y DATOS 0 02-07 SE REALIZA DESPLAZAMIENTO A DIRECCIÓN DE COMERCIO, SE ENCUENTRA COMERCIO CERRADO, PERSONA QUE ATIENDE POR UNA VENTANA DEL 3 PISO DEL PREDIO SE COMUNICA CON LA SRA. CLAUDIA Y ELLA LE INDICA QUE LLAMO A CANCELAR LA VISITA POR QUÉ LA FALLA ES DEL SERVICIO DE INTERNET DEL PREDIO. | W11: VISITA_TÉCNICA | X11: MA00B423 | Y11: TIPO I | Z11: TERRESTRE | AA11: MURCIA HERNANDEZ HARVEY IGNACIO | AB11: 1 | AC11: 0 | AD11: 0 | AE11: 0 | AF11: =IF(W11="SOPORTE_TELEFÓNICO",'BASE LIQUIDACION'!$B$10,IF(Y11="TIPO I",'BASE LIQUIDACION'!$C$3,IF(Y11="TIPO II",'BASE LIQUIDACION'!$C$4,IF(Y11="TIPO III",'BASE LIQUIDACION'!$C$5,'BASE LIQUIDACION'!$C$7)))) -> 65960.474 | AG11: =IF(W11="SOPORTE_TELEFÓNICO",'BASE LIQUIDACION'!$B$10,(AB11*AF11+AC11*'BASE LIQUIDACION'!$B$12+AD11*'BASE LIQUIDACION'!$B$11+INCIDENTES!AE11*'BASE LIQUIDACION'!$B$13)) -> 65960.474
A12: MEDELLIN | B12: =VLOOKUP(A12,'CENTRO DE COSTOS'!A:D,4,FALSE) -> JUAN SEBASTIÁN RÍOS CASTRILLÓN | C12: =VLOOKUP(A12,'CENTRO DE COSTOS'!A:D,2,FALSE) -> 0004-0005 | D12: 5631 | E12: 2379765 | F12: 79007 | G12: INCIDENTE | H12: ANTIOQUIA | I12: SABANETA | J12: PTM SABANETA PAPELERIA Y RECAR | K12: REDEBAN | L12: FO-25-1171187 | M12: 45840.333 | N12: 45840.553 | O12: NO | P12: USUARIO | Q12: CIERRE | R12: COMERCIO NO REALIZA CIERRE | S12: AGREGADOR | U12: CERRADO | V12: 02-07 SE ESCALA PARA VISITA. LLAMAR ANTES DE VISITAR, CONFIRMAR FALLA Y DATOS 0 02-07 SE REALIZA AJUSTES SOBRE LOS CIERRES | W12: VISITA_TÉCNICA | X12: FATZZ894 | Y12: TIPO I | Z12: TERRESTRE | AA12: HERNANDEZ CHAVARRIA JUAN CAMILO | AB12: 1 | AC12: 0 | AD12: 0 | AE12: 0 | AF12: =IF(W12="SOPORTE_TELEFÓNICO",'BASE LIQUIDACION'!$B$10,IF(Y12="TIPO I",'BASE LIQUIDACION'!$C$3,IF(Y12="TIPO II",'BASE LIQUIDACION'!$C$4,IF(Y12="TIPO III",'BASE LIQUIDACION'!$C$5,'BASE LIQUIDACION'!$C$7)))) -> 65960.474 | AG12: =IF(W12="SOPORTE_TELEFÓNICO",'BASE LIQUIDACION'!$B$10,(AB12*AF12+AC12*'BASE LIQUIDACION'!$B$12+AD12*'BASE LIQUIDACION'!$B$11+INCIDENTES!AE12*'BASE LIQUIDACION'!$B$13)) -> 65960.474
A13: MEDELLIN | B13: =VLOOKUP(A13,'CENTRO DE COSTOS'!A:D,4,FALSE) -> JUAN SEBASTIÁN RÍOS CASTRILLÓN | C13: =VLOOKUP(A13,'CENTRO DE COSTOS'!A:D,2,FALSE) -> 0004-0005 | D13: 5088 | E13: 2381539 | F13: 80073 | G13: INCIDENTE | H13: ANTIOQUIA | I13: BELLO | J13: BARRIO LA GABRIELA CALLE VIEJA BELLO 4 | K13: REDEBAN | L13: FO-25-1172101 | M13: 45840.39 | N13: 45840.554 | O13: NO | P13: USUARIO | Q13: MANTENIMIENTO | R13: MANTENIMIENTO GENERAL | S13: CB UNO A UNO | U13: CERRADO | V13: 02-07 SE ESCALA PARA VISITA. LLAMAR ANTES DE VISITAR, CONFIRMAR FALLA Y DATOS 0 02-07 SE REALIZÓ LIMPIEZA DE IMPRESORA POS OK | W13: VISITA_TÉCNICA | X13: SAXZZ552 | Y13: TIPO I | Z13: TERRESTRE | AA13: CASTAÑEDA PALACIO CARLOS FELIPE | AB13: 1 | AC13: 0 | AD13: 0 | AE13: 0 | AF13: =IF(W13="SOPORTE_TELEFÓNICO",'BASE LIQUIDACION'!$B$10,IF(Y13="TIPO I",'BASE LIQUIDACION'!$C$3,IF(Y13="TIPO II",'BASE LIQUIDACION'!$C$4,IF(Y13="TIPO III",'BASE LIQUIDACION'!$C$5,'BASE LIQUIDACION'!$C$7)))) -> 65960.474 | AG13: =IF(W13="SOPORTE_TELEFÓNICO",'BASE LIQUIDACION'!$B$10,(AB13*AF13+AC13*'BASE LIQUIDACION'!$B$12+AD13*'BASE LIQUIDACION'!$B$11+INCIDENTES!AE13*'BASE LIQUIDACION'!$B$13)) -> 65960.474
A14: MEDELLIN | B14: =VLOOKUP(A14,'CENTRO DE COSTOS'!A:D,4,FALSE) -> JUAN SEBASTIÁN RÍOS CASTRILLÓN | C14: =VLOOKUP(A14,'CENTRO DE COSTOS'!A:D,2,FALSE) -> 0004-0005 | D14: 5088 | E14: 2383581 | F14: 66013 | G14: INCIDENTE | H14: ANTIOQUIA | I14: BELLO | J14: BARRIO NIQUIA BELLO 16 | K14: REDEBAN | L14: FO-25-1173213 | M14: 45840.481 | N14: 45840.558 | O14: NO | P14: USUARIO | Q14: MANTENIMIENTO | R14: MANTENIMIENTO GENERAL | S14: CB UNO A UNO | U14: CERRADO | V14: 02-07 SE ESCALA PARA VISITA. LLAMAR ANTES DE VISITAR, CONFIRMAR FALLA Y DATOS 0 02-07 SE REALIZA MANTENIMIENTO AL EQUIPO Y SE CONECTA FUENTE DE PODER | W14: VISITA_TÉCNICA | X14: 9A00N419 | Y14: TIPO I | Z14: TERRESTRE | AA14: CERPA SUAREZ DUVAN CAMILO | AB14: 1 | AC14: 0 | AD14: 0 | AE14: 0 | AF14: =IF(W14="SOPORTE_TELEFÓNICO",'BASE LIQUIDACION'!$B$10,IF(Y14="TIPO I",'BASE LIQUIDACION'!$C$3,IF(Y14="TIPO II",'BASE LIQUIDACION'!$C$4,IF(Y14="TIPO III",'BASE LIQUIDACION'!$C$5,'BASE LIQUIDACION'!$C$7)))) -> 65960.474 | AG14: =IF(W14="SOPORTE_TELEFÓNICO",'BASE LIQUIDACION'!$B$10,(AB14*AF14+AC14*'BASE LIQUIDACION'!$B$12+AD14*'BASE LIQUIDACION'!$B$11+INCIDENTES!AE14*'BASE LIQUIDACION'!$B$13)) -> 65960.474
A15: IBAGUE | B15: =VLOOKUP(A15,'CENTRO DE COSTOS'!A:D,4,FALSE) -> KEVIN ALEXIS CORZO BUSTOS | C15: =VLOOKUP(A15,'CENTRO DE COSTOS'!A:D,2,FALSE) -> 0004-0007 | D15: 73585 | E15: 2384587 | F15: 28326 | G15: INCIDENTE | H15: TOLIMA | I15: PURIFICACION | J15: ARA0354 PURIFICACION ZONA SU | K15: REDEBAN | L15: FO-25-1175014 | M15: 45840.582 | N15: 45840.628 | O15: NO | P15: USUARIO | Q15: MANTENIMIENTO | R15: MANTENIMIENTO GENERAL | S15: RETAIL | U15: CERRADO | V15: 02-07 SE ESCALA A LA RED - SE PROCEDE A CERRAR YA QUE NO ATENDEMOS CADENA ARA ..02-07 RESPUESTA DE LA RED: TU SOLICITUD REFERENTE A GENERACIÓN DE CASOS CB ARA BANCOLOMBIA QUEDÓ RADICADA BAJO EL TICKET NÚMERO 5697837 AL ÁREA ENCARGADA. 0 | W15: SOPORTE_TELEFÓNICO | X15: 0 | Y15: TIPO II | Z15: TERRESTRE | AA15: 0 | AB15: 0 | AC15: 0 | AD15: 0 | AE15: 0 | AF15: =IF(W15="SOPORTE_TELEFÓNICO",'BASE LIQUIDACION'!$B$10,IF(Y15="TIPO I",'BASE LIQUIDACION'!$C$3,IF(Y15="TIPO II",'BASE LIQUIDACION'!$C$4,IF(Y15="TIPO III",'BASE LIQUIDACION'!$C$5,'BASE LIQUIDACION'!$C$7)))) -> 37904.654 | AG15: =IF(W15="SOPORTE_TELEFÓNICO",'BASE LIQUIDACION'!$B$10,(AB15*AF15+AC15*'BASE LIQUIDACION'!$B$12+AD15*'BASE LIQUIDACION'!$B$11+INCIDENTES!AE15*'BASE LIQUIDACION'!$B$13)) -> 37904.654
A16: CALI | B16: =VLOOKUP(A16,'CENTRO DE COSTOS'!A:D,4,FALSE) -> DIEGO FERNANDO HENAO CARDONA | C16: =VLOOKUP(A16,'CENTRO DE COSTOS'!A:D,2,FALSE) -> 0004-0003 | D16: 19001 | E16: 2379720 | F16: 69029 | G16: INCIDENTE | H16: CAUCA | I16: POPAYAN | J16: BARRIO BELMONTE POPAYAN | K16: REDEBAN | L16: FO-25-1171196 | M16: 45840.333 | N16: 45840.683 | O16: NO | P16: ENTIDAD | Q16: ERROR DE TRANSACCIONES | R16: TIPO DE TARJETA INVALIDA | S16: CB UNO A UNO | U16: CERRADO | V16: 02-07 SE ESCALA PARA VISITA. LLAMAR ANTES DE VISITAR, CONFIRMAR FALLA Y DATOS 0 02-07 SE LLEGA AL SITIO SE ENCUENTRA EQUIPO OK SE LLAMA ALA LÍNEA CORRESPONSALES INFORMAN PRESENTA BLOQUEO POR LA ENTIDAD POR TEMA COMPENSACION | W16: VISITA_TÉCNICA | X16: 9T1ZZ294 | Y16: TIPO III | Z16: TERRESTRE | AA16: GIMBUEL LASSO LUIS GERMAN | AB16: 1 | AC16: 0 | AD16: 0 | AE16: 0 | AF16: =IF(W16="SOPORTE_TELEFÓNICO",'BASE LIQUIDACION'!$B$10,IF(Y16="TIPO I",'BASE LIQUIDACION'!$C$3,IF(Y16="TIPO II",'BASE LIQUIDACION'!$C$4,IF(Y16="TIPO III",'BASE LIQUIDACION'!$C$5,'BASE LIQUIDACION'!$C$7)))) -> 275728.38 | AG16: =IF(W16="SOPORTE_TELEFÓNICO",'BASE LIQUIDACION'!$B$10,(AB16*AF16+AC16*'BASE LIQUIDACION'!$B$12+AD16*'BASE LIQUIDACION'!$B$11+INCIDENTES!AE16*'BASE LIQUIDACION'!$B$13)) -> 275728.38
A17: BOGOTA | B17: =VLOOKUP(A17,'CENTRO DE COSTOS'!A:D,4,FALSE) -> WILLIAM ASDRUBAL ROZO ROZO | C17: =VLOOKUP(A17,'CENTRO DE COSTOS'!A:D,2,FALSE) -> 0004-0004 | D17: 11001 | E17: 2384573 | F17: 18902 | G17: INCIDENTE | H17: CUNDINAMARCA | I17: BOGOTA | J17: PAGAFACIL CENTRO DE PAGOS LA 9 | K17: REDEBAN | L17: FO-25-1174015 | M17: 45840.58 | N17: 45841.476 | O17: NO | P17: USUARIO | Q17: USUARIOS | R17: USUARIOS BLOQUEADOS | S17: ROBUSTO | U17: CERRADO | V17: 02-07 SE ESCALA PARA VISITA. LLAMAR ANTES DE VISITAR, CONFIRMAR FALLA Y DATOS 0 03-07 SE RESTABLECEN CLAVES COMERCIO REALIZA PRUEBAS REALIZANDO EL CIERRE NO SE REALIZA PRUEBAS DE TRANSACCIÓNES DEBIDO A QUE LA CAJA NO LA ESTÁN USANDO Y NO LA PUEDEB ABRIR HASTA MAÑANA | W17: VISITA_TÉCNICA | X17: XRZZZ663 | Y17: TIPO I | Z17: TERRESTRE | AA17: MICHELI LOPEZ MIGUEL ANGEL | AB17: 1 | AC17: 0 | AD17: 0 | AE17: 0 | AF17: =IF(W17="SOPORTE_TELEFÓNICO",'BASE LIQUIDACION'!$B$10,IF(Y17="TIPO I",'BASE LIQUIDACION'!$C$3,IF(Y17="TIPO II",'BASE LIQUIDACION'!$C$4,IF(Y17="TIPO III",'BASE LIQUIDACION'!$C$5,'BASE LIQUIDACION'!$C$7)))) -> 65960.474 | AG17: =IF(W17="SOPORTE_TELEFÓNICO",'BASE LIQUIDACION'!$B$10,(AB17*AF17+AC17*'BASE LIQUIDACION'!$B$12+AD17*'BASE LIQUIDACION'!$B$11+INCIDENTES!AE17*'BASE LIQUIDACION'!$B$13)) -> 65960.474
A18: CALI | B18: =VLOOKUP(A18,'CENTRO DE COSTOS'!A:D,4,FALSE) -> DIEGO FERNANDO HENAO CARDONA | C18: =VLOOKUP(A18,'CENTRO DE COSTOS'!A:D,2,FALSE) -> 0004-0003 | D18: 76001 | E18: 2388444 | F18: 53834 | G18: INCIDENTE | H18: VALLE DEL CAUCA | I18: CALI | J18: BARRIO FLORESTA CALI 2 | K18: REDEBAN | L18: FO-25-1176899 | M18: 45841.356 | N18: 45841.494 | O18: NO | P18: USUARIO | Q18: CIERRE | R18: COMERCIO NO REALIZA CIERRE | S18: CB UNO A UNO | U18: CERRADO | V18: 03-07 SE ESCALA PARA VISITA. LLAMAR ANTES DE VISITAR, CONFIRMAR FALLA Y DATOS 0 03-07 SE REALIZA LLAMADA AL CLIENTE , SE VALIDA INCONVENIENTE, EL CLIENTE ESTABA DIGITANDO UNA CLAVE PARA CIERRES ERRADA, SE LE INDICA QUE LA CLAVE ESTANDAR ES 1526, EL CLIENTE PROCEDE A REALIZAR PRUEBAS Y INGRESA AL CIERRE CORRECTAMENTE. | W18: SOPORTE_TELEFÓNICO | X18: 0 | Y18: TIPO I | Z18: TERRESTRE | AA18: HENAO CARDONA DIEGO FERNANDO | AB18: 0 | AC18: 0 | AD18: 0 | AE18: 0 | AF18: =IF(W18="SOPORTE_TELEFÓNICO",'BASE LIQUIDACION'!$B$10,IF(Y18="TIPO I",'BASE LIQUIDACION'!$C$3,IF(Y18="TIPO II",'BASE LIQUIDACION'!$C$4,IF(Y18="TIPO III",'BASE LIQUIDACION'!$C$5,'BASE LIQUIDACION'!$C$7)))) -> 37904.654 | AG18: =IF(W18="SOPORTE_TELEFÓNICO",'BASE LIQUIDACION'!$B$10,(AB18*AF18+AC18*'BASE LIQUIDACION'!$B$12+AD18*'BASE LIQUIDACION'!$B$11+INCIDENTES!AE18*'BASE LIQUIDACION'!$B$13)) -> 37904.654
A19: MEDELLIN | B19: =VLOOKUP(A19,'CENTRO DE COSTOS'!A:D,4,FALSE) -> JUAN SEBASTIÁN RÍOS CASTRILLÓN | C19: =VLOOKUP(A19,'CENTRO DE COSTOS'!A:D,2,FALSE) -> 0004-0005 | D19: 5001 | E19: 2389782 | F19: 79923 | G19: INCIDENTE | H19: ANTIOQUIA | I19: MEDELLIN | J19: DISTRICOL EL MERCADO J&S PARQU | K19: REDEBAN | L19: FO-25-1177953 | M19: 45841.432 | N19: 45841.635 | O19: NO | P19: USUARIO | Q19: MANTENIMIENTO | R19: MANTENIMIENTO GENERAL | S19: AGREGADOR | U19: CERRADO | V19: 03-07 SE ESCALA PARA VISITA. LLAMAR ANTES DE VISITAR, CONFIRMAR FALLA Y DATOS 0 03-07 SE REALIZA MANTENIMIENTO AL EQUIPO TODO ESTÁ EN BUEN FUNCIONAMIENTO | W19: VISITA_TÉCNICA | X19: SAUZZ938 | Y19: TIPO I | Z19: TERRESTRE | AA19: CERPA SUAREZ DUVAN CAMILO | AB19: 1 | AC19: 0 | AD19: 0 | AE19: 0 | AF19: =IF(W19="SOPORTE_TELEFÓNICO",'BASE LIQUIDACION'!$B$10,IF(Y19="TIPO I",'BASE LIQUIDACION'!$C$3,IF(Y19="TIPO II",'BASE LIQUIDACION'!$C$4,IF(Y19="TIPO III",'BASE LIQUIDACION'!$C$5,'BASE LIQUIDACION'!$C$7)))) -> 65960.474 | AG19: =IF(W19="SOPORTE_TELEFÓNICO",'BASE LIQUIDACION'!$B$10,(AB19*AF19+AC19*'BASE LIQUIDACION'!$B$12+AD19*'BASE LIQUIDACION'!$B$11+INCIDENTES!AE19*'BASE LIQUIDACION'!$B$13)) -> 65960.474
A20: PASTO | B20: =VLOOKUP(A20,'CENTRO DE COSTOS'!A:D,4,FALSE) -> DIEGO FERNANDO HENAO CARDONA | C20: =VLOOKUP(A20,'CENTRO DE COSTOS'!A:D,2,FALSE) -> 0004-0003 | D20: 52356 | E20: 2386804 | F20: 44682 | G20: INCIDENTE | H20: NARIÑO | I20: IPIALES | J20: PTM IPIALES MISCELANEA Y PAPEL | K20: REDEBAN | L20: FO-25-1175433 | M20: 45840.691 | N20: 45841.644 | O20: NO | P20: USUARIO | Q20: MANTENIMIENTO | R20: MANTENIMIENTO GENERAL | S20: AGREGADOR | U20: CERRADO | V20: 02-07 SE ESCALA PARA VISITA. LLAMAR ANTES DE VISITAR, CONFIRMAR FALLA Y DATOS 0 03-07 SE VISITÓ EL CB PARA REVISAR INCONVENIENTE CON DATÁFONO, CLIENTE MANIFIESTA QUE SE REINICIABA, SE REALIZA MANTENIMIENTO, BORRADO DE SISTEMA OPERATIVO Y VERSIÓN, SE REINSTALA Y SE INICIALIZA, PRUEBAS OK, CB FUNCIONA CON NORMALIDAD | W20: VISITA_TÉCNICA | X20: AB1EZ108, MA00E720 | Y20: TIPO II | Z20: TERRESTRE | AA20: GUERRERO RAMIREZ OSCAR DARIO | AB20: 1 | AC20: 0 | AD20: 0 | AE20: 0 | AF20: =IF(W20="SOPORTE_TELEFÓNICO",'BASE LIQUIDACION'!$B$10,IF(Y20="TIPO I",'BASE LIQUIDACION'!$C$3,IF(Y20="TIPO II",'BASE LIQUIDACION'!$C$4,IF(Y20="TIPO III",'BASE LIQUIDACION'!$C$5,'BASE LIQUIDACION'!$C$7)))) -> 163813.56 | AG20: =IF(W20="SOPORTE_TELEFÓNICO",'BASE LIQUIDACION'!$B$10,(AB20*AF20+AC20*'BASE LIQUIDACION'!$B$12+AD20*'BASE LIQUIDACION'!$B$11+INCIDENTES!AE20*'BASE LIQUIDACION'!$B$13)) -> 163813.56
A21: MEDELLIN | B21: =VLOOKUP(A21,'CENTRO DE COSTOS'!A:D,4,FALSE) -> JUAN SEBASTIÁN RÍOS CASTRILLÓN | C21: =VLOOKUP(A21,'CENTRO DE COSTOS'!A:D,2,FALSE) -> 0004-0005 | D21: 5425 | E21: 2375218 | F21: 79106 | G21: INCIDENTE | H21: ANTIOQUIA | I21: MACEO | J21: BARRIO CALLE BOLIVAR MACEO | K21: REDEBAN | L21: FO-25-1163418 | M21: 45839.473 | N21: 45842.377 | O21: NO | P21: USUARIO | Q21: COMUNICACION | R21: CANAL DEL COMERCIO | S21: CB UNO A UNO | U21: CERRADO | V21: 01-07 SE REALIZA CONTACTO CON LUZ MARY CELIS AL NUMERO 3206745652 CONFIRMA FALLA, DATOS CORRECTOS. SE ESCALA PARA VISITA 0 03-07 SE VERIFICAN CONEXIÓNES Y SE IDENTIFICA CAÍDA DEL CANAL DEL USUARIO, SE ENSAYA EL SERVICIO CON EL CANAL DE UN VECINO Y EL SERVICIO FUNCIONA CORRECTAMENTE. | W21: VISITA_TÉCNICA | X21: SASZZ681 | Y21: TIPO III | Z21: TERRESTRE | AA21: BARRIENTOS HERNANDEZ CRISTIAN HORACIO | AB21: 1 | AC21: 0 | AD21: 0 | AE21: 0 | AF21: =IF(W21="SOPORTE_TELEFÓNICO",'BASE LIQUIDACION'!$B$10,IF(Y21="TIPO I",'BASE LIQUIDACION'!$C$3,IF(Y21="TIPO II",'BASE LIQUIDACION'!$C$4,IF(Y21="TIPO III",'BASE LIQUIDACION'!$C$5,'BASE LIQUIDACION'!$C$7)))) -> 275728.38 | AG21: =IF(W21="SOPORTE_TELEFÓNICO",'BASE LIQUIDACION'!$B$10,(AB21*AF21+AC21*'BASE LIQUIDACION'!$B$12+AD21*'BASE LIQUIDACION'!$B$11+INCIDENTES!AE21*'BASE LIQUIDACION'!$B$13)) -> 275728.38
A22: MEDELLIN | B22: =VLOOKUP(A22,'CENTRO DE COSTOS'!A:D,4,FALSE) -> JUAN SEBASTIÁN RÍOS CASTRILLÓN | C22: =VLOOKUP(A22,'CENTRO DE COSTOS'!A:D,2,FALSE) -> 0004-0005 | D22: 5264 | E22: 2384017 | F22: 79370 | G22: INCIDENTE | H22: ANTIOQUIA | I22: ENTRERRIOS | J22: BARRIO SECTOR CUATRO ESQUINAS ENTRERIOS | K22: REDEBAN | L22: FO-25-1173446 | M22: 45840.498 | N22: 45842.397 | O22: NO | P22: USUARIO | Q22: LECTOR DE BARRAS | R22: CAPACITACION MANIPULACION DE COMERCIO | S22: CB UNO A UNO | U22: CERRADO | V22: 02-07 SE ESCALA PARA VISITA. LLAMAR ANTES DE VISITAR, CONFIRMAR FALLA Y DATOS 0 04-07 SE REVISA LECTORA EN BUEN ESTADO SE DETECTA QUE CLIENTE NO ESTABA MANIPULANDO BIEN LA LECTORA SE LE EXPLICA COMO MANIPULARLA TODO OK | W22: VISITA_TÉCNICA | X22: 10XZZ908 | Y22: TIPO II | Z22: TERRESTRE | AA22: ALVAREZ ARENAS VICTOR HUGO | AB22: 1 | AC22: 0 | AD22: 0 | AE22: 0 | AF22: =IF(W22="SOPORTE_TELEFÓNICO",'BASE LIQUIDACION'!$B$10,IF(Y22="TIPO I",'BASE LIQUIDACION'!$C$3,IF(Y22="TIPO II",'BASE LIQUIDACION'!$C$4,IF(Y22="TIPO III",'BASE LIQUIDACION'!$C$5,'BASE LIQUIDACION'!$C$7)))) -> 163813.56 | AG22: =IF(W22="SOPORTE_TELEFÓNICO",'BASE LIQUIDACION'!$B$10,(AB22*AF22+AC22*'BASE LIQUIDACION'!$B$12+AD22*'BASE LIQUIDACION'!$B$11+INCIDENTES!AE22*'BASE LIQUIDACION'!$B$13)) -> 163813.56
A23: MEDELLIN | B23: =VLOOKUP(A23,'CENTRO DE COSTOS'!A:D,4,FALSE) -> JUAN SEBASTIÁN RÍOS CASTRILLÓN | C23: =VLOOKUP(A23,'CENTRO DE COSTOS'!A:D,2,FALSE) -> 0004-0005 | D23: 5001 | E23: 2389859 | F23: 79336 | G23: INCIDENTE | H23: ANTIOQUIA | I23: MEDELLIN | J23: BARRIO PEDREGAL MEDELLIN 13 | K23: REDEBAN | L23: FO-25-1177967 | M23: 45841.429 | N23: 45842.415 | O23: NO | P23: USUARIO | Q23: COMUNICACION | R23: CONEXIONES DE COMERCIO | S23: CB UNO A UNO | U23: CERRADO | V23: 03-07 SE ESCALA PARA VISITA. LLAMAR ANTES DE VISITAR, CONFIRMAR FALLA Y DATOS 0 04-07 SE REALIZA VALIDACIÓN DE EQUIPO ESTA EN BUEN ESTADO, SE PRESENTA DAÑO EN PUNTO DE INTERNET, SE REALIZO PRUEBA EN OTRO PUNTO DE INTERNET Y FUNCIONA CORRECTAMENTE, SE INFORMA AL CLIENTE COMUNICAR QUE EL PROVEEDOR | W23: VISITA_TÉCNICA | X23: A4WZZ863 | Y23: TIPO I | Z23: TERRESTRE | AA23: HERNANDEZ CHAVARRIA JUAN CAMILO | AB23: 1 | AC23: 0 | AD23: 0 | AE23: 0 | AF23: =IF(W23="SOPORTE_TELEFÓNICO",'BASE LIQUIDACION'!$B$10,IF(Y23="TIPO I",'BASE LIQUIDACION'!$C$3,IF(Y23="TIPO II",'BASE LIQUIDACION'!$C$4,IF(Y23="TIPO III",'BASE LIQUIDACION'!$C$5,'BASE LIQUIDACION'!$C$7)))) -> 65960.474 | AG23: =IF(W23="SOPORTE_TELEFÓNICO",'BASE LIQUIDACION'!$B$10,(AB23*AF23+AC23*'BASE LIQUIDACION'!$B$12+AD23*'BASE LIQUIDACION'!$B$11+INCIDENTES!AE23*'BASE LIQUIDACION'!$B$13)) -> 65960.474
A24: MEDELLIN | B24: =VLOOKUP(A24,'CENTRO DE COSTOS'!A:D,4,FALSE) -> JUAN SEBASTIÁN RÍOS CASTRILLÓN | C24: =VLOOKUP(A24,'CENTRO DE COSTOS'!A:D,2,FALSE) -> 0004-0005 | D24: 5425 | E24: 2379717 | F24: 76602 | G24: INCIDENTE | H24: ANTIOQUIA | I24: MACEO | J24: BARRIO LA PLAZUELA MACEO | K24: REDEBAN | L24: FO-25-1171205 | M24: 45840.333 | N24: 45842.426 | O24: NO | P24: USUARIO | Q24: COMUNICACION | R24: CANAL DEL COMERCIO | S24: CB UNO A UNO | U24: CERRADO | V24: 02-07 SE REALIZA CONTACTO CON RUBIALBA RODAS VALENCIA AL NUMERO 3135566743 CONFIRMA FALLA, DATOS CORRECTOS. SE ESCALA PARA VISITA 0 04-07 USUARIO CAMBIA DE OPERADOR, SE REALIZA INSTALACIÓN Y SE DEJAN SERVICIOS FUNCIONANDO CORRECTAMENTE | W24: VISITA_TÉCNICA | X24: V14ZZ278 | Y24: TIPO III | Z24: TERRESTRE | AA24: BARRIENTOS HERNANDEZ CRISTIAN HORACIO | AB24: 1 | AC24: 0 | AD24: 0 | AE24: 0 | AF24: =IF(W24="SOPORTE_TELEFÓNICO",'BASE LIQUIDACION'!$B$10,IF(Y24="TIPO I",'BASE LIQUIDACION'!$C$3,IF(Y24="TIPO II",'BASE LIQUIDACION'!$C$4,IF(Y24="TIPO III",'BASE LIQUIDACION'!$C$5,'BASE LIQUIDACION'!$C$7)))) -> 275728.38 | AG24: =IF(W24="SOPORTE_TELEFÓNICO",'BASE LIQUIDACION'!$B$10,(AB24*AF24+AC24*'BASE LIQUIDACION'!$B$12+AD24*'BASE LIQUIDACION'!$B$11+INCIDENTES!AE24*'BASE LIQUIDACION'!$B$13)) -> 275728.38
A25: MEDELLIN | B25: =VLOOKUP(A25,'CENTRO DE COSTOS'!A:D,4,FALSE) -> JUAN SEBASTIÁN RÍOS CASTRILLÓN | C25: =VLOOKUP(A25,'CENTRO DE COSTOS'!A:D,2,FALSE) -> 0004-0005 | D25: 5001 | E25: 2391115 | F25: 24257 | G25: INCIDENTE | H25: ANTIOQUIA | I25: MEDELLIN | J25: COMCARD SAN JAVIER TOTAL RED | K25: REDEBAN | L25: FO-25-1178781 | M25: 45841.503 | N25: 45842.447 | O25: NO | P25: USUARIO | Q25: LECTOR DE BARRAS | R25: ERROR PAGOS PARCIALES DE FACTURAS | S25: AGREGADOR | U25: CERRADO | V25: 03-07 SE ESCALA PARA VISITA. LLAMAR ANTES DE VISITAR, CONFIRMAR FALLA Y DATOS 0 04-07 SE LLEGA AL COMERCIO PERO SE EVIDENCIA QUE ESTÁ CERRADO SE INTENTA COMUNICACIÓN CON USUARIO PERO NO SE LOGRA SE ESPERA MÉDIA HORA EN SITIO PERO NO LLEGA USUARIA | W25: VISITA_TÉCNICA | X25: 0 | Y25: TIPO I | Z25: TERRESTRE | AA25: MONTOYA VELEZ ANDRES FELIPE | AB25: 1 | AC25: 0 | AD25: 0 | AE25: 0 | AF25: =IF(W25="SOPORTE_TELEFÓNICO",'BASE LIQUIDACION'!$B$10,IF(Y25="TIPO I",'BASE LIQUIDACION'!$C$3,IF(Y25="TIPO II",'BASE LIQUIDACION'!$C$4,IF(Y25="TIPO III",'BASE LIQUIDACION'!$C$5,'BASE LIQUIDACION'!$C$7)))) -> 65960.474 | AG25: =IF(W25="SOPORTE_TELEFÓNICO",'BASE LIQUIDACION'!$B$10,(AB25*AF25+AC25*'BASE LIQUIDACION'!$B$12+AD25*'BASE LIQUIDACION'!$B$11+INCIDENTES!AE25*'BASE LIQUIDACION'!$B$13)) -> 65960.474
A26: IBAGUE | B26: =VLOOKUP(A26,'CENTRO DE COSTOS'!A:D,4,FALSE) -> KEVIN ALEXIS CORZO BUSTOS | C26: =VLOOKUP(A26,'CENTRO DE COSTOS'!A:D,2,FALSE) -> 0004-0007 | D26: 73585 | E26: 2394091 | F26: 79783 | G26: INCIDENTE | H26: TOLIMA | I26: PURIFICACION | J26: BARRIO VILLA DE LAS PALMAS PURIFICACION | K26: REDEBAN | L26: FO-25-1181575 | M26: 45842.333 | N26: 45842.542 | O26: NO | P26: USUARIO | Q26: CIERRE | R26: COMERCIO NO REALIZA CIERRE | S26: CB UNO A UNO | U26: CERRADO | V26: 04-07 SE ESCALA PARA VISITA. LLAMAR ANTES DE VISITAR, CONFIRMAR FALLA Y DATOS 0 04-07 SE COMUNICA AL NÚMERO TELEFÓNICO 3206095053, LA SEÑORA ANGIE MONROY INDICA QUE DESDE LA LÍNEA 018000953344 LE DIERON SOLUCIÓN AL TEMA DE CIERRES MEDIANTE BORRADO DE TRANSACCIONES; EQUIPO OPERATIVO. | W26: SOPORTE_TELEFÓNICO | X26: 0 | Y26: TIPO II | Z26: TERRESTRE | AA26: BARRAGAN TAFUR EDWIN ESTEBAN | AB26: 0 | AC26: 0 | AD26: 0 | AE26: 0 | AF26: =IF(W26="SOPORTE_TELEFÓNICO",'BASE LIQUIDACION'!$B$10,IF(Y26="TIPO I",'BASE LIQUIDACION'!$C$3,IF(Y26="TIPO II",'BASE LIQUIDACION'!$C$4,IF(Y26="TIPO III",'BASE LIQUIDACION'!$C$5,'BASE LIQUIDACION'!$C$7)))) -> 37904.654 | AG26: =IF(W26="SOPORTE_TELEFÓNICO",'BASE LIQUIDACION'!$B$10,(AB26*AF26+AC26*'BASE LIQUIDACION'!$B$12+AD26*'BASE LIQUIDACION'!$B$11+INCIDENTES!AE26*'BASE LIQUIDACION'!$B$13)) -> 37904.654
A27: MEDELLIN | B27: =VLOOKUP(A27,'CENTRO DE COSTOS'!A:D,4,FALSE) -> JUAN SEBASTIÁN RÍOS CASTRILLÓN | C27: =VLOOKUP(A27,'CENTRO DE COSTOS'!A:D,2,FALSE) -> 0004-0005 | D27: 5360 | E27: 2393274 | F27: 12305 | G27: INCIDENTE | H27: ANTIOQUIA | I27: ITAGUI | J27: BARRIO SANTA MARIA III - ITAGU | K27: REDEBAN | L27: FO-25-1180859 | M27: 45841.694 | N27: 45842.591 | O27: NO | P27: USUARIO | Q27: MANTENIMIENTO | R27: MANTENIMIENTO GENERAL | S27: CB UNO A UNO | U27: CERRADO | V27: 03-07 SE ESCALA PARA VISITA. LLAMAR ANTES DE VISITAR, CONFIRMAR FALLA Y DATOS 0 04-07 SE LLEGA AL PUNTO SE LLAMA AL ENCARGADO Y DICE QUE FAVOR VENIR LA OTRA SEMANA YA QUE NO SE ENCUENTRA | W27: VISITA_TÉCNICA | X27: JAAAN929 | Y27: TIPO I | Z27: TERRESTRE | AA27: MORENO MEDINA JUAN PABLO | AB27: 1 | AC27: 0 | AD27: 0 | AE27: 0 | AF27: =IF(W27="SOPORTE_TELEFÓNICO",'BASE LIQUIDACION'!$B$10,IF(Y27="TIPO I",'BASE LIQUIDACION'!$C$3,IF(Y27="TIPO II",'BASE LIQUIDACION'!$C$4,IF(Y27="TIPO III",'BASE LIQUIDACION'!$C$5,'BASE LIQUIDACION'!$C$7)))) -> 65960.474 | AG27: =IF(W27="SOPORTE_TELEFÓNICO",'BASE LIQUIDACION'!$B$10,(AB27*AF27+AC27*'BASE LIQUIDACION'!$B$12+AD27*'BASE LIQUIDACION'!$B$11+INCIDENTES!AE27*'BASE LIQUIDACION'!$B$13)) -> 65960.474
A28: MEDELLIN | B28: =VLOOKUP(A28,'CENTRO DE COSTOS'!A:D,4,FALSE) -> JUAN SEBASTIÁN RÍOS CASTRILLÓN | C28: =VLOOKUP(A28,'CENTRO DE COSTOS'!A:D,2,FALSE) -> 0004-0005 | D28: 5042 | E28: 2393568 | F28: 42910 | G28: INCIDENTE | H28: ANTIOQUIA | I28: SANTA FE DE ANTIOQUIA | J28: BRR EL LLANO SANTA FE DE ANTIO | K28: REDEBAN | L28: FO-25-1181166 | M28: 45841.736 | N28: 45842.626 | O28: NO | P28: USUARIO | Q28: MANTENIMIENTO | R28: MANTENIMIENTO GENERAL | S28: CB UNO A UNO | U28: CERRADO | V28: 03-07 SE ESCALA PARA VISITA. LLAMAR ANTES DE VISITAR, CONFIRMAR FALLA Y DATOS 0 04-07 SE REALIZA MANTENIMIENTO AL PIN PAD YA QUE NO LEE ALGUNAS TARJETAS | W28: VISITA_TÉCNICA | X28: GZCZZ662 | Y28: TIPO II | Z28: TERRESTRE | AA28: CERPA SUAREZ DUVAN CAMILO | AB28: 1 | AC28: 0 | AD28: 0 | AE28: 0 | AF28: =IF(W28="SOPORTE_TELEFÓNICO",'BASE LIQUIDACION'!$B$10,IF(Y28="TIPO I",'BASE LIQUIDACION'!$C$3,IF(Y28="TIPO II",'BASE LIQUIDACION'!$C$4,IF(Y28="TIPO III",'BASE LIQUIDACION'!$C$5,'BASE LIQUIDACION'!$C$7)))) -> 163813.56 | AG28: =IF(W28="SOPORTE_TELEFÓNICO",'BASE LIQUIDACION'!$B$10,(AB28*AF28+AC28*'BASE LIQUIDACION'!$B$12+AD28*'BASE LIQUIDACION'!$B$11+INCIDENTES!AE28*'BASE LIQUIDACION'!$B$13)) -> 163813.56
A29: NEIVA | B29: =VLOOKUP(A29,'CENTRO DE COSTOS'!A:D,4,FALSE) -> KEVIN ALEXIS CORZO BUSTOS | C29: =VLOOKUP(A29,'CENTRO DE COSTOS'!A:D,2,FALSE) -> 0004-0007 | D29: 41016 | E29: 2390678 | F29: 75980 | G29: INCIDENTE | H29: HUILA | I29: AIPE | J29: PTM AIPE VARIEDADES J.C. | K29: REDEBAN | L29: FO-25-1178619 | M29: 45841.481 | N29: 45842.632 | O29: NO | P29: USUARIO | Q29: USUARIOS | R29: CREACION DE USUARIOS | S29: AGREGADOR | U29: CERRADO | V29: 03-07 SE ESCALA PARA VISITA. LLAMAR ANTES DE VISITAR, CONFIRMAR FALLA Y DATOS 0 04-07 EN LLAMADA CON CLIENTE JHOAN CAMPOS AL NÚMERO 3216890476 SE REALIZA GESTIÓN DE CLAVE. | W29: SOPORTE_TELEFÓNICO | X29: 0 | Y29: TIPO II | Z29: TERRESTRE | AA29: DIAZ VARGAS JONATHAN MIGUEL | AB29: 0 | AC29: 0 | AD29: 0 | AE29: 0 | AF29: =IF(W29="SOPORTE_TELEFÓNICO",'BASE LIQUIDACION'!$B$10,IF(Y29="TIPO I",'BASE LIQUIDACION'!$C$3,IF(Y29="TIPO II",'BASE LIQUIDACION'!$C$4,IF(Y29="TIPO III",'BASE LIQUIDACION'!$C$5,'BASE LIQUIDACION'!$C$7)))) -> 37904.654 | AG29: =IF(W29="SOPORTE_TELEFÓNICO",'BASE LIQUIDACION'!$B$10,(AB29*AF29+AC29*'BASE LIQUIDACION'!$B$12+AD29*'BASE LIQUIDACION'!$B$11+INCIDENTES!AE29*'BASE LIQUIDACION'!$B$13)) -> 37904.654
A30: PASTO | B30: =VLOOKUP(A30,'CENTRO DE COSTOS'!A:D,4,FALSE) -> DIEGO FERNANDO HENAO CARDONA | C30: =VLOOKUP(A30,'CENTRO DE COSTOS'!A:D,2,FALSE) -> 0004-0003 | D30: 52227 | E30: 2391004 | F30: 10557 | G30: INCIDENTE | H30: NARIÑO | I30: CUMBAL | J30: CUMBAL - NARINO | K30: REDEBAN | L30: FO-25-1178611 | M30: 45841.486 | N30: 45842.633 | O30: NO | P30: USUARIO | Q30: MANTENIMIENTO | R30: MANTENIMIENTO GENERAL | S30: CB UNO A UNO | U30: CERRADO | V30: 03-07 SE REALIZA CONTACTO CON ELIZABETH ESTRADA AL NUMERO 3207619819 CONFIRMA FALLA, DATOS CORRECTOS. SE ESCALA PARA VISITA 0 04-07 SE VISITA EL CB PARA REVISAR INCONVENIENTE CON DATÁFONO POR LENTITUD, SE REALIZA FORMATEO Y RE INSTALACIÓN DE SO Y VERSIÓN, SE HACEN PRUEBAS OK CORRESPONSAL OPERATIVO | W30: VISITA_TÉCNICA | X30: IZ2ZZ010 | Y30: TIPO III | Z30: TERRESTRE | AA30: GUERRERO RAMIREZ OSCAR DARIO | AB30: 1 | AC30: 0 | AD30: 0 | AE30: 0 | AF30: =IF(W30="SOPORTE_TELEFÓNICO",'BASE LIQUIDACION'!$B$10,IF(Y30="TIPO I",'BASE LIQUIDACION'!$C$3,IF(Y30="TIPO II",'BASE LIQUIDACION'!$C$4,IF(Y30="TIPO III",'BASE LIQUIDACION'!$C$5,'BASE LIQUIDACION'!$C$7)))) -> 275728.38 | AG30: =IF(W30="SOPORTE_TELEFÓNICO",'BASE LIQUIDACION'!$B$10,(AB30*AF30+AC30*'BASE LIQUIDACION'!$B$12+AD30*'BASE LIQUIDACION'!$B$11+INCIDENTES!AE30*'BASE LIQUIDACION'!$B$13)) -> 275728.38
A31: VALLEDUPAR | B31: =VLOOKUP(A31,'CENTRO DE COSTOS'!A:D,4,FALSE) -> JOSE MAURICIO HERNANDEZ ROJAS | C31: =VLOOKUP(A31,'CENTRO DE COSTOS'!A:D,2,FALSE) -> 0004-0001 | D31: 20001 | E31: 2395671 | F31: 75517 | G31: INCIDENTE | H31: CESAR | I31: VALLEDUPAR | J31: BARRIO EL CARMEN VALLEDUPAR 3 | K31: REDEBAN | L31: FO-25-1183121 | M31: 45842.404 | N31: 45842.652 | O31: NO | P31: ENTIDAD | Q31: ERROR DE TRANSACCIONES | R31: TRANSACCION NO PERMITIDA | S31: CB UNO A UNO | U31: CERRADO | V31: 04-07 SE ESCALA PARA VISITA. LLAMAR ANTES DE VISITAR, CONFIRMAR FALLA Y DATOS 0 04-07 SE LLEGA A SITIO Y SE EVIDENCIA QUE NO SE PODIAN HACER DEPOSITOS A NEQUI, SE REALIZA RESET DEL EQUIPO Y SE RECONFIGURA, SE LLAMA AL BANCO DE IGUAL FORMA Y SE DEJA EL SERVICIO RESTABLECIDO Y FUNCIONANDO AL 100% | W31: VISITA_TÉCNICA | X31: SA00C422 | Y31: TIPO I | Z31: TERRESTRE | AA31: MONTES DIAZ JOHN FRED | AB31: 1 | AC31: 0 | AD31: 0 | AE31: 0 | AF31: =IF(W31="SOPORTE_TELEFÓNICO",'BASE LIQUIDACION'!$B$10,IF(Y31="TIPO I",'BASE LIQUIDACION'!$C$3,IF(Y31="TIPO II",'BASE LIQUIDACION'!$C$4,IF(Y31="TIPO III",'BASE LIQUIDACION'!$C$5,'BASE LIQUIDACION'!$C$7)))) -> 65960.474 | AG31: =IF(W31="SOPORTE_TELEFÓNICO",'BASE LIQUIDACION'!$B$10,(AB31*AF31+AC31*'BASE LIQUIDACION'!$B$12+AD31*'BASE LIQUIDACION'!$B$11+INCIDENTES!AE31*'BASE LIQUIDACION'!$B$13)) -> 65960.474
A32: MEDELLIN | B32: =VLOOKUP(A32,'CENTRO DE COSTOS'!A:D,4,FALSE) -> JUAN SEBASTIÁN RÍOS CASTRILLÓN | C32: =VLOOKUP(A32,'CENTRO DE COSTOS'!A:D,2,FALSE) -> 0004-0005 | D32: 5001 | E32: 2394087 | F32: 77881 | G32: INCIDENTE | H32: ANTIOQUIA | I32: MEDELLIN | J32: PTM MEDELLIN NEGOCIO 360 | K32: REDEBAN | L32: FO-25-1181588 | M32: 45842.333 | N32: 45842.686 | O32: NO | P32: USUARIO | Q32: MANTENIMIENTO | R32: MANTENIMIENTO GENERAL | S32: AGREGADOR | U32: CERRADO | V32: 04-07 SE ESCALA PARA VISITA. LLAMAR ANTES DE VISITAR, CONFIRMAR FALLA Y DATOS 0 04-07 SE REALIZA MANTENIMIENTO AL EQUIPO Y SE EXPLICA SOBRE BORRADO DE TRANSACCIONES | W32: VISITA_TÉCNICA | X32: A1MZZ065-UVSZZ688 | Y32: TIPO I | Z32: TERRESTRE | AA32: CERPA SUAREZ DUVAN CAMILO | AB32: 1 | AC32: 0 | AD32: 0 | AE32: 0 | AF32: =IF(W32="SOPORTE_TELEFÓNICO",'BASE LIQUIDACION'!$B$10,IF(Y32="TIPO I",'BASE LIQUIDACION'!$C$3,IF(Y32="TIPO II",'BASE LIQUIDACION'!$C$4,IF(Y32="TIPO III",'BASE LIQUIDACION'!$C$5,'BASE LIQUIDACION'!$C$7)))) -> 65960.474 | AG32: =IF(W32="SOPORTE_TELEFÓNICO",'BASE LIQUIDACION'!$B$10,(AB32*AF32+AC32*'BASE LIQUIDACION'!$B$12+AD32*'BASE LIQUIDACION'!$B$11+INCIDENTES!AE32*'BASE LIQUIDACION'!$B$13)) -> 65960.474
A33: CARTAGENA | B33: =VLOOKUP(A33,'CENTRO DE COSTOS'!A:D,4,FALSE) -> JOSE MAURICIO HERNANDEZ ROJAS | C33: =VLOOKUP(A33,'CENTRO DE COSTOS'!A:D,2,FALSE) -> 0004-0001 | D33: 13430 | E33: 2397668 | F33: 60167 | G33: INCIDENTE | H33: BOLIVAR | I33: MAGANGUE | J33: BARRIO CENTRO MAGANGUE 7 | K33: REDEBAN | L33: FO-25-1184999 | M33: 45842.572 | N33: 45843.361 | O33: NO | P33: USUARIO | Q33: LECTOR DE BARRAS | R33: CAPACITACION MANIPULACION DE COMERCIO | S33: CB UNO A UNO | U33: CERRADO | V33: 04-07 SE ESCALA PARA VISITA. LLAMAR ANTES DE VISITAR, CONFIRMAR FALLA Y DATOS 0 04-07 SE COMUNICA CON LA SRA BERTHA RANGEL VIA WHATSAPP +57 301 2344865, SE REALIZA PRIMEROS AUXILIOS, SE INDICA CONECTAR EL ESCÁNER CON EL DATÁFONO APAGADO Y LUEGO ENCENDER, SE REALIZA PRUEBA DE LECTURA DE CÓDIGOS DE BARRAS EXITOSAS. SE LE INFORMA QUE EL ESCÁNER DEBE PERMANECER CONECTADO AL DATÁFONO PARA QUE NO SE DESCONFIGURE. SE LE RECOMIENDA PEDIR PINPAD O MODIFICAR LA VENTANILLA PARA QUE EL CLIENTE PUEDA COLOCAR LA CLAVE SIN NECESIDAD DE DESCONECTAR EL ACCESORIO. | W33: SOPORTE_TELEFÓNICO | X33: 0 | Y33: TIPO IV | Z33: TERRESTRE | AA33: SANTOS GUZMAN CHRISTIAN FELIPE | AB33: 0 | AC33: 0 | AD33: 0 | AE33: 0 | AF33: =IF(W33="SOPORTE_TELEFÓNICO",'BASE LIQUIDACION'!$B$10,IF(Y33="TIPO I",'BASE LIQUIDACION'!$C$3,IF(Y33="TIPO II",'BASE LIQUIDACION'!$C$4,IF(Y33="TIPO III",'BASE LIQUIDACION'!$C$5,'BASE LIQUIDACION'!$C$7)))) -> 37904.654 | AG33: =IF(W33="SOPORTE_TELEFÓNICO",'BASE LIQUIDACION'!$B$10,(AB33*AF33+AC33*'BASE LIQUIDACION'!$B$12+AD33*'BASE LIQUIDACION'!$B$11+INCIDENTES!AE33*'BASE LIQUIDACION'!$B$13)) -> 37904.654
A34: CALI | B34: =VLOOKUP(A34,'CENTRO DE COSTOS'!A:D,4,FALSE) -> DIEGO FERNANDO HENAO CARDONA | C34: =VLOOKUP(A34,'CENTRO DE COSTOS'!A:D,2,FALSE) -> 0004-0003 | D34: 76001 | E34: 2400348 | F34: 60641 | G34: INCIDENTE | H34: VALLE DEL CAUCA | I34: CALI | J34: DISTRICOL VARIEDADES MR PAP | K34: REDEBAN | L34: FO-25-1186932 | M34: 45843.339 | N34: 45843.543 | O34: NO | P34: USUARIO | Q34: COMUNICACION | R34: CONEXIONES DE COMERCIO | S34: AGREGADOR | U34: CERRADO | V34: 05-07 SE ESCALA PARA VISITA. LLAMAR ANTES DE VISITAR, CONFIRMAR FALLA Y DATOS 0 05-07 SE REALIZA LLAMADA AL CLIENTE Y SE VALIDA CONECTIVIDAD DEL SERVICIO, SE ENCUENTRA PROBLEMAS EN LA CONEXION DEL ROUTER , SE LE SOLICITA VALIDAR CABLEADO Y REINICIO DEL ROUTER, EL CLIENTE REALIZA LA LABOR Y SE PROCEDE A REALIZAR PRUEBAS EXITOSAS | W34: SOPORTE_TELEFÓNICO | X34: 0 | Y34: TIPO I | Z34: TERRESTRE | AA34: HENAO CARDONA DIEGO FERNANDO | AB34: 0 | AC34: 0 | AD34: 0 | AE34: 0 | AF34: =IF(W34="SOPORTE_TELEFÓNICO",'BASE LIQUIDACION'!$B$10,IF(Y34="TIPO I",'BASE LIQUIDACION'!$C$3,IF(Y34="TIPO II",'BASE LIQUIDACION'!$C$4,IF(Y34="TIPO III",'BASE LIQUIDACION'!$C$5,'BASE LIQUIDACION'!$C$7)))) -> 37904.654 | AG34: =IF(W34="SOPORTE_TELEFÓNICO",'BASE LIQUIDACION'!$B$10,(AB34*AF34+AC34*'BASE LIQUIDACION'!$B$12+AD34*'BASE LIQUIDACION'!$B$11+INCIDENTES!AE34*'BASE LIQUIDACION'!$B$13)) -> 37904.654
A35: YOPAL | B35: =VLOOKUP(A35,'CENTRO DE COSTOS'!A:D,4,FALSE) -> KEVIN ALEXIS CORZO BUSTOS | C35: =VLOOKUP(A35,'CENTRO DE COSTOS'!A:D,2,FALSE) -> 0004-0007 | D35: 85010 | E35: 2394937 | F35: 32216 | G35: INCIDENTE | H35: CASANARE | I35: AGUAZUL | J35: DISTRICOL SUPER DROGAS CUSIANA | K35: REDEBAN | L35: FO-25-1182157 | M35: 45842.358 | N35: 45843.648 | O35: NO | P35: USUARIO | Q35: COMUNICACION | R35: CONEXIONES DE COMERCIO | S35: AGREGADOR | U35: CERRADO | V35: 04-07 SE ESCALA PARA VISITA. LLAMAR ANTES DE VISITAR, CONFIRMAR FALLA Y DATOS 0 05-07 EN COMUNICACIÓN CON LA SEÑORA LAURA SIERRA AL NUMERO 3108210002, SE REALIZAN PRUEBAS OK. OPERATIVO EL SERVICIO, LA FALLA PRESENTA CONEXIONES INTERNAS DEL COMERCIO. OPERATIVO EL SERVICIO | W35: SOPORTE_TELEFÓNICO | X35: 0 | Y35: TIPO II | Z35: TERRESTRE | AA35: BERNAL ELAICA EDGAR ALEXIS | AB35: 0 | AC35: 0 | AD35: 0 | AE35: 0 | AF35: =IF(W35="SOPORTE_TELEFÓNICO",'BASE LIQUIDACION'!$B$10,IF(Y35="TIPO I",'BASE LIQUIDACION'!$C$3,IF(Y35="TIPO II",'BASE LIQUIDACION'!$C$4,IF(Y35="TIPO III",'BASE LIQUIDACION'!$C$5,'BASE LIQUIDACION'!$C$7)))) -> 37904.654 | AG35: =IF(W35="SOPORTE_TELEFÓNICO",'BASE LIQUIDACION'!$B$10,(AB35*AF35+AC35*'BASE LIQUIDACION'!$B$12+AD35*'BASE LIQUIDACION'!$B$11+INCIDENTES!AE35*'BASE LIQUIDACION'!$B$13)) -> 37904.654
A36: YOPAL | B36: =VLOOKUP(A36,'CENTRO DE COSTOS'!A:D,4,FALSE) -> KEVIN ALEXIS CORZO BUSTOS | C36: =VLOOKUP(A36,'CENTRO DE COSTOS'!A:D,2,FALSE) -> 0004-0007 | D36: 85001 | E36: 2400600 | F36: 31229 | G36: INCIDENTE | H36: CASANARE | I36: YOPAL | J36: BARRIO CORREGIMIENTO LA CHAPAR | K36: REDEBAN | L36: FO-25-1187490 | M36: 45843.392 | N36: 45843.649 | O36: NO | P36: USUARIO | Q36: NO ENCIENDE | R36: CONEXIONES DE COMERCIO | S36: CB UNO A UNO | U36: CERRADO | V36: 05-07 SE ESCALA PARA VISITA. LLAMAR ANTES DE VISITAR, CONFIRMAR FALLA Y DATOS 05/07/2025 EN COMUNICACIÓN CON LA SEÑORA ANDREA INDICA QUE POR HORARIO LABORAL ES HASTA LOS SABADOS HASTA LA 1:PM. NOS ATIENDE EN HORARIO HABIL EL LUNES. 05-07 EN COMUNICACIÓN CON LA SEÑORA SARA REYES AL NUMERO 3132450829, INDICA QUE SE ENCUENTRA OPERATIVO EL, LA FALLA ERA CONEXIONES INTERNAS DEL COMERCIO Y YA FUE RESUELTA. INDICA NO REQUIERE LA VISITA TÉCNICA | W36: SOPORTE_TELEFÓNICO | X36: 0 | Y36: TIPO I | Z36: TERRESTRE | AA36: BERNAL ELAICA EDGAR ALEXIS | AB36: 0 | AC36: 0 | AD36: 0 | AE36: 0 | AF36: =IF(W36="SOPORTE_TELEFÓNICO",'BASE LIQUIDACION'!$B$10,IF(Y36="TIPO I",'BASE LIQUIDACION'!$C$3,IF(Y36="TIPO II",'BASE LIQUIDACION'!$C$4,IF(Y36="TIPO III",'BASE LIQUIDACION'!$C$5,'BASE LIQUIDACION'!$C$7)))) -> 37904.654 | AG36: =IF(W36="SOPORTE_TELEFÓNICO",'BASE LIQUIDACION'!$B$10,(AB36*AF36+AC36*'BASE LIQUIDACION'!$B$12+AD36*'BASE LIQUIDACION'!$B$11+INCIDENTES!AE36*'BASE LIQUIDACION'!$B$13)) -> 37904.654
A37: MEDELLIN | B37: =VLOOKUP(A37,'CENTRO DE COSTOS'!A:D,4,FALSE) -> JUAN SEBASTIÁN RÍOS CASTRILLÓN | C37: =VLOOKUP(A37,'CENTRO DE COSTOS'!A:D,2,FALSE) -> 0004-0005 | D37: 5088 | E37: 2401170 | F37: 45042 | G37: INCIDENTE | H37: ANTIOQUIA | I37: BELLO | J37: DISTRICOL PUNTA ROMA | K37: REDEBAN | L37: FO-25-1188734 | M37: 45843.529 | N37: 45845.487 | O37: NO | P37: USUARIO | Q37: COMUNICACION | R37: CONEXIONES DE COMERCIO | S37: AGREGADOR | U37: CERRADO | V37: 05-07 SE ESCALA PARA VISITA. LLAMAR ANTES DE VISITAR, CONFIRMAR FALLA Y DATOS 06/07/2025 CB INFORMA QUE NO ABRE LOS DÍAS DOMINGO, SE APLAZA VISITA 07-07 SE COMUNICA CON EL USUARIO PARA CONFIRMAR LA VISITA E INDICA QUE YA SE TIENE CONEXIÓN AL EQUIPO ERA UN PROBLEMA DEL PROVEEDOR DE INTERNET DEL USUARIO. SERVICIO OPERATIVO | W37: SOPORTE_TELEFÓNICO | X37: 0 | Y37: TIPO I | Z37: TERRESTRE | AA37: ZAPATA LOPEZ EDWARD ASDRUBAL | AB37: 0 | AC37: 0 | AD37: 0 | AE37: 0 | AF37: =IF(W37="SOPORTE_TELEFÓNICO",'BASE LIQUIDACION'!$B$10,IF(Y37="TIPO I",'BASE LIQUIDACION'!$C$3,IF(Y37="TIPO II",'BASE LIQUIDACION'!$C$4,IF(Y37="TIPO III",'BASE LIQUIDACION'!$C$5,'BASE LIQUIDACION'!$C$7)))) -> 37904.654 | AG37: =IF(W37="SOPORTE_TELEFÓNICO",'BASE LIQUIDACION'!$B$10,(AB37*AF37+AC37*'BASE LIQUIDACION'!$B$12+AD37*'BASE LIQUIDACION'!$B$11+INCIDENTES!AE37*'BASE LIQUIDACION'!$B$13)) -> 37904.654
A38: TUNJA | B38: =VLOOKUP(A38,'CENTRO DE COSTOS'!A:D,4,FALSE) -> MIGUEL JULIÁN HERNÁNDEZ GUARÍN | C38: =VLOOKUP(A38,'CENTRO DE COSTOS'!A:D,2,FALSE) -> 0004-0008 | D38: 15001 | E38: 2404260 | F38: 79424 | G38: INCIDENTE | H38: BOYACA | I38: TUNJA | J38: BARRIO CENTRO TUNJA 31 | K38: REDEBAN | L38: FO-25-1192751 | M38: 45845.396 | N38: 45845.505 | O38: NO | P38: USUARIO | Q38: CIERRE | R38: COMERCIO NO REALIZA CIERRE | S38: CB UNO A UNO | U38: CERRADO | V38: 07-07 SE ESCALA PARA VISITA. LLAMAR ANTES DE VISITAR, CONFIRMAR FALLA Y DATOS 0 07-07 SE VISITA CB MANTENIMIENTO POS... CAPACITACIÓN CIERRE PARCIAL Y GENERAL PRUEBAS EXITOSAS | W38: VISITA_TÉCNICA | X38: 10XZZ962 | Y38: TIPO I | Z38: TERRESTRE | AA38: GONZALEZ GONZALEZ MARIO ALBERTO | AB38: 1 | AC38: 0 | AD38: 0 | AE38: 0 | AF38: =IF(W38="SOPORTE_TELEFÓNICO",'BASE LIQUIDACION'!$B$10,IF(Y38="TIPO I",'BASE LIQUIDACION'!$C$3,IF(Y38="TIPO II",'BASE LIQUIDACION'!$C$4,IF(Y38="TIPO III",'BASE LIQUIDACION'!$C$5,'BASE LIQUIDACION'!$C$7)))) -> 65960.474 | AG38: =IF(W38="SOPORTE_TELEFÓNICO",'BASE LIQUIDACION'!$B$10,(AB38*AF38+AC38*'BASE LIQUIDACION'!$B$12+AD38*'BASE LIQUIDACION'!$B$11+INCIDENTES!AE38*'BASE LIQUIDACION'!$B$13)) -> 65960.474
A39: BOGOTA | B39: =VLOOKUP(A39,'CENTRO DE COSTOS'!A:D,4,FALSE) -> WILLIAM ASDRUBAL ROZO ROZO | C39: =VLOOKUP(A39,'CENTRO DE COSTOS'!A:D,2,FALSE) -> 0004-0004 | D39: 25843 | E39: 2398472 | F39: 71906 | G39: INCIDENTE | H39: CUNDINAMARCA | I39: VILLA DE SAN DIEGO DE UBATE | J39: VILLA DE SAN DIEGO DE UBATE JU | K39: REDEBAN | L39: FO-25-1185761 | M39: 45842.64 | N39: 45845.532 | O39: NO | P39: USUARIO | Q39: CIERRE | R39: COMERCIO NO REALIZA CIERRE | S39: CB UNO A UNO | U39: CERRADO | V39: 04-07 SE ESCALA PARA VISITA. LLAMAR ANTES DE VISITAR, CONFIRMAR FALLA Y DATOS 05/07/2025 SE REALIZA CONTACTO CON LA SEÑORA JOHANA INDICANDO QUE ESTÁ DE VIAJE Y QUE NO PUEDE ATENDER EL DÍA DOMINGO DE IGUALMENTE POR PARTE DEL CALL CENTER QUE DOS DÍAS HÁBILES Y DESEA SER ATENDIDA EL DÍA LUNES 07-07 SE REALIZA BORRADO SO Y VERSIÓN OK SE ACTUALIZA SE CAPACITA AL COMERCIO EN COMO REALIZAR LOS CIERRES DE FORMA CORRECTA | W39: VISITA_TÉCNICA | X39: LN00M116 | Y39: TIPO II | Z39: TERRESTRE | AA39: HERNANDEZ NARANJO OSCAR EDUARDO | AB39: 1 | AC39: 0 | AD39: 0 | AE39: 0 | AF39: =IF(W39="SOPORTE_TELEFÓNICO",'BASE LIQUIDACION'!$B$10,IF(Y39="TIPO I",'BASE LIQUIDACION'!$C$3,IF(Y39="TIPO II",'BASE LIQUIDACION'!$C$4,IF(Y39="TIPO III",'BASE LIQUIDACION'!$C$5,'BASE LIQUIDACION'!$C$7)))) -> 163813.56 | AG39: =IF(W39="SOPORTE_TELEFÓNICO",'BASE LIQUIDACION'!$B$10,(AB39*AF39+AC39*'BASE LIQUIDACION'!$B$12+AD39*'BASE LIQUIDACION'!$B$11+INCIDENTES!AE39*'BASE LIQUIDACION'!$B$13)) -> 163813.56
A40: SINCELEJO | B40: =VLOOKUP(A40,'CENTRO DE COSTOS'!A:D,4,FALSE) -> JOSE MAURICIO HERNANDEZ ROJAS | C40: =VLOOKUP(A40,'CENTRO DE COSTOS'!A:D,2,FALSE) -> 0004-0001 | D40: 70215 | E40: 2401544 | F40: 58268 | G40: INCIDENTE | H40: SUCRE | I40: COROZAL | J40: DISTRICOL CERCATODO | K40: REDEBAN | L40: FO-25-1189573 | M40: 45843.647 | N40: 45845.536 | O40: NO | P40: USUARIO | Q40: COMUNICACION | R40: CONEXIONES DE COMERCIO | S40: AGREGADOR | U40: CERRADO | V40: 05-07 SE ESCALA PARA VISITA. LLAMAR ANTES DE VISITAR, CONFIRMAR FALLA Y DATOS 0 07-07 SE VISITA SITIO SE VERIFICA INFORMACIÓN SE REALIZA PRIMEROS AUXILIOS, LA FALLA CORRESPONDE AL CANAL DE COMERCIO, SE REALIZARON PRUEBAS EXITOSAS CON OTRO MÓDEM. EL CB SE ENCUENTRA FUNCIONANDO NORMALMENTE. TECLADO OK, IMPRESIÓN OK, LECTURA CHIP OK , ESCANEAR OK. | W40: VISITA_TÉCNICA | X40: IKZZZ609 | Y40: TIPO II | Z40: TERRESTRE | AA40: SANTOS GUZMAN CHRISTIAN FELIPE | AB40: 1 | AC40: 0 | AD40: 0 | AE40: 0 | AF40: =IF(W40="SOPORTE_TELEFÓNICO",'BASE LIQUIDACION'!$B$10,IF(Y40="TIPO I",'BASE LIQUIDACION'!$C$3,IF(Y40="TIPO II",'BASE LIQUIDACION'!$C$4,IF(Y40="TIPO III",'BASE LIQUIDACION'!$C$5,'BASE LIQUIDACION'!$C$7)))) -> 163813.56 | AG40: =IF(W40="SOPORTE_TELEFÓNICO",'BASE LIQUIDACION'!$B$10,(AB40*AF40+AC40*'BASE LIQUIDACION'!$B$12+AD40*'BASE LIQUIDACION'!$B$11+INCIDENTES!AE40*'BASE LIQUIDACION'!$B$13)) -> 163813.56
A41: MEDELLIN | B41: =VLOOKUP(A41,'CENTRO DE COSTOS'!A:D,4,FALSE) -> JUAN SEBASTIÁN RÍOS CASTRILLÓN | C41: =VLOOKUP(A41,'CENTRO DE COSTOS'!A:D,2,FALSE) -> 0004-0005 | D41: 5376 | E41: 2404540 | F41: 27550 | G41: INCIDENTE | H41: ANTIOQUIA | I41: LA CEJA | J41: COMCARD LA CEJA VARIEDADES | K41: REDEBAN | L41: FO-25-1193106 | M41: 45845.409 | N41: 45845.593 | O41: NO | P41: USUARIO | Q41: MANTENIMIENTO | R41: MANTENIMIENTO GENERAL | S41: AGREGADOR | U41: CERRADO | V41: 07-07 SE ESCALA PARA VISITA. LLAMAR ANTES DE VISITAR, CONFIRMAR FALLA Y DATOS 0 07-07 SE REALIZA MANTENIMIENTO SE CONFIGURA DE NUEVO LA LECTORA | W41: VISITA_TÉCNICA | X41: 99DZZ432 | Y41: TIPO II | Z41: TERRESTRE | AA41: CERPA SUAREZ DUVAN CAMILO | AB41: 1 | AC41: 0 | AD41: 0 | AE41: 0 | AF41: =IF(W41="SOPORTE_TELEFÓNICO",'BASE LIQUIDACION'!$B$10,IF(Y41="TIPO I",'BASE LIQUIDACION'!$C$3,IF(Y41="TIPO II",'BASE LIQUIDACION'!$C$4,IF(Y41="TIPO III",'BASE LIQUIDACION'!$C$5,'BASE LIQUIDACION'!$C$7)))) -> 163813.56 | AG41: =IF(W41="SOPORTE_TELEFÓNICO",'BASE LIQUIDACION'!$B$10,(AB41*AF41+AC41*'BASE LIQUIDACION'!$B$12+AD41*'BASE LIQUIDACION'!$B$11+INCIDENTES!AE41*'BASE LIQUIDACION'!$B$13)) -> 163813.56
A42: NEIVA | B42: =VLOOKUP(A42,'CENTRO DE COSTOS'!A:D,4,FALSE) -> KEVIN ALEXIS CORZO BUSTOS | C42: =VLOOKUP(A42,'CENTRO DE COSTOS'!A:D,2,FALSE) -> 0004-0007 | D42: 18001 | E42: 2395638 | F42: 70552 | G42: INCIDENTE | H42: CAQUETA | I42: FLORENCIA | J42: BARRIO ABBAS TURBAY FLORENICA | K42: REDEBAN | L42: FO-25-1183136 | M42: 45842.398 | N42: 45845.6 | O42: NO | P42: USUARIO | Q42: CIERRE | R42: COMERCIO NO REALIZA CIERRE | S42: CB UNO A UNO | U42: CERRADO | V42: 04-07 SE ESCALA PARA VISITA. LLAMAR ANTES DE VISITAR, CONFIRMAR FALLA Y DATOS 0 07-07 SE REALIZA BORRADO DE VERSIÓN SE INSTALA NUEVAMENTE, SE CONFIGURA PARÁMETROS SE INICIALIZA, SE REALIZA PRUEBAS CB OK SE DEJA OPERATIVO | W42: VISITA_TÉCNICA | X42: SV005490 | Y42: TIPO IV | Z42: TERRESTRE | AA42: BERMUDEZ SANCHEZ JOSE NEYBER | AB42: 1 | AC42: 0 | AD42: 0 | AE42: 0 | AF42: =IF(W42="SOPORTE_TELEFÓNICO",'BASE LIQUIDACION'!$B$10,IF(Y42="TIPO I",'BASE LIQUIDACION'!$C$3,IF(Y42="TIPO II",'BASE LIQUIDACION'!$C$4,IF(Y42="TIPO III",'BASE LIQUIDACION'!$C$5,'BASE LIQUIDACION'!$C$7)))) -> 479589.74 | AG42: =IF(W42="SOPORTE_TELEFÓNICO",'BASE LIQUIDACION'!$B$10,(AB42*AF42+AC42*'BASE LIQUIDACION'!$B$12+AD42*'BASE LIQUIDACION'!$B$11+INCIDENTES!AE42*'BASE LIQUIDACION'!$B$13)) -> 479589.74
A43: VILLAVICENCIO | B43: =VLOOKUP(A43,'CENTRO DE COSTOS'!A:D,4,FALSE) -> KEVIN ALEXIS CORZO BUSTOS | C43: =VLOOKUP(A43,'CENTRO DE COSTOS'!A:D,2,FALSE) -> 0004-0007 | D43: 50568 | E43: 2395867 | F43: 51424 | G43: INCIDENTE | H43: META | I43: PUERTO GAITAN | J43: BARRIO ZONA RURAL PUERTO GAITA | K43: REDEBAN | L43: FO-25-1183116 | M43: 45842.417 | N43: 45845.603 | O43: NO | P43: USUARIO | Q43: NO ENCIENDE | R43: CONEXIONES DE COMERCIO | S43: CB UNO A UNO | U43: CERRADO | V43: 04-07 SE INTENTA COMUNICACION CON CB AL NUMERO 3207684459 APAGADO, FAVOR LLAMAR LLAMAR ANTES DE VISITAR, CONFIRMAR FALLA Y DATOS 05/07/2025 POR HORARIO DE ATENCIÓN ABREN NUEVAMENTE HASTA EL DÍA LUNES. Y EL TRANSPORTE HACIA LA VEREDA DESDE PUERTO GAITAN SALEN EN HORAS DETERMINADAS Y ESCASO. 07-07 SE REALIZA VISITA A CB COMERCIO CERRADO SE REALIZA COMUNICACIÓN CON LA SEÑORA JHOANA 3207684459 QUIEN MANIFIESTA SERVICIO OPERATIVO SIN NOVEDADES | W43: VISITA_TÉCNICA | X43: 0 | Y43: TIPO III | Z43: TERRESTRE | AA43: CASTRILLON URREA LONDIER LEANDRO | AB43: 1 | AC43: 0 | AD43: 0 | AE43: 0 | AF43: =IF(W43="SOPORTE_TELEFÓNICO",'BASE LIQUIDACION'!$B$10,IF(Y43="TIPO I",'BASE LIQUIDACION'!$C$3,IF(Y43="TIPO II",'BASE LIQUIDACION'!$C$4,IF(Y43="TIPO III",'BASE LIQUIDACION'!$C$5,'BASE LIQUIDACION'!$C$7)))) -> 275728.38 | AG43: =IF(W43="SOPORTE_TELEFÓNICO",'BASE LIQUIDACION'!$B$10,(AB43*AF43+AC43*'BASE LIQUIDACION'!$B$12+AD43*'BASE LIQUIDACION'!$B$11+INCIDENTES!AE43*'BASE LIQUIDACION'!$B$13)) -> 275728.38
A44: CALI | B44: =VLOOKUP(A44,'CENTRO DE COSTOS'!A:D,4,FALSE) -> DIEGO FERNANDO HENAO CARDONA | C44: =VLOOKUP(A44,'CENTRO DE COSTOS'!A:D,2,FALSE) -> 0004-0003 | D44: 19001 | E44: 2405947 | F44: 66891 | G44: INCIDENTE | H44: CAUCA | I44: POPAYAN | J44: BARRIO CENTRO POPAYAN 25 | K44: REDEBAN | L44: FO-25-1194218 | M44: 45845.463 | N44: 45845.645 | O44: NO | P44: USUARIO | Q44: COMUNICACION | R44: CONEXIONES DE COMERCIO | S44: CB UNO A UNO | U44: CERRADO | V44: 07-07 SE ESCALA PARA VISITA. LLAMAR ANTES DE VISITAR, CONFIRMAR FALLA Y DATOS 0 07-07 SE REALIZA VALIDACION TELEFONICA CON EL SEÑOR JOEL, SE ENCUENTRA QUE AL TRATAR DE REALIZAR UN CAMBIO TROCO LAS CONEXIONES DEL DATAFONO, SE LE EXPLICA LA MANERA CORRECTA DE CONEXION, EL CLIENTE LA REALIZA Y REALIZA PRUEBAS EXITOSAS DE SERVICIO | W44: SOPORTE_TELEFÓNICO | X44: 0 | Y44: TIPO III | Z44: TERRESTRE | AA44: HENAO CARDONA DIEGO FERNANDO | AB44: 0 | AC44: 0 | AD44: 0 | AE44: 0 | AF44: =IF(W44="SOPORTE_TELEFÓNICO",'BASE LIQUIDACION'!$B$10,IF(Y44="TIPO I",'BASE LIQUIDACION'!$C$3,IF(Y44="TIPO II",'BASE LIQUIDACION'!$C$4,IF(Y44="TIPO III",'BASE LIQUIDACION'!$C$5,'BASE LIQUIDACION'!$C$7)))) -> 37904.654 | AG44: =IF(W44="SOPORTE_TELEFÓNICO",'BASE LIQUIDACION'!$B$10,(AB44*AF44+AC44*'BASE LIQUIDACION'!$B$12+AD44*'BASE LIQUIDACION'!$B$11+INCIDENTES!AE44*'BASE LIQUIDACION'!$B$13)) -> 37904.654
A45: CALI | B45: =VLOOKUP(A45,'CENTRO DE COSTOS'!A:D,4,FALSE) -> DIEGO FERNANDO HENAO CARDONA | C45: =VLOOKUP(A45,'CENTRO DE COSTOS'!A:D,2,FALSE) -> 0004-0003 | D45: 76109 | E45: 2405077 | F45: 67291 | G45: INCIDENTE | H45: VALLE DEL CAUCA | I45: BUENAVENTURA | J45: BARRIO EL TRIUNFO BUENAVENTURA | K45: REDEBAN | L45: FO-25-1193344 | M45: 45845.43 | N45: 45845.66 | O45: NO | P45: USUARIO | Q45: LECTOR DE BARRAS | R45: CAPACITACION MANIPULACION DE COMERCIO | S45: CB UNO A UNO | U45: CERRADO | V45: 07-07 SE ESCALA PARA VISITA. LLAMAR ANTES DE VISITAR, CONFIRMAR FALLA Y DATOS 0 07-07 SE VALIDA CON LA SEÑORA NATALIA EL PROBLEMA DE FORMATO INVALIDO, INDICA QUE UNAS FACTURAS LE APARECEEN ASI, SE PROCEDE A VALIDAR CON UNA FACTURA DE CLARO PERO EL LECTOR LA LEE SIN PROBLEMA, SE LE PIDE VALIDAR CON UNAS FACTURAS DISTINTAS Y TAMBIEN SON LEIDAS, SE LE INDICA QUE VALIDE EL CONVENIO DE ESAS FACCTURAS YA QUE EL PROBLEMA NO ES EL EQUIPO SINO EL TIPO DE FACTURA QUE ESTA INTENTANDO PAGAR | W45: SOPORTE_TELEFÓNICO | X45: 0 | Y45: TIPO III | Z45: TERRESTRE | AA45: HENAO CARDONA DIEGO FERNANDO | AB45: 0 | AC45: 0 | AD45: 0 | AE45: 0 | AF45: =IF(W45="SOPORTE_TELEFÓNICO",'BASE LIQUIDACION'!$B$10,IF(Y45="TIPO I",'BASE LIQUIDACION'!$C$3,IF(Y45="TIPO II",'BASE LIQUIDACION'!$C$4,IF(Y45="TIPO III",'BASE LIQUIDACION'!$C$5,'BASE LIQUIDACION'!$C$7)))) -> 37904.654 | AG45: =IF(W45="SOPORTE_TELEFÓNICO",'BASE LIQUIDACION'!$B$10,(AB45*AF45+AC45*'BASE LIQUIDACION'!$B$12+AD45*'BASE LIQUIDACION'!$B$11+INCIDENTES!AE45*'BASE LIQUIDACION'!$B$13)) -> 37904.654
A46: MEDELLIN | B46: =VLOOKUP(A46,'CENTRO DE COSTOS'!A:D,4,FALSE) -> JUAN SEBASTIÁN RÍOS CASTRILLÓN | C46: =VLOOKUP(A46,'CENTRO DE COSTOS'!A:D,2,FALSE) -> 0004-0005 | D46: 5579 | E46: 2394084 | F46: 45592 | G46: INCIDENTE | H46: ANTIOQUIA | I46: PUERTO BERRIO | J46: BARRIO EL HOYO PUERTO BERRIO | K46: REDEBAN | L46: FO-25-1181597 | M46: 45842.333 | N46: 45845.663 | O46: NO | P46: USUARIO | Q46: MANTENIMIENTO | R46: MANTENIMIENTO GENERAL | S46: CB UNO A UNO | U46: CERRADO | V46: 04-07 SE INTENTA COMUNICACION CON CB AL NUMERO 3117587992 APAGADO, FAVOR LLAMAR LLAMAR ANTES DE VISITAR, CONFIRMAR FALLA Y DATOS 0 07-07 PINPAD NO ENCIENDE YA QUE EL HUB ESTABA MAL CONECTADO, SE CONECTA Y QUEDA OPERATIVO | W46: VISITA_TÉCNICA | X46: AD000819 | Y46: TIPO III | Z46: TERRESTRE | AA46: BADEL ACUÑA LUIS ALBERTO | AB46: 1 | AC46: 0 | AD46: 0 | AE46: 0 | AF46: =IF(W46="SOPORTE_TELEFÓNICO",'BASE LIQUIDACION'!$B$10,IF(Y46="TIPO I",'BASE LIQUIDACION'!$C$3,IF(Y46="TIPO II",'BASE LIQUIDACION'!$C$4,IF(Y46="TIPO III",'BASE LIQUIDACION'!$C$5,'BASE LIQUIDACION'!$C$7)))) -> 275728.38 | AG46: =IF(W46="SOPORTE_TELEFÓNICO",'BASE LIQUIDACION'!$B$10,(AB46*AF46+AC46*'BASE LIQUIDACION'!$B$12+AD46*'BASE LIQUIDACION'!$B$11+INCIDENTES!AE46*'BASE LIQUIDACION'!$B$13)) -> 275728.38
A47: BOGOTA | B47: =VLOOKUP(A47,'CENTRO DE COSTOS'!A:D,4,FALSE) -> WILLIAM ASDRUBAL ROZO ROZO | C47: =VLOOKUP(A47,'CENTRO DE COSTOS'!A:D,2,FALSE) -> 0004-0004 | D47: 11001 | E47: 2405769 | F47: 45935 | G47: INCIDENTE | H47: CUNDINAMARCA | I47: BOGOTA | J47: PTM BOGOTA TRIGOS CARNES LA GR | K47: REDEBAN | L47: FO-25-1194215 | M47: 45845.463 | N47: 45845.717 | O47: NO | P47: USUARIO | Q47: USUARIOS | R47: MALA MANIPULACION POS | S47: AGREGADOR | U47: CERRADO | V47: 07-07 SE ESCALA PARA VISITA. LLAMAR ANTES DE VISITAR, CONFIRMAR FALLA Y DATOS 0 07-07 SE REALIZA COMUNICACIÓN AL NÚMERO 3164115734 INDICANDO LA SEÑORA MARIANA CRUZ QUE SOLICITA CAMBIO DEL NOMBRE DE CB PERO SE LE INFORMA QUE NO SE PUEDE REALIZAR ESE CAMBIO YA QUE POR PARTE DE REDEBAN NO AUTORIZAN ,SOLO SE PUEDE MODIFICAR DATOS DE DIRECCIÓN CUANDO SOLICITAN TRASLADOS ,SE LE INFORMA AL CLIENTE Y INDICA NO NECESITAR VISITA | W47: SOPORTE_TELEFÓNICO | X47: 0 | Y47: TIPO I | Z47: TERRESTRE | AA47: GALINDO ROJAS LUIS FELIPE | AB47: 0 | AC47: 0 | AD47: 0 | AE47: 0 | AF47: =IF(W47="SOPORTE_TELEFÓNICO",'BASE LIQUIDACION'!$B$10,IF(Y47="TIPO I",'BASE LIQUIDACION'!$C$3,IF(Y47="TIPO II",'BASE LIQUIDACION'!$C$4,IF(Y47="TIPO III",'BASE LIQUIDACION'!$C$5,'BASE LIQUIDACION'!$C$7)))) -> 37904.654 | AG47: =IF(W47="SOPORTE_TELEFÓNICO",'BASE LIQUIDACION'!$B$10,(AB47*AF47+AC47*'BASE LIQUIDACION'!$B$12+AD47*'BASE LIQUIDACION'!$B$11+INCIDENTES!AE47*'BASE LIQUIDACION'!$B$13)) -> 37904.654
A48: CARTAGENA | B48: =VLOOKUP(A48,'CENTRO DE COSTOS'!A:D,4,FALSE) -> JOSE MAURICIO HERNANDEZ ROJAS | C48: =VLOOKUP(A48,'CENTRO DE COSTOS'!A:D,2,FALSE) -> 0004-0001 | D48: 13001 | E48: 2405449 | F48: 66684 | G48: INCIDENTE | H48: BOLIVAR | I48: CARTAGENA | J48: PAGAFACIL RAMBLAS | K48: REDEBAN | L48: FO-25-1193793 | M48: 45845.447 | N48: 45845.733 | O48: NO | P48: USUARIO | Q48: USUARIOS | R48: USUARIOS BLOQUEADOS | S48: ROBUSTO | U48: CERRADO | V48: 07-07 SE ESCALA PARA VISITA. LLAMAR ANTES DE VISITAR, CONFIRMAR FALLA Y DATOS 0 07-07 SE BRINDA APOYO TELEFONO Y SE LE DAN INSTRUCCIONES DE COMO RESTABLECER EL USUARIO SUPERVISOR PARA PODER REALIZAR LOS DUPLICADOS , REALIZA PRUEBA Y TODO QUEDA OK | W48: SOPORTE_TELEFÓNICO | X48: 0 | Y48: TIPO I | Z48: TERRESTRE | AA48: MARTINEZ SALGUEDO ANDRES AUGUSTO | AB48: 0 | AC48: 0 | AD48: 0 | AE48: 0 | AF48: =IF(W48="SOPORTE_TELEFÓNICO",'BASE LIQUIDACION'!$B$10,IF(Y48="TIPO I",'BASE LIQUIDACION'!$C$3,IF(Y48="TIPO II",'BASE LIQUIDACION'!$C$4,IF(Y48="TIPO III",'BASE LIQUIDACION'!$C$5,'BASE LIQUIDACION'!$C$7)))) -> 37904.654 | AG48: =IF(W48="SOPORTE_TELEFÓNICO",'BASE LIQUIDACION'!$B$10,(AB48*AF48+AC48*'BASE LIQUIDACION'!$B$12+AD48*'BASE LIQUIDACION'!$B$11+INCIDENTES!AE48*'BASE LIQUIDACION'!$B$13)) -> 37904.654
A49: BOGOTA | B49: =VLOOKUP(A49,'CENTRO DE COSTOS'!A:D,4,FALSE) -> WILLIAM ASDRUBAL ROZO ROZO | C49: =VLOOKUP(A49,'CENTRO DE COSTOS'!A:D,2,FALSE) -> 0004-0004 | D49: 25286 | E49: 2404508 | F49: 76006 | G49: INCIDENTE | H49: CUNDINAMARCA | I49: FUNZA | J49: BARRIO LA CITA FUNZA 1 | K49: REDEBAN | L49: FO-25-1193101 | M49: 45845.404 | N49: 45846.408 | O49: NO | P49: ENTIDAD | Q49: ERROR DE TRANSACCIONES | R49: CONVENIOS NO HABILITADOS | S49: CB UNO A UNO | U49: CERRADO | V49: 07-07 SE ESCALA PARA VISITA. LLAMAR ANTES DE VISITAR, CONFIRMAR FALLA Y DATOS 0 08-07 SE REALIZA VISITA AL COMERCIO PARA VALIDAR FUNCIONAMIENTO DE PAGO POR CONVENIO Y TODO OPERA CON TOTAL NORMALIDAD. SE REALIZAN PRUEBAS OK. | W49: VISITA_TÉCNICA | X49: LM0BZ650 | Y49: TIPO II | Z49: TERRESTRE | AA49: CORTES VELANDIA MIGUEL ANGEL | AB49: 1 | AC49: 0 | AD49: 0 | AE49: 0 | AF49: =IF(W49="SOPORTE_TELEFÓNICO",'BASE LIQUIDACION'!$B$10,IF(Y49="TIPO I",'BASE LIQUIDACION'!$C$3,IF(Y49="TIPO II",'BASE LIQUIDACION'!$C$4,IF(Y49="TIPO III",'BASE LIQUIDACION'!$C$5,'BASE LIQUIDACION'!$C$7)))) -> 163813.56 | AG49: =IF(W49="SOPORTE_TELEFÓNICO",'BASE LIQUIDACION'!$B$10,(AB49*AF49+AC49*'BASE LIQUIDACION'!$B$12+AD49*'BASE LIQUIDACION'!$B$11+INCIDENTES!AE49*'BASE LIQUIDACION'!$B$13)) -> 163813.56
A50: PEREIRA | B50: =VLOOKUP(A50,'CENTRO DE COSTOS'!A:D,4,FALSE) -> DIEGO FERNANDO HENAO CARDONA | C50: =VLOOKUP(A50,'CENTRO DE COSTOS'!A:D,2,FALSE) -> 0004-0002 | D50: 63001 | E50: 2410786 | F50: 25343 | G50: INCIDENTE | H50: QUINDIO | I50: ARMENIA | J50: ARA0086 CASA FOGATA | K50: REDEBAN | L50: FO-25-1198308 | M50: 45846.347 | N50: 45846.512 | O50: NO | P50: USUARIO | Q50: MANTENIMIENTO | R50: MANTENIMIENTO GENERAL | S50: RETAIL | U50: CERRADO | V50: 08-07 SE ESCALA CASO ARA A LA RED**8-07 TU SOLICITUD REFERENTE A GENERACIÓN DE CASOS CB ARA BANCOLOMBIA QUEDÓ RADICADA BAJO EL TICKET NÚMERO 5705463 AL ÁREA ENCARGADA. 0 0 | W50: SOPORTE_TELEFÓNICO | X50: 0 | Y50: TIPO II | Z50: TERRESTRE | AA50: 0 | AB50: 0 | AC50: 0 | AD50: 0 | AE50: 0 | AF50: =IF(W50="SOPORTE_TELEFÓNICO",'BASE LIQUIDACION'!$B$10,IF(Y50="TIPO I",'BASE LIQUIDACION'!$C$3,IF(Y50="TIPO II",'BASE LIQUIDACION'!$C$4,IF(Y50="TIPO III",'BASE LIQUIDACION'!$C$5,'BASE LIQUIDACION'!$C$7)))) -> 37904.654 | AG50: =IF(W50="SOPORTE_TELEFÓNICO",'BASE LIQUIDACION'!$B$10,(AB50*AF50+AC50*'BASE LIQUIDACION'!$B$12+AD50*'BASE LIQUIDACION'!$B$11+INCIDENTES!AE50*'BASE LIQUIDACION'!$B$13)) -> 37904.654
A51: CALI | B51: =VLOOKUP(A51,'CENTRO DE COSTOS'!A:D,4,FALSE) -> DIEGO FERNANDO HENAO CARDONA | C51: =VLOOKUP(A51,'CENTRO DE COSTOS'!A:D,2,FALSE) -> 0004-0003 | D51: 76001 | E51: 2412646 | F51: 30980 | G51: INCIDENTE | H51: VALLE DEL CAUCA | I51: CALI | J51: BARRIO SALOMIA CALI | K51: REDEBAN | L51: FO-25-1199771 | M51: 45846.455 | N51: 45846.562 | O51: NO | P51: USUARIO | Q51: USUARIOS | R51: USUARIOS BLOQUEADOS | S51: CB UNO A UNO | U51: CERRADO | V51: 08-07 SE ESCALA PARA VISITA. LLAMAR ANTES DE VISITAR, CONFIRMAR FALLA Y DATOS 0 08-07 SE HABLA CON EL CLIENTE QUIEN INDICA QUE AYER NO PUDO REALIZAR CIERRE POR QUE EL DATAFONO NO LE PERMITIA EL INGRESO CON EL USUARIO QUE TENIA , PERO QUE AHORA LLEGO LA COMPAÑERA Y A ELLA SI LE DEJO CON EL USUARIO DE ELLA, YA PUDIERON SOLUCIONAR | W51: SOPORTE_TELEFÓNICO | X51: 0 | Y51: TIPO I | Z51: TERRESTRE | AA51: HENAO CARDONA DIEGO FERNANDO | AB51: 0 | AC51: 0 | AD51: 0 | AE51: 0 | AF51: =IF(W51="SOPORTE_TELEFÓNICO",'BASE LIQUIDACION'!$B$10,IF(Y51="TIPO I",'BASE LIQUIDACION'!$C$3,IF(Y51="TIPO II",'BASE LIQUIDACION'!$C$4,IF(Y51="TIPO III",'BASE LIQUIDACION'!$C$5,'BASE LIQUIDACION'!$C$7)))) -> 37904.654 | AG51: =IF(W51="SOPORTE_TELEFÓNICO",'BASE LIQUIDACION'!$B$10,(AB51*AF51+AC51*'BASE LIQUIDACION'!$B$12+AD51*'BASE LIQUIDACION'!$B$11+INCIDENTES!AE51*'BASE LIQUIDACION'!$B$13)) -> 37904.654
A52: MANIZALES | B52: =VLOOKUP(A52,'CENTRO DE COSTOS'!A:D,4,FALSE) -> DIEGO FERNANDO HENAO CARDONA | C52: =VLOOKUP(A52,'CENTRO DE COSTOS'!A:D,2,FALSE) -> 0004-0002 | D52: 17001 | E52: 2409340 | F52: 71098 | G52: INCIDENTE | H52: CALDAS | I52: MANIZALES | J52: DISTRICOL DISTRIBUIDORA DE COS | K52: REDEBAN | L52: FO-25-1196510 | M52: 45845.695 | N52: 45846.615 | O52: NO | P52: USUARIO | Q52: COMUNICACION | R52: CONEXIONES DE COMERCIO | S52: AGREGADOR | U52: CERRADO | V52: 07-07 SE ESCALA PARA VISITA. LLAMAR ANTES DE VISITAR, CONFIRMAR FALLA Y DATOS 0 08-07 SE REALIZA VISITA EN LA CUAL USUARIO INDICA QUE EL SERVICIO SE ENCUENTRA EN BUEN ESTADO, TENIA PROBLEMAS CON SU CABLEADO DEL PROVEEDOR DE INTERNET YA QUE SE ENCONTRABAN PISADOS, INDICA QUE CAMBIARON EL CABLE Y LE FUNCIONA CORRECTAMENTE, SE HACEN PRUEBAS SERVICIO OK | W52: VISITA_TÉCNICA | X52: NN00B520 | Y52: TIPO I | Z52: TERRESTRE | AA52: AGUIRRE HENAO RAUL EDUARDO | AB52: 1 | AC52: 0 | AD52: 0 | AE52: 0 | AF52: =IF(W52="SOPORTE_TELEFÓNICO",'BASE LIQUIDACION'!$B$10,IF(Y52="TIPO I",'BASE LIQUIDACION'!$C$3,IF(Y52="TIPO II",'BASE LIQUIDACION'!$C$4,IF(Y52="TIPO III",'BASE LIQUIDACION'!$C$5,'BASE LIQUIDACION'!$C$7)))) -> 65960.474 | AG52: =IF(W52="SOPORTE_TELEFÓNICO",'BASE LIQUIDACION'!$B$10,(AB52*AF52+AC52*'BASE LIQUIDACION'!$B$12+AD52*'BASE LIQUIDACION'!$B$11+INCIDENTES!AE52*'BASE LIQUIDACION'!$B$13)) -> 65960.474
A53: NEIVA | B53: =VLOOKUP(A53,'CENTRO DE COSTOS'!A:D,4,FALSE) -> KEVIN ALEXIS CORZO BUSTOS | C53: =VLOOKUP(A53,'CENTRO DE COSTOS'!A:D,2,FALSE) -> 0004-0007 | D53: 41551 | E53: 2412473 | F53: 42287 | G53: INCIDENTE | H53: HUILA | I53: PITALITO | J53: BARRIO SOLARTE PITALITO | K53: REDEBAN | L53: FO-25-1199282 | M53: 45846.441 | N53: 45847.448 | O53: NO | P53: USUARIO | Q53: COMUNICACION | R53: CONEXIONES DE COMERCIO | S53: CB UNO A UNO | U53: CERRADO | V53: 08-07 SE ESCALA PARA VISITA. LLAMAR ANTES DE VISITAR, CONFIRMAR FALLA Y DATOS 0 09-07 SE REALIZA VISITA AL PUNTO, CLIENTE INDICA QUE EQUIPO SE ENCUENTRA FUNCIONANDO CON NORMALIDAD DESPUÉS DE QUÉ CONECTÓ TODO CORRECTAMENTE. CLIENTE INDICA QUE SE COMUNICO A LA LINEA EN LA MAÑANA PARA CANCELAR ORDEN . CB OPERATIVO PRUEBAS CB OK | W53: VISITA_TÉCNICA | X53: 9B0NZ869 | Y53: TIPO III | Z53: TERRESTRE | AA53: DEVIA REINOSO JUAN CARLOS | AB53: 1 | AC53: 0 | AD53: 0 | AE53: 0 | AF53: =IF(W53="SOPORTE_TELEFÓNICO",'BASE LIQUIDACION'!$B$10,IF(Y53="TIPO I",'BASE LIQUIDACION'!$C$3,IF(Y53="TIPO II",'BASE LIQUIDACION'!$C$4,IF(Y53="TIPO III",'BASE LIQUIDACION'!$C$5,'BASE LIQUIDACION'!$C$7)))) -> 275728.38 | AG53: =IF(W53="SOPORTE_TELEFÓNICO",'BASE LIQUIDACION'!$B$10,(AB53*AF53+AC53*'BASE LIQUIDACION'!$B$12+AD53*'BASE LIQUIDACION'!$B$11+INCIDENTES!AE53*'BASE LIQUIDACION'!$B$13)) -> 275728.38
A54: MEDELLIN | B54: =VLOOKUP(A54,'CENTRO DE COSTOS'!A:D,4,FALSE) -> JUAN SEBASTIÁN RÍOS CASTRILLÓN | C54: =VLOOKUP(A54,'CENTRO DE COSTOS'!A:D,2,FALSE) -> 0004-0005 | D54: 5001 | E54: 2417367 | F54: 54118 | G54: INCIDENTE | H54: ANTIOQUIA | I54: MEDELLIN | J54: PTM MEDELLIN SUPER+ | K54: REDEBAN | L54: FO-25-1203971 | M54: 45847.342 | N54: 45847.462 | O54: NO | P54: USUARIO | Q54: MANTENIMIENTO | R54: MANTENIMIENTO GENERAL | S54: AGREGADOR | U54: CERRADO | V54: 09-07 SE ESCALA PARA VISITA. LLAMAR ANTES DE VISITAR, CONFIRMAR FALLA Y DATOS 0 09-07 SE REALIZA CAMBIO DE ENSORTIJADO, TODO OK | W54: VISITA_TÉCNICA | X54: XP3ZZ010 - XP3ZZ645 | Y54: TIPO I | Z54: TERRESTRE | AA54: HERNANDEZ CHAVARRIA JUAN CAMILO | AB54: 1 | AC54: 0 | AD54: 0 | AE54: 0 | AF54: =IF(W54="SOPORTE_TELEFÓNICO",'BASE LIQUIDACION'!$B$10,IF(Y54="TIPO I",'BASE LIQUIDACION'!$C$3,IF(Y54="TIPO II",'BASE LIQUIDACION'!$C$4,IF(Y54="TIPO III",'BASE LIQUIDACION'!$C$5,'BASE LIQUIDACION'!$C$7)))) -> 65960.474 | AG54: =IF(W54="SOPORTE_TELEFÓNICO",'BASE LIQUIDACION'!$B$10,(AB54*AF54+AC54*'BASE LIQUIDACION'!$B$12+AD54*'BASE LIQUIDACION'!$B$11+INCIDENTES!AE54*'BASE LIQUIDACION'!$B$13)) -> 65960.474
A55: IBAGUE | B55: =VLOOKUP(A55,'CENTRO DE COSTOS'!A:D,4,FALSE) -> KEVIN ALEXIS CORZO BUSTOS | C55: =VLOOKUP(A55,'CENTRO DE COSTOS'!A:D,2,FALSE) -> 0004-0007 | D55: 17380 | E55: 2418361 | F55: 75392 | G55: INCIDENTE | H55: CALDAS | I55: LA DORADA | J55: BARRIO CENTRO LA DORADA 12 | K55: REDEBAN | L55: FO-25-1204614 | M55: 45847.394 | N55: 45847.466 | O55: NO | P55: USUARIO | Q55: LECTOR DE BARRAS | R55: CAPACITACION MANIPULACION DE COMERCIO | S55: CB UNO A UNO | U55: CERRADO | V55: 09-07 EN COMUNICACION CON LA SEÑORA NANCY HURTADO AL NUMERO 3116091744 INDICA QUE EL LECTOR DE BARRAS NO LEE LAS FACTURAS, ES INTERMITENTE, CONFIRMA DATOS, SE ESCALA PARA VISITA 0 09-07 SE HABLA CON LA SEÑORA NANCY HURTADO, AL NÚMERO DE TELÉFONO 3116091744, ME INDICA QUE EL LECTOR SIRVE Y QUE NO LEE ALGUNOS RECIBOS, LE INDICO QUE HAY UNOS RECIBOS QUE SI TIENEN CONVENIO CON BANCOLOMBIA Y OTROS NO, QUE CUANDO LO HAGA LA LECTURA DE BARRAS EN UN HOJA SEA IMPRESA A LÁSER, QUE CUANDO SEA DIGITAL LO HAGA CON LA ILUMINACIÓN DE CELULAR AL 100% Y QUE SE REFLEJE EL LÁSER EN LA PANTALLA DEL CELULAR AL RECEPTOR DEL LECTOR DE BARRAS. ME DICE QUE SOLO PASA CON ALGUNOS RECIBOS Y QUE EL LECTOR ESTÁ FUNCIONANDO. LA SEÑORA NANCY HURTADO, TERMINA LA LLAMADA RÁPIDO PORQUE ESTÁ ATENDIENDO EL CORRESPONSAL Y QUE CUALQUIER COSA ELLA VUELVE A LLAMAR Y QUE AGREDESE MIS INDICACIONES QUE NO SABÍA | W55: SOPORTE_TELEFÓNICO | X55: 0 | Y55: TIPO III | Z55: TERRESTRE | AA55: VARGAS HERRERA JHON JAIRO | AB55: 0 | AC55: 0 | AD55: 0 | AE55: 0 | AF55: =IF(W55="SOPORTE_TELEFÓNICO",'BASE LIQUIDACION'!$B$10,IF(Y55="TIPO I",'BASE LIQUIDACION'!$C$3,IF(Y55="TIPO II",'BASE LIQUIDACION'!$C$4,IF(Y55="TIPO III",'BASE LIQUIDACION'!$C$5,'BASE LIQUIDACION'!$C$7)))) -> 37904.654 | AG55: =IF(W55="SOPORTE_TELEFÓNICO",'BASE LIQUIDACION'!$B$10,(AB55*AF55+AC55*'BASE LIQUIDACION'!$B$12+AD55*'BASE LIQUIDACION'!$B$11+INCIDENTES!AE55*'BASE LIQUIDACION'!$B$13)) -> 37904.654
A56: CUCUTA | B56: =VLOOKUP(A56,'CENTRO DE COSTOS'!A:D,4,FALSE) -> MIGUEL JULIÁN HERNÁNDEZ GUARÍN | C56: =VLOOKUP(A56,'CENTRO DE COSTOS'!A:D,2,FALSE) -> 0004-0008 | D56: 54498 | E56: 2416306 | F56: 60894 | G56: INCIDENTE | H56: NORTE DE SANTANDER | I56: OCAÑA | J56: PTM OCANA GILU | K56: REDEBAN | L56: FO-25-1205715 | M56: 45846.703 | N56: 45847.478 | O56: NO | P56: USUARIO | Q56: MANTENIMIENTO | R56: MANTENIMIENTO GENERAL | S56: AGREGADOR | U56: CERRADO | V56: 08-07 SE SOLICITA AL SEÑOR CESAR AUGUSTO LA DENUNCIA REALIZADA EN LA FISCALIA**9-07 10:34 SE ESCALA CASO A LA RED **9-07 11:00 ESTE CASO LO ESTAMOS MANEJANDO COMO UN TRASLADO NO SE HABÍA REALIZADO PORQUE EL CLIENTE NO NOS HABÍA COMPARTIDO LA DENUNCIA DE LOS EQUIPOS HURTADOS. POR FAVOR PROCEDER CON LA REPOSICIÓN DE LOS EQUIPOS.PUEDES PROCEDER CON EL CIERRE DEL CASO PORQUE JULI YA LO ESTÁ MANEJANDO COMO TRASLADO. 0 0 | W56: SOPORTE_TELEFÓNICO | X56: 0 | Y56: TIPO IV | Z56: TERRESTRE | AA56: 0 | AB56: 0 | AC56: 0 | AD56: 0 | AE56: 0 | AF56: =IF(W56="SOPORTE_TELEFÓNICO",'BASE LIQUIDACION'!$B$10,IF(Y56="TIPO I",'BASE LIQUIDACION'!$C$3,IF(Y56="TIPO II",'BASE LIQUIDACION'!$C$4,IF(Y56="TIPO III",'BASE LIQUIDACION'!$C$5,'BASE LIQUIDACION'!$C$7)))) -> 37904.654 | AG56: =IF(W56="SOPORTE_TELEFÓNICO",'BASE LIQUIDACION'!$B$10,(AB56*AF56+AC56*'BASE LIQUIDACION'!$B$12+AD56*'BASE LIQUIDACION'!$B$11+INCIDENTES!AE56*'BASE LIQUIDACION'!$B$13)) -> 37904.654
A57: PEREIRA | B57: =VLOOKUP(A57,'CENTRO DE COSTOS'!A:D,4,FALSE) -> DIEGO FERNANDO HENAO CARDONA | C57: =VLOOKUP(A57,'CENTRO DE COSTOS'!A:D,2,FALSE) -> 0004-0002 | D57: 76400 | E57: 2416669 | F57: 18445 | G57: INCIDENTE | H57: VALLE DEL CAUCA | I57: LA UNION | J57: BARRIO CENTRO II LA UNION | K57: REDEBAN | L57: FO-25-1203198 | M57: 45847.333 | N57: 45847.509 | O57: NO | P57: USUARIO | Q57: USUARIOS | R57: USUARIOS BLOQUEADOS | S57: CB UNO A UNO | U57: CERRADO | V57: 09-07 SE ESCALA PARA VISITA. LLAMAR ANTES DE VISITAR, CONFIRMAR FALLA Y DATOS 0 09-07 SE LLAMA AL CLIENTE Y SE HABLA CON EL SEÑOR ARNOLD QUIEN INDICA QUE EL YA HABIA LLAMADO A CANCELAR LA VISITA POR QUE AL APRECER EL USUARIO ESTABA BLOQUEADO, PERO ESTA MAÑANA YA LE FUNCIONO, SE CIERRA CASO | W57: SOPORTE_TELEFÓNICO | X57: 0 | Y57: TIPO II | Z57: TERRESTRE | AA57: HENAO CARDONA DIEGO FERNANDO | AB57: 0 | AC57: 0 | AD57: 0 | AE57: 0 | AF57: =IF(W57="SOPORTE_TELEFÓNICO",'BASE LIQUIDACION'!$B$10,IF(Y57="TIPO I",'BASE LIQUIDACION'!$C$3,IF(Y57="TIPO II",'BASE LIQUIDACION'!$C$4,IF(Y57="TIPO III",'BASE LIQUIDACION'!$C$5,'BASE LIQUIDACION'!$C$7)))) -> 37904.654 | AG57: =IF(W57="SOPORTE_TELEFÓNICO",'BASE LIQUIDACION'!$B$10,(AB57*AF57+AC57*'BASE LIQUIDACION'!$B$12+AD57*'BASE LIQUIDACION'!$B$11+INCIDENTES!AE57*'BASE LIQUIDACION'!$B$13)) -> 37904.654
A58: MEDELLIN | B58: =VLOOKUP(A58,'CENTRO DE COSTOS'!A:D,4,FALSE) -> JUAN SEBASTIÁN RÍOS CASTRILLÓN | C58: =VLOOKUP(A58,'CENTRO DE COSTOS'!A:D,2,FALSE) -> 0004-0005 | D58: 5001 | E58: 2416432 | F58: 31833 | G58: INCIDENTE | H58: ANTIOQUIA | I58: MEDELLIN | J58: BARRIO ROBLEDO PARQUE MEDELLIN | K58: REDEBAN | L58: FO-25-1202962 | M58: 45846.726 | N58: 45847.551 | O58: NO | P58: USUARIO | Q58: COMUNICACION | R58: CONEXIONES DE COMERCIO | S58: CB UNO A UNO | U58: CERRADO | V58: 08-07 SE ESCALA PARA VISITA. LLAMAR ANTES DE VISITAR, CONFIRMAR FALLA Y DATOS 0 09-07 SE REALIZA LA VALIDACIÓN DE LAS CONEXIONES SE VÁLIDA QUE EL SWITCH ESTABA DESCONECTADO Y SE HACEN PRUEBAS Y QUEDA OK | W58: VISITA_TÉCNICA | X58: 9B00K137 | Y58: TIPO I | Z58: TERRESTRE | AA58: MONTOYA VELEZ ANDRES FELIPE | AB58: 1 | AC58: 0 | AD58: 0 | AE58: 0 | AF58: =IF(W58="SOPORTE_TELEFÓNICO",'BASE LIQUIDACION'!$B$10,IF(Y58="TIPO I",'BASE LIQUIDACION'!$C$3,IF(Y58="TIPO II",'BASE LIQUIDACION'!$C$4,IF(Y58="TIPO III",'BASE LIQUIDACION'!$C$5,'BASE LIQUIDACION'!$C$7)))) -> 65960.474 | AG58: =IF(W58="SOPORTE_TELEFÓNICO",'BASE LIQUIDACION'!$B$10,(AB58*AF58+AC58*'BASE LIQUIDACION'!$B$12+AD58*'BASE LIQUIDACION'!$B$11+INCIDENTES!AE58*'BASE LIQUIDACION'!$B$13)) -> 65960.474
A59: MEDELLIN | B59: =VLOOKUP(A59,'CENTRO DE COSTOS'!A:D,4,FALSE) -> JUAN SEBASTIÁN RÍOS CASTRILLÓN | C59: =VLOOKUP(A59,'CENTRO DE COSTOS'!A:D,2,FALSE) -> 0004-0005 | D59: 5390 | E59: 2412577 | F59: 39390 | G59: INCIDENTE | H59: ANTIOQUIA | I59: LA PINTADA | J59: BARRIO PARQUE LA PINTADA 1 | K59: REDEBAN | L59: FO-25-1199750 | M59: 45846.447 | N59: 45847.574 | O59: NO | P59: USUARIO | Q59: MANTENIMIENTO | R59: MANTENIMIENTO GENERAL | S59: CB UNO A UNO | U59: CERRADO | V59: 08-07 SE ESCALA PARA VISITA. LLAMAR ANTES DE VISITAR, CONFIRMAR FALLA Y DATOS 0 09-07 SE REALIZA MANTENIMIENTO AL PIN PAD POR QUÉ NO LEE ALGUNAS TARJETAS | W59: VISITA_TÉCNICA | X59: AC007709 | Y59: TIPO II | Z59: TERRESTRE | AA59: CERPA SUAREZ DUVAN CAMILO | AB59: 1 | AC59: 0 | AD59: 0 | AE59: 0 | AF59: =IF(W59="SOPORTE_TELEFÓNICO",'BASE LIQUIDACION'!$B$10,IF(Y59="TIPO I",'BASE LIQUIDACION'!$C$3,IF(Y59="TIPO II",'BASE LIQUIDACION'!$C$4,IF(Y59="TIPO III",'BASE LIQUIDACION'!$C$5,'BASE LIQUIDACION'!$C$7)))) -> 163813.56 | AG59: =IF(W59="SOPORTE_TELEFÓNICO",'BASE LIQUIDACION'!$B$10,(AB59*AF59+AC59*'BASE LIQUIDACION'!$B$12+AD59*'BASE LIQUIDACION'!$B$11+INCIDENTES!AE59*'BASE LIQUIDACION'!$B$13)) -> 163813.56
A60: BOGOTA | B60: =VLOOKUP(A60,'CENTRO DE COSTOS'!A:D,4,FALSE) -> WILLIAM ASDRUBAL ROZO ROZO | C60: =VLOOKUP(A60,'CENTRO DE COSTOS'!A:D,2,FALSE) -> 0004-0004 | D60: 11001 | E60: 2418733 | F60: 79982 | G60: INCIDENTE | H60: CUNDINAMARCA | I60: BOGOTA | J60: BARRIO LA MERCED NORTE BOGOTA | K60: REDEBAN | L60: FO-25-1204811 | M60: 45847.412 | N60: 45847.671 | O60: NO | P60: ENTIDAD | Q60: ERROR DE TRANSACCIONES | R60: CONVENIOS NO HABILITADOS | S60: CB UNO A UNO | U60: CERRADO | V60: 09-07 SE ESCALA PARA VISITA. LLAMAR ANTES DE VISITAR, CONFIRMAR FALLA Y DATOS 0 09-07 SE REALIZA VISITA A CB PARA ATENDER INCIDENTE SE REALIZA EXPLICACION DE COMO REALIZAR EL PAGO POR ENEL ,SE REALIZAN PRUEBAS OK | W60: VISITA_TÉCNICA | X60: SAXZZ557 | Y60: TIPO I | Z60: TERRESTRE | AA60: GALINDO ROJAS LUIS FELIPE | AB60: 1 | AC60: 0 | AD60: 0 | AE60: 0 | AF60: =IF(W60="SOPORTE_TELEFÓNICO",'BASE LIQUIDACION'!$B$10,IF(Y60="TIPO I",'BASE LIQUIDACION'!$C$3,IF(Y60="TIPO II",'BASE LIQUIDACION'!$C$4,IF(Y60="TIPO III",'BASE LIQUIDACION'!$C$5,'BASE LIQUIDACION'!$C$7)))) -> 65960.474 | AG60: =IF(W60="SOPORTE_TELEFÓNICO",'BASE LIQUIDACION'!$B$10,(AB60*AF60+AC60*'BASE LIQUIDACION'!$B$12+AD60*'BASE LIQUIDACION'!$B$11+INCIDENTES!AE60*'BASE LIQUIDACION'!$B$13)) -> 65960.474
A61: PEREIRA | B61: =VLOOKUP(A61,'CENTRO DE COSTOS'!A:D,4,FALSE) -> DIEGO FERNANDO HENAO CARDONA | C61: =VLOOKUP(A61,'CENTRO DE COSTOS'!A:D,2,FALSE) -> 0004-0002 | D61: 63001 | E61: 2416422 | F61: 44082 | G61: INCIDENTE | H61: QUINDIO | I61: ARMENIA | J61: MULTIPAGAS INDEGA ARMENIA | K61: REDEBAN | L61: FO-25-1202958 | M61: 45846.723 | N61: 45847.684 | O61: NO | P61: USUARIO | Q61: MANTENIMIENTO | R61: MANTENIMIENTO GENERAL | S61: ROBUSTO | U61: CERRADO | V61: 08-07 SE ESCALA PARA VISITA. LLAMAR ANTES DE VISITAR, CONFIRMAR FALLA Y DATOS 0 09-07 SE VISITA COMERCIO SE REALIZÓ VERIFICACIÓN DE DATAFONO Y CABLEADO, SE REALIZÓ PRUEBAS OK. | W61: VISITA_TÉCNICA | X61: 9B00G010 | Y61: TIPO II | Z61: TERRESTRE | AA61: SANCHEZ SOLORZANO JUAN SEBASTIAN | AB61: 1 | AC61: 0 | AD61: 0 | AE61: 0 | AF61: =IF(W61="SOPORTE_TELEFÓNICO",'BASE LIQUIDACION'!$B$10,IF(Y61="TIPO I",'BASE LIQUIDACION'!$C$3,IF(Y61="TIPO II",'BASE LIQUIDACION'!$C$4,IF(Y61="TIPO III",'BASE LIQUIDACION'!$C$5,'BASE LIQUIDACION'!$C$7)))) -> 163813.56 | AG61: =IF(W61="SOPORTE_TELEFÓNICO",'BASE LIQUIDACION'!$B$10,(AB61*AF61+AC61*'BASE LIQUIDACION'!$B$12+AD61*'BASE LIQUIDACION'!$B$11+INCIDENTES!AE61*'BASE LIQUIDACION'!$B$13)) -> 163813.56
A62: MANIZALES | B62: =VLOOKUP(A62,'CENTRO DE COSTOS'!A:D,4,FALSE) -> DIEGO FERNANDO HENAO CARDONA | C62: =VLOOKUP(A62,'CENTRO DE COSTOS'!A:D,2,FALSE) -> 0004-0002 | D62: 17873 | E62: 2418722 | F62: 42699 | G62: INCIDENTE | H62: CALDAS | I62: VILLAMARIA | J62: MULTIPAGAS VILLAMARIA | K62: REDEBAN | L62: FO-25-1204822 | M62: 45847.411 | N62: 45847.71 | O62: NO | P62: USUARIO | Q62: NO ENCIENDE | R62: CONEXIONES DE COMERCIO | S62: ROBUSTO | U62: CERRADO | V62: 09-07 SE ESCALA PARA VISITA. LLAMAR ANTES DE VISITAR, CONFIRMAR FALLA Y DATOS 0 09-07 SE REALIZA VISITA CLIENTE INDICA QUE YA SE ENCUENTRA EN BUEN ESTADO Y NO SE LE REINICIA SERVICIO OK | W62: VISITA_TÉCNICA | X62: 9A7ZZ943 | Y62: TIPO I | Z62: TERRESTRE | AA62: AGUIRRE HENAO RAUL EDUARDO | AB62: 1 | AC62: 0 | AD62: 0 | AE62: 0 | AF62: =IF(W62="SOPORTE_TELEFÓNICO",'BASE LIQUIDACION'!$B$10,IF(Y62="TIPO I",'BASE LIQUIDACION'!$C$3,IF(Y62="TIPO II",'BASE LIQUIDACION'!$C$4,IF(Y62="TIPO III",'BASE LIQUIDACION'!$C$5,'BASE LIQUIDACION'!$C$7)))) -> 65960.474 | AG62: =IF(W62="SOPORTE_TELEFÓNICO",'BASE LIQUIDACION'!$B$10,(AB62*AF62+AC62*'BASE LIQUIDACION'!$B$12+AD62*'BASE LIQUIDACION'!$B$11+INCIDENTES!AE62*'BASE LIQUIDACION'!$B$13)) -> 65960.474
A63: BARRANQUILLA | B63: =VLOOKUP(A63,'CENTRO DE COSTOS'!A:D,4,FALSE) -> JOSE MAURICIO HERNANDEZ ROJAS | C63: =VLOOKUP(A63,'CENTRO DE COSTOS'!A:D,2,FALSE) -> 0004-0001 | D63: 8001 | E63: 2422146 | F63: 25233 | G63: INCIDENTE | H63: ATLANTICO | I63: BARRANQUILLA | J63: ARA0120 BQUILLA VILLA SAN PEDR | K63: REDEBAN | L63: FO-25-1207971 | M63: 45847.64 | N63: 45847.719 | O63: NO | P63: USUARIO | Q63: MANTENIMIENTO | R63: MANTENIMIENTO GENERAL | S63: RETAIL | U63: CERRADO | V63: 09-07 15:33 SE ESCALA CASO ARA A LA RED** 09-07 17:03 TU SOLICITUD REFERENTE A “GENERACIÓN DE CASOS CB ARA BANCOLOMBIA INC 2422146 CB 25233 “ QUEDÓ RADICADA BAJO EL TICKET NÚMERO 5708679 AL ÁREA ENCARGADA. PRONTO TE DARÁN RESPUESTA. 0 0 | W63: SOPORTE_TELEFÓNICO | X63: 0 | Y63: TIPO I | Z63: TERRESTRE | AA63: GARCIA CHAVARRIA TATIANA EDELMIRA | AB63: 0 | AC63: 0 | AD63: 0 | AE63: 0 | AF63: =IF(W63="SOPORTE_TELEFÓNICO",'BASE LIQUIDACION'!$B$10,IF(Y63="TIPO I",'BASE LIQUIDACION'!$C$3,IF(Y63="TIPO II",'BASE LIQUIDACION'!$C$4,IF(Y63="TIPO III",'BASE LIQUIDACION'!$C$5,'BASE LIQUIDACION'!$C$7)))) -> 37904.654 | AG63: =IF(W63="SOPORTE_TELEFÓNICO",'BASE LIQUIDACION'!$B$10,(AB63*AF63+AC63*'BASE LIQUIDACION'!$B$12+AD63*'BASE LIQUIDACION'!$B$11+INCIDENTES!AE63*'BASE LIQUIDACION'!$B$13)) -> 37904.654
A64: VILLAVICENCIO | B64: =VLOOKUP(A64,'CENTRO DE COSTOS'!A:D,4,FALSE) -> KEVIN ALEXIS CORZO BUSTOS | C64: =VLOOKUP(A64,'CENTRO DE COSTOS'!A:D,2,FALSE) -> 0004-0007 | D64: 95001 | E64: 2421437 | F64: 70956 | G64: INCIDENTE | H64: GUAVIARE | I64: SAN JOSE DEL GUAVIARE | J64: BARRIO LA ESPERANZA SAN JOSE D | K64: REDEBAN | L64: FO-25-1207554 | M64: 45847.597 | N64: 45848.484 | O64: NO | P64: ENTIDAD | Q64: ERROR DE TRANSACCIONES | R64: TRANSACCION NO PERMITIDA | S64: CB UNO A UNO | U64: CERRADO | V64: 09-07 SE ESCALA PARA VISITA. LLAMAR ANTES DE VISITAR, CONFIRMAR FALLA Y DATOS 0 10-07 SE REALIZA INICIALIZACION POR ERROR EN PARÁMETROS, PRUEBAS OK | W64: VISITA_TÉCNICA | X64: LN00D291 | Y64: TIPO IV | Z64: TERRESTRE | AA64: PEDREROS CONTRERAS MICHAEL STEVENS | AB64: 1 | AC64: 0 | AD64: 0 | AE64: 0 | AF64: =IF(W64="SOPORTE_TELEFÓNICO",'BASE LIQUIDACION'!$B$10,IF(Y64="TIPO I",'BASE LIQUIDACION'!$C$3,IF(Y64="TIPO II",'BASE LIQUIDACION'!$C$4,IF(Y64="TIPO III",'BASE LIQUIDACION'!$C$5,'BASE LIQUIDACION'!$C$7)))) -> 479589.74 | AG64: =IF(W64="SOPORTE_TELEFÓNICO",'BASE LIQUIDACION'!$B$10,(AB64*AF64+AC64*'BASE LIQUIDACION'!$B$12+AD64*'BASE LIQUIDACION'!$B$11+INCIDENTES!AE64*'BASE LIQUIDACION'!$B$13)) -> 479589.74
A65: CALI | B65: =VLOOKUP(A65,'CENTRO DE COSTOS'!A:D,4,FALSE) -> DIEGO FERNANDO HENAO CARDONA | C65: =VLOOKUP(A65,'CENTRO DE COSTOS'!A:D,2,FALSE) -> 0004-0003 | D65: 19548 | E65: 2409968 | F65: 57115 | G65: INCIDENTE | H65: CAUCA | I65: PIENDAMO | J65: BARRIO LUZ DEL PARAISO PIENDAM | K65: REDEBAN | L65: FO-25-1197333 | M65: 45846.333 | N65: 45848.485 | O65: NO | P65: USUARIO | Q65: CIERRE | R65: COMERCIO NO REALIZA CIERRE | S65: CB UNO A UNO | U65: CERRADO | V65: 08-07 SE ESCALA PARA VISITA. LLAMAR ANTES DE VISITAR, CONFIRMAR FALLA Y DATOS 0 10-07 SE REALIZA VALIDACION CON EL CLIENTE EL CUAL PRESENTA NOVEDAD CON EL CIERRE GENERAL QUE LE SALE DE DIAS ANTERIORES, INDICA QUE LLAMA A LA LINEA Y LE REALIZAN BORRADO DE MEMORIA PERO A LOS DIAS VUELVE A PASAR, SE VALIDA COMO EL CLIENTE ESTA REALIZANDO LOS CIERRES, Y SE ENCIENTRA QUE NO ESTA REALIZANDO EL CIERRE GENERAL CORRECTAMENTE, SE LE EXPLICA QUE AL TERMINAR EL CIERRE GENERAL DEBE CONFIRMAR CON LA TECLA VERDE PARA QUE EN LA PANTALLA DEL DATAOFNO LE SALGA EL MENSAJE CIERRE EXITOSO Y CON ESTE PROCESO YA EL DATAFOONO ELIMINA LAS TRANSACCIONES AUTOMATICAMENTE. | W65: SOPORTE_TELEFÓNICO | X65: 0 | Y65: TIPO III | Z65: TERRESTRE | AA65: HENAO CARDONA DIEGO FERNANDO | AB65: 0 | AC65: 0 | AD65: 0 | AE65: 0 | AF65: =IF(W65="SOPORTE_TELEFÓNICO",'BASE LIQUIDACION'!$B$10,IF(Y65="TIPO I",'BASE LIQUIDACION'!$C$3,IF(Y65="TIPO II",'BASE LIQUIDACION'!$C$4,IF(Y65="TIPO III",'BASE LIQUIDACION'!$C$5,'BASE LIQUIDACION'!$C$7)))) -> 37904.654 | AG65: =IF(W65="SOPORTE_TELEFÓNICO",'BASE LIQUIDACION'!$B$10,(AB65*AF65+AC65*'BASE LIQUIDACION'!$B$12+AD65*'BASE LIQUIDACION'!$B$11+INCIDENTES!AE65*'BASE LIQUIDACION'!$B$13)) -> 37904.654
A66: PEREIRA | B66: =VLOOKUP(A66,'CENTRO DE COSTOS'!A:D,4,FALSE) -> DIEGO FERNANDO HENAO CARDONA | C66: =VLOOKUP(A66,'CENTRO DE COSTOS'!A:D,2,FALSE) -> 0004-0002 | D66: 66001 | E66: 2423263 | F66: 70026 | G66: INCIDENTE | H66: RISARALDA | I66: PEREIRA | J66: REDY PEREIRA | K66: REDEBAN | L66: FO-25-1208547 | M66: 45847.702 | N66: 45848.506 | O66: NO | P66: USUARIO | Q66: NO ENCIENDE | R66: CONEXIONES DE COMERCIO | S66: ROBUSTO | U66: CERRADO | V66: 09-07 SE ESCALA PARA VISITA. LLAMAR ANTES DE VISITAR, CONFIRMAR FALLA Y DATOS 0 10-07 VISITAMOS COMERCIO EL DATÁFONO YA NO PRESENTA LA FALLA EL DÍA ANTERIOR NO PRENDIA PERO LO DEJARON DESCONECTADO POR UN RATO LUEGO LO CONECTARON NUEVAMENTE Y EL DATÁFONO PREDIO NORMAL Y DESDE ENTONCES ESTA FUNCIONANDO SIN NOVEDAD SE REALIZARON PRUEBAS OK. | W66: VISITA_TÉCNICA | X66: UV002107 | Y66: TIPO I | Z66: TERRESTRE | AA66: ARROYAVE CANO MANUEL GUILLERMO | AB66: 1 | AC66: 0 | AD66: 0 | AE66: 0 | AF66: =IF(W66="SOPORTE_TELEFÓNICO",'BASE LIQUIDACION'!$B$10,IF(Y66="TIPO I",'BASE LIQUIDACION'!$C$3,IF(Y66="TIPO II",'BASE LIQUIDACION'!$C$4,IF(Y66="TIPO III",'BASE LIQUIDACION'!$C$5,'BASE LIQUIDACION'!$C$7)))) -> 65960.474 | AG66: =IF(W66="SOPORTE_TELEFÓNICO",'BASE LIQUIDACION'!$B$10,(AB66*AF66+AC66*'BASE LIQUIDACION'!$B$12+AD66*'BASE LIQUIDACION'!$B$11+INCIDENTES!AE66*'BASE LIQUIDACION'!$B$13)) -> 65960.474
A67: VALLEDUPAR | B67: =VLOOKUP(A67,'CENTRO DE COSTOS'!A:D,4,FALSE) -> JOSE MAURICIO HERNANDEZ ROJAS | C67: =VLOOKUP(A67,'CENTRO DE COSTOS'!A:D,2,FALSE) -> 0004-0001 | D67: 13473 | E67: 2387153 | F67: 36229 | G67: INCIDENTE | H67: BOLIVAR | I67: MORALES | J67: BARRIO CENTRO MORALES | K67: REDEBAN | L67: FO-25-1175681 | M67: 45840.742 | N67: 45848.51 | O67: NO | P67: USUARIO | Q67: LECTOR DE BARRAS | R67: ERROR PAGOS PARCIALES DE FACTURAS | S67: CB UNO A UNO | U67: CERRADO | V67: 02-07 SE ESCALA PARA VISITA. LLAMAR ANTES DE VISITAR, CONFIRMAR FALLA Y DATOS .. SE VALIDA CON EL COORDINADOR UNA POSIBLE FECHA DE ATENCION ..10-07 POSIBLE FECHA DE ATENCION EL DIA 11-07 0 10-07 EN COMUNICACIÓN CON LA SEÑORA EIMY AL. MÓVIL 3004423348, INDICA QUE ESTABA PRESENTANDO FALLAS PARA REALZAR LOS. PAGOS DE LOS "CÓDIGOS DE BARRAS DE LA EMPRESA CENTRALES, PERO INFORMA QUE YA SE RESTABLECIÓ EL SERVICIO DESDE EL DÍA DE AYER Y A PODIDO PAGAR ESTOS RECIBOS, INDICA QUE LA FALLA ERA DE LA EMPRESA CENTRALES, INDICA QUE YA REQUIERE DE LA VISITA TÉCNICA, SE LE INFORMA QUE SI LLEGA A PRESENTAR UNA NUEVA NOVEDAD DEBERÁ SOLICITAR LA VISITA, CLIENTE ACEPTA. | W67: SOPORTE_TELEFÓNICO | X67: 0 | Y67: TIPO IV | Z67: TERRESTRE | AA67: SANTOS GONZALEZ JOHAN FABIAN | AB67: 0 | AC67: 0 | AD67: 0 | AE67: 0 | AF67: =IF(W67="SOPORTE_TELEFÓNICO",'BASE LIQUIDACION'!$B$10,IF(Y67="TIPO I",'BASE LIQUIDACION'!$C$3,IF(Y67="TIPO II",'BASE LIQUIDACION'!$C$4,IF(Y67="TIPO III",'BASE LIQUIDACION'!$C$5,'BASE LIQUIDACION'!$C$7)))) -> 37904.654 | AG67: =IF(W67="SOPORTE_TELEFÓNICO",'BASE LIQUIDACION'!$B$10,(AB67*AF67+AC67*'BASE LIQUIDACION'!$B$12+AD67*'BASE LIQUIDACION'!$B$11+INCIDENTES!AE67*'BASE LIQUIDACION'!$B$13)) -> 37904.654
A68: MEDELLIN | B68: =VLOOKUP(A68,'CENTRO DE COSTOS'!A:D,4,FALSE) -> JUAN SEBASTIÁN RÍOS CASTRILLÓN | C68: =VLOOKUP(A68,'CENTRO DE COSTOS'!A:D,2,FALSE) -> 0004-0005 | D68: 5001 | E68: 2425156 | F68: 41259 | G68: INCIDENTE | H68: ANTIOQUIA | I68: MEDELLIN | J68: PTM MEDELLIN MONTESSORI | K68: REDEBAN | L68: FO-25-1210052 | M68: 45848.375 | N68: 45848.534 | O68: NO | P68: USUARIO | Q68: COMUNICACION | R68: CONEXIONES DE COMERCIO | S68: AGREGADOR | U68: CERRADO | V68: 10-07 SE ESCALA PARA VISITA. LLAMAR ANTES DE VISITAR, CONFIRMAR FALLA Y DATOS 0 10-07 CONEXIONES DE COMERCIO FALLANDO | W68: VISITA_TÉCNICA | X68: 11HZZ255 - AA0QZ372 | Y68: TIPO I | Z68: TERRESTRE | AA68: MORENO MEDINA JUAN PABLO | AB68: 1 | AC68: 0 | AD68: 0 | AE68: 0 | AF68: =IF(W68="SOPORTE_TELEFÓNICO",'BASE LIQUIDACION'!$B$10,IF(Y68="TIPO I",'BASE LIQUIDACION'!$C$3,IF(Y68="TIPO II",'BASE LIQUIDACION'!$C$4,IF(Y68="TIPO III",'BASE LIQUIDACION'!$C$5,'BASE LIQUIDACION'!$C$7)))) -> 65960.474 | AG68: =IF(W68="SOPORTE_TELEFÓNICO",'BASE LIQUIDACION'!$B$10,(AB68*AF68+AC68*'BASE LIQUIDACION'!$B$12+AD68*'BASE LIQUIDACION'!$B$11+INCIDENTES!AE68*'BASE LIQUIDACION'!$B$13)) -> 65960.474
A69: MEDELLIN | B69: =VLOOKUP(A69,'CENTRO DE COSTOS'!A:D,4,FALSE) -> JUAN SEBASTIÁN RÍOS CASTRILLÓN | C69: =VLOOKUP(A69,'CENTRO DE COSTOS'!A:D,2,FALSE) -> 0004-0005 | D69: 5001 | E69: 2425924 | F69: 16829 | G69: INCIDENTE | H69: ANTIOQUIA | I69: MEDELLIN | J69: PAGAFACIL BARRIO TRISTE | K69: REDEBAN | L69: FO-25-1210424 | M69: 45848.41 | N69: 45848.66 | O69: NO | P69: USUARIO | Q69: COMUNICACION | R69: CONEXIONES DE COMERCIO | S69: ROBUSTO | U69: CERRADO | V69: 10-07 SE ESCALA PARA VISITA. LLAMAR ANTES DE VISITAR, CONFIRMAR FALLA Y DATOS 0 10-07 SE REALIZA REVISIÓN DE CONEXIONES, EQUIPO OK, INTERMITENCIAS DE PARTE DE CONEXIONES DE COMERCIO | W69: VISITA_TÉCNICA | X69: JFZZZ772 | Y69: TIPO I | Z69: TERRESTRE | AA69: QUINTERO SANCHEZ JUAN SEBASTIAN | AB69: 1 | AC69: 0 | AD69: 0 | AE69: 0 | AF69: =IF(W69="SOPORTE_TELEFÓNICO",'BASE LIQUIDACION'!$B$10,IF(Y69="TIPO I",'BASE LIQUIDACION'!$C$3,IF(Y69="TIPO II",'BASE LIQUIDACION'!$C$4,IF(Y69="TIPO III",'BASE LIQUIDACION'!$C$5,'BASE LIQUIDACION'!$C$7)))) -> 65960.474 | AG69: =IF(W69="SOPORTE_TELEFÓNICO",'BASE LIQUIDACION'!$B$10,(AB69*AF69+AC69*'BASE LIQUIDACION'!$B$12+AD69*'BASE LIQUIDACION'!$B$11+INCIDENTES!AE69*'BASE LIQUIDACION'!$B$13)) -> 65960.474
A70: NEIVA | B70: =VLOOKUP(A70,'CENTRO DE COSTOS'!A:D,4,FALSE) -> KEVIN ALEXIS CORZO BUSTOS | C70: =VLOOKUP(A70,'CENTRO DE COSTOS'!A:D,2,FALSE) -> 0004-0007 | D70: 41001 | E70: 2427258 | F70: 36089 | G70: INCIDENTE | H70: HUILA | I70: NEIVA | J70: BARRIO CENTRO NEIVA 9 | K70: REDEBAN | L70: FO-25-1211590 | M70: 45848.48 | N70: 45848.662 | O70: NO | P70: USUARIO | Q70: COMUNICACION | R70: CONEXIONES DE COMERCIO | S70: CB UNO A UNO | U70: CERRADO | V70: 10-07 SE ESCALA PARA VISITA. LLAMAR ANTES DE VISITAR, CONFIRMAR FALLA Y DATOS 0 10-07 SE REALIZA CAMBIO CABLE UTP, SE CALIDAD FUNCIONAMIENTO OK | W70: VISITA_TÉCNICA | X70: AB008650 | Y70: TIPO I | Z70: TERRESTRE | AA70: ANDRADE HERNANDEZ JUAN CARLOS | AB70: 1 | AC70: 0 | AD70: 0 | AE70: 0 | AF70: =IF(W70="SOPORTE_TELEFÓNICO",'BASE LIQUIDACION'!$B$10,IF(Y70="TIPO I",'BASE LIQUIDACION'!$C$3,IF(Y70="TIPO II",'BASE LIQUIDACION'!$C$4,IF(Y70="TIPO III",'BASE LIQUIDACION'!$C$5,'BASE LIQUIDACION'!$C$7)))) -> 65960.474 | AG70: =IF(W70="SOPORTE_TELEFÓNICO",'BASE LIQUIDACION'!$B$10,(AB70*AF70+AC70*'BASE LIQUIDACION'!$B$12+AD70*'BASE LIQUIDACION'!$B$11+INCIDENTES!AE70*'BASE LIQUIDACION'!$B$13)) -> 65960.474
A71: MEDELLIN | B71: =VLOOKUP(A71,'CENTRO DE COSTOS'!A:D,4,FALSE) -> JUAN SEBASTIÁN RÍOS CASTRILLÓN | C71: =VLOOKUP(A71,'CENTRO DE COSTOS'!A:D,2,FALSE) -> 0004-0005 | D71: 5380 | E71: 2424517 | F71: 24599 | G71: INCIDENTE | H71: ANTIOQUIA | I71: LA ESTRELLA | J71: REDY LA ESTRELLA | K71: REDEBAN | L71: FO-25-1209335 | M71: 45848.333 | N71: 45848.697 | O71: NO | P71: USUARIO | Q71: COMUNICACION | R71: CONEXIONES DE COMERCIO | S71: ROBUSTO | U71: CERRADO | V71: 10-07 SE ESCALA PARA VISITA. LLAMAR ANTES DE VISITAR, CONFIRMAR FALLA Y DATOS 0 10-07 SE HACE MANTENIMIENTO DE EQUIPO Y CABLEADO | W71: VISITA_TÉCNICA | X71: ABCOZ295 | Y71: TIPO I | Z71: TERRESTRE | AA71: MORENO MEDINA JUAN PABLO | AB71: 1 | AC71: 0 | AD71: 0 | AE71: 0 | AF71: =IF(W71="SOPORTE_TELEFÓNICO",'BASE LIQUIDACION'!$B$10,IF(Y71="TIPO I",'BASE LIQUIDACION'!$C$3,IF(Y71="TIPO II",'BASE LIQUIDACION'!$C$4,IF(Y71="TIPO III",'BASE LIQUIDACION'!$C$5,'BASE LIQUIDACION'!$C$7)))) -> 65960.474 | AG71: =IF(W71="SOPORTE_TELEFÓNICO",'BASE LIQUIDACION'!$B$10,(AB71*AF71+AC71*'BASE LIQUIDACION'!$B$12+AD71*'BASE LIQUIDACION'!$B$11+INCIDENTES!AE71*'BASE LIQUIDACION'!$B$13)) -> 65960.474
A72: MEDELLIN | B72: =VLOOKUP(A72,'CENTRO DE COSTOS'!A:D,4,FALSE) -> JUAN SEBASTIÁN RÍOS CASTRILLÓN | C72: =VLOOKUP(A72,'CENTRO DE COSTOS'!A:D,2,FALSE) -> 0004-0005 | D72: 5088 | E72: 2426718 | F72: 38647 | G72: INCIDENTE | H72: ANTIOQUIA | I72: BELLO | J72: BARRIO GIRASOLES BELLO | K72: REDEBAN | L72: FO-25-1211595 | M72: 45848.451 | N72: 45849.401 | O72: NO | P72: USUARIO | Q72: LECTOR DE TARJETAS | R72: OBSTRUCCION DEL LECTOR | S72: CB UNO A UNO | U72: CERRADO | V72: 10-07 SE ESCALA PARA VISITA. LLAMAR ANTES DE VISITAR, CONFIRMAR FALLA Y DATOS 0 11-07 SE REALIZA MANTENIMIENTO GENERAL | W72: VISITA_TÉCNICA | X72: GZ00Z193 | Y72: TIPO I | Z72: TERRESTRE | AA72: HERNANDEZ CHAVARRIA JUAN CAMILO | AB72: 1 | AC72: 0 | AD72: 0 | AE72: 0 | AF72: =IF(W72="SOPORTE_TELEFÓNICO",'BASE LIQUIDACION'!$B$10,IF(Y72="TIPO I",'BASE LIQUIDACION'!$C$3,IF(Y72="TIPO II",'BASE LIQUIDACION'!$C$4,IF(Y72="TIPO III",'BASE LIQUIDACION'!$C$5,'BASE LIQUIDACION'!$C$7)))) -> 65960.474 | AG72: =IF(W72="SOPORTE_TELEFÓNICO",'BASE LIQUIDACION'!$B$10,(AB72*AF72+AC72*'BASE LIQUIDACION'!$B$12+AD72*'BASE LIQUIDACION'!$B$11+INCIDENTES!AE72*'BASE LIQUIDACION'!$B$13)) -> 65960.474
A73: MEDELLIN | B73: =VLOOKUP(A73,'CENTRO DE COSTOS'!A:D,4,FALSE) -> JUAN SEBASTIÁN RÍOS CASTRILLÓN | C73: =VLOOKUP(A73,'CENTRO DE COSTOS'!A:D,2,FALSE) -> 0004-0005 | D73: 5001 | E73: 2428955 | F73: 68694 | G73: INCIDENTE | H73: ANTIOQUIA | I73: MEDELLIN | J73: PTM MEDELLIN MERCADOS BIBI | K73: REDEBAN | L73: FO-25-1213968 | M73: 45848.624 | N73: 45849.443 | O73: NO | P73: USUARIO | Q73: MANTENIMIENTO | R73: MANTENIMIENTO GENERAL | S73: AGREGADOR | U73: CERRADO | V73: 10-07 SE ESCALA PARA VISITA. LLAMAR ANTES DE VISITAR, CONFIRMAR FALLA Y DATOS 0 11-07 SE REALIZA MANTENIMIENTO AL EQUIPO Y SE VERIFICA CONEXIÓN Y SE CAMBIA CABLE ENTORCHADO TODO OK | W73: VISITA_TÉCNICA | X73: 9L0UZ948-9L0VZ097 | Y73: TIPO I | Z73: TERRESTRE | AA73: CERPA SUAREZ DUVAN CAMILO | AB73: 1 | AC73: 0 | AD73: 0 | AE73: 0 | AF73: =IF(W73="SOPORTE_TELEFÓNICO",'BASE LIQUIDACION'!$B$10,IF(Y73="TIPO I",'BASE LIQUIDACION'!$C$3,IF(Y73="TIPO II",'BASE LIQUIDACION'!$C$4,IF(Y73="TIPO III",'BASE LIQUIDACION'!$C$5,'BASE LIQUIDACION'!$C$7)))) -> 65960.474 | AG73: =IF(W73="SOPORTE_TELEFÓNICO",'BASE LIQUIDACION'!$B$10,(AB73*AF73+AC73*'BASE LIQUIDACION'!$B$12+AD73*'BASE LIQUIDACION'!$B$11+INCIDENTES!AE73*'BASE LIQUIDACION'!$B$13)) -> 65960.474
A74: MEDELLIN | B74: =VLOOKUP(A74,'CENTRO DE COSTOS'!A:D,4,FALSE) -> JUAN SEBASTIÁN RÍOS CASTRILLÓN | C74: =VLOOKUP(A74,'CENTRO DE COSTOS'!A:D,2,FALSE) -> 0004-0005 | D74: 5001 | E74: 2427593 | F74: 30042 | G74: INCIDENTE | H74: ANTIOQUIA | I74: MEDELLIN | J74: COMCARD MED RED ASUMOTOS | K74: REDEBAN | L74: FO-25-1212780 | M74: 45848.506 | N74: 45849.449 | O74: NO | P74: USUARIO | Q74: MANTENIMIENTO | R74: MANTENIMIENTO GENERAL | S74: AGREGADOR | U74: CERRADO | V74: 10-07 SE ESCALA PARA VISITA. LLAMAR ANTES DE VISITAR, CONFIRMAR FALLA Y DATOS 0 11-07 SE REALIZA VERIFICACIÓN DE IMPRESION CON PRUEBAS TODO OK | W74: VISITA_TÉCNICA | X74: BBQZZ204 | Y74: TIPO I | Z74: TERRESTRE | AA74: HERNANDEZ CHAVARRIA JUAN CAMILO | AB74: 1 | AC74: 0 | AD74: 0 | AE74: 0 | AF74: =IF(W74="SOPORTE_TELEFÓNICO",'BASE LIQUIDACION'!$B$10,IF(Y74="TIPO I",'BASE LIQUIDACION'!$C$3,IF(Y74="TIPO II",'BASE LIQUIDACION'!$C$4,IF(Y74="TIPO III",'BASE LIQUIDACION'!$C$5,'BASE LIQUIDACION'!$C$7)))) -> 65960.474 | AG74: =IF(W74="SOPORTE_TELEFÓNICO",'BASE LIQUIDACION'!$B$10,(AB74*AF74+AC74*'BASE LIQUIDACION'!$B$12+AD74*'BASE LIQUIDACION'!$B$11+INCIDENTES!AE74*'BASE LIQUIDACION'!$B$13)) -> 65960.474
A75: TUNJA | B75: =VLOOKUP(A75,'CENTRO DE COSTOS'!A:D,4,FALSE) -> MIGUEL JULIÁN HERNÁNDEZ GUARÍN | C75: =VLOOKUP(A75,'CENTRO DE COSTOS'!A:D,2,FALSE) -> 0004-0008 | D75: 15632 | E75: 2427750 | F75: 68265 | G75: INCIDENTE | H75: BOYACA | I75: SABOYA | J75: CENTRO SABOYA BOYACA | K75: REDEBAN | L75: FO-25-1212767 | M75: 45848.526 | N75: 45849.496 | O75: NO | P75: USUARIO | Q75: COMUNICACION | R75: CANAL DEL COMERCIO | S75: CB UNO A UNO | U75: CERRADO | V75: 10-07 SE ESCALA PARA VISITA. LLAMAR ANTES DE VISITAR, CONFIRMAR FALLA Y DATOS 0 11-07 EN COMUNICACIÓN CON LA LÍNEA LA SEÑORA YANETH RDORIGUEZ INDICA QUE EL SERVICIO ESTÁ FUNCIONANDO PERFECTAMENTE Y QUE NO REQUIERE VISITA, INFORMA QUE TUBO UNA FALLA DE COMUNICACIÓN PERO QUE YA ESTÁ RESUELTA. SOPORTE TELEFONICO | W75: SOPORTE_TELEFÓNICO | X75: 0 | Y75: TIPO II | Z75: TERRESTRE | AA75: HERRERA GARZON JEYSON STEVENT | AB75: 0 | AC75: 0 | AD75: 0 | AE75: 0 | AF75: =IF(W75="SOPORTE_TELEFÓNICO",'BASE LIQUIDACION'!$B$10,IF(Y75="TIPO I",'BASE LIQUIDACION'!$C$3,IF(Y75="TIPO II",'BASE LIQUIDACION'!$C$4,IF(Y75="TIPO III",'BASE LIQUIDACION'!$C$5,'BASE LIQUIDACION'!$C$7)))) -> 37904.654 | AG75: =IF(W75="SOPORTE_TELEFÓNICO",'BASE LIQUIDACION'!$B$10,(AB75*AF75+AC75*'BASE LIQUIDACION'!$B$12+AD75*'BASE LIQUIDACION'!$B$11+INCIDENTES!AE75*'BASE LIQUIDACION'!$B$13)) -> 37904.654
A76: MEDELLIN | B76: =VLOOKUP(A76,'CENTRO DE COSTOS'!A:D,4,FALSE) -> JUAN SEBASTIÁN RÍOS CASTRILLÓN | C76: =VLOOKUP(A76,'CENTRO DE COSTOS'!A:D,2,FALSE) -> 0004-0005 | D76: 5360 | E76: 2427961 | F76: 47476 | G76: INCIDENTE | H76: ANTIOQUIA | I76: ITAGUI | J76: DISTRICOL RINCON DEL PELUQUERO | K76: REDEBAN | L76: FO-25-1213087 | M76: 45848.549 | N76: 45849.505 | O76: NO | P76: USUARIO | Q76: COMUNICACION | R76: CONEXIONES DE COMERCIO | S76: AGREGADOR | U76: CERRADO | V76: 10-07 SE ESCALA PARA VISITA. LLAMAR ANTES DE VISITAR, CONFIRMAR FALLA Y DATOS 0 11-07 SE HACE MANTENIMIENTO DE EQUIPO Y CABLEADO | W76: VISITA_TÉCNICA | X76: GB00H005 | Y76: TIPO I | Z76: TERRESTRE | AA76: MORENO MEDINA JUAN PABLO | AB76: 1 | AC76: 0 | AD76: 0 | AE76: 0 | AF76: =IF(W76="SOPORTE_TELEFÓNICO",'BASE LIQUIDACION'!$B$10,IF(Y76="TIPO I",'BASE LIQUIDACION'!$C$3,IF(Y76="TIPO II",'BASE LIQUIDACION'!$C$4,IF(Y76="TIPO III",'BASE LIQUIDACION'!$C$5,'BASE LIQUIDACION'!$C$7)))) -> 65960.474 | AG76: =IF(W76="SOPORTE_TELEFÓNICO",'BASE LIQUIDACION'!$B$10,(AB76*AF76+AC76*'BASE LIQUIDACION'!$B$12+AD76*'BASE LIQUIDACION'!$B$11+INCIDENTES!AE76*'BASE LIQUIDACION'!$B$13)) -> 65960.474
A77: NEIVA | B77: =VLOOKUP(A77,'CENTRO DE COSTOS'!A:D,4,FALSE) -> KEVIN ALEXIS CORZO BUSTOS | C77: =VLOOKUP(A77,'CENTRO DE COSTOS'!A:D,2,FALSE) -> 0004-0007 | D77: 41001 | E77: 2428291 | F77: 80170 | G77: INCIDENTE | H77: HUILA | I77: NEIVA | J77: BARRIO LAS MARGARITAS NEIVA 1 | K77: REDEBAN | L77: FO-25-1213964 | M77: 45848.594 | N77: 45849.546 | O77: NO | P77: USUARIO | Q77: LECTOR DE BARRAS | R77: ERROR PAGOS PARCIALES DE FACTURAS | S77: CB UNO A UNO | U77: CERRADO | V77: 10-07 SE ESCALA PARA VISITA. LLAMAR ANTES DE VISITAR, CONFIRMAR FALLA Y DATOS 0 11-07 EN LLAMADA CON CLIENTE JUAN DAVID ALVAREZ AL NÚMERO 3112908304, SE LE INFORMA QUE EL RECIBO DEL GAS EN EL MOMENTO NO HAY CONVENIO PARA PODER REALIZAR LOS PAGOS, EL CUAL ERA EL QUE ESTABA INTENTANDO PAGAR. | W77: SOPORTE_TELEFÓNICO | X77: 0 | Y77: TIPO I | Z77: TERRESTRE | AA77: DIAZ VARGAS JONATHAN MIGUEL | AB77: 0 | AC77: 0 | AD77: 0 | AE77: 0 | AF77: =IF(W77="SOPORTE_TELEFÓNICO",'BASE LIQUIDACION'!$B$10,IF(Y77="TIPO I",'BASE LIQUIDACION'!$C$3,IF(Y77="TIPO II",'BASE LIQUIDACION'!$C$4,IF(Y77="TIPO III",'BASE LIQUIDACION'!$C$5,'BASE LIQUIDACION'!$C$7)))) -> 37904.654 | AG77: =IF(W77="SOPORTE_TELEFÓNICO",'BASE LIQUIDACION'!$B$10,(AB77*AF77+AC77*'BASE LIQUIDACION'!$B$12+AD77*'BASE LIQUIDACION'!$B$11+INCIDENTES!AE77*'BASE LIQUIDACION'!$B$13)) -> 37904.654
A78: MEDELLIN | B78: =VLOOKUP(A78,'CENTRO DE COSTOS'!A:D,4,FALSE) -> JUAN SEBASTIÁN RÍOS CASTRILLÓN | C78: =VLOOKUP(A78,'CENTRO DE COSTOS'!A:D,2,FALSE) -> 0004-0005 | D78: 5001 | E78: 2432997 | F78: 24793 | G78: INCIDENTE | H78: ANTIOQUIA | I78: MEDELLIN | J78: COMCARD MEDELLIN VARIEDADES | K78: REDEBAN | L78: FO-25-1216905 | M78: 45849.433 | N78: 45849.569 | O78: NO | P78: USUARIO | Q78: MANTENIMIENTO | R78: MANTENIMIENTO GENERAL | S78: AGREGADOR | U78: CERRADO | V78: 11-07 SE ESCALA PARA VISITA. LLAMAR ANTES DE VISITAR, CONFIRMAR FALLA Y DATOS 0 11-07 SE REALIZA MANTENIMIENTO Y SE CAMBIA RODILLO POR QUÉ NO IMPRIMIA BIEN | W78: VISITA_TÉCNICA | X78: ABGZZ592-II00T036 | Y78: TIPO I | Z78: TERRESTRE | AA78: CERPA SUAREZ DUVAN CAMILO | AB78: 1 | AC78: 0 | AD78: 0 | AE78: 0 | AF78: =IF(W78="SOPORTE_TELEFÓNICO",'BASE LIQUIDACION'!$B$10,IF(Y78="TIPO I",'BASE LIQUIDACION'!$C$3,IF(Y78="TIPO II",'BASE LIQUIDACION'!$C$4,IF(Y78="TIPO III",'BASE LIQUIDACION'!$C$5,'BASE LIQUIDACION'!$C$7)))) -> 65960.474 | AG78: =IF(W78="SOPORTE_TELEFÓNICO",'BASE LIQUIDACION'!$B$10,(AB78*AF78+AC78*'BASE LIQUIDACION'!$B$12+AD78*'BASE LIQUIDACION'!$B$11+INCIDENTES!AE78*'BASE LIQUIDACION'!$B$13)) -> 65960.474
A79: MEDELLIN | B79: =VLOOKUP(A79,'CENTRO DE COSTOS'!A:D,4,FALSE) -> JUAN SEBASTIÁN RÍOS CASTRILLÓN | C79: =VLOOKUP(A79,'CENTRO DE COSTOS'!A:D,2,FALSE) -> 0004-0005 | D79: 5088 | E79: 2432233 | F79: 75938 | G79: INCIDENTE | H79: ANTIOQUIA | I79: BELLO | J79: BARRIO LA GABRIELA BELLO 5 | K79: REDEBAN | L79: FO-25-1216264 | M79: 45849.38 | N79: 45849.64 | O79: NO | P79: USUARIO | Q79: CIERRE | R79: COMERCIO NO REALIZA CIERRE | S79: CB UNO A UNO | U79: CERRADO | V79: 11-07 SE ESCALA PARA VISITA. LLAMAR ANTES DE VISITAR, CONFIRMAR FALLA Y DATOS 0 11-07 SE REVISA EQUIPOS EL CLIENTE INDICA EQUIPO LENTO SE REALIZA CIERRE Y NO SE REALIZABA CIERRE DESDE EL 7 DE JULIO SE REALIZA EL CIERRE SE REALIZAN PRUEBAS EXITOSAS SERVICIO OPERATIVO SE LE EXPLICA AL CLIENTE COMO REALIZA EL CIERRE DIARIO | W79: VISITA_TÉCNICA | X79: FA09Z467 | Y79: TIPO I | Z79: TERRESTRE | AA79: ZAPATA LOPEZ EDWARD ASDRUBAL | AB79: 1 | AC79: 0 | AD79: 0 | AE79: 0 | AF79: =IF(W79="SOPORTE_TELEFÓNICO",'BASE LIQUIDACION'!$B$10,IF(Y79="TIPO I",'BASE LIQUIDACION'!$C$3,IF(Y79="TIPO II",'BASE LIQUIDACION'!$C$4,IF(Y79="TIPO III",'BASE LIQUIDACION'!$C$5,'BASE LIQUIDACION'!$C$7)))) -> 65960.474 | AG79: =IF(W79="SOPORTE_TELEFÓNICO",'BASE LIQUIDACION'!$B$10,(AB79*AF79+AC79*'BASE LIQUIDACION'!$B$12+AD79*'BASE LIQUIDACION'!$B$11+INCIDENTES!AE79*'BASE LIQUIDACION'!$B$13)) -> 65960.474
A80: TUNJA | B80: =VLOOKUP(A80,'CENTRO DE COSTOS'!A:D,4,FALSE) -> MIGUEL JULIÁN HERNÁNDEZ GUARÍN | C80: =VLOOKUP(A80,'CENTRO DE COSTOS'!A:D,2,FALSE) -> 0004-0008 | D80: 15001 | E80: 2432638 | F80: 79424 | G80: INCIDENTE | H80: BOYACA | I80: TUNJA | J80: BARRIO CENTRO TUNJA 31 | K80: REDEBAN | L80: FO-25-1216734 | M80: 45849.408 | N80: 45849.648 | O80: NO | P80: USUARIO | Q80: MANTENIMIENTO | R80: MANTENIMIENTO GENERAL | S80: CB UNO A UNO | U80: CERRADO | V80: 11-07 SE ESCALA PARA VISITA. LLAMAR ANTES DE VISITAR, CONFIRMAR FALLA Y DATOS 0 11-07 SE VISITA COMERCIO , EQUIPO IMPRIMIENDO CORRECTAMENTE , SE REALIZA BORRADO DE EQUIPO CARGANDO S.O Y VERSIÓN 10.3 N POR MANTENIMIENTO GENERAL Y PREVENTIVO , DEJANDO PRUEBAS DE IMPRESIÓN CORRECTAMENTE , | W80: VISITA_TÉCNICA | X80: 10XZZ962 | Y80: TIPO I | Z80: TERRESTRE | AA80: ALVARADO MORENO CRISTHIAN | AB80: 1 | AC80: 0 | AD80: 0 | AE80: 0 | AF80: =IF(W80="SOPORTE_TELEFÓNICO",'BASE LIQUIDACION'!$B$10,IF(Y80="TIPO I",'BASE LIQUIDACION'!$C$3,IF(Y80="TIPO II",'BASE LIQUIDACION'!$C$4,IF(Y80="TIPO III",'BASE LIQUIDACION'!$C$5,'BASE LIQUIDACION'!$C$7)))) -> 65960.474 | AG80: =IF(W80="SOPORTE_TELEFÓNICO",'BASE LIQUIDACION'!$B$10,(AB80*AF80+AC80*'BASE LIQUIDACION'!$B$12+AD80*'BASE LIQUIDACION'!$B$11+INCIDENTES!AE80*'BASE LIQUIDACION'!$B$13)) -> 65960.474
A81: MEDELLIN | B81: =VLOOKUP(A81,'CENTRO DE COSTOS'!A:D,4,FALSE) -> JUAN SEBASTIÁN RÍOS CASTRILLÓN | C81: =VLOOKUP(A81,'CENTRO DE COSTOS'!A:D,2,FALSE) -> 0004-0005 | D81: 5266 | E81: 2433727 | F81: 59486 | G81: INCIDENTE | H81: ANTIOQUIA | I81: ENVIGADO | J81: BARRIO EL SALADO ENVIGADO 1 | K81: REDEBAN | L81: FO-25-1217418 | M81: 45849.47 | N81: 45849.653 | O81: NO | P81: USUARIO | Q81: COMUNICACION | R81: CONEXIONES DE COMERCIO | S81: CB UNO A UNO | U81: CERRADO | V81: 11-07 SE ESCALA PARA VISITA. LLAMAR ANTES DE VISITAR, CONFIRMAR FALLA Y DATOS 0 11-07 SE HACE MANTENIMIENTO DE EQUIPO Y CABLEADO | W81: VISITA_TÉCNICA | X81: JA007412 | Y81: TIPO I | Z81: TERRESTRE | AA81: MORENO MEDINA JUAN PABLO | AB81: 1 | AC81: 0 | AD81: 0 | AE81: 0 | AF81: =IF(W81="SOPORTE_TELEFÓNICO",'BASE LIQUIDACION'!$B$10,IF(Y81="TIPO I",'BASE LIQUIDACION'!$C$3,IF(Y81="TIPO II",'BASE LIQUIDACION'!$C$4,IF(Y81="TIPO III",'BASE LIQUIDACION'!$C$5,'BASE LIQUIDACION'!$C$7)))) -> 65960.474 | AG81: =IF(W81="SOPORTE_TELEFÓNICO",'BASE LIQUIDACION'!$B$10,(AB81*AF81+AC81*'BASE LIQUIDACION'!$B$12+AD81*'BASE LIQUIDACION'!$B$11+INCIDENTES!AE81*'BASE LIQUIDACION'!$B$13)) -> 65960.474
A82: MEDELLIN | B82: =VLOOKUP(A82,'CENTRO DE COSTOS'!A:D,4,FALSE) -> JUAN SEBASTIÁN RÍOS CASTRILLÓN | C82: =VLOOKUP(A82,'CENTRO DE COSTOS'!A:D,2,FALSE) -> 0004-0005 | D82: 5001 | E82: 2434552 | F82: 80337 | G82: INCIDENTE | H82: ANTIOQUIA | I82: MEDELLIN | J82: PTM MEDELLIN DROGUERÍA LA PLAN | K82: REDEBAN | L82: FO-25-1218438 | M82: 45849.551 | N82: 45849.654 | O82: NO | P82: USUARIO | Q82: MANTENIMIENTO | R82: MANTENIMIENTO GENERAL | S82: AGREGADOR | U82: CERRADO | V82: 11-07 SE ESCALA PARA VISITA. LLAMAR ANTES DE VISITAR, CONFIRMAR FALLA Y DATOS 0 11-07 SE REALIZA LLAMADA CON EL SEÑOR GUILLERMO EL CUAL INFORMA QUE EL EQUIPO ESTÁ FUNCIONANDO CORRECTAMENTE QUE YA NO REQUIRE VISITA | W82: SOPORTE_TELEFÓNICO | X82: 0 | Y82: TIPO I | Z82: TERRESTRE | AA82: CERPA SUAREZ DUVAN CAMILO | AB82: 0 | AC82: 0 | AD82: 0 | AE82: 0 | AF82: =IF(W82="SOPORTE_TELEFÓNICO",'BASE LIQUIDACION'!$B$10,IF(Y82="TIPO I",'BASE LIQUIDACION'!$C$3,IF(Y82="TIPO II",'BASE LIQUIDACION'!$C$4,IF(Y82="TIPO III",'BASE LIQUIDACION'!$C$5,'BASE LIQUIDACION'!$C$7)))) -> 37904.654 | AG82: =IF(W82="SOPORTE_TELEFÓNICO",'BASE LIQUIDACION'!$B$10,(AB82*AF82+AC82*'BASE LIQUIDACION'!$B$12+AD82*'BASE LIQUIDACION'!$B$11+INCIDENTES!AE82*'BASE LIQUIDACION'!$B$13)) -> 37904.654
A83: CUCUTA | B83: =VLOOKUP(A83,'CENTRO DE COSTOS'!A:D,4,FALSE) -> MIGUEL JULIÁN HERNÁNDEZ GUARÍN | C83: =VLOOKUP(A83,'CENTRO DE COSTOS'!A:D,2,FALSE) -> 0004-0008 | D83: 54405 | E83: 2432592 | F83: 30672 | G83: INCIDENTE | H83: NORTE DE SANTANDER | I83: LOS PATIOS | J83: BARRIO ONCE DE NOVIMEMBRE LOS | K83: REDEBAN | L83: FO-25-1216722 | M83: 45849.412 | N83: 45849.677 | O83: NO | P83: USUARIO | Q83: MANTENIMIENTO | R83: MANTENIMIENTO GENERAL | S83: CB UNO A UNO | U83: CERRADO | V83: 11-07 SE ESCALA PARA VISITA. LLAMAR ANTES DE VISITAR, CONFIRMAR FALLA Y DATOS 0 11-07 SE VISITA COMERCIO Y SE REALIZA MANTENIMIENTO AL DATAFONO, SE ORGANIZAN CABLEADOS, MAGICBOX, HUB SE FIJA A LA BASE CON AMARRES PLÁSTICOS, SE REALIZAN CIERRES Y PRUEBAS OK. | W83: VISITA_TÉCNICA | X83: BOZZZ337 | Y83: TIPO I | Z83: TERRESTRE | AA83: TORRES MANTILLA JOSE DANIEL | AB83: 1 | AC83: 0 | AD83: 0 | AE83: 0 | AF83: =IF(W83="SOPORTE_TELEFÓNICO",'BASE LIQUIDACION'!$B$10,IF(Y83="TIPO I",'BASE LIQUIDACION'!$C$3,IF(Y83="TIPO II",'BASE LIQUIDACION'!$C$4,IF(Y83="TIPO III",'BASE LIQUIDACION'!$C$5,'BASE LIQUIDACION'!$C$7)))) -> 65960.474 | AG83: =IF(W83="SOPORTE_TELEFÓNICO",'BASE LIQUIDACION'!$B$10,(AB83*AF83+AC83*'BASE LIQUIDACION'!$B$12+AD83*'BASE LIQUIDACION'!$B$11+INCIDENTES!AE83*'BASE LIQUIDACION'!$B$13)) -> 65960.474
A84: PEREIRA | B84: =VLOOKUP(A84,'CENTRO DE COSTOS'!A:D,4,FALSE) -> DIEGO FERNANDO HENAO CARDONA | C84: =VLOOKUP(A84,'CENTRO DE COSTOS'!A:D,2,FALSE) -> 0004-0002 | D84: 76736 | E84: 2432828 | F84: 13622 | G84: INCIDENTE | H84: VALLE DEL CAUCA | I84: SEVILLA | J84: MULTIPAGAS SEVILLA | K84: REDEBAN | L84: FO-25-1216747 | M84: 45849.418 | N84: 45849.7 | O84: NO | P84: USUARIO | Q84: COMUNICACION | R84: CONEXIONES DE COMERCIO | S84: ROBUSTO | U84: CERRADO | V84: 11-07 SE ESCALA PARA VISITA. LLAMAR ANTES DE VISITAR, CONFIRMAR FALLA Y DATOS 0 11-07 SE REALIZA VALIDACION CON EL CLIENTE, QUIEN MANIFIESTA QUE LOS DATAFONOS SE QUEDAN EN CONECTANDO Y NO FUNCIONAN, NOS MUESTRAN EL ICONO DE LA RED EN VERDE, SE LE SOLICITA REVISION LAS CONEXIONES DEL ESTABLECIMIENTO, SE LE PIDE REINICIAR LOS DISPOSITIVOS DE INTERNET, EL CLIENTE REALIZA REINICIO DE EQUIPOS, VALIDA CABLEADO Y REALIZA CAMBIO DE PUERTOS DE LOS DATAFONOS, EL DATAFONO ALUMBRA LA RED EN VERDE Y CONFIRMA OPERATIVIDAD DE LOS EQUIPOS. | W84: SOPORTE_TELEFÓNICO | X84: 0 | Y84: TIPO II | Z84: TERRESTRE | AA84: HENAO CARDONA DIEGO FERNANDO | AB84: 0 | AC84: 0 | AD84: 0 | AE84: 0 | AF84: =IF(W84="SOPORTE_TELEFÓNICO",'BASE LIQUIDACION'!$B$10,IF(Y84="TIPO I",'BASE LIQUIDACION'!$C$3,IF(Y84="TIPO II",'BASE LIQUIDACION'!$C$4,IF(Y84="TIPO III",'BASE LIQUIDACION'!$C$5,'BASE LIQUIDACION'!$C$7)))) -> 37904.654 | AG84: =IF(W84="SOPORTE_TELEFÓNICO",'BASE LIQUIDACION'!$B$10,(AB84*AF84+AC84*'BASE LIQUIDACION'!$B$12+AD84*'BASE LIQUIDACION'!$B$11+INCIDENTES!AE84*'BASE LIQUIDACION'!$B$13)) -> 37904.654
A85: BUCARAMANGA | B85: =VLOOKUP(A85,'CENTRO DE COSTOS'!A:D,4,FALSE) -> MIGUEL JULIÁN HERNÁNDEZ GUARÍN | C85: =VLOOKUP(A85,'CENTRO DE COSTOS'!A:D,2,FALSE) -> 0004-0008 | D85: 68001 | E85: 2433304 | F85: 64093 | G85: INCIDENTE | H85: SANTANDER | I85: BUCARAMANGA | J85: BARRIO KENNEDY BUCARAMANGA 1 | K85: REDEBAN | L85: FO-25-1217000 | M85: 45849.443 | N85: 45850.41 | O85: NO | P85: USUARIO | Q85: COMUNICACION | R85: CANAL DEL COMERCIO | S85: CB UNO A UNO | U85: CERRADO | V85: 11-07 SE ESCALA PARA VISITA. LLAMAR ANTES DE VISITAR, CONFIRMAR FALLA Y DATOS 0 12-07 SE LLAMA A LA SEÑORITA VIVIANA QUIEN NOS INFORMA QUE EL ERROR ERA DEL CANAL Y YA ESTÁ OPERANDO CORRECTAMENTE POR LO ANTERIOR CANCELA VISITA TÉCNICA | W85: SOPORTE_TELEFÓNICO | X85: 0 | Y85: TIPO I | Z85: TERRESTRE | AA85: PEÑA DIAZ IVAN YESID | AB85: 0 | AC85: 0 | AD85: 0 | AE85: 0 | AF85: =IF(W85="SOPORTE_TELEFÓNICO",'BASE LIQUIDACION'!$B$10,IF(Y85="TIPO I",'BASE LIQUIDACION'!$C$3,IF(Y85="TIPO II",'BASE LIQUIDACION'!$C$4,IF(Y85="TIPO III",'BASE LIQUIDACION'!$C$5,'BASE LIQUIDACION'!$C$7)))) -> 37904.654 | AG85: =IF(W85="SOPORTE_TELEFÓNICO",'BASE LIQUIDACION'!$B$10,(AB85*AF85+AC85*'BASE LIQUIDACION'!$B$12+AD85*'BASE LIQUIDACION'!$B$11+INCIDENTES!AE85*'BASE LIQUIDACION'!$B$13)) -> 37904.654
A86: MEDELLIN | B86: =VLOOKUP(A86,'CENTRO DE COSTOS'!A:D,4,FALSE) -> JUAN SEBASTIÁN RÍOS CASTRILLÓN | C86: =VLOOKUP(A86,'CENTRO DE COSTOS'!A:D,2,FALSE) -> 0004-0005 | D86: 5001 | E86: 2434811 | F86: 73717 | G86: INCIDENTE | H86: ANTIOQUIA | I86: MEDELLIN | J86: BARRIO ROBLEDO PAJARITO MEDELL | K86: REDEBAN | L86: FO-25-1219149 | M86: 45849.575 | N86: 45850.492 | O86: NO | P86: USUARIO | Q86: COMUNICACION | R86: CANAL DEL COMERCIO | S86: CB UNO A UNO | U86: CERRADO | V86: 11-07 SE ESCALA PARA VISITA. LLAMAR ANTES DE VISITAR, CONFIRMAR FALLA Y DATOS 0 12-07 SE HABLA CON EL SEÑOR VICTOR GRACIAS E INFORMA QUE ESTA OPERANDO SIN PROBLEMAS ERA EL CANAL DEL COMERCIO | W86: SOPORTE_TELEFÓNICO | X86: 0 | Y86: TIPO I | Z86: TERRESTRE | AA86: PAREJA ECHAVARRIA JHON DAVID | AB86: 0 | AC86: 0 | AD86: 0 | AE86: 0 | AF86: =IF(W86="SOPORTE_TELEFÓNICO",'BASE LIQUIDACION'!$B$10,IF(Y86="TIPO I",'BASE LIQUIDACION'!$C$3,IF(Y86="TIPO II",'BASE LIQUIDACION'!$C$4,IF(Y86="TIPO III",'BASE LIQUIDACION'!$C$5,'BASE LIQUIDACION'!$C$7)))) -> 37904.654 | AG86: =IF(W86="SOPORTE_TELEFÓNICO",'BASE LIQUIDACION'!$B$10,(AB86*AF86+AC86*'BASE LIQUIDACION'!$B$12+AD86*'BASE LIQUIDACION'!$B$11+INCIDENTES!AE86*'BASE LIQUIDACION'!$B$13)) -> 37904.654
A87: BUCARAMANGA | B87: =VLOOKUP(A87,'CENTRO DE COSTOS'!A:D,4,FALSE) -> MIGUEL JULIÁN HERNÁNDEZ GUARÍN | C87: =VLOOKUP(A87,'CENTRO DE COSTOS'!A:D,2,FALSE) -> 0004-0008 | D87: 68001 | E87: 2437371 | F87: 77300 | G87: INCIDENTE | H87: SANTANDER | I87: BUCARAMANGA | J87: BARRIO SOTOMAYOR BUCARAMANGA 5 | K87: REDEBAN | L87: FO-25-1221225 | M87: 45850.394 | N87: 45850.585 | O87: NO | P87: USUARIO | Q87: NO ENCIENDE | R87: CONEXIONES DE COMERCIO | S87: CB UNO A UNO | U87: CERRADO | V87: 12-07 SE ESCALA PARA VISITA. LLAMAR ANTES DE VISITAR, CONFIRMAR FALLA Y DATOS 0 12-07 CB CON PROBLEMAS DE DATÁFONO NO ENCIENDE, SE VALIDA CONEXIONES, FALLA DE TOMA CORRIENTE DE CLIENTE, EQUIPO CON VERSIÓN 10.3N,PRUEBAS OK. NO CIERRE POR FLUJO DE CLIENTE. | W87: VISITA_TÉCNICA | X87: FACZZ877 | Y87: TIPO I | Z87: TERRESTRE | AA87: SANTOS GONZALEZ JOHAN FABIAN | AB87: 1 | AC87: 0 | AD87: 0 | AE87: 0 | AF87: =IF(W87="SOPORTE_TELEFÓNICO",'BASE LIQUIDACION'!$B$10,IF(Y87="TIPO I",'BASE LIQUIDACION'!$C$3,IF(Y87="TIPO II",'BASE LIQUIDACION'!$C$4,IF(Y87="TIPO III",'BASE LIQUIDACION'!$C$5,'BASE LIQUIDACION'!$C$7)))) -> 65960.474 | AG87: =IF(W87="SOPORTE_TELEFÓNICO",'BASE LIQUIDACION'!$B$10,(AB87*AF87+AC87*'BASE LIQUIDACION'!$B$12+AD87*'BASE LIQUIDACION'!$B$11+INCIDENTES!AE87*'BASE LIQUIDACION'!$B$13)) -> 65960.474
A88: BUCARAMANGA | B88: =VLOOKUP(A88,'CENTRO DE COSTOS'!A:D,4,FALSE) -> MIGUEL JULIÁN HERNÁNDEZ GUARÍN | C88: =VLOOKUP(A88,'CENTRO DE COSTOS'!A:D,2,FALSE) -> 0004-0008 | D88: 68001 | E88: 2437295 | F88: 48861 | G88: INCIDENTE | H88: SANTANDER | I88: BUCARAMANGA | J88: BARRIO LUZ DE SALVACION 1 BUCA | K88: REDEBAN | L88: FO-25-1221216 | M88: 45850.397 | N88: 45850.621 | O88: NO | P88: USUARIO | Q88: COMUNICACION | R88: CONEXIONES DE COMERCIO | S88: CB UNO A UNO | U88: CERRADO | V88: 12-07 SE ESCALA PARA VISITA. LLAMAR ANTES DE VISITAR, CONFIRMAR FALLA Y DATOS 0 12-07 SE REALIZA VISITA AL COMERCIO CB, SE VALIDA Y SE ENCUENTRA QUE EL DATÁFONO NO ENCIENDE SE VALIDAN CONEXIONES Y SE ENCUENTRA QUE ESTABA TOTALMENTE DESCARGADA LA BATERIA, SE LE EXPLICA AL CLIENTE COMO SE DEBE MANIPULAR PARA QUE NO SE VAYAN A QUEDAR NUEVAMENTE SIN FUNCIONAR EL EQUIPO | W88: VISITA_TÉCNICA | X88: AD00M793 | Y88: TIPO I | Z88: TERRESTRE | AA88: GONZALEZ ESTUPIÑAN YEISON WALTER ANTONIO | AB88: 1 | AC88: 0 | AD88: 0 | AE88: 0 | AF88: =IF(W88="SOPORTE_TELEFÓNICO",'BASE LIQUIDACION'!$B$10,IF(Y88="TIPO I",'BASE LIQUIDACION'!$C$3,IF(Y88="TIPO II",'BASE LIQUIDACION'!$C$4,IF(Y88="TIPO III",'BASE LIQUIDACION'!$C$5,'BASE LIQUIDACION'!$C$7)))) -> 65960.474 | AG88: =IF(W88="SOPORTE_TELEFÓNICO",'BASE LIQUIDACION'!$B$10,(AB88*AF88+AC88*'BASE LIQUIDACION'!$B$12+AD88*'BASE LIQUIDACION'!$B$11+INCIDENTES!AE88*'BASE LIQUIDACION'!$B$13)) -> 65960.474
A89: MEDELLIN | B89: =VLOOKUP(A89,'CENTRO DE COSTOS'!A:D,4,FALSE) -> JUAN SEBASTIÁN RÍOS CASTRILLÓN | C89: =VLOOKUP(A89,'CENTRO DE COSTOS'!A:D,2,FALSE) -> 0004-0005 | D89: 5212 | E89: 2437294 | F89: 68622 | G89: INCIDENTE | H89: ANTIOQUIA | I89: COPACABANA | J89: DISTRICOL PUNTO LLAVES | K89: REDEBAN | L89: FO-25-1221220 | M89: 45850.395 | N89: 45850.635 | O89: NO | P89: USUARIO | Q89: USUARIOS | R89: MALA MANIPULACION POS | S89: AGREGADOR | U89: CERRADO | V89: 12-07 SE ESCALA PARA VISITA. LLAMAR ANTES DE VISITAR, CONFIRMAR FALLA Y DATOS 0 12-07 SE REALIZA VISITA A COMERCIO OK, SE REALIZA MANTENIMIENTO OK, EQUIPO ESTÁ OPERATIVO OK, USUARIO INFORMA DE QUE NO LE GUSTA EL EQUIPO TECNOLOGÍA 2600, PERO EQUIPO ESTÁ FUNCIONANDO BIEN, NO PRESENTA NINGUNA FALLA | W89: VISITA_TÉCNICA | X89: A100T088 | Y89: TIPO I | Z89: TERRESTRE | AA89: MARTINEZ TOVAR OSCAR DAVID | AB89: 1 | AC89: 0 | AD89: 0 | AE89: 0 | AF89: =IF(W89="SOPORTE_TELEFÓNICO",'BASE LIQUIDACION'!$B$10,IF(Y89="TIPO I",'BASE LIQUIDACION'!$C$3,IF(Y89="TIPO II",'BASE LIQUIDACION'!$C$4,IF(Y89="TIPO III",'BASE LIQUIDACION'!$C$5,'BASE LIQUIDACION'!$C$7)))) -> 65960.474 | AG89: =IF(W89="SOPORTE_TELEFÓNICO",'BASE LIQUIDACION'!$B$10,(AB89*AF89+AC89*'BASE LIQUIDACION'!$B$12+AD89*'BASE LIQUIDACION'!$B$11+INCIDENTES!AE89*'BASE LIQUIDACION'!$B$13)) -> 65960.474
A90: MEDELLIN | B90: =VLOOKUP(A90,'CENTRO DE COSTOS'!A:D,4,FALSE) -> JUAN SEBASTIÁN RÍOS CASTRILLÓN | C90: =VLOOKUP(A90,'CENTRO DE COSTOS'!A:D,2,FALSE) -> 0004-0005 | D90: 5001 | E90: 2436823 | F90: 28592 | G90: INCIDENTE | H90: ANTIOQUIA | I90: MEDELLIN | J90: 0 | K90: REDEBAN | L90: FO-25-1223251 | M90: 45849.739 | N90: 45850.647 | O90: NO | P90: USUARIO | Q90: MANTENIMIENTO | R90: MANTENIMIENTO GENERAL | S90: CB UNO A UNO | U90: CERRADO | V90: 12-07 CLIENTE INDICA QUE SE EQUIVOCO DE CU, REALIZA NUEVA SOLICITUD. EN ATENCION BAJO EL RADICADO 2437573 CU 27592 0 0 | W90: SOPORTE_TELEFÓNICO | X90: 0 | Y90: TIPO I | Z90: TERRESTRE | AA90: 0 | AB90: 0 | AC90: 0 | AD90: 0 | AE90: 0 | AF90: =IF(W90="SOPORTE_TELEFÓNICO",'BASE LIQUIDACION'!$B$10,IF(Y90="TIPO I",'BASE LIQUIDACION'!$C$3,IF(Y90="TIPO II",'BASE LIQUIDACION'!$C$4,IF(Y90="TIPO III",'BASE LIQUIDACION'!$C$5,'BASE LIQUIDACION'!$C$7)))) -> 37904.654 | AG90: =IF(W90="SOPORTE_TELEFÓNICO",'BASE LIQUIDACION'!$B$10,(AB90*AF90+AC90*'BASE LIQUIDACION'!$B$12+AD90*'BASE LIQUIDACION'!$B$11+INCIDENTES!AE90*'BASE LIQUIDACION'!$B$13)) -> 37904.654
A91: MEDELLIN | B91: =VLOOKUP(A91,'CENTRO DE COSTOS'!A:D,4,FALSE) -> JUAN SEBASTIÁN RÍOS CASTRILLÓN | C91: =VLOOKUP(A91,'CENTRO DE COSTOS'!A:D,2,FALSE) -> 0004-0005 | D91: 5664 | E91: 2435267 | F91: 48480 | G91: INCIDENTE | H91: ANTIOQUIA | I91: SAN PEDRO DE LOS MILAGROS | J91: BARRIO PARQUE SAN PEDRO DE LOS | K91: REDEBAN | L91: FO-25-1219164 | M91: 45849.622 | N91: 45850.665 | O91: NO | P91: USUARIO | Q91: LECTOR DE TARJETAS | R91: OBSTRUCCION DEL LECTOR | S91: CB UNO A UNO | U91: CERRADO | V91: 11-07 SE ESCALA PARA VISITA. LLAMAR ANTES DE VISITAR, CONFIRMAR FALLA Y DATOS 0 12-07 SE REALIZÓ PRUEBA CON TARJETA ANTIGUA Y NUEVA, SALIERON OK | W91: VISITA_TÉCNICA | X91: II00J427 | Y91: TIPO II | Z91: TERRESTRE | AA91: HERNANDEZ CHAVARRIA JUAN CAMILO | AB91: 1 | AC91: 0 | AD91: 0 | AE91: 0 | AF91: =IF(W91="SOPORTE_TELEFÓNICO",'BASE LIQUIDACION'!$B$10,IF(Y91="TIPO I",'BASE LIQUIDACION'!$C$3,IF(Y91="TIPO II",'BASE LIQUIDACION'!$C$4,IF(Y91="TIPO III",'BASE LIQUIDACION'!$C$5,'BASE LIQUIDACION'!$C$7)))) -> 163813.56 | AG91: =IF(W91="SOPORTE_TELEFÓNICO",'BASE LIQUIDACION'!$B$10,(AB91*AF91+AC91*'BASE LIQUIDACION'!$B$12+AD91*'BASE LIQUIDACION'!$B$11+INCIDENTES!AE91*'BASE LIQUIDACION'!$B$13)) -> 163813.56
A92: MEDELLIN | B92: =VLOOKUP(A92,'CENTRO DE COSTOS'!A:D,4,FALSE) -> JUAN SEBASTIÁN RÍOS CASTRILLÓN | C92: =VLOOKUP(A92,'CENTRO DE COSTOS'!A:D,2,FALSE) -> 0004-0005 | D92: 5360 | E92: 2437116 | F92: 59913 | G92: INCIDENTE | H92: ANTIOQUIA | I92: ITAGUI | J92: PTM ITAGUI PAPELERIA Y VARIEDA | K92: REDEBAN | L92: FO-25-1220492 | M92: 45850.333 | N92: 45850.676 | O92: NO | P92: USUARIO | Q92: MANTENIMIENTO | R92: MANTENIMIENTO GENERAL | S92: AGREGADOR | U92: CERRADO | V92: 12-07 SE ESCALA PARA VISITA. LLAMAR ANTES DE VISITAR, CONFIRMAR FALLA Y DATOS 12/07/2025 SE LLAMA AL CLIENTE Y ME Y DICE QUE LA VISITA SE LA HAGAN EL LUNES YA QUE VA DE SALIDA EN ESTOS MOMENTOS 12-07 SE LLAMA AL CLIENTE Y ME DICE QUE LA VISITA SE LA HAGAN EL LUNES YA QUE VA DE SALIDA EN ESTOS MOMENTOS. SE LE INDICA REALIZAR SOLICITUD NUEVAMENTE. CERRAR | W92: SOPORTE_TELEFÓNICO | X92: 0 | Y92: TIPO I | Z92: TERRESTRE | AA92: MORENO MEDINA JUAN PABLO | AB92: 0 | AC92: 0 | AD92: 0 | AE92: 0 | AF92: =IF(W92="SOPORTE_TELEFÓNICO",'BASE LIQUIDACION'!$B$10,IF(Y92="TIPO I",'BASE LIQUIDACION'!$C$3,IF(Y92="TIPO II",'BASE LIQUIDACION'!$C$4,IF(Y92="TIPO III",'BASE LIQUIDACION'!$C$5,'BASE LIQUIDACION'!$C$7)))) -> 37904.654 | AG92: =IF(W92="SOPORTE_TELEFÓNICO",'BASE LIQUIDACION'!$B$10,(AB92*AF92+AC92*'BASE LIQUIDACION'!$B$12+AD92*'BASE LIQUIDACION'!$B$11+INCIDENTES!AE92*'BASE LIQUIDACION'!$B$13)) -> 37904.654
A93: MEDELLIN | B93: =VLOOKUP(A93,'CENTRO DE COSTOS'!A:D,4,FALSE) -> JUAN SEBASTIÁN RÍOS CASTRILLÓN | C93: =VLOOKUP(A93,'CENTRO DE COSTOS'!A:D,2,FALSE) -> 0004-0005 | D93: 5001 | E93: 2438606 | F93: 64209 | G93: INCIDENTE | H93: ANTIOQUIA | I93: MEDELLIN | J93: 0 | K93: REDEBAN | L93: FO-25-1224389 | M93: 45851.468 | N93: 45851.518 | O93: NO | P93: USUARIO | Q93: MANTENIMIENTO | R93: MANTENIMIENTO GENERAL | S93: RETAIL | U93: CERRADO | V93: 13-07 SE ESCALA A LA RED, SE PROCEDE A CERRAR YA QUE NO ATENDEMOS CADENA OLIMPICA - XX-07 TU SOLICITUD REFERENTE A GENERACIÓN DE CASOS CB OLIMPICA BANCOLOMBIA QUEDÓ RADICADA BAJO EL TICKET NÚMERO XXXXXX AL ÁREA ENCARGADA. 0 | W93: SOPORTE_TELEFÓNICO | X93: 0 | Y93: TIPO I | Z93: TERRESTRE | AA93: 0 | AB93: 0 | AC93: 0 | AD93: 0 | AE93: 0 | AF93: =IF(W93="SOPORTE_TELEFÓNICO",'BASE LIQUIDACION'!$B$10,IF(Y93="TIPO I",'BASE LIQUIDACION'!$C$3,IF(Y93="TIPO II",'BASE LIQUIDACION'!$C$4,IF(Y93="TIPO III",'BASE LIQUIDACION'!$C$5,'BASE LIQUIDACION'!$C$7)))) -> 37904.654 | AG93: =IF(W93="SOPORTE_TELEFÓNICO",'BASE LIQUIDACION'!$B$10,(AB93*AF93+AC93*'BASE LIQUIDACION'!$B$12+AD93*'BASE LIQUIDACION'!$B$11+INCIDENTES!AE93*'BASE LIQUIDACION'!$B$13)) -> 37904.654
A94: PEREIRA | B94: =VLOOKUP(A94,'CENTRO DE COSTOS'!A:D,4,FALSE) -> DIEGO FERNANDO HENAO CARDONA | C94: =VLOOKUP(A94,'CENTRO DE COSTOS'!A:D,2,FALSE) -> 0004-0002 | D94: 63001 | E94: 2440254 | F94: 25343 | G94: INCIDENTE | H94: QUINDIO | I94: ARMENIA | J94: ARA0086 CASA FOGATA | K94: REDEBAN | L94: FO-25-1226269 | M94: 45852.39 | N94: 45852.407 | O94: NO | P94: USUARIO | Q94: MANTENIMIENTO | R94: MANTENIMIENTO GENERAL | S94: RETAIL | U94: CERRADO | V94: 14-07 SE ESCALA A LA RED, SE PROCEDE A CERRAR YA QUE NO ATENDEMOS CADENA ARA - 14-07 TU SOLICITUD REFERENTE A GENERACIÓN DE CASOS CB ARA BANCOLOMBIA QUEDÓ RADICADA BAJO EL TICKET NÚMERO 5713494 AL ÁREA ENCARGADA. 0 0 | W94: SOPORTE_TELEFÓNICO | X94: 0 | Y94: TIPO II | Z94: TERRESTRE | AA94: 0 | AB94: 0 | AC94: 0 | AD94: 0 | AE94: 0 | AF94: =IF(W94="SOPORTE_TELEFÓNICO",'BASE LIQUIDACION'!$B$10,IF(Y94="TIPO I",'BASE LIQUIDACION'!$C$3,IF(Y94="TIPO II",'BASE LIQUIDACION'!$C$4,IF(Y94="TIPO III",'BASE LIQUIDACION'!$C$5,'BASE LIQUIDACION'!$C$7)))) -> 37904.654 | AG94: =IF(W94="SOPORTE_TELEFÓNICO",'BASE LIQUIDACION'!$B$10,(AB94*AF94+AC94*'BASE LIQUIDACION'!$B$12+AD94*'BASE LIQUIDACION'!$B$11+INCIDENTES!AE94*'BASE LIQUIDACION'!$B$13)) -> 37904.654
A95: TUNJA | B95: =VLOOKUP(A95,'CENTRO DE COSTOS'!A:D,4,FALSE) -> MIGUEL JULIÁN HERNÁNDEZ GUARÍN | C95: =VLOOKUP(A95,'CENTRO DE COSTOS'!A:D,2,FALSE) -> 0004-0008 | D95: 15455 | E95: 2438435 | F95: 40145 | G95: INCIDENTE | H95: BOYACA | I95: MIRAFLORES | J95: BARRIO CENTRO MIRAFLORES 1 | K95: REDEBAN | L95: FO-25-1224384 | M95: 45851.456 | N95: 45852.442 | O95: NO | P95: USUARIO | Q95: MANTENIMIENTO | R95: MANTENIMIENTO GENERAL | S95: CB UNO A UNO | U95: CERRADO | V95: 13-07 SE ESCALA PARA VISITA. LLAMAR ANTES DE VISITAR, CONFIRMAR FALLA Y DATOS 0 14-07 EN COMUNICACIÓN CON LA LÍNEA 3128564722 LA SEÑORA ANGI BARRETO INFORMA QUE EL SERVICIO YA ESTÁ FUNCIONANDO PERFECTAMENTE Y QUE NO REQUIERE VISITA, SIMPLEMENTE SE LE INDICA AL CLIENTE LA CORRECTA CONECCIÓN DEL LECTOR DE CÓDIGO DE BARRAS AL DATAFONO Y FUNCIONA BIEN. SE CIERRA COMO SOPORTE TELEFONICO | W95: SOPORTE_TELEFÓNICO | X95: 0 | Y95: TIPO IV | Z95: TERRESTRE | AA95: HERRERA GARZON JEYSON STEVENT | AB95: 0 | AC95: 0 | AD95: 0 | AE95: 0 | AF95: =IF(W95="SOPORTE_TELEFÓNICO",'BASE LIQUIDACION'!$B$10,IF(Y95="TIPO I",'BASE LIQUIDACION'!$C$3,IF(Y95="TIPO II",'BASE LIQUIDACION'!$C$4,IF(Y95="TIPO III",'BASE LIQUIDACION'!$C$5,'BASE LIQUIDACION'!$C$7)))) -> 37904.654 | AG95: =IF(W95="SOPORTE_TELEFÓNICO",'BASE LIQUIDACION'!$B$10,(AB95*AF95+AC95*'BASE LIQUIDACION'!$B$12+AD95*'BASE LIQUIDACION'!$B$11+INCIDENTES!AE95*'BASE LIQUIDACION'!$B$13)) -> 37904.654
A96: MEDELLIN | B96: =VLOOKUP(A96,'CENTRO DE COSTOS'!A:D,4,FALSE) -> JUAN SEBASTIÁN RÍOS CASTRILLÓN | C96: =VLOOKUP(A96,'CENTRO DE COSTOS'!A:D,2,FALSE) -> 0004-0005 | D96: 5001 | E96: 2439287 | F96: 26420 | G96: INCIDENTE | H96: ANTIOQUIA | I96: MEDELLIN | J96: BARRIO BELEN 2 MEDELLIN | K96: REDEBAN | L96: FO-25-1225375 | M96: 45852.347 | N96: 45852.465 | O96: NO | P96: USUARIO | Q96: MANTENIMIENTO | R96: MANTENIMIENTO GENERAL | S96: CB UNO A UNO | U96: CERRADO | V96: 14-07 SE ESCALA PARA VISITA. LLAMAR ANTES DE VISITAR, CONFIRMAR FALLA Y DATOS 0 14-07 SE VERIFICA ESTADO DE TECLAS Y SE REALIZA PRUEBAS DE PRESIÓN ESTÁN TODAS OK | W96: VISITA_TÉCNICA | X96: 9999F120 | Y96: TIPO I | Z96: TERRESTRE | AA96: HERNANDEZ CHAVARRIA JUAN CAMILO | AB96: 1 | AC96: 0 | AD96: 0 | AE96: 0 | AF96: =IF(W96="SOPORTE_TELEFÓNICO",'BASE LIQUIDACION'!$B$10,IF(Y96="TIPO I",'BASE LIQUIDACION'!$C$3,IF(Y96="TIPO II",'BASE LIQUIDACION'!$C$4,IF(Y96="TIPO III",'BASE LIQUIDACION'!$C$5,'BASE LIQUIDACION'!$C$7)))) -> 65960.474 | AG96: =IF(W96="SOPORTE_TELEFÓNICO",'BASE LIQUIDACION'!$B$10,(AB96*AF96+AC96*'BASE LIQUIDACION'!$B$12+AD96*'BASE LIQUIDACION'!$B$11+INCIDENTES!AE96*'BASE LIQUIDACION'!$B$13)) -> 65960.474
A97: CUCUTA | B97: =VLOOKUP(A97,'CENTRO DE COSTOS'!A:D,4,FALSE) -> MIGUEL JULIÁN HERNÁNDEZ GUARÍN | C97: =VLOOKUP(A97,'CENTRO DE COSTOS'!A:D,2,FALSE) -> 0004-0008 | D97: 54239 | E97: 2437257 | F97: 15003 | G97: INCIDENTE | H97: NORTE DE SANTANDER | I97: DURANIA | J97: BARRIO CENTRO DURANIA CUCUTA | K97: REDEBAN | L97: FO-25-1220847 | M97: 45850.367 | N97: 45852.505 | O97: NO | P97: USUARIO | Q97: COMUNICACION | R97: CONEXIONES DE COMERCIO | S97: CB UNO A UNO | U97: CERRADO | V97: 12-07 SE ESCALA PARA VISITA. LLAMAR ANTES DE VISITAR, CONFIRMAR FALLA Y DATOS 12/07/2025 SE PROGRAMA VISITA EN EL MUNICIPIO DE DURANIA PARA EL DIA LUNES 14/07 YA QUE EL DIA DE HOY NO SE ALCANZA A LLEGAR AL MUNICIPIO SOBRE LA HORA Y POR CAMBIOS DE EQUIPO POR PARTE DE RBM NO ES POSIBLE ATENDER LA ORDEN POR TEMA DE ACTIVO REDEBANCONTACTO GLADIS MELO - 3204920877 14-07 SE VISITA COMERCIO Y SE CAMBIA, CABLE UTP, SE CAMBIA MAGIC BOX, SE REALIZAN CIERRES Y PRUEBAS OK. | W97: VISITA_TÉCNICA | X97: 9A002780 | Y97: TIPO II | Z97: TERRESTRE | AA97: TORRES MANTILLA JOSE DANIEL | AB97: 1 | AC97: 0 | AD97: 0 | AE97: 0 | AF97: =IF(W97="SOPORTE_TELEFÓNICO",'BASE LIQUIDACION'!$B$10,IF(Y97="TIPO I",'BASE LIQUIDACION'!$C$3,IF(Y97="TIPO II",'BASE LIQUIDACION'!$C$4,IF(Y97="TIPO III",'BASE LIQUIDACION'!$C$5,'BASE LIQUIDACION'!$C$7)))) -> 163813.56 | AG97: =IF(W97="SOPORTE_TELEFÓNICO",'BASE LIQUIDACION'!$B$10,(AB97*AF97+AC97*'BASE LIQUIDACION'!$B$12+AD97*'BASE LIQUIDACION'!$B$11+INCIDENTES!AE97*'BASE LIQUIDACION'!$B$13)) -> 163813.56
A98: BUCARAMANGA | B98: =VLOOKUP(A98,'CENTRO DE COSTOS'!A:D,4,FALSE) -> MIGUEL JULIÁN HERNÁNDEZ GUARÍN | C98: =VLOOKUP(A98,'CENTRO DE COSTOS'!A:D,2,FALSE) -> 0004-0008 | D98: 68001 | E98: 2438080 | F98: 79985 | G98: INCIDENTE | H98: SANTANDER | I98: BUCARAMANGA | J98: BARRIO SAN FRANCISCO BUCARAMANGA 19 | K98: REDEBAN | L98: FO-25-1224236 | M98: 45851.333 | N98: 45852.506 | O98: NO | P98: USUARIO | Q98: COMUNICACION | R98: CANAL DEL COMERCIO | S98: CB UNO A UNO | U98: CERRADO | V98: 13-07 SE ESCALA PARA VISITA. LLAMAR ANTES DE VISITAR, CONFIRMAR FALLA Y DATOS 13/07/2025 NO SE LOGRÓ CONTACTO VÍA CHAO O LLAMADA AL 3208847178, SE REALIZARÁ VISITA EN FRÍO. 13-07 SE REALIZA VISITA EN FRÍO A COMERCIO DEBIDO A QUE NO RESPONDE LOS MENSAJES VÍA WHATSAPP Y NO RESPONDE LLAMADAS SE LLEGA A SITIO SE VALÍDA QUE SE ENCUENTRA CERRADO SE VUELVE A REALIZAR GESTION TELEFÓNICO NO CONTESTA SE PROCEDE A CERRAR LA ORDEN. 0 14-07 SE REALIZA VISITA AL COMERCIO CB, SE VALIDA Y AL MOMENTO DE REVISAR EL DATÁFONO SE ENCUENTRA APAGADO SE CAMBIO FUENTE Y SIGUE IGUAL DATÁFONO QUEMADO, SE INTENTA CON EL BACKUP PERO NO HAY CONEXIÓN A INTERNET, FALLAS CON EL OPERADOR TIGO EN LA ZONA, CLIENTE SE COMUNICA PARA SOLICITAR ARREGLO DEL INTERNET , YA QUE EL DIA SÁBADO Y DOMINGO LLOVIO MUY FUERTE EN LA CIUDAD | W98: VISITA_TÉCNICA | X98: SAXZZ529 | Y98: TIPO I | Z98: TERRESTRE | AA98: GONZALEZ ESTUPIÑAN YEISON WALTER ANTONIO | AB98: 2 | AC98: 0 | AD98: 0 | AE98: 0 | AF98: =IF(W98="SOPORTE_TELEFÓNICO",'BASE LIQUIDACION'!$B$10,IF(Y98="TIPO I",'BASE LIQUIDACION'!$C$3,IF(Y98="TIPO II",'BASE LIQUIDACION'!$C$4,IF(Y98="TIPO III",'BASE LIQUIDACION'!$C$5,'BASE LIQUIDACION'!$C$7)))) -> 65960.474 | AG98: =IF(W98="SOPORTE_TELEFÓNICO",'BASE LIQUIDACION'!$B$10,(AB98*AF98+AC98*'BASE LIQUIDACION'!$B$12+AD98*'BASE LIQUIDACION'!$B$11+INCIDENTES!AE98*'BASE LIQUIDACION'!$B$13)) -> 131920.95
A99: BUCARAMANGA | B99: =VLOOKUP(A99,'CENTRO DE COSTOS'!A:D,4,FALSE) -> MIGUEL JULIÁN HERNÁNDEZ GUARÍN | C99: =VLOOKUP(A99,'CENTRO DE COSTOS'!A:D,2,FALSE) -> 0004-0008 | D99: 68001 | E99: 2438655 | F99: 38830 | G99: INCIDENTE | H99: SANTANDER | I99: BUCARAMANGA | J99: PTM B MANGA JAIMES | K99: REDEBAN | L99: FO-25-1224984 | M99: 45851.707 | N99: 45852.66 | O99: NO | P99: USUARIO | Q99: NO ENCIENDE | R99: CONEXIONES DE COMERCIO | S99: AGREGADOR | U99: CERRADO | V99: 14-07 SE ESCALA PARA VISITA. LLAMAR ANTES DE VISITAR, CONFIRMAR FALLA Y DATOS 0 14-07 EN COMUNICACIÓN CON LA SEÑORA MARÍA AL MÓVIL 3187336245, INDICA QUE EL EQUIPO EL DÍA DE HOY ENCENDIÓ Y FUNCIÓNA CON NORMALIDAD, INDICA QUE Y NO REQUIERE DE LA VISITA TÉCNICA SE LE INFORMA QUE SI LLEGA A VOLVER A PRESENTAR UNA NUEVA NOVEDAD DEBERÁ LLAMAR A LA LÍNEA Y SOLICITAR NUEVAMENTE UNA VISITA TÉCNICA. | W99: SOPORTE_TELEFÓNICO | X99: 0 | Y99: TIPO I | Z99: TERRESTRE | AA99: SANTOS GONZALEZ JOHAN FABIAN | AB99: 0 | AC99: 0 | AD99: 0 | AE99: 0 | AF99: =IF(W99="SOPORTE_TELEFÓNICO",'BASE LIQUIDACION'!$B$10,IF(Y99="TIPO I",'BASE LIQUIDACION'!$C$3,IF(Y99="TIPO II",'BASE LIQUIDACION'!$C$4,IF(Y99="TIPO III",'BASE LIQUIDACION'!$C$5,'BASE LIQUIDACION'!$C$7)))) -> 37904.654 | AG99: =IF(W99="SOPORTE_TELEFÓNICO",'BASE LIQUIDACION'!$B$10,(AB99*AF99+AC99*'BASE LIQUIDACION'!$B$12+AD99*'BASE LIQUIDACION'!$B$11+INCIDENTES!AE99*'BASE LIQUIDACION'!$B$13)) -> 37904.654
A100: APARTADO | B100: =VLOOKUP(A100,'CENTRO DE COSTOS'!A:D,4,FALSE) -> JUAN SEBASTIÁN RÍOS CASTRILLÓN | C100: =VLOOKUP(A100,'CENTRO DE COSTOS'!A:D,2,FALSE) -> 0004-0005 | D100: 27800 | E100: 2437955 | F100: 44457 | G100: INCIDENTE | H100: CHOCO | I100: UNGUIA | J100: DISTRICOL MOTO PARTES J A S | K100: REDEBAN | L100: FO-25-1223919 | M100: 45851.333 | N100: 45852.686 | O100: NO | P100: USUARIO | Q100: MANTENIMIENTO | R100: MANTENIMIENTO GENERAL | S100: AGREGADOR | U100: CERRADO | V100: 13-07 SE INTENTA COMUNICACION CON EL USUARIO AL NUMERO 3233122151, PERO NO CONTESTA LA LLAMADA. SE ESCALA PARA VISITA, CONFIRMAR FALLA Y DATOS 0 14-07 SE HABLA CON USUARIA, SE DAN INDICACIONES PARA INGRESAR Y REALIZAR PRUEBAS DE CIERRES, SE REALIZAN SIN PROBLEMAS, CB OPERATIVO, SE CIERRA INCIDENTE. | W100: SOPORTE_TELEFÓNICO | X100: 0 | Y100: TIPO IV ESPECIAL | Z100: FLUVIAL | AA100: MORENO MEDINA JUAN PABLO | AB100: 0 | AC100: 0 | AD100: 0 | AE100: 0 | AF100: =IF(W100="SOPORTE_TELEFÓNICO",'BASE LIQUIDACION'!$B$10,IF(Y100="TIPO I",'BASE LIQUIDACION'!$C$3,IF(Y100="TIPO II",'BASE LIQUIDACION'!$C$4,IF(Y100="TIPO III",'BASE LIQUIDACION'!$C$5,'BASE LIQUIDACION'!$C$7)))) -> 37904.654 | AG100: =IF(W100="SOPORTE_TELEFÓNICO",'BASE LIQUIDACION'!$B$10,(AB100*AF100+AC100*'BASE LIQUIDACION'!$B$12+AD100*'BASE LIQUIDACION'!$B$11+INCIDENTES!AE100*'BASE LIQUIDACION'!$B$13)) -> 37904.654
...

Sheet OC
A1: CIUDAD SEDE | B1: COORDINADOR | C1: CENTRO DE COSTOS LÍNEACOM | D1: CÓDIGO DANE | E1: TA/CODIGO ACTIVIDAD | F1: CODIGO CB | G1: ACTIVIDAD | H1: DEPARTAMENTO | I1: CIUDAD | J1: NOMBRE DEL CB | K1: RED | L1: FO | M1: FECHA ASIGNACION A LINEA COMUNICACIONES | N1: FECHA DEL CIERRE DEL TICKET (DD/MM/AAAA) | O1: ACOMETIDA | P1: SOLICITUD | Q1: DESCRIPCIÓN | R1: FORMATO | S1: CADENA | T1: ESTADO | U1: CAUSAL ESTADO | V1: OBSERVACION | W1: FORMA DE ATENCIÓN | X1: TERMINAL | Y1: TIPIFICACION | Z1: TIPO DE TRAYECTO | AA1: NOMBRE DEL TECNICO | AB1: DIAS DE VISITA | AC1: SWITCH | AD1: ACOMETIDA DATOS | AE1: ACOMETIDA ELECTRICA | AF1: VALOR ACTIVIDAD | AG1: VALOR TOTAL
A2: BUCARAMANGA | B2: =VLOOKUP(A2,'CENTRO DE COSTOS'!A:D,4,FALSE) -> MIGUEL JULIÁN HERNÁNDEZ GUARÍN | C2: =VLOOKUP(A2,'CENTRO DE COSTOS'!A:D,2,FALSE) -> 0004-0008 | D2: 68745 | E2: 13657371 | F2: 39748 | G2: ORDEN DE CAMBIO | H2: SANTANDER | I2: SIMACOTA | J2: PTM SIMACOTA DE SHOPPING NC | K2: REDEBAN | L2: FO-25-1158159 | M2: 45839.349 | N2: 45845.677 | P2: TRASLADO | Q2: TRASLADO EXTERNO | R2: AGREGADOR | S2: COMCARD - PTM | T2: EJECUTADO_CANCELADO | U2: PETICIÓN USUARIO | V2: SOLICITUD DE TRASLADO EXTERNO 07/07/2025 EN COMUNICACIÓN CON LA SEÑORA DÉBORA CALDERÓN AL NÚMERO 3102736915 NOS INDICA REALIZAR LA VISITA EL DÍA DE MAÑANA DEBIDO A QUE EL DÍA DE HOY LE ESTÁN INSTALANDO EL INTERNET EN EL NUEVO COMERCIO 07/07/2025 En comunicación con la señora Débora Calderón Ramírez al número 3102736915 se le indica que cuando tenga el servicio de Internet en el comercio se comunique nuevamente a la línea de Bancolombia 018000953344 para gestionar nuevamente el traslado | W2: SOPORTE_TELEFÓNICO | X2: 0 | Y2: TIPO III | Z2: TERRESTRE | AA2: MARIÑO PABON JORGE ENRIQUE | AB2: 0 | AC2: 0 | AD2: 0 | AE2: 0 | AF2: =IF(W2="SOPORTE_TELEFÓNICO",'BASE LIQUIDACION'!$B$10,IF(Y2="TIPO I",'BASE LIQUIDACION'!$C$3,IF(Y2="TIPO II",'BASE LIQUIDACION'!$C$4,IF(Y2="TIPO III",'BASE LIQUIDACION'!$C$5,'BASE LIQUIDACION'!$C$7)))) -> 37904.654 | AG2: =IF(W2="SOPORTE_TELEFÓNICO",'BASE LIQUIDACION'!$B$10,(AB2*AF2+AC2*'BASE LIQUIDACION'!$B$13+AD2*'BASE LIQUIDACION'!$B$12+AE2*'BASE LIQUIDACION'!$B$11)) -> 37904.654
A3: BUCARAMANGA | B3: =VLOOKUP(A3,'CENTRO DE COSTOS'!A:D,4,FALSE) -> MIGUEL JULIÁN HERNÁNDEZ GUARÍN | C3: =VLOOKUP(A3,'CENTRO DE COSTOS'!A:D,2,FALSE) -> 0004-0008 | D3: 68547 | E3: 13550820 | F3: 67941 | G3: ORDEN DE CAMBIO | H3: SANTANDER | I3: PIEDECUESTA | J3: PTM PIEDECUESTA DON PALETA | K3: REDEBAN | L3: FO-25-1199698 | M3: 45846.401 | N3: 45847.487 | P3: TRASLADO | Q3: TRASLADO EXTERNO | R3: AGREGADOR | S3: COMCARD - PTM | T3: GESTIÓN_TELEFÓNICA | U3: CANCELADO POR EL USUARIO | V3: SOLICITUD DE TRASLADO 09/07/2025 SE COMUNICA CON LA SEÑORITA CLAUDIA LEÓN AL NUMERO 3183364093 EL CUAL NOS INFORMA QUE ELLA NO SOLICITO UN TRASLADO , QUE POR FAVOR ELLA NO DESEA CONTINUAR CON EL SERVICIO Y NECESITA UN RETIRO DE EQUIPOS , SE LE INFORMA QUE POR FAVOR LLAMAR AL NUMERO 018000953344 PARA QUE SOLICITE EL RETIRO DE LOS EQUIPOS 09/07/2025 SE COMUNICA CON LA SEÑORITA CLAUDIA LEÓN AL NUMERO 3183364093 EL CUAL NOS INFORMA QUE ELLA NO SOLICITO UN TRASLADO , QUE POR FAVOR ELLA NO DESEA CONTINUAR CON EL SERVICIO Y NECESITA UN RETIRO DE EQUIPOS , SE LE INFORMA QUE POR FAVOR LLAMAR AL NUMERO 018000953344 PARA QUE SOLICITE EL RETIRO DE LOS EQUIPOS | W3: SOPORTE_TELEFÓNICO | X3: 0 | Y3: TIPO II | Z3: TERRESTRE | AA3: BARAJAS BERMUDEZ YAHIR MAURICIO | AB3: 0 | AC3: 0 | AD3: 0 | AE3: 0 | AF3: =IF(W3="SOPORTE_TELEFÓNICO",'BASE LIQUIDACION'!$B$10,IF(Y3="TIPO I",'BASE LIQUIDACION'!$C$3,IF(Y3="TIPO II",'BASE LIQUIDACION'!$C$4,IF(Y3="TIPO III",'BASE LIQUIDACION'!$C$5,'BASE LIQUIDACION'!$C$7)))) -> 37904.654 | AG3: =IF(W3="SOPORTE_TELEFÓNICO",'BASE LIQUIDACION'!$B$10,(AB3*AF3+AC3*'BASE LIQUIDACION'!$B$13+AD3*'BASE LIQUIDACION'!$B$12+AE3*'BASE LIQUIDACION'!$B$11)) -> 37904.654
A4: BOGOTA | B4: =VLOOKUP(A4,'CENTRO DE COSTOS'!A:D,4,FALSE) -> WILLIAM ASDRUBAL ROZO ROZO | C4: =VLOOKUP(A4,'CENTRO DE COSTOS'!A:D,2,FALSE) -> 0004-0004 | D4: 25899 | E4: 13677662 | F4: 43058 | G4: ORDEN DE CAMBIO | H4: CUNDINAMARCA | I4: ZIPAQUIRA | J4: BARRIO CENTRO ZIPAQUIRA 3 | K4: REDEBAN | L4: FO-25-1193816 | M4: 45845.406 | N4: 45847.588 | P4: TRASLADO | Q4: TRASLADO EXTERNO | R4: CB UNO A UNO | S4: CB UNO A UNO | T4: GESTIÓN_TELEFÓNICA | U4: CANCELADO POR EL USUARIO | V4: SOLICITUD DE TRASLADO 0 09/07/2025 Se realiza llamada de validación se habla con la Sra. Doris Sierra quien informa que aún no cuenta con servicio de internet en el local donde se va a trasladar el corresponsal, se le informa que apenas tenga el servicio de internet se vuelva a comunicar con la linea de corresponsales y solicite nueva fecha de vista técnica para ejecutar el traslado. | W4: SOPORTE_TELEFÓNICO | X4: 0 | Y4: TIPO II | Z4: TERRESTRE | AA4: MURCIA HERNANDEZ HARVEY IGNACIO | AB4: 0 | AC4: 0 | AD4: 0 | AE4: 0 | AF4: =IF(W4="SOPORTE_TELEFÓNICO",'BASE LIQUIDACION'!$B$10,IF(Y4="TIPO I",'BASE LIQUIDACION'!$C$3,IF(Y4="TIPO II",'BASE LIQUIDACION'!$C$4,IF(Y4="TIPO III",'BASE LIQUIDACION'!$C$5,'BASE LIQUIDACION'!$C$7)))) -> 37904.654 | AG4: =IF(W4="SOPORTE_TELEFÓNICO",'BASE LIQUIDACION'!$B$10,(AB4*AF4+AC4*'BASE LIQUIDACION'!$B$13+AD4*'BASE LIQUIDACION'!$B$12+AE4*'BASE LIQUIDACION'!$B$11)) -> 37904.654
A5: CUCUTA | B5: =VLOOKUP(A5,'CENTRO DE COSTOS'!A:D,4,FALSE) -> MIGUEL JULIÁN HERNÁNDEZ GUARÍN | C5: =VLOOKUP(A5,'CENTRO DE COSTOS'!A:D,2,FALSE) -> 0004-0008 | D5: 54498 | E5: 13588666 | F5: 60894 | G5: ORDEN DE CAMBIO | H5: NORTE DE SANTANDER | I5: OCAÑA | J5: PTM OCANA GILU | K5: REDEBAN | L5: FO-25-1206123 | M5: 45846.401 | N5: 45847.628 | P5: TRASLADO | Q5: TRASLADO EXTERNO | R5: AGREGADOR | S5: COMCARD - PTM | T5: EJECUTADO_EXITOSO | U5: EJECUTADO EXITOSO | V5: SOLICITUD DE TRASLADO 0 08/07/2025 Se realizó visita al comercio y se encuentra solo datafono, no se encuentro pid pad, lectora ni hud, se le informa al cliente que para realizar correctamente el traslado debe tener las placas en el comercio, se le informa que no se puede realizar traslado ya que no cuenta con las placas o realizar el respectivo denuncio ante la fiscalía reportado las placas perdidas. 0 09/07/2025 SE REALIZÓ TRASLADO DE DIRECCIÓN OK, SE REALIZA CAMBIO DE DATAFONO POR COMPATIBILIDAD CON PID PAD INSTALADO, SE INSTALA PID PAD, LECTORA OK, SE INSTALARON EQUIPOS NUEVOS YA QUE EL EL SR GUSTAVO REPORTA A FISCALÍA LOS EQUIPOS, Y RBM AUTORIZA INSTALAR NUEVAMENTE. PRUEBAS CON RECHAZO GENERAL A LA ESPERA DE ACTIVACIÓN. Rbm autoriza instalar equipos nuevamente ya que el representante puso el reporte de robo de equipos ante la fiscalía, se instala pid pad y lectora Magic box 2600 | W5: VISITA_TÉCNICA | X5: KA00F795 | Y5: TIPO IV | Z5: TERRESTRE | AA5: MORA VEGA JEAMPIER | AB5: 1 | AC5: 0 | AD5: 0 | AE5: 0 | AF5: =IF(W5="SOPORTE_TELEFÓNICO",'BASE LIQUIDACION'!$B$10,IF(Y5="TIPO I",'BASE LIQUIDACION'!$C$3,IF(Y5="TIPO II",'BASE LIQUIDACION'!$C$4,IF(Y5="TIPO III",'BASE LIQUIDACION'!$C$5,'BASE LIQUIDACION'!$C$7)))) -> 479589.74 | AG5: =IF(W5="SOPORTE_TELEFÓNICO",'BASE LIQUIDACION'!$B$10,(AB5*AF5+AC5*'BASE LIQUIDACION'!$B$13+AD5*'BASE LIQUIDACION'!$B$12+AE5*'BASE LIQUIDACION'!$B$11)) -> 479589.74
A6: CARTAGENA | B6: =VLOOKUP(A6,'CENTRO DE COSTOS'!A:D,4,FALSE) -> JOSE MAURICIO HERNANDEZ ROJAS | C6: =VLOOKUP(A6,'CENTRO DE COSTOS'!A:D,2,FALSE) -> 0004-0001 | D6: 13001 | E6: 13461670 | F6: 69446 | G6: ORDEN DE CAMBIO | H6: BOLIVAR | I6: CARTAGENA | J6: PTM CARTAGENA DROGUERIA G V P | K6: REDEBAN | L6: FO-25-1199693 | M6: 45846.401 | N6: 45848.324 | P6: TRASLADO | Q6: TRASLADO EXTERNO | R6: AGREGADOR | S6: COMCARD - PTM | T6: GESTIÓN_TELEFÓNICA | U6: CANCELADO POR EL USUARIO | V6: SOLICITUD DE TRASLADO 09/07/2025 CLIENTE GERMÁN VALLE INFORMA VÍA TELEFONICA QUE SOLICITO EL TRASLADO HACE MUCHO TIEMPO Y NO SE LO HABÍAN QUERIDO APROBAR POR LO TANTO COMENTA QUE YA NO DESEA TENER EL CORRESPONSAL Y VA SOLICITAR EL CIERRE DEBIDO A QUE SE FUE DEL PAIS 09/07/2025 Cliente germán valle informa vía telefonica que solicito el traslado hace mucho tiempo y no se lo habían querido aprobar por lo tanto comenta que ya no desea tener el corresponsal y va solicitar el cierre debido a que se fue del pais | W6: SOPORTE_TELEFÓNICO | X6: 0 | Y6: TIPO I | Z6: TERRESTRE | AA6: MARTINEZ SALGUEDO ANDRES AUGUSTO | AB6: 0 | AC6: 0 | AD6: 0 | AE6: 0 | AF6: =IF(W6="SOPORTE_TELEFÓNICO",'BASE LIQUIDACION'!$B$10,IF(Y6="TIPO I",'BASE LIQUIDACION'!$C$3,IF(Y6="TIPO II",'BASE LIQUIDACION'!$C$4,IF(Y6="TIPO III",'BASE LIQUIDACION'!$C$5,'BASE LIQUIDACION'!$C$7)))) -> 37904.654 | AG6: =IF(W6="SOPORTE_TELEFÓNICO",'BASE LIQUIDACION'!$B$10,(AB6*AF6+AC6*'BASE LIQUIDACION'!$B$13+AD6*'BASE LIQUIDACION'!$B$12+AE6*'BASE LIQUIDACION'!$B$11)) -> 37904.654
A7: PEREIRA | B7: =VLOOKUP(A7,'CENTRO DE COSTOS'!A:D,4,FALSE) -> DIEGO FERNANDO HENAO CARDONA | C7: =VLOOKUP(A7,'CENTRO DE COSTOS'!A:D,2,FALSE) -> 0004-0002 | D7: 66001 | E7: 13365127 | F7: 71933 | G7: ORDEN DE CAMBIO | H7: RISARALDA | I7: PEREIRA | J7: DISTRICOL FENIX INTERNET Y PAP | K7: REDEBAN | L7: FO-25-1213639 | M7: 45848.454 | N7: 45849.48 | P7: TRASLADO | Q7: TRASLADO EXTERNO | R7: AGREGADOR | S7: DISTRICOL | T7: EJECUTADO_CANCELADO | U7: PETICIÓN USUARIO | V7: SOLICITUD DE TRASLADO EXTERNO 0 11/07/2025 Visitamos comercio pero el traslado externo no es posible realizarlo ya que la persona que le iba alquilar el local en la nueva dirección no le pudo dar espera para poder hacer el traslado por el momento ellos continúan en la misma dirección que es MZ 6 CS 12 | W7: VISITA_TÉCNICA | X7: 0 | Y7: TIPO I | Z7: TERRESTRE | AA7: ARROYAVE CANO MANUEL GUILLERMO | AB7: 1 | AC7: 0 | AD7: 0 | AE7: 0 | AF7: =IF(W7="SOPORTE_TELEFÓNICO",'BASE LIQUIDACION'!$B$10,IF(Y7="TIPO I",'BASE LIQUIDACION'!$C$3,IF(Y7="TIPO II",'BASE LIQUIDACION'!$C$4,IF(Y7="TIPO III",'BASE LIQUIDACION'!$C$5,'BASE LIQUIDACION'!$C$7)))) -> 65960.474 | AG7: =IF(W7="SOPORTE_TELEFÓNICO",'BASE LIQUIDACION'!$B$10,(AB7*AF7+AC7*'BASE LIQUIDACION'!$B$13+AD7*'BASE LIQUIDACION'!$B$12+AE7*'BASE LIQUIDACION'!$B$11)) -> 65960.474
A8: MEDELLIN | B8: =VLOOKUP(A8,'CENTRO DE COSTOS'!A:D,4,FALSE) -> JUAN SEBASTIÁN RÍOS CASTRILLÓN | C8: =VLOOKUP(A8,'CENTRO DE COSTOS'!A:D,2,FALSE) -> 0004-0005 | D8: 5736 | E8: 13408567 | F8: 77365 | G8: ORDEN DE CAMBIO | H8: ANTIOQUIA | I8: SEGOVIA | J8: DISTRICOL GIROS D Y M | K8: REDEBAN | L8: FO-25-1107247 | M8: 45826.354 | N8: 45852.635 | P8: TRASLADO | Q8: TRASLADO EXTERNO | R8: AGREGADOR | S8: DISTRICOL | T8: GESTIÓN_TELEFÓNICA | U8: CANCELADO POR LA ENTIDAD-SOPORTE TELEFONICO | V8: SOLICITUD TRASLADO EXTERNO - 25-06 ACTIVIDAD SE ATIENDE PROBABLEMENTE EL DÍA DE MAÑANA 26-06 ** 27-06 CASO ESCALADO A LA RED POR NOVEDAD DE ORDEN PUBLICO EN LA ZONA ** 14-07 LA RED: SEGUN INDICACION DE ENTIDAD POR FAVOR CANCELEMOS ESTE TRASLADO 27/06/2025 CASO ESCALADO A LA RED DEBIDO A INCONSISTENCIAS EN CUANTO A LA INFORMACIÓN DEL TRASLADO. ADICIONALMENTE DEBIDO A QUE ZONA DE CORREGIMIENTO TIENE NOVEDAD DE ORDEN PUBLICO POR FUERTE PRESENCIA DE LA GUERRILLA. 08/07/2025 CASO AUN ESCALADO SE CONSULTA A LA RED. 14/07/2025 Redeban informa que: "Según indicación de entidad por favor cancelemos este traslado". Se procede con cierre de ticket. | W8: SOPORTE_TELEFÓNICO | X8: 0 | Y8: TIPO IV | Z8: TERRESTRE | AA8: MORENO MEDINA JUAN PABLO | AB8: 0 | AC8: 0 | AD8: 0 | AE8: 0 | AF8: =IF(W8="SOPORTE_TELEFÓNICO",'BASE LIQUIDACION'!$B$10,IF(Y8="TIPO I",'BASE LIQUIDACION'!$C$3,IF(Y8="TIPO II",'BASE LIQUIDACION'!$C$4,IF(Y8="TIPO III",'BASE LIQUIDACION'!$C$5,'BASE LIQUIDACION'!$C$7)))) -> 37904.654 | AG8: =IF(W8="SOPORTE_TELEFÓNICO",'BASE LIQUIDACION'!$B$10,(AB8*AF8+AC8*'BASE LIQUIDACION'!$B$13+AD8*'BASE LIQUIDACION'!$B$12+AE8*'BASE LIQUIDACION'!$B$11)) -> 37904.654
A9: CALI | B9: =VLOOKUP(A9,'CENTRO DE COSTOS'!A:D,4,FALSE) -> DIEGO FERNANDO HENAO CARDONA | C9: =VLOOKUP(A9,'CENTRO DE COSTOS'!A:D,2,FALSE) -> 0004-0003 | D9: 19001 | E9: 13727668 | F9: 78387 | G9: ORDEN DE CAMBIO | H9: CAUCA | I9: POPAYAN | J9: BARRIO CENTRO POPAYAN 29 | K9: REDEBAN | L9: FO-25-1248828 | M9: 45855.723 | N9: 45861.368 | P9: TRASLADO | Q9: TRASLADO EXTERNO | R9: CB UNO A UNO | S9: CB UNO A UNO | T9: EJECUTADO_CANCELADO | U9: CB CERRADO - DESOCUPADO | V9: SOLICITUD DE TRASLADO EXTERNO 0 23/07/2025 Se llega al comercio se encuentra cerrado, se llama en repetidas ocaciones cliente no contesta, se escribe al what app tampoco contesta | W9: VISITA_TÉCNICA | X9: 0 | Y9: TIPO III | Z9: TERRESTRE | AA9: GIMBUEL LASSO LUIS GERMAN | AB9: 1 | AC9: 0 | AD9: 0 | AE9: 0 | AF9: =IF(W9="SOPORTE_TELEFÓNICO",'BASE LIQUIDACION'!$B$10,IF(Y9="TIPO I",'BASE LIQUIDACION'!$C$3,IF(Y9="TIPO II",'BASE LIQUIDACION'!$C$4,IF(Y9="TIPO III",'BASE LIQUIDACION'!$C$5,'BASE LIQUIDACION'!$C$7)))) -> 275728.38 | AG9: =IF(W9="SOPORTE_TELEFÓNICO",'BASE LIQUIDACION'!$B$10,(AB9*AF9+AC9*'BASE LIQUIDACION'!$B$13+AD9*'BASE LIQUIDACION'!$B$12+AE9*'BASE LIQUIDACION'!$B$11)) -> 275728.38
AG10: =SUM(AG2:AG9) -> 1010801.9

Sheet CENTRO DE COSTOS
A1: CIUDAD | B1: CENTRO_COSTO | C1: DESCRIPCION | D1: COORDINADOR
A2: APARTADO | B2: 0004-0005 | C2: Redeban Noroccidente (Medellín) | D2: JUAN SEBASTIÁN RÍOS CASTRILLÓN
A3: BARRANQUILLA | B3: 0004-0001 | C3: Redeban Costa (Barranqullla) | D3: JOSE MAURICIO HERNANDEZ ROJAS
A4: BOGOTA | B4: 0004-0004 | C4: Redeban Centro ( Bogotá) | D4: WILLIAM ASDRUBAL ROZO ROZO
A5: BUCARAMANGA | B5: 0004-0008 | C5: Redeban Santander | D5: MIGUEL JULIÁN HERNÁNDEZ GUARÍN
A6: CALI | B6: 0004-0003 | C6: Redeban Suroccidente (Cali) | D6: DIEGO FERNANDO HENAO CARDONA
A7: CARTAGENA | B7: 0004-0001 | C7: Redeban Costa (Barranqullla) | D7: JOSE MAURICIO HERNANDEZ ROJAS
A8: CUCUTA | B8: 0004-0008 | C8: Redeban Santander | D8: MIGUEL JULIÁN HERNÁNDEZ GUARÍN
A9: FLORENCIA | B9: 0004-0007 | C9: Redeban Oriente (Otros) | D9: KEVIN ALEXIS CORZO BUSTOS
A10: IBAGUE | B10: 0004-0007 | C10: Redeban Oriente (Otros) | D10: KEVIN ALEXIS CORZO BUSTOS
A11: MANIZALES | B11: 0004-0002 | C11: Redeban Eje Cafetero (Pereira) | D11: DIEGO FERNANDO HENAO CARDONA
A12: MEDELLIN | B12: 0004-0005 | C12: Redeban Noroccidente (Medellín) | D12: JUAN SEBASTIÁN RÍOS CASTRILLÓN
... A23: YOPAL | B23: 0004-0007 | C23: Redeban Oriente (Otros) | D23: KEVIN ALEXIS CORZO BUSTOS
