Workbook
Name A: #REF!
Name Actividad: #REF!
Name Analistas: #REF!
Name arearesponsable: #REF!
Name CCO: #REF!
Name Clientes: #REF!
Name COORDINADOR: #REF!
Name Coordinadores: #REF!
Name DOCUMENTADOR: #REF!
Name ES: #REF!
Name ESS: #REF!
Name Estado: #REF!
Name ESTADOACTIVIDAD: #REF!
Name ESTADOS: #REF!
Name ESTADOSCIERRES: #REF!
Name Facturacion: #REF!
Name FACTURACIÓN: #REF!
Name falla: #REF!
Name Fallas: #REF!
Name Grupo_Falla: #REF!
Name inconservmanager: #REF!
Name INCUMPLIMIENTO: #REF!
Name LISTA: #REF!
Name LISTA2: #REF!
Name LOLO: #REF!
Name solicitudes: #REF!
Name Tecnicos: #REF!
Name Version: #REF!

Sheet BASE LIQUIDACION REDEBAN 2025
A1: Tipificación | B1: Implementaciones | C1: Incidentes – Ordenes de Cambio | D1: Fallida | G1: Tipificación | H1: Actividad sin cambio de datafono | J1: Actividad + adicional cambio de datafono | L1: Visita Fallida | N1: Incremento 2025
A2: TIPO I | B2: =71384.4052*(1+$N$2) -> 75096.394 | C2: =62699.6885*(1+$N$2) -> 65960.072 | D2: =35693.4343*(1+$N$2) -> 37549.493 | H2: Instalación Pinpad + HUB | I2: Segunda actividad en mismo comercio, misma visita | J2: Instalación Pinpad + HUB | K2: Segunda actividad en mismo comercio, misma visita | N2: 0.052
A3: TIPO II | B3: =155716.4408*(1+$N$2) -> 163813.7 | C3: =137802.16*(1+$N$2) -> 144967.87 | D3: =117879.8485*(1+$N$2) -> 124009.6 | G3: Tipo I | H3: =31819.23994686*(1+$N$2) -> 33473.84 | I3: =26222.67548178*(1+$N$2) -> 27586.255 | J3: =51196.46628516*(1+$N$2) -> 53858.683 | K3: =42157.66342524*(1+$N$2) -> 44349.862 | L3: =28948.10610808*(1+$N$2) -> 30453.408
A4: TIPO III | B4: =262099.6015*(1+$N$2) -> 275728.78 | C4: =262099.6015*(1+$N$2) -> 275728.78 | D4: =262099.6015*(1+$N$2) -> 275728.78 | G4: Tipo II | H4: =98014.03066668*(1+$N$2) -> 103110.76 | I4: =26222.67548178*(1+$N$2) -> 27586.255 | J4: =119562.49505524*(1+$N$2) -> 125779.74 | K4: =42157.66342524*(1+$N$2) -> 44349.862 | L4: =94765.6295813*(1+$N$2) -> 99693.442
A5: TIPO IV | B5: =479878.9419*(1+$N$2) -> 504832.65 | C5: =455882.9625*(1+$N$2) -> 479588.88 | D5: =370911.6746*(1+$N$2) -> 390199.08 | G5: Tipo III | H5: =189140.9827006*(1+$N$2) -> 198976.31 | I5: =26222.67548178*(1+$N$2) -> 27586.255 | J5: =200461.60194168*(1+$N$2) -> 210885.61 | K5: =42157.66342524*(1+$N$2) -> 44349.862 | L5: =171492.68108896*(1+$N$2) -> 180410.3
A6: Destino Aéreo | B6: =939603.5767*(1+$N$2) -> 988462.96 | C6: a partir del 5to servicio | G6: Tipo IV | H6: =461621.60109668*(1+$N$2) -> 485625.92 | I6: =26222.67548178*(1+$N$2) -> 27586.255 | J6: =461621.60109668*(1+$N$2) -> 485625.92 | K6: =42157.66342524*(1+$N$2) -> 44349.862 | L6: =461621.60109668*(1+$N$2) -> 485625.92
G7: * Tipo IV Especial Donde se requiera desplazamiento aéreo o fluvial será facturado el valor de la actividad y adicional el valor de $988.463 por cada 5 actividades de esta tipología
A8: Tarifas para día adicional de actividades:
A9: Tipificación | B9: Día adicional- menos de dos horas | C9: Medio día adicional | D9: Día adicional- más de 4 horas
A10: Tipo I | B10: =71384.4052*(1+$N$2) -> 75096.394 | C10: =133455.9267*(1+$N$2) -> 140395.63 | D10: =191225.1201*(1+$N$2) -> 201168.83 | G10: Actividad | H10: Unidad | I10: Valor Unitario
A11: Tipo II | B11: =133455.9267*(1+$N$2) -> 140395.63 | C11: =191225.1201*(1+$N$2) -> 201168.83 | D11: =257740.6152*(1+$N$2) -> 271143.13 | G11: Gestión telefónica y cierre de incidente de bloqueo | H11: Unidad | I11: =17639.19516086*(1+$N$2) -> 18556.433
A12: Tipo III | B12: =186821.7926*(1+$N$2) -> 196536.53 | C12: =248892.0824*(1+$N$2) -> 261834.47 | D12: =306662.5075*(1+$N$2) -> 322608.96 | G12: Servicio de cierre de incidente de bloqueo | H12: Unidad | I12: =4810.80785492*(1+$N$2) -> 5060.9699
A13: Tipo IV | B13: =186821.7926*(1+$N$2) -> 196536.53 | C13: =248892.0824*(1+$N$2) -> 261834.47 | D13: =306662.5075*(1+$N$2) -> 322608.96
A16: Servicio | B16: Tarifa actividad | D16: VALOR DE LA TERMINAL ADICIONAL | E16: VALOR DE INSTALACIÓN DE BASE EN "Y"
A17: Papelería – Tarifa única | B17: =34010.9321*(1+$N$2) -> 35779.501 | D17: =20537.3658*(1+$N$2) -> 21605.309 | E17: =10737.9606*(1+$N$2) -> 11296.335
A18: Papelería Tipo II - Visita técnica | B18: =64310*(1+$N$2) -> 67654.12
A19: Solución telefónica | B19: =39202.5476*(1+$N$2) -> 41241.08
A22: Traifas 2024
A23: Tipificación | B23: Implementaciones | C23: Incidentes – Ordenes de Cambio | D23: Fallida | G23: Tipificación | H23: Actividad sin cambio de datafono | J23: Actividad + adicional cambio de datafono | L23: Visita Fallida
A24: TIPO I | B24: 71384.405 | C24: 62699.688 | D24: 35693.434 | H24: Instalación Pinpad + HUB | I24: Segunda actividad en mismo comercio, misma visita | J24: Instalación Pinpad + HUB | K24: Segunda actividad en mismo comercio, misma visita
A25: TIPO II | B25: 155716.44 | C25: 137802.16 | D25: 117879.85 | G25: Tipo I | H25: 31819.24 | I25: 26222.675 | J25: 51196.466 | K25: 42157.663 | L25: 28948.106
A26: TIPO III | B26: 262099.6 | C26: 262099.6 | D26: 262099.6 | G26: Tipo II | H26: 98014.031 | I26: 26222.675 | J26: 119562.5 | K26: 42157.663 | L26: 94765.63
A27: TIPO IV | B27: 479878.94 | C27: 455882.96 | D27: 370911.67 | G27: Tipo III | H27: 189140.98 | I27: 26222.675 | J27: 200461.6 | K27: 42157.663 | L27: 171492.68
A28: Destino Aéreo | B28: 939603.58 | C28: a partir del 5to servicio | G28: Tipo IV | H28: 461621.6 | I28: 26222.675 | J28: 461621.6 | K28: 42157.663 | L28: 461621.6
G29: * Tipo IV Especial Donde se requiera desplazamiento aéreo o fluvial será facturado el valor de la actividad y adicional el valor de $939,604 por cada 5 actividades de esta tipología
A30: Tarifas para día adicional de actividades:
A31: Tipificación | B31: Día adicional- menos de dos horas | C31: Medio día adicional | D31: Día adicional- más de 4 horas
A32: Tipo I | B32: 71384.405 | C32: 133455.93 | D32: 191225.12 | G32: Actividad | H32: Unidad | I32: Valor Unitario
A33: Tipo II | B33: 133455.93 | C33: 191225.12 | D33: 257740.62 | G33: Gestión telefónica y cierre de incidente de bloqueo | H33: Unidad | I33: 17639.195
A34: Tipo III | B34: 186821.79 | C34: 248892.08 | D34: 306662.51 | G34: Servicio de cierre de incidente de bloqueo | H34: Unidad | I34: 4810.8079
A35: Tipo IV | B35: 186821.79 | C35: 248892.08 | D35: 306662.51
A38: Servicio | B38: Tarifa actividad | D38: VALOR DE LA TERMINAL ADICIONAL | E38: VALOR DE INSTALACIÓN DE BASE EN "Y"
A39: Papelería – Tarifa única | B39: 34010.932 | D39: 20537.366 | E39: 10737.961
A40: Papelería Tipo II - Visita técnica | B40: 64310
A41: Solución telefónica | B41: 39202.548

Sheet RESUMEN LIQUIDACION
B1: Fecha | C1: 45991
A3: FACTURACIÓN ACTIVIDADES REDEBAN CB BANCOLOMBIA Y AVAL
A4: =UPPER("01" & " al " & TEXT(DAY(EOMONTH(C1,0)),"00") & " de " & TEXT(C1,"MMMM") & " de " & YEAR(C1)) -> 01 AL 30 DE NOVIEMBRE DE 2025
A6: CONCEPTOS | B6: CANTIDAD | C6: TOTAL
A7: Aperturas Bancolombia | B7: =IFERROR(COUNTA(APERTURAS_BANCOLOMBIA!A:A)-1,0) -> 134 | C7: =IFERROR(SUM(APERTURAS_BANCOLOMBIA!$AC$2:$AC$1048576),0) -> 21293919
A8: Incidentes Bancolombia | B8: =IFERROR(COUNTA(INCIDENTES_BANCOLOMBIA!A:A)-1,0) -> 878 | C8: =IFERROR(SUM(INCIDENTES_BANCOLOMBIA!$AF$2:$AF$1048576),0) -> 139839906
A9: Gestión de Campo Bancolombia | B9: =IFERROR(COUNTA(OC_BANCOLOMBIA!A:A)-1,0) -> 305 | C9: =IFERROR(SUM(OC_BANCOLOMBIA!$AF$2:$AF$1048576),0) -> 50610118
A10: Soporte Papelería Bancolombia | B10: =IFERROR(COUNTA(PAPELERIA!A:A)-1,0) -> 1252 | C10: =IFERROR(SUM(PAPELERIA!$AE$2:$AE$1048576),0) -> 53508554
A11: Aperturas Aval | B11: =IFERROR(COUNTA(APERTURAS_AVAL!A:A)-1,0) -> 146 | C11: =IFERROR(SUM(APERTURAS_AVAL!$AB$2:$AB$1048576),0) -> 27825072
A12: Incidentes Aval | B12: =IFERROR(COUNTA(INCIDENTES_AVAL!A:A)-1,0) -> 275 | C12: =IFERROR(SUM(INCIDENTES_AVAL!$AD$2:$AD$1048576),0) -> 33653822
A13: Gestión de Campo Aval | B13: =IFERROR(COUNTA(OC_AVAL!A:A)-1,0) -> 78 | C13: =IFERROR(SUM(OC_AVAL!$AF$2:$AF$1048576),0) -> 13701474
A14: Aperturas BBVA | B14: 0 | C14: =IFERROR(SUM([1]APERTURAS_BBVA!$AC$2:$AC$1048576),0) -> 0
A15: Gestión de Campo BBVA | B15: 0 | C15: =IFERROR(SUM([2]OC_BBVA!$AC$2:$AC$1048576),0) -> 0
A16: Incidentes BBVA | B16: =IFERROR(COUNTA(INCIDENTES_BBVA!A:A)-1,0) -> 2 | C16: =IFERROR(SUM(INCIDENTES_BBVA!$AB$2:$AB$1048576),0) -> 289936
A17: SUBTOTAL | C17: =SUM(C7:C16) -> 340722801
A18: Iva | C18: =C17*0.19 -> 64737332
A19: TOTAL | C19: =SUM(C17:C18) -> 4.0546013e+08

Sheet Hoja1
A2: aperturas bancol
A3: Etiquetas de fila | B3: Suma de VALOR TOTAL
A4: COSTA | B4: 2932879 | C4: cc | D4: valor
A5: 0004-0001 | B5: 2932879 | C5: =A5 -> 0004-0001 | D5: =B5 -> 2932879 | H5: Etiquetas de fila | I5: Suma de valor
A6: CUNDINAMARCA | B6: 1126440 | G6: costa | H6: 0004-0001 | I6: 54167362
A7: 0004-0004 | B7: 1126440 | C7: =A7 -> 0004-0004 | D7: =B7 -> 1126440 | G7: eje | H7: 0004-0002 | I7: 11543914
A8: NOROCCIDENTE | B8: 4230581 | G8: sur | H8: 0004-0003 | I8: 51231053
A9: 0004-0005 | B9: 4230581 | C9: =A9 -> 0004-0005 | D9: =B9 -> 4230581 | G9: centro | H9: 0004-0004 | I9: 38277806
A10: REMOTAS | B10: 1152226 | G10: noroccidente | H10: 0004-0005 | I10: 82920705
A11: 0004-0007 | B11: 1152226 | C11: =A11 -> 0004-0007 | D11: =B11 -> 1152226 | G11: oriente | H11: 0004-0007 | I11: 42377442
A12: SANTANDERES | B12: 5067578 | G12: santanderes | H12: 0004-0008 | I12: 60204519
A13: 0004-0008 | B13: 5067578 | C13: =A13 -> 0004-0008 | D13: =B13 -> 5067578 | H13: Total general | I13: 340722801
A14: SUROCCIDENTE Y EJE CAFETERO | B14: 6784215
A15: 0004-0002 | B15: 464198 | C15: =A15 -> 0004-0002 | D15: =B15 -> 464198
A16: 0004-0003 | B16: 6320017 | C16: =A16 -> 0004-0003 | D16: =B16 -> 6320017
A17: Total general | B17: 21293919
A19: incidentes bancol
A20: Etiquetas de fila | B20: Suma de VALOR TOTAL
A21: COSTA | B21: 25995256
A22: 0004-0001 | B22: 25995256 | C22: =A22 -> 0004-0001 | D22: =B22 -> 25995256
A23: CUNDINAMARCA | B23: 10394203
A24: 0004-0004 | B24: 10394203 | C24: =A24 -> 0004-0004 | D24: =B24 -> 10394203
A25: NOROCCIDENTE | B25: 40490024
A26: 0004-0005 | B26: 40490024 | C26: =A26 -> 0004-0005 | D26: =B26 -> 40490024
A27: REMOTAS | B27: 15077936
A28: 0004-0007 | B28: 15077936 | C28: =A28 -> 0004-0007 | D28: =B28 -> 15077936
A29: SANTANDERES | B29: 19749698
A30: 0004-0008 | B30: 19749698 | C30: =A30 -> 0004-0008 | D30: =B30 -> 19749698
A31: SUROCCIDENTE Y EJE CAFETERO | B31: 28132789
A32: 0004-0002 | B32: 4963142 | C32: =A32 -> 0004-0002 | D32: =B32 -> 4963142
A33: 0004-0003 | B33: 23169647 | C33: =A33 -> 0004-0003 | D33: =B33 -> 23169647
A34: Total general | B34: 139839906
A37: oc bancol
A38: Etiquetas de fila | B38: Suma de VALOR TOTAL
A39: COSTA | B39: 6529016
A40: 0004-0001 | B40: 6529016 | C40: =A40 -> 0004-0001 | D40: =B40 -> 6529016
A41: CUNDINAMARCA | B41: 5550587
A42: 0004-0004 | B42: 5550587 | C42: =A42 -> 0004-0004 | D42: =B42 -> 5550587
A43: NOROCCIDENTE | B43: 11903874
A44: 0004-0005 | B44: 11903874 | C44: =A44 -> 0004-0005 | D44: =B44 -> 11903874
A45: REMOTAS | B45: 8398737
A46: 0004-0007 | B46: 8398737 | C46: =A46 -> 0004-0007 | D46: =B46 -> 8398737
A47: SANTANDERES | B47: 10983949
A48: 0004-0008 | B48: 10983949 | C48: =A48 -> 0004-0008 | D48: =B48 -> 10983949
A49: SUROCCIDENTE Y EJE CAFETERO | B49: 7243955
A50: 0004-0002 | B50: 2074957 | C50: =A50 -> 0004-0002 | D50: =B50 -> 2074957
A51: 0004-0003 | B51: 5168998 | C51: =A51 -> 0004-0003 | D51: =B51 -> 5168998
A52: Total general | B52: 50610118
A56: papeleria
A57: Etiquetas de fila | B57: Suma de VALOR TOTAL
A58: COSTA | B58: 10707267
A59: 0004-0001 | B59: 10707267 | C59: =A59 -> 0004-0001 | D59: =B59 -> 10707267
A60: CUNDINAMARCA | B60: 7735193
A61: 0004-0004 | B61: 7735193 | C61: =A61 -> 0004-0004 | D61: =B61 -> 7735193
A62: NOROCCIDENTE | B62: 14711347
A63: 0004-0005 | B63: 14711347 | C63: =A63 -> 0004-0005 | D63: =B63 -> 14711347
A64: REMOTAS | B64: 3922357
A65: 0004-0007 | B65: 3922357 | C65: =A65 -> 0004-0007 | D65: =B65 -> 3922357
A66: SANTANDERES | B66: 7496148
A67: 0004-0008 | B67: 7496148 | C67: =A67 -> 0004-0008 | D67: =B67 -> 7496148
A68: SUROCCIDENTE Y EJE CAFETERO | B68: 8936242
A69: 0004-0002 | B69: 1903053 | C69: =A69 -> 0004-0002 | D69: =B69 -> 1903053
A70: 0004-0003 | B70: 7033189 | C70: =A70 -> 0004-0003 | D70: =B70 -> 7033189
A71: Total general | B71: 53508554
A74: apertura aval
A75: Etiquetas de fila | B75: Suma de VALOR FACTURABLE A LA RED
A76: COSTA | B76: 3527888
A77: 0004-0001 | B77: 3527888 | C77: =A77 -> 0004-0001 | D77: =B77 -> 3527888
A78: CUNDINAMARCA | B78: 5331139
A79: 0004-0004 | B79: 5331139 | C79: =A79 -> 0004-0004 | D79: =B79 -> 5331139
A80: NOROCCIDENTE | B80: 4298867
A81: 0004-0005 | B81: 4298867 | C81: =A81 -> 0004-0005 | D81: =B81 -> 4298867
A82: REMOTAS | B82: 3437712
A83: 0004-0007 | B83: 3437712 | C83: =A83 -> 0004-0007 | D83: =B83 -> 3437712
A84: SANTANDERES | B84: 7063760
A85: 0004-0008 | B85: 7063760 | C85: =A85 -> 0004-0008 | D85: =B85 -> 7063760
A86: SUROCCIDENTE Y EJE CAFETERO | B86: 4165706
A87: 0004-0002 | B87: 566538 | C87: =A87 -> 0004-0002 | D87: =B87 -> 566538
A88: 0004-0003 | B88: 3599168 | C88: =A88 -> 0004-0003 | D88: =B88 -> 3599168
A89: Total general | B89: 27825072
A91: incidente aval
A92: Etiquetas de fila | B92: Suma de VALOR FACTURABLE A LA RED
A93: BOGOTA | B93: 263840
A94: 0004-0004 | B94: 263840 | C94: =A94 -> 0004-0004 | D94: =B94 -> 263840
A95: COSTA | B95: 2153872
A96: 0004-0001 | B96: 2153872 | C96: =A96 -> 0004-0001 | D96: =B96 -> 2153872
A97: CUNDINAMARCA | B97: 5807427
A98: 0004-0004 | B98: 5807427 | C98: =A98 -> 0004-0004 | D98: =B98 -> 5807427
A99: NOROCCIDENTE | B99: 4457499
A100: 0004-0005 | B100: 4457499 | C100: =A100 -> 0004-0005 | D100: =B100 -> 4457499
A101: REMOTAS | B101: 8026116
A102: 0004-0007 | B102: 8026116 | C102: =A102 -> 0004-0007 | D102: =B102 -> 8026116
A103: SANTANDERES | B103: 7600051
A104: 0004-0008 | B104: 7600051 | C104: =A104 -> 0004-0008 | D104: =B104 -> 7600051
A105: SUROCCIDENTE Y EJE CAFETERO | B105: 5345017
A106: 0004-0002 | B106: 1150170 | C106: =A106 -> 0004-0002 | D106: =B106 -> 1150170
A107: 0004-0003 | B107: 4194847 | C107: =A107 -> 0004-0003 | D107: =B107 -> 4194847
A108: (en blanco)
A109: (en blanco)
A110: Total general | B110: 33653822
...

Sheet APERTURAS_BANCOLOMBIA
A1: CIUDAD SEDE | B1: ZONA | C1: CENTRO DE COSTOS LINEACOM | D1: CODIGO DANE | E1: TA/CODIGO ACTIVIDAD | F1: CODIGO CB | G1: ACTIVIDAD | H1: TIPO DE APERTURA | I1: DEPARTAMENTO | J1: CIUDAD | K1: NOMBRE DEL CB | L1: RED | M1: FO | N1: FECHA LISTA | O1: FECHA ULTIMA ACTUALIZACION | P1: FORMATO | Q1: CADENA | R1: ESTADO | S1: OBSERVACIONES CLIENTE | T1: FORMA DE ATENCION | U1: TERMINAL(ES) | V1: TIPIFICACION | W1: TIPO DE TRAYECTO | X1: NOMBRE DEL TECNICO | Y1: DIAS DE VISITA | Z1: DIA ADICIONAL | AA1: VALOR DIAS ACTIVIDAD FACTURABLES | AB1: VALOR DIAS ACOMPAÑAMIENTO FACTURABLES | AC1: VALOR TOTAL
A2: PASTO | B2: SUROCCIDENTE Y EJE CAFETERO | C2: 0004-0003 | D2: 52399 | E2: TA-25-1247989 | F2: 3007082042 | G2: APERTURA | H2: CB CRECIMIENTO ALIANZA - NUEVO | I2: NARIÑO | J2: LA UNION | K2: DISTRICOL DISTRI SALSAS LOPEZ | L2: REDEBAN | M2: FO-25-1751786 | N2: 45959.86 | O2: 45965.71 | P2: AGREGADOR | Q2: DISTRICOL | R2: EJECUTADO | S2: 29/10/2025 29-10 PROGRAMACIÓN REALIZADA POR LA ALIANZA| INSTALACIÓN PROGRAMADA PARA EL 2025-11-03 | 05/11/2025 SE REALIZA INSTALACIÓN DE CORRESPONSAL BANCARIO SE INSTALA VERSION SE CONFIGURA PARÁMETROS SE INICIALIZA SE REALIZA INSTALACIÓN DE PUBLICIDAD SE DICTA CAPACITACIÓN PRUEBAS DE FUNCIONAMIENTO EXITOSAS CB QUEDA OPERATIVO | T2: VISITA TECNICA | U2: CA002301 | V2: TIPO III | W2: TERRESTRE | X2: BRAVO MADROÑERO OSCAR ESTEBAN | Y2: 1 | Z2: 0 | AA2: 275729 | AB2: 196537 | AC2: 275729
A3: PASTO | B3: SUROCCIDENTE Y EJE CAFETERO | C3: 0004-0003 | D3: 52399 | E3: TA-25-1247990 | F3: 3007082043 | G3: APERTURA | H3: CB CRECIMIENTO ALIANZA - NUEVO | I3: NARIÑO | J3: LA UNION | K3: DISTRICOL PAP Y MIS DEL PARQUE | L3: REDEBAN | M3: FO-25-1751788 | N3: 45959.861 | O3: 45966.826 | P3: AGREGADOR | Q3: DISTRICOL | R3: EJECUTADO | S3: 29/10/2025 29-10 PROGRAMACIÓN REALIZADA POR LA ALIANZA| INSTALACIÓN PROGRAMADA PARA EL 2025-11-03 | 04/11/2025 SE ESTABLECE COMUNICACIÓN CON CLIENTE SE LE INFORMA QUE POR NOVEDAD EN LA VÍA NO FUE POSIBLE REALIZAR INSTALACIÓN EL DÍA DE HOY SE PROGRAMA VISITA PARA EL DÍA DE MAÑANA 05/11 | 05/11/2025 SE LLEGA A CORRESPONSAL A REALIZAR INSTALACIÓN DE CORRESPONSAL BANCARIO SE INICIA CONFIGURACIÓN DE DATAFONO SE VERIFICA QUE PLACA NO CONCUERDA CON TERMINAL Y NOMBRE DE CB SE ESCALA A RBM REALIZAN ACTUALIZACIÓN DE TERMINAL SE CONFIGURA PARÁMETROS SE INICIALIZA SE REALIZA INSTALACIÓN DE PUBLICIDAD SE DICTA CAPACITACIÓN PRUEBAS DE FUNCIONAMIENTO EXITOSAS CB QUEDA OPERATIVO | T3: VISITA TECNICA | U3: CA002302 | V3: TIPO III | W3: TERRESTRE | X3: BRAVO MADROÑERO OSCAR ESTEBAN | Y3: 1 | Z3: 0 | AA3: 275729 | AB3: 196537 | AC3: 275729
A4: BUCARAMANGA | B4: SANTANDERES | C4: 0004-0008 | D4: 81736 | E4: TA-25-1248004 | F4: 3007082067 | G4: APERTURA | H4: CB CRECIMIENTO ALIANZA - NUEVO | I4: ARAUCA | J4: SARAVENA | K4: DISTRICOL SOLUCIONES EMPRESARI | L4: REDEBAN | M4: FO-25-1751834 | N4: 45959.71 | O4: 45965.713 | P4: AGREGADOR | Q4: DISTRICOL | R4: EJECUTADO | S4: 29/10/2025 29-10 PROGRAMACIÓN REALIZADA POR LA ALIANZA| INSTALACIÓN PROGRAMADA PARA EL 2025-11-06 | 31/10/2025 EN COMUNICACIÓN CON EL SEÑOR FIDEL AL MOVIL 3162733574, EN COMUNICACIÓN CON EL SEÑOR FIDEL AL MOVIL 3162733574, NO SE LE INFORMA QUE ESTAMOS A LA ESPERA DE LA DISPONIBILIDAD DEL VUELO, QUÉ ESTARÍAMOS VISITANDOLO PARA REALIZAR LA INSTALACIÓN DESPUÉS DEL MARTES 4 DE NOVIEMBRE | 04/11/2025 EN COMUNICACIÓN CON EL SEÑOR FIDEL AL MOVIL 3162733574, SE CONFIRMA CANAL A DE DATOS Y SERVICIO ELECTRICO OK, SE VALIDA DISPONIBILIDAD DE ATENCIÓN PARA EL DÍA DE HOY 4 DE NOVIEMBRE | 04/11/2025 INSTALACIÓN DE CB BANCOLOMBIA, INSTALACION DE DATAFONO LECTORA FUENTE CABLE PACTHCORD Y BASE FUENTE Y CUBRE CLAVE, SE CAPACITA SOBRE LA WEB SOMOS BANCOLOMBIA, SE CAPACITA SOBRE RETIROS DEPÓSITOS RECUADOS TRASFERENCIAS SALDO Y SE EXPLICA SOBRE CIERRE Y CUADRE DIARIO. | T4: VISITA TECNICA | U4: CA002315 | V4: TIPO V | W4: AEREO | X4: SANTOS GONZALEZ JOHAN FABIAN | Y4: 1 | Z4: 0 | AA4: 988463 | AB4: 196537 | AC4: 988463
A5: PASTO | B5: SUROCCIDENTE Y EJE CAFETERO | C5: 0004-0003 | D5: 86320 | E5: TA-25-1248007 | F5: 3007082049 | G5: APERTURA | H5: CB CRECIMIENTO ALIANZA - NUEVO | I5: PUTUMAYO | J5: ORITO | K5: DISTRICOL ATLANTHA CJ | L5: REDEBAN | M5: FO-25-1751838 | N5: 45959.876 | O5: 45966.828 | P5: AGREGADOR | Q5: DISTRICOL | R5: EJECUTADO | S5: 29/10/2025 29-10 PROGRAMACIÓN REALIZADA POR LA ALIANZA| INSTALACIÓN PROGRAMADA PARA EL 2025-10-31 | 31/10/2025 NO ES POSIBLE VIAJAR EL DIA DE HOY HACIA EL DEPARTAMENTO DEL PUTUMAYO POR PROBLEMAS DE TRANSPORTE SE REALIZARA DESPLAZAMIENTO AL DIA MARTES . | 05/11/2025 SE VISITA EL COMERCIO PARA DAR APERTURA AL CB, SE INSTALA DATÁFONO CON MAGIC BOX, BASE, LECTORA, SE INSTALA PUBLICIDAD, SE DEJA ROLLOS, SE HACE PRUEBAS EXCEPTO DE RECAUDO POR NO TENER RECURSOS PARA HACERLO, SE CAPACITA OK, SOMOS BANCOLOMBIA OK CB OPERATIVO | T5: VISITA TECNICA | U5: CA002316 | V5: TIPO IV | W5: TERRESTRE | X5: GUERRERO RAMIREZ OSCAR DARIO | Y5: 1 | Z5: 0 | AA5: 504833 | AB5: 196537 | AC5: 504833
A6: MEDELLIN | B6: NOROCCIDENTE | C6: 0004-0005 | D6: 5001 | E6: TA-25-1253196 | F6: 3007082082 | G6: APERTURA | H6: CB CRECIMIENTO ALIANZA - NUEVO | I6: ANTIOQUIA | J6: MEDELLIN | K6: OPRAP MALL LA FRONTERA | L6: REDEBAN | M6: FO-25-1762877 | N6: 45961.726 | O6: 45971.701 | P6: ROBUSTO | Q6: OPRAP | R6: EJECUTADO | S6: 31/10/2025 31-10 SE REALIZA LLAMADA AL CLIENTE, SE HABLA CON EL SR WILLIAM CABRERA SE VALIDA DIRECCIÓN OK, CANAL OK, DISPONIBILIDAD TOTAL, SOLICITA PROGRAMAR VISITA EL 10-11-2025 POR QUE ESE DÍA COMIENZA A OPERAR EL PUNTO - COMUNICACIÓN POR WPP | 10/11/2025 SE REALIZA INSTALACIÓN DE CB ROBUSTO OK PRUEBAS OK NO SE CAPACITACIÓN CB ROBUSTO PUBLICIDAD INTERNA OK NO TELECARGA CUBRE CLAVE OK | T6: VISITA TECNICA | U6: CA003547 | V6: TIPO I | W6: TERRESTRE | X6: PAREJA ECHAVARRIA JHON DAVID | Y6: 1 | Z6: 0 | AA6: 75096 | AB6: 75096 | AC6: 75096
A7: BOGOTA | B7: CUNDINAMARCA | C7: 0004-0004 | D7: 11001 | E7: TA-25-1253197 | F7: 3007082080 | G7: APERTURA | H7: CB CRECIMIENTO ALIANZA - NUEVO | I7: CUNDINAMARCA | J7: BOGOTA | K7: OPRAP PLAZA DE LAS AMÉRICAS II | L7: REDEBAN | M7: FO-25-1762880 | N7: 45961.831 | O7: 45965.799 | P7: ROBUSTO | Q7: OPRAP | R7: EJECUTADO | S7: 31/10/2025 31-10 SE REALIZA LLAMADA AL CLIENTE, SE HABLA CON EL SR WILLIAM CABRERA SE VALIDA DIRECCIÓN OK, CANAL OK, DISPONIBILIDAD TOTAL | SOLICITA PROGRAMAR LA VISITA PARA LAS 4 PM EL 4-11-2025 - COMUNICACIÓN POR WPP | 05/11/2025 INSTALACIÓN DE CORRESPONSAL BANCARIO ROBUSTO OPRAP. EN EL CENTRO COMERCIAL PLAZA LAS AMÉRICAS SE REALIZA INSTALACIÓN DE SEIS CAJAS PRUEBAS CON CLIENTE A CADA UNA DE ELLAS CONFIGURACIÓN ACTIVACIÓN DE SERVICIOS NO SE INSTALA PUBLICIDAD YA QUE ES UN ROBUSTO NI SE DA CAPACITACIÓN AL CLIENTE | T7: VISITA TECNICA | U7: CA003641 | V7: TIPO I | W7: TERRESTRE | X7: GOMEZ VEGA DAVID SNEYDER | Y7: 1 | Z7: 0 | AA7: 75096 | AB7: 75096 | AC7: 75096
A8: MEDELLIN | B8: NOROCCIDENTE | C8: 0004-0005 | D8: 5001 | E8: TA-25-1270687 | F8: 3007082151 | G8: APERTURA | H8: CB CRECIMIENTO ALIANZA - NUEVO | I8: ANTIOQUIA | J8: MEDELLIN | K8: DISTRICOL LA ABUNDANCIA SHALOM | L8: REDEBAN | M8: FO-25-1790280 | N8: 45968.333 | O8: 45968.644 | R8: EJECUTADO | S8: 06/11/2025 06-11 PROGRAMACION REALIZADA POR LA ALIANZA| INSTALACIÓN PROGRAMADA PARA EL 2025-11-07 | 07/11/2025 SE INSTALA EQUIPO, SE REALIZA CAPACITACIÓN SE INSTALA PUBLICIDAD SE REALIZAN PRUEBAS EXITOSAS SERVICIO OPERATIVO OK | T8: VISITA TECNICA | U8: DA000378 | V8: TIPO I | W8: TERRESTRE | X8: ZAPATA LOPEZ EDWARD ASDRUBAL | Y8: 1 | Z8: 0 | AA8: 75096 | AB8: 75096 | AC8: 75096
A9: MEDELLIN | B9: NOROCCIDENTE | C9: 0004-0005 | D9: 5001 | E9: TA-25-1270688 | F9: 3007082152 | G9: APERTURA | H9: CB CRECIMIENTO ALIANZA - NUEVO | I9: ANTIOQUIA | J9: MEDELLIN | K9: DISTRICOL MERCOFERTAS | L9: REDEBAN | M9: FO-25-1790283 | N9: 45968.333 | O9: 45971.506 | R9: EJECUTADO | S9: 06/11/2025 06-11 PROGRAMACION REALIZADA POR LA ALIANZA| INSTALACIÓN PROGRAMADA PARA EL 2025-11-08 | 07/11/2025 INSTALACIÓN SE REPROGRAMA PARA DÍA LUNES 10 POR PREVENCIÓN DE NOVEDADES QUE SE PUEDAN PRESENTAR DÍA SÁBADO. SE INFORMÓ A USUARIO Y CON SU APROBACIÓN SE ACUERDA VISITA DÍA LUNES. | 11/11/2025 SE INSTALA PUBLICIDAD Y EQUIPOS A PETICIÓN DEL USUARIO, SE DEJAN SERVICIOS FUNCIONANDO CORRECTAMENTE, CAPACITACIÓN OK. | T9: VISITA TECNICA | U9: DA000379 | V9: TIPO I | W9: TERRESTRE | X9: BARRIENTOS HERNANDEZ CRISTIAN HORACIO | Y9: 1 | Z9: 0 | AA9: 75096 | AB9: 75096 | AC9: 75096
A10: MEDELLIN | B10: NOROCCIDENTE | C10: 0004-0005 | D10: 5001 | E10: TA-25-1270689 | F10: 3007082153 | G10: APERTURA | H10: CB CRECIMIENTO ALIANZA - NUEVO | I10: ANTIOQUIA | J10: MEDELLIN | K10: PTM MEDELLIN THE ALBANS | L10: REDEBAN | M10: FO-25-1790289 | N10: 45968.333 | O10: 45971.638 | R10: EJECUTADO | S10: 06/11/2025 06-11 PROGRAMACION REALIZADA POR LA ALIANZA| INSTALACIÓN PROGRAMADA PARA EL 2025-11-08 | 07/11/2025 INSTALACIÓN SE REPROGRAMA PARA DÍA LUNES 10 POR PREVENCIÓN DE NOVEDADES QUE SE PUEDAN PRESENTAR DÍA SÁBADO. SE INFORMÓ A USUARIO Y CON SU APROBACIÓN SE ACUERDA VISITA DÍA LUNES. | 11/11/2025 SE INSTALA PUBLICIDAD Y EQUIPOS A PETICIÓN DEL USUARIO, SE DEJAN SERVICIOS FUNCIONANDO CORRECTAMENTE | T10: VISITA TECNICA | U10: DA000380-DA000313 | V10: TIPO I | W10: TERRESTRE | X10: BARRIENTOS HERNANDEZ CRISTIAN HORACIO | Y10: 1 | Z10: 0 | AA10: 75096 | AB10: 75096 | AC10: 75096
A11: MEDELLIN | B11: NOROCCIDENTE | C11: 0004-0005 | D11: 5001 | E11: TA-25-1270690 | F11: 3007082154 | G11: APERTURA | H11: CB CRECIMIENTO ALIANZA - NUEVO | I11: ANTIOQUIA | J11: MEDELLIN | K11: PTM MEDELLIN DISTRIBUIDORA A&M | L11: REDEBAN | M11: FO-25-1790295 | N11: 45968.333 | O11: 45971.749 | R11: EJECUTADO | S11: 06/11/2025 06-11 PROGRAMACION REALIZADA POR LA ALIANZA| INSTALACIÓN PROGRAMADA PARA EL 2025-11-08 | 07/11/2025 INSTALACIÓN SE REPROGRAMA PARA DÍA LUNES 10 POR PREVENCIÓN DE NOVEDADES QUE SE PUEDAN PRESENTAR DÍA SÁBADO. SE INFORMÓ A USUARIO Y CON SU APROBACIÓN SE ACUERDA VISITA DÍA LUNES. | 10/11/2025 SE REALIZÓ VISITA TÉCNICA PARA LA INSTALACIÓN DEL CORRESPONSAL BANCOLOMBIA. EL USUARIO CONFIRMÓ SU IDENTIFICACIÓN Y SE VALIDARON LAS CONDICIONES DEL LUGAR, VERIFICANDO QUE CUMPLIERA CON LOS REQUISITOS NECESARIOS PARA LA INSTALACIÓN. UNA VEZ APROBADO EL ESPACIO, SE PROCEDIÓ CON LA INSTALACIÓN DE LOS EQUIPOS CORRESPONDIENTES. SE REALIZARON PRUEBAS FUNCIONALES, TODAS CON RESULTADOS EXITOSOS, GARANTIZANDO EL CORRECTO DESEMPEÑO DE LOS DISPOSITIVOS. POSTERIORMENTE, SE BRINDÓ CAPACITACIÓN AL USUARIO SOBRE EL USO DE LA PLATAFORMA SOMOS BANCOLOMBIA, INCLUYENDO EL MANEJO DE LOS EQUIPOS Y LA EJECUCIÓN DE TRANSACCIONES. TAMBIÉN SE INSTALARON LOS AVISOS INFORMATIVOS SEGÚN LAS INDICACIONES DEL CLIENTE. FINALIZADA LA INTERVENCIÓN, EL PUNTO QUEDÓ COMPLETAMENTE OPERATIVO Y LISTO PARA INICIAR ACTIVIDADES. | T11: VISITA TECNICA | U11: DA000381- DA000314 | V11: TIPO I | W11: TERRESTRE | X11: MARTINEZ TOVAR OSCAR DAVID | Y11: 1 | Z11: 0 | AA11: 75096 | AB11: 75096 | AC11: 75096
A12: MEDELLIN | B12: NOROCCIDENTE | C12: 0004-0005 | D12: 5001 | E12: TA-25-1270692 | F12: 3007082155 | G12: APERTURA | H12: CB CRECIMIENTO ALIANZA - NUEVO | I12: ANTIOQUIA | J12: MEDELLIN | K12: PTM MEDELLIN TU CYBER ESPACIO | L12: REDEBAN | M12: FO-25-1790300 | N12: 45968.333 | O12: 45971.551 | R12: EJECUTADO | S12: 06/11/2025 06-11 PROGRAMACION REALIZADA POR LA ALIANZA| INSTALACIÓN PROGRAMADA PARA EL 2025-11-08 | 10/11/2025 INSTALACIÓN SE REPROGRAMA PARA DÍA LUNES 10 POR PREVENCIÓN DE NOVEDADES QUE SE PUEDAN PRESENTAR DÍA SÁBADO. SE INFORMÓ A USUARIO Y CON SU APROBACIÓN SE ACUERDA VISITA DÍA LUNES. | 10/11/2025 SE REALIZÓ VISITA TÉCNICA PARA LA INSTALACIÓN DEL CORRESPONSAL BANCOLOMBIA. EL USUARIO CONFIRMÓ SU IDENTIFICACIÓN Y SE VALIDARON LAS CONDICIONES DEL LUGAR, VERIFICANDO QUE CUMPLIERA CON LOS REQUISITOS NECESARIOS PARA LA INSTALACIÓN. UNA VEZ APROBADO EL ESPACIO, SE PROCEDIÓ CON LA INSTALACIÓN DE LOS EQUIPOS CORRESPONDIENTES. SE REALIZARON PRUEBAS FUNCIONALES, TODAS CON RESULTADOS EXITOSOS, GARANTIZANDO EL CORRECTO DESEMPEÑO DE LOS DISPOSITIVOS. POSTERIORMENTE, SE BRINDÓ CAPACITACIÓN AL USUARIO SOBRE EL USO DE LA PLATAFORMA SOMOS BANCOLOMBIA, INCLUYENDO EL MANEJO DE LOS EQUIPOS Y LA EJECUCIÓN DE TRANSACCIONES. TAMBIÉN SE INSTALARON LOS AVISOS INFORMATIVOS SEGÚN LAS INDICACIONES DEL CLIENTE. FINALIZADA LA INTERVENCIÓN, EL PUNTO QUEDÓ COMPLETAMENTE OPERATIVO Y LISTO PARA INICIAR ACTIVIDADES. | T12: VISITA TECNICA | U12: DA000382- DA000315 | V12: TIPO I | W12: TERRESTRE | X12: MARTINEZ TOVAR OSCAR DAVID | Y12: 1 | Z12: 0 | AA12: 75096 | AB12: 75096 | AC12: 75096
A13: MEDELLIN | B13: NOROCCIDENTE | C13: 0004-0005 | D13: 5088 | E13: TA-25-1270694 | F13: 3007082149 | G13: APERTURA | H13: CB CRECIMIENTO ALIANZA - NUEVO | I13: ANTIOQUIA | J13: BELLO | K13: DISTRICOL ENTRECERRO | L13: REDEBAN | M13: FO-25-1790303 | N13: 45968.333 | O13: 45968.671 | R13: EJECUTADO | S13: 06/11/2025 06-11 PROGRAMACION REALIZADA POR LA ALIANZA| INSTALACIÓN PROGRAMADA PARA EL 2025-11-07 | 11/11/2025 SE INSTALA PUBLICIDAD Y EQUIPOS A PETICIÓN DEL USUARIO, SE DEJAN SERVICIOS FUNCIONANDO CORRECTAMENTE Y CAPACITACIÓN OK | T13: VISITA TECNICA | U13: DA000383 | V13: TIPO I | W13: TERRESTRE | X13: BARRIENTOS HERNANDEZ CRISTIAN HORACIO | Y13: 1 | Z13: 0 | AA13: 75096 | AB13: 75096 | AC13: 75096
A14: MEDELLIN | B14: NOROCCIDENTE | C14: 0004-0005 | D14: 5212 | E14: TA-25-1270696 | F14: 3007082126 | G14: APERTURA | H14: CB CRECIMIENTO ALIANZA - NUEVO | I14: ANTIOQUIA | J14: COPACABANA | K14: DISTRICOL LIDER | L14: REDEBAN | M14: FO-25-1790312 | N14: 45968.333 | O14: 45968.56 | R14: EJECUTADO | S14: 06/11/2025 06-11 PROGRAMACION REALIZADA POR LA ALIANZA| INSTALACIÓN PROGRAMADA PARA EL 2025-11-07 | 07/11/2025 SE INSTALA PUBLICIDAD Y EQUIPOS A PETICIÓN DEL USUARIO, SERVICIOS FUNCIONANDO CORRECTAMENTE Y CAPACITACIÓN OK | T14: VISITA TECNICA | U14: DA000384 | V14: TIPO I | W14: TERRESTRE | X14: BARRIENTOS HERNANDEZ CRISTIAN HORACIO | Y14: 1 | Z14: 0 | AA14: 75096 | AB14: 75096 | AC14: 75096
A15: MEDELLIN | B15: NOROCCIDENTE | C15: 0004-0005 | D15: 5318 | E15: TA-25-1270697 | F15: 3007082150 | G15: APERTURA | H15: CB CRECIMIENTO ALIANZA - NUEVO | I15: ANTIOQUIA | J15: GUARNE | K15: DISTRICOL TECNOVA GUARNE | L15: REDEBAN | M15: FO-25-1790317 | N15: 45968.333 | O15: 45968.624 | R15: EJECUTADO | S15: 06/11/2025 06-11 PROGRAMACION REALIZADA POR LA ALIANZA| INSTALACIÓN PROGRAMADA PARA EL 2025-11-07 | 07/11/2025 SE HACE IMPLEMENTACION OK EQUIPOS OPERATIVOS PRUEBAS EXITOSAS SOMOS BANCOLOMBIA INACTIVO | T15: VISITA TECNICA | U15: DA00385 | V15: TIPO II | W15: TERRESTRE | X15: DIAZ ZABALA FRANCIS DUBAN | Y15: 1 | Z15: 0 | AA15: 163814 | AB15: 140396 | AC15: 163814
A16: BUCARAMANGA | B16: SANTANDERES | C16: 0004-0008 | D16: 13670 | E16: TA-25-1270698 | F16: 3007082141 | G16: APERTURA | H16: CB CRECIMIENTO ALIANZA - NUEVO | I16: BOLIVAR | J16: SAN PABLO | K16: DISTRICOL PAPELERIA MARIETH | L16: REDEBAN | M16: FO-25-1790322 | N16: 45968.333 | O16: 45971.733 | R16: EJECUTADO | S16: 06/11/2025 06-11 PROGRAMACION REALIZADA POR LA ALIANZA| INSTALACIÓN PROGRAMADA PARA EL 2025-11-10 | 10/11/2025 SE REALIZA APERTURA CB BANCOLOMBIA PURO, SE INSTALA AVISO EXTERIOR, FLANGED, DISPLAY, BASE, DATÁFONO, LECTOR DE BARRAS,CUBRE CLAVES, SE HACE CREACION DE USUARIOS OK, CAPACITACIÓN GENERAL COMPLETA, SOMOS BANCOLOMBIA OK, PRUEBAS OK | T16: VISITA TECNICA | U16: DA000386 | V16: TIPO V | W16: TERRESTRE/FLUVIAL | X16: GONZALEZ ESTUPIÑAN YEISON WALTER ANTONIO | Y16: 1 | Z16: 0 | AA16: 504833 | AB16: 196537 | AC16: 504833
A17: BUCARAMANGA | B17: SANTANDERES | C17: 0004-0008 | D17: 13670 | E17: TA-25-1270699 | F17: 3007082142 | G17: APERTURA | H17: CB CRECIMIENTO ALIANZA - NUEVO | I17: BOLIVAR | J17: SAN PABLO | K17: DISTRICOL SERVISMART | L17: REDEBAN | M17: FO-25-1790328 | N17: 45968.333 | O17: 45972.451 | R17: EJECUTADO | S17: 06/11/2025 06-11 PROGRAMACION REALIZADA POR LA ALIANZA| INSTALACIÓN PROGRAMADA PARA EL 2025-11-11 | 11/11/2025 SE REALIZA APERTURA CB BANCOLOMBIA PURO, SE INSTALA AVISO EXTERIOR, FLANGED, DISPLAY,BASE, DATÁFONO, LECTOR DE BARRAS, CUBRE CLAVES, SE HACE CREACION DE USUARIOS A GUSTO DEL CLIENTE, SE HACE CAPACITACIÓN GENERAL COMPLETA, SE INDICA EL MANEJO CORRECTO DEL EQUIPO, SE HACEN PRUEBAS DEJANDO TODO OK | T17: VISITA TECNICA | U17: DA000387 | V17: TIPO V | W17: TERRESTRE/FLUVIAL | X17: GONZALEZ ESTUPIÑAN YEISON WALTER ANTONIO | Y17: 1 | Z17: 0 | AA17: 504833 | AB17: 196537 | AC17: 504833
A18: BUCARAMANGA | B18: SANTANDERES | C18: 0004-0008 | D18: 13670 | E18: TA-25-1270700 | F18: 3007082143 | G18: APERTURA | H18: CB CRECIMIENTO ALIANZA - NUEVO | I18: BOLIVAR | J18: SAN PABLO | K18: DISTRICOL DAYGLAT | L18: REDEBAN | M18: FO-25-1790336 | N18: 45968.333 | O18: 45972.675 | R18: EJECUTADO | S18: 06/11/2025 06-11 PROGRAMACION REALIZADA POR LA ALIANZA| INSTALACIÓN PROGRAMADA PARA EL 2025-11-11 | 11/11/2025 SE REALIZA CONTACTO TELEFÓNICO CON LA SEÑORA LILIANA RADA AL NÚMERO DE CONTACTO 3168226289 QUIEN COMENTA QUE TIENE LA DISPONIBLIDAD PARA ATENDERNOS, ADICIONAL SE LE PREGUNTA SOBRE SI HAY CERCANIA CON OTROS CB, LA CUAL ARGUMENTA QUE NO HAY PUNTOS CERCANOS NI TAMPOCO MANEJA DE OTROS BANCOS EN EL PUNTO DONDE SE INSTALA EL CORRESPONSAL | 11/11/2025 SE REALIZA APERTURA CB BANCOLOMBIA PURO, SE INSTALA AVISO EXTERIOR, FLANGED, DISPLAY,BASE, DATÁFONO, LECTOR DE BARRAS, CUBRE CLAVES, SE HACE CREACION DE USUARIOS A GUSTO DEL CLIENTE, SE HACE CAPACITACIÓN GENERAL COMPLETA, SE INDICA EL MANEJO CORRECTO DEL EQUIPO, SE HACEN PRUEBAS DEJANDO TODO OK | T18: VISITA TECNICA | U18: DA000388 | V18: TIPO V | W18: TERRESTRE/FLUVIAL | X18: GONZALEZ ESTUPIÑAN YEISON WALTER ANTONIO | Y18: 1 | Z18: 0 | AA18: 504833 | AB18: 196537 | AC18: 504833
A19: TUNJA | B19: SANTANDERES | C19: 0004-0008 | D19: 15224 | E19: TA-25-1270701 | F19: 3007082135 | G19: APERTURA | H19: CB CRECIMIENTO ALIANZA - NUEVO | I19: BOYACA | J19: CUCAITA | K19: PTM CUCAITA M Y S COMUNICACION | L19: REDEBAN | M19: FO-25-1790341 | N19: 45968.333 | O19: 45971.976 | R19: EJECUTADO | S19: 06/11/2025 06-11 PROGRAMACION REALIZADA POR LA ALIANZA| INSTALACIÓN PROGRAMADA PARA EL 2025-11-10 | 10/11/2025 SE INTENTA COMUNICACIÓN CON EL SEÑOR NELSON SUAREZ AL NÚMERO DE CONTACTO 3213096808 PARA CONFIRMAR LA DISPONIBILIDAD PARA EL DÍA DE HOY NO SE LOGRA CONTACTO SE DEJA MENSAJE POR WHATSAPP A ESPERA DE UNA RESPUESTA. | 10/11/2025 SE CONTACTA CLIENTE QUIÉN CONFIRMA TENER LA DISPONIBILIDAD PARA ATENDER LA VISITA EL DÍA DE HOY ROUTER DE INTERNET CERCA A DONDE VA QUEDAR INSTALADO EL DATÁFONO | 10/11/2025 SE EJECUTA APERTURA BANCOLOMBIA EXITOSA RED RBM INSTALADO EQUIPOS Y PUBLICIDAD PERSONAL CAPACITADO PRUEBAS OK CLIENTE CONFORME | T19: VISITA TECNICA | U19: DA000389 | V19: TIPO II | W19: TERRESTRE | X19: RODRIGUEZ MURCIA YERSON IVAN | Y19: 1 | Z19: 0 | AA19: 163814 | AB19: 140396 | AC19: 163814
... A43: BOGOTA | B43: CUNDINAMARCA | C43: 0004-0004 | D43: 11001 | E43: TA-25-1270742 | F43: 3007082121 | G43: APERTURA | H43: CB CRECIMIENTO ALIANZA - NUEVO | I43: CUNDINAMARCA | J43: BOGOTA | K43: PTM BOGOTA SERVIFLEXORG | L43: REDEBAN | M43: FO-25-1790478 | N43: 45968.333 | O43: 45971.69 | R43: EJECUTADO | S43: 06/11/2025 06-11 PROGRAMACION REALIZADA POR LA ALIANZA| INSTALACIÓN PROGRAMADA PARA EL 2025-11-10 | 10/11/2025 SE REALIZA INSTALACIÓN DE CB BANCOLOMBIA SIN NOVEDAD PRUEBA OK SE CREAN USUARIOS Y SE HABILITAN CIERRES OK | T43: VISITA TECNICA | U43: DA000414 | V43: TIPO I | W43: TERRESTRE | X43: ORTIZ MARTINEZ STIVEN | Y43: 1 | Z43: 0 | AA43: 75096 | AB43: 75096 | AC43: 75096
A44: PASTO | B44: SUROCCIDENTE Y EJE CAFETERO | C44: 0004-0003 | D44: 52001 | E44: TA-25-1270743 | F44: 3007040058 | G44: APERTURA | H44: DATAFONO ADICIONAL - ALIANZA | I44: NARIÑO | J44: PASTO | K44: DISTRICOL DROGUERIA SAN ANDRES | L44: REDEBAN | M44: FO-25-1790484 | N44: 45968.333 | O44: 45971.671 | P44: AGREGADOR | Q44: DISTRICOL | R44: EJECUTADO | S44: 06/11/2025 06-11 PROGRAMACION REALIZADA POR LA ALIANZA| INSTALACIÓN PROGRAMADA PARA EL 2025-11-10 | 10/11/2025 SE REALIZÓ LA INSTALACIÓN DE EQUIPOS Y ACCESORIOS POR DATÁFONO ADICIONAL, SE EXPLICA EL MANEJO DE DATÁFONO Y CIERRE DE TX, CLIENTE YA CONOCE EL MANEJO DE CB SE EJECUTAN PRUEBAS TX EXITOSAS QUEDA OPERATIVO. | T44: VISITA TECNICA | U44: DA000415 | V44: TIPO I | W44: TERRESTRE | X44: REMICIO AMADO JOHN HEBER | Y44: 1 | Z44: 0 | AA44: 75096 | AB44: 75096 | AC44: 75096
A45: IBAGUE | B45: REMOTAS | C45: 0004-0007 | D45: 73001 | E45: TA-25-1270744 | F45: 3007072312 | G45: APERTURA | H45: DATAFONO ADICIONAL - ALIANZA | I45: TOLIMA | J45: IBAGUE | K45: PTM IBAGUE TIENDA FRUVER TTATT | L45: REDEBAN | M45: FO-25-1790488 | N45: 45968.333 | O45: 45969.303 | P45: AGREGADOR | Q45: COMCARD - PTM | R45: EJECUTADO | S45: 08/11/2025 SE REALIZA INSTALACIÓN DE DATÁFONO ADICIONAL, SE REALIZA PRUEBAS DE FUNCIONAMIENTO EXITOSAS. CUBRE CLAVE INSTALADO | T45: VISITA TECNICA | U45: DA000416 | V45: TIPO I | W45: TERRESTRE | X45: BARRAGAN TAFUR EDWIN ESTEBAN | Y45: 1 | Z45: 0 | AA45: 75096 | AB45: 75096 | AC45: 75096
A46: CALI | B46: SUROCCIDENTE Y EJE CAFETERO | C46: 0004-0003 | D46: 76001 | E46: TA-25-1270746 | F46: 3007034986 | G46: APERTURA | H46: DATAFONO ADICIONAL - ALIANZA | I46: VALLE DEL CAUCA | J46: CALI | K46: DISTRICOL INTEGRAL CENTRO DE S | L46: REDEBAN | M46: FO-25-1790494 | N46: 45968.333 | O46: 45968.525 | P46: AGREGADOR | Q46: DISTRICOL | R46: EJECUTADO | S46: 06/11/2025 06-11 PROGRAMACION REALIZADA POR LA ALIANZA| INSTALACIÓN PROGRAMADA PARA EL 2025-11-07 | 07/11/2025 SE LLAMA AL CLIENTE Y SE VALIDA INSTALACIÓN Y DIRECCIÓN, SE VISITA EL COMERCIO, SE INSTALA DATAFONO, LECTORA, PINPAD, MAGIC BOX EN ADICIONAL CB BANCOLOMBIA PURO, PRUEBAS OK, TELECARGA TRNA | T46: VISITA TECNICA | U46: DA000417 | V46: TIPO I | W46: TERRESTRE | X46: HERRERA MONAR GEOVANNY | Y46: 1 | Z46: 0 | AA46: 75096 | AB46: 75096 | AC46: 75096
A47: CALI | B47: SUROCCIDENTE Y EJE CAFETERO | C47: 0004-0003 | D47: 76834 | E47: TA-25-1270747 | F47: 3007081986 | G47: APERTURA | H47: CB CRECIMIENTO ALIANZA - OTRAS LISTAS | I47: VALLE DEL CAUCA | J47: TULUA | K47: PTM TULUA YUAN CITY TULUA | L47: REDEBAN | M47: FO-25-1790502 | N47: 45968.333 | O47: 45971.783 | P47: AGREGADOR | Q47: COMCARD - PTM | R47: EJECUTADO | S47: 06/11/2025 06-11 PROGRAMACION REALIZADA POR LA ALIANZA| INSTALACIÓN PROGRAMADA PARA EL 2025-11-10 | 10/11/2025 SE INSTALA EQUIPO, LECTOR Y ACCESORIOS, LUEGO SE CAPACITA Y SE INSTALA PUBLICIDAD, PRUEBAS OK | T47: VISITA TECNICA | U47: DA000418 - CA000576 | V47: TIPO II | W47: TERRESTRE | X47: PAREDES CASTILLO DIEGO | Y47: 1 | Z47: 0 | AA47: 163814 | AB47: 140396 | AC47: 163814
A48: MEDELLIN | B48: NOROCCIDENTE | C48: 0004-0005 | D48: 5001 | E48: TA-25-1288927 | F48: 3007082177 | G48: APERTURA | H48: CB CRECIMIENTO ALIANZA - NUEVO | I48: ANTIOQUIA | J48: MEDELLIN | K48: PTM MEDELLIN VARIEDADES PICACH | L48: REDEBAN | M48: FO-25-1818137 | N48: 45974.333 | O48: 45975.57 | R48: EJECUTADO | S48: 12/11/2025 12-11 PROGRAMACION REALIZADA POR LA ALIANZA| INSTALACIÓN PROGRAMADA PARA EL 2025-11-14 | 14/11/2025 INSTALACIÓN DE CB MIXTO OK PUBLICIDAD Y CAPACITACIÓN OK PRUEBAS SOLO CONSULTA DE SALDO NO HAY PARA MÁS PRUEBAS CUBRE CLAVE OK NO TELECARGA | T48: VISITA TECNICA | U48: FB001812 - FB001591 | V48: TIPO I | W48: TERRESTRE | X48: PAREJA ECHAVARRIA JHON DAVID | Y48: 1 | Z48: 0 | AA48: 75096 | AB48: 75096 | AC48: 75096
A49: MEDELLIN | B49: NOROCCIDENTE | C49: 0004-0005 | D49: 5360 | E49: TA-25-1288928 | F49: 3007082169 | G49: APERTURA | H49: CB CRECIMIENTO ALIANZA - NUEVO | I49: ANTIOQUIA | J49: ITAGUI | K49: PTM ITAGUI GRANERO SUPER HISTO | L49: REDEBAN | M49: FO-25-1818139 | N49: 45974.333 | O49: 45975.688 | R49: EJECUTADO | S49: 12/11/2025 12-11 PROGRAMACION REALIZADA POR LA ALIANZA| INSTALACIÓN PROGRAMADA PARA EL 2025-11-14 | 15/11/2025 INSTALACIÓN CB OK | T49: VISITA TECNICA | U49: FB001813-FB001543 | V49: TIPO I | W49: TERRESTRE | X49: BADEL ACUÑA LUIS ALBERTO | Y49: 1 | Z49: 0 | AA49: 75096 | AB49: 75096 | AC49: 75096
A50: MEDELLIN | B50: NOROCCIDENTE | C50: 0004-0005 | D50: 5360 | E50: TA-25-1288929 | F50: 3007082170 | G50: APERTURA | H50: CB CRECIMIENTO ALIANZA - NUEVO | I50: ANTIOQUIA | J50: ITAGUI | K50: PTM ITAGUI MOTO CLUB S&S | L50: REDEBAN | M50: FO-25-1818143 | N50: 45974.333 | O50: 45975.564 | R50: EJECUTADO | S50: 12/11/2025 12-11 PROGRAMACION REALIZADA POR LA ALIANZA| INSTALACIÓN PROGRAMADA PARA EL 2025-11-14 | 14/11/2025 INSTALACIÓN CB OK | T50: VISITA TECNICA | U50: FB001814-FB001551 | V50: TIPO I | W50: TERRESTRE | X50: BADEL ACUÑA LUIS ALBERTO | Y50: 1 | Z50: 0 | AA50: 75096 | AB50: 75096 | AC50: 75096
A51: APARTADO | B51: NOROCCIDENTE | C51: 0004-0005 | D51: 5837 | E51: TA-25-1288930 | F51: 3007082172 | G51: APERTURA | H51: CB CRECIMIENTO ALIANZA - NUEVO | I51: ANTIOQUIA | J51: TURBO | K51: PTM TURBO TIENDA ARBASU | L51: REDEBAN | M51: FO-25-1818147 | N51: 45974.333 | O51: 45975.694 | R51: EJECUTADO | S51: 12/11/2025 12-11 PROGRAMACION REALIZADA POR LA ALIANZA| INSTALACIÓN PROGRAMADA PARA EL 2025-11-14 | 15/11/2025 SE INSTALA DATAFONO,MAGIBOX.LECTORA.BASE DATAFONO, PIN PAD Y PUBLICIDAD. SE DA CAPACITACION DE MANEJO DE EQUIPO Y PLATAFORMA SOMOS BANCOLOMBIA. SE HACEN PRUEBAS DE RETIRO,CONSULTA DE SALDO,CONSIGNACON, PRUEBA DE LECTORA Y SE DEJA TODO OK | T51: VISITA TECNICA | U51: FB001815 | V51: TIPO II | W51: TERRESTRE | X51: SALDARRIAGA MIRANDA SANTIAGO | Y51: 1 | Z51: 0 | AA51: 163814 | AB51: 140396 | AC51: 163814
A52: SANTA MARTA | B52: COSTA | C52: 0004-0001 | D52: 44847 | E52: TA-25-1288931 | F52: 3007082175 | G52: APERTURA | H52: CB CRECIMIENTO ALIANZA - NUEVO | I52: LA GUAJIRA | J52: URIBIA | K52: PTM URIBIA TIENDA Y VERDURERA | L52: REDEBAN | M52: FO-25-1818152 | N52: 45974.333 | O52: 45975.704 | R52: EJECUTADO | S52: 12/11/2025 12-11 PROGRAMACION REALIZADA POR LA ALIANZA| INSTALACIÓN PROGRAMADA PARA EL 2025-11-14 | 14/11/2025 SE REALIZA APERTURA DE CB, SE INSTALA DATAFONO, LECTOR Y PUBLICIDAD,SE ENTREGAN 40 ROLLOS, SE BRINDA CAPACITACIÓN, SE REALIZAN PRUEBAS DE DEPOSITO, RETIRO, TRANSFERENCIA, CONSULTA DE SALDO, ENTRE OTRAS, DEJANDO EL SERVICIO FUNCIONAL AL 100 % | T52: VISITA TECNICA | U52: FB001816 | V52: TIPO IV | W52: TERRESTRE | X52: MONTES DIAZ JOHN FRED | Y52: 1 | Z52: 0 | AA52: 504833 | AB52: 196537 | AC52: 504833
A53: PASTO | B53: SUROCCIDENTE Y EJE CAFETERO | C53: 0004-0003 | D53: 52001 | E53: TA-25-1288932 | F53: 3007082173 | G53: APERTURA | H53: CB CRECIMIENTO ALIANZA - NUEVO | I53: NARIÑO | J53: PASTO | K53: PTM PASTO IMPACTO NARIÑO 23 | L53: REDEBAN | M53: FO-25-1818158 | N53: 45974.333 | O53: 45974.626 | R53: EJECUTADO | S53: 12/11/2025 12-11 PROGRAMACION REALIZADA POR LA ALIANZA| INSTALACIÓN PROGRAMADA PARA EL 2025-11-13 | 13/11/2025 SE REALIZÓ LA INSTALACIÓN DE EQUIPOS PUBLICIDAD Y ACCESORIOS PARA APERTURA CB BANCOLOMBIA SE DIO CAPACITACIÓN MANEJO DE DATÁFONO CB Y SOMOS BANCOLOMBIA SE EJECUTAN PRUEBAS TX EXITOSAS QUEDA OPERATIVO | T53: VISITA TECNICA | U53: FB001818 - FB001566 | V53: TIPO I | W53: TERRESTRE | X53: REMICIO AMADO JOHN HEBER | Y53: 1 | Z53: 0 | AA53: 75096 | AB53: 75096 | AC53: 75096
A54: PASTO | B54: SUROCCIDENTE Y EJE CAFETERO | C54: 0004-0003 | D54: 52215 | E54: TA-25-1288933 | F54: 3007082171 | G54: APERTURA | H54: CB CRECIMIENTO ALIANZA - NUEVO | I54: NARIÑO | J54: CORDOBA | K54: PTM CORDOBA DROGUERIA EL COMER | L54: REDEBAN | M54: FO-25-1818160 | N54: 45974.333 | O54: 45975.709 | R54: EJECUTADO | S54: 12/11/2025 12-11 PROGRAMACION REALIZADA POR LA ALIANZA| INSTALACIÓN PROGRAMADA PARA EL 2025-11-14 | 14/11/2025 SE REALIZA INSTALACIÓN DE CB. SE CAPACITA SOBRE SOMOS BANCOLOMBIA, MANEJO DE DATAFONO Y PARTE ADMINISTRATIVA. SE INSTALA AVISO EXTERIOR, FLANGER Y DISPLAY LEGAL CON INSERTO HORARIO, TARIFAS Y NÚMERO DE CB. SE ENTREGAN 40 ROLLOS. SE REALIZA PRUEBAS TX EXITOSAS. QUEDA OPERATIVO | T54: VISITA TECNICA | U54: FB001819 | V54: TIPO II | W54: TERRESTRE | X54: CASTILLO HERRERA ALEX RICARDO | Y54: 1 | Z54: 0 | AA54: 163814 | AB54: 140396 | AC54: 163814
A55: BUCARAMANGA | B55: SANTANDERES | C55: 0004-0008 | D55: 68001 | E55: TA-25-1288937 | F55: 3007082166 | G55: APERTURA | H55: CB CRECIMIENTO ALIANZA - NUEVO | I55: SANTANDER | J55: BUCARAMANGA | K55: PTM BUCARAMANGA PAPELERIA NOGA | L55: REDEBAN | M55: FO-25-1818166 | N55: 45974.333 | O55: 45974.301 | R55: EJECUTADO | S55: 12/11/2025 12-11 PROGRAMACION REALIZADA POR LA ALIANZA| INSTALACIÓN PROGRAMADA PARA EL 2025-11-13 | 13/11/2025 EN COMUNICACIÓN CON CLIENTE INDICA Q NOS ATIENDES DESPUES DE LAS 3PM Q ABRE EL LOCAL, SE CONFIRMA INTERNET OK | 14/11/2025 SE INSTALA PUBLICIDAD COMPLETA ,DATAFONO ,LECTOR , CABLES Y FUENTE DE PODER. 40 ROLLOS, BASE, SE CAPACITAN CLIENTE MANEJO CORRESPONSAL CIERRES CUADRE DIARIO COMPENSACIÓN,MANEJO DATAFONO OK , VISITA EXITOSA PRUEBAS OK | T55: VISITA TECNICA | U55: FB001820 | V55: TIPO I | W55: TERRESTRE | X55: GELVEZ MOGOLLON JOSE ELISEO | Y55: 1 | Z55: 0 | AA55: 75096 | AB55: 75096 | AC55: 75096
A56: CALI | B56: SUROCCIDENTE Y EJE CAFETERO | C56: 0004-0003 | D56: 76001 | E56: TA-25-1288939 | F56: 3007082167 | G56: APERTURA | H56: CB CRECIMIENTO ALIANZA - NUEVO | I56: VALLE DEL CAUCA | J56: CALI | K56: PTM CALI SKYNET 2.2 | L56: REDEBAN | M56: FO-25-1818168 | N56: 45974.333 | O56: 45974.61 | R56: EJECUTADO | S56: 12/11/2025 12-11 PROGRAMACION REALIZADA POR LA ALIANZA| INSTALACIÓN PROGRAMADA PARA EL 2025-11-13 | 13/11/2025 SE INSTALA EQUIPO, LECTOR Y ACCESORIOS, LUEGO SE CAPACITA Y SE INSTALA PUBLICIDAD, PRUEBAS OK | T56: VISITA TECNICA | U56: FB001821 - FJZZZ533 | V56: TIPO I | W56: TERRESTRE | X56: PAREDES CASTILLO DIEGO | Y56: 1 | Z56: 0 | AA56: 75096 | AB56: 75096 | AC56: 75096
A57: CALI | B57: SUROCCIDENTE Y EJE CAFETERO | C57: 0004-0003 | D57: 76001 | E57: TA-25-1288940 | F57: 3007082168 | G57: APERTURA | H57: CB CRECIMIENTO ALIANZA - NUEVO | I57: VALLE DEL CAUCA | J57: CALI | K57: PTM CALI VARIEDADES BLU | L57: REDEBAN | M57: FO-25-1818172 | N57: 45974.333 | O57: 45974.304 | R57: EJECUTADO | S57: 12/11/2025 12-11 PROGRAMACION REALIZADA POR LA ALIANZA| INSTALACIÓN PROGRAMADA PARA EL 2025-11-13 | 14/11/2025 SE VISITA ESTABLECIMIENTO, SE REALIZA INSTALACIÓN CORRESPONSAL BANCOLOMBIA MIXTO M. TRANSACCIONES DE PRUEBA EXITOSAS. SE CAPACITA Y SE INSTALA PUBLICIDAD COMPLETA. COMERCIO SIN AVISO PUBLICITARIO, SIN EMBARGO SI ES EL MISMO OBJETIVO COMERCIAL, LA DIRECCION COINCIDE Y LA CÁMARA DE COMERCIO TAMBIEN TIENE EL MISMO NOMBRE DE LISTA DE CHEQUEO. | T57: VISITA TECNICA | U57: FB001822, FB001570 | V57: TIPO I | W57: TERRESTRE | X57: BOLAÑOS TABORDA JORGE ENRIQUE | Y57: 1 | Z57: 0 | AA57: 75096 | AB57: 75096 | AC57: 75096
A58: CALI | B58: SUROCCIDENTE Y EJE CAFETERO | C58: 0004-0003 | D58: 76869 | E58: TA-25-1288942 | F58: 3007082176 | G58: APERTURA | H58: CB CRECIMIENTO ALIANZA - NUEVO | I58: VALLE DEL CAUCA | J58: VIJES | K58: PTM VIJES DROGAS LA SUPERIOR | L58: REDEBAN | M58: FO-25-1818178 | N58: 45974.333 | O58: 45975.713 | R58: EJECUTADO | S58: 12/11/2025 12-11 PROGRAMACION REALIZADA POR LA ALIANZA| INSTALACIÓN PROGRAMADA PARA EL 2025-11-14 | 14/11/2025 SE LLAMA AL CLIENTE Y SE VÁLIDA INSTALACIÓN, DIRECCIÓN Y DISPONIBILIDAD, SE VISITA EL COMERCIO, SE INSTALA DATAFONO, LECTORA, ACCESORIOS EN APERTURA CB BANCOLOMBIA MIXTO, SE CAPACITA, PRUEBAS OK, TELECARGA TRNA | T58: VISITA TECNICA | U58: FB001823 - FB001580 | V58: TIPO II | W58: TERRESTRE | X58: HERRERA MONAR GEOVANNY | Y58: 1 | Z58: 0 | AA58: 163814 | AB58: 140396 | AC58: 163814
A59: BOGOTA | B59: CUNDINAMARCA | C59: 0004-0004 | D59: 11001 | E59: TA-25-1288948 | F59: 3007082165 | G59: APERTURA | H59: CB CRECIMIENTO ALIANZA - NUEVO | I59: CUNDINAMARCA | J59: BOGOTA | K59: PTM BOGOTA SHOESTYLE CALZADO | L59: REDEBAN | M59: FO-25-1818181 | N59: 45974.333 | O59: 45975.578 | R59: EJECUTADO | S59: 12/11/2025 12-11 PROGRAMACION REALIZADA POR LA ALIANZA| INSTALACIÓN PROGRAMADA PARA EL 2025-11-14 | 18/11/2025 APERTURA BANCOLOMBIA OK CAPACITACIÓN OK PUBLICIDAD OK SERVICIO OPERATIVO SOLO SE REALIZAN PRUEBAS CON AN INFORMACIÓN QUE NOS SUMINISTRO EL CLIENTE YA QUE NO SE CUENTA CON TARJETA DE PRUEBAS SUMISTRADA POR LA EMPRESA | T59: VISITA TECNICA | U59: FB001824 - FB001581 | V59: TIPO I | W59: TERRESTRE | X59: HERNANDEZ NARANJO OSCAR EDUARDO | Y59: 1 | Z59: 0 | AA59: 75096 | AB59: 75096 | AC59: 75096
A60: MONTERIA | B60: COSTA | C60: 0004-0001 | D60: 23555 | E60: TA-25-1288950 | F60: 3007035595 | G60: APERTURA | H60: DATAFONO ADICIONAL - ALIANZA | I60: CORDOBA | J60: PLANETA RICA | K60: DISTRICOL MULTIYA PARQUE | L60: REDEBAN | M60: FO-25-1818189 | N60: 45974.333 | O60: 45974.616 | P60: AGREGADOR | Q60: DISTRICOL | R60: EJECUTADO | S60: 12/11/2025 12-11 PROGRAMACION REALIZADA POR LA ALIANZA| INSTALACIÓN PROGRAMADA PARA EL 2025-11-13 | 13/11/2025 SE REALIZA LA INSTALACIÓN DE DATAFONO ADICIONAL, SE LE CREAN USUARIOS OPERADOR Y ADMINISTRADOR, SE REALIZAN PRUEBAS OK, CB OPERANDO CON NORMALIDAD | T60: VISITA TECNICA | U60: FB001825 | V60: TIPO II | W60: TERRESTRE | X60: ARRAZOLA HERNANDEZ NICOLAS AUGUSTO | Y60: 1 | Z60: 0 | AA60: 163814 | AB60: 140396 | AC60: 163814
A61: SINCELEJO | B61: COSTA | C61: 0004-0001 | D61: 70708 | E61: TA-25-1288955 | F61: 3007082064 | G61: APERTURA | H61: CB CRECIMIENTO ALIANZA - OTRAS LISTAS | I61: SUCRE | J61: SAN MARCOS | K61: DISTRICOL DROGUERÍA FARMASUCRE | L61: REDEBAN | M61: FO-25-1818199 | N61: 45974.333 | O61: 45974.622 | P61: AGREGADOR | Q61: DISTRICOL | R61: EJECUTADO | S61: 12/11/2025 12-11 PROGRAMACION REALIZADA POR LA ALIANZA| INSTALACIÓN PROGRAMADA PARA EL 2025-11-13 | 13/11/2025 SE REALIZA INSTALACIÓN DE CORRESPONSAL BANCOLOMBIA PURO OK, EQUIPOS INSTALADOS OPERATIVOS OK, PRUEBAS DE TRANSACCIONES EXITOSAS, PERSONAL CAPACITADO OK, CLIENTE CB VALIDA SALDO EN CERO DESPUES DE LA INSTALACIÓN OK, CB SE DEJA OPERATIVO SIN NOVEDAD | T61: VISITA TECNICA | U61: CA001882 | V61: TIPO III | W61: TERRESTRE | X61: GONZALEZ FERRER JESUS ALEXANDER | Y61: 1 | Z61: 0 | AA61: 275729 | AB61: 196537 | AC61: 275729
A62: CALI | B62: SUROCCIDENTE Y EJE CAFETERO | C62: 0004-0003 | D62: 76111 | E62: TA-25-1296774 | F62: 3007015527 | G62: APERTURA | H62: DATAFONO ADICIONAL - ALIANZA | I62: VALLE DEL CAUCA | J62: GUADALAJARA DE BUGA | K62: MULTIPAGAS BUGA | L62: REDEBAN | M62: FO-25-1828306 | N62: 45979.333 | O62: 45979.639 | P62: ROBUSTO | Q62: MULTIPAGAS | R62: EJECUTADO | S62: 14/11/2025 14-11 SE REALIZA LLAMADA AL CLIENTE, SE HABLA CON LA SRA CINDY PAOLA ANGARITA AL NUMERO 3158673642 SE VALIDA DIRECCIÓN OK, CANAL OK, DISPONIBILIDAD TOTAL, LLAMAR EL DÍA LA INSTALACIÓN PARA CONFIRMAR VISITA (PREFERIBLEMENTE EN HORAS DE LA MAÑANA) | 18/11/2025 SE VISITA CORRESPONSAL Y SE REALIZA INSTALACIÓN DATÁFONO ADICIONAL. TRANSACCIONES DE PRUEBA EXITOSAS | T62: VISITA TECNICA | U62: FB003614 | V62: TIPO II | W62: TERRESTRE | X62: BOLAÑOS TABORDA JORGE ENRIQUE | Y62: 1 | Z62: 0 | AA62: 163814 | AB62: 140396 | AC62: 163814
A63: YOPAL | B63: REMOTAS | C63: 0004-0007 | D63: 85001 | E63: TA-25-1296775 | F63: 3007023134 | G63: APERTURA | H63: DATAFONO ADICIONAL - ALIANZA | I63: CASANARE | J63: YOPAL | K63: MULTIPAGAS YOPAL | L63: REDEBAN | M63: FO-25-1828308 | N63: 45979.333 | O63: 45980.483 | P63: ROBUSTO | Q63: MULTIPAGAS | R63: EJECUTADO | S63: 14/11/2025 14-11 SE REALIZA LLAMADA AL CLIENTE, SE HABLA CON LA SRA ADRIANA RAMIREZ AL NUMERO 3115545295 SE VALIDA DIRECCIÓN OK, CANAL OK, DISPONIBILIDAD TOTAL, LLAMAR EL DÍA LA INSTALACIÓN PARA CONFIRMAR VISITA | 19/11/2025 SE VISITA COMERCIO, SE INSTALA DATÁFONO LECTOR Y PINPAD ADICIONAL. PRUEBAS OK. OPERATIVO EL SERVICIO. CB INDICA NO REQUIERE BASE. NO SE REGISTRA TIRILLA DE TRANSFERENCIA NO SE CUENTA CON TARJETA | T63: VISITA TECNICA | U63: FB003617 | V63: TIPO I | W63: TERRESTRE | X63: BERNAL ELAICA EDGAR ALEXIS | Y63: 1 | Z63: 0 | AA63: 75096 | AB63: 75096 | AC63: 75096
A64: MEDELLIN | B64: NOROCCIDENTE | C64: 0004-0005 | D64: 5001 | E64: TA-25-1315901 | F64: 3007082259 | G64: APERTURA | H64: CB CRECIMIENTO ALIANZA - NUEVO | I64: ANTIOQUIA | J64: MEDELLIN | K64: PTM MEDELLIN LA BENDICION MINI | L64: REDEBAN | M64: FO-25-1852517 | N64: 45982.333 | O64: 45985.534 | R64: EJECUTADO | S64: 20/11/2025 20-11 PROGRAMACION REALIZADA POR LA ALIANZA| INSTALACIÓN PROGRAMADA PARA EL 2025-11-24 | 24/11/2025 SE REALIZA INSTALACIÓN DE EQUIPO. CAPACITACIÓN Y SE INSTALA PUBLICIDAD SERVICIO OPERATIVO OK | T64: VISITA TECNICA | U64: OB001375 - OB000961 | V64: TIPO I | W64: TERRESTRE | X64: ZAPATA LOPEZ EDWARD ASDRUBAL | Y64: 1 | Z64: 0 | AA64: 75096 | AB64: 75096 | AC64: 75096
A65: MEDELLIN | B65: NOROCCIDENTE | C65: 0004-0005 | D65: 5001 | E65: TA-25-1315902 | F65: 3007082254 | G65: APERTURA | H65: CB CRECIMIENTO ALIANZA - NUEVO | I65: ANTIOQUIA | J65: MEDELLIN | K65: PTM MEDELLIN DIEGO ALEJANDRO | L65: REDEBAN | M65: FO-25-1852520 | N65: 45982.333 | O65: 45985.539 | R65: EJECUTADO | S65: 20/11/2025 20-11 PROGRAMACION REALIZADA POR LA ALIANZA| INSTALACIÓN PROGRAMADA PARA EL 2025-11-24 | 24/11/2025 SE INSTALA PUBLICIDAD Y EQUIPOS A PETICIÓN DEL USUARIO, SERVICIOS OK CAPACITACIÓN OK | T65: VISITA TECNICA | U65: OB001376-OB000964 | V65: TIPO I | W65: TERRESTRE | X65: BARRIENTOS HERNANDEZ CRISTIAN HORACIO | Y65: 1 | Z65: 0 | AA65: 75096 | AB65: 75096 | AC65: 75096
A66: MEDELLIN | B66: NOROCCIDENTE | C66: 0004-0005 | D66: 5001 | E66: TA-25-1315903 | F66: 3007082255 | G66: APERTURA | H66: CB CRECIMIENTO ALIANZA - NUEVO | I66: ANTIOQUIA | J66: MEDELLIN | K66: PTM MEDELLIN SALEJO PERFUMES | L66: REDEBAN | M66: FO-25-1852523 | N66: 45982.333 | O66: 45985.65 | R66: EJECUTADO | S66: 20/11/2025 20-11 PROGRAMACION REALIZADA POR LA ALIANZA| INSTALACIÓN PROGRAMADA PARA EL 2025-11-24 | 24/11/2025 SE INSTALA PUBLICIDAD Y EQUIPOS A PETICIÓN DEL USUARIO, SE DEJAN SERVICIOS FUNCIONANDO CORRECTAMENTE, CAPACITACIÓN OK | T66: VISITA TECNICA | U66: OB001377-OB000965 | V66: TIPO I | W66: TERRESTRE | X66: BARRIENTOS HERNANDEZ CRISTIAN HORACIO | Y66: 1 | Z66: 0 | AA66: 75096 | AB66: 75096 | AC66: 75096
A67: MEDELLIN | B67: NOROCCIDENTE | C67: 0004-0005 | D67: 5001 | E67: TA-25-1315904 | F67: 3007082256 | G67: APERTURA | H67: CB CRECIMIENTO ALIANZA - NUEVO | I67: ANTIOQUIA | J67: MEDELLIN | K67: PMT MEDELLIN A D G. | L67: REDEBAN | M67: FO-25-1852526 | N67: 45982.333 | O67: 45982.806 | R67: EJECUTADO | S67: 20/11/2025 20-11 PROGRAMACION REALIZADA POR LA ALIANZA| INSTALACIÓN PROGRAMADA PARA EL 2025-11-21 | 22/11/2025 SE REALIZA INSTALACIÓN DEL CB EXITOSAMENTE. SE CAPACITA SIN NOVEDAD, SE INSTALA PUBLICIDAD, SE REALIZAN PRUEBAS EXITOSAS. INSTALACION OK. | T67: VISITA TECNICA | U67: OB001378 | V67: TIPO I | W67: TERRESTRE | X67: RUA ALVAREZ RICHARD ANDRES | Y67: 1 | Z67: 0 | AA67: 75096 | AB67: 75096 | AC67: 75096
A68: MEDELLIN | B68: NOROCCIDENTE | C68: 0004-0005 | D68: 5001 | E68: TA-25-1315905 | F68: 3007082257 | G68: APERTURA | H68: CB CRECIMIENTO ALIANZA - NUEVO | I68: ANTIOQUIA | J68: MEDELLIN | K68: PTM MEDELLIN FERRETERIA EMANIS | L68: REDEBAN | M68: FO-25-1852531 | N68: 45982.333 | O68: 45985.515 | R68: EJECUTADO | S68: 20/11/2025 20-11 PROGRAMACION REALIZADA POR LA ALIANZA| INSTALACIÓN PROGRAMADA PARA EL 2025-11-24 | 24/11/2025 SE INSTALAN EQUIPOS OK | T68: VISITA TECNICA | U68: OB001379 - OB000971 | V68: TIPO I | W68: TERRESTRE | X68: QUINTERO SANCHEZ JUAN SEBASTIAN | Y68: 1 | Z68: 0 | AA68: 75096 | AB68: 75096 | AC68: 75096
A69: MEDELLIN | B69: NOROCCIDENTE | C69: 0004-0005 | D69: 5001 | E69: TA-25-1315906 | F69: 3007082258 | G69: APERTURA | H69: CB CRECIMIENTO ALIANZA - NUEVO | I69: ANTIOQUIA | J69: MEDELLIN | K69: PTM MEDELLIN TIENDA MIXTA EL P | L69: REDEBAN | M69: FO-25-1852533 | N69: 45982.333 | O69: 45985.629 | R69: EJECUTADO | S69: 20/11/2025 20-11 PROGRAMACION REALIZADA POR LA ALIANZA| INSTALACIÓN PROGRAMADA PARA EL 2025-11-24 | 24/11/2025 SE INSTALAN EQUIPOS OK | T69: VISITA TECNICA | U69: OB001380 - OB000972 | V69: TIPO I | W69: TERRESTRE | X69: QUINTERO SANCHEZ JUAN SEBASTIAN | Y69: 1 | Z69: 0 | AA69: 75096 | AB69: 75096 | AC69: 75096
A70: MEDELLIN | B70: NOROCCIDENTE | C70: 0004-0005 | D70: 5088 | E70: TA-25-1315907 | F70: 3007082251 | G70: APERTURA | H70: CB CRECIMIENTO ALIANZA - NUEVO | I70: ANTIOQUIA | J70: BELLO | K70: PTM BELLO EL BUEN PRECIO N & S | L70: REDEBAN | M70: FO-25-1852537 | N70: 45982.333 | O70: 45982.762 | R70: EJECUTADO | S70: 20/11/2025 20-11 PROGRAMACION REALIZADA POR LA ALIANZA| INSTALACIÓN PROGRAMADA PARA EL 2025-11-21 | 21/11/2025 SE REALIZA VISITA TÉCNICA PARA LA INSTALACIÓN DEL CORRESPONSAL BANCOLOMBIA. EL USUARIO CONFIRMA SU IDENTIFICACIÓN Y SE VALIDA EL SITIO, ENCONTRANDO CONDICIONES ADECUADAS. SE PROCEDE CON LA INSTALACIÓN Y CONFIGURACIÓN DE LOS EQUIPOS, ASEGURANDO SU CORRECTO FUNCIONAMIENTO. POSTERIORMENTE, SE CAPACITA AL CLIENTE EN EL MANEJO DEL EQUIPO, LA EJECUCIÓN DE TRANSACCIONES Y EL USO DE LA PLATAFORMA SOMOS BANCOLOMBIA. FINALMENTE, SE REALIZAN PRUEBAS OPERATIVAS CON RESULTADOS EXITOSOS, DEJANDO EL SERVICIO COMPLETAMENTE HABILITADO Y EN ÓPTIMAS CONDICIONES. EL CLIENTE QUEDA INFORMADO, CAPACITADO Y CON PLENA CONFIANZA EN EL FUNCIONAMIENTO DEL CORRESPONSAL. | T70: VISITA TECNICA | U70: OB001381-OB000975 | V70: TIPO I | W70: TERRESTRE | X70: MARTINEZ TOVAR OSCAR DAVID | Y70: 1 | Z70: 0 | AA70: 75096 | AB70: 75096 | AC70: 75096
A71: MEDELLIN | B71: NOROCCIDENTE | C71: 0004-0005 | D71: 5129 | E71: TA-25-1315908 | F71: 3007082243 | G71: APERTURA | H71: CB CRECIMIENTO ALIANZA - NUEVO | I71: ANTIOQUIA | J71: CALDAS | K71: PTM CALDAS DISTRIBUIDORA LAS | L71: REDEBAN | M71: FO-25-1852541 | N71: 45982.333 | O71: 45982.705 | R71: EJECUTADO | S71: 20/11/2025 20-11 PROGRAMACION REALIZADA POR LA ALIANZA| INSTALACIÓN PROGRAMADA PARA EL 2025-11-21 | 21/11/2025 SE REALIZA INSTALACIÓN DE EQUIPO, SE CAPACITA Y SE INSTALA PUBLICIDAD SE REALIZAN PRUEBAS EXITOSAS SERVICIO OPERATIVO OK | T71: VISITA TECNICA | U71: OB001382-OB000977 | V71: TIPO I | W71: TERRESTRE | X71: ZAPATA LOPEZ EDWARD ASDRUBAL | Y71: 1 | Z71: 0 | AA71: 75096 | AB71: 75096 | AC71: 75096
A72: MEDELLIN | B72: NOROCCIDENTE | C72: 0004-0005 | D72: 5360 | E72: TA-25-1315910 | F72: 3007082244 | G72: APERTURA | H72: CB CRECIMIENTO ALIANZA - NUEVO | I72: ANTIOQUIA | J72: ITAGUI | K72: PTM ITAGUI ALEXIS RICO ALZATE | L72: REDEBAN | M72: FO-25-1852544 | N72: 45982.333 | O72: 45982.504 | R72: EJECUTADO | S72: 20/11/2025 20-11 PROGRAMACION REALIZADA POR LA ALIANZA| INSTALACIÓN PROGRAMADA PARA EL 2025-11-21 | 21/11/2025 SE INSTALA PUBLICIDAD Y EQUIPOS A PETICIÓN DEL USUARIO, SERVICIOS OK CAPACITACIÓN OK USUARIO SOMOS BANCOLOMBIA NO HABILITADO POR EL BANCO | T72: VISITA TECNICA | U72: OB001383-OB000981 | V72: TIPO I | W72: TERRESTRE | X72: BARRIENTOS HERNANDEZ CRISTIAN HORACIO | Y72: 1 | Z72: 0 | AA72: 75096 | AB72: 75096 | AC72: 75096
A73: MEDELLIN | B73: NOROCCIDENTE | C73: 0004-0005 | D73: 5576 | E73: TA-25-1315911 | F73: 3007082247 | G73: APERTURA | H73: CB CRECIMIENTO ALIANZA - NUEVO | I73: ANTIOQUIA | J73: PUEBLORRICO | K73: PTM PUEBLORRICO GRANERO DONDE | L73: REDEBAN | M73: FO-25-1874381 | FO-25-1852547 | N73: 45982.333 | O73: 45986.408 | R73: EJECUTADO | S73: 26/11/2025 SE LLEVÓ A CABO LA INSTALACIÓN DE LOS AVISOS EXTERIORES E INTERIORES EN LA SEDE DEL CORRESPONSAL BANCOLOMBIA. ESTOS ELEMENTOS NO HABÍAN PODIDO SER INSTALADOS EL DÍA ANTERIOR DEBIDO AL RETRASO EN LA LLEGADA OCASIONADO POR EL VIAJE. LA INSTALACIÓN SE REALIZÓ SIGUIENDO LAS INDICACIONES ESPECÍFICAS DEL CLIENTE, GARANTIZANDO LA CORRECTA UBICACIÓN Y PRESENTACIÓN DE LOS AVISOS SEGÚN LO ACORDADO. | T73: VISITA TECNICA | U73: OB001384 | V73: TIPO III | W73: TERRESTRE | X73: MARTINEZ TOVAR OSCAR DAVID | Y73: 1 | Z73: 0 | AA73: 275729 | AB73: 196537 | AC73: 275729
A74: TUNJA | B74: SANTANDERES | C74: 0004-0008 | D74: 15407 | E74: TA-25-1315913 | F74: 3007082252 | G74: APERTURA | H74: CB CRECIMIENTO ALIANZA - NUEVO | I74: BOYACA | J74: VILLA DE LEYVA | K74: PTM VILLA DE LEYVA DROGUERIA E | L74: REDEBAN | M74: FO-25-1852551 | N74: 45982.333 | O74: 45982.711 | R74: EJECUTADO | S74: 20/11/2025 20-11 PROGRAMACION REALIZADA POR LA ALIANZA| INSTALACIÓN PROGRAMADA PARA EL 2025-11-21 | 21/11/2025 SE ESTABLECE COMUNICACIÓN CON EL SEÑOR JAIME ALIRIO SARMIENTO MORENO AL NÚMERO DE CONTACTO 3118275842 CLIENTE CONFIRMA TENER LA DISPONIBILIDAD PARA ATENDER LA VISITA EL DÍA DE HOY ROUTER DE INTERNET APROXIMADAMENTE A 3 METROS DE DISTANCIA DEL LUGAR DONDE VA QUEDAR INSTALADO EL DATÁFONO. | 21/11/2025 SE EJECUTA APERTURA BANCOLOMBIA EXITOSA RED RBM INSTALANDO EQUIPOS Y PUBLICIDAD PERSONAL CAPACITADO PRUEBAS OK CLIENTE CONFORME | T74: VISITA TECNICA | U74: OB001385 | V74: TIPO II | W74: TERRESTRE | X74: RODRIGUEZ MURCIA YERSON IVAN | Y74: 1 | Z74: 0 | AA74: 163814 | AB74: 140396 | AC74: 163814
A75: BUCARAMANGA | B75: SANTANDERES | C75: 0004-0008 | D75: 20710 | E75: TA-25-1315914 | F75: 3007082249 | G75: APERTURA | H75: CB CRECIMIENTO ALIANZA - NUEVO | I75: CESAR | J75: SAN ALBERTO | K75: PTM SAN ALBERTO MULTISERVICIOS | L75: REDEBAN | M75: FO-25-1852555 | N75: 45982.333 | O75: 45985.658 | R75: EJECUTADO | S75: 20/11/2025 20-11 PROGRAMACION REALIZADA POR LA ALIANZA| INSTALACIÓN PROGRAMADA PARA EL 2025-11-24 | 24/11/2025 EN COMUNICACIÓN CIN EL SR JOHAN SEBASTIÁN GELVEZ AL NÚMERO DE CONTACTO 3012032631 CONFIRMA DISPONIBILIDAD PARA PODER ATENDERNOS | 24/11/2025 SE REALIZA APERTURA BANCOLOMBIA CB MIXTO, SE INSTALA AVISO EXTERIOR, FLANGED, DISPLAY, BASE, DATÁFONO, LECTOR DE BARRAS, CUBRE CLAVES, MÁGIC BOX,PINPAD POR MÓDULO DE VIDRIO, SE CONFIGURÓ TERMINALES TANTO DE ADQUIRENCIA COMO LA DEL CB, SE CREAN USUARIOS AL GUSTO DEL CLIENTE, SE HACEN PRUEBAS DEJANDO TODO OK, .SOMOS BANCOLOMBIA OK | T75: VISITA TECNICA | U75: OB001386 | V75: TIPO III | W75: TERRESTRE | X75: GONZALEZ ESTUPIÑAN YEISON WALTER ANTONIO | Y75: 1 | Z75: 0 | AA75: 275729 | AB75: 196537 | AC75: 275729
... A89: BOGOTA | B89: CUNDINAMARCA | C89: 0004-0004 | D89: 11001 | E89: TA-25-1315933 | F89: 3007082235 | G89: APERTURA | H89: CB CRECIMIENTO ALIANZA - NUEVO | I89: CUNDINAMARCA | J89: BOGOTA | K89: PTM BOGOTA DROGUERIA CAMINO A | L89: REDEBAN | M89: FO-25-1852614 | N89: 45982.333 | O89: 45985.667 | R89: EJECUTADO | S89: 20/11/2025 20-11 PROGRAMACION REALIZADA POR LA ALIANZA| INSTALACIÓN PROGRAMADA PARA EL 2025-11-24 | 24/11/2025 SE LLEGA A LA DIRECCIÓN INDICADA Y SE REALIZA APERTURA DE PTM , SE HABILITAN MÓDULOS DE ADQUIRENCIA Y MÓDULO DE CORRESPONSALIA, PUBLICIDAD OK, USUARIO OK, SE REALIZA CAPACITACIÓN DE FUNCIONAMIENTO Y PAG SOMOS OK INGRESO OK, SE PROMUEVE EL BUEN USO Y CUIDADO DEL DATÁFONO, SE REALIZAN PRUEBAS EXITOSAS, NO SE TIENE TARJETA PARA REALIZAR PRUEBAS DE MÓDULO DE ADQUIRENCIA. | T89: VISITA TECNICA | U89: OB001403-OB001098 | V89: TIPO I | W89: TERRESTRE | X89: GARCIA PASTRANA KEVIN FERNANDO | Y89: 1 | Z89: 0 | AA89: 75096 | AB89: 75096 | AC89: 75096
A90: MEDELLIN | B90: NOROCCIDENTE | C90: 0004-0005 | D90: 5360 | E90: TA-25-1315935 | F90: 3007059913 | G90: APERTURA | H90: DATAFONO ADICIONAL - ALIANZA | I90: ANTIOQUIA | J90: ITAGUI | K90: PTM ITAGUI PAPELERIA Y VARIEDA | L90: REDEBAN | M90: FO-25-1852624 | N90: 45982.333 | O90: 45982.578 | P90: AGREGADOR | Q90: COMCARD - PTM | R90: EJECUTADO | S90: 20/11/2025 20-11 PROGRAMACION REALIZADA POR LA ALIANZA| INSTALACIÓN PROGRAMADA PARA EL 2025-11-21 | 21/11/2025 SE INSTALA DATÁFONO ADICIONAL A PETICIÓN DEL USUARIO, SE DEJAN SERVICIOS FUNCIONANDO CORRECTAMENTE | T90: VISITA TECNICA | U90: OB001405 | V90: TIPO I | W90: TERRESTRE | X90: BARRIENTOS HERNANDEZ CRISTIAN HORACIO | Y90: 1 | Z90: 0 | AA90: 75096 | AB90: 75096 | AC90: 75096
A91: NEIVA | B91: REMOTAS | C91: 0004-0007 | D91: 41298 | E91: TA-25-1315936 | F91: 3007077855 | G91: APERTURA | H91: DATAFONO ADICIONAL - ALIANZA | I91: HUILA | J91: GARZON | K91: DISTRICOL EL BODEGON MAYORISTA | L91: REDEBAN | M91: FO-25-1852627 | N91: 45982.333 | O91: 45985.699 | P91: AGREGADOR | Q91: DISTRICOL | R91: EJECUTADO | S91: 20/11/2025 20-11 PROGRAMACION REALIZADA POR LA ALIANZA| INSTALACIÓN PROGRAMADA PARA EL 2025-11-24 | 24/11/2025 SE REALIZA VISITA AL PUNTO, SE IMPLEMENTA DATAFONO Y LECTORA DE BARRAS , BASE, SE ENTREGAN 40 ROLLOS PAPEL RBM, SE DEJA EQUIPO CON VR 9.90 ,PRUEBAS CB OK, CB OPERATIVO.IMPLEMENTACION EXITOSA | T91: VISITA TECNICA | U91: OB001406 | V91: TIPO III | W91: TERRESTRE | X91: DEVIA REINOSO JUAN CARLOS | Y91: 1 | Z91: 0 | AA91: 275729 | AB91: 196537 | AC91: 275729
A92: PEREIRA | B92: SUROCCIDENTE Y EJE CAFETERO | C92: 0004-0002 | D92: 66001 | E92: TA-25-1315937 | F92: 3007079900 | G92: APERTURA | H92: DATAFONO ADICIONAL - ALIANZA | I92: RISARALDA | J92: PEREIRA | K92: DISTRICOL PERLA HORIZONTE | L92: REDEBAN | M92: FO-25-1852629 | N92: 45982.333 | O92: 45982.497 | P92: AGREGADOR | Q92: DISTRICOL | R92: EJECUTADO | S92: 20/11/2025 20-11 PROGRAMACION REALIZADA POR LA ALIANZA| INSTALACIÓN PROGRAMADA PARA EL 2025-11-21 | 21/11/2025 VISITAMOS COMERCIO REALIZAMOS INSTALACIÓN DE DATÁFONO, LECTOR DE BARRAS Y MAGIC BOX DESK 2600 CON BASE DATAFONO LO CONFIGURAMOS Y REALIZAMOS PRUEBAS OK NO INSTALAMOS NADA DE PUBLICIDAD YA QUE EL COMERCIO LAS TIENE. | T92: VISITA TECNICA | U92: OB001407 | V92: TIPO I | W92: TERRESTRE | X92: ARROYAVE CANO MANUEL GUILLERMO | Y92: 1 | Z92: 0 | AA92: 75096 | AB92: 75096 | AC92: 75096
A93: CALI | B93: SUROCCIDENTE Y EJE CAFETERO | C93: 0004-0003 | D93: 76001 | E93: TA-25-1315938 | F93: 3007053946 | G93: APERTURA | H93: DATAFONO ADICIONAL - ALIANZA | I93: VALLE DEL CAUCA | J93: CALI | K93: PTM CALI BOXPHONE | L93: REDEBAN | M93: FO-25-1852630 | N93: 45982.333 | O93: 45982.492 | P93: AGREGADOR | Q93: COMCARD - PTM | R93: EJECUTADO | S93: 20/11/2025 20-11 PROGRAMACION REALIZADA POR LA ALIANZA| INSTALACIÓN PROGRAMADA PARA EL 2025-11-21 | 21/11/2025 SE INSTALA DATÁFONO LECTOR PINPAD SE HACEN PRUEBAS Y QUEDA FUNCIONANDO CORRECTAMENTE | T93: VISITA TECNICA | U93: OB001408 | V93: TIPO I | W93: TERRESTRE | X93: CUERO RUIZ JHONNY | Y93: 1 | Z93: 0 | AA93: 75096 | AB93: 75096 | AC93: 75096
A94: BOGOTA | B94: CUNDINAMARCA | C94: 0004-0004 | D94: 11001 | E94: TA-25-1315939 | F94: 3007069137 | G94: APERTURA | H94: DATAFONO ADICIONAL - ALIANZA | I94: CUNDINAMARCA | J94: BOGOTA | K94: PTM BOGOTA ALDALAMI DISTRIBUI | L94: REDEBAN | M94: FO-25-1852635 | N94: 45982.333 | O94: 45985.705 | P94: AGREGADOR | Q94: COMCARD - PTM | R94: EJECUTADO | S94: 20/11/2025 20-11 PROGRAMACION REALIZADA POR LA ALIANZA| INSTALACIÓN PROGRAMADA PARA EL 2025-11-24 | 24/11/2025 INSTALACIÓN DE DATAFONO ADICIONAL OK PRUEBAS OK SIN NOVEDAD SERVICIO OPERATIVO SE REALIZAN PRUEBAS CON LA INFORMACIÓN QUE NOS SUMINISTRO EL CLIENTE CB CUENTA CON LA PUBLICIDAD INCOMPLETA | T94: VISITA TECNICA | U94: OB001409 | V94: TIPO I | W94: TERRESTRE | X94: HERNANDEZ NARANJO OSCAR EDUARDO | Y94: 1 | Z94: 0 | AA94: 75096 | AB94: 75096 | AC94: 75096
A95: BOGOTA | B95: CUNDINAMARCA | C95: 0004-0004 | D95: 11001 | E95: TA-25-1315940 | F95: 3007076822 | G95: APERTURA | H95: DATAFONO ADICIONAL - ALIANZA RED ASOCIADA AL PUNTO: REDEBAN MIXTO-PURO: PURO CODIGO UNICO COMERCIO: NUMERO DE DATAFONOS A INSTALAR: TERMINAL OBSERVACIONES DE LLAMADA: 20-11 PROGRAMACION REALIZADA POR LA ALIANZA | I95: CUNDINAMARCA | J95: BOGOTA | K95: PTM BOGOTA SOLUCIONES Y LOGIST | L95: REDEBAN | M95: FO-25-1852639 | N95: 45982.333 | O95: 45985.693 | P95: AGREGADOR | Q95: COMCARD - PTM | R95: EJECUTADO | S95: 20/11/2025 20-11 PROGRAMACION REALIZADA POR LA ALIANZA| INSTALACIÓN PROGRAMADA PARA EL 2025-11-24 | 27/11/2025 SE REALIZA INSTALACIÓN DE DATÁFONO ADICIONAL EN EL PUNTO, SE CAPACITA AL SEÑOR EFRÉN MORENO SE REALIZA SOLO RETIRO DE NEQUI DEBIDO A QUE NINGUNO DE LOS PRESENTES MANEJA TARJETA BANCOLOMBIA | T95: VISITA TECNICA | U95: OB001410 | V95: TIPO I | W95: TERRESTRE | X95: ALARCON AREVALO JOHAN STIVEN | Y95: 1 | Z95: 0 | AA95: 75096 | AB95: 75096 | AC95: 75096
A96: SANTA MARTA | B96: COSTA | C96: 0004-0001 | D96: 47001 | E96: TA-25-1315941 | F96: 3007082174 | G96: APERTURA | H96: CB CRECIMIENTO ALIANZA - OTRAS LISTAS | I96: MAGDALENA | J96: SANTA MARTA | K96: PTM SANTA MARTA ESTACION DE SE | L96: REDEBAN | M96: FO-25-1852643 | N96: 45982.333 | O96: 45982.668 | R96: EJECUTADO | S96: 20/11/2025 20-11 PROGRAMACION REALIZADA POR LA ALIANZA| INSTALACIÓN PROGRAMADA PARA EL 2025-11-21 | 22/11/2025 SE REALIZA APERTURA ADE CORRESPONDA BANCARIO A SATISFACCIÓN DEL CLIENTE, NO SE REALIZA CAPACITACIÓN SOMOS BANCOLOMBIA YA QUE EL USUARIO O LA CONTRASEÑA DE PRUEBA QUE NOS DAN A LOS TÉCNICOS ESTABA BLOQUEADA Y NO HABÍA ACCESO A LA PÁGINA | T96: VISITA TECNICA | U96: FB001529 | V96: TIPO I | W96: TERRESTRE | X96: THOMAS CAMPO SIGIFREDO SEGUNDO | Y96: 1 | Z96: 0 | AA96: 75096 | AB96: 75096 | AC96: 75096
A97: CALI | B97: SUROCCIDENTE Y EJE CAFETERO | C97: 0004-0003 | D97: 19001 | E97: TA-25-1315942 | F97: 3007081882 | G97: APERTURA | H97: CB CRECIMIENTO ALIANZA - OTRAS LISTAS | I97: CAUCA | J97: POPAYAN | K97: PTM POPAYAS TIENDA LA 14N | L97: REDEBAN | M97: FO-25-1852646 | N97: 45982.333 | O97: 45985.681 | P97: AGREGADOR | Q97: COMCARD - PTM | R97: EJECUTADO | S97: 20/11/2025 20-11 PROGRAMACION REALIZADA POR LA ALIANZA| INSTALACIÓN PROGRAMADA PARA EL 2025-11-24 | 25/11/2025 SE INGRESA EQUIPO PREINTALADO NO ENCIENDE SE CAMBIA EQUIPO SE INSTALA BASE FUENTE CUBRE CLAVES SE INSTALA SISTEMA OPERATIVO VERSIÓN CREACIÓN DE USUARIOS PRUEBAS NO SE REALIZAN GENERA RECHAZO SE LLAMO A LA ENTIDAD INFORMAN PUNTO ESTA INACTIVO POR PARTE LA ALIANZA PTM CAPACITACIÓN AL CB SE INSTALA AVISO EXTERIOR FLANGER DISPLAY LEGAL DE HORARIO SE ENTREGAN ROLLOS DE REDEBA SE HACE MARCACIÓN DE CÓDIGO DEL PUNTO POR ORDEN DE REDEBAN | T97: VISITA TECNICA | U97: AE001890 | V97: TIPO III | W97: TERRESTRE | X97: GIMBUEL LASSO LUIS GERMAN | Y97: 1 | Z97: 0 | AA97: 275729 | AB97: 196537 | AC97: 275729
A98: MEDELLIN | B98: NOROCCIDENTE | C98: 0004-0005 | D98: 5001 | E98: TA-25-1319220 | F98: 3007082268 | G98: APERTURA | H98: CB CRECIMIENTO ALIANZA - NUEVO | I98: ANTIOQUIA | J98: MEDELLIN | K98: DISTRICOL LLAVE MAGICA DISTRIB | L98: REDEBAN | M98: FO-25-1859217 | N98: 45985.333 | O98: 45986.652 | R98: EJECUTADO | S98: 21/11/2025 21-11 PROGRAMACION REALIZADA POR LA ALIANZA| INSTALACIÓN PROGRAMADA PARA EL 2025-11-25 | 25/11/2025 SE INSTALAN EQUIPOS OK | T98: VISITA TECNICA | U98: OB002009 | V98: TIPO I | W98: TERRESTRE | X98: QUINTERO SANCHEZ JUAN SEBASTIAN | Y98: 1 | Z98: 0 | AA98: 75096 | AB98: 75096 | AC98: 75096
A99: MEDELLIN | B99: NOROCCIDENTE | C99: 0004-0005 | D99: 5001 | E99: TA-25-1319221 | F99: 3007082269 | G99: APERTURA | H99: CB CRECIMIENTO ALIANZA - NUEVO | I99: ANTIOQUIA | J99: MEDELLIN | K99: DISTRICOL AMERICAN D&L | L99: REDEBAN | M99: FO-25-1859221 | N99: 45985.333 | O99: 45986.66 | R99: EJECUTADO | S99: 21/11/2025 21-11 PROGRAMACION REALIZADA POR LA ALIANZA| INSTALACIÓN PROGRAMADA PARA EL 2025-11-25 | 25/11/2025 INSTALACIÓN CB OK | T99: VISITA TECNICA | U99: OB002010 | V99: TIPO I | W99: TERRESTRE | X99: BADEL ACUÑA LUIS ALBERTO | Y99: 1 | Z99: 0 | AA99: 75096 | AB99: 75096 | AC99: 75096
A100: MEDELLIN | B100: NOROCCIDENTE | C100: 0004-0005 | D100: 5001 | E100: TA-25-1319222 | F100: 3007082270 | G100: APERTURA | H100: CB CRECIMIENTO ALIANZA - NUEVO | I100: ANTIOQUIA | J100: MEDELLIN | K100: DISTRICOL VICTORIA ACCESORIOS | L100: REDEBAN | M100: FO-25-1859227 | N100: 45985.333 | O100: 45986.679 | R100: EJECUTADO | S100: 21/11/2025 21-11 PROGRAMACION REALIZADA POR LA ALIANZA| INSTALACIÓN PROGRAMADA PARA EL 2025-11-25 | 25/11/2025 INSTALACIÓN CB OK | T100: VISITA TECNICA | U100: OB002011 | V100: TIPO I | W100: TERRESTRE | X100: BADEL ACUÑA LUIS ALBERTO | Y100: 1 | Z100: 0 | AA100: 75096 | AB100: 75096 | AC100: 75096
A101: CUCUTA | B101: SANTANDERES | C101: 0004-0008 | D101: 54001 | E101: TA-25-1319224 | F101: 3007082264 | G101: APERTURA | H101: CB CRECIMIENTO ALIANZA - NUEVO | I101: NORTE DE SANTANDER | J101: CUCUTA | K101: DISTRICOL MINI MARKET TECNOFER | L101: REDEBAN | M101: FO-25-1859234 | N101: 45985.333 | O101: 45986.718 | R101: EJECUTADO | S101: 21/11/2025 21-11 PROGRAMACION REALIZADA POR LA ALIANZA| INSTALACIÓN PROGRAMADA PARA EL 2025-11-25 | 25/11/2025 SE REALIZA LLAMADA TELEFÓNICA AL NÚMERO 3205528850 SE HABLÓ CON EL SR JOHAN Y MANIFIESTA QUE LO VISITEMOS A LAS 2PM , | 26/11/2025 SE REALIZA VISITA AL COMERCIO Y SE INSTALA DATAFONO LECTORA CABLEADO PUBLICIDAD BANCOLOMBIA OK, SOMOS BANCOLOMBIA OK, PRUEBAS EXITOSAS | T101: VISITA TECNICA | U101: OB002013 | V101: TIPO I | W101: TERRESTRE | X101: MORA VEGA JEAMPIER | Y101: 1 | Z101: 0 | AA101: 75096 | AB101: 75096 | AC101: 75096
A102: BUCARAMANGA | B102: SANTANDERES | C102: 0004-0008 | D102: 68001 | E102: TA-25-1319226 | F102: 3007082262 | G102: APERTURA | H102: CB CRECIMIENTO ALIANZA - NUEVO | I102: SANTANDER | J102: BUCARAMANGA | K102: DISTRICOL YUYIS MULTISERVICIO | L102: REDEBAN | M102: FO-25-1859238 | N102: 45985.333 | O102: 45985.492 | R102: EJECUTADO | S102: 21/11/2025 21-11 PROGRAMACION REALIZADA POR LA ALIANZA| INSTALACIÓN PROGRAMADA PARA EL 2025-11-24 | 24/11/2025 SE INSTALA PUBLICIDAD COMPLETA DATAFONO, LECTOR, PINPAD MAGIC BOX, SE CAPACITA CLIENTE MANEJO CORRESPONSAL, CIERRES CUATRO DIARIO, COMPENSACIÓN, MANEJO DATAFONO, PRUEBAS OK, INSTALACION EXITOSA | T102: VISITA TECNICA | U102: OB002014 | V102: TIPO I | W102: TERRESTRE | X102: GELVEZ MOGOLLON JOSE ELISEO | Y102: 1 | Z102: 0 | AA102: 75096 | AB102: 75096 | AC102: 75096
A103: BUCARAMANGA | B103: SANTANDERES | C103: 0004-0008 | D103: 68001 | E103: TA-25-1319227 | F103: 3007082263 | G103: APERTURA | H103: CB CRECIMIENTO ALIANZA - NUEVO | I103: SANTANDER | J103: BUCARAMANGA | K103: DISTRICOL ADOARTE | L103: REDEBAN | M103: FO-25-1859241 | N103: 45985.333 | O103: 45985.488 | R103: EJECUTADO | S103: 21/11/2025 21-11 PROGRAMACION REALIZADA POR LA ALIANZA| INSTALACIÓN PROGRAMADA PARA EL 2025-11-24 | 24/11/2025 EN COMUNICACIÓN CON EL SEÑOR CARLOS CONTRERAS NOS INDICA QUE TIENE LA DISPONIBILIDAD DE ATENDERNOS EN HORAS AM | 24/11/2025 INSTALACION Y ADECUACION DE CB, INSTALACION DE DATAFONO LECTORA FUENTE CABLE PACTHCORD, PINPAD, PRUEBAS OK, ADESIVO IDENTIFICADOR OK, CUBRE CLAVE OK, FLANGGER Y DISPLAY LEGAL OK Y AVISO EXTERIO OK. SE EXPLICA SOBRE LA WEB SOMOS BANCOLOMBIA, CIERRE Y CUADRE DIARIO, SE EXPLICA SOBRE USO Y MANEJO DE DATAFONO. PRUEBAS OK | T103: VISITA TECNICA | U103: OB002015 | V103: TIPO I | W103: TERRESTRE | X103: MARIÑO PABON JORGE ENRIQUE | Y103: 1 | Z103: 0 | AA103: 75096 | AB103: 75096 | AC103: 75096
A104: CALI | B104: SUROCCIDENTE Y EJE CAFETERO | C104: 0004-0003 | D104: 76364 | E104: TA-25-1319230 | F104: 3007082266 | G104: APERTURA | H104: CB CRECIMIENTO ALIANZA - NUEVO | I104: VALLE DEL CAUCA | J104: JAMUNDI | K104: DISTRICOL VARIEDADES Y COTELER | L104: REDEBAN | M104: FO-25-1859244 | N104: 45985.333 | O104: 45986.685 | R104: EJECUTADO | S104: 21/11/2025 21-11 PROGRAMACION REALIZADA POR LA ALIANZA| INSTALACIÓN PROGRAMADA PARA EL 2025-11-25 | 26/11/2025 SE VISITA ESTABLECIMIENTO, SE REALIZA INSTALACIÓN CORRESPONSAL BANCOLOMBIA PURO. TRANSACCIONES DE PRUEBA EXITOSAS. SE CAPACITA Y SE INSTALA PUBLICIDAD COMPLETA. | T104: VISITA TECNICA | U104: OB002016 | V104: TIPO II | W104: TERRESTRE | X104: BOLAÑOS TABORDA JORGE ENRIQUE | Y104: 1 | Z104: 0 | AA104: 163814 | AB104: 140396 | AC104: 163814
A105: YOPAL | B105: REMOTAS | C105: 0004-0007 | D105: 85001 | E105: TA-25-1319231 | F105: 3007082271 | G105: APERTURA | H105: CB CRECIMIENTO ALIANZA - NUEVO | I105: CASANARE | J105: YOPAL | K105: DISTRICOL SUMERCE | L105: REDEBAN | M105: FO-25-1859246 | N105: 45985.333 | O105: 45986.713 | R105: EJECUTADO | S105: 21/11/2025 21-11 PROGRAMACION REALIZADA POR LA ALIANZA| INSTALACIÓN PROGRAMADA PARA EL 2025-11-25 | 25/11/2025 SE VISITA COMERCIO, SE INSTALA DATÁFONO LECTOR BASE Y CUBRE TECLADO. PRUEBAS OK. OPERATIVO EL SERVICIO. NO SE REALIZA PRUEBA DE TRANSFERENCIA NO SE CUENTA CON TARJETA. SOMOS BANCOLOMBIA OK | T105: VISITA TECNICA | U105: OB002017 | V105: TIPO I | W105: TERRESTRE | X105: BERNAL ELAICA EDGAR ALEXIS | Y105: 1 | Z105: 0 | AA105: 75096 | AB105: 75096 | AC105: 75096
A106: PASTO | B106: SUROCCIDENTE Y EJE CAFETERO | C106: 0004-0003 | D106: 86001 | E106: TA-25-1319232 | F106: 3007082267 | G106: APERTURA | H106: CB CRECIMIENTO ALIANZA - NUEVO | I106: PUTUMAYO | J106: MOCOA | K106: DISTRICOL LA GRANJA DE MOCOA | L106: REDEBAN | M106: FO-25-1859250 | N106: 45985.333 | O106: 45987.5 | R106: EJECUTADO | S106: 21/11/2025 21-11 PROGRAMACION REALIZADA POR LA ALIANZA| INSTALACIÓN PROGRAMADA PARA EL 2025-11-25 | 25/11/2025 POR COMPLICACIONES EN EL TRANSPORTE SE ESTARÁ DESPLAZANDO HOY AL MUNICIPIO PARA MAÑANA REALIZAR LA APERTURA | 26/11/2025 SE VISITA EL COMERCIO PARA REALIZAR APERTURA DEL CORRESPONSAL, SE INSTALA DATÁFONO, CON LECTORA BASE Y CABLEADO, SE DEJA ROLLOS, SE INSTALA PUBLICIDAD, SE CAPACITA OK, SE HACE PRUEBAS EXCEPTO DE RECAUDO POR NO TENER MEDIOS PARA REALIZARLA, SOMOS BANCOLOMBIA OK, CB OPERATIVO | T106: VISITA TECNICA | U106: OB002018 | V106: TIPO IV | W106: TERRESTRE | X106: GUERRERO RAMIREZ OSCAR DARIO | Y106: 1 | Z106: 0 | AA106: 504833 | AB106: 196537 | AC106: 504833
A107: BOGOTA | B107: CUNDINAMARCA | C107: 0004-0004 | D107: 11001 | E107: TA-25-1319233 | F107: 3007082261 | G107: APERTURA | H107: CB CRECIMIENTO ALIANZA - NUEVO | I107: CUNDINAMARCA | J107: BOGOTA | K107: DISTRICOL TODO EN UNO SUBA | L107: REDEBAN | M107: FO-25-1859253 | N107: 45985.333 | O107: 45986.725 | R107: EJECUTADO | S107: 21/11/2025 21-11 PROGRAMACION REALIZADA POR LA ALIANZA| INSTALACIÓN PROGRAMADA PARA EL 2025-11-25 | 25/11/2025 SE VISITA COMERCIO, SE INSTALA CB BANCOLOMBIA, SE REALIZAN PRUEBAS OK, SE BRINDA CAPACITACIÓN DE USO, SE CREAN USUARIOS DEL CLIENTE, SE INSTALA PUBLICIDAD COMPLETA, NO UPS, SE EVIDENCIA EN CÁMARA Y COMERCIO QUE LA ACTIVIDAD ECONÓMICA DEL ESTABLECIMIENTO NO COMPRENDE JUEGOS DE AZAR O APUESTAS, SE ANEXA CÁMARA Y COMERCIO DONDE LOS CÓDIGOS DE ACTIVIDAD ECONÓMICA MUESTRAN OTRA ACTIVIDAD, LOS COLORES DEL ESTABLECIMIENTO SON DE LA RAZÓN SOCIAL ANTIGUA, ESTÁ INFORMACIÓN SE LE SUMINISTRA AL COORDINADOR Y A JHON SAMBONY PARA LA AUTORIZACIÓN DE INSTALACIÓN DE CB Y AFICIONAR EL PINPAD. | T107: VISITA TECNICA | U107: OB002019 | V107: TIPO I | W107: TERRESTRE | X107: VEGA MANRIQUE JONATAN MAURICIO | Y107: 1 | Z107: 0 | AA107: 75096 | AB107: 75096 | AC107: 75096
A108: APARTADO | B108: NOROCCIDENTE | C108: 0004-0005 | D108: 5837 | E108: TA-25-1330511 | F108: 3007078041 | G108: APERTURA | H108: DATAFONO ADICIONAL - ALIANZA | I108: ANTIOQUIA | J108: TURBO | K108: PTM LA JULIA OROZCO TIENDA MIX | L108: REDEBAN | M108: FO-25-1884056 | N108: 45988.333 | O108: 45989.618 | P108: AGREGADOR | Q108: COMCARD - PTM | R108: EJECUTADO | S108: 26/11/2025 26-11 PROGRAMACION REALIZADA POR LA ALIANZA| INSTALACIÓN PROGRAMADA PARA EL 2025-11-28 | 28/11/2025 SE INSTALA DATAFONO NUEVO,BASE,LECTORA Y MAGIBOX. SE HACEN PRUEBAS Y SE DEJA TODO OK | T108: VISITA TECNICA | U108: OB004863 | V108: TIPO II | W108: TERRESTRE | X108: SALDARRIAGA MIRANDA SANTIAGO | Y108: 1 | Z108: 0 | AA108: 163814 | AB108: 140396 | AC108: 163814
A109: BOGOTA | B109: CUNDINAMARCA | C109: 0004-0004 | D109: 11001 | E109: TA-25-1330513 | F109: 3007082234 | G109: APERTURA | H109: CB CRECIMIENTO ALIANZA - OTRAS LISTAS | I109: CUNDINAMARCA | J109: BOGOTA | K109: PTM BOGOTA DROGUERIA SPECIALME | L109: REDEBAN | M109: FO-25-1904464 | FO-25-1884063 | N109: 45988.333 | O109: 45989.711 | R109: EJECUTADO | EJECUTADO/CANCELADO | S109: 28/11/2025 SE REALIZA INSTALACIÓN DE CB, SE INSTALA DATÁFONO, LECTORA, BASE, 40 ROLLOS, CABLE DE RED Y SE REALIZA CAPACITACIÓN DEL CB AL SR SERGIO | T109: VISITA TECNICA | U109: AE006359 | V109: TIPO I | W109: TERRESTRE | X109: ALARCON AREVALO JOHAN STIVEN | Y109: 1 | Z109: 0 | AA109: 75096 | AB109: 75096 | AC109: 75096
A110: MEDELLIN | B110: NOROCCIDENTE | C110: 0004-0005 | D110: 5001 | E110: TA-25-1330535 | F110: 3007082356 | G110: APERTURA | H110: CB CRECIMIENTO ALIANZA - NUEVO | I110: ANTIOQUIA | J110: MEDELLIN | K110: PTM MEDELLIN ECONOFARMA | L110: REDEBAN | M110: FO-25-1884132 | N110: 45988.333 | O110: 45988.573 | R110: EJECUTADO | S110: 26/11/2025 26-11 PROGRAMACION REALIZADA POR LA ALIANZA| INSTALACIÓN PROGRAMADA PARA EL 2025-11-27 | 27/11/2025 INSTALACIÓN CB OK | T110: VISITA TECNICA | U110: OB004128-OB004836 | V110: TIPO I | W110: TERRESTRE | X110: BADEL ACUÑA LUIS ALBERTO | Y110: 1 | Z110: 0 | AA110: 75096 | AB110: 75096 | AC110: 75096
A111: MEDELLIN | B111: NOROCCIDENTE | C111: 0004-0005 | D111: 5001 | E111: TA-25-1330536 | F111: 3007082357 | G111: APERTURA | H111: CB CRECIMIENTO ALIANZA - NUEVO | I111: ANTIOQUIA | J111: MEDELLIN | K111: PTM MEDELLIN DROGUERIA FARMARK | L111: REDEBAN | M111: FO-25-1884135 | N111: 45988.333 | O111: 45988.578 | R111: EJECUTADO | S111: 26/11/2025 26-11 PROGRAMACION REALIZADA POR LA ALIANZA| INSTALACIÓN PROGRAMADA PARA EL 2025-11-27 | 27/11/2025 SE HACE IMPLEMENTACION OK EQUIPOS OPERATIVOS PRUEBAS EXITOSAS SOMOS BANCOLOMBIA INACTIVO | T111: VISITA TECNICA | U111: OB004837 | V111: TIPO I | W111: TERRESTRE | X111: DIAZ ZABALA FRANCIS DUBAN | Y111: 1 | Z111: 0 | AA111: 75096 | AB111: 75096 | AC111: 75096
A112: MEDELLIN | B112: NOROCCIDENTE | C112: 0004-0005 | D112: 5001 | E112: TA-25-1330537 | F112: 3007082358 | G112: APERTURA | H112: CB CRECIMIENTO ALIANZA - NUEVO | I112: ANTIOQUIA | J112: MEDELLIN | K112: PTM MEDELLIN TIENDA DE COSMETI | L112: REDEBAN | M112: FO-25-1884136 | N112: 45988.333 | O112: 45988.724 | R112: EJECUTADO | S112: 26/11/2025 26-11 PROGRAMACION REALIZADA POR LA ALIANZA| INSTALACIÓN PROGRAMADA PARA EL 2025-11-27 | 27/11/2025 SE HACE IMPLEMENTACION OK EQUIPOS OPERATIVOS PRUEBAS EXITOSAS SOMOS BANCOLOMBIA INACTIVO | T112: VISITA TECNICA | U112: OB004838 | V112: TIPO I | W112: TERRESTRE | X112: DIAZ ZABALA FRANCIS DUBAN | Y112: 1 | Z112: 0 | AA112: 75096 | AB112: 75096 | AC112: 75096
A113: MEDELLIN | B113: NOROCCIDENTE | C113: 0004-0005 | D113: 5120 | E113: TA-25-1330538 | F113: 3007082326 | G113: APERTURA | H113: CB CRECIMIENTO ALIANZA - NUEVO | I113: ANTIOQUIA | J113: CACERES | K113: PTM CACERES DROGUERIA SUPERFAR | L113: REDEBAN | M113: FO-25-1884140 | N113: 45988.333 | O113: 45989.631 | R113: EJECUTADO | S113: 26/11/2025 26-11 PROGRAMACION REALIZADA POR LA ALIANZA| INSTALACIÓN PROGRAMADA PARA EL 2025-11-28 | 28/11/2025 SE REALIZÓ INSTALACIÓN DE CB BANCOLOMBIA OK, PRUEBAS OK, USUARIOS OK, TELECARGA DRNA. | T113: VISITA TECNICA | U113: OB004839 | V113: TIPO IV | W113: TERRESTRE | X113: CALDERA SALCEDO CARLOS JULIO | Y113: 1 | Z113: 0 | AA113: 504833 | AB113: 196537 | AC113: 504833
A114: MEDELLIN | B114: NOROCCIDENTE | C114: 0004-0005 | D114: 5615 | E114: TA-25-1330541 | F114: 3007082320 | G114: APERTURA | H114: CB CRECIMIENTO ALIANZA - NUEVO | I114: ANTIOQUIA | J114: RIONEGRO | K114: PTM RIONEGRO TIENDA LA ESQUINA | L114: REDEBAN | M114: FO-25-1884146 | N114: 45988.333 | O114: 45989.636 | R114: EJECUTADO | S114: 26/11/2025 26-11 PROGRAMACION REALIZADA POR LA ALIANZA| INSTALACIÓN PROGRAMADA PARA EL 2025-11-28 | 28/11/2025 LA INSTALACIÓN DEL CORRESPONSAL BANCOLOMBIA SE REALIZÓ EXITOSAMENTE, INCLUYENDO LA PUESTA EN MARCHA DE LOS EQUIPOS , SE BRINDÓ CAPACITACIÓN AL CLIENTE SOBRE EL MANEJO DEL EQUIPO Y LOS PROCESOS DE TRANSACCIONES, ASEGURANDO UN USO ADECUADO DESDE EL PRIMER DÍA. ASIMISMO, SE INSTALARON LOS AVISOS SOLICITADOS, UBICÁNDOLOS DENTRO DEL LOCAL EN CUMPLIMIENTO DE LAS NORMAS DEL EDIFICIO, QUE NO PERMITEN INSTALACIÓN EN LA FACHADA EXTERNA. FINALMENTE, SE VERIFICÓ QUE TODO QUEDARA OPERATIVO Y EN CONDICIONES ÓPTIMAS PARA INICIAR LA ATENCIÓN AL PÚBLICO. | T114: VISITA TECNICA | U114: OB004841-OB004138 | V114: TIPO II | W114: TERRESTRE | X114: MARTINEZ TOVAR OSCAR DAVID | Y114: 1 | Z114: 0 | AA114: 163814 | AB114: 140396 | AC114: 163814
A115: MEDELLIN | B115: NOROCCIDENTE | C115: 0004-0005 | D115: 5690 | E115: TA-25-1330542 | F115: 3007082341 | G115: APERTURA | H115: CB CRECIMIENTO ALIANZA - NUEVO | I115: ANTIOQUIA | J115: SANTO DOMINGO | K115: PTM MEDELLIN AGENCIA COONORTE | L115: REDEBAN | M115: FO-25-1884148 | N115: 45988.333 | O115: 45989.576 | R115: EJECUTADO | S115: 26/11/2025 26-11 PROGRAMACION REALIZADA POR LA ALIANZA| INSTALACIÓN PROGRAMADA PARA EL 2025-11-28 | 28/11/2025 SE INSTALA PUBLICIDAD Y EQUIPOS A PETICIÓN DEL USUARIO, SERVICIOS OK, CAPACITACIÓN OK, USUARIO SOMOS BANCOLOMBIA NO CREADO POR EL BANCO | T115: VISITA TECNICA | U115: OB004842 | V115: TIPO II | W115: TERRESTRE | X115: BARRIENTOS HERNANDEZ CRISTIAN HORACIO | Y115: 1 | Z115: 0 | AA115: 163814 | AB115: 140396 | AC115: 163814
A116: BARRANQUILLA | B116: COSTA | C116: 0004-0001 | D116: 8001 | E116: TA-25-1330544 | F116: 3007082274 | G116: APERTURA | H116: CB CRECIMIENTO ALIANZA - NUEVO | I116: ATLANTICO | J116: BARRANQUILLA | K116: PTM BARRANQUILLA DROGUERIA Y V | L116: REDEBAN | M116: FO-25-1884154 | N116: 45988.333 | O116: 45988.743 | R116: EJECUTADO | S116: 26/11/2025 26-11 PROGRAMACION REALIZADA POR LA ALIANZA| INSTALACIÓN PROGRAMADA PARA EL 2025-11-27 | 27/11/2025 SE INSTALAN EQUIPOS, ACCESORIOS Y PUBLICIDAD PARA CB BANCOLOMBIA | T116: VISITA TECNICA | U116: OB004843 - OB004151 | V116: TIPO I | W116: TERRESTRE | X116: DE AVILA SIADES ALBERTO ENRIQUE | Y116: 1 | Z116: 0 | AA116: 75096 | AB116: 75096 | AC116: 75096
A117: BARRANQUILLA | B117: COSTA | C117: 0004-0001 | D117: 8001 | E117: TA-25-1330546 | F117: 3007082275 | G117: APERTURA | H117: CB CRECIMIENTO ALIANZA - NUEVO | I117: ATLANTICO | J117: BARRANQUILLA | K117: PTM ROBERTO DANIEL SAVIGNANO O | L117: REDEBAN | M117: FO-25-1884162 | N117: 45988.333 | O117: 45988.618 | R117: EJECUTADO | S117: 26/11/2025 26-11 PROGRAMACION REALIZADA POR LA ALIANZA| INSTALACIÓN PROGRAMADA PARA EL 2025-11-27 | 27/11/2025 SE INSTALAN EQUIPOS Y PUBLICIDAD PARA CB BANCOLOMBIA CORRESPONSAL MIXTO | T117: VISITA TECNICA | U117: OB004844 - OB004156 | V117: TIPO I | W117: TERRESTRE | X117: DE AVILA SIADES ALBERTO ENRIQUE | Y117: 1 | Z117: 0 | AA117: 75096 | AB117: 75096 | AC117: 75096
A118: CARTAGENA | B118: COSTA | C118: 0004-0001 | D118: 13836 | E118: TA-25-1330547 | F118: 3007082350 | G118: APERTURA | H118: CB CRECIMIENTO ALIANZA - NUEVO | I118: BOLIVAR | J118: TURBACO | K118: PTM TURBACO TIENDA Y VARIEDADE | L118: REDEBAN | M118: FO-25-1884169 | N118: 45988.333 | O118: 45989.569 | R118: EJECUTADO | S118: 26/11/2025 26-11 PROGRAMACION REALIZADA POR LA ALIANZA| INSTALACIÓN PROGRAMADA PARA EL 2025-11-28 | 28/11/2025 SE ESCALA NOVEDAD POR NO TENER NOMBRE DE NEGOCIO EL CUAL AUTORIZARON Y SE INSTALA Y SE ADJUNTA FOTO DE PRODUCTOS DENTRO DEL NEGOCIO | 29/11/2025 SE REALIZA INSTALACIÓN DE CORRESPONSAL AUTORIZADO SE INSTALA PUBLICIDAD SE REALIZAN PRUEBAS DE CONSULTA DE SALDO CONSIGNACIÓN RETIRO Y SE PRUEBA LECTOR DE BARRAS CON FACTURA SE CAPACITA Y TODO QUEDA OK | T118: VISITA TECNICA | U118: OB004845 | V118: TIPO II | W118: TERRESTRE | X118: MARTINEZ SALGUEDO ANDRES AUGUSTO | Y118: 1 | Z118: 0 | AA118: 163814 | AB118: 140396 | AC118: 163814
A119: MANIZALES | B119: SUROCCIDENTE Y EJE CAFETERO | C119: 0004-0002 | D119: 17001 | E119: TA-25-1330548 | F119: 3007082334 | G119: APERTURA | H119: CB CRECIMIENTO ALIANZA - NUEVO | I119: CALDAS | J119: MANIZALES | K119: PTM MANIZALES PAPELERIA LINDS | L119: REDEBAN | M119: FO-25-1884173 | N119: 45988.333 | O119: 45989.559 | R119: EJECUTADO | S119: 26/11/2025 26-11 PROGRAMACION REALIZADA POR LA ALIANZA| INSTALACIÓN PROGRAMADA PARA EL 2025-11-28 | 28/11/2025 SE REALIZA INSTALACIÓN DE DATAFONO Y ACCESORIOS BASE LECTOR 40 ROLLOS Y PUBLICIDAD SE CAPACITA AL COMERCIO SE CREAN USUARIOS SE HACEN PRUEBAS DE CONSULTA DE SALDO SOLAMENTE YA QUE USUARIO NO CUENTA CON HERRAMIENTAS PARA REALIZAR RETIRO RECAUDO NI CONSIGNACIÓN SERVICIO OK | T119: VISITA TECNICA | U119: OB004846 | V119: TIPO I | W119: TERRESTRE | X119: AGUIRRE HENAO RAUL EDUARDO | Y119: 1 | Z119: 0 | AA119: 75096 | AB119: 75096 | AC119: 75096
A120: MANIZALES | B120: SUROCCIDENTE Y EJE CAFETERO | C120: 0004-0002 | D120: 17001 | E120: TA-25-1330549 | F120: 3007082335 | G120: APERTURA | H120: CB CRECIMIENTO ALIANZA - NUEVO | I120: CALDAS | J120: MANIZALES | K120: PTM MANIZALES DROGUERIA FARMAM | L120: REDEBAN | M120: FO-25-1884177 | N120: 45988.333 | O120: 45989.739 | R120: EJECUTADO | S120: 26/11/2025 26-11 PROGRAMACION REALIZADA POR LA ALIANZA| INSTALACIÓN PROGRAMADA PARA EL 2025-11-28 | 28/11/2025 SE REALIZA INSTALACIÓN DE DATAFONO Y ACCESORIOS BASE LECTOR 40 ROLLOS Y PUBLICIDAD SE CAPACITA AL COMERCIO SE CREAN USUARIOS SE HACEN PRUEBAS DE CONSULTA DE SALDO SOLAMENTE YA QUE USUARIO NO CUENTA CON HERRAMIENTAS PARA REALIZAR RETIRO RECAUDO NI CONSIGNACIÓN SERVICIO OK | T120: VISITA TECNICA | U120: OB004847 | V120: TIPO I | W120: TERRESTRE | X120: AGUIRRE HENAO RAUL EDUARDO | Y120: 1 | Z120: 0 | AA120: 75096 | AB120: 75096 | AC120: 75096
... A135: CALI | B135: SUROCCIDENTE Y EJE CAFETERO | C135: 0004-0003 | D135: 76001 | E135: TA-25-1330558 | F135: 3007082306 | G135: APERTURA | H135: CB CRECIMIENTO ALIANZA - NUEVO | I135: VALLE DEL CAUCA | J135: CALI | K135: PTM CALI BY LOVE COSMETICS | L135: REDEBAN | M135: FO-25-1884202 | N135: 45988.333 | O135: 45989.794 | R135: EJECUTADO | S135: 26/11/2025 26-11 PROGRAMACION REALIZADA POR LA ALIANZA| INSTALACIÓN PROGRAMADA PARA EL 2025-11-28 | 29/11/2025 SE LLAMA AL CLIENTE, SE VALIDA INSTALACIÓN Y DISPONIBILIDAD, SE VISITA EL COMERCIO, SE INSTALA DATAFONO, LECTORA, PINPAD, MAGIC BOX, ACCESORIOS EN APERTURA CB BANCOLOMBIA MIXTO, SE CAPACITA, PRUEBAS OK, TELECARGA TRNA | T135: VISITA TECNICA | U135: OB004855 | V135: TIPO I | W135: TERRESTRE | X135: HERRERA MONAR GEOVANNY | Y135: 1 | Z135: 0 | AA135: 75096 | AB135: 75096 | AC135: 75096

Sheet INCIDENTES_BANCOLOMBIA
A1: CIUDAD SEDE | B1: ZONA | C1: CENTRO DE COSTOS LINEACOM | D1: CODIGO DANE | E1: TA/CODIGO ACTIVIDAD | F1: CODIGO CB | G1: ACTIVIDAD | H1: DEPARTAMENTO | I1: CIUDAD | J1: NOMBRE DEL CB | K1: RED | L1: FO | M1: FECHA ASIGNACION A LINEA COMUNICACIONES | N1: FECHA CIERRE DEL TICKET (DD/MM/AAAA HH:MM) | O1: ACOMETIDA | P1: GRUPO_FALLA | Q1: CATEGORIA | R1: FALLA | S1: FORMATO | T1: CADENA | U1: ESTADO | V1: OBSERVACION | W1: FORMA DE ATENCION | X1: TERMINAL(ES) | Y1: TIPIFICACION | Z1: TIPO DE TRAYECTO | AA1: NOMBRE DEL TECNICO | AB1: DIAS DE VISITA | AC1: DIA ADICIONAL | AD1: VALOR DIAS ACTIVIDAD FACTURABLES | AE1: VALOR DIAS ACOMPAÑAMIENTO FACTURABLES | AF1: VALOR TOTAL
A2: CALI | B2: SUROCCIDENTE Y EJE CAFETERO | C2: 0004-0003 | D2: 19075 | E2: 2940406 | F2: 3007029797 | G2: INCIDENTE | H2: CAUCA | I2: BALBOA | J2: BARRIO BELLO HORIZONTE BALBOA | K2: REDEBAN | L2: FO-25-1739872 | M2: 45957.543 | N2: 45966.606 | O2: NO | P2: HARDWARE | Q2: NO ENCIENDE | R2: DAÑO POS | S2: UNO A UNO | T2: CB UNO A UNO | U2: EJECUTADO | V2: 27/10/2025 EN COMUNICACION CON EL SR DANIELA BOTINA AL NUMERO 3112131929 SE CONFIRMAR FALLA Y DATOS . SE ESCALA PARA VISITA. | 31/10/2025 SE DDEBE VALIDAR DESPLAZAMIENTO PARA LA PROXIMA SEMANA YA QUE POR TEMAS DE ORDEN PUBLICO NO ES POSIBLE DESPLAZARSE EN EL MOMENTO. | 05/11/2025 EQUIPO NO ENCIENDE SE PROCEDE A CAMBIAR SE HACEN PRUEBAS OK TELECARGA DRNA | W2: VISITA TECNICA | X2: BL01Y339 | Y2: TIPO IV | Z2: TERRESTRE | AA2: GIMBUEL LASSO LUIS GERMAN | AB2: 1 | AC2: 0 | AD2: 479589 | AE2: 196537 | AF2: 479589
A3: MANIZALES | B3: SUROCCIDENTE Y EJE CAFETERO | C3: 0004-0002 | D3: 17513 | E3: 2949931 | F3: 3007057847 | G3: INCIDENTE | H3: CALDAS | I3: PACORA | J3: BARRIO PARQUE PRINCIPAL PACORA | K3: REDEBAN | L3: FO-25-1748333 | M3: 45959.333 | N3: 45966.716 | O3: NO | P3: HARDWARE | Q3: NO ENCIENDE | R3: DAÑO POS | S3: CB UNO A UNO | T3: CB UNO A UNO | U3: EJECUTADO | V3: 29/10/2025 SE ESCALA PARA VISITA. LLAMAR ANTES DE VISITAR, CONFIRMAR FALLA Y DATOS | 31/10/2025 SE ENCUENTRA PROBLEMAS CON LA VIA HACIA PACORA NO SE PUEDE REALIZAR DESPLAZAMIENTO , SE VALIDARA LA PROXIMA SEMANA | 05/11/2025 SE VISITA COMERCIO SE IDENTIFICA DATÁFONO SIN ENCENDER SOLO PITA SE REALIZA CAMBIO DE DATÁFONO SE REALIZA PRUEBAS OK | W3: VISITA TECNICA | X3: HA00F657 | Y3: TIPO III | Z3: TERRESTRE | AA3: LOAIZA LOPEZ JHON FREDDY | AB3: 1 | AC3: 0 | AD3: 275729 | AE3: 196537 | AF3: 275729
A4: PASTO | B4: SUROCCIDENTE Y EJE CAFETERO | C4: 0004-0003 | D4: 86749 | E4: 2952163 | F4: 3007032851 | G4: INCIDENTE | H4: PUTUMAYO | I4: SIBUNDOY | J4: BARRIO CASTELVI SIBUNDOY | K4: REDEBAN | L4: FO-25-1750657 | M4: 45959.437 | N4: 45966.622 | O4: NO | P4: HARDWARE | Q4: TECLADO | R4: DAÑO POS | S4: CB UNO A UNO | T4: CB UNO A UNO | U4: EJECUTADO | V4: 29/10/2025 SE ESCALA PARA VISITA. LLAMAR ANTES DE VISITAR, CONFIRMAR FALLA Y DATOS | 01/11/2025 SE DEBE REALIZAR DESPLAZAMIENTO LA PROXIMA SEMANA YA QUE POR PROBLEMAS EN LA VIA NO SE PUEDDE VIAJAR. | 05/11/2025 SE REALIZA CAMBIO DE DATÁFONO POR DAÑO EN TECLADO, SE RECONFIGURA OK PARÁMETROS OK Y SE REALIZAN PRUEBAS EXITOSAS DE TRANSACCIÓNES | W4: VISITA TECNICA | X4: 9A002709 | Y4: TIPO III | Z4: TERRESTRE | AA4: PAZ MARTINEZ RICHARD HUMBERTO | AB4: 1 | AC4: 0 | AD4: 275729 | AE4: 196537 | AF4: 275729
A5: MEDELLIN | B5: NOROCCIDENTE | C5: 0004-0005 | D5: 5411 | E5: 2954435 | F5: 3007019441 | G5: INCIDENTE | H5: ANTIOQUIA | I5: LIBORINA | J5: SIMON BOLIVAR LIBORINA | K5: REDEBAN | L5: FO-25-1753516 | M5: 45959.634 | N5: 45962.394 | O5: NO | P5: HARDWARE | Q5: LECTOR DE BARRAS | R5: CABLE LECTORA AVERIADO | S5: CB UNO A UNO | T5: CB UNO A UNO | U5: EJECUTADO | V5: 29/10/2025 SE ESCALA PARA VISITA. LLAMAR ANTES DE VISITAR, CONFIRMAR FALLA Y DATOS | 01/11/2025 SE CAMBIA CABLE DE LECTOR | W5: VISITA TECNICA | X5: AAAAA342 | Y5: TIPO III | Z5: TERRESTRE | AA5: CASTAÑEDA PALACIO CARLOS FELIPE | AB5: 1 | AC5: 0 | AD5: 275729 | AE5: 196537 | AF5: 275729
A6: MEDELLIN | B6: NOROCCIDENTE | C6: 0004-0005 | D6: 5861 | E6: 2956913 | F6: 3007018510 | G6: INCIDENTE | H6: ANTIOQUIA | I6: VENECIA | J6: PARQUE PPAL II VENECIA | K6: REDEBAN | L6: FO-25-1755916 | M6: 45960.372 | N6: 45962.545 | O6: NO | P6: HARDWARE | Q6: COMUNICACION | R6: DAÑO POS | S6: CB UNO A UNO | T6: CB UNO A UNO | U6: EJECUTADO | V6: 30/10/2025 SE ESCALA PARA VISITA. LLAMAR ANTES DE VISITAR, CONFIRMAR FALLA Y DATOS | 01/11/2025 CIERRE EN LA VÍA POR DERRUMBE , SE ESPERA EL ACCESO EN LA VÍA | 01/11/2025 SE REALIZA CAMBIO DE EQUIPO PORQUE NO INICIALIZA SE HACEN PRUEBAS OK | W6: VISITA TECNICA | X6: BL01Y316 | Y6: TIPO II | Z6: TERRESTRE | AA6: MONTOYA VELEZ ANDRES FELIPE | AB6: 1 | AC6: 0 | AD6: 144968 | AE6: 140396 | AF6: 144968
A7: CALI | B7: SUROCCIDENTE Y EJE CAFETERO | C7: 0004-0003 | D7: 19001 | E7: 2958591 | F7: 3007080294 | G7: INCIDENTE | H7: CAUCA | I7: POPAYAN | J7: BARRIO NUEVA FRONTERA POPAYAN | K7: REDEBAN | L7: FO-25-1758927 | M7: 45960.488 | N7: 45962.561 | O7: NO | P7: HARDWARE | Q7: CIERRE | R7: MEMORIA DEL DISPOSITIVO INSUFICIENTE | S7: UNO A UNO | T7: UNO A UNO | U7: EJECUTADO / CANCELADO | V7: 30/10/2025 SE ESCALA PARA VISITA. LLAMAR ANTES DE VISITAR, CONFIRMAR FALLA Y DATOS | 01/11/2025 SE REALIZA LLAMADA CON EL CLIENTE INFORMA SI PUEDE ATENDER TIENE PROBLEMAS CON EL CIERRE GENERAL SE LLEGA AL SITIO Y SE ENCUENTA CERRADO SE LLAMA AL CLIENTE INFORMA SE LE PRESENTO UN ASUNTO PERSONAL POR TANTO NO PUDO ATENDER SE LE INFORMA CERRAMOS EL CASO Y LLAMAR NUEVAMENTE CUANDO ESTE EN EL LOCAL | W7: VISITA TECNICA | X7: NO APLICA | Y7: TIPO III | Z7: TERRESTRE | AA7: GIMBUEL LASSO LUIS GERMAN | AB7: 1 | AC7: 0 | AD7: 275729 | AE7: 196537 | AF7: 275729
A8: CALI | B8: SUROCCIDENTE Y EJE CAFETERO | C8: 0004-0003 | D8: 19001 | E8: 2958748 | F8: 3007079319 | G8: INCIDENTE | H8: CAUCA | I8: POPAYAN | J8: BARRIO EL RECUERDO POPAYAN 4 | K8: REDEBAN | L8: FO-25-1759244 | M8: 45960.494 | N8: 45962.492 | O8: NO | P8: HARDWARE | Q8: ALERT IRRUPTION | R8: ALERT IRRUPTION | S8: UNO A UNO | T8: UNO A UNO | U8: EJECUTADO / CANCELADO | V8: 30/10/2025 SE ESCALA PARA VISITA. LLAMAR ANTES DE VISITAR, CONFIRMAR FALLA Y DATOS | 01/11/2025 SE LLEGA AL SITIO SE ENCUENTRA QUE EL DIA DE AYER EN LA TARDE AL CLIENTE LE MIGRARON A WOMPI POR TANTO NO SE ATIENDE CASO | W8: VISITA TECNICA | X8: NO APLICA | Y8: TIPO III | Z8: TERRESTRE | AA8: GIMBUEL LASSO LUIS GERMAN | AB8: 1 | AC8: 0 | AD8: 275729 | AE8: 196537 | AF8: 275729
A9: CALI | B9: SUROCCIDENTE Y EJE CAFETERO | C9: 0004-0003 | D9: 19001 | E9: 2958800 | F9: 3007035736 | G9: INCIDENTE | H9: CAUCA | I9: POPAYAN | J9: BARRIO LOS HOYOS POPAYAN | K9: REDEBAN | L9: FO-25-1758919 | M9: 45960.489 | N9: 45962.427 | P9: HARDWARE | Q9: LECTOR DE TARJETAS | R9: MENSAJE RETIRE TARJETA | S9: CB UNO A UNO | T9: CB UNO A UNO | V9: 30/10/2025 SE ESCALA PARA VISITA. LLAMAR ANTES DE VISITAR, CONFIRMAR FALLA Y DATOS | 01/11/2025 SE REALIZA LLAMADA CON EL SEÑOR IGNACIO INFORMA EL PIN PAD YA ESTA FUNCIONANDO CORRECTAMENTE YA LEE LAS TARJETAS OK | W9: SOPORTE TELEFONICO | Y9: TIPO III | Z9: TERRESTRE | AA9: GIMBUEL LASSO LUIS GERMAN | AB9: 0 | AC9: 0 | AD9: 41241 | AE9: 0 | AF9: 41241
A10: APARTADO | B10: NOROCCIDENTE | C10: 0004-0005 | D10: 5147 | E10: 2961166 | F10: 3007048955 | G10: INCIDENTE | H10: ANTIOQUIA | I10: CAREPA | J10: DISTRICOL INSUMOS EL PANADERO | K10: REDEBAN | L10: FO-25-1762976 | M10: 45961.333 | N10: 45962.526 | O10: NO | P10: HARDWARE | Q10: NO ENCIENDE | R10: DAÑO POS | S10: AGREGADOR | T10: DISTRICOL | U10: EJECUTADO | V10: 31/10/2025 SE ESCALA PARA VISITA. LLAMAR ANTES DE VISITAR, CONFIRMAR FALLA Y DATOS | 01/11/2025 DATAFONO APAGADO COMPLETAMENTE. DAÑO POS. USUARIA REPORTA QUE SE REINICIABA ALMOMENTO DE HACER UNA TRANSFERENCIA. SE HACE CAMBIO DE DATAFONO, SE CAMBIA LECTORA YA QUE LA ACTUAL NO ES COMPATIBLE CON DATAFONO DESK 2600 TIENE EL CANLE MUY CORTO. SE HACEN PRUEBAS DE CONSULTA DE SALDO,RETIRO Y CONIGNCION DEJANDO TODO OK | W10: VISITA TECNICA | X10: AD00O592 | Y10: TIPO I | Z10: TERRESTRE | AA10: SALDARRIAGA MIRANDA SANTIAGO | AB10: 1 | AC10: 0 | AD10: 65960 | AE10: 75096 | AF10: 65960
A11: CUCUTA | B11: SANTANDERES | C11: 0004-0008 | D11: 54599 | E11: 2961229 | F11: 3007054574 | G11: INCIDENTE | H11: NORTE DE SANTANDER | I11: RAGONVALIA | J11: BARRIO CENTENARIO RAGONVALIA | K11: REDEBAN | L11: FO-25-1762973 | M11: 45961.333 | N11: 45965.555 | O11: NO | P11: HARDWARE | Q11: LECTOR DE TARJETAS | R11: MENSAJE RETIRE TARJETA | S11: CB UNO A UNO | T11: CB UNO A UNO | U11: EJECUTADO | V11: 31/10/2025 SE ESCALA PARA VISITA. LLAMAR ANTES DE VISITAR, CONFIRMAR FALLA Y DATOS | 02/11/2025 SE REALIZA LLAMADA AL NÚMERO 3138511784 Y SE ESTABLECE COMUNICACIÓN CON LA SEÑORA MARTA LOZANO, A QUIEN SE INFORMA QUE, POR MOTIVOS DE DISPONIBILIDAD DE TRANSPORTE Y DÍAS FESTIVOS EN LA ZONA, NO ES POSIBLE EFECTUAR EL DESPLAZAMIENTO AL MUNICIPIO EN LA FECHA PREVISTA. SE REPROGRAMA LA VISITA TÉCNICA PARA EL DÍA 04/11/2025, A PARTIR DE LAS 10:00 A.M. | 04/11/2025 SE VISITA COMERCIO Y SE REALIZA CAMBIO DE DETAFONO POR DAÑO DE RETIRE SU TARJETA, SE REALIZAN CIERRES Y PRUEBAS OK. | W11: VISITA TECNICA | X11: II5ZZ964 | Y11: TIPO III | Z11: TERRESTRE | AA11: TORRES MANTILLA JOSE DANIEL | AB11: 1 | AC11: 0 | AD11: 275729 | AE11: 196537 | AF11: 275729
A12: MEDELLIN | B12: NOROCCIDENTE | C12: 0004-0005 | D12: 5579 | E12: 2961791 | F12: 3007059964 | G12: INCIDENTE | H12: ANTIOQUIA | I12: PUERTO BERRIO | J12: BARRIO BRR CENTRO PUERTO BERRI | K12: REDEBAN | L12: FO-25-1763641 | M12: 45961.37 | N12: 45965.405 | O12: NO | P12: HARDWARE | Q12: SE REINICIA | R12: DAÑO POS | S12: CB UNO A UNO | T12: CB UNO A UNO | U12: EJECUTADO | V12: 31/10/2025 SE ESCALA PARA VISITA. LLAMAR ANTES DE VISITAR, CONFIRMAR FALLA Y DATOS | 03/11/2025 SITIO TIPO III NO SE LOGRÓ VISITAR DÍA SÁBADO POR LEJANÍA DE MUNICIPIO. POR PROBLEMA DE DATAFONO Y SOPORTE PARA CAMBIOS VISITA DEBE SER REALIZADA EN DÍA HÁBIL PARA PODER REALIZAR CAMBIO DE EQUIPO POR REINICIOS. | 04/11/2025 SE CAMBIA EQUIPO POR DAÑO EN PUERTO DE ENERGÍA TODO QUEDA OK | W12: VISITA TECNICA | X12: LA00A058 | Y12: TIPO III | Z12: TERRESTRE | AA12: ALVAREZ ARENAS VICTOR HUGO | AB12: 1 | AC12: 0 | AD12: 275729 | AE12: 196537 | AF12: 275729
A13: MEDELLIN | B13: NOROCCIDENTE | C13: 0004-0005 | D13: 5145 | E13: 2961932 | F13: 3007037596 | G13: INCIDENTE | H13: ANTIOQUIA | I13: CARAMANTA | J13: DISTRICOL SURTICARAMANTA | K13: REDEBAN | L13: FO-25-1763651 | M13: 45961.365 | N13: 45965.51 | O13: NO | P13: SOFTWARE | Q13: COMUNICACION | R13: VERIFIQUE PARAMETROS | S13: AGREGADOR | T13: DISTRICOL | U13: EJECUTADO | V13: 31/10/2025 SE ESCALA PARA VISITA. LLAMAR ANTES DE VISITAR, CONFIRMAR FALLA Y DATOS | 03/11/2025 SITIO TIPO III NO SE LOGRÓ AGENDAR PARA VISITA EL DÍA SÁBADO POR LEJANÍA DE MUNICIPIO. VISITA SERÁ REALIZADA DÍA MARTES. | 04/11/2025 SE REALIZÓ CONFIGURACIÓN DE COMUNICACIÓN | W13: VISITA TECNICA | X13: 9A00Q949 | Y13: TIPO III | Z13: TERRESTRE | AA13: CASTAÑEDA PALACIO CARLOS FELIPE | AB13: 1 | AC13: 0 | AD13: 275729 | AE13: 196537 | AF13: 275729
A14: VILLAVICENCIO | B14: REMOTAS | C14: 0004-0007 | D14: 50001 | E14: 2962225 | F14: 3007059982 | G14: INCIDENTE | H14: META | I14: VILLAVICENCIO | J14: BARRIO BRR ROSA BLANCA VILLAVI | K14: REDEBAN | L14: FO-25-1763638 | M14: 45961.383 | N14: 45962.357 | O14: NO | P14: HARDWARE | Q14: IMPRESION | R14: NO IMPRIME UNO O VARIOS CARACTERES | S14: CB UNO A UNO | T14: CB UNO A UNO | U14: EJECUTADO / CANCELADO | V14: 31/10/2025 SE ESCALA PARA VISITA. LLAMAR ANTES DE VISITAR, CONFIRMAR FALLA Y DATOS | 01/11/2025 SE REALIZA VISITA A COMERCIO LOCAL CERRADO SE REALIZA INTENTO DE COMUNICACIÓN VÍA TELEFÓNICA AL NÚMERO TELEFÓNICO 3203783078 NO ES POSIBLE CONTACTAR A TITULAR | W14: VISITA TECNICA | X14: NA | Y14: TIPO I | Z14: TERRESTRE | AA14: CASTRILLON URREA LONDIER LEANDRO | AB14: 1 | AC14: 0 | AD14: 65960 | AE14: 75096 | AF14: 65960
A15: MEDELLIN | B15: NOROCCIDENTE | C15: 0004-0005 | D15: 5129 | E15: 2962528 | F15: 3007081006 | G15: INCIDENTE | H15: ANTIOQUIA | I15: CALDAS | J15: PTM CALDAS BOTANICASALOMON | K15: REDEBAN | L15: FO-25-1764078 | M15: 45961.406 | N15: 45962.364 | O15: NO | P15: HARDWARE | Q15: LECTOR DE BARRAS | R15: FORMATO INVALIDO LECTOR DAÑADO | S15: AGREGADOR | T15: COMCARD - PTM | U15: EJECUTADO | V15: 31/10/2025 SE ESCALA PARA VISITA. LLAMAR ANTES DE VISITAR, CONFIRMAR FALLA Y DATOS | 31/10/2025 SE REALIZA CAMBIO DE LECTORA YA QUE NO LEÍA LAS FACTURAS. | W15: VISITA TECNICA | X15: FJZZZ896 FJZZZ502 | Y15: TIPO I | Z15: TERRESTRE | AA15: RAMIREZ TABARES JUAN DIEGO | AB15: 1 | AC15: 0 | AD15: 65960 | AE15: 75096 | AF15: 65960
A16: VILLAVICENCIO | B16: REMOTAS | C16: 0004-0007 | D16: 50001 | E16: 2962900 | F16: 3007065243 | G16: INCIDENTE | H16: META | I16: VILLAVICENCIO | J16: BARRIO VEREDA APIAY VILLAVICEN | K16: REDEBAN | L16: FO-25-1764704 | M16: 45961.439 | N16: 45962.397 | O16: NO | P16: HARDWARE | Q16: TECLADO | R16: DAÑO POS | S16: UNO A UNO | T16: CB UNO A UNO | U16: EJECUTADO | V16: 31/10/2025 SE ESCALA PARA VISITA. LLAMAR ANTES DE VISITAR, CONFIRMAR FALLA Y DATOS | 01/11/2025 SE VISITA CB Y SE REALIZA CAMBIO DE DATÁFONO POR DALO RN RL TECLADO. SE INSTALA NUEVO EQUIPO SE CONFIGURA POS SE INICIALIZA SE CREAN USUARIOS CORRECTAMENTE Y SE REALIZA PRUEBAS EXITOSAS PRUEBAS OK | W16: VISITA TECNICA | X16: 2A008782 | Y16: TIPO I | Z16: TERRESTRE | AA16: GARZON RUIZ LUIS MIGUEL | AB16: 1 | AC16: 0 | AD16: 65960 | AE16: 75096 | AF16: 65960
A17: BOGOTA | B17: CUNDINAMARCA | C17: 0004-0004 | D17: 11001 | E17: 2962925 | F17: 3007022814 | G17: INCIDENTE | H17: CUNDINAMARCA | I17: BOGOTA | J17: MULTIPAGAS CHAPINERO | K17: REDEBAN | L17: FO-25-1764689 | M17: 45961.447 | N17: 45962.437 | O17: NO | P17: HARDWARE | Q17: HUB | R17: DAÑO HUB | S17: ROBUSTO | T17: MULTIPAGAS | U17: EJECUTADO | V17: 31/10/2025 SE ESCALA PARA VISITA. LLAMAR ANTES DE VISITAR, CONFIRMAR FALLA Y DATOS | 01/11/2025 SE LLEGA A COMERCIO SE VÁLIDA DAÑO EN HUB EN EL CABLE ROTO SE CAMBIA SE REALIZAN PRUEBAS EXITOSAS | W17: VISITA TECNICA | X17: BBBV322 | Y17: TIPO I | Z17: TERRESTRE | AA17: INFANTE SIERRA MANUEL FERNANDO | AB17: 1 | AC17: 0 | AD17: 65960 | AE17: 75096 | AF17: 65960
A18: TUNJA | B18: SANTANDERES | C18: 0004-0008 | D18: 15238 | E18: 2963025 | F18: 3007042195 | G18: INCIDENTE | H18: BOYACA | I18: DUITAMA | J18: BARRIO SAN JUAN BOSCO DUITAMA | K18: REDEBAN | L18: FO-25-1764691 | M18: 45961.446 | N18: 45962.511 | O18: NO | P18: HARDWARE | Q18: IMPRESION | R18: NO AVANZA PAPEL | S18: CB UNO A UNO | T18: CB UNO A UNO | U18: EJECUTADO | V18: 31/10/2025 SE ESCALA PARA VISITA. LLAMAR ANTES DE VISITAR, CONFIRMAR FALLA Y DATOS | 01/11/2025 CAMBIO DE EQUIPO DAÑO EN IMPRESIÓN NO AVANZA PAPEL | W18: VISITA TECNICA | X18: 9A2ZZ531 | Y18: TIPO II | Z18: TERRESTRE | AA18: HERRERA GARZON JEYSON STEVENT | AB18: 1 | AC18: 0 | AD18: 144968 | AE18: 140396 | AF18: 144968
A19: MEDELLIN | B19: NOROCCIDENTE | C19: 0004-0005 | D19: 5667 | E19: 2963381 | F19: 3007080962 | G19: INCIDENTE | H19: ANTIOQUIA | I19: SAN RAFAEL | J19: BARRIOS SAN RAFAEL SAN RAFAEL | K19: REDEBAN | L19: FO-25-1765114 | M19: 45961.479 | N19: 45962.501 | O19: NO | P19: HARDWARE | Q19: COMUNICACION | R19: MENSAJE CABLE DE RED DESCONECTADO | S19: UNO A UNO | T19: UNO A UNO | U19: EJECUTADO | V19: 31/10/2025 SE ESCALA PARA VISITA. LLAMAR ANTES DE VISITAR, CONFIRMAR FALLA Y DATOS | 01/11/2025 SE CAMBIA EQUIPO PORQUE NO QUIERE COGER EL INTERNET (DAÑO POS) | W19: VISITA TECNICA | X19: FIZZZ296 | Y19: TIPO III | Z19: TERRESTRE | AA19: RUA ALVAREZ RICHARD ANDRES | AB19: 1 | AC19: 0 | AD19: 275729 | AE19: 196537 | AF19: 275729
A20: BUCARAMANGA | B20: SANTANDERES | C20: 0004-0008 | D20: 68276 | E20: 2963505 | F20: 3007075321 | G20: INCIDENTE | H20: SANTANDER | I20: FLORIDABLANCA | J20: BARRIO LA CUMBRE FLORIDABLANCA | K20: REDEBAN | L20: FO-25-1765117 | M20: 45961.479 | N20: 45962.405 | O20: NO | P20: HARDWARE | Q20: PANTALLA | R20: DAÑO POS | S20: CB UNO A UNO | T20: CB UNO A UNO | U20: EJECUTADO | V20: 31/10/2025 SE ESCALA PARA VISITA. LLAMAR ANTES DE VISITAR, CONFIRMAR FALLA Y DATOS | 01/11/2025 SE REALIZA CAMBIO DE DATÁFONO POR DAÑO PANTALLA, SE CAMBIA PINPAD ERROR RETIRE TARJETA, SE INSTALA MAGIBOX. PRUEBAS Y LIMPIEZA DE EQUIPOS OK. | W20: VISITA TECNICA | X20: LM003508 | Y20: TIPO I | Z20: TERRESTRE | AA20: MARTINEZ FLOREZ DONIS ALBERTO | AB20: 1 | AC20: 0 | AD20: 65960 | AE20: 75096 | AF20: 65960
A21: BARRANQUILLA | B21: COSTA | C21: 0004-0001 | D21: 8758 | E21: 2963598 | F21: 3007063501 | G21: INCIDENTE | H21: ATLANTICO | I21: SOLEDAD | J21: DISTRICOL VARIEDADES DIANA | K21: REDEBAN | L21: FO-25-1765287 | M21: 45961.501 | N21: 45962.49 | O21: NO | P21: HARDWARE | Q21: COMUNICACION | R21: DAÑO POS | S21: AGREGADOR | T21: DISTRICOL | U21: EJECUTADO | V21: 31/10/2025 SE ESCALA PARA VISITA. LLAMAR ANTES DE VISITAR, CONFIRMAR FALLA Y DATOS | 01/11/2025 SE REALIZA VISITA SE PROCEDE A CAMBIAR EQUIPO YA QUE POSIBLE FALLA EN EL PUERTO DE RED ,SE CAMBIA EQUIPO SE HACEN PRUEBAS Y TODO OK, CB OPERATIVO | W21: VISITA TECNICA | X21: HA00W611 | Y21: TIPO I | Z21: TERRESTRE | AA21: PORRAS CASTRO DARLON NASCK | AB21: 1 | AC21: 0 | AD21: 65960 | AE21: 75096 | AF21: 65960
... A37: MEDELLIN | B37: NOROCCIDENTE | C37: 0004-0005 | D37: 5591 | E37: 2966054 | F37: 3007023516 | G37: INCIDENTE | H37: ANTIOQUIA | I37: PUERTO TRIUNFO | J37: BARRIO CENTRO PUERTO TRIUNFO | K37: REDEBAN | L37: FO-25-1767941 | M37: 45962.333 | N37: 45965.64 | O37: NO | P37: HARDWARE | Q37: IMPRESION | R37: NO AVANZA PAPEL | S37: CB UNO A UNO | T37: CB UNO A UNO | U37: EJECUTADO | V37: 01/11/2025 SE ESCALA PARA VISITA. LLAMAR ANTES DE VISITAR, CONFIRMAR FALLA Y DATOS | 04/11/2025 SE REALIZA LIMPIEZA A LOS ENGRANAJES DE LA IMPRESORA, SERVICIOS QUEDAN FUNCIONANDO CORRECTAMENTE | W37: VISITA TECNICA | X37: ABC09478 | Y37: TIPO IV | Z37: TERRESTRE | AA37: BARRIENTOS HERNANDEZ CRISTIAN HORACIO | AB37: 1 | AC37: 0 | AD37: 479589 | AE37: 196537 | AF37: 479589
A38: CALI | B38: SUROCCIDENTE Y EJE CAFETERO | C38: 0004-0003 | D38: 76520 | E38: 2966055 | F38: 3007025481 | G38: INCIDENTE | H38: VALLE DEL CAUCA | I38: PALMIRA | J38: BARRIO ZAMORANO III PALMIRA | K38: REDEBAN | L38: FO-25-1767940 | M38: 45962.333 | N38: 45962.422 | P38: HARDWARE | Q38: CIERRE | R38: SE REINICIA | S38: CB UNO A UNO | T38: CB UNO A UNO | V38: 01/11/2025 SE ESCALA PARA VISITA. LLAMAR ANTES DE VISITAR, CONFIRMAR FALLA Y DATOS | 01/11/2025 SE REALIZÓ GESTIÓN TELEFÓNICA PARA CONFIRMAR LA VISITA CON EL CLIENTE, LA CLIENTE ME INFORMA QUE EL DÍA DE AYER NO LE FUNCIONÓ LA CLAVE DEL SUPERVISOR PARA REALIZAR EL CIERRE, DURANTE LA LLAMADA SE LE INDICA QUE REINICIE EL DATÁFONO, LUEGO SE LE INDICA QUE INGRESE CON EL USUARIO AL MENU OPERATIVO DEL DATÁFONO,LA CLIENTA PROCEDE A HACER UN CIERRE PARCIAL DONDE LA CLAVE DEL SUPERVISOR (1526)SE ENCONTRÓ FUNCIONANDO OK SIN NOVEDAD,LA USUARIA AGRADECE LA ATENCIÓN BRINDADA Y MANIFIESTA QUE YA NO REQUIERE LA VISITA TÉCNICA EN EL SITIO YA QUE ESA ERA LA ÚNICA FALLA QUE ESTABA PRESENTANDO. | W38: SOPORTE TELEFONICO | Y38: TIPO I | Z38: TERRESTRE | AA38: SANCHEZ URREGO ROBINSON DAVID | AB38: 0 | AC38: 0 | AD38: 41241 | AE38: 0 | AF38: 41241
A39: CARTAGENA | B39: COSTA | C39: 0004-0001 | D39: 13001 | E39: 2966463 | F39: 3007071581 | G39: INCIDENTE | H39: BOLIVAR | I39: CARTAGENA | J39: BARRIO VILLA DE ARANJUEZ | K39: REDEBAN | L39: FO-25-1768573 | M39: 45962.422 | N39: 45962.551 | O39: NO | P39: SOFTWARE | Q39: ACTUALIZACION | R39: VERSION CARGA SO VR | S39: CB UNO A UNO | T39: CB UNO A UNO | U39: EJECUTADO | V39: 01/11/2025 SE ESCALA PARA VISITA. LLAMAR ANTES DE VISITAR, CONFIRMAR FALLA Y DATOS | 01/11/2025 SE REALIZA BORRADO DE VERSIÓN Y S.O TENÍA PROBLEMA CON EL CIERRE SE LE EXPLICA AL CLIENTE QUE HAGA CIERRE TODOS LOS DÍAS TODO OK | W39: VISITA TECNICA | X39: LN00F209 | Y39: TIPO I | Z39: TERRESTRE | AA39: CANEDO HERRERA ALEXANDER | AB39: 1 | AC39: 0 | AD39: 65960 | AE39: 75096 | AF39: 65960
A40: PASTO | B40: SUROCCIDENTE Y EJE CAFETERO | C40: 0004-0003 | D40: 52001 | E40: 2966487 | F40: 3007066625 | G40: INCIDENTE | H40: NARIÑO | I40: PASTO | J40: PTM PASTO ASESORARTE MULTISERV | K40: REDEBAN | L40: FO-25-1768878 | M40: 45962.448 | N40: 45965.518 | O40: NO | P40: HARDWARE | Q40: PINPAD | R40: ALERTADO | S40: AGREGADOR | T40: COMCARD - PTM | U40: EJECUTADO | V40: 01/11/2025 SE ESCALA PARA VISITA. LLAMAR ANTES DE VISITAR, CONFIRMAR FALLA Y DATOS | 01/11/2025 SE VALIDA INCONVENIENTE , CLIENTE LABORA HASTA MEDIA DIA, SE PROGRAMARA VISITA EL DIA MARTES. | 04/11/2025 SE ENCUENTRA PIN PAD ALERTADO Y CABLE DE PIN PAD DAÑADO ,SE REALIZA CAMBIO DE PIN PAD Y CABLE Y SE RECONFIGURAR OK PARÁMETROS OK Y SE REALIZA PRUEBAS EXITOSAS DE TRANSACCIÓNES | W40: VISITA TECNICA | X40: 7A0BZ688 | Y40: TIPO I | Z40: TERRESTRE | AA40: PAZ MARTINEZ RICHARD HUMBERTO | AB40: 1 | AC40: 0 | AD40: 65960 | AE40: 75096 | AF40: 65960
A41: BUCARAMANGA | B41: SANTANDERES | C41: 0004-0008 | D41: 68001 | E41: 2966492 | F41: 3007072301 | G41: INCIDENTE | H41: SANTANDER | I41: BUCARAMANGA | J41: BARRIO MUTIS BUCARAMANGA 5 | K41: REDEBAN | L41: FO-25-1768942 | M41: 45962.453 | N41: 45962.532 | O41: NO | P41: HARDWARE | Q41: TECLADO | R41: DAÑO POS | S41: CB UNO A UNO | T41: CB UNO A UNO | U41: EJECUTADO | V41: 01/11/2025 SE ESCALA PARA VISITA. LLAMAR ANTES DE VISITAR, CONFIRMAR FALLA Y DATOS | 01/11/2025 SE CAMBIA EQUIPO DEBIDO TECLADO DURO , SE REALIZA INYECCIÓN DE SISTEMA Y VERSIÓN INICIALIZADA OK PRUEBAS OK | W41: VISITA TECNICA | X41: ON00N747 | Y41: TIPO I | Z41: TERRESTRE | AA41: HERRERA LUQUE SAUL JAVIER | AB41: 1 | AC41: 0 | AD41: 65960 | AE41: 75096 | AF41: 65960
A42: APARTADO | B42: NOROCCIDENTE | C42: 0004-0005 | D42: 5045 | E42: 2966545 | F42: 3007032311 | G42: INCIDENTE | H42: ANTIOQUIA | I42: APARTADO | J42: PAGAFACIL BARRIO ORTIZ I | K42: REDEBAN | L42: FO-25-1768563 | M42: 45962.425 | N42: 45962.521 | O42: NO | P42: SOFTWARE | Q42: COMUNICACION | R42: PARAMETROS DE CONFIGURACION EN POS | S42: ROBUSTO | T42: PAGAFACIL | U42: EJECUTADO | V42: 01/11/2025 SE ESCALA PARA VISITA. LLAMAR ANTES DE VISITAR, CONFIRMAR FALLA Y DATOS | 01/11/2025 DATAFONO NO TIENE TONO SE REALIZA CARGA DE PARAMETRO. Y REINICIALIZACION | W42: VISITA TECNICA | X42: 111UZ771 | Y42: TIPO I | Z42: TERRESTRE | AA42: CASTRO HENAO DANIEL ESTEBAN | AB42: 1 | AC42: 0 | AD42: 65960 | AE42: 75096 | AF42: 65960
A43: PEREIRA | B43: SUROCCIDENTE Y EJE CAFETERO | C43: 0004-0002 | D43: 66001 | E43: 2966547 | F43: 3007025363 | G43: INCIDENTE | H43: RISARALDA | I43: PEREIRA | J43: ARA0030 PARQ INDUSTRIAL VIEJO | K43: REDEBAN | L43: FO-25-1769426 | M43: 45962.427 | N43: 45962.537 | P43: HARDWARE | Q43: NO ENCIENDE | R43: DAÑO POS | S43: RETAIL | T43: TIENDAS ARA | V43: 01/11/2025 SE ESCALA CASO ARA A LA RED** TU SOLICITUD REFERENTE A GENERACIÓN DE CASOS CB ARA BANCOLOMBIA QUEDÓ RADICADA BAJO EL TICKET NÚMERO AL ÁREA ENCARGADA. | 01/11/2025 SE ESCALA CASO ARA A LA RED** TU SOLICITUD REFERENTE A GENERACIÓN DE CASOS CB ARA BANCOLOMBIA QUEDÓ RADICADA BAJO EL TICKET NÚMERO AL ÁREA ENCARGADA. | 01/11/2025 SE ESCALA CASO ARA A LA RED** TU SOLICITUD REFERENTE A GENERACIÓN DE CASOS CB ARA BANCOLOMBIA QUEDÓ RADICADA BAJO EL TICKET NÚMERO AL ÁREA ENCARGADA. | 01/11/2025 SE ESCALA CASO ARA A LA RED** TU SOLICITUD REFERENTE A GENERACIÓN DE CASOS CB ARA BANCOLOMBIA QUEDÓ RADICADA BAJO EL TICKET NÚMERO AL ÁREA ENCARGADA. | W43: SOPORTE TELEFONICO | Y43: TIPO I | Z43: TERRESTRE | AA43: ARRAZOLA HERNANDEZ NICOLAS AUGUSTO | AB43: 0 | AC43: 0 | AD43: 41241 | AE43: 0 | AF43: 41241
A44: SINCELEJO | B44: COSTA | C44: 0004-0001 | D44: 70708 | E44: 2966553 | F44: 3007047319 | G44: INCIDENTE | H44: SUCRE | I44: SAN MARCOS | J44: BARRIO LAS FLORES SAN MARCOS | K44: REDEBAN | L44: FO-25-1768611 | M44: 45962.43 | N44: 45965.658 | O44: NO | P44: HARDWARE | Q44: IMPRESION | R44: NO IMPRIME UNO O VARIOS CARACTERES | S44: CB UNO A UNO | T44: CB UNO A UNO | U44: EJECUTADO | V44: 01/11/2025 SE ESCALA PARA VISITA. LLAMAR ANTES DE VISITAR, CONFIRMAR FALLA Y DATOS | 04/11/2025 SE VISITA COMERCIO POR UNA FALLA, SE HACE CAMBIO DE EQUIPO, CAUSAL G1 NO IMPRIME UNO O VARIOS CARACTERES, SE DEJA CON LA VERSIÓN 10,3, SE REALIZAN PRUEBAS OK, SE CREA USUARIO Y CONTRASEÑA. | W44: VISITA TECNICA | X44: TR00D627 | Y44: TIPO III | Z44: TERRESTRE | AA44: CACERES HERNANDEZ ANDRES | AB44: 1 | AC44: 0 | AD44: 275729 | AE44: 196537 | AF44: 275729
A45: NEIVA | B45: REMOTAS | C45: 0004-0007 | D45: 41016 | E45: 2966555 | F45: 3007071912 | G45: INCIDENTE | H45: HUILA | I45: AIPE | J45: AIPE SAN MARTIN | K45: REDEBAN | L45: FO-25-1768786 | M45: 45962.434 | N45: 45965.522 | O45: NO | P45: HARDWARE | Q45: PINPAD | R45: DAÑO POS | S45: CB UNO A UNO | T45: CB UNO A UNO | U45: EJECUTADO | V45: 01/11/2025 SE ESCALA ACTIVIDAD PARA GESTION WOMPI | 02/11/2025 POR HORARIO DE ATENCIÓN HOY NO ABREN. DISPONIBLE PARA VISITA EN DIA HABIL. | 04/11/2025 SE REALIZA VISITA AL PUNTO SE CAMBIA PIN PAD POR FALLA EN EL TECLADO, SE CAMBIA TAMBIÉN EL DATAFONO YA QUE ESTE NO ES COMPATIBLE CON LA TECNOLOGÍA DSK 1600 DEL PIN PAD. SE DEJA EQUIPO CON VR 10.3 PRUEBAS CB OK CB OPERATIVO | W45: VISITA TECNICA | X45: LN00M122 | Y45: TIPO II | Z45: TERRESTRE | AA45: DEVIA REINOSO JUAN CARLOS | AB45: 1 | AC45: 0 | AD45: 144968 | AE45: 140396 | AF45: 144968
A46: BOGOTA | B46: CUNDINAMARCA | C46: 0004-0004 | D46: 25754 | E46: 2966627 | F46: 3007076979 | G46: INCIDENTE | H46: CUNDINAMARCA | I46: SOACHA | J46: BARRIO BUENOS AIRES SOACHA | K46: REDEBAN | L46: FO-25-1776680 | FO-25-1768568 | M46: 45962.423 | N46: 45966.681 | O46: NO | P46: HARDWARE | Q46: ALERT IRRUPTION | R46: ALERT IRRUPTION | S46: UNO A UNO | T46: UNO A UNO | U46: EJECUTADO / CANCELADO | V46: 05/11/2025 SE REALIZA VISITA AL COMERCIO PERO SE ENCUENTRA CERRADO TEL DE CONTACTO NO RESPONDE 3223265189 | W46: VISITA TECNICA | X46: A18ZZ416 | Y46: TIPO I | Z46: TERRESTRE | AA46: ROZO ROZO WILLIAM ASDRUBAL | AB46: 2 | AC46: 0 | AD46: 131920 | AE46: 75096 | AF46: 131920
A47: MEDELLIN | B47: NOROCCIDENTE | C47: 0004-0005 | D47: 5001 | E47: 2966630 | F47: 3007016829 | G47: INCIDENTE | H47: ANTIOQUIA | I47: MEDELLIN | J47: PAGAFACIL BARRIO TRISTE | K47: REDEBAN | L47: FO-25-1768566 | M47: 45962.424 | N47: 45962.494 | O47: NO | P47: HARDWARE | Q47: IMPRESION | R47: NO IMPRIME UNO O VARIOS CARACTERES | S47: ROBUSTO | T47: PAGAFACIL | U47: EJECUTADO | V47: 01/11/2025 SE ESCALA PARA VISITA. LLAMAR ANTES DE VISITAR, CONFIRMAR FALLA Y DATOS | 01/11/2025 LIMPIEZA DE IMPRESORA SUCIAS OK PRUEBAS OK NO TELECARGA | W47: VISITA TECNICA | X47: JFZZZ773 | Y47: TIPO I | Z47: TERRESTRE | AA47: PAREJA ECHAVARRIA JHON DAVID | AB47: 1 | AC47: 0 | AD47: 65960 | AE47: 75096 | AF47: 65960
A48: MEDELLIN | B48: NOROCCIDENTE | C48: 0004-0005 | D48: 27001 | E48: 2966635 | F48: 3007030020 | G48: INCIDENTE | H48: CHOCO | I48: QUIBDO | J48: DISTRICOL GRO A RA O | K48: REDEBAN | L48: FO-25-1768612 | M48: 45962.429 | N48: 45966.42 | O48: NO | P48: HARDWARE | Q48: LECTOR DE TARJETAS | R48: MENSAJE RETIRE TARJETA | S48: AGREGADOR | T48: DISTRICOL | U48: EJECUTADO | V48: 01/11/2025 SE ESCALA PARA VISITA. LLAMAR ANTES DE VISITAR, CONFIRMAR FALLA Y DATOS | 05/11/2025 SE REEALIZA CAMBIO DE EQUIPO POR DAÑO? SE REALIZAN PRUEBAS Y EL CB QUEDA OPERATIVO | W48: VISITA TECNICA | X48: BB0ZZ037 | Y48: TIPO V | Z48: AEREO | AA48: ROBLEDO DIAZ ANDRES FELIPE | AB48: 1 | AC48: 0 | AD48: 988463 | AE48: 196537 | AF48: 988463
A49: CALI | B49: SUROCCIDENTE Y EJE CAFETERO | C49: 0004-0003 | D49: 76109 | E49: 2966648 | F49: 3007063162 | G49: INCIDENTE | H49: VALLE DEL CAUCA | I49: BUENAVENTURA | J49: BARRIO CENTRO BUENAVENTURA 9 | K49: REDEBAN | L49: FO-25-1768881 | M49: 45962.447 | N49: 45962.588 | O49: NO | P49: HARDWARE | Q49: COMUNICACION | R49: MENSAJE CABLE DE RED DESCONECTADO | S49: CB UNO A UNO | T49: CB UNO A UNO | U49: EJECUTADO | V49: 01/11/2025 SE ESCALA PARA VISITA. LLAMAR ANTES DE VISITAR, CONFIRMAR FALLA Y DATOS | 01/11/2025 SE REALIZA CAMBIO DE EQUIPO E6 PUERTO IP MALO Y SE CAMBIA LECTOR L4 SE BLOQUEA, CB BANCOLOMBIA PURO, PRUEBAS OK | W49: VISITA TECNICA | X49: JA00T600 | Y49: TIPO III | Z49: TERRESTRE | AA49: PAREDES CASTILLO DIEGO | AB49: 1 | AC49: 0 | AD49: 275729 | AE49: 196537 | AF49: 275729
A50: CALI | B50: SUROCCIDENTE Y EJE CAFETERO | C50: 0004-0003 | D50: 76377 | E50: 2966654 | F50: 3007011717 | G50: INCIDENTE | H50: VALLE DEL CAUCA | I50: LA CUMBRE | J50: LA CUMBRE VALLE DEL CAUCA | K50: REDEBAN | L50: FO-25-1768871 | M50: 45962.45 | N50: 45965.553 | O50: NO | P50: SOFTWARE | Q50: COMUNICACION | R50: VERIFIQUE PARAMETROS | S50: CB UNO A UNO | T50: CB UNO A UNO | U50: EJECUTADO | V50: 01/11/2025 SE ESCALA PARA VISITA. LLAMAR ANTES DE VISITAR, CONFIRMAR FALLA Y DATOS | 04/11/2025 BUUE DÍA CLIENTE NO LABORA EL FIN DE SEMANA SE VALIDARA EL DÍA MARTES | 04/11/2025 SE REALIZA BORRADO E INSTALACIÓN DE LA VERSIÓN DEL SOFTWARES, SE REALIZA INICIALIZACIÓN SIN NOVEDAD. SE REALIZARON PRUEBAS OPERATIVAS SIN NOVEDAD. CB QUEDA OKEY. | W50: VISITA TECNICA | X50: GA00R085 | Y50: TIPO II | Z50: TERRESTRE | AA50: TORRES GARCIA JENDRY JOSE | AB50: 1 | AC50: 0 | AD50: 144968 | AE50: 140396 | AF50: 144968
A51: TUNJA | B51: SANTANDERES | C51: 0004-0008 | D51: 15776 | E51: 2966670 | F51: 3007029397 | G51: INCIDENTE | H51: BOYACA | I51: SUTAMARCHAN | J51: BARRIO CENTRO SUTAMARCHAN | K51: REDEBAN | L51: FO-25-1769498 | M51: 45962.465 | N51: 45965.561 | O51: NO | P51: SOFTWARE | Q51: ACTUALIZACION | R51: VERSION CARGA SO VR | S51: UNO A UNO | T51: CB UNO A UNO | U51: EJECUTADO | V51: 01/11/2025 SE ESCALA PARA VISITA. LLAMAR ANTES DE VISITAR, CONFIRMAR FALLA Y DATOS | 03/11/2025 EN COMUNICACIÓN CON LA SEÑORA MARTHA AL MOVIL 3138923176, SE CONFIRMA QUE EL. DATAFONO ESTA MOSTRANDO LA HORA ERRONEA Y ADICIONALMENTE LAS TECLAS DEL DATAFONO ESTA FALLANDO, SE LE INFORMA QUE ES FIN DE SEMANA Y SE REQUIERE CAMBIO DE DATAFONO PERO AL SER FIN DE SEMANA NO ES POSIBLE REALIZAR ESTA GESTIÓN, SE LE INFORMA QUE LA VIISTA QUEDA PROGRAMADA PARA EL DÍA MARTES 4 DE NOVIEMBRE DEL 2025 DESPUÉS DE LAS 8AM EN ADELANTE SEGÚN DISPONIBILIDAD DE TRANSPORTE DE LA ZONA. | 04/11/2025 SE REALIZA VISITA AL COMERCIO, SE CONFIGURA LA HORA DEL EQUIPO POR SOLICITUD DEO CLIENTE, PRUEBAS OK. | W51: VISITA TECNICA | X51: 2ZZZZ579 AB00N307 | Y51: TIPO II | Z51: TERRESTRE | AA51: SOLER HOYOS CRISTIAN LEONARDO | AB51: 1 | AC51: 0 | AD51: 144968 | AE51: 140396 | AF51: 144968
A52: PEREIRA | B52: SUROCCIDENTE Y EJE CAFETERO | C52: 0004-0002 | D52: 76823 | E52: 2966779 | F52: 3007026405 | G52: INCIDENTE | H52: VALLE DEL CAUCA | I52: TORO | J52: TORO III VALLE DEL CAUCA | K52: REDEBAN | L52: FO-25-1769822 | M52: 45962.591 | N52: 45965.515 | O52: NO | P52: HARDWARE | Q52: IMPRESION | R52: TAPA IMPRESORA | S52: CB UNO A UNO | T52: CB UNO A UNO | U52: EJECUTADO | V52: 01/11/2025 SE ESCALA ACTIVIDAD PARA GESTION WOMPI | 02/11/2025 EN COMUNICACIÓN CON EL CLIENTE SE VÁLIDA QUE SE DEBE CAMBIAR EQUIPO, SE LE INDICA AL CLIENTE QUE SE VISITA EL MARTES YA QUE NO HAY SOPORTE DE PARTE DE RBM HOY Y MAÑANA DÍA FESTIVO. | 04/11/2025 VISITAMOS COMERCIO EL DATÁFONO TIENE LA TAPA DE LA IMPRESORA DAÑADA, REALOZAMOS CAMBIO LO CONFIGURAMOS REALIZAMOS PRUEBAS CON EL NUEVO DATÁFONO OK. | W52: VISITA TECNICA | X52: BL01X656 GZ00Z327 | Y52: TIPO II | Z52: TERRESTRE | AA52: ARROYAVE CANO MANUEL GUILLERMO | AB52: 1 | AC52: 0 | AD52: 144968 | AE52: 140396 | AF52: 144968
A53: MONTERIA | B53: COSTA | C53: 0004-0001 | D53: 23580 | E53: 2966783 | F53: 3007059789 | G53: INCIDENTE | H53: CORDOBA | I53: PUERTO LIBERTADOR | J53: DISTRICOL ELBUENPRECIOPUERTOLI | K53: REDEBAN | L53: FO-25-1769867 | M53: 45962.594 | N53: 45965.542 | O53: NO | P53: HARDWARE | Q53: IMPRESION | R53: NO IMPRIME UNO O VARIOS CARACTERES | S53: AGREGADOR | T53: DISTRICOL | U53: EJECUTADO | V53: 01/11/2025 SE ESCALA PARA VISITA. LLAMAR ANTES DE VISITAR, CONFIRMAR FALLA Y DATOS | 12/11/2025 SE VISITA SITIO, SE CAMBIA DATAFONO Y CABLE MAGIC BOX OK. SE REALIZAN PRUEBAS EXITOSAS | W53: VISITA TECNICA | X53: FUA0B329 | Y53: TIPO IV | Z53: TERRESTRE | AA53: COGOLLO VERTEL EDER LUIS | AB53: 1 | AC53: 0 | AD53: 479589 | AE53: 196537 | AF53: 479589
A54: MEDELLIN | B54: NOROCCIDENTE | C54: 0004-0005 | D54: 5615 | E54: 2966962 | F54: 3007030313 | G54: INCIDENTE | H54: ANTIOQUIA | I54: RIONEGRO | J54: BARRIO AEROPUERTO RIONEGRO RIO | K54: REDEBAN | L54: FO-25-1769870 | M54: 45962.593 | N54: 45965.621 | O54: NO | P54: HARDWARE | Q54: PINPAD | R54: ALERTADO | S54: CB UNO A UNO | T54: CB UNO A UNO | U54: EJECUTADO | V54: 01/11/2025 SE ESCALA PARA VISITA. LLAMAR ANTES DE VISITAR, CONFIRMAR FALLA Y DATOS | 04/11/2025 SE REALIZA CAMBIO DE PINPAD SE REALIZA REINSTALACIÓN DE S.O Y VERSIÓN Y QUEDA OK SE HACEN PRUEBAS OK | W54: VISITA TECNICA | X54: SVEZZ979 | Y54: TIPO II | Z54: TERRESTRE | AA54: MONTOYA VELEZ ANDRES FELIPE | AB54: 1 | AC54: 0 | AD54: 144968 | AE54: 140396 | AF54: 144968
A55: CUCUTA | B55: SANTANDERES | C55: 0004-0008 | D55: 54660 | E55: 2966983 | F55: 3007077564 | G55: INCIDENTE | H55: NORTE DE SANTANDER | I55: SALAZAR | J55: BARRIO CENTRO SALAZAR | K55: REDEBAN | L55: FO-25-1770110 | M55: 45962.643 | N55: 45965.662 | O55: NO | P55: SOFTWARE | Q55: COMUNICACION | R55: VERIFIQUE PARAMETROS | S55: CB UNO A UNO | T55: CB UNO A UNO | U55: EJECUTADO | V55: 01/11/2025 SE ESCALA PARA VISITA. LLAMAR ANTES DE VISITAR, CONFIRMAR FALLA Y DATOS | 03/11/2025 SE REALIZA LLAMADA AL NÚMERO3134785466 Y SE ESTABLECE COMUNICACIÓN CON LA SR JOSUÉ, A QUIEN SE INFORMA QUE, POR MOTIVOS DE DISPONIBILIDAD DE TRANSPORTE Y DÍAS FESTIVOS EN LA ZONA, NO ES POSIBLE EFECTUAR EL DESPLAZAMIENTO AL MUNICIPIO EN LA FECHA PREVISTA. SE REPROGRAMA LA VISITA TÉCNICA PARA EL DÍA 04/11/2025, A PARTIR DE LAS 8AM | 04/11/2025 SE REALIZA VISITA, SE ENCUENTRA DATAFONO CON REVERSO PENDIENTE, SE REALIZA BORRADO DE TRANSACCIONES, SE REALIZAN PRUEBAS Y CIERRES OK. | W55: VISITA TECNICA | X55: 10HZZ132 | Y55: TIPO II | Z55: TERRESTRE | AA55: PACHECO BUITRAGO JAVIER ALONSO | AB55: 1 | AC55: 0 | AD55: 144968 | AE55: 140396 | AF55: 144968
... A59: MEDELLIN | B59: NOROCCIDENTE | C59: 0004-0005 | D59: 5001 | E59: 2967137 | F59: 3007079705 | G59: INCIDENTE | H59: ANTIOQUIA | I59: MEDELLIN | J59: PTM MEDELLIN ALPES MULTISERVIC | K59: REDEBAN | L59: FO-25-1770540 | M59: 45963.333 | N59: 45965.585 | O59: NO | P59: HARDWARE | Q59: IMPRESION | R59: NO IMPRIME UNO O VARIOS CARACTERES | S59: AGREGADOR | T59: COMCARD - PTM | U59: EJECUTADO | V59: 02/11/2025 SE ESCALA PARA VISITA. LLAMAR ANTES DE VISITAR, CONFIRMAR FALLA Y DATOS | 02/11/2025 EN COMUNICACIÓN CON LA SEÑORA BETTY SEÑA AL NÚMERO 3224373966 INDICA QUE LA FALLA PERSISTE EL BAUCHER SACA UNA LÍNEA BLANCA QUE NO DEJA VER BIEN EL VALOR Y ADICIONAL A ESO NO PRESTAN SERVICIO DE CORRESPONSAL EL DÍA DE HOY DOMINGO NI MAÑANA LUNES FESTIVO, NO SE ENCUENTRAN EN LA CIUDAD, LLEGAN EL DÍA MARTES | 04/11/2025 SE REALIZA CAMBIO DE EQUIPO DESPUÉS DE COMPROBACIONES DE DAÑO EN IMPRESORA, PRUEBAS OK | W59: VISITA TECNICA | X59: V1YZZ447 V1YZZ787 | Y59: TIPO I | Z59: TERRESTRE | AA59: QUINTERO SANCHEZ JUAN SEBASTIAN | AB59: 1 | AC59: 0 | AD59: 65960 | AE59: 75096 | AF59: 65960
A60: CALI | B60: SUROCCIDENTE Y EJE CAFETERO | C60: 0004-0003 | D60: 19001 | E60: 2967388 | F60: 3007080294 | G60: INCIDENTE | H60: CAUCA | I60: POPAYAN | J60: BARRIO NUEVA FRONTERA POPAYAN | K60: REDEBAN | L60: FO-25-1770899 | M60: 45963.464 | N60: 45965.538 | P60: HARDWARE | Q60: CIERRE | R60: MEMORIA DEL DISPOSITIVO INSUFICIENTE | S60: UNO A UNO | T60: UNO A UNO | V60: 02/11/2025 SE ESCALA PARA VISITA. LLAMAR ANTES DE VISITAR, CONFIRMAR FALLA Y DATOS | 04/11/2025 SE LLAMA A LA SEÑORA MAGALI INFORMA EL DATAFONO EL DIA DE HOY SE LO MIGRARON A WOMPI POR TANTO SE CANCELA ACTIVIDAD | W60: SOPORTE TELEFONICO | Y60: TIPO III | Z60: TERRESTRE | AA60: GIMBUEL LASSO LUIS GERMAN | AB60: 0 | AC60: 0 | AD60: 41241 | AE60: 0 | AF60: 41241
A61: VILLAVICENCIO | B61: REMOTAS | C61: 0004-0007 | D61: 50001 | E61: 2967450 | F61: 3007062324 | G61: INCIDENTE | H61: META | I61: VILLAVICENCIO | J61: BARRIO VEGA ORIENTAL VILLAVICE | K61: REDEBAN | L61: FO-25-1770749 | M61: 45963.419 | N61: 45965.451 | O61: NO | P61: HARDWARE | Q61: LECTOR DE BARRAS | R61: CABLE LECTORA AVERIADO | S61: CB UNO A UNO | T61: CB UNO A UNO | U61: EJECUTADO | V61: 02/11/2025 SE ESCALA PARA VISITA. LLAMAR ANTES DE VISITAR, CONFIRMAR FALLA Y DATOS | 04/11/2025 SE REALIZA CAMBIO DE LECTOR DE BARRAS POR DAÑO EN CABLE SE REALIZA PRUEBAS BÁSICAS SIN NOVEDAD | W61: VISITA TECNICA | X61: OA00C245 | Y61: TIPO I | Z61: TERRESTRE | AA61: ROZO JIMENEZ EDGAR ARMANDO | AB61: 1 | AC61: 0 | AD61: 65960 | AE61: 75096 | AF61: 65960
A62: CUCUTA | B62: SANTANDERES | C62: 0004-0008 | D62: 54001 | E62: 2967483 | F62: 3007066925 | G62: INCIDENTE | H62: NORTE DE SANTANDER | I62: CUCUTA | J62: BARRIO ALFONSO LOPEZ CUCUTA 5 | K62: REDEBAN | L62: FO-25-1771108 | M62: 45963.563 | N62: 45965.685 | O62: NO | P62: HARDWARE | Q62: ALERT IRRUPTION | R62: ALERT IRRUPTION | S62: CB UNO A UNO | T62: CB UNO A UNO | U62: EJECUTADO | V62: 02/11/2025 SE ESCALA ACTIVIDAD PARA GESTION WOMPI | 04/11/2025 CASO CON FALLA ALERTADO. SE PROGRAMA PARA EL DIA 4/11/2025 POR CAMBIO DE ACTIVO . EN AM | 04/11/2025 SE REALIZÓ VISITA AL COMERCIO Y SE ENCUENTRA DATAFONO MODO ALERTADO, SE REALIZA CAMBIO DE EQUIPO PRUEBAS EXITOSAS | W62: VISITA TECNICA | X62: 4A0AZ453 | Y62: TIPO I | Z62: TERRESTRE | AA62: MORA VEGA JEAMPIER | AB62: 1 | AC62: 0 | AD62: 65960 | AE62: 75096 | AF62: 65960
A63: BARRANQUILLA | B63: COSTA | C63: 0004-0001 | D63: 8001 | E63: 2967529 | F63: 3007051869 | G63: INCIDENTE | H63: ATLANTICO | I63: BARRANQUILLA | J63: PTM BARRANQUILLA KANDS 2 | K63: REDEBAN | L63: FO-25-1770750 | M63: 45963.414 | N63: 45963.637 | O63: NO | P63: HARDWARE | Q63: NO ENCIENDE SE REINICIA | R63: FUENTE PODER AVERIADA | S63: AGREGADOR | T63: COMCARD - PTM | U63: EJECUTADO | V63: 02/11/2025 SE ESCALA PARA VISITA. LLAMAR ANTES DE VISITAR, CONFIRMAR FALLA Y DATOS | 02/11/2025 DATAFONO TENÍA FUENTE DE PODER DAÑADA, SE REMPLAZA Y QUE OK | W63: VISITA TECNICA | X63: BA0BZ023 NA00B769 | Y63: TIPO I | Z63: TERRESTRE | AA63: DE AVILA SIADES ALBERTO ENRIQUE | AB63: 1 | AC63: 0 | AD63: 65960 | AE63: 75096 | AF63: 65960
A64: IBAGUE | B64: REMOTAS | C64: 0004-0007 | D64: 73001 | E64: 2967532 | F64: 3007058615 | G64: INCIDENTE | H64: TOLIMA | I64: IBAGUE | J64: PTM IBAGUE TIENDA ONLYS | K64: REDEBAN | L64: FO-25-1770772 | M64: 45963.429 | N64: 45965.493 | O64: NO | P64: HARDWARE | Q64: TECLADO | R64: DAÑO POS | S64: AGREGADOR | T64: COMCARD - PTM | U64: EJECUTADO | V64: 02/11/2025 SE ESCALA PARA VISITA. LLAMAR ANTES DE VISITAR, CONFIRMAR FALLA Y DATOS | 02/11/2025 SIN SOPORTE DE ACTIVOS REDEBAN PARA CAMBIO DE EQUIPO POR TECLADO MALO | 04/11/2025 SE REALIZA CAMBIO DE DATÁFONO POR TACLADO MALO, SE REALIZA PRUEBAS DE FUNCIONAMIENTO EXITOSAS. CUBRE CLAVE INSTALADO | W64: VISITA TECNICA | X64: IVZZZ930 IWZZZ040 | Y64: TIPO I | Z64: TERRESTRE | AA64: BARRAGAN TAFUR EDWIN ESTEBAN | AB64: 1 | AC64: 0 | AD64: 65960 | AE64: 75096 | AF64: 65960
A65: BUCARAMANGA | B65: SANTANDERES | C65: 0004-0008 | D65: 68500 | E65: 2967985 | F65: 3007080035 | G65: INCIDENTE | H65: SANTANDER | I65: OIBA | J65: BARRIO POIMA OIBA OIBA | K65: REDEBAN | L65: FO-25-1772507 | M65: 45964.48 | N65: 45965.734 | O65: NO | P65: HARDWARE | Q65: IMPRESION | R65: TAPA IMPRESORA | S65: UNO A UNO | T65: UNO A UNO | U65: EJECUTADO | V65: 03/11/2025 SE ESCALA PARA VISITA. LLAMAR ANTES DE VISITAR, CONFIRMAR FALLA Y DATOS | 04/11/2025 SE HACE PRESENCIA EN COMERCIO SE VALIDA ESTADO DEL EQUIPO CLIENTE INFORMA QUE EL EQUIPO SE LE HBAIA CAIDO Y SE LE HABÍA SALIDO EL RODILLO PERO QUE ELLA SE LE COLOCO Y EL EQUIPO YA ESTÁ IMPRIMIENDO BIEN SE VALIDA CONEXIONES OK PRUEBAS OK SE PROCEDE A CERRAR ORDEN | W65: VISITA TECNICA | X65: SAXZZ451 | Y65: TIPO III | Z65: TERRESTRE | AA65: BARRERA ORTEGA MARLON STWAR | AB65: 1 | AC65: 0 | AD65: 275729 | AE65: 196537 | AF65: 275729
A66: YOPAL | B66: REMOTAS | C66: 0004-0007 | D66: 85001 | E66: 2967986 | F66: 3007071975 | G66: INCIDENTE | H66: CASANARE | I66: YOPAL | J66: YOPAL PROVINCIA | K66: REDEBAN | L66: FO-25-1772506 | M66: 45964.481 | N66: 45965.433 | P66: SOFTWARE | Q66: ERROR DE TRANSACCIONES | R66: RECHAZO GENERAL | S66: CB UNO A UNO | T66: CB UNO A UNO | V66: 03/11/2025 SE ESCALA PARA VISITA. LLAMAR ANTES DE VISITAR, CONFIRMAR FALLA Y DATOS | 03/11/2025 SIN SOPORTE DE REDEBAN PARA VALIDAR RECHAZO GENERAL | 04/11/2025 EN COMUNICACIÓN CON EL SEÑOR FRANCISCO ZULUAGA AL NUMERO 3144334647, INDICA NO REQUIERE LA VISITA, EL SERVICIO SE ENCUENTRA OPERATIVO. | W66: SOPORTE TELEFONICO | Y66: TIPO I | Z66: TERRESTRE | AA66: BERNAL ELAICA EDGAR ALEXIS | AB66: 0 | AC66: 0 | AD66: 41241 | AE66: 0 | AF66: 41241
A67: MEDELLIN | B67: NOROCCIDENTE | C67: 0004-0005 | D67: 5001 | E67: 2967992 | F67: 3007070025 | G67: INCIDENTE | H67: ANTIOQUIA | I67: MEDELLIN | J67: PTM MEDELLIN TOSCANA Ñ2 | K67: REDEBAN | L67: FO-25-1772489 | M67: 45964.489 | N67: 45965.453 | O67: NO | P67: HARDWARE | Q67: LECTOR DE TARJETAS | R67: DAÑO POS | S67: AGREGADOR | T67: COMCARD - PTM | U67: EJECUTADO | V67: 03/11/2025 SE ESCALA PARA VISITA. LLAMAR ANTES DE VISITAR, CONFIRMAR FALLA Y DATOS | 04/11/2025 SE REALIZA CAMBIO DE DATÁFONO POR DAÑO EN LECTOR DE TARJETAS. | W67: VISITA TECNICA | X67: UV001531 UV001674 | Y67: TIPO I | Z67: TERRESTRE | AA67: RAMIREZ TABARES JUAN DIEGO | AB67: 1 | AC67: 0 | AD67: 65960 | AE67: 75096 | AF67: 65960
A68: VALLEDUPAR | B68: COSTA | C68: 0004-0001 | D68: 13473 | E68: 2968075 | F68: 3007061347 | G68: INCIDENTE | H68: BOLIVAR | I68: MORALES | J68: BARRIO MINA GALLO MORALES | K68: REDEBAN | L68: FO-25-1772495 | M68: 45964.488 | N68: 45966.771 | O68: NO | P68: SOFTWARE | Q68: COMUNICACION | R68: VERIFIQUE PARAMETROS | S68: CB UNO A UNO | T68: CB UNO A UNO | U68: EJECUTADO | V68: 03/11/2025 SE ESCALA PARA VISITA. LLAMAR ANTES DE VISITAR, CONFIRMAR FALLA Y DATOS | 05/11/2025 SE REALIZA VISITA Y SE HACE MANTENIMIENTO AL SISTEMA OPERATIVO Y VERSIÓN YA QUE PRESENTA ERROR EN PARÁMETROS DE COMUNICACIÓN SE HACEN PRUEBAS EXITOSA | W68: VISITA TECNICA | X68: HA00J530 | Y68: TIPO IV | Z68: TERRESTRE | AA68: PEÑA DIAZ IVAN YESID | AB68: 1 | AC68: 0 | AD68: 479589 | AE68: 196537 | AF68: 479589
A69: VALLEDUPAR | B69: COSTA | C69: 0004-0001 | D69: 44650 | E69: 2968094 | F69: 3007031484 | G69: INCIDENTE | H69: LA GUAJIRA | I69: SAN JUAN DEL CESAR | J69: ARRIO CENTRO 6 | K69: REDEBAN | L69: FO-25-1773177 | M69: 45964.567 | N69: 45965.501 | O69: NO | P69: HARDWARE | Q69: IMPRESION | R69: NO AVANZA PAPEL | S69: CB UNO A UNO | T69: CB UNO A UNO | U69: EJECUTADO | V69: 03/11/2025 SE ESCALA PARA VISITA. LLAMAR ANTES DE VISITAR, CONFIRMAR FALLA Y DATOS | 24/11/2025 BUENOS DIAS SE VISITA CB Y SE LE HACE CAMBIO DE EQUIPO YA QUE HA TENIDO PROBLEMAS CON LA IMPRESIÓN | W69: VISITA TECNICA | X69: 1111D226 | Y69: TIPO II | Z69: TERRESTRE | AA69: BENITEZ CARVAJAL ALVARO JAVIER | AB69: 1 | AC69: 0 | AD69: 144968 | AE69: 140396 | AF69: 144968
A70: MONTERIA | B70: COSTA | C70: 0004-0001 | D70: 23001 | E70: 2968149 | F70: 3007065136 | G70: INCIDENTE | H70: CORDOBA | I70: MONTERIA | J70: BARRIO NUEVA ESPERANZA MONTERI | K70: REDEBAN | L70: FO-25-1772512 | M70: 45964.475 | N70: 45965.469 | O70: NO | P70: HARDWARE | Q70: IMPRESION | R70: NO IMPRIME UNO O VARIOS CARACTERES | S70: CB UNO A UNO | T70: CB UNO A UNO | U70: EJECUTADO | V70: 03/11/2025 SE ESCALA PARA VISITA. LLAMAR ANTES DE VISITAR, CONFIRMAR FALLA Y DATOS | 04/11/2025 SE REALIZA LA VISITA AL COMERCIO, SE INSPECCIONA EL DATAFONO EVIDENCIANDO QUE AL IMPRIMIR VARIOS CARACTERES, SE PROCEDE A CAMBIAR EQUIPO SE CREAN USUARIOS SE CAPACITA AL CLIENTE EL CORRECTO FUNCIONAMIENTO DEL EQUIPO PIN PAD Y LECTORA DE BARRAS FUNCIONANDO CON NORMALIDAD PRUEBAS EXITOSAS. CB OPERA CON NORMALIDAD | W70: VISITA TECNICA | X70: 1A007846 | Y70: TIPO I | Z70: TERRESTRE | AA70: ARRAZOLA HERNANDEZ NICOLAS AUGUSTO | AB70: 1 | AC70: 0 | AD70: 65960 | AE70: 75096 | AF70: 65960
A71: CALI | B71: SUROCCIDENTE Y EJE CAFETERO | C71: 0004-0003 | D71: 76001 | E71: 2968150 | F71: 3007011896 | G71: INCIDENTE | H71: VALLE DEL CAUCA | I71: CALI | J71: SURTIFAMILIAR ALCAZARES | K71: REDEBAN | L71: FO-25-1772510 | M71: 45964.476 | N71: 45965.528 | O71: NO | P71: HARDWARE | Q71: IMPRESION | R71: RODILLO AVERIADO | S71: CB UNO A UNO | T71: SURTIFAMILIAR | U71: EJECUTADO | V71: 03/11/2025 SE ESCALA PARA VISITA. LLAMAR ANTES DE VISITAR, CONFIRMAR FALLA Y DATOS | 04/11/2025 SE CAMBIA DATÁFONO YA QUE TIENE RODILLO MALO | W71: VISITA TECNICA | X71: SA00M803 | Y71: TIPO I | Z71: TERRESTRE | AA71: CUERO RUIZ JHONNY | AB71: 1 | AC71: 0 | AD71: 65960 | AE71: 75096 | AF71: 65960
A72: VILLAVICENCIO | B72: REMOTAS | C72: 0004-0007 | D72: 50313 | E72: 2968192 | F72: 3007056118 | G72: INCIDENTE | H72: META | I72: GRANADA | J72: BARRIO PARAISO MEDIO EL PARAIS | K72: REDEBAN | L72: FO-25-1772744 | M72: 45964.565 | N72: 45965.633 | O72: NO | P72: HARDWARE | Q72: IMPRESION | R72: NO AVANZA PAPEL | S72: CB UNO A UNO | T72: CB UNO A UNO | U72: EJECUTADO | V72: 03/11/2025 SE ESCALA PARA VISITA. LLAMAR ANTES DE VISITAR, CONFIRMAR FALLA Y DATOS | 04/11/2025 SE REALIZA CAMBIO DE DATAFONO POR DAÑO EN IMPRESORA, NO AVANZA EL PAPEL, SE CREA USUARIO, PRUEBAS OK | W72: VISITA TECNICA | X72: 9BMZZ479 | Y72: TIPO II | Z72: TERRESTRE | AA72: MURCIA HERNANDEZ HARVEY IGNACIO | AB72: 1 | AC72: 0 | AD72: 144968 | AE72: 140396 | AF72: 144968
A73: MEDELLIN | B73: NOROCCIDENTE | C73: 0004-0005 | D73: 5001 | E73: 2968260 | F73: 3007040473 | G73: INCIDENTE | H73: ANTIOQUIA | I73: MEDELLIN | J73: DISTRICOL MISCELANEA LA 45 | K73: REDEBAN | L73: FO-25-1774106 | M73: 45964.739 | N73: 45965.638 | O73: NO | P73: HARDWARE | Q73: CABLEADO | R73: DAÑO POS | S73: AGREGADOR | T73: DISTRICOL | U73: EJECUTADO | V73: 04/11/2025 SE ESCALA PARA VISITA. LLAMAR ANTES DE VISITAR, CONFIRMAR FALLA Y DATOS | 04/11/2025 SE VALIDA EL CABLEADO EN EL PUNTO Y ESTÁ BIEN, PERO NO CUENTA CON TAPA EL POS Y LO MUEVEN MUCHO POR LO CUAL, SE LE PONE UNA TAPA AL POS Y SE RECORTA UNA PARTE DEL ENSORTIJADO PARA QUE ENCAJE EL LECTOR DE BARRAS. | W73: VISITA TECNICA | X73: AB0LZ209 | Y73: TIPO I | Z73: TERRESTRE | AA73: MARIN PIEDRAHITA JIMMY ALEXIS | AB73: 1 | AC73: 0 | AD73: 65960 | AE73: 75096 | AF73: 65960
A74: CUCUTA | B74: SANTANDERES | C74: 0004-0008 | D74: 54518 | E74: 2968401 | F74: 3007078628 | G74: INCIDENTE | H74: NORTE DE SANTANDER | I74: PAMPLONA | J74: BARRIO CENTRO PAMPLONA 23 | K74: REDEBAN | L74: FO-25-1773424 | M74: 45964.621 | N74: 45966.721 | O74: NO | P74: HARDWARE | Q74: CABLEADO | R74: CABLE MAGICBOX AVERIADO | S74: CB UNO A UNO | T74: CB UNO A UNO | U74: EJECUTADO | V74: 03/11/2025 SE ESCALA PARA VISITA. LLAMAR ANTES DE VISITAR, CONFIRMAR FALLA Y DATOS | 05/11/2025 SE VISITA COMERCIO, SE REALIZA CAMBIO DE CABLE MAGIC BOX POR DAÑO, SE HACEN PRUEBAS EXITOSA, CB OPERATIVO. | W74: VISITA TECNICA | X74: FAMZZ302 | Y74: TIPO III | Z74: TERRESTRE | AA74: NARANJO AFANADOR RUBEN JESUS | AB74: 1 | AC74: 0 | AD74: 275729 | AE74: 196537 | AF74: 275729
A75: IBAGUE | B75: REMOTAS | C75: 0004-0007 | D75: 17380 | E75: 2968735 | F75: 3007065582 | G75: INCIDENTE | H75: CALDAS | I75: LA DORADA | J75: DISTRICOL KARAMELO TIENDA | K75: REDEBAN | L75: FO-25-1774105 | M75: 45965.333 | N75: 45966.707 | O75: NO | P75: HARDWARE | Q75: COMUNICACION | R75: DAÑO POS | S75: AGREGADOR | T75: DISTRICOL | U75: EJECUTADO | V75: 04/11/2025 SE ESCALA PARA VISITA. LLAMAR ANTES DE VISITAR, CONFIRMAR FALLA Y DATOS | 05/11/2025 SE CAMBIA DATÁFONO POR FALLA DEL PUERTO RJ-45 DE CONEXIÓN A INTERNET. SE HACEN LAS PRUEBAS DE TRANSACCIONES TODO OK | W75: VISITA TECNICA | X75: 4A00B173 | Y75: TIPO III | Z75: TERRESTRE | AA75: VARGAS HERRERA JHON JAIRO | AB75: 1 | AC75: 0 | AD75: 275729 | AE75: 196537 | AF75: 275729
A76: CUCUTA | B76: SANTANDERES | C76: 0004-0008 | D76: 54001 | E76: 2968872 | F76: 3007072904 | G76: INCIDENTE | H76: NORTE DE SANTANDER | I76: CUCUTA | J76: BARRIO RAFAEL NUNEZ CUCUTA 1 | K76: REDEBAN | L76: FO-25-1774635 | M76: 45965.36 | N76: 45965.508 | O76: NO | P76: HARDWARE | Q76: PANTALLA | R76: DAÑO POS | S76: CB UNO A UNO | T76: CB UNO A UNO | U76: EJECUTADO | V76: 04/11/2025 SE ESCALA PARA VISITA. LLAMAR ANTES DE VISITAR, CONFIRMAR FALLA Y DATOS | 04/11/2025 SE VISITA COMERCIO, SE REALIZA CAMBIO DE DATFONO POR DAÑO DE PANTALLA, SE HACEN PRUEBAS OK. | W76: VISITA TECNICA | X76: EF00S444 | Y76: TIPO I | Z76: TERRESTRE | AA76: NARANJO AFANADOR RUBEN JESUS | AB76: 1 | AC76: 0 | AD76: 65960 | AE76: 75096 | AF76: 65960
A77: BUCARAMANGA | B77: SANTANDERES | C77: 0004-0008 | D77: 68547 | E77: 2969105 | F77: 3007037553 | G77: INCIDENTE | H77: SANTANDER | I77: PIEDECUESTA | J77: PTM PIEDECUESTA EL EDEN | K77: REDEBAN | L77: FO-25-1774631 | M77: 45965.364 | N77: 45965.713 | O77: NO | P77: HARDWARE | Q77: PINPAD | R77: ALERTADO | S77: AGREGADOR | T77: COMCARD - PTM | U77: EJECUTADO | V77: 04/11/2025 SE ESCALA PARA VISITA. LLAMAR ANTES DE VISITAR, CONFIRMAR FALLA Y DATOS | 04/11/2025 AE VISITA COMERCIO SE REALIZA EL CAMBIO DE EQUIPO DATÁFONO OK, PINPAD OK, VERSION 10.3 OK , SE REALIZAN PRUEBAS OK, PINPAD OK, LECTOR DE BARRAS OK, CB OPERATIVO | W77: VISITA TECNICA | X77: GZ00O438 XP08Z051 | Y77: TIPO II | Z77: TERRESTRE | AA77: BARAJAS BERMUDEZ YAHIR MAURICIO | AB77: 1 | AC77: 0 | AD77: 144968 | AE77: 140396 | AF77: 144968
A78: VILLAVICENCIO | B78: REMOTAS | C78: 0004-0007 | D78: 50226 | E78: 2969160 | F78: 3007032635 | G78: INCIDENTE | H78: META | I78: CUMARAL | J78: BARRIO CENTRO CUMARAL META 1 | K78: REDEBAN | L78: FO-25-1775226 | M78: 45965.373 | N78: 45966.488 | O78: NO | P78: HARDWARE | Q78: ALERT IRRUPTION | R78: ALERT IRRUPTION | S78: UNO A UNO | T78: CB UNO A UNO | U78: EJECUTADO | V78: 04/11/2025 SE ESCALA PARA VISITA. LLAMAR ANTES DE VISITAR, CONFIRMAR FALLA Y DATOS | 05/11/2025 SE REALIZA VISITA AL CB POR SOLICITUD DATÁFONO ALERTADO, SE LLEGA AL PUNTO Y SE VERIFICA EL DATÁFONO EFECTIVAMENTE TIENE LA FALLA ALERT INTERRUPTION SE PROSE DE A REALIZAR EL CAMBIO DE EQUIPO SE INSTALA EL NUEVO SE REALIZAN PRUEBAS Y TODO OK | W78: VISITA TECNICA | X78: BL01X771 | Y78: TIPO II | Z78: TERRESTRE | AA78: MOLINA CASTRO JAVIER ALBERTO | AB78: 1 | AC78: 0 | AD78: 144968 | AE78: 140396 | AF78: 144968
A79: VILLAVICENCIO | B79: REMOTAS | C79: 0004-0007 | D79: 94343 | E79: 2969191 | F79: 3007070792 | G79: INCIDENTE | H79: GUAINIA | I79: BARRANCO MINAS | J79: BARRANCOMINAS | K79: REDEBAN | L79: FO-25-1775222 | M79: 45965.38 | N79: 45968.758 | P79: SOFTWARE | Q79: LECTOR DE BARRAS | R79: LECTOR DESCONFIGURADO | S79: CB UNO A UNO | T79: CB UNO A UNO | V79: 04/11/2025 SE ESCALA PARA VISITA. LLAMAR ANTES DE VISITAR, CONFIRMAR FALLA Y DATOS | 07/11/2025 SE REALIZA CONTACTO VÍA WHATSAPP CON LA SEÑORA KAREN AL NÚMERO 3118522225 SE REALIZA SOPORTE A LECTOR DE BARRAS, CONFIGURACIÓN OK PRUEBAS OK SIN NOVEDAD | W79: SOPORTE TELEFONICO | Y79: TIPO V | Z79: AEREO | AA79: CASTRILLON URREA LONDIER LEANDRO | AB79: 0 | AC79: 0 | AD79: 41241 | AE79: 0 | AF79: 41241
A80: CALI | B80: SUROCCIDENTE Y EJE CAFETERO | C80: 0004-0003 | D80: 76111 | E80: 2969394 | F80: 3007070395 | G80: INCIDENTE | H80: VALLE DEL CAUCA | I80: GUADALAJARA DE BUGA | J80: DISTRICOL MISCEL. NAGASHIMA | K80: REDEBAN | L80: FO-25-1775221 | M80: 45965.38 | N80: 45966.484 | O80: NO | P80: HARDWARE | Q80: COMUNICACION | R80: MENSAJE CABLE DE RED DESCONECTADO | S80: AGREGADOR | T80: DISTRICOL | U80: EJECUTADO / CANCELADO | V80: 04/11/2025 SE ESCALA PARA VISITA. LLAMAR ANTES DE VISITAR, CONFIRMAR FALLA Y DATOS | 05/11/2025 SE REALIZÓ GESTIÓN TELEFÓNICA Y SE CONFIRMÓ LA VISITA CON LA CLIENTE, AL LLEGAR AL SITIO UBICADO CON LA DIRECCIÓN EXACTA REGISTRADA NO SE ENCONTRÓ EL COMERCIO, SE CONTACTÓ NUEVAMENTE LA CLIENTE LA CUAL ME INDICA QUE ÉL CB YA SE ENCUENTRA EN OTRA DIRECCIÓN YA QUE SE TRASLADÓ, REDEBAN NO AUTORIZA ATENDER ESTE SERVICIO YA QUE AÚN NO EXISTE UNA SOLICITUD DE TRASLADO PARA LA ACTUALIZACIÓN DE LA DIRECCIÓN DEL CB EN EL SISTEMA, SE CONTACTA LA CLIENTA Y SE LE INDICA QUE DEBE HACER DICHA SOLICITUD Y SOLICITAR EL SERVICIO NUEVAMENTE. | W80: VISITA TECNICA | X80: NO HUBO INTERVENCIÓN A LOS EQUIPOS. | Y80: TIPO II | Z80: TERRESTRE | AA80: SANCHEZ URREGO ROBINSON DAVID | AB80: 1 | AC80: 0 | AD80: 144968 | AE80: 140396 | AF80: 144968
A81: CALI | B81: SUROCCIDENTE Y EJE CAFETERO | C81: 0004-0003 | D81: 19455 | E81: 2969594 | F81: 3007066993 | G81: INCIDENTE | H81: CAUCA | I81: MIRANDA | J81: PAGAFACIL MIRANDA | K81: REDEBAN | L81: FO-25-1775214 | M81: 45965.393 | N81: 45966.565 | O81: NO | P81: HARDWARE | Q81: HUB | R81: PUERTO USB DAÑADO | S81: ROBUSTO | T81: PAGAFACIL | U81: EJECUTADO | V81: 04/11/2025 SE ESCALA PARA VISITA. LLAMAR ANTES DE VISITAR, CONFIRMAR FALLA Y DATOS | 05/11/2025 SE REALIZA CABIO DE 3 HUB, 2 POR HB2 PUERTOS USB MALOS Y 1 POR HB3 NO RECONOCE CONECTOR, CB BANCOLOMBIA PURO, PRUEBAS OK | W81: VISITA TECNICA | X81: 6Z0IZ665 - 6Z0HZ950 - 6Z0IZ664 | Y81: TIPO III | Z81: TERRESTRE | AA81: PAREDES CASTILLO DIEGO | AB81: 1 | AC81: 0 | AD81: 275729 | AE81: 196537 | AF81: 275729
A82: MEDELLIN | B82: NOROCCIDENTE | C82: 0004-0005 | D82: 27361 | E82: 2969771 | F82: 3007046094 | G82: INCIDENTE | H82: CHOCO | I82: ISTMINA | J82: BARRIO CALLE PRINCIPAL ISTMINA | K82: REDEBAN | L82: FO-25-1775208 | M82: 45965.395 | N82: 45966.724 | O82: NO | P82: SOFTWARE | Q82: SE REINICIA | R82: AL REALIZAR CIERRE CARGA VERSION | S82: CB UNO A UNO | T82: CB UNO A UNO | U82: EJECUTADO | V82: 04/11/2025 SE ESCALA PARA VISITA. LLAMAR ANTES DE VISITAR, CONFIRMAR FALLA Y DATOS | 05/11/2025 SE REILZA CAMBIO DE EQUIPO POR REINICIO, SE REALIZA PRUEBAS Y EL CB QUEDA OPERATIVO | W82: VISITA TECNICA | X82: XP004638 | Y82: TIPO V | Z82: AEREO | AA82: ROBLEDO DIAZ ANDRES FELIPE | AB82: 1 | AC82: 0 | AD82: 988463 | AE82: 196537 | AF82: 988463
A83: CALI | B83: SUROCCIDENTE Y EJE CAFETERO | C83: 0004-0003 | D83: 76364 | E83: 2969804 | F83: 3007077110 | G83: INCIDENTE | H83: VALLE DEL CAUCA | I83: JAMUNDI | J83: BARRIO JAMUNDI JAMUNDI 2 | K83: REDEBAN | L83: FO-25-1775210 | M83: 45965.394 | N83: 45966.418 | O83: NO | P83: HARDWARE | Q83: HUB | R83: SE REINICIA | S83: CB UNO A UNO | T83: CB UNO A UNO | U83: EJECUTADO | V83: 04/11/2025 SE ESCALA PARA VISITA. LLAMAR ANTES DE VISITAR, CONFIRMAR FALLA Y DATOS | 05/11/2025 SE REALIZA CAMBIO DE HUB DEBIDO A DAÑO EN EL CABLE LO QUE OCASIONA CONSTANTES REINICIOS, SE REALIZA CAMBIO DE VERSIÓN YA QUE EL DATAFONO CONTABA CON LA VERSIÓN 9.92, SE REALIZAN PRUEBAS OK. | W83: VISITA TECNICA | X83: LM8ZZ321 | Y83: TIPO II | Z83: TERRESTRE | AA83: MONTERO MUESES GIAN CARLO | AB83: 1 | AC83: 0 | AD83: 144968 | AE83: 140396 | AF83: 144968
A84: IBAGUE | B84: REMOTAS | C84: 0004-0007 | D84: 17495 | E84: 2970300 | F84: 3007024076 | G84: INCIDENTE | H84: CALDAS | I84: NORCASIA | J84: PTM MULTIMOVIL FC | K84: REDEBAN | L84: FO-25-1775530 | M84: 45965.416 | N84: 45967.603 | O84: NO | P84: HARDWARE | Q84: TECLADO | R84: DAÑO POS | S84: AGREGADOR | T84: COMCARD - PTM | U84: EJECUTADO | V84: 04/11/2025 SE ESCALA PARA VISITA. LLAMAR ANTES DE VISITAR, CONFIRMAR FALLA Y DATOS | 06/11/2025 SE CAMBIA DATÁFONO POR DETERIORO DEL TECLADO. SE HACEN LAS PRUEBAS DE TRANSACCIONES TODO OK | W84: VISITA TECNICA | X84: ABC0W563 MA00C043 | Y84: TIPO IV | Z84: TERRESTRE | AA84: VARGAS HERRERA JHON JAIRO | AB84: 1 | AC84: 0 | AD84: 479589 | AE84: 196537 | AF84: 479589
A85: CALI | B85: SUROCCIDENTE Y EJE CAFETERO | C85: 0004-0003 | D85: 76001 | E85: 2970543 | F85: 3007041183 | G85: INCIDENTE | H85: VALLE DEL CAUCA | I85: CALI | J85: PTM CALI LA EXITOSA | K85: REDEBAN | L85: FO-25-1776465 | M85: 45965.43 | N85: 45965.581 | O85: NO | P85: HARDWARE | Q85: IMPRESION | R85: NO IMPRIME UNO O VARIOS CARACTERES | S85: AGREGADOR | T85: COMCARD - PTM | U85: EJECUTADO | V85: 04/11/2025 SE ESCALA PARA VISITA. LLAMAR ANTES DE VISITAR, CONFIRMAR FALLA Y DATOS | 04/11/2025 SE REALIZA LIMPIEZA EN IMPRESORA, SE CAMBIA FUENTE Y MAGIC BOX DEBIDO A IMPRESIÓN BORROSA, SE REALIZA CAMBIO DE VERSIÓN EN EL DATAFONO YA QUE CONTABA CON LA VERSIÓN 9.92, SE REALIZAN PRUEBAS OK. | W85: VISITA TECNICA | X85: AA0QZ396 | Y85: TIPO I | Z85: TERRESTRE | AA85: MONTERO MUESES GIAN CARLO | AB85: 1 | AC85: 0 | AD85: 65960 | AE85: 75096 | AF85: 65960
A86: MEDELLIN | B86: NOROCCIDENTE | C86: 0004-0005 | D86: 5697 | E86: 2970647 | F86: 3007026801 | G86: INCIDENTE | H86: ANTIOQUIA | I86: EL SANTUARIO | J86: BARRIO SANTUARIO EL SANTUARIO | K86: REDEBAN | L86: FO-25-1776463 | M86: 45965.431 | N86: 45966.668 | O86: NO | P86: HARDWARE | Q86: SE REINICIA | R86: DAÑO POS | S86: UNO A UNO | T86: CB UNO A UNO | U86: EJECUTADO | V86: 04/11/2025 SE ESCALA PARA VISITA. LLAMAR ANTES DE VISITAR, CONFIRMAR FALLA Y DATOS | 05/11/2025 SE REALIZA CAMBIO DE FUENTE DE PODER YA QUE SE REINICIABA TRAS EL TACTO | W86: VISITA TECNICA | X86: 9999X094 | Y86: TIPO II | Z86: TERRESTRE | AA86: HERNANDEZ CHAVARRIA JUAN CAMILO | AB86: 1 | AC86: 0 | AD86: 144968 | AE86: 140396 | AF86: 144968
A87: MEDELLIN | B87: NOROCCIDENTE | C87: 0004-0005 | D87: 5376 | E87: 2970949 | F87: 3007074193 | G87: INCIDENTE | H87: ANTIOQUIA | I87: LA CEJA | J87: BARRIO CORREGIMIENTO SAN JOSE | K87: REDEBAN | L87: FO-25-1776448 | M87: 45965.447 | N87: 45966.451 | O87: NO | P87: HARDWARE | Q87: LECTOR DE BARRAS | R87: FORMATO INVALIDO LECTOR DAÑADO | S87: CB UNO A UNO | T87: CB UNO A UNO | U87: EJECUTADO | V87: 04/11/2025 SE ESCALA PARA VISITA. LLAMAR ANTES DE VISITAR, CONFIRMAR FALLA Y DATOS | 05/11/2025 SE REALIZA CONFIGURACIÓN DE LECTOR YA QUE ESTABA DESCONOCIDO FIGURADO | W87: VISITA TECNICA | X87: EG2ZZ991 | Y87: TIPO II | Z87: TERRESTRE | AA87: HERNANDEZ CHAVARRIA JUAN CAMILO | AB87: 1 | AC87: 0 | AD87: 144968 | AE87: 140396 | AF87: 144968
A88: MEDELLIN | B88: NOROCCIDENTE | C88: 0004-0005 | D88: 5001 | E88: 2971062 | F88: 3007012705 | G88: INCIDENTE | H88: ANTIOQUIA | I88: MEDELLIN | J88: PAGAFACIL SAN ANTONIO DE PRADO | K88: REDEBAN | L88: FO-25-1776446 | M88: 45965.452 | N88: 45965.69 | P88: SOFTWARE | Q88: LECTOR DE BARRAS | R88: LECTOR DESCONFIGURADO | S88: ROBUSTO | T88: PAGAFACIL | V88: 04/11/2025 SE ESCALA PARA VISITA. LLAMAR ANTES DE VISITAR, CONFIRMAR FALLA Y DATOS | 04/11/2025 SE LLAMA AL CLIENTE Y SE LE INDICA COMO HABILITAR EL LECTOR DE BARRAS, QUEDA OPERATIVO | W88: SOPORTE TELEFONICO | Y88: TIPO I | Z88: TERRESTRE | AA88: CARDONA MOLINA BROLIN STIVEN | AB88: 0 | AC88: 0 | AD88: 41241 | AE88: 0 | AF88: 41241
A89: MEDELLIN | B89: NOROCCIDENTE | C89: 0004-0005 | D89: 27361 | E89: 2971236 | F89: 3007073470 | G89: INCIDENTE | H89: CHOCO | I89: ISTMINA | J89: PTM ITSMINA VARIEDADES MARIAMI | K89: REDEBAN | L89: FO-25-1776483 | M89: 45965.46 | N89: 45967.427 | O89: NO | P89: HARDWARE | Q89: SE REINICIA | R89: DAÑO POS | S89: AGREGADOR | T89: COMCARD - PTM | U89: EJECUTADO / CANCELADO | V89: 04/11/2025 SE ESCALA PARA VISITA. LLAMAR ANTES DE VISITAR, CONFIRMAR FALLA Y DATOS | 06/11/2025 SE REALIZA VISITA, SE ENCONTRABA COMERCIO CERRADO, SE INTENTA COMUNICACIÓN SIN EXITO | W89: VISITA TECNICA | X89: MM00Y632 | Y89: TIPO V | Z89: AEREO | AA89: ROBLEDO DIAZ ANDRES FELIPE | AB89: 1 | AC89: 0 | AD89: 988463 | AE89: 196537 | AF89: 988463
A90: BUCARAMANGA | B90: SANTANDERES | C90: 0004-0008 | D90: 13688 | E90: 2971279 | F90: 3007080807 | G90: INCIDENTE | H90: BOLIVAR | I90: SANTA ROSA DEL SUR | J90: BARRIO SAN MARTIN SANTA ROSA DEL SUR 3 | K90: REDEBAN | L90: FO-25-1776439 | M90: 45965.466 | N90: 45967.46 | O90: NO | P90: HARDWARE | Q90: IMPRESION | R90: NO IMPRIME UNO O VARIOS CARACTERES | S90: UNO A UNO | T90: UNO A UNO | U90: EJECUTADO | V90: 04/11/2025 SE ESCALA PARA VISITA. LLAMAR ANTES DE VISITAR, CONFIRMAR FALLA Y DATOS | 06/11/2025 CAMBIO DE EQUIPO POR DAÑO EN LA IMPRESORA SE HACEN PRUEBAS EXITOSA | W90: VISITA TECNICA | X90: F8ZZZ005 | Y90: TIPO V | Z90: TERRESTRE/FLUVIAL | AA90: PEÑA DIAZ IVAN YESID | AB90: 1 | AC90: 0 | AD90: 479589 | AE90: 196537 | AF90: 479589
A91: APARTADO | B91: NOROCCIDENTE | C91: 0004-0005 | D91: 5045 | E91: 2971429 | F91: 3007043294 | G91: INCIDENTE | H91: ANTIOQUIA | I91: APARTADO | J91: BARRIO LA MARTINA APARTADO | K91: REDEBAN | L91: FO-25-1776433 | M91: 45965.475 | N91: 45966.456 | O91: NO | P91: HARDWARE | Q91: NO ENCIENDE SE REINICIA | R91: FUENTE PODER AVERIADA | S91: CB UNO A UNO | T91: CB UNO A UNO | U91: EJECUTADO | V91: 04/11/2025 SE ESCALA PARA VISITA. LLAMAR ANTES DE VISITAR, CONFIRMAR FALLA Y DATOS | 05/11/2025 DATAFONO NO ENCIENDE Y SE REINICIA CONSTANTEMENTE, SE VALIDA BATERIA Y TERMINAL(DATAFONO) Y SE ENCUENTRAN EN PERFECTO ESTADO. SE PRUEBA CON OTRA MAGIBOX Y SE IDENTIFICA QUE LA EXISTENTE TIENE PROBLEMAS DE PODER QUE HACE QUE SE REINICIE EL EQUIPO CONSTANTEMENTE. SE INSTALA UNA NUEVA MAGIBOX SE HACEN PRUEBAS Y YA EL DATAFONO NO SE REINICIA AL MOMENTO DE HACER MOVIMIENTOS, TODO SE DEJA OK | W91: VISITA TECNICA | X91: GB0DZ166 | Y91: TIPO I | Z91: TERRESTRE | AA91: SALDARRIAGA MIRANDA SANTIAGO | AB91: 1 | AC91: 0 | AD91: 65960 | AE91: 75096 | AF91: 65960
A92: MEDELLIN | B92: NOROCCIDENTE | C92: 0004-0005 | D92: 5234 | E92: 2971458 | F92: 3007010420 | G92: INCIDENTE | H92: ANTIOQUIA | I92: DABEIBA | J92: DABEIBA II - ANTIOQUIA | K92: REDEBAN | L92: FO-25-1776428 | M92: 45965.479 | N92: 45965.766 | O92: NO | P92: HARDWARE | Q92: IMPRESION | R92: NO IMPRIME UNO O VARIOS CARACTERES | S92: CB UNO A UNO | T92: CB UNO A UNO | U92: EJECUTADO | V92: 04/11/2025 SE ESCALA PARA VISITA. LLAMAR ANTES DE VISITAR, CONFIRMAR FALLA Y DATOS | 04/11/2025 SE LIMPIA ROLLO DE IMPRESORA PORQUE ESTABA MUY SUCIO Y SE LIMPIA LA IMPRESORA DEJÁNDOLA OK | W92: VISITA TECNICA | X92: BA0LZ914 | Y92: TIPO IV | Z92: TERRESTRE | AA92: RUA ALVAREZ RICHARD ANDRES | AB92: 1 | AC92: 0 | AD92: 479589 | AE92: 196537 | AF92: 479589
A93: BUCARAMANGA | B93: SANTANDERES | C93: 0004-0008 | D93: 68001 | E93: 2971604 | F93: 3007033739 | G93: INCIDENTE | H93: SANTANDER | I93: BUCARAMANGA | J93: COMCARD B MANGA CENTRAL | K93: REDEBAN | L93: FO-25-1776431 | M93: 45965.478 | N93: 45965.641 | O93: NO | P93: HARDWARE | Q93: IMPRESION | R93: TAPA IMPRESORA | S93: AGREGADOR | T93: COMCARD - PTM | U93: EJECUTADO | V93: 04/11/2025 SE ESCALA PARA VISITA. LLAMAR ANTES DE VISITAR, CONFIRMAR FALLA Y DATOS | 04/11/2025 SE REALIZA CAMBIO DE ETAPA LECTORA EQUIPO DESK 3500 PRUEBAS OK SERVICIO OPERATIVO | W93: VISITA TECNICA | X93: 1EZZZ877 II00S835 | Y93: TIPO I | Z93: TERRESTRE | AA93: REYES RAMIREZ DIEGO ALEXANDER | AB93: 1 | AC93: 0 | AD93: 65960 | AE93: 75096 | AF93: 65960
A94: MANIZALES | B94: SUROCCIDENTE Y EJE CAFETERO | C94: 0004-0002 | D94: 17001 | E94: 2971738 | F94: 3007026345 | G94: INCIDENTE | H94: CALDAS | I94: MANIZALES | J94: MERCALDAS CRISTO REY | K94: REDEBAN | L94: FO-25-1776492 | M94: 45965.489 | N94: 45966.425 | O94: NO | P94: HARDWARE | Q94: LECTOR DE BARRAS | R94: CABLE LECTORA AVERIADO | S94: CB UNO A UNO | T94: MERCALDAS | U94: EJECUTADO | V94: 04/11/2025 SE ESCALA PARA VISITA. LLAMAR ANTES DE VISITAR, CONFIRMAR FALLA Y DATOS | 05/11/2025 SE REALIZA VISITA SE CAMBIA LECTORA POR CABLE EN MAL ESTADO Y DETERIORADA Y SE CAMBIA FUENTE DE PODER YA QUE HACE MAL CONTACTO Y LO REINICIA, SE HACEN PRUEBAS SERVICIO OK | W94: VISITA TECNICA | X94: SA00M796 | Y94: TIPO I | Z94: TERRESTRE | AA94: AGUIRRE HENAO RAUL EDUARDO | AB94: 1 | AC94: 0 | AD94: 65960 | AE94: 75096 | AF94: 65960
A95: CALI | B95: SUROCCIDENTE Y EJE CAFETERO | C95: 0004-0003 | D95: 76616 | E95: 2971742 | F95: 3007057317 | G95: INCIDENTE | H95: VALLE DEL CAUCA | I95: RIOFRIO | J95: BARRIO CENTRO RIOFRIO 4 | K95: REDEBAN | L95: FO-25-1776489 | M95: 45965.49 | N95: 45966.669 | O95: NO | P95: HARDWARE | Q95: IMPRESION | R95: NO IMPRIME UNO O VARIOS CARACTERES | S95: CB UNO A UNO | T95: CB UNO A UNO | U95: EJECUTADO | V95: 04/11/2025 SE ESCALA PARA VISITA. LLAMAR ANTES DE VISITAR, CONFIRMAR FALLA Y DATOS | 05/11/2025 SE LLAMA AL CLIENTE SE VÁLIDA INCIDENTE Y DIRECCIÓN, SE VISITA EL COMERCIO, SE REVISA LOS EQUIPOS ESTÁ FALLANDO EL DATAFONO NO IMPRIME UNO O VARIOS CARACTERES POR LO QUE SE CAMBIA RESOLVIENDO EL DAÑO, PRUEBAS OK, TELECARGA TRNA | W95: VISITA TECNICA | X95: TRSZZ884 | Y95: TIPO II | Z95: TERRESTRE | AA95: HERRERA MONAR GEOVANNY | AB95: 1 | AC95: 0 | AD95: 144968 | AE95: 140396 | AF95: 144968
A96: APARTADO | B96: NOROCCIDENTE | C96: 0004-0005 | D96: 5045 | E96: 2971786 | F96: 3007037866 | G96: INCIDENTE | H96: ANTIOQUIA | I96: APARTADO | J96: DISTRICOL SERVITODO | K96: REDEBAN | L96: FO-25-1776585 | M96: 45965.5 | N96: 45966.432 | O96: NO | P96: HARDWARE | Q96: LECTOR DE BARRAS | R96: DAÑO POS | S96: AGREGADOR | T96: DISTRICOL | U96: EJECUTADO | V96: 04/11/2025 SE ESCALA PARA VISITA. LLAMAR ANTES DE VISITAR, CONFIRMAR FALLA Y DATOS | 05/11/2025 SE HACE CAMBIO DE LECTORA YA QUE LA ACTUAL NO ENCIENDE Y CUANDO ENCIENDE NO LEE LOS CODIGOS DE BARRA. SE HACEN PRUEBA DE LECTORA DEJANDO TODO OK | W96: VISITA TECNICA | X96: GZ00R505 | Y96: TIPO I | Z96: TERRESTRE | AA96: SALDARRIAGA MIRANDA SANTIAGO | AB96: 1 | AC96: 0 | AD96: 65960 | AE96: 75096 | AF96: 65960
A97: MEDELLIN | B97: NOROCCIDENTE | C97: 0004-0005 | D97: 5190 | E97: 2972066 | F97: 3007018751 | G97: INCIDENTE | H97: ANTIOQUIA | I97: CISNEROS | J97: COMCARD CISNEROS CELUFER | K97: REDEBAN | L97: FO-25-1776805 | M97: 45965.519 | N97: 45965.645 | O97: NO | P97: HARDWARE | Q97: LECTOR DE TARJETAS | R97: DAÑO POS | S97: AGREGADOR | T97: COMCARD - PTM | U97: EJECUTADO | V97: 04/11/2025 SE ESCALA PARA VISITA. LLAMAR ANTES DE VISITAR, CONFIRMAR FALLA Y DATOS | 04/11/2025 SE LIMPIA CONTACTO DE LECTOR CHIP SE HACEN PRUEBAS OK | W97: VISITA TECNICA | X97: PZZZZ647 | Y97: TIPO II | Z97: TERRESTRE | AA97: ALVAREZ ARENAS VICTOR HUGO | AB97: 1 | AC97: 0 | AD97: 144968 | AE97: 140396 | AF97: 144968
A98: MEDELLIN | B98: NOROCCIDENTE | C98: 0004-0005 | D98: 5148 | E98: 2972072 | F98: 3007073576 | G98: INCIDENTE | H98: ANTIOQUIA | I98: EL CARMEN DE VIBORAL | J98: DISTRICOL TIENDA OWEN EL CARME | K98: REDEBAN | L98: FO-25-1776804 | M98: 45965.52 | N98: 45966.551 | O98: NO | P98: HARDWARE | Q98: SE REINICIA | R98: DAÑO POS | S98: AGREGADOR | T98: DISTRICOL | U98: EJECUTADO | V98: 04/11/2025 SE ESCALA PARA VISITA. LLAMAR ANTES DE VISITAR, CONFIRMAR FALLA Y DATOS | 05/11/2025 SE REALIZA CAMBIO DE EQUIPO YA QUE SE ESTÁ REINICIANDO Y LAS TIRILLAS LAS SACA MUY BORROSAS | W98: VISITA TECNICA | X98: SV00W501 | Y98: TIPO II | Z98: TERRESTRE | AA98: HERNANDEZ CHAVARRIA JUAN CAMILO | AB98: 1 | AC98: 0 | AD98: 144968 | AE98: 140396 | AF98: 144968
A99: MONTERIA | B99: COSTA | C99: 0004-0001 | D99: 23162 | E99: 2972298 | F99: 3007058628 | G99: INCIDENTE | H99: CORDOBA | I99: CERETE | J99: DISTRICOL PARAISO TROPICAL | K99: REDEBAN | L99: FO-25-1777073 | M99: 45965.543 | N99: 45966.529 | O99: NO | P99: SOFTWARE | Q99: ACTUALIZACION | R99: VERSION CARGA SO VR | S99: AGREGADOR | T99: DISTRICOL | U99: EJECUTADO | V99: 04/11/2025 SE ESCALA PARA VISITA. LLAMAR ANTES DE VISITAR, CONFIRMAR FALLA Y DATOS | 05/11/2025 SE FORMATEA DATAFONO, SE INSTALA SO Y VR 10.3 PARA SOLUCIONAR FALLA, SE REALIZAN PRUEBAS OK | W99: VISITA TECNICA | X99: IVZZZ943 | Y99: TIPO I | Z99: TERRESTRE | AA99: ARRAZOLA HERNANDEZ NICOLAS AUGUSTO | AB99: 1 | AC99: 0 | AD99: 65960 | AE99: 75096 | AF99: 65960
A100: BUCARAMANGA | B100: SANTANDERES | C100: 0004-0008 | D100: 68276 | E100: 2972423 | F100: 3007055358 | G100: INCIDENTE | H100: SANTANDER | I100: FLORIDABLANCA | J100: DISTRICOL DROGUERIA WENDY | K100: REDEBAN | L100: FO-25-1777061 | M100: 45965.558 | N100: 45966.483 | O100: NO | P100: HARDWARE | Q100: DETERIORO | R100: DATAFONO | S100: AGREGADOR | T100: DISTRICOL | U100: EJECUTADO | V100: 04/11/2025 SE ESCALA PARA VISITA. LLAMAR ANTES DE VISITAR, CONFIRMAR FALLA Y DATOS | 05/11/2025 SE REALIZA CAMBIO DE DATÁFONO POR DETERIORO PANTALLA Y PUERTO USB EN DAÑO, PRUEBAS Y LIMPIEZA DE EQUIPOS OK. | W100: VISITA TECNICA | X100: TRDZZ740 | Y100: TIPO I | Z100: TERRESTRE | AA100: MARTINEZ FLOREZ DONIS ALBERTO | AB100: 1 | AC100: 0 | AD100: 65960 | AE100: 75096 | AF100: 65960
... A105: VALLEDUPAR | B105: COSTA | C105: 0004-0001 | D105: 20001 | E105: 2972620 | F105: 3007081359 | G105: INCIDENTE | H105: CESAR | I105: VALLEDUPAR | J105: DISTRICOLSOLUCIONSERVICIOSPLAY | K105: REDEBAN | L105: FO-25-1777207 | M105: 45965.578 | N105: 45966.576 | O105: NO | P105: HARDWARE | Q105: IMPRESION | R105: NO AVANZA PAPEL | S105: AGREGADOR | T105: DISTRICOL | U105: EJECUTADO | V105: 04/11/2025 SE ESCALA PARA VISITA. LLAMAR ANTES DE VISITAR, CONFIRMAR FALLA Y DATOS | 05/11/2025 SE REALIZA VISITA POR SOLCITUD DE CLIENTE,SE LLEGA A SITIO CLIENTE NOS MANIFIESTA QUE EN OCACIONES EL DATÁFONO REALIZA TRANSACCIÓN OERO NO IMPRIME EL EQUIPO EN DIAS ANTERIORES CLIENTE SE VISITO SE LE REALIZO BORRADO E INSTALACON DE VERSIONAMIENTO Y S.O Y A LOS DIAS VOLVIO EL EQUIPO A FALLAR, CON NUEVA VISITA SE REALIZA CAMBIÓ DE EQUIPO DEJANDO EQUIPO DESK 3500 PRUEBAS OK AL 100% | W105: VISITA TECNICA | X105: VGZZZ806 | Y105: TIPO I | Z105: TERRESTRE | AA105: MAESTRE MENGUAL EDGAR ENRIQUE | AB105: 1 | AC105: 0 | AD105: 65960 | AE105: 75096 | AF105: 65960
A106: VALLEDUPAR | B106: COSTA | C106: 0004-0001 | D106: 20011 | E106: 2972854 | F106: 3007010052 | G106: INCIDENTE | H106: CESAR | I106: AGUACHICA | J106: BARRIO MARIA EUGENIA | K106: REDEBAN | L106: FO-25-1777478 | M106: 45965.595 | N106: 45967.607 | P106: HARDWARE | Q106: COMUNICACION | R106: MENSAJE CABLE DE RED DESCONECTADO | S106: CB UNO A UNO | T106: CB UNO A UNO | V106: 04/11/2025 SE ESCALA PARA VISITA. LLAMAR ANTES DE VISITAR, CONFIRMAR FALLA Y DATOS | 06/11/2025 SE REALIZA LLAMADA AL CLIENTE Y CONTESTA LA SEÑORA OLGA PEÑALOZA, LA CUAL INDICA QUE DIAS ANTERIORES TENIA FALLAS CON LA CONEXIÓN DE INTERNET PERO QUE HOY SE ENCUENTRA FUNCIONANDO CORRECTAMENTE, HA ESTADO HACIENDO CUALQUIER TIPO DE TRANSACCIÓN SIN NINGÚN INCONVENIENTE | W106: SOPORTE TELEFONICO | Y106: TIPO IV | Z106: TERRESTRE | AA106: MONTES DIAZ JOHN FRED | AB106: 0 | AC106: 0 | AD106: 41241 | AE106: 0 | AF106: 41241
A107: TUNJA | B107: SANTANDERES | C107: 0004-0008 | D107: 15176 | E107: 2973194 | F107: 3007039211 | G107: INCIDENTE | H107: BOYACA | I107: CHIQUINQUIRA | J107: BARRIO EL POLO CHIQUINQUIRA | K107: REDEBAN | L107: FO-25-1778025 | M107: 45965.61 | N107: 45966.534 | O107: NO | P107: HARDWARE | Q107: IMPRESION | R107: RODILLO AVERIADO | S107: CB UNO A UNO | T107: CB UNO A UNO | U107: EJECUTADO | V107: 04/11/2025 SE ESCALA PARA VISITA. LLAMAR ANTES DE VISITAR, CONFIRMAR FALLA Y DATOS | 05/11/2025 SE VISITA CB MANTENIMIENTO DE EQUIPO CAMBIO DE RODILLO POR DAÑO PRUEBAS EXITOSAS | W107: VISITA TECNICA | X107: GZ05Z829 | Y107: TIPO III | Z107: TERRESTRE | AA107: GONZALEZ GONZALEZ MARIO ALBERTO | AB107: 1 | AC107: 0 | AD107: 275729 | AE107: 196537 | AF107: 275729
A108: VALLEDUPAR | B108: COSTA | C108: 0004-0001 | D108: 20001 | E108: 2973413 | F108: 3007064360 | G108: INCIDENTE | H108: CESAR | I108: VALLEDUPAR | J108: PAGAFACIL GALERIA POPULAR | K108: REDEBAN | L108: FO-25-1778023 | M108: 45965.615 | N108: 45966.711 | O108: NO | P108: HARDWARE | Q108: PINPAD | R108: SE REINICIA | S108: ROBUSTO | T108: PAGAFACIL | U108: EJECUTADO | V108: 04/11/2025 SE ESCALA PARA VISITA. LLAMAR ANTES DE VISITAR, CONFIRMAR FALLA Y DATOS | 05/11/2025 SE REALIZA CAMBIÓ DE PIN PAD Y HUB POR REINICO CONTANTE , PRUEBAS OK AL 100 % | W108: VISITA TECNICA | X108: 7A003833 | Y108: TIPO I | Z108: TERRESTRE | AA108: MAESTRE MENGUAL EDGAR ENRIQUE | AB108: 1 | AC108: 0 | AD108: 65960 | AE108: 75096 | AF108: 65960
A109: CALI | B109: SUROCCIDENTE Y EJE CAFETERO | C109: 0004-0003 | D109: 76001 | E109: 2973656 | F109: 3007063111 | G109: INCIDENTE | H109: VALLE DEL CAUCA | I109: CALI | J109: PAGAFACIL PARQUE DE LA CANA | K109: REDEBAN | L109: FO-25-1788592 | M109: 45965.665 | N109: 45967.581 | O109: NO | P109: HARDWARE | Q109: SE REINICIA | R109: DAÑO POS | S109: ROBUSTO | T109: PAGAFACIL | U109: EJECUTADO | V109: 06/11/2025 SE ESCALA PARA VISITA. LLAMAR ANTES DE VISITAR, CONFIRMAR FALLA Y DATOS | 06/11/2025 SE LIMPIA DATAFONO SE CAMBIA MAGIC BOX TETRA Y QUEDA FUNCIONANDO CORRECTAMENTE | W109: VISITA TECNICA | X109: JA00T549 | Y109: TIPO I | Z109: TERRESTRE | AA109: CUERO RUIZ JHONNY | AB109: 1 | AC109: 0 | AD109: 65960 | AE109: 75096 | AF109: 65960
A110: BARRANQUILLA | B110: COSTA | C110: 0004-0001 | D110: 8001 | E110: 2974449 | F110: 3007058442 | G110: INCIDENTE | H110: ATLANTICO | I110: BARRANQUILLA | J110: PTM BARRANQUILLA DROGUERIA YI | K110: REDEBAN | L110: FO-25-1778804 | M110: 45965.696 | N110: 45966.473 | O110: NO | P110: HARDWARE | Q110: IMPRESION | R110: TAPA IMPRESORA | S110: AGREGADOR | T110: COMCARD - PTM | U110: EJECUTADO | V110: 26/10/2027 SE ESCALA PARA VISITA. LLAMAR ANTES DE VISITAR, CONFIRMAR FALLA Y DATOS | 05/11/2025 SE REALIZA VISITA AL COMERCIO SE ENCUENTRA DATÁFONO CON TAPA DE IMPRESORA DAÑADA LO CUAL NO DEJABA IMPRIMIR BIEN LOS VAUCHER SE CAMBIA TAPA DE IMPRESORA SE REALIZAN PRUEBAS EXITOSAS Y EL CB QUEDA OPERATIVO | W110: VISITA TECNICA | X110: XYZZZ949 TRYZZ127 | Y110: TIPO I | Z110: TERRESTRE | AA110: PEÑALOZA GUTIERREZ RAFAEL GUSTAVO | AB110: 1 | AC110: 0 | AD110: 65960 | AE110: 75096 | AF110: 65960
A111: BUCARAMANGA | B111: SANTANDERES | C111: 0004-0008 | D111: 54385 | E111: 2974635 | F111: 3007039800 | G111: INCIDENTE | H111: NORTE DE SANTANDER | I111: LA ESPERANZA | J111: BARRIO LA FERIA I LA ESPERANZA | K111: REDEBAN | L111: FO-25-1778803 | M111: 45965.698 | N111: 45967.5 | O111: NO | P111: HARDWARE | Q111: IMPRESION | R111: NO AVANZA PAPEL | S111: CB UNO A UNO | T111: CB UNO A UNO | U111: EJECUTADO | V111: 26/10/2027 SE ESCALA PARA VISITA. LLAMAR ANTES DE VISITAR, CONFIRMAR FALLA Y DATOS | 06/11/2025 SE REALIZA VISITA AL COMERCIO SE HACE CAMBIO DE DATAFONO SE REALIZAN PRUEBAS OK | W111: VISITA TECNICA | X111: 9A0EZ834 | Y111: TIPO III | Z111: TERRESTRE | AA111: MARIÑO PABON JORGE ENRIQUE | AB111: 1 | AC111: 0 | AD111: 275729 | AE111: 196537 | AF111: 275729
A112: BOGOTA | B112: CUNDINAMARCA | C112: 0004-0004 | D112: 11001 | E112: 2974762 | F112: 3007074887 | G112: INCIDENTE | H112: CUNDINAMARCA | I112: BOGOTA | J112: BARRIO PATIO BONITO 3 BOGOTA | K112: REDEBAN | L112: FO-25-1778885 | M112: 45965.725 | N112: 45966.49 | O112: NO | P112: HARDWARE | Q112: LECTOR DE TARJETAS | R112: DAÑO POS | S112: CB UNO A UNO | T112: CB UNO A UNO | U112: EJECUTADO | V112: 04/11/2025 SE ESCALA PARA VISITA. LLAMAR ANTES DE VISITAR, CONFIRMAR FALLA Y DATOS | 05/11/2025 SE LLEGA A LA DIRECCIÓN INDICADA Y SE REALIZA CAMBIO DE PINPAD POR BLOQUEO EN LECTOR DE CHIPS . CUPO OK, SE REALIZA PRUEBA DE CONSULTA DE SALDO SE CONFIRMA FUNCIONAMIENTO DE LECTOR DE CHIPS. | W112: VISITA TECNICA | X112: ONTZZ208 | Y112: TIPO I | Z112: TERRESTRE | AA112: GARCIA PASTRANA KEVIN FERNANDO | AB112: 1 | AC112: 0 | AD112: 65960 | AE112: 75096 | AF112: 65960
A113: BUCARAMANGA | B113: SANTANDERES | C113: 0004-0008 | D113: 68547 | E113: 2974976 | F113: 3007066265 | G113: INCIDENTE | H113: SANTANDER | I113: PIEDECUESTA | J113: DISTRICOL EL REY DG | K113: REDEBAN | L113: FO-25-1778940 | M113: 45966.333 | N113: 45966.414 | O113: NO | P113: HARDWARE | Q113: ALERT IRRUPTION | R113: ALERT IRRUPTION | S113: AGREGADOR | T113: DISTRICOL | U113: EJECUTADO | V113: 04/11/2025 SE ESCALA PARA VISITA. LLAMAR ANTES DE VISITAR, CONFIRMAR FALLA Y DATOS | 05/11/2025 SE REALIZA CAMBIO DE DATAFONO POR A6 CAMBIO DE S.O Y VERSIÓN 9.90 CREACIÓN DE USUARIOS PRUEBAS OK SERVICIO OPERATIVO | W113: VISITA TECNICA | X113: SA00M824 | Y113: TIPO II | Z113: TERRESTRE | AA113: REYES RAMIREZ DIEGO ALEXANDER | AB113: 1 | AC113: 0 | AD113: 144968 | AE113: 140396 | AF113: 144968
A114: VILLAVICENCIO | B114: REMOTAS | C114: 0004-0007 | D114: 50606 | E114: 2974987 | F114: 3007078912 | G114: INCIDENTE | H114: META | I114: RESTREPO | J114: BARRIO CENTRO RESTREPO 6 | K114: REDEBAN | L114: FO-25-1778938 | M114: 45966.333 | N114: 45966.672 | O114: NO | P114: HARDWARE | Q114: IMPRESION | R114: TAPA IMPRESORA | S114: CB UNO A UNO | T114: CB UNO A UNO | U114: EJECUTADO | V114: 04/11/2025 SE ESCALA PARA VISITA. LLAMAR ANTES DE VISITAR, CONFIRMAR FALLA Y DATOS | 05/11/2025 SE REALIZA VISITA AL CB POR SOLICITUD DE IMPRESORA NO FUNCIONA, SE LLEGA AL LUGAR Y SE VERIFICA EL EQUIPO Y SE EVIDENCIA QUE LA TAPA DEL DATÁFONO NO ESTÁ BIEN AJUSTADA, SE AJUSTA BIEN Y SE PEGA LA BASE YA QUE EL USUARIO COMENTA QUE POR ESTAR MOVIENDOLO SE DESAJUSTA, SE REALIZA PRUEBAS Y TODO OK | W114: VISITA TECNICA | X114: F1SZZ785 | Y114: TIPO II | Z114: TERRESTRE | AA114: MOLINA CASTRO JAVIER ALBERTO | AB114: 1 | AC114: 0 | AD114: 144968 | AE114: 140396 | AF114: 144968
A115: CALI | B115: SUROCCIDENTE Y EJE CAFETERO | C115: 0004-0003 | D115: 19364 | E115: 2975036 | F115: 3007038063 | G115: INCIDENTE | H115: CAUCA | I115: JAMBALO | J115: BARRIO ZUMBICO JAMBALO | K115: REDEBAN | L115: FO-25-1781008 | M115: 45966.333 | N115: 45971.359 | O115: NO | P115: HARDWARE | Q115: LECTOR DE BARRAS | R115: CABLE LECTORA AVERIADO | S115: CB UNO A UNO | T115: CB UNO A UNO | U115: EJECUTADO | V115: 05/11/2025 SE ESCALA PARA VISITA. LLAMAR ANTES DE VISITAR, CONFIRMAR FALLA Y DATOS | 10/11/2025 SE INGRESA LECTOR CABLE MALO SE PROCEDE A CAMBIAR LECTOR SE HACEN PRUEBAS OK | W115: VISITA TECNICA | X115: GZ00Z970 | Y115: TIPO III | Z115: TERRESTRE | AA115: GIMBUEL LASSO LUIS GERMAN | AB115: 1 | AC115: 0 | AD115: 275729 | AE115: 196537 | AF115: 275729
A116: BUCARAMANGA | B116: SANTANDERES | C116: 0004-0008 | D116: 68162 | E116: 2975086 | F116: 3007012024 | G116: INCIDENTE | H116: SANTANDER | I116: CERRITO | J116: CERRITO - SANTANDER | K116: REDEBAN | L116: FO-25-1780984 | M116: 45966.333 | N116: 45972.499 | O116: NO | P116: HARDWARE | Q116: LECTOR DE TARJETAS | R116: MENSAJE RETIRE TARJETA | S116: CB UNO A UNO | T116: CB UNO A UNO | U116: EJECUTADO | V116: 05/11/2025 SE ESCALA PARA VISITA. LLAMAR ANTES DE VISITAR, CONFIRMAR FALLA Y DATOS | 07/11/2025 SE INFORMA QUE DEBIDO A DERRUMBES EN LA VÍA BUCARAMANGA,-MALAGA EL TRASPORTE INTERMUNICIPAL NO ES FRECUENTE POR REMISIÓN DE LOS MISMOS NO ES POSIBLE EL DESPLAZAMIENTO EL DIA DE HOY POR LO ANTERIOR SE LE INDICO A LA SEÑORA AZUCENA QUE SE REALIZARÁ EL DÍA LUNES 10 DE NOV DEPENDIENDO COMO CONTINÚE ESTA VÍA | 09/11/2025 SE LE INFORMO A LA SEÑORA AZUCENA QUE INICIAMOS DESPLAZAMIENTO EL DÍA LUNES PARA ESTE MUNICIPIO Y LA ESTAREMOS VISITANDO | 11/11/2025 SE REALIZA CAMBIO DE DATÁFONO POR ERROR EN LA LECTURA DE TARJETA CON CHIP, PRUEBAS EXITOSAS | W116: VISITA TECNICA | X116: JAAAG296 | Y116: TIPO IV | Z116: TERRESTRE | AA116: PEÑA DIAZ IVAN YESID | AB116: 1 | AC116: 0 | AD116: 479589 | AE116: 196537 | AF116: 479589
A117: SINCELEJO | B117: COSTA | C117: 0004-0001 | D117: 70001 | E117: 2975105 | F117: 3007069782 | G117: INCIDENTE | H117: SUCRE | I117: SINCELEJO | J117: PAGAFACIL GUACARI | K117: REDEBAN | L117: FO-25-1778958 | M117: 45966.333 | N117: 45966.655 | O117: NO | P117: HARDWARE | Q117: IMPRESION | R117: NO IMPRIME UNO O VARIOS CARACTERES | S117: ROBUSTO | T117: PAGAFACIL | U117: EJECUTADO | V117: 04/11/2025 SE ESCALA PARA VISITA. LLAMAR ANTES DE VISITAR, CONFIRMAR FALLA Y DATOS | 05/11/2025 SE VISITA SITIO SE VERIFICA INFORMACIÓN SE REALIZA PRIMEROS AUXILIOS, DATÁFONO NO IMPRIME COMPLETO, SE OBSERVA DAÑO EN LOS PIÑONES INTERNOS, SE PROCEDE A CAMBIO DE EQUIPO, SE REALIZA PRUEBA TRX EXITOSA. | W117: VISITA TECNICA | X117: NN000808 | Y117: TIPO I | Z117: TERRESTRE | AA117: SANTOS GUZMAN CHRISTIAN FELIPE | AB117: 1 | AC117: 0 | AD117: 65960 | AE117: 75096 | AF117: 65960
A118: BUCARAMANGA | B118: SANTANDERES | C118: 0004-0008 | D118: 68276 | E118: 2975112 | F118: 3007067507 | G118: INCIDENTE | H118: SANTANDER | I118: FLORIDABLANCA | J118: PTM FLORIDABLANCA TIENDA NUBIS | K118: REDEBAN | L118: FO-25-1781011 | M118: 45966.333 | N118: 45967.394 | O118: NO | P118: HARDWARE | Q118: IMPRESION | R118: NO AVANZA PAPEL | S118: AGREGADOR | T118: COMCARD - PTM | U118: EJECUTADO | V118: 05/11/2025 SE ESCALA PARA VISITA. LLAMAR ANTES DE VISITAR, CONFIRMAR FALLA Y DATOS | 05/11/2025 EN COMUNICACIÓN CON LA ADMINISTRADORA NUBIA DELGADO AL CELULAR 3118653581, INFORMA QUE LA FALLA DEL DATÁFONO NO IMPRIME Y ESTÁ MUY DETERIORADO QUE SE BLOQUEA MUY SEGUIDO, SE LE INFORMA QUE PARA CAMBIO DE EQUIPOS SOLO TENEMOS SOPORTE REDEBAN PARA CAMBIO DE EQUIPOS HASTA LAS 5:30 PM, CLIENTE INDICA QUE PODEMOS PASAR MAÑANA 6 DE NOVIEMBRE A LAS 8:00 AM SE REPROGRAMA ACTIVIDAD POR CAMBIO DE EQUIPO | 06/11/2025 SE REALIZA CAMBIO DE DATÁFONO, CABLE DESK 2600 Y FUENTE DESK 2600, POR FALLA DE IMPRESIÓN, NO AVANZA PAPEL, PRUEBAS Y LIMPIEZA DE EQUIPOS OK. CB MIXTO TERMINAL 9T00K335. | W118: VISITA TECNICA | X118: 9T00K193 9T00K335 | Y118: TIPO I | Z118: TERRESTRE | AA118: MARTINEZ FLOREZ DONIS ALBERTO | AB118: 1 | AC118: 0 | AD118: 65960 | AE118: 75096 | AF118: 65960
... A126: BOGOTA | B126: CUNDINAMARCA | C126: 0004-0004 | D126: 11001 | E126: 2976437 | F126: 3007028687 | G126: INCIDENTE | H126: CUNDINAMARCA | I126: BOGOTA | J126: REVAL PRADO VERANIEGO | K126: REDEBAN | L126: FO-25-1781373 | M126: 45966.388 | N126: 45967.578 | O126: NO | P126: HARDWARE | Q126: NO ENCIENDE | R126: DAÑO POS | S126: ROBUSTO | T126: REVAL | U126: EJECUTADO | V126: 05/11/2025 SE ESCALA PARA VISITA. LLAMAR ANTES DE VISITAR, CONFIRMAR FALLA Y DATOS | 06/11/2025 ME COMUNICO CON COMERCIO AL NÚMERO 3053253578 INDICA QUE HABRÉN HASTA LAS 10 DE LA MAÑANA ,POR FUERTES LLUVIAS NO HAY DESPLAZAMIENTO | 06/11/2025 SE LLEGA A COMERCIO SE VÁLIDA FALLA EN CONEXIONES ELÉCTRICAS DEL CLIENTE SE CAMBIA DATÁFONO NO PRENDE SE VÁLIDAN PRUEBAS EXITOSA | W126: VISITA TECNICA | X126: BBBB3491 | Y126: TIPO I | Z126: TERRESTRE | AA126: INFANTE SIERRA MANUEL FERNANDO | AB126: 1 | AC126: 0 | AD126: 65960 | AE126: 75096 | AF126: 65960
A127: YOPAL | B127: REMOTAS | C127: 0004-0007 | D127: 85010 | E127: 2976915 | F127: 3007036797 | G127: INCIDENTE | H127: CASANARE | I127: AGUAZUL | J127: DISTRICOL SUPER DROGAS CUSIANA | K127: REDEBAN | L127: FO-25-1781361 | M127: 45966.411 | N127: 45968.395 | P127: SOFTWARE | Q127: LECTOR DE BARRAS | R127: LECTOR DESCONFIGURADO | S127: AGREGADOR | T127: DISTRICOL | V127: 05/11/2025 SE ESCALA PARA VISITA. LLAMAR ANTES DE VISITAR, CONFIRMAR FALLA Y DATOS | 07/11/2025 EN COMUNICACIÓN CON LA SEÑORA MILENA ROBLES AL NUMERO 3148816180, SE COMPARTE MANUAL DE AUTOGESTION, SE ORIENTA PARA CONFIGURA LECTOR DE BARRAS. INDICA OPERATIVO EL SERVICIO. | W127: SOPORTE TELEFONICO | Y127: TIPO II | Z127: TERRESTRE | AA127: BERNAL ELAICA EDGAR ALEXIS | AB127: 0 | AC127: 0 | AD127: 41241 | AE127: 0 | AF127: 41241
A128: TUNJA | B128: SANTANDERES | C128: 0004-0008 | D128: 15236 | E128: 2977384 | F128: 3007040855 | G128: INCIDENTE | H128: BOYACA | I128: CHIVOR | J128: BARRIO CENTRO CHIVOR 2 | K128: REDEBAN | L128: FO-25-1781741 | M128: 45966.444 | N128: 45967.654 | O128: NO | P128: HARDWARE | Q128: NO ENCIENDE SE REINICIA | R128: FUENTE PODER AVERIADA | S128: CB UNO A UNO | T128: CB UNO A UNO | U128: EJECUTADO | V128: 05/11/2025 SE ESCALA PARA VISITA. LLAMAR ANTES DE VISITAR, CONFIRMAR FALLA Y DATOS | 06/11/2025 CAMBIO DE FUENTE DE PODER EXITOSA, CABLE DE CABLE ENTORCHADO EXITOSO. PRUEBAS OK | W128: VISITA TECNICA | X128: AA0OZ828 | Y128: TIPO III | Z128: TERRESTRE | AA128: HERRERA GARZON JEYSON STEVENT | AB128: 1 | AC128: 0 | AD128: 275729 | AE128: 196537 | AF128: 275729
A129: BUCARAMANGA | B129: SANTANDERES | C129: 0004-0008 | D129: 68001 | E129: 2977463 | F129: 3007078585 | G129: INCIDENTE | H129: SANTANDER | I129: BUCARAMANGA | J129: PTM BUCARAMANGA INTERRAPIDISIM | K129: REDEBAN | L129: FO-25-1781839 | M129: 45966.447 | N129: 45966.706 | O129: NO | P129: SOFTWARE | Q129: COMUNICACION | R129: VERIFIQUE PARAMETROS | S129: AGREGADOR | T129: COMCARD - PTM | U129: EJECUTADO | V129: 05/11/2025 SE ESCALA PARA VISITA. LLAMAR ANTES DE VISITAR, CONFIRMAR FALLA Y DATOS | 05/11/2025 SE ENCUENTRA DATAFONO DESCONFIGURADO, SE PROCEDE A FORMATEAR SE INSTALA S.O Y VERSION 9.90 SE HACEN PRUEBAS OK VISITA EXITOSA | W129: VISITA TECNICA | X129: F1MZZ614 F1MZZ787 | Y129: TIPO I | Z129: TERRESTRE | AA129: GELVEZ MOGOLLON JOSE ELISEO | AB129: 1 | AC129: 0 | AD129: 65960 | AE129: 75096 | AF129: 65960
...

Sheet OC_BANCOLOMBIA
A1: CIUDAD SEDE | B1: ZONA | C1: CENTRO DE COSTOS LINEACOM | D1: CODIGO DANE | E1: TA/CODIGO ACTIVIDAD | F1: CODIGO CB | G1: ACTIVIDAD | H1: DEPARTAMENTO | I1: CIUDAD | J1: NOMBRE DEL CB | K1: RED | L1: FO | M1: FECHA ASIGNACION A LINEA COMUNICACIONES | N1: FECHA CIERRE DEL TICKET (DD/MM/AAAA HH:MM) | O1: ACOMETIDA | P1: SOLICITUD | Q1: DESCRIPCION | R1: FORMATO | S1: CADENA | T1: ESTADO | U1: CAUSAL ESTADO | V1: OBSERVACION | W1: FORMA DE ATENCION | X1: TERMINAL(ES) | Y1: TIPIFICACION | Z1: TIPO DE TRAYECTO | AA1: NOMBRE DEL TECNICO | AB1: DIAS DE VISITA | AC1: DIA ADICIONAL | AD1: VALOR DIAS ACTIVIDAD FACTURABLES | AE1: VALOR DIAS ACOMPAÑAMIENTO FACTURABLES | AF1: VALOR TOTAL
A2: PASTO | B2: SUROCCIDENTE Y EJE CAFETERO | C2: 0004-0003 | D2: 52001 | E2: 2931894 | F2: 3007079834 | G2: OC BASE DATAFONO | H2: NARIÑO | I2: PASTO | J2: PTM PASTO BONNE VIE CAFE | K2: REDEBAN | L2: FO-25-1730687 | M2: 45954.598 | N2: 45980.693 | O2: NO | P2: BASEDATAFONO | Q2: BASE DATAFONO | R2: AGREGADOR | S2: COMCARD - PTM | T2: EJECUTADO / CANCELADO | U2: PETICIÓN USUARIO | V2: 24/10/2025 SE ESCALA PARA VISITA, POR FAVOR COMUNICARSE CON EL USUARIO PARA CONFIRMAR UBICACIÓN | 19/11/2025 SE VISITA CB PERO SE ENCUENTRA CERRADO. SE REALIZA COMUNICACIÓN TELEFÓNICA CON LA CLIENTE E INFORMA QUE NO ABREN LOS SÁBADOS YA QUE EL NEGOCIO ESTÁ EN UNA UNIVERSIDAD. PIDE SE VISITE DE LUNES A VIERNES | W2: VISITA TECNICA | X2: N/A | Y2: TIPO I | Z2: TERRESTRE | AA2: CASTILLO HERRERA ALEX RICARDO | AB2: 1 | AC2: 0 | AD2: 65960 | AE2: 75096 | AF2: 65960
A3: BOGOTA | B3: CUNDINAMARCA | C3: 0004-0004 | D3: 94001 | E3: 2948836 | F3: 3007053385 | G3: OC BASE DATAFONO | H3: GUAINIA | I3: INIRIDA | J3: BARRIO PUERTO INIRIDA INIRIDA | K3: REDEBAN | L3: FO-25-1747834 | M3: 45958.672 | N3: 45986.342 | O3: NO | P3: BASEDATAFONO | Q3: BASE DATAFONO | R3: CB UNO A UNO | S3: CB UNO A UNO | T3: EJECUTADO | U3: EJECUTADO EXITOSO | V3: 28/10/2025 EN COMUNICACIÓN CON LA SEÑORA LUZ JANETH SILVA ACEVEDO AL NÚMERO 3174948595 CONFIRMA SOLICITUD, DATOS CORRECTOS. SE ESCALA PARA VISITA | 05/11/2025 ACTIVIDAD NO SE VIAJA, SE LE CONSULTA A SEBASTIAN GONZÁLEZ DE RBM SOBRE LA VISITA A ESTE COMERCIO, SE LLEGA ACUERDO DE ENVIAR POR ENCOMIENDA, ENVIÓ SE HACE POR SERVIENTREGA GUÍA 2235596500. SE ESPERA CONFIRMACIÓN DEL RECIBO DEL CB , POSTERIOR A ELLOS SE ENVIARÁ RESPUESTA POR CORREO EMVIADO LUNES 4-11-2025 | 25/11/2025 SE ENVÍA BASE DATAFONO CON AUTORIZACION DE SEBASTIAN GONZALEZ DE REDEBA | W3: SOPORTE TELEFONICO | X3: NN | Y3: TIPO V | Z3: AEREO | AA3: CABARCAS BENJUMEA MILENA MARIA | AB3: 0 | AC3: 0 | AD3: 41241 | AE3: 0 | AF3: 41241
A4: SANTA MARTA | B4: COSTA | C4: 0004-0001 | D4: 47268 | E4: 2955544 | F4: 3007060847 | G4: OC BASE DATAFONO | H4: MAGDALENA | I4: EL RETEN | J4: BARRIO CENTRO EL RETEN 1 | K4: REDEBAN | L4: FO-25-1755267 | M4: 45959.702 | N4: 45966.617 | O4: NO | P4: BASEDATAFONO | Q4: BASE DATAFONO | R4: CB UNO A UNO | S4: CB UNO A UNO | T4: EJECUTADO | U4: EJECUTADO EXITOSO | V4: 30/10/2025 SE COMUNICA CON EL USUARIO VALIDAR UBICACION, SOLICITUD Y PROGRAMAR VISITA TECNICA | 05/11/2025 SE REALIZA ENTREGA E INSTALACIÓN DE BASE PARA DATÁFONO A SATISFACCIÓN DEL CLIENTE | W4: VISITA TECNICA | X4: 3007060847 | Y4: TIPO III | Z4: TERRESTRE | AA4: THOMAS CAMPO SIGIFREDO SEGUNDO | AB4: 1 | AC4: 0 | AD4: 275729 | AE4: 196537 | AF4: 275729
A5: APARTADO | B5: NOROCCIDENTE | C5: 0004-0005 | D5: 5837 | E5: 2960343 | F5: 3007073555 | G5: OC BASE DATAFONO | H5: ANTIOQUIA | I5: TURBO | J5: DISTRICOL CENTRAL DEL PVC Y AC | K5: REDEBAN | L5: FO-25-1761686 | M5: 45960.665 | N5: 45962.415 | O5: NO | P5: BASEDATAFONO | Q5: BASE DATAFONO | R5: AGREGADOR | S5: DISTRICOL | T5: EJECUTADO | U5: EJECUTADO EXITOSO | V5: 30/10/2025 POR FAVOR, COMUNICARSE CON USUARIO PARA CONFIRMAR UBICACION, SOLICITUD Y PROGRAMAR VISITA TECNICA | 31/10/2025 SE INSTALA BASE DE DATAFONO DESK 2600 | W5: VISITA TECNICA | X5: SW00W480 | Y5: TIPO II | Z5: TERRESTRE | AA5: SALDARRIAGA MIRANDA SANTIAGO | AB5: 1 | AC5: 0 | AD5: 144968 | AE5: 140396 | AF5: 144968
A6: BOGOTA | B6: CUNDINAMARCA | C6: 0004-0004 | D6: 25035 | E6: 2961801 | F6: 3007062804 | G6: OC BASE DATAFONO | H6: CUNDINAMARCA | I6: ANAPOIMA | J6: PTM ANAPOIMA DROGUERIA SOFSALU | K6: REDEBAN | L6: FO-25-1763298 | M6: 45961.351 | N6: 45969.374 | O6: NO | P6: BASEDATAFONO | Q6: BASE DATAFONO | R6: AGREGADOR | S6: COMCARD - PTM | T6: EJECUTADO | U6: EJECUTADO EXITOSO | V6: 31/10/2025 POR FAVOR, COMUNICARSE CON USUARIO PARA CONFIRMAR UBICACION, SOLICITUD Y PROGRAMAR VISITA TECNICA | 07/11/2025 SE REALIZA VISITA DE CAMPO ENCONTRADO QUE BASE ESTÁ ROTA, POR LO ANTERIOR SE CAMBIA BASE. | W6: VISITA TECNICA | X6: LA00Q015-AB110482 | Y6: TIPO II | Z6: TERRESTRE | AA6: LOZADA ROJAS CHRISTIAN ANDRES | AB6: 1 | AC6: 0 | AD6: 144968 | AE6: 140396 | AF6: 144968
A7: VILLAVICENCIO | B7: REMOTAS | C7: 0004-0007 | D7: 50001 | E7: 2962741 | F7: 3007065243 | G7: OC BASE DATAFONO | H7: META | I7: VILLAVICENCIO | J7: BARRIO VEREDA APIAY VILLAVICEN | K7: REDEBAN | L7: FO-25-1764556 | M7: 45961.429 | N7: 45962.424 | O7: NO | P7: BASEDATAFONO | Q7: BASE DATAFONO | R7: UNO A UNO | S7: CB UNO A UNO | T7: EJECUTADO | U7: EJECUTADO EXITOSO | V7: 31/10/2025 POR FAVOR, COMUNICARSE CON USUARIO PARA CONFIRMAR UBICACION, SOLICITUD Y PROGRAMAR VISITA TECNICA | 01/11/2025 SE VISITA CB Y SE REALIZA PEGADO DE BASE CON CINTA DOBLE FAZ. LA BASE SE ENCUENTRA DESPEGADA. | W7: VISITA TECNICA | X7: 2A008782 | Y7: TIPO I | Z7: TERRESTRE | AA7: GARZON RUIZ LUIS MIGUEL | AB7: 1 | AC7: 0 | AD7: 65960 | AE7: 75096 | AF7: 65960
A8: APARTADO | B8: NOROCCIDENTE | C8: 0004-0005 | D8: 5837 | E8: 2968749 | F8: 3007038814 | G8: OC BASE DATAFONO | H8: ANTIOQUIA | I8: TURBO | J8: PTM VARILOCHE ALL FASHION | K8: REDEBAN | L8: FO-25-1774262 | M8: 45965.335 | N8: 45971.663 | O8: NO | P8: BASEDATAFONO | Q8: BASE DATAFONO | R8: AGREGADOR | S8: COMCARD - PTM | T8: EJECUTADO | U8: EJECUTADO EXITOSO | V8: 04/11/2025 POR FAVOR, COMUNICARSE CON USUARIO PARA CONFIRMAR UBICACION, SOLICITUD Y PROGRAMAR VISITA TECNICA | 10/11/2025 SE INSTALA BASE DATAFONO DESK2600 | W8: VISITA TECNICA | X8: NN00L465 | Y8: TIPO II | Z8: TERRESTRE | AA8: SALDARRIAGA MIRANDA SANTIAGO | AB8: 1 | AC8: 0 | AD8: 144968 | AE8: 140396 | AF8: 144968
A9: IBAGUE | B9: REMOTAS | C9: 0004-0007 | D9: 73001 | E9: 2972033 | F9: 3007061087 | G9: OC BASE DATAFONO | H9: TOLIMA | I9: IBAGUE | J9: PTM IBAGUE SUPERTIENDA VILLAS | K9: REDEBAN | L9: FO-25-1776678 | M9: 45965.506 | N9: 45966.519 | O9: NO | P9: BASEDATAFONO | Q9: BASE DATAFONO | R9: AGREGADOR | S9: COMCARD - PTM | T9: EJECUTADO | U9: EJECUTADO EXITOSO | V9: 05/11/2025 SE REALIZA INSTALACIÓN DE BASE PARA DATÁFONO POR MOTIVO DE DAÑO. | W9: VISITA TECNICA | X9: NA00F139 | Y9: TIPO I | Z9: TERRESTRE | AA9: BARRAGAN TAFUR EDWIN ESTEBAN | AB9: 1 | AC9: 0 | AD9: 65960 | AE9: 75096 | AF9: 65960
A10: IBAGUE | B10: REMOTAS | C10: 0004-0007 | D10: 17380 | E10: 2975179 | F10: 3007047959 | G10: OC BASE DATAFONO | H10: CALDAS | I10: LA DORADA | J10: DISTRICOL TIENDA DILAN | K10: REDEBAN | L10: FO-25-1779603 | M10: 45966.333 | N10: 45968.351 | O10: NO | P10: BASEDATAFONO | Q10: BASE DATAFONO | R10: AGREGADOR | S10: DISTRICOL | T10: EJECUTADO | U10: EJECUTADO EXITOSO | V10: 05/11/2025 POR FAVOR, COMUNICARSE CON USUARIO PARA CONFIRMAR UBICACION, SOLICITUD Y PROGRAMAR VISITA TECNICA | 06/11/2025 SE VISITA CORRESPONSAL Y SE VERIFA QUE LA BASE ESTÁ EN BUEN ESTADO, NO HAY FISURA O ALGUNA PARTE DAÑADA DE LA BASE PARA DATÁFONO | W10: VISITA TECNICA | X10: 9C00I697 | Y10: TIPO III | Z10: TERRESTRE | AA10: VARGAS HERRERA JHON JAIRO | AB10: 1 | AC10: 0 | AD10: 275729 | AE10: 196537 | AF10: 275729
A11: CUCUTA | B11: SANTANDERES | C11: 0004-0008 | D11: 54518 | E11: 2978592 | F11: 3007077556 | G11: OC BASE DATAFONO | H11: NORTE DE SANTANDER | I11: PAMPLONA | J11: BARRIO LAS AMERICAS PAMPLONA | K11: REDEBAN | L11: FO-25-1783344 | M11: 45966.54 | N11: 45973.499 | O11: NO | P11: BASEDATAFONO | Q11: BASE DATAFONO | R11: CB UNO A UNO | S11: CB UNO A UNO | T11: EJECUTADO | U11: EJECUTADO EXITOSO | V11: 05/11/2025 POR FAVOR, COMUNICARSE CON USUARIO PARA CONFIRMAR UBICACION, SOLICITUD Y PROGRAMAR VISITA TECNICA | 12/11/2025 SE ENCONTRÓ BASE SUELTA, SE PROCEDE A REALIZAR LOS AJUSTES EN TORNILLOS SUELTO Y PEGADO DE LA BASE | W11: VISITA TECNICA | X11: 10HZZ124 | Y11: TIPO III | Z11: TERRESTRE | AA11: PEÑA DIAZ IVAN YESID | AB11: 1 | AC11: 0 | AD11: 275729 | AE11: 196537 | AF11: 275729
A12: MONTERIA | B12: COSTA | C12: 0004-0001 | D12: 5495 | E12: 2978813 | F12: 3007059996 | G12: OC BASE DATAFONO | H12: ANTIOQUIA | I12: NECHI | J12: PTM NECHI CELULARES Y ACCESOR | K12: REDEBAN | L12: FO-25-1783341 | M12: 45966.553 | N12: 45967.482 | O12: NO | P12: BASEDATAFONO | Q12: BASE DATAFONO | R12: AGREGADOR | S12: COMCARD - PTM | T12: EJECUTADO | U12: EJECUTADO EXITOSO | V12: 05/11/2025 POR FAVOR, COMUNICARSE CON USUARIO PARA CONFIRMAR UBICACION, SOLICITUD Y PROGRAMAR VISITA TECNICA | 06/11/2025 SE REALIZA VISITA TÉCNICA PARA ENTREGA E INSTALACIÓN DE BASE PARA DATAFONO. SE INSTALA NUEVA BASE POR MOTIVO QUE LA ANTERIOR SE PARTIÓ. | W12: VISITA TECNICA | X12: MA00B402 | Y12: TIPO III | Z12: TERRESTRE | AA12: CASSIANI PEREZ RAUL RAMIRO | AB12: 1 | AC12: 0 | AD12: 275729 | AE12: 196537 | AF12: 275729
A13: VILLAVICENCIO | B13: REMOTAS | C13: 0004-0007 | D13: 50711 | E13: 2978953 | F13: 3007064167 | G13: OC BASE DATAFONO | H13: META | I13: VISTAHERMOSA | J13: BARRIO CENTRO VISTAHERMOSA 4 | K13: REDEBAN | L13: FO-25-1783418 | M13: 45966.581 | N13: 45968.488 | O13: NO | P13: BASEDATAFONO | Q13: BASE DATAFONO | R13: CB UNO A UNO | S13: CB UNO A UNO | T13: EJECUTADO | U13: EJECUTADO EXITOSO | V13: 05/11/2025 POR FAVOR, COMUNICARSE CON USUARIO PARA CONFIRMAR UBICACION, SOLICITUD Y PROGRAMAR VISITA TECNICA | 07/11/2025 SE REALIZA VISTA AL CB POR SOLICITUD DE PEGADO DE BASE, SE PEGA LA BASE Y SE DEJA OK PERO EN EL PUEBLO ESTÁ FALLANDO EL INTENT Y NO SE PUEDE REALIZAR PRUEBA DE CONSULTA DE SALDO | W13: VISITA TECNICA | X13: LA01152 | Y13: TIPO III | Z13: TERRESTRE | AA13: MOLINA CASTRO JAVIER ALBERTO | AB13: 1 | AC13: 0 | AD13: 275729 | AE13: 196537 | AF13: 275729
... A268: BOGOTA | B268: CUNDINAMARCA | C268: 0004-0004 | D268: 11001 | E268: 14344156 | F268: 3007078636 | G268: OC PINPAD | H268: CUNDINAMARCA | I268: BOGOTA | J268: PTM BOGOTA PAPELERIA ALCALA | K268: REDEBAN | L268: FO-25-1804657 | FO-25-1782600 | M268: 45965.708 | N268: 45971.483 | O268: NO | P268: PINPAD | Q268: PINPAD | R268: AGREGADOR | S268: COMCARD - PTM | T268: EJECUTADO | U268: EJECUTADO EXITOSO | V268: 10/11/2025 INSTALACIÓN DE PIN PAD OK PRUEBAS OK | W268: VISITA TECNICA | X268: SA0ZZ052 | Y268: TIPO I | Z268: TERRESTRE | AA268: GOMEZ VEGA DAVID SNEYDER | AB268: 2 | AC268: 0 | AD268: 131920 | AE268: 75096 | AF268: 131920
A269: BOGOTA | B269: CUNDINAMARCA | C269: 0004-0004 | D269: 11001 | E269: 14417347 | F269: 3007082121 | G269: OC PINPAD | H269: CUNDINAMARCA | I269: BOGOTA | J269: PTM BOGOTA SERVIFLEXORG | K269: REDEBAN | L269: FO-25-1829806 | M269: 45975.51 | N269: 45986.438 | O269: NO | P269: PINPAD | Q269: PINPAD | T269: EJECUTADO | U269: EJECUTADO EXITOSO | V269: 14/11/2025 POR FAVOR, COMUNICARSE CON USUARIO PARA CONFIRMAR UBICACION, SOLICITUD Y PROGRAMAR VISITA TECNICA | 25/11/2025 SE VISITA COMERCIO, SE INSTALA PINPAD, SE REALIZAN PRUEBAS, PRUEBAS OK .... EL FO SE ENVIA EL DÍA DE HOY YA QUE EL DÍA 18 DEL PRESENTE MES LA APP NO PERMITIÓ ENVIARLO | W269: VISITA TECNICA | X269: DA000414 | Y269: TIPO I | Z269: TERRESTRE | AA269: ORTIZ YARA FRANKLYN ISRAEL | AB269: 1 | AC269: 0 | AD269: 65960 | AE269: 75096 | AF269: 65960
A270: MEDELLIN | B270: NOROCCIDENTE | C270: 0004-0005 | D270: 5209 | E270: 14419713 | F270: 3007027709 | G270: OC PINPAD | H270: ANTIOQUIA | I270: CONCORDIA | J270: DISTRICOL VARIEDADES ANGELA | K270: REDEBAN | L270: FO-25-1842492 | M270: 45979.675 | N270: 45987.667 | O270: NO | P270: PINPAD | Q270: PINPAD | R270: AGREGADOR | S270: DISTRICOL | T270: EJECUTADO | U270: EJECUTADO EXITOSO | V270: 18/11/2025 POR FAVOR, COMUNICARSE CON USUARIO PARA CONFIRMAR UBICACION, SOLICITUD Y PROGRAMAR VISITA TECNICA | 26/11/2025 SE REALIZÓ VISITA TÉCNICA AL CORRESPONSAL BANCOLOMBIA PARA INSTALAR DOS PINPAD. EL USUARIO CONFIRMÓ SU IDENTIFICACIÓN Y SE VERIFICÓ QUE EL SITIO CONTARA CON CABINA DE SEGURIDAD EN ÓPTIMAS CONDICIONES. TRAS LA INSTALACIÓN Y PRUEBAS DE FUNCIONAMIENTO, AMBOS DISPOSITIVOS QUEDARON OPERATIVOS, DEJANDO AL CORRESPONSAL HABILITADO PARA REALIZAR TRANSACCIONES DE MANERA SEGURA Y EFICIENTE. | W270: VISITA TECNICA | X270: 99WZZ887 | Y270: TIPO III | Z270: TERRESTRE | AA270: MARTINEZ TOVAR OSCAR DAVID | AB270: 1 | AC270: 0 | AD270: 275729 | AE270: 196537 | AF270: 275729
A271: BOGOTA | B271: CUNDINAMARCA | C271: 0004-0004 | D271: 11001 | E271: 14425578 | F271: 3007079715 | G271: OC PINPAD | H271: CUNDINAMARCA | I271: BOGOTA | J271: PTM BOGOTA YENBUTIK COSMETIC | K271: REDEBAN | L271: FO-25-1842497 | M271: 45979.675 | N271: 45980.736 | O271: NO | P271: PINPAD | Q271: PINPAD | R271: AGREGADOR | S271: COMCARD - PTM | T271: EJECUTADO | U271: EJECUTADO EXITOSO | V271: 18/11/2025 POR FAVOR, COMUNICARSE CON USUARIO PARA CONFIRMAR UBICACION, SOLICITUD Y PROGRAMAR VISITA TECNICA | 19/11/2025 SE REALIZA INSTALACIÓN DE PIN PAD. PRUEBA OK | W271: VISITA TECNICA | X271: F1WZZ976 | Y271: TIPO I | Z271: TERRESTRE | AA271: ORTIZ MARTINEZ STIVEN | AB271: 1 | AC271: 0 | AD271: 65960 | AE271: 75096 | AF271: 65960
A272: BUCARAMANGA | B272: SANTANDERES | C272: 0004-0008 | D272: 81001 | E272: 14212952 | F272: 3007033931 | G272: OC TRASLADO | H272: ARAUCA | I272: ARAUCA | J272: BARRIO CRISTO REY ARAUCA | K272: REDEBAN | L272: FO-25-1726242 | M272: 45953.516 | N272: 45968.419 | O272: NO | P272: TRASLADO | Q272: TRASLADO EXTERNO | R272: CB UNO A UNO | S272: CB UNO A UNO | T272: EJECUTADO | U272: EJECUTADO EXITOSO | V272: 23/10/2025 SE CONFIRMAN DATOS Y SOLICITUD CON EL USUARIO, SE ESCALA PARA VIISTA-POR FAVOR LLAMAR ANTES DE DESPLAZARSE | 30/10/2025 SE INFORMA AL CLIENTE QUE POR MOTIVOS DE ALGUNOS INCONVENIENTES DE ORDEN PÚBLICO SE ESTÁ A LA ESPERA DE LA COMPRA DE UN PASAJE DE VUELO PARA REALIZAR EL DESPLAZAMIENTO AL DEPARTAMENTO DE ARAUCA POR LO ANTERIOR SE DEBE AGENDAR PARA LA SIGUIENTE SEMANA | 31/10/2025 EN COMUNICACIÓN CON LA SEÑORA JUDITH AL MOVÍ L 3138884318, SE LE INFORMA QUE APARTIR DEL DÍA 4 DE NOVIEMBRE ESTARÍAMOS VISITANDO LA POR DISPONIBILIDAD DEL VUELO. | 04/11/2025 EN COMUNICACIÓN CON LA SEÑORA ADRIANA AL MOVIL 316 3379469, SE LE INFORMA QUE DEBIDO A QUE ES ZONA ROJA, SE ESTARÁ VISITANDO APARTIR DEL DÍA MIÉRCOLES 5 DE NOVIEMBRE DEL 2025 EN ADELANTE SEGÚN LA DISPONIBILIDAD DE TRANSPORTE HACIA EL MUNICIPIO. | 07/11/2025 SE REALIZA TRASLADO DE CB BANCOLOMBIA, CLIENTE YA CONTABA CON EQUIPOS EN NUEVA DIRECCIÓN, SE REALIZA BORRADO E INYECCION DE SO +VER 9.90, CONFIGURACION CB OK, CUBRE CLAVE OK, PRUEBAS OK. CLIENTE NO TIENE PUBLICIDAD SE LE INDICA DE LLAMAR A LA LINEA Y SOLICITARLA | W272: VISITA TECNICA | X272: BL01Y173 | Y272: TIPO V | Z272: AEREO | AA272: SANTOS GONZALEZ JOHAN FABIAN | AB272: 1 | AC272: 0 | AD272: 988463 | AE272: 196537 | AF272: 988463
A273: BUCARAMANGA | B273: SANTANDERES | C273: 0004-0008 | D273: 81065 | E273: 14214190 | F273: 3007042875 | G273: OC TRASLADO | H273: ARAUCA | I273: ARAUQUITA | J273: DISTRICOL SERVI LA VIRGEN | K273: REDEBAN | L273: FO-25-1710740 | M273: 45950.712 | N273: 45968.354 | O273: NO | P273: TRASLADO | Q273: TRASLADO EXTERNO | R273: AGREGADOR | S273: DISTRICOL | T273: EJECUTADO | U273: EJECUTADO EXITOSO | V273: 21/10/2025 EN COMUNICACIÓN CON LA SRA JENNY FERNANDA AYALA SALCEDO TAPIAS AL NÚMERO 3106790049 NOS CONFIRMA LA SOLICITUD, DATOS CORRECTOS. SE ESCALA PARA VISITA, POR FAVOR LLAMAR ANTES DE DESPLAZARSE | 27/10/2025 SE REALIZA LLAMADA TELEFÓNICA PARA ATENDER EL TRASLADO Y SE LE.INFORMA AL USUARIO QUE ESTAMOS A LA ESPERA DE LA COMPRA DE EL VUELO PARA EL TRASLADO AL DEPARTAMENTO DE ARAUCA, SE LE INFORMARÁ APENAS ESTEMOS EN DESPLAZAMIENTO YA QUE SE PRESENTARON ALGUNOS ATENTADOS DE ORDEN PÚBLICO | 31/10/2025 EN COMUNICACIÓN CON LA SEÑORA MÓNICA AL MOVIL 3112660579, SE CONFIRMA VISITA PARA DESPUÉS DEL DÍA 4 DE NOVIEMBRE POR DISPONIBILIDAD DEL VUELO HACIA EL DEPARTAMENTO DE ARAUCA. | 06/11/2025 TRASLADO DE CB, COMERCIO YA SE ENCUENTRA EN NUEVA DIRECCIÓN, NO CUENTA CON PUBLICIDAD, SE REALIZA BORRADO E INYECCION DE SO+VER 9.90, CONFIGURACION CB OK, PRUEBAS OK, NUEVA DIRECCIÓN OK. | W273: VISITA TECNICA | X273: 9A8ZZ951 | Y273: TIPO V | Z273: AEREO | AA273: SANTOS GONZALEZ JOHAN FABIAN | AB273: 1 | AC273: 0 | AD273: 988463 | AE273: 196537 | AF273: 988463
A274: MEDELLIN | B274: NOROCCIDENTE | C274: 0004-0005 | D274: 5686 | E274: 14249449 | F274: 3007031779 | G274: OC TRASLADO | H274: ANTIOQUIA | I274: SANTA ROSA DE OSOS | J274: BARRIO LA TERMINAL SANTA ROSA | K274: REDEBAN | L274: FO-25-1747841 | M274: 45958.636 | N274: 45967.594 | O274: NO | P274: TRASLADO | Q274: TRASLADO EXTERNO | R274: CB UNO A UNO | S274: CB UNO A UNO | T274: EJECUTADO | U274: EJECUTADO EXITOSO | V274: 28/10/2025 EN COMUNICACIÓN CON LA SEÑORA LUZ YANIT MARTINEZ ECHAVARRIA AL NÚMERO 3128385036 CONFIRMA SOLICITUD, DATOS CORRECTOS. SE ESCALA PARA VISITA | 06/11/2025 SE TRASLADAN EQUIPOS OK | W274: VISITA TECNICA | X274: BL08Z839 | Y274: TIPO II | Z274: TERRESTRE | AA274: QUINTERO SANCHEZ JUAN SEBASTIAN | AB274: 1 | AC274: 0 | AD274: 144968 | AE274: 140396 | AF274: 144968
A275: MONTERIA | B275: COSTA | C275: 0004-0001 | D275: 23466 | E275: 14249551 | F275: 3007064272 | G275: OC TRASLADO | H275: CORDOBA | I275: MONTELIBANO | J275: BARRIO CENTRO MONTELIBANO 5 | K275: REDEBAN | L275: FO-25-1755264 | M275: 45959.702 | N275: 45962.422 | O275: NO | P275: TRASLADO | Q275: TRASLADO EXTERNO | R275: CB UNO A UNO | S275: CB UNO A UNO | T275: EJECUTADO | U275: EJECUTADO EXITOSO | V275: 30/10/2025 SE COMUNICA CON EL USUARIO VALIDAR UBICACION, SOLICITUD Y PROGRAMAR VISITA TECNICA | 31/10/2025 SE REALIZA TRASLADO DE CB A DIRECCIÓN CLL 10 # 13-3 AP 02 DE FORMA EXITOSA. SE INICIALIZA TERMINAL Y SE CONFIRMA CAMBIO DE DIRECCIÓN. NO SÉ REALIZAN PRUEBAS, CB BLOQUEADO POR ENTIDAD. CB SIN PUBLICIDAD | W275: VISITA TECNICA | X275: AA000799 | Y275: TIPO IV | Z275: TERRESTRE | AA275: COGOLLO VERTEL EDER LUIS | AB275: 1 | AC275: 0 | AD275: 479589 | AE275: 196537 | AF275: 479589
A276: YOPAL | B276: REMOTAS | C276: 0004-0007 | D276: 85015 | E276: 14280867 | F276: 3007074822 | G276: OC TRASLADO | H276: CASANARE | I276: CHAMEZA | J276: BARRIO CENTRO CHAMEZA 3 | K276: REDEBAN | L276: FO-25-1755270 | M276: 45959.702 | N276: 45963.449 | O276: NO | P276: TRASLADO | Q276: TRASLADO EXTERNO | R276: UNO A UNO | S276: UNO A UNO | T276: EJECUTADO | U276: EJECUTADO EXITOSO | V276: 30/10/2025 SE COMUNICA CON EL USUARIO VALIDAR UBICACION, SOLICITUD Y PROGRAMAR VISITA TECNICA | 01/11/2025 SE VISITA COMERCIO, SE REALIZA TRASLADO OK. OPERATIVO EL SERVICIO | W276: VISITA TECNICA | X276: MNPZZ772-SVZZZ728 | Y276: TIPO IV | Z276: TERRESTRE | AA276: BERNAL ELAICA EDGAR ALEXIS | AB276: 1 | AC276: 0 | AD276: 479589 | AE276: 196537 | AF276: 479589
A277: APARTADO | B277: NOROCCIDENTE | C277: 0004-0005 | D277: 5665 | E277: 14281225 | F277: 3007021004 | G277: OC TRASLADO | H277: ANTIOQUIA | I277: SAN PEDRO DE URABA | J277: 16 DE MAYO SAN PEDRO DE URABA | K277: REDEBAN | L277: FO-25-1747842 | M277: 45958.636 | N277: 45968.592 | O277: NO | P277: TRASLADO | Q277: TRASLADO EXTERNO | R277: CB UNO A UNO | S277: CB UNO A UNO | T277: EJECUTADO | U277: EJECUTADO EXITOSO | V277: 28/10/2025 EN COMUNICACIÓN CON LA SEÑORA KARINA LUCIA CALDERIN MUÑOZ AL NÚMERO 3117190379 CONFIRMA SOLICITUD, DATOS CORRECTOS. SE ESCALA PARA VISITA, SOLICITA UNA PRONTA ATENCIÓN | 07/11/2025 SE REALIZA TRASLADO CB, PUNTO OPERATIVO | W277: VISITA TECNICA | X277: AAAZ739 | Y277: TIPO III | Z277: TERRESTRE | AA277: CASTRO HENAO DANIEL ESTEBAN | AB277: 1 | AC277: 0 | AD277: 275729 | AE277: 196537 | AF277: 275729
A278: NEIVA | B278: REMOTAS | C278: 0004-0007 | D278: 41001 | E278: 14283085 | F278: 3007050882 | G278: OC TRASLADO | H278: HUILA | I278: NEIVA | J278: BARRIO LOS ANDES NEIVA 1 | K278: REDEBAN | L278: FO-25-1755263 | M278: 45959.702 | N278: 45962.419 | O278: NO | P278: TRASLADO | Q278: TRASLADO EXTERNO | R278: UNO A UNO | S278: CB UNO A UNO | T278: EJECUTADO | U278: EJECUTADO EXITOSO | V278: 30/10/2025 POR FAVOR, COMUNICARSE CON USUARIO PARA CONFIRMAR UBICACION, SOLICITUD Y PROGRAMAR VISITA TECNICA | 31/10/2025 CLIENTE HABÍA REALIZADO EL TRASLADO DE PUBLICIDAD Y EQUIPOS , SE INSTALA AVISO EXTERIOR , SE FORMATEA ,CONFIGURA E INICIALIZA DATAFONO, SE CREA USUARIO Y CLAVE CON EL CLIENTE, SE REALIZA PRUEBAS DÓNDE SALE RECHAZO GENERAL, SE LLAMA A LA LINEA CB 018000953344 PARA SOLICITAR HABILITACIÓN TEMPORAL PARA REALIZAR PRUEBAS , SE ESPERA 10 MINUTOS ,SE REALIZA PRUEBAS DE NUEVO 15 MINUTOS DESPUÉS DE LA LLAMADA SALIENDO SALIENDO RECHAZO GENERAL , SE INFORMA AL CLIENTE QUE EL PUNTO LO HABILITARAN A MÁS TARDAR EL 6 DE NOVIEMBRE SEGÚN CONVERSACIÓN CON LA LINEA CB 018000953344. | W278: VISITA TECNICA | X278: II01Z059 | Y278: TIPO I | Z278: TERRESTRE | AA278: ANDRADE HERNANDEZ JUAN CARLOS | AB278: 1 | AC278: 0 | AD278: 65960 | AE278: 75096 | AF278: 65960
A279: PASTO | B279: SUROCCIDENTE Y EJE CAFETERO | C279: 0004-0003 | D279: 86568 | E279: 14285278 | F279: 3007064187 | G279: OC TRASLADO | H279: PUTUMAYO | I279: PUERTO ASIS | J279: BARRIO LAS AMERICAS PUERTO ASI | K279: REDEBAN | L279: FO-25-1755269 | M279: 45959.702 | N279: 45967.681 | O279: NO | P279: TRASLADO | Q279: TRASLADO EXTERNO | R279: CB UNO A UNO | S279: CB UNO A UNO | T279: EJECUTADO | U279: EJECUTADO EXITOSO | V279: 30/10/2025 SE COMUNICA CON EL USUARIO VALIDAR UBICACION, SOLICITUD Y PROGRAMAR VISITA TECNICA | 06/11/2025 DESPLAZAMIENTO HASTA EL CB | 06/11/2025 SE VISITA EL CORRESPONSAL EN UNA NUEVA DIRECCIÓN PARA HACER EFECTIVO EL TRASLADO, SE INICIALIZA LAS DOS TERMINALES OK, CAMBIO DE DIRECCIÓN OK, PERO EL CORRESPONSAL TIENE UN BLOQUEO POR PARTE DE LA ENTIDAD POR LO QUE TODAS LAS TRANSACCIONES DAN RECHAZO GENERAL, LA USUARIA SE DEBERÁ COMUNICAR A LA LÍNEA PARA VALIDAR QUE EL CORRESPONSAL HAYA SIDO DESBLOQUEADO | W279: VISITA TECNICA | X279: LA01Z172, NSZZZ722 | Y279: TIPO IV | Z279: TERRESTRE | AA279: GUERRERO RAMIREZ OSCAR DARIO | AB279: 1 | AC279: 0 | AD279: 479589 | AE279: 196537 | AF279: 479589
A280: NEIVA | B280: REMOTAS | C280: 0004-0007 | D280: 41615 | E280: 14299983 | F280: 3007078964 | G280: OC TRASLADO | H280: HUILA | I280: RIVERA | J280: BARRIO CENTRO BAJO RIVERA 1 | K280: REDEBAN | L280: FO-25-1782608 | M280: 45965.703 | N280: 45968.467 | O280: NO | P280: TRASLADO | Q280: TRASLADO EXTERNO | R280: UNO A UNO | S280: UNO A UNO | T280: EJECUTADO | U280: EJECUTADO EXITOSO | V280: 05/11/2025 SE LLAMA A EL NUMERO 3223254854 3207128409 NO HAY COMUNICACION POR FAVOR, COMUNICARSE CON USUARIO PARA CONFIRMAR UBICACION, SOLICITUD Y PROGRAMAR VISITA TECNICA | 07/11/2025 SE REALIZA TRASLADO EXITOSO, SE HACEN PRUEBAS EFECTIVAS | W280: VISITA TECNICA | X280: FASZZ034 | Y280: TIPO I | Z280: TERRESTRE | AA280: DIAZ VARGAS JONATHAN MIGUEL | AB280: 1 | AC280: 0 | AD280: 65960 | AE280: 75096 | AF280: 65960
A281: APARTADO | B281: NOROCCIDENTE | C281: 0004-0005 | D281: 5837 | E281: 14300642 | F281: 3007039220 | G281: OC TRASLADO | H281: ANTIOQUIA | I281: TURBO | J281: BARRIO TURBO TURBO | K281: REDEBAN | L281: FO-25-1782602 | M281: 45965.703 | N281: 45972.617 | O281: NO | P281: TRASLADO | Q281: TRASLADO EXTERNO | R281: CB UNO A UNO | S281: CB UNO A UNO | T281: EJECUTADO | U281: EJECUTADO EXITOSO | V281: 05/11/2025 SE LLAMA AL NUMERO 3215352243 SE VALIDA DATOS, UBICACION, SOLICITUD Y PROGRAMAR VISITA TECNICA | 11/11/2025 SE TRASLADA DATAFONO, LECTORA, SE INSTALA PUBLICIDAD AVISO EXTERIOR. SE INICIALIZA Y SE ACTUALIZA LOS DATOS CON LA DIRECCION ACTUAL. SE HACEN PRUEBAS DE CONSULTA DE SALDO Y IMPRIMIR VERSION CON LA INFOR ACTUAL Y LA NUEVA. DEJANDO TODO FUNCIONANDO CORRECTAMENTE. | W281: VISITA TECNICA | X281: GZ06Z009 | Y281: TIPO II | Z281: TERRESTRE | AA281: SALDARRIAGA MIRANDA SANTIAGO | AB281: 1 | AC281: 0 | AD281: 144968 | AE281: 140396 | AF281: 144968
... A306: BOGOTA | B306: CUNDINAMARCA | C306: 0004-0004 | D306: 11001 | E306: 14378101 | F306: 3007042330 | G306: OC TRASLADO | H306: CUNDINAMARCA | I306: BOGOTA | J306: BARRIO KENEDY BOGOTA | K306: REDEBAN | L306: FO-25-1833418 | FO-25-1829726 | M306: 45975.516 | N306: 45979.596 | O306: NO | P306: TRASLADO | Q306: TRASLADO EXTERNO | R306: CB UNO A UNO | S306: CB UNO A UNO | T306: EJECUTADO | EJECUTADO / CANCELADO | U306: EJECUTADO EXITOSO | V306: 18/11/2025 DURANTE LA VISITA TECNICA SE REALIZA TRASLADO DE CORRESPONSAL EN LUGARES INDICADOS POR CORRESPONSAL SIN NOVEDAD EN INSTALACIÓN PRUEBAS OK SALDO OK A CONFORMIDAD DE CORRESPONSAL | W306: VISITA TECNICA | X306: AA2ZZ072 | Y306: TIPO I | Z306: TERRESTRE | AA306: GALEANO SORIANO JUAN DAVID | AB306: 1 | AC306: 0 | AD306: 65960 | AE306: 75096 | AF306: 65960

Sheet PAPELERIA
A1: CIUDAD SEDE | B1: ZONA | C1: CENTRO DE COSTOS LINEACOM | D1: CODIGO DANE | E1: TA/CODIGO ACTIVIDAD | F1: CODIGO CB | G1: ACTIVIDAD | H1: DEPARTAMENTO | I1: CIUDAD | J1: NOMBRE DEL CB | K1: RED | L1: FO | M1: FECHA ASIGNACION A LINEA COMUNICACIONES | N1: FECHA CIERRE DEL TICKET (DD/MM/AAAA HH:MM) | O1: ACOMETIDA | P1: SOLICITUD | Q1: DESCRIPCION | R1: FORMATO | S1: CADENA | T1: ESTADO | U1: CAUSAL ESTADO | V1: OBSERVACION | W1: FORMA DE ATENCION | X1: TERMINAL(ES) | Y1: TIPIFICACION | Z1: TIPO DE TRAYECTO | AA1: NOMBRE DEL TECNICO | AB1: DIAS DE VISITA | AC1: VALOR DIAS ACTIVIDAD FACTURABLES | AD1: VALOR DIAS ACOMPAÑAMIENTO FACTURABLES | AE1: VALOR TOTAL
A2: VALLEDUPAR | B2: COSTA | C2: 0004-0001 | D2: 20175 | E2: 2763740 | F2: 3007075868 | G2: OC ENVIO ROLLOS | H2: CESAR | I2: CHIMICHAGUA | J2: DISTRICOL COMPANY MARTINEZ | K2: REDEBAN | L2: FO-25-1553954 | M2: 45919.333 | N2: 45965.463 | P2: ROLLOS | Q2: ROLLOS | R2: AGREGADOR | S2: DISTRICOL | T2: EJECUTADO | U2: EJECUTADO EXITOSO | V2: 19/09/2025 SE REALIZA ENVIO DE ROLLOS CON GUIA | 25/09/2025 SE INTENTA COMUNICACIÓN AL NÚMERO 3117639852 PARA VALIDAR SI RECIBIÓ LOS ROLLOS PERO NO HAY RESPUESTA | 26/09/2025 SE COMUNICA CON EL USUARIO DONDE INFORMA QUE AUN NO RECIBE LOS ROLLOS | 07/10/2025 SE LLAMA AL USUARIO Y CONFIRMA QUE AUN NO LE HAN LLEGADO LOS ROLLOS | 22/10/2025 SE VALIDA CON USUARIO, INFORMA QUE AUN NO RECIBE . SE ESCALA CON SERVIENTREGA | 23/10/2025 SERVIENTREGA: 2205447187: CUENTA CON EL RADICADO # 87148744 AÚN EN PROCESO. TE PEDIMOS DISCULPAS POR LA DEMORA, DEBIDO A LA FALTA DE RESPUESTA REASIGNAMOS Y ESCALAMOS EL CASO NUEVAMENTE CON LA REGIONAL ENCARGADA PARA QUE NOS PUEDAN COLABORAR CON MAYOR AGILIDAD. SEGUIMOS PENDIENTES DE LA RESPUESTA FINAL DE LOGÍSTICA MIENTRAS SE REALIZA SU DEBIDA GESTIÓN. | 04/11/2025 SE REALIZA ENVIO DE 10 ROLLOS, CON LA GUIA 2205447187 SERVIENTREGA. SE CONFIRMA ENTREGA EXITOSA POR PARTE DE LA TRANSPORTADORA | W2: ENVIO | Y2: TIPO IV | Z2: TERRESTRE | AB2: 0 | AC2: 35780 | AD2: 75096 | AE2: 35780
A3: CALI | B3: SUROCCIDENTE Y EJE CAFETERO | C3: 0004-0003 | D3: 19809 | E3: 2840483 | F3: 3007042146 | G3: OC ENVIO ROLLOS | H3: CAUCA | I3: TIMBIQUI | J3: DISTRICOL VARIEDADES MODATRONI | K3: REDEBAN | L3: FO-25-1642934 | M3: 45936.333 | N3: 45966.494 | P3: ROLLOS | Q3: ROLLOS | R3: AGREGADOR | S3: DISTRICOL | T3: EJECUTADO | U3: EJECUTADO EXITOSO | V3: 07/10/2025 SE CONFIRMA DATOS CON USUARIO. SE REALIZA ENVIO DE ROLLOS CON GUIA | 05/11/2025 SE REALIZA ENVIO DE 30 ROLLOS, CON LA GUIA 2185553847 SERVIENTREGA. SE CONFIRMA ENTREGA EXITOSA POR PARTE DE LA TRANSPORTADORA | W3: ENVIO | Y3: TIPO V | Z3: AEREO | AB3: 0 | AC3: 35780 | AD3: 75096 | AE3: 35780
A4: PASTO | B4: SUROCCIDENTE Y EJE CAFETERO | C4: 0004-0003 | D4: 86569 | E4: 2845946 | F4: 3007044997 | G4: OC ENVIO ROLLOS | H4: PUTUMAYO | I4: PUERTO CAICEDO | J4: DISTRICOL MERCACENTRO J&M | K4: REDEBAN | L4: FO-25-1636917 | M4: 45936.612 | N4: 45965.465 | P4: ROLLOS | Q4: ROLLOS | R4: AGREGADOR | S4: DISTRICOL | T4: EJECUTADO | U4: EJECUTADO EXITOSO | V4: 06/10/2025 DATOS CONFIRMADOS. SE REALIZA ENVIO DE ROLLOS CON GUIA | 14/10/2025 SE LLAMA AL USUARIO EL CUAL CONFIRMA QUE AUN NO LE HA LLEGADO EL PEDIDO | 04/11/2025 SE REALIZA ENVIO DE 100 ROLLOS, CON LA GUIA 2185553834 SERVIENTREGA. SE CONFIRMA ENTREGA EXITOSA POR PARTE DE LA TRANSPORTADORA | W4: ENVIO | Y4: TIPO IV | Z4: TERRESTRE | AB4: 0 | AC4: 35780 | AD4: 75096 | AE4: 35780
A5: PASTO | B5: SUROCCIDENTE Y EJE CAFETERO | C5: 0004-0003 | D5: 52693 | E5: 2868741 | F5: 3007050658 | G5: OC ENVIO ROLLOS | H5: NARIÑO | I5: SAN PABLO | J5: PTM SAN PABLO SUPERMERCADO DEL | K5: REDEBAN | L5: FO-25-1666857 | M5: 45940.465 | N5: 45966.406 | P5: ROLLOS | Q5: ROLLOS | R5: AGREGADOR | S5: COMCARD - PTM | T5: EJECUTADO | U5: EJECUTADO EXITOSO | V5: 10/10/2025 SE CONFIRMAN DATOS, SE REALIZA ENVIO DE ROLLOS CON GUIA | 04/11/2025 EN COMUNICACION USUARIO INFORMA QUE AUN NO RECIBE LOS ROLLOS | 06/11/2025 SE REALIZA ENVIO DE 50 ROLLOS, CON LA GUIA 2185553864 SERVIENTREGA. SE CONFIRMA ENTREGA EXITOSA POR PARTE DE LA TRANSPORTADORA | W5: ENVIO | Y5: TIPO IV | Z5: TERRESTRE | AB5: 0 | AC5: 35780 | AD5: 75096 | AE5: 35780
