Workbook
Name A: #REF!
Name Actividad: [1]Formulas!$H$2:$H$5000
Name arearesponsable: '[2]Listas desplegables'!$BB$2:$BB$100
Name Clientes: [1]Clientes!$A$2:$A$100
Name COORDINADOR: [3]Hoja2!$D$2:$D$30
Name Coordinadores: [1]Coordinadores!$A$2:$A$1000
Name DOCUMENTADOR: [3]Hoja2!$A$2:$A$30
Name ES: [3]Hoja2!$K$2:$K$30
Name ESS: [3]Hoja2!$K$2:$K$30
Name Estado: [1]Formulas!$K$2:$K$5000
Name ESTADOACTIVIDAD: [3]Hoja2!$M$2:$M$30
Name ESTADOS: '[4]Listas desplegables'!$B$1:$D$1
Name ESTADOSCIERRES: '[5]lista desplegable'!$CX$1:$DA$1
Name Facturacion: '[6]Listas desplegables'!$AO$1:$AR$1
Name FACTURACIÓN: '[4]Listas desplegables'!$Y$1:$AB$1
Name falla: #REF!
Name Fallas: '[7]Listas desplegables'!$F$2:$L$2
Name Grupo_Falla: '[8]Listas Desplegables'!$CH$2:$CH$5
Name inconservmanager: '[9]Listas desplegables'!$BC$2:$BC$100
Name INCUMPLIMIENTO: '[2]Listas desplegables'!$AK$1:$AN$1
Name LISTA: [10]Dptos!$A$1139:$A$1171
Name LISTA2: #REF!
Name LOLO: [11]Coordinadores!$A$2:$A$1000
Name solicitudes: '[12]Listas desplegables'!$AF$1:$AQ$1
Name Tecnicos: [1]Tecnicos!$A$2:$A$1000
Name Version: [1]Formulas!$I$2:$I$3

Sheet BASE LIQUIDACION
A1: TARIFAS 2025 | E1: Incremento 2025
A2: Tipificación | B2: Descripción | C2: Dia actividad Exitosa | D2: Dia actividad Fallida | E2: 0.052
A3: Tipo I | B3: Metropolitano | C3: =62700.07*(1+$E$2) -> 65960.474 | D3: =42357.4*(1+$E$2) -> 44559.985
A4: Tipo II | B4: Hasta 3 horas | C4: =155716.31*(1+$E$2) -> 163813.56 | D4: =127766.53*(1+$E$2) -> 134410.39
A5: Tipo III | B5: De 3 a 5 horas | C5: =262099.22*(1+$E$2) -> 275728.38 | D5: =211886.19*(1+$E$2) -> 222904.27
A6: Tipo IV | B6: Más de 5 horas | C6: =455883.78*(1+$E$2) -> 479589.74 | D6: =441833.68*(1+$E$2) -> 464809.03
A7: Destino aereo | B7: No incluye valor del Tiquete | C7: =455883.78*(1+$E$2) -> 479589.74 | D7: =441833.68*(1+$E$2) -> 464809.03
A8: *Donde se requiera transporte aéreo o fluvial se factura adicional a tarifa TIPO IV el valor del tiquete + el 12% de admon.
A10: Gestión Telefónica | B10: =36031.04*(1+$E$2) -> 37904.654
A11: Mts Acometida electrica | B11: =30182.1*(1+$E$2) -> 31751.569
A12: Mts Acometida datos | B12: =15432.22*(1+$E$2) -> 16234.695
A13: switche | B13: =244669.03*(1+$E$2) -> 257391.82
A14: Router | B14: =291399.51*(1+$E$2) -> 306552.28
A15: Envio operador Logistico | B15: =53547.34*(1+$E$2) -> 56331.802

Sheet RESUMEN LIQUIDACIONES
A1: LÍNEA COMUNICACIONES S.A.S | F1: FACTURACIÓN CORRESPONSALES BANCARIOS TIQUIETES AEREOS
A2: FACTURACIÓN PROYECTO CB BANCOLOMBIA | F2: =A3 -> 45962
A3: 45962
F4: CONCEPTOS | G4: TRAYECTOS | H4: TOTAL | I4: % Administración | J4: TOTAL
A5: CONCEPTOS | B5: CANTIDAD | C5: VALOR UNITARIO | D5: VALOR TOTAL | F5: INCIDENTE 3003898 | G5: BUCARAMANGA - ARAUCA - BUCARAMANGA | H5: =440000+285800 -> 725800 | I5: =H5*0.12 -> 87096 | J5: =H5+I5 -> 812896
A6: Adecuaciones CB | B6: =COUNTA(ADECUCACIONES!A:A)-1 -> 7 | C6: 0 | D6: =SUM(ADECUCACIONES!AE2:AE10000) -> 2274665 | I6: =H6*0.12 -> 0 | J6: =H6+I6 -> 0
A7: Incidentes | B7: =COUNTA(INCIDENTES!A:A)-1 -> 88 | C7: 0 | D7: =SUM(INCIDENTES!AH2:AH9913) -> 9077759 | I7: =H7*0.12 -> 0 | J7: =H7+I7 -> 0
A8: Ordenes de Cambio | B8: =COUNTA(OC!A:A)-1 -> 4 | C8: 0 | D8: =SUM(OC!AG2:AG10000) -> 263840 | I8: =H8*0.12 -> 0 | J8: =H8+I8 -> 0
A9: Tiquetes | B9: 1 | C9: 0 | D9: =J12 -> 812896 | I9: =H9*0.12 -> 0 | J9: =H9+I9 -> 0
A10: SUBTOTAL | D10: =SUM(D6:D9) -> 12429160 | I10: =H10*0.12 -> 0 | J10: =H10+I10 -> 0
A11: Iva | D11: =D10*0.19 -> 2361540.4 | I11: =H11*0.12 -> 0 | J11: =H11+I11 -> 0
A12: TOTAL | D12: =D10+D11 -> 14790700 | F12: TOTAL | H12: =SUM(H5:H11) -> 725800 | I12: =SUM(I5:I11) -> 87096 | J12: =SUM(J5:J11) -> 812896

Sheet ADECUCACIONES
A1: CIUDAD SEDE | B1: ZONA | C1: CENTRO DE COSTOS LINEACOM | D1: CODIGO DANE | E1: TA/CODIGO ACTIVIDAD | F1: CODIGO CB | G1: ACTIVIDAD | H1: TIPO DE APERTURA | I1: DEPARTAMENTO | J1: CIUDAD | K1: NOMBRE DEL CB | L1: RED | M1: FO | N1: FECHA LISTA | O1: FECHA ULTIMA ACTUALIZACION | P1: FORMATO | Q1: CADENA | R1: ESTADO | S1: OBSERVACIONES CLIENTE | T1: FORMA DE ATENCION | U1: TERMINAL(ES) | V1: TIPIFICACION | W1: TIPO DE TRAYECTO | X1: NOMBRE DEL TECNICO | Y1: ACOMETIDA DATOS | Z1: ACOMETIDA ELECTRICA | AA1: SWITCH | AB1: ROUTER | AC1: VALOR DIAS ACTIVIDAD FACTURABLES | AD1: DIAS ACTIVIDAD FACTURABLES | AE1: VALOR TOTAL INSTALACION DE PUBLICIDAD
A2: MEDELLIN | B2: NOROCCIDENTE | C2: 0004-0005 | D2: 5736 | E2: TA-25-1247964 | F2: 3007082061 | G2: APERTURA | H2: CB CRECIMIENTO ALIANZA - NUEVO | I2: ANTIOQUIA | J2: SEGOVIA | K2: DISTRICOL PLANETARIO 2000 | L2: REDEBAN | M2: FO-25-1765343 | FO-25-1751719 | N2: 45959.882 | O2: 45965.644 | P2: AGREGADOR | Q2: DISTRICOL | R2: CANCELADO | EJECUTADO/CANCELADO | S2: 04/11/2025 ENTIDAD SOLICITA CANCELAR LA INSTALACIÓN | T2: SOPORTE TELEFONICO | V2: TIPO IV | W2: TERRESTRE | X2: ECHEVERRI ECHEVERRI EVELIN DANIELA | Y2: 0 | Z2: 0 | AA2: 0 | AB2: 0 | AC2: 1 | AD2: 464809 | AE2: 464809
A3: APARTADO | B3: NOROCCIDENTE | C3: 0004-0005 | D3: 27006 | E3: TA-25-1247980 | F3: 3007082025 | G3: APERTURA | H3: CB CRECIMIENTO ALIANZA - NUEVO | I3: CHOCO | J3: ACANDI | K3: DISTRICOL CONFITERIA VENTANITA | L3: REDEBAN | M3: FO-25-1751759 | N3: 45959.724 | O3: 45966.822 | P3: AGREGADOR | Q3: DISTRICOL | R3: EJECUTADO/CANCELADO | S3: 29/10/2025 29-10 PROGRAMACIÓN REALIZADA POR LA ALIANZA| INSTALACIÓN PROGRAMADA PARA EL 2025-11-05 | 06/11/2025 SE LLEGA A SITIO, SE ENCUENTRA QUE EL COMERCIO ES UN RESTAURANTE PANADERÍA, NO SE VE COMO CONFITERÍA. ADICIONAL EN TODO EL FRENTE TIENE UN CORRESPONSAL BANCOLOMBIA Y AL LADO IZQUIERDO A 40 METROS TIENE OTRO CORRESPONSAL. SE ESCALA TEMA A COORDINADOR EL CUAL INDICA NO INSTALAR POR PROXIMIDAD ENTRE CORRESPONSALES. | T3: VISITA TECNICA | V3: TIPO V | W3: AEREO | X3: CASTRO HENAO DANIEL ESTEBAN | Y3: 0 | Z3: 0 | AA3: 0 | AB3: 0 | AC3: 1 | AD3: 988463 | AE3: 988463
A4: PASTO | B4: SUROCCIDENTE Y EJE CAFETERO | C4: 0004-0003 | D4: 86865 | E4: TA-25-1248008 | F4: 3007082070 | G4: APERTURA | H4: CB CRECIMIENTO ALIANZA - NUEVO | I4: PUTUMAYO | J4: VALLE DEL GUAMUEZ | K4: DISTRICOL ESTILO REAL | L4: REDEBAN | M4: FO-25-1751843 | N4: 45959.876 | O4: 45966.833 | P4: AGREGADOR | Q4: DISTRICOL | R4: EJECUTADO/CANCELADO | S4: 29/10/2025 29-10 PROGRAMACIÓN REALIZADA POR LA ALIANZA| INSTALACIÓN PROGRAMADA PARA EL 2025-10-31 | 31/10/2025 NO ES POSIBLE VIAJAR EL DIA DE HOY HACIA EL DEPARTAMENTO DEL PUTUMAYO POR PROBLEMAS DE TRANSPORTE SE REALIZARA DESPLAZAMIENTO AL DIA MARTES | 06/11/2025 SE VISITA EL COMERCIO PARA DAR APERTURA AL CB PERO NO ES POSIBLE YA QUE EL CLIENTE AUN NO TIENE LA ADECUACIÓN DE DATOS Y ENERGIA LISTOS DONDE VA A QUEDAR UBICADO EL DATAFONO, INFORMA QUE CUANDO TENGA DICHA ADECUACION INFORMARA PARA HACER LA INSTALACIÓN | T4: VISITA TECNICA | V4: TIPO IV | W4: TERRESTRE | X4: GUERRERO RAMIREZ OSCAR DARIO | Y4: 0 | Z4: 0 | AA4: 0 | AB4: 0 | AC4: 1 | AD4: 464809 | AE4: 464809
A5: CALI | B5: SUROCCIDENTE Y EJE CAFETERO | C5: 0004-0003 | D5: 76520 | E5: TA-25-1315926 | F5: 3007082246 | G5: APERTURA | H5: CB CRECIMIENTO ALIANZA - NUEVO | I5: VALLE DEL CAUCA | J5: PALMIRA | K5: PTM PALMIRA TIENDA Y VARIEDADE | L5: REDEBAN | M5: FO-25-1852593 | N5: 45982.333 | O5: 45985.506 | R5: EJECUTADO/CANCELADO | S5: 20/11/2025 20-11 PROGRAMACION REALIZADA POR LA ALIANZA| INSTALACIÓN PROGRAMADA PARA EL 2025-11-24 | 24/11/2025 SE PROCEDE LLAMA AL CONTACTO PARA CONFIRMAR VISITA, DONDE SE EVIDENCIA QUÉ DIRECCIÓN EN ORDEN DE INSTALACIÓN NO COINCIDE CON LA DIRECCIÓN FÍSICA DEL CLIENTE. SE PROCEDE A VISITAR PARA CONFIRMAR. DIRECCIÓN CORRECTA DEL COMERCIO ES CARRERA 27 B # 3 0-6. SE EVIDENCIÓ QUE CÁMARA Y COMERCIO ESTÁ ERRADA Y SE LE INDICA AL CLIENTE QUE DEBE CORREGIR Y ENVIAR DATOS NUEVAMENTE. | T5: VISITA TECNICA | V5: TIPO I | W5: TERRESTRE | X5: BOLAÑOS TABORDA JORGE ENRIQUE | Y5: 0 | Z5: 0 | AA5: 0 | AB5: 0 | AC5: 1 | AD5: 44560 | AE5: 44560
A6: MEDELLIN | B6: NOROCCIDENTE | C6: 0004-0005 | D6: 5001 | E6: TA-25-1315934 | F6: 3007079707 | G6: APERTURA | H6: DATAFONO ADICIONAL - ALIANZA | I6: ANTIOQUIA | J6: MEDELLIN | K6: PTM MEDELLIN PAPELERIA Y VARIE | L6: REDEBAN | M6: FO-25-1852618 | N6: 45982.333 | O6: 45983.515 | P6: AGREGADOR | Q6: COMCARD - PTM | R6: EJECUTADO/CANCELADO | S6: 20/11/2025 20-11 PROGRAMACION REALIZADA POR LA ALIANZA| INSTALACIÓN PROGRAMADA PARA EL 2025-11-21 | 22/11/2025 NO SE HACE LA INSTALACIÓN DEL DATAFONO ADICIONAL PORQUE EN EL PUNTO HAY UN EFECTY, ESCALO LO SUCEDIDO Y NO PERMITEN LA VISITA | T6: VISITA TECNICA | V6: TIPO I | W6: TERRESTRE | X6: RUA ALVAREZ RICHARD ANDRES | Y6: 0 | Z6: 0 | AA6: 0 | AB6: 0 | AC6: 1 | AD6: 44560 | AE6: 44560
A7: BOGOTA | B7: CUNDINAMARCA | C7: 0004-0004 | D7: 25599 | E7: TA-25-1319223 | F7: 3007082265 | G7: APERTURA | H7: CB CRECIMIENTO ALIANZA - NUEVO | I7: CUNDINAMARCA | J7: APULO | K7: DISTRICOL AUTOSERVICIO APULO | L7: REDEBAN | M7: FO-25-1859233 | N7: 45985.333 | O7: 45986.422 | R7: EJECUTADO/CANCELADO | S7: 21/11/2025 21-11 PROGRAMACION REALIZADA POR LA ALIANZA| INSTALACIÓN PROGRAMADA PARA EL 2025-11-25 | 25/11/2025 SE VISITA COMERCIO, SE VALIDA CB CERCANO Y NO SE PUEDE REALIZAR LA INSTALACIÓN. SE ESCALA CON EL COORDINADOR INDICANDO QUE SE CIERRA | T7: VISITA TECNICA | V7: TIPO III | W7: TERRESTRE | X7: ARIAS QUILINDO JULIAN | Y7: 0 | Z7: 0 | AA7: 0 | AB7: 0 | AC7: 1 | AD7: 222904 | AE7: 222904
A8: BOGOTA | B8: CUNDINAMARCA | C8: 0004-0004 | D8: 11001 | E8: TA-25-1330513 | F8: 3007082234 | G8: APERTURA | H8: CB CRECIMIENTO ALIANZA - OTRAS LISTAS | I8: CUNDINAMARCA | J8: BOGOTA | K8: PTM BOGOTA DROGUERIA SPECIALME | L8: REDEBAN | M8: FO-25-1904464 | FO-25-1884063 | N8: 45988.333 | O8: 45989.711 | R8: EJECUTADO | EJECUTADO/CANCELADO | S8: 28/11/2025 SE REALIZA INSTALACIÓN DE CB, SE INSTALA DATÁFONO, LECTORA, BASE, 40 ROLLOS, CABLE DE RED Y SE REALIZA CAPACITACIÓN DEL CB AL SR SERGIO | T8: VISITA TECNICA | U8: AE006359 | V8: TIPO I | W8: TERRESTRE | X8: ALARCON AREVALO JOHAN STIVEN | Y8: 0 | Z8: 0 | AA8: 0 | AB8: 0 | AC8: 1 | AD8: 44560 | AE8: 44560

Sheet INCIDENTES
A1: CIUDAD SEDE | B1: ZONA | C1: CENTRO DE COSTOS LINEACOM | D1: CODIGO DANE | E1: TA/CODIGO ACTIVIDAD | F1: CODIGO CB | G1: ACTIVIDAD | H1: DEPARTAMENTO | I1: CIUDAD | J1: NOMBRE DEL CB | K1: RED | L1: FO | M1: FECHA ASIGNACION A LINEA COMUNICACIONES | N1: FECHA CIERRE DEL TICKET (DD/MM/AAAA HH:MM) | O1: ACOMETIDA | P1: GRUPO_FALLA | Q1: CATEGORIA | R1: FALLA | S1: FORMATO | T1: CADENA | U1: ESTADO | V1: OBSERVACION | W1: FORMA DE ATENCION | X1: TERMINAL(ES) | Y1: TIPIFICACION | Z1: TIPO DE TRAYECTO | AA1: NOMBRE DEL TECNICO | AB1: DIAS DE VISITA | AC1: ACOMETIDA DATOS | AD1: ACOMETIDA ELÉCTRICA | AE1: SWITCH | AF1: ROUTER | AG1: VALOR DIAS ACTIVIDAD FACTURABLES | AH1: VALOR DIAS ACOMPAÑAMIENTO FACTURABLES
A2: PASTO | B2: SUROCCIDENTE Y EJE CAFETERO | C2: 0004-0003 | D2: 86568 | E2: 2958278 | F2: 3007065915 | G2: INCIDENTE | H2: PUTUMAYO | I2: PUERTO ASIS | J2: BARRIO LAS AMERICAS PUERTO ASI | K2: REDEBAN | L2: FO-25-1757311 | M2: 45960.462 | N2: 45967.49 | O2: NO | P2: USUARIO | Q2: CIERRE | R2: COMERCIO NO REALIZA CIERRE | S2: CB UNO A UNO | T2: CB UNO A UNO | U2: EJECUTADO | V2: 30/10/2025 SE ESCALA PARA VISITA. LLAMAR ANTES DE VISITAR, CONFIRMAR FALLA Y DATOS | 01/11/2025 SE DEBE REALIZAR DESPLZAMIENTO EL DIA MARTES YA QUE POR PROBLEMAS EN LA VIA HACIA PUTUMAYO NO SE PUEDE VIAJAR ESTA SEMANA. | 06/11/2025 SE INICIA DESPLAZAMIENTO HASTA EL MPO | 06/11/2025 SE REALIZA VISITA AL CB PARA REVISAR FALLA USUARIO NO PODIA REALIZAR CIERRE DE FORMA CORRECTA, SE REALIZA BORRADO DE DATÁFONO Y SE REINSTALA SOFTWARE Y VERSIÓN, SE INICIALIZA OK, SE HACE PIERNAS OK Y SE EXPLICA A USUARIA COMO DEBE REALIZAR EL CIERRE DE FORMA CORRECTA, CB OPERATIVO | W2: VISITA TECNICA | X2: 3A00G829 | Y2: TIPO IV | Z2: TERRESTRE | AA2: GUERRERO RAMIREZ OSCAR DARIO | AB2: 1 | AC2: 0 | AD2: 0 | AE2: 0 | AF2: 0 | AG2: 479590 | AH2: 479590
A3: NEIVA | B3: REMOTAS | C3: 0004-0007 | D3: 41001 | E3: 2962236 | F3: 3007031706 | G3: INCIDENTE | H3: HUILA | I3: NEIVA | J3: BARRIO CENTRO 3 NEIVA | K3: REDEBAN | L3: FO-25-1763637 | M3: 45961.383 | N3: 45962.361 | O3: NO | P3: USUARIO | Q3: USUARIOS | R3: CREACION DE USUARIOS | S3: CB UNO A UNO | T3: CB UNO A UNO | V3: 31/10/2025 SE ESCALA PARA VISITA. LLAMAR ANTES DE VISITAR, CONFIRMAR FALLA Y DATOS | 01/11/2025 EN LLAMADA CON CLIENTE JUAN CARLOS LOZADA SE REALIZA CONFIGURACIÓN DE CLAVE DE SUPERVISOR. | W3: SOPORTE TELEFONICO | Y3: TIPO I | Z3: TERRESTRE | AA3: DIAZ VARGAS JONATHAN MIGUEL | AB3: 0 | AC3: 0 | AD3: 0 | AE3: 0 | AF3: 0 | AG3: 37905 | AH3: 37905
A4: TUNJA | B4: SANTANDERES | C4: 0004-0008 | D4: 15238 | E4: 2963361 | F4: 3007026691 | G4: INCIDENTE | H4: BOYACA | I4: DUITAMA | J4: BARRIO POLIDEPORTIVO LAS AMERI | K4: REDEBAN | L4: FO-25-1765119 | M4: 45961.475 | N4: 45962.451 | O4: NO | P4: USUARIO | Q4: COMUNICACION | R4: CANAL DEL COMERCIO | S4: UNO A UNO | T4: CB UNO A UNO | V4: 31/10/2025 SE ESCALA PARA VISITA. LLAMAR ANTES DE VISITAR, CONFIRMAR FALLA Y DATOS | 01/11/2025 EN COMUNICACIÓN CON LA CLIENTE, SEÑORA ANGIE SIERRA, AL NÚMERO CELULAR 3154643408, SE CONFIRMA QUE ACTUALMENTE EL PUNTO SE ENCUENTRA OPERANDO CORRECTAMENTE, CON COMUNICACIÓN EXITOSA. LA CLIENTE INFORMA QUE NO AUTORIZA LA ATENCIÓN DE LA VISITA TÉCNICA HASTA QUE EL NUEVO PROVEEDOR DE INTERNET HAYA COMPLETADO LA INSTALACIÓN Y DEJADO OPERATIVO EL SERVICIO EN EL COMERCIO, A FIN DE REALIZAR POSTERIORMENTE LA CONFIGURACIÓN DE LAS DIRECCIONES IP DE COMUNICACIÓN PARA CADA EQUIPO. SE LE INDICA A LA CLIENTE QUE, DADO LO ANTERIOR, SE PROCEDERÁ CON EL CIERRE DE LA ORDEN ACTUAL, Y QUE DEBERÁ COMUNICARSE NUEVAMENTE PARA SOLICITAR MANTENIMIENTO UNA VEZ EL COMERCIO CUENTE CON EL NUEVO CANAL DE COMUNICACIÓN HABILITADO. | W4: SOPORTE TELEFONICO | Y4: TIPO II | Z4: TERRESTRE | AA4: ALVARADO MORENO CRISTHIAN | AB4: 0 | AC4: 0 | AD4: 0 | AE4: 0 | AF4: 0 | AG4: 37905 | AH4: 37905
A5: BUCARAMANGA | B5: SANTANDERES | C5: 0004-0008 | D5: 68855 | E5: 2964118 | F5: 3007078026 | G5: INCIDENTE | H5: SANTANDER | I5: VALLE DE SAN JOSE | J5: BARRIO SAN ROQUE VALLE DE SAN | K5: REDEBAN | L5: FO-25-1765828 | M5: 45961.538 | N5: 45965.408 | O5: NO | P5: USUARIO | Q5: LECTOR DE TARJETAS | R5: OBSTRUCCION DEL LECTOR | S5: CB UNO A UNO | T5: CB UNO A UNO | V5: 31/10/2025 SE ESCALA PARA VISITA. LLAMAR ANTES DE VISITAR, CONFIRMAR FALLA Y DATOS | 03/11/2025 SE ESTABLECE COMUNICACIÓN CON LA SEÑORA GINA AL NÚMERO 3167092023 QUIEN INFORMA QUE EL DATÁFONO NO LE LEE NINGUNA TARJETA SE LE INFORMA QUE EL DIA DE HOY NO SE CUENTA CON SOPORTE DE REDEBAN PARA PODER REALIZAR EL CAMBIO DE EQUIPO POR LO QUE SE REPROGRAMA LA ACTIVIDAD PARA EL DIA MIÉRCOLES EN EL TRANSCURSO DEL DÍA CLIENTE INFORMA QUE NO TIENE NINGÚN INCONVENIENTE | 04/11/2025 SE ESTABLECE COMUNICACIÓN CON LA SEÑORA CLAUDIA AL NÚMERO 3187317848 INFORMA QUE EL EQUIPO EL DIA DE HOY YA LE ESTA LEYENDO LAS TARJETAS SE SOLICITA FOTO DE BAUCHER COMO EVIDENCIA Y SE PROCEDE A CERRAR ORDEN | W5: SOPORTE TELEFONICO | Y5: TIPO III | Z5: TERRESTRE | AA5: BARRERA ORTEGA MARLON STWAR | AB5: 0 | AC5: 0 | AD5: 0 | AE5: 0 | AF5: 0 | AG5: 37905 | AH5: 37905
A6: CARTAGENA | B6: COSTA | C6: 0004-0001 | D6: 13001 | E6: 2965065 | F6: 3007030332 | G6: INCIDENTE | H6: BOLIVAR | I6: CARTAGENA | J6: BARRIO MANGA CARTAGENA DE INDI | K6: REDEBAN | L6: FO-25-1766919 | M6: 45961.66 | N6: 45962.411 | O6: NO | P6: USUARIO | Q6: CIERRE | R6: COMERCIO NO REALIZA CIERRE | S6: CB UNO A UNO | T6: CB UNO A UNO | U6: EJECUTADO | V6: 31/10/2025 SE ESCALA PARA VISITA. LLAMAR ANTES DE VISITAR, CONFIRMAR FALLA Y DATOS | 01/11/2025 CLIENTE PROBLEMA CON LA CLAVE DEL CIERRE SE INGRESA Y SE COLOCA NUEVAMENTE LA CLAVE SE HACEN PRUEBAS TODO OK | W6: VISITA TECNICA | X6: AB11T106 | Y6: TIPO I | Z6: TERRESTRE | AA6: CANEDO HERRERA ALEXANDER | AB6: 1 | AC6: 0 | AD6: 0 | AE6: 0 | AF6: 0 | AG6: 65960 | AH6: 65960
A7: MEDELLIN | B7: NOROCCIDENTE | C7: 0004-0005 | D7: 5148 | E7: 2966577 | F7: 3007072668 | G7: INCIDENTE | H7: ANTIOQUIA | I7: EL CARMEN DE VIBORAL | J7: SAN JOSE EL CARMEN DE VIBORAL | K7: REDEBAN | L7: FO-25-1768943 | M7: 45962.453 | N7: 45964.378 | O7: NO | P7: USUARIO | Q7: NO ENCIENDE | R7: CONEXIONES DE COMERCIO | S7: CB UNO A UNO | T7: CB UNO A UNO | V7: 01/11/2025 SE ESCALA PARA VISITA. LLAMAR ANTES DE VISITAR, CONFIRMAR FALLA Y DATOS | 03/11/2025 SE HABLA CON USUARIO Y NOS INFORMA QUE DATAFONO YA ESTÁ FUNCIONAL, NO RESPONDIA EL EQUIPO Y MOSTRABA TECLADO BLOQUEADO PERO CB YA ESTA OPERATIVO, SE CIERRA INCIENTE. | W7: SOPORTE TELEFONICO | Y7: TIPO II | Z7: TERRESTRE | AA7: RIOS CASTRILLON JUAN SEBASTIAN | AB7: 0 | AC7: 0 | AD7: 0 | AE7: 0 | AF7: 0 | AG7: 37905 | AH7: 37905
A8: BOGOTA | B8: CUNDINAMARCA | C8: 0004-0004 | D8: 11001 | E8: 2966634 | F8: 3007026555 | G8: INCIDENTE | H8: CUNDINAMARCA | I8: BOGOTA | J8: PAGAFACIL BOSA | K8: REDEBAN | L8: FO-25-1768619 | M8: 45962.428 | N8: 45962.563 | O8: NO | P8: USUARIO | Q8: MANTENIMIENTO | R8: MANTENIMIENTO GENERAL | S8: ROBUSTO | T8: PAGAFACIL | U8: EJECUTADO | V8: 01/11/2025 SE ESCALA PARA VISITA. LLAMAR ANTES DE VISITAR, CONFIRMAR FALLA Y DATOS | 01/11/2025 SE REALIZA REVISIÓN DEL CABLEADO Y SE OBSERVA QUE EL CABLE DEL PINPAD SE ENCUENTRA DESCONECTADO | W8: VISITA TECNICA | X8: 9999I348 | Y8: TIPO I | Z8: TERRESTRE | AA8: ALARCON AREVALO JOHAN STIVEN | AB8: 1 | AC8: 0 | AD8: 0 | AE8: 0 | AF8: 0 | AG8: 65960 | AH8: 65960
A9: PASTO | B9: SUROCCIDENTE Y EJE CAFETERO | C9: 0004-0003 | D9: 52001 | E9: 2966652 | F9: 3007071128 | G9: INCIDENTE | H9: NARIÑO | I9: PASTO | J9: PTM PASTO TIENDA MARTINNA | K9: REDEBAN | L9: FO-25-1768874 | M9: 45962.449 | N9: 45965.563 | O9: NO | P9: USUARIO | Q9: COMUNICACION | R9: CANAL DEL COMERCIO | S9: AGREGADOR | T9: COMCARD - PTM | V9: 01/11/2025 SE ESCALA PARA VISITA. LLAMAR ANTES DE VISITAR, CONFIRMAR FALLA Y DATOS | 01/11/2025 SE VALIDA CLIENTE VALIDARA CON PROVEEDOR DE INTERNET YA QUE TIENE PROBLEMAS CON MAS DISPOSITIVOS, PIDE QUE VALIDEMOS EL MARTES PARA REVISAR SI ES NECESARIA LA VISITA, NO LABORA FIN DE SEMANA | 04/11/2025 SE REALIZA LLAMADA TELEFÓNICA PARA CONFIRMAR VISITA,SE CONTACTA CON LA SEÑORA PAOLA GUERRERO LA CUÁL INFORMA QUE EL DÍA QUE LLAMO NO CONECTABA EL DATÁFONO A INTERNET PERO QUE AL DÍA SIGUIENTE YA FUNCIONÓ NORMALMENTE POR LO CUAL YA NO DESEA VISITA EN EL COMERCIO Y AUTORIZA CERRAR LA TA... | W9: SOPORTE TELEFONICO | Y9: TIPO I | Z9: TERRESTRE | AA9: PAZ MARTINEZ RICHARD HUMBERTO | AB9: 0 | AC9: 0 | AD9: 0 | AE9: 0 | AF9: 0 | AG9: 37905 | AH9: 37905
A10: NEIVA | B10: REMOTAS | C10: 0004-0007 | D10: 41132 | E10: 2966657 | F10: 3007037411 | G10: INCIDENTE | H10: HUILA | I10: CAMPOALEGRE | J10: BARRIO CENTRO CAMPOALEGRE 1 | K10: REDEBAN | L10: FO-25-1768868 | M10: 45962.451 | N10: 45965.628 | O10: NO | P10: USUARIO | Q10: COMUNICACION | R10: CONEXIONES DE COMERCIO | S10: UNO A UNO | T10: CB UNO A UNO | U10: EJECUTADO | V10: 01/11/2025 SE ESCALA PARA VISITA. LLAMAR ANTES DE VISITAR, CONFIRMAR FALLA Y DATOS | 03/11/2025 SIN SOPORTE DE REDEBAN PARA CAMBIO DE EQUIPO | 04/11/2025 SE REALIZA REVISIÓN DE CABLEADO ENCONTRANDO CONECTOR SUELTO DE UNA DERIVACIÓN, SE CONECTA AL MÓDEM , SE EVIDENCIA CONEXIÓN EXITOSA Y SE REALIZA PRUEBAS OK | W10: VISITA TECNICA | X10: AB00M753 | Y10: TIPO II | Z10: TERRESTRE | AA10: ANDRADE HERNANDEZ JUAN CARLOS | AB10: 1 | AC10: 0 | AD10: 0 | AE10: 0 | AF10: 0 | AG10: 163814 | AH10: 163814
A11: PASTO | B11: SUROCCIDENTE Y EJE CAFETERO | C11: 0004-0003 | D11: 52560 | E11: 2967577 | F11: 3007029267 | G11: INCIDENTE | H11: NARIÑO | I11: POTOSI | J11: BARRIO PARQUE BOLIVAR POTOSI | K11: REDEBAN | L11: FO-25-1771261 | M11: 45963.587 | N11: 45965.531 | O11: NO | P11: USUARIO | Q11: MANTENIMIENTO | R11: MANTENIMIENTO GENERAL | S11: CB UNO A UNO | T11: CB UNO A UNO | V11: 02/11/2025 SE ESCALA PARA VISITA. LLAMAR ANTES DE VISITAR, CONFIRMAR FALLA Y DATOS | 04/11/2025 SE REALIZA COMUNICACIÓN TELEFÓNICA CON EL CLIENTE PARA CONFIRMAR VISITA TÉCNICA PERO INFORMA QUE EL LE HIZO LIMPIEZA A LA IMPRESORA Y QUEDÓ FUNCIONANDO CORRECTAMENTE, INDICA QUE NO ES NECESARIO VISITAR. CLIENTE AUTORIZA CERRAR ACTIVIDAD | W11: SOPORTE TELEFONICO | Y11: TIPO II | Z11: TERRESTRE | AA11: CASTILLO HERRERA ALEX RICARDO | AB11: 0 | AC11: 0 | AD11: 0 | AE11: 0 | AF11: 0 | AG11: 37905 | AH11: 37905
A12: BOGOTA | B12: CUNDINAMARCA | C12: 0004-0004 | D12: 25126 | E12: 2967584 | F12: 3007034784 | G12: INCIDENTE | H12: CUNDINAMARCA | I12: CAJICA | J12: DISTRICOL ESCOLARES Y PAPELE 2 | K12: REDEBAN | L12: FO-25-1771260 | M12: 45963.608 | N12: 45965.631 | O12: NO | P12: USUARIO | Q12: NO ENCIENDE | R12: CONEXIONES DE COMERCIO | S12: AGREGADOR | T12: DISTRICOL | U12: EJECUTADO | V12: 02/11/2025 SE ESCALA PARA VISITA. LLAMAR ANTES DE VISITAR, CONFIRMAR FALLA Y DATOS | 02/11/2025 NO HAY SOPORTE DE ACTIVOS PARA ATENDER ACTIVIDAD | 04/11/2025 DURANTE LA VISITA TECNICA PARA ATENDER INCIDENTE REPORTADO POR CORRESPONSAL BANCARIO, CORRESPONSAL NOS INDICA QUE EL DAÑO YA FUE SOLUCIONADO, SE HACEN PRUEBAS CONFIRMANDO QUE SERVICIO SE ENCUENTRA FUNCIONAL Y OPERATIVO A CONFORMIDAD DEL CB SIN NOVEDAD EN EL INCIDENTE SALDO OK NOTA NO SE INGRESA A COMERCIO NO SE MANIPULA EQUIPOS NO SE TOMA FOTO DE PLACAS | W12: VISITA TECNICA | X12: BL01F357 | Y12: TIPO II | Z12: TERRESTRE | AA12: GALEANO SORIANO JUAN DAVID | AB12: 1 | AC12: 0 | AD12: 0 | AE12: 0 | AF12: 0 | AG12: 163814 | AH12: 163814
A13: IBAGUE | B13: REMOTAS | C13: 0004-0007 | D13: 73001 | E13: 2969545 | F13: 3007073613 | G13: INCIDENTE | H13: TOLIMA | I13: IBAGUE | J13: PTM IBAGUE MERK' ABASTO | K13: REDEBAN | L13: FO-25-1775218 | M13: 45965.387 | N13: 45966.408 | O13: NO | P13: USUARIO | Q13: COMUNICACION | R13: CANAL DEL COMERCIO | S13: AGREGADOR | T13: COMCARD - PTM | V13: 04/11/2025 SE ESCALA PARA VISITA. LLAMAR ANTES DE VISITAR, CONFIRMAR FALLA Y DATOS | 05/11/2025 SE COMUNICA AL NÚMERO 3142681316, LA SEÑORA SOL ESCAMILLA INDICA HABER PRESENTADO PROBLEMAS DE CONEXIÓN. SOLICITA VALIDAR NUEVAMENTE A PARTIR DE LAS 10 AM DEL DÍA DE HOY DEBIDO A QUE SE ENCUENTRA REALIZANDO COMPENSACIÓN. GESTIÓN TELEFÓNICA | 05/11/2025 SE COMUNICA AL 3142681316, EL CLIENTE INDICA HABER PRESENTADO FALLAS EN SERVICIO DE INTERNET, SE VERIFICA FUNCIONAMIENTO DEL EQUIPO OK. | W13: SOPORTE TELEFONICO | Y13: TIPO I | Z13: TERRESTRE | AA13: BARRAGAN TAFUR EDWIN ESTEBAN | AB13: 0 | AC13: 0 | AD13: 0 | AE13: 0 | AF13: 0 | AG13: 37905 | AH13: 37905
A14: CARTAGENA | B14: COSTA | C14: 0004-0001 | D14: 13244 | E14: 2970043 | F14: 3007017580 | G14: INCIDENTE | H14: BOLIVAR | I14: EL CARMEN DE BOLIVAR | J14: BARRIO CENTRO II EL CARMEN DE | K14: REDEBAN | L14: FO-25-1775337 | M14: 45965.408 | N14: 45968.389 | O14: NO | P14: USUARIO | Q14: COMUNICACION | R14: CANAL DEL COMERCIO | S14: CB UNO A UNO | T14: CB UNO A UNO | U14: EJECUTADO / CANCELADO | V14: 04/11/2025 SE ESCALA PARA VISITA. LLAMAR ANTES DE VISITAR, CONFIRMAR FALLA Y DATOS | 06/11/2025 SE LLEGA AL SITIO INFORMAN QUE EN EL DIA DE HOY CASUALMENTE UN CAMIÓN PASO Y ROMPIÓ EL CABLE DEL INTERNET EN EL MOMENTO NO TIENEN SERVICIO PERO SE VA VALIDAR EN SITIO UN TIEMPO SE ESPERA PARA VER SI SE RESUELVE LA NOVEDAD | 07/11/2025 SE INTENTO VALIDAR LA NOVEDAD PERO DEBIDO A QUE EL CLIENTE QUEDÓ SIN INTERNET POR QUE UN CAMIÓN ROMPIÓ EL CABLE DEL INTERNET NO FUE POSIBLE GESTIONAR LA NOVEDAD Y TAMPOCO REALIZAR PRUEBAS CON EL EQUIPO AFECTADO EL CUAL SE INTENTO PROBAR Y NO TIENE CONEXIÓN A INTERNET SE LE INDICA AL CLIENTE QUE DEBE LLAMAR NUEVAMENTE A LA LINEA CUANDO LE ARREGLEN EL DAÑO QUE TIENE CON EL PROVEEDOR DE INTERNET PARA PODER VALIDAR | W14: VISITA TECNICA | X14: 9B08Z086 | Y14: TIPO III | Z14: TERRESTRE | AA14: MARTINEZ SALGUEDO ANDRES AUGUSTO | AB14: 1 | AC14: 0 | AD14: 0 | AE14: 0 | AF14: 0 | AG14: 275728 | AH14: 275728
A15: BUCARAMANGA | B15: SANTANDERES | C15: 0004-0008 | D15: 68276 | E15: 2974237 | F15: 3007036258 | G15: INCIDENTE | H15: SANTANDER | I15: FLORIDABLANCA | J15: BARRIO ALARES FLORIDABLANCA 1 | K15: REDEBAN | L15: FO-25-1778544 | M15: 45965.67 | N15: 45966.652 | O15: NO | P15: USUARIO | Q15: COMUNICACION | R15: CANAL DEL COMERCIO | S15: CB UNO A UNO | T15: CB UNO A UNO | U15: EJECUTADO | V15: 04/11/2025 SE ESCALA PARA VISITA. LLAMAR ANTES DE VISITAR, CONFIRMAR FALLA Y DATOS | 05/11/2025 SE REALIZA VISITA, SE VÁLIDA CONEXIÓNES Y CORRESPONSAL PRESENTA ERROR DE CONEXIÓN, SE VÁLIDA CON OTRO DATÁFONO Y LA FALLA PERSISTE, SE CAMBIA DE CONEXIONES A OTROS PUERTO Y A OTRO SWICH Y AÚN CONTINÚA CON LA FALLA, SE COMPARTE INTERNET DEL CELULAR A UN PORTÁTIL SE REALIZAN PRUEBAS EXITOSA, CLIENTE PROCEDE A COMUNICARSE CON EL OPERADOR DE ETHERNET, ACTUALIZAN, SE REINICIA MODEM Y DATÁFONO EMPIEZA A OPERAR EXITOSAMENTE, SE REALIZAN PRUEBAS EXITOSA. | W15: VISITA TECNICA | X15: 9A00G111 | Y15: TIPO I | Z15: TERRESTRE | AA15: MARTINEZ FLOREZ DONIS ALBERTO | AB15: 1 | AC15: 0 | AD15: 0 | AE15: 0 | AF15: 0 | AG15: 65960 | AH15: 65960
A16: CALI | B16: SUROCCIDENTE Y EJE CAFETERO | C16: 0004-0003 | D16: 76001 | E16: 2975677 | F16: 3007081193 | G16: INCIDENTE | H16: VALLE DEL CAUCA | I16: CALI | J16: BARRIO ULPIANO LLOREDA CALI 1 | K16: REDEBAN | L16: FO-25-1780957 | M16: 45966.348 | N16: 45966.475 | O16: NO | P16: USUARIO | Q16: CIERRE | R16: COMERCIO NO REALIZA CIERRE | S16: UNO A UNO | T16: UNO A UNO | U16: EJECUTADO | V16: 05/11/2025 SE ESCALA PARA VISITA. LLAMAR ANTES DE VISITAR, CONFIRMAR FALLA Y DATOS | 05/11/2025 SE VISITA CORRESPONSAL Y SE REALIZA CIERRE Y BORRADO DE MEMORIA. TRANSACCIONES DE PRUEBA EXITOSAS. | W16: VISITA TECNICA | X16: FKZZZ652 | Y16: TIPO I | Z16: TERRESTRE | AA16: BOLAÑOS TABORDA JORGE ENRIQUE | AB16: 1 | AC16: 0 | AD16: 0 | AE16: 0 | AF16: 0 | AG16: 65960 | AH16: 65960
A17: MEDELLIN | B17: NOROCCIDENTE | C17: 0004-0005 | D17: 15572 | E17: 2978682 | F17: 3007030721 | G17: INCIDENTE | H17: BOYACA | I17: PUERTO BOYACA | J17: DISTRICOL MISCELANEA LOS CHIQU | K17: REDEBAN | L17: FO-25-1784703 | M17: 45966.55 | N17: 45968.408 | O17: NO | P17: USUARIO | Q17: LECTOR DE TARJETAS | R17: OBSTRUCCION DEL LECTOR | S17: AGREGADOR | T17: DISTRICOL | V17: 06/11/2025 SE ESCALA PARA VISITA. LLAMAR ANTES DE VISITAR, CONFIRMAR FALLA Y DATOS | 07/11/2025 SE HABLA CON EL USUARIO E INDICA QUE EL PINPAD YA ESTÁ BUENO Y EL CB ESTÁ TOTALMENTE OPERATIVO , CB OK | W17: SOPORTE TELEFONICO | Y17: TIPO IV | Z17: TERRESTRE | AA17: MONTOYA VELEZ ANDRES FELIPE | AB17: 0 | AC17: 0 | AD17: 0 | AE17: 0 | AF17: 0 | AG17: 37905 | AH17: 37905
A18: MONTERIA | B18: COSTA | C18: 0004-0001 | D18: 23001 | E18: 2980491 | F18: 3007082047 | G18: INCIDENTE | H18: CORDOBA | I18: MONTERIA | J18: DISTRICOL COFFE MARK 3 | K18: REDEBAN | L18: FO-25-1784870 | M18: 45966.7 | N18: 45967.572 | O18: NO | P18: USUARIO | Q18: COMUNICACION | R18: CANAL DEL COMERCIO | S18: AGREGADOR | T18: DISTRICOL | U18: EJECUTADO / CANCELADO | V18: 05/11/2025 SE ESCALA PARA VISITA. LLAMAR ANTES DE VISITAR, CONFIRMAR FALLA Y DATOS | 06/11/2025 SE LLEGA AL SITIO, SE ENCUENTRA CERRADO SE REALIZA LLAMADA AL CONTACTO DEL CB INDICANDO, ESPERAR 20 MINUTOS PARA LLEGAR AL PUNTO Y PODER RECIBIR LA VISITA TÉCNICA | 06/11/2025 SE LLEGA AL COMERCIO SE ENCUENTRA CERRADO, SE PROCEDE A CONTACTAR AL SEÑOR KEVIN CONTRERAS 3046700913 INDICA AL TÉCNICO ESPERAR 15 MINUTOS PARA LLEGAR AL COMERCIO Y RECIBIR LA VISITA TÉCNICA, TÉCNICO LLEVA 60 MINUTOS A QUE EL SEÑOR LLEGUE, PERO NO LLEGO AL PUNTO SE PROCEDE A DOCUMENTAR LA TAREA. VISITA FALLIDA, NO SE MANIPULA EQUIPOS | W18: VISITA TECNICA | X18: CA002291 | Y18: TIPO I | Z18: TERRESTRE | AA18: ARRAZOLA HERNANDEZ NICOLAS AUGUSTO | AB18: 1 | AC18: 0 | AD18: 0 | AE18: 0 | AF18: 0 | AG18: 65960 | AH18: 65960
A19: MEDELLIN | B19: NOROCCIDENTE | C19: 0004-0005 | D19: 5001 | E19: 2983143 | F19: 3007029997 | G19: INCIDENTE | H19: ANTIOQUIA | I19: MEDELLIN | J19: PAGAFACIL VIVA LAURELES | K19: REDEBAN | L19: FO-25-1787147 | M19: 45967.427 | N19: 45967.627 | O19: NO | P19: USUARIO | Q19: MANTENIMIENTO | R19: MANTENIMIENTO GENERAL | S19: ROBUSTO | T19: PAGAFACIL | U19: EJECUTADO | V19: 06/11/2025 SE ESCALA PARA VISITA. LLAMAR ANTES DE VISITAR, CONFIRMAR FALLA Y DATOS | 06/11/2025 SE LLAMA A CLIENTE PARA CONFIRMAR VISITA Y NOS COMENTA QUE PUEDE ATENDER A PARTIR DE LAS 2PM | 06/11/2025 SE REALIZA MANTENIMIENTO DE DATÁFONO, PRUBAS OK | W19: VISITA TECNICA | X19: BBNZZ971 | Y19: TIPO I | Z19: TERRESTRE | AA19: CARDONA MOLINA BROLIN STIVEN | AB19: 1 | AC19: 0 | AD19: 0 | AE19: 0 | AF19: 0 | AG19: 65960 | AH19: 65960
A20: MEDELLIN | B20: NOROCCIDENTE | C20: 0004-0005 | D20: 5664 | E20: 2983582 | F20: 3007048480 | G20: INCIDENTE | H20: ANTIOQUIA | I20: SAN PEDRO DE LOS MILAGROS | J20: BARRIO PARQUE SAN PEDRO DE LOS | K20: REDEBAN | L20: FO-25-1787207 | M20: 45967.457 | N20: 45968.708 | O20: NO | P20: USUARIO | Q20: COMUNICACION | R20: CANAL DEL COMERCIO | S20: CB UNO A UNO | T20: CB UNO A UNO | V20: 06/11/2025 SE ESCALA PARA VISITA. LLAMAR ANTES DE VISITAR, CONFIRMAR FALLA Y DATOS | 08/11/2025 OPERARIA INFORMA QUE LUEGO DE UN PAR DE HORAS EL EQUIPO FUNCIONO SIN PROBLEMA. CB OPERATIVO, SE CIERRA INCIDENTE. | W20: SOPORTE TELEFONICO | Y20: TIPO II | Z20: TERRESTRE | AA20: ZAPATA LOPEZ EDWARD ASDRUBAL | AB20: 0 | AC20: 0 | AD20: 0 | AE20: 0 | AF20: 0 | AG20: 37905 | AH20: 37905
A21: NEIVA | B21: REMOTAS | C21: 0004-0007 | D21: 41132 | E21: 2984757 | F21: 3007061198 | G21: INCIDENTE | H21: HUILA | I21: CAMPOALEGRE | J21: BARRIO CENTRO CAMPOALEGRE 5 | K21: REDEBAN | L21: FO-25-1790600 | M21: 45967.539 | N21: 45968.447 | O21: NO | P21: ENTIDAD | Q21: ERROR DE TRANSACCIONES | R21: TRANSACCION NO PERMITIDA | S21: CB UNO A UNO | T21: CB UNO A UNO | U21: EJECUTADO | V21: 06/11/2025 SE ESCALA PARA VISITA. LLAMAR ANTES DE VISITAR, CONFIRMAR FALLA Y DATOS | 07/11/2025 SE REALIZA VISITA AL PUNTO, CLIENTE INDICA QUE EQUIPO PRESENTABA LETRERO ROJO EN LA PANTALLA Y NO PERMITÍA HACER NINGÚNA TRANSACCIÓN SE REALIZA VALIDACIÓN EN PUNTO, SE EVIDENCIA EQUIPO SE ENCUENTRA OPERANDO CON NORMALIDAD, YA QUE EL PROBLEMA FUE UNA CAÍDANO BLOQUEA DE LA PLATAFORMA . CB OPERATIVO | W21: VISITA TECNICA | X21: 9TZZZ261 | Y21: TIPO II | Z21: TERRESTRE | AA21: DEVIA REINOSO JUAN CARLOS | AB21: 1 | AC21: 0 | AD21: 0 | AE21: 0 | AF21: 0 | AG21: 163814 | AH21: 163814
A22: MEDELLIN | B22: NOROCCIDENTE | C22: 0004-0005 | D22: 5390 | E22: 2986974 | F22: 3007063733 | G22: INCIDENTE | H22: ANTIOQUIA | I22: LA PINTADA | J22: BARRIO SECTOR EL CRUCERO LA PI | K22: REDEBAN | L22: FO-25-1793198 | M22: 45967.73 | N22: 45968.709 | O22: NO | P22: USUARIO | Q22: MANTENIMIENTO | R22: MANTENIMIENTO GENERAL | S22: CB UNO A UNO | T22: CB UNO A UNO | V22: 06/11/2025 SE ESCALA PARA VISITA. LLAMAR ANTES DE VISITAR, CONFIRMAR FALLA Y DATOS | 08/11/2025 USUARIO INFORMA QUE LUEGO DE DESCONECTAR BATERIA Y VOLVER A CONECTAR YA FUNCIONO NUEVAMENTE EL EQUIPO, SE VOLVIO A PRESENTAR LUEGO LA NOVEDAD PERO VOLVIO A SOLUCIONAR DE LA MISMA FORMA Y HOY HA ESTADO OPERANDO SIN PROBLEMA, CB OPERATIVO, SE CIERRA INCIDENTE. | W22: SOPORTE TELEFONICO | Y22: TIPO II | Z22: TERRESTRE | AA22: ZAPATA LOPEZ EDWARD ASDRUBAL | AB22: 0 | AC22: 0 | AD22: 0 | AE22: 0 | AF22: 0 | AG22: 37905 | AH22: 37905
A23: BUCARAMANGA | B23: SANTANDERES | C23: 0004-0008 | D23: 68276 | E23: 2987238 | F23: 3007045683 | G23: INCIDENTE | H23: SANTANDER | I23: FLORIDABLANCA | J23: BARRIO OASIS FLORIDABLANCA 1 | K23: REDEBAN | L23: FO-25-1793891 | M23: 45968.333 | N23: 45969.619 | O23: NO | P23: USUARIO | Q23: NO ENCIENDE | R23: CONEXIONES DE COMERCIO | S23: CB UNO A UNO | T23: CB UNO A UNO | V23: 07/11/2025 SE ESCALA PARA VISITA. LLAMAR ANTES DE VISITAR, CONFIRMAR FALLA Y DATOS | 08/11/2025 EN COMUNICACIÓN TELEFÓNICA CON SEÑOR ALEJANDRO MORÓN PARA ATENDER INCIDENTE, NOS PREGUNTA SI YO LE LLEVO EL DATÁFONO DE WOMPI LE INDICO QUE NO QUE VOY POR UNA SOLICITUD DE REDEBAN POR ALGÚN DAÑO EN EL EQUIPO, PERO NOS INDICA QUE EL PENSABA QUE YO LE IBA A INSTALAR YLS NUEVA TECNOLOGÍA POR LO TANTO INDICA QUE POR ESTE MOTIVO ERA LA LLAMADA ENTONCES CANCELA LA VISITA TÉCNICA | W23: SOPORTE TELEFONICO | Y23: TIPO I | Z23: TERRESTRE | AA23: PEÑA DIAZ IVAN YESID | AB23: 0 | AC23: 0 | AD23: 0 | AE23: 0 | AF23: 0 | AG23: 37905 | AH23: 37905
A24: PEREIRA | B24: SUROCCIDENTE Y EJE CAFETERO | C24: 0004-0002 | D24: 66001 | E24: 2988056 | F24: 3007017109 | G24: INCIDENTE | H24: RISARALDA | I24: PEREIRA | J24: BARRIO HAMBURGO PEREIRA | K24: REDEBAN | L24: FO-25-1794764 | M24: 45968.358 | N24: 45968.681 | O24: NO | P24: USUARIO | Q24: CIERRE | R24: COMERCIO NO REALIZA CIERRE | S24: CB UNO A UNO | T24: CB UNO A UNO | U24: EJECUTADO | V24: 07/11/2025 SE ESCALA PARA VISITA. LLAMAR ANTES DE VISITAR, CONFIRMAR FALLA Y DATOS | 07/11/2025 SE VISITA COMERCIO SE IDENTIFICA DATÁFONO DESCONFIGURADO SE REINSTALA APLICATIVO SE REALIZA PRUEBAS OK | W24: VISITA TECNICA | X24: AB000095 | Y24: TIPO I | Z24: TERRESTRE | AA24: LOAIZA LOPEZ JHON FREDDY | AB24: 1 | AC24: 0 | AD24: 0 | AE24: 0 | AF24: 0 | AG24: 65960 | AH24: 65960
A25: MEDELLIN | B25: NOROCCIDENTE | C25: 0004-0005 | D25: 5088 | E25: 2989510 | F25: 3007046702 | G25: INCIDENTE | H25: ANTIOQUIA | I25: BELLO | J25: DISTRICOL PAPELERIA Y MISCELAN | K25: REDEBAN | L25: FO-25-1795477 | M25: 45968.438 | N25: 45968.507 | O25: NO | P25: USUARIO | Q25: COMUNICACION | R25: CONEXIONES DE COMERCIO | S25: AGREGADOR | T25: DISTRICOL | V25: 07/11/2025 SE ESCALA PARA VISITA. LLAMAR ANTES DE VISITAR, CONFIRMAR FALLA Y DATOS | 07/11/2025 SE REALIZA CONTACTO TELEFÓNICO CON EL USUARIO PARA CONFIRMAR EL INCIDENTE PREVIAMENTE REPORTADO RELACIONADO CON EL DATÁFONO. EL USUARIO INDICA QUE LA FALLA PRESENTADA CORRESPONDÍA A PROBLEMAS DE CONEXIÓN DEL COMERCIO, NO DEL DISPOSITIVO. TRAS REALIZAR LAS VALIDACIONES PERTINENTES, SE CONFIRMA QUE EL DATÁFONO SE ENCUENTRA ACTUALMENTE OPERATIVO Y FUNCIONANDO CON NORMALIDAD | W25: SOPORTE TELEFONICO | Y25: TIPO I | Z25: TERRESTRE | AA25: MARTINEZ TOVAR OSCAR DAVID | AB25: 0 | AC25: 0 | AD25: 0 | AE25: 0 | AF25: 0 | AG25: 37905 | AH25: 37905
A26: NEIVA | B26: REMOTAS | C26: 0004-0007 | D26: 18001 | E26: 2990957 | F26: 3007053542 | G26: INCIDENTE | H26: CAQUETA | I26: FLORENCIA | J26: DISTRICOL VARIEDADES MARY | K26: REDEBAN | L26: FO-25-1796632 | M26: 45968.596 | N26: 45971.43 | O26: NO | P26: USUARIO | Q26: USUARIOS | R26: MALA MANIPULACION POS | S26: AGREGADOR | T26: DISTRICOL | U26: EJECUTADO / CANCELADO | V26: 07/11/2025 SE ESCALA PARA VISITA. LLAMAR ANTES DE VISITAR, CONFIRMAR FALLA Y DATOS | 11/11/2025 SE LLEGA AL CB Y SE CB SE ENCUENTRA TRABAJANDO CON NORMALIDAD, CLIENTE ESTÁ INCONFORME CON EL EQUIPO DESK2600 QUE SE LE DEJO INSTALADO YA QUE ELLA QUIERE ES EL DESK3500 SE LE INDICA QUE EQUIPOS DESK3500 NO SE TIENEN Y QUE EL DESK2600 QUE SE LE INSTALO ES UN EQUIPO NUEVO Y QUE SE ENCUENTRA FUNCIONANDO CON NORMALIDAD Y ESTÁ EN BUEN ESTADO. | W26: VISITA TECNICA | X26: TR0VZ619 | Y26: TIPO IV | Z26: TERRESTRE | AA26: BERMUDEZ SANCHEZ JOSE NEYBER | AB26: 1 | AC26: 0 | AD26: 0 | AE26: 0 | AF26: 0 | AG26: 479590 | AH26: 479590
A27: IBAGUE | B27: REMOTAS | C27: 0004-0007 | D27: 73001 | E27: 2992385 | F27: 3007076197 | G27: INCIDENTE | H27: TOLIMA | I27: IBAGUE | J27: DISTRICOL DROGUERIA SALUD PLUS | K27: REDEBAN | L27: FO-25-1797901 | M27: 45968.691 | N27: 45969.489 | O27: NO | P27: USUARIO | Q27: NO ENCIENDE | R27: CONEXIONES DE COMERCIO | S27: AGREGADOR | T27: DISTRICOL | U27: EJECUTADO | V27: 08/11/2025 SE VALIDA CABLE MAGIC BOX DETERIORADO, SE REEMPLAZA Y SE REALIZA PRUEBAS DE FUNCIONAMIENTO EXITOSAS. CUBRE CLAVE INSTALADO | W27: VISITA TECNICA | X27: FA0GZ489 | Y27: TIPO I | Z27: TERRESTRE | AA27: BARRAGAN TAFUR EDWIN ESTEBAN | AB27: 1 | AC27: 0 | AD27: 0 | AE27: 0 | AF27: 0 | AG27: 65960 | AH27: 65960
A28: CALI | B28: SUROCCIDENTE Y EJE CAFETERO | C28: 0004-0003 | D28: 76520 | E28: 2992927 | F28: 3007069957 | G28: INCIDENTE | H28: VALLE DEL CAUCA | I28: PALMIRA | J28: PTM PALMIRA ELECTROMUEBLES PAL | K28: REDEBAN | L28: FO-25-1798119 | M28: 45968.745 | N28: 45969.531 | O28: NO | P28: USUARIO | Q28: COMUNICACION | R28: CONEXIONES DE COMERCIO | S28: AGREGADOR | T28: COMCARD - PTM | U28: EJECUTADO | V28: 07/11/2025 SE ESCALA PARA VISITA. LLAMAR ANTES DE VISITAR, CONFIRMAR FALLA Y DATOS | 08/11/2025 SE LLEGA AL COMERCIO PERO EL EQUIPO ESTA FUNCIONANDO CORRECTAMENTE SE ACTUALIZA A ULTIMA VERSIÓN SE HACEN PRUEBAS Y QUEDA FUNCIONANDO CORRECTAMENTE | W28: VISITA TECNICA | X28: TV002835 A300R558 | Y28: TIPO I | Z28: TERRESTRE | AA28: CUERO RUIZ JHONNY | AB28: 1 | AC28: 0 | AD28: 0 | AE28: 0 | AF28: 0 | AG28: 65960 | AH28: 65960
A29: CALI | B29: SUROCCIDENTE Y EJE CAFETERO | C29: 0004-0003 | D29: 76001 | E29: 2993386 | F29: 3007058730 | G29: INCIDENTE | H29: VALLE DEL CAUCA | I29: CALI | J29: PTM CALI CASA DIGITAL 73 | K29: REDEBAN | L29: FO-25-1800431 | M29: 45969.499 | N29: 45971.637 | O29: NO | P29: USUARIO | Q29: MANTENIMIENTO | R29: MANTENIMIENTO GENERAL | S29: AGREGADOR | T29: COMCARD - PTM | U29: EJECUTADO / CANCELADO | V29: 08/11/2025 SE ESCALA PARA VISITA. LLAMAR ANTES DE VISITAR, CONFIRMAR FALLA Y DATOS | 09/11/2025 SE LLAMA AL CLIENTE E INDICA QUE NO SE ENCUENTRA EN EL COMERCIO QUE SI PODEMOS VISITAR EL DIA DE MAÑANA | 10/11/2025 SE LLEGA A LA DIRECCION Y SE ENCUENTRA EL CB CERRADO, AUNQUE SE INTENTO COMUNICACION NO FUE EXITOSO. | W29: VISITA TECNICA | X29: 000000 | Y29: TIPO I | Z29: TERRESTRE | AA29: TORRES GARCIA JENDRY JOSE | AB29: 1 | AC29: 0 | AD29: 0 | AE29: 0 | AF29: 0 | AG29: 65960 | AH29: 65960
A30: BUCARAMANGA | B30: SANTANDERES | C30: 0004-0008 | D30: 13744 | E30: 2993450 | F30: 3007047102 | G30: INCIDENTE | H30: BOLIVAR | I30: SIMITI | J30: BARRIO CENTRO SIMITI | K30: REDEBAN | L30: FO-25-1799544 | M30: 45969.403 | N30: 45972.727 | O30: NO | P30: USUARIO | Q30: COMUNICACION | R30: CONEXIONES DE COMERCIO | S30: CB UNO A UNO | T30: CB UNO A UNO | V30: 08/11/2025 SE ESCALA PARA VISITA. LLAMAR ANTES DE VISITAR, CONFIRMAR FALLA Y DATOS | 11/11/2025 SE ESTABLECE CONTACTO VÍA WHATSAPP CON LA SEÑORA SURLEY GUZMÁN 3170767829 YA QUE EN LA ZONA NO FUNCIONA LA RED DE LÍNEA CELULAR, LA CLIENTE NOS COMENTA QUE EL INCONVENIENTE ESTABA EN LA CONEXIÓN DEL CABLE DE RED DEL COMERCIO POR TAL MOTIVO LA CLIENTE LO CAMBIÓ Y SE RESTABLECIÓ EL SERVICIO, COMENTA TAMBIÉN QUE NO HAY NECESIDAD QUE LA VISITEMOS YA QUE EL DATÁFONO ESTÁ OPERATIVO, ADICIONAL ARGUMENTA QUE PARA ENTRAR A LA ZONA ESTÁ BASTANTE PELIGROSO YA QUE ES ZONA ROJA | W30: SOPORTE TELEFONICO | Y30: TIPO V | Z30: TERRESTRE/FLUVIAL | AA30: GONZALEZ ESTUPIÑAN YEISON WALTER ANTONIO | AB30: 0 | AC30: 0 | AD30: 0 | AE30: 0 | AF30: 0 | AG30: 37905 | AH30: 37905
A31: MEDELLIN | B31: NOROCCIDENTE | C31: 0004-0005 | D31: 5761 | E31: 2993579 | F31: 3007076161 | G31: INCIDENTE | H31: ANTIOQUIA | I31: SOPETRAN | J31: BARRIO VEREDA LLANO DE MONTANA | K31: REDEBAN | L31: FO-25-1801309 | M31: 45969.543 | N31: 45971.462 | O31: NO | P31: USUARIO | Q31: MANTENIMIENTO | R31: MANTENIMIENTO GENERAL | S31: CB UNO A UNO | T31: CB UNO A UNO | U31: EJECUTADO | V31: 08/11/2025 SE ESCALA PARA VISITA. LLAMAR ANTES DE VISITAR, CONFIRMAR FALLA Y DATOS | 10/11/2025 SE REALIZA MANTENIMIENTO Y LIMPIEZA AL DATÁFONO YA QUE NO LEÍA NINGUNA TARJETA, LUEGO DEL MATENIMIETO QUEDA FUNCIONAL, PRUEBAS OK | W31: VISITA TECNICA | X31: FA0LZ814 | Y31: TIPO II | Z31: TERRESTRE | AA31: CARDONA MOLINA BROLIN STIVEN | AB31: 1 | AC31: 0 | AD31: 0 | AE31: 0 | AF31: 0 | AG31: 163814 | AH31: 163814
A32: BUCARAMANGA | B32: SANTANDERES | C32: 0004-0008 | D32: 68307 | E32: 2994001 | F32: 3007073607 | G32: INCIDENTE | H32: SANTANDER | I32: GIRON | J32: PTM LA REPUBLICA GIRON SUPERME | K32: REDEBAN | L32: FO-25-1801883 | M32: 45970.385 | N32: 45971.342 | O32: NO | P32: USUARIO | Q32: NO ENCIENDE | R32: CONEXIONES DE COMERCIO | S32: AGREGADOR | T32: COMCARD - PTM | V32: 09/11/2025 SE ESCALA PARA VISITA. LLAMAR ANTES DE VISITAR, CONFIRMAR FALLA Y DATOS | 09/11/2025 EN COMUNICACIÓN CON EL EL SEÑOR JESÚS RUEDA RÍOS AL NÚMERO 3212449499 SE LE INDICA QUE ESTAREMOS REALIZANDO LA VISITA TÉCNICA EL DÍA 10 DE NOVIEMBRE A PARTIR DE LAS 8 AM DEBIDO A QUE EL DÍA DE HOY NO HAY SOPORTE REDEBAN PARA CAMBIO | 10/11/2025 EN COMUNICACIÓN CON EL SEÑOR JESÚS AL MOVIL 3212449499, INDICA QUE NO SE ENCUENTRA EN EL LOCAL YA QUE VA REALIZAR EL. PROCESO DE COMPENSACIÓN, NOS SUMINISTRA EL NÚMERO DE LA SEÑORITA MARGY, E INDICA QUE NO ES NECESARIO REALIZAR EL DESPLAZAMIENTO AL SITIO YA QUE EL EQUIPO EL DÍA DE HOY ESTÁ FUNCIONANDO CORRECTAMENTE. | 10/11/2025 EN COMUNICACIÓN CON LA SEÑORA MARGY AL MOVIL 3227216243, INDICA QUE NO ES NECESARIO EL DESPLAZAMIENTO AL SITIO DEBIDO A QUE EL EQUIPO EL DÍA DE HOY ESTÁ FUNCIONANDO CORRECTAMENTE, SE LE INDICA QUE SE VA REALIZAR EL CIERRE DE LA ORDEN, CLIENTE CONFORME INDICA QUE SI PRESENTE UNA NUEVA NOVEDAD LLAMARA A SOLICITAR NUEVAMENTE LA VISITA. SE LE INDICA A CLIENTE DE REALIZAR UNA PRUEBA PERO INDICA QUE NO ES POSIBLE REALIZAR TRANSACCIONES YA QUE ESTA EN PROCESO DE COMPENSACIÓN A CERO. | W32: SOPORTE TELEFONICO | Y32: TIPO I | Z32: TERRESTRE | AA32: SANTOS GONZALEZ JOHAN FABIAN | AB32: 0 | AC32: 0 | AD32: 0 | AE32: 0 | AF32: 0 | AG32: 37905 | AH32: 37905
A33: MANIZALES | B33: SUROCCIDENTE Y EJE CAFETERO | C33: 0004-0002 | D33: 17867 | E33: 2994976 | F33: 3007062494 | G33: INCIDENTE | H33: CALDAS | I33: VICTORIA | J33: DISTRICOL DONDE LUCY | K33: REDEBAN | L33: FO-25-1804475 | M33: 45971.396 | N33: 45972.709 | O33: NO | P33: USUARIO | Q33: NO ENCIENDE | R33: CONEXIONES DE COMERCIO | S33: AGREGADOR | T33: DISTRICOL | V33: 10/11/2025 SE ESCALA PARA VISITA. LLAMAR ANTES DE VISITAR, CONFIRMAR FALLA Y DATOS | 11/11/2025 SE REALIZA LLAMADA CON USUARIO PARA VALIDAR DAÑO EL CUAL INDICA QUE YA LE ESTA TRABAJANDO CON NORMALIDAD Y NO REQUIERE LA VISITA | W33: SOPORTE TELEFONICO | Y33: TIPO III | Z33: TERRESTRE | AA33: AGUIRRE HENAO RAUL EDUARDO | AB33: 0 | AC33: 0 | AD33: 0 | AE33: 0 | AF33: 0 | AG33: 37905 | AH33: 37905
A34: NEIVA | B34: REMOTAS | C34: 0004-0007 | D34: 41551 | E34: 2996005 | F34: 3007072154 | G34: INCIDENTE | H34: HUILA | I34: PITALITO | J34: DISTRICOL OPTIMERKA SAN RAFAEL | K34: REDEBAN | L34: FO-25-1805098 | M34: 45971.443 | N34: 45972.463 | O34: NO | P34: USUARIO | Q34: COMUNICACION | R34: CONEXIONES DE COMERCIO | S34: AGREGADOR | T34: DISTRICOL | U34: EJECUTADO | V34: 10/11/2025 SE ESCALA PARA VISITA. LLAMAR ANTES DE VISITAR, CONFIRMAR FALLA Y DATOS | 11/11/2025 SE REALIZA VISITA AL PUNTO, SE CORRIGE CON EL INGENIERO ENCARGADO UNA FALLA DE IP'S QUE SE PRESENTA EN EL PUNTO , SE CAMBIAN IP FIJAS PRUEBAS CB OK, CB OPERATIVO. | W34: VISITA TECNICA | X34: NN00N623 | Y34: TIPO III | Z34: TERRESTRE | AA34: DEVIA REINOSO JUAN CARLOS | AB34: 1 | AC34: 0 | AD34: 0 | AE34: 0 | AF34: 0 | AG34: 275728 | AH34: 275728
A35: MEDELLIN | B35: NOROCCIDENTE | C35: 0004-0005 | D35: 5001 | E35: 2999185 | F35: 3007030841 | G35: INCIDENTE | H35: ANTIOQUIA | I35: MEDELLIN | J35: PAPELERIA Y COMERCIALIZADORA | K35: REDEBAN | L35: FO-25-1809738 | M35: 45972.333 | N35: 45972.581 | O35: NO | P35: USUARIO | Q35: CIERRE | R35: COMERCIO NO REALIZA CIERRE | S35: AGREGADOR | T35: COMCARD - PTM | U35: EJECUTADO | V35: 11/11/2025 SE ESCALA PARA VISITA. LLAMAR ANTES DE VISITAR, CONFIRMAR FALLA Y DATOS | 11/11/2025 SE BORRA TRANSACCIONES Y RECONFIGURA SI SE LE EXPLICA AL CLIENTE CIERRE | W35: VISITA TECNICA | X35: BVZZZ224 TRZZZ883 | Y35: TIPO I | Z35: TERRESTRE | AA35: ALVAREZ ARENAS VICTOR HUGO | AB35: 1 | AC35: 0 | AD35: 0 | AE35: 0 | AF35: 0 | AG35: 65960 | AH35: 65960
A36: TUNJA | B36: SANTANDERES | C36: 0004-0008 | D36: 15176 | E36: 3001520 | F36: 3007077395 | G36: INCIDENTE | H36: BOYACA | I36: CHIQUINQUIRA | J36: BARRIO VILLA REPUBLICANA CHIQUINQUIRA | K36: REDEBAN | L36: FO-25-1810798 | M36: 45972.416 | N36: 45972.52 | O36: NO | P36: USUARIO | Q36: COMUNICACION | R36: CANAL DEL COMERCIO | S36: UNO A UNO | T36: UNO A UNO | U36: EJECUTADO | V36: 11/11/2025 SE ESCALA PARA VISITA. LLAMAR ANTES DE VISITAR, CONFIRMAR FALLA Y DATOS | 11/11/2025 SE VISITA PUNTO EVIDENCIANDO QUE LA FALLA REPORTADA ES DEBIDO AL INTERNET DEL COMERCIO ROUTER REPETIDOR DESCONFIGURADO SE REALIZAN CORRECCIONES PRUEBAS OK CLIENTE CONFORME | W36: VISITA TECNICA | X36: SAAZZ158 | Y36: TIPO III | Z36: TERRESTRE | AA36: RODRIGUEZ MURCIA YERSON IVAN | AB36: 1 | AC36: 0 | AD36: 0 | AE36: 0 | AF36: 0 | AG36: 275728 | AH36: 275728
A37: PEREIRA | B37: SUROCCIDENTE Y EJE CAFETERO | C37: 0004-0002 | D37: 66001 | E37: 3003644 | F37: 3007033989 | G37: INCIDENTE | H37: RISARALDA | I37: PEREIRA | J37: PAGAFACIL LA 14 PEREIRA | K37: REDEBAN | L37: FO-25-1813145 | M37: 45972.582 | N37: 45973.386 | O37: NO | P37: USUARIO | Q37: MANTENIMIENTO | R37: MANTENIMIENTO GENERAL | S37: ROBUSTO | T37: PAGAFACIL | U37: EJECUTADO / CANCELADO | V37: 12/11/2025 VISITAMOS COMERCIO PERO NO ES POSIBLE REALIZAR LA ACTIVIDAD YA QUE PASARON 50 MINUTOS Y EL JEFE AÚN NO AUTORIZA EL INGRESO DEL TÉCNICO, LE INDICAMOS A LA SRA MARCELA QUE SE DEBE CANCELAR YA QUE TENEMOS MÁS ACTIVIDADES POR HACER Y CUANDO NOS PUEDAN ATENDER LLAMAR NUEVAMENTE Y SOLICITAR UNA VISITA, NO FIRMAN CONTROL DE VISITA. | W37: VISITA TECNICA | Y37: TIPO I | Z37: TERRESTRE | AA37: ARROYAVE CANO MANUEL GUILLERMO | AB37: 1 | AC37: 0 | AD37: 0 | AE37: 0 | AF37: 0 | AG37: 65960 | AH37: 65960
A38: BUCARAMANGA | B38: SANTANDERES | C38: 0004-0008 | D38: 81001 | E38: 3003898 | F38: 3007079030 | G38: INCIDENTE | H38: ARAUCA | I38: ARAUCA | J38: BARRIO SAN LUCAS ARAUCA 1 | K38: REDEBAN | L38: FO-25-1813134 | M38: 45972.611 | N38: 45981.381 | O38: NO | P38: USUARIO | Q38: COMUNICACION | R38: CONEXIONES DE COMERCIO | S38: CB UNO A UNO | T38: CB UNO A UNO | U38: EJECUTADO | V38: 11/11/2025 SE ESCALA PARA VISITA. LLAMAR ANTES DE VISITAR, CONFIRMAR FALLA Y DATOS | 19/11/2025 SE ESTABLECE COMUNICACIÓN CON EL SEÑOR JUAN BELEÑO AL NÚMERO 3103204648 VIA WHATSAPP SE LE INFORMA QUE EL DIA DE MAÑANA SE ESTARA VISITANDO PARA REALIZAR EL RESPECTIVO MANTENIMIENTO DEBIDO A QUE NO SE PODIA VISITAR ANTES YA QUE NO HABIAN VUELOS DISPONIBLES Y EL ORDEN PÚBLICO EN LA ZONA ESTABA ALTERADO | 20/11/2025 SE HACE PRESENCIA EN COMERCIO SE VALIDA CONEXIONES DE RED LAS CUALES ESTAN OK SE VALIDA LA FALLA CLIENTE INFORMA QUE LOS DIAS QUE SE PRESENTO LA FALLA FUE DEBIDO A UNA CAIDA DE SEÑAL EN EL DEPARTAMENTO Y POR ESO PRESENTABA DICHO INCONVENIENTE SE TOMA REGISTRO FOTOGRÁFICO Y SE PROCEDE A CERRAR ORDEN | W38: VISITA TECNICA | X38: SASZZ605 | Y38: TIPO V | Z38: AEREO | AA38: BARRERA ORTEGA MARLON STWAR | AB38: 1 | AC38: 0 | AD38: 0 | AE38: 0 | AF38: 0 | AG38: 988463 | AH38: 988463
A39: APARTADO | B39: NOROCCIDENTE | C39: 0004-0005 | D39: 5045 | E39: 3007357 | F39: 3007064886 | G39: INCIDENTE | H39: ANTIOQUIA | I39: APARTADO | J39: DISRICOL PREMIUM CELL LA 97 | K39: REDEBAN | L39: FO-25-1816403 | M39: 45973.396 | N39: 45973.599 | O39: NO | P39: USUARIO | Q39: COMUNICACION | R39: CANAL DEL COMERCIO | S39: AGREGADOR | T39: DISTRICOL | U39: EJECUTADO | V39: 12/11/2025 SE ESCALA PARA VISITA. LLAMAR ANTES DE VISITAR, CONFIRMAR FALLA Y DATOS | 12/11/2025 ERROR DE CONEXIÓN SIN TONO, SE REPISA PARAMETRO Y SARAFONO QUEDA FUNCIONADO. | W39: VISITA TECNICA | X39: 5A002508 | Y39: TIPO I | Z39: TERRESTRE | AA39: CASTRO HENAO DANIEL ESTEBAN | AB39: 1 | AC39: 0 | AD39: 0 | AE39: 0 | AF39: 0 | AG39: 65960 | AH39: 65960
A40: MEDELLIN | B40: NOROCCIDENTE | C40: 0004-0005 | D40: 5001 | E40: 3008587 | F40: 3007038794 | G40: INCIDENTE | H40: ANTIOQUIA | I40: MEDELLIN | J40: PTM MED CHQUI | K40: REDEBAN | L40: FO-25-1817489 | M40: 45973.47 | N40: 45974.397 | O40: NO | P40: USUARIO | Q40: LECTOR DE BARRAS | R40: CAPACITACION MANIPULACION DE COMERCIO | S40: AGREGADOR | T40: COMCARD - PTM | V40: 12/11/2025 SE ESCALA PARA VISITA. LLAMAR ANTES DE VISITAR, CONFIRMAR FALLA Y DATOS | 13/11/2025 SE LLAMA AL CLIENTE Y BOS CONENTA QUE HACE 2 DÍAS NO LE FUNCIONABA EL LECTOR DE BARRAS, SE LE INDICA COMO HABITILARLO Y QUEDA OPERATIVO | W40: SOPORTE TELEFONICO | Y40: TIPO I | Z40: TERRESTRE | AA40: CARDONA MOLINA BROLIN STIVEN | AB40: 0 | AC40: 0 | AD40: 0 | AE40: 0 | AF40: 0 | AG40: 37905 | AH40: 37905
A41: YOPAL | B41: REMOTAS | C41: 0004-0007 | D41: 85001 | E41: 3011030 | F41: 3007023134 | G41: INCIDENTE | H41: CASANARE | I41: YOPAL | J41: MULTIPAGAS YOPAL | K41: REDEBAN | L41: FO-25-1819682 | M41: 45973.66 | N41: 45974.432 | O41: NO | P41: USUARIO | Q41: MANTENIMIENTO | R41: MANTENIMIENTO GENERAL | S41: ROBUSTO | T41: MULTIPAGAS | U41: EJECUTADO / CANCELADO | V41: 12/11/2025 SE ESCALA PARA VISITA. LLAMAR ANTES DE VISITAR, CONFIRMAR FALLA Y DATOS | 13/11/2025 SE VISITA COMERCIO, ADRIANA RAMIREZ INDICA QUE LA SOLICITUD ES PARA INSTALAR DOS COMBOS DE DATAFONOS PARA DOS CAJAS NUEVAS. INFORMA NO PRESENTAR FALLAS EN EL SERVICIO. NO SE TOCAN EQUIPOS, NO SE INGRESA A LA CABINA POR TAL MOTIVO NO SE REGISTRA FOTOS DE TIRILLA. | W41: VISITA TECNICA | Y41: TIPO I | Z41: TERRESTRE | AA41: BERNAL ELAICA EDGAR ALEXIS | AB41: 1 | AC41: 0 | AD41: 0 | AE41: 0 | AF41: 0 | AG41: 65960 | AH41: 65960
A42: MEDELLIN | B42: NOROCCIDENTE | C42: 0004-0005 | D42: 5001 | E42: 3011289 | F42: 3007024166 | G42: INCIDENTE | H42: ANTIOQUIA | I42: MEDELLIN | J42: COMCARD MEDELLIN PICACHO 2 | K42: REDEBAN | L42: FO-25-1820019 | M42: 45973.699 | N42: 45974.577 | O42: NO | P42: USUARIO | Q42: MANTENIMIENTO | R42: MANTENIMIENTO GENERAL | S42: AGREGADOR | T42: COMCARD - PTM | U42: EJECUTADO | V42: 12/11/2025 SE ESCALA PARA VISITA. LLAMAR ANTES DE VISITAR, CONFIRMAR FALLA Y DATOS | 13/11/2025 SE LLAMA AL CLIENTE Y NOS INDICA QUE NO ESTÁ EN EL PUNTO, QUE LLEGA A LAS 2PM | 13/11/2025 SE CAMBIA FUENTE DE PODER POR DAÑO, QUEDA OPERATIVO | W42: VISITA TECNICA | X42: ABC3Z066 XPSZZ104 | Y42: TIPO I | Z42: TERRESTRE | AA42: CARDONA MOLINA BROLIN STIVEN | AB42: 1 | AC42: 0 | AD42: 0 | AE42: 0 | AF42: 0 | AG42: 65960 | AH42: 65960
A43: CUCUTA | B43: SANTANDERES | C43: 0004-0008 | D43: 54001 | E43: 3013058 | F43: 3007077828 | G43: INCIDENTE | H43: NORTE DE SANTANDER | I43: CUCUTA | J43: BARRIO EL CENTRO CUCUTA 81 | K43: REDEBAN | L43: FO-25-1821824 | M43: 45974.391 | N43: 45974.718 | O43: NO | P43: USUARIO | Q43: COMUNICACION | R43: CANAL DEL COMERCIO | S43: CB UNO A UNO | T43: CB UNO A UNO | U43: EJECUTADO | V43: 13/11/2025 SE ESCALA PARA VISITA. LLAMAR ANTES DE VISITAR, CONFIRMAR FALLA Y DATOS | 13/11/2025 SE REALIZA VISITA, COMERCIO INFORMA QUE EL SERVICIO SE ENCUENTRA OPERATIVO Y NO REQUIERE LA VISITA TÉCNICA. | W43: VISITA TECNICA | Y43: TIPO I | Z43: TERRESTRE | AA43: PACHECO BUITRAGO JAVIER ALONSO | AB43: 1 | AC43: 0 | AD43: 0 | AE43: 0 | AF43: 0 | AG43: 65960 | AH43: 65960
A44: MANIZALES | B44: SUROCCIDENTE Y EJE CAFETERO | C44: 0004-0002 | D44: 17001 | E44: 3015079 | F44: 3007025300 | G44: INCIDENTE | H44: CALDAS | I44: MANIZALES | J44: ARA0092 CARRERA 21 | K44: REDEBAN | L44: FO-25-1823659 | M44: 45974.525 | N44: 45975.444 | O44: NO | P44: USUARIO | Q44: MANTENIMIENTO | R44: MANTENIMIENTO GENERAL | S44: RETAIL | T44: TIENDAS ARA | V44: 13/11/2025 SE ESCALA PARA VISITA. LLAMAR ANTES DE VISITAR, CONFIRMAR FALLA Y DATOS | 14/11/2025 SE ESCALO ACTIVIDAD A LA RED SERA ATENDIDA POR LA FUERZA COMERCIAL DE REDEBAN | W44: SOPORTE TELEFONICO | Y44: TIPO I | Z44: TERRESTRE | AA44: GARCIA CHAVARRIA TATIANA EDELMIRA | AB44: 0 | AC44: 0 | AD44: 0 | AE44: 0 | AF44: 0 | AG44: 37905 | AH44: 37905
A45: PASTO | B45: SUROCCIDENTE Y EJE CAFETERO | C45: 0004-0003 | D45: 52320 | E45: 3015283 | F45: 3007072485 | G45: INCIDENTE | H45: NARIÑO | I45: GUAITARILLA | J45: DISTRICOL SURTIHO GUAITARILLA | K45: REDEBAN | L45: FO-25-1823489 | M45: 45974.518 | N45: 45975.553 | O45: NO | P45: USUARIO | Q45: COMUNICACION | R45: CONEXIONES DE COMERCIO | S45: AGREGADOR | T45: DISTRICOL | U45: EJECUTADO | V45: 13/11/2025 SE ESCALA PARA VISITA. LLAMAR ANTES DE VISITAR, CONFIRMAR FALLA Y DATOS | 14/11/2025 SE VISITA EL CB PARA REVISAR FALLA DE DATÁFONO POR CONEXIÓN, SE OBSERVA MALA CONEXIÓN EN CABLEADO DEL USUARIO, SE REPISA TAMBIÉN CONFIGURACIÓN DE CONEXIÓN DEL DATÁFONO Y SE HACE PRUEBAS EXITOSAS, EL CB QUEDA OPERATIVO | W45: VISITA TECNICA | X45: TV00L300 | Y45: TIPO II | Z45: TERRESTRE | AA45: GUERRERO RAMIREZ OSCAR DARIO | AB45: 1 | AC45: 0 | AD45: 0 | AE45: 0 | AF45: 0 | AG45: 163814 | AH45: 163814
A46: BOGOTA | B46: CUNDINAMARCA | C46: 0004-0004 | D46: 11001 | E46: 3017565 | F46: 3007072338 | G46: INCIDENTE | H46: CUNDINAMARCA | I46: BOGOTA | J46: PTM MALU PET | K46: REDEBAN | L46: FO-25-1825749 | M46: 45975.333 | N46: 45975.476 | O46: NO | P46: USUARIO | Q46: COMUNICACION | R46: CANAL DEL COMERCIO | S46: AGREGADOR | T46: COMCARD - PTM | V46: 13/11/2025 SE ESCALA PARA VISITA. LLAMAR ANTES DE VISITAR, CONFIRMAR FALLA Y DATOS | 14/11/2025 NOS CONTACTAMOS CON LA SEÑORA DIANA CANEDA AL NÚMERO 3208762580 PARA CONFIRMAR VISITA PERO CLIENTE MANIFIESTA QUE EL L ERROR ES DEL CANAL DE COMUNICACIÓN O PROVEEDOR DE INTERNET DE SU LOCAL POR TANTO SE CIERRA ORDEN | W46: SOPORTE TELEFONICO | Y46: TIPO I | Z46: TERRESTRE | AA46: SOTO LONDOÑO FREDY ALEXANDER | AB46: 0 | AC46: 0 | AD46: 0 | AE46: 0 | AF46: 0 | AG46: 37905 | AH46: 37905
A47: YOPAL | B47: REMOTAS | C47: 0004-0007 | D47: 85010 | E47: 3020080 | F47: 3007073662 | G47: INCIDENTE | H47: CASANARE | I47: AGUAZUL | J47: DISTRICOL BABY LEA KIDS | K47: REDEBAN | L47: FO-25-1828773 | M47: 45975.492 | N47: 45976.399 | O47: NO | P47: USUARIO | Q47: COMUNICACION | R47: CONEXIONES DE COMERCIO | S47: AGREGADOR | T47: DISTRICOL | V47: 14/11/2025 SE ESCALA PARA VISITA. LLAMAR ANTES DE VISITAR, CONFIRMAR FALLA Y DATOS | 15/11/2025 EN COMUNICACIÓN CON LA SEÑORA LENDRA MOLANO AL NUMERO 3115522019, INFORMA QUE CAMBIO EL CABLE DE RED Y YA SE ENCUENTRA OPERATIVO EL SERVICIO. INDICA NO REQUIERE LA VISITA | W47: SOPORTE TELEFONICO | Y47: TIPO II | Z47: TERRESTRE | AA47: BERNAL ELAICA EDGAR ALEXIS | AB47: 0 | AC47: 0 | AD47: 0 | AE47: 0 | AF47: 0 | AG47: 37905 | AH47: 37905
A48: BUCARAMANGA | B48: SANTANDERES | C48: 0004-0008 | D48: 68307 | E48: 3020484 | F48: 3007032269 | G48: INCIDENTE | H48: SANTANDER | I48: GIRON | J48: COMCARD GIRON CHEPITA | K48: REDEBAN | L48: FO-25-1829112 | M48: 45975.556 | N48: 45976.408 | O48: NO | P48: USUARIO | Q48: CIERRE | R48: COMERCIO NO REALIZA CIERRE | S48: AGREGADOR | T48: COMCARD - PTM | V48: 14/11/2025 SE ESCALA PARA VISITA. LLAMAR ANTES DE VISITAR, CONFIRMAR FALLA Y DATOS | 15/11/2025 SE ESTABLECE CONTACTO TELEFÓNICO Y VIA WHATSAPP CON LA SEÑORA JOSEFINA HERNANDEZ BELTRÁN AL NÚMERO 3117113057 QUIEN NOS SOLICITA QUE REALICEMOS LA VISITA EL DIA MARTES YA QUE NO SE ENCUENTRA EN EL LOCAL A LO CUAL SE LE INDICA QUE NO ES POSIBLE REALIZAR REAGENDAMIENTOS Y QUE SE DEBE VOLVER A COMUNICAR UNA VEZ SE ENCUENTRE EN EL ESTABLECIMIENTO PARA PODER REALIZAR EL SERVICIO TÉCNICO A LO CUAL INDICA QUE ELLA LE HABÍA INDICADO A LA ASESORA QUE NO IBA A ESTAR DURANTE EL FIN DE SEMANA QUE ELLA SE VOLVERA A COMUNICAR | W48: SOPORTE TELEFONICO | Y48: TIPO I | Z48: TERRESTRE | AA48: REYES RAMIREZ DIEGO ALEXANDER | AB48: 0 | AC48: 0 | AD48: 0 | AE48: 0 | AF48: 0 | AG48: 37905 | AH48: 37905
A49: MEDELLIN | B49: NOROCCIDENTE | C49: 0004-0005 | D49: 5088 | E49: 3021101 | F49: 3007044415 | G49: INCIDENTE | H49: ANTIOQUIA | I49: BELLO | J49: DISTRICOL VARGAS PAN | K49: REDEBAN | L49: FO-25-1829715 | M49: 45975.6 | N49: 45976.614 | O49: NO | P49: USUARIO | Q49: USUARIOS | R49: MALA MANIPULACION POS | S49: AGREGADOR | T49: DISTRICOL | V49: 14/11/2025 SE ESCALA PARA VISITA. LLAMAR ANTES DE VISITAR, CONFIRMAR FALLA Y DATOS | 15/11/2025 SE REALIZA GESTIÓN TELEFÓNICA CON EL SEÑOR HERNÁN VARGAS, USUARIO INFORMA QUE YA EL SERVICIO SE REESTABLECIÓ, YA NO ES NECESARIO LA VISITA | W49: SOPORTE TELEFONICO | Y49: TIPO I | Z49: TERRESTRE | AA49: BARRIENTOS HERNANDEZ CRISTIAN HORACIO | AB49: 0 | AC49: 0 | AD49: 0 | AE49: 0 | AF49: 0 | AG49: 37905 | AH49: 37905
A50: BOGOTA | B50: CUNDINAMARCA | C50: 0004-0004 | D50: 11001 | E50: 3022984 | F50: 3007073655 | G50: INCIDENTE | H50: CUNDINAMARCA | I50: BOGOTA | J50: DISTRICOL JOHEPLAST | K50: REDEBAN | L50: FO-25-1832719 | M50: 45976.495 | N50: 45979.494 | O50: NO | P50: USUARIO | Q50: CIERRE | R50: COMERCIO NO REALIZA CIERRE | S50: AGREGADOR | T50: DISTRICOL | U50: EJECUTADO | V50: 15/11/2025 SE ESCALA PARA VISITA. LLAMAR ANTES DE VISITAR, CONFIRMAR FALLA Y DATOS | 16/11/2025 SE REALIZAN VARIOS INTENTOS DE CONTACTO AL NÚMERO 3209976554 CON LA SEÑORA LAURA QUIEN DICE QUE LOS DOMINGOS Y FESTIVOS NO TIENEN QUE DEJO MUY BIEN DICHO CUANDO LLAMO EL HORARIO DE ATENCIÓN PIDE QUE SE ATIENDA EL MARTES EN EL HORARIO 6AM A 12 M DICE QUE NUNCA LE HAN INSTALADO LECTOR DE BARRAS DE DEBE CONFIRMAR INVENTARIO CON REDEBAN Y LOS FINES DE SEMANA Y FESTIVOS NO TENEMOS ESTE SOPORTE DE ATENDERÁ EL SIGUIENTE DÍA HÁBIL | 18/11/2025 DURANTE LA VISITA TECNICA ENCONTRAMOS QUE EL DATÁFONO NO LE PERMITE REALIZAR EL CIERRE POR ACUMULACIÓN DE TRANSACCIONES SE REALIZA BORRADO DE TRANSACCIONES ADICIONAL SE REALIZAN TRANSACCIONES DE PRUEBA Y SE BRINDA INFORMACIÓN DEL CORRECTO CIERRE QUEDANDO OKAY LA FUNCIONALIDAD DE CIERRE SIN NOVEDAD EN EL INCIDENTE A CONFORMIDAD CORRESPONSAL BANCARIO | W50: VISITA TECNICA | X50: EF02Z332 | Y50: TIPO I | Z50: TERRESTRE | AA50: GALEANO SORIANO JUAN DAVID | AB50: 1 | AC50: 0 | AD50: 0 | AE50: 0 | AF50: 0 | AG50: 65960 | AH50: 65960
A51: MEDELLIN | B51: NOROCCIDENTE | C51: 0004-0005 | D51: 5001 | E51: 3023198 | F51: 3007024166 | G51: INCIDENTE | H51: ANTIOQUIA | I51: MEDELLIN | J51: COMCARD MEDELLIN PICACHO 2 | K51: REDEBAN | L51: FO-25-1834319 | M51: 45976.653 | N51: 45979.542 | O51: NO | P51: USUARIO | Q51: MANTENIMIENTO | R51: MANTENIMIENTO GENERAL | S51: AGREGADOR | T51: COMCARD - PTM | V51: 16/11/2025 SE ESCALA PARA VISITA. LLAMAR ANTES DE VISITAR, CONFIRMAR FALLA Y DATOS | 16/11/2025 COMERCIO INDICA QUE NO ABRE NI DOMINGOS NI FESTIVOS, SE APLAZA VISITA | 18/11/2025 SE LLAMA AL CLIENTE Y NOS COMENTA QUE LOS REINICIOS SON POR FALTA DE BASE DE DATÁFONO, SE LE INDICA SOLICITAR LA BASE PARA QUE EL CABLEADO NO SE LE DESCONECTE, EL PUNTO SE HABÍA VISITADO ANTERIORMENTE Y SE CAMBIO TODO EL CABLEADO Y FUENTE DE PODER | W51: SOPORTE TELEFONICO | Y51: TIPO I | Z51: TERRESTRE | AA51: CARDONA MOLINA BROLIN STIVEN | AB51: 0 | AC51: 0 | AD51: 0 | AE51: 0 | AF51: 0 | AG51: 37905 | AH51: 37905
A52: IBAGUE | B52: REMOTAS | C52: 0004-0007 | D52: 73870 | E52: 3023373 | F52: 3007041301 | G52: INCIDENTE | H52: TOLIMA | I52: VILLAHERMOSA | J52: BARRIO CENTRO VILLAHERMOSA 2 | K52: REDEBAN | L52: FO-25-1834284 | M52: 45977.333 | N52: 45987.373 | O52: SI | P52: HARDWARE | Q52: CABLEADO | R52: CABLE MAGICBOX AVERIADO | S52: CB UNO A UNO | T52: CB UNO A UNO | U52: EJECUTADO | V52: 16/11/2025 SE ESCALA PARA VISITA. LLAMAR ANTES DE VISITAR, CONFIRMAR FALLA Y DATOS | 26/11/2025 SE CAMBIA CABLE MAGIC BOX, CABLE, FUENTE DE PODER Y CABLE DE RED POR DETERIORO. SE HACEN LAS PRUEBAS DE TRANSACCIONES TODO OK | W52: VISITA TECNICA | X52: AB0QZ076 II00B770 | Y52: TIPO III | Z52: TERRESTRE | AA52: VARGAS HERRERA JHON JAIRO | AB52: 0 | AC52: 10 | AD52: 0 | AE52: 0 | AF52: 0 | AG52: 16234.695 | AH52: 162350
A53: MEDELLIN | B53: NOROCCIDENTE | C53: 0004-0005 | D53: 5129 | E53: 3023447 | F53: 3007081006 | G53: INCIDENTE | H53: ANTIOQUIA | I53: CALDAS | J53: PTM CALDAS BOTANICASALOMON | K53: REDEBAN | L53: FO-25-1834660 | M53: 45977.441 | N53: 45978.708 | O53: NO | P53: USUARIO | Q53: COMUNICACION | R53: CANAL DEL COMERCIO | S53: AGREGADOR | T53: COMCARD - PTM | V53: 16/11/2025 SE ESCALA PARA VISITA. LLAMAR ANTES DE VISITAR, CONFIRMAR FALLA Y DATOS | 17/11/2025 NO HAY PERSONA DISPONIBLE EL LUNES FESTIVO, SE REPROGRAMA PARA DIA | 17/11/2025 17/11 SE HABLA CON SEÑORA LUISA Y NOS INFORMA QUE EL PROBLEMA DE CONEXION SE ARREGLÓ EL MISMO DÍA. CB ESTA OPERATIVO, SE CIERRA INCIDENTE. | W53: SOPORTE TELEFONICO | Y53: TIPO I | Z53: TERRESTRE | AA53: QUINTERO SANCHEZ JUAN SEBASTIAN | AB53: 0 | AC53: 0 | AD53: 0 | AE53: 0 | AF53: 0 | AG53: 37905 | AH53: 37905
A54: APARTADO | B54: NOROCCIDENTE | C54: 0004-0005 | D54: 5837 | E54: 3024180 | F54: 3007080844 | G54: INCIDENTE | H54: ANTIOQUIA | I54: TURBO | J54: PTM TURBO MICELANIA Y PAPELERI | K54: REDEBAN | L54: FO-25-1836443 | M54: 45978.477 | N54: 45979.462 | O54: NO | P54: USUARIO | Q54: COMUNICACION | R54: CANAL DEL COMERCIO | S54: AGREGADOR | T54: COMCARD - PTM | U54: EJECUTADO | V54: 17/11/2025 SE ESCALA PARA VISITA. LLAMAR ANTES DE VISITAR, CONFIRMAR FALLA Y DATOS | 18/11/2025 SE LLEGA A SITIO Y DATAFONO SE ENCUENTRA OPERATIVO, SE CAPACITA AL CLIENTE EN MANIPULACIÓN DEL DATAFONO. | W54: VISITA TECNICA | X54: FHZZZ003 | Y54: TIPO II | Z54: TERRESTRE | AA54: CASTRO HENAO DANIEL ESTEBAN | AB54: 1 | AC54: 0 | AD54: 0 | AE54: 0 | AF54: 0 | AG54: 163814 | AH54: 163814
A55: YOPAL | B55: REMOTAS | C55: 0004-0007 | D55: 85010 | E55: 3025380 | F55: 3007032217 | G55: INCIDENTE | H55: CASANARE | I55: AGUAZUL | J55: DISTRICOL SURTIDORA LA 15 | K55: REDEBAN | L55: FO-25-1838039 | M55: 45979.353 | N55: 45979.572 | O55: NO | P55: USUARIO | Q55: COMUNICACION | R55: CONEXIONES DE COMERCIO | S55: AGREGADOR | T55: DISTRICOL | V55: 18/11/2025 SE ESCALA PARA VISITA. LLAMAR ANTES DE VISITAR, CONFIRMAR FALLA Y DATOS | 18/11/2025 EN COMUNICACIÓN CON LA SEÑORA SOCORRO GONZALEZ AL NUMERO 3125841417 INDICA NO REQUIERE LA VISITA, YA CAMBIO LA EXTENSIÓN DE CORRIENTE Q ALIMENTA AL DATAFONO. INFORMA OPERATIVO EL SERVICIO | W55: SOPORTE TELEFONICO | Y55: TIPO II | Z55: TERRESTRE | AA55: BERNAL ELAICA EDGAR ALEXIS | AB55: 0 | AC55: 0 | AD55: 0 | AE55: 0 | AF55: 0 | AG55: 37905 | AH55: 37905
A56: BARRANQUILLA | B56: COSTA | C56: 0004-0001 | D56: 8001 | E56: 3027532 | F56: 3007073676 | G56: INCIDENTE | H56: ATLANTICO | I56: BARRANQUILLA | J56: PTM BARRANQUILLA PUNTO SERVIS | K56: REDEBAN | L56: FO-25-1839348 | M56: 45979.433 | N56: 45979.501 | O56: NO | P56: USUARIO | Q56: COMUNICACION | R56: CANAL DEL COMERCIO | S56: AGREGADOR | T56: COMCARD - PTM | V56: 18/11/2025 SE ESCALA PARA VISITA. LLAMAR ANTES DE VISITAR, CONFIRMAR FALLA Y DATOS | 18/11/2025 EN COMUNICACIÓN VIA WASHAP CON LA SEÑORA LEIDY AL NUMERO 3218288241, ME INFORMA QUE RECIENTEMENTE EL PROVEDOR DE INTERNET LE CAMBIÓ EL MÓDEM Y HA TENIDO PROBLEMAS DE CONEXIÓN POR CABLE, QUE POR WIFI LE FUNCIONA TODO BIEN, QUE FALLA ES CUANDO CONECTAN ALGÚN DISPOSITIVO POR CABLE, SE LE INDICA QUE VALIDE CON SU PROVEDOR DE INTERNET ESA FALLA Y HAGA PRUEBAS, Y SI PERDISTE LA FALLA DESPUÉS DE VALIDAR QUE LOS PUERTOS ESTÁN OK, QUE VUELVA A GENERAR UNA VISITA | W56: SOPORTE TELEFONICO | Y56: TIPO I | Z56: TERRESTRE | AA56: DE AVILA SIADES ALBERTO ENRIQUE | AB56: 0 | AC56: 0 | AD56: 0 | AE56: 0 | AF56: 0 | AG56: 37905 | AH56: 37905
A57: VILLAVICENCIO | B57: REMOTAS | C57: 0004-0007 | D57: 50001 | E57: 3028784 | F57: 3007023433 | G57: INCIDENTE | H57: META | I57: VILLAVICENCIO | J57: BARRIO SANANTONIO VILLAVICENCI | K57: REDEBAN | L57: FO-25-1840958 | M57: 45979.519 | N57: 45979.721 | O57: NO | P57: USUARIO | Q57: NO ENCIENDE | R57: CONEXIONES DE COMERCIO | S57: CB UNO A UNO | T57: CB UNO A UNO | U57: EJECUTADO | V57: 18/11/2025 SE ESCALA PARA VISITA. LLAMAR ANTES DE VISITAR, CONFIRMAR FALLA Y DATOS | 18/11/2025 SE REALIZA REVISIÓN DE DATÁFONO NO SE ENCUENTRA NOVEDAD, AL REVISAR EL CABLEADO SE ENCUENTRA QUE LA FUENTE DE PODER NO CORRESPONDE AL DATÁFONO, LO QUE GENERA REINICIO AL REALIZAR IMPRESIÓN EN EL DATÁFONO, SE REALIZA BORRADO HE INSTALACIÓN DE SISTEMA OPERATIVO Y VERSIÓN CON PARCHE, SE VALIDA TERMINAL CORRECTA, SE REALIZA AJUSTE DE CABLE DE PODER CORRECTO, PRUEBAS OK. | W57: VISITA TECNICA | X57: TR000995 | Y57: TIPO I | Z57: TERRESTRE | AA57: MURCIA HERNANDEZ HARVEY IGNACIO | AB57: 1 | AC57: 0 | AD57: 0 | AE57: 0 | AF57: 0 | AG57: 65960 | AH57: 65960
A58: APARTADO | B58: NOROCCIDENTE | C58: 0004-0005 | D58: 5490 | E58: 3034523 | F58: 3007069295 | G58: INCIDENTE | H58: ANTIOQUIA | I58: NECOCLI | J58: BARRIO MARIA ANTONIA NECOCLI | K58: REDEBAN | L58: FO-25-1846174 | M58: 45980.461 | N58: 45981.51 | O58: NO | P58: USUARIO | Q58: COMUNICACION | R58: CANAL DEL COMERCIO | S58: CB UNO A UNO | T58: CB UNO A UNO | U58: EJECUTADO | V58: 19/11/2025 SE ESCALA PARA VISITA. LLAMAR ANTES DE VISITAR, CONFIRMAR FALLA Y DATOS | 20/11/2025 INTERNET DE CLIENTE NONFUNCIONABA BIEN, CABLE QUEDA BIEN CONECTADO Y DATAFONO OPERATIVO. | W58: VISITA TECNICA | X58: 9L6ZZ629 | Y58: TIPO II | Z58: TERRESTRE | AA58: CASTRO HENAO DANIEL ESTEBAN | AB58: 1 | AC58: 0 | AD58: 0 | AE58: 0 | AF58: 0 | AG58: 163814 | AH58: 163814
A59: IBAGUE | B59: REMOTAS | C59: 0004-0007 | D59: 73671 | E59: 3036530 | F59: 3007068404 | G59: INCIDENTE | H59: TOLIMA | I59: SALDAÑA | J59: EL JARDIN SALDANA | K59: REDEBAN | L59: FO-25-1848342 | M59: 45980.642 | N59: 45982.381 | O59: NO | P59: USUARIO | Q59: COMUNICACION | R59: CANAL DEL COMERCIO | S59: CB UNO A UNO | T59: CB UNO A UNO | V59: 19/11/2025 SE ESCALA PARA VISITA. LLAMAR ANTES DE VISITAR, CONFIRMAR FALLA Y DATOS | 21/11/2025 SE COMUNICA AL NÚMERO 3112717579, LA SEÑORA CLAUDIA LOZANO INDICA HABER PRESENTADO ERROR EN CONEXIÓN AL PARECER POR INCONVENIENTES CON EL PROVEEDOR DE INTERNET. INDICA QUE EL SERVICIO SE ENCUENTRA OPERATIVO. | W59: SOPORTE TELEFONICO | Y59: TIPO II | Z59: TERRESTRE | AA59: BARRAGAN TAFUR EDWIN ESTEBAN | AB59: 0 | AC59: 0 | AD59: 0 | AE59: 0 | AF59: 0 | AG59: 37905 | AH59: 37905
A60: BUCARAMANGA | B60: SANTANDERES | C60: 0004-0008 | D60: 68081 | E60: 3037794 | F60: 3007075278 | G60: INCIDENTE | H60: SANTANDER | I60: BARRANCABERMEJA | J60: PTM BARRANCABERMEJA AUTOSERVIC | K60: REDEBAN | L60: FO-25-1850288 | M60: 45981.333 | N60: 45981.626 | O60: NO | P60: USUARIO | Q60: CIERRE | R60: COMERCIO NO REALIZA CIERRE | S60: AGREGADOR | T60: COMCARD - PTM | V60: 20/11/2025 SE ESCALA PARA VISITA. LLAMAR ANTES DE VISITAR, CONFIRMAR FALLA Y DATOS | 20/11/2025 SE ESTABLECE CONTACTO TELEFÓNICO Y VIA WHATSAPP AL NÚMERO 321 3581957 CON EL USUARIO JOHAN SEBASTIAN ZARATE GARCIA QUIEN NOS INDICA QUE LA FALLA FUE MOMENTANEA PERO QUE YA LOGRO REALIZAR CIERRES Y SACAR DUPLICADOS CON NORMALIDAD INDICA NO REQUERIR EL SERVICIO TÉCNICO | W60: SOPORTE TELEFONICO | Y60: TIPO III | Z60: TERRESTRE | AA60: REYES RAMIREZ DIEGO ALEXANDER | AB60: 0 | AC60: 0 | AD60: 0 | AE60: 0 | AF60: 0 | AG60: 37905 | AH60: 37905
A61: MEDELLIN | B61: NOROCCIDENTE | C61: 0004-0005 | D61: 27245 | E61: 3037947 | F61: 3007029015 | G61: INCIDENTE | H61: CHOCO | I61: EL CARMEN DE ATRATO | J61: BARRIO EL CORAZON DE MARIA EL | K61: REDEBAN | L61: FO-25-1850299 | M61: 45981.333 | N61: 45982.39 | O61: NO | P61: USUARIO | Q61: COMUNICACION | R61: CANAL DEL COMERCIO | S61: CB UNO A UNO | T61: CB UNO A UNO | U61: EJECUTADO | V61: 20/11/2025 SE ESCALA PARA VISITA. LLAMAR ANTES DE VISITAR, CONFIRMAR FALLA Y DATOS | 21/11/2025 SE LLEGA SE REVISA ENSORTIJADO FUENTE PUERTOS CABLEADOS EN GENERAL TODO EN BUEN ESTADO CLIENTE MANIFIESTA Q NO ES DE SIEMPRE Y SE QUEDA CONECTANDO PROCESANDO SE LE EXPLICA QUE ESO ES UN PROBLEMA DE CANAL SE LE REALIZA MANTENIMIENTO AL EQUIPO TODO QUEDA OK | W61: VISITA TECNICA | X61: BBBBE977 | Y61: TIPO IV | Z61: TERRESTRE | AA61: ALVAREZ ARENAS VICTOR HUGO | AB61: 1 | AC61: 0 | AD61: 0 | AE61: 0 | AF61: 0 | AG61: 479590 | AH61: 479590
A62: MEDELLIN | B62: NOROCCIDENTE | C62: 0004-0005 | D62: 5360 | E62: 3037950 | F62: 3007019571 | G62: INCIDENTE | H62: ANTIOQUIA | I62: ITAGUI | J62: COMCARD ITAGUI TODOLINUX | K62: REDEBAN | L62: FO-25-1850290 | M62: 45981.333 | N62: 45982.344 | O62: NO | P62: USUARIO | Q62: USUARIOS | R62: CREACION DE USUARIOS | S62: AGREGADOR | T62: COMCARD - PTM | V62: 20/11/2025 SE ESCALA PARA VISITA. LLAMAR ANTES DE VISITAR, CONFIRMAR FALLA Y DATOS | 21/11/2025 SE REALIZÓ GESTIÓN TELEFÓNICA SE HABLÓ CON EL SEÑOR ANTONIO NOS INDICA QUE EL DATAFONO SE ENCUENTRA TOTALMENTE OPERATIVO SE PROCEDE A CERRAR CASO | W62: SOPORTE TELEFONICO | Y62: TIPO I | Z62: TERRESTRE | AA62: CASTAÑEDA PALACIO CARLOS FELIPE | AB62: 0 | AC62: 0 | AD62: 0 | AE62: 0 | AF62: 0 | AG62: 37905 | AH62: 37905
A63: MEDELLIN | B63: NOROCCIDENTE | C63: 0004-0005 | D63: 5360 | E63: 3042668 | F63: 3007015190 | G63: INCIDENTE | H63: ANTIOQUIA | I63: ITAGUI | J63: BARRIO CALATRAVA ITAGUI | K63: REDEBAN | L63: FO-25-1853730 | M63: 45981.657 | N63: 45982.432 | O63: NO | P63: USUARIO | Q63: LECTOR DE TARJETAS | R63: OBSTRUCCION DEL LECTOR | S63: CB UNO A UNO | T63: CB UNO A UNO | U63: EJECUTADO | V63: 20/11/2025 SE ESCALA PARA VISITA. LLAMAR ANTES DE VISITAR, CONFIRMAR FALLA Y DATOS | 21/11/2025 SE REALIZÓ LIMPIEZA DE LECTOR CHIP | W63: VISITA TECNICA | X63: TR0KZ478 | Y63: TIPO I | Z63: TERRESTRE | AA63: CASTAÑEDA PALACIO CARLOS FELIPE | AB63: 1 | AC63: 0 | AD63: 0 | AE63: 0 | AF63: 0 | AG63: 65960 | AH63: 65960
A64: PASTO | B64: SUROCCIDENTE Y EJE CAFETERO | C64: 0004-0003 | D64: 52001 | E64: 3042728 | F64: 3007058607 | G64: INCIDENTE | H64: NARIÑO | I64: PASTO | J64: PTM PASTO PAPELERIA CLIPS PA | K64: REDEBAN | L64: FO-25-1853741 | M64: 45981.65 | N64: 45982.452 | O64: NO | P64: USUARIO | Q64: MANTENIMIENTO | R64: MANTENIMIENTO GENERAL | S64: AGREGADOR | T64: COMCARD - PTM | U64: EJECUTADO | V64: 20/11/2025 SE ESCALA PARA VISITA. LLAMAR ANTES DE VISITAR, CONFIRMAR FALLA Y DATOS | 21/11/2025 SE VISITA EL CB PARA REVISAR FALLA DE DATÁFONO SE ENCUENTRA CON LA HORA DESACTUALIZADA, SE REALIZA MANTENIMIENTO AL DATÁFONO, SE BORRA SISTEMA OPERATIVO Y VERSIÓN, SE REINSTALA Y SE HACE PRUEBAS OK, CB OPERATIVO | W64: VISITA TECNICA | X64: IVZZZ922 IWZZZ034 | Y64: TIPO I | Z64: TERRESTRE | AA64: GUERRERO RAMIREZ OSCAR DARIO | AB64: 1 | AC64: 0 | AD64: 0 | AE64: 0 | AF64: 0 | AG64: 65960 | AH64: 65960
A65: SANTA MARTA | B65: COSTA | C65: 0004-0001 | D65: 47245 | E65: 3043463 | F65: 3007036421 | G65: INCIDENTE | H65: MAGDALENA | I65: EL BANCO | J65: PAGAFACIL EL BANCO | K65: REDEBAN | L65: FO-25-1856023 | M65: 45982.333 | N65: 45982.498 | O65: NO | P65: USUARIO | Q65: CIERRE | R65: COMERCIO NO REALIZA CIERRE | S65: ROBUSTO | T65: PAGAFACIL | V65: 21/11/2025 SE ESCALA PARA VISITA. LLAMAR ANTES DE VISITAR, CONFIRMAR FALLA Y DATOS | 21/11/2025 SE LLAMA A LA SEÑORA ADRIANA HINCAPIÉ Y ESTA MANIFIESTA QUE DIAS ANTERIORES NO DEJABA HACER EL CIERRE PORQUE LE SALIA CLAVE INCORRECTA, EL DIA DE HOY INTENTO NUEVAMENTE Y YA LE DEJO REALIZAR EL CIERRE, EL SERVICIO SE ENCUENTRA OPERANDO SIN NINGUNA NOVEDAD | W65: SOPORTE TELEFONICO | Y65: TIPO IV | Z65: TERRESTRE | AA65: MONTES DIAZ JOHN FRED | AB65: 0 | AC65: 0 | AD65: 0 | AE65: 0 | AF65: 0 | AG65: 37905 | AH65: 37905
A66: MEDELLIN | B66: NOROCCIDENTE | C66: 0004-0005 | D66: 5001 | E66: 3043479 | F66: 3007050085 | G66: INCIDENTE | H66: ANTIOQUIA | I66: MEDELLIN | J66: PTM MEDELLIN VARIEDADES MI TE | K66: REDEBAN | L66: FO-25-1856010 | M66: 45982.333 | N66: 45982.399 | O66: NO | P66: USUARIO | Q66: LECTOR DE TARJETAS | R66: OBSTRUCCION DEL LECTOR | S66: AGREGADOR | T66: COMCARD - PTM | U66: EJECUTADO | V66: 21/11/2025 SE REALIZÓ LIMPIEZA DE LECTOR CHIP | W66: VISITA TECNICA | X66: II00T976 TRZZZ953 | Y66: TIPO I | Z66: TERRESTRE | AA66: CASTAÑEDA PALACIO CARLOS FELIPE | AB66: 1 | AC66: 0 | AD66: 0 | AE66: 0 | AF66: 0 | AG66: 65960 | AH66: 65960
A67: PASTO | B67: SUROCCIDENTE Y EJE CAFETERO | C67: 0004-0003 | D67: 52683 | E67: 3044963 | F67: 3007052690 | G67: INCIDENTE | H67: NARIÑO | I67: SANDONA | J67: PTM DROGUERIA EL INGENIO | K67: REDEBAN | L67: FO-25-1857478 | M67: 45982.415 | N67: 45985.547 | O67: NO | P67: USUARIO | Q67: COMUNICACION | R67: CONEXIONES DE COMERCIO | S67: AGREGADOR | T67: COMCARD - PTM | U67: EJECUTADO | V67: 21/11/2025 SE ESCALA PARA VISITA. LLAMAR ANTES DE VISITAR, CONFIRMAR FALLA Y DATOS | 22/11/2025 SE HABLA CON EL CLIENTE PERO INDICA QUE TAMBIEN PRESENTAN PROBLEMAS CON EL INTERNET Y ESTAN EN ESPERA DE LA VISITA EL DIA DE HOY PARA VALIDAR EL CANAL, SE VALIDARA EL LUNES PARA VERIFICAR SI EL SERVICIO YA ESTA ACTIVO Y SI SE REQUIERE VISITA PARA VERIFICAR EL DATAFONO. | 24/11/2025 SE ENCUENTRA DATÁFONO SIN CONEXIÓN SE REVISA CONEXIONES DEL COMERCIO Y SE HACE MANTENIMIENTO Y SE LOGRA CONEXIÓN EXITOSA CONFIGURACIÓN OK PARÁMETROS OK Y SE REALIZAN PRUEBAS EXITOSAS DE TRANSACCIONES | W67: VISITA TECNICA | X67: TR0FZ909 | Y67: TIPO II | Z67: TERRESTRE | AA67: PAZ MARTINEZ RICHARD HUMBERTO | AB67: 1 | AC67: 0 | AD67: 0 | AE67: 0 | AF67: 0 | AG67: 163814 | AH67: 163814
A68: SINCELEJO | B68: COSTA | C68: 0004-0001 | D68: 70001 | E68: 3045706 | F68: 3007030117 | G68: INCIDENTE | H68: SUCRE | I68: SINCELEJO | J68: BARRIO VERACRUZ SINCELEJO | K68: REDEBAN | L68: FO-25-1857930 | M68: 45982.452 | N68: 45982.634 | O68: NO | P68: USUARIO | Q68: MANTENIMIENTO | R68: MANTENIMIENTO GENERAL | S68: CB UNO A UNO | T68: CB UNO A UNO | U68: EJECUTADO | V68: 21/11/2025 SE ESCALA PARA VISITA. LLAMAR ANTES DE VISITAR, CONFIRMAR FALLA Y DATOS | 21/11/2025 SE VISITA SITIO SE VERIFICA INFORMACIÓN, SE REALIZA PRIMEROS AUXILIOS, SE DESCARTA CABLEADO, ROLLOS; SE IDENTIFICA BATERIA VOLTAJE BAJO, SE CARGA BATERIA, EL CB SE ENCUENTRA FUNCIONANDO NORMALMENTE. | W68: VISITA TECNICA | X68: BL0AZ045 | Y68: TIPO I | Z68: TERRESTRE | AA68: SANTOS GUZMAN CHRISTIAN FELIPE | AB68: 1 | AC68: 0 | AD68: 0 | AE68: 0 | AF68: 0 | AG68: 65960 | AH68: 65960
A69: YOPAL | B69: REMOTAS | C69: 0004-0007 | D69: 85001 | E69: 3048175 | F69: 3007075008 | G69: INCIDENTE | H69: CASANARE | I69: YOPAL | J69: DISTRICOL CACHARRERÍA Y PAPELE | K69: REDEBAN | L69: FO-25-1861206 | M69: 45982.688 | N69: 45983.438 | O69: NO | P69: USUARIO | Q69: MANTENIMIENTO | R69: MANTENIMIENTO GENERAL | S69: AGREGADOR | T69: DISTRICOL | V69: 21/11/2025 SE ESCALA PARA VISITA. LLAMAR ANTES DE VISITAR, CONFIRMAR FALLA Y DATOS | 22/11/2025 EN COMUNICACIÓN CON LA SEÑORA LILIANA CACERES AL NUMERO 3107643994, SE LE INDICA EL AJUSTE DE LA TAPA DE IMPRESION Y EL INGRESO DEL ROLLO Y QUE AL MOMENTO DE IMPRIMIR NO DEBE TENER OBJETOS QUE NO PERMITA EL PROCESO. INFORMA OPERATIVO EL SERVICIO | W69: SOPORTE TELEFONICO | Y69: TIPO I | Z69: TERRESTRE | AA69: BERNAL ELAICA EDGAR ALEXIS | AB69: 0 | AC69: 0 | AD69: 0 | AE69: 0 | AF69: 0 | AG69: 37905 | AH69: 37905
A70: MEDELLIN | B70: NOROCCIDENTE | C70: 0004-0005 | D70: 5101 | E70: 3048225 | F70: 3007038747 | G70: INCIDENTE | H70: ANTIOQUIA | I70: CIUDAD BOLIVAR | J70: BARRIO PARQUE CIUDAD BOLIVAR | K70: REDEBAN | L70: FO-25-1861207 | M70: 45982.685 | N70: 45986.65 | O70: NO | P70: USUARIO | Q70: COMUNICACION | R70: CANAL DEL COMERCIO | S70: CB UNO A UNO | T70: CB UNO A UNO | U70: EJECUTADO | V70: 21/11/2025 SE ESCALA PARA VISITA. LLAMAR ANTES DE VISITAR, CONFIRMAR FALLA Y DATOS | 25/11/2025 DURANTE LA VISITA TÉCNICA AL CORRESPONSAL BANCOLOMBIA, EL USUARIO CONFIRMA SU IDENTIFICACIÓN Y REPORTA FALLAS EN EL DATÁFONO AL MOMENTO DE EJECUTAR TRANSACCIONES. EL DISPOSITIVO MUESTRA EL MENSAJE DE ERROR “TLS 1002”, IMPIDIENDO LA OPERACIÓN NORMAL. SE PROCEDE CON LA VALIDACIÓN Y MANTENIMIENTO PREVENTIVO DEL EQUIPO, VERIFICANDO SU ESTADO FÍSICO Y FUNCIONAL. TRAS LA REVISIÓN, SE DETERMINA QUE EL ORIGEN DEL PROBLEMA NO CORRESPONDE AL DATÁFONO, SINO A DEFICIENCIAS EN LA CONEXIÓN DE INTERNET DEL COMERCIO. FINALMENTE, SE INFORMA AL USUARIO SOBRE LA NECESIDAD DE ORGANIZAR Y ESTABILIZAR EL SERVICIO DE INTERNET PARA ASEGURAR EL CORRECTO FUNCIONAMIENTO DEL DISPOSITIVO Y EVITAR REINCIDENCIAS DEL ERROR. | W70: VISITA TECNICA | X70: GZ01Z374 | Y70: TIPO II | Z70: TERRESTRE | AA70: MARTINEZ TOVAR OSCAR DAVID | AB70: 1 | AC70: 0 | AD70: 0 | AE70: 0 | AF70: 0 | AG70: 163814 | AH70: 163814
A71: BUCARAMANGA | B71: SANTANDERES | C71: 0004-0008 | D71: 68418 | E71: 3049141 | F71: 3007019292 | G71: INCIDENTE | H71: SANTANDER | I71: LOS SANTOS | J71: BARRIO SECTOR MERCADO CAMPESIN | K71: REDEBAN | L71: FO-25-1863025 | M71: 45983.386 | N71: 45985.417 | O71: NO | P71: USUARIO | Q71: COMUNICACION | R71: CANAL DEL COMERCIO | S71: CB UNO A UNO | T71: CB UNO A UNO | U71: EJECUTADO | V71: 22/11/2025 SE ESCALA PARA VISITA. LLAMAR ANTES DE VISITAR, CONFIRMAR FALLA Y DATOS | 22/11/2025 SE REALIZA LLAMADA TELEFÓNICA AL NÚMERO 3112014815 SE HABLA CON LA SEÑORITA ANGÉLICA SILVA PARA LA ATENCIÓN DE INCIDENTE. SE LOGRA IDENTIFICAR QUE EQUIPO NO ESTÁ FUNCIONANDO POR LO TANTO SE INDICA QUE SE DEBE VISITAR Y CAMBIAR EL EQUIPO, NOS INDICA TOTAL DISPONIBILIDAD, PERO LA TIPOLOGÍA II ESTÁ UBICADA EN ZONA RURAL DEL MUNICIPIO DE LOS SANTOS Y SE DEBE TOMAR TRASPORTE EL CUAL NO ES CONSTANTE, POR LO TANTO NO SE ALCANZA EL DÍA DE HOY A REALIZAR YA QUE POR PARTE DE LA RED SOLO ES POSIBLE CAMBIO DE EQUIPOS HASTA 1:00 PM , DE LO CONTRARIO SE TENDRÁ QUE VISITAR EL DÍA LUNES 24 DE NOVIEMBRE | 24/11/2025 SE VISITO COMERCIO YA QUE PRESENTABA FALLA EN LA CONEXIÓN TODO EL FIN DE SEMANA PERO EL DÍA DE HOY YA ESTÁ OPERANDO CORRECTAMENTE YA QUE HABÍA FALLA EN EL CANAL DE COMUNICACIÓN | W71: VISITA TECNICA | X71: BL01Y374 | Y71: TIPO II | Z71: TERRESTRE | AA71: PEÑA DIAZ IVAN YESID | AB71: 1 | AC71: 0 | AD71: 0 | AE71: 0 | AF71: 0 | AG71: 163814 | AH71: 163814
A72: MEDELLIN | B72: NOROCCIDENTE | C72: 0004-0005 | D72: 5360 | E72: 3049166 | F72: 3007046735 | G72: INCIDENTE | H72: ANTIOQUIA | I72: ITAGUI | J72: BARRIO ITAGUI ITAGUI 8 | K72: REDEBAN | L72: FO-25-1863475 | M72: 45983.432 | N72: 45985.47 | O72: NO | P72: USUARIO | Q72: LECTOR DE TARJETAS | R72: OBSTRUCCION DEL LECTOR | S72: CB UNO A UNO | T72: CB UNO A UNO | U72: EJECUTADO | V72: 22/11/2025 SE ESCALA PARA VISITA. LLAMAR ANTES DE VISITAR, CONFIRMAR FALLA Y DATOS | 24/11/2025 SE REALIZÓ LIMPIEZA DE LECTOR CHIP | W72: VISITA TECNICA | X72: TR008163 | Y72: TIPO I | Z72: TERRESTRE | AA72: CASTAÑEDA PALACIO CARLOS FELIPE | AB72: 1 | AC72: 0 | AD72: 0 | AE72: 0 | AF72: 0 | AG72: 65960 | AH72: 65960
A73: PASTO | B73: SUROCCIDENTE Y EJE CAFETERO | C73: 0004-0003 | D73: 52001 | E73: 3049382 | F73: 3007050428 | G73: INCIDENTE | H73: NARIÑO | I73: PASTO | J73: PTM PASTO ORIENTAR SS | K73: REDEBAN | L73: FO-25-1864382 | M73: 45983.524 | N73: 45985.448 | O73: NO | P73: USUARIO | Q73: NO ENCIENDE | R73: CONEXIONES DE COMERCIO | S73: AGREGADOR | T73: COMCARD - PTM | V73: 22/11/2025 SE ESCALA PARA VISITA. LLAMAR ANTES DE VISITAR, CONFIRMAR FALLA Y DATOS | 22/11/2025 SE VALIDA DAÑO PERO CLIENTE SOLO LABORA HASTA LAS 2 , SE VALIDARA EL DIA LUNES ADEMAS POSIBLE CAMBIO. | 24/11/2025 SE ESTABLECE COMUNICACIÓN CON CLIENTE INFORMA QUE YA NO ES NECESARIA LA VISITA YA QUE NO SE LES A PRESENTADO FALLA NUEVAMENTE SOLO FUE UNA VEZ Y HASTA EL MOMENTO TIENE TOTAL NORMALIDAD DEL SERVICIO AUTORIZA CERRAR ORDEN DE SERVICIO | W73: SOPORTE TELEFONICO | Y73: TIPO I | Z73: TERRESTRE | AA73: BRAVO MADROÑERO OSCAR ESTEBAN | AB73: 0 | AC73: 0 | AD73: 0 | AE73: 0 | AF73: 0 | AG73: 37905 | AH73: 37905
A74: MEDELLIN | B74: NOROCCIDENTE | C74: 0004-0005 | D74: 5001 | E74: 3051946 | F74: 3007073145 | G74: INCIDENTE | H74: ANTIOQUIA | I74: MEDELLIN | J74: DISTRICOL CAFETERIA EL CID | K74: REDEBAN | L74: FO-25-1869008 | M74: 45985.384 | N74: 45985.66 | O74: NO | P74: USUARIO | Q74: MANTENIMIENTO | R74: MANTENIMIENTO GENERAL | S74: AGREGADOR | T74: DISTRICOL | U74: EJECUTADO | V74: 24/11/2025 SE ESCALA PARA VISITA. LLAMAR ANTES DE VISITAR, CONFIRMAR FALLA Y DATOS | 25/11/2025 FUENTE DE PODER MAL CONECTADA, SE ORGANIZA, EQUIPOS OPERATIVOS | W74: VISITA TECNICA | X74: NN00R451 | Y74: TIPO I | Z74: TERRESTRE | AA74: BADEL ACUÑA LUIS ALBERTO | AB74: 1 | AC74: 0 | AD74: 0 | AE74: 0 | AF74: 0 | AG74: 65960 | AH74: 65960
A75: BUCARAMANGA | B75: SANTANDERES | C75: 0004-0008 | D75: 68001 | E75: 3053752 | F75: 3007074426 | G75: INCIDENTE | H75: SANTANDER | I75: BUCARAMANGA | J75: BARRIO SAN FRANCISCO BUCARAMAN | K75: REDEBAN | L75: FO-25-1870562 | M75: 45985.496 | N75: 45986.433 | O75: NO | P75: USUARIO | Q75: COMUNICACION | R75: CONEXIONES DE COMERCIO | S75: UNO A UNO | T75: UNO A UNO | U75: EJECUTADO | V75: 24/11/2025 SE ESCALA PARA VISITA. LLAMAR ANTES DE VISITAR, CONFIRMAR FALLA Y DATOS | 25/11/2025 SE REALIZA VISITA EN PUNTO EL CUAL SE ENCUENTRA CERRADO SE ESTABLECE CONTACTO TELEFÓNICO CON EL USUARIO QUIEN NOS CONFIRMA QUE NO REQUIERE EL SERVICIO TÉCNICO YA QUE LA FALLA SE PRESENTA POR UNA MALA CONEXIÓN LA CUAL SE SOLUCIONO Y EL SERVICIO YA SE ENCUENTRA OPERATIVO | W75: VISITA TECNICA | X75: MNBZZ929 | Y75: TIPO I | Z75: TERRESTRE | AA75: REYES RAMIREZ DIEGO ALEXANDER | AB75: 1 | AC75: 0 | AD75: 0 | AE75: 0 | AF75: 0 | AG75: 65960 | AH75: 65960
A76: PASTO | B76: SUROCCIDENTE Y EJE CAFETERO | C76: 0004-0003 | D76: 52352 | E76: 3056922 | F76: 3007025628 | G76: INCIDENTE | H76: NARIÑO | I76: ILES | J76: AV IPIALES DE ILES NARINO | K76: REDEBAN | L76: FO-25-1872951 | M76: 45985.707 | N76: 45986.478 | O76: NO | P76: USUARIO | Q76: LECTOR DE BARRAS | R76: CAPACITACION MANIPULACION DE COMERCIO | S76: CB UNO A UNO | T76: CB UNO A UNO | V76: 24/11/2025 SE ESCALA PARA VISITA. LLAMAR ANTES DE VISITAR, CONFIRMAR FALLA Y DATOS | 25/11/2025 SE CONTACTA CON LA SEÑORA NANCY PANTOJA PARA CONFIRMAR VISITA PERO LA SEÑORA NANCY INFORMA QUE EL DÍA DE AYER INTENTO PASAR UNA FACTURA Y NO LE LEYO PERO QUE EL DÍA DE HOY YA LE ESTA LEYENDO NORMALMENTE LAS FACTURAS POR LO CUAL INFORMA QUE YA NO DESEA VISITA TÉCNICA... SE CIERRA TA | W76: SOPORTE TELEFONICO | Y76: TIPO II | Z76: TERRESTRE | AA76: PAZ MARTINEZ RICHARD HUMBERTO | AB76: 0 | AC76: 0 | AD76: 0 | AE76: 0 | AF76: 0 | AG76: 37905 | AH76: 37905
A77: MEDELLIN | B77: NOROCCIDENTE | C77: 0004-0005 | D77: 5088 | E77: 3057277 | F77: 3007061727 | G77: INCIDENTE | H77: ANTIOQUIA | I77: BELLO | J77: DISTRICOL PAPELERIA Y MINITIEN | K77: REDEBAN | L77: FO-25-1874514 | M77: 45986.333 | N77: 45986.534 | O77: NO | P77: USUARIO | Q77: CIERRE | R77: COMERCIO NO REALIZA CIERRE | S77: AGREGADOR | T77: DISTRICOL | V77: 25/11/2025 SE ESCALA PARA VISITA. LLAMAR ANTES DE VISITAR, CONFIRMAR FALLA Y DATOS | 25/11/2025 SE HABLA CON SEÑORA PAOLA Y NOS INFORMÓ QUE YA LOGRÓ REALIZAR EL CIERRE CON AYUDA DEL ENCARGADO., SE REALIZA PROCESO DE CIERRE SIN NOVEDAD. CB OPERATIVO. | W77: SOPORTE TELEFONICO | Y77: TIPO I | Z77: TERRESTRE | AA77: HENAO JARAMILLO JUAN JOSE | AB77: 0 | AC77: 0 | AD77: 0 | AE77: 0 | AF77: 0 | AG77: 37905 | AH77: 37905
A78: BARRANQUILLA | B78: COSTA | C78: 0004-0001 | D78: 8638 | E78: 3058276 | F78: 3007048428 | G78: INCIDENTE | H78: ATLANTICO | I78: SABANALARGA | J78: PTM SABANALARGA MULTISERVICI | K78: REDEBAN | L78: FO-25-1874695 | M78: 45986.371 | N78: 45987.722 | O78: NO | P78: ENTIDAD | Q78: ERROR DE TRANSACCIONES | R78: TRANSACCION NO PERMITIDA | S78: AGREGADOR | T78: COMCARD - PTM | U78: EJECUTADO | V78: 25/11/2025 SE ESCALA PARA VISITA. LLAMAR ANTES DE VISITAR, CONFIRMAR FALLA Y DATOS | 26/11/2025 SE LLAMA AL COMERCIO Y SE LE PREGUNTA SI TIENE ALGÚN BLOQUEO CON EL BANCO O LA RED PTM, Y ME INFORMAN QUE ELLOS LLAMARON Y LES DIJERON QUE ESTABA TODO OK POR PARTE DE ELLOS, SE PROCEDE A DESPLAZARSE AL SITIO . SE LLEGA AL COMERCIO, Y HAY DOS DATAFONOS DE LA RED PTM, UN DATAFONO MIXTO Y EL OTRO PURO, AL HACER CUALQUIER TIPO DE TRANSACCIÓN SALE EL MENSAJE " TARJETA NO SOPORTADA" EN SITIO DE LLAMA NUEVAMENTE A LAS LÍNEA DE BANCOLOMBIA Y PTM, Y LE INFORMAN LOS MISMO AL CLIENTE ME COLOCO EN CONTACTO CON SOPORTE DE RBM, QUIENES HACEN PRUEBAS , ME DICEN QUE CAMBIE EL DATAFONO PURO, SE CAMBIA PERO SIGUEN IGUAL LUEGO LE LLEGA UN MENSAJE A LA EMPLEADA DE SU JEFE, QUIEN LE INFORMA QUE LO LLAMARON DE PTM A DECIRLE QUE NO SIGA INSISTIENDO, PORQUE ESTÁN BLOQUEADOS POR PTM POR UN TEMA DE ACTUALIZACIÓN DE DATOS CB QUEDA SIN OPERAR | W78: VISITA TECNICA | X78: NA00K179 | Y78: TIPO II | Z78: TERRESTRE | AA78: DE AVILA SIADES ALBERTO ENRIQUE | AB78: 1 | AC78: 0 | AD78: 0 | AE78: 0 | AF78: 0 | AG78: 163814 | AH78: 163814
A79: APARTADO | B79: NOROCCIDENTE | C79: 0004-0005 | D79: 5045 | E79: 3058648 | F79: 3007064886 | G79: INCIDENTE | H79: ANTIOQUIA | I79: APARTADO | J79: DISRICOL PREMIUM CELL LA 97 | K79: REDEBAN | L79: FO-25-1875240 | M79: 45986.39 | N79: 45986.647 | O79: NO | P79: USUARIO | Q79: COMUNICACION | R79: CANAL DEL COMERCIO | S79: AGREGADOR | T79: DISTRICOL | U79: EJECUTADO | V79: 25/11/2025 SE ESCALA PARA VISITA. LLAMAR ANTES DE VISITAR, CONFIRMAR FALLA Y DATOS | 25/11/2025 NO TIENE COMUNICACIÓN DATAFONO, SE INICIALIZA Y SE CARGANDO NUEVAMENTE PARÁMETROS. | W79: VISITA TECNICA | X79: 5A002508 | Y79: TIPO I | Z79: TERRESTRE | AA79: CASTRO HENAO DANIEL ESTEBAN | AB79: 1 | AC79: 0 | AD79: 0 | AE79: 0 | AF79: 0 | AG79: 65960 | AH79: 65960
A80: BUCARAMANGA | B80: SANTANDERES | C80: 0004-0008 | D80: 68190 | E80: 3058862 | F80: 3007026648 | G80: INCIDENTE | H80: SANTANDER | I80: CIMITARRA | J80: VIA PRINCIPAL CIMITARRA SANTAN | K80: REDEBAN | L80: FO-25-1875575 | M80: 45986.408 | N80: 45987.682 | O80: NO | P80: USUARIO | Q80: COMUNICACION | R80: CONEXIONES DE COMERCIO | S80: CB UNO A UNO | T80: CB UNO A UNO | V80: 25/11/2025 SE ESCALA PARA VISITA. LLAMAR ANTES DE VISITAR, CONFIRMAR FALLA Y DATOS | 26/11/2025 EN COMUNICACIÓN CON LA SEÑORA BLANCA AL MOVIL 3118617478, INDICA QUE NO REQUIERE DE LA VISITA TÉCNICA, INDICA QUE YA SE CORRIGIÓ LA FALLA ERA UN PROBLEMA CON EL PROVEEDOR DE INTERNET, SE LE INFORMA QUE SE CERRARÁ LA ORDEN Y CUALQUIER NUEVA NOVEDAD DEBERÁ SOLICITAR UNA NUEVA VISITA, CLIENTE CONFORME. | W80: SOPORTE TELEFONICO | Y80: TIPO IV | Z80: TERRESTRE | AA80: SANTOS GONZALEZ JOHAN FABIAN | AB80: 0 | AC80: 0 | AD80: 0 | AE80: 0 | AF80: 0 | AG80: 37905 | AH80: 37905
A81: CARTAGENA | B81: COSTA | C81: 0004-0001 | D81: 13001 | E81: 3059852 | F81: 3007069104 | G81: INCIDENTE | H81: BOLIVAR | I81: CARTAGENA | J81: PTM CARTAGENA PAPELERIA Y VARI | K81: REDEBAN | L81: FO-25-1876400 | M81: 45986.455 | N81: 45986.665 | O81: NO | P81: USUARIO | Q81: COMUNICACION | R81: CANAL DEL COMERCIO | S81: AGREGADOR | T81: COMCARD - PTM | U81: EJECUTADO | V81: 25/11/2025 SE ESCALA PARA VISITA. LLAMAR ANTES DE VISITAR, CONFIRMAR FALLA Y DATOS | 25/11/2025 SE VALIDA NOVEDAD CLIENTE CON RESTRICCIÓN EN EL MÓDEM DEL PROVEEDOR SE RESTABLECEN PARÁMETROS Y TODO QUEDA OK | W81: VISITA TECNICA | X81: A103Z510 A104Z857 | Y81: TIPO I | Z81: TERRESTRE | AA81: MARTINEZ SALGUEDO ANDRES AUGUSTO | AB81: 1 | AC81: 0 | AD81: 0 | AE81: 0 | AF81: 0 | AG81: 65960 | AH81: 65960
A82: PEREIRA | B82: SUROCCIDENTE Y EJE CAFETERO | C82: 0004-0002 | D82: 76041 | E82: 3062758 | F82: 3007034987 | G82: INCIDENTE | H82: VALLE DEL CAUCA | I82: ANSERMANUEVO | J82: DISTRICOL CELULARES MAGICELL | K82: REDEBAN | L82: FO-25-1880087 | M82: 45986.705 | N82: 45987.681 | O82: NO | P82: USUARIO | Q82: MANTENIMIENTO | R82: MANTENIMIENTO GENERAL | S82: AGREGADOR | T82: DISTRICOL | U82: EJECUTADO | V82: 25/11/2025 SE ESCALA PARA VISITA. LLAMAR ANTES DE VISITAR, CONFIRMAR FALLA Y DATOS | 26/11/2025 SE CAMBIA DE ROLLO Y SE REALIZA IMPRESIÓN DE PRUEBA EXITOSA, SE REALIZA TRX EXITOSA. | W82: VISITA TECNICA | X82: BL01X123 | Y82: TIPO II | Z82: TERRESTRE | AA82: FRANCO CAÑAVERAL YAMID RAUL | AB82: 1 | AC82: 0 | AD82: 0 | AE82: 0 | AF82: 0 | AG82: 163814 | AH82: 163814
A83: YOPAL | B83: REMOTAS | C83: 0004-0007 | D83: 85001 | E83: 3064097 | F83: 3007078773 | G83: INCIDENTE | H83: CASANARE | I83: YOPAL | J83: DISTRICOL DROGUERIA DROVITAL S | K83: REDEBAN | L83: FO-25-1885926 | FO-25-1881850 | M83: 45987.368 | N83: 45990.515 | O83: NO | P83: ENTIDAD | Q83: ERROR DE TRANSACCIONES | R83: TRANSACCION NO PERMITIDA | S83: AGREGADOR | T83: DISTRICOL | U83: EJECUTADO / CANCELADO | V83: 29/11/2025 SE VISITA COMERCIO, CB NO OPERATIVO, LA TERMINAL AL MOMENTO DE INICIALIZACION INDICA TERMINAL NO EXISTE. SE ESCALA A COORDINADOR DE ZONA. AUTORIZA EL RETIRO DEL CB. NO SE CUENTA CON SOPORTE RBM | W83: VISITA TECNICA | X83: AE005095 | Y83: TIPO I | Z83: TERRESTRE | AA83: BERNAL ELAICA EDGAR ALEXIS | AB83: 2 | AC83: 0 | AD83: 0 | AE83: 0 | AF83: 0 | AG83: 65960 | AH83: 131920
A84: IBAGUE | B84: REMOTAS | C84: 0004-0007 | D84: 73001 | E84: 3066334 | F84: 3007050001 | G84: INCIDENTE | H84: TOLIMA | I84: IBAGUE | J84: BARRIO AMBALA IBAGUE 4 | K84: REDEBAN | L84: FO-25-1883648 | M84: 45987.499 | N84: 45987.726 | O84: NO | P84: USUARIO | Q84: CIERRE | R84: COMERCIO NO REALIZA CIERRE | S84: UNO A UNO | T84: CB UNO A UNO | U84: EJECUTADO | V84: 25/11/2025 SE ESCALA PARA VISITA. LLAMAR ANTES DE VISITAR, CONFIRMAR FALLA Y DATOS | 26/11/2025 SE CONFIGURA CLAVE DE SUPERVISOR 1526 PARA REALIZAR CIERRE Y DUPLICADO EL CB REALIZA CIERRE,SE HACEN PRUEBAS O.K | W84: VISITA TECNICA | X84: II00S485 | Y84: TIPO I | Z84: TERRESTRE | AA84: GUTIERREZ CAMILO ANDRES | AB84: 1 | AC84: 0 | AD84: 0 | AE84: 0 | AF84: 0 | AG84: 65960 | AH84: 65960
A85: BOGOTA | B85: CUNDINAMARCA | C85: 0004-0004 | D85: 11001 | E85: 3072673 | F85: 3007029601 | G85: INCIDENTE | H85: CUNDINAMARCA | I85: BOGOTA | J85: OPRAP ISIERRA 100 | K85: REDEBAN | L85: FO-25-1898936 | M85: 45988.626 | N85: 45989.586 | O85: NO | P85: USUARIO | Q85: COMUNICACION | R85: CONEXIONES DE COMERCIO | S85: ROBUSTO | T85: OPRAP | U85: EJECUTADO | V85: 27/11/2025 SE ESCALA PARA VISITA. LLAMAR ANTES DE VISITAR, CONFIRMAR FALLA Y DATOS | 28/11/2025 DEMORAS EN ACCESO POR QUÉ NO CONTESTAN LA LÍNEA 018000 DE BANCOLOMBIA PARA CONFIRMAR IDENTIDAD DEL TÉCNICO | 28/11/2025 SE REALIZA CAMBIO DE CABLE ETHERNET POR DAÑO, SERVICIO OPERATIVO PRUEBAS OK TRNA RBM SE REALIZA PRUEBA CON UNA CONSIGNACIÓN REALIZADA POR CLIENTE NO HAY COMO HACER RETIRO NI CONSULTA | W85: VISITA TECNICA | X85: BBBCZ862 | Y85: TIPO I | Z85: TERRESTRE | AA85: BUSTOS MORA DIEGO MANUEL | AB85: 1 | AC85: 0 | AD85: 0 | AE85: 0 | AF85: 0 | AG85: 65960 | AH85: 65960
A86: MONTERIA | B86: COSTA | C86: 0004-0001 | D86: 23001 | E86: 3074275 | F86: 3007070162 | G86: INCIDENTE | H86: CORDOBA | I86: MONTERIA | J86: BARRIO LA VICTORIA MONTERIA | K86: REDEBAN | L86: FO-25-1901001 | M86: 45989.359 | N86: 45989.762 | O86: NO | P86: USUARIO | Q86: CIERRE | R86: COMERCIO NO REALIZA CIERRE | S86: CB UNO A UNO | T86: CB UNO A UNO | U86: EJECUTADO | V86: 28/11/2025 SE ESCALA PARA VISITA. LLAMAR ANTES DE VISITAR, CONFIRMAR FALLA Y DATOS | 28/11/2025 SE VISITA SITIO, SE REALIZA BORRADO DE MEMORIA CON AUTORIZACIÓN DEL CB, SE LE INDICA PROCESO PARA HACER CORRECTO CIERRE DEL DATAFONO OK. | W86: VISITA TECNICA | X86: EF007251 | Y86: TIPO I | Z86: TERRESTRE | AA86: COGOLLO VERTEL EDER LUIS | AB86: 1 | AC86: 0 | AD86: 0 | AE86: 0 | AF86: 0 | AG86: 65960 | AH86: 65960
A87: APARTADO | B87: NOROCCIDENTE | C87: 0004-0005 | D87: 5172 | E87: 3075387 | F87: 3007010024 | G87: INCIDENTE | H87: ANTIOQUIA | I87: CHIGORODO | J87: BARRIO EL BOSQUE | K87: REDEBAN | L87: FO-25-1901801 | M87: 45989.427 | N87: 45989.714 | O87: NO | P87: USUARIO | Q87: COMUNICACION | R87: CANAL DEL COMERCIO | S87: CB UNO A UNO | T87: CB UNO A UNO | U87: EJECUTADO | V87: 28/11/2025 SE ESCALA PARA VISITA. LLAMAR ANTES DE VISITAR, CONFIRMAR FALLA Y DATOS | 28/11/2025 SE REALIZA REPISADO DE CONFIGURACIÓN | W87: VISITA TECNICA | X87: GZUZZ121 | Y87: TIPO II | Z87: TERRESTRE | AA87: CASTRO HENAO DANIEL ESTEBAN | AB87: 1 | AC87: 0 | AD87: 0 | AE87: 0 | AF87: 0 | AG87: 163814 | AH87: 163814
A88: APARTADO | B88: NOROCCIDENTE | C88: 0004-0005 | D88: 5147 | E88: 3075975 | F88: 3007079886 | G88: INCIDENTE | H88: ANTIOQUIA | I88: CAREPA | J88: DISTRICOL COOTRANSCAR | K88: REDEBAN | L88: FO-25-1902425 | M88: 45989.471 | N88: 45989.662 | O88: NO | P88: USUARIO | Q88: COMUNICACION | R88: CANAL DEL COMERCIO | S88: AGREGADOR | T88: DISTRICOL | U88: EJECUTADO | V88: 28/11/2025 SE ESCALA PARA VISITA. LLAMAR ANTES DE VISITAR, CONFIRMAR FALLA Y DATOS | 28/11/2025 SE FORMATEA, CONFIGURA PARÁMETROS Y SE INICIALIZA. DTAFONO QUEDA OPERATIVO. | W88: VISITA TECNICA | X88: SAUZZ945 | Y88: TIPO I | Z88: TERRESTRE | AA88: CASTRO HENAO DANIEL ESTEBAN | AB88: 1 | AC88: 0 | AD88: 0 | AE88: 0 | AF88: 0 | AG88: 65960 | AH88: 65960
A89: MEDELLIN | B89: NOROCCIDENTE | C89: 0004-0005 | D89: 5631 | E89: 3077882 | F89: 3007016056 | G89: INCIDENTE | H89: ANTIOQUIA | I89: SABANETA | J89: ALKOMPRAR MAYORCA | K89: REDEBAN | L89: FO-25-1906254 | M89: 45990.389 | N89: 45990.521 | O89: NO | P89: USUARIO | Q89: COMUNICACION | R89: CANAL DEL COMERCIO | S89: RETAIL | T89: CONTIGO / ALKOMPRAR | U89: EJECUTADO | V89: 29/11/2025 SE ESCALA PARA VISITA. LLAMAR ANTES DE VISITAR, CONFIRMAR FALLA Y DATOS | 29/11/2025 SE REALIZÓ VISITA SE VÁLIDA CANAL DEL CB SE EVIDENCIA QUE EL PUERTO DE RED PRESENTA PROBLEMAS DE CONEXIÓN SE ESCALA DAÑO A SISTEMAS DE ALKOMPRAR SE PROCEDE A CERRAR CASO | W89: VISITA TECNICA | X89: JAXZZ840 | Y89: TIPO I | Z89: TERRESTRE | AA89: CASTAÑEDA PALACIO CARLOS FELIPE | AB89: 1 | AC89: 0 | AD89: 0 | AE89: 0 | AF89: 0 | AG89: 65960 | AH89: 65960

Sheet OC
A1: CIUDAD SEDE | B1: ZONA | C1: CENTRO DE COSTOS LINEACOM | D1: CODIGO DANE | E1: TA/CODIGO ACTIVIDAD | F1: CODIGO CB | G1: ACTIVIDAD | H1: DEPARTAMENTO | I1: CIUDAD | J1: NOMBRE DEL CB | K1: RED | L1: FO | M1: FECHA ASIGNACION A LINEA COMUNICACIONES | N1: FECHA CIERRE DEL TICKET (DD/MM/AAAA HH:MM) | O1: ACOMETIDA | P1: SOLICITUD | Q1: DESCRIPCION | R1: FORMATO | S1: CADENA | T1: ESTADO | U1: CAUSAL ESTADO | V1: OBSERVACION | W1: FORMA DE ATENCION | X1: TERMINAL(ES) | Y1: TIPIFICACION | Z1: TIPO DE TRAYECTO | AA1: NOMBRE DEL TECNICO | AB1: DIAS DE VISITA | AC1: SWITCH | AD1: ACOMETIDA DATOS | AE1: ACOMETIDA ELÉCTRICA | AF1: VALOR ACTIVIDAD | AG1: VALOR TOTAL
A2: MONTERIA | B2: COSTA | C2: 0004-0001 | D2: 23001 | E2: 14316455 | F2: 3007080792 | G2: OC TRASLADO | H2: CORDOBA | I2: MONTERIA | J2: BARRIO URBINA MONTERIA | K2: REDEBAN | L2: FO-25-1782612 | M2: 45965.703 | N2: 45967.631 | O2: NO | P2: TRASLADO | Q2: TRASLADO EXTERNO | R2: UNO A UNO | S2: UNO A UNO | T2: EJECUTADO / CANCELADO | U2: PETICIÓN USUARIO | V2: 05/11/2025 SE LLAMA A EL NUMERO 3244366733 3008019110 NO HAY COMUNICACION POR FAVOR, COMUNICARSE CON USUARIO PARA CONFIRMAR UBICACION, SOLICITUD Y PROGRAMAR VISITA TECNICA | W2: VISITA TECNICA | Y2: TIPO I | Z2: TERRESTRE | AA2: ARRAZOLA HERNANDEZ NICOLAS AUGUSTO | AB2: 1 | AC2: 0 | AD2: 0 | AE2: 0 | AF2: 65960 | AG2: 65960
A3: MANIZALES | B3: SUROCCIDENTE Y EJE CAFETERO | C3: 0004-0002 | D3: 17001 | E3: 14318975-1 | F3: 3007080031 | G3: OC TRASLADO | H3: CALDAS | I3: MANIZALES | J3: BARRIO PALERMO MANIZALES 7 | K3: REDEBAN | L3: FO-25-1782613 | M3: 45965.703 | N3: 45967.573 | O3: NO | P3: TRASLADO | Q3: TRASLADO EXTERNO | R3: UNO A UNO | S3: UNO A UNO | T3: EJECUTADO / CANCELADO | U3: PETICIÓN RED | V3: 05/11/2025 SE LLAMA A EL NUMERO 3016020848 3023843981 NO HAY COMUNICACION POR FAVOR, COMUNICARSE CON USUARIO PARA CONFIRMAR UBICACION, SOLICITUD Y PROGRAMAR VISITA TECNICA | W3: VISITA TECNICA | Y3: TIPO I | Z3: TERRESTRE | AA3: AGUIRRE HENAO RAUL EDUARDO | AB3: 1 | AC3: 0 | AD3: 0 | AE3: 0 | AF3: 65960 | AG3: 65960
A4: BOGOTA | B4: CUNDINAMARCA | C4: 0004-0004 | D4: 11001 | E4: 14375539 | F4: 3007072000 | G4: OC TRASLADO | H4: CUNDINAMARCA | I4: BOGOTA | J4: MARATU | K4: REDEBAN | L4: FO-25-1829717 | M4: 45975.516 | N4: 45980.464 | O4: NO | P4: TRASLADO | Q4: TRASLADO EXTERNO | R4: CB UNO A UNO | S4: CB UNO A UNO | T4: EJECUTADO | U4: PETICIÓN RED | V4: 14/11/2025 POR FAVOR, COMUNICARSE CON USUARIO PARA CONFIRMAR UBICACION, SOLICITUD Y PROGRAMAR VISITA TECNICA | 19/11/2025 SE LLEGA ALA DIRECCIÓN INDICADA Y NO ES POSIBLE REALIZAR EL TRASLADO A LA DIRECCIÓN CR 94 # 68 A 68 YA QUE EL EQUIPO SE BLOQUEÓ AL INICIALIZARLO, COMERCIO REALIZA LLAMADA PARA SOLICITAR EL INCIDENTE Y PODER CAMBIAR EQUIPOS. | W4: VISITA TECNICA | X4: LN00M210 | Y4: TIPO I | Z4: TERRESTRE | AA4: GARCIA PASTRANA KEVIN FERNANDO | AB4: 1 | AC4: 0 | AD4: 0 | AE4: 0 | AF4: 65960 | AG4: 65960
A5: BOGOTA | B5: CUNDINAMARCA | C5: 0004-0004 | D5: 11001 | E5: 14378101 | F5: 3007042330 | G5: OC TRASLADO | H5: CUNDINAMARCA | I5: BOGOTA | J5: BARRIO KENEDY BOGOTA | K5: REDEBAN | L5: FO-25-1833418 | FO-25-1829726 | M5: 45975.516 | N5: 45979.596 | O5: NO | P5: TRASLADO | Q5: TRASLADO EXTERNO | R5: CB UNO A UNO | S5: CB UNO A UNO | T5: EJECUTADO | EJECUTADO / CANCELADO | U5: EJECUTADO EXITOSO | V5: 18/11/2025 DURANTE LA VISITA TECNICA SE REALIZA TRASLADO DE CORRESPONSAL EN LUGARES INDICADOS POR CORRESPONSAL SIN NOVEDAD EN INSTALACIÓN PRUEBAS OK SALDO OK A CONFORMIDAD DE CORRESPONSAL | W5: VISITA TECNICA | X5: AA2ZZ072 | Y5: TIPO I | Z5: TERRESTRE | AA5: GALEANO SORIANO JUAN DAVID | AB5: 1 | AC5: 0 | AD5: 0 | AE5: 0 | AF5: 65960 | AG5: 65960
